{
  "type": "Feature",
  "properties": {
    "iso:country":"TR",
    "sg:address":"Ataturk Cad.resit Berberoglu Ishani K:6",
    "sg:city":"Adapazari",
    "sg:classifiers":[
        {
            "category":"Banks & Credit Unions",
            "subcategory":"Investment Brokerage",
            "type":"Services"
        }
    ],
    "sg:phone":"+90 24224401207",
    "sg:postcode":"54040",
    "sg:province":"Antalya",
    "sg:tags":[
        "exporter"
    ],
    "wof:name":"Antalya Ihracat?i Birlikleri Genel Sekreterligi",
    "wof:placetype":"venue"
},
  "geometry": {"coordinates":[30.703135,36.887505],"type":"Point"}
}