{
  "type": "Feature",
  "properties": {
    "addr:full":"Halaskargazi Cd. Sark Apt. D:10 Osmanbey \u00dcsk\u00fcdar Istanbul 34672",
    "addr:housenumber":"10",
    "addr:postcode":"34672",
    "addr:street":"Halaskargazi Cd. Sark Apt. D",
    "iso:country":"TR",
    "sg:address":"Halaskargazi Cd. Sark Apt. D:10 Osmanbey",
    "sg:city":"\u00dcsk\u00fcdar",
    "sg:classifiers":[
        {
            "category":"Building & Trades",
            "subcategory":"Construction",
            "type":"Services"
        }
    ],
    "sg:phone":"+90 212 224 9513",
    "sg:postcode":"34672",
    "sg:province":"Istanbul",
    "sg:tags":[
        "foundation"
    ],
    "wof:name":"Basin Konseyi Day. Gelistirme Vakfi",
    "wof:placetype":"venue"
},
  "geometry": {"coordinates":[28.9641532898,41.0496711731],"type":"Point"}
}