{
  "type": "Feature",
  "properties": {
    "addr:full":"Ali Gedikler Korkuteli Antalya 07800",
    "addr:postcode":"07800",
    "iso:country":"TR",
    "sg:address":"Ali Gedikler",
    "sg:city":"Korkuteli",
    "sg:classifiers":[
        {
            "category":"Government",
            "subcategory":"Office",
            "type":"Public Place"
        }
    ],
    "sg:phone":"+90 242 652 5001",
    "sg:postcode":"07800",
    "sg:province":"Antalya",
    "sg:tags":[
        "municipality"
    ],
    "wof:name":"Yesilyayla Belediye Baskani",
    "wof:placetype":"venue"
},
  "geometry": {"coordinates":[30.7031345367,36.8875045776],"type":"Point"}
}