{
  "type": "Feature",
  "properties": {
    "addr:full":"A. Ipek? Cd. 1 Emintas San. Sit. No:158-184 Bayrampasa Yukari Dudullu Istanbul 34776",
    "addr:housenumber":"?;1;bayrampasa",
    "addr:postcode":"34776",
    "addr:street":"A.;Cd.",
    "iso:country":"TR",
    "sg:address":"A. Ipek? Cd. 1 Emintas San. Sit. No:158-184 Bayrampasa",
    "sg:city":"Yukari Dudullu",
    "sg:classifiers":[
        {
            "category":"Manufacturing",
            "subcategory":"Rubber & Plastics",
            "type":"Manufacturing & Wholesale Goods"
        }
    ],
    "sg:phone":"+90 212 577 4687",
    "sg:postcode":"34776",
    "sg:province":"Istanbul",
    "sg:tags":[
        "industry"
    ],
    "wof:name":"Ar-sel Plastik Baski Ve Ambalaj San.",
    "wof:placetype":"venue"
},
  "geometry": {"coordinates":[29.175403595,41.0060424805],"type":"Point"}
}