{
  "type": "Feature",
  "properties": {
    "iso:country":"TR",
    "sg:address":"Aliriza Gurcan Cad. Nadide Sk. No: 1/1",
    "sg:city":"Merter",
    "sg:classifiers":[
        {
            "category":"Shopping",
            "subcategory":"Clothing, Apparel, & Fashions",
            "type":"Retail Goods"
        }
    ],
    "sg:phone":"+90 212 643 1813",
    "sg:province":"Istanbul",
    "sg:tags":[
        "underwear"
    ],
    "wof:name":"Keskin Tekstil",
    "wof:placetype":"venue"
},
  "geometry": {"coordinates":[28.893156,41.006767],"type":"Point"}
}