{
  "type": "Feature",
  "properties": {
    "iso:country":"TR",
    "sg:address":"Kakule Sk.no7-1",
    "sg:city":"Yenik?",
    "sg:classifiers":[
        {
            "category":"Mining & Drilling",
            "type":"Manufacturing & Wholesale Goods"
        }
    ],
    "sg:phone":"+90 212 257 3840",
    "sg:province":"Istanbul",
    "sg:tags":[
        "underwater",
        "working"
    ],
    "wof:name":"Mavi Deniz Ltd.sti.",
    "wof:placetype":"venue"
},
  "geometry": {"coordinates":[28.975925,41.012379],"type":"Point"}
}