{
  "type": "Feature",
  "properties": {
    "iso:country":"TR",
    "sg:address":"Medine Cad. Ruhan 2 Apt.",
    "sg:city":"Pendik",
    "sg:classifiers":[
        {
            "category":"Shopping",
            "subcategory":"Bicycles & Sporting Goods",
            "type":"Retail Goods"
        }
    ],
    "sg:phone":"+90 412 233 5185",
    "sg:postcode":"81480",
    "sg:province":"Diyarbakir",
    "sg:tags":[
        "motorcycle"
    ],
    "wof:name":"Onder Bisiklet",
    "wof:placetype":"venue"
},
  "geometry": {"coordinates":[40.225334,37.91581],"type":"Point"}
}