{
  "type": "Feature",
  "properties": {
    "iso:country":"TR",
    "sg:address":"Gulsan San. Sit. 54.sok. No:66 Gulsan San.sit.",
    "sg:city":"Siteler",
    "sg:classifiers":[
        {
            "category":"Home & Garden",
            "subcategory":"Hardware",
            "type":"Retail Goods"
        }
    ],
    "sg:phone":"+90 362 228 1009",
    "sg:postcode":"07070",
    "sg:province":"Samsun",
    "sg:tags":[
        "store"
    ],
    "wof:name":"Semizoglu Hirdavat San. Ve Tic.",
    "wof:placetype":"venue"
},
  "geometry": {"coordinates":[36.3381233215,41.2815742493],"type":"Point"}
}