{
  "type": "Feature",
  "properties": {
    "iso:country":"TR",
    "sg:address":"Canakkale Kordon",
    "sg:city":"Nisantasi",
    "sg:classifiers":[
        {
            "category":"Shopping",
            "subcategory":"Gifts & Souvenirs",
            "type":"Retail Goods"
        }
    ],
    "sg:phone":"+90 286 217 0324",
    "sg:postcode":"80200",
    "sg:province":"?anakkale",
    "wof:name":"Canakkale Seramik El Sanatlari",
    "wof:placetype":"venue"
},
  "geometry": {"coordinates":[26.4076156616,40.1321716309],"type":"Point"}
}