{
  "type": "Feature",
  "properties": {
    "iso:country":"TR",
    "sg:address":"Nalcaci Cad 86-88",
    "sg:city":"Konya",
    "sg:classifiers":[
        {
            "category":"Banks & Credit Unions",
            "subcategory":"Bank",
            "type":"Services"
        }
    ],
    "sg:phone":"+90 332 237 7727",
    "sg:province":"42060",
    "wof:name":"Demirbank Tas",
    "wof:placetype":"venue"
},
  "geometry": {"coordinates":[32.495655,37.888657],"type":"Point"}
}