{
  "type": "Feature",
  "properties": {
    "addr:full":"Bodrum Patara Mugla",
    "iso:country":"TR",
    "sg:address":"Bodrum",
    "sg:city":"Patara",
    "sg:orig_category":"Hotels: Motels",
    "sg:phone":"+90 252 316 3980",
    "sg:province":"Mugla",
    "wof:name":"Pedasa Gardens Hotel",
    "wof:placetype":"venue"
},
  "geometry": {"coordinates":[27.4333992004,37.0395011902],"type":"Point"}
}