{
  "type": "Feature",
  "properties": {
    "iso:country":"TR",
    "sg:address":"Omer Avni Mh. Inebolu Sk. No:31/2",
    "sg:city":"Kabatas",
    "sg:classifiers":[
        {
            "category":"Marine",
            "type":"Transportation"
        }
    ],
    "sg:phone":"+90 212 243 2586",
    "sg:postcode":"24600",
    "sg:province":"Istanbul",
    "sg:tags":[
        "shipowner"
    ],
    "wof:name":"En-ko Denizciliktic.a.s.",
    "wof:placetype":"venue"
},
  "geometry": {"coordinates":[28.975925,41.012379],"type":"Point"}
}