{
  "type": "Feature",
  "properties": {
    "addr:full":"Kayseri Yolu Uzeri ?rg? Nevsehir",
    "addr:housenumber":"uzeri ?;?",
    "addr:street":"Kayseri Yolu;Rg",
    "iso:country":"TR",
    "sg:address":"Kayseri Yolu Uzeri",
    "sg:city":"?rg?",
    "sg:orig_category":"Hotels: Motels",
    "sg:phone":"+90 384 341 3980",
    "sg:province":"Nevsehir",
    "wof:name":"Merit Inn Otel Holiday Village",
    "wof:placetype":"venue"
},
  "geometry": {"coordinates":[34.6258583069,38.870639801],"type":"Point"}
}