{
  "type": "Feature",
  "properties": {
    "addr:full":"Meclis-i Mebusan Cad 35, Findikli, 80040 Istanbul Gayrettepe Istanbul 34349",
    "addr:housenumber":"35",
    "addr:postcode":"80040;34349",
    "addr:street":"Mebusan Cad",
    "iso:country":"TR",
    "sg:address":"Meclis-i Mebusan Cad 35, Findikli, 80040 Istanbul",
    "sg:city":"Gayrettepe",
    "sg:classifiers":[
        {
            "category":"Banks & Credit Unions",
            "subcategory":"Bank",
            "type":"Services"
        }
    ],
    "sg:phone":"+90 212 251 2121",
    "sg:postcode":"34349",
    "sg:province":"Istanbul",
    "sg:website":"http://www.teb.com.tr",
    "wof:name":"T?k Ekonomi Bankasi As",
    "wof:placetype":"venue"
},
  "geometry": {"coordinates":[28.987488,41.029537],"type":"Point"}
}