{
  "type": "Feature",
  "properties": {
    "iso:country":"TR",
    "sg:address":"Bozburun Mh A.nazif Zorlu San.sitesi 7152 Sk.no.2",
    "sg:city":"G?m?sler",
    "sg:classifiers":[
        {
            "category":"Food & Beverages",
            "subcategory":"Meat & Fish",
            "type":"Retail Goods"
        }
    ],
    "sg:phone":"+90 258 371 8338",
    "sg:postcode":"20100",
    "sg:province":"Denizli",
    "sg:tags":[
        "seafood"
    ],
    "wof:name":"?zpekler Su ?r?nleri",
    "wof:placetype":"venue"
},
  "geometry": {"coordinates":[29.0830821991,37.7894973755],"type":"Point"}
}