{
  "type": "Feature",
  "properties": {
    "addr:full":"Dikmen S 4 Blok No: 9 Ayranci Bursa 04400",
    "addr:housenumber":"blok no 9",
    "addr:postcode":"04400",
    "addr:street":"Bursa",
    "iso:country":"TR",
    "sg:address":"Dikmen S 4 Blok No: 9",
    "sg:city":"Ayranci",
    "sg:classifiers":[
        {
            "category":"Government",
            "subcategory":"Fire Station",
            "type":"Public Place"
        }
    ],
    "sg:phone":"+90 224 364 4364",
    "sg:postcode":"04400",
    "sg:province":"Bursa",
    "sg:tags":[
        "decoration"
    ],
    "wof:name":"Bakir Dekorasyon",
    "wof:placetype":"venue"
},
  "geometry": {"coordinates":[29.0586109161,40.1844291687],"type":"Point"}
}