{
  "type": "Feature",
  "properties": {
    "addr:full":"Yavuzselim Cad. No:23 64100 ?inarli Usak",
    "addr:housenumber":"23",
    "addr:postcode":"64100",
    "addr:street":"Yavuzselim Cad. No;Inarli Usak",
    "iso:country":"TR",
    "sg:address":"Yavuzselim Cad. No:23 64100",
    "sg:city":"?inarli",
    "sg:classifiers":[
        {
            "category":"Shopping",
            "subcategory":"Crafts & Fabrics",
            "type":"Retail Goods"
        }
    ],
    "sg:phone":"+90 276 215 1712",
    "sg:province":"Usak",
    "sg:tags":[
        "knitting"
    ],
    "wof:name":"Kuntdokur Mensucat A.s.",
    "wof:placetype":"venue"
},
  "geometry": {"coordinates":[29.4148902893,38.6716957092],"type":"Point"}
}