{
  "type": "Feature",
  "properties": {
    "addr:full":"Organize San.b?gesi Ikitelli Nazilli Istanbul 65600",
    "addr:postcode":"65600",
    "iso:country":"TR",
    "sg:address":"Organize San.b?gesi Ikitelli",
    "sg:city":"Nazilli",
    "sg:classifiers":[
        {
            "category":"Wholesale",
            "subcategory":"Durable Goods & Equipment",
            "type":"Manufacturing & Wholesale Goods"
        }
    ],
    "sg:phone":"+90 212 485 7821",
    "sg:postcode":"65600",
    "sg:province":"Istanbul",
    "sg:tags":[
        "consumer"
    ],
    "wof:name":"Bumak",
    "wof:placetype":"venue"
},
  "geometry": {"coordinates":[28.9861831665,41.0408554077],"type":"Point"}
}