{
  "type": "Feature",
  "properties": {
    "iso:country":"TR",
    "sg:address":"Karatas Cd. No.145",
    "sg:city":"Kocarli",
    "sg:classifiers":[
        {
            "category":"Farming",
            "subcategory":"Farm",
            "type":"Manufacturing & Wholesale Goods"
        }
    ],
    "sg:phone":"+90 322 321 3195",
    "sg:postcode":"09970",
    "sg:province":"Adana",
    "sg:tags":[
        "agricultural",
        "product"
    ],
    "wof:name":"Akpinar Tarim ?rn. A.s.",
    "wof:placetype":"venue"
},
  "geometry": {"coordinates":[35.3390045166,36.9790649414],"type":"Point"}
}