{
  "type": "Feature",
  "properties": {
    "iso:country":"TR",
    "sg:address":"Topkapi Ticaret Merkezi 2.kisim No:81",
    "sg:city":"Ikitelli",
    "sg:classifiers":[
        {
            "category":"Wholesale",
            "subcategory":"Auto Parts",
            "type":"Manufacturing & Wholesale Goods"
        }
    ],
    "sg:phone":"+90 212 482 0266",
    "sg:postcode":"34670",
    "sg:province":"Istanbul",
    "sg:tags":[
        "spare"
    ],
    "wof:name":"Aker Otomotiv",
    "wof:placetype":"venue"
},
  "geometry": {"coordinates":[28.7923316956,41.087600708],"type":"Point"}
}