{
  "type": "Feature",
  "properties": {
    "addr:full":"S?? Cd. No:55 ?mraniye \u00dcmraniye Istanbul",
    "addr:housenumber":"? ?;no 55 ?",
    "addr:street":"S;Cd.;Mraniye",
    "iso:country":"TR",
    "sg:address":"S?? Cd. No:55 ?mraniye",
    "sg:city":"\u00dcmraniye",
    "sg:classifiers":[
        {
            "category":"Manufacturing",
            "subcategory":"Rubber & Plastics",
            "type":"Manufacturing & Wholesale Goods"
        }
    ],
    "sg:phone":"+90 216 316 8503",
    "sg:province":"Istanbul",
    "sg:tags":[
        "industry"
    ],
    "wof:name":"G?rcam Plastik Dograma San. Tic. Ltd. Sti.",
    "wof:placetype":"venue"
},
  "geometry": {"coordinates":[29.2383918762,41.0308189392],"type":"Point"}
}