{
  "type": "Feature",
  "properties": {
    "iso:country":"TR",
    "sg:address":"Resit Galip Cd. No:88/5 G.o.pasa",
    "sg:city":"\u00dcmraniye",
    "sg:orig_category":"General Industrial Products",
    "sg:phone":"+90 312 445 0244",
    "sg:postcode":"81260",
    "sg:province":"Ankara",
    "wof:name":"Medikal Inoks Paslanmaz ?elik Cihaz. Sistem. Imal. A.s.",
    "wof:placetype":"venue"
},
  "geometry": {"coordinates":[32.8534011841,39.8884048462],"type":"Point"}
}