{
  "type": "Feature",
  "properties": {
    "addr:full":"Demirkapi Cd. Bayrampasa ?arsisi No:1/59 K:3 Bayrampasa Mersin Istanbul 52750",
    "addr:housenumber":"?;no;/ 59 k 3",
    "addr:postcode":"52750",
    "addr:street":"Demirkapi Cd. Bayrampasa;Bayrampasa",
    "iso:country":"TR",
    "sg:address":"Demirkapi Cd. Bayrampasa ?arsisi No:1/59 K:3 Bayrampasa",
    "sg:city":"Mersin",
    "sg:classifiers":[
        {
            "category":"Mining & Drilling",
            "type":"Manufacturing & Wholesale Goods"
        }
    ],
    "sg:phone":"+90 212 614 7230",
    "sg:postcode":"52750",
    "sg:province":"Istanbul",
    "sg:tags":[
        "industry",
        "mine"
    ],
    "wof:name":"Bereket K?m?rc?l?k San. Tic. Ltd. Sti.",
    "wof:placetype":"venue"
},
  "geometry": {"coordinates":[28.9759254456,41.0123786926],"type":"Point"}
}