{
  "type": "Feature",
  "properties": {
    "addr:full":"1201.sok. Teknik Malzeme Is Merkezi No:17 -p35 Bah\u00e7elievler Izmir 06500",
    "addr:housenumber":"no;p35",
    "addr:postcode":"06500",
    "iso:country":"TR",
    "sg:address":"1201.sok. Teknik Malzeme Is Merkezi No:17 -p35",
    "sg:city":"Bah\u00e7elievler",
    "sg:orig_category":"Environment Technolojy",
    "sg:phone":"+90 232 459 5049",
    "sg:postcode":"06500",
    "sg:province":"Izmir",
    "wof:name":"Cevsutek Ltd.sti.",
    "wof:placetype":"venue"
},
  "geometry": {"coordinates":[27.1423015594,38.4251480103],"type":"Point"}
}