{
  "type": "Feature",
  "properties": {
    "iso:country":"TR",
    "sg:address":"Esentepe Mah.keresteciler Sitesi 89.sok. No: 22/a",
    "sg:city":"Izmit",
    "sg:classifiers":[
        {
            "category":"Shopping",
            "subcategory":"Clothing, Apparel, & Fashions",
            "type":"Retail Goods"
        }
    ],
    "sg:phone":"+90 352 240 4048",
    "sg:postcode":"41300",
    "sg:province":"Kayseri",
    "sg:tags":[
        "bag-belt-accessories"
    ],
    "wof:name":"Ercalik Canta San.",
    "wof:placetype":"venue"
},
  "geometry": {"coordinates":[35.489136,38.722576],"type":"Point"}
}