{
  "type": "Feature",
  "properties": {
    "addr:full":"Kaptanpasa Sokak No: 21 06700 Ankara Cagaloglu Ankara 34440",
    "addr:housenumber":"no 21",
    "addr:postcode":"06700;34440",
    "addr:street":"Kaptanpasa Sokak",
    "iso:country":"TR",
    "sg:address":"Kaptanpasa Sokak No: 21 06700 Ankara",
    "sg:city":"Cagaloglu",
    "sg:classifiers":[
        {
            "category":"Shopping",
            "type":"Retail Goods"
        }
    ],
    "sg:phone":"+90 312 447 1558",
    "sg:postcode":"34440",
    "sg:province":"Ankara",
    "sg:tags":[
        "finished",
        "-",
        "metallic"
    ],
    "wof:name":"Tunatek Hasir Celik San. Ltd Sti",
    "wof:placetype":"venue"
},
  "geometry": {"coordinates":[32.875957489,39.8964424133],"type":"Point"}
}