{
  "type": "Feature",
  "properties": {
    "addr:full":"Ugur Mumcu Cad Meftun Is Merkezi Kat4/406 Kdz Eregli Zonguldak 67300",
    "addr:housenumber":"kat4 / 406",
    "addr:postcode":"67300",
    "addr:street":"Mumcu Cad Meftun;Kdz Eregli",
    "iso:country":"TR",
    "sg:address":"Ugur Mumcu Cad Meftun Is Merkezi Kat4/406",
    "sg:city":"Kdz Eregli",
    "sg:classifiers":[
        {
            "category":"Train Station",
            "subcategory":"Rail",
            "type":"Transportation"
        }
    ],
    "sg:postcode":"67300",
    "sg:province":"Zonguldak",
    "sg:tags":[
        "sheet",
        "iron"
    ],
    "wof:name":"Vesile Metal San A.s",
    "wof:placetype":"venue"
},
  "geometry": {"coordinates":[31.7925,41.451401],"type":"Point"}
}