{
  "type": "Feature",
  "properties": {
    "addr:full":"Avni Sizen Cd. No:2/a Mecidiyek? Uskudar Istanbul 34704",
    "addr:housenumber":"no 2 / a;?",
    "addr:postcode":"34704",
    "addr:street":"Cd.;Mecidiyek",
    "iso:country":"TR",
    "sg:address":"Avni Sizen Cd. No:2/a Mecidiyek?",
    "sg:city":"Uskudar",
    "sg:classifiers":[
        {
            "category":"Banks & Credit Unions",
            "subcategory":"Investment Brokerage",
            "type":"Services"
        }
    ],
    "sg:phone":"+90 212 275 9531",
    "sg:postcode":"34704",
    "sg:province":"Istanbul",
    "sg:tags":[
        "-",
        "export",
        "import"
    ],
    "wof:name":"G?ltas Yapi ?r?n. San. Tic. A.s.",
    "wof:placetype":"venue"
},
  "geometry": {"coordinates":[28.9861831665,41.0408554077],"type":"Point"}
}