{
  "type": "Feature",
  "properties": {
    "iso:country":"TR",
    "sg:address":"P.k: 81",
    "sg:city":"Tepebasi",
    "sg:classifiers":[
        {
            "category":"Wholesale",
            "subcategory":"Books, Periodicals, & Newspapers",
            "type":"Manufacturing & Wholesale Goods"
        }
    ],
    "sg:phone":"+90 352 222 0102",
    "sg:postcode":"Istanbu",
    "sg:province":"Kayseri",
    "sg:tags":[
        "house",
        "publishing"
    ],
    "wof:name":"Akademi Ugur Er Tarimsal Kitap Tanitim Hizm.paz.",
    "wof:placetype":"venue"
},
  "geometry": {"coordinates":[29.2620620728,40.8785095215],"type":"Point"}
}