{
  "type": "Feature",
  "properties": {
    "addr:full":"Barbaros Bulvari No:24/8 Balmumcu Istanbul 34349",
    "addr:housenumber":"no 24 / 8",
    "addr:postcode":"34349",
    "addr:street":"Barbaros Bulvari",
    "iso:country":"TR",
    "sg:address":"Barbaros Bulvari No:24/8",
    "sg:city":"Balmumcu",
    "sg:classifiers":[
        {
            "category":"Professional",
            "subcategory":"Engineering",
            "type":"Services"
        }
    ],
    "sg:phone":"+90 212 274 3828",
    "sg:postcode":"34349",
    "sg:province":"Istanbul",
    "sg:tags":[
        "architect"
    ],
    "wof:name":"Merka M?savirlik M?messillik M?hendis. Tic. A.s.",
    "wof:placetype":"venue"
},
  "geometry": {"coordinates":[28.9861831665,41.0408554077],"type":"Point"}
}