{
  "type": "Feature",
  "properties": {
    "addr:full":"Osmanbey Sk. Ist. Ish. K:1/101 Hasanpasa/kadik? Konya 34722",
    "addr:housenumber":"1 / 101",
    "addr:postcode":"34722",
    "addr:street":"Osmanbey Sk. Ist. Ish. K",
    "iso:country":"TR",
    "sg:address":"Osmanbey Sk. Ist. Ish. K:1/101",
    "sg:city":"Hasanpasa/kadik?",
    "sg:classifiers":[
        {
            "category":"Wholesale",
            "subcategory":"Medical Equipment & Supplies",
            "type":"Manufacturing & Wholesale Goods"
        }
    ],
    "sg:phone":"+90 332 350 0228",
    "sg:postcode":"34722",
    "sg:province":"Konya",
    "sg:tags":[
        "material"
    ],
    "wof:name":"Start Medical",
    "wof:placetype":"venue"
},
  "geometry": {"coordinates":[32.4990272522,37.8715362549],"type":"Point"}
}