{
  "type": "Feature",
  "properties": {
    "iso:country":"TR",
    "sg:address":"Y. Beyazit Cd. No:24/a",
    "sg:city":"Y.bosna",
    "sg:classifiers":[
        {
            "category":"Shopping",
            "subcategory":"Florist",
            "type":"Retail Goods"
        }
    ],
    "sg:phone":"+90 212 551 1974",
    "sg:province":"Istanbul",
    "sg:tags":[
        "flower"
    ],
    "wof:name":"Safak Ulusl. ?i?ek?ilik",
    "wof:placetype":"venue"
},
  "geometry": {"coordinates":[29.167181015,40.9164772034],"type":"Point"}
}