{
  "type": "Feature",
  "properties": {
    "addr:full":"Ortakent Bodrum Mugla 48400",
    "addr:postcode":"48400",
    "iso:country":"TR",
    "sg:address":"Ortakent",
    "sg:city":"Bodrum",
    "sg:classifiers":[
        {
            "category":"Social Services",
            "subcategory":"Retirement Home",
            "type":"Services"
        }
    ],
    "sg:phone":"+90 252358508635",
    "sg:postcode":"48400",
    "sg:province":"Mugla",
    "sg:tags":[
        "holiday",
        "village"
    ],
    "wof:name":"Club M?skebi",
    "wof:placetype":"venue"
},
  "geometry": {"coordinates":[27.2962493896,37.1072387695],"type":"Point"}
}