{
  "type": "Feature",
  "properties": {
    "addr:full":"Bostanci Sanayi Sitesi Huzukoca Cad. Cilek Sok. No:10 Icerenkoy Istanbul Istanbul",
    "addr:housenumber":"no 10",
    "addr:street":"Bostanci Sanayi Sitesi Huzukoca Cad. Cilek Sok.",
    "iso:country":"TR",
    "sg:address":"Bostanci Sanayi Sitesi Huzukoca Cad. Cilek Sok. No:10 Icerenkoy",
    "sg:city":"Istanbul",
    "sg:classifiers":[
        {
            "category":"Utilities",
            "subcategory":"Recycling",
            "type":"Services"
        }
    ],
    "sg:phone":"+90 216 575 5812",
    "sg:province":"Istanbul",
    "sg:tags":[
        "measuring",
        "weighing"
    ],
    "wof:name":"Baykon Endustriyel Tarim Sistemleri A.s.",
    "wof:placetype":"venue"
},
  "geometry": {"coordinates":[29.1039009094,40.9737281799],"type":"Point"}
}