{
  "type": "Feature",
  "properties": {
    "iso:country":"TR",
    "sg:address":"Buyukdere Cad. No: 45/26 Sisli",
    "sg:city":"Gayrettepe",
    "sg:classifiers":[
        {
            "category":"Professional",
            "subcategory":"Testing Lab",
            "type":"Services"
        }
    ],
    "sg:phone":"+90 212 211 1327",
    "sg:postcode":"34349",
    "sg:province":"Istanbul",
    "sg:tags":[
        "laboratory",
        "material"
    ],
    "wof:name":"Labora Lab. Mlz. Tic. A.s.",
    "wof:placetype":"venue"
},
  "geometry": {"coordinates":[29.0153751373,41.0741081238],"type":"Point"}
}