{
  "type": "Feature",
  "properties": {
    "iso:country":"TR",
    "sg:address":"Millet Cad .no:162",
    "sg:city":"Topkapi",
    "sg:classifiers":[
        {
            "category":"Wholesale",
            "subcategory":"Auto Parts",
            "type":"Manufacturing & Wholesale Goods"
        }
    ],
    "sg:phone":"+90 212 621 4071",
    "sg:postcode":"34093",
    "sg:province":"Istanbul",
    "sg:tags":[
        "spare"
    ],
    "wof:name":"Eryaz As",
    "wof:placetype":"venue"
},
  "geometry": {"coordinates":[28.8863658905,41.0688476562],"type":"Point"}
}