{
  "type": "Feature",
  "properties": {
    "addr:full":"58.sok. No:71 Ostim Ikitelli/K\u00fc\u00e7\u00fck\u00e7ekmece Ankara 34670",
    "addr:housenumber":"no 71",
    "addr:postcode":"34670",
    "iso:country":"TR",
    "sg:address":"58.sok. No:71 Ostim",
    "sg:city":"Ikitelli/K\u00fc\u00e7\u00fck\u00e7ekmece",
    "sg:classifiers":[
        {
            "category":"Manufacturing",
            "subcategory":"Metals",
            "type":"Manufacturing & Wholesale Goods"
        }
    ],
    "sg:phone":"+90 31238539333435",
    "sg:postcode":"34670",
    "sg:province":"Ankara",
    "sg:tags":[
        "iron-steel",
        "peoducts"
    ],
    "wof:name":"Seyda San. Urunl. Ic Ve Dis Tic.ltd.sti.",
    "wof:placetype":"venue"
},
  "geometry": {"coordinates":[32.7448616028,39.9804763794],"type":"Point"}
}