{
  "type": "Feature",
  "properties": {
    "iso:country":"TR",
    "sg:address":"Halkali Cd. No:78",
    "sg:city":"Sefak?",
    "sg:classifiers":[
        {
            "category":"Shopping",
            "subcategory":"Florist",
            "type":"Retail Goods"
        }
    ],
    "sg:phone":"+90 212 580 2529",
    "sg:province":"Istanbul",
    "sg:tags":[
        "flower"
    ],
    "wof:name":"Ulusl. ?nal ?i?ek Galerisi",
    "wof:placetype":"venue"
},
  "geometry": {"coordinates":[28.7976398468,41.0020751953],"type":"Point"}
}