{
  "type": "Feature",
  "properties": {
    "iso:country":"TR",
    "sg:address":"Hacieyupli Koyu",
    "sg:city":"Tandogan",
    "sg:classifiers":[
        {
            "category":"Farming",
            "subcategory":"Farm",
            "type":"Manufacturing & Wholesale Goods"
        }
    ],
    "sg:phone":"+90 258 371 8074",
    "sg:postcode":"44050",
    "sg:province":"Denizli",
    "sg:tags":[
        "agricultural",
        "product"
    ],
    "wof:name":"Agroma",
    "wof:placetype":"venue"
},
  "geometry": {"coordinates":[29.0864906311,37.773525238],"type":"Point"}
}