{
  "type": "Feature",
  "properties": {
    "iso:country":"TR",
    "sg:address":"Selamet Mah.2 Cevizli Cad.19/b",
    "sg:city":"Gulbahce",
    "sg:classifiers":[
        {
            "category":"Manufacturing",
            "subcategory":"Building Materials",
            "type":"Manufacturing & Wholesale Goods"
        }
    ],
    "sg:phone":"+90 224 256 3875",
    "sg:postcode":"31070",
    "sg:province":"Bursa",
    "sg:tags":[
        "lifts-elevators"
    ],
    "wof:name":"Yilmaz Asansor",
    "wof:placetype":"venue"
},
  "geometry": {"coordinates":[29.0707683563,40.198802948],"type":"Point"}
}