{
  "type": "Feature",
  "properties": {
    "iso:country":"TR",
    "sg:address":"Akhun Cad. No:2 Sincan Organize San.b?g.",
    "sg:city":"Maltepe",
    "sg:classifiers":[
        {
            "category":"Food & Beverages",
            "subcategory":"Supermarket",
            "type":"Retail Goods"
        }
    ],
    "sg:phone":"+90 312 267 2051",
    "sg:postcode":"01000",
    "sg:province":"Ankara",
    "sg:tags":[
        "frozen"
    ],
    "wof:name":"Harika Dondurulmus Gida A.s.",
    "wof:placetype":"venue"
},
  "geometry": {"coordinates":[32.8560333252,39.9438743591],"type":"Point"}
}