{
  "type": "Feature",
  "properties": {
    "iso:country":"TR",
    "sg:address":"Necatibey Cd. No:95",
    "sg:city":"Karak\u00f6y",
    "sg:classifiers":[
        {
            "category":"Utilities",
            "subcategory":"Natural Gas",
            "type":"Services"
        }
    ],
    "sg:phone":"+90 212 249 2495",
    "sg:province":"Istanbul",
    "sg:tags":[
        "tank-heating-natural"
    ],
    "wof:name":"Era End?striyel R?le Imalat San. Tic. Ltd. Sti.",
    "wof:placetype":"venue"
},
  "geometry": {"coordinates":[28.9794883728,41.026134491],"type":"Point"}
}