{
  "type": "Feature",
  "properties": {
    "iso:country":"TR",
    "sg:address":"Kemalpasa Cad. No: 12 Pinarbasi",
    "sg:city":"Ikitelli/K\u00fc\u00e7\u00fck\u00e7ekmece",
    "sg:classifiers":[
        {
            "category":"Building & Trades",
            "subcategory":"Construction",
            "type":"Services"
        }
    ],
    "sg:phone":"+90 232 479 1066",
    "sg:postcode":"34670",
    "sg:province":"Izmir",
    "sg:tags":[
        "industry",
        "mold"
    ],
    "wof:name":"Etap Makina Kalip Ve Plastik. San.a.s.",
    "wof:placetype":"venue"
},
  "geometry": {"coordinates":[29.0394763947,40.1991119385],"type":"Point"}
}