{
  "type": "Feature",
  "properties": {
    "addr:full":"Millet Cad. Karagul Is Merkezi No:84/200 Findikzade Istanbul",
    "addr:housenumber":"no 84 / 200",
    "addr:street":"Millet Cad. Karagul",
    "iso:country":"TR",
    "sg:address":"Millet Cad. Karagul Is Merkezi No:84/200",
    "sg:city":"Findikzade",
    "sg:classifiers":[
        {
            "category":"Manufacturing",
            "subcategory":"Glass & Minerals",
            "type":"Manufacturing & Wholesale Goods"
        }
    ],
    "sg:phone":"+90 212 621 1167",
    "sg:province":"Istanbul",
    "sg:tags":[
        "glass-mirror"
    ],
    "wof:name":"Delta",
    "wof:placetype":"venue"
},
  "geometry": {"coordinates":[28.9759254456,41.0123786926],"type":"Point"}
}