{
  "type": "Feature",
  "properties": {
    "iso:country":"TR",
    "sg:address":"Mahatma Cad.no:56 G.o.p.",
    "sg:city":"Boyobat",
    "sg:classifiers":[
        {
            "category":"Government",
            "subcategory":"Embassy",
            "type":"Public Place"
        }
    ],
    "sg:phone":"+90 312 446 5831",
    "sg:province":"Ankara",
    "sg:tags":[
        "foreign"
    ],
    "wof:name":"Filipinler B?y?kel?iligi",
    "wof:placetype":"venue"
},
  "geometry": {"coordinates":[32.876209259,39.8921089172],"type":"Point"}
}