{
  "type": "Feature",
  "properties": {
    "iso:country":"TR",
    "sg:address":"Alidede Mah. Bagdat ?arsisi No:44",
    "sg:city":"Nazilli",
    "sg:classifiers":[
        {
            "category":"Home & Garden",
            "subcategory":"Household Appliances",
            "type":"Retail Goods"
        }
    ],
    "sg:phone":"+90 322 359 6040",
    "sg:postcode":"65600",
    "sg:province":"Adana",
    "sg:tags":[
        "utensil",
        "electrical"
    ],
    "wof:name":"Arba Elektronik Gida Insaat Sanayi Ve Ticaret Ltd. Sti.",
    "wof:placetype":"venue"
},
  "geometry": {"coordinates":[35.3250198364,36.9854202271],"type":"Point"}
}