{
  "type": "Feature",
  "properties": {
    "iso:country":"TR",
    "sg:address":"?akmak?lar Yokusu No:47",
    "sg:city":"Mercan",
    "sg:orig_category":"Textile Suplementaries",
    "sg:phone":"+90 212 528 6031",
    "sg:postcode":"12600",
    "sg:province":"Istanbul",
    "wof:name":"Sila Tic.",
    "wof:placetype":"venue"
},
  "geometry": {"coordinates":[29.0204143524,41.0160713196],"type":"Point"}
}