{
  "type": "Feature",
  "properties": {
    "addr:full":"Zambak Sk. No:25 Beyoglu 07230 Istanbul",
    "addr:housenumber":"25",
    "addr:postcode":"07230",
    "addr:street":"Zambak Sk. No",
    "iso:country":"TR",
    "sg:address":"Zambak Sk. No:25 Beyoglu",
    "sg:city":"07230",
    "sg:classifiers":[
        {
            "category":"Sports & Exercise",
            "subcategory":"Tennis Court",
            "type":"Entertainment"
        }
    ],
    "sg:phone":"+90 212 251 0401",
    "sg:province":"Istanbul",
    "sg:tags":[
        "equipment",
        "material"
    ],
    "wof:name":"Dinamik Doga Sporlari Turizm San. Tic. Ltd. Sti.",
    "wof:placetype":"venue"
},
  "geometry": {"coordinates":[28.982935,41.036633],"type":"Point"}
}