{
  "type": "Feature",
  "properties": {
    "iso:country":"TR",
    "sg:address":"Ibrahim Bostanci",
    "sg:city":"Baklan",
    "sg:classifiers":[
        {
            "category":"Government",
            "subcategory":"Office",
            "type":"Public Place"
        }
    ],
    "sg:phone":"+90 364 452 2021",
    "sg:postcode":"32500",
    "sg:province":"?orum",
    "sg:tags":[
        "municipality"
    ],
    "wof:name":"Bogazkale Belediye Baskani",
    "wof:placetype":"venue"
},
  "geometry": {"coordinates":[30.9526996613,37.7938499451],"type":"Point"}
}