{
  "type": "Feature",
  "properties": {
    "addr:full":"Ata 2.sitesi Akasya Cad.villa 27 Cengelkoy Istanbul 28950",
    "addr:housenumber":"27",
    "addr:postcode":"28950",
    "addr:street":"Cengelkoy Istanbul",
    "iso:country":"TR",
    "sg:address":"Ata 2.sitesi Akasya Cad.villa 27",
    "sg:city":"Cengelkoy",
    "sg:classifiers":[
        {
            "category":"Home & Garden",
            "subcategory":"Building Materials",
            "type":"Retail Goods"
        }
    ],
    "sg:phone":"+90 216 486 0030",
    "sg:postcode":"28950",
    "sg:province":"Istanbul",
    "sg:tags":[
        "stone",
        "natural",
        "marble"
    ],
    "wof:name":"Aydogan Import Export",
    "wof:placetype":"venue"
},
  "geometry": {"coordinates":[28.9861831665,41.0408554077],"type":"Point"}
}