{
  "type": "Feature",
  "properties": {
    "iso:country":"TR",
    "sg:address":"Bagdat Cad. No:138",
    "sg:city":"Gebze",
    "sg:classifiers":[
        {
            "category":"Food & Beverages",
            "subcategory":"Specialty",
            "type":"Retail Goods"
        }
    ],
    "sg:phone":"+90 262 646 5120",
    "sg:postcode":"41400",
    "sg:province":"Kocaeli",
    "sg:tags":[
        "materials-spices",
        "additive"
    ],
    "wof:name":"Mikromaks",
    "wof:placetype":"venue"
},
  "geometry": {"coordinates":[29.953130722,40.7665405273],"type":"Point"}
}