{
  "type": "Feature",
  "properties": {
    "iso:country":"TR",
    "sg:address":"Kasap Sok.no:19/15",
    "sg:city":"Esentepe",
    "sg:classifiers":[
        {
            "category":"Shopping",
            "subcategory":"Crafts & Fabrics",
            "type":"Retail Goods"
        }
    ],
    "sg:phone":"+90 212 275 0244",
    "sg:postcode":"01930",
    "sg:province":"Istanbul",
    "sg:tags":[
        "knitting"
    ],
    "wof:name":"Intima Tekstil San.a.s.",
    "wof:placetype":"venue"
},
  "geometry": {"coordinates":[29.0103473663,41.067653656],"type":"Point"}
}