{
  "type": "Feature",
  "properties": {
    "addr:full":"Yeni San Sit. Cumhuriyet Cad. No: 230 Topkapi Balikesir 34020",
    "addr:housenumber":"230",
    "addr:postcode":"34020",
    "addr:street":"Cumhuriyet Cad. No;Balikesir",
    "iso:country":"TR",
    "sg:address":"Yeni San Sit. Cumhuriyet Cad. No: 230",
    "sg:city":"Topkapi",
    "sg:classifiers":[
        {
            "category":"Wholesale",
            "subcategory":"Auto Parts",
            "type":"Manufacturing & Wholesale Goods"
        }
    ],
    "sg:phone":"+90 266 246 3231",
    "sg:postcode":"34020",
    "sg:province":"Balikesir",
    "sg:tags":[
        "spare"
    ],
    "wof:name":"Eray Oto",
    "wof:placetype":"venue"
},
  "geometry": {"coordinates":[27.8853626251,39.6448822021],"type":"Point"}
}