{
  "type": "Feature",
  "properties": {
    "iso:country":"TR",
    "sg:address":"R?garli Sk. No:16/134 Ulus",
    "sg:city":"Okmeydani",
    "sg:classifiers":[
        {
            "category":"Professional",
            "subcategory":"Detective & Security Services",
            "type":"Services"
        }
    ],
    "sg:phone":"+90 312 311 7044",
    "sg:postcode":"43050",
    "sg:province":"Ankara",
    "sg:tags":[
        "material"
    ],
    "wof:name":"Alfa Elektronik Tv Uydu Sistem. A.s.",
    "wof:placetype":"venue"
},
  "geometry": {"coordinates":[32.856033,39.943874],"type":"Point"}
}