{
  "type": "Feature",
  "properties": {
    "addr:full":"Gaziakdemir Mah. Cenk Sok. No: 44 G?g?en Bursa",
    "addr:housenumber":"no 44 g ? g ?",
    "addr:street":"Gaziakdemir Mah. Cenk Sok.;En Bursa",
    "iso:country":"TR",
    "sg:address":"Gaziakdemir Mah. Cenk Sok. No: 44",
    "sg:city":"G?g?en",
    "sg:classifiers":[
        {
            "category":"Shopping",
            "subcategory":"Clothing, Apparel, & Fashions",
            "type":"Retail Goods"
        }
    ],
    "sg:phone":"+90 224 232 1052",
    "sg:province":"Bursa",
    "sg:tags":[
        "ready",
        "wear"
    ],
    "wof:name":"Dostex Konfeksiyon San.tic.",
    "wof:placetype":"venue"
},
  "geometry": {"coordinates":[29.0432090759,40.2018852234],"type":"Point"}
}