{
  "type": "Feature",
  "properties": {
    "iso:country":"TR",
    "sg:address":"Yeniyol Cad. 22/3 Sisli",
    "sg:city":"Besiktas",
    "sg:classifiers":[
        {
            "category":"Organizations",
            "subcategory":"Professional Association",
            "type":"Services"
        }
    ],
    "sg:phone":"+90 212",
    "sg:postcode":"75200",
    "sg:province":"Istanbul",
    "sg:tags":[
        "fair"
    ],
    "wof:name":"Demoplex Ltd. Sti.",
    "wof:placetype":"venue"
},
  "geometry": {"coordinates":[28.972322464,41.0417823792],"type":"Point"}
}