{
  "type": "Feature",
  "properties": {
    "addr:full":"Kizilarik Mah.gazi Bulvari No:454 \u00dcsk\u00fcdar Antalya",
    "addr:housenumber":"no",
    "addr:street":"Mah.Gazi Bulvari;U\u0308Skuedar",
    "iso:country":"TR",
    "sg:address":"Kizilarik Mah.gazi Bulvari No:454",
    "sg:city":"\u00dcsk\u00fcdar",
    "sg:classifiers":[
        {
            "category":"Manufacturing",
            "subcategory":"Building Materials",
            "type":"Manufacturing & Wholesale Goods"
        }
    ],
    "sg:phone":"+90 242 339 2111",
    "sg:province":"Antalya",
    "sg:tags":[
        "promotional"
    ],
    "wof:name":"Erbaylar Hasircilik Ve Turzm Ltd.sti.",
    "wof:placetype":"venue"
},
  "geometry": {"coordinates":[30.7257328033,36.9130172729],"type":"Point"}
}