{
  "type": "Feature",
  "properties": {
    "addr:full":"1 Matbaacilar Sit. ?iftehavuzlar Yolu Sk. Maltepe Bak\u0131rk\u00f6y Istanbul",
    "addr:housenumber":"1;?",
    "addr:street":"Matbaacilar Sit.;Iftehavuzlar Yolu Sk. Maltepe Bakirkoey",
    "iso:country":"TR",
    "sg:address":"1 Matbaacilar Sit. ?iftehavuzlar Yolu Sk. Maltepe",
    "sg:city":"Bak\u0131rk\u00f6y",
    "sg:classifiers":[
        {
            "category":"Shopping",
            "subcategory":"Stationery & Office Supplies",
            "type":"Retail Goods"
        }
    ],
    "sg:phone":"+90 212 565 3886",
    "sg:province":"Istanbul",
    "sg:tags":[
        "paper"
    ],
    "wof:name":"Kagitpas Kagit?ilik",
    "wof:placetype":"venue"
},
  "geometry": {"coordinates":[28.9126701355,41.0204658508],"type":"Point"}
}