{
  "type": "Feature",
  "properties": {
    "addr:full":"San. Sitesi 6. Ada 9. Blok Edremit Ikitelli/K\u00fc\u00e7\u00fck\u00e7ekmece Balikesir 34670",
    "addr:housenumber":"blok edremit",
    "addr:postcode":"34670",
    "addr:street":"Ada 9;Balikesir",
    "iso:country":"TR",
    "sg:address":"San. Sitesi 6. Ada 9. Blok Edremit",
    "sg:city":"Ikitelli/K\u00fc\u00e7\u00fck\u00e7ekmece",
    "sg:classifiers":[
        {
            "category":"Manufacturing",
            "subcategory":"Tools & Machinery",
            "type":"Manufacturing & Wholesale Goods"
        }
    ],
    "sg:phone":"+90 266 373 2805",
    "sg:postcode":"34670",
    "sg:province":"Balikesir",
    "sg:tags":[
        "machine",
        "industry"
    ],
    "wof:name":"Ermaksan Erler Makina San. Tic. Koll. Sti.",
    "wof:placetype":"venue"
},
  "geometry": {"coordinates":[27.8833007812,39.6520996094],"type":"Point"}
}