{
  "type": "Feature",
  "properties": {
    "addr:full":"Y. Beyazit Cd. No:140 Y. Bosna Istanbul 42250",
    "addr:housenumber":"no",
    "addr:postcode":"42250",
    "addr:street":"Cd.;140 Y. Bosna",
    "iso:country":"TR",
    "sg:address":"Y. Beyazit Cd. No:140 Y.",
    "sg:city":"Bosna",
    "sg:classifiers":[
        {
            "category":"Shopping",
            "subcategory":"Florist",
            "type":"Retail Goods"
        }
    ],
    "sg:phone":"+90 212 653 8261",
    "sg:postcode":"42250",
    "sg:province":"Istanbul",
    "sg:tags":[
        "flower"
    ],
    "wof:name":"Yesim Ulusl. ?i?ek?ilik",
    "wof:placetype":"venue"
},
  "geometry": {"coordinates":[28.7526302338,41.1940803528],"type":"Point"}
}