{
  "type": "Feature",
  "properties": {
    "iso:country":"TR",
    "sg:address":"31.sok. No:6 Pinarbasi",
    "sg:city":"Ortak?",
    "sg:classifiers":[
        {
            "category":"Organizations",
            "subcategory":"Professional Association",
            "type":"Services"
        }
    ],
    "sg:phone":"+90 232 479 0325",
    "sg:postcode":"80840",
    "sg:province":"Izmir",
    "wof:name":"Pinarbasi Esnaf Sanatkarlar Odasi",
    "wof:placetype":"venue"
},
  "geometry": {"coordinates":[32.5594444275,39.9631576538],"type":"Point"}
}