{
  "type": "Feature",
  "properties": {
    "addr:full":"2. San. Sit. 302. Sk. No:25 Bornova Merkez Izmir",
    "addr:housenumber":"2;302",
    "addr:street":"San. Sit.;Sk. No 25 Bornova",
    "iso:country":"TR",
    "sg:address":"2. San. Sit. 302. Sk. No:25 Bornova",
    "sg:city":"Merkez",
    "sg:classifiers":[
        {
            "category":"Wholesale",
            "subcategory":"Machinery & Supplies",
            "type":"Manufacturing & Wholesale Goods"
        }
    ],
    "sg:phone":"+90 232 486 5848",
    "sg:province":"Izmir",
    "sg:tags":[
        "bearing",
        "ball"
    ],
    "wof:name":"Disli San. Tic. Ltd. Sti.",
    "wof:placetype":"venue"
},
  "geometry": {"coordinates":[27.219601,38.466202],"type":"Point"}
}