{
  "type": "Feature",
  "properties": {
    "addr:full":"4.bolge 10.cad. No:12 B.cekmece Melikgazi Istanbul 38070",
    "addr:housenumber":"no 12",
    "addr:postcode":"38070",
    "addr:street":"B.Cekmece Melikgazi",
    "iso:country":"TR",
    "sg:address":"4.bolge 10.cad. No:12 B.cekmece",
    "sg:city":"Melikgazi",
    "sg:classifiers":[
        {
            "category":"Manufacturing",
            "subcategory":"Metals",
            "type":"Manufacturing & Wholesale Goods"
        }
    ],
    "sg:phone":"+90 212 886 8787",
    "sg:postcode":"38070",
    "sg:province":"Istanbul",
    "sg:tags":[
        "aluminium",
        "industry"
    ],
    "wof:name":"Sistem Aluminyum",
    "wof:placetype":"venue"
},
  "geometry": {"coordinates":[28.5661048889,41.0191421509],"type":"Point"}
}