{
  "type": "Feature",
  "properties": {
    "addr:full":"Mesrutiyet Mah. Haci Mansur Sk. No:94/3 Osmanbey Istanbul 63000",
    "addr:housenumber":"94 / 3",
    "addr:postcode":"63000",
    "addr:street":"Mesrutiyet Mah. Haci Mansur Sk. No",
    "iso:country":"TR",
    "sg:address":"Mesrutiyet Mah. Haci Mansur Sk. No:94/3",
    "sg:city":"Osmanbey",
    "sg:classifiers":[
        {
            "category":"Shopping",
            "subcategory":"Clothing, Apparel, & Fashions",
            "type":"Retail Goods"
        }
    ],
    "sg:phone":"+90 2122324685679",
    "sg:postcode":"63000",
    "sg:province":"Istanbul",
    "sg:tags":[
        "woman",
        "wear"
    ],
    "wof:name":"Soydan Koll. Giyim San. Tic. Ltd. Sti. .",
    "wof:placetype":"venue"
},
  "geometry": {"coordinates":[28.9903488159,41.0538444519],"type":"Point"}
}