{
  "type": "Feature",
  "properties": {
    "addr:full":"Ortaklar Cd. No:13 S? Apt M.k? Bakirk?y Istanbul",
    "addr:housenumber":"no 13;?",
    "addr:street":"S",
    "iso:country":"TR",
    "sg:address":"Ortaklar Cd. No:13 S? Apt M.k?",
    "sg:city":"Bakirk?y",
    "sg:classifiers":[
        {
            "category":"Professional",
            "subcategory":"Employment Agencies",
            "type":"Services"
        }
    ],
    "sg:phone":"+90 212 274 9950",
    "sg:province":"Istanbul",
    "sg:tags":[
        "machine"
    ],
    "wof:name":"Ipas-ofis Otomasyon Sistem. San. Tic.",
    "wof:placetype":"venue"
},
  "geometry": {"coordinates":[28.9958343506,41.0652160645],"type":"Point"}
}