{
  "type": "Feature",
  "properties": {
    "addr:full":"Kayahatun Sk. No:23 Harbiye Istanbul 31080",
    "addr:housenumber":"23",
    "addr:postcode":"31080",
    "addr:street":"Kayahatun Sk. No",
    "iso:country":"TR",
    "sg:address":"Kayahatun Sk. No:23",
    "sg:city":"Harbiye",
    "sg:classifiers":[
        {
            "category":"Airport",
            "subcategory":"International",
            "type":"Transportation"
        }
    ],
    "sg:phone":"+90 212 532 8202",
    "sg:postcode":"31080",
    "sg:province":"Istanbul",
    "wof:name":"Alp Uluslararasi Tasima.",
    "wof:placetype":"venue"
},
  "geometry": {"coordinates":[28.9864845276,41.0490760803],"type":"Point"}
}