{
  "type": "Feature",
  "properties": {
    "iso:country":"TR",
    "sg:address":"Ihsaniye Mah Kirim Cad No:2",
    "sg:city":"Sisli",
    "sg:classifiers":[
        {
            "category":"Manufacturing",
            "subcategory":"Glass & Minerals",
            "type":"Manufacturing & Wholesale Goods"
        }
    ],
    "sg:phone":"+90 222 221 2639",
    "sg:postcode":"65710",
    "sg:province":"Eskisehir",
    "sg:tags":[
        "glass-mirror"
    ],
    "wof:name":"Seray Cam",
    "wof:placetype":"venue"
},
  "geometry": {"coordinates":[30.5223484039,39.7793998718],"type":"Point"}
}