{
  "type": "Feature",
  "properties": {
    "addr:full":"Kahyalar Beldesi Inonu Cad. Gazipasa Antalya 01120",
    "addr:postcode":"01120",
    "addr:street":"Inonu Cad. Gazipasa",
    "iso:country":"TR",
    "sg:address":"Kahyalar Beldesi Inonu Cad.",
    "sg:city":"Gazipasa",
    "sg:classifiers":[
        {
            "category":"Manufacturing",
            "subcategory":"Chemicals & Compounds",
            "type":"Manufacturing & Wholesale Goods"
        }
    ],
    "sg:phone":"+90 242 582 7372",
    "sg:postcode":"01120",
    "sg:province":"Antalya",
    "sg:tags":[
        "agricultural"
    ],
    "wof:name":"Kalayci Tarim",
    "wof:placetype":"venue"
},
  "geometry": {"coordinates":[30.7031345367,36.8875045776],"type":"Point"}
}