{
  "type": "Feature",
  "properties": {
    "addr:full":"Yesiloba Mh. San. Sit. 26. Blok No:1 Sel?uklu Adana 42300",
    "addr:housenumber":"26 blok no 1;?",
    "addr:postcode":"42300",
    "addr:street":"Yesiloba Mh. San. Sit.;Uklu Adana",
    "iso:country":"TR",
    "sg:address":"Yesiloba Mh. San. Sit. 26. Blok No:1",
    "sg:city":"Sel?uklu",
    "sg:classifiers":[
        {
            "category":"Wholesale",
            "subcategory":"Machinery & Supplies",
            "type":"Manufacturing & Wholesale Goods"
        }
    ],
    "sg:phone":"+90 322 428 5051",
    "sg:postcode":"42300",
    "sg:province":"Adana",
    "sg:tags":[
        "heavy",
        "construction",
        "macinery"
    ],
    "wof:name":"Oguz Mak.",
    "wof:placetype":"venue"
},
  "geometry": {"coordinates":[35.3250198364,36.9854202271],"type":"Point"}
}