{
  "type": "Feature",
  "properties": {
    "addr:full":"Ucler Mah. Isilca Cad.no:2 Dinar Melikgazi Afyon 38030",
    "addr:housenumber":"2",
    "addr:postcode":"38030",
    "addr:street":"Ucler Mah. Isilca Cad.No;Melikgazi",
    "iso:country":"TR",
    "sg:address":"Ucler Mah. Isilca Cad.no:2 Dinar",
    "sg:city":"Melikgazi",
    "sg:classifiers":[
        {
            "category":"Government",
            "subcategory":"Office",
            "type":"Public Place"
        }
    ],
    "sg:phone":"+90 272 353 6064",
    "sg:postcode":"38030",
    "sg:province":"Afyon",
    "sg:tags":[
        "chamber",
        "industry",
        "commerce"
    ],
    "wof:name":"Dinar Ticaret Ve Sanayi Odasi",
    "wof:placetype":"venue"
},
  "geometry": {"coordinates":[30.5382652283,38.7579841614],"type":"Point"}
}