{
  "type": "Feature",
  "properties": {
    "iso:country":"TR",
    "sg:address":"Divanyolu Cd. No:14 Sultanahmet",
    "sg:city":"Kadikoy",
    "sg:orig_category":"Art Galeries",
    "sg:phone":"+90 212 526 9096",
    "sg:postcode":"01370",
    "sg:province":"Istanbul",
    "wof:name":"Tedev El Sanat. Tic. A.s.",
    "wof:placetype":"venue"
},
  "geometry": {"coordinates":[28.9861831665,41.0408554077],"type":"Point"}
}