{
  "type": "Feature",
  "properties": {
    "addr:full":"62. Ada Gardenya 3 Plaza Kat:2 D:10 Atasehir Kartal Istanbul 34880",
    "addr:housenumber":"62;3;2 d 10",
    "addr:postcode":"34880",
    "addr:street":"Ada Gardenya;Plaza Kat;Atasehir Kartal",
    "iso:country":"TR",
    "sg:address":"62. Ada Gardenya 3 Plaza Kat:2 D:10 Atasehir",
    "sg:city":"Kartal",
    "sg:classifiers":[
        {
            "category":"Manufacturing",
            "subcategory":"Metals",
            "type":"Manufacturing & Wholesale Goods"
        }
    ],
    "sg:phone":"+90 216 455 2456",
    "sg:postcode":"34880",
    "sg:province":"Istanbul",
    "sg:tags":[
        "iron-steel",
        "peoducts"
    ],
    "wof:name":"Parita Dis Ticaret Mumessillik Ltd.sti.",
    "wof:placetype":"venue"
},
  "geometry": {"coordinates":[29.1972026825,40.9157752991],"type":"Point"}
}