{
  "type": "Feature",
  "properties": {
    "iso:country":"TR",
    "sg:address":"Eski Baglar Mah.17/b",
    "sg:city":"Topkapi",
    "sg:classifiers":[
        {
            "category":"Manufacturing",
            "subcategory":"Building Materials",
            "type":"Manufacturing & Wholesale Goods"
        }
    ],
    "sg:phone":"+90 222 320 9982",
    "sg:postcode":"34020",
    "sg:province":"Eskisehir",
    "sg:tags":[
        "promotional"
    ],
    "wof:name":"Ikinci Bahar 1-2",
    "wof:placetype":"venue"
},
  "geometry": {"coordinates":[30.5340633392,39.7612609863],"type":"Point"}
}