{
  "type": "Feature",
  "properties": {
    "iso:country":"TR",
    "sg:address":"Saglik Caddesi 42",
    "sg:city":"Kusadasi",
    "sg:classifiers":[
        {
            "category":"Banks & Credit Unions",
            "subcategory":"Bank",
            "type":"Services"
        }
    ],
    "sg:phone":"+90 256 614 2899",
    "sg:postcode":"09400",
    "sg:province":"09400",
    "wof:name":"Milli Aydin Bankasi Tas, Tarisbank",
    "wof:placetype":"venue"
},
  "geometry": {"coordinates":[38.335449,38.350281],"type":"Point"}
}