{
  "type": "Feature",
  "properties": {
    "iso:country":"TR",
    "sg:address":"Cumh. Cd. No:18 K:4 Elmadag",
    "sg:city":"Kizilay",
    "sg:classifiers":[
        {
            "category":"Building & Trades",
            "subcategory":"Construction",
            "type":"Services"
        }
    ],
    "sg:phone":"+90 212 225 0063",
    "sg:postcode":"23050",
    "sg:province":"Istanbul",
    "sg:tags":[
        "foundation"
    ],
    "wof:name":"Anne-cocuk Egitim Vakfi",
    "wof:placetype":"venue"
},
  "geometry": {"coordinates":[28.9759254456,41.0123786926],"type":"Point"}
}