{
  "type": "Feature",
  "properties": {
    "iso:country":"TR",
    "sg:address":"Halaskargazi Cad. No.184/1 Pangalti",
    "sg:city":"\u00dcmraniye",
    "sg:classifiers":[
        {
            "category":"Wholesale",
            "subcategory":"Medical Equipment & Supplies",
            "type":"Manufacturing & Wholesale Goods"
        }
    ],
    "sg:phone":"+90 212 296 1293",
    "sg:postcode":"81260",
    "sg:province":"Istanbul",
    "wof:name":"Medi-ka Tibbi Cihazlar San. Ve Tic. A.s.",
    "wof:placetype":"venue"
},
  "geometry": {"coordinates":[28.9861831665,41.0408554077],"type":"Point"}
}