{
  "type": "Feature",
  "properties": {
    "addr:full":"Inonu C. Sumer Sk. No:1 Kadikoy Istanbul 01370",
    "addr:postcode":"01370",
    "addr:street":"Sumer Sk. No 1 Kadikoy",
    "iso:country":"TR",
    "sg:address":"Inonu C. Sumer Sk. No:1",
    "sg:city":"Kadikoy",
    "sg:classifiers":[
        {
            "category":"Manufacturing",
            "subcategory":"Textiles",
            "type":"Manufacturing & Wholesale Goods"
        }
    ],
    "sg:phone":"+90 216 410 6693",
    "sg:postcode":"01370",
    "sg:province":"Istanbul",
    "sg:tags":[
        "chemical"
    ],
    "wof:name":"Beto Kagit Ve Kim. Mad. San. Ltd. Sti.",
    "wof:placetype":"venue"
},
  "geometry": {"coordinates":[28.9861831665,41.0408554077],"type":"Point"}
}