{
  "type": "Feature",
  "properties": {
    "addr:full":"Atat?k Bulv. Ata Apt. D:13 No:231 Cankaya Ey\u00fcp Ankara",
    "addr:housenumber":"ata;13 no 231",
    "addr:street":"K Bulv.;D;Cankaya Eyuep",
    "iso:country":"TR",
    "sg:address":"Atat?k Bulv. Ata Apt. D:13 No:231 Cankaya",
    "sg:city":"Ey\u00fcp",
    "sg:classifiers":[
        {
            "category":"Organizations",
            "subcategory":"Membership Organization",
            "type":"Services"
        }
    ],
    "sg:phone":"+90 312 428 4157",
    "sg:province":"Ankara",
    "wof:name":"Gubre Uret. Dernegi",
    "wof:placetype":"venue"
},
  "geometry": {"coordinates":[32.8660087585,39.8925590515],"type":"Point"}
}