{
  "type": "Feature",
  "properties": {
    "addr:full":"Hamam Sok. Hurriyet Carsisi No:331-32 Mahmutpasa Istanbul 60100",
    "addr:postcode":"331-32;60100",
    "addr:street":"Hamam Sok. Hurriyet Carsisi No",
    "iso:country":"TR",
    "sg:address":"Hamam Sok. Hurriyet Carsisi No:331-32",
    "sg:city":"Mahmutpasa",
    "sg:classifiers":[
        {
            "category":"Shopping",
            "subcategory":"Clothing, Apparel, & Fashions",
            "type":"Retail Goods"
        }
    ],
    "sg:phone":"+90 212 668 1178",
    "sg:postcode":"60100",
    "sg:province":"Istanbul",
    "sg:tags":[
        "underwear"
    ],
    "wof:name":"Mercan Camasirlari",
    "wof:placetype":"venue"
},
  "geometry": {"coordinates":[29.187054,40.888966],"type":"Point"}
}