{
  "type": "Feature",
  "properties": {
    "iso:country":"TR",
    "sg:address":"Istiklal Cad.cebirhan Kat:2/30",
    "sg:city":"?amdibi",
    "sg:classifiers":[
        {
            "category":"Food & Beverages",
            "subcategory":"Meat & Fish",
            "type":"Retail Goods"
        }
    ],
    "sg:phone":"+90 262 323 1120",
    "sg:province":"Kocaeli",
    "sg:tags":[
        "seafood"
    ],
    "wof:name":"Martas Marmara Gida Sanayi Imalat Ve Ihr.a.s",
    "wof:placetype":"venue"
},
  "geometry": {"coordinates":[29.881521225,40.8532714844],"type":"Point"}
}