{
  "type": "Feature",
  "properties": {
    "iso:country":"TR",
    "sg:address":"Eski Edirne Asfalti Malkocoglu Mah. No:31",
    "sg:city":"G O Pasa",
    "sg:classifiers":[
        {
            "category":"Manufacturing",
            "subcategory":"Glass & Minerals",
            "type":"Manufacturing & Wholesale Goods"
        }
    ],
    "sg:phone":"+90 212 594 7128",
    "sg:province":"Istanbul",
    "sg:tags":[
        "glass-mirror"
    ],
    "wof:name":"Ozdemir Kardesler Cam",
    "wof:placetype":"venue"
},
  "geometry": {"coordinates":[28.8483905792,41.1184577942],"type":"Point"}
}