{
  "type": "Feature",
  "properties": {
    "addr:full":"2.san.sitesi 302 Sokak No:8/a Bornova- Beylikd?? 34905 Izmir",
    "addr:housenumber":"beylikd ? ?",
    "addr:postcode":"34905",
    "addr:street":"302 Sokak No 8 / A Bornova",
    "iso:country":"TR",
    "sg:address":"2.san.sitesi 302 Sokak No:8/a Bornova-",
    "sg:city":"Beylikd?? 34905",
    "sg:classifiers":[
        {
            "category":"Manufacturing",
            "subcategory":"Tools & Machinery",
            "type":"Manufacturing & Wholesale Goods"
        }
    ],
    "sg:phone":"+90 232 486 3353",
    "sg:province":"Izmir",
    "sg:tags":[
        "machine",
        "industry"
    ],
    "wof:name":"Eba Yedek Par?a Imalat Sanayi Ve Ticaret Ltd.sti.",
    "wof:placetype":"venue"
},
  "geometry": {"coordinates":[27.2196006775,38.4662017822],"type":"Point"}
}