{
  "type": "Feature",
  "properties": {
    "iso:country":"TR",
    "sg:address":"Tekstilkent Ticaret Merkezi B 10 Blok No:79",
    "sg:city":"Esenler",
    "sg:classifiers":[
        {
            "category":"Manufacturing",
            "subcategory":"Textiles",
            "type":"Manufacturing & Wholesale Goods"
        }
    ],
    "sg:phone":"+90 212 438 0390",
    "sg:postcode":"34190",
    "sg:province":"Istanbul",
    "sg:tags":[
        "chemical"
    ],
    "wof:name":"Pigsan Emprime Baski Boyalari",
    "wof:placetype":"venue"
},
  "geometry": {"coordinates":[29.2125148773,40.9275741577],"type":"Point"}
}