{
  "type": "Feature",
  "properties": {
    "addr:full":"Akay Cd. No:15 D:2 K??esat Mecidiyek\u00f6y Ankara",
    "addr:housenumber":"no 15 d 2 k ? ?",
    "addr:street":"Akay Cd.",
    "iso:country":"TR",
    "sg:address":"Akay Cd. No:15 D:2 K??esat",
    "sg:city":"Mecidiyek\u00f6y",
    "sg:classifiers":[
        {
            "category":"Organizations",
            "subcategory":"Membership Organization",
            "type":"Services"
        }
    ],
    "sg:phone":"+90 312 419 4591",
    "sg:province":"Ankara",
    "wof:name":"Turk Kadinlar Konseyi Dernegi",
    "wof:placetype":"venue"
},
  "geometry": {"coordinates":[32.8604812622,39.9429283142],"type":"Point"}
}