{
  "type": "Feature",
  "properties": {
    "iso:country":"TR",
    "sg:address":"Birlik Sanayi Sitesi 5.cad.no:41",
    "sg:city":"B\u00fcy\u00fck\u00e7ekmece",
    "sg:classifiers":[
        {
            "category":"Manufacturing",
            "subcategory":"Tools & Machinery",
            "type":"Manufacturing & Wholesale Goods"
        }
    ],
    "sg:phone":"+90 212875261718",
    "sg:postcode":"34905",
    "sg:province":"Istanbul",
    "sg:tags":[
        "machine",
        "industry"
    ],
    "wof:name":"Aksel Makina Imalat Sanayi",
    "wof:placetype":"venue"
},
  "geometry": {"coordinates":[29.1171207428,41.022441864],"type":"Point"}
}