{
  "type": "Feature",
  "properties": {
    "addr:full":"Emek Otel Yunusemre Cad. Sarigazi Eskisehir 34785",
    "addr:postcode":"34785",
    "addr:street":"Yunusemre Cad. Sarigazi Eskisehir",
    "iso:country":"TR",
    "sg:address":"Emek Otel Yunusemre Cad.",
    "sg:city":"Sarigazi",
    "sg:classifiers":[
        {
            "category":"Food & Beverages",
            "subcategory":"Groceries & Convenience Stores",
            "type":"Retail Goods"
        }
    ],
    "sg:phone":"+90 222 231 2940",
    "sg:postcode":"34785",
    "sg:province":"Eskisehir",
    "sg:tags":[
        "product"
    ],
    "wof:name":"Muzaffer Kozanlioglu Kalabak Memba Sulari",
    "wof:placetype":"venue"
},
  "geometry": {"coordinates":[30.5175457001,39.7700805664],"type":"Point"}
}