{
  "type": "Feature",
  "properties": {
    "iso:country":"TR",
    "sg:address":"Eregli Sk. No:12",
    "sg:city":"Siteler",
    "sg:classifiers":[
        {
            "category":"Manufacturing",
            "subcategory":"Glass & Minerals",
            "type":"Manufacturing & Wholesale Goods"
        }
    ],
    "sg:phone":"+90 312 351 8188",
    "sg:postcode":"07070",
    "sg:province":"Ankara",
    "sg:tags":[
        "glass-mirror"
    ],
    "wof:name":"Nurcam Ltd. Sti.",
    "wof:placetype":"venue"
},
  "geometry": {"coordinates":[33.0913314819,40.1385536194],"type":"Point"}
}