{
  "type": "Feature",
  "properties": {
    "addr:full":"Halaskargazi Mahallesi, Rumeli Caddesi Zafer Sokak, Ugur Apt, No:15/2 Nisantasi 34731 Istanbu",
    "addr:postcode":"34731",
    "addr:street":"Mahallesi Rumeli Caddesi Zafer Sokak;Nisantasi",
    "iso:country":"TR",
    "sg:address":"Halaskargazi Mahallesi, Rumeli Caddesi",
    "sg:city":"Zafer Sokak, Ugur Apt, No:15/2 Nisantasi",
    "sg:classifiers":[
        {
            "category":"Travel",
            "subcategory":"Travel Agent",
            "type":"Entertainment"
        }
    ],
    "sg:phone":"+90 212 233 3986",
    "sg:postcode":"Istanbu",
    "sg:province":"34731",
    "sg:website":"peraair.net",
    "wof:name":"Pera Air And Tourism",
    "wof:placetype":"venue"
},
  "geometry": {"coordinates":[28.5672702789,41.2639083862],"type":"Point"}
}