{
  "type": "Feature",
  "properties": {
    "addr:full":"Ikitelli Org.san.bolg.giyim Sanatkarlari Koop.4.ada C Blok Kat:4 No:417 Ikitelli Istanbul 34306",
    "addr:housenumber":"blok kat 4 no 417",
    "addr:postcode":"34306",
    "addr:street":"Ikitelli Istanbul",
    "iso:country":"TR",
    "sg:address":"Ikitelli Org.san.bolg.giyim Sanatkarlari Koop.4.ada C Blok Kat:4 No:417",
    "sg:city":"Ikitelli",
    "sg:classifiers":[
        {
            "category":"Parking",
            "subcategory":"Garage",
            "type":"Transportation"
        }
    ],
    "sg:phone":"+90 212 671 2640",
    "sg:postcode":"34306",
    "sg:province":"Istanbul",
    "sg:tags":[
        "zipper"
    ],
    "wof:name":"Sentez Tekstil Yan Urunleri San.tic.ltd.sti.",
    "wof:placetype":"venue"
},
  "geometry": {"coordinates":[28.7984962463,41.0884017944],"type":"Point"}
}