{
  "type": "Feature",
  "properties": {
    "iso:country":"TR",
    "sg:address":"Hocapasa Sk. Hayyan Pasj. No:49/13 Sirkeci",
    "sg:city":"Kartal",
    "sg:classifiers":[
        {
            "category":"Wholesale",
            "subcategory":"Durable Goods & Equipment",
            "type":"Manufacturing & Wholesale Goods"
        }
    ],
    "sg:phone":"+90 212 526 1472",
    "sg:postcode":"81450",
    "sg:province":"Istanbul",
    "sg:tags":[
        "consumer"
    ],
    "wof:name":"Vefa Tic. A.s.",
    "wof:placetype":"venue"
},
  "geometry": {"coordinates":[28.9861831665,41.0408554077],"type":"Point"}
}