{
  "type": "Feature",
  "properties": {
    "addr:full":"Istanbul Yolu 2.km. Erciyes Is Merkezi 6.cad. No: 22 Kizilay Ankara 23050",
    "addr:housenumber":"2.km;6.cad no 22",
    "addr:postcode":"23050",
    "addr:street":"Istanbul Yolu",
    "iso:country":"TR",
    "sg:address":"Istanbul Yolu 2.km. Erciyes Is Merkezi 6.cad. No: 22",
    "sg:city":"Kizilay",
    "sg:classifiers":[
        {
            "category":"Shopping",
            "subcategory":"Party Supplies",
            "type":"Retail Goods"
        }
    ],
    "sg:phone":"+90 312 397 6635",
    "sg:postcode":"23050",
    "sg:province":"Ankara",
    "sg:tags":[
        "sound",
        "light",
        "system"
    ],
    "wof:name":"Avis Prodiction",
    "wof:placetype":"venue"
},
  "geometry": {"coordinates":[32.8560333252,39.9438743591],"type":"Point"}
}