{
  "type": "Feature",
  "properties": {
    "addr:full":"Kocman Cad. No:14 Evren Mah. 34540 Gunesli Istanbul K???k?ekmece Istanbul",
    "addr:housenumber":"14;mah.",
    "addr:postcode":"34540;?",
    "addr:street":"Kocman Cad. No;Evren",
    "iso:country":"TR",
    "sg:address":"Kocman Cad. No:14 Evren Mah. 34540 Gunesli Istanbul",
    "sg:city":"K???k?ekmece",
    "sg:classifiers":[
        {
            "category":"Manufacturing",
            "subcategory":"Motor Vehicles & Parts",
            "type":"Manufacturing & Wholesale Goods"
        }
    ],
    "sg:phone":"+90 212 515 9866",
    "sg:province":"Istanbul",
    "sg:tags":[
        "engine"
    ],
    "wof:name":"Elis Elektrik Elektronik End.tic",
    "wof:placetype":"venue"
},
  "geometry": {"coordinates":[28.9861793518,41.040851593],"type":"Point"}
}