{
  "type": "Feature",
  "properties": {
    "addr:full":"Hamitabat Mah. 79. Sk. No:35 Cine Aydin 01370",
    "addr:housenumber":"79;35",
    "addr:postcode":"01370",
    "addr:street":"Mah.;Sk. No",
    "iso:country":"TR",
    "sg:address":"Hamitabat Mah. 79. Sk. No:35",
    "sg:city":"Cine",
    "sg:classifiers":[
        {
            "category":"Food & Beverages",
            "subcategory":"Meat & Fish",
            "type":"Retail Goods"
        }
    ],
    "sg:phone":"+90 256 711 6780",
    "sg:postcode":"01370",
    "sg:province":"Aydin",
    "sg:tags":[
        "product"
    ],
    "wof:name":"Yore As Bes. Tic. A.s.",
    "wof:placetype":"venue"
},
  "geometry": {"coordinates":[27.8324394226,37.8409690857],"type":"Point"}
}