{
  "type": "Feature",
  "properties": {
    "addr:full":"Kaya Sultan Sok. No:103/b Kozyatagi Sahinbey Istanbul 27010",
    "addr:housenumber":"no;/ b",
    "addr:postcode":"27010",
    "addr:street":"Kaya Sultan Sok.",
    "iso:country":"TR",
    "sg:address":"Kaya Sultan Sok. No:103/b Kozyatagi",
    "sg:city":"Sahinbey",
    "sg:classifiers":[
        {
            "category":"Structure",
            "subcategory":"Office Building",
            "type":"Public Place"
        }
    ],
    "sg:phone":"+90 216 458 3000",
    "sg:postcode":"27010",
    "sg:province":"Istanbul",
    "sg:tags":[
        "satellite",
        "system"
    ],
    "wof:name":"Basari Uydu Sistemleri",
    "wof:placetype":"venue"
},
  "geometry": {"coordinates":[29.095957,40.968014],"type":"Point"}
}