{
  "type": "Feature",
  "properties": {
    "iso:country":"TR",
    "sg:address":"K. Karabekir. Cad. Cinar Psj. No:p/19 Bornova",
    "sg:city":"Sahinbey",
    "sg:classifiers":[
        {
            "category":"Professional",
            "subcategory":"Testing Lab",
            "type":"Services"
        }
    ],
    "sg:phone":"+90 232 388 2803",
    "sg:postcode":"27300",
    "sg:province":"Izmir",
    "sg:tags":[
        "laboratory",
        "material"
    ],
    "wof:name":"Erdem Ltd. Sti.",
    "wof:placetype":"venue"
},
  "geometry": {"coordinates":[27.1296863556,38.4186973572],"type":"Point"}
}