{
  "type": "Feature",
  "properties": {
    "addr:full":"Atat?k Bulv. Sk. No:255 Cankaya Mecidiyek\u00f6y Ankara",
    "addr:housenumber":"255",
    "addr:street":"K Bulv. Sk. No",
    "iso:country":"TR",
    "sg:address":"Atat?k Bulv. Sk. No:255 Cankaya",
    "sg:city":"Mecidiyek\u00f6y",
    "sg:classifiers":[
        {
            "category":"Organizations",
            "subcategory":"Membership Organization",
            "type":"Services"
        }
    ],
    "sg:phone":"+90 312 468 4007",
    "sg:province":"Ankara",
    "wof:name":"Turk-japon Kadinlari Dost. Kultur Dernegi",
    "wof:placetype":"venue"
},
  "geometry": {"coordinates":[32.8660087585,39.8925590515],"type":"Point"}
}