{
  "type": "Feature",
  "properties": {
    "addr:full":"Ragip T?? Cad. No:202/a, 06180 Yenimahalle Ankara Merkez Ankara 25000",
    "addr:housenumber":"202 / a",
    "addr:postcode":"06180;25000",
    "addr:street":"? Cad. No",
    "iso:country":"TR",
    "sg:address":"Ragip T?? Cad. No:202/a, 06180 Yenimahalle Ankara",
    "sg:city":"Merkez",
    "sg:classifiers":[
        {
            "category":"Manufacturing",
            "subcategory":"Wood Products",
            "type":"Manufacturing & Wholesale Goods"
        }
    ],
    "sg:phone":"+90 312 343 7000",
    "sg:postcode":"25000",
    "sg:province":"Ankara",
    "sg:tags":[
        "furniture"
    ],
    "wof:name":"Dortdivan Cerceve & Macun San Tic Ltd Sti",
    "wof:placetype":"venue"
},
  "geometry": {"coordinates":[32.8035926819,39.9657325745],"type":"Point"}
}