{
  "type": "Feature",
  "properties": {
    "addr:full":"Katip Celebi Sok.no:3/3 Cankaya \u00c7ankaya Ankara 06640",
    "addr:housenumber":"3 / 3",
    "addr:postcode":"06640",
    "addr:street":"Katip;Sok.No",
    "iso:country":"TR",
    "sg:address":"Katip Celebi Sok.no:3/3 Cankaya",
    "sg:city":"\u00c7ankaya",
    "sg:classifiers":[
        {
            "category":"Shopping",
            "subcategory":"Party Supplies",
            "type":"Retail Goods"
        }
    ],
    "sg:phone":"+90 312 427 3349",
    "sg:postcode":"06640",
    "sg:province":"Ankara",
    "sg:tags":[
        "sound",
        "light",
        "system"
    ],
    "wof:name":"Art Elektronik Sistemleri Ltd.sti.",
    "wof:placetype":"venue"
},
  "geometry": {"coordinates":[32.8605690002,39.8989181519],"type":"Point"}
}