{
  "type": "Feature",
  "properties": {
    "iso:country":"TR",
    "sg:address":"Sair Nigar Sok. No:36/1 Nisantasi-",
    "sg:city":"Osmanbey",
    "sg:classifiers":[
        {
            "category":"Shopping",
            "subcategory":"Baby Store",
            "type":"Retail Goods"
        }
    ],
    "sg:phone":"+90 212 230 3737",
    "sg:postcode":"63000",
    "sg:province":"Istanbul",
    "sg:tags":[
        "wear"
    ],
    "wof:name":"Bambini Giyim San.tic.ltd.sti.",
    "wof:placetype":"venue"
},
  "geometry": {"coordinates":[28.99058,41.053165],"type":"Point"}
}