{
  "type": "Feature",
  "properties": {
    "addr:full":"Demirciler Sitesi 2.cadde No:11 34760 Zeytinburnu Istanbul 41000",
    "addr:housenumber":"no 11",
    "addr:postcode":"34760;41000",
    "addr:street":"Demirciler",
    "iso:country":"TR",
    "sg:address":"Demirciler Sitesi 2.cadde No:11 34760",
    "sg:city":"Zeytinburnu",
    "sg:classifiers":[
        {
            "category":"Shopping",
            "subcategory":"Crafts & Fabrics",
            "type":"Retail Goods"
        }
    ],
    "sg:phone":"+90 212 664 2200",
    "sg:postcode":"41000",
    "sg:province":"Istanbul",
    "sg:tags":[
        "weaving"
    ],
    "wof:name":"Jutsan Polipropilen ?uval Ve Ip Sanayi A.s.",
    "wof:placetype":"venue"
},
  "geometry": {"coordinates":[28.8070316315,41.0673942566],"type":"Point"}
}