{
  "type": "Feature",
  "properties": {
    "iso:country":"TR",
    "sg:address":"Sabuncular Cd. Findik?lar Sk. Gencay Han No:6 Emin?? Istanbul",
    "sg:city":"Osmanbey",
    "sg:classifiers":[
        {
            "category":"Shopping",
            "subcategory":"Stationery & Office Supplies",
            "type":"Retail Goods"
        }
    ],
    "sg:phone":"+90 212 512 9632",
    "sg:postcode":"63000",
    "sg:province":"Istanbul",
    "wof:name":"Ekol Kirtasiye Ith. Ihr. Ltd. Sti.",
    "wof:placetype":"venue"
},
  "geometry": {"coordinates":[28.975925,41.012379],"type":"Point"}
}