{
  "type": "Feature",
  "properties": {
    "iso:country":"TR",
    "sg:address":"Izzet Baysal Cd. No:194",
    "sg:city":"Mersin",
    "sg:classifiers":[
        {
            "category":"Wholesale",
            "subcategory":"Home Furnishings",
            "type":"Manufacturing & Wholesale Goods"
        }
    ],
    "sg:phone":"+90 374 212 4037",
    "sg:postcode":"52750",
    "sg:province":"Bolu",
    "sg:tags":[
        "furniture"
    ],
    "wof:name":"Latif Mob. Paz. Taah. Tic.",
    "wof:placetype":"venue"
},
  "geometry": {"coordinates":[31.5988750458,40.7306365967],"type":"Point"}
}