{
  "type": "Feature",
  "properties": {
    "iso:country":"TR",
    "sg:address":"Mebusan Yokusu No95 K6",
    "sg:city":"Findikli",
    "sg:classifiers":[
        {
            "category":"Freight",
            "type":"Transportation"
        }
    ],
    "sg:phone":"+90 212 252 3912",
    "sg:postcode":"01470",
    "sg:province":"Istanbul",
    "sg:tags":[
        "agent",
        "shipping",
        "broker"
    ],
    "wof:name":"Formar Denizcilik Ltd.sti.",
    "wof:placetype":"venue"
},
  "geometry": {"coordinates":[28.982382,41.030647],"type":"Point"}
}