{
  "type": "Feature",
  "properties": {
    "iso:country":"TR",
    "sg:address":"12.cad. 40.sok. No:6",
    "sg:city":"Demetevler",
    "sg:classifiers":[
        {
            "category":"Manufacturing",
            "subcategory":"Food",
            "type":"Manufacturing & Wholesale Goods"
        }
    ],
    "sg:phone":"+90 31234549443366",
    "sg:postcode":"01180",
    "sg:province":"Ankara",
    "sg:tags":[
        "wholesaler"
    ],
    "wof:name":"Altug Gida Ve Iht. Mad. San.tic. Ltd.sti.",
    "wof:placetype":"venue"
},
  "geometry": {"coordinates":[32.7436523438,39.9773368835],"type":"Point"}
}