{
  "type": "Feature",
  "properties": {
    "iso:country":"TR",
    "sg:address":"Petek Bozkaya Ishani A Blok No:2 No:219",
    "sg:city":"Ulus",
    "sg:classifiers":[
        {
            "category":"Professional",
            "subcategory":"Engineering",
            "type":"Services"
        }
    ],
    "sg:phone":"+90 224 255 7269",
    "sg:postcode":"01940",
    "sg:province":"Bursa",
    "sg:tags":[
        "architect"
    ],
    "wof:name":"Mrt Insaat Tekstil San.tic.ltd.sti.",
    "wof:placetype":"venue"
},
  "geometry": {"coordinates":[29.0586109161,40.1844291687],"type":"Point"}
}