{
  "type": "Feature",
  "properties": {
    "iso:country":"TR",
    "sg:address":"S?b? Sk. No:9 Zeytinburnu",
    "sg:city":"Kocamustafapasa",
    "sg:classifiers":[
        {
            "category":"Freight",
            "type":"Transportation"
        }
    ],
    "sg:phone":"+90 212 558 1277",
    "sg:postcode":"34098",
    "sg:province":"Istanbul",
    "sg:tags":[
        "packing",
        "industry"
    ],
    "wof:name":"Aktas Oluklu Ambalaj San. Tic. Ltd. Sti.",
    "wof:placetype":"venue"
},
  "geometry": {"coordinates":[28.9110374451,41.0035896301],"type":"Point"}
}