{
  "type": "Feature",
  "properties": {
    "iso:country":"TR",
    "sg:address":"Istanbul Youlu 35.km.",
    "sg:city":"Kazan",
    "sg:classifiers":[
        {
            "category":"Structure",
            "subcategory":"Office Building",
            "type":"Public Place"
        }
    ],
    "sg:phone":"+90 312 818 6326",
    "sg:postcode":"06980",
    "sg:province":"Ankara",
    "sg:tags":[
        "scaffolding",
        "form"
    ],
    "wof:name":"Panel Makina Sanayi Ve Ticret Ltd. Sti.",
    "wof:placetype":"venue"
},
  "geometry": {"coordinates":[32.856033,39.943874],"type":"Point"}
}