{
  "type": "Feature",
  "properties": {
    "addr:full":"Kayacan Mah.mungan Apt.kat.3 47100 Mardin",
    "addr:housenumber":"apt.kat.3",
    "addr:postcode":"47100",
    "iso:country":"TR",
    "sg:address":"Kayacan Mah.mungan Apt.kat.3",
    "sg:city":"47100",
    "sg:classifiers":[
        {
            "category":"Professional",
            "subcategory":"Computer Services",
            "type":"Services"
        }
    ],
    "sg:phone":"+90 533 771 8343",
    "sg:province":"Mardin",
    "sg:tags":[
        "application",
        "software"
    ],
    "wof:name":"Marsoft Yazilim & Donanim",
    "wof:placetype":"venue"
},
  "geometry": {"coordinates":[40.7201957703,37.3247451782],"type":"Point"}
}