{
  "type": "Feature",
  "properties": {
    "addr:full":"Cumh. Cd. No:229 Harbiye \u00dcmraniye Istanbul 81230",
    "addr:housenumber":"no",
    "addr:postcode":"81230",
    "addr:street":"Cumh. Cd.;Harbiye",
    "iso:country":"TR",
    "sg:address":"Cumh. Cd. No:229 Harbiye",
    "sg:city":"\u00dcmraniye",
    "sg:classifiers":[
        {
            "category":"Shopping",
            "subcategory":"Stationery & Office Supplies",
            "type":"Retail Goods"
        }
    ],
    "sg:phone":"+90 212 230 1267",
    "sg:postcode":"81230",
    "sg:province":"Istanbul",
    "sg:tags":[
        "furniture"
    ],
    "wof:name":"Tuna Girsberger",
    "wof:placetype":"venue"
},
  "geometry": {"coordinates":[28.9759254456,41.0123786926],"type":"Point"}
}