{
  "type": "Feature",
  "properties": {
    "addr:full":"Nuriye Civelek Cad No:3 Kirikhan Hatay 31440",
    "addr:postcode":"31440",
    "addr:street":"Civelek Cad No 3 Kirikhan",
    "iso:country":"TR",
    "sg:address":"Nuriye Civelek Cad No:3",
    "sg:city":"Kirikhan",
    "sg:classifiers":[
        {
            "category":"Manufacturing",
            "subcategory":"Chemicals & Compounds",
            "type":"Manufacturing & Wholesale Goods"
        }
    ],
    "sg:phone":"+90 326 345 1015",
    "sg:postcode":"31440",
    "sg:province":"Hatay",
    "sg:tags":[
        "agricultural"
    ],
    "wof:name":"Cingi Tarim Ltd.sti.",
    "wof:placetype":"venue"
},
  "geometry": {"coordinates":[36.349811554,36.4018478394],"type":"Point"}
}