{
  "type": "Feature",
  "properties": {
    "addr:full":"?merli Mah. Adnan Kahveci Cad. Hadimk? ?atalca Istanbul 34870",
    "addr:housenumber":"?;hadimk ? ?",
    "addr:postcode":"34870",
    "addr:street":"Merli Mah. Adnan Kahveci Cad.",
    "iso:country":"TR",
    "sg:address":"?merli Mah. Adnan Kahveci Cad. Hadimk?",
    "sg:city":"?atalca",
    "sg:classifiers":[
        {
            "category":"Manufacturing",
            "subcategory":"Leather Goods",
            "type":"Manufacturing & Wholesale Goods"
        }
    ],
    "sg:phone":"+90 212 798 2450",
    "sg:postcode":"34870",
    "sg:province":"Istanbul",
    "sg:tags":[
        "chemical"
    ],
    "wof:name":"Gemsan Genel End?tri Maddeleri San. Ve Tic. A.s.",
    "wof:placetype":"venue"
},
  "geometry": {"coordinates":[29.1942977905,40.9005393982],"type":"Point"}
}