{
  "type": "Feature",
  "properties": {
    "iso:country":"TR",
    "sg:address":"Nispetiye Cad. No:18/a Blok D:6 1.levent",
    "sg:city":"Bal?va",
    "sg:orig_category":"Enegy Contractors",
    "sg:phone":"+90 2122837445729",
    "sg:province":"Istanbul",
    "wof:name":"Aes Alternatif Enerji Sistemleri Ve Tic.ltd.sti.",
    "wof:placetype":"venue"
},
  "geometry": {"coordinates":[28.9861793518,41.040851593],"type":"Point"}
}