{
  "type": "Feature",
  "properties": {
    "iso:country":"TR",
    "sg:address":"B.ihsaniye Mah. Hazim Ulusahin Is Merkezi A Blok No:202",
    "sg:city":"Gaziosmanpasa",
    "sg:classifiers":[
        {
            "category":"Travel",
            "subcategory":"Travel Agent",
            "type":"Entertainment"
        }
    ],
    "sg:phone":"+90 332 238 6010",
    "sg:postcode":"01950",
    "sg:province":"Konya",
    "sg:tags":[
        "agency",
        "tourism"
    ],
    "wof:name":"Bosna Turizm",
    "wof:placetype":"venue"
},
  "geometry": {"coordinates":[33.0667152405,39.2111282349],"type":"Point"}
}