{
  "type": "Feature",
  "properties": {
    "iso:country":"TR",
    "sg:address":"Nazli Hanim Sk. Nazli Han 12/11",
    "sg:city":"Karakoy",
    "sg:classifiers":[
        {
            "category":"Building & Trades",
            "subcategory":"Electrical",
            "type":"Services"
        }
    ],
    "sg:phone":"+90 212 235 9090",
    "sg:postcode":"07700",
    "sg:province":"Istanbul",
    "sg:tags":[
        "equipment",
        "lighting"
    ],
    "wof:name":"Celik Is Kalip Aydinlatma San. Tic. Ltd. Sti.",
    "wof:placetype":"venue"
},
  "geometry": {"coordinates":[29.1571006775,41.0069046021],"type":"Point"}
}