{
  "type": "Feature",
  "properties": {
    "addr:full":"Gazi Bulv. No:67 Pamukova Aydin 54900",
    "addr:housenumber":"no 67",
    "addr:postcode":"54900",
    "addr:street":"Gazi Bulv.;Pamukova Aydin",
    "iso:country":"TR",
    "sg:address":"Gazi Bulv. No:67",
    "sg:city":"Pamukova",
    "sg:classifiers":[
        {
            "category":"Farming",
            "subcategory":"Farm",
            "type":"Manufacturing & Wholesale Goods"
        }
    ],
    "sg:phone":"+90 256 212 7655",
    "sg:postcode":"54900",
    "sg:province":"Aydin",
    "sg:tags":[
        "agricultural",
        "product"
    ],
    "wof:name":"Karetta Tarim Urunleri",
    "wof:placetype":"venue"
},
  "geometry": {"coordinates":[27.8377170563,37.8525886536],"type":"Point"}
}