{
  "type": "Feature",
  "properties": {
    "addr:full":"Cumhuriyet Cad. Uma? Apt. No: 141/147 K: 4 D: 9 Elmadag Istanbul 65900",
    "addr:housenumber":"?;/ 147 k 4 d 9",
    "addr:postcode":"65900",
    "addr:street":"Cumhuriyet Cad. Uma;No 141",
    "iso:country":"TR",
    "sg:address":"Cumhuriyet Cad. Uma? Apt. No: 141/147 K: 4 D: 9",
    "sg:city":"Elmadag",
    "sg:classifiers":[
        {
            "category":"Travel",
            "subcategory":"Travel Agent",
            "type":"Entertainment"
        }
    ],
    "sg:phone":"+90 23448772323058",
    "sg:postcode":"65900",
    "sg:province":"Istanbul",
    "sg:tags":[
        "agency",
        "tourism"
    ],
    "wof:name":"Mira Turizm Incentive House",
    "wof:placetype":"venue"
},
  "geometry": {"coordinates":[28.9861831665,41.0408554077],"type":"Point"}
}