{
  "type": "Feature",
  "properties": {
    "iso:country":"TR",
    "sg:address":"Taksim Cd. No:61/1 Taksim",
    "sg:city":"Topkapi",
    "sg:classifiers":[
        {
            "category":"Farming",
            "subcategory":"Fish & Marine Products",
            "type":"Manufacturing & Wholesale Goods"
        }
    ],
    "sg:phone":"+90 212 253 0582",
    "sg:postcode":"24620",
    "sg:province":"Istanbul",
    "sg:tags":[
        "automotive"
    ],
    "wof:name":"Alza Otomotiv San. Tic. A.s.",
    "wof:placetype":"venue"
},
  "geometry": {"coordinates":[28.9837169647,41.0368728638],"type":"Point"}
}