{
  "type": "Feature",
  "properties": {
    "addr:full":"859 Sk.n:6/402 Vatan Ishani35250 Konak G?esli Izmir",
    "addr:housenumber":"859;6 / 402;?",
    "addr:street":"Sk.N;Konak G",
    "iso:country":"TR",
    "sg:address":"859 Sk.n:6/402 Vatan Ishani35250 Konak",
    "sg:city":"G?esli",
    "sg:classifiers":[
        {
            "category":"Shopping",
            "subcategory":"Clothing, Apparel, & Fashions",
            "type":"Retail Goods"
        }
    ],
    "sg:phone":"+90 2324415823329",
    "sg:province":"Izmir",
    "sg:tags":[
        "watch",
        "lighter"
    ],
    "wof:name":"Anka Mucevherat Saat San.tic.ltd.sti.",
    "wof:placetype":"venue"
},
  "geometry": {"coordinates":[27.1592006683,38.4269981384],"type":"Point"}
}