{
  "type": "Feature",
  "properties": {
    "iso:country":"TR",
    "sg:address":"Sakizagaci Kennedy Cd. No:55/a Bakirk?",
    "sg:city":"Gayrettepe/besiktas",
    "sg:classifiers":[
        {
            "category":"Farming",
            "subcategory":"Fish & Marine Products",
            "type":"Manufacturing & Wholesale Goods"
        }
    ],
    "sg:phone":"+90 212 543 8748",
    "sg:postcode":"80280",
    "sg:province":"Istanbul",
    "sg:tags":[
        "automotive"
    ],
    "wof:name":"Balkan Motorlu Ara?lar Pazarlar San. Tic. Ltd. Sti.",
    "wof:placetype":"venue"
},
  "geometry": {"coordinates":[28.8859272003,40.97864151],"type":"Point"}
}