{
  "type": "Feature",
  "properties": {
    "iso:country":"TR",
    "sg:address":"Aktas Mah. Tashancilar Cad.sureyya Sok. Kutucuoglu Apt.b Blok. No:28/b",
    "sg:city":"Karasu",
    "sg:classifiers":[
        {
            "category":"Farming",
            "subcategory":"Farm & Veterinary Services",
            "type":"Manufacturing & Wholesale Goods"
        }
    ],
    "sg:phone":"+90 374 212 1636",
    "sg:postcode":"04000",
    "sg:province":"Bolu",
    "sg:tags":[
        "veterinarian"
    ],
    "wof:name":"Ozen Veteriner Klinigi",
    "wof:placetype":"venue"
},
  "geometry": {"coordinates":[31.6107006073,40.7332992554],"type":"Point"}
}