{
  "type": "Feature",
  "properties": {
    "addr:full":"855.sok.no:28 Konak Acipayam Izmir 20873",
    "addr:postcode":"20873",
    "addr:street":"Konak Acipayam",
    "iso:country":"TR",
    "sg:address":"855.sok.no:28 Konak",
    "sg:city":"Acipayam",
    "sg:classifiers":[
        {
            "category":"Shopping",
            "subcategory":"Luggage & Leather Goods",
            "type":"Retail Goods"
        }
    ],
    "sg:phone":"+90 232 445 2881",
    "sg:postcode":"20873",
    "sg:province":"Izmir",
    "sg:tags":[
        "leather-fur",
        "wear"
    ],
    "wof:name":"Altuner Cantacilik Ltd.sti.",
    "wof:placetype":"venue"
},
  "geometry": {"coordinates":[27.1316776276,38.41954422],"type":"Point"}
}