{
  "type": "Feature",
  "properties": {
    "iso:country":"TR",
    "sg:address":"Ataturk Cad. No.169",
    "sg:city":"Gursu",
    "sg:classifiers":[
        {
            "category":"Shopping",
            "subcategory":"Crafts & Fabrics",
            "type":"Retail Goods"
        }
    ],
    "sg:phone":"+90 224 371 3800",
    "sg:postcode":"07070",
    "sg:province":"Bursa",
    "sg:tags":[
        "yarn"
    ],
    "wof:name":"Akbaslar Tekstil San. Ve Tic. A.s.",
    "wof:placetype":"venue"
},
  "geometry": {"coordinates":[29.7198963165,40.430103302],"type":"Point"}
}