{
  "type": "Feature",
  "properties": {
    "addr:full":"Aksaray Valide Camii Sk. No:107/5 Bagcilar Istanbul 33115",
    "addr:housenumber":"107 / 5",
    "addr:postcode":"33115",
    "addr:street":"Sk. No",
    "iso:country":"TR",
    "sg:address":"Aksaray Valide Camii Sk. No:107/5",
    "sg:city":"Bagcilar",
    "sg:classifiers":[
        {
            "category":"Shopping",
            "subcategory":"Stationery & Office Supplies",
            "type":"Retail Goods"
        }
    ],
    "sg:phone":"+90 212 632 2817",
    "sg:postcode":"33115",
    "sg:province":"Istanbul",
    "sg:tags":[
        "paper"
    ],
    "wof:name":"Supay Kagit Rulo San. Ve Tic. A.s.",
    "wof:placetype":"venue"
},
  "geometry": {"coordinates":[28.9759254456,41.0123786926],"type":"Point"}
}