{
  "type": "Feature",
  "properties": {
    "addr:full":"Menemen Deri Serbest Bolgesi Menemen \u00c7orlu Izmir",
    "addr:street":"C\u0327Orlu",
    "iso:country":"TR",
    "sg:address":"Menemen Deri Serbest Bolgesi Menemen",
    "sg:city":"\u00c7orlu",
    "sg:classifiers":[
        {
            "category":"Shopping",
            "subcategory":"Luggage & Leather Goods",
            "type":"Retail Goods"
        }
    ],
    "sg:phone":"+90 232 842 6163",
    "sg:province":"Izmir",
    "sg:tags":[
        "leather-fur",
        "wear"
    ],
    "wof:name":"Maraslioglu-mader Deri Ltd.sti.",
    "wof:placetype":"venue"
},
  "geometry": {"coordinates":[27.0697994232,38.606098175],"type":"Point"}
}