{
  "type": "Feature",
  "properties": {
    "addr:full":"Hamitabat Mah. 79. Sk. No:15 Cine Aydin 01370",
    "addr:housenumber":"79;15",
    "addr:postcode":"01370",
    "addr:street":"Mah.;Sk. No",
    "iso:country":"TR",
    "sg:address":"Hamitabat Mah. 79. Sk. No:15",
    "sg:city":"Cine",
    "sg:classifiers":[
        {
            "category":"Farming",
            "subcategory":"Farm",
            "type":"Manufacturing & Wholesale Goods"
        }
    ],
    "sg:phone":"+90 256711614271",
    "sg:postcode":"01370",
    "sg:province":"Aydin",
    "sg:tags":[
        "agricultural",
        "product"
    ],
    "wof:name":"Atakoy Zeytinleri",
    "wof:placetype":"venue"
},
  "geometry": {"coordinates":[28.4863967896,37.8117027283],"type":"Point"}
}