{
  "type": "Feature",
  "properties": {
    "addr:full":"Istiklal Cd. No:102 Esenyurt Istanbul 07800",
    "addr:housenumber":"no",
    "addr:postcode":"07800",
    "addr:street":"Istiklal Cd.",
    "iso:country":"TR",
    "sg:address":"Istiklal Cd. No:102",
    "sg:city":"Esenyurt",
    "sg:classifiers":[
        {
            "category":"Mining & Drilling",
            "type":"Manufacturing & Wholesale Goods"
        }
    ],
    "sg:phone":"+90 212 591 2895",
    "sg:postcode":"07800",
    "sg:province":"Istanbul",
    "sg:tags":[
        "excavation",
        "demolition"
    ],
    "wof:name":"Top?ular Hafriyat",
    "wof:placetype":"venue"
},
  "geometry": {"coordinates":[28.9767818451,41.033454895],"type":"Point"}
}