{
  "type": "Feature",
  "properties": {
    "addr:full":"Tepecik Mah.gazyaba Yoku No:7 Rami Kocaeli 34055",
    "addr:postcode":"34055",
    "addr:street":"No 7 Rami",
    "iso:country":"TR",
    "sg:address":"Tepecik Mah.gazyaba Yoku No:7",
    "sg:city":"Rami",
    "sg:classifiers":[
        {
            "category":"Home & Garden",
            "subcategory":"Hardware",
            "type":"Retail Goods"
        }
    ],
    "sg:phone":"+90 262 325 7329",
    "sg:postcode":"34055",
    "sg:province":"Kocaeli",
    "sg:tags":[
        "store"
    ],
    "wof:name":"Ugur Ticaret Teknik Hirdavat Ve Muhendislik Plastikleri",
    "wof:placetype":"venue"
},
  "geometry": {"coordinates":[29.9345855713,40.7669563293],"type":"Point"}
}