{
  "type": "Feature",
  "properties": {
    "addr:full":"Altiparmak Cd. Altiparmak Sok. Nilufer Apt.no:1/10 Karak\u00f6y Bursa 16510",
    "addr:housenumber":"1 / 10",
    "addr:postcode":"16510",
    "addr:street":"Altiparmak Cd. Altiparmak Sok. Nilufer Apt.No;Bursa",
    "iso:country":"TR",
    "sg:address":"Altiparmak Cd. Altiparmak Sok. Nilufer Apt.no:1/10",
    "sg:city":"Karak\u00f6y",
    "sg:classifiers":[
        {
            "category":"Organizations",
            "subcategory":"Membership Organization",
            "type":"Services"
        }
    ],
    "sg:phone":"+90 224 224 8640",
    "sg:postcode":"16510",
    "sg:province":"Bursa",
    "wof:name":"Bursa Halkla Iliskiler Dernegi",
    "wof:placetype":"venue"
},
  "geometry": {"coordinates":[29.0586109161,40.1844291687],"type":"Point"}
}