{
  "type": "Feature",
  "properties": {
    "addr:full":"Yenibosna Hurriyet Mah. Kadioglu Sok.no:15 Yenibosna Istanbul 43270",
    "addr:housenumber":"15",
    "addr:postcode":"43270",
    "addr:street":"Hurriyet Mah. Kadioglu Sok.No;Istanbul",
    "iso:country":"TR",
    "sg:address":"Yenibosna Hurriyet Mah. Kadioglu Sok.no:15",
    "sg:city":"Yenibosna",
    "sg:classifiers":[
        {
            "category":"Shopping",
            "subcategory":"Clothing, Apparel, & Fashions",
            "type":"Retail Goods"
        }
    ],
    "sg:phone":"+90 212 652 2025",
    "sg:postcode":"43270",
    "sg:province":"Istanbul",
    "sg:tags":[
        "ready",
        "wear"
    ],
    "wof:name":"Ece Tekstil",
    "wof:placetype":"venue"
},
  "geometry": {"coordinates":[28.8402366638,40.9977684021],"type":"Point"}
}