{
  "type": "Feature",
  "properties": {
    "iso:country":"TR",
    "sg:address":"?akmak Mahallesi, Ikbal Cad. No:76/a",
    "sg:city":"\u00dcmraniye",
    "sg:orig_category":"Food Machinies",
    "sg:phone":"+90 216 365 3305",
    "sg:province":"Istanbul",
    "wof:name":"Ilmak Makina Sanayi Ve Ticaret Ltd.",
    "wof:placetype":"venue"
},
  "geometry": {"coordinates":[29.125705719,41.0071601868],"type":"Point"}
}