{
  "type": "Feature",
  "properties": {
    "addr:full":"30. Sk. No:113 Ostim \u00dcmraniye Ankara 34776",
    "addr:housenumber":"30;113",
    "addr:postcode":"34776",
    "addr:street":"Sk. No",
    "iso:country":"TR",
    "sg:address":"30. Sk. No:113 Ostim",
    "sg:city":"\u00dcmraniye",
    "sg:classifiers":[
        {
            "category":"Manufacturing",
            "subcategory":"Metals",
            "type":"Manufacturing & Wholesale Goods"
        }
    ],
    "sg:phone":"+90 312 385 1552",
    "sg:postcode":"34776",
    "sg:province":"Ankara",
    "sg:tags":[
        "iron-steel",
        "peoducts"
    ],
    "wof:name":"Arites Metal San. Tic. Ltd. Sti.",
    "wof:placetype":"venue"
},
  "geometry": {"coordinates":[32.7407417297,39.9712257385],"type":"Point"}
}