{
  "type": "Feature",
  "properties": {
    "addr:full":"1438 Sok. Sema Apt. No:1 Kat:2 D:4 Alsancak Devlet Hastanesi Karsisi Alsancak Sisli Izmir 65710",
    "addr:housenumber":"1438;apt.;kat 2 d 4",
    "addr:postcode":"65710",
    "addr:street":"Sok. Sema;No 1;Devlet Hastanesi Karsisi",
    "iso:country":"TR",
    "sg:address":"1438 Sok. Sema Apt. No:1 Kat:2 D:4 Alsancak Devlet Hastanesi Karsisi Alsancak",
    "sg:city":"Sisli",
    "sg:classifiers":[
        {
            "category":"Health Services",
            "subcategory":"Medical Lab",
            "type":"Services"
        }
    ],
    "sg:phone":"+90 232 464 2207",
    "sg:postcode":"65710",
    "sg:province":"Izmir",
    "wof:name":"Uckun Tib Laboratuvari",
    "wof:placetype":"venue"
},
  "geometry": {"coordinates":[27.1423015594,38.4251480103],"type":"Point"}
}