{
  "type": "Feature",
  "properties": {
    "addr:full":"?ukur ?esme Caddesi Asici Is Hani No:19 - Gaziosmanpasa 64020 Istanbul",
    "addr:housenumber":"?;?;no 19",
    "addr:postcode":"64020",
    "addr:street":"Ukur;Esme Caddesi Asici Is;Gaziosmanpasa",
    "iso:country":"TR",
    "sg:address":"?ukur ?esme Caddesi Asici Is Hani No:19 - Gaziosmanpasa",
    "sg:city":"64020",
    "sg:classifiers":[
        {
            "category":"Government",
            "subcategory":"Post Office",
            "type":"Public Place"
        }
    ],
    "sg:phone":"+90 212 578 0344",
    "sg:province":"Istanbul",
    "sg:tags":[
        "notary"
    ],
    "wof:name":"Gaziosmanpasa 1 Noterligi",
    "wof:placetype":"venue"
},
  "geometry": {"coordinates":[28.8927993774,41.0976409912],"type":"Point"}
}