{
  "type": "Feature",
  "properties": {
    "addr:full":"Ozveren Sk. No:33/10 Maltepe Bornova Ankara 35040",
    "addr:housenumber":"33 / 10",
    "addr:postcode":"35040",
    "addr:street":"Ozveren Sk. No;Maltepe",
    "iso:country":"TR",
    "sg:address":"Ozveren Sk. No:33/10 Maltepe",
    "sg:city":"Bornova",
    "sg:classifiers":[
        {
            "category":"Wholesale",
            "subcategory":"Machinery & Supplies",
            "type":"Manufacturing & Wholesale Goods"
        }
    ],
    "sg:phone":"+90 312 231 0979",
    "sg:postcode":"35040",
    "sg:province":"Ankara",
    "sg:tags":[
        "laboratory",
        "equipment"
    ],
    "wof:name":"Melkosan Tibbi Cihaz Alet",
    "wof:placetype":"venue"
},
  "geometry": {"coordinates":[32.8469161987,39.9225273132],"type":"Point"}
}