{
  "type": "Feature",
  "properties": {
    "iso:country":"TR",
    "sg:address":"Bulbulderesi Cad. No:126/1-19 -b5",
    "sg:city":"K.esat",
    "sg:classifiers":[
        {
            "category":"Building & Trades",
            "subcategory":"Landscaping Services",
            "type":"Services"
        }
    ],
    "sg:phone":"+90 312 446 4422",
    "sg:province":"Ankara",
    "sg:tags":[
        "landscape"
    ],
    "wof:name":"Marmara Peyzaj",
    "wof:placetype":"venue"
},
  "geometry": {"coordinates":[32.8638000488,39.9162254333],"type":"Point"}
}