{
  "type": "Feature",
  "properties": {
    "iso:country":"TR",
    "sg:address":"Degirmi?em Mah. 9 Nolu Sok No: 22/3",
    "sg:city":"Sisli",
    "sg:classifiers":[
        {
            "category":"Travel",
            "subcategory":"Travel Agent",
            "type":"Entertainment"
        }
    ],
    "sg:phone":"+90 3422206464729",
    "sg:postcode":"65710",
    "sg:province":"Gaziantep",
    "sg:tags":[
        "agency",
        "tourism"
    ],
    "wof:name":"Arsan Turizm Ve Seyahat Acentasi",
    "wof:placetype":"venue"
},
  "geometry": {"coordinates":[37.4416732788,36.9459457397],"type":"Point"}
}