{
  "type": "Feature",
  "properties": {
    "addr:full":"Akdeniz Cad. 129 Sok. Bah?ci Apt. A Blok Sahilkent Finike Antalya 07740",
    "addr:housenumber":"129;?",
    "addr:postcode":"07740",
    "addr:street":"Akdeniz Cad.;Sok. Bah",
    "iso:country":"TR",
    "sg:address":"Akdeniz Cad. 129 Sok. Bah?ci Apt. A Blok Sahilkent",
    "sg:city":"Finike",
    "sg:classifiers":[
        {
            "category":"Professional",
            "subcategory":"Business Services",
            "type":"Services"
        }
    ],
    "sg:phone":"+90 242 855 4340",
    "sg:postcode":"07740",
    "sg:province":"Antalya",
    "sg:tags":[
        "food",
        "product",
        "exporter",
        "aricultural"
    ],
    "wof:name":"Bah?eci Group",
    "wof:placetype":"venue"
},
  "geometry": {"coordinates":[30.7031345367,36.8875045776],"type":"Point"}
}