{
  "type": "Feature",
  "properties": {
    "iso:country":"TR",
    "sg:address":"541. Sk. No:4",
    "sg:city":"Ikitelli/K\u00fc\u00e7\u00fck\u00e7ekmece",
    "sg:classifiers":[
        {
            "category":"Manufacturing",
            "subcategory":"Metals",
            "type":"Manufacturing & Wholesale Goods"
        }
    ],
    "sg:phone":"+90 258 261 6200",
    "sg:postcode":"34670",
    "sg:province":"Denizli",
    "sg:tags":[
        "iron-steel",
        "peoducts"
    ],
    "wof:name":"Se?kin Demir San. Ltd. Sti.",
    "wof:placetype":"venue"
},
  "geometry": {"coordinates":[29.063444,37.748047],"type":"Point"}
}