{
  "type": "Feature",
  "properties": {
    "iso:country":"TR",
    "sg:address":"K??yol Sok. No:9 K:2 D:3",
    "sg:city":"Bostanci",
    "sg:classifiers":[
        {
            "category":"Transit Center",
            "subcategory":"Freight",
            "type":"Transportation"
        }
    ],
    "sg:phone":"+90 216 384 7354",
    "sg:postcode":"25900",
    "sg:province":"Istanbul",
    "wof:name":"Amiral Gemi Ve Deniz Ac.ltd.sti",
    "wof:placetype":"venue"
},
  "geometry": {"coordinates":[29.033159256,41.0641593933],"type":"Point"}
}