{
  "type": "Feature",
  "properties": {
    "iso:country":"TR",
    "sg:address":"Inebey Mah. K???klanga Cad. No:7 K:4/5",
    "sg:city":"Aksaray",
    "sg:classifiers":[
        {
            "category":"Travel",
            "subcategory":"Travel Agent",
            "type":"Entertainment"
        }
    ],
    "sg:phone":"+90 6327300",
    "sg:postcode":"31030",
    "sg:province":"Istanbul",
    "sg:tags":[
        "agency",
        "tourism"
    ],
    "wof:name":"Cicoda Travel Turizm",
    "wof:placetype":"venue"
},
  "geometry": {"coordinates":[28.9861831665,41.0408554077],"type":"Point"}
}