{
  "type": "Feature",
  "properties": {
    "addr:full":"Rizabey Sok.kataroglu Apt.no:33/2 Kirazlitepe- Beylerbeyi Istanbul 20300",
    "addr:housenumber":"33 / 2",
    "addr:postcode":"20300",
    "addr:street":"Apt.No",
    "iso:country":"TR",
    "sg:address":"Rizabey Sok.kataroglu Apt.no:33/2 Kirazlitepe-",
    "sg:city":"Beylerbeyi",
    "sg:classifiers":[
        {
            "category":"Manufacturing",
            "subcategory":"Textiles",
            "type":"Manufacturing & Wholesale Goods"
        }
    ],
    "sg:phone":"+90 216 422 2055",
    "sg:postcode":"20300",
    "sg:province":"Istanbul",
    "sg:tags":[
        "cloth",
        "worker"
    ],
    "wof:name":"Enak Tekstil Ve Promosyon Ltd",
    "wof:placetype":"venue"
},
  "geometry": {"coordinates":[28.9759254456,41.0123786926],"type":"Point"}
}