{
  "type": "Feature",
  "properties": {
    "iso:country":"TR",
    "sg:address":"Agir San. B?ge. 8. Sk. No:11",
    "sg:city":"Ikitelli/K\u00fc\u00e7\u00fck\u00e7ekmece",
    "sg:classifiers":[
        {
            "category":"Manufacturing",
            "subcategory":"Metals",
            "type":"Manufacturing & Wholesale Goods"
        }
    ],
    "sg:phone":"+90 266 712 3305",
    "sg:postcode":"34670",
    "sg:province":"Balikesir",
    "sg:tags":[
        "iron-steel",
        "peoducts"
    ],
    "wof:name":"Ayyildiz ?elik D?vme San. Ltd. Sti.",
    "wof:placetype":"venue"
},
  "geometry": {"coordinates":[27.8833007812,39.6520996094],"type":"Point"}
}