{
  "type": "Feature",
  "properties": {
    "addr:full":"Ivedik Cad.no: 320 Yenimahalle Caglayan Ankara 07600",
    "addr:housenumber":"320",
    "addr:postcode":"07600",
    "addr:street":"Yenimahalle",
    "iso:country":"TR",
    "sg:address":"Ivedik Cad.no: 320 Yenimahalle",
    "sg:city":"Caglayan",
    "sg:classifiers":[
        {
            "category":"Manufacturing",
            "subcategory":"Glass & Minerals",
            "type":"Manufacturing & Wholesale Goods"
        }
    ],
    "sg:phone":"+90 312 343 5181",
    "sg:postcode":"07600",
    "sg:province":"Ankara",
    "sg:tags":[
        "glassware"
    ],
    "wof:name":"Pidosan",
    "wof:placetype":"venue"
},
  "geometry": {"coordinates":[32.8030128479,39.9640274048],"type":"Point"}
}