{
  "type": "Feature",
  "properties": {
    "iso:country":"TR",
    "sg:address":"Incilipinar Mah. 3.cad. Akinalan Is Merkezi Kat:3 No:3",
    "sg:city":"Kad\u0131k\u00f6y",
    "sg:classifiers":[
        {
            "category":"Farming",
            "subcategory":"Farm",
            "type":"Manufacturing & Wholesale Goods"
        }
    ],
    "sg:phone":"+90 342 230 4022",
    "sg:province":"Gaziantep",
    "sg:tags":[
        "agricultural",
        "product"
    ],
    "wof:name":"Bir-kan Tarim Teknolojileri",
    "wof:placetype":"venue"
},
  "geometry": {"coordinates":[37.3761024475,37.0629463196],"type":"Point"}
}