{
  "type": "Feature",
  "properties": {
    "iso:country":"TR",
    "sg:address":"Kabatas Setustu Saadet Apt. No.6 K.3 D.5",
    "sg:city":"Kabatas",
    "sg:classifiers":[
        {
            "category":"Transit Center",
            "subcategory":"Freight",
            "type":"Transportation"
        }
    ],
    "sg:phone":"+90 212 252 9293",
    "sg:postcode":"24600",
    "sg:province":"Istanbul",
    "wof:name":"Istanbul Denizcilik A.s.",
    "wof:placetype":"venue"
},
  "geometry": {"coordinates":[28.9759254456,41.0123786926],"type":"Point"}
}