{
  "type": "Feature",
  "properties": {
    "addr:full":"Esnaflar Sitesi B Blok No:33 Bozyazi Malatya 33830",
    "addr:housenumber":"blok no 33",
    "addr:postcode":"33830",
    "addr:street":"Bozyazi Malatya",
    "iso:country":"TR",
    "sg:address":"Esnaflar Sitesi B Blok No:33",
    "sg:city":"Bozyazi",
    "sg:classifiers":[
        {
            "category":"Farming",
            "subcategory":"Farm & Veterinary Services",
            "type":"Manufacturing & Wholesale Goods"
        }
    ],
    "sg:phone":"+90 442 324 8122",
    "sg:postcode":"33830",
    "sg:province":"Malatya",
    "sg:tags":[
        "veterinarian"
    ],
    "wof:name":"Nuh Gelegen",
    "wof:placetype":"venue"
},
  "geometry": {"coordinates":[38.3143005371,38.3474998474],"type":"Point"}
}