{
  "type": "Feature",
  "properties": {
    "addr:full":"Yildiz Posta Cad. Yener Sok. No:3 Esentepe Istanbul 01930",
    "addr:housenumber":"no 3",
    "addr:postcode":"01930",
    "addr:street":"Posta Cad. Yener Sok.",
    "iso:country":"TR",
    "sg:address":"Yildiz Posta Cad. Yener Sok. No:3",
    "sg:city":"Esentepe",
    "sg:classifiers":[
        {
            "category":"Utilities",
            "subcategory":"Water",
            "type":"Services"
        }
    ],
    "sg:phone":"+90 212 275 4544",
    "sg:postcode":"01930",
    "sg:province":"Istanbul",
    "sg:tags":[
        "vegetable",
        "margarine",
        "oil"
    ],
    "wof:name":"Aymar Yag San. A.s",
    "wof:placetype":"venue"
},
  "geometry": {"coordinates":[28.9776649475,41.0738868713],"type":"Point"}
}