{
  "type": "Feature",
  "properties": {
    "addr:full":"Cinnah Cad. No: 22/5 \u00c7ankaya Ankara 06105",
    "addr:housenumber":"22 / 5",
    "addr:postcode":"06105",
    "addr:street":"Cinnah Cad. No;C\u0327Ankaya Ankara",
    "iso:country":"TR",
    "sg:address":"Cinnah Cad. No: 22/5",
    "sg:city":"\u00c7ankaya",
    "sg:classifiers":[
        {
            "category":"Travel",
            "subcategory":"Travel Agent",
            "type":"Entertainment"
        }
    ],
    "sg:phone":"+90 312428246642",
    "sg:postcode":"06105",
    "sg:province":"Ankara",
    "sg:tags":[
        "agency",
        "tourism"
    ],
    "wof:name":"Adim Turizm",
    "wof:placetype":"venue"
},
  "geometry": {"coordinates":[32.8604812622,39.9429283142],"type":"Point"}
}