{
  "type": "Feature",
  "properties": {
    "addr:full":"Abide-i H?riyet Cad. Iskele Sk. 2/18 Sisli Mersin Istanbul 52750",
    "addr:housenumber":"2 / 18",
    "addr:postcode":"52750",
    "addr:street":"Riyet Cad. Iskele Sk.;Sisli",
    "iso:country":"TR",
    "sg:address":"Abide-i H?riyet Cad. Iskele Sk. 2/18 Sisli",
    "sg:city":"Mersin",
    "sg:classifiers":[
        {
            "category":"Wholesale",
            "subcategory":"Medical Equipment & Supplies",
            "type":"Manufacturing & Wholesale Goods"
        }
    ],
    "sg:phone":"+90 212 232 9230",
    "sg:postcode":"52750",
    "sg:province":"Istanbul",
    "wof:name":"Ipek Tib Urn. Tic. A.s.",
    "wof:placetype":"venue"
},
  "geometry": {"coordinates":[28.9861831665,41.0408554077],"type":"Point"}
}