{
  "type": "Feature",
  "properties": {
    "iso:country":"TR",
    "sg:address":"Tevfik Fikret Cad. 23",
    "sg:city":"G?g?en",
    "sg:classifiers":[
        {
            "category":"Shopping",
            "subcategory":"Clothing, Apparel, & Fashions",
            "type":"Retail Goods"
        }
    ],
    "sg:phone":"+90 212 555 5840",
    "sg:province":"Istanbul",
    "sg:tags":[
        "underwear"
    ],
    "wof:name":"?zmet Tekstil",
    "wof:placetype":"venue"
},
  "geometry": {"coordinates":[28.881601,41.069096],"type":"Point"}
}