{
  "type": "Feature",
  "properties": {
    "addr:full":"Soyak Yenisehir Palmiye Evleri C2 Blok D.35/ \u00dcmraniye Istanbul 03650",
    "addr:housenumber":"blok d.35 / u\u0308mraniye",
    "addr:postcode":"03650",
    "addr:street":"C2;Istanbul",
    "iso:country":"TR",
    "sg:address":"Soyak Yenisehir Palmiye Evleri C2 Blok D.35/",
    "sg:city":"\u00dcmraniye",
    "sg:classifiers":[
        {
            "category":"Building & Trades",
            "subcategory":"Landscaping Services",
            "type":"Services"
        }
    ],
    "sg:phone":"+90 216 533 0976",
    "sg:postcode":"03650",
    "sg:province":"Istanbul",
    "sg:tags":[
        "landscape"
    ],
    "wof:name":"?zge Peyzaj",
    "wof:placetype":"venue"
},
  "geometry": {"coordinates":[28.9759254456,41.0123786926],"type":"Point"}
}