{
  "type": "Feature",
  "properties": {
    "iso:country":"TR",
    "sg:address":"Denizer Cad.karab? Sok.no:23/a Cevizli-kartal",
    "sg:city":"G?tepe",
    "sg:classifiers":[
        {
            "category":"Wholesale",
            "subcategory":"Medical Equipment & Supplies",
            "type":"Manufacturing & Wholesale Goods"
        }
    ],
    "sg:phone":"+90 216 371 2012",
    "sg:province":"Istanbul",
    "sg:tags":[
        "material"
    ],
    "wof:name":"Anadolu Ithalat Ihracat Ltd.",
    "wof:placetype":"venue"
},
  "geometry": {"coordinates":[29.1610298157,40.9178390503],"type":"Point"}
}