{
  "type": "Feature",
  "properties": {
    "addr:full":"Ger-san San. Sit. 6456 Sk. No.63 Ergazi Yenimahalle Ankara 06",
    "addr:housenumber":"06",
    "addr:street":"6456 Sk. No.63 Ergazi;Ankara",
    "iso:country":"TR",
    "sg:address":"Ger-san San. Sit. 6456 Sk. No.63 Ergazi",
    "sg:city":"Yenimahalle",
    "sg:classifiers":[
        {
            "category":"Shopping",
            "subcategory":"Stationery & Office Supplies",
            "type":"Retail Goods"
        }
    ],
    "sg:phone":"+90 312 255 4370",
    "sg:postcode":"06",
    "sg:province":"Ankara",
    "sg:tags":[
        "paper"
    ],
    "wof:name":"Delta Kagitcilik",
    "wof:placetype":"venue"
},
  "geometry": {"coordinates":[32.8560333252,39.9438743591],"type":"Point"}
}