{
  "type": "Feature",
  "properties": {
    "iso:country":"TR",
    "sg:address":"Halaskargazi Cad.no:295/4 Osmanbey",
    "sg:city":"Aksaray",
    "sg:classifiers":[
        {
            "category":"Banks & Credit Unions",
            "subcategory":"Financial Services",
            "type":"Services"
        }
    ],
    "sg:phone":"+90 212 233 2750",
    "sg:postcode":"31030",
    "sg:province":"Istanbul",
    "sg:tags":[
        "finance"
    ],
    "wof:name":"Arti Menkul Kiymetler A.s",
    "wof:placetype":"venue"
},
  "geometry": {"coordinates":[28.9885787964,41.0618247986],"type":"Point"}
}