{
  "type": "Feature",
  "properties": {
    "iso:country":"TR",
    "sg:address":"San.bolgesi 6.cad. No:70",
    "sg:city":"Osmangazi",
    "sg:classifiers":[
        {
            "category":"Home & Garden",
            "subcategory":"Kitchen Supply",
            "type":"Retail Goods"
        }
    ],
    "sg:phone":"+90 352 320 1104",
    "sg:postcode":"16030",
    "sg:province":"Kayseri",
    "sg:tags":[
        "wardrobe"
    ],
    "wof:name":"Polmersan Mutfak Banyo Dokum Mermer San.tic. Ltd.sti.",
    "wof:placetype":"venue"
},
  "geometry": {"coordinates":[35.4891357422,38.7225761414],"type":"Point"}
}