{
  "type": "Feature",
  "properties": {
    "iso:country":"TR",
    "sg:address":"B??dere Cd. Arzu Apt. No:99 D:9 Gayrettepe",
    "sg:city":"Beyoglu",
    "sg:classifiers":[
        {
            "category":"Building & Trades",
            "subcategory":"Construction",
            "type":"Services"
        }
    ],
    "sg:phone":"+90 212 356 2424",
    "sg:postcode":"46810",
    "sg:province":"Istanbul",
    "sg:tags":[
        "foundation"
    ],
    "wof:name":"Rumeli Egitim Vakfi",
    "wof:placetype":"venue"
},
  "geometry": {"coordinates":[28.9952659607,41.0810394287],"type":"Point"}
}