{
  "type": "Feature",
  "properties": {
    "iso:country":"TR",
    "sg:address":"Denizli",
    "sg:city":"Ikitelli/K\u00fc\u00e7\u00fck\u00e7ekmece",
    "sg:classifiers":[
        {
            "category":"Health Services",
            "subcategory":"Hospital",
            "type":"Services"
        }
    ],
    "sg:phone":"+90 258 261 1900",
    "sg:postcode":"34660",
    "sg:province":"Denizli",
    "sg:tags":[
        "state"
    ],
    "wof:name":"Askeri Hastane",
    "wof:placetype":"venue"
},
  "geometry": {"coordinates":[29.291389,37.743332],"type":"Point"}
}