{
  "type": "Feature",
  "properties": {
    "addr:full":"Tiyatro Cad. Yahya Pasa Sok.azak Big.center No:19 K:1 Beyazit Zeytinburnu Istanbul 34020",
    "addr:housenumber":"19 k 1",
    "addr:postcode":"34020",
    "addr:street":"Tiyatro Cad. Yahya Pasa;Big.Center No;Beyazit Zeytinburnu",
    "iso:country":"TR",
    "sg:address":"Tiyatro Cad. Yahya Pasa Sok.azak Big.center No:19 K:1 Beyazit",
    "sg:city":"Zeytinburnu",
    "sg:classifiers":[
        {
            "category":"Manufacturing",
            "subcategory":"Leather Goods",
            "type":"Manufacturing & Wholesale Goods"
        }
    ],
    "sg:phone":"+90 212 638 3520",
    "sg:postcode":"34020",
    "sg:province":"Istanbul",
    "wof:name":"Agca Deri Pazarlama San. Ve Tic. Ltd. Sti.",
    "wof:placetype":"venue"
},
  "geometry": {"coordinates":[28.9026374817,40.9924430847],"type":"Point"}
}