{
  "type": "Feature",
  "properties": {
    "addr:full":"K.ayasofya Cad. No:26 Sultanahmet Istanbul 34122",
    "addr:housenumber":"26",
    "addr:postcode":"34122",
    "addr:street":"K.Ayasofya Cad. No",
    "iso:country":"TR",
    "sg:address":"K.ayasofya Cad. No:26",
    "sg:city":"Sultanahmet",
    "sg:orig_category":"Hotels: Motels",
    "sg:phone":"+90 212 518 2323",
    "sg:postcode":"34122",
    "sg:province":"Istanbul",
    "wof:name":"Hotel Sarnic",
    "wof:placetype":"venue"
},
  "geometry": {"coordinates":[28.9753646851,41.0035552979],"type":"Point"}
}