{
  "type": "Feature",
  "properties": {
    "addr:full":"Perpa Ticaret Merkezi B Blok No:2311 2313 Okmeydani Istanbul 43050",
    "addr:housenumber":"2313",
    "addr:postcode":"43050",
    "addr:street":"Okmeydani Istanbul",
    "iso:country":"TR",
    "sg:address":"Perpa Ticaret Merkezi B Blok No:2311 2313",
    "sg:city":"Okmeydani",
    "sg:orig_category":"Perpa",
    "sg:phone":"+90 21232073111",
    "sg:postcode":"43050",
    "sg:province":"Istanbul",
    "sg:website":"aktifsaat.com",
    "wof:name":"Aktif Zaman Kont Sis Ltd Sti",
    "wof:placetype":"venue"
},
  "geometry": {"coordinates":[28.9759254456,41.0123786926],"type":"Point"}
}