{
  "type": "Feature",
  "properties": {
    "addr:full":"Izettin ?alislar Cd. No:51/a Bah\u00e7elievler Istanbul 34180",
    "addr:housenumber":"no 51 / a",
    "addr:postcode":"34180",
    "addr:street":"Alislar Cd.",
    "iso:country":"TR",
    "sg:address":"Izettin ?alislar Cd. No:51/a",
    "sg:city":"Bah\u00e7elievler",
    "sg:classifiers":[
        {
            "category":"Utilities",
            "subcategory":"Natural Gas",
            "type":"Services"
        }
    ],
    "sg:phone":"+90 212 575 3072",
    "sg:postcode":"34180",
    "sg:province":"Istanbul",
    "sg:tags":[
        "tank-heating-natural"
    ],
    "wof:name":"Katre Elektronik Ltd. Sti.",
    "wof:placetype":"venue"
},
  "geometry": {"coordinates":[28.9861831665,41.0408554077],"type":"Point"}
}