{
  "type": "Feature",
  "properties": {
    "addr:full":"Gokalp Mah.31 Sk. No.6 Zeytinburnu Beyazit Istanbul 34490",
    "addr:housenumber":"zeytinburnu",
    "addr:postcode":"34490",
    "addr:street":"Mah.31 Sk. No.6;Istanbul",
    "iso:country":"TR",
    "sg:address":"Gokalp Mah.31 Sk. No.6 Zeytinburnu",
    "sg:city":"Beyazit",
    "sg:classifiers":[
        {
            "category":"Manufacturing",
            "subcategory":"Leather Goods",
            "type":"Manufacturing & Wholesale Goods"
        }
    ],
    "sg:phone":"+90 212 661 0949",
    "sg:postcode":"34490",
    "sg:province":"Istanbul",
    "wof:name":"Derimpeks Deri San. Ltd.sti.",
    "wof:placetype":"venue"
},
  "geometry": {"coordinates":[28.9108829498,40.9920349121],"type":"Point"}
}