{
  "type": "Feature",
  "properties": {
    "addr:full":"19 Mayis Org.san.sitesi 56.sok No 11 Kutlukent Samsun 55330",
    "addr:housenumber":"19;56.sok no 11",
    "addr:postcode":"55330",
    "addr:street":"Mayis Org.San.Sitesi;Kutlukent Samsun",
    "iso:country":"TR",
    "sg:address":"19 Mayis Org.san.sitesi 56.sok No 11",
    "sg:city":"Kutlukent",
    "sg:classifiers":[
        {
            "category":"Utilities",
            "subcategory":"Recycling",
            "type":"Services"
        }
    ],
    "sg:phone":"+90 362 266 9393",
    "sg:postcode":"55330",
    "sg:province":"Samsun",
    "sg:tags":[
        "measuring",
        "weighing"
    ],
    "wof:name":"Ertebas Elektronik",
    "wof:placetype":"venue"
},
  "geometry": {"coordinates":[36.3381233215,41.2815742493],"type":"Point"}
}