{
  "type": "Feature",
  "properties": {
    "addr:full":"Cumhuriyet Caddesi No:247 Sisli Istanbul 65710",
    "addr:housenumber":"no",
    "addr:postcode":"65710",
    "addr:street":"Cumhuriyet Caddesi",
    "iso:country":"TR",
    "sg:address":"Cumhuriyet Caddesi No:247",
    "sg:city":"Sisli",
    "sg:classifiers":[
        {
            "category":"Travel",
            "subcategory":"Travel Agent",
            "type":"Entertainment"
        }
    ],
    "sg:phone":"+90 2924800",
    "sg:postcode":"65710",
    "sg:province":"Istanbul",
    "sg:tags":[
        "agency",
        "tourism"
    ],
    "wof:name":"Bintur Turizm Seyahat Acentasi",
    "wof:placetype":"venue"
},
  "geometry": {"coordinates":[29.1255912781,41.0904655457],"type":"Point"}
}