{
  "type": "Feature",
  "properties": {
    "addr:full":"Gulbahar Cad.8.sok.no:78 Gunesli Istanbul 01660",
    "addr:housenumber":"78",
    "addr:postcode":"01660",
    "iso:country":"TR",
    "sg:address":"Gulbahar Cad.8.sok.no:78",
    "sg:city":"Gunesli",
    "sg:classifiers":[
        {
            "category":"Professional",
            "subcategory":"Employment Agencies",
            "type":"Services"
        }
    ],
    "sg:phone":"+90 212 515 7069",
    "sg:postcode":"01660",
    "sg:province":"Istanbul",
    "sg:tags":[
        "personnel"
    ],
    "wof:name":"Ozmenler Turizm",
    "wof:placetype":"venue"
},
  "geometry": {"coordinates":[28.8584976196,41.0459747314],"type":"Point"}
}