{
  "type": "Feature",
  "properties": {
    "addr:full":"Talatpasa Blv. No:9/14 Saman Pzr. G?tepe Ankara",
    "addr:housenumber":"14;?",
    "addr:street":"Blv. No 9 /;Pzr. G",
    "iso:country":"TR",
    "sg:address":"Talatpasa Blv. No:9/14 Saman Pzr.",
    "sg:city":"G?tepe",
    "sg:classifiers":[
        {
            "category":"Wholesale",
            "subcategory":"Medical Equipment & Supplies",
            "type":"Manufacturing & Wholesale Goods"
        }
    ],
    "sg:phone":"+90 312 311 4377",
    "sg:province":"Ankara",
    "sg:tags":[
        "material"
    ],
    "wof:name":"Avrasya Medikal",
    "wof:placetype":"venue"
},
  "geometry": {"coordinates":[32.8604812622,39.9429283142],"type":"Point"}
}