{
  "type": "Feature",
  "properties": {
    "addr:full":"Sanayi Carsisi Isi Gunduz Sok. No:31/103 Ikitelli Konya 34306",
    "addr:housenumber":"no 31 / 103",
    "addr:postcode":"34306",
    "addr:street":"Gunduz Sok.;Ikitelli Konya",
    "iso:country":"TR",
    "sg:address":"Sanayi Carsisi Isi Gunduz Sok. No:31/103",
    "sg:city":"Ikitelli",
    "sg:classifiers":[
        {
            "category":"Autos & Motor Vehicles",
            "subcategory":"Auto Supplies",
            "type":"Retail Goods"
        }
    ],
    "sg:phone":"+90 332 236 1414",
    "sg:postcode":"34306",
    "sg:province":"Konya",
    "sg:tags":[
        "accessory"
    ],
    "wof:name":"Onur Oto Ic & Dis Dizayn",
    "wof:placetype":"venue"
},
  "geometry": {"coordinates":[33.0667152405,39.2111282349],"type":"Point"}
}