{
  "type": "Feature",
  "properties": {
    "addr:full":"Mavi Bulvar Toros Mah.6 Sok. Guler Apt Zemin Kat No:14/d Gulbahce Adana 31070",
    "addr:housenumber":"kat no 14 / d",
    "addr:postcode":"31070",
    "addr:street":"Mah.6 Sok. Guler;Gulbahce Adana",
    "iso:country":"TR",
    "sg:address":"Mavi Bulvar Toros Mah.6 Sok. Guler Apt Zemin Kat No:14/d",
    "sg:city":"Gulbahce",
    "sg:classifiers":[
        {
            "category":"Manufacturing",
            "subcategory":"Building Materials",
            "type":"Manufacturing & Wholesale Goods"
        }
    ],
    "sg:phone":"+90 322 225 1185",
    "sg:postcode":"31070",
    "sg:province":"Adana",
    "sg:tags":[
        "lifts-elevators"
    ],
    "wof:name":"Yilmaz Asansorleri",
    "wof:placetype":"venue"
},
  "geometry": {"coordinates":[35.3137359619,37.0007171631],"type":"Point"}
}