{
  "type": "Feature",
  "properties": {
    "iso:country":"TR",
    "sg:address":"Mithatpasa Cd. San. Sites 5. Sk. No:7 Edremit",
    "sg:city":"B\u00fcy\u00fck\u00e7ekmece",
    "sg:classifiers":[
        {
            "category":"Manufacturing",
            "subcategory":"Tools & Machinery",
            "type":"Manufacturing & Wholesale Goods"
        }
    ],
    "sg:phone":"+90 266 372 2134",
    "sg:postcode":"34905",
    "sg:province":"Balikesir",
    "sg:tags":[
        "machine",
        "industry"
    ],
    "wof:name":"Ak?aylar Makina San. Tapi Eleman. End?strisi Tic. Ltd. Sti.",
    "wof:placetype":"venue"
},
  "geometry": {"coordinates":[27.8833007812,39.6520996094],"type":"Point"}
}