{
  "type": "Feature",
  "properties": {
    "addr:full":"Bostanci Yolu No:79 Y.dudullu-umraniye Ikitelli/K\u00fc\u00e7\u00fck\u00e7ekmece Istanbul 34660",
    "addr:housenumber":"no 79",
    "addr:postcode":"34660",
    "addr:street":"Bostanci Yolu",
    "iso:country":"TR",
    "sg:address":"Bostanci Yolu No:79 Y.dudullu-umraniye",
    "sg:city":"Ikitelli/K\u00fc\u00e7\u00fck\u00e7ekmece",
    "sg:orig_category":"Furniture Supplamentary",
    "sg:phone":"+90 216 313 1090",
    "sg:postcode":"34660",
    "sg:province":"Istanbul",
    "wof:name":"Sefa Sunger Koltuk Malzemeleri Ltd.sti.",
    "wof:placetype":"venue"
},
  "geometry": {"coordinates":[29.1340732574,40.98254776],"type":"Point"}
}