{
  "type": "Feature",
  "properties": {
    "iso:country":"TR",
    "sg:address":"Istanbul",
    "sg:city":"Ikitelli/K\u00fc\u00e7\u00fck\u00e7ekmece",
    "sg:classifiers":[
        {
            "category":"Health Services",
            "subcategory":"Hospital",
            "type":"Services"
        }
    ],
    "sg:phone":"+90 212 252 4300",
    "sg:postcode":"34660",
    "sg:province":"Istanbul",
    "sg:tags":[
        "state"
    ],
    "wof:name":"Taksim Hastanesi",
    "wof:placetype":"venue"
},
  "geometry": {"coordinates":[28.766441,41.163429],"type":"Point"}
}