{
  "type": "Feature",
  "properties": {
    "addr:full":"Resitpasa Sok. Omer Bey Apt No: 4 \u00dcmraniye Istanbul 03650",
    "addr:postcode":"03650",
    "addr:street":"Resitpasa Sok. Omer Bey Apt No 4",
    "iso:country":"TR",
    "sg:address":"Resitpasa Sok. Omer Bey Apt No: 4",
    "sg:city":"\u00dcmraniye",
    "sg:classifiers":[
        {
            "category":"Manufacturing",
            "subcategory":"Building Materials",
            "type":"Manufacturing & Wholesale Goods"
        }
    ],
    "sg:phone":"+90 216 412 9378",
    "sg:postcode":"03650",
    "sg:province":"Istanbul",
    "sg:tags":[
        "lifts-elevators"
    ],
    "wof:name":"Sanlift Asans?leri San Tic",
    "wof:placetype":"venue"
},
  "geometry": {"coordinates":[29.051235199,41.1175956726],"type":"Point"}
}