{
  "type": "Feature",
  "properties": {
    "addr:full":"Mersin Yolu ?zeri Hipodrom Bitisigi Antakya Adana 31000",
    "addr:housenumber":"?",
    "addr:postcode":"31000",
    "addr:street":"Mersin Yolu;Adana",
    "iso:country":"TR",
    "sg:address":"Mersin Yolu ?zeri Hipodrom Bitisigi",
    "sg:city":"Antakya",
    "sg:classifiers":[
        {
            "category":"Food & Beverages",
            "subcategory":"Groceries & Convenience Stores",
            "type":"Retail Goods"
        }
    ],
    "sg:phone":"+90 322 428 1154",
    "sg:postcode":"31000",
    "sg:province":"Adana",
    "sg:tags":[
        "drink-",
        "soft"
    ],
    "wof:name":"Istanbul Mesrubat San.imsa As.",
    "wof:placetype":"venue"
},
  "geometry": {"coordinates":[35.313736,37.000717],"type":"Point"}
}