{
  "type": "Feature",
  "properties": {
    "iso:country":"TR",
    "sg:address":"Hurriyet Mah.manolya Sok. No:33/b-",
    "sg:city":"Caglayan",
    "sg:classifiers":[
        {
            "category":"Manufacturing",
            "subcategory":"Glass & Minerals",
            "type":"Manufacturing & Wholesale Goods"
        }
    ],
    "sg:phone":"+90 212 225 4044",
    "sg:postcode":"07600",
    "sg:province":"Istanbul",
    "sg:tags":[
        "glass-mirror"
    ],
    "wof:name":"Doruk Cam Ticaret",
    "wof:placetype":"venue"
},
  "geometry": {"coordinates":[28.9828510284,41.0726547241],"type":"Point"}
}