{
  "type": "Feature",
  "properties": {
    "addr:full":"Istoc Tic.merkezi 12.ada No:26 Bagcilar Kad\u0131k\u00f6y Istanbul 34000",
    "addr:housenumber":"no 26",
    "addr:postcode":"34000",
    "iso:country":"TR",
    "sg:address":"Istoc Tic.merkezi 12.ada No:26 Bagcilar",
    "sg:city":"Kad\u0131k\u00f6y",
    "sg:classifiers":[
        {
            "category":"Shopping",
            "subcategory":"Computers & Home Electronics",
            "type":"Retail Goods"
        }
    ],
    "sg:phone":"+90 212 659 6186",
    "sg:postcode":"34000",
    "sg:province":"Istanbul",
    "sg:tags":[
        "product",
        "electric-electronic"
    ],
    "wof:name":"Elektronik San.tic.ltd.sti.",
    "wof:placetype":"venue"
},
  "geometry": {"coordinates":[28.9861831665,41.0408554077],"type":"Point"}
}