{
  "type": "Feature",
  "properties": {
    "iso:country":"TR",
    "sg:address":"Tepecik Yolu Derya Sit. A Blok D:12 Etiler",
    "sg:city":"Nazilli",
    "sg:classifiers":[
        {
            "category":"Wholesale",
            "subcategory":"Medical Equipment & Supplies",
            "type":"Manufacturing & Wholesale Goods"
        }
    ],
    "sg:phone":"+90 212 265 1584",
    "sg:postcode":"65600",
    "sg:province":"Istanbul",
    "wof:name":"Nur Medikal",
    "wof:placetype":"venue"
},
  "geometry": {"coordinates":[28.9861831665,41.0408554077],"type":"Point"}
}