{
  "type": "Feature",
  "properties": {
    "iso:country":"TR",
    "sg:address":"Orta Mah K???k Hamam Cad No:18",
    "sg:city":"Adapazari",
    "sg:classifiers":[
        {
            "category":"Banks & Credit Unions",
            "subcategory":"Investment Brokerage",
            "type":"Services"
        }
    ],
    "sg:phone":"+90 264 279 8098",
    "sg:postcode":"54040",
    "sg:province":"Sakarya",
    "sg:tags":[
        "exporter"
    ],
    "wof:name":"Alsa Saat Kuyumculuk Tic Ltd.sti.",
    "wof:placetype":"venue"
},
  "geometry": {"coordinates":[30.400871,40.786667],"type":"Point"}
}