{
  "type": "Feature",
  "properties": {
    "iso:country":"TR",
    "sg:address":"Kasim Sk. No.55 Merter",
    "sg:city":"Ikitelli/K\u00fc\u00e7\u00fck\u00e7ekmece",
    "sg:classifiers":[
        {
            "category":"Shopping",
            "subcategory":"Shoes",
            "type":"Retail Goods"
        }
    ],
    "sg:phone":"+90 212 502 0062",
    "sg:postcode":"34670",
    "sg:province":"Istanbul",
    "wof:name":"Akpas Ayakkabi Spor Malz.a.s.",
    "wof:placetype":"venue"
},
  "geometry": {"coordinates":[28.884678,41.009182],"type":"Point"}
}