{
  "type": "Feature",
  "properties": {
    "addr:full":"Ortabah? Caddesi No:51 - Besiktas 64020 Istanbul",
    "addr:housenumber":"no 51",
    "addr:postcode":"64020",
    "addr:street":"? Caddesi;Besiktas",
    "iso:country":"TR",
    "sg:address":"Ortabah? Caddesi No:51 - Besiktas",
    "sg:city":"64020",
    "sg:classifiers":[
        {
            "category":"Government",
            "subcategory":"Post Office",
            "type":"Public Place"
        }
    ],
    "sg:phone":"+90 212 260 2246",
    "sg:province":"Istanbul",
    "sg:tags":[
        "notary"
    ],
    "wof:name":"Besiktas 1 Noterligi",
    "wof:placetype":"venue"
},
  "geometry": {"coordinates":[29.0283794403,41.0764884949],"type":"Point"}
}