{
  "type": "Feature",
  "properties": {
    "addr:full":"Kisla Cad.sanayi Cikmazi Sok. No:4 Rami Istanbul 34055",
    "addr:housenumber":"no 4",
    "addr:postcode":"34055",
    "addr:street":"Cikmazi Sok.",
    "iso:country":"TR",
    "sg:address":"Kisla Cad.sanayi Cikmazi Sok. No:4",
    "sg:city":"Rami",
    "sg:classifiers":[
        {
            "category":"Shopping",
            "subcategory":"Crafts & Fabrics",
            "type":"Retail Goods"
        }
    ],
    "sg:phone":"+90 21261654333",
    "sg:postcode":"34055",
    "sg:province":"Istanbul",
    "sg:tags":[
        "yarn"
    ],
    "wof:name":"Boyar Tekstil San.tic.a.s.",
    "wof:placetype":"venue"
},
  "geometry": {"coordinates":[28.9026298523,41.0180053711],"type":"Point"}
}