{
  "type": "Feature",
  "properties": {
    "addr:full":"Abdibey C. Saadet Sk. No.1 Fikirtepe Istanbul 34720",
    "addr:postcode":"34720",
    "addr:street":"Saadet Sk. No.1",
    "iso:country":"TR",
    "sg:address":"Abdibey C. Saadet Sk. No.1",
    "sg:city":"Fikirtepe",
    "sg:classifiers":[
        {
            "category":"Food & Beverages",
            "subcategory":"Dairy",
            "type":"Retail Goods"
        }
    ],
    "sg:phone":"+90 216 348 3468",
    "sg:postcode":"34720",
    "sg:province":"Istanbul",
    "sg:tags":[
        "pruducts",
        "milk"
    ],
    "wof:name":"Ada S?t Maml.koll.sti.",
    "wof:placetype":"venue"
},
  "geometry": {"coordinates":[29.0554466248,40.9919433594],"type":"Point"}
}