{
  "type": "Feature",
  "properties": {
    "addr:full":"Soganlik Cad. 59/b Kartal Bolvadin Istanbul 03300",
    "addr:housenumber":"59 / b",
    "addr:postcode":"03300",
    "addr:street":"Soganlik Cad.;Kartal Bolvadin",
    "iso:country":"TR",
    "sg:address":"Soganlik Cad. 59/b Kartal",
    "sg:city":"Bolvadin",
    "sg:classifiers":[
        {
            "category":"Social Services",
            "subcategory":"Retirement Home",
            "type":"Services"
        }
    ],
    "sg:phone":"+90 216 389 8060",
    "sg:postcode":"03300",
    "sg:province":"Istanbul",
    "sg:tags":[
        "door"
    ],
    "wof:name":"Ersan Reklam Ltd.",
    "wof:placetype":"venue"
},
  "geometry": {"coordinates":[29.1965885162,40.9169387817],"type":"Point"}
}