{
  "type": "Feature",
  "properties": {
    "iso:country":"TR",
    "sg:address":"Haracci K.mehmet Mah.fukarababasi Sok. Ozer Han Kat:2 No:1 Fatih",
    "sg:city":"Sisli",
    "sg:classifiers":[
        {
            "category":"Professional",
            "subcategory":"Detective & Security Services",
            "type":"Services"
        }
    ],
    "sg:phone":"+90 212 534 8671",
    "sg:postcode":"34381",
    "sg:province":"Istanbul",
    "sg:tags":[
        "material"
    ],
    "wof:name":"Akay Guvenlik",
    "wof:placetype":"venue"
},
  "geometry": {"coordinates":[28.984884,41.061108],"type":"Point"}
}