{
  "type": "Feature",
  "properties": {
    "iso:country":"TR",
    "sg:address":"Dereboyu Caddesi, ?zg? Sokak, ?ali Binasi",
    "sg:city":"Halkali",
    "sg:orig_category":"Printinh House",
    "sg:phone":"+90 212 696 5227",
    "sg:postcode":"23410",
    "sg:province":"Istanbul",
    "wof:name":"?ali Grafik",
    "wof:placetype":"venue"
},
  "geometry": {"coordinates":[28.9759254456,41.0123786926],"type":"Point"}
}