{
  "type": "Feature",
  "properties": {
    "iso:country":"TR",
    "sg:address":"Ugur Sk. No.2",
    "sg:city":"Kagithane",
    "sg:classifiers":[
        {
            "category":"Shopping",
            "subcategory":"Clothing, Apparel, & Fashions",
            "type":"Retail Goods"
        }
    ],
    "sg:phone":"+90 212 295 4700",
    "sg:postcode":"34406",
    "sg:province":"Istanbul",
    "sg:tags":[
        "underwear"
    ],
    "wof:name":"Ayyildiz Tekstil Ve Konfeksiyon San. A.s.",
    "wof:placetype":"venue"
},
  "geometry": {"coordinates":[28.977005,41.074024],"type":"Point"}
}