{
  "type": "Feature",
  "properties": {
    "addr:full":"Basvekil Cad.salman Pasaji Kat 1 No: 41 K.mustafapasa Istanbul Fatih Istanbul 01740",
    "addr:housenumber":"kat 1 no 41",
    "addr:postcode":"01740",
    "iso:country":"TR",
    "sg:address":"Basvekil Cad.salman Pasaji Kat 1 No: 41 K.mustafapasa Istanbul",
    "sg:city":"Fatih",
    "sg:orig_category":"Auto Galeries",
    "sg:phone":"+90 535 304 0944",
    "sg:postcode":"01740",
    "sg:province":"Istanbul",
    "wof:name":"Baykon Otomotiv Ltd.sti",
    "wof:placetype":"venue"
},
  "geometry": {"coordinates":[28.9861831665,41.0408554077],"type":"Point"}
}