{
  "type": "Feature",
  "properties": {
    "iso:country":"TR",
    "sg:address":"3.san. Sit . No.21",
    "sg:city":"Sultanhamam",
    "sg:classifiers":[
        {
            "category":"Shopping",
            "subcategory":"Crafts & Fabrics",
            "type":"Retail Goods"
        }
    ],
    "sg:phone":"+90 258 268 7857",
    "sg:province":"Denizli",
    "sg:tags":[
        "weaving"
    ],
    "wof:name":"Ozgecan Tekstil Ltd.sti.",
    "wof:placetype":"venue"
},
  "geometry": {"coordinates":[29.0864906311,37.773525238],"type":"Point"}
}