{
  "type": "Feature",
  "properties": {
    "addr:full":"Piyalepasa Mh. Kuzen Sk. No:6 Okmeydani B?y?k?ekmece Istanbul 34900",
    "addr:housenumber":"b ? y ? k ?",
    "addr:postcode":"34900",
    "addr:street":"Piyalepasa Mh. Kuzen Sk. No 6",
    "iso:country":"TR",
    "sg:address":"Piyalepasa Mh. Kuzen Sk. No:6 Okmeydani",
    "sg:city":"B?y?k?ekmece",
    "sg:classifiers":[
        {
            "category":"Home & Garden",
            "subcategory":"Kitchen Supply",
            "type":"Retail Goods"
        }
    ],
    "sg:phone":"+90 212 253 0792",
    "sg:postcode":"34900",
    "sg:province":"Istanbul",
    "sg:tags":[
        "fire",
        "extinguisher"
    ],
    "wof:name":"Alev Yangin S?nd?rme Cihaz. San. Tic.",
    "wof:placetype":"venue"
},
  "geometry": {"coordinates":[28.9759254456,41.0123786926],"type":"Point"}
}