{
  "type": "Feature",
  "properties": {
    "addr:full":"Istanbul Cd. 111 Cesme Konya 15930",
    "addr:housenumber":"111",
    "addr:postcode":"15930",
    "addr:street":"Cd.",
    "iso:country":"TR",
    "sg:address":"Istanbul Cd. 111",
    "sg:city":"Cesme",
    "sg:orig_category":"Hotels: Motels",
    "sg:phone":"+90 332 351 0291",
    "sg:postcode":"15930",
    "sg:province":"Konya",
    "wof:name":"Hora Otel",
    "wof:placetype":"venue"
},
  "geometry": {"coordinates":[33.0667152405,39.2111282349],"type":"Point"}
}