{
  "type": "Feature",
  "properties": {
    "addr:full":"Pembe Ev. San. B?g. Ikitelli/K\u00fc\u00e7\u00fck\u00e7ekmece Karab?k 34670",
    "addr:postcode":"34670",
    "iso:country":"TR",
    "sg:address":"Pembe Ev. San. B?g.",
    "sg:city":"Ikitelli/K\u00fc\u00e7\u00fck\u00e7ekmece",
    "sg:classifiers":[
        {
            "category":"Professional",
            "subcategory":"Business Services",
            "type":"Services"
        }
    ],
    "sg:phone":"+90 370 424 2753",
    "sg:postcode":"34670",
    "sg:province":"Karab?k",
    "sg:tags":[
        "industry",
        "casting"
    ],
    "wof:name":"K?rek?iler Had. San. Tic. Ltd. Sti.",
    "wof:placetype":"venue"
},
  "geometry": {"coordinates":[28.9674797058,41.0096588135],"type":"Point"}
}