{
  "type": "Feature",
  "properties": {
    "iso:country":"TR",
    "sg:address":"Bayman Cd. No:14/3 4. Levent",
    "sg:city":"Osmangazi",
    "sg:classifiers":[
        {
            "category":"Home & Garden",
            "subcategory":"Kitchen Supply",
            "type":"Retail Goods"
        }
    ],
    "sg:phone":"+90 212 270 3409",
    "sg:postcode":"16030",
    "sg:province":"Istanbul",
    "sg:tags":[
        "wardrobe"
    ],
    "wof:name":"Pano Ahsap San. Ltd.",
    "wof:placetype":"venue"
},
  "geometry": {"coordinates":[29.0058498383,41.0980033875],"type":"Point"}
}