{
  "type": "Feature",
  "properties": {
    "addr:full":"Basin Cd. M?ettip Sk. No:15/b Basinevleri Tel. (312) 322 99 42 4.levent Ankara",
    "addr:housenumber":"15 / b;42 4.levent",
    "addr:postcode":"322",
    "addr:street":"Basin;M;Ettip Sk. No;Basinevleri Tel.;99",
    "iso:country":"TR",
    "sg:address":"Basin Cd. M?ettip Sk. No:15/b Basinevleri Tel. (312) 322 99 42",
    "sg:city":"4.levent",
    "sg:orig_category":"Printinh House",
    "sg:phone":"+90 312 230 8400",
    "sg:province":"Ankara",
    "wof:name":"Basaraslan Tic. - Remaksa Ltd.",
    "wof:placetype":"venue"
},
  "geometry": {"coordinates":[32.8560333252,39.9438743591],"type":"Point"}
}