{
  "type": "Feature",
  "properties": {
    "addr:full":"Esentepe Cd. Bildircin Sk. No: 8 Mecidiyek\u00f6y Istanbul 34387",
    "addr:postcode":"34387",
    "addr:street":"Esentepe Cd. Bildircin Sk. No 8 Mecidiyekoey",
    "iso:country":"TR",
    "sg:address":"Esentepe Cd. Bildircin Sk. No: 8",
    "sg:city":"Mecidiyek\u00f6y",
    "sg:classifiers":[
        {
            "category":"Home & Garden",
            "subcategory":"Household Appliances",
            "type":"Retail Goods"
        }
    ],
    "sg:phone":"+90 212 211 3233",
    "sg:postcode":"34387",
    "sg:province":"Istanbul",
    "sg:tags":[
        "conditioner",
        "air"
    ],
    "wof:name":"Aaf Hava Filtreleri Tic.",
    "wof:placetype":"venue"
},
  "geometry": {"coordinates":[28.9942111969,41.0812492371],"type":"Point"}
}