{
  "type": "Feature",
  "properties": {
    "iso:country":"TR",
    "sg:address":"Plaza Spring Giz B.blok Maslak",
    "sg:city":"Kazasker",
    "sg:classifiers":[
        {
            "category":"Shopping",
            "subcategory":"Photographic Equipment",
            "type":"Retail Goods"
        }
    ],
    "sg:phone":"+90 212276164041",
    "sg:province":"Istanbul",
    "sg:tags":[
        "photo"
    ],
    "wof:name":"Deyim A.s. (resim Cerceveleri Ve Aksesuarlari)",
    "wof:placetype":"venue"
},
  "geometry": {"coordinates":[29.012298584,41.1274490356],"type":"Point"}
}