{
  "type": "Feature",
  "properties": {
    "addr:full":"Turgut Ozal Cad. Galvano Sit.a 15 Ikitelli Istanbul 34306",
    "addr:housenumber":"15",
    "addr:postcode":"34306",
    "addr:street":"Turgut Ozal Cad. Galvano Sit.A;Istanbul",
    "iso:country":"TR",
    "sg:address":"Turgut Ozal Cad. Galvano Sit.a 15",
    "sg:city":"Ikitelli",
    "sg:classifiers":[
        {
            "category":"Food & Beverages",
            "subcategory":"Groceries & Convenience Stores",
            "type":"Retail Goods"
        }
    ],
    "sg:phone":"+90 212 549 1613",
    "sg:postcode":"34306",
    "sg:province":"Istanbul",
    "sg:tags":[
        "ready"
    ],
    "wof:name":"Bmt Ltd.",
    "wof:placetype":"venue"
},
  "geometry": {"coordinates":[28.7984962463,41.0884017944],"type":"Point"}
}