{
  "type": "Feature",
  "properties": {
    "iso:country":"TR",
    "sg:address":"Yeni Bursa Yolu Vezirciftligi No:157 Izmit",
    "sg:city":"Ikitelli/K\u00fc\u00e7\u00fck\u00e7ekmece",
    "sg:classifiers":[
        {
            "category":"Manufacturing",
            "subcategory":"Tools & Machinery",
            "type":"Manufacturing & Wholesale Goods"
        }
    ],
    "sg:phone":"+90 262 335 4993",
    "sg:postcode":"34670",
    "sg:province":"Kocaeli",
    "sg:tags":[
        "machine",
        "industry"
    ],
    "wof:name":"Tam Celik San.ltd.sti.",
    "wof:placetype":"venue"
},
  "geometry": {"coordinates":[29.881521225,40.8532714844],"type":"Point"}
}