{
  "type": "Feature",
  "properties": {
    "addr:full":"Birlik Sanayi Sitesi 4.cad.no:48 B\u00fcy\u00fck\u00e7ekmece Istanbul 34905",
    "addr:housenumber":"48",
    "addr:postcode":"34905",
    "addr:street":"Sitesi;Bueyuekc\u0327Ekmece Istanbul",
    "iso:country":"TR",
    "sg:address":"Birlik Sanayi Sitesi 4.cad.no:48",
    "sg:city":"B\u00fcy\u00fck\u00e7ekmece",
    "sg:orig_category":"Beylikd?z? Birlik Industrial Site",
    "sg:phone":"+90 212875039697",
    "sg:postcode":"34905",
    "sg:province":"Istanbul",
    "wof:name":"Universal Metal Pres Sanayi Veticaret",
    "wof:placetype":"venue"
},
  "geometry": {"coordinates":[28.808413,41.073933],"type":"Point"}
}