{
  "type": "Feature",
  "properties": {
    "addr:full":"Camlitepe Sok. No:51- Siteler Ankara 07070",
    "addr:housenumber":"no 51",
    "addr:postcode":"07070",
    "addr:street":"Camlitepe Sok.",
    "iso:country":"TR",
    "sg:address":"Camlitepe Sok. No:51-",
    "sg:city":"Siteler",
    "sg:classifiers":[
        {
            "category":"Manufacturing",
            "subcategory":"Glass & Minerals",
            "type":"Manufacturing & Wholesale Goods"
        }
    ],
    "sg:phone":"+90 312 353 6270",
    "sg:postcode":"07070",
    "sg:province":"Ankara",
    "sg:tags":[
        "glass-mirror"
    ],
    "wof:name":"As Isi Yalitim Cam San Ve Tic Ltd",
    "wof:placetype":"venue"
},
  "geometry": {"coordinates":[32.8888015747,39.9214630127],"type":"Point"}
}