{
  "type": "Feature",
  "properties": {
    "iso:country":"TR",
    "sg:address":"Kanalboyu Ipek Cad. No:3/a",
    "sg:city":"Erenkoy",
    "sg:classifiers":[
        {
            "category":"Farming",
            "subcategory":"Farm",
            "type":"Manufacturing & Wholesale Goods"
        }
    ],
    "sg:phone":"+90 422 321 1451",
    "sg:postcode":"07060",
    "sg:province":"Malatya",
    "sg:tags":[
        "agricultural",
        "product"
    ],
    "wof:name":"Planet Tic.",
    "wof:placetype":"venue"
},
  "geometry": {"coordinates":[38.3143005371,38.3474998474],"type":"Point"}
}