{
  "type": "Feature",
  "properties": {
    "addr:full":"Cevat Sakir Caddesi A.ayranci 48400 Ankara",
    "addr:postcode":"48400",
    "addr:street":"Sakir Caddesi A.Ayranci",
    "iso:country":"TR",
    "sg:address":"Cevat Sakir Caddesi",
    "sg:city":"A.ayranci",
    "sg:classifiers":[
        {
            "category":"Travel",
            "subcategory":"Travel Agent",
            "type":"Entertainment"
        }
    ],
    "sg:phone":"+90 252 316 3246",
    "sg:postcode":"Ankara",
    "sg:province":"48400",
    "sg:website":"gokin.tomurcuk@hapimag.com",
    "wof:name":"Boder - Bodrum Hotel Association",
    "wof:placetype":"venue"
},
  "geometry": {"coordinates":[27.491060257,37.0702705383],"type":"Point"}
}