{
  "type": "Feature",
  "properties": {
    "addr:full":"Rihtim Cd.sevket Bey Han No12/5 Kad\u0131k\u00f6y Istanbul 34990",
    "addr:postcode":"34990",
    "iso:country":"TR",
    "sg:address":"Rihtim Cd.sevket Bey Han No12/5",
    "sg:city":"Kad\u0131k\u00f6y",
    "sg:classifiers":[
        {
            "category":"Marine",
            "type":"Transportation"
        }
    ],
    "sg:phone":"+90 216 337 2681",
    "sg:postcode":"34990",
    "sg:province":"Istanbul",
    "sg:tags":[
        "shipowner"
    ],
    "wof:name":"Sel-ay Denizcilik Ltd.sti.",
    "wof:placetype":"venue"
},
  "geometry": {"coordinates":[27.49641,40.982037],"type":"Point"}
}