{
  "type": "Feature",
  "properties": {
    "iso:country":"TR",
    "sg:address":"35.sok. No:80/6 Bahcelievler",
    "sg:city":"Mersin",
    "sg:classifiers":[
        {
            "category":"Professional",
            "subcategory":"Business Services",
            "type":"Services"
        }
    ],
    "sg:phone":"+90 312 223 9683",
    "sg:postcode":"52750",
    "sg:province":"Ankara",
    "sg:tags":[
        "food",
        "product",
        "exporter",
        "aricultural"
    ],
    "wof:name":"Argiza Import & Export",
    "wof:placetype":"venue"
},
  "geometry": {"coordinates":[32.8194656372,39.9042701721],"type":"Point"}
}