{
  "type": "Feature",
  "properties": {
    "addr:full":"Karacaoren Koyu Kizilcahamam Taksim Ankara 24040",
    "addr:postcode":"24040",
    "iso:country":"TR",
    "sg:address":"Karacaoren Koyu Kizilcahamam",
    "sg:city":"Taksim",
    "sg:orig_category":"Hotels: Motels",
    "sg:phone":"+90 312 232 4820",
    "sg:postcode":"24040",
    "sg:province":"Ankara",
    "wof:name":"Ay-fidam",
    "wof:placetype":"venue"
},
  "geometry": {"coordinates":[32.8604812622,39.9429283142],"type":"Point"}
}