{
  "type": "Feature",
  "properties": {
    "addr:full":"Maresal F. ?akmak Cd. No:41 Maltepe Bah\u00e7elievler Istanbul 34180",
    "addr:housenumber":"no 41",
    "addr:postcode":"34180",
    "addr:street":"Akmak Cd.",
    "iso:country":"TR",
    "sg:address":"Maresal F. ?akmak Cd. No:41 Maltepe",
    "sg:city":"Bah\u00e7elievler",
    "sg:orig_category":"General Industrial Products",
    "sg:phone":"+90 216 441 2394",
    "sg:postcode":"34180",
    "sg:province":"Istanbul",
    "wof:name":"Kalip Takim San. A.s.",
    "wof:placetype":"venue"
},
  "geometry": {"coordinates":[32.829498291,39.9325561523],"type":"Point"}
}