{
  "type": "Feature",
  "properties": {
    "addr:full":"Izzettin ?. Cd. No:62 Bah?lievler \u00dcmraniye Istanbul",
    "addr:housenumber":"?;no 62;?",
    "addr:street":"Cd.;Bah",
    "iso:country":"TR",
    "sg:address":"Izzettin ?. Cd. No:62 Bah?lievler",
    "sg:city":"\u00dcmraniye",
    "sg:classifiers":[
        {
            "category":"Manufacturing",
            "subcategory":"Rubber & Plastics",
            "type":"Manufacturing & Wholesale Goods"
        }
    ],
    "sg:phone":"+90 212 587 0303",
    "sg:province":"Istanbul",
    "sg:tags":[
        "industry"
    ],
    "wof:name":"Isi G?z Al?minyum Plastik San.",
    "wof:placetype":"venue"
},
  "geometry": {"coordinates":[28.8701763153,40.999256134],"type":"Point"}
}