{
  "type": "Feature",
  "properties": {
    "addr:full":"Baglar Mah. Mehmet Akif Cad. No. 27 34540 G?esli Istanbul Zeytinburnu Istanbul 34020",
    "addr:housenumber":"27;g ?",
    "addr:postcode":"34540;34020",
    "addr:street":"Baglar Mah. Mehmet Akif Cad. No.",
    "iso:country":"TR",
    "sg:address":"Baglar Mah. Mehmet Akif Cad. No. 27 34540 G?esli Istanbul",
    "sg:city":"Zeytinburnu",
    "sg:classifiers":[
        {
            "category":"Shopping",
            "subcategory":"Clothing, Apparel, & Fashions",
            "type":"Retail Goods"
        }
    ],
    "sg:phone":"+90 212 656 2887",
    "sg:postcode":"34020",
    "sg:province":"Istanbul",
    "sg:tags":[
        "clothes"
    ],
    "wof:name":"Bensu Giyim San Ve Tic As",
    "wof:placetype":"venue"
},
  "geometry": {"coordinates":[28.9861831665,41.0408554077],"type":"Point"}
}