{
  "type": "Feature",
  "properties": {
    "iso:country":"TR",
    "sg:address":"Fulya Mah.mehmetcik Cd.esenler Sk.no22 D6 A Kapisi",
    "sg:city":"Mecidiyek\u00f6y",
    "sg:classifiers":[
        {
            "category":"Marine",
            "type":"Transportation"
        }
    ],
    "sg:phone":"+90 212 211 6463",
    "sg:postcode":"34387",
    "sg:province":"Istanbul",
    "sg:tags":[
        "shipowner"
    ],
    "wof:name":"Ileri Denizcilik San. A.s. .",
    "wof:placetype":"venue"
},
  "geometry": {"coordinates":[28.992159,41.072021],"type":"Point"}
}