{
  "type": "Feature",
  "properties": {
    "iso:country":"TR",
    "sg:address":"Afyon Sk. No:16 Beyoglu",
    "sg:city":"Bayrampasa",
    "sg:classifiers":[
        {
            "category":"Communications",
            "subcategory":"Film & Video Production",
            "type":"Services"
        }
    ],
    "sg:phone":"+90 212 244 7865",
    "sg:postcode":"36100",
    "sg:province":"Istanbul",
    "sg:tags":[
        "-"
    ],
    "wof:name":"Standart Video Filmcilik A.s.",
    "wof:placetype":"venue"
},
  "geometry": {"coordinates":[28.9805603027,41.0344009399],"type":"Point"}
}