{
  "type": "Feature",
  "properties": {
    "iso:country":"TR",
    "sg:address":"Asirefendi Cad. No:83",
    "sg:city":"Sultanhamam",
    "sg:classifiers":[
        {
            "category":"Shopping",
            "subcategory":"Crafts & Fabrics",
            "type":"Retail Goods"
        }
    ],
    "sg:phone":"+90 212 522 0387",
    "sg:province":"Istanbul",
    "sg:tags":[
        "weaving"
    ],
    "wof:name":"Akgur Kumas Tic.san. A.s.",
    "wof:placetype":"venue"
},
  "geometry": {"coordinates":[28.9716434479,41.0147972107],"type":"Point"}
}