{
  "type": "Feature",
  "properties": {
    "addr:full":"General S?r?sk. Karatli Cd. No:10/1 Bakirk? Gayrettepe Istanbul 34349",
    "addr:housenumber":"? r ?;no 10 / 1 bakirk ?",
    "addr:postcode":"34349",
    "addr:street":"General S;Sk. Karatli Cd.",
    "iso:country":"TR",
    "sg:address":"General S?r?sk. Karatli Cd. No:10/1 Bakirk?",
    "sg:city":"Gayrettepe",
    "sg:classifiers":[
        {
            "category":"Banks & Credit Unions",
            "subcategory":"Investment Brokerage",
            "type":"Services"
        }
    ],
    "sg:phone":"+90 212 572 6909",
    "sg:postcode":"34349",
    "sg:province":"Istanbul",
    "sg:tags":[
        "course",
        "language"
    ],
    "wof:name":"G?zen Dil Egitim Kursu",
    "wof:placetype":"venue"
},
  "geometry": {"coordinates":[29.0118026733,41.0541763306],"type":"Point"}
}