{
  "type": "Feature",
  "properties": {
    "iso:country":"TR",
    "sg:address":"Ankara Cd. Manolya Sk. No:14/16 Yayalar K??pendik",
    "sg:city":"Esenler",
    "sg:classifiers":[
        {
            "category":"Manufacturing",
            "subcategory":"Rubber & Plastics",
            "type":"Manufacturing & Wholesale Goods"
        }
    ],
    "sg:phone":"+90 216 307 2824",
    "sg:postcode":"01350",
    "sg:province":"Istanbul",
    "sg:tags":[
        "industry"
    ],
    "wof:name":"Gurbet?iler Plastik San. Tic. A.s.",
    "wof:placetype":"venue"
},
  "geometry": {"coordinates":[29.2699432373,40.8975563049],"type":"Point"}
}