{
  "type": "Feature",
  "properties": {
    "addr:full":"Eski Londra Asfalti No: 5 Gungoren 1.levent Besiktas Istanbul 80600",
    "addr:housenumber":"1.levent",
    "addr:postcode":"80600",
    "addr:street":"Eski Londra Asfalti No 5 Gungoren",
    "iso:country":"TR",
    "sg:address":"Eski Londra Asfalti No: 5 Gungoren",
    "sg:city":"1.levent Besiktas",
    "sg:classifiers":[
        {
            "category":"Manufacturing",
            "subcategory":"Building Materials",
            "type":"Manufacturing & Wholesale Goods"
        }
    ],
    "sg:phone":"+90 212 539 1084",
    "sg:postcode":"80600",
    "sg:province":"Istanbul",
    "sg:tags":[
        "promotional"
    ],
    "wof:name":"Scrikss Maden Ve Plastik San. A.s.",
    "wof:placetype":"venue"
},
  "geometry": {"coordinates":[28.8125934601,40.9978561401],"type":"Point"}
}