{
  "type": "Feature",
  "properties": {
    "addr:full":"Taskahve 12/2 Kemalpasa Izmir 01340",
    "addr:housenumber":"12 / 2",
    "addr:postcode":"01340",
    "addr:street":"Taskahve;Kemalpasa Izmir",
    "iso:country":"TR",
    "sg:address":"Taskahve 12/2",
    "sg:city":"Kemalpasa",
    "sg:classifiers":[
        {
            "category":"Shopping",
            "subcategory":"Clothing, Apparel, & Fashions",
            "type":"Retail Goods"
        }
    ],
    "sg:phone":"+90 232 878 8216",
    "sg:postcode":"01340",
    "sg:province":"Izmir",
    "sg:tags":[
        "ready",
        "wear"
    ],
    "wof:name":"Delta Giyim Sanayi Ltd.sti.",
    "wof:placetype":"venue"
},
  "geometry": {"coordinates":[29.0439529419,40.2035064697],"type":"Point"}
}