{
  "type": "Feature",
  "properties": {
    "addr:full":"Kartal Cad. Tevfik Fikret Sok. 2/3 Yakacik-kartal ?igli Istanbul 35580",
    "addr:housenumber":"2 / 3 yakacik-kartal ?",
    "addr:postcode":"35580",
    "addr:street":"Kartal Cad. Tevfik Fikret Sok.",
    "iso:country":"TR",
    "sg:address":"Kartal Cad. Tevfik Fikret Sok. 2/3 Yakacik-kartal",
    "sg:city":"?igli",
    "sg:classifiers":[
        {
            "category":"Shopping",
            "type":"Retail Goods"
        }
    ],
    "sg:phone":"+90 216 309 1946",
    "sg:postcode":"35580",
    "sg:province":"Istanbul",
    "sg:tags":[
        "material",
        "cleaning"
    ],
    "wof:name":"Taro Temizlik & Ambalaj",
    "wof:placetype":"venue"
},
  "geometry": {"coordinates":[28.9861831665,41.0408554077],"type":"Point"}
}