{
  "type": "Feature",
  "properties": {
    "addr:full":"Gurselpasa Mah. 47 Sok. No:8 Buca Adana 35390",
    "addr:housenumber":"no 8",
    "addr:postcode":"35390",
    "addr:street":"Gurselpasa Mah. 47 Sok.;Buca Adana",
    "iso:country":"TR",
    "sg:address":"Gurselpasa Mah. 47 Sok. No:8",
    "sg:city":"Buca",
    "sg:classifiers":[
        {
            "category":"Food & Beverages",
            "subcategory":"Meat & Fish",
            "type":"Retail Goods"
        }
    ],
    "sg:phone":"+90 322 261 1003",
    "sg:postcode":"35390",
    "sg:province":"Adana",
    "sg:tags":[
        "seafood"
    ],
    "wof:name":"Emsa Su Urunleri Pazarlama Ve Ithalat Tic. A.s.",
    "wof:placetype":"venue"
},
  "geometry": {"coordinates":[35.2833175659,37.0481567383],"type":"Point"}
}