{
  "type": "Feature",
  "properties": {
    "iso:country":"TR",
    "sg:address":"Rabat Sk.no:11 G.o.p.",
    "sg:city":"Boyobat",
    "sg:classifiers":[
        {
            "category":"Government",
            "subcategory":"Embassy",
            "type":"Public Place"
        }
    ],
    "sg:phone":"+90 312 437 6020",
    "sg:province":"Ankara",
    "sg:tags":[
        "foreign"
    ],
    "wof:name":"Fas Kralligi B?y?kelciligi",
    "wof:placetype":"venue"
},
  "geometry": {"coordinates":[32.8697433472,39.895275116],"type":"Point"}
}