{
  "type": "Feature",
  "properties": {
    "addr:full":"Cagaloglu Kozyatagi Istanbul 34742",
    "addr:postcode":"34742",
    "iso:country":"TR",
    "sg:address":"Cagaloglu",
    "sg:city":"Kozyatagi",
    "sg:classifiers":[
        {
            "category":"Shopping",
            "subcategory":"Crafts & Fabrics",
            "type":"Retail Goods"
        }
    ],
    "sg:phone":"+90 212 527 7912",
    "sg:postcode":"34742",
    "sg:province":"Istanbul",
    "sg:tags":[
        "yarn"
    ],
    "wof:name":"Altin Iplik Ltd.sti.",
    "wof:placetype":"venue"
},
  "geometry": {"coordinates":[28.975276947,41.0127792358],"type":"Point"}
}