{
  "type": "Feature",
  "properties": {
    "iso:country":"TR",
    "sg:address":"Hizirbey Mah. Sahil Cad.no:187/b",
    "sg:city":"Kadikoy",
    "sg:classifiers":[
        {
            "category":"Food & Beverages",
            "subcategory":"Groceries & Convenience Stores",
            "type":"Retail Goods"
        }
    ],
    "sg:phone":"+90 462 230 0854",
    "sg:postcode":"01370",
    "sg:province":"Trabzon",
    "sg:tags":[
        "ready"
    ],
    "wof:name":"Kinali Kardesler Gida Tic.san.ihr.ltd.sti.",
    "wof:placetype":"venue"
},
  "geometry": {"coordinates":[39.7124099731,41.0101470947],"type":"Point"}
}