{
  "type": "Feature",
  "properties": {
    "addr:full":"Mustafa Kemal Cad. No:126/d Bornova Ineg?l Izmir 16400",
    "addr:housenumber":"126 / d;ineg",
    "addr:postcode":"16400",
    "addr:street":"Mustafa Kemal Cad. No;L Izmir",
    "iso:country":"TR",
    "sg:address":"Mustafa Kemal Cad. No:126/d Bornova",
    "sg:city":"Ineg?l",
    "sg:classifiers":[
        {
            "category":"Home & Garden",
            "subcategory":"Kitchen Supply",
            "type":"Retail Goods"
        }
    ],
    "sg:phone":"+90 232 339 1698",
    "sg:postcode":"16400",
    "sg:province":"Izmir",
    "sg:tags":[
        "wardrobe"
    ],
    "wof:name":"Bakislar Mutfak Banyo",
    "wof:placetype":"venue"
},
  "geometry": {"coordinates":[27.2021389008,38.461101532],"type":"Point"}
}