{
  "type": "Feature",
  "properties": {
    "addr:full":"Babiali Cad. No:18/52 Cagaloglu Istanbul",
    "addr:housenumber":"18 / 52",
    "addr:street":"Babiali Cad. No",
    "iso:country":"TR",
    "sg:address":"Babiali Cad. No:18/52",
    "sg:city":"Cagaloglu",
    "sg:orig_category":"Carpet-kilim-blanket",
    "sg:phone":"+90 212 526 1828",
    "sg:province":"Istanbul",
    "wof:name":"Esin Turizm Pazarl. Ic Ve Dis Tic. Ltd. Sti.",
    "wof:placetype":"venue"
},
  "geometry": {"coordinates":[28.9861831665,41.0408554077],"type":"Point"}
}