{
  "type": "Feature",
  "properties": {
    "iso:country":"TR",
    "sg:address":"1038 Sk. No.71 Yesildere",
    "sg:city":"Laleli",
    "sg:classifiers":[
        {
            "category":"Shopping",
            "subcategory":"Luggage & Leather Goods",
            "type":"Retail Goods"
        }
    ],
    "sg:phone":"+90 232 433 5673",
    "sg:postcode":"24300",
    "sg:province":"Izmir",
    "sg:tags":[
        "leather-fur",
        "wear"
    ],
    "wof:name":"G?kova Deri San. A.s.",
    "wof:placetype":"venue"
},
  "geometry": {"coordinates":[27.1533298492,38.4091072083],"type":"Point"}
}