{
  "type": "Feature",
  "properties": {
    "iso:country":"TR",
    "sg:address":"Metropol Is Merkezi F Blok No:171",
    "sg:city":"Bayrampasa",
    "sg:classifiers":[
        {
            "category":"Communications",
            "subcategory":"Film & Video Production",
            "type":"Services"
        }
    ],
    "sg:phone":"+90 324 336 0030",
    "sg:postcode":"36100",
    "sg:province":"I?el",
    "sg:tags":[
        "-"
    ],
    "wof:name":"Radyo Metropol A.s.",
    "wof:placetype":"venue"
},
  "geometry": {"coordinates":[43.0778312683,40.5926704407],"type":"Point"}
}