{
  "type": "Feature",
  "properties": {
    "addr:full":"Kocman Cad. Polat Is Merkz. C-blok No:6 Gunesli Ist. Osmanbey Istanbul 63000",
    "addr:postcode":"63000",
    "addr:street":"Kocman Cad. Polat Is;C-Blok No 6 Gunesli",
    "iso:country":"TR",
    "sg:address":"Kocman Cad. Polat Is Merkz. C-blok No:6 Gunesli Ist.",
    "sg:city":"Osmanbey",
    "sg:classifiers":[
        {
            "category":"Home & Garden",
            "subcategory":"Home Furnishings",
            "type":"Retail Goods"
        }
    ],
    "sg:phone":"+90 212 651 9292",
    "sg:postcode":"63000",
    "sg:province":"Istanbul",
    "sg:tags":[
        "quilt",
        "bed"
    ],
    "wof:name":"Sabah Yatak Sanayi Ve Ticaret A.s.",
    "wof:placetype":"venue"
},
  "geometry": {"coordinates":[28.975925,41.012379],"type":"Point"}
}