{
  "type": "Feature",
  "properties": {
    "iso:country":"TR",
    "sg:address":"I?el",
    "sg:city":"Ikitelli/K\u00fc\u00e7\u00fck\u00e7ekmece",
    "sg:classifiers":[
        {
            "category":"Health Services",
            "subcategory":"Hospital",
            "type":"Services"
        }
    ],
    "sg:phone":"+90 324 714 1159",
    "sg:postcode":"34660",
    "sg:province":"I?el",
    "sg:tags":[
        "state"
    ],
    "wof:name":"Silifke Devlet Hastanesi",
    "wof:placetype":"venue"
},
  "geometry": {"coordinates":[-96.825279,37.775135],"type":"Point"}
}