{
  "type": "Feature",
  "properties": {
    "addr:full":"Ferit Selim Pasa Cad. 58/1 Bahcelievler Istanbul 01980",
    "addr:housenumber":"58 / 1",
    "addr:postcode":"01980",
    "addr:street":"Pasa Cad.",
    "iso:country":"TR",
    "sg:address":"Ferit Selim Pasa Cad. 58/1",
    "sg:city":"Bahcelievler",
    "sg:classifiers":[
        {
            "category":"Shopping",
            "subcategory":"Florist",
            "type":"Retail Goods"
        }
    ],
    "sg:phone":"+90 212 644 5850",
    "sg:postcode":"01980",
    "sg:province":"Istanbul",
    "sg:tags":[
        "flower"
    ],
    "wof:name":"?i?ekbank Uluslararasi ?i?ek?ilik",
    "wof:placetype":"venue"
},
  "geometry": {"coordinates":[28.8600463867,41.0104217529],"type":"Point"}
}