{
  "type": "Feature",
  "properties": {
    "addr:full":"Mithatpasa Cd. No: 34 Kizilay Ikitelli/K\u00fc\u00e7\u00fck\u00e7ekmece Ankara 34670",
    "addr:housenumber":"no 34",
    "addr:postcode":"34670",
    "addr:street":"Mithatpasa Cd.",
    "iso:country":"TR",
    "sg:address":"Mithatpasa Cd. No: 34 Kizilay",
    "sg:city":"Ikitelli/K\u00fc\u00e7\u00fck\u00e7ekmece",
    "sg:orig_category":"Printinh House",
    "sg:phone":"+90 312431601516",
    "sg:postcode":"34670",
    "sg:province":"Ankara",
    "wof:name":"Isik Bilgi Egitim Hizmetleri Yayinc.matba.ve Ins.tic.ltd.sti.",
    "wof:placetype":"venue"
},
  "geometry": {"coordinates":[32.857837677,39.9223251343],"type":"Point"}
}