{
  "type": "Feature",
  "properties": {
    "addr:full":"Hatboyu Cad. No:6/8/9 Bakirkoy Iskenderun Istanbul 31200",
    "addr:housenumber":"8 / 9",
    "addr:postcode":"31200",
    "addr:street":"Hatboyu Cad. No 6 /;Bakirkoy",
    "iso:country":"TR",
    "sg:address":"Hatboyu Cad. No:6/8/9 Bakirkoy",
    "sg:city":"Iskenderun",
    "sg:classifiers":[
        {
            "category":"Manufacturing",
            "subcategory":"Rubber & Plastics",
            "type":"Manufacturing & Wholesale Goods"
        }
    ],
    "sg:phone":"+90 212 572 9855",
    "sg:postcode":"31200",
    "sg:province":"Istanbul",
    "sg:tags":[
        "industry"
    ],
    "wof:name":"Ensa Plastik Ltd.sti.",
    "wof:placetype":"venue"
},
  "geometry": {"coordinates":[28.824300766,40.9622383118],"type":"Point"}
}