{
  "type": "Feature",
  "properties": {
    "addr:full":"Tuna Cad. No:18/5 Yenisiher 07100 Ankara",
    "addr:housenumber":"18 / 5",
    "addr:postcode":"07100",
    "addr:street":"Tuna Cad. No;Yenisiher",
    "iso:country":"TR",
    "sg:address":"Tuna Cad. No:18/5 Yenisiher",
    "sg:city":"07100",
    "sg:classifiers":[
        {
            "category":"Wholesale",
            "subcategory":"Medical Equipment & Supplies",
            "type":"Manufacturing & Wholesale Goods"
        }
    ],
    "sg:phone":"+90 312 435 8180",
    "sg:province":"Ankara",
    "sg:tags":[
        "material"
    ],
    "wof:name":"Genc Medikal Ltd. Sti.",
    "wof:placetype":"venue"
},
  "geometry": {"coordinates":[32.8604812622,39.9429283142],"type":"Point"}
}