{
  "type": "Feature",
  "properties": {
    "iso:country":"TR",
    "sg:address":"Nuri Pasa Mh. Bulv. Cd. No:132 Ag? Ishani Z.burnu",
    "sg:city":"Alsancak",
    "sg:classifiers":[
        {
            "category":"Professional",
            "subcategory":"Detective & Security Services",
            "type":"Services"
        }
    ],
    "sg:phone":"+90 212 582 6012",
    "sg:postcode":"35210",
    "sg:province":"Istanbul",
    "sg:tags":[
        "material"
    ],
    "wof:name":"Ges End. Elekt. Guvenlik Sistemleri",
    "wof:placetype":"venue"
},
  "geometry": {"coordinates":[28.975925,41.012379],"type":"Point"}
}