{
  "type": "Feature",
  "properties": {
    "addr:full":"Vefapoyraz Cad.no:46 Sisli Harbiye Istanbul 31080",
    "addr:housenumber":"46",
    "addr:postcode":"31080",
    "addr:street":"Sisli Harbiye",
    "iso:country":"TR",
    "sg:address":"Vefapoyraz Cad.no:46 Sisli",
    "sg:city":"Harbiye",
    "sg:classifiers":[
        {
            "category":"Shopping",
            "subcategory":"Party Supplies",
            "type":"Retail Goods"
        }
    ],
    "sg:phone":"+90 212 530 7848",
    "sg:postcode":"31080",
    "sg:province":"Istanbul",
    "sg:tags":[
        "sound",
        "light",
        "system"
    ],
    "wof:name":"Hippokrates Ogb-organizasyon Gelistirme Birimi",
    "wof:placetype":"venue"
},
  "geometry": {"coordinates":[28.9874916077,41.0705223083],"type":"Point"}
}