{
  "type": "Feature",
  "properties": {
    "addr:full":"Halil Rifat Pasa Mah. Teoman Sk. No.24 Okmeydani Istanbul 43050",
    "addr:postcode":"43050",
    "addr:street":"Halil Rifat Pasa Mah. Teoman Sk. No.24 Okmeydani",
    "iso:country":"TR",
    "sg:address":"Halil Rifat Pasa Mah. Teoman Sk. No.24",
    "sg:city":"Okmeydani",
    "sg:classifiers":[
        {
            "category":"Wholesale",
            "subcategory":"Machinery & Supplies",
            "type":"Manufacturing & Wholesale Goods"
        }
    ],
    "sg:phone":"+90 212 222 1522",
    "sg:postcode":"43050",
    "sg:province":"Istanbul",
    "sg:tags":[
        "agricultural"
    ],
    "wof:name":"Temtas Tarim Makinalari A.s.",
    "wof:placetype":"venue"
},
  "geometry": {"coordinates":[28.9759254456,41.0123786926],"type":"Point"}
}