{
  "type": "Feature",
  "properties": {
    "addr:full":"Kagizman Cad. No: 17 Dogubeyazit Agri 04900",
    "addr:housenumber":"17",
    "addr:postcode":"04900",
    "addr:street":"Kagizman Cad. No",
    "iso:country":"TR",
    "sg:address":"Kagizman Cad. No: 17",
    "sg:city":"Dogubeyazit",
    "sg:classifiers":[
        {
            "category":"Travel",
            "subcategory":"Travel Agent",
            "type":"Entertainment"
        }
    ],
    "sg:phone":"+90 472 215 1371",
    "sg:postcode":"04900",
    "sg:province":"Agri",
    "sg:tags":[
        "agency",
        "tourism"
    ],
    "wof:name":"Mefser Turizm",
    "wof:placetype":"venue"
},
  "geometry": {"coordinates":[43.0526733398,39.7331542969],"type":"Point"}
}