{
  "type": "Feature",
  "properties": {
    "addr:full":"B??dere Cd. No:84 Mecidiyek? Ikitelli Istanbul 34306",
    "addr:housenumber":"? ?;no 84;?",
    "addr:postcode":"34306",
    "addr:street":"B;Dere Cd.;Mecidiyek",
    "iso:country":"TR",
    "sg:address":"B??dere Cd. No:84 Mecidiyek?",
    "sg:city":"Ikitelli",
    "sg:classifiers":[
        {
            "category":"Farming",
            "subcategory":"Fish & Marine Products",
            "type":"Manufacturing & Wholesale Goods"
        }
    ],
    "sg:phone":"+90 212 266 0237",
    "sg:postcode":"34306",
    "sg:province":"Istanbul",
    "sg:tags":[
        "automotive"
    ],
    "wof:name":"Tasit San. A.s.",
    "wof:placetype":"venue"
},
  "geometry": {"coordinates":[28.99842453,41.0696411133],"type":"Point"}
}