{
  "type": "Feature",
  "properties": {
    "iso:country":"TR",
    "sg:address":"Ulucanlar Cad. No:88/12 Cebeci",
    "sg:city":"Merkez",
    "sg:classifiers":[
        {
            "category":"Wholesale",
            "subcategory":"Medical Equipment & Supplies",
            "type":"Manufacturing & Wholesale Goods"
        }
    ],
    "sg:phone":"+90 312 363 5359",
    "sg:postcode":"26000",
    "sg:province":"Ankara",
    "sg:tags":[
        "material"
    ],
    "wof:name":"Sevmed Medikal Ltd. Sti.",
    "wof:placetype":"venue"
},
  "geometry": {"coordinates":[32.8662567139,39.9359588623],"type":"Point"}
}