{
  "type": "Feature",
  "properties": {
    "iso:country":"TR",
    "sg:address":"Altinay Cd. No:8 Siteler",
    "sg:city":"Ikitelli/K\u00fc\u00e7\u00fck\u00e7ekmece",
    "sg:classifiers":[
        {
            "category":"Building & Trades",
            "subcategory":"Plumbing",
            "type":"Services"
        }
    ],
    "sg:phone":"+90 312 348 8942",
    "sg:postcode":"34670",
    "sg:province":"Ankara",
    "sg:tags":[
        "pipe",
        "industry"
    ],
    "wof:name":"Altinay Tic. Koll. Sti.",
    "wof:placetype":"venue"
},
  "geometry": {"coordinates":[32.902545929,39.9555282593],"type":"Point"}
}