{
  "type": "Feature",
  "properties": {
    "addr:full":"Imes Sanayi Sitesi C Blok 311.sok. No: 26 Y.dudullu Kazasker Istanbul",
    "addr:housenumber":"no 26",
    "iso:country":"TR",
    "sg:address":"Imes Sanayi Sitesi C Blok 311.sok. No: 26 Y.dudullu",
    "sg:city":"Kazasker",
    "sg:classifiers":[
        {
            "category":"Manufacturing",
            "subcategory":"Chemicals & Compounds",
            "type":"Manufacturing & Wholesale Goods"
        }
    ],
    "sg:phone":"+90 212 365 0709",
    "sg:province":"Istanbul",
    "sg:tags":[
        "pharmaceutical"
    ],
    "wof:name":"Ufuk Kimya Ilac San.tic.ltd.sti.",
    "wof:placetype":"venue"
},
  "geometry": {"coordinates":[28.9759254456,41.0123786926],"type":"Point"}
}