{
  "type": "Feature",
  "properties": {
    "iso:country":"TR",
    "sg:address":"Cumhuriyet Caddesi Pak Apt. 6,",
    "sg:city":"Elmadag",
    "sg:classifiers":[
        {
            "category":"Freight",
            "type":"Transportation"
        }
    ],
    "sg:phone":"+90 212 231 2844",
    "sg:postcode":"65900",
    "sg:province":"Istanbul",
    "sg:tags":[
        "cargo",
        "air"
    ],
    "wof:name":"Swissair",
    "wof:placetype":"venue"
},
  "geometry": {"coordinates":[28.9865493774,41.0424003601],"type":"Point"}
}