{
  "type": "Feature",
  "properties": {
    "iso:country":"TR",
    "sg:address":"Kurkculer Cad.y.dudullu",
    "sg:city":"Pinarbasi",
    "sg:classifiers":[
        {
            "category":"Farming",
            "subcategory":"Fish & Marine Products",
            "type":"Manufacturing & Wholesale Goods"
        }
    ],
    "sg:phone":"+90 2163136709729",
    "sg:postcode":"07630",
    "sg:province":"Istanbul",
    "sg:tags":[
        "automotive"
    ],
    "wof:name":"Kuralkan Motorlu Araclar A.s.",
    "wof:placetype":"venue"
},
  "geometry": {"coordinates":[29.1702098846,41.0106925964],"type":"Point"}
}