{
  "type": "Feature",
  "properties": {
    "iso:country":"TR",
    "sg:address":"San. B?ge. Sarik? G?en",
    "sg:city":"\u00dcmraniye",
    "sg:classifiers":[
        {
            "category":"Manufacturing",
            "subcategory":"Rubber & Plastics",
            "type":"Manufacturing & Wholesale Goods"
        }
    ],
    "sg:phone":"+90 266 774 1950",
    "sg:postcode":"81240",
    "sg:province":"Balikesir",
    "sg:tags":[
        "industry"
    ],
    "wof:name":"Tabakoglu Kau?uk San. Tic. A.s.",
    "wof:placetype":"venue"
},
  "geometry": {"coordinates":[27.8833007812,39.6520996094],"type":"Point"}
}