{
  "type": "Feature",
  "properties": {
    "addr:full":"Aksaray Cad. ?m?r Ishani. No: 4/501-502 K: 5 Laleli Istanbul 24300",
    "addr:housenumber":"?;501-502 k 5",
    "addr:postcode":"24300",
    "addr:street":"Aksaray Cad.;M;No 4 /",
    "iso:country":"TR",
    "sg:address":"Aksaray Cad. ?m?r Ishani. No: 4/501-502 K: 5",
    "sg:city":"Laleli",
    "sg:classifiers":[
        {
            "category":"Travel",
            "subcategory":"Travel Agent",
            "type":"Entertainment"
        }
    ],
    "sg:phone":"+90 6386431",
    "sg:postcode":"24300",
    "sg:province":"Istanbul",
    "sg:tags":[
        "agency",
        "tourism"
    ],
    "wof:name":"Cemsa Turizm",
    "wof:placetype":"venue"
},
  "geometry": {"coordinates":[28.9861831665,41.0408554077],"type":"Point"}
}