{
  "type": "Feature",
  "properties": {
    "addr:full":"Organize Sanayi Bolgesi 33060 Karaman",
    "addr:postcode":"33060",
    "addr:street":"Organize Sanayi Bolgesi",
    "iso:country":"TR",
    "sg:address":"Organize Sanayi Bolgesi",
    "sg:city":"33060",
    "sg:orig_category":"Dryfood-dried Nuts",
    "sg:phone":"+90 338 224 1081",
    "sg:province":"Karaman",
    "wof:name":"Duru Bulgur Gida San.tic. A.s.",
    "wof:placetype":"venue"
},
  "geometry": {"coordinates":[33.3437995911,36.9919395447],"type":"Point"}
}