{
  "type": "Feature",
  "properties": {
    "iso:country":"TR",
    "sg:address":"Hurmali Mah.2 Sok.no:9",
    "sg:city":"Alanya",
    "sg:classifiers":[
        {
            "category":"Building & Trades",
            "subcategory":"Locksmith",
            "type":"Services"
        }
    ],
    "sg:phone":"+90 322 435 2553",
    "sg:postcode":"07400",
    "sg:province":"Adana",
    "sg:tags":[
        "lock",
        "key"
    ],
    "wof:name":"Yale Dogan",
    "wof:placetype":"venue"
},
  "geometry": {"coordinates":[35.3360710144,36.9838447571],"type":"Point"}
}