{
  "type": "Feature",
  "properties": {
    "iso:country":"TR",
    "sg:address":"Seyit Nizam Mah.aksemsettin Tramvay Duragi Karsisi Ak Evler A-blok No:5-6",
    "sg:city":"Y.bosna",
    "sg:classifiers":[
        {
            "category":"Manufacturing",
            "subcategory":"Textiles",
            "type":"Manufacturing & Wholesale Goods"
        }
    ],
    "sg:phone":"+90 212 415 0305",
    "sg:province":"Istanbul",
    "sg:tags":[
        "chemical"
    ],
    "wof:name":"Arjen Tekstil San.tic.ltd.sti.",
    "wof:placetype":"venue"
},
  "geometry": {"coordinates":[28.910238266,41.048992157],"type":"Point"}
}