{
  "type": "Feature",
  "properties": {
    "addr:full":"129/6. Sk. Y. San. Sit. No:17 Sisli Izmir 65710",
    "addr:housenumber":"129 / 6;no 17",
    "addr:postcode":"65710",
    "addr:street":"Sk. Y. San. Sit.;Sisli Izmir",
    "iso:country":"TR",
    "sg:address":"129/6. Sk. Y. San. Sit. No:17",
    "sg:city":"Sisli",
    "sg:classifiers":[
        {
            "category":"Home & Garden",
            "subcategory":"Household Appliances",
            "type":"Retail Goods"
        }
    ],
    "sg:phone":"+90 232 374 4159",
    "sg:postcode":"65710",
    "sg:province":"Izmir",
    "sg:tags":[
        "conditioner",
        "air"
    ],
    "wof:name":"Isimsan M?h.san.tic.",
    "wof:placetype":"venue"
},
  "geometry": {"coordinates":[27.1296863556,38.4186973572],"type":"Point"}
}