{
  "type": "Feature",
  "properties": {
    "addr:full":"Yavuz Selim Mah. 4/10 Sok. No:14 Bagcilar Istanbul 33115",
    "addr:housenumber":"4 / 10;no 14",
    "addr:postcode":"33115",
    "addr:street":"Mah.;Sok.;Istanbul",
    "iso:country":"TR",
    "sg:address":"Yavuz Selim Mah. 4/10 Sok. No:14",
    "sg:city":"Bagcilar",
    "sg:classifiers":[
        {
            "category":"Government",
            "subcategory":"Fire Station",
            "type":"Public Place"
        }
    ],
    "sg:phone":"+90 212 656 5480",
    "sg:postcode":"33115",
    "sg:province":"Istanbul",
    "sg:tags":[
        "decoration"
    ],
    "wof:name":"Kaymakci Insaat Turizm San.ltd.sti.",
    "wof:placetype":"venue"
},
  "geometry": {"coordinates":[28.9861831665,41.0408554077],"type":"Point"}
}