{
  "type": "Feature",
  "properties": {
    "addr:full":"Alp Mh. 58. Bulvari No:55 Zeytinburnu Karak\u00f6y Istanbul 80030",
    "addr:housenumber":"58 bulvari no 55",
    "addr:postcode":"80030",
    "addr:street":"Mh.",
    "iso:country":"TR",
    "sg:address":"Alp Mh. 58. Bulvari No:55 Zeytinburnu",
    "sg:city":"Karak\u00f6y",
    "sg:classifiers":[
        {
            "category":"Mining & Drilling",
            "type":"Manufacturing & Wholesale Goods"
        }
    ],
    "sg:phone":"+90 212 582 4652",
    "sg:postcode":"80030",
    "sg:province":"Istanbul",
    "sg:tags":[
        "industry",
        "mine"
    ],
    "wof:name":"Ak?a K?m?r San. Tic. Ltd. Sti.",
    "wof:placetype":"venue"
},
  "geometry": {"coordinates":[28.9759254456,41.0123786926],"type":"Point"}
}