{
  "type": "Feature",
  "properties": {
    "iso:country":"TR",
    "sg:address":"Karagoz Caddesi No:23 Fevzi Cakmak Blv. No:124 27010",
    "sg:city":"?aglayan",
    "sg:classifiers":[
        {
            "category":"Shopping",
            "subcategory":"Stationery & Office Supplies",
            "type":"Retail Goods"
        }
    ],
    "sg:phone":"+90 342 231 1128",
    "sg:postcode":"80340",
    "sg:province":"Gaziantep",
    "sg:tags":[
        "furniture"
    ],
    "wof:name":"Mobel Mobilya Sanayi Ve Ticaret.",
    "wof:placetype":"venue"
},
  "geometry": {"coordinates":[37.3428726196,37.0847587585],"type":"Point"}
}