{
  "type": "Feature",
  "properties": {
    "addr:full":"Istiklal C.m?yyet Sk. Beyoglu \u00c7orlu Istanbul",
    "addr:street":"Yyet Sk. Beyoglu",
    "iso:country":"TR",
    "sg:address":"Istiklal C.m?yyet Sk. Beyoglu",
    "sg:city":"\u00c7orlu",
    "sg:classifiers":[
        {
            "category":"Shopping",
            "subcategory":"Luggage & Leather Goods",
            "type":"Retail Goods"
        }
    ],
    "sg:phone":"+90 212 293 9980",
    "sg:province":"Istanbul",
    "sg:tags":[
        "leather-fur",
        "wear"
    ],
    "wof:name":"?mit K?rk. San. A.s.",
    "wof:placetype":"venue"
},
  "geometry": {"coordinates":[28.9673175812,41.0431060791],"type":"Point"}
}