{
  "type": "Feature",
  "properties": {
    "addr:full":"Otogar Cad.no: 5 Antakya Hatay 31000",
    "addr:housenumber":"5",
    "addr:postcode":"31000",
    "addr:street":"Cad.No",
    "iso:country":"TR",
    "sg:address":"Otogar Cad.no: 5",
    "sg:city":"Antakya",
    "sg:classifiers":[
        {
            "category":"Farming",
            "subcategory":"Farm & Veterinary Services",
            "type":"Manufacturing & Wholesale Goods"
        }
    ],
    "sg:phone":"+90 326 215 4159",
    "sg:postcode":"31000",
    "sg:province":"Hatay",
    "sg:tags":[
        "veterinarian"
    ],
    "wof:name":"Mehmet Yolcu",
    "wof:placetype":"venue"
},
  "geometry": {"coordinates":[36.1653785706,36.2062568665],"type":"Point"}
}