{
  "type": "Feature",
  "properties": {
    "iso:country":"TR",
    "sg:address":"Dr.mediha Eldem Sok. No 40",
    "sg:city":"Cankaya",
    "sg:orig_category":"Hotels: Motels",
    "sg:phone":"+90 312 435 5110",
    "sg:postcode":"07080",
    "sg:province":"Ankara",
    "wof:name":"Hotel Evkuran",
    "wof:placetype":"venue"
},
  "geometry": {"coordinates":[32.8593597412,39.9209747314],"type":"Point"}
}