{
  "type": "Feature",
  "properties": {
    "addr:full":"Organize Sanayi Bolgesi Organize Cad. Altindag ?orum 06070",
    "addr:housenumber":"altindag ?",
    "addr:postcode":"06070",
    "addr:street":"Organize Sanayi Bolgesi Organize Cad.",
    "iso:country":"TR",
    "sg:address":"Organize Sanayi Bolgesi Organize Cad.",
    "sg:city":"Altindag",
    "sg:classifiers":[
        {
            "category":"Autos & Motor Vehicles",
            "subcategory":"Auto Supplies",
            "type":"Retail Goods"
        }
    ],
    "sg:phone":"+90 364254954952",
    "sg:postcode":"06070",
    "sg:province":"?orum",
    "sg:tags":[
        "accessory"
    ],
    "wof:name":"Erksan Oto Radyat?r San. Ve Tic.ltd.sti.",
    "wof:placetype":"venue"
},
  "geometry": {"coordinates":[32.8532714844,39.929309845],"type":"Point"}
}