{
  "type": "Feature",
  "properties": {
    "iso:country":"TR",
    "sg:address":"Ahmet Mithat Efendi Cd. No:13",
    "sg:city":"Sirkeci",
    "sg:classifiers":[
        {
            "category":"Transit Center",
            "subcategory":"Freight",
            "type":"Transportation"
        }
    ],
    "sg:phone":"+90 212 337 1847",
    "sg:postcode":"34112",
    "sg:province":"Istanbul",
    "wof:name":"Kaptan Denizcilik A.s.",
    "wof:placetype":"venue"
},
  "geometry": {"coordinates":[28.9727325439,41.015537262],"type":"Point"}
}