{
  "type": "Feature",
  "properties": {
    "addr:full":"Des San Sit. 1.cad.d:04 Blok No:7 Dudullu Istanbul",
    "addr:housenumber":"1.cad.d 04 blok no 7",
    "addr:street":"Des San Sit.",
    "iso:country":"TR",
    "sg:address":"Des San Sit. 1.cad.d:04 Blok No:7",
    "sg:city":"Dudullu",
    "sg:classifiers":[
        {
            "category":"Farming",
            "subcategory":"Poultry Farm",
            "type":"Manufacturing & Wholesale Goods"
        }
    ],
    "sg:phone":"+90 216 365 5716",
    "sg:province":"Istanbul",
    "sg:tags":[
        "poultry-turkey-ostrich"
    ],
    "wof:name":"Doga Pilic Ve Gida San.tic.ltd.sti",
    "wof:placetype":"venue"
},
  "geometry": {"coordinates":[28.9759254456,41.0123786926],"type":"Point"}
}