{
  "type": "Feature",
  "properties": {
    "addr:full":"?sk? Cad. 24/9 Cankaya Fatih Ankara 01740",
    "addr:housenumber":"24 / 9",
    "addr:postcode":"?;01740",
    "addr:street":"Cad.",
    "iso:country":"TR",
    "sg:address":"?sk? Cad. 24/9 Cankaya",
    "sg:city":"Fatih",
    "sg:classifiers":[
        {
            "category":"Building & Trades",
            "subcategory":"Construction",
            "type":"Services"
        }
    ],
    "sg:phone":"+90 312 468 1525",
    "sg:postcode":"01740",
    "sg:province":"Ankara",
    "sg:tags":[
        "foundation"
    ],
    "wof:name":"Mesleki Egitim Ve Kucuk San. Dest. Vakfi",
    "wof:placetype":"venue"
},
  "geometry": {"coordinates":[29.2591190338,40.9095230103],"type":"Point"}
}