{
  "type": "Feature",
  "properties": {
    "iso:country":"TR",
    "sg:address":"Uluyol Siteler Cad.7.blok No:7 Bayrampasa",
    "sg:city":"Ikitelli",
    "sg:classifiers":[
        {
            "category":"Shopping",
            "subcategory":"Shoes",
            "type":"Retail Goods"
        }
    ],
    "sg:phone":"+90 212 563 1783",
    "sg:postcode":"34306",
    "sg:province":"Istanbul",
    "wof:name":"Haznedar Ayakkabi Ve Deri ?r?nleri A.s",
    "wof:placetype":"venue"
},
  "geometry": {"coordinates":[28.909605,41.030766],"type":"Point"}
}