{
  "type": "Feature",
  "properties": {
    "iso:country":"TR",
    "sg:address":"Kariye Mh. Nester Sk. No:60/a",
    "sg:city":"Edirnekapi",
    "sg:classifiers":[
        {
            "category":"Home & Garden",
            "subcategory":"Household Appliances",
            "type":"Retail Goods"
        }
    ],
    "sg:phone":"+90 212 632 7626",
    "sg:province":"Istanbul",
    "sg:tags":[
        "conditioner",
        "air"
    ],
    "wof:name":"Alser Isi. Sog. San.",
    "wof:placetype":"venue"
},
  "geometry": {"coordinates":[28.9389419556,41.0304031372],"type":"Point"}
}