{
  "type": "Feature",
  "properties": {
    "iso:country":"TR",
    "sg:address":"Fatih Cad.",
    "sg:city":"Merter",
    "sg:classifiers":[
        {
            "category":"Manufacturing",
            "subcategory":"Textiles",
            "type":"Manufacturing & Wholesale Goods"
        }
    ],
    "sg:phone":"+90 212 637 3434",
    "sg:province":"Istanbul",
    "sg:tags":[
        "machinery"
    ],
    "wof:name":"Astas Endustri Tekstil Mak.a.s.",
    "wof:placetype":"venue"
},
  "geometry": {"coordinates":[28.7225952148,40.979309082],"type":"Point"}
}