{
  "type": "Feature",
  "properties": {
    "iso:country":"TR",
    "sg:address":"Arifaga Sk. No:14/2 Y.bosna",
    "sg:city":"Karak?y",
    "sg:classifiers":[
        {
            "category":"Wholesale",
            "subcategory":"Machinery & Supplies",
            "type":"Manufacturing & Wholesale Goods"
        }
    ],
    "sg:phone":"+90 212 550 7716",
    "sg:postcode":"-",
    "sg:province":"Istanbul",
    "sg:tags":[
        "bearing",
        "ball"
    ],
    "wof:name":"Rultas Rulman San. Tic. Ltd. Sti.",
    "wof:placetype":"venue"
},
  "geometry": {"coordinates":[28.822306,41.018517],"type":"Point"}
}