{
  "type": "Feature",
  "properties": {
    "addr:full":"Kiztasi Cad.no:1/2 Fatih Ikitelli/K\u00fc\u00e7\u00fck\u00e7ekmece Istanbul 34670",
    "addr:housenumber":"1 / 2",
    "addr:postcode":"34670",
    "addr:street":"Cad.No;Fatih Ikitelli / Kuec\u0327Uekc\u0327Ekmece",
    "iso:country":"TR",
    "sg:address":"Kiztasi Cad.no:1/2 Fatih",
    "sg:city":"Ikitelli/K\u00fc\u00e7\u00fck\u00e7ekmece",
    "sg:classifiers":[
        {
            "category":"Health Services",
            "subcategory":"Dentist",
            "type":"Services"
        }
    ],
    "sg:phone":"+90 212 521 1351",
    "sg:postcode":"34670",
    "sg:province":"Istanbul",
    "sg:tags":[
        "dental",
        "material"
    ],
    "wof:name":"Pormed San.tic.ltd.sti.",
    "wof:placetype":"venue"
},
  "geometry": {"coordinates":[28.9861831665,41.0408554077],"type":"Point"}
}