{
  "type": "Feature",
  "properties": {
    "iso:country":"TR",
    "sg:address":"Keresteciler Sit 790 Sok No 11",
    "sg:city":"24000",
    "sg:classifiers":[
        {
            "category":"Manufacturing",
            "subcategory":"Wood Products",
            "type":"Manufacturing & Wholesale Goods"
        }
    ],
    "sg:phone":"+90 446 214 6349",
    "sg:province":"Erzincan",
    "sg:tags":[
        "forest"
    ],
    "wof:name":"Dasstan Ticaret",
    "wof:placetype":"venue"
},
  "geometry": {"coordinates":[39.4905014038,39.7491989136],"type":"Point"}
}