{
  "type": "Feature",
  "properties": {
    "addr:full":"Sarimsakli/ Ayvalik Balikesir 01680",
    "addr:postcode":"01680",
    "addr:street":"Balikesir",
    "iso:country":"TR",
    "sg:address":"Sarimsakli/",
    "sg:city":"Ayvalik",
    "sg:orig_category":"Hotels: Motels",
    "sg:phone":"+90 266 324 1048",
    "sg:postcode":"01680",
    "sg:province":"Balikesir",
    "wof:name":"Ankar Oteli",
    "wof:placetype":"venue"
},
  "geometry": {"coordinates":[27.8853626251,39.6448822021],"type":"Point"}
}