{
  "type": "Feature",
  "properties": {
    "addr:full":"Hirkai Serif Cad. 9/2 Fatih Findikzade Istanbul 34270",
    "addr:housenumber":"9 / 2",
    "addr:postcode":"34270",
    "addr:street":"Serif Cad.;Fatih",
    "iso:country":"TR",
    "sg:address":"Hirkai Serif Cad. 9/2 Fatih",
    "sg:city":"Findikzade",
    "sg:classifiers":[
        {
            "category":"Wholesale",
            "subcategory":"Medical Equipment & Supplies",
            "type":"Manufacturing & Wholesale Goods"
        }
    ],
    "sg:phone":"+90 212 585 5171",
    "sg:postcode":"34270",
    "sg:province":"Istanbul",
    "wof:name":"Azer Ith. Ihr. Paz. Ltd.",
    "wof:placetype":"venue"
},
  "geometry": {"coordinates":[28.9861831665,41.0408554077],"type":"Point"}
}