{
  "type": "Feature",
  "properties": {
    "iso:country":"TR",
    "sg:address":"Yenimahalle 45",
    "sg:city":"Bayrampasa",
    "sg:classifiers":[
        {
            "category":"Banks & Credit Unions",
            "subcategory":"Bank",
            "type":"Services"
        }
    ],
    "sg:phone":"+90 312 385 5410",
    "sg:postcode":"36100",
    "sg:province":"Ostim",
    "wof:name":"Toprakbank As",
    "wof:placetype":"venue"
},
  "geometry": {"coordinates":[32.748398,39.973225],"type":"Point"}
}