{
  "type": "Feature",
  "properties": {
    "addr:full":"Karatay San. ?elik Sk. No:57 \u00dcmraniye Konya",
    "addr:street":"Elik Sk. No 57",
    "iso:country":"TR",
    "sg:address":"Karatay San. ?elik Sk. No:57",
    "sg:city":"\u00dcmraniye",
    "sg:orig_category":"General Industrial Products",
    "sg:phone":"+90 332 233 7414",
    "sg:province":"Konya",
    "wof:name":"Duysak Otomotiv San. Tic. A.s.",
    "wof:placetype":"venue"
},
  "geometry": {"coordinates":[32.4990272522,37.8715362549],"type":"Point"}
}