{
  "type": "Feature",
  "properties": {
    "addr:full":"Ataturk Cad. No: 88/b Mersin Eskisehir 52750",
    "addr:housenumber":"88 / b",
    "addr:postcode":"52750",
    "addr:street":"Ataturk Cad. No",
    "iso:country":"TR",
    "sg:address":"Ataturk Cad. No: 88/b",
    "sg:city":"Mersin",
    "sg:classifiers":[
        {
            "category":"Home & Garden",
            "subcategory":"Building Materials",
            "type":"Retail Goods"
        }
    ],
    "sg:phone":"+90 222 231 5972",
    "sg:postcode":"52750",
    "sg:province":"Eskisehir",
    "sg:tags":[
        "stone",
        "natural",
        "marble"
    ],
    "wof:name":"Eskisehir Ay Mermer San.tic.ltd.sti.",
    "wof:placetype":"venue"
},
  "geometry": {"coordinates":[30.5154705048,39.7782936096],"type":"Point"}
}