{
  "type": "Feature",
  "properties": {
    "addr:full":"Oba Apt. K:2 Osmanbey Babadag Istanbul 20480",
    "addr:housenumber":"2",
    "addr:postcode":"20480",
    "addr:street":"Osmanbey",
    "iso:country":"TR",
    "sg:address":"Oba Apt. K:2 Osmanbey",
    "sg:city":"Babadag",
    "sg:classifiers":[
        {
            "category":"Shopping",
            "subcategory":"Crafts & Fabrics",
            "type":"Retail Goods"
        }
    ],
    "sg:phone":"+90 212 246 0074",
    "sg:postcode":"20480",
    "sg:province":"Istanbul",
    "sg:tags":[
        "weaving"
    ],
    "wof:name":"Ozbucak Sanayi Tic.a.s.",
    "wof:placetype":"venue"
},
  "geometry": {"coordinates":[28.984336853,41.0317001343],"type":"Point"}
}