{
  "type": "Feature",
  "properties": {
    "iso:country":"TR",
    "sg:address":"Sivas",
    "sg:city":"Findikzade",
    "sg:classifiers":[
        {
            "category":"Wholesale",
            "subcategory":"Medical Equipment & Supplies",
            "type":"Manufacturing & Wholesale Goods"
        }
    ],
    "sg:phone":"+90 346 227 2666",
    "sg:postcode":"34270",
    "sg:province":"Sivas",
    "wof:name":"Baysa Medikal",
    "wof:placetype":"venue"
},
  "geometry": {"coordinates":[36.0735740662,39.1077384949],"type":"Point"}
}