{
  "type": "Feature",
  "properties": {
    "addr:full":"Nispetiye Cad.no 40/8 Levent 34340 - Besiktas ?nye Istanbul 52300",
    "addr:housenumber":"40 / 8",
    "addr:postcode":"34340;?;52300",
    "iso:country":"TR",
    "sg:address":"Nispetiye Cad.no 40/8 Levent 34340 - Besiktas",
    "sg:city":"?nye",
    "sg:classifiers":[
        {
            "category":"Health Services",
            "subcategory":"Clinic",
            "type":"Services"
        }
    ],
    "sg:phone":"+90 212 283 0333",
    "sg:postcode":"52300",
    "sg:province":"Istanbul",
    "wof:name":"Acibadem Etiler Poliklinigi",
    "wof:placetype":"venue"
},
  "geometry": {"coordinates":[28.9861831665,41.0408554077],"type":"Point"}
}