{
  "type": "Feature",
  "properties": {
    "addr:full":"San. Mh. S. Selim Cd. Sahinler Sk. No.17/a 4. Levent Kartal Istanbul 46000",
    "addr:housenumber":"4",
    "addr:postcode":"46000",
    "addr:street":"Selim Cd. Sahinler Sk. No.17 / A",
    "iso:country":"TR",
    "sg:address":"San. Mh. S. Selim Cd. Sahinler Sk. No.17/a 4. Levent",
    "sg:city":"Kartal",
    "sg:classifiers":[
        {
            "category":"Shopping",
            "subcategory":"Stationery & Office Supplies",
            "type":"Retail Goods"
        }
    ],
    "sg:phone":"+90 212 278 6550",
    "sg:postcode":"46000",
    "sg:province":"Istanbul",
    "sg:tags":[
        "furniture"
    ],
    "wof:name":"Atalanlar Orman Urn. Paz. Mob. Dek. San.",
    "wof:placetype":"venue"
},
  "geometry": {"coordinates":[28.9811306,41.0765838623],"type":"Point"}
}