{
  "type": "Feature",
  "properties": {
    "addr:full":"Akdeniz San. Sit. 5033 Sk. No.39 \u00dcmraniye Antalya 34500",
    "addr:postcode":"34500",
    "addr:street":"5033 Sk. No.39",
    "iso:country":"TR",
    "sg:address":"Akdeniz San. Sit. 5033 Sk. No.39",
    "sg:city":"\u00dcmraniye",
    "sg:classifiers":[
        {
            "category":"Home & Garden",
            "subcategory":"Kitchen Supply",
            "type":"Retail Goods"
        }
    ],
    "sg:phone":"+90 242 221 2343",
    "sg:postcode":"34500",
    "sg:province":"Antalya",
    "sg:tags":[
        "wardrobe"
    ],
    "wof:name":"Momdesan",
    "wof:placetype":"venue"
},
  "geometry": {"coordinates":[30.7031345367,36.8875045776],"type":"Point"}
}