{
  "type": "Feature",
  "properties": {
    "addr:full":"Ataturk Cd.cemak Ish. K:4 No:36 Kazanli I?el 33281",
    "addr:housenumber":"4 no 36;?",
    "addr:postcode":"33281",
    "addr:street":"Ish. K;I;El",
    "iso:country":"TR",
    "sg:address":"Ataturk Cd.cemak Ish. K:4 No:36",
    "sg:city":"Kazanli",
    "sg:classifiers":[
        {
            "category":"Food & Beverages",
            "subcategory":"Fruits & Vegetables",
            "type":"Retail Goods"
        }
    ],
    "sg:phone":"+90 324 233 6150",
    "sg:postcode":"33281",
    "sg:province":"I?el",
    "sg:tags":[
        "fresh"
    ],
    "wof:name":"Duran Naranciye Ltd.sti.",
    "wof:placetype":"venue"
},
  "geometry": {"coordinates":[33.8587112427,36.7328910828],"type":"Point"}
}