{
  "type": "Feature",
  "properties": {
    "iso:country":"TR",
    "sg:address":"Cebeci Yolu 594. Sk. No:29 K??k?",
    "sg:city":"Kartal",
    "sg:classifiers":[
        {
            "category":"Farming",
            "subcategory":"Fish & Marine Products",
            "type":"Manufacturing & Wholesale Goods"
        }
    ],
    "sg:phone":"+90 212 537 8023",
    "sg:postcode":"46000",
    "sg:province":"Istanbul",
    "sg:tags":[
        "automotive"
    ],
    "wof:name":"Roteks Otomotiv San. Tic. A.s.",
    "wof:placetype":"venue"
},
  "geometry": {"coordinates":[28.9019126892,41.0773429871],"type":"Point"}
}