{
  "type": "Feature",
  "properties": {
    "addr:full":"Tiyatro Cad. E.k. Cami Sok. No:8 Deri Is Merkz. Beyazit Istanbul 65400",
    "addr:housenumber":"no",
    "addr:postcode":"65400",
    "addr:street":"Tiyatro Cad. E.K. Cami Sok.",
    "iso:country":"TR",
    "sg:address":"Tiyatro Cad. E.k. Cami Sok. No:8 Deri Is Merkz.",
    "sg:city":"Beyazit",
    "sg:classifiers":[
        {
            "category":"Manufacturing",
            "subcategory":"Leather Goods",
            "type":"Manufacturing & Wholesale Goods"
        }
    ],
    "sg:phone":"+90 212 592 8406",
    "sg:postcode":"65400",
    "sg:province":"Istanbul",
    "wof:name":"Lapassione Deri Ve Canta",
    "wof:placetype":"venue"
},
  "geometry": {"coordinates":[28.9759254456,41.0123786926],"type":"Point"}
}