{
  "type": "Feature",
  "properties": {
    "addr:full":"G?sel Mah. Campark Sok. No:1/a Kagithane Istanbul 34406",
    "addr:housenumber":"no 1 / a",
    "addr:postcode":"34406",
    "addr:street":"Mah. Campark Sok.",
    "iso:country":"TR",
    "sg:address":"G?sel Mah. Campark Sok. No:1/a",
    "sg:city":"Kagithane",
    "sg:classifiers":[
        {
            "category":"Manufacturing",
            "subcategory":"Glass & Minerals",
            "type":"Manufacturing & Wholesale Goods"
        }
    ],
    "sg:phone":"+90 212 220 6490",
    "sg:postcode":"34406",
    "sg:province":"Istanbul",
    "sg:tags":[
        "glass-mirror"
    ],
    "wof:name":"Birlik Cam Buzlama Ve Insaat San.tic. Ltd.sti.",
    "wof:placetype":"venue"
},
  "geometry": {"coordinates":[28.9681472778,41.0811843872],"type":"Point"}
}