{
  "type": "Feature",
  "properties": {
    "addr:full":"Yeni Camlica Mah. Yedpa Tic. Merkz. D Cad. No:147/148 Umraniye Bornova Istanbul 35090",
    "addr:housenumber":"147 / 148",
    "addr:postcode":"35090",
    "addr:street":"Camlica Mah. Yedpa;D Cad. No;Umraniye",
    "iso:country":"TR",
    "sg:address":"Yeni Camlica Mah. Yedpa Tic. Merkz. D Cad. No:147/148 Umraniye",
    "sg:city":"Bornova",
    "sg:classifiers":[
        {
            "category":"Wholesale",
            "subcategory":"Auto Parts",
            "type":"Manufacturing & Wholesale Goods"
        }
    ],
    "sg:phone":"+90 216 471 1014",
    "sg:postcode":"35090",
    "sg:province":"Istanbul",
    "sg:tags":[
        "spare"
    ],
    "wof:name":"?z-is Oto Yan Sanayii Tic. Ltd.sti.",
    "wof:placetype":"venue"
},
  "geometry": {"coordinates":[28.9861831665,41.0408554077],"type":"Point"}
}