{
  "type": "Feature",
  "properties": {
    "addr:full":"Organize Sanayi B?gesi 1.cad. 1.sok. 5/c Ikitelli/K\u00fc\u00e7\u00fck\u00e7ekmece Aksaray 34670",
    "addr:housenumber":"?;5 / c ikitelli",
    "addr:postcode":"34670",
    "addr:street":"Organize Sanayi B;Aksaray",
    "iso:country":"TR",
    "sg:address":"Organize Sanayi B?gesi 1.cad. 1.sok. 5/c",
    "sg:city":"Ikitelli/K\u00fc\u00e7\u00fck\u00e7ekmece",
    "sg:classifiers":[
        {
            "category":"Building & Trades",
            "subcategory":"Construction",
            "type":"Services"
        }
    ],
    "sg:phone":"+90 382 266 2108",
    "sg:postcode":"34670",
    "sg:province":"Aksaray",
    "sg:tags":[
        "industry",
        "mold"
    ],
    "wof:name":"Polikalip Kalipcilik Metal San.tic.ltd.sti.",
    "wof:placetype":"venue"
},
  "geometry": {"coordinates":[34.0284004211,38.3745994568],"type":"Point"}
}