{
  "type": "Feature",
  "properties": {
    "addr:full":"Konya Yolu Cevizlidere Mh. 3. Sk. No:15 Balgat \u00dcmraniye Ankara",
    "addr:housenumber":"cevizlidere mh. 3;15",
    "addr:street":"Konya Yolu;Sk. No",
    "iso:country":"TR",
    "sg:address":"Konya Yolu Cevizlidere Mh. 3. Sk. No:15 Balgat",
    "sg:city":"\u00dcmraniye",
    "sg:classifiers":[
        {
            "category":"Manufacturing",
            "subcategory":"Tools & Machinery",
            "type":"Manufacturing & Wholesale Goods"
        }
    ],
    "sg:phone":"+90 312 286 7761",
    "sg:province":"Ankara",
    "sg:tags":[
        "machine",
        "industry"
    ],
    "wof:name":"Ko?aklar Hidrolik Mak. San.",
    "wof:placetype":"venue"
},
  "geometry": {"coordinates":[32.8183670044,39.9107475281],"type":"Point"}
}