{
  "type": "Feature",
  "properties": {
    "addr:full":"Piri Mehmet Pasa Mah.mis Sok.altinkoc Pasaji No:11/10 Silivri 4.levent Istanbul",
    "addr:housenumber":"10",
    "addr:street":"No 11 /",
    "iso:country":"TR",
    "sg:address":"Piri Mehmet Pasa Mah.mis Sok.altinkoc Pasaji No:11/10 Silivri",
    "sg:city":"4.levent",
    "sg:orig_category":"Printinh House",
    "sg:phone":"+90 212 727 1176",
    "sg:province":"Istanbul",
    "wof:name":"Bek-is Matbaacilik Reklamcilik Tur.san.tic.ltd.sti.",
    "wof:placetype":"venue"
},
  "geometry": {"coordinates":[28.2486991882,41.0741996765],"type":"Point"}
}