{
  "type": "Feature",
  "properties": {
    "addr:full":"Mahmutbey Haci Bostan Cad. No:7 Bagcilar Istanbul 34550",
    "addr:postcode":"34550",
    "addr:street":"Bostan Cad. No 7 Bagcilar",
    "iso:country":"TR",
    "sg:address":"Mahmutbey Haci Bostan Cad. No:7",
    "sg:city":"Bagcilar",
    "sg:classifiers":[
        {
            "category":"Building & Trades",
            "subcategory":"Locksmith",
            "type":"Services"
        }
    ],
    "sg:phone":"+90 212 445 0365",
    "sg:postcode":"34550",
    "sg:province":"Istanbul",
    "sg:tags":[
        "lock",
        "key"
    ],
    "wof:name":"Guler Anahtar Ve Kilit San.koll.sti.",
    "wof:placetype":"venue"
},
  "geometry": {"coordinates":[28.8253517151,41.0566596985],"type":"Point"}
}