{
  "type": "Feature",
  "properties": {
    "addr:full":"G?eme Sk. No:6/4 Kavaklidere Ankara 35040",
    "addr:housenumber":"4",
    "addr:postcode":"35040",
    "addr:street":"Eme Sk. No 6 /",
    "iso:country":"TR",
    "sg:address":"G?eme Sk. No:6/4",
    "sg:city":"Kavaklidere",
    "sg:classifiers":[
        {
            "category":"Professional",
            "subcategory":"Engineering",
            "type":"Services"
        }
    ],
    "sg:phone":"+90 312 468 0599",
    "sg:postcode":"35040",
    "sg:province":"Ankara",
    "sg:tags":[
        "architect"
    ],
    "wof:name":"Seap M?savir. M?hendis. Insaat Tic. Ltd. Sti.",
    "wof:placetype":"venue"
},
  "geometry": {"coordinates":[32.8604812622,39.9429283142],"type":"Point"}
}