{
  "type": "Feature",
  "properties": {
    "addr:full":"Evliya Celebi Mah. Deniz Sok. No:34/1 Tuzla Istanbul 01900",
    "addr:housenumber":"no 34 / 1",
    "addr:postcode":"01900",
    "addr:street":"Celebi Mah. Deniz Sok.;Istanbul",
    "iso:country":"TR",
    "sg:address":"Evliya Celebi Mah. Deniz Sok. No:34/1",
    "sg:city":"Tuzla",
    "sg:classifiers":[
        {
            "category":"Manufacturing",
            "subcategory":"Watercraft",
            "type":"Manufacturing & Wholesale Goods"
        }
    ],
    "sg:phone":"+90 216 446 5909",
    "sg:postcode":"01900",
    "sg:province":"Istanbul",
    "sg:tags":[
        "builder",
        "yacht",
        "trough"
    ],
    "wof:name":"Revizyon Gemi Insa Ve Tasimacilik Ltd.sti.",
    "wof:placetype":"venue"
},
  "geometry": {"coordinates":[32.8161125183,39.9680938721],"type":"Point"}
}