{
  "type": "Feature",
  "properties": {
    "addr:full":"Talatpasa Cd. No:29 G?tepe Sisli Istanbul 65710",
    "addr:housenumber":"no 29 g ?",
    "addr:postcode":"65710",
    "addr:street":"Talatpasa Cd.",
    "iso:country":"TR",
    "sg:address":"Talatpasa Cd. No:29 G?tepe",
    "sg:city":"Sisli",
    "sg:classifiers":[
        {
            "category":"Shopping",
            "subcategory":"Stationery & Office Supplies",
            "type":"Retail Goods"
        }
    ],
    "sg:phone":"+90 212 282 5793",
    "sg:postcode":"65710",
    "sg:province":"Istanbul",
    "wof:name":"A?ikkapi Kirtasiye",
    "wof:placetype":"venue"
},
  "geometry": {"coordinates":[28.980459,41.078827],"type":"Point"}
}