{
  "type": "Feature",
  "properties": {
    "iso:country":"TR",
    "sg:address":"Davutpasa Cd. Yilanli Ayazma Sk. No:8 Topkapi",
    "sg:city":"Okmeydani",
    "sg:classifiers":[
        {
            "category":"Sports & Exercise",
            "subcategory":"Tennis Court",
            "type":"Entertainment"
        }
    ],
    "sg:phone":"+90 212 567 4700",
    "sg:postcode":"80270",
    "sg:province":"Istanbul",
    "sg:tags":[
        "equipment",
        "material"
    ],
    "wof:name":"?rme Is Teks. San. A.s.",
    "wof:placetype":"venue"
},
  "geometry": {"coordinates":[28.907211,41.015591],"type":"Point"}
}