{
  "type": "Feature",
  "properties": {
    "addr:full":"Birlik Mah. 806.sok. No:11 Atisalani Ikitelli/K\u00fc\u00e7\u00fck\u00e7ekmece Istanbul 34670",
    "addr:housenumber":"806.sok no 11",
    "addr:postcode":"34670",
    "addr:street":"Birlik Mah.",
    "iso:country":"TR",
    "sg:address":"Birlik Mah. 806.sok. No:11 Atisalani",
    "sg:city":"Ikitelli/K\u00fc\u00e7\u00fck\u00e7ekmece",
    "sg:classifiers":[
        {
            "category":"Shopping",
            "subcategory":"Stationery & Office Supplies",
            "type":"Retail Goods"
        }
    ],
    "sg:phone":"+90 212 646 7251",
    "sg:postcode":"34670",
    "sg:province":"Istanbul",
    "sg:tags":[
        "furniture"
    ],
    "wof:name":"Beysan",
    "wof:placetype":"venue"
},
  "geometry": {"coordinates":[28.8690471649,41.0486831665],"type":"Point"}
}