{
  "type": "Feature",
  "properties": {
    "addr:full":"Asimbey Sk. 22 Aksaray Istanbul 31030",
    "addr:postcode":"31030",
    "addr:street":"Asimbey Sk. 22",
    "iso:country":"TR",
    "sg:address":"Asimbey Sk. 22",
    "sg:city":"Aksaray",
    "sg:orig_category":"Hotels: Motels",
    "sg:phone":"+90 21258959062",
    "sg:postcode":"31030",
    "sg:province":"Istanbul",
    "wof:name":"Koza Hotel",
    "wof:placetype":"venue"
},
  "geometry": {"coordinates":[29.0351371765,40.9948005676],"type":"Point"}
}