{
  "type": "Feature",
  "properties": {
    "iso:country":"TR",
    "sg:address":"Sanayi Cad. No:28 Cetin Sk. 81445 Kurtkoy-pendik Istanbul",
    "sg:city":"Yakapinar-misis",
    "sg:classifiers":[
        {
            "category":"Farming",
            "subcategory":"Livestock Farm",
            "type":"Manufacturing & Wholesale Goods"
        }
    ],
    "sg:phone":"+90 216 378 5104",
    "sg:province":"Istanbul",
    "sg:tags":[
        "agriculture"
    ],
    "wof:name":"Ansel Metal Imalat San Ve Tic As",
    "wof:placetype":"venue"
},
  "geometry": {"coordinates":[29.3045749664,40.9037857056],"type":"Point"}
}