{
  "type": "Feature",
  "properties": {
    "addr:full":"Hasan Can Orta Istanbul 01945",
    "addr:postcode":"01945",
    "addr:street":"Hasan",
    "iso:country":"TR",
    "sg:address":"Hasan Can",
    "sg:city":"Orta",
    "sg:classifiers":[
        {
            "category":"Government",
            "subcategory":"Office",
            "type":"Public Place"
        }
    ],
    "sg:phone":"+90 216 443 5601",
    "sg:postcode":"01945",
    "sg:province":"Istanbul",
    "sg:tags":[
        "municipality"
    ],
    "wof:name":"?mraniye Belediye Baskani",
    "wof:placetype":"venue"
},
  "geometry": {"coordinates":[29.1532745361,40.9368972778],"type":"Point"}
}