{
  "type": "Feature",
  "properties": {
    "addr:full":"Talatpasa Mah. Akcali Sk. No.3 Okmeydani Istanbul 43050",
    "addr:postcode":"43050",
    "addr:street":"Talatpasa Mah. Akcali Sk. No.3",
    "iso:country":"TR",
    "sg:address":"Talatpasa Mah. Akcali Sk. No.3",
    "sg:city":"Okmeydani",
    "sg:classifiers":[
        {
            "category":"Government",
            "subcategory":"Post Office",
            "type":"Public Place"
        }
    ],
    "sg:phone":"+90 212 222 1110",
    "sg:postcode":"43050",
    "sg:province":"Istanbul",
    "sg:tags":[
        "distribution"
    ],
    "wof:name":"Is-mail Dagitim",
    "wof:placetype":"venue"
},
  "geometry": {"coordinates":[28.9678478241,41.0640182495],"type":"Point"}
}