{
  "type": "Feature",
  "properties": {
    "iso:country":"TR",
    "sg:address":"Kestel Bursa Yolu No:28 Bursa",
    "sg:city":"K???k?ekmece",
    "sg:classifiers":[
        {
            "category":"Home & Garden",
            "subcategory":"Household Appliances",
            "type":"Retail Goods"
        }
    ],
    "sg:phone":"+90 224 221 6413",
    "sg:province":"Bursa",
    "sg:tags":[
        "kitchenware"
    ],
    "wof:name":"Baki T?fek-?zt?fek Bi?ak Madeni Esya Tic.",
    "wof:placetype":"venue"
},
  "geometry": {"coordinates":[29.2029914856,40.197769165],"type":"Point"}
}