{
  "type": "Feature",
  "properties": {
    "addr:full":"Sair Esref Bulvari No: 3/3, 35210 ?ankaya, Ankara Mersin Ankara 52750",
    "addr:housenumber":"no 3 / 3",
    "addr:postcode":"35210;52750",
    "addr:street":"Esref Bulvari",
    "iso:country":"TR",
    "sg:address":"Sair Esref Bulvari No: 3/3, 35210 ?ankaya, Ankara",
    "sg:city":"Mersin",
    "sg:classifiers":[
        {
            "category":"Banks & Credit Unions",
            "subcategory":"Bank",
            "type":"Services"
        }
    ],
    "sg:phone":"+90 232 441 9888",
    "sg:postcode":"52750",
    "sg:province":"Ankara",
    "sg:website":"http://www.egstrade.com.tr",
    "wof:name":"Egs Ege Giyim Sanayi Dis Ticaret As",
    "wof:placetype":"venue"
},
  "geometry": {"coordinates":[32.856033,39.943874],"type":"Point"}
}