{
  "type": "Feature",
  "properties": {
    "addr:full":"Londra Asfalti Avcilar Yenimahalle Istanbul 15030",
    "addr:postcode":"15030",
    "addr:street":"Londra",
    "iso:country":"TR",
    "sg:address":"Londra Asfalti Avcilar",
    "sg:city":"Yenimahalle",
    "sg:classifiers":[
        {
            "category":"Farming",
            "subcategory":"Fish & Marine Products",
            "type":"Manufacturing & Wholesale Goods"
        }
    ],
    "sg:phone":"+90 212 591 9349",
    "sg:postcode":"15030",
    "sg:province":"Istanbul",
    "sg:tags":[
        "automotive"
    ],
    "wof:name":"Aks Otomotiv Pazarlama San. Ltd. Sti.",
    "wof:placetype":"venue"
},
  "geometry": {"coordinates":[28.7986927032,40.9808769226],"type":"Point"}
}