{
  "type": "Feature",
  "properties": {
    "iso:country":"TR",
    "sg:address":"Mutlukoy Sitesi 1.sok. No:12",
    "sg:city":"Umitkoy",
    "sg:classifiers":[
        {
            "category":"Farming",
            "subcategory":"Farm & Veterinary Services",
            "type":"Manufacturing & Wholesale Goods"
        }
    ],
    "sg:phone":"+90 312235332523",
    "sg:postcode":"06810",
    "sg:province":"Ankara",
    "sg:tags":[
        "veterinarian"
    ],
    "wof:name":"Levent Kemeroz",
    "wof:placetype":"venue"
},
  "geometry": {"coordinates":[32.6771774292,39.8612861633],"type":"Point"}
}