{
  "type": "Feature",
  "properties": {
    "addr:full":"Ali Gara?glu Osmangazi Bursa 46050",
    "addr:postcode":"46050",
    "iso:country":"TR",
    "sg:address":"Ali Gara?glu",
    "sg:city":"Osmangazi",
    "sg:classifiers":[
        {
            "category":"Government",
            "subcategory":"Office",
            "type":"Public Place"
        }
    ],
    "sg:phone":"+90 224 267 2000",
    "sg:postcode":"46050",
    "sg:province":"Bursa",
    "sg:tags":[
        "municipality"
    ],
    "wof:name":"Ovaak? Belediye Baskani",
    "wof:placetype":"venue"
},
  "geometry": {"coordinates":[29.0580043793,40.1947555542],"type":"Point"}
}