{
  "type": "Feature",
  "properties": {
    "iso:country":"TR",
    "sg:address":"?ankaya Cd.no:20/1 ?ankaya",
    "sg:city":"Cankaya",
    "sg:classifiers":[
        {
            "category":"Government",
            "subcategory":"Embassy",
            "type":"Public Place"
        }
    ],
    "sg:phone":"+90 312 441 3204",
    "sg:postcode":"07080",
    "sg:province":"Ankara",
    "sg:tags":[
        "foreign"
    ],
    "wof:name":"Meksika B?y?kel?iligi",
    "wof:placetype":"venue"
},
  "geometry": {"coordinates":[32.8583068848,39.8877029419],"type":"Point"}
}