{
  "type": "Feature",
  "properties": {
    "addr:full":"Cumhuriyet Caddesi 91 Kat 2 Elmadag Istanbul 65900",
    "addr:housenumber":"91 kat 2",
    "addr:postcode":"65900",
    "addr:street":"Cumhuriyet Caddesi",
    "iso:country":"TR",
    "sg:address":"Cumhuriyet Caddesi 91 Kat 2",
    "sg:city":"Elmadag",
    "sg:classifiers":[
        {
            "category":"Banks & Credit Unions",
            "subcategory":"Investment Brokerage",
            "type":"Services"
        }
    ],
    "sg:phone":"+90 212 241 5749",
    "sg:postcode":"65900",
    "sg:province":"Istanbul",
    "sg:tags":[
        "line",
        "air"
    ],
    "wof:name":"Lot (polish Airlines)",
    "wof:placetype":"venue"
},
  "geometry": {"coordinates":[28.9759254456,41.0123786926],"type":"Point"}
}