{
  "type": "Feature",
  "properties": {
    "iso:country":"TR",
    "sg:address":"Eregli Sok.no:67/b",
    "sg:city":"Siteler",
    "sg:classifiers":[
        {
            "category":"Retail",
            "subcategory":"Auto Rental",
            "type":"Services"
        }
    ],
    "sg:phone":"+90 3538295",
    "sg:postcode":"07070",
    "sg:province":"Ankara",
    "sg:tags":[
        "machine",
        "furniture"
    ],
    "wof:name":"?zbaskent Makine",
    "wof:placetype":"venue"
},
  "geometry": {"coordinates":[33.0913314819,40.1385536194],"type":"Point"}
}