{
  "type": "Feature",
  "properties": {
    "iso:country":"TR",
    "sg:address":"58.bulv. C. 55/3 S. ?agdas Ish. Zeytinburnu",
    "sg:city":"Beyazit",
    "sg:classifiers":[
        {
            "category":"Manufacturing",
            "subcategory":"Leather Goods",
            "type":"Manufacturing & Wholesale Goods"
        }
    ],
    "sg:phone":"+90 212 546 7804",
    "sg:postcode":"65400",
    "sg:province":"Istanbul",
    "wof:name":"Proses Ith.ihr. Ltd.sti.",
    "wof:placetype":"venue"
},
  "geometry": {"coordinates":[28.9759254456,41.0123786926],"type":"Point"}
}