{
  "type": "Feature",
  "properties": {
    "iso:country":"TR",
    "sg:address":"Ahievran Cad. No:148 Ostim",
    "sg:city":"Kozyatagi",
    "sg:classifiers":[
        {
            "category":"Manufacturing",
            "subcategory":"Metals",
            "type":"Manufacturing & Wholesale Goods"
        }
    ],
    "sg:phone":"+90 312 385 3566",
    "sg:postcode":"34742",
    "sg:province":"Ankara",
    "sg:tags":[
        "iron-steel",
        "peoducts"
    ],
    "wof:name":"Turgut Profil",
    "wof:placetype":"venue"
},
  "geometry": {"coordinates":[32.7425804138,39.9758682251],"type":"Point"}
}