{
  "type": "Feature",
  "properties": {
    "addr:full":"Belediye Parsel Ge? 8. Sk. No:18 Mecidiyek? Nazilli Istanbul 65600",
    "addr:housenumber":"8 sk. no 18;?",
    "addr:postcode":"65600",
    "addr:street":"Mecidiyek",
    "iso:country":"TR",
    "sg:address":"Belediye Parsel Ge? 8. Sk. No:18 Mecidiyek?",
    "sg:city":"Nazilli",
    "sg:classifiers":[
        {
            "category":"Home & Garden",
            "subcategory":"Household Appliances",
            "type":"Retail Goods"
        }
    ],
    "sg:phone":"+90 212 211 6422",
    "sg:postcode":"65600",
    "sg:province":"Istanbul",
    "sg:tags":[
        "utensil",
        "electrical"
    ],
    "wof:name":"?zkaradeniz Tic. A.s.",
    "wof:placetype":"venue"
},
  "geometry": {"coordinates":[28.9861831665,41.0408554077],"type":"Point"}
}