{
  "type": "Feature",
  "properties": {
    "addr:full":"Astim Org.san.bol. Hava Alani Yolu No: 189 Tuzla Aydin 81700",
    "addr:housenumber":"no",
    "addr:postcode":"81700",
    "addr:street":"Alani Yolu;Aydin",
    "iso:country":"TR",
    "sg:address":"Astim Org.san.bol. Hava Alani Yolu No: 189",
    "sg:city":"Tuzla",
    "sg:classifiers":[
        {
            "category":"Building & Trades",
            "subcategory":"Plumbing",
            "type":"Services"
        }
    ],
    "sg:phone":"+90 256 225 4473",
    "sg:postcode":"81700",
    "sg:province":"Aydin",
    "wof:name":"Demar Muhendislik Makina Aritma Tesisleri",
    "wof:placetype":"venue"
},
  "geometry": {"coordinates":[28.4863967896,37.8117027283],"type":"Point"}
}