{
  "type": "Feature",
  "properties": {
    "iso:country":"TR",
    "sg:address":"2.cad. No:19 Y.dudullu Organize Sanayi Bolgesi 81260 Umraniye Istanbul",
    "sg:city":"Beyoglu",
    "sg:classifiers":[
        {
            "category":"Manufacturing",
            "subcategory":"Metals",
            "type":"Manufacturing & Wholesale Goods"
        }
    ],
    "sg:phone":"+90 216 364 2103",
    "sg:postcode":"34437",
    "sg:province":"Istanbul",
    "sg:tags":[
        "metallurgy",
        "metalworking"
    ],
    "wof:name":"Tezguller Makina Kalip Ins San Tic Ltd Sti",
    "wof:placetype":"venue"
},
  "geometry": {"coordinates":[29.1563796997,40.9979782104],"type":"Point"}
}