{
  "type": "Feature",
  "properties": {
    "addr:full":"Ankara Yolu 17.km. Nazilli Bursa 65600",
    "addr:housenumber":"17.km",
    "addr:postcode":"65600",
    "addr:street":"Ankara Yolu;Bursa",
    "iso:country":"TR",
    "sg:address":"Ankara Yolu 17.km.",
    "sg:city":"Nazilli",
    "sg:classifiers":[
        {
            "category":"Wholesale",
            "subcategory":"Durable Goods & Equipment",
            "type":"Manufacturing & Wholesale Goods"
        }
    ],
    "sg:phone":"+90 224 384 1373",
    "sg:postcode":"65600",
    "sg:province":"Bursa",
    "sg:tags":[
        "consumer"
    ],
    "wof:name":"Ferkan A.s.",
    "wof:placetype":"venue"
},
  "geometry": {"coordinates":[29.0586109161,40.1844291687],"type":"Point"}
}