{
  "type": "Feature",
  "properties": {
    "addr:full":"A?ktan Sk. No:5 Siteler Etiler Ankara 07010",
    "addr:housenumber":"?",
    "addr:postcode":"07010",
    "addr:street":"A;Ktan Sk. No 5 Siteler",
    "iso:country":"TR",
    "sg:address":"A?ktan Sk. No:5 Siteler",
    "sg:city":"Etiler",
    "sg:classifiers":[
        {
            "category":"Manufacturing",
            "subcategory":"Wood Products",
            "type":"Manufacturing & Wholesale Goods"
        }
    ],
    "sg:phone":"+90 312 350 5374",
    "sg:postcode":"07010",
    "sg:province":"Ankara",
    "sg:tags":[
        "forest"
    ],
    "wof:name":"Akin Orman ?r?nleri Ve Insaat Malzeme Tic.",
    "wof:placetype":"venue"
},
  "geometry": {"coordinates":[29.1010971069,40.1994857788],"type":"Point"}
}