{
  "type": "Feature",
  "properties": {
    "iso:country":"TR",
    "sg:address":"Mesrutiyet Cd. Fatih Apt. No:41 D:31 Kizilay",
    "sg:city":"Ortak?",
    "sg:classifiers":[
        {
            "category":"Organizations",
            "subcategory":"Professional Association",
            "type":"Services"
        }
    ],
    "sg:phone":"+90 312 431 7958",
    "sg:postcode":"80840",
    "sg:province":"Ankara",
    "wof:name":"Tmmob Peyzaj Mimarlari Odasi",
    "wof:placetype":"venue"
},
  "geometry": {"coordinates":[32.8621253967,39.9192886353],"type":"Point"}
}