{
  "type": "Feature",
  "properties": {
    "addr:full":"Esentepe Cad. Akinoglu Apt. No:8/2 Mecidiyekoy Istanbul 34387",
    "addr:housenumber":"2",
    "addr:postcode":"34387",
    "addr:street":"Esentepe Cad. Akinoglu Apt. No 8 /",
    "iso:country":"TR",
    "sg:address":"Esentepe Cad. Akinoglu Apt. No:8/2",
    "sg:city":"Mecidiyekoy",
    "sg:classifiers":[
        {
            "category":"Building & Trades",
            "subcategory":"Locksmith",
            "type":"Services"
        }
    ],
    "sg:phone":"+90 212 275 1511",
    "sg:postcode":"34387",
    "sg:province":"Istanbul",
    "sg:tags":[
        "lock",
        "key"
    ],
    "wof:name":"Yavuz Anahtar",
    "wof:placetype":"venue"
},
  "geometry": {"coordinates":[28.9921588898,41.0720214844],"type":"Point"}
}