{
  "type": "Feature",
  "properties": {
    "addr:full":"Konya Yolu Kaleseramik No:82 D:1 Belgat Fatih Ankara 01740",
    "addr:housenumber":"kaleseramik;1",
    "addr:postcode":"01740",
    "addr:street":"Konya Yolu;No 82 D",
    "iso:country":"TR",
    "sg:address":"Konya Yolu Kaleseramik No:82 D:1 Belgat",
    "sg:city":"Fatih",
    "sg:classifiers":[
        {
            "category":"Building & Trades",
            "subcategory":"Construction",
            "type":"Services"
        }
    ],
    "sg:phone":"+90 312 286 5196",
    "sg:postcode":"01740",
    "sg:province":"Ankara",
    "sg:tags":[
        "foundation"
    ],
    "wof:name":"Kaleseramik Egitim Vakfi",
    "wof:placetype":"venue"
},
  "geometry": {"coordinates":[32.8560333252,39.9438743591],"type":"Point"}
}