{
  "type": "Feature",
  "properties": {
    "addr:full":"Merkez Mh. Marmara Cd. No:7 Avcilar Istanbul 01350",
    "addr:housenumber":"no 7",
    "addr:postcode":"01350",
    "addr:street":"Merkez Mh. Marmara Cd.",
    "iso:country":"TR",
    "sg:address":"Merkez Mh. Marmara Cd. No:7",
    "sg:city":"Avcilar",
    "sg:classifiers":[
        {
            "category":"Shopping",
            "subcategory":"Florist",
            "type":"Retail Goods"
        }
    ],
    "sg:phone":"+90 212 591 8164",
    "sg:postcode":"01350",
    "sg:province":"Istanbul",
    "sg:tags":[
        "flower"
    ],
    "wof:name":"Orkide ?i?ek Evi",
    "wof:placetype":"venue"
},
  "geometry": {"coordinates":[29.0906467438,40.9661827087],"type":"Point"}
}