{
  "type": "Feature",
  "properties": {
    "iso:country":"TR",
    "sg:address":"Sincan San. Sit. 3.cd. No:1",
    "sg:city":"Ikitelli7k???k?ekmece",
    "sg:classifiers":[
        {
            "category":"Home & Garden",
            "subcategory":"Hardware",
            "type":"Retail Goods"
        }
    ],
    "sg:phone":"+90 312 270 2261",
    "sg:postcode":"34670",
    "sg:province":"Ankara",
    "sg:tags":[
        "compressor",
        "pump"
    ],
    "wof:name":"Vimpi Fiskos Mayi Pompa. Imal. San. Tic. Ltd. Sti.",
    "wof:placetype":"venue"
},
  "geometry": {"coordinates":[32.8560333252,39.9438743591],"type":"Point"}
}