{
  "type": "Feature",
  "properties": {
    "addr:full":"Afyon-ankara Yolu 8.km Alibeykoy Afyon 34060",
    "addr:housenumber":"8.km",
    "addr:postcode":"34060",
    "addr:street":"Afyon-Ankara Yolu;Afyon",
    "iso:country":"TR",
    "sg:address":"Afyon-ankara Yolu 8.km",
    "sg:city":"Alibeykoy",
    "sg:classifiers":[
        {
            "category":"Food & Beverages",
            "subcategory":"Meat & Fish",
            "type":"Retail Goods"
        }
    ],
    "sg:phone":"+90 272 223 1111",
    "sg:postcode":"34060",
    "sg:province":"Afyon",
    "sg:tags":[
        "product"
    ],
    "wof:name":"Ozlem Turistik Dinlenme Yesisleri Ve Petrol Urunleri (petrol Ofisi Bayigi)",
    "wof:placetype":"venue"
},
  "geometry": {"coordinates":[30.5382652283,38.7579841614],"type":"Point"}
}