{
  "type": "Feature",
  "properties": {
    "addr:full":"?rnek Sanayi Sitesi 366. Sok. No: 32 06660 Ostim Ankara Karsiyaka Ankara 01900",
    "addr:housenumber":"?;366;no 32",
    "addr:postcode":"06660;01900",
    "addr:street":"Rnek Sanayi Sitesi;Sok.",
    "iso:country":"TR",
    "sg:address":"?rnek Sanayi Sitesi 366. Sok. No: 32 06660 Ostim Ankara",
    "sg:city":"Karsiyaka",
    "sg:classifiers":[
        {
            "category":"Autos & Motor Vehicles",
            "subcategory":"Automobile Sales",
            "type":"Retail Goods"
        }
    ],
    "sg:phone":"+90 312 354 2540",
    "sg:postcode":"01900",
    "sg:province":"Ankara",
    "sg:tags":[
        "motor-cars"
    ],
    "wof:name":"Eysan Auto Accessories San Tic Ltd Sti",
    "wof:placetype":"venue"
},
  "geometry": {"coordinates":[32.8560333252,39.9438743591],"type":"Point"}
}