{
  "type": "Feature",
  "properties": {
    "iso:country":"TR",
    "sg:address":"Gazi Alemsah Mh. Altay Sok 16/a",
    "sg:city":"Meram",
    "sg:classifiers":[
        {
            "category":"Professional",
            "subcategory":"Business Services",
            "type":"Services"
        }
    ],
    "sg:phone":"+90 536 827 0666",
    "sg:postcode":"42100",
    "sg:province":"Konya",
    "wof:name":"As Ajans",
    "wof:placetype":"venue"
},
  "geometry": {"coordinates":[32.4924850464,37.8697891235],"type":"Point"}
}