{
  "type": "Feature",
  "properties": {
    "iso:country":"TR",
    "sg:address":"Tahsin Soylu Cad No.43/a",
    "sg:city":"Anamur",
    "sg:classifiers":[
        {
            "category":"Banks & Credit Unions",
            "subcategory":"Bank",
            "type":"Services"
        }
    ],
    "sg:phone":"+90 324 814 1071",
    "sg:postcode":"33630",
    "sg:province":"33640",
    "wof:name":"T?kiye Is Bankasi As",
    "wof:placetype":"venue"
},
  "geometry": {"coordinates":[28.605888,41.011383],"type":"Point"}
}