{
  "type": "Feature",
  "properties": {
    "iso:country":"TR",
    "sg:address":"1710.sok. No:17 D.3",
    "sg:city":"Karsiyaka",
    "sg:classifiers":[
        {
            "category":"Professional",
            "subcategory":"Engineering",
            "type":"Services"
        }
    ],
    "sg:phone":"+90 232 364 4735",
    "sg:postcode":"01900",
    "sg:province":"Izmir",
    "sg:tags":[
        "architect"
    ],
    "wof:name":"Pera Mimarlik & Dekorasyon",
    "wof:placetype":"venue"
},
  "geometry": {"coordinates":[27.1423015594,38.4251480103],"type":"Point"}
}