{
  "type": "Feature",
  "properties": {
    "iso:country":"TR",
    "sg:address":"Organize San. B?. 7. Cad. No:45 Organize San. B?.",
    "sg:city":"Ikitelli/K\u00fc\u00e7\u00fck\u00e7ekmece",
    "sg:classifiers":[
        {
            "category":"Manufacturing",
            "subcategory":"Metals",
            "type":"Manufacturing & Wholesale Goods"
        }
    ],
    "sg:phone":"+90 352321100133",
    "sg:postcode":"34670",
    "sg:province":"Kayseri",
    "sg:tags":[
        "industry"
    ],
    "wof:name":"Haska Celik Kapi Mobil San.",
    "wof:placetype":"venue"
},
  "geometry": {"coordinates":[35.4891357422,38.7225761414],"type":"Point"}
}