{
  "type": "Feature",
  "properties": {
    "addr:full":"Imes San.sit.a Blok 106 Sok.no:31-33 Y.dudullu Istanbul",
    "addr:housenumber":"blok 106;31-33",
    "addr:street":"Sok.No",
    "iso:country":"TR",
    "sg:address":"Imes San.sit.a Blok 106 Sok.no:31-33",
    "sg:city":"Y.dudullu",
    "sg:classifiers":[
        {
            "category":"Manufacturing",
            "subcategory":"Rubber & Plastics",
            "type":"Manufacturing & Wholesale Goods"
        }
    ],
    "sg:phone":"+90 216 314 1299",
    "sg:province":"Istanbul",
    "sg:tags":[
        "industry"
    ],
    "wof:name":"Pimet Plastik Metal Sanayi Ve Ticaret Ltd.sti.",
    "wof:placetype":"venue"
},
  "geometry": {"coordinates":[28.9759254456,41.0123786926],"type":"Point"}
}