{
  "type": "Feature",
  "properties": {
    "addr:full":"Tomruk Sk. Emniyet Han No:20/428 Tahtakale M.koy. Istanbul",
    "addr:housenumber":"/ 428",
    "addr:street":"Tomruk Sk.;Tahtakale M.Koy.",
    "iso:country":"TR",
    "sg:address":"Tomruk Sk. Emniyet Han No:20/428 Tahtakale",
    "sg:city":"M.koy.",
    "sg:classifiers":[
        {
            "category":"Manufacturing",
            "subcategory":"Textiles",
            "type":"Manufacturing & Wholesale Goods"
        }
    ],
    "sg:phone":"+90 212 519 4977",
    "sg:province":"Istanbul",
    "sg:tags":[
        "fiberglass",
        "polyester"
    ],
    "wof:name":"Polyester Mam?l. San.",
    "wof:placetype":"venue"
},
  "geometry": {"coordinates":[28.717502594,41.076713562],"type":"Point"}
}