{
  "type": "Feature",
  "properties": {
    "addr:full":"Mustafa Hazar Ceyhan Bursa 01920",
    "addr:postcode":"01920",
    "iso:country":"TR",
    "sg:address":"Mustafa Hazar",
    "sg:city":"Ceyhan",
    "sg:classifiers":[
        {
            "category":"Government",
            "subcategory":"Office",
            "type":"Public Place"
        }
    ],
    "sg:phone":"+90 224 841 2142",
    "sg:postcode":"01920",
    "sg:province":"Bursa",
    "sg:tags":[
        "municipality"
    ],
    "wof:name":"B??orhan Belediye Baskani",
    "wof:placetype":"venue"
},
  "geometry": {"coordinates":[29.3257751465,40.6580886841],"type":"Point"}
}