{
  "type": "Feature",
  "properties": {
    "iso:country":"TR",
    "sg:address":"Menekse 1. Sk. No:5/13 Kizilay",
    "sg:city":"Mersin",
    "sg:classifiers":[
        {
            "category":"Professional",
            "subcategory":"Detective & Security Services",
            "type":"Services"
        }
    ],
    "sg:phone":"+90 312419640304",
    "sg:postcode":"52750",
    "sg:province":"Ankara",
    "sg:tags":[
        "material"
    ],
    "wof:name":"Temag G?venlik Sistem.tic. Ltd. Sti.",
    "wof:placetype":"venue"
},
  "geometry": {"coordinates":[32.853027,39.923428],"type":"Point"}
}