{
  "type": "Feature",
  "properties": {
    "iso:country":"TR",
    "sg:address":"?oban?sme Mah. Sanayi Cad. No:11",
    "sg:city":"Yenibosna",
    "sg:classifiers":[
        {
            "category":"Manufacturing",
            "subcategory":"Food",
            "type":"Manufacturing & Wholesale Goods"
        }
    ],
    "sg:phone":"+90 212 452 7292",
    "sg:postcode":"43270",
    "sg:province":"Istanbul",
    "sg:tags":[
        "product",
        "floury",
        "macaroni"
    ],
    "sg:website":"baykur.com.tr",
    "wof:name":"Baykur Gida Sanayi Ve Ticaret A.s.",
    "wof:placetype":"venue"
},
  "geometry": {"coordinates":[28.9861831665,41.0408554077],"type":"Point"}
}