{
  "type": "Feature",
  "properties": {
    "addr:full":"Sivas Cad.no:145 / A Silivri Kayseri 34570",
    "addr:housenumber":"145 / a",
    "addr:postcode":"34570",
    "iso:country":"TR",
    "sg:address":"Sivas Cad.no:145 / A",
    "sg:city":"Silivri",
    "sg:classifiers":[
        {
            "category":"Professional",
            "subcategory":"Engineering",
            "type":"Services"
        }
    ],
    "sg:phone":"+90 352223992772",
    "sg:postcode":"34570",
    "sg:province":"Kayseri",
    "sg:tags":[
        "architect"
    ],
    "wof:name":"Art Dekor Ic Mimari & Dekorasyon Mega Tasarim A.s.",
    "wof:placetype":"venue"
},
  "geometry": {"coordinates":[36.4393234253,38.2791290283],"type":"Point"}
}