{
  "type": "Feature",
  "properties": {
    "addr:full":"Istasyon Cad.no:14 Alpu Eskisehir 01470",
    "addr:housenumber":"14",
    "addr:postcode":"01470",
    "addr:street":"Alpu Eskisehir",
    "iso:country":"TR",
    "sg:address":"Istasyon Cad.no:14",
    "sg:city":"Alpu",
    "sg:classifiers":[
        {
            "category":"Farming",
            "subcategory":"Farm",
            "type":"Manufacturing & Wholesale Goods"
        }
    ],
    "sg:phone":"+90 222 511 2058",
    "sg:postcode":"01470",
    "sg:province":"Eskisehir",
    "sg:tags":[
        "agricultural",
        "product"
    ],
    "wof:name":"Akturk Ticaret",
    "wof:placetype":"venue"
},
  "geometry": {"coordinates":[31.19049263,39.7034416199],"type":"Point"}
}