{
  "type": "Feature",
  "properties": {
    "addr:full":"Organize San.bol.bagcilar G?g?en San.sit.14.blok No:27 K:2 Ikitelli Istanbul 34306",
    "addr:housenumber":"? g ?;27 k 2",
    "addr:postcode":"34306",
    "addr:street":"San.Bol.Bagcilar G;En San.Sit.14.Blok No",
    "iso:country":"TR",
    "sg:address":"Organize San.bol.bagcilar G?g?en San.sit.14.blok No:27 K:2",
    "sg:city":"Ikitelli",
    "sg:classifiers":[
        {
            "category":"Food & Beverages",
            "subcategory":"Meat & Fish",
            "type":"Retail Goods"
        }
    ],
    "sg:phone":"+90 212 671 0406",
    "sg:postcode":"34306",
    "sg:province":"Istanbul",
    "sg:tags":[
        "seafood"
    ],
    "sg:website":"okyanusgida.com.tr",
    "wof:name":"Okyanus Gida San.ve Dis.tic Ltd.",
    "wof:placetype":"venue"
},
  "geometry": {"coordinates":[28.7984962463,41.0884017944],"type":"Point"}
}