{
  "type": "Feature",
  "properties": {
    "addr:full":"Umurbey Mah. Beyazit Sok. No: 48/b Odemis Izmir 35750",
    "addr:housenumber":"no 48 / b",
    "addr:postcode":"35750",
    "addr:street":"Mah. Beyazit Sok.;Odemis Izmir",
    "iso:country":"TR",
    "sg:address":"Umurbey Mah. Beyazit Sok. No: 48/b",
    "sg:city":"Odemis",
    "sg:classifiers":[
        {
            "category":"Airport",
            "subcategory":"International",
            "type":"Transportation"
        }
    ],
    "sg:phone":"+90 232 545 7296",
    "sg:postcode":"35750",
    "sg:province":"Izmir",
    "wof:name":"Oz Anadolu Nakliyat Yurt Ici Ve Yurt Disi Tasimacilik",
    "wof:placetype":"venue"
},
  "geometry": {"coordinates":[27.1423015594,38.4251480103],"type":"Point"}
}