{
  "type": "Feature",
  "properties": {
    "addr:full":"Cinnah Cd. No:96/6 ?ankaya Esenler . Atisalani Ankara",
    "addr:housenumber":"no 96 / 6 ?",
    "addr:street":"Cinnah Cd.;Ankaya Esenler Atisalani",
    "iso:country":"TR",
    "sg:address":"Cinnah Cd. No:96/6 ?ankaya",
    "sg:city":"Esenler . Atisalani",
    "sg:classifiers":[
        {
            "category":"Mining & Drilling",
            "type":"Manufacturing & Wholesale Goods"
        }
    ],
    "sg:phone":"+90 312 440 8683",
    "sg:province":"Ankara",
    "sg:tags":[
        "industry",
        "mine"
    ],
    "wof:name":"Adler Ithalat Ihracat Madencilik Ve Tic. Ltd. Sti.",
    "wof:placetype":"venue"
},
  "geometry": {"coordinates":[32.8842658997,39.8827056885],"type":"Point"}
}