{
  "type": "Feature",
  "properties": {
    "addr:full":"Ragip T. Cd. No:19 Yenimah Ankara",
    "addr:housenumber":"no 19",
    "addr:street":"T. Cd.;Yenimah",
    "iso:country":"TR",
    "sg:address":"Ragip T. Cd. No:19",
    "sg:city":"Yenimah",
    "sg:classifiers":[
        {
            "category":"Home & Garden",
            "subcategory":"Kitchen Supply",
            "type":"Retail Goods"
        }
    ],
    "sg:phone":"+90 312 343 3261",
    "sg:province":"Ankara",
    "sg:tags":[
        "wardrobe"
    ],
    "wof:name":"Atilla Ticaret",
    "wof:placetype":"venue"
},
  "geometry": {"coordinates":[32.8159332275,39.9615745544],"type":"Point"}
}