{
  "type": "Feature",
  "properties": {
    "addr:full":"Sifa Yoks. Galip O. Cd. No:24 Ey\u00fcp Istanbul 34050",
    "addr:housenumber":"no 24",
    "addr:postcode":"34050",
    "addr:street":"O. Cd.;Istanbul",
    "iso:country":"TR",
    "sg:address":"Sifa Yoks. Galip O. Cd. No:24",
    "sg:city":"Ey\u00fcp",
    "sg:classifiers":[
        {
            "category":"Government",
            "subcategory":"Fire Station",
            "type":"Public Place"
        }
    ],
    "sg:phone":"+90 212 565 6678",
    "sg:postcode":"34050",
    "sg:province":"Istanbul",
    "sg:tags":[
        "decoration"
    ],
    "wof:name":"Bozkurt Mobilya",
    "wof:placetype":"venue"
},
  "geometry": {"coordinates":[28.9861831665,41.0408554077],"type":"Point"}
}