{
  "type": "Feature",
  "properties": {
    "addr:full":"Orhaniye Koyu Pk:95 Marmaris Mugla 48700",
    "addr:housenumber":"95",
    "addr:postcode":"48700",
    "addr:street":"Koyu Pk",
    "iso:country":"TR",
    "sg:address":"Orhaniye Koyu Pk:95",
    "sg:city":"Marmaris",
    "sg:classifiers":[
        {
            "category":"Recreation",
            "subcategory":"Boat Charter",
            "type":"Entertainment"
        }
    ],
    "sg:phone":"+90 252 411 1836",
    "sg:postcode":"48700",
    "sg:province":"Mugla",
    "sg:tags":[
        "yachting"
    ],
    "wof:name":"Mizana Yachting",
    "wof:placetype":"venue"
},
  "geometry": {"coordinates":[28.3658008575,37.2196006775],"type":"Point"}
}