{
  "type": "Feature",
  "properties": {
    "addr:full":"Istanbul Izmir Istanbul",
    "iso:country":"TR",
    "sg:address":"Istanbul",
    "sg:city":"Izmir",
    "sg:classifiers":[
        {
            "category":"Banks & Credit Unions",
            "subcategory":"Bank",
            "type":"Services"
        }
    ],
    "sg:province":"Istanbul",
    "wof:name":"Investment Financing As",
    "wof:placetype":"venue"
},
  "geometry": {"coordinates":[28.975925,41.012379],"type":"Point"}
}