{
  "type": "Feature",
  "properties": {
    "addr:full":"Gulbahar Mah G?bag Cad ?imen Sok Meric Konak Apt No:6 Mecidiyek? Cagaloglu Istanbul 34440",
    "addr:housenumber":"?;?",
    "addr:postcode":"34440",
    "addr:street":"Mah G;Bag Cad;Imen Sok Meric;Mecidiyek",
    "iso:country":"TR",
    "sg:address":"Gulbahar Mah G?bag Cad ?imen Sok Meric Konak Apt No:6 Mecidiyek?",
    "sg:city":"Cagaloglu",
    "sg:classifiers":[
        {
            "category":"Home & Garden",
            "subcategory":"Kitchen Supply",
            "type":"Retail Goods"
        }
    ],
    "sg:phone":"+90 212 267 4878",
    "sg:postcode":"34440",
    "sg:province":"Istanbul",
    "sg:tags":[
        "fire",
        "extinguisher"
    ],
    "wof:name":"Alan Elektronik San Tic Ltd",
    "wof:placetype":"venue"
},
  "geometry": {"coordinates":[28.9666919708,41.0404586792],"type":"Point"}
}