{
  "type": "Feature",
  "properties": {
    "addr:full":"Tashan Sok. 36/c Silifke Ikitelli/K\u00fc\u00e7\u00fck\u00e7ekmece I?el 34670",
    "addr:housenumber":"36 / c",
    "addr:postcode":"34670",
    "addr:street":"Tashan Sok.;El",
    "iso:country":"TR",
    "sg:address":"Tashan Sok. 36/c Silifke",
    "sg:city":"Ikitelli/K\u00fc\u00e7\u00fck\u00e7ekmece",
    "sg:classifiers":[
        {
            "category":"Shopping",
            "subcategory":"Computers & Home Electronics",
            "type":"Retail Goods"
        }
    ],
    "sg:phone":"+90 324 714 1166",
    "sg:postcode":"34670",
    "sg:province":"I?el",
    "sg:tags":[
        "product",
        "electric-electronic"
    ],
    "wof:name":"Yilmaz Tokelektrik Ltd.sti.",
    "wof:placetype":"venue"
},
  "geometry": {"coordinates":[28.9674797058,41.0096588135],"type":"Point"}
}