{
  "type": "Feature",
  "properties": {
    "addr:full":"Ankara Cad.no:11 Turgutlu Manisa 45410",
    "addr:housenumber":"11",
    "addr:postcode":"45410",
    "addr:street":"Turgutlu Manisa",
    "iso:country":"TR",
    "sg:address":"Ankara Cad.no:11",
    "sg:city":"Turgutlu",
    "sg:classifiers":[
        {
            "category":"Home & Garden",
            "subcategory":"Hardware",
            "type":"Retail Goods"
        }
    ],
    "sg:phone":"+90 236 313 3359",
    "sg:postcode":"45410",
    "sg:province":"Manisa",
    "sg:tags":[
        "compressor",
        "pump"
    ],
    "wof:name":"Yavuzel Red?kt?r",
    "wof:placetype":"venue"
},
  "geometry": {"coordinates":[28.9016876221,41.0495948792],"type":"Point"}
}