{
  "type": "Feature",
  "properties": {
    "addr:full":"Vatan Mh. Serdar Sk. No:13 Bayrampasa 35250 Istanbul",
    "addr:housenumber":"13",
    "addr:postcode":"35250",
    "addr:street":"Sk. No",
    "iso:country":"TR",
    "sg:address":"Vatan Mh. Serdar Sk. No:13 Bayrampasa",
    "sg:city":"35250",
    "sg:classifiers":[
        {
            "category":"Freight",
            "type":"Transportation"
        }
    ],
    "sg:phone":"+90 212 567 8880",
    "sg:province":"Istanbul",
    "sg:tags":[
        "packing",
        "industry"
    ],
    "wof:name":"Has Vakum Ambalaj",
    "wof:placetype":"venue"
},
  "geometry": {"coordinates":[28.9054145813,41.0301361084],"type":"Point"}
}