{
  "type": "Feature",
  "properties": {
    "addr:full":"Baglar Cad. 225/14 G.osmanpasa Ankara",
    "addr:housenumber":"225 / 14",
    "addr:street":"Baglar Cad.;G.Osmanpasa",
    "iso:country":"TR",
    "sg:address":"Baglar Cad. 225/14",
    "sg:city":"G.osmanpasa",
    "sg:classifiers":[
        {
            "category":"Professional",
            "subcategory":"Engineering",
            "type":"Services"
        }
    ],
    "sg:phone":"+90 312 447 6842",
    "sg:province":"Ankara",
    "sg:tags":[
        "architect"
    ],
    "wof:name":"G&m Muhendislik Ins. San. Ve Tic.ltd.sti.",
    "wof:placetype":"venue"
},
  "geometry": {"coordinates":[32.8604812622,39.9429283142],"type":"Point"}
}