{
  "type": "Feature",
  "properties": {
    "addr:full":"19 Mayis Mah. Sehit Serdar Erdal Sok. No:4 B?y?k?ekmece Istanbul 34900",
    "addr:housenumber":"19;no 4 b ? y ? k ?",
    "addr:postcode":"34900",
    "addr:street":"Mayis Mah. Sehit Serdar;Sok.",
    "iso:country":"TR",
    "sg:address":"19 Mayis Mah. Sehit Serdar Erdal Sok. No:4",
    "sg:city":"B?y?k?ekmece",
    "sg:classifiers":[
        {
            "category":"Building & Trades",
            "subcategory":"Plumbing",
            "type":"Services"
        }
    ],
    "sg:phone":"+90 212 882 6035",
    "sg:postcode":"34900",
    "sg:province":"Istanbul",
    "wof:name":"1a Yerden Isitma Ve Tesisat Sistemleri A.s.",
    "wof:placetype":"venue"
},
  "geometry": {"coordinates":[28.5848255157,41.0235939026],"type":"Point"}
}