{
  "type": "Feature",
  "properties": {
    "iso:country":"TR",
    "sg:address":"?amlik Cd. No:29 Silahtar",
    "sg:city":"Topkapi",
    "sg:classifiers":[
        {
            "category":"Freight",
            "type":"Transportation"
        }
    ],
    "sg:phone":"+90 212 626 6086",
    "sg:postcode":"34020",
    "sg:province":"Istanbul",
    "sg:tags":[
        "packing",
        "industry"
    ],
    "wof:name":"?zertas Ambalaj Mak. San. Tic. Ltd. Sti.",
    "wof:placetype":"venue"
},
  "geometry": {"coordinates":[29.0058689117,41.0891799927],"type":"Point"}
}