{
  "type": "Feature",
  "properties": {
    "iso:country":"TR",
    "sg:address":"426 Sok.no:5 Keresteciler Sitesi Bornova",
    "sg:city":"07100",
    "sg:classifiers":[
        {
            "category":"Manufacturing",
            "subcategory":"Wood Products",
            "type":"Manufacturing & Wholesale Goods"
        }
    ],
    "sg:phone":"+90 232 435 0102",
    "sg:province":"Izmir",
    "sg:tags":[
        "forest"
    ],
    "wof:name":"Kerem Orman ?r?nleri",
    "wof:placetype":"venue"
},
  "geometry": {"coordinates":[27.2196006775,38.4662017822],"type":"Point"}
}