{
  "type": "Feature",
  "properties": {
    "addr:full":"K?? San. Site. 1. Blok No:3/a ?mraniye Kocasinan Istanbul 38100",
    "addr:housenumber":"? ? san.;blok no 3 / a ?",
    "addr:postcode":"38100",
    "addr:street":"Site. 1;Mraniye Kocasinan",
    "iso:country":"TR",
    "sg:address":"K?? San. Site. 1. Blok No:3/a ?mraniye",
    "sg:city":"Kocasinan",
    "sg:classifiers":[
        {
            "category":"Retail",
            "subcategory":"Auto Repair",
            "type":"Services"
        }
    ],
    "sg:phone":"+90 216 329 6826",
    "sg:postcode":"38100",
    "sg:province":"Istanbul",
    "sg:tags":[
        "maintenance"
    ],
    "wof:name":"Kaynak Oto Tic. Koll. Sti.",
    "wof:placetype":"venue"
},
  "geometry": {"coordinates":[28.9861831665,41.0408554077],"type":"Point"}
}