{
  "type": "Feature",
  "properties": {
    "iso:country":"TR",
    "sg:address":"Fevzi Cakmak Mah. Nebioglu Sok. No:4",
    "sg:city":"Merkez",
    "sg:classifiers":[
        {
            "category":"Shopping",
            "type":"Retail Goods"
        }
    ],
    "sg:phone":"+90 332 342 1232",
    "sg:postcode":"61200",
    "sg:province":"Konya",
    "sg:tags":[
        "material",
        "cleaning"
    ],
    "wof:name":"Cevher Kimya Plastik Ve Maden San.tic. Ltd.sti.",
    "wof:placetype":"venue"
},
  "geometry": {"coordinates":[33.0667152405,39.2111282349],"type":"Point"}
}