{
  "type": "Feature",
  "properties": {
    "addr:full":"Haznedar Inonu Cad. No:40 Kizilay Istanbul 06640",
    "addr:housenumber":"40",
    "addr:postcode":"06640",
    "addr:street":"Inonu Cad. No",
    "iso:country":"TR",
    "sg:address":"Haznedar Inonu Cad. No:40",
    "sg:city":"Kizilay",
    "sg:classifiers":[
        {
            "category":"Shopping",
            "subcategory":"Shoes",
            "type":"Retail Goods"
        }
    ],
    "sg:phone":"+90 212 575 2601",
    "sg:postcode":"06640",
    "sg:province":"Istanbul",
    "wof:name":"Dizdar Kundura",
    "wof:placetype":"venue"
},
  "geometry": {"coordinates":[28.877686,41.039124],"type":"Point"}
}