{
  "type": "Feature",
  "properties": {
    "iso:country":"TR",
    "sg:address":"Ankara Cd. No:84 Sirkeci",
    "sg:city":"Osmanbey",
    "sg:classifiers":[
        {
            "category":"Shopping",
            "subcategory":"Stationery & Office Supplies",
            "type":"Retail Goods"
        }
    ],
    "sg:phone":"+90 212 526 4345",
    "sg:postcode":"63000",
    "sg:province":"Istanbul",
    "wof:name":"Emniyet Kirtasiye Imal. Toptan",
    "wof:placetype":"venue"
},
  "geometry": {"coordinates":[28.976213,41.01556],"type":"Point"}
}