{
  "type": "Feature",
  "properties": {
    "addr:full":"Izmir Ikitelli/K\u00fc\u00e7\u00fck\u00e7ekmece Izmir 34670",
    "addr:postcode":"34670",
    "iso:country":"TR",
    "sg:address":"Izmir",
    "sg:city":"Ikitelli/K\u00fc\u00e7\u00fck\u00e7ekmece",
    "sg:classifiers":[
        {
            "category":"Building & Trades",
            "subcategory":"Construction",
            "type":"Services"
        }
    ],
    "sg:phone":"+90 232 482 3302",
    "sg:postcode":"34670",
    "sg:province":"Izmir",
    "sg:tags":[
        "industry",
        "mold"
    ],
    "wof:name":"Bati Makina Kalip San. A.s.",
    "wof:placetype":"venue"
},
  "geometry": {"coordinates":[27.1454906464,38.430519104],"type":"Point"}
}