{
  "type": "Feature",
  "properties": {
    "addr:full":"Gazi M. Kemal Bulv. No:121 D:22 Tandogan Beyoglu Ankara 46810",
    "addr:housenumber":"no 121 d 22",
    "addr:postcode":"46810",
    "addr:street":"Kemal Bulv.;Tandogan Beyoglu",
    "iso:country":"TR",
    "sg:address":"Gazi M. Kemal Bulv. No:121 D:22 Tandogan",
    "sg:city":"Beyoglu",
    "sg:classifiers":[
        {
            "category":"Building & Trades",
            "subcategory":"Construction",
            "type":"Services"
        }
    ],
    "sg:phone":"+90 312 232 3096",
    "sg:postcode":"46810",
    "sg:province":"Ankara",
    "sg:tags":[
        "foundation"
    ],
    "wof:name":"Turkiye Cevre Egitim Vakfi",
    "wof:placetype":"venue"
},
  "geometry": {"coordinates":[32.5820045471,39.9783782959],"type":"Point"}
}