{
  "type": "Feature",
  "properties": {
    "iso:country":"TR",
    "sg:address":"H?k?met Alani No:8",
    "sg:city":"42200",
    "sg:classifiers":[
        {
            "category":"Banks & Credit Unions",
            "subcategory":"Investment Brokerage",
            "type":"Services"
        }
    ],
    "sg:phone":"+90 332 351 1338",
    "sg:province":"Konya",
    "sg:tags":[
        "course",
        "language"
    ],
    "wof:name":"Prodem",
    "wof:placetype":"venue"
},
  "geometry": {"coordinates":[32.4990272522,37.8715362549],"type":"Point"}
}