{
  "type": "Feature",
  "properties": {
    "iso:country":"TR",
    "sg:address":"Sehit A. Yavuz Sk. No:9/12",
    "sg:city":"Kizilay",
    "sg:classifiers":[
        {
            "category":"Manufacturing",
            "subcategory":"Chemicals & Compounds",
            "type":"Manufacturing & Wholesale Goods"
        }
    ],
    "sg:phone":"+90 312 418 0585",
    "sg:postcode":"23050",
    "sg:province":"Ankara",
    "sg:tags":[
        "medicine"
    ],
    "wof:name":"Met Ltd. Sti.",
    "wof:placetype":"venue"
},
  "geometry": {"coordinates":[32.8518981934,39.9205131531],"type":"Point"}
}