{
  "type": "Feature",
  "properties": {
    "addr:full":"Ataturk Cd.yasat Ish.k:4 No:403 Mersin I?el 52750",
    "addr:housenumber":"4",
    "addr:postcode":"? el 52750",
    "addr:street":"Ish.K;No 403",
    "iso:country":"TR",
    "sg:address":"Ataturk Cd.yasat Ish.k:4 No:403",
    "sg:city":"Mersin",
    "sg:classifiers":[
        {
            "category":"Professional",
            "subcategory":"Business Services",
            "type":"Services"
        }
    ],
    "sg:phone":"+90 324 238 4388",
    "sg:postcode":"52750",
    "sg:province":"I?el",
    "sg:tags":[
        "food",
        "product",
        "exporter",
        "aricultural"
    ],
    "wof:name":"Tacyildiz Ltd.sti.",
    "wof:placetype":"venue"
},
  "geometry": {"coordinates":[37.7128486633,41.0530204773],"type":"Point"}
}