{
  "type": "Feature",
  "properties": {
    "iso:country":"TR",
    "sg:address":"G.o.p. Mah. Ataturk Cad. 113/d Cerkezkoy",
    "sg:city":"Gayrettepe",
    "sg:classifiers":[
        {
            "category":"Professional",
            "subcategory":"Testing Lab",
            "type":"Services"
        }
    ],
    "sg:phone":"+90 21272694307267",
    "sg:postcode":"34349",
    "sg:province":"Istanbul",
    "sg:tags":[
        "laboratory",
        "material"
    ],
    "wof:name":"Labtek Laboratuar Teknolojileri",
    "wof:placetype":"venue"
},
  "geometry": {"coordinates":[27.9963684082,41.2974281311],"type":"Point"}
}