{
  "type": "Feature",
  "properties": {
    "addr:full":"Irfanbastug Caddesi No:142 Altinpark Sultanahmet Ankara 34122",
    "addr:housenumber":"no",
    "addr:postcode":"34122",
    "addr:street":"Irfanbastug Caddesi;Altinpark",
    "iso:country":"TR",
    "sg:address":"Irfanbastug Caddesi No:142 Altinpark",
    "sg:city":"Sultanahmet",
    "sg:classifiers":[
        {
            "category":"Organizations",
            "subcategory":"Professional Association",
            "type":"Services"
        }
    ],
    "sg:phone":"+90 312",
    "sg:postcode":"34122",
    "sg:province":"Ankara",
    "sg:tags":[
        "fair"
    ],
    "wof:name":"Anfa Altinpark Isletmeleri Limited Sirketi",
    "wof:placetype":"venue"
},
  "geometry": {"coordinates":[32.8762283325,39.9695167542],"type":"Point"}
}