{
  "type": "Feature",
  "properties": {
    "addr:full":"Atat?k Oto San. Sit. No:256 Maslak Nazilli Istanbul 65600",
    "addr:postcode":"65600",
    "addr:street":"Maslak",
    "iso:country":"TR",
    "sg:address":"Atat?k Oto San. Sit. No:256 Maslak",
    "sg:city":"Nazilli",
    "sg:classifiers":[
        {
            "category":"Home & Garden",
            "subcategory":"Household Appliances",
            "type":"Retail Goods"
        }
    ],
    "sg:phone":"+90 212 276 5762",
    "sg:postcode":"65600",
    "sg:province":"Istanbul",
    "sg:tags":[
        "utensil",
        "electrical"
    ],
    "wof:name":"Comri Ev Cih. San.",
    "wof:placetype":"venue"
},
  "geometry": {"coordinates":[28.9861831665,41.0408554077],"type":"Point"}
}