{
  "type": "Feature",
  "properties": {
    "addr:full":"Kent Koop.mah.218 Sok.dostluk Carsisi K:2 No:29 Akpinar Ankara 01640",
    "addr:housenumber":"2 no 29",
    "addr:postcode":"01640",
    "addr:street":"Akpinar Ankara",
    "iso:country":"TR",
    "sg:address":"Kent Koop.mah.218 Sok.dostluk Carsisi K:2 No:29",
    "sg:city":"Akpinar",
    "sg:classifiers":[
        {
            "category":"Farming",
            "subcategory":"Farm & Veterinary Services",
            "type":"Manufacturing & Wholesale Goods"
        }
    ],
    "sg:phone":"+90 312 351 8332",
    "sg:postcode":"01640",
    "sg:province":"Ankara",
    "sg:tags":[
        "veterinarian"
    ],
    "wof:name":"Huseyin Dereli",
    "wof:placetype":"venue"
},
  "geometry": {"coordinates":[32.8560333252,39.9438743591],"type":"Point"}
}