{
  "type": "Feature",
  "properties": {
    "addr:full":"Ciftehavuzlar Cad. Prestij Is Merkezi No:27/211-221 Bayrampasa Kemalpasa Istanbul 01340",
    "addr:housenumber":"no 27 / 211-221",
    "addr:postcode":"01340",
    "addr:street":"Ciftehavuzlar Cad. Prestij;Bayrampasa Kemalpasa",
    "iso:country":"TR",
    "sg:address":"Ciftehavuzlar Cad. Prestij Is Merkezi No:27/211-221 Bayrampasa",
    "sg:city":"Kemalpasa",
    "sg:classifiers":[
        {
            "category":"Freight",
            "type":"Transportation"
        }
    ],
    "sg:phone":"+90 21249346223",
    "sg:postcode":"01340",
    "sg:province":"Istanbul",
    "sg:tags":[
        "packing",
        "industry"
    ],
    "wof:name":"Gozde Kagitcilik Kirtasiye Dis Tic.ltd.sti.",
    "wof:placetype":"venue"
},
  "geometry": {"coordinates":[28.9759254456,41.0123786926],"type":"Point"}
}