{
  "type": "Feature",
  "properties": {
    "iso:country":"TR",
    "sg:address":"Nenehatun Cad. No:47/1 G.o.p",
    "sg:city":"58000",
    "sg:classifiers":[
        {
            "category":"Wholesale",
            "subcategory":"Medical Equipment & Supplies",
            "type":"Manufacturing & Wholesale Goods"
        }
    ],
    "sg:phone":"+90 312 436 7270",
    "sg:province":"Ankara",
    "sg:tags":[
        "material"
    ],
    "wof:name":"Saba Ltd. Sti.",
    "wof:placetype":"venue"
},
  "geometry": {"coordinates":[32.8675613403,39.9005432129],"type":"Point"}
}