{
  "type": "Feature",
  "properties": {
    "addr:full":"Kara?yir Mah.eflatun Sok.sa?ilarli Apt.no:35 14100 Bolu",
    "addr:housenumber":"35",
    "addr:postcode":"14100",
    "addr:street":"Apt.No",
    "iso:country":"TR",
    "sg:address":"Kara?yir Mah.eflatun Sok.sa?ilarli Apt.no:35",
    "sg:city":"14100",
    "sg:classifiers":[
        {
            "category":"Manufacturing",
            "subcategory":"Food",
            "type":"Manufacturing & Wholesale Goods"
        }
    ],
    "sg:phone":"+90 374 215 3011",
    "sg:province":"Bolu",
    "sg:tags":[
        "wholesaler"
    ],
    "wof:name":"Arbak Gida Ith.maddeleri T?t?n ?retim Pazarlama",
    "wof:placetype":"venue"
},
  "geometry": {"coordinates":[31.6107006073,40.7332992554],"type":"Point"}
}