{
  "type": "Feature",
  "properties": {
    "addr:full":"Atakoy 9.kisim B-14 D:29 Kagithane Istanbul 34406",
    "addr:housenumber":"b-14 d 29",
    "addr:postcode":"34406",
    "addr:street":"Istanbul",
    "iso:country":"TR",
    "sg:address":"Atakoy 9.kisim B-14 D:29",
    "sg:city":"Kagithane",
    "sg:classifiers":[
        {
            "category":"Food & Beverages",
            "subcategory":"Meat & Fish",
            "type":"Retail Goods"
        }
    ],
    "sg:phone":"+90 212 275 3882",
    "sg:postcode":"34406",
    "sg:province":"Istanbul",
    "sg:tags":[
        "product"
    ],
    "wof:name":"Sanalet",
    "wof:placetype":"venue"
},
  "geometry": {"coordinates":[28.8492851257,40.9891548157],"type":"Point"}
}