{
  "type": "Feature",
  "properties": {
    "addr:full":"H?imet Cad. 15 Boz?? 11300",
    "addr:housenumber":"15;? ?",
    "addr:postcode":"11300",
    "addr:street":"Imet Cad.;Boz",
    "iso:country":"TR",
    "sg:address":"H?imet Cad. 15",
    "sg:city":"Boz??",
    "sg:classifiers":[
        {
            "category":"Banks & Credit Unions",
            "subcategory":"Bank",
            "type":"Services"
        }
    ],
    "sg:phone":"+90 228 318 1410",
    "sg:province":"11300",
    "wof:name":"Toprakbank As",
    "wof:placetype":"venue"
},
  "geometry": {"coordinates":[29.004736,41.084213],"type":"Point"}
}