{
  "type": "Feature",
  "properties": {
    "addr:full":"2. Sahil Boyu No:27 Ayvalik Ikitelli/K\u00fc\u00e7\u00fck\u00e7ekmece Balikesir 34670",
    "addr:housenumber":"2;27",
    "addr:postcode":"34670",
    "addr:street":"Sahil Boyu No;Balikesir",
    "iso:country":"TR",
    "sg:address":"2. Sahil Boyu No:27 Ayvalik",
    "sg:city":"Ikitelli/K\u00fc\u00e7\u00fck\u00e7ekmece",
    "sg:classifiers":[
        {
            "category":"Food & Beverages",
            "subcategory":"Meat & Fish",
            "type":"Retail Goods"
        }
    ],
    "sg:phone":"+90 266 312 2101",
    "sg:postcode":"34670",
    "sg:province":"Balikesir",
    "sg:tags":[
        "packing"
    ],
    "wof:name":"Mehmet Kocakundak?i",
    "wof:placetype":"venue"
},
  "geometry": {"coordinates":[27.8833007812,39.6520996094],"type":"Point"}
}