{
  "type": "Feature",
  "properties": {
    "addr:full":"10006/1 Sk. No:16 Cigli Izmir 46000",
    "addr:housenumber":"10006 / 1;16",
    "addr:postcode":"46000",
    "addr:street":"Sk. No",
    "iso:country":"TR",
    "sg:address":"10006/1 Sk. No:16",
    "sg:city":"Cigli",
    "sg:classifiers":[
        {
            "category":"Food & Beverages",
            "subcategory":"Groceries & Convenience Stores",
            "type":"Retail Goods"
        }
    ],
    "sg:phone":"+90 232 328 0909",
    "sg:postcode":"46000",
    "sg:province":"Izmir",
    "sg:tags":[
        "product"
    ],
    "wof:name":"Aytas Gida Ve Ihtiyac Mad.san.ve Tic.as.",
    "wof:placetype":"venue"
},
  "geometry": {"coordinates":[27.1829338074,38.4402923584],"type":"Point"}
}