{
  "type": "Feature",
  "properties": {
    "iso:country":"TR",
    "sg:address":"Incirli Cd. Dr. Salih Zeki Sk. No. Hizalan Sitesi B1 Blok No:1",
    "sg:city":"Bakirkoy",
    "sg:classifiers":[
        {
            "category":"Farming",
            "subcategory":"Farm & Veterinary Services",
            "type":"Manufacturing & Wholesale Goods"
        }
    ],
    "sg:phone":"+90 212 660 3924",
    "sg:postcode":"35790",
    "sg:province":"Istanbul",
    "sg:tags":[
        "veterinarian"
    ],
    "wof:name":"Cizmeli Kedi Vet.klinigi Ltd.sti.",
    "wof:placetype":"venue"
},
  "geometry": {"coordinates":[28.9759254456,41.0123786926],"type":"Point"}
}