{
  "type": "Feature",
  "properties": {
    "addr:full":"Ayta?mh. Dereboyu Cd. No:32 Halkali 07230 Istanbul",
    "addr:housenumber":"no 32",
    "addr:postcode":"07230",
    "addr:street":"Mh. Dereboyu Cd.;Halkali",
    "iso:country":"TR",
    "sg:address":"Ayta?mh. Dereboyu Cd. No:32 Halkali",
    "sg:city":"07230",
    "sg:classifiers":[
        {
            "category":"Sports & Exercise",
            "subcategory":"Tennis Court",
            "type":"Entertainment"
        }
    ],
    "sg:phone":"+90 212 548 3177",
    "sg:province":"Istanbul",
    "sg:tags":[
        "equipment",
        "material"
    ],
    "wof:name":"Akg?nd?z San. ?rn. Dis Tic. Ltd. Sti.",
    "wof:placetype":"venue"
},
  "geometry": {"coordinates":[28.7838,41.043674],"type":"Point"}
}