{
  "type": "Feature",
  "properties": {
    "iso:country":"TR",
    "sg:address":"Ayta?mh. Dereboyu Cd. No:32 Halkali",
    "sg:city":"07230",
    "sg:classifiers":[
        {
            "category":"Sports & Exercise",
            "subcategory":"Tennis Court",
            "type":"Entertainment"
        }
    ],
    "sg:phone":"+90 212 548 3177",
    "sg:province":"Istanbul",
    "sg:tags":[
        "equipment",
        "material"
    ],
    "wof:name":"Akg?nd?z San. ?rn. Dis Tic. Ltd. Sti.",
    "wof:placetype":"venue"
},
  "geometry": {"coordinates":[28.7838,41.043674],"type":"Point"}
}