{
  "type": "Feature",
  "properties": {
    "iso:country":"TR",
    "sg:address":"G??suyu Cd. No:6",
    "sg:city":"Topkapi",
    "sg:classifiers":[
        {
            "category":"Manufacturing",
            "subcategory":"Glass & Minerals",
            "type":"Manufacturing & Wholesale Goods"
        }
    ],
    "sg:phone":"+90 212 567 1509",
    "sg:postcode":"24620",
    "sg:province":"Istanbul",
    "sg:tags":[
        "glass-mirror"
    ],
    "wof:name":"Istanbul Cam San. A.s.",
    "wof:placetype":"venue"
},
  "geometry": {"coordinates":[28.9841861725,41.0552787781],"type":"Point"}
}