{
  "type": "Feature",
  "properties": {
    "addr:full":"S?er Mh. 28 Sk. No:37 Zeytinburnu Konak Istanbul 07110",
    "addr:housenumber":"28;37",
    "addr:postcode":"?;07110",
    "addr:street":"S;Er Mh.;Sk. No",
    "iso:country":"TR",
    "sg:address":"S?er Mh. 28 Sk. No:37 Zeytinburnu",
    "sg:city":"Konak",
    "sg:classifiers":[
        {
            "category":"Wholesale",
            "subcategory":"Durable Goods & Equipment",
            "type":"Manufacturing & Wholesale Goods"
        }
    ],
    "sg:phone":"+90 212 582 3291",
    "sg:postcode":"07110",
    "sg:province":"Istanbul",
    "sg:tags":[
        "consumer"
    ],
    "wof:name":"Adalilar Bonmarse A.s.",
    "wof:placetype":"venue"
},
  "geometry": {"coordinates":[28.9861831665,41.0408554077],"type":"Point"}
}