{
  "type": "Feature",
  "properties": {
    "iso:country":"TR",
    "sg:address":"Cam Ayna Ahsap Dekorasyon Sit.fevzi Cakmak Bulv.26. Sok. No:6/b",
    "sg:city":"Uskudar",
    "sg:classifiers":[
        {
            "category":"Manufacturing",
            "subcategory":"Glass & Minerals",
            "type":"Manufacturing & Wholesale Goods"
        }
    ],
    "sg:phone":"+90 342 321 3183",
    "sg:postcode":"34672",
    "sg:province":"Gaziantep",
    "sg:tags":[
        "glass-mirror"
    ],
    "wof:name":"Kare Cam Ayna Ahsap Dekorasyon Ltd.sti.",
    "wof:placetype":"venue"
},
  "geometry": {"coordinates":[37.3761024475,37.0629463196],"type":"Point"}
}