{
  "type": "Feature",
  "properties": {
    "iso:country":"TR",
    "sg:address":"Beyler Mah.kili?slan Cad.no:115 Iznik",
    "sg:city":"Melikgazi",
    "sg:classifiers":[
        {
            "category":"Government",
            "subcategory":"Office",
            "type":"Public Place"
        }
    ],
    "sg:phone":"+90 224 757 1576",
    "sg:postcode":"38030",
    "sg:province":"Bursa",
    "sg:tags":[
        "chamber",
        "industry",
        "commerce"
    ],
    "wof:name":"Iznik Ticaret Ve Sanayi Odasi",
    "wof:placetype":"venue"
},
  "geometry": {"coordinates":[29.0586109161,40.1844291687],"type":"Point"}
}