{
  "type": "Feature",
  "properties": {
    "addr:full":"Mimar Sinan Cad. No:86 Edirnekapi Bursa",
    "addr:housenumber":"86",
    "addr:street":"Mimar Sinan Cad. No",
    "iso:country":"TR",
    "sg:address":"Mimar Sinan Cad. No:86",
    "sg:city":"Edirnekapi",
    "sg:classifiers":[
        {
            "category":"Government",
            "subcategory":"Fire Station",
            "type":"Public Place"
        }
    ],
    "sg:phone":"+90 224 813 2267",
    "sg:province":"Bursa",
    "sg:tags":[
        "decoration"
    ],
    "wof:name":"Erdonmez Dekorasyon",
    "wof:placetype":"venue"
},
  "geometry": {"coordinates":[29.1264591217,40.1867790222],"type":"Point"}
}