{
  "type": "Feature",
  "properties": {
    "iso:country":"TR",
    "sg:address":"Agir San. B?ge. Menekse Sk. No:4",
    "sg:city":"Bornova",
    "sg:classifiers":[
        {
            "category":"Building & Trades",
            "subcategory":"Construction",
            "type":"Services"
        }
    ],
    "sg:phone":"+90 266 242 4222",
    "sg:postcode":"35040",
    "sg:province":"Balikesir",
    "sg:tags":[
        "tank-boiler-heating",
        "unit"
    ],
    "wof:name":"Balikesir Kazan Makina Imalat Sanayi A.s.",
    "wof:placetype":"venue"
},
  "geometry": {"coordinates":[27.8853626251,39.6448822021],"type":"Point"}
}