{
  "type": "Feature",
  "properties": {
    "addr:full":"Sabuni Mah Edirne 22100 22050",
    "addr:postcode":"22100 22050",
    "addr:street":"Sabuni Mah Edirne",
    "iso:country":"TR",
    "sg:address":"Sabuni Mah",
    "sg:city":"Edirne",
    "sg:classifiers":[
        {
            "category":"Banks & Credit Unions",
            "subcategory":"Bank",
            "type":"Services"
        }
    ],
    "sg:phone":"+90 284 225 3817",
    "sg:postcode":"22050",
    "sg:province":"22100",
    "wof:name":"T?kiye Is Bankasi As",
    "wof:placetype":"venue"
},
  "geometry": {"coordinates":[26.559574,41.673576],"type":"Point"}
}