{
  "type": "Feature",
  "properties": {
    "iso:country":"TR",
    "sg:address":"P.k.226 Kavaklidere",
    "sg:city":"Ikitelli/K\u00fc\u00e7\u00fck\u00e7ekmece",
    "sg:classifiers":[
        {
            "category":"Manufacturing",
            "subcategory":"Metals",
            "type":"Manufacturing & Wholesale Goods"
        }
    ],
    "sg:phone":"+90 312 447 9077",
    "sg:postcode":"34670",
    "sg:province":"Ankara",
    "sg:tags":[
        "iron-steel",
        "peoducts"
    ],
    "wof:name":"Cengiz Korkmaz-titco",
    "wof:placetype":"venue"
},
  "geometry": {"coordinates":[32.8861961365,39.888885498],"type":"Point"}
}