{
  "type": "Feature",
  "properties": {
    "addr:full":"Tuna Cd. No:15 Bayrampasa B. ?ekmece Istanbul 34400",
    "addr:housenumber":"no 15",
    "addr:postcode":"34400",
    "addr:street":"Cd.;B.",
    "iso:country":"TR",
    "sg:address":"Tuna Cd. No:15 Bayrampasa",
    "sg:city":"B. ?ekmece",
    "sg:classifiers":[
        {
            "category":"Manufacturing",
            "subcategory":"Metals",
            "type":"Manufacturing & Wholesale Goods"
        }
    ],
    "sg:phone":"+90 212 544 1334",
    "sg:postcode":"34400",
    "sg:province":"Istanbul",
    "sg:tags":[
        "industry"
    ],
    "wof:name":"Kromas Mak. Metal San. Tic. Ltd. Sti.",
    "wof:placetype":"venue"
},
  "geometry": {"coordinates":[28.9119625092,41.0539550781],"type":"Point"}
}