{
  "type": "Feature",
  "properties": {
    "addr:full":"Tahtakale Cd. C?ertt?k Sk. Pir Han K:3 No:303 Emin?? Istanbul Mersin Istanbul 52750",
    "addr:housenumber":"?;?;3;? ?",
    "addr:postcode":"52750",
    "addr:street":"Tahtakale Cd. C;K Sk. Pir Han K;No 303",
    "iso:country":"TR",
    "sg:address":"Tahtakale Cd. C?ertt?k Sk. Pir Han K:3 No:303 Emin?? Istanbul",
    "sg:city":"Mersin",
    "sg:classifiers":[
        {
            "category":"Professional",
            "subcategory":"Art Services",
            "type":"Services"
        }
    ],
    "sg:phone":"+90 212 526 4923",
    "sg:postcode":"52750",
    "sg:province":"Istanbul",
    "sg:tags":[
        "marketing"
    ],
    "wof:name":"Cemmark I? Dis Tic. Ltd. Sti.",
    "wof:placetype":"venue"
},
  "geometry": {"coordinates":[28.9861831665,41.0408554077],"type":"Point"}
}