{
  "type": "Feature",
  "properties": {
    "iso:country":"TR",
    "sg:address":"Cumhuriyet Bulvari No:139",
    "sg:city":"Mersin",
    "sg:classifiers":[
        {
            "category":"Manufacturing",
            "subcategory":"Metals",
            "type":"Manufacturing & Wholesale Goods"
        }
    ],
    "sg:phone":"+90 232 422 1071",
    "sg:postcode":"52750",
    "sg:province":"Izmir",
    "sg:tags":[
        "iron-steel",
        "peoducts"
    ],
    "wof:name":"Eregli Demir ?elik Fabrikasi A.s.",
    "wof:placetype":"venue"
},
  "geometry": {"coordinates":[27.1352024078,38.4297637939],"type":"Point"}
}