{
  "type": "Feature",
  "properties": {
    "iso:country":"TR",
    "sg:address":"A.gazi Cad.mh.lale Sok.no.6",
    "sg:city":"Sultanbeyli",
    "sg:classifiers":[
        {
            "category":"Food & Beverages",
            "subcategory":"Specialty",
            "type":"Retail Goods"
        }
    ],
    "sg:phone":"+90 216 398 7126",
    "sg:province":"Istanbul",
    "sg:tags":[
        "materials-spices",
        "additive"
    ],
    "wof:name":"Polater Maya Sanayi",
    "wof:placetype":"venue"
},
  "geometry": {"coordinates":[28.9856815338,41.1001548767],"type":"Point"}
}