{
  "type": "Feature",
  "properties": {
    "addr:full":"Ankara Asfalti 7.km Uskudar Denizli 81100",
    "addr:postcode":"81100",
    "iso:country":"TR",
    "sg:address":"Ankara Asfalti 7.km",
    "sg:city":"Uskudar",
    "sg:classifiers":[
        {
            "category":"Shopping",
            "subcategory":"Crafts & Fabrics",
            "type":"Retail Goods"
        }
    ],
    "sg:phone":"+90 258 268 2355",
    "sg:postcode":"81100",
    "sg:province":"Denizli",
    "sg:tags":[
        "textile",
        "-leather",
        "exporter"
    ],
    "wof:name":"K?seler Tekstil Ltd.",
    "wof:placetype":"venue"
},
  "geometry": {"coordinates":[29.0788803101,37.7851867676],"type":"Point"}
}