{
  "type": "Feature",
  "properties": {
    "addr:full":"Serifali Mevki Imes E-kapisi Karsisi Kutup Sok. No:25 Y.dudullu Beyoglu Istanbul 34437",
    "addr:housenumber":"no 25",
    "addr:postcode":"34437",
    "addr:street":"Kutup Sok.;Y.Dudullu Beyoglu",
    "iso:country":"TR",
    "sg:address":"Serifali Mevki Imes E-kapisi Karsisi Kutup Sok. No:25 Y.dudullu",
    "sg:city":"Beyoglu",
    "sg:classifiers":[
        {
            "category":"Manufacturing",
            "subcategory":"Metals",
            "type":"Manufacturing & Wholesale Goods"
        }
    ],
    "sg:phone":"+90 216 466 6446",
    "sg:postcode":"34437",
    "sg:province":"Istanbul",
    "sg:tags":[
        "industry"
    ],
    "wof:name":"?amlica Metal Ambalaj Ltd.sti.",
    "wof:placetype":"venue"
},
  "geometry": {"coordinates":[28.9870662689,41.0371894836],"type":"Point"}
}