{
  "type": "Feature",
  "properties": {
    "addr:full":"Yalniz Selvi Cad. No:3 Soganlik Kartal Istanbul 46000",
    "addr:postcode":"46000",
    "addr:street":"Selvi Cad. No 3 Soganlik",
    "iso:country":"TR",
    "sg:address":"Yalniz Selvi Cad. No:3 Soganlik",
    "sg:city":"Kartal",
    "sg:classifiers":[
        {
            "category":"Food & Beverages",
            "subcategory":"Meat & Fish",
            "type":"Retail Goods"
        }
    ],
    "sg:phone":"+90 21630987105",
    "sg:postcode":"46000",
    "sg:province":"Istanbul",
    "sg:tags":[
        "product"
    ],
    "wof:name":"?nl?er Et",
    "wof:placetype":"venue"
},
  "geometry": {"coordinates":[28.9861831665,41.0408554077],"type":"Point"}
}