{
  "type": "Feature",
  "properties": {
    "addr:full":"Halit Ziya Bulvari No:32 Siteler Izmir 06160",
    "addr:housenumber":"no 32",
    "addr:postcode":"06160",
    "addr:street":"Ziya Bulvari",
    "iso:country":"TR",
    "sg:address":"Halit Ziya Bulvari No:32",
    "sg:city":"Siteler",
    "sg:classifiers":[
        {
            "category":"Banks & Credit Unions",
            "subcategory":"Investment Brokerage",
            "type":"Services"
        }
    ],
    "sg:phone":"+90 232 425 1835",
    "sg:postcode":"06160",
    "sg:province":"Izmir",
    "sg:tags":[
        "-",
        "export",
        "import"
    ],
    "wof:name":"Adim Nakis Ithalat Ihracat San. Tic. A.s.",
    "wof:placetype":"venue"
},
  "geometry": {"coordinates":[27.1333999634,38.4233932495],"type":"Point"}
}