{
  "type": "Feature",
  "properties": {
    "addr:full":"G??suyu Cad. Hastane Yolu No.6 Maltepe Aksaray Istanbul 31030",
    "addr:housenumber":"? ?;no.6",
    "addr:postcode":"31030",
    "addr:street":"Suyu Cad. Hastane Yolu",
    "iso:country":"TR",
    "sg:address":"G??suyu Cad. Hastane Yolu No.6 Maltepe",
    "sg:city":"Aksaray",
    "sg:classifiers":[
        {
            "category":"Autos & Motor Vehicles",
            "subcategory":"Auto Supplies",
            "type":"Retail Goods"
        }
    ],
    "sg:phone":"+90 212 674 0661",
    "sg:postcode":"31030",
    "sg:province":"Istanbul",
    "sg:tags":[
        "accessory"
    ],
    "wof:name":"Oto Uzay Koll.sti.",
    "wof:placetype":"venue"
},
  "geometry": {"coordinates":[28.9861831665,41.0408554077],"type":"Point"}
}