{
  "type": "Feature",
  "properties": {
    "addr:full":"Halaskargazi Cd. No:391 Cevher Apt. No:6 Sisli Kizilay Istanbul 23050",
    "addr:housenumber":"no",
    "addr:postcode":"23050",
    "addr:street":"Halaskargazi Cd.;Cevher;No 6 Sisli Kizilay",
    "iso:country":"TR",
    "sg:address":"Halaskargazi Cd. No:391 Cevher Apt. No:6 Sisli",
    "sg:city":"Kizilay",
    "sg:classifiers":[
        {
            "category":"Wholesale",
            "subcategory":"Books, Periodicals, & Newspapers",
            "type":"Manufacturing & Wholesale Goods"
        }
    ],
    "sg:phone":"+90 212 246 5718",
    "sg:postcode":"23050",
    "sg:province":"Istanbul",
    "sg:tags":[
        "house",
        "publishing"
    ],
    "wof:name":"Gen? Kardes Egitim Hizmet. Tic. Ltd. Sti.",
    "wof:placetype":"venue"
},
  "geometry": {"coordinates":[28.9913578033,41.0809173584],"type":"Point"}
}