{
  "type": "Feature",
  "properties": {
    "iso:country":"TR",
    "sg:address":"Dery Adil Sok, 88/7 Nar Tesvikiye",
    "sg:city":"Istanbul",
    "sg:classifiers":[
        {
            "category":"Travel",
            "subcategory":"Travel Agent",
            "type":"Entertainment"
        }
    ],
    "sg:phone":"+90 902 122 4896",
    "sg:province":"80200",
    "sg:website":"www.petentour.com",
    "wof:name":"Peten Turizm",
    "wof:placetype":"venue"
},
  "geometry": {"coordinates":[28.9674797058,41.0096588135],"type":"Point"}
}