{
  "type": "Feature",
  "properties": {
    "addr:full":"Topcular Mah.topcular Cad. No:33 Ey\u00fcp Istanbul 34050",
    "addr:housenumber":"33",
    "addr:postcode":"34050",
    "addr:street":"Mah.Topcular Cad. No;Istanbul",
    "iso:country":"TR",
    "sg:address":"Topcular Mah.topcular Cad. No:33",
    "sg:city":"Ey\u00fcp",
    "sg:classifiers":[
        {
            "category":"Freight",
            "type":"Transportation"
        }
    ],
    "sg:phone":"+90 212 612 9877",
    "sg:postcode":"34050",
    "sg:province":"Istanbul",
    "sg:tags":[
        "packing",
        "industry"
    ],
    "wof:name":"?zge Ambalaj",
    "wof:placetype":"venue"
},
  "geometry": {"coordinates":[28.9239349365,41.0389823914],"type":"Point"}
}