{
  "type": "Feature",
  "properties": {
    "addr:full":"Tarsus Yolu Uzeri 10.km. Mersin I?el 52750",
    "addr:housenumber":"uzeri;?",
    "addr:postcode":"52750",
    "addr:street":"Tarsus Yolu;Mersin I;El",
    "iso:country":"TR",
    "sg:address":"Tarsus Yolu Uzeri 10.km.",
    "sg:city":"Mersin",
    "sg:classifiers":[
        {
            "category":"Food & Beverages",
            "subcategory":"Groceries & Convenience Stores",
            "type":"Retail Goods"
        }
    ],
    "sg:phone":"+90 324 221 5961",
    "sg:postcode":"52750",
    "sg:province":"I?el",
    "sg:tags":[
        "drink-",
        "soft"
    ],
    "wof:name":"Ozgu Gida Tic.a.s.",
    "wof:placetype":"venue"
},
  "geometry": {"coordinates":[34.900101,36.920101],"type":"Point"}
}