{
  "type": "Feature",
  "properties": {
    "iso:country":"TR",
    "sg:address":"Kiztasi Cd. No:4",
    "sg:city":"Aksaray",
    "sg:classifiers":[
        {
            "category":"Shopping",
            "subcategory":"Florist",
            "type":"Retail Goods"
        }
    ],
    "sg:phone":"+90 212 525 8090",
    "sg:postcode":"31030",
    "sg:province":"Istanbul",
    "sg:tags":[
        "flower"
    ],
    "wof:name":"Yeni Renk ?i?ek Evi",
    "wof:placetype":"venue"
},
  "geometry": {"coordinates":[28.951215744,41.0164985657],"type":"Point"}
}