{
  "type": "Feature",
  "properties": {
    "addr:full":"K?fez T?k Petrol Yani Kadikoy Kocaeli 01370",
    "addr:postcode":"01370",
    "addr:street":"Kocaeli",
    "iso:country":"TR",
    "sg:address":"K?fez T?k Petrol Yani",
    "sg:city":"Kadikoy",
    "sg:classifiers":[
        {
            "category":"Transit Center",
            "subcategory":"Freight",
            "type":"Transportation"
        }
    ],
    "sg:phone":"+90 262 641 8355",
    "sg:postcode":"01370",
    "sg:province":"Kocaeli",
    "wof:name":"Marmara Transport A.s.",
    "wof:placetype":"venue"
},
  "geometry": {"coordinates":[29.881521225,40.8532714844],"type":"Point"}
}