{
  "type": "Feature",
  "properties": {
    "addr:full":"1245.sok. No:49 Yenisehir Zeytinburnu Izmir 34276",
    "addr:housenumber":"no 49",
    "addr:postcode":"34276",
    "addr:street":"Yenisehir Zeytinburnu",
    "iso:country":"TR",
    "sg:address":"1245.sok. No:49 Yenisehir",
    "sg:city":"Zeytinburnu",
    "sg:classifiers":[
        {
            "category":"Shopping",
            "subcategory":"Luggage & Leather Goods",
            "type":"Retail Goods"
        }
    ],
    "sg:phone":"+90 232 449 4849",
    "sg:postcode":"34276",
    "sg:province":"Izmir",
    "sg:tags":[
        "leather-fur",
        "wear"
    ],
    "wof:name":"Modemey Deri Giyim San. Ve Tic. Ltd.sti.",
    "wof:placetype":"venue"
},
  "geometry": {"coordinates":[27.1651916504,38.4260139465],"type":"Point"}
}