{
  "type": "Feature",
  "properties": {
    "addr:full":"Gersan San. Sit. 653.sok. No:79 Beykoz Ankara 37870",
    "addr:housenumber":"no 79",
    "addr:postcode":"37870",
    "addr:street":"Gersan",
    "iso:country":"TR",
    "sg:address":"Gersan San. Sit. 653.sok. No:79",
    "sg:city":"Beykoz",
    "sg:classifiers":[
        {
            "category":"Building & Trades",
            "subcategory":"Landscaping Services",
            "type":"Services"
        }
    ],
    "sg:phone":"+90 312 257 2818",
    "sg:postcode":"37870",
    "sg:province":"Ankara",
    "sg:tags":[
        "landscape"
    ],
    "wof:name":"Turkuaz Peyzaj",
    "wof:placetype":"venue"
},
  "geometry": {"coordinates":[32.8560333252,39.9438743591],"type":"Point"}
}