{
  "type": "Feature",
  "properties": {
    "addr:full":"42. Sok. No: 53 06370 Ostim Ankara Konak Ankara 07110",
    "addr:housenumber":"no 53",
    "addr:postcode":"06370;07110",
    "addr:street":"42 Sok.",
    "iso:country":"TR",
    "sg:address":"42. Sok. No: 53 06370 Ostim Ankara",
    "sg:city":"Konak",
    "sg:classifiers":[
        {
            "category":"Real Estate",
            "subcategory":"Surveying",
            "type":"Services"
        }
    ],
    "sg:phone":"+90 312 354 5258",
    "sg:postcode":"07110",
    "sg:province":"Ankara",
    "sg:tags":[
        "equipment",
        "material",
        "good",
        "-",
        "handling"
    ],
    "wof:name":"Ancasan San Tic Ltd Sti",
    "wof:placetype":"venue"
},
  "geometry": {"coordinates":[32.7491836548,39.9762954712],"type":"Point"}
}