{
  "type": "Feature",
  "properties": {
    "addr:full":"10024 Sok. No: 9 A.o.s.b ?igli Izmir 35620",
    "addr:housenumber":"no 9 a.o.s.b ?",
    "addr:postcode":"10024;35620",
    "addr:street":"Sok.",
    "iso:country":"TR",
    "sg:address":"10024 Sok. No: 9 A.o.s.b",
    "sg:city":"?igli",
    "sg:classifiers":[
        {
            "category":"Professional",
            "subcategory":"Detective & Security Services",
            "type":"Services"
        }
    ],
    "sg:phone":"+90 2323281645729",
    "sg:postcode":"35620",
    "sg:province":"Izmir",
    "sg:tags":[
        "material"
    ],
    "wof:name":"Polimek Elektronik San.tic.a.s.",
    "wof:placetype":"venue"
},
  "geometry": {"coordinates":[27.044577,38.495911],"type":"Point"}
}