{
  "type": "Feature",
  "properties": {
    "addr:full":"Osmanaga Mah. Elif Sk. No:14/1 Kadik? Fomara Istanbul",
    "addr:housenumber":"14 / 1 kadik ?",
    "addr:street":"Osmanaga Mah. Elif Sk. No",
    "iso:country":"TR",
    "sg:address":"Osmanaga Mah. Elif Sk. No:14/1 Kadik?",
    "sg:city":"Fomara",
    "sg:classifiers":[
        {
            "category":"Wholesale",
            "subcategory":"Medical Equipment & Supplies",
            "type":"Manufacturing & Wholesale Goods"
        }
    ],
    "sg:phone":"+90 216 338 1071",
    "sg:province":"Istanbul",
    "sg:tags":[
        "material"
    ],
    "wof:name":"Orpa Paz. Ith. Ihr.",
    "wof:placetype":"venue"
},
  "geometry": {"coordinates":[28.9759254456,41.0123786926],"type":"Point"}
}