{
  "type": "Feature",
  "properties": {
    "addr:full":"Istiklal Cad 285-287 Istanbul 80050",
    "addr:postcode":"285-287;80050",
    "addr:street":"Istiklal Cad",
    "iso:country":"TR",
    "sg:address":"Istiklal Cad 285-287",
    "sg:city":"Istanbul",
    "sg:classifiers":[
        {
            "category":"Banks & Credit Unions",
            "subcategory":"Bank",
            "type":"Services"
        }
    ],
    "sg:phone":"+90 212 244 3193",
    "sg:province":"80050",
    "wof:name":"Yapi Ve Kredi, Bankasi As",
    "wof:placetype":"venue"
},
  "geometry": {"coordinates":[36.161449,36.202663],"type":"Point"}
}