{
  "type": "Feature",
  "properties": {
    "iso:country":"TR",
    "sg:address":"Tahtakale Cd. No:63 Emin?? Istanbul",
    "sg:city":"Emin\u00f6n\u00fc/Ca\u011falo\u011flu",
    "sg:classifiers":[
        {
            "category":"Shopping",
            "subcategory":"Stationery & Office Supplies",
            "type":"Retail Goods"
        }
    ],
    "sg:phone":"+90 212 522 2269",
    "sg:province":"Istanbul",
    "wof:name":"Turhan Kirtasiye San. Tic. Ltd. Sti.",
    "wof:placetype":"venue"
},
  "geometry": {"coordinates":[28.975925,41.012379],"type":"Point"}
}