{
  "type": "Feature",
  "properties": {
    "iso:country":"TR",
    "sg:address":"Inonu Cad. No:156 34620 Sefakoy Istanbul",
    "sg:city":"Beyoglu",
    "sg:classifiers":[
        {
            "category":"Manufacturing",
            "subcategory":"Metals",
            "type":"Manufacturing & Wholesale Goods"
        }
    ],
    "sg:phone":"+90 212 624 3135",
    "sg:postcode":"34437",
    "sg:province":"Istanbul",
    "sg:tags":[
        "metallurgy",
        "metalworking"
    ],
    "wof:name":"Kerim Celik Mamulleri Imalat Tic As",
    "wof:placetype":"venue"
},
  "geometry": {"coordinates":[28.7769985199,40.9971885681],"type":"Point"}
}