{
  "type": "Feature",
  "properties": {
    "iso:country":"TR",
    "sg:address":"Kayisdagi Cd. No:231/b Kayisdagi",
    "sg:city":"Yenidogan",
    "sg:classifiers":[
        {
            "category":"Home & Garden",
            "subcategory":"Kitchen Supply",
            "type":"Retail Goods"
        }
    ],
    "sg:phone":"+90 216 360 9240",
    "sg:postcode":"01260",
    "sg:province":"Istanbul",
    "sg:tags":[
        "wardrobe"
    ],
    "wof:name":"?rge Yapi Eleman A.s.",
    "wof:placetype":"venue"
},
  "geometry": {"coordinates":[29.1404380798,40.9785346985],"type":"Point"}
}