{
  "type": "Feature",
  "properties": {
    "addr:full":"Istiklal Mh. Ertugrul Bey Sk. No.27 Silivri Eskisehir 34750",
    "addr:housenumber":"silivri",
    "addr:postcode":"34750",
    "addr:street":"Eskisehir",
    "iso:country":"TR",
    "sg:address":"Istiklal Mh. Ertugrul Bey Sk. No.27",
    "sg:city":"Silivri",
    "sg:classifiers":[
        {
            "category":"Farming",
            "subcategory":"Poultry Farm",
            "type":"Manufacturing & Wholesale Goods"
        }
    ],
    "sg:phone":"+90 222 335 3821",
    "sg:postcode":"34750",
    "sg:province":"Eskisehir",
    "sg:tags":[
        "poultry-turkey-ostrich"
    ],
    "wof:name":"Sazova Tavuk ?iftligi Ltd.",
    "wof:placetype":"venue"
},
  "geometry": {"coordinates":[30.5166683197,39.7742271423],"type":"Point"}
}