{
  "type": "Feature",
  "properties": {
    "addr:full":"Osman Kavuncu Cad. D?enoglu Vkf. Ish. No:6/302 Tarabya Kayseri 80820",
    "addr:housenumber":"?;302",
    "addr:postcode":"80820",
    "addr:street":"Kavuncu Cad. D;Ish. No 6 /",
    "iso:country":"TR",
    "sg:address":"Osman Kavuncu Cad. D?enoglu Vkf. Ish. No:6/302",
    "sg:city":"Tarabya",
    "sg:classifiers":[
        {
            "category":"Wholesale",
            "subcategory":"Medical Equipment & Supplies",
            "type":"Manufacturing & Wholesale Goods"
        }
    ],
    "sg:phone":"+90 352 336 7177",
    "sg:postcode":"80820",
    "sg:province":"Kayseri",
    "wof:name":"Sukran Medikal",
    "wof:placetype":"venue"
},
  "geometry": {"coordinates":[35.4364013672,38.7450408936],"type":"Point"}
}