{
  "type": "Feature",
  "properties": {
    "iso:country":"TR",
    "sg:address":"122 Sk. No.5",
    "sg:city":"Akhisar",
    "sg:classifiers":[
        {
            "category":"Utilities",
            "subcategory":"Water",
            "type":"Services"
        }
    ],
    "sg:phone":"+90 236 581 3022",
    "sg:postcode":"45200",
    "sg:province":"Manisa",
    "sg:tags":[
        "vegetable",
        "margarine",
        "oil"
    ],
    "wof:name":"Akhisar Zeytinyagi Koop.",
    "wof:placetype":"venue"
},
  "geometry": {"coordinates":[27.4587745667,38.6163673401],"type":"Point"}
}