{
  "type": "Feature",
  "properties": {
    "addr:full":"B??parmakkapi Sk. No:14 D:4 Beyoglu Salipazari Istanbul 80040",
    "addr:housenumber":"? ?;14 d 4",
    "addr:postcode":"80040",
    "addr:street":"B;Parmakkapi Sk. No;Beyoglu Salipazari",
    "iso:country":"TR",
    "sg:address":"B??parmakkapi Sk. No:14 D:4 Beyoglu",
    "sg:city":"Salipazari",
    "sg:classifiers":[
        {
            "category":"Building & Trades",
            "subcategory":"Construction",
            "type":"Services"
        }
    ],
    "sg:phone":"+90 212 249 1554",
    "sg:postcode":"80040",
    "sg:province":"Istanbul",
    "sg:tags":[
        "foundation"
    ],
    "wof:name":"Heinrich Boll Vakfi Turkiye Irtibat Buro.",
    "wof:placetype":"venue"
},
  "geometry": {"coordinates":[28.9825344086,41.0352592468],"type":"Point"}
}