{
  "type": "Feature",
  "properties": {
    "iso:country":"TR",
    "sg:address":"Arif Bey Cad 6",
    "sg:city":"Adapazari",
    "sg:classifiers":[
        {
            "category":"Banks & Credit Unions",
            "subcategory":"Bank",
            "type":"Services"
        }
    ],
    "sg:phone":"+90 454 216 0793",
    "sg:postcode":"54000",
    "sg:province":"Giresun",
    "wof:name":"T?kiye Vakiflar, Bankasi Tao",
    "wof:placetype":"venue"
},
  "geometry": {"coordinates":[29.163097,40.913277],"type":"Point"}
}