{
  "type": "Feature",
  "properties": {
    "addr:full":"Hurriyet Mah. Sumbul Sok. No:25 D:4-6 Sirinevler Istanbul 15040",
    "addr:housenumber":"no 25 d 4-6",
    "addr:postcode":"15040",
    "addr:street":"Hurriyet Mah. Sumbul Sok.;Istanbul",
    "iso:country":"TR",
    "sg:address":"Hurriyet Mah. Sumbul Sok. No:25 D:4-6",
    "sg:city":"Sirinevler",
    "sg:classifiers":[
        {
            "category":"Shopping",
            "subcategory":"Crafts & Fabrics",
            "type":"Retail Goods"
        }
    ],
    "sg:phone":"+90 212 552 7373",
    "sg:postcode":"15040",
    "sg:province":"Istanbul",
    "sg:tags":[
        "embroidery"
    ],
    "wof:name":"Ari Nakis Sanayi Limited Sti.",
    "wof:placetype":"venue"
},
  "geometry": {"coordinates":[28.9861831665,41.0408554077],"type":"Point"}
}