{
  "type": "Feature",
  "properties": {
    "addr:full":"Duacinari Dsi Gulveren Sok. No:53 Mersin Bursa 52750",
    "addr:housenumber":"no 53",
    "addr:postcode":"52750",
    "addr:street":"Gulveren Sok.",
    "iso:country":"TR",
    "sg:address":"Duacinari Dsi Gulveren Sok. No:53",
    "sg:city":"Mersin",
    "sg:classifiers":[
        {
            "category":"Government",
            "subcategory":"Fire Station",
            "type":"Public Place"
        }
    ],
    "sg:phone":"+90 224 361 0351",
    "sg:postcode":"52750",
    "sg:province":"Bursa",
    "sg:tags":[
        "decoration"
    ],
    "wof:name":"Ozkan Mobilya Dekorasyon",
    "wof:placetype":"venue"
},
  "geometry": {"coordinates":[29.0586109161,40.1844291687],"type":"Point"}
}