{
  "type": "Feature",
  "properties": {
    "iso:country":"TR",
    "sg:address":"Dazkiri",
    "sg:city":"Dazkiri",
    "sg:orig_category":"Non-classified Establishments",
    "sg:phone":"+90 272 421 3060",
    "sg:postcode":"03950",
    "sg:province":"Afyon",
    "wof:name":"Turba Tavukculuk",
    "wof:placetype":"venue"
},
  "geometry": {"coordinates":[30.5382652283,38.7579841614],"type":"Point"}
}