{
  "type": "Feature",
  "properties": {
    "addr:full":"Sivrihisar Cd. No:22/b Ikitelli/K\u00fc\u00e7\u00fck\u00e7ekmece Eskisehir 34670",
    "addr:housenumber":"no 22 / b",
    "addr:postcode":"34670",
    "addr:street":"Sivrihisar Cd.;Eskisehir",
    "iso:country":"TR",
    "sg:address":"Sivrihisar Cd. No:22/b",
    "sg:city":"Ikitelli/K\u00fc\u00e7\u00fck\u00e7ekmece",
    "sg:classifiers":[
        {
            "category":"Home & Garden",
            "subcategory":"Hardware",
            "type":"Retail Goods"
        }
    ],
    "sg:phone":"+90 222 334 6103",
    "sg:postcode":"34670",
    "sg:province":"Eskisehir",
    "sg:tags":[
        "store"
    ],
    "wof:name":"Yunuslar A.s.",
    "wof:placetype":"venue"
},
  "geometry": {"coordinates":[30.5154705048,39.7782936096],"type":"Point"}
}