{
  "type": "Feature",
  "properties": {
    "addr:full":"Fak?te Cad. No:21/a Osmangazi Bursa 16330",
    "addr:housenumber":"?;21 / a",
    "addr:postcode":"16330",
    "addr:street":"Te Cad. No;Osmangazi Bursa",
    "iso:country":"TR",
    "sg:address":"Fak?te Cad. No:21/a",
    "sg:city":"Osmangazi",
    "sg:classifiers":[
        {
            "category":"Wholesale",
            "subcategory":"Medical Equipment & Supplies",
            "type":"Manufacturing & Wholesale Goods"
        }
    ],
    "sg:phone":"+90 224 366 5522",
    "sg:postcode":"16330",
    "sg:province":"Bursa",
    "wof:name":"Tum Tip San. Ltd.",
    "wof:placetype":"venue"
},
  "geometry": {"coordinates":[29.0586109161,40.1844291687],"type":"Point"}
}