{
  "type": "Feature",
  "properties": {
    "iso:country":"TR",
    "sg:address":"Birlik San. Sit. 3. Cd. No:135 B.?ekmece",
    "sg:city":"Maltepe",
    "sg:classifiers":[
        {
            "category":"Manufacturing",
            "subcategory":"Tools & Machinery",
            "type":"Manufacturing & Wholesale Goods"
        }
    ],
    "sg:phone":"+90 212 875 1339",
    "sg:postcode":"34852",
    "sg:province":"Istanbul",
    "sg:tags":[
        "machine",
        "industry"
    ],
    "wof:name":"Dema Makina Ins. Taah. Tic. Ltd.",
    "wof:placetype":"venue"
},
  "geometry": {"coordinates":[29.1434249878,40.936882019],"type":"Point"}
}