{
  "type": "Feature",
  "properties": {
    "addr:full":"Kemeralti Cd. No:34 Karak? Maltepe Istanbul 01000",
    "addr:housenumber":"no 34",
    "addr:postcode":"?;01000",
    "addr:street":"Kemeralti Cd.",
    "iso:country":"TR",
    "sg:address":"Kemeralti Cd. No:34 Karak?",
    "sg:city":"Maltepe",
    "sg:classifiers":[
        {
            "category":"Shopping",
            "subcategory":"Computers & Home Electronics",
            "type":"Retail Goods"
        }
    ],
    "sg:phone":"+90 212 245 6662",
    "sg:postcode":"01000",
    "sg:province":"Istanbul",
    "sg:tags":[
        "connector",
        "cable"
    ],
    "wof:name":"T?rk Kablo Mam?lleri Tevzii A.s.",
    "wof:placetype":"venue"
},
  "geometry": {"coordinates":[28.9861831665,41.0408554077],"type":"Point"}
}