{
  "type": "Feature",
  "properties": {
    "addr:full":"Kocamansur Sok.no.45/3 Sisli Ba?esehir Istanbul",
    "iso:country":"TR",
    "sg:address":"Kocamansur Sok.no.45/3 Sisli",
    "sg:city":"Ba?esehir",
    "sg:classifiers":[
        {
            "category":"Banks & Credit Unions",
            "subcategory":"Financial Services",
            "type":"Services"
        }
    ],
    "sg:phone":"+90 212 231 8423",
    "sg:province":"Istanbul",
    "sg:tags":[
        "consultant"
    ],
    "wof:name":"Bulent Soylan Yeminli Mali Musv.a.s.",
    "wof:placetype":"venue"
},
  "geometry": {"coordinates":[28.986371994,41.0604438782],"type":"Point"}
}