{
  "type": "Feature",
  "properties": {
    "iso:country":"TR",
    "sg:address":"Tekin Oteli Karsisi No: 6",
    "sg:city":"Acibadem",
    "sg:classifiers":[
        {
            "category":"Farming",
            "subcategory":"Farm & Veterinary Services",
            "type":"Manufacturing & Wholesale Goods"
        }
    ],
    "sg:phone":"+90 432 216 3493",
    "sg:postcode":"34718",
    "sg:province":"Van",
    "sg:tags":[
        "veterinarian"
    ],
    "wof:name":"Vetisan Veterinerlik Ve Ilaclari Ltd.sti.",
    "wof:placetype":"venue"
},
  "geometry": {"coordinates":[43.3729553223,38.5011177063],"type":"Point"}
}