{
  "type": "Feature",
  "properties": {
    "addr:full":"Meclis-i Mebusan 145/6, Findikli, 80040 Istanbul Istanbul Istanbul",
    "addr:housenumber":"145 / 6",
    "addr:postcode":"80040",
    "addr:street":"Findikli",
    "iso:country":"TR",
    "sg:address":"Meclis-i Mebusan 145/6, Findikli, 80040 Istanbul",
    "sg:city":"Istanbul",
    "sg:classifiers":[
        {
            "category":"Banks & Credit Unions",
            "subcategory":"Bank",
            "type":"Services"
        }
    ],
    "sg:province":"Istanbul",
    "wof:name":"Teb Sigorta As",
    "wof:placetype":"venue"
},
  "geometry": {"coordinates":[28.989296,41.032139],"type":"Point"}
}