{
  "type": "Feature",
  "properties": {
    "iso:country":"TR",
    "sg:address":"E-90 Karayolu ?zeri Toprakkale/osmaniye",
    "sg:city":"Sultanbeyli",
    "sg:classifiers":[
        {
            "category":"Wholesale",
            "subcategory":"Auto Parts",
            "type":"Manufacturing & Wholesale Goods"
        }
    ],
    "sg:phone":"+90 322 654 2200",
    "sg:province":"Adana",
    "sg:tags":[
        "spare"
    ],
    "wof:name":"Ketsan Motorlu Ara?ar-yedek Par? San Ve Tic.ltd.sti.",
    "wof:placetype":"venue"
},
  "geometry": {"coordinates":[35.3250198364,36.9854202271],"type":"Point"}
}