{
  "type": "Feature",
  "properties": {
    "addr:full":"Fetih Mah.inkisaf Sok.no:10 Karatay Konya 42030",
    "addr:housenumber":"10",
    "addr:postcode":"42030",
    "addr:street":"Sok.No",
    "iso:country":"TR",
    "sg:address":"Fetih Mah.inkisaf Sok.no:10",
    "sg:city":"Karatay",
    "sg:classifiers":[
        {
            "category":"Professional",
            "subcategory":"Business Services",
            "type":"Services"
        }
    ],
    "sg:phone":"+90 3553795",
    "sg:postcode":"42030",
    "sg:province":"Konya",
    "sg:tags":[
        "food",
        "product",
        "exporter",
        "aricultural"
    ],
    "wof:name":"Izi S?t A.s",
    "wof:placetype":"venue"
},
  "geometry": {"coordinates":[32.5395545959,37.8700294495],"type":"Point"}
}