{
  "type": "Feature",
  "properties": {
    "iso:country":"TR",
    "sg:address":"Cinarcik Sk. No:73 G.osmanpasa",
    "sg:city":"Beyoglu",
    "sg:classifiers":[
        {
            "category":"Building & Trades",
            "subcategory":"Construction",
            "type":"Services"
        }
    ],
    "sg:phone":"+90 2125641549329",
    "sg:postcode":"46810",
    "sg:province":"Istanbul",
    "sg:tags":[
        "foundation"
    ],
    "wof:name":"Sualti Sporlarini Ve Sualti Degerlerini Koruma Vakfi",
    "wof:placetype":"venue"
},
  "geometry": {"coordinates":[28.9200153351,41.056678772],"type":"Point"}
}