{
  "type": "Feature",
  "properties": {
    "addr:full":"Muslular Mob. Pasj. Osmanbey Cd. No:85 Ineg? Ikitelli/K\u00fc\u00e7\u00fck\u00e7ekmece Bursa",
    "addr:housenumber":"no 85;?",
    "addr:street":"Osmanbey Cd.;Ineg",
    "iso:country":"TR",
    "sg:address":"Muslular Mob. Pasj. Osmanbey Cd. No:85 Ineg?",
    "sg:city":"Ikitelli/K\u00fc\u00e7\u00fck\u00e7ekmece",
    "sg:classifiers":[
        {
            "category":"Wholesale",
            "subcategory":"Home Furnishings",
            "type":"Manufacturing & Wholesale Goods"
        }
    ],
    "sg:phone":"+90 224 715 1020",
    "sg:province":"Bursa",
    "sg:tags":[
        "furniture"
    ],
    "wof:name":"Muslular Mobilya",
    "wof:placetype":"venue"
},
  "geometry": {"coordinates":[29.0398807526,40.1076583862],"type":"Point"}
}