{
  "type": "Feature",
  "properties": {
    "iso:country":"TR",
    "sg:address":"Isiklar Cad. Ihsan ?iviler Apt. No:41 K:2 D:4",
    "sg:city":"Kad\u0131k\u00f6y",
    "sg:classifiers":[
        {
            "category":"Travel",
            "subcategory":"Travel Agent",
            "type":"Entertainment"
        }
    ],
    "sg:phone":"+90 242 311 6662",
    "sg:province":"Antalya",
    "sg:tags":[
        "agency",
        "tourism"
    ],
    "wof:name":"Tourplus Turizm (antalya Sb.)",
    "wof:placetype":"venue"
},
  "geometry": {"coordinates":[30.7092056274,36.8790512085],"type":"Point"}
}