{
  "type": "Feature",
  "properties": {
    "iso:country":"TR",
    "sg:address":"Elmali Mah. 2.sok. Cakiraga Is Merkezi Kat.4 D:28",
    "sg:city":"Karakoy",
    "sg:classifiers":[
        {
            "category":"Freight",
            "type":"Transportation"
        }
    ],
    "sg:phone":"+90 242 247 6396",
    "sg:postcode":"07700",
    "sg:province":"Antalya",
    "sg:tags":[
        "agent",
        "shipping",
        "broker"
    ],
    "wof:name":"Gunmar Shipping .co.ltd.",
    "wof:placetype":"venue"
},
  "geometry": {"coordinates":[30.703135,36.887505],"type":"Point"}
}