{
  "type": "Feature",
  "properties": {
    "iso:country":"TR",
    "sg:address":"?erkezk?",
    "sg:city":"Maltepe",
    "sg:classifiers":[
        {
            "category":"Home & Garden",
            "subcategory":"Home Furnishings",
            "type":"Retail Goods"
        }
    ],
    "sg:phone":"+90 282 726 6020",
    "sg:postcode":"01000",
    "sg:province":"Tekirdag",
    "sg:tags":[
        "textile"
    ],
    "wof:name":"Dinarsu A.s",
    "wof:placetype":"venue"
},
  "geometry": {"coordinates":[27.518995285,40.9782791138],"type":"Point"}
}