{
  "type": "Feature",
  "properties": {
    "addr:full":"Meclis-i Mebusan Cd. Deniz Apt. No:159/a D:1 Beyoglu Ortak? Istanbul 80840",
    "addr:housenumber":"a d 1;?",
    "addr:postcode":"80840",
    "addr:street":"Cd.;Beyoglu Ortak",
    "iso:country":"TR",
    "sg:address":"Meclis-i Mebusan Cd. Deniz Apt. No:159/a D:1 Beyoglu",
    "sg:city":"Ortak?",
    "sg:classifiers":[
        {
            "category":"Organizations",
            "subcategory":"Professional Association",
            "type":"Services"
        }
    ],
    "sg:phone":"+90 212 293 2988",
    "sg:postcode":"80840",
    "sg:province":"Istanbul",
    "wof:name":"Tmmob Gemi Muhendis Odasi",
    "wof:placetype":"venue"
},
  "geometry": {"coordinates":[28.9949550629,41.057056427],"type":"Point"}
}