{
  "type": "Feature",
  "properties": {
    "iso:country":"TR",
    "sg:address":"Fevzi Cakmak Cad 74",
    "sg:city":"Istanbul",
    "sg:classifiers":[
        {
            "category":"Banks & Credit Unions",
            "subcategory":"Bank",
            "type":"Services"
        }
    ],
    "sg:phone":"+90 224220728",
    "sg:province":"Bursa",
    "wof:name":"Iller Bankasi",
    "wof:placetype":"venue"
},
  "geometry": {"coordinates":[29.060438,40.191807],"type":"Point"}
}