{
  "type": "Feature",
  "properties": {
    "addr:full":"1563. Sk. No:6/a B\u00fcy\u00fck\u00e7ekmece Izmir 34905",
    "addr:housenumber":"1563",
    "addr:postcode":"34905",
    "addr:street":"Sk. No 6 / A Bueyuekc\u0327Ekmece",
    "iso:country":"TR",
    "sg:address":"1563. Sk. No:6/a",
    "sg:city":"B\u00fcy\u00fck\u00e7ekmece",
    "sg:classifiers":[
        {
            "category":"Building & Trades",
            "subcategory":"Construction",
            "type":"Services"
        }
    ],
    "sg:phone":"+90 232 486 1290",
    "sg:postcode":"34905",
    "sg:province":"Izmir",
    "sg:tags":[
        "industry",
        "mold"
    ],
    "wof:name":"Isik Kalip San. Koll. Sti.",
    "wof:placetype":"venue"
},
  "geometry": {"coordinates":[27.1693916321,38.4378089905],"type":"Point"}
}