{
  "type": "Feature",
  "properties": {
    "iso:country":"TR",
    "sg:address":"Kocamustafa Efendi Cad. No:3/5",
    "sg:city":"Kagithane",
    "sg:classifiers":[
        {
            "category":"Mining & Drilling",
            "type":"Manufacturing & Wholesale Goods"
        }
    ],
    "sg:phone":"+90 252214937677",
    "sg:postcode":"34406",
    "sg:province":"Mugla",
    "sg:tags":[
        "industry",
        "mine"
    ],
    "wof:name":"Hedef Madden Patlayici Ve San. Mad. Ins.taahhut Ltd.sti.",
    "wof:placetype":"venue"
},
  "geometry": {"coordinates":[28.3658008575,37.2196006775],"type":"Point"}
}