{
  "type": "Feature",
  "properties": {
    "addr:full":"57. Sk. No:64-69 Ostim Melikgazi Ankara 38070",
    "addr:housenumber":"57",
    "addr:postcode":"38070",
    "addr:street":"Sk. No 64-69",
    "iso:country":"TR",
    "sg:address":"57. Sk. No:64-69 Ostim",
    "sg:city":"Melikgazi",
    "sg:classifiers":[
        {
            "category":"Manufacturing",
            "subcategory":"Metals",
            "type":"Manufacturing & Wholesale Goods"
        }
    ],
    "sg:phone":"+90 312 354 7621",
    "sg:postcode":"38070",
    "sg:province":"Ankara",
    "sg:tags":[
        "aluminium",
        "industry"
    ],
    "wof:name":"Safter Metal San. Tic. Ltd. Sti.",
    "wof:placetype":"venue"
},
  "geometry": {"coordinates":[32.7455329895,39.9797782898],"type":"Point"}
}