{
  "type": "Feature",
  "properties": {
    "addr:full":"Kemankes Mah. Agac Tulumba Sok. 7/a Karak? Bah\u00e7elievler Istanbul 06500",
    "addr:housenumber":"7 / a;?",
    "addr:postcode":"06500",
    "addr:street":"Kemankes Mah. Agac Tulumba Sok.;Karak",
    "iso:country":"TR",
    "sg:address":"Kemankes Mah. Agac Tulumba Sok. 7/a Karak?",
    "sg:city":"Bah\u00e7elievler",
    "sg:orig_category":"Environment Technolojy",
    "sg:phone":"+90 212252791718",
    "sg:postcode":"06500",
    "sg:province":"Istanbul",
    "wof:name":"Bilgin Su Aritma Sistemleri",
    "wof:placetype":"venue"
},
  "geometry": {"coordinates":[28.9861831665,41.0408554077],"type":"Point"}
}