{
  "type": "Feature",
  "properties": {
    "iso:country":"TR",
    "sg:address":"Muallim Koy Pk.119 Gebze Izmit",
    "sg:city":"B Cigli",
    "sg:orig_category":"General Industrial Products",
    "sg:phone":"+90 26275913114",
    "sg:province":"Kocaeli",
    "wof:name":"Ucer Zimpara Tasi San.tic.ltd.",
    "wof:placetype":"venue"
},
  "geometry": {"coordinates":[29.9483566284,40.7759857178],"type":"Point"}
}