{
  "type": "Feature",
  "properties": {
    "iso:country":"TR",
    "sg:address":"Zeytinlik Mah. Hoca Hasan Sok. Ata Apt. No:6/1 Bakirkoy",
    "sg:city":"Nisantasi",
    "sg:classifiers":[
        {
            "category":"Shopping",
            "subcategory":"Gifts & Souvenirs",
            "type":"Retail Goods"
        }
    ],
    "sg:phone":"+90 212 543 6019",
    "sg:postcode":"80200",
    "sg:province":"Istanbul",
    "wof:name":"Bozoglu Grup Reklam Ve Tanitim Urunleri",
    "wof:placetype":"venue"
},
  "geometry": {"coordinates":[28.8434429169,40.9957122803],"type":"Point"}
}