{
  "type": "Feature",
  "properties": {
    "addr:full":"Bagdat C. No.243 Maltepe Istanbul 01000",
    "addr:postcode":"01000",
    "addr:street":"Maltepe",
    "iso:country":"TR",
    "sg:address":"Bagdat C. No.243",
    "sg:city":"Maltepe",
    "sg:classifiers":[
        {
            "category":"Wholesale",
            "subcategory":"Farm Supplies",
            "type":"Manufacturing & Wholesale Goods"
        }
    ],
    "sg:phone":"+90 216 371 9135",
    "sg:postcode":"01000",
    "sg:province":"Istanbul",
    "sg:tags":[
        "feed",
        "industry"
    ],
    "wof:name":"Mersin Yem Fab. A.s.",
    "wof:placetype":"venue"
},
  "geometry": {"coordinates":[29.057182312,40.9728546143],"type":"Point"}
}