{
  "type": "Feature",
  "properties": {
    "addr:full":"Klodfarer Cd. Alibey Ishani No:39/a Sultanahmet Mahmutbey Istanbul 46600",
    "addr:housenumber":"39 / a",
    "addr:postcode":"46600",
    "addr:street":"Klodfarer Cd. Alibey Ishani No",
    "iso:country":"TR",
    "sg:address":"Klodfarer Cd. Alibey Ishani No:39/a Sultanahmet",
    "sg:city":"Mahmutbey",
    "sg:classifiers":[
        {
            "category":"Shopping",
            "subcategory":"Stationery & Office Supplies",
            "type":"Retail Goods"
        }
    ],
    "sg:phone":"+90 212 518 1780",
    "sg:postcode":"46600",
    "sg:province":"Istanbul",
    "wof:name":"Bilim Kirtasiye",
    "wof:placetype":"venue"
},
  "geometry": {"coordinates":[28.975925,41.012379],"type":"Point"}
}