{
  "type": "Feature",
  "properties": {
    "addr:full":"Gimat 4. Blok No: 81 Macunk? Yenimahalle 06370 Merkez Ankara Yakapinar-misis Ankara",
    "addr:housenumber":"4 blok no 81;?",
    "addr:postcode":"06370",
    "addr:street":"Gimat;Macunk",
    "iso:country":"TR",
    "sg:address":"Gimat 4. Blok No: 81 Macunk? Yenimahalle 06370 Merkez Ankara",
    "sg:city":"Yakapinar-misis",
    "sg:classifiers":[
        {
            "category":"Farming",
            "subcategory":"Livestock Farm",
            "type":"Manufacturing & Wholesale Goods"
        }
    ],
    "sg:phone":"+90 312 397 4540",
    "sg:province":"Ankara",
    "sg:tags":[
        "agriculture"
    ],
    "wof:name":"Zafer Ihracat Ithalat Gida San. Ve Tic. Ltd Sti",
    "wof:placetype":"venue"
},
  "geometry": {"coordinates":[32.8560333252,39.9438743591],"type":"Point"}
}