{
  "type": "Feature",
  "properties": {
    "addr:full":"Sanayi Cad. No:16 Kurtk?- Pendik Istanbul 34916",
    "addr:housenumber":"16;?",
    "addr:postcode":"34916",
    "addr:street":"Sanayi Cad. No",
    "iso:country":"TR",
    "sg:address":"Sanayi Cad. No:16 Kurtk?-",
    "sg:city":"Pendik",
    "sg:classifiers":[
        {
            "category":"Manufacturing",
            "subcategory":"Glass & Minerals",
            "type":"Manufacturing & Wholesale Goods"
        }
    ],
    "sg:phone":"+90 216 378 1121",
    "sg:postcode":"34916",
    "sg:province":"Istanbul",
    "sg:tags":[
        "glass-mirror"
    ],
    "wof:name":"Dogus Cam Sanayi Ticaret Ltd.sti.",
    "wof:placetype":"venue"
},
  "geometry": {"coordinates":[29.2916927338,40.9024200439],"type":"Point"}
}