{
  "type": "Feature",
  "properties": {
    "addr:full":"Yaslikoyu Cad. 23/5 Sirkeci Istanbul 34112",
    "addr:housenumber":"23 / 5",
    "addr:postcode":"34112",
    "addr:street":"Yaslikoyu Cad.",
    "iso:country":"TR",
    "sg:address":"Yaslikoyu Cad. 23/5",
    "sg:city":"Sirkeci",
    "sg:classifiers":[
        {
            "category":"Manufacturing",
            "subcategory":"Textiles",
            "type":"Manufacturing & Wholesale Goods"
        }
    ],
    "sg:phone":"+90 212 511 6630",
    "sg:postcode":"34112",
    "sg:province":"Istanbul",
    "sg:tags":[
        "linen",
        "yarn"
    ],
    "wof:name":"Baltas Ic Ve Dis Ticaret A.s.",
    "wof:placetype":"venue"
},
  "geometry": {"coordinates":[28.811378479,40.9989509583],"type":"Point"}
}