{
  "type": "Feature",
  "properties": {
    "iso:country":"TR",
    "sg:address":"Avukat Cad. No:193",
    "sg:city":"Kagithane",
    "sg:classifiers":[
        {
            "category":"Freight",
            "type":"Transportation"
        }
    ],
    "sg:phone":"+90 212 241 2140",
    "sg:postcode":"34406",
    "sg:province":"Istanbul",
    "sg:tags":[
        "packing",
        "industry"
    ],
    "wof:name":"Ambalaj 2000 Oluklu Mukavva Koli San.",
    "wof:placetype":"venue"
},
  "geometry": {"coordinates":[28.9777507782,41.054523468],"type":"Point"}
}