{
  "type": "Feature",
  "properties": {
    "addr:full":"Koyunlar Cd. Park Sk. Macunk? Eskisehir",
    "addr:housenumber":"?",
    "addr:street":"Koyunlar Cd. Park Sk. Macunk",
    "iso:country":"TR",
    "sg:address":"Koyunlar Cd. Park Sk.",
    "sg:city":"Macunk?",
    "sg:classifiers":[
        {
            "category":"Manufacturing",
            "subcategory":"Food",
            "type":"Manufacturing & Wholesale Goods"
        }
    ],
    "sg:phone":"+90 222 233 7184",
    "sg:province":"Eskisehir",
    "sg:tags":[
        "wholesaler"
    ],
    "wof:name":"Basak Gida Ith.ihr.ltd.sti.",
    "wof:placetype":"venue"
},
  "geometry": {"coordinates":[30.5175457001,39.7700805664],"type":"Point"}
}