{
  "type": "Feature",
  "properties": {
    "iso:country":"TR",
    "sg:address":"Sanayi Cad. No:4",
    "sg:city":"Cifteler",
    "sg:classifiers":[
        {
            "category":"Farming",
            "subcategory":"Farm & Veterinary Services",
            "type":"Manufacturing & Wholesale Goods"
        }
    ],
    "sg:phone":"+90 2225412730541",
    "sg:postcode":"26700",
    "sg:province":"Eskisehir",
    "sg:tags":[
        "veterinarian"
    ],
    "wof:name":"Hasan Cavusoglu",
    "wof:placetype":"venue"
},
  "geometry": {"coordinates":[30.5250930786,39.772983551],"type":"Point"}
}