{
  "type": "Feature",
  "properties": {
    "iso:country":"TR",
    "sg:address":"M.sevket Pasa Mh. Sivas Sk. No.17",
    "sg:city":"Okmeydani",
    "sg:classifiers":[
        {
            "category":"Food & Beverages",
            "subcategory":"Dairy",
            "type":"Retail Goods"
        }
    ],
    "sg:phone":"+90 212 237 0940",
    "sg:postcode":"43050",
    "sg:province":"Istanbul",
    "sg:tags":[
        "pruducts",
        "milk"
    ],
    "wof:name":"?inar S?t ?r?nl.ltd.sti.",
    "wof:placetype":"venue"
},
  "geometry": {"coordinates":[29.0044536591,41.0773658752],"type":"Point"}
}