{
  "type": "Feature",
  "properties": {
    "iso:country":"TR",
    "sg:address":"Koroglu Cad. No:67/2",
    "sg:city":"G.o.pasa",
    "sg:classifiers":[
        {
            "category":"Farming",
            "subcategory":"Farm & Veterinary Services",
            "type":"Manufacturing & Wholesale Goods"
        }
    ],
    "sg:phone":"+90 312 446 3535",
    "sg:province":"Ankara",
    "sg:tags":[
        "clinic"
    ],
    "wof:name":"Gokhan Okyay",
    "wof:placetype":"venue"
},
  "geometry": {"coordinates":[29.1818790436,41.0414924622],"type":"Point"}
}