{
  "type": "Feature",
  "properties": {
    "addr:full":"Oto San. Sit. ?elik Sk. No:52/2 4.levent 46000 Istanbul",
    "addr:housenumber":"52 / 2 4.levent",
    "addr:postcode":"46000",
    "addr:street":"Elik Sk. No",
    "iso:country":"TR",
    "sg:address":"Oto San. Sit. ?elik Sk. No:52/2 4.levent",
    "sg:city":"46000",
    "sg:classifiers":[
        {
            "category":"Shopping",
            "subcategory":"Stationery & Office Supplies",
            "type":"Retail Goods"
        }
    ],
    "sg:phone":"+90 212 279 0473",
    "sg:province":"Istanbul",
    "sg:tags":[
        "paper"
    ],
    "wof:name":"Plastek Plastik Kagit ?rn. Ltd. Sti.",
    "wof:placetype":"venue"
},
  "geometry": {"coordinates":[29.0159626007,41.0816841125],"type":"Point"}
}