{
  "type": "Feature",
  "properties": {
    "iso:country":"TR",
    "sg:address":"Mahmut Pasha Street",
    "sg:city":"Istanbul",
    "sg:classifiers":[
        {
            "category":"Banks & Credit Unions",
            "subcategory":"Bank",
            "type":"Services"
        }
    ],
    "sg:phone":"+90 392 228 3207",
    "sg:province":"Mersin",
    "wof:name":"Cyprus Turkish Coop., Central Bank Ltd.",
    "wof:placetype":"venue"
},
  "geometry": {"coordinates":[34.632542,36.7999],"type":"Point"}
}