{
  "type": "Feature",
  "properties": {
    "iso:country":"TR",
    "sg:address":"Perpa Ticaret Merkezi, B-blok, Kat:11, No:1743,",
    "sg:city":"Okmeydani",
    "sg:orig_category":"Orthopedical Materials",
    "sg:phone":"+90 2123207370729",
    "sg:postcode":"34384",
    "sg:province":"Istanbul",
    "wof:name":"Pro-tek Tibbi Cihaz Ve Hizmetleri Ticaret Ltd. Sti",
    "wof:placetype":"venue"
},
  "geometry": {"coordinates":[28.9688739777,41.0575942993],"type":"Point"}
}