{
  "type": "Feature",
  "properties": {
    "iso:country":"TR",
    "sg:address":"Abdi Ipekci Cad 64",
    "sg:city":"Istanbul",
    "sg:classifiers":[
        {
            "category":"Banks & Credit Unions",
            "subcategory":"Bank",
            "type":"Services"
        }
    ],
    "sg:phone":"+90 212 565 1430",
    "sg:province":"34160",
    "wof:name":"Iktisat Bankasi, T?k As",
    "wof:placetype":"venue"
},
  "geometry": {"coordinates":[28.87059,41.017696],"type":"Point"}
}