{
  "type": "Feature",
  "properties": {
    "iso:country":"TR",
    "sg:address":"Merkez Cd. Kirazli Sk. No.8/2",
    "sg:city":"Sefak?",
    "sg:classifiers":[
        {
            "category":"Shopping",
            "subcategory":"Clothing, Apparel, & Fashions",
            "type":"Retail Goods"
        }
    ],
    "sg:phone":"+90 212 584 0984",
    "sg:province":"Istanbul",
    "sg:tags":[
        "ready",
        "wear"
    ],
    "wof:name":"Rece Tekstil A.s.",
    "wof:placetype":"venue"
},
  "geometry": {"coordinates":[28.8224849701,41.0356330872],"type":"Point"}
}