{
  "type": "Feature",
  "properties": {
    "iso:country":"TR",
    "sg:address":"Sirma Sk. No:5 Siteler",
    "sg:city":"Siteler",
    "sg:classifiers":[
        {
            "category":"Manufacturing",
            "subcategory":"Wood Products",
            "type":"Manufacturing & Wholesale Goods"
        }
    ],
    "sg:phone":"+90 312 349 0518",
    "sg:postcode":"06660",
    "sg:province":"Ankara",
    "sg:tags":[
        "forest"
    ],
    "wof:name":"Inta Aga? Mam?l. Paz. A.s.",
    "wof:placetype":"venue"
},
  "geometry": {"coordinates":[32.8905487061,39.9611167908],"type":"Point"}
}