{
  "type": "Feature",
  "properties": {
    "iso:country":"TR",
    "sg:address":"Ankara Karayolu 7.km.",
    "sg:city":"Kartal",
    "sg:classifiers":[
        {
            "category":"Freight",
            "type":"Transportation"
        }
    ],
    "sg:phone":"+90 258 268 0580",
    "sg:postcode":"34876",
    "sg:province":"Denizli",
    "sg:tags":[
        "packing",
        "industry"
    ],
    "wof:name":"Dentas A.s",
    "wof:placetype":"venue"
},
  "geometry": {"coordinates":[29.0864906311,37.773525238],"type":"Point"}
}