{
  "type": "Feature",
  "properties": {
    "addr:full":"1202/6 Sk. No.48 Yenisehir Izmir 31750",
    "addr:housenumber":"1202 / 6",
    "addr:postcode":"31750",
    "addr:street":"Sk. No.48 Yenisehir",
    "iso:country":"TR",
    "sg:address":"1202/6 Sk. No.48",
    "sg:city":"Yenisehir",
    "sg:classifiers":[
        {
            "category":"Utilities",
            "subcategory":"Water",
            "type":"Services"
        }
    ],
    "sg:phone":"+90 232 433 5533",
    "sg:postcode":"31750",
    "sg:province":"Izmir",
    "sg:tags":[
        "vegetable",
        "margarine",
        "oil"
    ],
    "wof:name":"Sahil Yag San. A.s.",
    "wof:placetype":"venue"
},
  "geometry": {"coordinates":[27.1674423218,38.4269065857],"type":"Point"}
}