{
  "type": "Feature",
  "properties": {
    "addr:full":"Sair Esref Blv. Vefa Apt No:83/3 Alsancak Merkez Izmir 51200",
    "addr:housenumber":"83 / 3",
    "addr:postcode":"51200",
    "addr:street":"Blv. Vefa Apt No",
    "iso:country":"TR",
    "sg:address":"Sair Esref Blv. Vefa Apt No:83/3 Alsancak",
    "sg:city":"Merkez",
    "sg:classifiers":[
        {
            "category":"Manufacturing",
            "subcategory":"Chemicals & Compounds",
            "type":"Manufacturing & Wholesale Goods"
        }
    ],
    "sg:phone":"+90 232 464 3864",
    "sg:postcode":"51200",
    "sg:province":"Izmir",
    "sg:tags":[
        "medicine"
    ],
    "wof:name":"Orucogullari Kim. San. Ltd. Sti.",
    "wof:placetype":"venue"
},
  "geometry": {"coordinates":[27.1296863556,38.4186973572],"type":"Point"}
}