{
  "type": "Feature",
  "properties": {
    "addr:full":"Meryem Sok. No: 8 Yakacik ?aglayan Istanbul",
    "addr:housenumber":"no 8 yakacik ?",
    "addr:street":"Meryem Sok.",
    "iso:country":"TR",
    "sg:address":"Meryem Sok. No: 8 Yakacik",
    "sg:city":"?aglayan",
    "sg:classifiers":[
        {
            "category":"Retail",
            "subcategory":"Storage",
            "type":"Services"
        }
    ],
    "sg:phone":"+90 216 377 0257",
    "sg:province":"Istanbul",
    "sg:tags":[
        "shelving",
        "system"
    ],
    "wof:name":"Atlas Magaza Ekipmanlari Paz.ve San.a.s.",
    "wof:placetype":"venue"
},
  "geometry": {"coordinates":[29.270634,40.940968],"type":"Point"}
}