{
  "type": "Feature",
  "properties": {
    "iso:country":"TR",
    "sg:address":"43/a Sk. No:18 Ostim",
    "sg:city":"Okmeydani",
    "sg:classifiers":[
        {
            "category":"Shopping",
            "subcategory":"Stationery & Office Supplies",
            "type":"Retail Goods"
        }
    ],
    "sg:phone":"+90 312 354 6978",
    "sg:postcode":"43050",
    "sg:province":"Ankara",
    "wof:name":"Temel Dagitim Ltd. Sti.",
    "wof:placetype":"venue"
},
  "geometry": {"coordinates":[32.745285,39.974121],"type":"Point"}
}