{
  "type": "Feature",
  "properties": {
    "addr:full":"Barbaros Bulv. Cd. Han No:125 Besiktas Istanbul 75200",
    "addr:housenumber":"125",
    "addr:postcode":"75200",
    "addr:street":"Barbaros Bulv. Cd. Han No",
    "iso:country":"TR",
    "sg:address":"Barbaros Bulv. Cd. Han No:125",
    "sg:city":"Besiktas",
    "sg:classifiers":[
        {
            "category":"Mining & Drilling",
            "type":"Manufacturing & Wholesale Goods"
        }
    ],
    "sg:phone":"+90 212 274 7200",
    "sg:postcode":"75200",
    "sg:province":"Istanbul",
    "sg:tags":[
        "industry",
        "mine"
    ],
    "wof:name":"Camis Madencilik A.s.",
    "wof:placetype":"venue"
},
  "geometry": {"coordinates":[29.1522827148,41.0140419006],"type":"Point"}
}