{
  "type": "Feature",
  "properties": {
    "addr:full":"Talatpasa Bulvari No:37/b Bah\u00e7elievler Istanbul 34180",
    "addr:housenumber":"no 37 / b",
    "addr:postcode":"34180",
    "addr:street":"Talatpasa Bulvari",
    "iso:country":"TR",
    "sg:address":"Talatpasa Bulvari No:37/b",
    "sg:city":"Bah\u00e7elievler",
    "sg:classifiers":[
        {
            "category":"Utilities",
            "subcategory":"Natural Gas",
            "type":"Services"
        }
    ],
    "sg:phone":"+90 212 539 0875",
    "sg:postcode":"34180",
    "sg:province":"Istanbul",
    "sg:tags":[
        "tank-heating-natural"
    ],
    "wof:name":"Deltamak Ltd. Sti.",
    "wof:placetype":"venue"
},
  "geometry": {"coordinates":[28.9861831665,41.0408554077],"type":"Point"}
}