{
  "type": "Feature",
  "properties": {
    "addr:full":"Atat?k Bul 16/c Aydin 09400 01513",
    "addr:housenumber":"16 / c",
    "addr:postcode":"09400",
    "addr:street":"Bul;Aydin",
    "iso:country":"TR",
    "sg:address":"Atat?k Bul 16/c",
    "sg:city":"Aydin",
    "sg:classifiers":[
        {
            "category":"Banks & Credit Unions",
            "subcategory":"Bank",
            "type":"Services"
        }
    ],
    "sg:phone":"+90 256 612 6157",
    "sg:postcode":"01513",
    "sg:province":"09400",
    "wof:name":"Kocbank As",
    "wof:placetype":"venue"
},
  "geometry": {"coordinates":[34.628223,36.797989],"type":"Point"}
}