{
  "type": "Feature",
  "properties": {
    "iso:country":"TR",
    "sg:address":"Esenler Cd. No:39 Bayrampasa",
    "sg:city":"Bagcilar",
    "sg:classifiers":[
        {
            "category":"Shopping",
            "subcategory":"Stationery & Office Supplies",
            "type":"Retail Goods"
        }
    ],
    "sg:phone":"+90 212 567 2115",
    "sg:postcode":"33115",
    "sg:province":"Istanbul",
    "sg:tags":[
        "furniture"
    ],
    "wof:name":"Tursan Buro Mob.",
    "wof:placetype":"venue"
},
  "geometry": {"coordinates":[28.8663959503,41.0345916748],"type":"Point"}
}