{
  "type": "Feature",
  "properties": {
    "addr:full":"Kayisdagi Mah.atilla Cad. No:79 Kad\u0131k\u00f6y Istanbul 34990",
    "addr:housenumber":"79",
    "addr:postcode":"34990",
    "addr:street":"Mah.Atilla Cad. No;Istanbul",
    "iso:country":"TR",
    "sg:address":"Kayisdagi Mah.atilla Cad. No:79",
    "sg:city":"Kad\u0131k\u00f6y",
    "sg:classifiers":[
        {
            "category":"Shopping",
            "subcategory":"Stationery & Office Supplies",
            "type":"Retail Goods"
        }
    ],
    "sg:phone":"+90 216 365 7106",
    "sg:postcode":"34990",
    "sg:province":"Istanbul",
    "sg:tags":[
        "furniture"
    ],
    "wof:name":"Iskur Limited Sti.",
    "wof:placetype":"venue"
},
  "geometry": {"coordinates":[29.1446094513,40.9859352112],"type":"Point"}
}