{
  "type": "Feature",
  "properties": {
    "iso:country":"TR",
    "sg:address":"Gaziler Cad. 406/b Yenisehir",
    "sg:city":"Balgat",
    "sg:classifiers":[
        {
            "category":"Shopping",
            "subcategory":"Pharmacy",
            "type":"Retail Goods"
        }
    ],
    "sg:phone":"+90 2325322877127",
    "sg:postcode":"63510",
    "sg:province":"Izmir",
    "sg:tags":[
        "store",
        "drug"
    ],
    "wof:name":"Eczamarket",
    "wof:placetype":"venue"
},
  "geometry": {"coordinates":[27.1423015594,38.4251480103],"type":"Point"}
}