{
  "type": "Feature",
  "properties": {
    "addr:full":"Seyit Nizam Cd. G?aydin Apt. No:36 Zeytinburnu Iskenderun Istanbul 31200",
    "addr:housenumber":"?",
    "addr:postcode":"31200",
    "addr:street":"Seyit Nizam Cd. G;Zeytinburnu",
    "iso:country":"TR",
    "sg:address":"Seyit Nizam Cd. G?aydin Apt. No:36 Zeytinburnu",
    "sg:city":"Iskenderun",
    "sg:classifiers":[
        {
            "category":"Manufacturing",
            "subcategory":"Tools & Machinery",
            "type":"Manufacturing & Wholesale Goods"
        }
    ],
    "sg:phone":"+90 212 582 3511",
    "sg:postcode":"31200",
    "sg:province":"Istanbul",
    "sg:tags":[
        "machine",
        "industry"
    ],
    "wof:name":"G?r?msan Makina San. Koll. Sti.",
    "wof:placetype":"venue"
},
  "geometry": {"coordinates":[28.8735599518,40.9942359924],"type":"Point"}
}