{
  "type": "Feature",
  "properties": {
    "iso:country":"TR",
    "sg:address":"Ebusuud Cad. No:45 Sirkeci",
    "sg:city":"B\u00fcy\u00fck\u00e7ekmece",
    "sg:classifiers":[
        {
            "category":"Shopping",
            "subcategory":"Bicycles & Sporting Goods",
            "type":"Retail Goods"
        }
    ],
    "sg:phone":"+90 212513490915",
    "sg:postcode":"34524",
    "sg:province":"Istanbul",
    "sg:tags":[
        "motorcycle"
    ],
    "wof:name":"Arzu Bisiklet Tic. Ve San. A.s.",
    "wof:placetype":"venue"
},
  "geometry": {"coordinates":[28.975925,41.012379],"type":"Point"}
}