{
  "type": "Feature",
  "properties": {
    "addr:full":"G. His Mah. 7 Eyl? Cad. ?zt?k Pasaji No:22/e Beyoglu Aydin 46810",
    "addr:housenumber":"7;?;?;?;22 / e",
    "addr:postcode":"46810",
    "addr:street":"G.;Mah.;Cad.;K Pasaji No;Beyoglu Aydin",
    "iso:country":"TR",
    "sg:address":"G. His Mah. 7 Eyl? Cad. ?zt?k Pasaji No:22/e",
    "sg:city":"Beyoglu",
    "sg:classifiers":[
        {
            "category":"Shopping",
            "subcategory":"Clothing, Apparel, & Fashions",
            "type":"Retail Goods"
        }
    ],
    "sg:phone":"+90 256 213 2009",
    "sg:postcode":"46810",
    "sg:province":"Aydin",
    "sg:tags":[
        "ready",
        "wear"
    ],
    "wof:name":"Menderes Teks. Baski Konf. San. Tic.",
    "wof:placetype":"venue"
},
  "geometry": {"coordinates":[28.4863967896,37.8117027283],"type":"Point"}
}