{
  "type": "Feature",
  "properties": {
    "iso:country":"TR",
    "sg:address":"Cinarli Mah. 13.sk. G?de Apt. K.2 D:5",
    "sg:city":"Turhal",
    "sg:classifiers":[
        {
            "category":"Wholesale",
            "subcategory":"Farm Supplies",
            "type":"Manufacturing & Wholesale Goods"
        }
    ],
    "sg:phone":"+90 322 459 2242",
    "sg:postcode":"60300",
    "sg:province":"Adana",
    "sg:tags":[
        "feed",
        "industry"
    ],
    "wof:name":"Redif Gida Pazarlama Sanayi Ve Ticaret Ltd.sti.",
    "wof:placetype":"venue"
},
  "geometry": {"coordinates":[35.3137359619,37.0007171631],"type":"Point"}
}