{
  "type": "Feature",
  "properties": {
    "iso:country":"TR",
    "sg:address":"H. Efendi Mah. Gen?ik Cad. No:50/c",
    "sg:city":"Mersin",
    "sg:classifiers":[
        {
            "category":"Wholesale",
            "subcategory":"Medical Equipment & Supplies",
            "type":"Manufacturing & Wholesale Goods"
        }
    ],
    "sg:phone":"+90 256 213 9514",
    "sg:postcode":"52750",
    "sg:province":"Aydin",
    "wof:name":"Cagri Medikal",
    "wof:placetype":"venue"
},
  "geometry": {"coordinates":[27.8324394226,37.8409690857],"type":"Point"}
}