{
  "type": "Feature",
  "properties": {
    "addr:full":"Cengiz T. Cd. No:7 K.k? Ikitelli/K\u00fc\u00e7\u00fck\u00e7ekmece Istanbul 34660",
    "addr:housenumber":"no 7 k.k ?",
    "addr:postcode":"34660",
    "addr:street":"T. Cd.;Ikitelli",
    "iso:country":"TR",
    "sg:address":"Cengiz T. Cd. No:7 K.k?",
    "sg:city":"Ikitelli/K\u00fc\u00e7\u00fck\u00e7ekmece",
    "sg:classifiers":[
        {
            "category":"Shopping",
            "subcategory":"Stationery & Office Supplies",
            "type":"Retail Goods"
        }
    ],
    "sg:phone":"+90 212 615 0022",
    "sg:postcode":"34660",
    "sg:province":"Istanbul",
    "wof:name":"Sakin Kirtasiye",
    "wof:placetype":"venue"
},
  "geometry": {"coordinates":[29.052183,40.995239],"type":"Point"}
}