{
  "type": "Feature",
  "properties": {
    "addr:full":"Bilkent Plaza B3 Blok No:11 Bilkent Ankara",
    "iso:country":"TR",
    "sg:address":"Bilkent Plaza B3 Blok No:11",
    "sg:city":"Bilkent",
    "sg:classifiers":[
        {
            "category":"Building & Trades",
            "subcategory":"Landscaping Services",
            "type":"Services"
        }
    ],
    "sg:phone":"+90 312",
    "sg:province":"Ankara",
    "sg:tags":[
        "landscape"
    ],
    "wof:name":"Kalemci Group",
    "wof:placetype":"venue"
},
  "geometry": {"coordinates":[32.8560333252,39.9438743591],"type":"Point"}
}