{
  "type": "Feature",
  "properties": {
    "addr:full":"Des Sanayi Sitesi 1.cad.2 D.blok No:7 Y.dudullu Istanbul",
    "addr:housenumber":"1.cad.2 d.blok no 7",
    "addr:street":"Des Sanayi Sitesi",
    "iso:country":"TR",
    "sg:address":"Des Sanayi Sitesi 1.cad.2 D.blok No:7",
    "sg:city":"Y.dudullu",
    "sg:orig_category":"Des Istanbul",
    "sg:phone":"+90 216 420 6049",
    "sg:province":"Istanbul",
    "wof:name":"Mayis Makina Sand Blasting Equipment Sanayi Vetic",
    "wof:placetype":"venue"
},
  "geometry": {"coordinates":[28.9110412598,41.0490264893],"type":"Point"}
}