{
  "type": "Feature",
  "properties": {
    "iso:country":"TR",
    "sg:address":"Litros Yolu 2. Mat Sit. 2. Blok A 3 Topkapi",
    "sg:city":"Bagcilar",
    "sg:classifiers":[
        {
            "category":"Shopping",
            "subcategory":"Stationery & Office Supplies",
            "type":"Retail Goods"
        }
    ],
    "sg:phone":"+90 212 544 5210",
    "sg:postcode":"33115",
    "sg:province":"Istanbul",
    "sg:tags":[
        "paper"
    ],
    "wof:name":"S?nmez Kagit?ilik",
    "wof:placetype":"venue"
},
  "geometry": {"coordinates":[28.9759254456,41.0123786926],"type":"Point"}
}