{
  "type": "Feature",
  "properties": {
    "iso:country":"TR",
    "sg:address":"Sabuncu Han Cad. Atmaca Ishani No.31/13 Tahtakale, Emin?? Istanbul",
    "sg:city":"\u00c7ankaya",
    "sg:orig_category":"Bijouterie",
    "sg:phone":"+90 212 519 5354",
    "sg:province":"Istanbul",
    "wof:name":"Nsa Bijuteri",
    "wof:placetype":"venue"
},
  "geometry": {"coordinates":[28.975925,41.012379],"type":"Point"}
}