{
  "type": "Feature",
  "properties": {
    "addr:full":"Sabuncu Han Cad. Atmaca Ishani No.31/13 Tahtakale, Emin?? Istanbul \u00c7ankaya Istanbul",
    "addr:housenumber":"no.31 / 13;? ?",
    "addr:street":"Cad.;Ishani;Tahtakale Emin",
    "iso:country":"TR",
    "sg:address":"Sabuncu Han Cad. Atmaca Ishani No.31/13 Tahtakale, Emin?? Istanbul",
    "sg:city":"\u00c7ankaya",
    "sg:orig_category":"Bijouterie",
    "sg:phone":"+90 212 519 5354",
    "sg:province":"Istanbul",
    "wof:name":"Nsa Bijuteri",
    "wof:placetype":"venue"
},
  "geometry": {"coordinates":[28.975925,41.012379],"type":"Point"}
}