{
  "type": "Feature",
  "properties": {
    "iso:country":"TR",
    "sg:address":"Mesih Pasa Cd. No:44/6",
    "sg:city":"Laleli",
    "sg:classifiers":[
        {
            "category":"Home & Garden",
            "subcategory":"Home Furnishings",
            "type":"Retail Goods"
        }
    ],
    "sg:phone":"+90 212 518 7950",
    "sg:postcode":"24300",
    "sg:province":"Istanbul",
    "sg:tags":[
        "-curtains",
        "upholstery"
    ],
    "wof:name":"Bayteks Tekstil Pazarlama",
    "wof:placetype":"venue"
},
  "geometry": {"coordinates":[28.969957,41.009197],"type":"Point"}
}