{
  "type": "Feature",
  "properties": {
    "addr:full":"Abidinpasa Cad. 104 Sk. No:5/24 Osmangazi Adana 16330",
    "addr:housenumber":"104;24",
    "addr:postcode":"16330",
    "addr:street":"Abidinpasa Cad.;Sk. No 5 /",
    "iso:country":"TR",
    "sg:address":"Abidinpasa Cad. 104 Sk. No:5/24",
    "sg:city":"Osmangazi",
    "sg:classifiers":[
        {
            "category":"Wholesale",
            "subcategory":"Medical Equipment & Supplies",
            "type":"Manufacturing & Wholesale Goods"
        }
    ],
    "sg:phone":"+90 322 452 5370",
    "sg:postcode":"16330",
    "sg:province":"Adana",
    "wof:name":"Toros-an Ltd. Sti.",
    "wof:placetype":"venue"
},
  "geometry": {"coordinates":[35.3250198364,36.9854202271],"type":"Point"}
}