{
  "type": "Feature",
  "properties": {
    "iso:country":"TR",
    "sg:address":"Poyrazli Sk. No:27/29 Merter",
    "sg:city":"Yenibosna",
    "sg:classifiers":[
        {
            "category":"Manufacturing",
            "subcategory":"Rubber & Plastics",
            "type":"Manufacturing & Wholesale Goods"
        }
    ],
    "sg:phone":"+90 212 575 7792",
    "sg:postcode":"43270",
    "sg:province":"Istanbul",
    "sg:tags":[
        "industry"
    ],
    "wof:name":"Can Plastik San.",
    "wof:placetype":"venue"
},
  "geometry": {"coordinates":[28.874048233,41.0175209045],"type":"Point"}
}