{
  "type": "Feature",
  "properties": {
    "iso:country":"TR",
    "sg:address":"Batalgazi Mah. Selcukhan Cad. Kizilcik Sok. No: 12 Sultanbeyli",
    "sg:city":"4.levent",
    "sg:classifiers":[
        {
            "category":"Home & Garden",
            "subcategory":"Furniture",
            "type":"Retail Goods"
        }
    ],
    "sg:phone":"+90 216 592 1477",
    "sg:province":"Istanbul",
    "sg:tags":[
        "armchair",
        "sofa"
    ],
    "wof:name":"Ruya Yayli Yataklari",
    "wof:placetype":"venue"
},
  "geometry": {"coordinates":[29.2749996185,40.9641189575],"type":"Point"}
}