{
  "type": "Feature",
  "properties": {
    "addr:full":"Fenari Mh. Kemal Kaynas Cd. No:36/b Merkez Ikitelli/K\u00fc\u00e7\u00fck\u00e7ekmece Karaman 34670",
    "addr:housenumber":"no 36 / b;ikitelli / kuec\u0327uekc\u0327ekmece",
    "addr:postcode":"34670",
    "addr:street":"Fenari Mh. Kemal Kaynas Cd.;Merkez;Karaman",
    "iso:country":"TR",
    "sg:address":"Fenari Mh. Kemal Kaynas Cd. No:36/b Merkez",
    "sg:city":"Ikitelli/K\u00fc\u00e7\u00fck\u00e7ekmece",
    "sg:orig_category":"Aluminium Carpentary",
    "sg:phone":"+90 338 212 1804",
    "sg:postcode":"34670",
    "sg:province":"Karaman",
    "wof:name":"Celikler Ins. Malz. San.",
    "wof:placetype":"venue"
},
  "geometry": {"coordinates":[33.2219009399,37.1814002991],"type":"Point"}
}