{
  "type": "Feature",
  "properties": {
    "iso:country":"TR",
    "sg:address":"Sinanpasa Kopru Sokak Celik Is Merkezi 10/70 Besiktas",
    "sg:city":"Istanbul",
    "sg:classifiers":[
        {
            "category":"Professional",
            "subcategory":"Computer Services",
            "type":"Services"
        }
    ],
    "sg:postcode":"34440",
    "sg:tags":[
        "bots",
        "semantics",
        "intelligent-agents"
    ],
    "sg:website":"http://www.botego.com/english.htm",
    "wof:name":"Botego",
    "wof:placetype":"venue"
},
  "geometry": {"coordinates":[29.003631,41.043039],"type":"Point"}
}