{
  "type": "Feature",
  "properties": {
    "iso:country":"TR",
    "sg:address":"Yukari Dudullu Organize B?egsi 3 Cad. No. 1 34776 ?mraniye Istanbul",
    "sg:city":"Kartal",
    "sg:classifiers":[
        {
            "category":"Professional",
            "subcategory":"Engineering",
            "type":"Services"
        }
    ],
    "sg:phone":"+90 216 364 8760",
    "sg:postcode":"46000",
    "sg:province":"Istanbul",
    "sg:tags":[
        "machine",
        "-",
        "mechanical"
    ],
    "wof:name":"Royal Conta San Ve Tic As",
    "wof:placetype":"venue"
},
  "geometry": {"coordinates":[28.9861831665,41.0408554077],"type":"Point"}
}