{
  "type": "Feature",
  "properties": {
    "addr:full":"Sivas Karayolu 14.km. Okmeydani Yozgat 43050",
    "addr:postcode":"43050",
    "addr:street":"Karayolu;Okmeydani",
    "iso:country":"TR",
    "sg:address":"Sivas Karayolu 14.km.",
    "sg:city":"Okmeydani",
    "sg:classifiers":[
        {
            "category":"Freight",
            "type":"Transportation"
        }
    ],
    "sg:phone":"+90 354 223 6019",
    "sg:postcode":"43050",
    "sg:province":"Yozgat",
    "sg:tags":[
        "packing",
        "industry"
    ],
    "wof:name":"Ensarplastik San.ve Tic.a.s.",
    "wof:placetype":"venue"
},
  "geometry": {"coordinates":[34.8055000305,39.8212013245],"type":"Point"}
}