{
  "type": "Feature",
  "properties": {
    "iso:country":"TR",
    "sg:address":"3. Sn. Sit. 6 Blok",
    "sg:city":"Ikitelli/K\u00fc\u00e7\u00fck\u00e7ekmece",
    "sg:classifiers":[
        {
            "category":"Manufacturing",
            "subcategory":"Tools & Machinery",
            "type":"Manufacturing & Wholesale Goods"
        }
    ],
    "sg:phone":"+90 256 225 1770",
    "sg:postcode":"34670",
    "sg:province":"Aydin",
    "sg:tags":[
        "machine",
        "industry"
    ],
    "wof:name":"Sua Mak. San. A.s.",
    "wof:placetype":"venue"
},
  "geometry": {"coordinates":[28.4863967896,37.8117027283],"type":"Point"}
}