{
  "type": "Feature",
  "properties": {
    "addr:full":"Ceyhan Yolu 5.km. No: 315 Ikitelli/K\u00fc\u00e7\u00fck\u00e7ekmece Adana 34660",
    "addr:housenumber":"5.km no 315",
    "addr:postcode":"34660",
    "addr:street":"Ceyhan Yolu;Adana",
    "iso:country":"TR",
    "sg:address":"Ceyhan Yolu 5.km. No: 315",
    "sg:city":"Ikitelli/K\u00fc\u00e7\u00fck\u00e7ekmece",
    "sg:classifiers":[
        {
            "category":"Manufacturing",
            "subcategory":"Tools & Machinery",
            "type":"Manufacturing & Wholesale Goods"
        }
    ],
    "sg:phone":"+90 322 346 1023",
    "sg:postcode":"34660",
    "sg:province":"Adana",
    "sg:tags":[
        "machine",
        "industry"
    ],
    "wof:name":"Sarmaksan Makina San.ve Ticaret As.",
    "wof:placetype":"venue"
},
  "geometry": {"coordinates":[35.3137359619,37.0007171631],"type":"Point"}
}