{
  "type": "Feature",
  "properties": {
    "addr:full":"Ikitelli Organize Sanayi B?gesi Metal Is Sanayi Sitesi 8.blok No:1 Ikitelli/K\u00fc\u00e7\u00fck\u00e7ekmece Istanbul 34660",
    "addr:housenumber":"?;no",
    "addr:postcode":"34660",
    "addr:street":"Organize Sanayi B;Sitesi",
    "iso:country":"TR",
    "sg:address":"Ikitelli Organize Sanayi B?gesi Metal Is Sanayi Sitesi 8.blok No:1",
    "sg:city":"Ikitelli/K\u00fc\u00e7\u00fck\u00e7ekmece",
    "sg:classifiers":[
        {
            "category":"Building & Trades",
            "subcategory":"Electrical",
            "type":"Services"
        }
    ],
    "sg:phone":"+90 212 671 2771",
    "sg:postcode":"34660",
    "sg:province":"Istanbul",
    "sg:tags":[
        "equipment",
        "lighting"
    ],
    "wof:name":"Model Avize Ticaret Ve San.ltd.sti",
    "wof:placetype":"venue"
},
  "geometry": {"coordinates":[29.0496292114,41.0075798035],"type":"Point"}
}