{
  "type": "Feature",
  "properties": {
    "iso:country":"TR",
    "sg:address":"Turizm Cad.no.1",
    "sg:city":"Aksaray",
    "sg:classifiers":[
        {
            "category":"Banks & Credit Unions",
            "subcategory":"Bank",
            "type":"Services"
        }
    ],
    "sg:phone":"+90 212 512 0410",
    "sg:postcode":"31030",
    "sg:province":"68100",
    "wof:name":"T?kiye Emlak, Bankasi As",
    "wof:placetype":"venue"
},
  "geometry": {"coordinates":[34.026196,38.371422],"type":"Point"}
}