{
  "type": "Feature",
  "properties": {
    "addr:full":"Atat?k Bulvari No:118/3 Kusadasi Aydin 09400",
    "addr:housenumber":"no;/ 3",
    "addr:postcode":"09400",
    "addr:street":"K Bulvari;Kusadasi Aydin",
    "iso:country":"TR",
    "sg:address":"Atat?k Bulvari No:118/3",
    "sg:city":"Kusadasi",
    "sg:classifiers":[
        {
            "category":"Transit Center",
            "subcategory":"Freight",
            "type":"Transportation"
        }
    ],
    "sg:phone":"+90 256 614 2999",
    "sg:postcode":"09400",
    "sg:province":"Aydin",
    "wof:name":"Dutilh Koll. Sti.",
    "wof:placetype":"venue"
},
  "geometry": {"coordinates":[28.4863967896,37.8117027283],"type":"Point"}
}