{
  "type": "Feature",
  "properties": {
    "addr:full":"Direkli Han Sk. Ambarci Is Merkezi No: 25 Kat: 4 Daire: 95 Emin?? Istanbul Kizilay Istanbul 23050",
    "addr:housenumber":"no 25 kat 4;95;? ?",
    "addr:postcode":"23050",
    "addr:street":"Daire",
    "iso:country":"TR",
    "sg:address":"Direkli Han Sk. Ambarci Is Merkezi No: 25 Kat: 4 Daire: 95 Emin?? Istanbul",
    "sg:city":"Kizilay",
    "sg:classifiers":[
        {
            "category":"Manufacturing",
            "subcategory":"Chemicals & Compounds",
            "type":"Manufacturing & Wholesale Goods"
        }
    ],
    "sg:phone":"+90 212511828351",
    "sg:postcode":"23050",
    "sg:province":"Istanbul",
    "sg:tags":[
        "medicine"
    ],
    "wof:name":"Istanbul Kimya Ve Gida San. Tic. Ltd. Sti.",
    "wof:placetype":"venue"
},
  "geometry": {"coordinates":[28.9759254456,41.0123786926],"type":"Point"}
}