{
  "type": "Feature",
  "properties": {
    "addr:full":"Davutpasa Cd. Tim-2 No:12/98 Topkapi Istanbul 24620",
    "addr:housenumber":"tim-2 no 12 / 98",
    "addr:postcode":"24620",
    "addr:street":"Davutpasa Cd.",
    "iso:country":"TR",
    "sg:address":"Davutpasa Cd. Tim-2 No:12/98",
    "sg:city":"Topkapi",
    "sg:classifiers":[
        {
            "category":"Home & Garden",
            "subcategory":"Household Appliances",
            "type":"Retail Goods"
        }
    ],
    "sg:phone":"+90 212 544 2042",
    "sg:postcode":"24620",
    "sg:province":"Istanbul",
    "sg:tags":[
        "conditioner",
        "air"
    ],
    "wof:name":"As Sog. Klima San.",
    "wof:placetype":"venue"
},
  "geometry": {"coordinates":[28.9759254456,41.0123786926],"type":"Point"}
}