{
  "type": "Feature",
  "properties": {
    "addr:full":"Sanayi Cad. No:80 Bornova Nazilli Izmir 65600",
    "addr:postcode":"65600",
    "addr:street":"Sanayi Cad. No 80",
    "iso:country":"TR",
    "sg:address":"Sanayi Cad. No:80 Bornova",
    "sg:city":"Nazilli",
    "sg:classifiers":[
        {
            "category":"Shopping",
            "subcategory":"Clothing, Apparel, & Fashions",
            "type":"Retail Goods"
        }
    ],
    "sg:phone":"+90 232 435 1978",
    "sg:postcode":"65600",
    "sg:province":"Izmir",
    "sg:tags":[
        "ready",
        "wear"
    ],
    "wof:name":"Aktar Giyim Ltd.",
    "wof:placetype":"venue"
},
  "geometry": {"coordinates":[27.1854438782,38.4441604614],"type":"Point"}
}