{
  "type": "Feature",
  "properties": {
    "addr:full":"Kervan Ge?ez Sk. No:7/a Mecidiyek? ?aglayan Istanbul",
    "addr:housenumber":"? ?",
    "addr:street":"Ez Sk. No 7 / A Mecidiyek",
    "iso:country":"TR",
    "sg:address":"Kervan Ge?ez Sk. No:7/a Mecidiyek?",
    "sg:city":"?aglayan",
    "sg:classifiers":[
        {
            "category":"Shopping",
            "subcategory":"Stationery & Office Supplies",
            "type":"Retail Goods"
        }
    ],
    "sg:phone":"+90 212 267 3147",
    "sg:province":"Istanbul",
    "wof:name":"G?ven Kirtasiye",
    "wof:placetype":"venue"
},
  "geometry": {"coordinates":[28.975925,41.012379],"type":"Point"}
}