{
  "type": "Feature",
  "properties": {
    "addr:full":"Siyavuspasa Sok. Asilsoy Ticaret Merkezi Kat 2 No. 87 34450 Mercan Istanbul Cagaloglu Istanbul 34440",
    "addr:housenumber":"asilsoy ticaret merkezi kat 2 no. 87",
    "addr:postcode":"34450;34440",
    "addr:street":"Siyavuspasa Sok.",
    "iso:country":"TR",
    "sg:address":"Siyavuspasa Sok. Asilsoy Ticaret Merkezi Kat 2 No. 87 34450 Mercan Istanbul",
    "sg:city":"Cagaloglu",
    "sg:classifiers":[
        {
            "category":"Shopping",
            "type":"Retail Goods"
        }
    ],
    "sg:phone":"+90 212 512 7310",
    "sg:postcode":"34440",
    "sg:province":"Istanbul",
    "sg:tags":[
        "finished",
        "-",
        "metallic"
    ],
    "wof:name":"Asil Tic Ve Ev Gerecleri Paz Ltd Sti",
    "wof:placetype":"venue"
},
  "geometry": {"coordinates":[28.9666919708,41.0404586792],"type":"Point"}
}