{
  "type": "Feature",
  "properties": {
    "iso:country":"TR",
    "sg:address":"Tersane Cad. Arapkayyum Sk. No:12 Karakoy",
    "sg:city":"Ikitelli/K\u00fc\u00e7\u00fck\u00e7ekmece",
    "sg:classifiers":[
        {
            "category":"Home & Garden",
            "subcategory":"Kitchen Supply",
            "type":"Retail Goods"
        }
    ],
    "sg:phone":"+90 212 254 7260",
    "sg:postcode":"34660",
    "sg:province":"Istanbul",
    "sg:tags":[
        "steel",
        "utensil"
    ],
    "wof:name":"Porcesan San. Ve Tic. A.s.",
    "wof:placetype":"venue"
},
  "geometry": {"coordinates":[29.049629,41.00758],"type":"Point"}
}