{
  "type": "Feature",
  "properties": {
    "addr:full":"Zafer Mah.yesil Sok. No:19 Yenibosna Yenikent Istanbul 06938",
    "addr:housenumber":"no 19",
    "addr:postcode":"06938",
    "addr:street":"Mah.Yesil Sok.",
    "iso:country":"TR",
    "sg:address":"Zafer Mah.yesil Sok. No:19 Yenibosna",
    "sg:city":"Yenikent",
    "sg:classifiers":[
        {
            "category":"Home & Garden",
            "subcategory":"Kitchen Supply",
            "type":"Retail Goods"
        }
    ],
    "sg:phone":"+90 212 652 1799",
    "sg:postcode":"06938",
    "sg:province":"Istanbul",
    "sg:tags":[
        "wardrobe"
    ],
    "wof:name":"Zengin Dekorasyon",
    "wof:placetype":"venue"
},
  "geometry": {"coordinates":[28.8350582123,40.9960021973],"type":"Point"}
}