{
  "type": "Feature",
  "properties": {
    "iso:country":"TR",
    "sg:address":"Rauf Orbay Cad. 11/c Icmeler-",
    "sg:city":"Tuzla",
    "sg:classifiers":[
        {
            "category":"Freight",
            "type":"Transportation"
        }
    ],
    "sg:phone":"+90 216 446 7417",
    "sg:postcode":"01900",
    "sg:province":"Istanbul",
    "sg:tags":[
        "agent",
        "shipping",
        "broker"
    ],
    "wof:name":"Gs (general Store) Denizcilik Ltd.sti.",
    "wof:placetype":"venue"
},
  "geometry": {"coordinates":[29.293064,40.842873],"type":"Point"}
}