{
  "type": "Feature",
  "properties": {
    "addr:full":"K. Karabekir Cad. No:41/112 Iskitler K.cekmece Ankara",
    "addr:housenumber":"41 / 112",
    "addr:street":"K. Karabekir Cad. No;Iskitler K.Cekmece",
    "iso:country":"TR",
    "sg:address":"K. Karabekir Cad. No:41/112 Iskitler",
    "sg:city":"K.cekmece",
    "sg:classifiers":[
        {
            "category":"Professional",
            "subcategory":"Testing Lab",
            "type":"Services"
        }
    ],
    "sg:phone":"+90 312 341 3388",
    "sg:province":"Ankara",
    "sg:tags":[
        "laboratory",
        "material"
    ],
    "wof:name":"Can Tip Ltd. Sti.",
    "wof:placetype":"venue"
},
  "geometry": {"coordinates":[36.3196144104,41.2798347473],"type":"Point"}
}