{
  "type": "Feature",
  "properties": {
    "addr:full":"Cankaya Mh.k.milliye Cd. Seviindik Ish.no:1/5 Mersin I?el 52750",
    "addr:housenumber":"1 / 5",
    "addr:postcode":"? el 52750",
    "addr:street":"Cd.;Ish.No",
    "iso:country":"TR",
    "sg:address":"Cankaya Mh.k.milliye Cd. Seviindik Ish.no:1/5",
    "sg:city":"Mersin",
    "sg:classifiers":[
        {
            "category":"Professional",
            "subcategory":"Business Services",
            "type":"Services"
        }
    ],
    "sg:phone":"+90 324 233 3525",
    "sg:postcode":"52750",
    "sg:province":"I?el",
    "sg:tags":[
        "food",
        "product",
        "exporter",
        "aricultural"
    ],
    "wof:name":"Inter-sim San.ltd.sti.",
    "wof:placetype":"venue"
},
  "geometry": {"coordinates":[37.7128486633,41.0530204773],"type":"Point"}
}