{
  "type": "Feature",
  "properties": {
    "iso:country":"TR",
    "sg:address":"Spor Cd. Yakacik Yan Yol No:45 Kartal",
    "sg:city":"Karak\u00f6y",
    "sg:classifiers":[
        {
            "category":"Wholesale",
            "subcategory":"Vending Machines",
            "type":"Manufacturing & Wholesale Goods"
        }
    ],
    "sg:phone":"+90 216 374 5234",
    "sg:province":"Istanbul",
    "sg:tags":[
        "rod",
        "welding"
    ],
    "wof:name":"Can Kaynak San. Tic.",
    "wof:placetype":"venue"
},
  "geometry": {"coordinates":[29.1848335266,40.8910751343],"type":"Point"}
}