{
  "type": "Feature",
  "properties": {
    "addr:full":"Ophthalmic Products Sales \u00c7ankaya Ankara 06420",
    "addr:postcode":"06420",
    "iso:country":"TR",
    "sg:address":"Ophthalmic Products Sales",
    "sg:city":"\u00c7ankaya",
    "sg:classifiers":[
        {
            "category":"Wholesale",
            "subcategory":"Medical Equipment & Supplies",
            "type":"Manufacturing & Wholesale Goods"
        }
    ],
    "sg:phone":"+90 312 433 1142",
    "sg:postcode":"06420",
    "sg:province":"Ankara",
    "sg:tags":[
        "material"
    ],
    "wof:name":"Mikron Oftalmoloji",
    "wof:placetype":"venue"
},
  "geometry": {"coordinates":[32.8585090637,39.9217453003],"type":"Point"}
}