{
  "type": "Feature",
  "properties": {
    "addr:full":"Ismet Ionu Cad. No:153 Sel?uklu Eskisehir",
    "addr:housenumber":"153;?",
    "addr:street":"Ionu Cad. No;Uklu Eskisehir",
    "iso:country":"TR",
    "sg:address":"Ismet Ionu Cad. No:153",
    "sg:city":"Sel?uklu",
    "sg:classifiers":[
        {
            "category":"Wholesale",
            "subcategory":"Auto Parts",
            "type":"Manufacturing & Wholesale Goods"
        }
    ],
    "sg:phone":"+90 222335391323",
    "sg:province":"Eskisehir",
    "sg:tags":[
        "spare"
    ],
    "wof:name":"Eskisehir Jant San. Ve Tic. A.s.",
    "wof:placetype":"venue"
},
  "geometry": {"coordinates":[30.5154705048,39.7782936096],"type":"Point"}
}