{
  "type": "Feature",
  "properties": {
    "addr:full":"Kiz Kulesi Sk.no:44 G.o.p. Cankaya Ankara 07080",
    "addr:housenumber":"44",
    "addr:postcode":"07080",
    "addr:street":"Sk.No",
    "iso:country":"TR",
    "sg:address":"Kiz Kulesi Sk.no:44 G.o.p.",
    "sg:city":"Cankaya",
    "sg:classifiers":[
        {
            "category":"Government",
            "subcategory":"Embassy",
            "type":"Public Place"
        }
    ],
    "sg:phone":"+90 312 446 7485",
    "sg:postcode":"07080",
    "sg:province":"Ankara",
    "sg:tags":[
        "foreign"
    ],
    "wof:name":"L?bnan Cumh.b?y?kel?iligi",
    "wof:placetype":"venue"
},
  "geometry": {"coordinates":[32.8719558716,39.8902320862],"type":"Point"}
}