{
  "type": "Feature",
  "properties": {
    "addr:full":"1.top. Tic. Mrk. No: 201-202 Cevizlibag Fatih Istanbul 34470",
    "addr:postcode":"34470",
    "addr:street":"No 201-202",
    "iso:country":"TR",
    "sg:address":"1.top. Tic. Mrk. No: 201-202 Cevizlibag",
    "sg:city":"Fatih",
    "sg:orig_category":"Printinh House",
    "sg:phone":"+90 212 482 0335",
    "sg:postcode":"34470",
    "sg:province":"Istanbul",
    "wof:name":"Erol Etiket Matbaacilik Ambalaj San. Tic. Ltd. Sti.",
    "wof:placetype":"venue"
},
  "geometry": {"coordinates":[29.0481739044,41.0933380127],"type":"Point"}
}