{
  "type": "Feature",
  "properties": {
    "iso:country":"TR",
    "sg:address":"Cemalpasa Mah.282.sok. Aksogan Apt.no:19/2",
    "sg:city":"Ikitelli/K\u00fc\u00e7\u00fck\u00e7ekmece",
    "sg:classifiers":[
        {
            "category":"Manufacturing",
            "subcategory":"Tools & Machinery",
            "type":"Manufacturing & Wholesale Goods"
        }
    ],
    "sg:phone":"+90 322 454 3339",
    "sg:postcode":"34670",
    "sg:province":"Adana",
    "sg:tags":[
        "machine",
        "industry"
    ],
    "wof:name":"?niversal Makina Imalat Montaj San. Ve Tic. Ltd. Sti.",
    "wof:placetype":"venue"
},
  "geometry": {"coordinates":[35.3137359619,37.0007171631],"type":"Point"}
}