{
  "type": "Feature",
  "properties": {
    "iso:country":"TR",
    "sg:address":"In??cd. 17. Sk. No:28 Esenler",
    "sg:city":"B?y?k?ekmece",
    "sg:classifiers":[
        {
            "category":"Home & Garden",
            "subcategory":"Kitchen Supply",
            "type":"Retail Goods"
        }
    ],
    "sg:phone":"+90 212 611 4273",
    "sg:postcode":"34900",
    "sg:province":"Istanbul",
    "sg:tags":[
        "fire",
        "extinguisher"
    ],
    "wof:name":"Ammar Yangin S?nd?rme Cihaz.",
    "wof:placetype":"venue"
},
  "geometry": {"coordinates":[28.906583786,41.0073623657],"type":"Point"}
}