{
  "type": "Feature",
  "properties": {
    "addr:full":"Mahmutbey Yolu No:103 Mahmutbey Istanbul 46600",
    "addr:housenumber":"no",
    "addr:postcode":"46600",
    "addr:street":"Mahmutbey Yolu;Mahmutbey",
    "iso:country":"TR",
    "sg:address":"Mahmutbey Yolu No:103",
    "sg:city":"Mahmutbey",
    "sg:classifiers":[
        {
            "category":"Shopping",
            "subcategory":"Clothing, Apparel, & Fashions",
            "type":"Retail Goods"
        }
    ],
    "sg:phone":"+90 212 550 4389",
    "sg:postcode":"46600",
    "sg:province":"Istanbul",
    "sg:tags":[
        "ready",
        "wear"
    ],
    "wof:name":"Akyigit Tekstil Konfeksiyon Ve Magazacilik Sanayi Ticaret A.s.",
    "wof:placetype":"venue"
},
  "geometry": {"coordinates":[28.8336677551,41.0328521729],"type":"Point"}
}