{
  "type": "Feature",
  "properties": {
    "addr:full":"Cumhuriyet Cad. 64 Yalova 81910 17900",
    "addr:housenumber":"64",
    "addr:postcode":"81910 17900",
    "addr:street":"Cumhuriyet Cad.",
    "iso:country":"TR",
    "sg:address":"Cumhuriyet Cad. 64",
    "sg:city":"Yalova",
    "sg:classifiers":[
        {
            "category":"Banks & Credit Unions",
            "subcategory":"Bank",
            "type":"Services"
        }
    ],
    "sg:phone":"+90 216 814 4236",
    "sg:postcode":"17900",
    "sg:province":"81910",
    "wof:name":"Etibank Bao",
    "wof:placetype":"venue"
},
  "geometry": {"coordinates":[33.776108,41.374882],"type":"Point"}
}