{
  "type": "Feature",
  "properties": {
    "addr:full":"Koza Sok.75/6 Gop- Cankaya Ankara 07080",
    "addr:postcode":"07080",
    "iso:country":"TR",
    "sg:address":"Koza Sok.75/6 Gop-",
    "sg:city":"Cankaya",
    "sg:classifiers":[
        {
            "category":"Building & Trades",
            "subcategory":"Landscaping Services",
            "type":"Services"
        }
    ],
    "sg:phone":"+90 312 436 9493",
    "sg:postcode":"07080",
    "sg:province":"Ankara",
    "sg:tags":[
        "landscape"
    ],
    "wof:name":"Armasan Aritma Mad.ins. Ve Gida San.tic.ltd.sti.",
    "wof:placetype":"venue"
},
  "geometry": {"coordinates":[32.8560333252,39.9438743591],"type":"Point"}
}