{
  "type": "Feature",
  "properties": {
    "iso:country":"TR",
    "sg:address":"Caferaga Moda Cd. No:123",
    "sg:city":"Kad\u0131k\u00f6y",
    "sg:classifiers":[
        {
            "category":"Airport",
            "subcategory":"International",
            "type":"Transportation"
        }
    ],
    "sg:phone":"+90 216 338 1560",
    "sg:postcode":"34990",
    "sg:province":"Istanbul",
    "wof:name":"L.s.s. Uluslararasi Nakliyat Ins. Taah. Turizm A.s.",
    "wof:placetype":"venue"
},
  "geometry": {"coordinates":[29.3354206085,40.8783607483],"type":"Point"}
}