{
  "type": "Feature",
  "properties": {
    "addr:full":"Atat?k Bulv. ?nl?is Merk. A Blok No:23/30-44 Unkapani Istanbul 55020",
    "addr:housenumber":"?;blok no 23 / 30-44",
    "addr:postcode":"?;merk.;55020",
    "addr:street":"K Bulv.;A;Unkapani Istanbul",
    "iso:country":"TR",
    "sg:address":"Atat?k Bulv. ?nl?is Merk. A Blok No:23/30-44",
    "sg:city":"Unkapani",
    "sg:classifiers":[
        {
            "category":"Manufacturing",
            "subcategory":"Textiles",
            "type":"Manufacturing & Wholesale Goods"
        }
    ],
    "sg:phone":"+90 212 534 1755",
    "sg:postcode":"55020",
    "sg:province":"Istanbul",
    "sg:tags":[
        "cloth",
        "worker"
    ],
    "wof:name":"Is Elbise. Piramit. San. Tic. Ltd. Sti.",
    "wof:placetype":"venue"
},
  "geometry": {"coordinates":[28.9759254456,41.0123786926],"type":"Point"}
}