{
  "type": "Feature",
  "properties": {
    "addr:full":"K??k?, Cebeci Cad. No.94 G.o.pasa Bayrampasa Istanbul 36100",
    "addr:housenumber":"? ? k ?",
    "addr:postcode":"36100",
    "addr:street":"Cebeci Cad. No.94 G.O.Pasa Bayrampasa",
    "iso:country":"TR",
    "sg:address":"K??k?, Cebeci Cad. No.94 G.o.pasa",
    "sg:city":"Bayrampasa",
    "sg:classifiers":[
        {
            "category":"Freight",
            "type":"Transportation"
        }
    ],
    "sg:phone":"+90 212 537 2442",
    "sg:postcode":"36100",
    "sg:province":"Istanbul",
    "sg:tags":[
        "packing",
        "industry"
    ],
    "wof:name":"T?rkoglu Ambalaj San. Ve Tic. A.s.",
    "wof:placetype":"venue"
},
  "geometry": {"coordinates":[28.8951797485,41.0794487],"type":"Point"}
}