{
  "type": "Feature",
  "properties": {
    "iso:country":"TR",
    "sg:address":"Kinali Mevkii Silivri",
    "sg:city":"\u00dcmraniye",
    "sg:classifiers":[
        {
            "category":"Shopping",
            "subcategory":"Stationery & Office Supplies",
            "type":"Retail Goods"
        }
    ],
    "sg:phone":"+90 212 715 2323",
    "sg:postcode":"81230",
    "sg:province":"Istanbul",
    "sg:tags":[
        "furniture"
    ],
    "wof:name":"Tuna Celik A.s.",
    "wof:placetype":"venue"
},
  "geometry": {"coordinates":[28.6022090912,41.0162391663],"type":"Point"}
}