{
  "type": "Feature",
  "properties": {
    "iso:country":"TR",
    "sg:address":"Muallim Naci Cd. No:100 Ortak?",
    "sg:city":"Findikzade-fatih",
    "sg:classifiers":[
        {
            "category":"Building & Trades",
            "subcategory":"Construction",
            "type":"Services"
        }
    ],
    "sg:phone":"+90 212 259 3262",
    "sg:province":"Istanbul",
    "sg:tags":[
        "foundation"
    ],
    "wof:name":"Turkpetrol Vakfi",
    "wof:placetype":"venue"
},
  "geometry": {"coordinates":[29.030626297,41.0498008728],"type":"Point"}
}