{
  "type": "Feature",
  "properties": {
    "addr:full":"A.ipekci Cad. No:5 Nisantasi Istanbul 25370",
    "addr:postcode":"25370",
    "addr:street":"A.Ipekci Cad. No 5 Nisantasi",
    "iso:country":"TR",
    "sg:address":"A.ipekci Cad. No:5",
    "sg:city":"Nisantasi",
    "sg:classifiers":[
        {
            "category":"Shopping",
            "subcategory":"Clothing, Apparel, & Fashions",
            "type":"Retail Goods"
        }
    ],
    "sg:phone":"+90 212230496123",
    "sg:postcode":"25370",
    "sg:province":"Istanbul",
    "sg:tags":[
        "ready",
        "wear"
    ],
    "wof:name":"Gerboy Tekstil San A.s.",
    "wof:placetype":"venue"
},
  "geometry": {"coordinates":[29.2806739807,40.8698043823],"type":"Point"}
}