{
  "type": "Feature",
  "properties": {
    "addr:full":"Bahriye Cad. No.20 Kasimpasa Etiler Istanbul 07010",
    "addr:postcode":"07010",
    "addr:street":"Bahriye Cad. No.20 Kasimpasa",
    "iso:country":"TR",
    "sg:address":"Bahriye Cad. No.20 Kasimpasa",
    "sg:city":"Etiler",
    "sg:classifiers":[
        {
            "category":"Manufacturing",
            "subcategory":"Wood Products",
            "type":"Manufacturing & Wholesale Goods"
        }
    ],
    "sg:phone":"+90 212 250 5411",
    "sg:postcode":"07010",
    "sg:province":"Istanbul",
    "sg:tags":[
        "forest"
    ],
    "wof:name":"Akdeniz Orman Urunleri San. Ve Tic. A.s.",
    "wof:placetype":"venue"
},
  "geometry": {"coordinates":[28.9669322968,41.0349311829],"type":"Point"}
}