{
  "type": "Feature",
  "properties": {
    "addr:full":"1471. Sk. No:3 Alsancak Sel?uklu Izmir 42300",
    "addr:housenumber":"1471",
    "addr:postcode":"? uklu;42300",
    "addr:street":"Sk. No 3",
    "iso:country":"TR",
    "sg:address":"1471. Sk. No:3 Alsancak",
    "sg:city":"Sel?uklu",
    "sg:classifiers":[
        {
            "category":"Wholesale",
            "subcategory":"Machinery & Supplies",
            "type":"Manufacturing & Wholesale Goods"
        }
    ],
    "sg:phone":"+90 232 421 5216",
    "sg:postcode":"42300",
    "sg:province":"Izmir",
    "sg:tags":[
        "heavy",
        "construction",
        "macinery"
    ],
    "wof:name":"L?her Asans?r San. Tic. Ltd. Sti.",
    "wof:placetype":"venue"
},
  "geometry": {"coordinates":[27.1423015594,38.4251480103],"type":"Point"}
}