{
  "type": "Feature",
  "properties": {
    "addr:full":"Eski Sanayi B?gesi 1.cad.no:11 Hacilar Organze Sanayi 3.cad. Ineg? Kayseri 16410",
    "addr:housenumber":"?;11;3.cad ineg ?",
    "addr:postcode":"16410",
    "addr:street":"Eski Sanayi B;Hacilar Organze Sanayi",
    "iso:country":"TR",
    "sg:address":"Eski Sanayi B?gesi 1.cad.no:11 Hacilar Organze Sanayi 3.cad.",
    "sg:city":"Ineg?",
    "sg:classifiers":[
        {
            "category":"Home & Garden",
            "subcategory":"Furniture",
            "type":"Retail Goods"
        }
    ],
    "sg:phone":"+90 352 320 8436",
    "sg:postcode":"16410",
    "sg:province":"Kayseri",
    "sg:tags":[
        "armchair",
        "sofa"
    ],
    "wof:name":"Emre Mobilya",
    "wof:placetype":"venue"
},
  "geometry": {"coordinates":[35.3756904602,38.7385253906],"type":"Point"}
}