{
  "type": "Feature",
  "properties": {
    "iso:country":"TR",
    "sg:address":"Birlik San.sit.2.cad.no:103-105",
    "sg:city":"B\u00fcy\u00fck\u00e7ekmece",
    "sg:classifiers":[
        {
            "category":"Home & Garden",
            "subcategory":"Household Appliances",
            "type":"Retail Goods"
        }
    ],
    "sg:phone":"+90 2128750346875",
    "sg:postcode":"34905",
    "sg:province":"Istanbul",
    "sg:tags":[
        "kitchenware"
    ],
    "sg:website":"plasbak.com",
    "wof:name":"Plasbak Plastik Bakalit Enj Ve Kalip San.ltd.sti",
    "wof:placetype":"venue"
},
  "geometry": {"coordinates":[28.9759254456,41.0123786926],"type":"Point"}
}