{
  "type": "Feature",
  "properties": {
    "addr:full":"Gediz Cad.no:3 K:6 D:12 Bornova Izmir 35040",
    "addr:housenumber":"3 k 6 d 12",
    "addr:postcode":"35040",
    "addr:street":"Cad.No;Bornova Izmir",
    "iso:country":"TR",
    "sg:address":"Gediz Cad.no:3 K:6 D:12",
    "sg:city":"Bornova",
    "sg:classifiers":[
        {
            "category":"Farming",
            "subcategory":"Farm",
            "type":"Manufacturing & Wholesale Goods"
        }
    ],
    "sg:phone":"+90 232 388 4659",
    "sg:postcode":"35040",
    "sg:province":"Izmir",
    "sg:tags":[
        "agricultural",
        "product"
    ],
    "wof:name":"H.a.y Export & Import Ltd.",
    "wof:placetype":"venue"
},
  "geometry": {"coordinates":[27.2215518951,38.4658889771],"type":"Point"}
}