{
  "type": "Feature",
  "properties": {
    "addr:full":"Yeni San.sit.sanayi Cad. 2/3 Sokak No:14 Nilufer Aydin 16370",
    "addr:housenumber":"2 /;no 14",
    "addr:postcode":"16370",
    "addr:street":"San.Sit.Sanayi Cad.;3 Sokak;Nilufer Aydin",
    "iso:country":"TR",
    "sg:address":"Yeni San.sit.sanayi Cad. 2/3 Sokak No:14",
    "sg:city":"Nilufer",
    "sg:classifiers":[
        {
            "category":"Manufacturing",
            "subcategory":"Tools & Machinery",
            "type":"Manufacturing & Wholesale Goods"
        }
    ],
    "sg:phone":"+90 256 225 1674",
    "sg:postcode":"16370",
    "sg:province":"Aydin",
    "sg:tags":[
        "machine",
        "industry"
    ],
    "wof:name":"Belmak Makina San.ve Tic.a.s.",
    "wof:placetype":"venue"
},
  "geometry": {"coordinates":[28.4863967896,37.8117027283],"type":"Point"}
}