{
  "type": "Feature",
  "properties": {
    "iso:country":"TR",
    "sg:address":"Cumhuriyet Bulvari No. 26 Kat: 5/505",
    "sg:city":"Konak",
    "sg:orig_category":"Dryfood-dried Nuts",
    "sg:phone":"+90 232 441 1064",
    "sg:postcode":"07110",
    "sg:province":"Izmir",
    "wof:name":"?zsaber Gida ?r?nleri",
    "wof:placetype":"venue"
},
  "geometry": {"coordinates":[27.1423015594,38.4251480103],"type":"Point"}
}