{
  "type": "Feature",
  "properties": {
    "iso:country":"TR",
    "sg:address":"3. San. Sit. 54. Sk. No:26",
    "sg:city":"Ikitelli/K\u00fc\u00e7\u00fck\u00e7ekmece",
    "sg:classifiers":[
        {
            "category":"Manufacturing",
            "subcategory":"Tools & Machinery",
            "type":"Manufacturing & Wholesale Goods"
        }
    ],
    "sg:phone":"+90 258 268 1089",
    "sg:postcode":"34660",
    "sg:province":"Denizli",
    "sg:tags":[
        "machine",
        "industry"
    ],
    "wof:name":"Kurban Makina San.",
    "wof:placetype":"venue"
},
  "geometry": {"coordinates":[29.0864906311,37.773525238],"type":"Point"}
}