{
  "type": "Feature",
  "properties": {
    "addr:full":"Turan Gunes Cad. No:514 Izmit Kocaeli 41000",
    "addr:housenumber":"514",
    "addr:postcode":"41000",
    "addr:street":"Gunes Cad. No;Kocaeli",
    "iso:country":"TR",
    "sg:address":"Turan Gunes Cad. No:514",
    "sg:city":"Izmit",
    "sg:classifiers":[
        {
            "category":"Wholesale",
            "subcategory":"Machinery & Supplies",
            "type":"Manufacturing & Wholesale Goods"
        }
    ],
    "sg:phone":"+90 262 322 1714",
    "sg:postcode":"41000",
    "sg:province":"Kocaeli",
    "sg:tags":[
        "agricultural"
    ],
    "wof:name":"Palazoglu Tarim Aletleri San. Tic.ltd.sti.",
    "wof:placetype":"venue"
},
  "geometry": {"coordinates":[29.9748210907,40.7915344238],"type":"Point"}
}