{
  "type": "Feature",
  "properties": {
    "addr:full":"Organize San. Deri Bol.yan Sanayi Aydinli-tuzla Beyazit Istanbul 65400",
    "addr:postcode":"65400",
    "addr:street":"Organize;Bol.Yan Sanayi Aydinli-Tuzla Beyazit",
    "iso:country":"TR",
    "sg:address":"Organize San. Deri Bol.yan Sanayi Aydinli-tuzla",
    "sg:city":"Beyazit",
    "sg:classifiers":[
        {
            "category":"Manufacturing",
            "subcategory":"Leather Goods",
            "type":"Manufacturing & Wholesale Goods"
        }
    ],
    "sg:phone":"+90 216 591 0020",
    "sg:postcode":"65400",
    "sg:province":"Istanbul",
    "wof:name":"Megaplast Deri Suni Deri Teks.a.s.",
    "wof:placetype":"venue"
},
  "geometry": {"coordinates":[28.9759254456,41.0123786926],"type":"Point"}
}