{
  "type": "Feature",
  "properties": {
    "iso:country":"TR",
    "sg:address":"Karsli Ahmet Cad. Eryuva Sitesi E Blok D:3",
    "sg:city":"I?renk?",
    "sg:classifiers":[
        {
            "category":"Professional",
            "subcategory":"Employment Agencies",
            "type":"Services"
        }
    ],
    "sg:phone":"+90 216 576 1855",
    "sg:province":"Istanbul",
    "sg:tags":[
        "personnel"
    ],
    "wof:name":"A Tur Turizm Organizasyon Oto Tic. Ltd. Sti.",
    "wof:placetype":"venue"
},
  "geometry": {"coordinates":[28.9759254456,41.0123786926],"type":"Point"}
}