{
  "type": "Feature",
  "properties": {
    "addr:full":"Ikitelli Org. San. Bolgesi Cevre San. Sitesi No:28-30 Ikitelli Yukari Dudullu Istanbul 34776",
    "addr:postcode":"34776",
    "addr:street":"Org.",
    "iso:country":"TR",
    "sg:address":"Ikitelli Org. San. Bolgesi Cevre San. Sitesi No:28-30 Ikitelli",
    "sg:city":"Yukari Dudullu",
    "sg:classifiers":[
        {
            "category":"Manufacturing",
            "subcategory":"Rubber & Plastics",
            "type":"Manufacturing & Wholesale Goods"
        }
    ],
    "sg:phone":"+90 212 485 2195",
    "sg:postcode":"34776",
    "sg:province":"Istanbul",
    "sg:tags":[
        "industry"
    ],
    "wof:name":"Akhan Plastik Kalip Ve Hediyelik Esya San.tic. Ltd.sti.",
    "wof:placetype":"venue"
},
  "geometry": {"coordinates":[29.175403595,41.0060424805],"type":"Point"}
}