{
  "type": "Feature",
  "properties": {
    "iso:country":"TR",
    "sg:address":"Hariciye Konak Sk. No:11/2 G??suyu",
    "sg:city":"Kad\u0131k\u00f6y",
    "sg:classifiers":[
        {
            "category":"Communications",
            "subcategory":"Film & Video Production",
            "type":"Services"
        }
    ],
    "sg:phone":"+90 212 243 5021",
    "sg:postcode":"34726",
    "sg:province":"Istanbul",
    "sg:tags":[
        "-"
    ],
    "wof:name":"Akin Ses G?r?nt? Merkezi Ltd. Sti.",
    "wof:placetype":"venue"
},
  "geometry": {"coordinates":[29.0445384979,40.975063324],"type":"Point"}
}