{
  "type": "Feature",
  "properties": {
    "addr:full":"Kozyatagi Sarikanarya Sk. No:13/1 Kad\u0131k\u00f6y Istanbul 34990",
    "addr:housenumber":"13 / 1",
    "addr:postcode":"34990",
    "addr:street":"Sarikanarya Sk. No",
    "iso:country":"TR",
    "sg:address":"Kozyatagi Sarikanarya Sk. No:13/1",
    "sg:city":"Kad\u0131k\u00f6y",
    "sg:classifiers":[
        {
            "category":"Utilities",
            "subcategory":"Natural Gas",
            "type":"Services"
        }
    ],
    "sg:phone":"+90 216 380 4166",
    "sg:postcode":"34990",
    "sg:province":"Istanbul",
    "sg:tags":[
        "tank-heating-natural"
    ],
    "wof:name":"M.t.g. M?hendis. Tic. Ltd. Sti.",
    "wof:placetype":"venue"
},
  "geometry": {"coordinates":[28.9861831665,41.0408554077],"type":"Point"}
}