{
  "type": "Feature",
  "properties": {
    "iso:country":"TR",
    "sg:address":"Yalova Koyu Boyaciburnu Mevkii",
    "sg:city":"Eceabat",
    "sg:classifiers":[
        {
            "category":"Food & Beverages",
            "subcategory":"Supermarket",
            "type":"Retail Goods"
        }
    ],
    "sg:phone":"+90 286 212 5047",
    "sg:postcode":"17900",
    "sg:province":"?anakkale",
    "sg:tags":[
        "frozen"
    ],
    "wof:name":"Amati Bosforo A.s.",
    "wof:placetype":"venue"
},
  "geometry": {"coordinates":[29.2712001801,40.65599823],"type":"Point"}
}