{
  "type": "Feature",
  "properties": {
    "iso:country":"TR",
    "sg:address":"Universite Bulvari Konak Mah.gumuspala Sok. No: 1/1 Sahinbey",
    "sg:city":"Osmangazi",
    "sg:classifiers":[
        {
            "category":"Wholesale",
            "subcategory":"Machinery & Supplies",
            "type":"Manufacturing & Wholesale Goods"
        }
    ],
    "sg:phone":"+90 342 335 4987",
    "sg:postcode":"16220",
    "sg:province":"Gaziantep",
    "sg:tags":[
        "laboratory",
        "equipment"
    ],
    "wof:name":"Turkuaz Saglik Urunleri Ltd.sti.",
    "wof:placetype":"venue"
},
  "geometry": {"coordinates":[37.3761024475,37.0629463196],"type":"Point"}
}