{
  "type": "Feature",
  "properties": {
    "addr:full":"Hukumet Cad. 1103. Sok. No:5/1-2 Gebze Sisli Kocaeli 65710",
    "addr:housenumber":"no 5 / 1-2",
    "addr:postcode":"1103;65710",
    "addr:street":"Hukumet Cad.;Sok.;Sisli",
    "iso:country":"TR",
    "sg:address":"Hukumet Cad. 1103. Sok. No:5/1-2 Gebze",
    "sg:city":"Sisli",
    "sg:classifiers":[
        {
            "category":"Shopping",
            "subcategory":"Pharmacy",
            "type":"Retail Goods"
        }
    ],
    "sg:phone":"+90 262 641 2184",
    "sg:postcode":"65710",
    "sg:province":"Kocaeli",
    "sg:tags":[
        "store",
        "drug"
    ],
    "wof:name":"Teknik Tarim Ecza Deposu San.tic.ltd.sti.",
    "wof:placetype":"venue"
},
  "geometry": {"coordinates":[29.9345855713,40.7669563293],"type":"Point"}
}