{
  "type": "Feature",
  "properties": {
    "iso:country":"TR",
    "sg:address":"Yeni Sular Cd. No:9 Sariyer",
    "sg:city":"Ikitelli/K\u00fc\u00e7\u00fck\u00e7ekmece",
    "sg:classifiers":[
        {
            "category":"Shopping",
            "subcategory":"Stationery & Office Supplies",
            "type":"Retail Goods"
        }
    ],
    "sg:phone":"+90 212 242 0518",
    "sg:postcode":"34660",
    "sg:province":"Istanbul",
    "wof:name":"Akademi Kitap Kirtasiye",
    "wof:placetype":"venue"
},
  "geometry": {"coordinates":[29.049629,41.00758],"type":"Point"}
}