{
  "type": "Feature",
  "properties": {
    "addr:full":"30. Sk. No:141 Ostim Gayrettepe/besiktas Ankara 80280",
    "addr:housenumber":"30;141",
    "addr:postcode":"80280",
    "addr:street":"Sk. No",
    "iso:country":"TR",
    "sg:address":"30. Sk. No:141 Ostim",
    "sg:city":"Gayrettepe/besiktas",
    "sg:classifiers":[
        {
            "category":"Farming",
            "subcategory":"Fish & Marine Products",
            "type":"Manufacturing & Wholesale Goods"
        }
    ],
    "sg:phone":"+90 312 354 2156",
    "sg:postcode":"80280",
    "sg:province":"Ankara",
    "sg:tags":[
        "automotive"
    ],
    "wof:name":"Baysallar Damper Dingil San. Ltd. Sti.",
    "wof:placetype":"venue"
},
  "geometry": {"coordinates":[32.7407417297,39.9712257385],"type":"Point"}
}