{
  "type": "Feature",
  "properties": {
    "iso:country":"TR",
    "sg:address":"Ak?y Cad.no:144 Gaziemir",
    "sg:city":"M.koy",
    "sg:classifiers":[
        {
            "category":"Sports & Exercise",
            "subcategory":"Ski Slope",
            "type":"Entertainment"
        }
    ],
    "sg:phone":"+90 232 251 5537",
    "sg:province":"Izmir",
    "sg:tags":[
        "wear"
    ],
    "wof:name":"Sts S?zer Tekstil Ltd.",
    "wof:placetype":"venue"
},
  "geometry": {"coordinates":[27.126101,38.323299],"type":"Point"}
}