{
  "type": "Feature",
  "properties": {
    "iso:country":"TR",
    "sg:address":"E.buyukdere Cad.no:19",
    "sg:city":"4 Levet",
    "sg:classifiers":[
        {
            "category":"Food & Beverages",
            "subcategory":"Candy",
            "type":"Retail Goods"
        }
    ],
    "sg:phone":"+90 212 264 0567",
    "sg:province":"Istanbul",
    "sg:tags":[
        "biscuit-chocolate-candy"
    ],
    "wof:name":"Ari Gida San.a.s.",
    "wof:placetype":"venue"
},
  "geometry": {"coordinates":[28.990128,41.06287],"type":"Point"}
}