{
  "type": "Feature",
  "properties": {
    "addr:full":"Ankara Asfalti ?zeri Kartal \u00dcmraniye Istanbul",
    "addr:street":"Kartal",
    "iso:country":"TR",
    "sg:address":"Ankara Asfalti ?zeri Kartal",
    "sg:city":"\u00dcmraniye",
    "sg:classifiers":[
        {
            "category":"Farming",
            "subcategory":"Fish & Marine Products",
            "type":"Manufacturing & Wholesale Goods"
        }
    ],
    "sg:phone":"+90 216 353 2828",
    "sg:province":"Istanbul",
    "sg:tags":[
        "automotive"
    ],
    "wof:name":"Eas Ak?m?lat?r Lastik Isi San. A.s.",
    "wof:placetype":"venue"
},
  "geometry": {"coordinates":[29.1595001221,40.9112014771],"type":"Point"}
}