{
  "type": "Feature",
  "properties": {
    "addr:full":"1170.sok. No:151 D:4 Gurcesme Maltepe Izmir 34843",
    "addr:housenumber":"no 151 d 4",
    "addr:postcode":"34843",
    "addr:street":"Gurcesme Maltepe",
    "iso:country":"TR",
    "sg:address":"1170.sok. No:151 D:4 Gurcesme",
    "sg:city":"Maltepe",
    "sg:classifiers":[
        {
            "category":"Banks & Credit Unions",
            "subcategory":"Investment Brokerage",
            "type":"Services"
        }
    ],
    "sg:phone":"+90 23244948244822",
    "sg:postcode":"34843",
    "sg:province":"Izmir",
    "sg:tags":[
        "-",
        "export",
        "import"
    ],
    "wof:name":"Sirdas Danismanlik & Halkla Iliskiler",
    "wof:placetype":"venue"
},
  "geometry": {"coordinates":[27.1423015594,38.4251480103],"type":"Point"}
}