{
  "type": "Feature",
  "properties": {
    "iso:country":"TR",
    "sg:address":"Sengoz Sok.no:3/4",
    "sg:city":"\u00dcmraniye",
    "sg:classifiers":[
        {
            "category":"Shopping",
            "subcategory":"Clothing, Apparel, & Fashions",
            "type":"Retail Goods"
        }
    ],
    "sg:phone":"+90 216527880506",
    "sg:postcode":"03650",
    "sg:province":"Istanbul",
    "sg:tags":[
        "underwear"
    ],
    "wof:name":"Nino Tekstil San.tic.ltd.sti.",
    "wof:placetype":"venue"
},
  "geometry": {"coordinates":[29.153831,41.011902],"type":"Point"}
}