{
  "type": "Feature",
  "properties": {
    "addr:full":"Mesurtiyet Cad.asli Han. No:18 Kat.1 Galatasaray Gayrettepe Istanbul 34349",
    "addr:postcode":"34349",
    "iso:country":"TR",
    "sg:address":"Mesurtiyet Cad.asli Han. No:18 Kat.1 Galatasaray",
    "sg:city":"Gayrettepe",
    "sg:classifiers":[
        {
            "category":"Banks & Credit Unions",
            "subcategory":"Investment Brokerage",
            "type":"Services"
        }
    ],
    "sg:phone":"+90 212 249 1981",
    "sg:postcode":"34349",
    "sg:province":"Istanbul",
    "sg:tags":[
        "course",
        "language"
    ],
    "wof:name":"Global Vision International Education",
    "wof:placetype":"venue"
},
  "geometry": {"coordinates":[29.0118026733,41.0541763306],"type":"Point"}
}