{
  "type": "Feature",
  "properties": {
    "addr:full":"Huzur Sitesi 5. Blok K: 2 Lara Antalya 07230",
    "addr:housenumber":"blok k 2",
    "addr:postcode":"07230",
    "addr:street":"5",
    "iso:country":"TR",
    "sg:address":"Huzur Sitesi 5. Blok K: 2",
    "sg:city":"Lara",
    "sg:classifiers":[
        {
            "category":"Travel",
            "subcategory":"Travel Agent",
            "type":"Entertainment"
        }
    ],
    "sg:phone":"+90 242 349 4696",
    "sg:postcode":"07230",
    "sg:province":"Antalya",
    "sg:tags":[
        "agency",
        "tourism"
    ],
    "wof:name":"G?ltur Turizm",
    "wof:placetype":"venue"
},
  "geometry": {"coordinates":[30.7092056274,36.8790512085],"type":"Point"}
}