{
  "type": "Feature",
  "properties": {
    "addr:full":"B. Yeri G?en?ishani No:18 Bayrampasa Denizli 36100",
    "addr:housenumber":"18",
    "addr:postcode":"36100",
    "addr:street":"Yeri G;Ishani No",
    "iso:country":"TR",
    "sg:address":"B. Yeri G?en?ishani No:18",
    "sg:city":"Bayrampasa",
    "sg:classifiers":[
        {
            "category":"Manufacturing",
            "subcategory":"Metals",
            "type":"Manufacturing & Wholesale Goods"
        }
    ],
    "sg:phone":"+90 258 263 9298",
    "sg:postcode":"36100",
    "sg:province":"Denizli",
    "sg:tags":[
        "iron-steel",
        "peoducts"
    ],
    "wof:name":"?zen Demir Ltd. Sti.",
    "wof:placetype":"venue"
},
  "geometry": {"coordinates":[29.0864906311,37.773525238],"type":"Point"}
}