{
  "type": "Feature",
  "properties": {
    "addr:full":"B?ent Sk. No:53/8 24000 Ankara",
    "addr:housenumber":"sk. no 53 / 8",
    "addr:postcode":"24000",
    "addr:street":"B;Ent",
    "iso:country":"TR",
    "sg:address":"B?ent Sk. No:53/8",
    "sg:city":"24000",
    "sg:classifiers":[
        {
            "category":"Manufacturing",
            "subcategory":"Wood Products",
            "type":"Manufacturing & Wholesale Goods"
        }
    ],
    "sg:phone":"+90 312 426 5045",
    "sg:province":"Ankara",
    "sg:tags":[
        "forest"
    ],
    "wof:name":"Dunav Orman ?r?nleri Ltd. Sti.",
    "wof:placetype":"venue"
},
  "geometry": {"coordinates":[32.8560333252,39.9438743591],"type":"Point"}
}