{
  "type": "Feature",
  "properties": {
    "addr:full":"Sanayi S. Sanayi Cd. No: 27/1 Iskenderun Hatay 31200",
    "addr:housenumber":"no 27 / 1",
    "addr:postcode":"31200",
    "addr:street":"Sanayi S. Sanayi Cd.",
    "iso:country":"TR",
    "sg:address":"Sanayi S. Sanayi Cd. No: 27/1",
    "sg:city":"Iskenderun",
    "sg:classifiers":[
        {
            "category":"Building & Trades",
            "subcategory":"Plumbing",
            "type":"Services"
        }
    ],
    "sg:phone":"+90 326 656 2030",
    "sg:postcode":"31200",
    "sg:province":"Hatay",
    "sg:tags":[
        "filter",
        "industry"
    ],
    "wof:name":"Sampiyon Filtre San. A.s.",
    "wof:placetype":"venue"
},
  "geometry": {"coordinates":[29.2633476257,40.8794517517],"type":"Point"}
}