{
  "type": "Feature",
  "properties": {
    "iso:country":"TR",
    "sg:address":"Mursel Pata Bulvari No:18",
    "sg:city":"Basmane",
    "sg:classifiers":[
        {
            "category":"Utilities",
            "subcategory":"Electric",
            "type":"Services"
        }
    ],
    "sg:phone":"+90 232 425 2911",
    "sg:postcode":"35240",
    "sg:province":"Izmir",
    "sg:tags":[
        "energy",
        "solar"
    ],
    "wof:name":"Orjin Solar Teknik",
    "wof:placetype":"venue"
},
  "geometry": {"coordinates":[27.146618,38.424278],"type":"Point"}
}