{
  "type": "Feature",
  "properties": {
    "iso:country":"TR",
    "sg:address":"Mahatma Gandi Cad.no:27/6 G.o.p",
    "sg:city":"4.levent",
    "sg:classifiers":[
        {
            "category":"Manufacturing",
            "subcategory":"Building Materials",
            "type":"Manufacturing & Wholesale Goods"
        }
    ],
    "sg:phone":"+90 312 447 9331",
    "sg:postcode":"80650",
    "sg:province":"Ankara",
    "sg:tags":[
        "promotional"
    ],
    "wof:name":"Yeni Cizgi Bas.yay.ltd.sti.",
    "wof:placetype":"venue"
},
  "geometry": {"coordinates":[32.8741722107,39.890827179],"type":"Point"}
}