{
  "type": "Feature",
  "properties": {
    "iso:country":"TR",
    "sg:address":"Istanbul Yolu 12.km Yeni Baskent San. Sit. No:56/36",
    "sg:city":"Ergazi",
    "sg:orig_category":"Prefabric Construction",
    "sg:phone":"+90 312 278 4227",
    "sg:postcode":"06370",
    "sg:province":"Ankara",
    "wof:name":"Es Prefabrik",
    "wof:placetype":"venue"
},
  "geometry": {"coordinates":[32.7294197083,39.9771499634],"type":"Point"}
}