{
  "type": "Feature",
  "properties": {
    "iso:country":"TR",
    "sg:address":"Cemalpasa Mah. Gazipasa Bulvari Tek Apt. Kat:3 No:33 Seyhan",
    "sg:city":"Mecidiyek\u00f6y",
    "sg:classifiers":[
        {
            "category":"Professional",
            "subcategory":"Detective & Security Services",
            "type":"Services"
        }
    ],
    "sg:phone":"+90 322 458 2929",
    "sg:province":"Adana",
    "sg:tags":[
        "material"
    ],
    "wof:name":"Koral Isletmecilik Ltd.sti.",
    "wof:placetype":"venue"
},
  "geometry": {"coordinates":[35.332973,36.970501],"type":"Point"}
}