{
  "type": "Feature",
  "properties": {
    "iso:country":"TR",
    "sg:address":"19.mayis Mah.inonu Cad. Turaboglu Sok. Sumko Sitesi A2 Blok D.4",
    "sg:city":"Kozyatagi",
    "sg:classifiers":[
        {
            "category":"Shopping",
            "subcategory":"Crafts & Fabrics",
            "type":"Retail Goods"
        }
    ],
    "sg:phone":"+90 216 372 6688",
    "sg:postcode":"34742",
    "sg:province":"Istanbul",
    "sg:tags":[
        "yarn"
    ],
    "wof:name":"Harmanci Iplik San.ve Dis Tic.ltd.sti.",
    "wof:placetype":"venue"
},
  "geometry": {"coordinates":[29.0954437256,40.9691467285],"type":"Point"}
}