{
  "type": "Feature",
  "properties": {
    "addr:full":"Altunizade Mah. Kisikli Cad. Kusbakisi Sok. No: 4 Uskudar Osmanbey Istanbul 63000",
    "addr:housenumber":"no 4",
    "addr:postcode":"63000",
    "addr:street":"Mah. Kisikli Cad. Kusbakisi Sok.;Uskudar Osmanbey",
    "iso:country":"TR",
    "sg:address":"Altunizade Mah. Kisikli Cad. Kusbakisi Sok. No: 4 Uskudar",
    "sg:city":"Osmanbey",
    "sg:classifiers":[
        {
            "category":"Shopping",
            "subcategory":"Stationery & Office Supplies",
            "type":"Retail Goods"
        }
    ],
    "sg:phone":"+90 212 474 0800",
    "sg:postcode":"63000",
    "sg:province":"Istanbul",
    "sg:tags":[
        "furniture"
    ],
    "wof:name":"Surat Egitim Araclari Ve Boro Mobilya Sistemleri A.s.",
    "wof:placetype":"venue"
},
  "geometry": {"coordinates":[29.0458011627,41.0235061646],"type":"Point"}
}