{
  "type": "Feature",
  "properties": {
    "addr:full":"Ordu Cad. No:4 Emek Mah. 81230 Sarigazi Istanbul Merkez Istanbul 24000",
    "addr:housenumber":"mah.",
    "addr:postcode":"81230;24000",
    "addr:street":"Ordu Cad. No 4 Emek",
    "iso:country":"TR",
    "sg:address":"Ordu Cad. No:4 Emek Mah. 81230 Sarigazi Istanbul",
    "sg:city":"Merkez",
    "sg:classifiers":[
        {
            "category":"Food & Beverages",
            "subcategory":"Groceries & Convenience Stores",
            "type":"Retail Goods"
        }
    ],
    "sg:phone":"+90 216 365 0215",
    "sg:postcode":"24000",
    "sg:province":"Istanbul",
    "sg:tags":[
        "product",
        "related"
    ],
    "wof:name":"Akas Akbalik Gida San Ve Tic A.s.",
    "wof:placetype":"venue"
},
  "geometry": {"coordinates":[29.1946086884,41.0020446777],"type":"Point"}
}