{
  "type": "Feature",
  "properties": {
    "iso:country":"TR",
    "sg:address":"?aglayan Vatan Cd. No: 102",
    "sg:city":"Sisli",
    "sg:classifiers":[
        {
            "category":"Shopping",
            "subcategory":"Crafts & Fabrics",
            "type":"Retail Goods"
        }
    ],
    "sg:phone":"+90 212 246 0097",
    "sg:postcode":"65710",
    "sg:province":"Istanbul",
    "sg:tags":[
        "embroidery"
    ],
    "wof:name":"Akg?l Nakis San. Tic. Ltd.",
    "wof:placetype":"venue"
},
  "geometry": {"coordinates":[29.1644096375,41.0053100586],"type":"Point"}
}