{
  "type": "Feature",
  "properties": {
    "addr:full":"Abd?ezel Pasa Cd. No:285 Cibali Gebze Istanbul 41400",
    "addr:housenumber":"no 285",
    "addr:postcode":"41400",
    "addr:street":"Pasa Cd.",
    "iso:country":"TR",
    "sg:address":"Abd?ezel Pasa Cd. No:285 Cibali",
    "sg:city":"Gebze",
    "sg:classifiers":[
        {
            "category":"Shopping",
            "subcategory":"Bicycles & Sporting Goods",
            "type":"Retail Goods"
        }
    ],
    "sg:phone":"+90 212 534 9353",
    "sg:postcode":"41400",
    "sg:province":"Istanbul",
    "sg:tags":[
        "equipment",
        "marine",
        "hunting"
    ],
    "wof:name":"Bogazi?i Balik?ilik Ve Deniz Mal. Ltd. Sti.",
    "wof:placetype":"venue"
},
  "geometry": {"coordinates":[28.9861831665,41.0408554077],"type":"Point"}
}