{
  "type": "Feature",
  "properties": {
    "iso:country":"TR",
    "sg:address":"F.?akmak 2. Sk. No:27/4",
    "sg:city":"D.tepe",
    "sg:classifiers":[
        {
            "category":"Professional",
            "subcategory":"Engineering",
            "type":"Services"
        }
    ],
    "sg:phone":"+90 312 229 7624",
    "sg:province":"Ankara",
    "sg:tags":[
        "architect"
    ],
    "wof:name":"Ilna M?hendis. Ltd. Sti.",
    "wof:placetype":"venue"
},
  "geometry": {"coordinates":[32.8604812622,39.9429283142],"type":"Point"}
}