{
  "type": "Feature",
  "properties": {
    "addr:full":"Kasap Sk. No:18/56 Esentepe Istanbul 01930",
    "addr:housenumber":"18 / 56",
    "addr:postcode":"01930",
    "addr:street":"Kasap Sk. No",
    "iso:country":"TR",
    "sg:address":"Kasap Sk. No:18/56",
    "sg:city":"Esentepe",
    "sg:classifiers":[
        {
            "category":"Transit Center",
            "subcategory":"Freight",
            "type":"Transportation"
        }
    ],
    "sg:phone":"+90 212 272 2740",
    "sg:postcode":"01930",
    "sg:province":"Istanbul",
    "wof:name":"Arsay Denizcilik Tic. A.s.",
    "wof:placetype":"venue"
},
  "geometry": {"coordinates":[28.9408359528,41.0297393799],"type":"Point"}
}