{
  "type": "Feature",
  "properties": {
    "iso:country":"TR",
    "sg:address":"Barbaros Bulv. No:21",
    "sg:city":"Besiktas",
    "sg:classifiers":[
        {
            "category":"Airport",
            "subcategory":"International",
            "type":"Transportation"
        }
    ],
    "sg:phone":"+90 212 251 3901",
    "sg:postcode":"75200",
    "sg:province":"Istanbul",
    "wof:name":"Rota Uluslararasi Tasima. Ins. San. Ith. Ihr.ltd.",
    "wof:placetype":"venue"
},
  "geometry": {"coordinates":[29.2416858673,41.0165176392],"type":"Point"}
}