{
  "type": "Feature",
  "properties": {
    "iso:country":"TR",
    "sg:address":"1. San. 8. Sk. No:18",
    "sg:city":"Bornova",
    "sg:classifiers":[
        {
            "category":"Wholesale",
            "subcategory":"Machinery & Supplies",
            "type":"Manufacturing & Wholesale Goods"
        }
    ],
    "sg:phone":"+90 256 225 2652",
    "sg:postcode":"35040",
    "sg:province":"Aydin",
    "sg:tags":[
        "agricultural"
    ],
    "wof:name":"Ugurlu Ziraat Aletleri A.s.",
    "wof:placetype":"venue"
},
  "geometry": {"coordinates":[33.7800102234,41.3909225464],"type":"Point"}
}