{
  "type": "Feature",
  "properties": {
    "iso:country":"TR",
    "sg:address":"Cobankizi Sok. No:11/6 Buyukdere -sariyer",
    "sg:city":"19100",
    "sg:classifiers":[
        {
            "category":"Banks & Credit Unions",
            "subcategory":"Investment Brokerage",
            "type":"Services"
        }
    ],
    "sg:phone":"+90 212",
    "sg:province":"Istanbul",
    "sg:tags":[
        "-",
        "export",
        "import"
    ],
    "wof:name":"Alpeks Dis Ticaret Ve Pazarlama Ltd.sti.",
    "wof:placetype":"venue"
},
  "geometry": {"coordinates":[29.0304603577,41.155620575],"type":"Point"}
}