{
  "type": "Feature",
  "properties": {
    "addr:full":"Menderes Cad.no.73 Akbank Bitisigi Silifke I?el 3340",
    "addr:housenumber":"cad.no.73",
    "addr:postcode":"3340",
    "addr:street":"Menderes;El",
    "iso:country":"TR",
    "sg:address":"Menderes Cad.no.73 Akbank Bitisigi",
    "sg:city":"Silifke",
    "sg:classifiers":[
        {
            "category":"Professional",
            "type":"Services"
        }
    ],
    "sg:phone":"+90 324 714 9005",
    "sg:postcode":"3340",
    "sg:province":"I?el",
    "sg:tags":[
        "catering"
    ],
    "wof:name":"Mentes Telekom",
    "wof:placetype":"venue"
},
  "geometry": {"coordinates":[28.8766899109,41.039188385],"type":"Point"}
}