{
  "type": "Feature",
  "properties": {
    "addr:full":"Ebe Hanim Sok. No:8/2 G??suyu Istanbul",
    "addr:housenumber":"no 8 / 2 g ? ?",
    "addr:street":"Hanim Sok.",
    "iso:country":"TR",
    "sg:address":"Ebe Hanim Sok. No:8/2",
    "sg:city":"G??suyu",
    "sg:classifiers":[
        {
            "category":"Recreation",
            "subcategory":"Boat Charter",
            "type":"Entertainment"
        }
    ],
    "sg:phone":"+90 21229352832",
    "sg:province":"Istanbul",
    "sg:tags":[
        "yachting"
    ],
    "wof:name":"Apaz Denizcilik (istanbul Office)",
    "wof:placetype":"venue"
},
  "geometry": {"coordinates":[28.9902515411,41.035949707],"type":"Point"}
}