{
  "type": "Feature",
  "properties": {
    "iso:country":"TR",
    "sg:address":"Bankalar Okcumusa",
    "sg:city":"Galata",
    "sg:classifiers":[
        {
            "category":"Banks & Credit Unions",
            "subcategory":"Bank",
            "type":"Services"
        }
    ],
    "sg:phone":"+90 212 252 2404",
    "sg:province":"80000",
    "wof:name":"T?kiye Emlak, Bankasi As",
    "wof:placetype":"venue"
},
  "geometry": {"coordinates":[28.957722,41.021263],"type":"Point"}
}