{
  "type": "Feature",
  "properties": {
    "iso:country":"TR",
    "sg:address":"S. Nedim Sk. No:2/9 Cankaya",
    "sg:city":"\u00dcsk\u00fcdar",
    "sg:classifiers":[
        {
            "category":"Building & Trades",
            "subcategory":"Construction",
            "type":"Services"
        }
    ],
    "sg:phone":"+90 312 441 4870",
    "sg:province":"Ankara",
    "sg:tags":[
        "foundation"
    ],
    "wof:name":"Beyaz Nokta Vakfi",
    "wof:placetype":"venue"
},
  "geometry": {"coordinates":[32.8506355286,39.8936195374],"type":"Point"}
}