{
  "type": "Feature",
  "properties": {
    "iso:country":"TR",
    "sg:address":"Millet Cad, Belediye",
    "sg:city":"Kayseri",
    "sg:classifiers":[
        {
            "category":"Banks & Credit Unions",
            "subcategory":"Bank",
            "type":"Services"
        }
    ],
    "sg:phone":"+90 352 222 1123",
    "sg:postcode":"63600",
    "sg:province":"38040",
    "wof:name":"T?k Ekonomi, Bankasi As",
    "wof:placetype":"venue"
},
  "geometry": {"coordinates":[36.357243,41.270943],"type":"Point"}
}