{
  "type": "Feature",
  "properties": {
    "addr:full":"Ostim San. Sit. 56. Sk. No:133-151-153 Ikitelli/K\u00fc\u00e7\u00fck\u00e7ekmece Ankara 34670",
    "addr:housenumber":"56",
    "addr:postcode":"133-151-153;34670",
    "addr:street":"Sk. No",
    "iso:country":"TR",
    "sg:address":"Ostim San. Sit. 56. Sk. No:133-151-153",
    "sg:city":"Ikitelli/K\u00fc\u00e7\u00fck\u00e7ekmece",
    "sg:orig_category":"General Industrial Products",
    "sg:phone":"+90 312 354 0617",
    "sg:postcode":"34670",
    "sg:province":"Ankara",
    "wof:name":"Akin Isi Mak. San. Tic. A.s.",
    "wof:placetype":"venue"
},
  "geometry": {"coordinates":[32.8560333252,39.9438743591],"type":"Point"}
}