{
  "type": "Feature",
  "properties": {
    "addr:full":"Cumhuriyet Cad.kutlu Ishani Kat:2 No:1 Tatvan Bitlis 13200",
    "addr:housenumber":"kat 2 no 1",
    "addr:postcode":"13200",
    "addr:street":"Tatvan Bitlis",
    "iso:country":"TR",
    "sg:address":"Cumhuriyet Cad.kutlu Ishani Kat:2 No:1",
    "sg:city":"Tatvan",
    "sg:classifiers":[
        {
            "category":"Organizations",
            "subcategory":"Membership Organization",
            "type":"Services"
        }
    ],
    "sg:phone":"+90 434 828 0101",
    "sg:postcode":"13200",
    "sg:province":"Bitlis",
    "wof:name":"Tatvan Turizm Gelistirme Kalkinma Ve Yard. Dernegi",
    "wof:placetype":"venue"
},
  "geometry": {"coordinates":[42.1081352234,38.399356842],"type":"Point"}
}