{
  "type": "Feature",
  "properties": {
    "iso:country":"TR",
    "sg:address":"Numunebag Cd. No:3/b Bayrampasa",
    "sg:city":"\u00dcmraniye",
    "sg:classifiers":[
        {
            "category":"Manufacturing",
            "subcategory":"Rubber & Plastics",
            "type":"Manufacturing & Wholesale Goods"
        }
    ],
    "sg:phone":"+90 212 544 3090",
    "sg:province":"Istanbul",
    "sg:tags":[
        "industry"
    ],
    "wof:name":"G?rtan Plastik San. Tic. Ltd. Sti.",
    "wof:placetype":"venue"
},
  "geometry": {"coordinates":[28.9011554718,41.0516204834],"type":"Point"}
}