{
  "type": "Feature",
  "properties": {
    "iso:country":"TR",
    "sg:address":"Mavi Cd. No:1",
    "sg:city":"Iskenderun",
    "sg:classifiers":[
        {
            "category":"Wholesale",
            "subcategory":"Petroleum",
            "type":"Manufacturing & Wholesale Goods"
        }
    ],
    "sg:phone":"+90 224 243 1340",
    "sg:postcode":"31200",
    "sg:province":"Bursa",
    "wof:name":"Aygaz A.s.",
    "wof:placetype":"venue"
},
  "geometry": {"coordinates":[28.9606800079,40.2474746704],"type":"Point"}
}