{
  "type": "Feature",
  "properties": {
    "iso:country":"TR",
    "sg:address":"1374 Sk. No.10/14",
    "sg:city":"\u00c7orlu",
    "sg:classifiers":[
        {
            "category":"Shopping",
            "subcategory":"Luggage & Leather Goods",
            "type":"Retail Goods"
        }
    ],
    "sg:phone":"+90 232 425 5255",
    "sg:province":"Izmir",
    "sg:tags":[
        "leather-fur",
        "wear"
    ],
    "wof:name":"Evren Deri San. Ltd.sti.",
    "wof:placetype":"venue"
},
  "geometry": {"coordinates":[27.1377849579,38.4260482788],"type":"Point"}
}