{
  "type": "Feature",
  "properties": {
    "iso:country":"TR",
    "sg:address":"Utku Mah. Boyacilik Sok. No:127/2",
    "sg:city":"Sisli",
    "sg:classifiers":[
        {
            "category":"Organizations",
            "subcategory":"Professional Association",
            "type":"Services"
        }
    ],
    "sg:phone":"+90 236",
    "sg:postcode":"65710",
    "sg:province":"Manisa",
    "sg:tags":[
        "fair"
    ],
    "wof:name":"S.n.s Fuarcilik Tanitim Reklamcilik Organizasyon Ve Yay. Ltd.sti.",
    "wof:placetype":"venue"
},
  "geometry": {"coordinates":[27.4297008514,38.6222000122],"type":"Point"}
}