{
  "type": "Feature",
  "properties": {
    "addr:full":"Tasyaka Mah. Oludeniz Cad.no:58 Fethiye Ikitelli/K\u00fc\u00e7\u00fck\u00e7ekmece Mugla 34660",
    "addr:housenumber":"58",
    "addr:postcode":"34660",
    "addr:street":"Tasyaka Mah.;Cad.No",
    "iso:country":"TR",
    "sg:address":"Tasyaka Mah. Oludeniz Cad.no:58 Fethiye",
    "sg:city":"Ikitelli/K\u00fc\u00e7\u00fck\u00e7ekmece",
    "sg:classifiers":[
        {
            "category":"Personal",
            "subcategory":"Sauna",
            "type":"Services"
        }
    ],
    "sg:phone":"+90 252 612 5141",
    "sg:postcode":"34660",
    "sg:province":"Mugla",
    "sg:tags":[
        "pool"
    ],
    "wof:name":"Senel Kimya Mak.muh.san.tic.ltd.",
    "wof:placetype":"venue"
},
  "geometry": {"coordinates":[29.132734,36.622299],"type":"Point"}
}