{
  "type": "Feature",
  "properties": {
    "iso:country":"TR",
    "sg:address":"Fevzi Pasa Cad. No:33/10 Fatih",
    "sg:city":"Fatih",
    "sg:classifiers":[
        {
            "category":"Organizations",
            "subcategory":"Membership Organization",
            "type":"Services"
        }
    ],
    "sg:phone":"+90 212 631 7803",
    "sg:postcode":"01740",
    "sg:province":"Istanbul",
    "wof:name":"?nder (imam-hatip Lisesi Mezunlari Ve Mensuplari Dernegi)",
    "wof:placetype":"venue"
},
  "geometry": {"coordinates":[28.9861831665,41.0408554077],"type":"Point"}
}