{
  "type": "Feature",
  "properties": {
    "iso:country":"TR",
    "sg:address":"Murselpasa Bulv. 1266 Sok. 10/402 Kahramanlar",
    "sg:city":"?atalca",
    "sg:classifiers":[
        {
            "category":"Manufacturing",
            "subcategory":"Leather Goods",
            "type":"Manufacturing & Wholesale Goods"
        }
    ],
    "sg:phone":"+90 232 484 1434",
    "sg:postcode":"34870",
    "sg:province":"Izmir",
    "sg:tags":[
        "chemical"
    ],
    "wof:name":"Ser Kimya Deri San.tic. Ltd.sti.",
    "wof:placetype":"venue"
},
  "geometry": {"coordinates":[27.1465129852,38.4238853455],"type":"Point"}
}