{
  "type": "Feature",
  "properties": {
    "iso:country":"TR",
    "sg:address":"Topkapi Suri? No:38",
    "sg:city":"Sapanca",
    "sg:classifiers":[
        {
            "category":"Building & Trades",
            "subcategory":"Construction",
            "type":"Services"
        }
    ],
    "sg:phone":"+90 212 629 0340",
    "sg:postcode":"54600",
    "sg:province":"Istanbul",
    "sg:tags":[
        "foundation"
    ],
    "wof:name":"Ahi K?lt?r?n? Arastirma Ve Egt. Vakfi",
    "wof:placetype":"venue"
},
  "geometry": {"coordinates":[28.9842224121,41.0126800537],"type":"Point"}
}