{
  "type": "Feature",
  "properties": {
    "iso:country":"TR",
    "sg:address":"Ata?2 Sok.no:66/9",
    "sg:city":"Kizilay",
    "sg:classifiers":[
        {
            "category":"Organizations",
            "subcategory":"Professional Association",
            "type":"Services"
        }
    ],
    "sg:phone":"+90 312 430 6434",
    "sg:postcode":"23050",
    "sg:province":"Ankara",
    "wof:name":"?evre M?hendisleri Odasi",
    "wof:placetype":"venue"
},
  "geometry": {"coordinates":[32.8500862122,39.8725967407],"type":"Point"}
}