{
  "type": "Feature",
  "properties": {
    "addr:full":"Kurtalan Yolu 56100 Siirt",
    "addr:postcode":"56100",
    "addr:street":"Kurtalan Yolu",
    "iso:country":"TR",
    "sg:address":"Kurtalan Yolu",
    "sg:city":"56100",
    "sg:classifiers":[
        {
            "category":"Home & Garden",
            "subcategory":"Carpets & Floor Coverings",
            "type":"Retail Goods"
        }
    ],
    "sg:phone":"+90 484 224 3444",
    "sg:province":"Siirt",
    "sg:tags":[
        "aluminium",
        "foil"
    ],
    "wof:name":"Simas Al?i",
    "wof:placetype":"venue"
},
  "geometry": {"coordinates":[41.5789833069,37.9241714478],"type":"Point"}
}