{
  "type": "Feature",
  "properties": {
    "iso:country":"TR",
    "sg:address":"Osmangazi Mahallesi",
    "sg:city":"Setbasi",
    "sg:classifiers":[
        {
            "category":"Banks & Credit Unions",
            "subcategory":"Bank",
            "type":"Services"
        }
    ],
    "sg:phone":"+90 224 224 4256",
    "sg:province":"16010",
    "wof:name":"Kocbank As",
    "wof:placetype":"venue"
},
  "geometry": {"coordinates":[30.475494,39.750088],"type":"Point"}
}