{
  "type": "Feature",
  "properties": {
    "iso:country":"TR",
    "sg:address":"Necatibey Bulv. No.14",
    "sg:city":"Dudullu",
    "sg:classifiers":[
        {
            "category":"Farming",
            "subcategory":"Poultry Farm",
            "type":"Manufacturing & Wholesale Goods"
        }
    ],
    "sg:phone":"+90 232 422 1435",
    "sg:province":"Izmir",
    "sg:tags":[
        "poultry-turkey-ostrich"
    ],
    "wof:name":"Ege Tad Tavuk?uluk San. A.s.",
    "wof:placetype":"venue"
},
  "geometry": {"coordinates":[27.0591335297,38.3913459778],"type":"Point"}
}