{
  "type": "Feature",
  "properties": {
    "iso:country":"TR",
    "sg:address":"Kultur Mah. Aydin Sok. No:11-b Ulus Ist",
    "sg:city":"Emin?? 34280",
    "sg:classifiers":[
        {
            "category":"Manufacturing",
            "subcategory":"Building Materials",
            "type":"Manufacturing & Wholesale Goods"
        }
    ],
    "sg:phone":"+90 212 287 9932",
    "sg:province":"Istanbul",
    "sg:tags":[
        "promotional"
    ],
    "wof:name":"Prosel Tanitim",
    "wof:placetype":"venue"
},
  "geometry": {"coordinates":[28.8206958771,40.9819564819],"type":"Point"}
}