{
  "type": "Feature",
  "properties": {
    "iso:country":"TR",
    "sg:address":"Eregli Sk. No:39/4",
    "sg:city":"Siteler",
    "sg:classifiers":[
        {
            "category":"Manufacturing",
            "subcategory":"Glass & Minerals",
            "type":"Manufacturing & Wholesale Goods"
        }
    ],
    "sg:phone":"+90 312 350 8070",
    "sg:postcode":"07070",
    "sg:province":"Ankara",
    "sg:tags":[
        "glass-mirror"
    ],
    "wof:name":"Campa Dekoratif Cam San. Ltd. Sti.",
    "wof:placetype":"venue"
},
  "geometry": {"coordinates":[32.9384307861,39.9596138],"type":"Point"}
}