{
  "type": "Feature",
  "properties": {
    "iso:country":"TR",
    "sg:address":"Yeni Mh. 41. Sk. No:4 Merkez",
    "sg:city":"38070",
    "sg:orig_category":"Aluminium Carpentary",
    "sg:phone":"+90 452214745522",
    "sg:province":"Ordu",
    "wof:name":"Kilicoglu Tic. Ins. Malz.",
    "wof:placetype":"venue"
},
  "geometry": {"coordinates":[28.841709137,41.0422363281],"type":"Point"}
}