{
  "type": "Feature",
  "properties": {
    "addr:full":"19 Mayis Cad. No:2 Istiklal Mah. 81240 Umraniye Istanbul Cagaloglu Istanbul 34440",
    "addr:housenumber":"19;mah.",
    "addr:postcode":"81240;34440",
    "addr:street":"Mayis Cad. No 2 Istiklal",
    "iso:country":"TR",
    "sg:address":"19 Mayis Cad. No:2 Istiklal Mah. 81240 Umraniye Istanbul",
    "sg:city":"Cagaloglu",
    "sg:classifiers":[
        {
            "category":"Shopping",
            "type":"Retail Goods"
        }
    ],
    "sg:phone":"+90 216 335 1206",
    "sg:postcode":"34440",
    "sg:province":"Istanbul",
    "sg:tags":[
        "finished",
        "-",
        "metallic"
    ],
    "wof:name":"Guc-san Plastik Ve Kalip San",
    "wof:placetype":"venue"
},
  "geometry": {"coordinates":[29.1044998169,41.0190544128],"type":"Point"}
}