{
  "type": "Feature",
  "properties": {
    "iso:country":"TR",
    "sg:address":"Ataturk Bulvari No:148/4 Aksaray",
    "sg:city":"Asagi Ayranci",
    "sg:classifiers":[
        {
            "category":"Banks & Credit Unions",
            "subcategory":"Financial Services",
            "type":"Services"
        }
    ],
    "sg:province":"Istanbul",
    "sg:tags":[
        "finance"
    ],
    "wof:name":"Ekol Menkul Degerler A.s.",
    "wof:placetype":"venue"
},
  "geometry": {"coordinates":[28.9551258087,41.0093383789],"type":"Point"}
}