{
  "type": "Feature",
  "properties": {
    "iso:country":"TR",
    "sg:address":"Husrev Gerede Cd. No:112 Tesvikiye",
    "sg:city":"?k?ar",
    "sg:classifiers":[
        {
            "category":"Professional",
            "subcategory":"Computer Services",
            "type":"Services"
        }
    ],
    "sg:phone":"+90 212 261 0163",
    "sg:province":"Istanbul",
    "sg:tags":[
        "application",
        "software"
    ],
    "wof:name":"Protekila Elekt.yazilim Ltd .sti .",
    "wof:placetype":"venue"
},
  "geometry": {"coordinates":[29.0004405975,41.0529289246],"type":"Point"}
}