{
  "type": "Feature",
  "properties": {
    "iso:country":"TR",
    "sg:address":"Meseli S. No: 38/1",
    "sg:city":"4.levent",
    "sg:classifiers":[
        {
            "category":"Manufacturing",
            "subcategory":"Building Materials",
            "type":"Manufacturing & Wholesale Goods"
        }
    ],
    "sg:phone":"+90 212 282 8256",
    "sg:province":"Istanbul",
    "sg:tags":[
        "floor-wall",
        "covering"
    ],
    "wof:name":"Fibrobeton San.ltd.sti.",
    "wof:placetype":"venue"
},
  "geometry": {"coordinates":[29.3493423462,40.895450592],"type":"Point"}
}