{
  "type": "Feature",
  "properties": {
    "iso:country":"TR",
    "sg:address":"Fatihcad. Aksoy Ismrk. 11/b",
    "sg:city":"Merter",
    "sg:classifiers":[
        {
            "category":"Shopping",
            "subcategory":"Clothing, Apparel, & Fashions",
            "type":"Retail Goods"
        }
    ],
    "sg:phone":"+90 212 507 3337",
    "sg:province":"Istanbul",
    "sg:tags":[
        "ready",
        "wear"
    ],
    "wof:name":"Bey Grup Teks. A.s",
    "wof:placetype":"venue"
},
  "geometry": {"coordinates":[30.5263748169,39.7823448181],"type":"Point"}
}