{
  "type": "Feature",
  "properties": {
    "addr:full":"Ugur Mumcu Cad. No:17/b G.osmanpasa Ankara",
    "addr:housenumber":"17 / b",
    "addr:street":"Mumcu Cad. No;G.Osmanpasa",
    "iso:country":"TR",
    "sg:address":"Ugur Mumcu Cad. No:17/b",
    "sg:city":"G.osmanpasa",
    "sg:classifiers":[
        {
            "category":"Home & Garden",
            "subcategory":"Home Furnishings",
            "type":"Retail Goods"
        }
    ],
    "sg:phone":"+90 312 437 7300",
    "sg:province":"Ankara",
    "sg:tags":[
        "textile"
    ],
    "wof:name":"Ser Tekstil Co.",
    "wof:placetype":"venue"
},
  "geometry": {"coordinates":[32.8710174561,39.8924827576],"type":"Point"}
}