{
  "type": "Feature",
  "properties": {
    "addr:full":"Kosuyolu Katip Salih Sok. No:116 Kadikoy Bayrampasa Istanbul 34160",
    "addr:housenumber":"sok. no 116",
    "addr:postcode":"34160",
    "addr:street":"Katip Salih;Kadikoy Bayrampasa",
    "iso:country":"TR",
    "sg:address":"Kosuyolu Katip Salih Sok. No:116 Kadikoy",
    "sg:city":"Bayrampasa",
    "sg:classifiers":[
        {
            "category":"Manufacturing",
            "subcategory":"Chemicals & Compounds",
            "type":"Manufacturing & Wholesale Goods"
        }
    ],
    "sg:phone":"+90 216 428 6280",
    "sg:postcode":"34160",
    "sg:province":"Istanbul",
    "sg:tags":[
        "industry"
    ],
    "wof:name":"Enkem Kimya",
    "wof:placetype":"venue"
},
  "geometry": {"coordinates":[28.9861831665,41.0408554077],"type":"Point"}
}