{
  "type": "Feature",
  "properties": {
    "addr:full":"H?riyet Mah. Dr.cemil Beng?cad. Ertugrul Sk. No.2 Caglayan 54100 Istanbul",
    "addr:postcode":"?;54100",
    "addr:street":"Riyet Mah. Dr.Cemil;Cad.;Sk. No.2",
    "iso:country":"TR",
    "sg:address":"H?riyet Mah. Dr.cemil Beng?cad. Ertugrul Sk. No.2 Caglayan",
    "sg:city":"54100",
    "sg:classifiers":[
        {
            "category":"Home & Garden",
            "subcategory":"Building Materials",
            "type":"Retail Goods"
        }
    ],
    "sg:phone":"+90 212 296 0811",
    "sg:province":"Istanbul",
    "sg:tags":[
        "window",
        "door",
        "plastic"
    ],
    "wof:name":"Avrasya Plastik Dograma Aks Ve Sac Profil San.tic.ltd.sti.",
    "wof:placetype":"venue"
},
  "geometry": {"coordinates":[28.9824085236,41.0775985718],"type":"Point"}
}