{
  "type": "Feature",
  "properties": {
    "addr:full":"Karliktepe Mh. Top?mlar Sk. No:23 Kartal Mecidiyek\u00f6y Istanbul 34387",
    "addr:housenumber":"?;23",
    "addr:postcode":"34387",
    "addr:street":"Karliktepe Mh. Top;Mlar Sk. No",
    "iso:country":"TR",
    "sg:address":"Karliktepe Mh. Top?mlar Sk. No:23 Kartal",
    "sg:city":"Mecidiyek\u00f6y",
    "sg:classifiers":[
        {
            "category":"Shopping",
            "subcategory":"Computers & Home Electronics",
            "type":"Retail Goods"
        }
    ],
    "sg:phone":"+90 216 374 3309",
    "sg:postcode":"34387",
    "sg:province":"Istanbul",
    "sg:tags":[
        "product",
        "electric-electronic"
    ],
    "wof:name":"Lusso Aydin. San.",
    "wof:placetype":"venue"
},
  "geometry": {"coordinates":[28.9861831665,41.0408554077],"type":"Point"}
}