{
  "type": "Feature",
  "properties": {
    "iso:country":"TR",
    "sg:address":"Kayseri Cd. Irfan Sk. Kederoglu Ish. No:51 Altunsu Mh. Kozakli",
    "sg:city":"Mecidiyek\u00f6y",
    "sg:classifiers":[
        {
            "category":"Organizations",
            "subcategory":"Membership Organization",
            "type":"Services"
        }
    ],
    "sg:phone":"+90 384 471 4936",
    "sg:province":"Nevsehir",
    "wof:name":"Turistik Kozakli Kaplicalarini Tan. Dernegi",
    "wof:placetype":"venue"
},
  "geometry": {"coordinates":[34.8499984741,39.2332992554],"type":"Point"}
}