{
  "type": "Feature",
  "properties": {
    "iso:country":"TR",
    "sg:address":"Barbaros Bulvari No:10/5",
    "sg:city":"Besiktas",
    "sg:classifiers":[
        {
            "category":"Building & Trades",
            "subcategory":"Electrical",
            "type":"Services"
        }
    ],
    "sg:phone":"+90 212 268 0708",
    "sg:postcode":"75200",
    "sg:province":"Istanbul",
    "sg:tags":[
        "equipment",
        "lighting"
    ],
    "wof:name":"Osram Amp?l Tic. A.s.",
    "wof:placetype":"venue"
},
  "geometry": {"coordinates":[28.8369083405,41.0264968872],"type":"Point"}
}