{
  "type": "Feature",
  "properties": {
    "iso:country":"TR",
    "sg:address":"Ticaret Ve Sanayi Odasi Karsisi. G?k?eoglu Ishani. No: 30/4",
    "sg:city":"Manavgat",
    "sg:classifiers":[
        {
            "category":"Travel",
            "subcategory":"Travel Agent",
            "type":"Entertainment"
        }
    ],
    "sg:phone":"+90 242 248 8709",
    "sg:postcode":"07600",
    "sg:province":"Antalya",
    "sg:tags":[
        "agency",
        "tourism"
    ],
    "wof:name":"Vesa Turizm (antalya Sb.)",
    "wof:placetype":"venue"
},
  "geometry": {"coordinates":[30.7092056274,36.8790512085],"type":"Point"}
}