{
  "type": "Feature",
  "properties": {
    "iso:country":"TR",
    "sg:address":"D??c?er Sanayi Sitesi 10/a Blok No:17",
    "sg:city":"Gebze",
    "sg:classifiers":[
        {
            "category":"Home & Garden",
            "subcategory":"Building Materials",
            "type":"Retail Goods"
        }
    ],
    "sg:phone":"+90 262 642 2121",
    "sg:postcode":"41400",
    "sg:province":"Kocaeli",
    "sg:tags":[
        "window",
        "door"
    ],
    "wof:name":"Di-ba Plastik",
    "wof:placetype":"venue"
},
  "geometry": {"coordinates":[29.9345855713,40.7669563293],"type":"Point"}
}