{
  "type": "Feature",
  "properties": {
    "addr:full":"Yeni Sanayi Sitesi 32.cadde No:1 Merkez Kahramanmaras 46010",
    "addr:housenumber":"32.cadde no 1",
    "addr:postcode":"46010",
    "addr:street":"Yeni Sanayi Sitesi;Merkez Kahramanmaras",
    "iso:country":"TR",
    "sg:address":"Yeni Sanayi Sitesi 32.cadde No:1",
    "sg:city":"Merkez",
    "sg:classifiers":[
        {
            "category":"Home & Garden",
            "subcategory":"Household Appliances",
            "type":"Retail Goods"
        }
    ],
    "sg:phone":"+90 344 236 3662",
    "sg:postcode":"46010",
    "sg:province":"Kahramanmaras",
    "sg:tags":[
        "kitchenware"
    ],
    "wof:name":"Maras Tutku Metal",
    "wof:placetype":"venue"
},
  "geometry": {"coordinates":[36.9282989502,37.5894012451],"type":"Point"}
}