{
  "type": "Feature",
  "properties": {
    "addr:full":"Dumankaya Ismerk. No:8 D?tyol Pendik Istanbul 34916",
    "addr:housenumber":"?",
    "addr:postcode":"34916",
    "addr:street":"No 8 D",
    "iso:country":"TR",
    "sg:address":"Dumankaya Ismerk. No:8 D?tyol",
    "sg:city":"Pendik",
    "sg:classifiers":[
        {
            "category":"Home & Garden",
            "subcategory":"Hardware",
            "type":"Retail Goods"
        }
    ],
    "sg:phone":"+90 216 379 3722",
    "sg:postcode":"34916",
    "sg:province":"Istanbul",
    "sg:tags":[
        "store"
    ],
    "wof:name":"Reks End?striyel ?rn. Tic. Paz. A.s.",
    "wof:placetype":"venue"
},
  "geometry": {"coordinates":[28.9861831665,41.0408554077],"type":"Point"}
}