{
  "type": "Feature",
  "properties": {
    "addr:full":"B.dere Cad.hukukcular Sitesi No: 24 K:5 D:53 M.koy Istanbul",
    "addr:housenumber":"5 d 53",
    "addr:street":"K",
    "iso:country":"TR",
    "sg:address":"B.dere Cad.hukukcular Sitesi No: 24 K:5 D:53",
    "sg:city":"M.koy",
    "sg:classifiers":[
        {
            "category":"Bars & Pubs",
            "subcategory":"Nightclub",
            "type":"Food & Drink"
        }
    ],
    "sg:phone":"+90 212 288 4367",
    "sg:province":"Istanbul",
    "sg:tags":[
        "oprerators",
        "pier",
        "jetty"
    ],
    "wof:name":"Deniz Deniz Isleri Insaat Ve Taahhut Tic.ltd.sti.",
    "wof:placetype":"venue"
},
  "geometry": {"coordinates":[29.0148353577,41.0912704468],"type":"Point"}
}