{
  "type": "Feature",
  "properties": {
    "iso:country":"TR",
    "sg:address":"Sadirvan Cad. 51/1",
    "sg:city":"06836",
    "sg:orig_category":"Prefabric Construction",
    "sg:phone":"+90 378 227 2230",
    "sg:province":"Bartin",
    "wof:name":"Ustaoglu Prefabrik Yapi Elemanlari",
    "wof:placetype":"venue"
},
  "geometry": {"coordinates":[32.3374443054,41.6328010559],"type":"Point"}
}