{
  "type": "Feature",
  "properties": {
    "iso:country":"TR",
    "sg:address":"Ataturk Cad. Kumbahce Camii Alti",
    "sg:city":"Bodrum",
    "sg:classifiers":[
        {
            "category":"Food & Beverages",
            "subcategory":"Candy",
            "type":"Retail Goods"
        }
    ],
    "sg:phone":"+90 252 313 9151",
    "sg:postcode":"48400",
    "sg:province":"Mugla",
    "sg:tags":[
        "biscuit-chocolate-candy"
    ],
    "wof:name":"Ilke Gida Maddeleri Pazarlama Ltd.sti.",
    "wof:placetype":"venue"
},
  "geometry": {"coordinates":[28.365801,37.219601],"type":"Point"}
}