{
  "type": "Feature",
  "properties": {
    "iso:country":"TR",
    "sg:address":"Ikitelli Organize Sanayi B?gesi Metal Is Sanayi Sitesi 6.blok No",
    "sg:city":"Iskenderun",
    "sg:classifiers":[
        {
            "category":"Manufacturing",
            "subcategory":"Rubber & Plastics",
            "type":"Manufacturing & Wholesale Goods"
        }
    ],
    "sg:phone":"+90 212 671 3402",
    "sg:postcode":"31200",
    "sg:province":"Istanbul",
    "sg:tags":[
        "industry"
    ],
    "sg:website":"elektroplast.com.tr",
    "wof:name":"Elektro Plast Elek-elektronik-plastik Malz.ltd.",
    "wof:placetype":"venue"
},
  "geometry": {"coordinates":[28.9759254456,41.0123786926],"type":"Point"}
}