{
  "type": "Feature",
  "properties": {
    "addr:full":"Zumrutevler Tulin Cad.no:63 Maltepe Bagcilar Istanbul 33115",
    "addr:housenumber":"63",
    "addr:postcode":"33115",
    "addr:street":"Cad.No",
    "iso:country":"TR",
    "sg:address":"Zumrutevler Tulin Cad.no:63 Maltepe",
    "sg:city":"Bagcilar",
    "sg:classifiers":[
        {
            "category":"Wholesale",
            "subcategory":"Home Furnishings",
            "type":"Manufacturing & Wholesale Goods"
        }
    ],
    "sg:phone":"+90 216 371 6125",
    "sg:postcode":"33115",
    "sg:province":"Istanbul",
    "sg:tags":[
        "furniture"
    ],
    "wof:name":"Ozgur Mobilya",
    "wof:placetype":"venue"
},
  "geometry": {"coordinates":[28.9861831665,41.0408554077],"type":"Point"}
}