{
  "type": "Feature",
  "properties": {
    "addr:full":"Inkilap Cd.no8 ?esme Izmir",
    "addr:housenumber":"?",
    "addr:street":"Esme",
    "iso:country":"TR",
    "sg:address":"Inkilap Cd.no8",
    "sg:city":"?esme",
    "sg:classifiers":[
        {
            "category":"Freight",
            "type":"Transportation"
        }
    ],
    "sg:phone":"+90 232 712 6932",
    "sg:province":"Izmir",
    "sg:tags":[
        "agent",
        "shipping",
        "broker"
    ],
    "wof:name":"Tamer Gemicilik Ltd.sti.",
    "wof:placetype":"venue"
},
  "geometry": {"coordinates":[27.129686,38.418697],"type":"Point"}
}