{
  "type": "Feature",
  "properties": {
    "addr:full":"Cumhuriyet Meydani Meydan Apt. 11/2, Pasaport Izmir 35210",
    "addr:postcode":"35210",
    "addr:street":"Pasaport",
    "iso:country":"TR",
    "sg:address":"Cumhuriyet Meydani Meydan Apt. 11/2,",
    "sg:city":"Pasaport",
    "sg:classifiers":[
        {
            "category":"Freight",
            "type":"Transportation"
        }
    ],
    "sg:phone":"+90 2324634960463",
    "sg:postcode":"35210",
    "sg:province":"Izmir",
    "sg:tags":[
        "cargo",
        "air"
    ],
    "wof:name":"Swissair",
    "wof:placetype":"venue"
},
  "geometry": {"coordinates":[36.1658630371,36.2060699463],"type":"Point"}
}