{
  "type": "Feature",
  "properties": {
    "iso:country":"TR",
    "sg:address":"Tahtakale Cd. Pirhan No:22 K:2 D:207 Emin?? Istanbul",
    "sg:city":"Besiktas",
    "sg:classifiers":[
        {
            "category":"Shopping",
            "subcategory":"Stationery & Office Supplies",
            "type":"Retail Goods"
        }
    ],
    "sg:phone":"+90 212 513 4209",
    "sg:postcode":"34347",
    "sg:province":"Istanbul",
    "wof:name":"Derya Kirtasiye Ith. Imal. Dah. Tic. Ltd. Sti.",
    "wof:placetype":"venue"
},
  "geometry": {"coordinates":[29.026354,41.05397],"type":"Point"}
}