{
  "type": "Feature",
  "properties": {
    "addr:full":"S??gelik Mev. Orhangazi Iskenderun Bursa 31200",
    "addr:housenumber":"? ?",
    "addr:postcode":"31200",
    "addr:street":"S;Gelik Mev. Orhangazi",
    "iso:country":"TR",
    "sg:address":"S??gelik Mev. Orhangazi",
    "sg:city":"Iskenderun",
    "sg:classifiers":[
        {
            "category":"Wholesale",
            "subcategory":"Petroleum",
            "type":"Manufacturing & Wholesale Goods"
        }
    ],
    "sg:phone":"+90 224 573 6391",
    "sg:postcode":"31200",
    "sg:province":"Bursa",
    "wof:name":"Denge Petrol",
    "wof:placetype":"venue"
},
  "geometry": {"coordinates":[29.0580043793,40.1947555542],"type":"Point"}
}