{
  "type": "Feature",
  "properties": {
    "iso:country":"TR",
    "sg:address":"Gazi Mustafa",
    "sg:city":"Maltepe",
    "sg:classifiers":[
        {
            "category":"Banks & Credit Unions",
            "subcategory":"Bank",
            "type":"Services"
        }
    ],
    "sg:phone":"+90 312 231 9775",
    "sg:postcode":"01000",
    "sg:province":"06570",
    "wof:name":"T?kiye Vakiflar, Bankasi Tao",
    "wof:placetype":"venue"
},
  "geometry": {"coordinates":[32.846558,39.927845],"type":"Point"}
}