{
  "type": "Feature",
  "properties": {
    "addr:full":"Baglarbasi,selamiali Mh.reisul Kuttar Sk.no.50 D2 Uskudar Istanbul 34672",
    "addr:housenumber":"d2",
    "addr:postcode":"34672",
    "addr:street":"Sk.No.50",
    "iso:country":"TR",
    "sg:address":"Baglarbasi,selamiali Mh.reisul Kuttar Sk.no.50 D2",
    "sg:city":"Uskudar",
    "sg:classifiers":[
        {
            "category":"Freight",
            "type":"Transportation"
        }
    ],
    "sg:phone":"+90 216 343 4722",
    "sg:postcode":"34672",
    "sg:province":"Istanbul",
    "sg:tags":[
        "agent",
        "shipping",
        "broker"
    ],
    "wof:name":"Assos Denizcilik Ltd.sti.",
    "wof:placetype":"venue"
},
  "geometry": {"coordinates":[29.015442,41.021832],"type":"Point"}
}