{
  "type": "Feature",
  "properties": {
    "addr:full":"Yenidere Sok. No: 21 Mecidiyek\u00f6y Istanbul 80100",
    "addr:housenumber":"no 21",
    "addr:postcode":"80100",
    "addr:street":"Yenidere Sok.;Istanbul",
    "iso:country":"TR",
    "sg:address":"Yenidere Sok. No: 21",
    "sg:city":"Mecidiyek\u00f6y",
    "sg:classifiers":[
        {
            "category":"Communications",
            "subcategory":"Newspaper",
            "type":"Services"
        }
    ],
    "sg:phone":"+90 212 216 9161",
    "sg:postcode":"80100",
    "sg:province":"Istanbul",
    "sg:tags":[
        "advertising"
    ],
    "wof:name":"Reklam58",
    "wof:placetype":"venue"
},
  "geometry": {"coordinates":[28.9610500336,41.0376663208],"type":"Point"}
}