{
  "type": "Feature",
  "properties": {
    "iso:country":"TR",
    "sg:address":"Hotel Grand Inn Omurtak Str. No:9 Corlu",
    "sg:city":"Ikitelli/K\u00fc\u00e7\u00fck\u00e7ekmece",
    "sg:classifiers":[
        {
            "category":"Shopping",
            "subcategory":"Computers & Home Electronics",
            "type":"Retail Goods"
        }
    ],
    "sg:phone":"+90 282 654 2646",
    "sg:postcode":"34670",
    "sg:province":"Tekirdag",
    "sg:tags":[
        "connector",
        "cable"
    ],
    "wof:name":"A & K Cable Int. Trade Co.",
    "wof:placetype":"venue"
},
  "geometry": {"coordinates":[27.518995285,40.9782791138],"type":"Point"}
}