{
  "type": "Feature",
  "properties": {
    "iso:country":"TR",
    "sg:address":"Dr. Orhan Maltepe Cd. No:86/a",
    "sg:city":"Pendik",
    "sg:classifiers":[
        {
            "category":"Building & Trades",
            "subcategory":"Electrical",
            "type":"Services"
        }
    ],
    "sg:phone":"+90 216 354 1907",
    "sg:postcode":"34916",
    "sg:province":"Istanbul",
    "sg:tags":[
        "equipment",
        "lighting"
    ],
    "wof:name":"Pendik Aydinlatma Elektrik Malzeme. San. Tic.",
    "wof:placetype":"venue"
},
  "geometry": {"coordinates":[29.2340984344,40.8787307739],"type":"Point"}
}