{
  "type": "Feature",
  "properties": {
    "addr:full":"Ankara Asfalti, Soganlik? Karsisi 81420 Kartal Istanbul Ikitelli Istanbul 34306",
    "addr:postcode":"81420;34306",
    "addr:street":"Karsisi",
    "iso:country":"TR",
    "sg:address":"Ankara Asfalti, Soganlik? Karsisi 81420 Kartal Istanbul",
    "sg:city":"Ikitelli",
    "sg:classifiers":[
        {
            "category":"Sports & Exercise",
            "subcategory":"Playing Field",
            "type":"Entertainment"
        }
    ],
    "sg:phone":"+90 216 389 5884",
    "sg:postcode":"34306",
    "sg:province":"Istanbul",
    "sg:tags":[
        "game"
    ],
    "wof:name":"Adel Kalemcilik Tic Ve San As",
    "wof:placetype":"venue"
},
  "geometry": {"coordinates":[28.7984962463,41.0884017944],"type":"Point"}
}