{
  "type": "Feature",
  "properties": {
    "iso:country":"TR",
    "sg:address":"Sude Pen Bahadir D?ndar K???k Sanayi Sitesi 2.blok No:43",
    "sg:city":"48000",
    "sg:classifiers":[
        {
            "category":"Home & Garden",
            "subcategory":"Building Materials",
            "type":"Retail Goods"
        }
    ],
    "sg:phone":"+90 252 214 0124",
    "sg:province":"Mugla",
    "sg:tags":[
        "window",
        "door",
        "plastic"
    ],
    "wof:name":"Plaspen",
    "wof:placetype":"venue"
},
  "geometry": {"coordinates":[28.3658008575,37.2196006775],"type":"Point"}
}