{
  "type": "Feature",
  "properties": {
    "iso:country":"TR",
    "sg:address":"Yapici Is Mrk Asma Kat P:103",
    "sg:city":"Sel?uklu",
    "sg:classifiers":[
        {
            "category":"Food & Beverages",
            "subcategory":"Specialty",
            "type":"Retail Goods"
        }
    ],
    "sg:province":"Konya",
    "sg:tags":[
        "materials-spices",
        "additive"
    ],
    "wof:name":"Avci Gida Katki Maddeleri Paz.",
    "wof:placetype":"venue"
},
  "geometry": {"coordinates":[32.4990272522,37.8715362549],"type":"Point"}
}