{
  "type": "Feature",
  "properties": {
    "addr:full":"Dogu San. Sit. 2. Blok No:23 Y.bosna Eskigaraj Istanbul",
    "addr:housenumber":"2 blok no 23",
    "addr:street":"Sit.",
    "iso:country":"TR",
    "sg:address":"Dogu San. Sit. 2. Blok No:23 Y.bosna",
    "sg:city":"Eskigaraj",
    "sg:classifiers":[
        {
            "category":"Manufacturing",
            "subcategory":"Rubber & Plastics",
            "type":"Manufacturing & Wholesale Goods"
        }
    ],
    "sg:phone":"+90 212 653 8895",
    "sg:province":"Istanbul",
    "sg:tags":[
        "industry"
    ],
    "wof:name":"Sem Metal Plastik Ltd. Sti.",
    "wof:placetype":"venue"
},
  "geometry": {"coordinates":[28.9759254456,41.0123786926],"type":"Point"}
}