{
  "type": "Feature",
  "properties": {
    "addr:full":"Yokus Csm. Sk. No:69/1 Cerrahpasa 22/306 Istanbul",
    "addr:housenumber":"69 / 1;22 / 306",
    "addr:street":"Sk. No;Cerrahpasa",
    "iso:country":"TR",
    "sg:address":"Yokus Csm. Sk. No:69/1 Cerrahpasa",
    "sg:city":"22/306",
    "sg:classifiers":[
        {
            "category":"Wholesale",
            "subcategory":"Medical Equipment & Supplies",
            "type":"Manufacturing & Wholesale Goods"
        }
    ],
    "sg:phone":"+90 212 255 1556",
    "sg:province":"Istanbul",
    "wof:name":"Guner Medikal",
    "wof:placetype":"venue"
},
  "geometry": {"coordinates":[28.9395999908,41.0067405701],"type":"Point"}
}