{
  "type": "Feature",
  "properties": {
    "iso:country":"TR",
    "sg:address":"Yenice Mh. 143 Sk. No.9",
    "sg:city":"Turkoglu",
    "sg:classifiers":[
        {
            "category":"Farming",
            "subcategory":"Farm",
            "type":"Manufacturing & Wholesale Goods"
        }
    ],
    "sg:phone":"+90 242 242 4051",
    "sg:postcode":"46000",
    "sg:province":"Antalya",
    "sg:tags":[
        "agricultural",
        "product"
    ],
    "wof:name":"Mavikent Tarim Ltd.sti.",
    "wof:placetype":"venue"
},
  "geometry": {"coordinates":[32.4821281433,37.8302650452],"type":"Point"}
}