{
  "type": "Feature",
  "properties": {
    "addr:full":"Fikri K?e Alanya Istanbul 07400",
    "addr:postcode":"07400",
    "iso:country":"TR",
    "sg:address":"Fikri K?e",
    "sg:city":"Alanya",
    "sg:classifiers":[
        {
            "category":"Government",
            "subcategory":"Office",
            "type":"Public Place"
        }
    ],
    "sg:phone":"+90 216383095758",
    "sg:postcode":"07400",
    "sg:province":"Istanbul",
    "sg:tags":[
        "municipality"
    ],
    "wof:name":"Maltepe Belediye Baskani",
    "wof:placetype":"venue"
},
  "geometry": {"coordinates":[28.6678295135,41.0433311462],"type":"Point"}
}