{
  "type": "Feature",
  "properties": {
    "iso:country":"TR",
    "sg:address":"Vatan Cd. Cemil Sk. No:21 Caglayan",
    "sg:city":"Seyhan",
    "sg:classifiers":[
        {
            "category":"Shopping",
            "subcategory":"Stationery & Office Supplies",
            "type":"Retail Goods"
        }
    ],
    "sg:phone":"+90 212 247 7784",
    "sg:postcode":"01111",
    "sg:province":"Istanbul",
    "sg:tags":[
        "furniture"
    ],
    "wof:name":"Sancak Mob.",
    "wof:placetype":"venue"
},
  "geometry": {"coordinates":[28.9809131622,41.0739517212],"type":"Point"}
}