{
  "type": "Feature",
  "properties": {
    "addr:full":"Bostancibasi Sk. No.13/2 Besiktas Istanbul 75200",
    "addr:housenumber":"2",
    "addr:postcode":"75200",
    "addr:street":"Bostancibasi Sk. No.13 /",
    "iso:country":"TR",
    "sg:address":"Bostancibasi Sk. No.13/2",
    "sg:city":"Besiktas",
    "sg:classifiers":[
        {
            "category":"Building & Trades",
            "subcategory":"Landscaping Services",
            "type":"Services"
        }
    ],
    "sg:phone":"+90 212 259 2003",
    "sg:postcode":"75200",
    "sg:province":"Istanbul",
    "sg:tags":[
        "landscape"
    ],
    "wof:name":"Mng Peyzaj Planlama Ve Mimarlik Ofisi",
    "wof:placetype":"venue"
},
  "geometry": {"coordinates":[28.9741344452,41.0473022461],"type":"Point"}
}