{
  "type": "Feature",
  "properties": {
    "iso:country":"TR",
    "sg:address":"Harikzadeler Sok. No:48",
    "sg:city":"Laleli",
    "sg:orig_category":"Hotels: Motels",
    "sg:phone":"+90 212 511 7874",
    "sg:postcode":"34170",
    "sg:province":"Istanbul",
    "wof:name":"Klas Hotel",
    "wof:placetype":"venue"
},
  "geometry": {"coordinates":[28.958486557,41.0117149353],"type":"Point"}
}