{
  "type": "Feature",
  "properties": {
    "addr:full":"Alacam Sk. 36/29 Cankaya Y.dudullu Ankara",
    "addr:housenumber":"29",
    "addr:street":"Alacam Sk. 36 /",
    "iso:country":"TR",
    "sg:address":"Alacam Sk. 36/29 Cankaya",
    "sg:city":"Y.dudullu",
    "sg:orig_category":"General Industrial Products",
    "sg:phone":"+90 312 467 3593",
    "sg:province":"Ankara",
    "wof:name":"Palsan Endustri Ve Ticaret Ltd. Sti.",
    "wof:placetype":"venue"
},
  "geometry": {"coordinates":[32.8548583984,39.8959770203],"type":"Point"}
}