{
  "type": "Feature",
  "properties": {
    "addr:full":"Nisantoplar Mh Camii Sk No:3 Nurtepe Kagithane Istanbul 34406",
    "addr:postcode":"34406",
    "addr:street":"Nisantoplar",
    "iso:country":"TR",
    "sg:address":"Nisantoplar Mh Camii Sk No:3 Nurtepe",
    "sg:city":"Kagithane",
    "sg:classifiers":[
        {
            "category":"Manufacturing",
            "subcategory":"Glass & Minerals",
            "type":"Manufacturing & Wholesale Goods"
        }
    ],
    "sg:phone":"+90 212 294 7300",
    "sg:postcode":"34406",
    "sg:province":"Istanbul",
    "sg:tags":[
        "glass-mirror"
    ],
    "wof:name":"Ozgur Cam Insaat Yapi Malz",
    "wof:placetype":"venue"
},
  "geometry": {"coordinates":[28.9599609375,41.0745010376],"type":"Point"}
}