{
  "type": "Feature",
  "properties": {
    "addr:full":"Y. Emre Cd. No:34 4.levent Iskenderun Istanbul 31200",
    "addr:housenumber":"no;4.levent",
    "addr:postcode":"31200",
    "addr:street":"Cd.",
    "iso:country":"TR",
    "sg:address":"Y. Emre Cd. No:34 4.levent",
    "sg:city":"Iskenderun",
    "sg:classifiers":[
        {
            "category":"Shopping",
            "subcategory":"Computers & Home Electronics",
            "type":"Retail Goods"
        }
    ],
    "sg:phone":"+90 212 280 4534",
    "sg:postcode":"31200",
    "sg:province":"Istanbul",
    "sg:tags":[
        "product",
        "electric-electronic"
    ],
    "wof:name":"Panel Elektro San.",
    "wof:placetype":"venue"
},
  "geometry": {"coordinates":[28.9861831665,41.0408554077],"type":"Point"}
}