{
  "type": "Feature",
  "properties": {
    "iso:country":"TR",
    "sg:address":"B??dere Cad Dogus",
    "sg:city":"Istanbul",
    "sg:classifiers":[
        {
            "category":"Banks & Credit Unions",
            "subcategory":"Bank",
            "type":"Services"
        }
    ],
    "sg:phone":"+90 212 288 2000",
    "sg:province":"80290",
    "wof:name":"K?fezbank",
    "wof:placetype":"venue"
},
  "geometry": {"coordinates":[35.503899,38.676971],"type":"Point"}
}