{
  "type": "Feature",
  "properties": {
    "addr:full":"Bagdat Cad. 62/2 Kiziltoprak Istanbul 07300",
    "addr:housenumber":"62 / 2",
    "addr:postcode":"07300",
    "addr:street":"Bagdat Cad.",
    "iso:country":"TR",
    "sg:address":"Bagdat Cad. 62/2",
    "sg:city":"Kiziltoprak",
    "sg:classifiers":[
        {
            "category":"Professional",
            "type":"Services"
        }
    ],
    "sg:phone":"+90 2163309892330",
    "sg:postcode":"07300",
    "sg:province":"Istanbul",
    "sg:tags":[
        "catering"
    ],
    "wof:name":"Le Chic Catering & Davet Organizasyon Ltd.sti.",
    "wof:placetype":"venue"
},
  "geometry": {"coordinates":[28.9861831665,41.0408554077],"type":"Point"}
}