{
  "type": "Feature",
  "properties": {
    "iso:country":"TR",
    "sg:address":"17 Eylul Mah. S.i.gurcan Cad. No: 86 Bandirma",
    "sg:city":"4.levent",
    "sg:classifiers":[
        {
            "category":"Manufacturing",
            "subcategory":"Building Materials",
            "type":"Manufacturing & Wholesale Goods"
        }
    ],
    "sg:phone":"+90 266 712 2538",
    "sg:postcode":"80650",
    "sg:province":"Balikesir",
    "sg:tags":[
        "promotional"
    ],
    "wof:name":"Yontu",
    "wof:placetype":"venue"
},
  "geometry": {"coordinates":[27.8833007812,39.6520996094],"type":"Point"}
}