{
  "type": "Feature",
  "properties": {
    "addr:full":"Z.g?alp Mh. 39 Sk.no.45/1 Zeytinburnu \u00c7ankaya Istanbul 06550",
    "addr:housenumber":"39 sk.no.45 / 1",
    "addr:postcode":"06550",
    "addr:street":"Mh.;Zeytinburnu",
    "iso:country":"TR",
    "sg:address":"Z.g?alp Mh. 39 Sk.no.45/1 Zeytinburnu",
    "sg:city":"\u00c7ankaya",
    "sg:classifiers":[
        {
            "category":"Manufacturing",
            "subcategory":"Leather Goods",
            "type":"Manufacturing & Wholesale Goods"
        }
    ],
    "sg:phone":"+90 212 558 1182",
    "sg:postcode":"06550",
    "sg:province":"Istanbul",
    "wof:name":"?zel Deri Giyim Ltd.sti.",
    "wof:placetype":"venue"
},
  "geometry": {"coordinates":[28.9759254456,41.0123786926],"type":"Point"}
}