{
  "type": "Feature",
  "properties": {
    "addr:full":"Gedikpasa Haman Cad. Neviye Sok. Tan. Is Hani No:41/a Beyazit Beyazit Istanbul 34470",
    "addr:housenumber":"no 41 / a",
    "addr:postcode":"34470",
    "addr:street":"Haman Cad. Neviye Sok. Tan. Is",
    "iso:country":"TR",
    "sg:address":"Gedikpasa Haman Cad. Neviye Sok. Tan. Is Hani No:41/a Beyazit",
    "sg:city":"Beyazit",
    "sg:classifiers":[
        {
            "category":"Shopping",
            "subcategory":"Shoes",
            "type":"Retail Goods"
        }
    ],
    "sg:phone":"+90 212 517 4782",
    "sg:postcode":"34470",
    "sg:province":"Istanbul",
    "wof:name":"K?se Ayakkabi Tekstil Bilgisayar San.tic.ltd.sti.",
    "wof:placetype":"venue"
},
  "geometry": {"coordinates":[29.048174,41.093338],"type":"Point"}
}