{
  "type": "Feature",
  "properties": {
    "iso:country":"TR",
    "sg:address":"Mahmutbey Yolu Barbaros Mah. 7/2 Sok. No:22 Bagcilar",
    "sg:city":"Mersin",
    "sg:classifiers":[
        {
            "category":"Home & Garden",
            "subcategory":"Building Materials",
            "type":"Retail Goods"
        }
    ],
    "sg:phone":"+90 212 651 8770",
    "sg:postcode":"52750",
    "sg:province":"Istanbul",
    "sg:tags":[
        "window",
        "door",
        "plastic"
    ],
    "wof:name":"G?npenplastik Dograma San.tic.ltd.sti.",
    "wof:placetype":"venue"
},
  "geometry": {"coordinates":[28.8389015198,41.0243225098],"type":"Point"}
}