{
  "type": "Feature",
  "properties": {
    "iso:country":"TR",
    "sg:address":"Imes San. Sit. A Blok 107. Sk. No:39 Y.dudullu",
    "sg:city":"B\u00fcy\u00fck\u00e7ekmece",
    "sg:classifiers":[
        {
            "category":"Building & Trades",
            "subcategory":"Construction",
            "type":"Services"
        }
    ],
    "sg:phone":"+90 216 314 1846",
    "sg:postcode":"34905",
    "sg:province":"Istanbul",
    "sg:tags":[
        "industry",
        "mold"
    ],
    "wof:name":"G?ler Mak. Kalip San.",
    "wof:placetype":"venue"
},
  "geometry": {"coordinates":[28.9759254456,41.0123786926],"type":"Point"}
}