{
  "type": "Feature",
  "properties": {
    "iso:country":"TR",
    "sg:address":"Bayramyeri Meydani",
    "sg:city":"Denizli",
    "sg:classifiers":[
        {
            "category":"Banks & Credit Unions",
            "subcategory":"Bank",
            "type":"Services"
        }
    ],
    "sg:phone":"+90 258 263 9371",
    "sg:postcode":"01130",
    "sg:province":"20100",
    "wof:name":"T?kiye Is Bankasi As",
    "wof:placetype":"venue"
},
  "geometry": {"coordinates":[29.055231,40.181606],"type":"Point"}
}