{
  "type": "Feature",
  "properties": {
    "addr:full":"Cinnah Cad 38 Ankara 06690 63570",
    "addr:housenumber":"38",
    "addr:postcode":"06690 63570",
    "addr:street":"Cinnah Cad",
    "iso:country":"TR",
    "sg:address":"Cinnah Cad 38",
    "sg:city":"Ankara",
    "sg:classifiers":[
        {
            "category":"Banks & Credit Unions",
            "subcategory":"Bank",
            "type":"Services"
        }
    ],
    "sg:phone":"+90 312 440 3010",
    "sg:postcode":"63570",
    "sg:province":"06690",
    "wof:name":"Demirbank Tas",
    "wof:placetype":"venue"
},
  "geometry": {"coordinates":[32.857586,39.895824],"type":"Point"}
}