{
  "type": "Feature",
  "properties": {
    "addr:full":"Atilgan Sokak Siteler Altindag Ankara 07050",
    "addr:postcode":"07050",
    "addr:street":"Atilgan Sokak",
    "iso:country":"TR",
    "sg:address":"Atilgan Sokak Siteler",
    "sg:city":"Altindag",
    "sg:classifiers":[
        {
            "category":"Manufacturing",
            "subcategory":"Wood Products",
            "type":"Manufacturing & Wholesale Goods"
        }
    ],
    "sg:phone":"+90 312 353 1033",
    "sg:postcode":"07050",
    "sg:province":"Ankara",
    "sg:tags":[
        "forest"
    ],
    "wof:name":"Arsan Kaplama Ve Kereste",
    "wof:placetype":"venue"
},
  "geometry": {"coordinates":[32.9081039429,39.9558792114],"type":"Point"}
}