{
  "type": "Feature",
  "properties": {
    "addr:full":"Acipayam Asf. 6049 Sk. No.10 Zeytinburnu Denizli 34020",
    "addr:housenumber":"6049",
    "addr:postcode":"34020",
    "addr:street":"Asf.;Sk. No.10",
    "iso:country":"TR",
    "sg:address":"Acipayam Asf. 6049 Sk. No.10",
    "sg:city":"Zeytinburnu",
    "sg:classifiers":[
        {
            "category":"Manufacturing",
            "subcategory":"Leather Goods",
            "type":"Manufacturing & Wholesale Goods"
        }
    ],
    "sg:phone":"+90 258 266 4391",
    "sg:postcode":"34020",
    "sg:province":"Denizli",
    "wof:name":"Avrasya Deri Ltd.sti.",
    "wof:placetype":"venue"
},
  "geometry": {"coordinates":[35.3178825378,36.989616394],"type":"Point"}
}