{
  "type": "Feature",
  "properties": {
    "addr:full":"Kemer Bodrum Antalya 48400",
    "addr:postcode":"48400",
    "iso:country":"TR",
    "sg:address":"Kemer",
    "sg:city":"Bodrum",
    "sg:classifiers":[
        {
            "category":"Recreation",
            "subcategory":"Boat Charter",
            "type":"Entertainment"
        }
    ],
    "sg:phone":"+90 242 814 2792",
    "sg:postcode":"48400",
    "sg:province":"Antalya",
    "sg:tags":[
        "yachting"
    ],
    "wof:name":"Yokem Yachting",
    "wof:placetype":"venue"
},
  "geometry": {"coordinates":[30.5662612915,36.595741272],"type":"Point"}
}