{
  "type": "Feature",
  "properties": {
    "addr:full":"Defne Sk. No.19 Merter Istanbul",
    "addr:street":"Defne Sk. No.19",
    "iso:country":"TR",
    "sg:address":"Defne Sk. No.19",
    "sg:city":"Merter",
    "sg:classifiers":[
        {
            "category":"Shopping",
            "subcategory":"Clothing, Apparel, & Fashions",
            "type":"Retail Goods"
        }
    ],
    "sg:phone":"+90 212 507 7244",
    "sg:province":"Istanbul",
    "sg:tags":[
        "ready",
        "wear"
    ],
    "wof:name":"Nu & Tekstil A.s.",
    "wof:placetype":"venue"
},
  "geometry": {"coordinates":[28.5577926636,41.0134735107],"type":"Point"}
}