{
  "type": "Feature",
  "properties": {
    "iso:country":"TR",
    "sg:address":"Ihsaniye Mah. Tabil Mehmet Pasa Cad. Cesme Sok. No:2/6 B",
    "sg:city":"Sindirgi",
    "sg:classifiers":[
        {
            "category":"Farming",
            "subcategory":"Farm & Veterinary Services",
            "type":"Manufacturing & Wholesale Goods"
        }
    ],
    "sg:phone":"+90 374 213 2214",
    "sg:postcode":"10330",
    "sg:province":"Bolu",
    "sg:tags":[
        "veterinarian"
    ],
    "wof:name":"Ismail Gurluk",
    "wof:placetype":"venue"
},
  "geometry": {"coordinates":[31.6107006073,40.7332992554],"type":"Point"}
}