{
  "type": "Feature",
  "properties": {
    "addr:full":"19. Blok. No:568 Gimat Yenimahalle Ankara 06",
    "addr:housenumber":"blok. no 568;06",
    "addr:street":"Gimat;Ankara",
    "iso:country":"TR",
    "sg:address":"19. Blok. No:568 Gimat",
    "sg:city":"Yenimahalle",
    "sg:classifiers":[
        {
            "category":"Shopping",
            "subcategory":"Stationery & Office Supplies",
            "type":"Retail Goods"
        }
    ],
    "sg:phone":"+90 312 336 4745",
    "sg:postcode":"06",
    "sg:province":"Ankara",
    "sg:tags":[
        "paper"
    ],
    "wof:name":"Fanysoft Sihhi Kagit San. Tic. Ltd. Sti.",
    "wof:placetype":"venue"
},
  "geometry": {"coordinates":[32.7661018372,39.9571838379],"type":"Point"}
}