{
  "type": "Feature",
  "properties": {
    "iso:country":"TR",
    "sg:address":"Izmir Bulvari No:207",
    "sg:city":"Erb Aa",
    "sg:classifiers":[
        {
            "category":"Manufacturing",
            "subcategory":"Wood Products",
            "type":"Manufacturing & Wholesale Goods"
        }
    ],
    "sg:phone":"+90 258 261 3714",
    "sg:postcode":"60500",
    "sg:province":"Denizli",
    "sg:tags":[
        "forest"
    ],
    "wof:name":"Astas Orman Urunleri San.tic. Ltd.sti.",
    "wof:placetype":"venue"
},
  "geometry": {"coordinates":[29.0878982544,37.787979126],"type":"Point"}
}