{
  "type": "Feature",
  "properties": {
    "addr:full":"Incilipinar Mah. Akinalan Is Merkezi K: 2/7 Fatih Gaziantep 01740",
    "addr:housenumber":"2 / 7",
    "addr:postcode":"01740",
    "addr:street":"Incilipinar Mah. Akinalan;K;Fatih",
    "iso:country":"TR",
    "sg:address":"Incilipinar Mah. Akinalan Is Merkezi K: 2/7",
    "sg:city":"Fatih",
    "sg:orig_category":"Dryfood-dried Nuts",
    "sg:phone":"+90 342 232 9482",
    "sg:postcode":"01740",
    "sg:province":"Gaziantep",
    "wof:name":"Ruden Dis Tic. Ltd. Sti.",
    "wof:placetype":"venue"
},
  "geometry": {"coordinates":[37.4416732788,36.9459457397],"type":"Point"}
}