{
  "type": "Feature",
  "properties": {
    "addr:full":"Besevler K.san B? 75 Blok No:46 Besevler Bursa 16300",
    "addr:housenumber":"75 blok no 46",
    "addr:postcode":"16300",
    "addr:street":"Bursa",
    "iso:country":"TR",
    "sg:address":"Besevler K.san B? 75 Blok No:46",
    "sg:city":"Besevler",
    "sg:classifiers":[
        {
            "category":"Manufacturing",
            "subcategory":"Metals",
            "type":"Manufacturing & Wholesale Goods"
        }
    ],
    "sg:phone":"+90 224 441 7831",
    "sg:postcode":"16300",
    "sg:province":"Bursa",
    "sg:tags":[
        "processing"
    ],
    "wof:name":"Beysantas As",
    "wof:placetype":"venue"
},
  "geometry": {"coordinates":[29.1601390839,40.1895179749],"type":"Point"}
}