{
  "type": "Feature",
  "properties": {
    "iso:country":"TR",
    "sg:address":"Kiztasi Cad. No : 56 / 1",
    "sg:city":"Fatih",
    "sg:classifiers":[
        {
            "category":"Building & Trades",
            "subcategory":"Construction",
            "type":"Services"
        }
    ],
    "sg:phone":"+90 212 533 7202",
    "sg:postcode":"01740",
    "sg:province":"Istanbul",
    "sg:tags":[
        "foundation"
    ],
    "wof:name":"Arastirma Ve K?lt?r Vakfi",
    "wof:placetype":"venue"
},
  "geometry": {"coordinates":[28.9513988495,41.0167617798],"type":"Point"}
}