{
  "type": "Feature",
  "properties": {
    "iso:country":"TR",
    "sg:address":"Dosab Sardunya Sok. No:5",
    "sg:city":"Halkali",
    "sg:classifiers":[
        {
            "category":"Manufacturing",
            "subcategory":"Textiles",
            "type":"Manufacturing & Wholesale Goods"
        }
    ],
    "sg:phone":"+90 224 261 0666",
    "sg:postcode":"23410",
    "sg:province":"Bursa",
    "sg:tags":[
        "sizing",
        "dye"
    ],
    "wof:name":"Rateks Tekstil A.s.",
    "wof:placetype":"venue"
},
  "geometry": {"coordinates":[29.0586109161,40.1844291687],"type":"Point"}
}