{
  "type": "Feature",
  "properties": {
    "iso:country":"TR",
    "sg:address":"Gazi Cad. G?l?psj. K:3 No:44",
    "sg:city":"Mersin",
    "sg:classifiers":[
        {
            "category":"Wholesale",
            "subcategory":"Medical Equipment & Supplies",
            "type":"Manufacturing & Wholesale Goods"
        }
    ],
    "sg:phone":"+90 412 221 3714",
    "sg:postcode":"52750",
    "sg:province":"Diyarbakir",
    "wof:name":"Eray Medikal Ltd.",
    "wof:placetype":"venue"
},
  "geometry": {"coordinates":[40.2107009888,37.9244651794],"type":"Point"}
}