{
  "type": "Feature",
  "properties": {
    "iso:country":"TR",
    "sg:address":"4/1 Sok.no:6/c",
    "sg:city":"Uckuyular",
    "sg:classifiers":[
        {
            "category":"Food & Beverages",
            "subcategory":"Groceries & Convenience Stores",
            "type":"Retail Goods"
        }
    ],
    "sg:phone":"+90 232 248 4669",
    "sg:postcode":"35140",
    "sg:province":"Izmir",
    "sg:tags":[
        "drink-",
        "soft"
    ],
    "wof:name":"Elsa Dagitim",
    "wof:placetype":"venue"
},
  "geometry": {"coordinates":[27.073502,38.397457],"type":"Point"}
}