{
  "type": "Feature",
  "properties": {
    "iso:country":"TR",
    "sg:address":"Soganlik Yolu Timurlenk Sk. No:3 Kartal",
    "sg:city":"Kad\u0131k\u00f6y",
    "sg:classifiers":[
        {
            "category":"Manufacturing",
            "subcategory":"Metals",
            "type":"Manufacturing & Wholesale Goods"
        }
    ],
    "sg:phone":"+90 216 377 1355",
    "sg:postcode":"34990",
    "sg:province":"Istanbul",
    "sg:tags":[
        "industry"
    ],
    "wof:name":"Senkrom Metal Seramik Kaplama Ltd. Sti.",
    "wof:placetype":"venue"
},
  "geometry": {"coordinates":[29.2110500336,40.9091567993],"type":"Point"}
}