{
  "type": "Feature",
  "properties": {
    "addr:full":"6 Cadde No:59 Kirac Koyu Akin Mah 3 Bolge 34900 Buyukcekmece Istanbul Emin\u00f6n\u00fc/Ca\u011falo\u011flu Istanbul 34245",
    "addr:housenumber":"no 59;koyu;3",
    "addr:postcode":"34900;34245",
    "addr:street":"6 Cadde;Akin Mah",
    "iso:country":"TR",
    "sg:address":"6 Cadde No:59 Kirac Koyu Akin Mah 3 Bolge 34900 Buyukcekmece Istanbul",
    "sg:city":"Emin\u00f6n\u00fc/Ca\u011falo\u011flu",
    "sg:classifiers":[
        {
            "category":"Personal",
            "subcategory":"Shoe Repair & Shine",
            "type":"Services"
        }
    ],
    "sg:phone":"+90 212 886 7611",
    "sg:postcode":"34245",
    "sg:province":"Istanbul",
    "sg:tags":[
        "leather"
    ],
    "wof:name":"Kiraliler Ayakkabicilik San Tic As",
    "wof:placetype":"venue"
},
  "geometry": {"coordinates":[28.9128303528,41.0602035522],"type":"Point"}
}