{
  "type": "Feature",
  "properties": {
    "iso:country":"TR",
    "sg:address":"Krom Apt. Yah Cad.342/b",
    "sg:city":"Denizli",
    "sg:classifiers":[
        {
            "category":"Banks & Credit Unions",
            "subcategory":"Bank",
            "type":"Services"
        }
    ],
    "sg:phone":"+90 232 368 6660",
    "sg:postcode":"01130",
    "sg:province":"Izmir",
    "wof:name":"Demirbank Tas",
    "wof:placetype":"venue"
},
  "geometry": {"coordinates":[27.129686,38.418697],"type":"Point"}
}