{
  "type": "Feature",
  "properties": {
    "addr:full":"Malatya Merkez Malatya",
    "iso:country":"TR",
    "sg:address":"Malatya",
    "sg:city":"Merkez",
    "sg:classifiers":[
        {
            "category":"Banks & Credit Unions",
            "subcategory":"Bank",
            "type":"Services"
        }
    ],
    "sg:phone":"+90 82113000",
    "sg:province":"Malatya",
    "wof:name":"T?kiye Cumhuriyet Merkez Bankasi",
    "wof:placetype":"venue"
},
  "geometry": {"coordinates":[38.314301,38.3475],"type":"Point"}
}