{
  "type": "Feature",
  "properties": {
    "addr:full":"Yasar T?? G?basi Bilecik",
    "iso:country":"TR",
    "sg:address":"Yasar T??",
    "sg:city":"G?basi",
    "sg:classifiers":[
        {
            "category":"Government",
            "subcategory":"Office",
            "type":"Public Place"
        }
    ],
    "sg:phone":"+90 228 212 1042",
    "sg:province":"Bilecik",
    "sg:tags":[
        "municipality"
    ],
    "wof:name":"Bilecik Ili Belediye Baskani",
    "wof:placetype":"venue"
},
  "geometry": {"coordinates":[30.0647029877,39.9047889709],"type":"Point"}
}