{
  "type": "Feature",
  "properties": {
    "addr:full":"Esentepe Cad. No:6/5 Mecidiyekoy \u00c7ankaya Istanbul",
    "addr:housenumber":"5",
    "addr:street":"Esentepe Cad. No 6 /",
    "iso:country":"TR",
    "sg:address":"Esentepe Cad. No:6/5 Mecidiyekoy",
    "sg:city":"\u00c7ankaya",
    "sg:classifiers":[
        {
            "category":"Professional",
            "subcategory":"Computer Services",
            "type":"Services"
        }
    ],
    "sg:phone":"+90 212 212 8788",
    "sg:province":"Istanbul",
    "sg:tags":[
        "application",
        "software"
    ],
    "wof:name":"Ema Bilgisayar Sistemleri Ve Yazilim Hizmetleri Ltd.",
    "wof:placetype":"venue"
},
  "geometry": {"coordinates":[28.9968395233,41.0705795288],"type":"Point"}
}