{
  "type": "Feature",
  "properties": {
    "addr:full":"Ank. Asf. Yakacik Yan Yolu Zeytinler Sk. Yakacik Iskenderun Istanbul 31200",
    "addr:postcode":"31200",
    "addr:street":"Yan Yolu;Sk.",
    "iso:country":"TR",
    "sg:address":"Ank. Asf. Yakacik Yan Yolu Zeytinler Sk. Yakacik",
    "sg:city":"Iskenderun",
    "sg:classifiers":[
        {
            "category":"Manufacturing",
            "subcategory":"Tools & Machinery",
            "type":"Manufacturing & Wholesale Goods"
        }
    ],
    "sg:phone":"+90 216 377 0034",
    "sg:postcode":"31200",
    "sg:province":"Istanbul",
    "sg:tags":[
        "machine",
        "industry"
    ],
    "wof:name":"Ert?rkler Makina San. Tic. A.s.",
    "wof:placetype":"venue"
},
  "geometry": {"coordinates":[28.9759254456,41.0123786926],"type":"Point"}
}