{
  "type": "Feature",
  "properties": {
    "addr:full":"K?ithane Cd. No:2 K?ithane Halkali Istanbul 23410",
    "addr:housenumber":"no 2 k ?",
    "addr:postcode":"23410",
    "addr:street":"Ithane Cd.;Ithane Halkali",
    "iso:country":"TR",
    "sg:address":"K?ithane Cd. No:2 K?ithane",
    "sg:city":"Halkali",
    "sg:classifiers":[
        {
            "category":"Shopping",
            "subcategory":"Stationery & Office Supplies",
            "type":"Retail Goods"
        }
    ],
    "sg:phone":"+90 212 232 9308",
    "sg:postcode":"23410",
    "sg:province":"Istanbul",
    "sg:tags":[
        "furniture"
    ],
    "wof:name":"Demeter Dekor.",
    "wof:placetype":"venue"
},
  "geometry": {"coordinates":[28.9759254456,41.0123786926],"type":"Point"}
}