{
  "type": "Feature",
  "properties": {
    "addr:full":"Kucuk Langa Cad.kosehan No:46/10 K 3- Aksaray Istanbul 31030",
    "addr:housenumber":"10 k 3",
    "addr:postcode":"31030",
    "addr:street":"Kucuk;No 46 /",
    "iso:country":"TR",
    "sg:address":"Kucuk Langa Cad.kosehan No:46/10 K 3-",
    "sg:city":"Aksaray",
    "sg:classifiers":[
        {
            "category":"Manufacturing",
            "subcategory":"Building Materials",
            "type":"Manufacturing & Wholesale Goods"
        }
    ],
    "sg:phone":"+90 212 530 0377",
    "sg:postcode":"31030",
    "sg:province":"Istanbul",
    "sg:tags":[
        "lifts-elevators"
    ],
    "wof:name":"Evren Asans? Sanayi",
    "wof:placetype":"venue"
},
  "geometry": {"coordinates":[28.9759254456,41.0123786926],"type":"Point"}
}