{
  "type": "Feature",
  "properties": {
    "addr:full":"Org.san.b?. 1.c No.10 Iskitler Kayseri 06070",
    "addr:housenumber":"no.10",
    "addr:postcode":"06070",
    "addr:street":"1.C",
    "iso:country":"TR",
    "sg:address":"Org.san.b?. 1.c No.10",
    "sg:city":"Iskitler",
    "sg:classifiers":[
        {
            "category":"Food & Beverages",
            "subcategory":"Candy",
            "type":"Retail Goods"
        }
    ],
    "sg:phone":"+90 352 232 3074",
    "sg:postcode":"06070",
    "sg:province":"Kayseri",
    "sg:tags":[
        "biscuit-chocolate-candy"
    ],
    "wof:name":"Ak Gida A.s.",
    "wof:placetype":"venue"
},
  "geometry": {"coordinates":[35.489136,38.722576],"type":"Point"}
}