{
  "type": "Feature",
  "properties": {
    "addr:full":"Fahrettin Altay Cad. Cesur Ish. No: 2/13 Kad\u0131k\u00f6y Antalya 80020",
    "addr:housenumber":"13",
    "addr:postcode":"80020",
    "addr:street":"Fahrettin Altay Cad. Cesur Ish. No 2 /",
    "iso:country":"TR",
    "sg:address":"Fahrettin Altay Cad. Cesur Ish. No: 2/13",
    "sg:city":"Kad\u0131k\u00f6y",
    "sg:classifiers":[
        {
            "category":"Manufacturing",
            "subcategory":"Building Materials",
            "type":"Manufacturing & Wholesale Goods"
        }
    ],
    "sg:phone":"+90 242 244 7218",
    "sg:postcode":"80020",
    "sg:province":"Antalya",
    "sg:tags":[
        "promotional"
    ],
    "wof:name":"Bilgi Evi Danismanlik Ltd.",
    "wof:placetype":"venue"
},
  "geometry": {"coordinates":[30.7031345367,36.8875045776],"type":"Point"}
}