{
  "type": "Feature",
  "properties": {
    "addr:full":"Vatan Mah. Cevizlik Sok. No:46 Yildirim Bursa 03300",
    "addr:housenumber":"no 46",
    "addr:postcode":"03300",
    "addr:street":"Mah. Cevizlik Sok.;Bursa",
    "iso:country":"TR",
    "sg:address":"Vatan Mah. Cevizlik Sok. No:46",
    "sg:city":"Yildirim",
    "sg:classifiers":[
        {
            "category":"Wholesale",
            "subcategory":"Machinery & Supplies",
            "type":"Manufacturing & Wholesale Goods"
        }
    ],
    "sg:phone":"+90 224 361 9103",
    "sg:postcode":"03300",
    "sg:province":"Bursa",
    "sg:tags":[
        "agricultural"
    ],
    "wof:name":"Dincmak Mak. San.tic. Ltd.sti.",
    "wof:placetype":"venue"
},
  "geometry": {"coordinates":[29.0580043793,40.1947555542],"type":"Point"}
}