{
  "type": "Feature",
  "properties": {
    "iso:country":"TR",
    "sg:address":"Hal Yolu Bay Plaza No:5 K:5 I?renk?",
    "sg:city":"Seyhan",
    "sg:classifiers":[
        {
            "category":"Manufacturing",
            "subcategory":"Chemicals & Compounds",
            "type":"Manufacturing & Wholesale Goods"
        }
    ],
    "sg:phone":"+90 216 380 8109",
    "sg:postcode":"01120",
    "sg:province":"Istanbul",
    "sg:tags":[
        "pharmaceutical"
    ],
    "wof:name":"Gen Ila? Ve Saglik ?r?nleri San.tic.ltd",
    "wof:placetype":"venue"
},
  "geometry": {"coordinates":[28.9759254456,41.0123786926],"type":"Point"}
}