{
  "type": "Feature",
  "properties": {
    "addr:full":"Muratdede Mah. 358 Sk. No. 17 Kavaklidere Denizli 35040",
    "addr:housenumber":"358;17",
    "addr:postcode":"35040",
    "addr:street":"Muratdede Mah.;Sk. No.",
    "iso:country":"TR",
    "sg:address":"Muratdede Mah. 358 Sk. No. 17",
    "sg:city":"Kavaklidere",
    "sg:classifiers":[
        {
            "category":"Home & Garden",
            "subcategory":"Home Furnishings",
            "type":"Retail Goods"
        }
    ],
    "sg:phone":"+90 258 262 1672",
    "sg:postcode":"35040",
    "sg:province":"Denizli",
    "sg:tags":[
        "textile"
    ],
    "wof:name":"Ugurlu Tekstil",
    "wof:placetype":"venue"
},
  "geometry": {"coordinates":[29.0788803101,37.7851867676],"type":"Point"}
}