{
  "type": "Feature",
  "properties": {
    "addr:full":"Cumhuriyet Cad. Saner Is Merkezi Kat 1 No: 26-27 Osmangazi Bursa 16300",
    "addr:housenumber":"kat 1 no 26-27",
    "addr:postcode":"16300",
    "addr:street":"Cumhuriyet Cad. Saner",
    "iso:country":"TR",
    "sg:address":"Cumhuriyet Cad. Saner Is Merkezi Kat 1 No: 26-27",
    "sg:city":"Osmangazi",
    "sg:classifiers":[
        {
            "category":"Shopping",
            "subcategory":"Baby Store",
            "type":"Retail Goods"
        }
    ],
    "sg:phone":"+90 224 223 8539",
    "sg:postcode":"16300",
    "sg:province":"Bursa",
    "sg:tags":[
        "wear"
    ],
    "wof:name":"Pedi Kids",
    "wof:placetype":"venue"
},
  "geometry": {"coordinates":[29.160139,40.189518],"type":"Point"}
}