{
  "type": "Feature",
  "properties": {
    "addr:full":"M?rselpasa Blv. No:24/16 Arslanbey Is Mrk. Konak Izmir 07110",
    "addr:housenumber":"24 / 16",
    "addr:postcode":"07110",
    "addr:street":"Blv. No;Arslanbey Is",
    "iso:country":"TR",
    "sg:address":"M?rselpasa Blv. No:24/16 Arslanbey Is Mrk.",
    "sg:city":"Konak",
    "sg:classifiers":[
        {
            "category":"Sports & Exercise",
            "subcategory":"Swimming Pool",
            "type":"Entertainment"
        }
    ],
    "sg:phone":"+90 4467230",
    "sg:postcode":"07110",
    "sg:province":"Izmir",
    "sg:tags":[
        "cartridge-toner-",
        "ink"
    ],
    "wof:name":"Sanfaks B?ro Cihazlari San.tic.ltd.sti",
    "wof:placetype":"venue"
},
  "geometry": {"coordinates":[27.1423015594,38.4251480103],"type":"Point"}
}