{
  "type": "Feature",
  "properties": {
    "addr:full":"M??dar Eminpasa Sk. Cesmeli Han No:6 Mercan Istanbul 12600",
    "addr:postcode":"12600",
    "addr:street":"Eminpasa Sk.",
    "iso:country":"TR",
    "sg:address":"M??dar Eminpasa Sk. Cesmeli Han No:6",
    "sg:city":"Mercan",
    "sg:classifiers":[
        {
            "category":"Sports & Exercise",
            "subcategory":"Ski Slope",
            "type":"Entertainment"
        }
    ],
    "sg:phone":"+90 212 513 0394",
    "sg:postcode":"12600",
    "sg:province":"Istanbul",
    "sg:tags":[
        "wear"
    ],
    "wof:name":"Regs Jeans",
    "wof:placetype":"venue"
},
  "geometry": {"coordinates":[28.975925,41.012379],"type":"Point"}
}