{
  "type": "Feature",
  "properties": {
    "addr:full":"Sururi Mah. Haci Kucuk Cami Sok. Havuzlu Han Kat:4 No:100 Sultanhamam Istanbul",
    "addr:housenumber":"4",
    "addr:street":"Cami Sok. Havuzlu Han Kat;No 100 Sultanhamam",
    "iso:country":"TR",
    "sg:address":"Sururi Mah. Haci Kucuk Cami Sok. Havuzlu Han Kat:4 No:100",
    "sg:city":"Sultanhamam",
    "sg:classifiers":[
        {
            "category":"Shopping",
            "subcategory":"Crafts & Fabrics",
            "type":"Retail Goods"
        }
    ],
    "sg:phone":"+90 212 528 9985",
    "sg:province":"Istanbul",
    "sg:tags":[
        "weaving"
    ],
    "wof:name":"Beyza Tekstil Kumascilik",
    "wof:placetype":"venue"
},
  "geometry": {"coordinates":[28.9759254456,41.0123786926],"type":"Point"}
}