{
  "type": "Feature",
  "properties": {
    "addr:full":"M. Sevketpasa Mh. Sahinkaya Sk. No:9 Okmeydani Istanbul 43050",
    "addr:postcode":"43050",
    "addr:street":"Mh. Sahinkaya Sk. No 9 Okmeydani",
    "iso:country":"TR",
    "sg:address":"M. Sevketpasa Mh. Sahinkaya Sk. No:9",
    "sg:city":"Okmeydani",
    "sg:classifiers":[
        {
            "category":"Shopping",
            "subcategory":"Florist",
            "type":"Retail Goods"
        }
    ],
    "sg:phone":"+90 212 256 7339",
    "sg:postcode":"43050",
    "sg:province":"Istanbul",
    "sg:tags":[
        "flower"
    ],
    "wof:name":"Flora Center ?i?ek Merk. Ltd. Sti.",
    "wof:placetype":"venue"
},
  "geometry": {"coordinates":[28.9662876129,41.0555114746],"type":"Point"}
}