{
  "type": "Feature",
  "properties": {
    "addr:full":"Karaca Sk.no:19 G.o.p. Goztepe Ankara 01220",
    "addr:housenumber":"19",
    "addr:postcode":"01220",
    "addr:street":"G.O.P. Goztepe",
    "iso:country":"TR",
    "sg:address":"Karaca Sk.no:19 G.o.p.",
    "sg:city":"Goztepe",
    "sg:classifiers":[
        {
            "category":"Government",
            "subcategory":"Embassy",
            "type":"Public Place"
        }
    ],
    "sg:phone":"+90 312 441 1364",
    "sg:postcode":"01220",
    "sg:province":"Ankara",
    "sg:tags":[
        "foreign"
    ],
    "wof:name":"Katar Devleti B?y?kel?iligi",
    "wof:placetype":"venue"
},
  "geometry": {"coordinates":[32.8725357056,39.8881072998],"type":"Point"}
}