{
  "type": "Feature",
  "properties": {
    "addr:full":"Mithatpasa C. No.199 Bal?va Izmir",
    "addr:housenumber":"?",
    "addr:street":"C.;Bal",
    "iso:country":"TR",
    "sg:address":"Mithatpasa C. No.199",
    "sg:city":"Bal?va",
    "sg:classifiers":[
        {
            "category":"Food & Beverages",
            "subcategory":"Meat & Fish",
            "type":"Retail Goods"
        }
    ],
    "sg:phone":"+90 232 277 0212",
    "sg:province":"Izmir",
    "sg:tags":[
        "seafood"
    ],
    "wof:name":"Yigit Su Urnl. A.s.",
    "wof:placetype":"venue"
},
  "geometry": {"coordinates":[27.1082668304,38.4055633545],"type":"Point"}
}