{
  "type": "Feature",
  "properties": {
    "iso:country":"TR",
    "sg:address":"4. Sk. No:23 Ostim",
    "sg:city":"\u00dcmraniye",
    "sg:classifiers":[
        {
            "category":"Manufacturing",
            "subcategory":"Rubber & Plastics",
            "type":"Manufacturing & Wholesale Goods"
        }
    ],
    "sg:phone":"+90 312 354 0146",
    "sg:province":"Ankara",
    "sg:tags":[
        "industry"
    ],
    "wof:name":"G?ral Yapi End?strisi San. Tic. Ltd. Sti.",
    "wof:placetype":"venue"
},
  "geometry": {"coordinates":[32.7474136353,39.9668121338],"type":"Point"}
}