{
  "type": "Feature",
  "properties": {
    "iso:country":"TR",
    "sg:address":"Hosnudiye Mah. Hacet Sk. No:2/a",
    "sg:city":"Merter",
    "sg:orig_category":"Orthopedical Materials",
    "sg:phone":"+90 222 231 4481",
    "sg:postcode":"34010",
    "sg:province":"Eskisehir",
    "wof:name":"Capa Sag. Hizmet.",
    "wof:placetype":"venue"
},
  "geometry": {"coordinates":[30.5160694122,39.7782249451],"type":"Point"}
}