{
  "type": "Feature",
  "properties": {
    "iso:country":"TR",
    "sg:address":"Davutpasa Cad.litros Yolu Cevre Han No: 7/17 Maltepe-",
    "sg:city":"Topkapi",
    "sg:classifiers":[
        {
            "category":"Food & Beverages",
            "subcategory":"Groceries & Convenience Stores",
            "type":"Retail Goods"
        }
    ],
    "sg:phone":"+90 212 544 8787",
    "sg:postcode":"24620",
    "sg:province":"Istanbul",
    "sg:tags":[
        "ready"
    ],
    "wof:name":"Marmara Makina",
    "wof:placetype":"venue"
},
  "geometry": {"coordinates":[28.9759254456,41.0123786926],"type":"Point"}
}