{
  "type": "Feature",
  "properties": {
    "addr:full":"Hamit Kaplan Sok.no: 3/3 R?garli Ankara",
    "addr:housenumber":"3 / 3 r ?",
    "addr:street":"Sok.No",
    "iso:country":"TR",
    "sg:address":"Hamit Kaplan Sok.no: 3/3",
    "sg:city":"R?garli",
    "sg:classifiers":[
        {
            "category":"Manufacturing",
            "subcategory":"Building Materials",
            "type":"Manufacturing & Wholesale Goods"
        }
    ],
    "sg:phone":"+90 312 310 2224",
    "sg:province":"Ankara",
    "sg:tags":[
        "lifts-elevators"
    ],
    "wof:name":"Cihan Ticaret",
    "wof:placetype":"venue"
},
  "geometry": {"coordinates":[32.4879341125,37.8932876587],"type":"Point"}
}