{
  "type": "Feature",
  "properties": {
    "iso:country":"TR",
    "sg:address":"Org San Bolg 5.cad.no:16",
    "sg:city":"Merter",
    "sg:classifiers":[
        {
            "category":"Shopping",
            "subcategory":"Crafts & Fabrics",
            "type":"Retail Goods"
        }
    ],
    "sg:phone":"+90 352 321 1779",
    "sg:province":"Kayseri",
    "sg:tags":[
        "knitting"
    ],
    "wof:name":"Irem Tekstil San.tic.ltd.sti",
    "wof:placetype":"venue"
},
  "geometry": {"coordinates":[35.4891357422,38.7225761414],"type":"Point"}
}