{
  "type": "Feature",
  "properties": {
    "iso:country":"TR",
    "sg:address":"Cumhuriyet Caddesi No:243 K:2 Harbiye",
    "sg:city":"Sisli",
    "sg:classifiers":[
        {
            "category":"Travel",
            "subcategory":"Travel Agent",
            "type":"Entertainment"
        }
    ],
    "sg:phone":"+90 2414065",
    "sg:postcode":"65710",
    "sg:province":"Istanbul",
    "sg:tags":[
        "agency",
        "tourism"
    ],
    "wof:name":"Duru International Turizm",
    "wof:placetype":"venue"
},
  "geometry": {"coordinates":[28.9861831665,41.0408554077],"type":"Point"}
}