{
  "type": "Feature",
  "properties": {
    "iso:country":"TR",
    "sg:address":"Aliemiri 1. Sk. Semker Apt. D:1 Yenisehir",
    "sg:city":"Erenk?",
    "sg:classifiers":[
        {
            "category":"Organizations",
            "subcategory":"Professional Association",
            "type":"Services"
        }
    ],
    "sg:phone":"+90 412 221 0312",
    "sg:province":"Diyarbakir",
    "wof:name":"Diyarbakir Esnaf Ve Sanatkar. Odalari Birl.",
    "wof:placetype":"venue"
},
  "geometry": {"coordinates":[40.2302932739,37.9175834656],"type":"Point"}
}