{
  "type": "Feature",
  "properties": {
    "addr:full":"Urunlu Mha. Uludag Univ. Ust Gecidi Yani Eczaneler Arkasi No:19 Kartal Bursa 34880",
    "addr:postcode":"34880",
    "addr:street":"Gecidi;No 19 Kartal",
    "iso:country":"TR",
    "sg:address":"Urunlu Mha. Uludag Univ. Ust Gecidi Yani Eczaneler Arkasi No:19",
    "sg:city":"Kartal",
    "sg:classifiers":[
        {
            "category":"Manufacturing",
            "subcategory":"Metals",
            "type":"Manufacturing & Wholesale Goods"
        }
    ],
    "sg:phone":"+90 224 442 8378",
    "sg:postcode":"34880",
    "sg:province":"Bursa",
    "sg:tags":[
        "iron-steel",
        "peoducts"
    ],
    "wof:name":"Metapres A.s.",
    "wof:placetype":"venue"
},
  "geometry": {"coordinates":[29.0580043793,40.1947555542],"type":"Point"}
}