{
  "type": "Feature",
  "properties": {
    "iso:country":"TR",
    "sg:address":"K. Karabekir Cd. No:112/8 Ulus",
    "sg:city":"B.?ekmece",
    "sg:classifiers":[
        {
            "category":"Farming",
            "subcategory":"Fish & Marine Products",
            "type":"Manufacturing & Wholesale Goods"
        }
    ],
    "sg:phone":"+90 312 309 3079",
    "sg:province":"Ankara",
    "sg:tags":[
        "automotive"
    ],
    "wof:name":"G?ktaslar Otomotiv A.s.",
    "wof:placetype":"venue"
},
  "geometry": {"coordinates":[29.1020469666,40.1980743408],"type":"Point"}
}