{
  "type": "Feature",
  "properties": {
    "addr:full":"Eski Edirne Asfalti No:324 500 Evler G.o.pasa ?nye Istanbul 52300",
    "addr:housenumber":"500",
    "addr:postcode":"52300",
    "addr:street":"Eski;No 324;Nye",
    "iso:country":"TR",
    "sg:address":"Eski Edirne Asfalti No:324 500 Evler G.o.pasa",
    "sg:city":"?nye",
    "sg:classifiers":[
        {
            "category":"Farming",
            "subcategory":"Fish & Marine Products",
            "type":"Manufacturing & Wholesale Goods"
        }
    ],
    "sg:phone":"+90 212 649 3738",
    "sg:postcode":"52300",
    "sg:province":"Istanbul",
    "sg:tags":[
        "automotive"
    ],
    "wof:name":"Furkan Otomotiv",
    "wof:placetype":"venue"
},
  "geometry": {"coordinates":[28.8973484039,41.0688934326],"type":"Point"}
}