{
  "type": "Feature",
  "properties": {
    "iso:country":"TR",
    "sg:address":"Esat Cad . No:73",
    "sg:city":"K.esat",
    "sg:classifiers":[
        {
            "category":"Farming",
            "subcategory":"Farm & Veterinary Services",
            "type":"Manufacturing & Wholesale Goods"
        }
    ],
    "sg:phone":"+90 312 417 7543",
    "sg:province":"Ankara",
    "sg:tags":[
        "veterinarian"
    ],
    "wof:name":"Alper Ayhan",
    "wof:placetype":"venue"
},
  "geometry": {"coordinates":[32.8931312561,39.9691390991],"type":"Point"}
}