{
  "type": "Feature",
  "properties": {
    "iso:country":"TR",
    "sg:address":"Tahtakale Cad. Pacaci Sok. No:16",
    "sg:city":"Tahtakale",
    "sg:classifiers":[
        {
            "category":"Home & Garden",
            "subcategory":"Hardware",
            "type":"Retail Goods"
        }
    ],
    "sg:phone":"+90 212 527 1657",
    "sg:postcode":"16040",
    "sg:province":"Istanbul",
    "sg:tags":[
        "store"
    ],
    "wof:name":"Unver Hirdavat San. Paz. Tic.ltd.sti.",
    "wof:placetype":"venue"
},
  "geometry": {"coordinates":[28.9861831665,41.0408554077],"type":"Point"}
}