{
  "type": "Feature",
  "properties": {
    "addr:full":"Metal Isleri San.sitesi 2.cad.no:22 Kisikk? Seyhan Izmir 01120",
    "addr:housenumber":"22;?",
    "addr:postcode":"01120",
    "addr:street":"Kisikk",
    "iso:country":"TR",
    "sg:address":"Metal Isleri San.sitesi 2.cad.no:22 Kisikk?",
    "sg:city":"Seyhan",
    "sg:classifiers":[
        {
            "category":"Manufacturing",
            "subcategory":"Metals",
            "type":"Manufacturing & Wholesale Goods"
        }
    ],
    "sg:phone":"+90 232 257 5259",
    "sg:postcode":"01120",
    "sg:province":"Izmir",
    "sg:tags":[
        "industry"
    ],
    "wof:name":"Orkut San Profil Demir Ve Insaat San.tic.ltd.sti.",
    "wof:placetype":"venue"
},
  "geometry": {"coordinates":[27.1296863556,38.4186973572],"type":"Point"}
}