{
  "type": "Feature",
  "properties": {
    "iso:country":"TR",
    "sg:address":"Hasfirin Cd. Sinanpasa Shopping Center Besiktas",
    "sg:city":"Okmeydani",
    "sg:classifiers":[
        {
            "category":"Sports & Exercise",
            "subcategory":"Tennis Court",
            "type":"Entertainment"
        }
    ],
    "sg:phone":"+90 212 260 1779",
    "sg:postcode":"80270",
    "sg:province":"Istanbul",
    "sg:tags":[
        "equipment",
        "material"
    ],
    "wof:name":"Tuba Spor Tekstil San. Tic. Ltd. Sti.",
    "wof:placetype":"venue"
},
  "geometry": {"coordinates":[28.975925,41.012379],"type":"Point"}
}