{
  "type": "Feature",
  "properties": {
    "addr:full":"3.emintas San.sit. No:1/78 Top?lar Ey\u00fcp Istanbul 34055",
    "addr:housenumber":"78;?",
    "addr:postcode":"34055",
    "addr:street":"No 1 /;Lar Eyuep",
    "iso:country":"TR",
    "sg:address":"3.emintas San.sit. No:1/78 Top?lar",
    "sg:city":"Ey\u00fcp",
    "sg:classifiers":[
        {
            "category":"Manufacturing",
            "subcategory":"Metals",
            "type":"Manufacturing & Wholesale Goods"
        }
    ],
    "sg:phone":"+90 212 501 5560",
    "sg:postcode":"34055",
    "sg:province":"Istanbul",
    "sg:tags":[
        "processing"
    ],
    "wof:name":"Elar Elektronik Mak.san.tic.ltd.sti",
    "wof:placetype":"venue"
},
  "geometry": {"coordinates":[28.9230213165,41.0406188965],"type":"Point"}
}