{
  "type": "Feature",
  "properties": {
    "addr:full":"K.hane Cad. Kanarya Sok. No:11/a Caglayan-kagithane Mersin Istanbul 52750",
    "addr:housenumber":"no 11 / a",
    "addr:postcode":"52750",
    "addr:street":"K.Hane Cad. Kanarya Sok.;Caglayan-Kagithane",
    "iso:country":"TR",
    "sg:address":"K.hane Cad. Kanarya Sok. No:11/a Caglayan-kagithane",
    "sg:city":"Mersin",
    "sg:classifiers":[
        {
            "category":"Wholesale",
            "subcategory":"Home Furnishings",
            "type":"Manufacturing & Wholesale Goods"
        }
    ],
    "sg:phone":"+90 212 231 0914",
    "sg:postcode":"52750",
    "sg:province":"Istanbul",
    "sg:tags":[
        "furniture"
    ],
    "wof:name":"Cetin Mobilya Ve Dekorasyon San.tic.ltd.sti.",
    "wof:placetype":"venue"
},
  "geometry": {"coordinates":[28.9861831665,41.0408554077],"type":"Point"}
}