{
  "type": "Feature",
  "properties": {
    "iso:country":"TR",
    "sg:address":"Bahcelievler Cad Otel Sk No 50 Turgutreis",
    "sg:city":"Bodrum",
    "sg:classifiers":[
        {
            "category":"Social Services",
            "subcategory":"Retirement Home",
            "type":"Services"
        }
    ],
    "sg:phone":"+90 252 382 7880",
    "sg:postcode":"80200",
    "sg:province":"Mugla",
    "sg:tags":[
        "holiday",
        "village"
    ],
    "wof:name":"Mar Hotel",
    "wof:placetype":"venue"
},
  "geometry": {"coordinates":[28.3628406525,37.215675354],"type":"Point"}
}