{
  "type": "Feature",
  "properties": {
    "addr:full":"In??cad. Hatuncuk Camii Sk. No:14/1-2 Merkez Trabzon 61040",
    "addr:housenumber":"14 / 1-2",
    "addr:postcode":"61040",
    "addr:street":"In ? ? Cad.;Sk. No",
    "iso:country":"TR",
    "sg:address":"In??cad. Hatuncuk Camii Sk. No:14/1-2",
    "sg:city":"Merkez",
    "sg:classifiers":[
        {
            "category":"Shopping",
            "subcategory":"Gifts & Souvenirs",
            "type":"Retail Goods"
        }
    ],
    "sg:phone":"+90 2293407",
    "sg:postcode":"61040",
    "sg:province":"Trabzon",
    "wof:name":"Siyah Beyaz Grafik Sanatlar",
    "wof:placetype":"venue"
},
  "geometry": {"coordinates":[39.682308197,40.9971046448],"type":"Point"}
}