{
  "type": "Feature",
  "properties": {
    "addr:full":"Yenicarsi Cad. 33 Ferah Apt. 80060 Galatasaray Maltepe Istanbul 01000",
    "addr:housenumber":"33",
    "addr:postcode":"80060;01000",
    "addr:street":"Yenicarsi Cad.",
    "iso:country":"TR",
    "sg:address":"Yenicarsi Cad. 33 Ferah Apt. 80060 Galatasaray",
    "sg:city":"Maltepe",
    "sg:classifiers":[
        {
            "category":"Wholesale",
            "subcategory":"Books, Periodicals, & Newspapers",
            "type":"Manufacturing & Wholesale Goods"
        }
    ],
    "sg:phone":"+90 212 252 6375",
    "sg:postcode":"01000",
    "sg:province":"Istanbul",
    "sg:tags":[
        "house",
        "publishing"
    ],
    "wof:name":"Mavibulut Yayinlari",
    "wof:placetype":"venue"
},
  "geometry": {"coordinates":[28.9759254456,41.0123786926],"type":"Point"}
}