{
  "type": "Feature",
  "properties": {
    "addr:full":"Ataturk Oto Sanayi Nazmi Akbaci Tic.merkezi No:161 Maslak Senirkent Istanbul 32600",
    "addr:postcode":"32600",
    "addr:street":"No;Maslak",
    "iso:country":"TR",
    "sg:address":"Ataturk Oto Sanayi Nazmi Akbaci Tic.merkezi No:161 Maslak",
    "sg:city":"Senirkent",
    "sg:classifiers":[
        {
            "category":"Wholesale",
            "subcategory":"Auto Parts",
            "type":"Manufacturing & Wholesale Goods"
        }
    ],
    "sg:phone":"+90 212 285 9546",
    "sg:postcode":"32600",
    "sg:province":"Istanbul",
    "sg:tags":[
        "spare"
    ],
    "wof:name":"Akden Turbo Ltd.sti.",
    "wof:placetype":"venue"
},
  "geometry": {"coordinates":[28.9861831665,41.0408554077],"type":"Point"}
}