{
  "type": "Feature",
  "properties": {
    "iso:country":"TR",
    "sg:address":"Ak?aga?sk. No.11",
    "sg:city":"Merter",
    "sg:classifiers":[
        {
            "category":"Shopping",
            "subcategory":"Clothing, Apparel, & Fashions",
            "type":"Retail Goods"
        }
    ],
    "sg:phone":"+90 212 637 2660",
    "sg:province":"Istanbul",
    "sg:tags":[
        "ready",
        "wear"
    ],
    "wof:name":"Interline Tekstil A.s.",
    "wof:placetype":"venue"
},
  "geometry": {"coordinates":[32.4871749878,37.8804130554],"type":"Point"}
}