{
  "type": "Feature",
  "properties": {
    "iso:country":"TR",
    "sg:address":"Halep Cad. Kavaklibag 1.sok. No:2/8",
    "sg:city":"Cankaya",
    "sg:classifiers":[
        {
            "category":"Professional",
            "subcategory":"Engineering",
            "type":"Services"
        }
    ],
    "sg:phone":"+90 422 325 0032",
    "sg:postcode":"07080",
    "sg:province":"Malatya",
    "sg:tags":[
        "architect"
    ],
    "wof:name":"Buray Muh.mim. Tic. San. Ltd. Sti.",
    "wof:placetype":"venue"
},
  "geometry": {"coordinates":[38.3195266724,38.3488922119],"type":"Point"}
}