{
  "type": "Feature",
  "properties": {
    "addr:full":"Necatibey Cad.no:91 Karakoy Merter Istanbul",
    "addr:housenumber":"91",
    "iso:country":"TR",
    "sg:address":"Necatibey Cad.no:91 Karakoy",
    "sg:city":"Merter",
    "sg:classifiers":[
        {
            "category":"Wholesale",
            "subcategory":"Auto Parts",
            "type":"Manufacturing & Wholesale Goods"
        }
    ],
    "sg:phone":"+90 212 292 5473",
    "sg:province":"Istanbul",
    "sg:tags":[
        "spare"
    ],
    "wof:name":"Teknik -motor Ltd.",
    "wof:placetype":"venue"
},
  "geometry": {"coordinates":[28.9790115356,41.0256652832],"type":"Point"}
}