{
  "type": "Feature",
  "properties": {
    "addr:full":"Yuzyil Massit 5.cad. 10/b Bagcilar Besiktas Istanbul 80200",
    "addr:housenumber":"10 / b",
    "addr:postcode":"80200",
    "addr:street":"Bagcilar Besiktas",
    "iso:country":"TR",
    "sg:address":"Yuzyil Massit 5.cad. 10/b Bagcilar",
    "sg:city":"Besiktas",
    "sg:classifiers":[
        {
            "category":"Communications",
            "subcategory":"Film & Video Production",
            "type":"Services"
        }
    ],
    "sg:phone":"+90 212 629 2321",
    "sg:postcode":"80200",
    "sg:province":"Istanbul",
    "sg:tags":[
        "-"
    ],
    "wof:name":"Fast Production Uluslararasi Tv Film Ve Reklamcilik Ltd.sti.",
    "wof:placetype":"venue"
},
  "geometry": {"coordinates":[28.9759254456,41.0123786926],"type":"Point"}
}