{
  "type": "Feature",
  "properties": {
    "iso:country":"TR",
    "sg:address":"Ankara Asf. Menzil ?ayi Mevki",
    "sg:city":"K?ek?",
    "sg:classifiers":[
        {
            "category":"Manufacturing",
            "subcategory":"Food",
            "type":"Manufacturing & Wholesale Goods"
        }
    ],
    "sg:phone":"+90 262 364 7401",
    "sg:province":"Kocaeli",
    "sg:tags":[
        "wholesaler"
    ],
    "wof:name":"Pinat Gida San. As.",
    "wof:placetype":"venue"
},
  "geometry": {"coordinates":[29.881521225,40.8532714844],"type":"Point"}
}