{
  "type": "Feature",
  "properties": {
    "addr:full":"Nuhkuyusu Cd. No:52 Usk?ar Istanbul",
    "addr:housenumber":"no 52",
    "addr:postcode":"?",
    "addr:street":"Nuhkuyusu Cd.",
    "iso:country":"TR",
    "sg:address":"Nuhkuyusu Cd. No:52",
    "sg:city":"Usk?ar",
    "sg:classifiers":[
        {
            "category":"Government",
            "subcategory":"Fire Station",
            "type":"Public Place"
        }
    ],
    "sg:phone":"+90 216 333 0873",
    "sg:province":"Istanbul",
    "sg:tags":[
        "decoration"
    ],
    "wof:name":"Yunuslar Ins.",
    "wof:placetype":"venue"
},
  "geometry": {"coordinates":[29.0322036743,41.0181694031],"type":"Point"}
}