{
  "type": "Feature",
  "properties": {
    "addr:full":"Senyurt Sit. Kat:2 No:212 Sivas Osmangazi Sivas 16050",
    "addr:housenumber":"kat 2 no 212",
    "addr:postcode":"16050",
    "iso:country":"TR",
    "sg:address":"Senyurt Sit. Kat:2 No:212 Sivas",
    "sg:city":"Osmangazi",
    "sg:classifiers":[
        {
            "category":"Wholesale",
            "subcategory":"Medical Equipment & Supplies",
            "type":"Manufacturing & Wholesale Goods"
        }
    ],
    "sg:phone":"+90 346 225 6680",
    "sg:postcode":"16050",
    "sg:province":"Sivas",
    "wof:name":"Gelisim Medikal Teknik",
    "wof:placetype":"venue"
},
  "geometry": {"coordinates":[37.0182571411,39.750087738],"type":"Point"}
}