{
  "type": "Feature",
  "properties": {
    "iso:country":"TR",
    "sg:address":"Atat?k Bulvari No:154/1 Bakanliklar",
    "sg:city":"Bayrampasa",
    "sg:classifiers":[
        {
            "category":"Communications",
            "subcategory":"Film & Video Production",
            "type":"Services"
        }
    ],
    "sg:phone":"+90 312 468 0701",
    "sg:postcode":"36100",
    "sg:province":"Ankara",
    "sg:tags":[
        "-"
    ],
    "wof:name":"Ulusal Uydu Radio Tv Yapim A.s.",
    "wof:placetype":"venue"
},
  "geometry": {"coordinates":[32.8560333252,39.9438743591],"type":"Point"}
}