{
  "type": "Feature",
  "properties": {
    "addr:full":"Rauf Orbay Cad.no:19/1 Tuzla Istanbul 01900",
    "addr:housenumber":"19 / 1",
    "addr:postcode":"01900",
    "addr:street":"Cad.No;Istanbul",
    "iso:country":"TR",
    "sg:address":"Rauf Orbay Cad.no:19/1",
    "sg:city":"Tuzla",
    "sg:classifiers":[
        {
            "category":"Marine",
            "type":"Transportation"
        }
    ],
    "sg:phone":"+90 216 395 9728",
    "sg:postcode":"01900",
    "sg:province":"Istanbul",
    "sg:tags":[
        "equipment",
        "maritime"
    ],
    "wof:name":"Betesan M?h.gemi Elk.ins.i? Dis.tic.ltd",
    "wof:placetype":"venue"
},
  "geometry": {"coordinates":[28.9861831665,41.0408554077],"type":"Point"}
}