{
  "type": "Feature",
  "properties": {
    "iso:country":"TR",
    "sg:address":"Nuripasa M. 55 S. No: 9 Zeytinburnu",
    "sg:city":"Y.dudullu",
    "sg:classifiers":[
        {
            "category":"Home & Garden",
            "subcategory":"Building Materials",
            "type":"Retail Goods"
        }
    ],
    "sg:phone":"+90 212 547 8484",
    "sg:postcode":"81260",
    "sg:province":"Istanbul",
    "sg:tags":[
        "window",
        "door",
        "plastic"
    ],
    "wof:name":"Al-pa Alimunyum Pancur San. Tic. Ltd. Sti.",
    "wof:placetype":"venue"
},
  "geometry": {"coordinates":[28.9030838013,40.9898223877],"type":"Point"}
}