{
  "type": "Feature",
  "properties": {
    "iso:country":"TR",
    "sg:address":"Yeni Golcuk Yolu Uzeri Aksa Aku Yani",
    "sg:city":"\u00dcmraniye",
    "sg:classifiers":[
        {
            "category":"Utilities",
            "subcategory":"Fuel Oil & Lpg",
            "type":"Services"
        }
    ],
    "sg:phone":"+90 262 349 4856",
    "sg:province":"Kocaeli",
    "sg:tags":[
        "gas",
        "system"
    ],
    "wof:name":"Korfez Oto Gaz",
    "wof:placetype":"venue"
},
  "geometry": {"coordinates":[29.881521225,40.8532714844],"type":"Point"}
}