{
  "type": "Feature",
  "properties": {
    "addr:full":"Esenler Yolu No:28/7 Maltepe Mersin Istanbul 52750",
    "addr:housenumber":"no 28 / 7",
    "addr:postcode":"52750",
    "addr:street":"Esenler Yolu",
    "iso:country":"TR",
    "sg:address":"Esenler Yolu No:28/7 Maltepe",
    "sg:city":"Mersin",
    "sg:classifiers":[
        {
            "category":"Manufacturing",
            "subcategory":"Metals",
            "type":"Manufacturing & Wholesale Goods"
        }
    ],
    "sg:phone":"+90 212 576 6766",
    "sg:postcode":"52750",
    "sg:province":"Istanbul",
    "sg:tags":[
        "iron-steel",
        "peoducts"
    ],
    "wof:name":"Esen Demir ?elik San. Tic. Ltd. Sti.",
    "wof:placetype":"venue"
},
  "geometry": {"coordinates":[28.9106407166,41.031578064],"type":"Point"}
}