{
  "type": "Feature",
  "properties": {
    "iso:country":"TR",
    "sg:address":"1585 Sokak No:1 Mersinli",
    "sg:city":"Mersin",
    "sg:classifiers":[
        {
            "category":"Manufacturing",
            "subcategory":"Tools & Machinery",
            "type":"Manufacturing & Wholesale Goods"
        }
    ],
    "sg:phone":"+90 232 486 8576",
    "sg:postcode":"52750",
    "sg:province":"Izmir",
    "sg:tags":[
        "machine",
        "industry"
    ],
    "wof:name":"Kaan Makina San. Ve Tic. Erdal D?r?st",
    "wof:placetype":"venue"
},
  "geometry": {"coordinates":[27.1794300079,38.4408493042],"type":"Point"}
}