{
  "type": "Feature",
  "properties": {
    "addr:full":"Selanik Cd. Yesim Apt. No:19 D:1 Kizilay Ortak? Ankara 80840",
    "addr:housenumber":"19 d 1",
    "addr:postcode":"80840",
    "addr:street":"Selanik Cd. Yesim Apt. No;Ortak;Ankara",
    "iso:country":"TR",
    "sg:address":"Selanik Cd. Yesim Apt. No:19 D:1 Kizilay",
    "sg:city":"Ortak?",
    "sg:classifiers":[
        {
            "category":"Organizations",
            "subcategory":"Professional Association",
            "type":"Services"
        }
    ],
    "sg:phone":"+90 312 418 4712",
    "sg:postcode":"80840",
    "sg:province":"Ankara",
    "wof:name":"Tmmob Cevre Muhendis. Odasi",
    "wof:placetype":"venue"
},
  "geometry": {"coordinates":[32.8560333252,39.9438743591],"type":"Point"}
}