{
  "type": "Feature",
  "properties": {
    "addr:full":"Topkapi Cd. No:27 Topkapi Mecidiyek\u00f6y Istanbul 34387",
    "addr:housenumber":"no 27",
    "addr:postcode":"34387",
    "addr:street":"Cd.;Topkapi Mecidiyekoey",
    "iso:country":"TR",
    "sg:address":"Topkapi Cd. No:27 Topkapi",
    "sg:city":"Mecidiyek\u00f6y",
    "sg:classifiers":[
        {
            "category":"Organizations",
            "subcategory":"Membership Organization",
            "type":"Services"
        }
    ],
    "sg:phone":"+90 212 523 6232",
    "sg:postcode":"34387",
    "sg:province":"Istanbul",
    "wof:name":"Topkapi Fukaraperver Cem.",
    "wof:placetype":"venue"
},
  "geometry": {"coordinates":[28.9861831665,41.0408554077],"type":"Point"}
}