{
  "type": "Feature",
  "properties": {
    "iso:country":"TR",
    "sg:address":"Yeni Tabakhane 76 Nolu Sok. No:6",
    "sg:city":"Sehitkamil",
    "sg:classifiers":[
        {
            "category":"Shopping",
            "subcategory":"Clothing, Apparel, & Fashions",
            "type":"Retail Goods"
        }
    ],
    "sg:phone":"+90 342 225 3136",
    "sg:postcode":"27000",
    "sg:province":"Gaziantep",
    "sg:tags":[
        "bag-belt-accessories"
    ],
    "wof:name":"?ag Deri",
    "wof:placetype":"venue"
},
  "geometry": {"coordinates":[37.131859,36.717205],"type":"Point"}
}