{
  "type": "Feature",
  "properties": {
    "addr:full":"Sultanciftligi 2.cebeci Yolu 2573.sok. No:29 Gaziosmanpasa Istanbul 01950",
    "addr:housenumber":"2573.sok no 29",
    "addr:postcode":"01950",
    "addr:street":"2.Cebeci Yolu;Istanbul",
    "iso:country":"TR",
    "sg:address":"Sultanciftligi 2.cebeci Yolu 2573.sok. No:29",
    "sg:city":"Gaziosmanpasa",
    "sg:classifiers":[
        {
            "category":"Home & Garden",
            "subcategory":"Hardware",
            "type":"Retail Goods"
        }
    ],
    "sg:phone":"+90 212 619 4980",
    "sg:postcode":"01950",
    "sg:province":"Istanbul",
    "sg:tags":[
        "store"
    ],
    "wof:name":"Yilmaz Bronz",
    "wof:placetype":"venue"
},
  "geometry": {"coordinates":[28.9861831665,41.0408554077],"type":"Point"}
}