{
  "type": "Feature",
  "properties": {
    "addr:full":"Davutpasa Cad. 34, Topkapi, 34020 Istanbul Levent Istanbul 01310",
    "addr:housenumber":"34",
    "addr:postcode":"34020;01310",
    "addr:street":"Davutpasa Cad.",
    "iso:country":"TR",
    "sg:address":"Davutpasa Cad. 34, Topkapi, 34020 Istanbul",
    "sg:city":"Levent",
    "sg:classifiers":[
        {
            "category":"Banks & Credit Unions",
            "subcategory":"Bank",
            "type":"Services"
        }
    ],
    "sg:phone":"+90 212 233 0180",
    "sg:postcode":"01310",
    "sg:province":"Istanbul",
    "wof:name":"Cukurova Ithalat Ve Ihracat Tas",
    "wof:placetype":"venue"
},
  "geometry": {"coordinates":[28.91049,41.014313],"type":"Point"}
}