{
  "type": "Feature",
  "properties": {
    "iso:country":"TR",
    "sg:address":"Yesillik Cadde No:459/f",
    "sg:city":"Karabaglar",
    "sg:classifiers":[
        {
            "category":"Wholesale",
            "subcategory":"Machinery & Supplies",
            "type":"Manufacturing & Wholesale Goods"
        }
    ],
    "sg:phone":"+90 232 237 5259",
    "sg:postcode":"44210",
    "sg:province":"Izmir",
    "sg:tags":[
        "agricultural"
    ],
    "wof:name":"Makteks Makina Limited Sirketi",
    "wof:placetype":"venue"
},
  "geometry": {"coordinates":[27.1346626282,38.3827552795],"type":"Point"}
}