{
  "type": "Feature",
  "properties": {
    "iso:country":"TR",
    "sg:address":"K.sanayi Sitesi 25.blok No:21",
    "sg:city":"Kartal",
    "sg:classifiers":[
        {
            "category":"Farming",
            "subcategory":"Fish & Marine Products",
            "type":"Manufacturing & Wholesale Goods"
        }
    ],
    "sg:phone":"+90 224 441 1092",
    "sg:postcode":"46000",
    "sg:province":"Bursa",
    "sg:tags":[
        "automotive"
    ],
    "wof:name":"Seha Otomotiv",
    "wof:placetype":"venue"
},
  "geometry": {"coordinates":[29.0580043793,40.1947555542],"type":"Point"}
}