{
  "type": "Feature",
  "properties": {
    "addr:full":"Turan Gunes Bulvari 4.cad. No:69 Yildis-cankaya Kad\u0131k\u00f6y Ankara 81010",
    "addr:housenumber":"4.cad no 69",
    "addr:postcode":"81010",
    "addr:street":"Gunes Bulvari",
    "iso:country":"TR",
    "sg:address":"Turan Gunes Bulvari 4.cad. No:69 Yildis-cankaya",
    "sg:city":"Kad\u0131k\u00f6y",
    "sg:orig_category":"Aluminium Carpentary",
    "sg:phone":"+90 312 441 7042",
    "sg:postcode":"81010",
    "sg:province":"Ankara",
    "wof:name":"Pimeks Group",
    "wof:placetype":"venue"
},
  "geometry": {"coordinates":[32.8560333252,39.9438743591],"type":"Point"}
}