{
  "type": "Feature",
  "properties": {
    "iso:country":"TR",
    "sg:address":"Hizirbey Cad.no:73/a Fikirtepe Kadikoy",
    "sg:city":"Okmeydani",
    "sg:classifiers":[
        {
            "category":"Professional",
            "subcategory":"Detective & Security Services",
            "type":"Services"
        }
    ],
    "sg:phone":"+90 216 449 4836",
    "sg:postcode":"43050",
    "sg:province":"Istanbul",
    "sg:tags":[
        "material"
    ],
    "wof:name":"Ayibil Elektronik Sanayi Ve Tic.ltd.sti.",
    "wof:placetype":"venue"
},
  "geometry": {"coordinates":[29.049021,40.99213],"type":"Point"}
}