{
  "type": "Feature",
  "properties": {
    "addr:full":"Ragip Gumuspala Cad.ahenk Han No: 43/24 Eminonu \u00dcsk\u00fcdar Istanbul 34672",
    "addr:housenumber":"24",
    "addr:postcode":"34672",
    "addr:street":"Eminonu U\u0308Skuedar",
    "iso:country":"TR",
    "sg:address":"Ragip Gumuspala Cad.ahenk Han No: 43/24 Eminonu",
    "sg:city":"\u00dcsk\u00fcdar",
    "sg:classifiers":[
        {
            "category":"Manufacturing",
            "subcategory":"Building Materials",
            "type":"Manufacturing & Wholesale Goods"
        }
    ],
    "sg:phone":"+90 212 522 1856",
    "sg:postcode":"34672",
    "sg:province":"Istanbul",
    "sg:tags":[
        "promotional"
    ],
    "wof:name":"Abdurrakman Kaleli Ogullari Tic.koll.sti.",
    "wof:placetype":"venue"
},
  "geometry": {"coordinates":[29.0154418945,41.0218315125],"type":"Point"}
}