{
  "type": "Feature",
  "properties": {
    "addr:full":"Abdi Ipek? Cad.?zel Idare Is Merkezi K:2 No:201 Bayrampasa Seyhan Istanbul 01000",
    "addr:housenumber":"abdi;?;?",
    "addr:postcode":"201;01000",
    "addr:street":"Ipek;Cad.;K 2 No",
    "iso:country":"TR",
    "sg:address":"Abdi Ipek? Cad.?zel Idare Is Merkezi K:2 No:201 Bayrampasa",
    "sg:city":"Seyhan",
    "sg:classifiers":[
        {
            "category":"Shopping",
            "subcategory":"Pharmacy",
            "type":"Retail Goods"
        }
    ],
    "sg:phone":"+90 212 544 5920",
    "sg:postcode":"01000",
    "sg:province":"Istanbul",
    "sg:tags":[
        "store",
        "drug"
    ],
    "wof:name":"Aroma Ila? San. Ltd. Sti.",
    "wof:placetype":"venue"
},
  "geometry": {"coordinates":[28.9861831665,41.0408554077],"type":"Point"}
}