{
  "type": "Feature",
  "properties": {
    "iso:country":"TR",
    "sg:address":"Ikitelli Organize Sanayi B?gesi Ipkas Sanayi Sitesi 6 B Blok No:37-40",
    "sg:city":"Ikitelli/K\u00fc\u00e7\u00fck\u00e7ekmece",
    "sg:classifiers":[
        {
            "category":"Home & Garden",
            "subcategory":"Hardware",
            "type":"Retail Goods"
        }
    ],
    "sg:phone":"+90 212 549 5177",
    "sg:postcode":"34670",
    "sg:province":"Istanbul",
    "sg:tags":[
        "store"
    ],
    "wof:name":"Er?ag Sanayi Ve Ticaret",
    "wof:placetype":"venue"
},
  "geometry": {"coordinates":[28.9861831665,41.0408554077],"type":"Point"}
}