{
  "type": "Feature",
  "properties": {
    "addr:full":"Zumrutevler Zuybeydehanim Sok. No: 26 Maltepe Cankaya Istanbul 07080",
    "addr:housenumber":"no 26",
    "addr:postcode":"07080",
    "addr:street":"Zuybeydehanim Sok.;Maltepe Cankaya",
    "iso:country":"TR",
    "sg:address":"Zumrutevler Zuybeydehanim Sok. No: 26 Maltepe",
    "sg:city":"Cankaya",
    "sg:classifiers":[
        {
            "category":"Home & Garden",
            "subcategory":"Kitchen Supply",
            "type":"Retail Goods"
        }
    ],
    "sg:phone":"+90 216 441 2060",
    "sg:postcode":"07080",
    "sg:province":"Istanbul",
    "sg:tags":[
        "wardrobe"
    ],
    "wof:name":"Aden Akrilik",
    "wof:placetype":"venue"
},
  "geometry": {"coordinates":[28.9759254456,41.0123786926],"type":"Point"}
}