{
  "type": "Feature",
  "properties": {
    "iso:country":"TR",
    "sg:address":"Saltak Cad.s?? Apt.21/1",
    "sg:city":"Sultan?ftligi",
    "sg:classifiers":[
        {
            "category":"Shopping",
            "subcategory":"Crafts & Fabrics",
            "type":"Retail Goods"
        }
    ],
    "sg:phone":"+90 258 262 2447",
    "sg:province":"Denizli",
    "sg:tags":[
        "knitting"
    ],
    "wof:name":"Bilal Tekstil Ltd.sti.",
    "wof:placetype":"venue"
},
  "geometry": {"coordinates":[29.0824947357,37.7817001343],"type":"Point"}
}