{
  "type": "Feature",
  "properties": {
    "iso:country":"TR",
    "sg:address":"Zafer Mahallesi 107 Sokak No:41",
    "sg:city":"Nazilli",
    "sg:classifiers":[
        {
            "category":"Manufacturing",
            "subcategory":"Food",
            "type":"Manufacturing & Wholesale Goods"
        }
    ],
    "sg:phone":"+90 256 313 4119",
    "sg:postcode":"65600",
    "sg:province":"Aydin",
    "sg:tags":[
        "wholesaler"
    ],
    "wof:name":"Kanaat Gida San. Tic. Ltd. Sti.",
    "wof:placetype":"venue"
},
  "geometry": {"coordinates":[27.8459663391,37.8448829651],"type":"Point"}
}