{
  "type": "Feature",
  "properties": {
    "iso:country":"TR",
    "sg:address":"Mehmet Bey Yolu 20.sok. No:14",
    "sg:city":"Sirinevler",
    "sg:classifiers":[
        {
            "category":"Shopping",
            "subcategory":"Clothing, Apparel, & Fashions",
            "type":"Retail Goods"
        }
    ],
    "sg:phone":"+90 212 654 4629",
    "sg:postcode":"15040",
    "sg:province":"Istanbul",
    "sg:tags":[
        "ready",
        "wear"
    ],
    "wof:name":"Ince Konfeksiyon",
    "wof:placetype":"venue"
},
  "geometry": {"coordinates":[28.8362731934,41.0299568176],"type":"Point"}
}