{
  "type": "Feature",
  "properties": {
    "addr:full":"2835 Sok. No:32/1 San Sit Besiktas Izmir 75200",
    "addr:housenumber":"no 32 / 1",
    "addr:postcode":"2835;75200",
    "addr:street":"Sok.",
    "iso:country":"TR",
    "sg:address":"2835 Sok. No:32/1 San Sit",
    "sg:city":"Besiktas",
    "sg:classifiers":[
        {
            "category":"Manufacturing",
            "subcategory":"Glass & Minerals",
            "type":"Manufacturing & Wholesale Goods"
        }
    ],
    "sg:phone":"+90 232 433 7703",
    "sg:postcode":"75200",
    "sg:province":"Izmir",
    "sg:tags":[
        "glass-mirror"
    ],
    "wof:name":"Ucel Cam Ve Ayna San Ve Tic Ltd.",
    "wof:placetype":"venue"
},
  "geometry": {"coordinates":[27.1296863556,38.4186973572],"type":"Point"}
}