{
  "type": "Feature",
  "properties": {
    "iso:country":"TR",
    "sg:address":"Davutpasa Cd. Litros Yolu 1 Topkapi",
    "sg:city":"B Cigli",
    "sg:orig_category":"General Industrial Products",
    "sg:phone":"+90 212 544 2606",
    "sg:province":"Istanbul",
    "wof:name":"T?rk Elek. End?strisi A.s.",
    "wof:placetype":"venue"
},
  "geometry": {"coordinates":[28.9258460999,41.0199203491],"type":"Point"}
}