{
  "type": "Feature",
  "properties": {
    "iso:country":"TR",
    "sg:address":"Millet Cd. K??saray No:26 D:3 Aksaray",
    "sg:city":"\u00dcsk\u00fcdar",
    "sg:classifiers":[
        {
            "category":"Building & Trades",
            "subcategory":"Construction",
            "type":"Services"
        }
    ],
    "sg:phone":"+90 212 521 6002",
    "sg:postcode":"34672",
    "sg:province":"Istanbul",
    "sg:tags":[
        "foundation"
    ],
    "wof:name":"Dogu Turkistan Vakfi",
    "wof:placetype":"venue"
},
  "geometry": {"coordinates":[28.9277267456,41.014705658],"type":"Point"}
}