{
  "type": "Feature",
  "properties": {
    "iso:country":"TR",
    "sg:address":"Kazim Dirk Mah. Suvari Cad. No:8/1",
    "sg:city":"Bornova",
    "sg:classifiers":[
        {
            "category":"Farming",
            "subcategory":"Farm",
            "type":"Manufacturing & Wholesale Goods"
        }
    ],
    "sg:phone":"+90 232 343 2651",
    "sg:postcode":"35040",
    "sg:province":"Izmir",
    "sg:tags":[
        "agricultural",
        "product"
    ],
    "wof:name":"Skal International",
    "wof:placetype":"venue"
},
  "geometry": {"coordinates":[27.2117557526,38.4634437561],"type":"Point"}
}