{
  "type": "Feature",
  "properties": {
    "addr:full":"Siracevizler Cad.ozler Apt.no: 97/2 Sisli Istanbul 65710",
    "addr:housenumber":"97 / 2",
    "addr:postcode":"65710",
    "addr:street":"Apt.No",
    "iso:country":"TR",
    "sg:address":"Siracevizler Cad.ozler Apt.no: 97/2",
    "sg:city":"Sisli",
    "sg:classifiers":[
        {
            "category":"Building & Trades",
            "subcategory":"Landscaping Services",
            "type":"Services"
        }
    ],
    "sg:phone":"+90 212 232 3399",
    "sg:postcode":"65710",
    "sg:province":"Istanbul",
    "sg:tags":[
        "landscape"
    ],
    "wof:name":"Petyap Peyzaj Insaat Tekstil Petrol Kimya Ith.ihr.",
    "wof:placetype":"venue"
},
  "geometry": {"coordinates":[28.966091156,41.0518684387],"type":"Point"}
}