{
  "type": "Feature",
  "properties": {
    "iso:country":"TR",
    "sg:address":"Organize San.bolg.7.cad. No:22",
    "sg:city":"Ikitelli/K\u00fc\u00e7\u00fck\u00e7ekmece",
    "sg:classifiers":[
        {
            "category":"Building & Trades",
            "subcategory":"Plumbing",
            "type":"Services"
        }
    ],
    "sg:phone":"+90 352 321 1743",
    "sg:postcode":"34670",
    "sg:province":"Kayseri",
    "sg:tags":[
        "pipe",
        "industry"
    ],
    "wof:name":"Ozsan Soba",
    "wof:placetype":"venue"
},
  "geometry": {"coordinates":[35.4891357422,38.7225761414],"type":"Point"}
}