{
  "type": "Feature",
  "properties": {
    "iso:country":"TR",
    "sg:address":"Abdullah Bostanci",
    "sg:city":"?ivril",
    "sg:classifiers":[
        {
            "category":"Government",
            "subcategory":"Office",
            "type":"Public Place"
        }
    ],
    "sg:phone":"+90 284 811 6009",
    "sg:province":"Edirne",
    "sg:tags":[
        "municipality"
    ],
    "wof:name":"Enez Belediye Baskani",
    "wof:placetype":"venue"
},
  "geometry": {"coordinates":[28.9527950287,41.0563545227],"type":"Point"}
}