{
  "type": "Feature",
  "properties": {
    "addr:full":"50. Yil Mah. M. Cad. No:82 Gaziosmanpasa Istanbul 01950",
    "addr:housenumber":"50;82",
    "addr:postcode":"01950",
    "addr:street":"Yil Mah. M. Cad. No;Istanbul",
    "iso:country":"TR",
    "sg:address":"50. Yil Mah. M. Cad. No:82",
    "sg:city":"Gaziosmanpasa",
    "sg:orig_category":"Carpet-kilim-blanket",
    "sg:phone":"+90 212 594 4148",
    "sg:postcode":"01950",
    "sg:province":"Istanbul",
    "wof:name":"Aksu Halicilik Ltd. Sti.",
    "wof:placetype":"venue"
},
  "geometry": {"coordinates":[28.8968391418,41.0556716919],"type":"Point"}
}