{
  "type": "Feature",
  "properties": {
    "iso:country":"TR",
    "sg:address":"Hamidiye Mah. Serakent Sitesi No.13/13",
    "sg:city":"Kagithane",
    "sg:classifiers":[
        {
            "category":"Building & Trades",
            "subcategory":"Landscaping Services",
            "type":"Services"
        }
    ],
    "sg:phone":"+90 212 216 3956",
    "sg:postcode":"34406",
    "sg:province":"Istanbul",
    "sg:tags":[
        "landscape"
    ],
    "wof:name":"Bone Ltd.sti. (magic Crystal)",
    "wof:placetype":"venue"
},
  "geometry": {"coordinates":[28.9681472778,41.0811843872],"type":"Point"}
}