{
  "type": "Feature",
  "properties": {
    "iso:country":"TR",
    "sg:address":"Murat Yilmaz",
    "sg:city":"Acipayam",
    "sg:classifiers":[
        {
            "category":"Government",
            "subcategory":"Office",
            "type":"Public Place"
        }
    ],
    "sg:phone":"+90 446 214 8107",
    "sg:postcode":"23000",
    "sg:province":"Erzincan",
    "sg:tags":[
        "municipality"
    ],
    "wof:name":"Demirkent Belediye Baskani",
    "wof:placetype":"venue"
},
  "geometry": {"coordinates":[29.2896404266,40.8966751099],"type":"Point"}
}