{
  "type": "Feature",
  "properties": {
    "addr:full":"Hasanefendi Mah. H??et Bulv. No:19/2 Merkez Aydin 09100",
    "addr:housenumber":"no 19 / 2",
    "addr:postcode":"09100",
    "addr:street":"Hasanefendi Mah. H ? ? Et Bulv.;Merkez Aydin",
    "iso:country":"TR",
    "sg:address":"Hasanefendi Mah. H??et Bulv. No:19/2",
    "sg:city":"Merkez",
    "sg:classifiers":[
        {
            "category":"Manufacturing",
            "subcategory":"Textiles",
            "type":"Manufacturing & Wholesale Goods"
        }
    ],
    "sg:phone":"+90 256 214 1446",
    "sg:postcode":"09100",
    "sg:province":"Aydin",
    "sg:tags":[
        "cloth",
        "worker"
    ],
    "wof:name":"Stratejix",
    "wof:placetype":"venue"
},
  "geometry": {"coordinates":[27.8425998688,37.8527984619],"type":"Point"}
}