{
  "type": "Feature",
  "properties": {
    "addr:full":"Akay Cad 4 Cankaya Merkez Ankara",
    "addr:housenumber":"4",
    "addr:street":"Akay Cad",
    "iso:country":"TR",
    "sg:address":"Akay Cad 4 Cankaya",
    "sg:city":"Merkez",
    "sg:classifiers":[
        {
            "category":"Banks & Credit Unions",
            "subcategory":"Bank",
            "type":"Services"
        }
    ],
    "sg:phone":"+90 312 219 7331",
    "sg:province":"Ankara",
    "wof:name":"T?kiye Cumhuriyeti, Ziraat Bankasi",
    "wof:placetype":"venue"
},
  "geometry": {"coordinates":[32.856911,39.913414],"type":"Point"}
}