{
  "type": "Feature",
  "properties": {
    "iso:country":"TR",
    "sg:address":"Ciftlik Mah.mete Sok. No: 25",
    "sg:city":"Seyhan",
    "sg:classifiers":[
        {
            "category":"Manufacturing",
            "subcategory":"Building Materials",
            "type":"Manufacturing & Wholesale Goods"
        }
    ],
    "sg:phone":"+90 2344378",
    "sg:postcode":"01100",
    "sg:province":"Samsun",
    "sg:tags":[
        "lifts-elevators"
    ],
    "wof:name":"Vemas Asansor Pazarlama San.tic.",
    "wof:placetype":"venue"
},
  "geometry": {"coordinates":[36.3349151611,41.281539917],"type":"Point"}
}