{
  "type": "Feature",
  "properties": {
    "iso:country":"TR",
    "sg:address":"B?l? Sk. No:36/5 Kavaklidere",
    "sg:city":"Kagithane",
    "sg:orig_category":"Scavening Services",
    "sg:phone":"+90 312 418 3610",
    "sg:postcode":"34406",
    "sg:province":"Ankara",
    "wof:name":"Biltem Temizlik Pazarlama San. Tic. Ltd. Sti.",
    "wof:placetype":"venue"
},
  "geometry": {"coordinates":[32.824242,39.923958],"type":"Point"}
}