{
  "type": "Feature",
  "properties": {
    "iso:country":"TR",
    "sg:address":"Keresteciler Sit. 421. Sk. No:3 Bornova",
    "sg:city":"Merkez",
    "sg:classifiers":[
        {
            "category":"Manufacturing",
            "subcategory":"Wood Products",
            "type":"Manufacturing & Wholesale Goods"
        }
    ],
    "sg:phone":"+90 232 486 2808",
    "sg:postcode":"53100",
    "sg:province":"Izmir",
    "sg:tags":[
        "forest"
    ],
    "wof:name":"Ortas Orman ?r?n. Paz. Tic. San. A.s.",
    "wof:placetype":"venue"
},
  "geometry": {"coordinates":[27.1502513885,38.4001121521],"type":"Point"}
}