{
  "type": "Feature",
  "properties": {
    "iso:country":"TR",
    "sg:address":"Amiral Tafdil Sok. No:23",
    "sg:city":"Sultanahmet",
    "sg:orig_category":"Hotels: Motels",
    "sg:phone":"+90 21251774725",
    "sg:postcode":"34400",
    "sg:province":"Istanbul",
    "wof:name":"Historia Hotel Ottoman House",
    "wof:placetype":"venue"
},
  "geometry": {"coordinates":[28.9792060852,41.0040016174],"type":"Point"}
}