{
  "type": "Feature",
  "properties": {
    "addr:full":"Bagdat Cd. Ptt Pasj. No:179/243 Maltepe Istanbul 01000",
    "addr:housenumber":"179 / 243",
    "addr:postcode":"01000",
    "addr:street":"Bagdat Cd.;Pasj. No;Istanbul",
    "iso:country":"TR",
    "sg:address":"Bagdat Cd. Ptt Pasj. No:179/243",
    "sg:city":"Maltepe",
    "sg:classifiers":[
        {
            "category":"Airport",
            "subcategory":"International",
            "type":"Transportation"
        }
    ],
    "sg:phone":"+90 216 383 1526",
    "sg:postcode":"01000",
    "sg:province":"Istanbul",
    "wof:name":"?akiroglu Nakliyat",
    "wof:placetype":"venue"
},
  "geometry": {"coordinates":[29.2859802246,40.8871612549],"type":"Point"}
}