{
  "type": "Feature",
  "properties": {
    "addr:full":"Atat?k Cad. No:4/-10 Tire \u00c7ankaya Izmir 06610",
    "addr:housenumber":"-10",
    "addr:postcode":"06610",
    "addr:street":"K Cad. No 4 /",
    "iso:country":"TR",
    "sg:address":"Atat?k Cad. No:4/-10 Tire",
    "sg:city":"\u00c7ankaya",
    "sg:classifiers":[
        {
            "category":"Shopping",
            "subcategory":"Pharmacy",
            "type":"Retail Goods"
        }
    ],
    "sg:phone":"+90 232 512 4053",
    "sg:postcode":"06610",
    "sg:province":"Izmir",
    "sg:tags":[
        "store",
        "drug"
    ],
    "wof:name":"Fatih Eczanesi",
    "wof:placetype":"venue"
},
  "geometry": {"coordinates":[27.1423015594,38.4251480103],"type":"Point"}
}