{
  "type": "Feature",
  "properties": {
    "addr:full":"B??dere Cad 42 Mecidiyek? Istanbul Istanbul",
    "addr:housenumber":"? ?;42;?",
    "addr:street":"B;Dere Cad",
    "iso:country":"TR",
    "sg:address":"B??dere Cad 42 Mecidiyek?",
    "sg:city":"Istanbul",
    "sg:classifiers":[
        {
            "category":"Banks & Credit Unions",
            "subcategory":"Bank",
            "type":"Services"
        }
    ],
    "sg:phone":"+90 212 231 8111",
    "sg:province":"Istanbul",
    "wof:name":"Birlesik T?k K?fez Bankasi As",
    "wof:placetype":"venue"
},
  "geometry": {"coordinates":[28.992979,41.080627],"type":"Point"}
}