{
  "type": "Feature",
  "properties": {
    "addr:full":"Merkez Mah.kumru Sok. No:4 Gungoren Sisli Istanbul 34834",
    "addr:housenumber":"no 4",
    "addr:postcode":"34834",
    "addr:street":"Mah.Kumru Sok.",
    "iso:country":"TR",
    "sg:address":"Merkez Mah.kumru Sok. No:4 Gungoren",
    "sg:city":"Sisli",
    "sg:classifiers":[
        {
            "category":"Freight",
            "type":"Transportation"
        }
    ],
    "sg:phone":"+90 212 557 7110",
    "sg:postcode":"34834",
    "sg:province":"Istanbul",
    "sg:tags":[
        "packing",
        "industry"
    ],
    "wof:name":"Olkar Ambalaj San.tic.ltd.sti.",
    "wof:placetype":"venue"
},
  "geometry": {"coordinates":[28.8751125336,41.0221748352],"type":"Point"}
}