{
  "type": "Feature",
  "properties": {
    "addr:full":"Organize San. B?. 4. Cad. No:19 Tuzla Kayseri 81700",
    "addr:housenumber":"4;19",
    "addr:postcode":"81700",
    "addr:street":"Organize;Cad. No",
    "iso:country":"TR",
    "sg:address":"Organize San. B?. 4. Cad. No:19",
    "sg:city":"Tuzla",
    "sg:classifiers":[
        {
            "category":"Home & Garden",
            "subcategory":"Household Appliances",
            "type":"Retail Goods"
        }
    ],
    "sg:phone":"+90 35232115133",
    "sg:postcode":"81700",
    "sg:province":"Kayseri",
    "sg:tags":[
        "kitchenware"
    ],
    "wof:name":"Ilkay Emaye Mak. San. Ltd. Sti.",
    "wof:placetype":"venue"
},
  "geometry": {"coordinates":[35.4891357422,38.7225761414],"type":"Point"}
}