{
  "type": "Feature",
  "properties": {
    "addr:full":"Kazim Karabekir Cad. No:6 Ineg? Aydin",
    "addr:housenumber":"?",
    "addr:street":"Karabekir Cad. No 6 Ineg",
    "iso:country":"TR",
    "sg:address":"Kazim Karabekir Cad. No:6",
    "sg:city":"Ineg?",
    "sg:classifiers":[
        {
            "category":"Food & Beverages",
            "subcategory":"Candy",
            "type":"Retail Goods"
        }
    ],
    "sg:phone":"+90 256214007021",
    "sg:province":"Aydin",
    "sg:tags":[
        "biscuit-chocolate-candy"
    ],
    "wof:name":"Fistikci Oglu Gida San. Ins. Ltd. Sti.",
    "wof:placetype":"venue"
},
  "geometry": {"coordinates":[27.843401,37.849079],"type":"Point"}
}