{
  "type": "Feature",
  "properties": {
    "iso:country":"TR",
    "sg:address":"Canakkale Asfalti 7.km. Edincik/",
    "sg:city":"Bandirma",
    "sg:classifiers":[
        {
            "category":"Wholesale",
            "subcategory":"Machinery & Supplies",
            "type":"Manufacturing & Wholesale Goods"
        }
    ],
    "sg:phone":"+90 266 727 1250",
    "sg:postcode":"10200",
    "sg:province":"Balikesir",
    "sg:tags":[
        "agricultural"
    ],
    "wof:name":"Koymak Tarim Makinalari Sanayi",
    "wof:placetype":"venue"
},
  "geometry": {"coordinates":[27.8833007812,39.6520996094],"type":"Point"}
}