{
  "type": "Feature",
  "properties": {
    "iso:country":"TR",
    "sg:address":"Dinar Asf.",
    "sg:city":"Sandikli",
    "sg:classifiers":[
        {
            "category":"Wholesale",
            "subcategory":"Farm Supplies",
            "type":"Manufacturing & Wholesale Goods"
        }
    ],
    "sg:phone":"+90 272 515 2521",
    "sg:postcode":"25900",
    "sg:province":"Afyon",
    "sg:tags":[
        "feed",
        "industry"
    ],
    "wof:name":"Akt?rkler Yem San. Koll.sti.",
    "wof:placetype":"venue"
},
  "geometry": {"coordinates":[30.5417995453,38.7557983398],"type":"Point"}
}