{
  "type": "Feature",
  "properties": {
    "iso:country":"TR",
    "sg:address":"Merkez: 100 Yil Mah.ziraat Sk.uysal Apt.no 12/a Sube:istiklal Cad.istiklal Is Hani Kat6 Daire 15",
    "sg:city":"100. Yil",
    "sg:classifiers":[
        {
            "category":"Landmark",
            "subcategory":"Square",
            "type":"Public Place"
        }
    ],
    "sg:phone":"+90 282 263 6162",
    "sg:postcode":"59100",
    "sg:province":"Tekirdag",
    "sg:tags":[
        "surveyor"
    ],
    "wof:name":"Trakya Uluslararasi G?etim Denizcilik Ltd.sti.",
    "wof:placetype":"venue"
},
  "geometry": {"coordinates":[27.507751,40.966351],"type":"Point"}
}