{
  "type": "Feature",
  "properties": {
    "addr:full":"Eski Bagdat Cad. No.:19/1 Bostanci Istanbul 34840",
    "addr:housenumber":"19 / 1",
    "addr:postcode":"34840",
    "addr:street":"Eski Bagdat Cad. No.",
    "iso:country":"TR",
    "sg:address":"Eski Bagdat Cad. No.:19/1",
    "sg:city":"Bostanci",
    "sg:classifiers":[
        {
            "category":"Wholesale",
            "subcategory":"Chemicals & Plastics",
            "type":"Manufacturing & Wholesale Goods"
        }
    ],
    "sg:phone":"+90 216 388 9970",
    "sg:postcode":"34840",
    "sg:province":"Istanbul",
    "sg:tags":[
        "raw",
        "material"
    ],
    "wof:name":"Biesterfeld-bv Plastik Tic. A.s.",
    "wof:placetype":"venue"
},
  "geometry": {"coordinates":[29.0991516113,40.951259613],"type":"Point"}
}