{
  "type": "Feature",
  "properties": {
    "iso:country":"TR",
    "sg:address":"Idealtepe Anneler Sok.durkent Sit.c Blok No:13/20",
    "sg:city":"Maltepe",
    "sg:classifiers":[
        {
            "category":"Wholesale",
            "subcategory":"Plants",
            "type":"Manufacturing & Wholesale Goods"
        }
    ],
    "sg:phone":"+90 216 417 5530",
    "sg:postcode":"01000",
    "sg:province":"Istanbul",
    "sg:tags":[
        "natural",
        "spice"
    ],
    "wof:name":"Gmt Gida Maddeleri San. Tic.ltd.sti.",
    "wof:placetype":"venue"
},
  "geometry": {"coordinates":[28.975925,41.012379],"type":"Point"}
}