{
  "type": "Feature",
  "properties": {
    "iso:country":"TR",
    "sg:address":"Perpa 11 Kat 1848 Okmeydani",
    "sg:city":"Okmaydani",
    "sg:orig_category":"Perpa",
    "sg:phone":"+90 212 222 7200",
    "sg:province":"Istanbul",
    "sg:website":"telmar.com.tr",
    "wof:name":"Telmar Iletisim Sistemleri Ltd",
    "wof:placetype":"venue"
},
  "geometry": {"coordinates":[28.9759254456,41.0123786926],"type":"Point"}
}