{
  "type": "Feature",
  "properties": {
    "addr:full":"Fethiye Cad. Karagoz Ishani No:70 Izmit Kocaeli 41000",
    "addr:housenumber":"karagoz;70",
    "addr:postcode":"41000",
    "addr:street":"Fethiye Cad.;Ishani No;Kocaeli",
    "iso:country":"TR",
    "sg:address":"Fethiye Cad. Karagoz Ishani No:70",
    "sg:city":"Izmit",
    "sg:classifiers":[
        {
            "category":"Professional",
            "subcategory":"Engineering",
            "type":"Services"
        }
    ],
    "sg:phone":"+90 262 323 0270",
    "sg:postcode":"41000",
    "sg:province":"Kocaeli",
    "sg:tags":[
        "architect"
    ],
    "wof:name":"Batgun Ic Mimarlik",
    "wof:placetype":"venue"
},
  "geometry": {"coordinates":[29.9345855713,40.7669563293],"type":"Point"}
}