{
  "type": "Feature",
  "properties": {
    "addr:full":"Deniz Mah. 45 Nolu Sok.no:81 Sincanli Gaziantep",
    "addr:housenumber":"45 nolu sok.no 81",
    "addr:street":"Deniz Mah.;Sincanli Gaziantep",
    "iso:country":"TR",
    "sg:address":"Deniz Mah. 45 Nolu Sok.no:81",
    "sg:city":"Sincanli",
    "sg:classifiers":[
        {
            "category":"Home & Garden",
            "subcategory":"Building Materials",
            "type":"Retail Goods"
        }
    ],
    "sg:phone":"+90 342 233 3361",
    "sg:province":"Gaziantep",
    "sg:tags":[
        "stone",
        "natural",
        "marble"
    ],
    "wof:name":"Turkhshvision",
    "wof:placetype":"venue"
},
  "geometry": {"coordinates":[37.4416732788,36.9459457397],"type":"Point"}
}