{
  "type": "Feature",
  "properties": {
    "iso:country":"TR",
    "sg:address":"408.sok. No:20/b 3.san. Sitesi Bornova",
    "sg:city":"Ikitelli/K\u00fc\u00e7\u00fck\u00e7ekmece",
    "sg:classifiers":[
        {
            "category":"Retail",
            "subcategory":"Auto Repair",
            "type":"Services"
        }
    ],
    "sg:phone":"+90 232 462 2032",
    "sg:postcode":"34670",
    "sg:province":"Izmir",
    "sg:tags":[
        "maintenance"
    ],
    "wof:name":"Nur Oto Elektronik",
    "wof:placetype":"venue"
},
  "geometry": {"coordinates":[27.1423015594,38.4251480103],"type":"Point"}
}