{
  "type": "Feature",
  "properties": {
    "addr:full":"Kenan Evren Bulvari ?akirlarlioglu Apt. No:56/1 Bodrum Antalya 48400",
    "addr:housenumber":"?;1 bodrum",
    "addr:postcode":"48400",
    "addr:street":"Kenan Evren Bulvari",
    "iso:country":"TR",
    "sg:address":"Kenan Evren Bulvari ?akirlarlioglu Apt. No:56/1",
    "sg:city":"Bodrum",
    "sg:classifiers":[
        {
            "category":"Recreation",
            "subcategory":"Boat Charter",
            "type":"Entertainment"
        }
    ],
    "sg:phone":"+90 242 248 9420",
    "sg:postcode":"48400",
    "sg:province":"Antalya",
    "sg:tags":[
        "yachting"
    ],
    "wof:name":"Holitur Tourism",
    "wof:placetype":"venue"
},
  "geometry": {"coordinates":[30.7031345367,36.8875045776],"type":"Point"}
}