{
  "type": "Feature",
  "properties": {
    "addr:full":"Bugday Pazari Nedim Murat Oglu Is Menkezi No: 19/28 Alasehir Erzincan 45600",
    "addr:housenumber":"28",
    "addr:postcode":"45600",
    "addr:street":"No 19 /",
    "iso:country":"TR",
    "sg:address":"Bugday Pazari Nedim Murat Oglu Is Menkezi No: 19/28",
    "sg:city":"Alasehir",
    "sg:classifiers":[
        {
            "category":"Manufacturing",
            "subcategory":"Chemicals & Compounds",
            "type":"Manufacturing & Wholesale Goods"
        }
    ],
    "sg:phone":"+90 446 224 2451",
    "sg:postcode":"45600",
    "sg:province":"Erzincan",
    "sg:tags":[
        "agricultural"
    ],
    "wof:name":"Ozyigit Tarim & Saf Petek Aricilik",
    "wof:placetype":"venue"
},
  "geometry": {"coordinates":[39.4905014038,39.7491989136],"type":"Point"}
}