{
  "type": "Feature",
  "properties": {
    "addr:full":"Bomonti Lala Sahin Sk. Lala Sahin Cikmazi No.11 Sisli Fatih Istanbul 34080",
    "addr:housenumber":"no.11",
    "addr:postcode":"34080",
    "addr:street":"Sisli Fatih Istanbul",
    "iso:country":"TR",
    "sg:address":"Bomonti Lala Sahin Sk. Lala Sahin Cikmazi No.11 Sisli",
    "sg:city":"Fatih",
    "sg:classifiers":[
        {
            "category":"Social Services",
            "subcategory":"Retirement Home",
            "type":"Services"
        }
    ],
    "sg:phone":"+90 212 296 2626",
    "sg:postcode":"34080",
    "sg:province":"Istanbul",
    "sg:tags":[
        "door"
    ],
    "wof:name":"Toros Reklamcilik",
    "wof:placetype":"venue"
},
  "geometry": {"coordinates":[28.9759254456,41.0123786926],"type":"Point"}
}