{
  "type": "Feature",
  "properties": {
    "addr:full":"B??yer Mahallesi 07410payallar Alanya Antalya 07400",
    "addr:housenumber":"? ?;07410payallar",
    "addr:postcode":"07400",
    "addr:street":"B;Yer Mahallesi",
    "iso:country":"TR",
    "sg:address":"B??yer Mahallesi 07410payallar",
    "sg:city":"Alanya",
    "sg:orig_category":"Hotels: Motels",
    "sg:phone":"+90 24254537143",
    "sg:postcode":"07400",
    "sg:province":"Antalya",
    "wof:name":"Sun Heaven Apart Hotel",
    "wof:placetype":"venue"
},
  "geometry": {"coordinates":[30.7092056274,36.8790512085],"type":"Point"}
}