{
  "type": "Feature",
  "properties": {
    "addr:full":"Yesiloba Mah. T.c.beriker Bul. Adana Is Merkez.b Blok No:2 Semikler Adana 20085",
    "addr:housenumber":"blok no 2",
    "addr:postcode":"20085",
    "addr:street":"Yesiloba Mah. T.C.Beriker Bul.;Semikler Adana",
    "iso:country":"TR",
    "sg:address":"Yesiloba Mah. T.c.beriker Bul. Adana Is Merkez.b Blok No:2",
    "sg:city":"Semikler",
    "sg:classifiers":[
        {
            "category":"Food & Beverages",
            "subcategory":"Candy",
            "type":"Retail Goods"
        }
    ],
    "sg:phone":"+90 322 428 0202",
    "sg:postcode":"20085",
    "sg:province":"Adana",
    "sg:tags":[
        "biscuit-chocolate-candy"
    ],
    "wof:name":"Oguz Pazarlama Ve Seker San Ve Tic.ltd.sti.",
    "wof:placetype":"venue"
},
  "geometry": {"coordinates":[35.313736,37.000717],"type":"Point"}
}