{
  "type": "Feature",
  "properties": {
    "addr:full":"Talas Cad. No:24/2 Merkez Kayseri 26000",
    "addr:housenumber":"24 / 2 merkez",
    "addr:postcode":"26000",
    "addr:street":"Talas Cad. No",
    "iso:country":"TR",
    "sg:address":"Talas Cad. No:24/2",
    "sg:city":"Merkez",
    "sg:classifiers":[
        {
            "category":"Wholesale",
            "subcategory":"Medical Equipment & Supplies",
            "type":"Manufacturing & Wholesale Goods"
        }
    ],
    "sg:phone":"+90 352 231 4306",
    "sg:postcode":"26000",
    "sg:province":"Kayseri",
    "sg:tags":[
        "material"
    ],
    "wof:name":"Safak Tibbi Cih. Ltd. Sti.",
    "wof:placetype":"venue"
},
  "geometry": {"coordinates":[35.4768218994,38.7423248291],"type":"Point"}
}