{
  "type": "Feature",
  "properties": {
    "addr:full":"Ortaklar Caddesi Onur Apartmani No:2/4 - Sisli \u00c7ankaya Istanbul 06700",
    "addr:postcode":"06700",
    "addr:street":"Ortaklar Caddesi",
    "iso:country":"TR",
    "sg:address":"Ortaklar Caddesi Onur Apartmani No:2/4 - Sisli",
    "sg:city":"\u00c7ankaya",
    "sg:classifiers":[
        {
            "category":"Health Services",
            "subcategory":"Medical Lab",
            "type":"Services"
        }
    ],
    "sg:phone":"+90 212 272 8294",
    "sg:postcode":"06700",
    "sg:province":"Istanbul",
    "wof:name":"Net Tip Tibbi Tahliller Laboratuvari",
    "wof:placetype":"venue"
},
  "geometry": {"coordinates":[28.9861831665,41.0408554077],"type":"Point"}
}