{
  "type": "Feature",
  "properties": {
    "addr:full":"Cankari Cad, Ulus Is Hani Istanbul Ankara",
    "addr:street":"Cankari Cad",
    "iso:country":"TR",
    "sg:address":"Cankari Cad, Ulus Is Hani",
    "sg:city":"Istanbul",
    "sg:classifiers":[
        {
            "category":"Banks & Credit Unions",
            "subcategory":"Bank",
            "type":"Services"
        }
    ],
    "sg:phone":"+90 4117893",
    "sg:province":"Ankara",
    "wof:name":"Denizcilik Bankasi Tas",
    "wof:placetype":"venue"
},
  "geometry": {"coordinates":[32.856033,39.943874],"type":"Point"}
}