{
  "type": "Feature",
  "properties": {
    "addr:full":"?inar Mahallesi 5/4 Sokak No: 2 Bagcilar Istanbul 33115",
    "addr:housenumber":"?;5 /",
    "addr:postcode":"33115",
    "addr:street":"Inar Mahallesi;4 Sokak No 2 Bagcilar",
    "iso:country":"TR",
    "sg:address":"?inar Mahallesi 5/4 Sokak No: 2",
    "sg:city":"Bagcilar",
    "sg:classifiers":[
        {
            "category":"Professional",
            "subcategory":"Business Services",
            "type":"Services"
        }
    ],
    "sg:phone":"+90 212",
    "sg:postcode":"33115",
    "sg:province":"Istanbul",
    "wof:name":"Yeni Bagcilar Gazetesi",
    "wof:placetype":"venue"
},
  "geometry": {"coordinates":[29.0321407318,41.1172637939],"type":"Point"}
}