{
  "type": "Feature",
  "properties": {
    "addr:full":"Toyota Plaza Arkasi Keykat Mah.no:9 Melikgazi Kayseri 38010",
    "addr:housenumber":"9",
    "addr:postcode":"38010",
    "addr:street":"Mah.No",
    "iso:country":"TR",
    "sg:address":"Toyota Plaza Arkasi Keykat Mah.no:9",
    "sg:city":"Melikgazi",
    "sg:classifiers":[
        {
            "category":"Banks & Credit Unions",
            "subcategory":"Investment Brokerage",
            "type":"Services"
        }
    ],
    "sg:phone":"+90 352 326 8654",
    "sg:postcode":"38010",
    "sg:province":"Kayseri",
    "sg:tags":[
        "injection",
        "plastic"
    ],
    "wof:name":"?zates Plastik",
    "wof:placetype":"venue"
},
  "geometry": {"coordinates":[35.4891357422,38.7225761414],"type":"Point"}
}