{
  "type": "Feature",
  "properties": {
    "addr:full":"Cakmakli K??akcaburgaz Mevkii 11.cad. San-bir Bul. 4. B?ge 34900 B??cekmece Istanbul Atasehir Istanbul 81120",
    "addr:housenumber":"4 b ?;b ? ?",
    "addr:postcode":"34900;81120",
    "addr:street":"Akcaburgaz Mevkii 11.Cad San-Bir Bul.;Ge",
    "iso:country":"TR",
    "sg:address":"Cakmakli K??akcaburgaz Mevkii 11.cad. San-bir Bul. 4. B?ge 34900 B??cekmece Istanbul",
    "sg:city":"Atasehir",
    "sg:classifiers":[
        {
            "category":"Bars & Pubs",
            "subcategory":"Nightclub",
            "type":"Food & Drink"
        }
    ],
    "sg:phone":"+90 212 886 7880",
    "sg:postcode":"81120",
    "sg:province":"Istanbul",
    "sg:tags":[
        "cake",
        "bread"
    ],
    "wof:name":"Vatan Gida San",
    "wof:placetype":"venue"
},
  "geometry": {"coordinates":[28.975925,41.012379],"type":"Point"}
}