{
  "type": "Feature",
  "properties": {
    "addr:full":"Kisla Caddesi Cicoz Yolu No:20 Top?ular Bayrampasa Istanbul 34055",
    "addr:housenumber":"no 20;?",
    "addr:postcode":"34055",
    "addr:street":"Kisla Caddesi Cicoz Yolu;Top",
    "iso:country":"TR",
    "sg:address":"Kisla Caddesi Cicoz Yolu No:20 Top?ular",
    "sg:city":"Bayrampasa",
    "sg:classifiers":[
        {
            "category":"Train Station",
            "subcategory":"Rail",
            "type":"Transportation"
        }
    ],
    "sg:phone":"+90 212 567 7794",
    "sg:postcode":"34055",
    "sg:province":"Istanbul",
    "sg:tags":[
        "sheet",
        "iron"
    ],
    "wof:name":"Mades Metal San Ve Tic.ltd",
    "wof:placetype":"venue"
},
  "geometry": {"coordinates":[28.923021,41.040619],"type":"Point"}
}