{
  "type": "Feature",
  "properties": {
    "addr:full":"Maltepe Sisli Ankara 34200",
    "addr:postcode":"34200",
    "addr:street":"Maltepe;Ankara",
    "iso:country":"TR",
    "sg:address":"Maltepe",
    "sg:city":"Sisli",
    "sg:classifiers":[
        {
            "category":"Shopping",
            "subcategory":"Stationery & Office Supplies",
            "type":"Retail Goods"
        }
    ],
    "sg:phone":"+90 312 266 4410",
    "sg:postcode":"34200",
    "sg:province":"Ankara",
    "sg:tags":[
        "paper"
    ],
    "wof:name":"Meteksan Matbaacilik Teknik San. Tic. Ltd. Sti.",
    "wof:placetype":"venue"
},
  "geometry": {"coordinates":[28.902551651,41.0522270203],"type":"Point"}
}