{
  "type": "Feature",
  "properties": {
    "iso:country":"TR",
    "sg:address":"Dersane Sk.park Apt.no.16/6",
    "sg:city":"Harbiye",
    "sg:classifiers":[
        {
            "category":"Shopping",
            "subcategory":"Clothing, Apparel, & Fashions",
            "type":"Retail Goods"
        }
    ],
    "sg:phone":"+90 212 230 1853",
    "sg:postcode":"31080",
    "sg:province":"Istanbul",
    "sg:tags":[
        "ready",
        "wear"
    ],
    "wof:name":"Ofra Tekstil A.s.",
    "wof:placetype":"venue"
},
  "geometry": {"coordinates":[29.0078811646,41.0441474915],"type":"Point"}
}