{
  "type": "Feature",
  "properties": {
    "addr:full":"Cankiri Cad. Fatih Is Hani No:26 Kat:7 D:19 Ulus Ortak? Ankara 80840",
    "addr:housenumber":"no 26 kat 7 d 19;?",
    "addr:postcode":"80840",
    "addr:street":"Cankiri Cad. Fatih Is;Ulus Ortak",
    "iso:country":"TR",
    "sg:address":"Cankiri Cad. Fatih Is Hani No:26 Kat:7 D:19 Ulus",
    "sg:city":"Ortak?",
    "sg:classifiers":[
        {
            "category":"Organizations",
            "subcategory":"Professional Association",
            "type":"Services"
        }
    ],
    "sg:phone":"+90 312 309 3606",
    "sg:postcode":"80840",
    "sg:province":"Ankara",
    "wof:name":"Teknikler Birligi Genel Merkezi",
    "wof:placetype":"venue"
},
  "geometry": {"coordinates":[32.8560333252,39.9438743591],"type":"Point"}
}