{
  "type": "Feature",
  "properties": {
    "addr:full":"Yali Mah.misafir Sok.no.13 Akcakoca Bolu 25560",
    "addr:postcode":"25560",
    "addr:street":"Bolu",
    "iso:country":"TR",
    "sg:address":"Yali Mah.misafir Sok.no.13",
    "sg:city":"Akcakoca",
    "sg:classifiers":[
        {
            "category":"Farming",
            "subcategory":"Farm & Veterinary Services",
            "type":"Manufacturing & Wholesale Goods"
        }
    ],
    "sg:phone":"+90 374611325861",
    "sg:postcode":"25560",
    "sg:province":"Bolu",
    "sg:tags":[
        "veterinarian"
    ],
    "wof:name":"Mustafa Ozdemir",
    "wof:placetype":"venue"
},
  "geometry": {"coordinates":[31.6107006073,40.7332992554],"type":"Point"}
}