{
  "type": "Feature",
  "properties": {
    "iso:country":"TR",
    "sg:address":"Merkez Mh. Fatih Sk. No:1/a",
    "sg:city":"Avcilar",
    "sg:classifiers":[
        {
            "category":"Shopping",
            "subcategory":"Florist",
            "type":"Retail Goods"
        }
    ],
    "sg:phone":"+90 212 509 2856",
    "sg:postcode":"01350",
    "sg:province":"Istanbul",
    "sg:tags":[
        "flower"
    ],
    "wof:name":"G?n?l ?i?ek Galerisi",
    "wof:placetype":"venue"
},
  "geometry": {"coordinates":[28.8627986908,41.0420684814],"type":"Point"}
}