{
  "type": "Feature",
  "properties": {
    "addr:full":"Cumhuriyet Meydani Denizer Is Merkezi No:25 Edremit Balikesir 04500",
    "addr:housenumber":"no 25",
    "addr:postcode":"04500",
    "addr:street":"Balikesir",
    "iso:country":"TR",
    "sg:address":"Cumhuriyet Meydani Denizer Is Merkezi No:25",
    "sg:city":"Edremit",
    "sg:classifiers":[
        {
            "category":"Utilities",
            "subcategory":"Water",
            "type":"Services"
        }
    ],
    "sg:phone":"+90 266 373 2220",
    "sg:postcode":"04500",
    "sg:province":"Balikesir",
    "sg:tags":[
        "vegetable",
        "margarine",
        "oil"
    ],
    "wof:name":"Resat Akillioglu-biyolojik Urunler San.tic.sti.",
    "wof:placetype":"venue"
},
  "geometry": {"coordinates":[27.8833007812,39.6520996094],"type":"Point"}
}