{
  "type": "Feature",
  "properties": {
    "iso:country":"TR",
    "sg:address":"Im? 2 Blok No:2243 Unkapani",
    "sg:city":"\u00dcmraniye",
    "sg:classifiers":[
        {
            "category":"Manufacturing",
            "subcategory":"Tools & Machinery",
            "type":"Manufacturing & Wholesale Goods"
        }
    ],
    "sg:phone":"+90 212 528 4521",
    "sg:postcode":"34776",
    "sg:province":"Istanbul",
    "sg:tags":[
        "machine",
        "industry"
    ],
    "wof:name":"Kardesler Dikis Makina San. Tic. Ltd. Sti.",
    "wof:placetype":"venue"
},
  "geometry": {"coordinates":[29.175403595,41.0060424805],"type":"Point"}
}