{
  "type": "Feature",
  "properties": {
    "addr:full":"Muttalip Cad. Ege Sok. No:1/2 Edremit Eskisehir 04500",
    "addr:housenumber":"no 1 / 2",
    "addr:postcode":"04500",
    "addr:street":"Muttalip Cad. Ege Sok.;Eskisehir",
    "iso:country":"TR",
    "sg:address":"Muttalip Cad. Ege Sok. No:1/2",
    "sg:city":"Edremit",
    "sg:classifiers":[
        {
            "category":"Manufacturing",
            "subcategory":"Building Materials",
            "type":"Manufacturing & Wholesale Goods"
        }
    ],
    "sg:phone":"+90 222 231 1414",
    "sg:postcode":"04500",
    "sg:province":"Eskisehir",
    "sg:tags":[
        "lifts-elevators"
    ],
    "wof:name":"Koseoglu As Asansor",
    "wof:placetype":"venue"
},
  "geometry": {"coordinates":[30.5175457001,39.7700805664],"type":"Point"}
}