{
  "type": "Feature",
  "properties": {
    "addr:full":"Igdir Yolu 4. Km. Dogubayazit Agri",
    "addr:housenumber":"4 km.",
    "addr:street":"Igdir Yolu;Dogubayazit Agri",
    "iso:country":"TR",
    "sg:address":"Igdir Yolu 4. Km.",
    "sg:city":"Dogubayazit",
    "sg:classifiers":[
        {
            "category":"Structure",
            "subcategory":"Warehouse",
            "type":"Public Place"
        }
    ],
    "sg:phone":"+90 472 312 3221",
    "sg:province":"Agri",
    "wof:name":"Bayazit Antrepoculuk Nakliyat Ve Ticaret Ltd.sti.",
    "wof:placetype":"venue"
},
  "geometry": {"coordinates":[43.0544013977,39.7225990295],"type":"Point"}
}