{
  "type": "Feature",
  "properties": {
    "addr:full":"Sirtas S. No: 13/3 Mecidiyekoy Istanbul 34387",
    "addr:housenumber":"no 13 / 3",
    "addr:postcode":"34387",
    "addr:street":"Sirtas",
    "iso:country":"TR",
    "sg:address":"Sirtas S. No: 13/3",
    "sg:city":"Mecidiyekoy",
    "sg:classifiers":[
        {
            "category":"Building & Trades",
            "subcategory":"Locksmith",
            "type":"Services"
        }
    ],
    "sg:phone":"+90 2122129992212",
    "sg:postcode":"34387",
    "sg:province":"Istanbul",
    "sg:tags":[
        "lock",
        "key"
    ],
    "wof:name":"Alkur Ins. San. Ltd.sti.",
    "wof:placetype":"venue"
},
  "geometry": {"coordinates":[29.1910610199,41.0025939941],"type":"Point"}
}