{
  "type": "Feature",
  "properties": {
    "addr:full":"Carrefoursa Alisveris Merkezi 6522 Sok. 1. Giris P.26 Yali Mah. Karsiyaka Izmir 01900",
    "addr:housenumber":"1;mah.",
    "addr:postcode":"01900",
    "addr:street":"6522 Sok.;P.26",
    "iso:country":"TR",
    "sg:address":"Carrefoursa Alisveris Merkezi 6522 Sok. 1. Giris P.26 Yali Mah.",
    "sg:city":"Karsiyaka",
    "sg:classifiers":[
        {
            "category":"Travel",
            "subcategory":"Travel Agent",
            "type":"Entertainment"
        }
    ],
    "sg:phone":"+90 232 324 2016",
    "sg:postcode":"01900",
    "sg:province":"Izmir",
    "sg:tags":[
        "agency",
        "tourism"
    ],
    "wof:name":"Teoden Turizm",
    "wof:placetype":"venue"
},
  "geometry": {"coordinates":[27.1423015594,38.4251480103],"type":"Point"}
}