{
  "type": "Feature",
  "properties": {
    "addr:full":"Cumhuriyet Meydani, Sehit Tekirdag 59850 59000",
    "addr:postcode":"59850 59000",
    "addr:street":"Sehit Tekirdag",
    "iso:country":"TR",
    "sg:address":"Cumhuriyet Meydani, Sehit",
    "sg:city":"Tekirdag",
    "sg:classifiers":[
        {
            "category":"Banks & Credit Unions",
            "subcategory":"Bank",
            "type":"Services"
        }
    ],
    "sg:phone":"+90 282 651 7319",
    "sg:postcode":"59000",
    "sg:province":"59850",
    "wof:name":"T?kiye T??c?er, Bankasi Yasarbank As",
    "wof:placetype":"venue"
},
  "geometry": {"coordinates":[30.348812,40.698048],"type":"Point"}
}