{
  "type": "Feature",
  "properties": {
    "iso:country":"TR",
    "sg:address":"Perpa Ism. K:13 No:2321 Okmeydani",
    "sg:city":"Hasanpasa/kadik?",
    "sg:classifiers":[
        {
            "category":"Wholesale",
            "subcategory":"Medical Equipment & Supplies",
            "type":"Manufacturing & Wholesale Goods"
        }
    ],
    "sg:phone":"+90 212 222 2000",
    "sg:postcode":"34722",
    "sg:province":"Istanbul",
    "sg:tags":[
        "material"
    ],
    "wof:name":"Somar Dis Tic. San.",
    "wof:placetype":"venue"
},
  "geometry": {"coordinates":[29.0459918976,40.9934997559],"type":"Point"}
}