{
  "type": "Feature",
  "properties": {
    "iso:country":"TR",
    "sg:address":"Fatih Mah.cengiz Sok.topel Cad. No:4 A",
    "sg:city":"Buyukcekmece",
    "sg:classifiers":[
        {
            "category":"Manufacturing",
            "subcategory":"Building Materials",
            "type":"Manufacturing & Wholesale Goods"
        }
    ],
    "sg:phone":"+90 212 881 2524",
    "sg:postcode":"34500",
    "sg:province":"Istanbul",
    "sg:tags":[
        "lifts-elevators"
    ],
    "wof:name":"Tuna Asansor",
    "wof:placetype":"venue"
},
  "geometry": {"coordinates":[28.7708702087,40.9847450256],"type":"Point"}
}