{
  "type": "Feature",
  "properties": {
    "addr:full":"Orhangazi Cad.kardesler Sok. No: 32/1 Maltepe Istanbul 01000",
    "addr:housenumber":"no 32 / 1",
    "addr:postcode":"01000",
    "addr:street":"Cad.Kardesler Sok.;Istanbul",
    "iso:country":"TR",
    "sg:address":"Orhangazi Cad.kardesler Sok. No: 32/1",
    "sg:city":"Maltepe",
    "sg:classifiers":[
        {
            "category":"Manufacturing",
            "subcategory":"Building Materials",
            "type":"Manufacturing & Wholesale Goods"
        }
    ],
    "sg:phone":"+90 216 305 6294",
    "sg:postcode":"01000",
    "sg:province":"Istanbul",
    "sg:tags":[
        "lifts-elevators"
    ],
    "wof:name":"El-sa Asansor San",
    "wof:placetype":"venue"
},
  "geometry": {"coordinates":[29.2318019867,41.018321991],"type":"Point"}
}