{
  "type": "Feature",
  "properties": {
    "addr:full":"Izzetpasa ?iftligi Mh. Firin Sk. No:32/1 Sisli Istanbul 65710",
    "addr:housenumber":"32 / 1",
    "addr:postcode":"65710",
    "addr:street":"Iftligi Mh. Firin Sk. No",
    "iso:country":"TR",
    "sg:address":"Izzetpasa ?iftligi Mh. Firin Sk. No:32/1",
    "sg:city":"Sisli",
    "sg:classifiers":[
        {
            "category":"Utilities",
            "subcategory":"Natural Gas",
            "type":"Services"
        }
    ],
    "sg:phone":"+90 212 230 8274",
    "sg:postcode":"65710",
    "sg:province":"Istanbul",
    "sg:tags":[
        "tank-heating-natural"
    ],
    "wof:name":"??z?m Makine Insaat San. Tic. Ltd. Sti.",
    "wof:placetype":"venue"
},
  "geometry": {"coordinates":[28.9861831665,41.0408554077],"type":"Point"}
}