{
  "type": "Feature",
  "properties": {
    "iso:country":"TR",
    "sg:address":"Yesilk?",
    "sg:city":"Elmadag",
    "sg:classifiers":[
        {
            "category":"Freight",
            "type":"Transportation"
        }
    ],
    "sg:phone":"+90 212 263 0941",
    "sg:postcode":"65900",
    "sg:province":"Istanbul",
    "sg:tags":[
        "cargo",
        "air"
    ],
    "wof:name":"G?kusagi Sportif Havacilik",
    "wof:placetype":"venue"
},
  "geometry": {"coordinates":[28.8299026489,40.9577865601],"type":"Point"}
}