{
  "type": "Feature",
  "properties": {
    "addr:full":"Alemdag Cad 27 \u00dcmraniye 81240",
    "addr:housenumber":"27",
    "addr:postcode":"81240",
    "addr:street":"Alemdag Cad",
    "iso:country":"TR",
    "sg:address":"Alemdag Cad 27",
    "sg:city":"\u00dcmraniye",
    "sg:classifiers":[
        {
            "category":"Banks & Credit Unions",
            "subcategory":"Bank",
            "type":"Services"
        }
    ],
    "sg:phone":"+90 216 328 2304",
    "sg:province":"81240",
    "wof:name":"T?kiye Emlak, Bankasi As",
    "wof:placetype":"venue"
},
  "geometry": {"coordinates":[29.06477,41.021961],"type":"Point"}
}