{
  "type": "Feature",
  "properties": {
    "addr:full":"Cevatpasa Mah Komiser Resat Dayi Cad No:44 Bayrampasa Istanbul 36100",
    "addr:housenumber":"44",
    "addr:postcode":"36100",
    "addr:street":"Cevatpasa Mah Komiser Resat Dayi Cad No;Istanbul",
    "iso:country":"TR",
    "sg:address":"Cevatpasa Mah Komiser Resat Dayi Cad No:44",
    "sg:city":"Bayrampasa",
    "sg:classifiers":[
        {
            "category":"Building & Trades",
            "subcategory":"Landscaping Services",
            "type":"Services"
        }
    ],
    "sg:phone":"+90 212 477 8352",
    "sg:postcode":"36100",
    "sg:province":"Istanbul",
    "sg:tags":[
        "market"
    ],
    "wof:name":"Tekin S?permarket",
    "wof:placetype":"venue"
},
  "geometry": {"coordinates":[28.9861831665,41.0408554077],"type":"Point"}
}