{
  "type": "Feature",
  "properties": {
    "addr:full":"S.esref Bulvan 18 Altay Is Mrk. Kat 3 No.l 304 Cankaya Izmir 07080",
    "addr:housenumber":"18;kat 3;304",
    "addr:postcode":"07080",
    "addr:street":"Altay Is Mrk.;No.L",
    "iso:country":"TR",
    "sg:address":"S.esref Bulvan 18 Altay Is Mrk. Kat 3 No.l 304",
    "sg:city":"Cankaya",
    "sg:classifiers":[
        {
            "category":"Freight",
            "type":"Transportation"
        }
    ],
    "sg:phone":"+90 232 441 3829",
    "sg:postcode":"07080",
    "sg:province":"Izmir",
    "sg:tags":[
        "cargo",
        "air"
    ],
    "wof:name":"British Airways",
    "wof:placetype":"venue"
},
  "geometry": {"coordinates":[27.1296863556,38.4186973572],"type":"Point"}
}