{
  "type": "Feature",
  "properties": {
    "iso:country":"TR",
    "sg:address":"Karsiyaka",
    "sg:city":"Ikitelli/K\u00fc\u00e7\u00fck\u00e7ekmece",
    "sg:classifiers":[
        {
            "category":"Manufacturing",
            "subcategory":"Tools & Machinery",
            "type":"Manufacturing & Wholesale Goods"
        }
    ],
    "sg:phone":"+90 232 364 4222",
    "sg:postcode":"34670",
    "sg:province":"Izmir",
    "sg:tags":[
        "machine",
        "industry"
    ],
    "wof:name":"Senkon Ltd.sti.",
    "wof:placetype":"venue"
},
  "geometry": {"coordinates":[27.1220397949,38.4564743042],"type":"Point"}
}