{
  "type": "Feature",
  "properties": {
    "iso:country":"TR",
    "sg:address":"Perpa Tic. Mrk. A Blok Kat:11 No:1469",
    "sg:city":"Okmeydani",
    "sg:classifiers":[
        {
            "category":"Home & Garden",
            "subcategory":"Household Appliances",
            "type":"Retail Goods"
        }
    ],
    "sg:phone":"+90 212222703522088",
    "sg:postcode":"43050",
    "sg:province":"Istanbul",
    "sg:tags":[
        "conditioner",
        "air"
    ],
    "wof:name":"Botes Klima Taahh?t San. Tic. Ltd. Sti.",
    "wof:placetype":"venue"
},
  "geometry": {"coordinates":[28.9759254456,41.0123786926],"type":"Point"}
}