{
  "type": "Feature",
  "properties": {
    "iso:country":"TR",
    "sg:address":"Adnan Kahveci Bul. No:85 Bah?lievler",
    "sg:city":"Alsancak",
    "sg:orig_category":"Orthopedical Materials",
    "sg:phone":"+90 212 441 2777",
    "sg:postcode":"01365",
    "sg:province":"Istanbul",
    "wof:name":"Ortem Ortopedi Saglik Gere?leri",
    "wof:placetype":"venue"
},
  "geometry": {"coordinates":[28.8635597229,41.001991272],"type":"Point"}
}