{
  "type": "Feature",
  "properties": {
    "addr:full":"Anadolu Mah. Aticilar Cad. 42 Topkapi Bursa 34020",
    "addr:housenumber":"42",
    "addr:postcode":"34020",
    "addr:street":"Mah. Aticilar Cad.",
    "iso:country":"TR",
    "sg:address":"Anadolu Mah. Aticilar Cad. 42",
    "sg:city":"Topkapi",
    "sg:classifiers":[
        {
            "category":"Wholesale",
            "subcategory":"Auto Parts",
            "type":"Manufacturing & Wholesale Goods"
        }
    ],
    "sg:phone":"+90 2243619707729",
    "sg:postcode":"34020",
    "sg:province":"Bursa",
    "sg:tags":[
        "spare"
    ],
    "wof:name":"Destek Otomotiv Yan Sanayi Ve Ticaret A.s.",
    "wof:placetype":"venue"
},
  "geometry": {"coordinates":[29.0586109161,40.1844291687],"type":"Point"}
}