{
  "type": "Feature",
  "properties": {
    "iso:country":"TR",
    "sg:address":"Ikitelli Organize Sanayi B?gesi Isd? San.sit.1.blok No:20",
    "sg:city":"Ikitelli/K\u00fc\u00e7\u00fck\u00e7ekmece",
    "sg:classifiers":[
        {
            "category":"Banks & Credit Unions",
            "subcategory":"Atm",
            "type":"Services"
        }
    ],
    "sg:phone":"+90 21248590151",
    "sg:postcode":"34670",
    "sg:province":"Istanbul",
    "sg:tags":[
        "armature",
        "gas"
    ],
    "sg:website":"cermetal.com",
    "wof:name":"Cer Metal Enjeksiyon Sanayi",
    "wof:placetype":"venue"
},
  "geometry": {"coordinates":[28.9759254456,41.0123786926],"type":"Point"}
}