{
  "type": "Feature",
  "properties": {
    "addr:full":"Cumhuriyet Mah.2.cad.no:45 Beylikd??sanayi Sitesi Beykent B???kmece Istanbul 34900",
    "addr:housenumber":"45;? ?;? ? ?",
    "addr:postcode":"34900",
    "addr:street":"Cumhuriyet Mah.2.Cad.No;Sanayi Sitesi Beykent B",
    "iso:country":"TR",
    "sg:address":"Cumhuriyet Mah.2.cad.no:45 Beylikd??sanayi Sitesi Beykent",
    "sg:city":"B???kmece",
    "sg:classifiers":[
        {
            "category":"Building & Trades",
            "subcategory":"Electrical",
            "type":"Services"
        }
    ],
    "sg:phone":"+90 212 873 3990",
    "sg:postcode":"34900",
    "sg:province":"Istanbul",
    "sg:tags":[
        "equipment",
        "electric"
    ],
    "sg:website":"aymet.net",
    "wof:name":"Aymet Makina Ve Rezistans Sanayi Tic.ltd.sti",
    "wof:placetype":"venue"
},
  "geometry": {"coordinates":[28.9861831665,41.0408554077],"type":"Point"}
}