{
  "type": "Feature",
  "properties": {
    "iso:country":"TR",
    "sg:address":"Perpa Tic. Merk. K:4-5 No:219 Okmeydani",
    "sg:city":"\u00dcsk\u00fcdar",
    "sg:classifiers":[
        {
            "category":"Home & Garden",
            "subcategory":"Kitchen Supply",
            "type":"Retail Goods"
        }
    ],
    "sg:phone":"+90 212 222 7111",
    "sg:postcode":"34674",
    "sg:province":"Istanbul",
    "sg:tags":[
        "fire",
        "extinguisher"
    ],
    "wof:name":"Delta Yangin & G?v. Hizm. San. Tic. Ltd. Sti.",
    "wof:placetype":"venue"
},
  "geometry": {"coordinates":[29.0278072357,41.0316886902],"type":"Point"}
}