{
  "type": "Feature",
  "properties": {
    "addr:full":"Fevzipasa Mah. 55. Sk. No.10 Sisli Adana 80260",
    "addr:housenumber":"55",
    "addr:postcode":"80260",
    "addr:street":"Fevzipasa Mah.;Sk. No.10 Sisli",
    "iso:country":"TR",
    "sg:address":"Fevzipasa Mah. 55. Sk. No.10",
    "sg:city":"Sisli",
    "sg:classifiers":[
        {
            "category":"Freight",
            "type":"Transportation"
        }
    ],
    "sg:phone":"+90 322429272728",
    "sg:postcode":"80260",
    "sg:province":"Adana",
    "sg:tags":[
        "packing",
        "industry"
    ],
    "wof:name":"Yilsan Plastik Ambalaj San. Ve Tic. A.s.",
    "wof:placetype":"venue"
},
  "geometry": {"coordinates":[35.3103103638,36.9742126465],"type":"Point"}
}