{
  "type": "Feature",
  "properties": {
    "iso:country":"TR",
    "sg:address":"Bagdat Cad 469",
    "sg:city":"Suadiye",
    "sg:classifiers":[
        {
            "category":"Banks & Credit Unions",
            "subcategory":"Bank",
            "type":"Services"
        }
    ],
    "sg:phone":"+90 216 411 7353",
    "sg:postcode":"34740",
    "sg:province":"81070",
    "wof:name":"Kentbank As",
    "wof:placetype":"venue"
},
  "geometry": {"coordinates":[29.080339,40.960392],"type":"Point"}
}