{
  "type": "Feature",
  "properties": {
    "iso:country":"TR",
    "sg:address":"Saglik Sok. 19/14 Sihhiye",
    "sg:city":"1.levent",
    "sg:classifiers":[
        {
            "category":"Wholesale",
            "subcategory":"Machinery & Supplies",
            "type":"Manufacturing & Wholesale Goods"
        }
    ],
    "sg:phone":"+90 312 435 0727",
    "sg:postcode":"34340",
    "sg:province":"Ankara",
    "sg:tags":[
        "laboratory",
        "equipment"
    ],
    "wof:name":"Atomika Teknik Cihazlar Ltd.sti.",
    "wof:placetype":"venue"
},
  "geometry": {"coordinates":[32.8823738098,39.903465271],"type":"Point"}
}