{
  "type": "Feature",
  "properties": {
    "addr:full":"Yalniz Selvi Caddesi No:9 Soganlik Kartal Istanbul 81440",
    "addr:postcode":"81440",
    "addr:street":"Selvi Caddesi No 9 Soganlik",
    "iso:country":"TR",
    "sg:address":"Yalniz Selvi Caddesi No:9 Soganlik",
    "sg:city":"Kartal",
    "sg:classifiers":[
        {
            "category":"Manufacturing",
            "subcategory":"Building Materials",
            "type":"Manufacturing & Wholesale Goods"
        }
    ],
    "sg:phone":"+90 216 452 5010",
    "sg:postcode":"81440",
    "sg:province":"Istanbul",
    "sg:tags":[
        "lifts-elevators"
    ],
    "wof:name":"Yeterlift Asans? San. Ve Tic. Ltd. Sti.",
    "wof:placetype":"venue"
},
  "geometry": {"coordinates":[29.2035064697,40.8946838379],"type":"Point"}
}