{
  "type": "Feature",
  "properties": {
    "iso:country":"TR",
    "sg:address":"Yeni Yalova Yolu No.299",
    "sg:city":"Cevizlibag",
    "sg:classifiers":[
        {
            "category":"Airport",
            "subcategory":"International",
            "type":"Transportation"
        }
    ],
    "sg:phone":"+90 224 273 4802",
    "sg:postcode":"57700",
    "sg:province":"Bursa",
    "wof:name":"Bursa Birlik Nakliyat Ve Ticaret A.s.",
    "wof:placetype":"venue"
},
  "geometry": {"coordinates":[29.0621795654,40.2271881104],"type":"Point"}
}