{
  "type": "Feature",
  "properties": {
    "addr:full":"129/3sk No 23 4. Sn.st. Bornova Izmir 35040",
    "addr:housenumber":"129 / 3sk no 23 4;bornova",
    "addr:postcode":"35040",
    "addr:street":"Sn.St.",
    "iso:country":"TR",
    "sg:address":"129/3sk No 23 4. Sn.st.",
    "sg:city":"Bornova",
    "sg:classifiers":[
        {
            "category":"Building & Trades",
            "subcategory":"Construction",
            "type":"Services"
        }
    ],
    "sg:phone":"+90 232 375 6176",
    "sg:postcode":"35040",
    "sg:province":"Izmir",
    "sg:tags":[
        "tank-boiler-heating",
        "unit"
    ],
    "wof:name":"Al?elik End.?elik Konst.taa.san.tic.ltd.sti.",
    "wof:placetype":"venue"
},
  "geometry": {"coordinates":[27.1423015594,38.4251480103],"type":"Point"}
}