{
  "type": "Feature",
  "properties": {
    "addr:full":"Baglarbasi Cad.no:14 Gaziosmanpasa Merkez Istanbul 46100",
    "addr:housenumber":"14",
    "addr:postcode":"46100",
    "addr:street":"Gaziosmanpasa",
    "iso:country":"TR",
    "sg:address":"Baglarbasi Cad.no:14 Gaziosmanpasa",
    "sg:city":"Merkez",
    "sg:classifiers":[
        {
            "category":"Shopping",
            "subcategory":"Crafts & Fabrics",
            "type":"Retail Goods"
        }
    ],
    "sg:phone":"+90 212 417 7850",
    "sg:postcode":"46100",
    "sg:province":"Istanbul",
    "sg:tags":[
        "textile",
        "-leather",
        "exporter"
    ],
    "wof:name":"Aydinlar Intarnational",
    "wof:placetype":"venue"
},
  "geometry": {"coordinates":[28.9861831665,41.0408554077],"type":"Point"}
}