{
  "type": "Feature",
  "properties": {
    "iso:country":"TR",
    "sg:address":"Ivedik Caddesi 448",
    "sg:city":"Demetevler",
    "sg:classifiers":[
        {
            "category":"Banks & Credit Unions",
            "subcategory":"Bank",
            "type":"Services"
        }
    ],
    "sg:phone":"+90 312 346 1921",
    "sg:postcode":"01180",
    "sg:province":"06200",
    "wof:name":"Etibank Bao",
    "wof:placetype":"venue"
},
  "geometry": {"coordinates":[32.789925,39.968151],"type":"Point"}
}