{
  "type": "Feature",
  "properties": {
    "addr:full":"129. /16 Sk. No:28 4. San. Sit. \u00dcmraniye Izmir",
    "addr:housenumber":"129 / 16;4",
    "addr:street":"Sk. No 28;San. Sit.",
    "iso:country":"TR",
    "sg:address":"129. /16 Sk. No:28 4. San. Sit.",
    "sg:city":"\u00dcmraniye",
    "sg:classifiers":[
        {
            "category":"Home & Garden",
            "subcategory":"Hardware",
            "type":"Retail Goods"
        }
    ],
    "sg:phone":"+90 232 339 2297",
    "sg:province":"Izmir",
    "sg:tags":[
        "generator",
        "power"
    ],
    "wof:name":"Emsas Elektrik Malz. San. A.s.",
    "wof:placetype":"venue"
},
  "geometry": {"coordinates":[27.1296863556,38.4186973572],"type":"Point"}
}