{
  "type": "Feature",
  "properties": {
    "addr:full":"Meclis-i Mebusan Cad 137 Istanbul 80040",
    "addr:housenumber":"137",
    "addr:postcode":"80040",
    "addr:street":"Mebusan Cad",
    "iso:country":"TR",
    "sg:address":"Meclis-i Mebusan Cad 137",
    "sg:city":"Istanbul",
    "sg:classifiers":[
        {
            "category":"Banks & Credit Unions",
            "subcategory":"Bank",
            "type":"Services"
        }
    ],
    "sg:phone":"+90 212 251 2792",
    "sg:province":"80040",
    "wof:name":"T?kiye Sinai, Kalkinma Bankasi As",
    "wof:placetype":"venue"
},
  "geometry": {"coordinates":[28.989826,41.032051],"type":"Point"}
}