{
  "type": "Feature",
  "properties": {
    "iso:country":"TR",
    "sg:address":"Caferpasa Caddesi G?l Sitesi No:8",
    "sg:city":"Bodrum",
    "sg:classifiers":[
        {
            "category":"Travel",
            "subcategory":"Travel Agent",
            "type":"Entertainment"
        }
    ],
    "sg:phone":"+90 2523165632313",
    "sg:postcode":"48400",
    "sg:province":"Mugla",
    "sg:tags":[
        "agency",
        "tourism"
    ],
    "wof:name":"Borda Turizm",
    "wof:placetype":"venue"
},
  "geometry": {"coordinates":[28.3628406525,37.215675354],"type":"Point"}
}