{
  "type": "Feature",
  "properties": {
    "addr:full":"I?eler Mevkii No:5 Tuzla Istanbul 01900",
    "addr:housenumber":"?",
    "addr:postcode":"01900",
    "addr:street":"I;Eler Mevkii No 5",
    "iso:country":"TR",
    "sg:address":"I?eler Mevkii No:5",
    "sg:city":"Tuzla",
    "sg:classifiers":[
        {
            "category":"Marine",
            "type":"Transportation"
        }
    ],
    "sg:phone":"+90 216 395 2304",
    "sg:postcode":"01900",
    "sg:province":"Istanbul",
    "sg:tags":[
        "equipment",
        "maritime"
    ],
    "wof:name":"Yildirim Gemi Insaat San. A.s.",
    "wof:placetype":"venue"
},
  "geometry": {"coordinates":[28.9861831665,41.0408554077],"type":"Point"}
}