{
  "type": "Feature",
  "properties": {
    "addr:full":"T?be Meydani Cankaya Nevsehir 07080",
    "addr:postcode":"07080",
    "addr:street":"T",
    "iso:country":"TR",
    "sg:address":"T?be Meydani",
    "sg:city":"Cankaya",
    "sg:orig_category":"Hotels: Motels",
    "sg:phone":"+90 384 213 7300",
    "sg:postcode":"07080",
    "sg:province":"Nevsehir",
    "wof:name":"Kapadokya Hotel",
    "wof:placetype":"venue"
},
  "geometry": {"coordinates":[34.7110939026,38.6325645447],"type":"Point"}
}