{
  "type": "Feature",
  "properties": {
    "addr:full":"Mevlana Halit Mah. Hatboyu Cad. Esref -4 Apt.b-104 Iskenderun Diyarbakir 31200",
    "addr:housenumber":"-4 apt.b-104",
    "addr:postcode":"31200",
    "addr:street":"Halit Mah. Hatboyu Cad. Esref;Diyarbakir",
    "iso:country":"TR",
    "sg:address":"Mevlana Halit Mah. Hatboyu Cad. Esref -4 Apt.b-104",
    "sg:city":"Iskenderun",
    "sg:classifiers":[
        {
            "category":"Wholesale",
            "subcategory":"Petroleum",
            "type":"Manufacturing & Wholesale Goods"
        }
    ],
    "sg:phone":"+90 412 233 5888",
    "sg:postcode":"31200",
    "sg:province":"Diyarbakir",
    "wof:name":"Er-ba Petrol,turizm,ins.tic.san.ltd.sti.",
    "wof:placetype":"venue"
},
  "geometry": {"coordinates":[40.2253341675,37.9158096313],"type":"Point"}
}