{
  "type": "Feature",
  "properties": {
    "addr:full":"Haci Mimi Mh. Kemeralti Cd. No:23 Karak? Bagcilar Istanbul 34560",
    "addr:housenumber":"no 23;?",
    "addr:postcode":"34560",
    "addr:street":"Mh. Kemeralti Cd.;Karak",
    "iso:country":"TR",
    "sg:address":"Haci Mimi Mh. Kemeralti Cd. No:23 Karak?",
    "sg:city":"Bagcilar",
    "sg:classifiers":[
        {
            "category":"Shopping",
            "subcategory":"Bicycles & Sporting Goods",
            "type":"Retail Goods"
        }
    ],
    "sg:phone":"+90 212 245 4855",
    "sg:postcode":"34560",
    "sg:province":"Istanbul",
    "sg:tags":[
        "equipment",
        "marine",
        "hunting"
    ],
    "wof:name":"?etinkaya Avcilik Malz. San. Tic. Ltd. Sti.",
    "wof:placetype":"venue"
},
  "geometry": {"coordinates":[28.9861831665,41.0408554077],"type":"Point"}
}