{
  "type": "Feature",
  "properties": {
    "iso:country":"TR",
    "sg:address":"Altinova Mah.kader Cad.no:23-27",
    "sg:city":"Ikitelli",
    "sg:classifiers":[
        {
            "category":"Wholesale",
            "subcategory":"Auto Parts",
            "type":"Manufacturing & Wholesale Goods"
        }
    ],
    "sg:phone":"+90 224 215 0370",
    "sg:postcode":"34306",
    "sg:province":"Bursa",
    "sg:tags":[
        "spare"
    ],
    "wof:name":"Bto Co Ltd.",
    "wof:placetype":"venue"
},
  "geometry": {"coordinates":[29.0586109161,40.1844291687],"type":"Point"}
}