{
  "type": "Feature",
  "properties": {
    "addr:full":"Yeni Sanayi Seker Kismi 9.sok. No:17 Senirkent Kayseri 32600",
    "addr:housenumber":"9.sok no 17",
    "addr:postcode":"32600",
    "addr:street":"Yeni Sanayi Seker Kismi",
    "iso:country":"TR",
    "sg:address":"Yeni Sanayi Seker Kismi 9.sok. No:17",
    "sg:city":"Senirkent",
    "sg:classifiers":[
        {
            "category":"Utilities",
            "subcategory":"Electric",
            "type":"Services"
        }
    ],
    "sg:phone":"+90 352 332 1800",
    "sg:postcode":"32600",
    "sg:province":"Kayseri",
    "sg:tags":[
        "accumulator",
        "-",
        "batery"
    ],
    "wof:name":"Aklas Aku Lastik San.tic. A.s.",
    "wof:placetype":"venue"
},
  "geometry": {"coordinates":[35.489136,38.722576],"type":"Point"}
}