{
  "type": "Feature",
  "properties": {
    "addr:full":"I.m.? 5.blok No:5402 Unkapani Istanbul 55020",
    "addr:housenumber":"no 5402",
    "addr:postcode":"55020",
    "addr:street":"Unkapani Istanbul",
    "iso:country":"TR",
    "sg:address":"I.m.? 5.blok No:5402",
    "sg:city":"Unkapani",
    "sg:classifiers":[
        {
            "category":"Government",
            "subcategory":"Fire Station",
            "type":"Public Place"
        }
    ],
    "sg:phone":"+90 21251105855",
    "sg:postcode":"55020",
    "sg:province":"Istanbul",
    "sg:tags":[
        "decoration"
    ],
    "wof:name":"Serilen Hali Ve Yer D?seme.tic. Ve San. Ltd. Sti.",
    "wof:placetype":"venue"
},
  "geometry": {"coordinates":[28.9103794098,41.0486907959],"type":"Point"}
}