{
  "type": "Feature",
  "properties": {
    "addr:full":"1558 Sok. No:12 Halkapinar Ikitelli/K\u00fc\u00e7\u00fck\u00e7ekmece Izmir 34670",
    "addr:housenumber":"1558;no 12",
    "addr:postcode":"34670",
    "addr:street":"Sok.",
    "iso:country":"TR",
    "sg:address":"1558 Sok. No:12 Halkapinar",
    "sg:city":"Ikitelli/K\u00fc\u00e7\u00fck\u00e7ekmece",
    "sg:classifiers":[
        {
            "category":"Freight",
            "type":"Transportation"
        }
    ],
    "sg:phone":"+90 232 486 3633",
    "sg:postcode":"34670",
    "sg:province":"Izmir",
    "sg:tags":[
        "packing",
        "industry"
    ],
    "wof:name":"Soncag Tarim Orman ?r?nleri",
    "wof:placetype":"venue"
},
  "geometry": {"coordinates":[27.1644477844,38.4340019226],"type":"Point"}
}