{
  "type": "Feature",
  "properties": {
    "iso:country":"TR",
    "sg:address":"Ankara Cad. No: 85",
    "sg:city":"Pendik",
    "sg:classifiers":[
        {
            "category":"Manufacturing",
            "subcategory":"Textiles",
            "type":"Manufacturing & Wholesale Goods"
        }
    ],
    "sg:phone":"+90 216 390 8757",
    "sg:postcode":"34916",
    "sg:province":"Istanbul",
    "sg:tags":[
        "machinery"
    ],
    "wof:name":"Deka Makina Mumessillik A.s.",
    "wof:placetype":"venue"
},
  "geometry": {"coordinates":[29.1905345917,40.8882751465],"type":"Point"}
}