{
  "type": "Feature",
  "properties": {
    "addr:full":"Bandirma Cad. No: 75 Lara Balikesir 07230",
    "addr:housenumber":"75",
    "addr:postcode":"07230",
    "addr:street":"Bandirma Cad. No",
    "iso:country":"TR",
    "sg:address":"Bandirma Cad. No: 75",
    "sg:city":"Lara",
    "sg:classifiers":[
        {
            "category":"Government",
            "subcategory":"Fire Station",
            "type":"Public Place"
        }
    ],
    "sg:phone":"+90 266 265 4590",
    "sg:postcode":"07230",
    "sg:province":"Balikesir",
    "sg:tags":[
        "decoration"
    ],
    "wof:name":"Delta Tasarim",
    "wof:placetype":"venue"
},
  "geometry": {"coordinates":[27.9416179657,39.6835632324],"type":"Point"}
}