{
  "type": "Feature",
  "properties": {
    "iso:country":"TR",
    "sg:address":"Yayla Mah. 1604 Sk. No.3",
    "sg:city":"K???k?ekmece",
    "sg:orig_category":"Non-classified Establishments",
    "sg:phone":"+90 246 218 9579",
    "sg:province":"Isparta",
    "wof:name":"Yariktaslar Tic.ltd.sti.",
    "wof:placetype":"venue"
},
  "geometry": {"coordinates":[30.5437049866,37.7885932922],"type":"Point"}
}