{
  "type": "Feature",
  "properties": {
    "addr:full":"M. Kemalpasa Mh. Atalar Cd. No:1 Sirinevler Eskisehir 15040",
    "addr:housenumber":"no 1",
    "addr:postcode":"15040",
    "addr:street":"Mh. Atalar Cd.;Eskisehir",
    "iso:country":"TR",
    "sg:address":"M. Kemalpasa Mh. Atalar Cd. No:1",
    "sg:city":"Sirinevler",
    "sg:classifiers":[
        {
            "category":"Utilities",
            "subcategory":"Natural Gas",
            "type":"Services"
        }
    ],
    "sg:phone":"+90 222 234 6986",
    "sg:postcode":"15040",
    "sg:province":"Eskisehir",
    "sg:tags":[
        "tank-heating-natural"
    ],
    "wof:name":"Kurun M?hendis. Ltd. Sti.",
    "wof:placetype":"venue"
},
  "geometry": {"coordinates":[30.5154705048,39.7782936096],"type":"Point"}
}