{
  "type": "Feature",
  "properties": {
    "addr:full":"Sariyakup Mah.12 Sok. No:52-53 64100 Adana",
    "addr:housenumber":"no",
    "addr:postcode":"64100",
    "addr:street":"Mah.12 Sok.",
    "iso:country":"TR",
    "sg:address":"Sariyakup Mah.12 Sok. No:52-53",
    "sg:city":"64100",
    "sg:classifiers":[
        {
            "category":"Manufacturing",
            "subcategory":"Leather Goods",
            "type":"Manufacturing & Wholesale Goods"
        }
    ],
    "sg:phone":"+90 322 361 0296",
    "sg:province":"Adana",
    "sg:tags":[
        "chemical"
    ],
    "wof:name":"?zlokmaci Deri Sanayi",
    "wof:placetype":"venue"
},
  "geometry": {"coordinates":[35.331035614,36.9641990662],"type":"Point"}
}