{
  "type": "Feature",
  "properties": {
    "iso:country":"TR",
    "sg:address":"Ankara Karayolu 25 Km.no:158 Kemalpasa",
    "sg:city":"Mersin",
    "sg:classifiers":[
        {
            "category":"Freight",
            "type":"Transportation"
        }
    ],
    "sg:phone":"+90 232 877 0855",
    "sg:postcode":"52750",
    "sg:province":"Izmir",
    "sg:tags":[
        "packing",
        "industry"
    ],
    "wof:name":"Kaplamin A.s",
    "wof:placetype":"venue"
},
  "geometry": {"coordinates":[27.1296863556,38.4186973572],"type":"Point"}
}