{
  "type": "Feature",
  "properties": {
    "iso:country":"TR",
    "sg:address":"Obalar Cad. No:531 Seyhan",
    "sg:city":"Mersin",
    "sg:classifiers":[
        {
            "category":"Manufacturing",
            "subcategory":"Rubber & Plastics",
            "type":"Manufacturing & Wholesale Goods"
        }
    ],
    "sg:phone":"+90 322 435 4363",
    "sg:postcode":"52750",
    "sg:province":"Adana",
    "sg:tags":[
        "industry"
    ],
    "wof:name":"Oguzhan Plastik Sanayi Ticaret Paz.ltd.sti.",
    "wof:placetype":"venue"
},
  "geometry": {"coordinates":[35.3144264221,36.9788703918],"type":"Point"}
}