{
  "type": "Feature",
  "properties": {
    "addr:full":"Kunduracilar Cad.banka Sok. Bahadir Is Hani No:7 Kad\u0131k\u00f6y Trabzon 61420",
    "addr:postcode":"61420",
    "addr:street":"Cad.Banka Sok. Bahadir Is;No 7 Kadikoey Trabzon",
    "iso:country":"TR",
    "sg:address":"Kunduracilar Cad.banka Sok. Bahadir Is Hani No:7",
    "sg:city":"Kad\u0131k\u00f6y",
    "sg:classifiers":[
        {
            "category":"Professional",
            "subcategory":"Computer Services",
            "type":"Services"
        }
    ],
    "sg:phone":"+90 462 326 7850",
    "sg:postcode":"61420",
    "sg:province":"Trabzon",
    "sg:tags":[
        "application",
        "software"
    ],
    "wof:name":"Detay Bilgisayar",
    "wof:placetype":"venue"
},
  "geometry": {"coordinates":[39.7165603638,41.0012931824],"type":"Point"}
}