{
  "type": "Feature",
  "properties": {
    "addr:full":"Gavremoglu Mah. Zenneci Sok. Maide Is Merkezi No:20/11 \u00dcsk\u00fcdar Kayseri 34662",
    "addr:housenumber":"no 20 / 11",
    "addr:postcode":"34662",
    "addr:street":"Gavremoglu Mah. Zenneci Sok. Maide",
    "iso:country":"TR",
    "sg:address":"Gavremoglu Mah. Zenneci Sok. Maide Is Merkezi No:20/11",
    "sg:city":"\u00dcsk\u00fcdar",
    "sg:classifiers":[
        {
            "category":"Banks & Credit Unions",
            "subcategory":"Investment Brokerage",
            "type":"Services"
        }
    ],
    "sg:phone":"+90 352 222 1411",
    "sg:postcode":"34662",
    "sg:province":"Kayseri",
    "sg:tags":[
        "-",
        "export",
        "import"
    ],
    "wof:name":"Censoy Dis Ticaret Ltd.sti.",
    "wof:placetype":"venue"
},
  "geometry": {"coordinates":[36.4393234253,38.2791290283],"type":"Point"}
}