{
  "type": "Feature",
  "properties": {
    "addr:full":"Abide-i Hurriyet Cad. Palazoglu Sok. Kose Apt. No:26728 Sisli Eminonu Istanbul",
    "addr:postcode":"26728",
    "addr:street":"Hurriyet Cad. Palazoglu Sok.;No",
    "iso:country":"TR",
    "sg:address":"Abide-i Hurriyet Cad. Palazoglu Sok. Kose Apt. No:26728 Sisli",
    "sg:city":"Eminonu",
    "sg:classifiers":[
        {
            "category":"Utilities",
            "subcategory":"Electric",
            "type":"Services"
        }
    ],
    "sg:phone":"+90 212 233 4513",
    "sg:province":"Istanbul",
    "sg:tags":[
        "accumulator",
        "-",
        "batery"
    ],
    "wof:name":"Enerji 2000 A.s.",
    "wof:placetype":"venue"
},
  "geometry": {"coordinates":[28.987904,41.058693],"type":"Point"}
}