{
  "type": "Feature",
  "properties": {
    "iso:country":"TR",
    "sg:address":"Ibrahim Karaoglanoglu Cad. Cekimser Sk. No.27 Seyrantepe, 4.levent",
    "sg:city":"Isikkent",
    "sg:classifiers":[
        {
            "category":"Wholesale",
            "subcategory":"Plants",
            "type":"Manufacturing & Wholesale Goods"
        }
    ],
    "sg:phone":"+90 212 281 5246",
    "sg:postcode":"32100",
    "sg:province":"Istanbul",
    "sg:tags":[
        "natural",
        "spice"
    ],
    "wof:name":"Dogus Kumanya Gida Dagitim Ve Paz.ltd.sti.",
    "wof:placetype":"venue"
},
  "geometry": {"coordinates":[28.992867,41.097549],"type":"Point"}
}