{
  "type": "Feature",
  "properties": {
    "iso:country":"TR",
    "sg:address":"Yakut Sok. Yakut Psj.no:7/2",
    "sg:city":"Bakirkoy",
    "sg:classifiers":[
        {
            "category":"Building & Trades",
            "subcategory":"Electrical",
            "type":"Services"
        }
    ],
    "sg:phone":"+90 212 542 1999",
    "sg:postcode":"35790",
    "sg:province":"Istanbul",
    "sg:tags":[
        "equipment",
        "lighting"
    ],
    "wof:name":"Kandil Aydinlatma San.tic.ltd.sti.",
    "wof:placetype":"venue"
},
  "geometry": {"coordinates":[28.9759254456,41.0123786926],"type":"Point"}
}