{
  "type": "Feature",
  "properties": {
    "addr:full":"Ahmet Rasim Sk.no:14 ?ankaya Etiler Ankara 07010",
    "addr:housenumber":"14 ?",
    "addr:postcode":"07010",
    "addr:street":"Sk.No;Ankaya Etiler",
    "iso:country":"TR",
    "sg:address":"Ahmet Rasim Sk.no:14 ?ankaya",
    "sg:city":"Etiler",
    "sg:classifiers":[
        {
            "category":"Government",
            "subcategory":"Embassy",
            "type":"Public Place"
        }
    ],
    "sg:phone":"+90 312 439 2740",
    "sg:postcode":"07010",
    "sg:province":"Ankara",
    "sg:tags":[
        "foreign"
    ],
    "wof:name":"?zbekistan B?y?kel?iligi",
    "wof:placetype":"venue"
},
  "geometry": {"coordinates":[32.854473114,39.8835334778],"type":"Point"}
}