{
  "type": "Feature",
  "properties": {
    "iso:country":"TR",
    "sg:address":"Kemaliye Mah. Turanli Sok. No: 42",
    "sg:city":"Hendek",
    "sg:classifiers":[
        {
            "category":"Food & Beverages",
            "subcategory":"Candy",
            "type":"Retail Goods"
        }
    ],
    "sg:phone":"+90 264 614 5367",
    "sg:postcode":"21950",
    "sg:province":"Sakarya",
    "sg:tags":[
        "biscuit-chocolate-candy"
    ],
    "wof:name":"Hastat",
    "wof:placetype":"venue"
},
  "geometry": {"coordinates":[41.947128,37.925163],"type":"Point"}
}