{
  "type": "Feature",
  "properties": {
    "iso:country":"TR",
    "sg:address":"Arapseyh Cad. No:27/d",
    "sg:city":"Bostanci",
    "sg:classifiers":[
        {
            "category":"Home & Garden",
            "subcategory":"Building Materials",
            "type":"Retail Goods"
        }
    ],
    "sg:phone":"+90 346 223 3404",
    "sg:postcode":"25900",
    "sg:province":"Sivas",
    "sg:tags":[
        "stone",
        "natural",
        "marble"
    ],
    "wof:name":"Emmioglu Mermer Madencilik Insaat San. Ve Tic. A.s.",
    "wof:placetype":"venue"
},
  "geometry": {"coordinates":[37.0182571411,39.750087738],"type":"Point"}
}