{
  "type": "Feature",
  "properties": {
    "iso:country":"TR",
    "sg:address":"Ataturk Cad. No:382 Bedirhan",
    "sg:city":"Sel?klu",
    "sg:classifiers":[
        {
            "category":"Wholesale",
            "subcategory":"Medical Equipment & Supplies",
            "type":"Manufacturing & Wholesale Goods"
        }
    ],
    "sg:phone":"+90 464 213 0283",
    "sg:postcode":"42060",
    "sg:province":"Rize",
    "wof:name":"Zafer Medikal Ve Saglik Hizmetleri Ltd.sti.",
    "wof:placetype":"venue"
},
  "geometry": {"coordinates":[40.525718689,41.0242195129],"type":"Point"}
}