{
  "type": "Feature",
  "properties": {
    "iso:country":"TR",
    "sg:address":"In??cd. No:47 Kesan",
    "sg:city":"Kad\u0131k\u00f6y",
    "sg:classifiers":[
        {
            "category":"Organizations",
            "subcategory":"Membership Organization",
            "type":"Services"
        }
    ],
    "sg:phone":"+90 284 714 6395",
    "sg:postcode":"34722",
    "sg:province":"Edirne",
    "wof:name":"Kesan Zihinsel Bed. Ozurluler Day. Dernegi",
    "wof:placetype":"venue"
},
  "geometry": {"coordinates":[26.554069519,41.6770401001],"type":"Point"}
}