{
  "type": "Feature",
  "properties": {
    "iso:country":"TR",
    "sg:address":"Ankara Cad 34",
    "sg:city":"Kartal",
    "sg:classifiers":[
        {
            "category":"Banks & Credit Unions",
            "subcategory":"Bank",
            "type":"Services"
        }
    ],
    "sg:phone":"+90 216 306 4696",
    "sg:postcode":"46000",
    "sg:province":"81410",
    "wof:name":"Demirbank Tas",
    "wof:placetype":"venue"
},
  "geometry": {"coordinates":[29.268559,40.89883],"type":"Point"}
}