{
  "type": "Feature",
  "properties": {
    "addr:full":"Vatan Cad. Vatan Palas Apt. No:12 Aksaray Fatih Istanbul 01740",
    "addr:postcode":"01740",
    "addr:street":"Vatan Cad.",
    "iso:country":"TR",
    "sg:address":"Vatan Cad. Vatan Palas Apt. No:12 Aksaray",
    "sg:city":"Fatih",
    "sg:classifiers":[
        {
            "category":"Wholesale",
            "subcategory":"Medical Equipment & Supplies",
            "type":"Manufacturing & Wholesale Goods"
        }
    ],
    "sg:phone":"+90 212 531 8256",
    "sg:postcode":"01740",
    "sg:province":"Istanbul",
    "sg:tags":[
        "material"
    ],
    "wof:name":"Medart Hastane Bilgi Sistemleri A.s.",
    "wof:placetype":"venue"
},
  "geometry": {"coordinates":[28.9759254456,41.0123786926],"type":"Point"}
}