{
  "type": "Feature",
  "properties": {
    "iso:country":"TR",
    "sg:address":"Acipayam Yolu ?z. 3. Km.",
    "sg:city":"Merkez",
    "sg:classifiers":[
        {
            "category":"Home & Garden",
            "subcategory":"Kitchen Supply",
            "type":"Retail Goods"
        }
    ],
    "sg:phone":"+90 258 266 0960",
    "sg:postcode":"20100",
    "sg:province":"Denizli",
    "sg:tags":[
        "steel",
        "utensil"
    ],
    "wof:name":"Emsan Besyildiz ?elik San. Tic. A.s.",
    "wof:placetype":"venue"
},
  "geometry": {"coordinates":[29.083082,37.789497],"type":"Point"}
}