{
  "type": "Feature",
  "properties": {
    "addr:full":"Karacakaya Cad. 148 Siteler 06160 07070",
    "addr:housenumber":"148",
    "addr:postcode":"06160 07070",
    "addr:street":"Karacakaya Cad.",
    "iso:country":"TR",
    "sg:address":"Karacakaya Cad. 148",
    "sg:city":"Siteler",
    "sg:classifiers":[
        {
            "category":"Banks & Credit Unions",
            "subcategory":"Bank",
            "type":"Services"
        }
    ],
    "sg:phone":"+90 312 348 5842",
    "sg:postcode":"07070",
    "sg:province":"06160",
    "wof:name":"Etibank Bao",
    "wof:placetype":"venue"
},
  "geometry": {"coordinates":[32.902164,39.957291],"type":"Point"}
}