{
  "type": "Feature",
  "properties": {
    "addr:full":"Cemal G. Bulv. Baskent Apt. No:69 D:16 Cankaya Beyoglu Ankara 46810",
    "addr:housenumber":"69 d 16",
    "addr:postcode":"46810",
    "addr:street":"Cemal G. Bulv. Baskent Apt. No;Cankaya Beyoglu",
    "iso:country":"TR",
    "sg:address":"Cemal G. Bulv. Baskent Apt. No:69 D:16 Cankaya",
    "sg:city":"Beyoglu",
    "sg:classifiers":[
        {
            "category":"Building & Trades",
            "subcategory":"Construction",
            "type":"Services"
        }
    ],
    "sg:phone":"+90 312 362 0443",
    "sg:postcode":"46810",
    "sg:province":"Ankara",
    "sg:tags":[
        "foundation"
    ],
    "wof:name":"Sosyal Hizm. Arast. Belgeleme Ve Egitme Vakfi",
    "wof:placetype":"venue"
},
  "geometry": {"coordinates":[32.8560333252,39.9438743591],"type":"Point"}
}