{
  "type": "Feature",
  "properties": {
    "iso:country":"TR",
    "sg:address":"Yeni San. Sitesi 18.carsi No.17",
    "sg:city":"Sariyer",
    "sg:classifiers":[
        {
            "category":"Utilities",
            "subcategory":"Electric",
            "type":"Services"
        }
    ],
    "sg:phone":"+90 344 236 3029",
    "sg:postcode":"33740",
    "sg:province":"Kahramanmaras",
    "sg:tags":[
        "energy",
        "solar"
    ],
    "wof:name":"Paksu Gunes Enerjisi Sistemleri",
    "wof:placetype":"venue"
},
  "geometry": {"coordinates":[36.928299,37.589401],"type":"Point"}
}