{
  "type": "Feature",
  "properties": {
    "addr:full":"Kemerburgaz. C. No.88 Kagithane Istanbul 34406",
    "addr:postcode":"34406",
    "addr:street":"C. No.88 Kagithane",
    "iso:country":"TR",
    "sg:address":"Kemerburgaz. C. No.88",
    "sg:city":"Kagithane",
    "sg:classifiers":[
        {
            "category":"Food & Beverages",
            "subcategory":"Meat & Fish",
            "type":"Retail Goods"
        }
    ],
    "sg:phone":"+90 212 294 7800",
    "sg:postcode":"34406",
    "sg:province":"Istanbul",
    "sg:tags":[
        "product"
    ],
    "wof:name":"Besler Et Gida San. A.s.",
    "wof:placetype":"venue"
},
  "geometry": {"coordinates":[28.9707660675,41.0864982605],"type":"Point"}
}