{
  "type": "Feature",
  "properties": {
    "addr:full":"Semsettin Gunaltay Cad. No:175/25 Kadikoy- Erenkoy Istanbul 07060",
    "addr:housenumber":"175 / 25",
    "addr:postcode":"07060",
    "addr:street":"Gunaltay Cad. No;Kadikoy Erenkoy",
    "iso:country":"TR",
    "sg:address":"Semsettin Gunaltay Cad. No:175/25 Kadikoy-",
    "sg:city":"Erenkoy",
    "sg:classifiers":[
        {
            "category":"Home & Garden",
            "subcategory":"Household Appliances",
            "type":"Retail Goods"
        }
    ],
    "sg:phone":"+90 216 360 6365",
    "sg:postcode":"07060",
    "sg:province":"Istanbul",
    "sg:tags":[
        "conditioner",
        "air"
    ],
    "wof:name":"Aktif Muhendislik Taah.tic.san.ltd.sti.",
    "wof:placetype":"venue"
},
  "geometry": {"coordinates":[29.0789089203,40.9772605896],"type":"Point"}
}