{
  "type": "Feature",
  "properties": {
    "iso:country":"TR",
    "sg:address":"Burak Reis Cad.no:14 Camdibi-bornova",
    "sg:city":"Hadimk?",
    "sg:classifiers":[
        {
            "category":"Home & Garden",
            "subcategory":"Kitchen Supply",
            "type":"Retail Goods"
        }
    ],
    "sg:phone":"+90 232 435 2643",
    "sg:postcode":"34555",
    "sg:province":"Izmir",
    "sg:tags":[
        "wardrobe"
    ],
    "wof:name":"Domdoek",
    "wof:placetype":"venue"
},
  "geometry": {"coordinates":[27.1296863556,38.4186973572],"type":"Point"}
}