{
  "type": "Feature",
  "properties": {
    "iso:country":"TR",
    "sg:address":"2.sanayi Sitesi138 Sok No:9",
    "sg:city":"Merkez",
    "sg:orig_category":"Automat Industry",
    "sg:phone":"+90 258 371 9840",
    "sg:postcode":"20200",
    "sg:province":"Denizli",
    "wof:name":"Beskardes Otoboya Kaporta",
    "wof:placetype":"venue"
},
  "geometry": {"coordinates":[29.0788803101,37.7851867676],"type":"Point"}
}