{
  "type": "Feature",
  "properties": {
    "addr:full":"Cobancesme Mah. Gencosman Sok. No:4/1 Yenibosna Istanbul 43270",
    "addr:housenumber":"no 4 / 1",
    "addr:postcode":"43270",
    "addr:street":"Cobancesme Mah. Gencosman Sok.",
    "iso:country":"TR",
    "sg:address":"Cobancesme Mah. Gencosman Sok. No:4/1",
    "sg:city":"Yenibosna",
    "sg:classifiers":[
        {
            "category":"Shopping",
            "subcategory":"Clothing, Apparel, & Fashions",
            "type":"Retail Goods"
        }
    ],
    "sg:phone":"+90 212 503 9414",
    "sg:postcode":"43270",
    "sg:province":"Istanbul",
    "sg:tags":[
        "ready",
        "wear"
    ],
    "wof:name":"Demo Tekstil Ltd.sti.",
    "wof:placetype":"venue"
},
  "geometry": {"coordinates":[28.8245315552,41.0008583069],"type":"Point"}
}