{
  "type": "Feature",
  "properties": {
    "iso:country":"TR",
    "sg:address":"Hamdi Kutlar Cad.no:10",
    "sg:city":"Osman Gazi",
    "sg:classifiers":[
        {
            "category":"Shopping",
            "subcategory":"Shoes",
            "type":"Retail Goods"
        }
    ],
    "sg:phone":"+90 342 231 8082",
    "sg:postcode":"16240",
    "sg:province":"Gaziantep",
    "wof:name":"Peba Poliuretan Terlik Ayakk. San.a.s",
    "wof:placetype":"venue"
},
  "geometry": {"coordinates":[37.392616,37.063236],"type":"Point"}
}