{
  "type": "Feature",
  "properties": {
    "iso:country":"TR",
    "sg:address":"23 Nisan Cad. No:71,",
    "sg:city":"Buyukada",
    "sg:orig_category":"Hotels: Motels",
    "sg:phone":"+90 216 382 6950",
    "sg:postcode":"28300",
    "sg:province":"Istanbul",
    "wof:name":"Splendid Hotel",
    "wof:placetype":"venue"
},
  "geometry": {"coordinates":[29.237695694,40.878490448],"type":"Point"}
}