{
  "type": "Feature",
  "properties": {
    "addr:full":"Yakacik Yanyol Senem Sok No: 11 Kartal Istanbul Kartal Istanbul 34876",
    "addr:housenumber":"no 11",
    "addr:postcode":"34876",
    "addr:street":"Senem Sok",
    "iso:country":"TR",
    "sg:address":"Yakacik Yanyol Senem Sok No: 11 Kartal Istanbul",
    "sg:city":"Kartal",
    "sg:classifiers":[
        {
            "category":"Freight",
            "type":"Transportation"
        }
    ],
    "sg:phone":"+90 216 377 2855",
    "sg:postcode":"34876",
    "sg:province":"Istanbul",
    "sg:tags":[
        "packing",
        "industry"
    ],
    "wof:name":"Cesur Ambalaj Sanayi",
    "wof:placetype":"venue"
},
  "geometry": {"coordinates":[29.2291717529,40.9073181152],"type":"Point"}
}