{
  "type": "Feature",
  "properties": {
    "addr:full":"Demirciler Cad.no:3 Kesan Edirne 22850",
    "addr:housenumber":"3",
    "addr:postcode":"22850",
    "addr:street":"Cad.No;Edirne",
    "iso:country":"TR",
    "sg:address":"Demirciler Cad.no:3",
    "sg:city":"Kesan",
    "sg:classifiers":[
        {
            "category":"Manufacturing",
            "subcategory":"Food",
            "type":"Manufacturing & Wholesale Goods"
        }
    ],
    "sg:phone":"+90 284 715 0715",
    "sg:postcode":"22850",
    "sg:province":"Edirne",
    "sg:tags":[
        "wholesaler"
    ],
    "wof:name":"Ekomar Birlesik Gida Ltd.sti.",
    "wof:placetype":"venue"
},
  "geometry": {"coordinates":[28.9003944397,41.0073165894],"type":"Point"}
}