{
  "type": "Feature",
  "properties": {
    "addr:full":"Organize San.bol.30.sok. No:5 Selcuklu Burdur 32650",
    "addr:housenumber":"san.bol.30.sok no 5",
    "addr:postcode":"32650",
    "addr:street":"Organize",
    "iso:country":"TR",
    "sg:address":"Organize San.bol.30.sok. No:5",
    "sg:city":"Selcuklu",
    "sg:classifiers":[
        {
            "category":"Wholesale",
            "subcategory":"Machinery & Supplies",
            "type":"Manufacturing & Wholesale Goods"
        }
    ],
    "sg:phone":"+90 248 252 9833",
    "sg:postcode":"32650",
    "sg:province":"Burdur",
    "sg:tags":[
        "agricultural"
    ],
    "wof:name":"Ormak Tarim Makinalari Imalat San. Ve Tic. A.s.",
    "wof:placetype":"venue"
},
  "geometry": {"coordinates":[30.2842998505,37.7192993164],"type":"Point"}
}