{
  "type": "Feature",
  "properties": {
    "iso:country":"TR",
    "sg:address":"Ulu Cad. Cakmak Sok.no:14/b",
    "sg:city":"Sultanbeyli",
    "sg:classifiers":[
        {
            "category":"Wholesale",
            "subcategory":"Auto Parts",
            "type":"Manufacturing & Wholesale Goods"
        }
    ],
    "sg:phone":"+90 224 254 6762",
    "sg:province":"Bursa",
    "sg:tags":[
        "spare"
    ],
    "wof:name":"Kayasan Silecek San.a.s",
    "wof:placetype":"venue"
},
  "geometry": {"coordinates":[29.0398807526,40.1076583862],"type":"Point"}
}