{
  "type": "Feature",
  "properties": {
    "iso:country":"TR",
    "sg:address":"Anafartalar Cad 5",
    "sg:city":"Balikesir",
    "sg:classifiers":[
        {
            "category":"Banks & Credit Unions",
            "subcategory":"Bank",
            "type":"Services"
        }
    ],
    "sg:phone":"+90 266 245 0147",
    "sg:postcode":"10000",
    "sg:province":"10100",
    "wof:name":"Etibank Bao",
    "wof:placetype":"venue"
},
  "geometry": {"coordinates":[27.880211,39.644531],"type":"Point"}
}