{
  "type": "Feature",
  "properties": {
    "addr:full":"Yesil?men Sk. No:75 Demirel Ishani Ihlamur K???kmece Ikitelli Istanbul",
    "addr:housenumber":"75",
    "addr:street":"Sk. No",
    "iso:country":"TR",
    "sg:address":"Yesil?men Sk. No:75 Demirel Ishani Ihlamur",
    "sg:city":"K???kmece Ikitelli",
    "sg:classifiers":[
        {
            "category":"Manufacturing",
            "subcategory":"Wood Products",
            "type":"Manufacturing & Wholesale Goods"
        }
    ],
    "sg:phone":"+90 212 258 8820",
    "sg:province":"Istanbul",
    "sg:tags":[
        "forest"
    ],
    "wof:name":"Orma Orman Mam?l. Entegre San. A.s.",
    "wof:placetype":"venue"
},
  "geometry": {"coordinates":[28.9759254456,41.0123786926],"type":"Point"}
}