{
  "type": "Feature",
  "properties": {
    "addr:full":"Tren Istasyonu Karsisi Gaziemir Izmir 35410",
    "addr:postcode":"35410",
    "addr:street":"Gaziemir",
    "iso:country":"TR",
    "sg:address":"Tren Istasyonu Karsisi",
    "sg:city":"Gaziemir",
    "sg:classifiers":[
        {
            "category":"Freight",
            "type":"Transportation"
        }
    ],
    "sg:phone":"+90 232 251 3434",
    "sg:postcode":"35410",
    "sg:province":"Izmir",
    "sg:tags":[
        "agent",
        "shipping",
        "broker"
    ],
    "wof:name":"Metar Denizcilik A.s.",
    "wof:placetype":"venue"
},
  "geometry": {"coordinates":[27.126474,38.333626],"type":"Point"}
}