{
  "type": "Feature",
  "properties": {
    "iso:country":"TR",
    "sg:address":"Cumhuriyet Cd. No:18/a Elmadag",
    "sg:city":"Kirac-buyukcekmece",
    "sg:orig_category":"Printinh House",
    "sg:phone":"+90 212 231 0236",
    "sg:province":"Istanbul",
    "wof:name":"G?nes Yayinlari A.s.",
    "wof:placetype":"venue"
},
  "geometry": {"coordinates":[29.1838188171,40.9062690735],"type":"Point"}
}