{
  "type": "Feature",
  "properties": {
    "addr:full":"Abdullah C. Sk. No:12 Cankaya Mersin Ankara 52750",
    "addr:housenumber":"sk. no 12",
    "addr:postcode":"52750",
    "addr:street":"C.;Cankaya",
    "iso:country":"TR",
    "sg:address":"Abdullah C. Sk. No:12 Cankaya",
    "sg:city":"Mersin",
    "sg:classifiers":[
        {
            "category":"Wholesale",
            "subcategory":"Home Furnishings",
            "type":"Manufacturing & Wholesale Goods"
        }
    ],
    "sg:phone":"+90 312 238 1133",
    "sg:postcode":"52750",
    "sg:province":"Ankara",
    "sg:tags":[
        "furniture"
    ],
    "wof:name":"Lamelta",
    "wof:placetype":"venue"
},
  "geometry": {"coordinates":[32.8604812622,39.9429283142],"type":"Point"}
}