{
  "type": "Feature",
  "properties": {
    "addr:full":"Dr.refik Saydam Caddesi Dizdar Apartmani No:53 K:6 Tepebasi Beyoglu Istanbul 46810",
    "addr:housenumber":"apartmani no 53 k 6",
    "addr:postcode":"46810",
    "addr:street":"Saydam Caddesi;Tepebasi Beyoglu",
    "iso:country":"TR",
    "sg:address":"Dr.refik Saydam Caddesi Dizdar Apartmani No:53 K:6 Tepebasi",
    "sg:city":"Beyoglu",
    "sg:classifiers":[
        {
            "category":"Travel",
            "subcategory":"Travel Agent",
            "type":"Entertainment"
        }
    ],
    "sg:phone":"+90 23862622388305",
    "sg:postcode":"46810",
    "sg:province":"Istanbul",
    "sg:tags":[
        "agency",
        "tourism"
    ],
    "wof:name":"Oktogon Turizm",
    "wof:placetype":"venue"
},
  "geometry": {"coordinates":[28.9861831665,41.0408554077],"type":"Point"}
}