{
  "type": "Feature",
  "properties": {
    "addr:full":"Nuripasa Mh .63 Sk. No:3 / 9 Zeytinburnu Ikitelli/K\u00fc\u00e7\u00fck\u00e7ekmece Istanbul 34670",
    "addr:housenumber":"63;9",
    "addr:postcode":"34670",
    "addr:street":"Nuripasa Mh;Sk. No 3 /",
    "iso:country":"TR",
    "sg:address":"Nuripasa Mh .63 Sk. No:3 / 9 Zeytinburnu",
    "sg:city":"Ikitelli/K\u00fc\u00e7\u00fck\u00e7ekmece",
    "sg:orig_category":"Aluminium Carpentary",
    "sg:phone":"+90 212 582 6041",
    "sg:postcode":"34670",
    "sg:province":"Istanbul",
    "wof:name":"Ziya Aliminyum Dog .a.s.",
    "wof:placetype":"venue"
},
  "geometry": {"coordinates":[28.9041404724,40.9866485596],"type":"Point"}
}