{
  "type": "Feature",
  "properties": {
    "iso:country":"TR",
    "sg:address":"San. B?g. 10. Cd. No:8",
    "sg:city":"Merkez",
    "sg:classifiers":[
        {
            "category":"Home & Garden",
            "subcategory":"Furniture",
            "type":"Retail Goods"
        }
    ],
    "sg:phone":"+90 352 234 0722",
    "sg:province":"Kayseri",
    "sg:tags":[
        "armchair",
        "sofa"
    ],
    "wof:name":"Sevgi Mobilya",
    "wof:placetype":"venue"
},
  "geometry": {"coordinates":[36.4393234253,38.2791290283],"type":"Point"}
}