{
  "type": "Feature",
  "properties": {
    "iso:country":"TR",
    "sg:address":"Hasan Mevsuf Sok. No: 5",
    "sg:city":"Safranbolu",
    "sg:orig_category":"Hotels: Motels",
    "sg:phone":"+90 286 217 0857",
    "sg:postcode":"78600",
    "sg:province":"?anakkale",
    "wof:name":"Otel Kestambol",
    "wof:placetype":"venue"
},
  "geometry": {"coordinates":[32.7593612671,41.3400802612],"type":"Point"}
}