{
  "type": "Feature",
  "properties": {
    "addr:full":"Des Sitesi 111. Sok.d:12/12 Dudullu Ikitelli/K\u00fc\u00e7\u00fck\u00e7ekmece Istanbul 34670",
    "addr:housenumber":"111;12 / 12",
    "addr:postcode":"34670",
    "addr:street":"Des Sitesi;Dudullu Ikitelli / Kuec\u0327Uekc\u0327Ekmece",
    "iso:country":"TR",
    "sg:address":"Des Sitesi 111. Sok.d:12/12 Dudullu",
    "sg:city":"Ikitelli/K\u00fc\u00e7\u00fck\u00e7ekmece",
    "sg:classifiers":[
        {
            "category":"Manufacturing",
            "subcategory":"Metals",
            "type":"Manufacturing & Wholesale Goods"
        }
    ],
    "sg:phone":"+90 216 466 3395",
    "sg:postcode":"34670",
    "sg:province":"Istanbul",
    "sg:tags":[
        "iron-steel",
        "peoducts"
    ],
    "wof:name":"Sesinoks Paslanmaz Ltd.sti.",
    "wof:placetype":"venue"
},
  "geometry": {"coordinates":[29.1825675964,41.0036888123],"type":"Point"}
}