{
  "type": "Feature",
  "properties": {
    "addr:full":"Cemil T. Cd. No:16-18 ?iftehavuzlar G?g?en Istanbul",
    "addr:housenumber":"no 16-18 ?;? g ?",
    "addr:street":"T. Cd.;Iftehavuzlar G",
    "iso:country":"TR",
    "sg:address":"Cemil T. Cd. No:16-18 ?iftehavuzlar",
    "sg:city":"G?g?en",
    "sg:classifiers":[
        {
            "category":"Wholesale",
            "subcategory":"Home Furnishings",
            "type":"Manufacturing & Wholesale Goods"
        }
    ],
    "sg:phone":"+90 216 360 3443",
    "sg:province":"Istanbul",
    "sg:tags":[
        "furniture"
    ],
    "wof:name":"Fatih Kiral Mobilya Dekor.",
    "wof:placetype":"venue"
},
  "geometry": {"coordinates":[28.9861793518,41.040851593],"type":"Point"}
}