{
  "type": "Feature",
  "properties": {
    "addr:full":"Zafer Mah.1008 Sok.no:35 Kad\u0131k\u00f6y Denizli 34734",
    "addr:housenumber":"35",
    "addr:postcode":"34734",
    "addr:street":"Sok.No",
    "iso:country":"TR",
    "sg:address":"Zafer Mah.1008 Sok.no:35",
    "sg:city":"Kad\u0131k\u00f6y",
    "sg:classifiers":[
        {
            "category":"Shopping",
            "subcategory":"Crafts & Fabrics",
            "type":"Retail Goods"
        }
    ],
    "sg:phone":"+90 258 371 2157",
    "sg:postcode":"34734",
    "sg:province":"Denizli",
    "sg:tags":[
        "textile",
        "-leather",
        "exporter"
    ],
    "wof:name":"Dogan Iplik Sanayi Ltd.",
    "wof:placetype":"venue"
},
  "geometry": {"coordinates":[29.0788803101,37.7851867676],"type":"Point"}
}