{
  "type": "Feature",
  "properties": {
    "iso:country":"TR",
    "sg:address":"Kusdili Cd. No:36 Kadik?",
    "sg:city":"Antakya",
    "sg:classifiers":[
        {
            "category":"Education",
            "subcategory":"Special Training",
            "type":"Public Place"
        }
    ],
    "sg:phone":"+90 216 346 9775",
    "sg:postcode":"31000",
    "sg:province":"Istanbul",
    "sg:tags":[
        "course"
    ],
    "wof:name":"Kusdili Hosteslik Ve Spikerlik Kursu",
    "wof:placetype":"venue"
},
  "geometry": {"coordinates":[29.0331497192,40.9885635376],"type":"Point"}
}