{
  "type": "Feature",
  "properties": {
    "iso:country":"TR",
    "sg:address":"Halk Sok.no:28/14 Kolej",
    "sg:city":"Ba?esehir",
    "sg:classifiers":[
        {
            "category":"Banks & Credit Unions",
            "subcategory":"Financial Services",
            "type":"Services"
        }
    ],
    "sg:phone":"+90 312 431 5510",
    "sg:province":"Ankara",
    "sg:tags":[
        "consultant"
    ],
    "wof:name":"Dunya Musavirlik Ic Ve Dis Ticaret Ltd.",
    "wof:placetype":"venue"
},
  "geometry": {"coordinates":[32.8586387634,39.9262199402],"type":"Point"}
}