{
  "type": "Feature",
  "properties": {
    "iso:country":"TR",
    "sg:address":"Abide-i Hurriyet Cad.mine Apt.no:284/3 Kat:4 D:11 Sisli",
    "sg:city":"K??bakkalk?",
    "sg:classifiers":[
        {
            "category":"Professional",
            "subcategory":"Business Services",
            "type":"Services"
        }
    ],
    "sg:phone":"+90 212 234 4369",
    "sg:province":"Istanbul",
    "wof:name":"2000 Production",
    "wof:placetype":"venue"
},
  "geometry": {"coordinates":[28.987903595,41.0586929321],"type":"Point"}
}