{
  "type": "Feature",
  "properties": {
    "addr:full":"T?el Cad. No.38/301-302 Kut Han Karak? Gebze Istanbul 41400",
    "addr:housenumber":"no.38 / 301-302;?",
    "addr:postcode":"41400",
    "addr:street":"T ? El Cad.",
    "iso:country":"TR",
    "sg:address":"T?el Cad. No.38/301-302 Kut Han Karak?",
    "sg:city":"Gebze",
    "sg:classifiers":[
        {
            "category":"Real Estate",
            "subcategory":"Surveying",
            "type":"Services"
        }
    ],
    "sg:phone":"+90 212 245 4453",
    "sg:postcode":"41400",
    "sg:province":"Istanbul",
    "sg:tags":[
        "adhesive",
        "glue"
    ],
    "wof:name":"Dilsen Demir Celik Hirdavat San.ltd.sti.",
    "wof:placetype":"venue"
},
  "geometry": {"coordinates":[28.9759254456,41.0123786926],"type":"Point"}
}