{
  "type": "Feature",
  "properties": {
    "addr:full":"Yesillik Cad.no:231 Karabaglar Istanbul 44210",
    "addr:housenumber":"231",
    "addr:postcode":"44210",
    "addr:street":"Karabaglar Istanbul",
    "iso:country":"TR",
    "sg:address":"Yesillik Cad.no:231",
    "sg:city":"Karabaglar",
    "sg:classifiers":[
        {
            "category":"Government",
            "subcategory":"Fire Station",
            "type":"Public Place"
        }
    ],
    "sg:phone":"+90 232 264 1875",
    "sg:postcode":"44210",
    "sg:province":"Istanbul",
    "sg:tags":[
        "decoration"
    ],
    "wof:name":"Dekim Dekorasyon Ve Yapi Elemanlari Ltd.sti.",
    "wof:placetype":"venue"
},
  "geometry": {"coordinates":[29.2591953278,40.917049408],"type":"Point"}
}