{
  "type": "Feature",
  "properties": {
    "iso:country":"TR",
    "sg:address":"Molla Feneri Sok. No:37 Cagaloglu Ist.",
    "sg:city":"4.levent",
    "sg:orig_category":"Printinh House",
    "sg:phone":"+90 212 528 6089",
    "sg:province":"Istanbul",
    "wof:name":"Barclub",
    "wof:placetype":"venue"
},
  "geometry": {"coordinates":[28.8206958771,40.9819564819],"type":"Point"}
}