{
  "type": "Feature",
  "properties": {
    "iso:country":"TR",
    "sg:address":"Suyu Kars. No.26",
    "sg:city":"\u00c7orlu",
    "sg:classifiers":[
        {
            "category":"Shopping",
            "subcategory":"Luggage & Leather Goods",
            "type":"Retail Goods"
        }
    ],
    "sg:phone":"+90 282 686 2081",
    "sg:postcode":"59850",
    "sg:province":"Tekirdag",
    "sg:tags":[
        "leather-fur",
        "wear"
    ],
    "wof:name":"Efta Deri A.s.",
    "wof:placetype":"venue"
},
  "geometry": {"coordinates":[27.8592834473,41.1327972412],"type":"Point"}
}