{
  "type": "Feature",
  "properties": {
    "addr:full":"Sanayi Sitesi 508.sok. No:1 Beysehir B. ?ekmece Konya 34400",
    "addr:housenumber":"508.sok no 1",
    "addr:postcode":"34400",
    "addr:street":"Sanayi Sitesi;B.;Ekmece",
    "iso:country":"TR",
    "sg:address":"Sanayi Sitesi 508.sok. No:1 Beysehir",
    "sg:city":"B. ?ekmece",
    "sg:classifiers":[
        {
            "category":"Manufacturing",
            "subcategory":"Metals",
            "type":"Manufacturing & Wholesale Goods"
        }
    ],
    "sg:phone":"+90 332 512 3818",
    "sg:postcode":"34400",
    "sg:province":"Konya",
    "sg:tags":[
        "industry"
    ],
    "wof:name":"Koc Metal Sanayi Ltd.sti.",
    "wof:placetype":"venue"
},
  "geometry": {"coordinates":[32.4990272522,37.8715362549],"type":"Point"}
}