{
  "type": "Feature",
  "properties": {
    "addr:full":"Imes Sanayi Sitesi B Blok 206/18 Y. Dudullu \u00dcmraniye Istanbul",
    "addr:housenumber":"blok 206 / 18 y.",
    "addr:street":"Dudullu",
    "iso:country":"TR",
    "sg:address":"Imes Sanayi Sitesi B Blok 206/18 Y. Dudullu",
    "sg:city":"\u00dcmraniye",
    "sg:classifiers":[
        {
            "category":"Building & Trades",
            "subcategory":"Construction",
            "type":"Services"
        }
    ],
    "sg:phone":"+90 216 364 3038",
    "sg:province":"Istanbul",
    "sg:tags":[
        "industry",
        "mold"
    ],
    "wof:name":"K?b?oglu Kalip Imalat Ve Pres Sanayi",
    "wof:placetype":"venue"
},
  "geometry": {"coordinates":[28.9759254456,41.0123786926],"type":"Point"}
}