{
  "type": "Feature",
  "properties": {
    "addr:full":"Hocapasa Mah. Orhaniye Cad. No: 25/2 Sirkeci Istanbul 34112",
    "addr:housenumber":"25 / 2",
    "addr:postcode":"34112",
    "addr:street":"Hocapasa Mah. Orhaniye Cad. No",
    "iso:country":"TR",
    "sg:address":"Hocapasa Mah. Orhaniye Cad. No: 25/2",
    "sg:city":"Sirkeci",
    "sg:classifiers":[
        {
            "category":"Travel",
            "subcategory":"Travel Agent",
            "type":"Entertainment"
        }
    ],
    "sg:phone":"+90 52265355228353",
    "sg:postcode":"34112",
    "sg:province":"Istanbul",
    "sg:tags":[
        "agency",
        "tourism"
    ],
    "wof:name":"Sentez Turizm Ticaret A.s.",
    "wof:placetype":"venue"
},
  "geometry": {"coordinates":[28.9861831665,41.0408554077],"type":"Point"}
}