{
  "type": "Feature",
  "properties": {
    "iso:country":"TR",
    "sg:address":"Ikitelli Organize Sanayi B?gesi Demirciler Sanayi Sitesi B-1 Blok No:33",
    "sg:city":"Ikitelli/K\u00fc\u00e7\u00fck\u00e7ekmece",
    "sg:classifiers":[
        {
            "category":"Train Station",
            "subcategory":"Rail",
            "type":"Transportation"
        }
    ],
    "sg:phone":"+90 212 549 5447",
    "sg:postcode":"34670",
    "sg:province":"Istanbul",
    "sg:tags":[
        "sheet",
        "iron"
    ],
    "sg:website":"ozdemetal.com",
    "wof:name":"?zde Metal Sanayi Tic.ltd.sti",
    "wof:placetype":"venue"
},
  "geometry": {"coordinates":[28.975925,41.012379],"type":"Point"}
}