{
  "type": "Feature",
  "properties": {
    "addr:full":"N?hetiye Cad No: 42 A Blok Kat: 4 Daire: 13 Besiktas Kad\u0131k\u00f6y Istanbul 34726",
    "addr:housenumber":"?;42 a blok kat 4;13",
    "addr:postcode":"34726",
    "addr:street":"N;Hetiye Cad No;Daire",
    "iso:country":"TR",
    "sg:address":"N?hetiye Cad No: 42 A Blok Kat: 4 Daire: 13 Besiktas",
    "sg:city":"Kad\u0131k\u00f6y",
    "sg:classifiers":[
        {
            "category":"Communications",
            "subcategory":"Film & Video Production",
            "type":"Services"
        }
    ],
    "sg:phone":"+90 212 227 9274",
    "sg:postcode":"34726",
    "sg:province":"Istanbul",
    "sg:tags":[
        "-"
    ],
    "wof:name":"Broadcast M?hendislik Ve Prod?ksiyon San.tic.ltd.sti",
    "wof:placetype":"venue"
},
  "geometry": {"coordinates":[29.0445384979,40.975063324],"type":"Point"}
}