{
  "type": "Feature",
  "properties": {
    "iso:country":"TR",
    "sg:address":"Ataturk Mahikitelli Cad. No:65/a Ikitelli-",
    "sg:city":"Parseller",
    "sg:classifiers":[
        {
            "category":"Manufacturing",
            "subcategory":"Glass & Minerals",
            "type":"Manufacturing & Wholesale Goods"
        }
    ],
    "sg:phone":"+90 212 548 4961",
    "sg:province":"Istanbul",
    "sg:tags":[
        "glass-mirror"
    ],
    "wof:name":"Istanbul Cam",
    "wof:placetype":"venue"
},
  "geometry": {"coordinates":[28.8017139435,41.0480270386],"type":"Point"}
}