{
  "type": "Feature",
  "properties": {
    "addr:full":"In??cad. No:66 Taksim Asagi Ayranci Istanbul",
    "addr:housenumber":"66",
    "addr:street":"In ? ? Cad. No;Asagi",
    "iso:country":"TR",
    "sg:address":"In??cad. No:66 Taksim",
    "sg:city":"Asagi Ayranci",
    "sg:classifiers":[
        {
            "category":"Banks & Credit Unions",
            "subcategory":"Financial Services",
            "type":"Services"
        }
    ],
    "sg:phone":"+90 212 252 7650",
    "sg:province":"Istanbul",
    "sg:tags":[
        "finance"
    ],
    "wof:name":"Carsi Menkul Degerler A.s",
    "wof:placetype":"venue"
},
  "geometry": {"coordinates":[28.9866142273,41.0371932983],"type":"Point"}
}