{
  "type": "Feature",
  "properties": {
    "addr:full":"Salma Tomruk Cad. No:14 Edirnekapi Istanbul",
    "addr:housenumber":"14",
    "addr:street":"Tomruk Cad. No",
    "iso:country":"TR",
    "sg:address":"Salma Tomruk Cad. No:14",
    "sg:city":"Edirnekapi",
    "sg:classifiers":[
        {
            "category":"Manufacturing",
            "subcategory":"Food",
            "type":"Manufacturing & Wholesale Goods"
        }
    ],
    "sg:phone":"+90 212 521 5389",
    "sg:province":"Istanbul",
    "sg:tags":[
        "product",
        "floury",
        "macaroni"
    ],
    "wof:name":"Un Kamer Ltd.sti.",
    "wof:placetype":"venue"
},
  "geometry": {"coordinates":[28.9386577606,41.0292243958],"type":"Point"}
}