{
  "type": "Feature",
  "properties": {
    "addr:full":"I.m.? 5. Blok No:5515 Unkapani Istanbul 34470",
    "addr:housenumber":"blok no 5515",
    "addr:postcode":"34470",
    "addr:street":"5;Unkapani Istanbul",
    "iso:country":"TR",
    "sg:address":"I.m.? 5. Blok No:5515",
    "sg:city":"Unkapani",
    "sg:classifiers":[
        {
            "category":"Government",
            "subcategory":"Fire Station",
            "type":"Public Place"
        }
    ],
    "sg:phone":"+90 21251356686",
    "sg:postcode":"34470",
    "sg:province":"Istanbul",
    "sg:tags":[
        "decoration"
    ],
    "wof:name":"Yagmur Halicilik",
    "wof:placetype":"venue"
},
  "geometry": {"coordinates":[28.9103794098,41.0486907959],"type":"Point"}
}