{
  "type": "Feature",
  "properties": {
    "iso:country":"TR",
    "sg:address":"Maltepe, G??suyu Cd. No:56 Topkapi",
    "sg:city":"Erenk?",
    "sg:classifiers":[
        {
            "category":"Home & Garden",
            "subcategory":"Kitchen Supply",
            "type":"Retail Goods"
        }
    ],
    "sg:phone":"+90 212 576 1659",
    "sg:province":"Istanbul",
    "sg:tags":[
        "wardrobe"
    ],
    "wof:name":"Surdekor Ahsap Mutfak Banyo",
    "wof:placetype":"venue"
},
  "geometry": {"coordinates":[28.9759254456,41.0123786926],"type":"Point"}
}