{
  "type": "Feature",
  "properties": {
    "addr:full":"Hamdi ?zse?r Orta ?orum 01945",
    "addr:postcode":"01945",
    "addr:street":"Zse;R",
    "iso:country":"TR",
    "sg:address":"Hamdi ?zse?r",
    "sg:city":"Orta",
    "sg:classifiers":[
        {
            "category":"Government",
            "subcategory":"Office",
            "type":"Public Place"
        }
    ],
    "sg:phone":"+90 364 471 6255",
    "sg:postcode":"01945",
    "sg:province":"?orum",
    "sg:tags":[
        "municipality"
    ],
    "wof:name":"Elvan?lebi Belediye Baskani",
    "wof:placetype":"venue"
},
  "geometry": {"coordinates":[35.751991272,37.4670600891],"type":"Point"}
}