{
  "type": "Feature",
  "properties": {
    "iso:country":"TR",
    "sg:address":"Istasyon Cad. No.6/b Yesilk?",
    "sg:city":"\u00c7orlu",
    "sg:classifiers":[
        {
            "category":"Shopping",
            "subcategory":"Luggage & Leather Goods",
            "type":"Retail Goods"
        }
    ],
    "sg:phone":"+90 212 574 3104",
    "sg:province":"Istanbul",
    "sg:tags":[
        "leather-fur",
        "wear"
    ],
    "wof:name":"Jivego Deri Ve S?et Ltd.sti.",
    "wof:placetype":"venue"
},
  "geometry": {"coordinates":[28.8244400024,40.9613075256],"type":"Point"}
}