{
  "type": "Feature",
  "properties": {
    "addr:full":"Kervan G. Sk. Dilan ?ars. No:8/60 Mecidiyek? Kizilay Istanbul 06650",
    "addr:housenumber":"? ars. no 8 / 60;?",
    "addr:postcode":"06650",
    "addr:street":"Kervan G. Sk. Dilan;Mecidiyek",
    "iso:country":"TR",
    "sg:address":"Kervan G. Sk. Dilan ?ars. No:8/60 Mecidiyek?",
    "sg:city":"Kizilay",
    "sg:classifiers":[
        {
            "category":"Shopping",
            "subcategory":"Stationery & Office Supplies",
            "type":"Retail Goods"
        }
    ],
    "sg:phone":"+90 212 288 7149",
    "sg:postcode":"06650",
    "sg:province":"Istanbul",
    "wof:name":"Onursen Kirtasiye San. Tic. Ltd. Sti.",
    "wof:placetype":"venue"
},
  "geometry": {"coordinates":[28.975925,41.012379],"type":"Point"}
}