{
  "type": "Feature",
  "properties": {
    "addr:full":"Leblebiciler Sk. No:29/31 Balat Istanbul 09270",
    "addr:housenumber":"29 / 31",
    "addr:postcode":"09270",
    "addr:street":"Leblebiciler Sk. No",
    "iso:country":"TR",
    "sg:address":"Leblebiciler Sk. No:29/31",
    "sg:city":"Balat",
    "sg:classifiers":[
        {
            "category":"Shopping",
            "subcategory":"Computers & Home Electronics",
            "type":"Retail Goods"
        }
    ],
    "sg:phone":"+90 212 521 8287",
    "sg:postcode":"09270",
    "sg:province":"Istanbul",
    "sg:tags":[
        "animal"
    ],
    "wof:name":"?agri Akvaryum Kus?uluk",
    "wof:placetype":"venue"
},
  "geometry": {"coordinates":[28.9861831665,41.0408554077],"type":"Point"}
}