{
  "type": "Feature",
  "properties": {
    "iso:country":"TR",
    "sg:address":"859 Sk. No.6",
    "sg:city":"Maltepe",
    "sg:classifiers":[
        {
            "category":"Farming",
            "subcategory":"Farm",
            "type":"Manufacturing & Wholesale Goods"
        }
    ],
    "sg:phone":"+90 232 484 2503",
    "sg:postcode":"01000",
    "sg:province":"Izmir",
    "sg:tags":[
        "agricultural",
        "product"
    ],
    "wof:name":"Baykanlar Tarim Urn. A.s.",
    "wof:placetype":"venue"
},
  "geometry": {"coordinates":[27.1618213654,38.3993415833],"type":"Point"}
}