{
  "type": "Feature",
  "properties": {
    "iso:country":"TR",
    "sg:address":"Ikitell Org.san.b?g.sefak? San.sit.9 Blok No:2-4-6",
    "sg:city":"Ikitell",
    "sg:classifiers":[
        {
            "category":"Professional",
            "type":"Services"
        }
    ],
    "sg:phone":"+90 212671353567",
    "sg:province":"Istanbul",
    "sg:tags":[
        "catering"
    ],
    "wof:name":"Em & Ti Catering Group",
    "wof:placetype":"venue"
},
  "geometry": {"coordinates":[28.9095592499,41.0490531921],"type":"Point"}
}