{
  "type": "Feature",
  "properties": {
    "addr:full":"Necatibey Cad. No:91 Karakoy Ikitelli/K\u00fc\u00e7\u00fck\u00e7ekmece Istanbul 34670",
    "addr:housenumber":"91",
    "addr:postcode":"34670",
    "addr:street":"Necatibey Cad. No",
    "iso:country":"TR",
    "sg:address":"Necatibey Cad. No:91 Karakoy",
    "sg:city":"Ikitelli/K\u00fc\u00e7\u00fck\u00e7ekmece",
    "sg:classifiers":[
        {
            "category":"Manufacturing",
            "subcategory":"Tools & Machinery",
            "type":"Manufacturing & Wholesale Goods"
        }
    ],
    "sg:phone":"+90 212 251 5180",
    "sg:postcode":"34670",
    "sg:province":"Istanbul",
    "sg:tags":[
        "machine",
        "industry"
    ],
    "wof:name":"Teknik-motor Makine Sanayi Ve Tic. Ltd.",
    "wof:placetype":"venue"
},
  "geometry": {"coordinates":[28.9779453278,41.0247802734],"type":"Point"}
}