{
  "type": "Feature",
  "properties": {
    "iso:country":"TR",
    "sg:address":"P.box. 120",
    "sg:city":"Ikitelli/K\u00fc\u00e7\u00fck\u00e7ekmece",
    "sg:classifiers":[
        {
            "category":"Wholesale",
            "subcategory":"Auto Parts",
            "type":"Manufacturing & Wholesale Goods"
        }
    ],
    "sg:phone":"+90 362 266 8090",
    "sg:postcode":"34670",
    "sg:province":"Samsun",
    "sg:tags":[
        "spare"
    ],
    "wof:name":"Fkk Guney Oto Lastik Takoz San. Ve Tic. A.s.",
    "wof:placetype":"venue"
},
  "geometry": {"coordinates":[36.3381233215,41.2815742493],"type":"Point"}
}