{
  "type": "Feature",
  "properties": {
    "iso:country":"TR",
    "sg:address":"Erdin Aydin",
    "sg:city":"Karatas",
    "sg:classifiers":[
        {
            "category":"Government",
            "subcategory":"Office",
            "type":"Public Place"
        }
    ],
    "sg:phone":"+90 446 233 6208",
    "sg:postcode":"01900",
    "sg:province":"Erzincan",
    "sg:tags":[
        "municipality"
    ],
    "wof:name":"Bah?lik? Belediye Baskani",
    "wof:placetype":"venue"
},
  "geometry": {"coordinates":[39.4905014038,39.7491989136],"type":"Point"}
}