{
  "type": "Feature",
  "properties": {
    "addr:full":"2. Murat Cad. No:20 ?ekirge Bursa 16070",
    "addr:housenumber":"2;20 ?",
    "addr:postcode":"16070",
    "addr:street":"Murat Cad. No;Bursa",
    "iso:country":"TR",
    "sg:address":"2. Murat Cad. No:20",
    "sg:city":"?ekirge",
    "sg:orig_category":"Hotels: Motels",
    "sg:phone":"+90 224233950010",
    "sg:postcode":"16070",
    "sg:province":"Bursa",
    "wof:name":"Dilmen Hotel",
    "wof:placetype":"venue"
},
  "geometry": {"coordinates":[29.0473003387,40.1908607483],"type":"Point"}
}