{
  "type": "Feature",
  "properties": {
    "iso:country":"TR",
    "sg:address":"Hudavendigar Cad. No: 4 34410",
    "sg:city":"Sirkeci",
    "sg:orig_category":"Dryfood-dried Nuts",
    "sg:phone":"+90 212 514 1553",
    "sg:postcode":"34112",
    "sg:province":"Istanbul",
    "wof:name":"Inan Ic Ve Dis Tic.a.s.",
    "wof:placetype":"venue"
},
  "geometry": {"coordinates":[28.9861831665,41.0408554077],"type":"Point"}
}