{
  "type": "Feature",
  "properties": {
    "iso:country":"TR",
    "sg:address":"Sanayi Mah. No.10",
    "sg:city":"Gonen",
    "sg:classifiers":[
        {
            "category":"Farming",
            "subcategory":"Livestock Farm",
            "type":"Manufacturing & Wholesale Goods"
        }
    ],
    "sg:phone":"+90 242 345 9379",
    "sg:postcode":"32090",
    "sg:province":"Antalya",
    "sg:tags":[
        "fattening-breeding"
    ],
    "wof:name":"Yavuz Hayvancilik Ltd.sti.",
    "wof:placetype":"venue"
},
  "geometry": {"coordinates":[30.693025589,36.9046974182],"type":"Point"}
}