{
  "type": "Feature",
  "properties": {
    "iso:country":"TR",
    "sg:address":"Deniz Mahallesi Fevzi Cakmak Caddesi No 28",
    "sg:city":"Derince",
    "sg:classifiers":[
        {
            "category":"Freight",
            "type":"Transportation"
        }
    ],
    "sg:phone":"+90 262 239 2185",
    "sg:postcode":"31000",
    "sg:province":"Kocaeli",
    "sg:tags":[
        "agent",
        "shipping",
        "broker"
    ],
    "wof:name":"Ural Tasimacilik Ticaret Ltd.",
    "wof:placetype":"venue"
},
  "geometry": {"coordinates":[29.828867,40.753925],"type":"Point"}
}