{
  "type": "Feature",
  "properties": {
    "iso:country":"TR",
    "sg:address":"Alaaddin Cd. Emir Pervane Sk.",
    "sg:city":"Cankaya",
    "sg:orig_category":"Hotels: Motels",
    "sg:phone":"+90 332 351 1575",
    "sg:postcode":"07080",
    "sg:province":"Konya",
    "wof:name":"Kanarya Otel",
    "wof:placetype":"venue"
},
  "geometry": {"coordinates":[33.0667152405,39.2111282349],"type":"Point"}
}