{
  "type": "Feature",
  "properties": {
    "addr:full":"Bagdat Cad. No:541 Catal?sme - Suadiye Istanbul 34740",
    "addr:postcode":"541;?;34740",
    "addr:street":"Bagdat Cad. No",
    "iso:country":"TR",
    "sg:address":"Bagdat Cad. No:541 Catal?sme -",
    "sg:city":"Suadiye",
    "sg:classifiers":[
        {
            "category":"Government",
            "subcategory":"Fire Station",
            "type":"Public Place"
        }
    ],
    "sg:phone":"+90 216 416 3029",
    "sg:postcode":"34740",
    "sg:province":"Istanbul",
    "sg:tags":[
        "decoration"
    ],
    "wof:name":"Kado-co Insaat San.dis Tic.ltd",
    "wof:placetype":"venue"
},
  "geometry": {"coordinates":[28.9861831665,41.0408554077],"type":"Point"}
}