{
  "type": "Feature",
  "properties": {
    "iso:country":"TR",
    "sg:address":"Eski Sanayi Sitesi Ahi Evren Cad. 18.sok. No:19",
    "sg:city":"Yukari Dudullu",
    "sg:classifiers":[
        {
            "category":"Manufacturing",
            "subcategory":"Rubber & Plastics",
            "type":"Manufacturing & Wholesale Goods"
        }
    ],
    "sg:phone":"+90 362 238 4285",
    "sg:postcode":"34776",
    "sg:province":"Samsun",
    "sg:tags":[
        "industry"
    ],
    "wof:name":"As-cag Plastik Imalat Ve Tic.ltd.sti.",
    "wof:placetype":"venue"
},
  "geometry": {"coordinates":[36.3378410339,41.2897186279],"type":"Point"}
}