{
  "type": "Feature",
  "properties": {
    "iso:country":"TR",
    "sg:address":"10002 Sok. No:30 A.o.s.b 35100",
    "sg:city":"?igli",
    "sg:classifiers":[
        {
            "category":"Wholesale",
            "subcategory":"Machinery & Supplies",
            "type":"Manufacturing & Wholesale Goods"
        }
    ],
    "sg:phone":"+90 232 376 8087",
    "sg:province":"Izmir",
    "sg:tags":[
        "agricultural"
    ],
    "wof:name":"Obel Onur Baglanti Elemanlari Sanayi Ve Ticaret A.s.",
    "wof:placetype":"venue"
},
  "geometry": {"coordinates":[27.2107315063,38.4449691772],"type":"Point"}
}