{
  "type": "Feature",
  "properties": {
    "addr:full":"Barbaros Bul, Morbasan Gaziantep Istanbul 63570",
    "addr:postcode":"63570",
    "addr:street":"Morbasan",
    "iso:country":"TR",
    "sg:address":"Barbaros Bul, Morbasan",
    "sg:city":"Gaziantep",
    "sg:classifiers":[
        {
            "category":"Banks & Credit Unions",
            "subcategory":"Bank",
            "type":"Services"
        }
    ],
    "sg:phone":"+90 212 274 7777",
    "sg:postcode":"63570",
    "sg:province":"Istanbul",
    "wof:name":"Kocbank As",
    "wof:placetype":"venue"
},
  "geometry": {"coordinates":[29.011852,41.056908],"type":"Point"}
}