{
  "type": "Feature",
  "properties": {
    "addr:full":"Halkali 2.etap A203/58 Bak\u0131rk\u00f6y Istanbul 34140",
    "addr:housenumber":"a203 / 58",
    "addr:postcode":"34140",
    "addr:street":"Istanbul",
    "iso:country":"TR",
    "sg:address":"Halkali 2.etap A203/58",
    "sg:city":"Bak\u0131rk\u00f6y",
    "sg:orig_category":"Printinh House",
    "sg:phone":"+90 212 548 3250",
    "sg:postcode":"34140",
    "sg:province":"Istanbul",
    "wof:name":"Tonde Istanbul-turkiye",
    "wof:placetype":"venue"
},
  "geometry": {"coordinates":[28.8291702271,41.0670547485],"type":"Point"}
}