{
  "type": "Feature",
  "properties": {
    "addr:full":"108 Sok.no:59 Kemalpasa Mahallesi Pinarbasi Top?lar Izmir 34055",
    "addr:housenumber":"108;59 kemalpasa;?",
    "addr:postcode":"34055",
    "addr:street":"Sok.No;Mahallesi Pinarbasi Top",
    "iso:country":"TR",
    "sg:address":"108 Sok.no:59 Kemalpasa Mahallesi Pinarbasi",
    "sg:city":"Top?lar",
    "sg:classifiers":[
        {
            "category":"Manufacturing",
            "subcategory":"Tools & Machinery",
            "type":"Manufacturing & Wholesale Goods"
        }
    ],
    "sg:phone":"+90 232 479 2103",
    "sg:postcode":"34055",
    "sg:province":"Izmir",
    "sg:tags":[
        "machine",
        "industry"
    ],
    "wof:name":"Dizmak Makina Ve Yedek Par?a San.ve Tic.ltd.sti.",
    "wof:placetype":"venue"
},
  "geometry": {"coordinates":[27.1296863556,38.4186973572],"type":"Point"}
}