{
  "type": "Feature",
  "properties": {
    "addr:full":"Yasar Buhan Ceyhan Bitlis 01920",
    "addr:postcode":"01920",
    "addr:street":"Ceyhan",
    "iso:country":"TR",
    "sg:address":"Yasar Buhan",
    "sg:city":"Ceyhan",
    "sg:classifiers":[
        {
            "category":"Government",
            "subcategory":"Office",
            "type":"Public Place"
        }
    ],
    "sg:phone":"+90 434 226 5911",
    "sg:postcode":"01920",
    "sg:province":"Bitlis",
    "sg:tags":[
        "municipality"
    ],
    "wof:name":"Bitlis Belediye Baskani",
    "wof:placetype":"venue"
},
  "geometry": {"coordinates":[42.1083984375,38.3997001648],"type":"Point"}
}