{
  "type": "Feature",
  "properties": {
    "iso:country":"TR",
    "sg:address":"Gumussuyu Cad. Haci Emin Aga Sok. No:14",
    "sg:city":"Bayrampasa",
    "sg:classifiers":[
        {
            "category":"Shopping",
            "subcategory":"Clothing, Apparel, & Fashions",
            "type":"Retail Goods"
        }
    ],
    "sg:phone":"+90 212 613 9682",
    "sg:postcode":"36100",
    "sg:province":"Istanbul",
    "sg:tags":[
        "woman",
        "wear"
    ],
    "wof:name":"Erteks Dis Tic.san. Ve Tic. Ltd.sti.",
    "wof:placetype":"venue"
},
  "geometry": {"coordinates":[28.9949550629,41.0521011353],"type":"Point"}
}