{
  "type": "Feature",
  "properties": {
    "addr:full":"Gazi Mustafa Kemal Bulvari No: 20 33040 Mersin I?el 52750",
    "addr:housenumber":"no 20",
    "addr:postcode":"33040;? el 52750",
    "addr:street":"Mustafa Kemal Bulvari",
    "iso:country":"TR",
    "sg:address":"Gazi Mustafa Kemal Bulvari No: 20 33040",
    "sg:city":"Mersin",
    "sg:orig_category":"Hotels: Motels",
    "sg:phone":"+90 324 234 1200",
    "sg:postcode":"52750",
    "sg:province":"I?el",
    "wof:name":"Otel Gondol",
    "wof:placetype":"venue"
},
  "geometry": {"coordinates":[34.600528717,36.8091697693],"type":"Point"}
}