{
  "type": "Feature",
  "properties": {
    "addr:full":"Yeni Yol Cad. No:16-18 Sisli Nazilli Istanbul 65600",
    "addr:housenumber":"no 16-18",
    "addr:postcode":"65600",
    "addr:street":"Yeni Yol Cad.;Sisli Nazilli",
    "iso:country":"TR",
    "sg:address":"Yeni Yol Cad. No:16-18 Sisli",
    "sg:city":"Nazilli",
    "sg:classifiers":[
        {
            "category":"Wholesale",
            "subcategory":"Durable Goods & Equipment",
            "type":"Manufacturing & Wholesale Goods"
        }
    ],
    "sg:phone":"+90 212 224 5410",
    "sg:postcode":"65600",
    "sg:province":"Istanbul",
    "sg:tags":[
        "consumer"
    ],
    "wof:name":"Arcelik Nadir Ltd. Sti.",
    "wof:placetype":"venue"
},
  "geometry": {"coordinates":[28.9861831665,41.0408554077],"type":"Point"}
}