{
  "type": "Feature",
  "properties": {
    "iso:country":"TR",
    "sg:address":"Besyol Fabrikalar Cad.no:21 Sefak?",
    "sg:city":"Beypazari",
    "sg:classifiers":[
        {
            "category":"Freight",
            "type":"Transportation"
        }
    ],
    "sg:phone":"+90 212 541 6180",
    "sg:postcode":"06730",
    "sg:province":"Istanbul",
    "sg:tags":[
        "packing",
        "industry"
    ],
    "wof:name":"Cem Ofset Matbaacilik San.a.s",
    "wof:placetype":"venue"
},
  "geometry": {"coordinates":[28.7944545746,40.9903869629],"type":"Point"}
}