{
  "type": "Feature",
  "properties": {
    "addr:full":"Gai Akdemir Mah. Guney Sok. No:17/a Bayrampasa Bursa 36100",
    "addr:housenumber":"no 17 / a",
    "addr:postcode":"36100",
    "addr:street":"Mah. Guney Sok.;Bursa",
    "iso:country":"TR",
    "sg:address":"Gai Akdemir Mah. Guney Sok. No:17/a",
    "sg:city":"Bayrampasa",
    "sg:classifiers":[
        {
            "category":"Building & Trades",
            "subcategory":"Construction",
            "type":"Services"
        }
    ],
    "sg:phone":"+90 224 618 1414",
    "sg:postcode":"36100",
    "sg:province":"Bursa",
    "sg:tags":[
        "industry",
        "mold"
    ],
    "wof:name":"Uslu Kaucuk",
    "wof:placetype":"venue"
},
  "geometry": {"coordinates":[29.0580043793,40.1947555542],"type":"Point"}
}