{
  "type": "Feature",
  "properties": {
    "iso:country":"TR",
    "sg:address":"Barbaros Cd. No:3 Pendik",
    "sg:city":"Yukari Dudullu",
    "sg:classifiers":[
        {
            "category":"Manufacturing",
            "subcategory":"Rubber & Plastics",
            "type":"Manufacturing & Wholesale Goods"
        }
    ],
    "sg:phone":"+90 216 378 2105",
    "sg:postcode":"34776",
    "sg:province":"Istanbul",
    "sg:tags":[
        "industry"
    ],
    "wof:name":"Avitas Avdagic Polyester Plastik San. Tic.",
    "wof:placetype":"venue"
},
  "geometry": {"coordinates":[29.2903518677,40.9000587463],"type":"Point"}
}