{
  "type": "Feature",
  "properties": {
    "addr:full":"Lale Cad. Yaylakli Ishani No:4/15 Atakum Nevsehir 55105",
    "addr:housenumber":"15",
    "addr:postcode":"55105",
    "addr:street":"Lale Cad. Yaylakli Ishani No 4 /",
    "iso:country":"TR",
    "sg:address":"Lale Cad. Yaylakli Ishani No:4/15",
    "sg:city":"Atakum",
    "sg:orig_category":"Non-classified Establishments",
    "sg:phone":"+90 384 212 8214",
    "sg:postcode":"55105",
    "sg:province":"Nevsehir",
    "wof:name":"Ertarim Tohumculuk",
    "wof:placetype":"venue"
},
  "geometry": {"coordinates":[34.7110939026,38.6325645447],"type":"Point"}
}