{
  "type": "Feature",
  "properties": {
    "addr:full":"Vatan Cd. Ortadogu Ismerk. No:2 K:3 ?aglayan Karatay Istanbul 42000",
    "addr:housenumber":"3 ?",
    "addr:postcode":"42000",
    "addr:street":"Cd.;Ismerk. No 2 K;Aglayan",
    "iso:country":"TR",
    "sg:address":"Vatan Cd. Ortadogu Ismerk. No:2 K:3 ?aglayan",
    "sg:city":"Karatay",
    "sg:classifiers":[
        {
            "category":"Professional",
            "subcategory":"Art Services",
            "type":"Services"
        }
    ],
    "sg:phone":"+90 212 224 9531",
    "sg:postcode":"42000",
    "sg:province":"Istanbul",
    "sg:tags":[
        "marketing"
    ],
    "wof:name":"Unisoft Yazilim Pazarlama Tic. A.s.",
    "wof:placetype":"venue"
},
  "geometry": {"coordinates":[28.9861831665,41.0408554077],"type":"Point"}
}