{
  "type": "Feature",
  "properties": {
    "iso:country":"TR",
    "sg:address":"Kazim Dirik Cad. No:7 Naldoken Mah.bornova",
    "sg:city":"Beypazari",
    "sg:classifiers":[
        {
            "category":"Manufacturing",
            "subcategory":"Wood Products",
            "type":"Manufacturing & Wholesale Goods"
        }
    ],
    "sg:phone":"+90 232 373 6335",
    "sg:postcode":"06730",
    "sg:province":"Izmir",
    "sg:tags":[
        "forest"
    ],
    "wof:name":"Bozdag Orman Urunleri Nak.ins.san.ve Tic.ltd.sti.",
    "wof:placetype":"venue"
},
  "geometry": {"coordinates":[27.1423015594,38.4251480103],"type":"Point"}
}