{
  "type": "Feature",
  "properties": {
    "addr:full":"In??cd. 37. Sk. No:11 Merkez Besiktas Adana 80630",
    "addr:housenumber":"11",
    "addr:postcode":"80630",
    "addr:street":"In ? ? Cd. 37 Sk. No;Besiktas",
    "iso:country":"TR",
    "sg:address":"In??cd. 37. Sk. No:11 Merkez",
    "sg:city":"Besiktas",
    "sg:classifiers":[
        {
            "category":"Organizations",
            "subcategory":"Membership Organization",
            "type":"Services"
        }
    ],
    "sg:phone":"+90 322 351 3680",
    "sg:postcode":"80630",
    "sg:province":"Adana",
    "wof:name":"Adana Dis Teknis. Dern.",
    "wof:placetype":"venue"
},
  "geometry": {"coordinates":[35.3250198364,36.9854202271],"type":"Point"}
}