{
  "type": "Feature",
  "properties": {
    "iso:country":"TR",
    "sg:address":"Karaduvar Mh.",
    "sg:city":"Tuzla",
    "sg:classifiers":[
        {
            "category":"Wholesale",
            "subcategory":"Petroleum",
            "type":"Manufacturing & Wholesale Goods"
        }
    ],
    "sg:phone":"+90 324 234 7676",
    "sg:postcode":"01900",
    "sg:province":"I?el",
    "wof:name":"Atas Anadolu Tasfiyehanesi A.s.",
    "wof:placetype":"venue"
},
  "geometry": {"coordinates":[34.6949615479,36.8255958557],"type":"Point"}
}