{
  "type": "Feature",
  "properties": {
    "iso:country":"TR",
    "sg:address":"D?gmeci Mah. Suburcu Cad. Aliveli Ish. K: 1 No: 22/203",
    "sg:city":"Sisli",
    "sg:classifiers":[
        {
            "category":"Travel",
            "subcategory":"Travel Agent",
            "type":"Entertainment"
        }
    ],
    "sg:phone":"+90 342220284546",
    "sg:postcode":"65710",
    "sg:province":"Gaziantep",
    "sg:tags":[
        "agency",
        "tourism"
    ],
    "wof:name":"Sura Turizm",
    "wof:placetype":"venue"
},
  "geometry": {"coordinates":[37.4416732788,36.9459457397],"type":"Point"}
}