{
  "type": "Feature",
  "properties": {
    "addr:full":"Cemil Ko?k Icehisar ?orum",
    "addr:housenumber":"? k icehisar ?",
    "addr:street":"Ko",
    "iso:country":"TR",
    "sg:address":"Cemil Ko?k",
    "sg:city":"Icehisar",
    "sg:classifiers":[
        {
            "category":"Government",
            "subcategory":"Office",
            "type":"Public Place"
        }
    ],
    "sg:phone":"+90 364 298 8661",
    "sg:province":"?orum",
    "sg:tags":[
        "municipality"
    ],
    "wof:name":"Seydim Belediye Baskani",
    "wof:placetype":"venue"
},
  "geometry": {"coordinates":[35.4317016602,38.9577407837],"type":"Point"}
}