{
  "type": "Feature",
  "properties": {
    "addr:full":"Ataturk Sanayi Bolgesi Ibni Sina Cad. No:3 Hadimkoy Istanbul",
    "addr:street":"Ataturk Sanayi Bolgesi Ibni Sina Cad. No 3 Hadimkoy",
    "iso:country":"TR",
    "sg:address":"Ataturk Sanayi Bolgesi Ibni Sina Cad. No:3",
    "sg:city":"Hadimkoy",
    "sg:classifiers":[
        {
            "category":"Manufacturing",
            "subcategory":"Textiles",
            "type":"Manufacturing & Wholesale Goods"
        }
    ],
    "sg:phone":"+90 212 771 2828",
    "sg:province":"Istanbul",
    "sg:tags":[
        "chemical"
    ],
    "wof:name":"Kemiteks Kimya San.ve Tic.a.s.",
    "wof:placetype":"venue"
},
  "geometry": {"coordinates":[28.9861831665,41.0408554077],"type":"Point"}
}