{
  "type": "Feature",
  "properties": {
    "iso:country":"TR",
    "sg:address":"Iskitler Cd. No:50/4 Iskitler",
    "sg:city":"Alsancak",
    "sg:classifiers":[
        {
            "category":"Professional",
            "subcategory":"Detective & Security Services",
            "type":"Services"
        }
    ],
    "sg:phone":"+90 312 342 2663",
    "sg:postcode":"35210",
    "sg:province":"Ankara",
    "sg:tags":[
        "material"
    ],
    "wof:name":"Genesis Elektronik San. Tic. Ltd. Sti.",
    "wof:placetype":"venue"
},
  "geometry": {"coordinates":[32.856033,39.943874],"type":"Point"}
}