{
  "type": "Feature",
  "properties": {
    "addr:full":"Ataturk Cad. 115/1 Antakya Hatay 31000",
    "addr:housenumber":"115 / 1",
    "addr:postcode":"31000",
    "addr:street":"Ataturk Cad.",
    "iso:country":"TR",
    "sg:address":"Ataturk Cad. 115/1",
    "sg:city":"Antakya",
    "sg:classifiers":[
        {
            "category":"Farming",
            "subcategory":"Farm",
            "type":"Manufacturing & Wholesale Goods"
        }
    ],
    "sg:phone":"+90 326 221 1181",
    "sg:postcode":"31000",
    "sg:province":"Hatay",
    "sg:tags":[
        "agricultural",
        "product"
    ],
    "wof:name":"Akas Ali Kavak Tarim Urunleri San. Tic. A.s.",
    "wof:placetype":"venue"
},
  "geometry": {"coordinates":[36.1603889465,36.2034378052],"type":"Point"}
}