{
  "type": "Feature",
  "properties": {
    "iso:country":"TR",
    "sg:address":"Cihannuma Mh. Bostancibasi Sk. No:13 Besiktas",
    "sg:city":"Yenisehir",
    "sg:classifiers":[
        {
            "category":"Building & Trades",
            "subcategory":"Plumbing",
            "type":"Services"
        }
    ],
    "sg:phone":"+90 212 261 9240",
    "sg:postcode":"31750",
    "sg:province":"Istanbul",
    "wof:name":"Artas End?stri Tesis. Taahh?t Tic. A.s.",
    "wof:placetype":"venue"
},
  "geometry": {"coordinates":[28.9797496796,41.0313796997],"type":"Point"}
}