{
  "type": "Feature",
  "properties": {
    "addr:full":"Ortaklar Cd. No:34 Mecidiyek\u00f6y Istanbul 34387",
    "addr:housenumber":"no 34",
    "addr:postcode":"34387",
    "addr:street":"Istanbul",
    "iso:country":"TR",
    "sg:address":"Ortaklar Cd. No:34",
    "sg:city":"Mecidiyek\u00f6y",
    "sg:classifiers":[
        {
            "category":"Shopping",
            "subcategory":"Florist",
            "type":"Retail Goods"
        }
    ],
    "sg:phone":"+90 212 274 9326",
    "sg:postcode":"34387",
    "sg:province":"Istanbul",
    "sg:tags":[
        "flower"
    ],
    "wof:name":"Sevda Ulusl. ?i?ek?ilik",
    "wof:placetype":"venue"
},
  "geometry": {"coordinates":[28.9973278046,41.063243866],"type":"Point"}
}