{
  "type": "Feature",
  "properties": {
    "iso:country":"TR",
    "sg:address":"Kemeralti Cad. No:59 Karak?",
    "sg:city":"33050",
    "sg:classifiers":[
        {
            "category":"Manufacturing",
            "subcategory":"Building Materials",
            "type":"Manufacturing & Wholesale Goods"
        }
    ],
    "sg:phone":"+90 212 249 5521",
    "sg:province":"Istanbul",
    "sg:tags":[
        "hospital"
    ],
    "wof:name":"Teknik Celik San. Tic. A.s.",
    "wof:placetype":"venue"
},
  "geometry": {"coordinates":[28.979259491,41.0264091492],"type":"Point"}
}