{
  "type": "Feature",
  "properties": {
    "addr:full":"D?gmeci Mah. Karag?z Cad. Petrol Ishani K: 2 No: 204 Sahinbey Gaziantep 27700",
    "addr:housenumber":"? z;2 no 204",
    "addr:postcode":"27700",
    "addr:street":"Gmeci Mah. Karag;Sahinbey Gaziantep",
    "iso:country":"TR",
    "sg:address":"D?gmeci Mah. Karag?z Cad. Petrol Ishani K: 2 No: 204",
    "sg:city":"Sahinbey",
    "sg:classifiers":[
        {
            "category":"Travel",
            "subcategory":"Travel Agent",
            "type":"Entertainment"
        }
    ],
    "sg:phone":"+90 342221028889",
    "sg:postcode":"27700",
    "sg:province":"Gaziantep",
    "sg:tags":[
        "agency",
        "tourism"
    ],
    "wof:name":"Habib Turizm",
    "wof:placetype":"venue"
},
  "geometry": {"coordinates":[37.4416732788,36.9459457397],"type":"Point"}
}