{
  "type": "Feature",
  "properties": {
    "iso:country":"TR",
    "sg:address":"29 Ekim Cad. No:23 34530 Bahcelievler Istanbul",
    "sg:city":"Kad\u0131k\u00f6y",
    "sg:classifiers":[
        {
            "category":"Banks & Credit Unions",
            "subcategory":"Financial Services",
            "type":"Services"
        }
    ],
    "sg:phone":"+90 212 454 2424",
    "sg:postcode":"81110",
    "sg:province":"Istanbul",
    "sg:tags":[
        "banking",
        "finance",
        "insurance"
    ],
    "wof:name":"Ihlas Holding",
    "wof:placetype":"venue"
},
  "geometry": {"coordinates":[28.8196811676,41.0038070679],"type":"Point"}
}