{
  "type": "Feature",
  "properties": {
    "addr:full":"Sanayi Mah. 100.yil Cad. No.15, 4.levent Istanbul 80660",
    "addr:housenumber":"4.levent",
    "addr:postcode":"80660",
    "addr:street":"Sanayi Mah. 100.Yil Cad. No.15",
    "iso:country":"TR",
    "sg:address":"Sanayi Mah. 100.yil Cad. No.15,",
    "sg:city":"4.levent",
    "sg:classifiers":[
        {
            "category":"Home & Garden",
            "subcategory":"Building Materials",
            "type":"Retail Goods"
        }
    ],
    "sg:phone":"+90 212 280 3082",
    "sg:postcode":"80660",
    "sg:province":"Istanbul",
    "sg:tags":[
        "window",
        "door"
    ],
    "wof:name":"Aygun Polimer Ltd.sti.",
    "wof:placetype":"venue"
},
  "geometry": {"coordinates":[29.2032794952,40.8993492126],"type":"Point"}
}