{
  "type": "Feature",
  "properties": {
    "iso:country":"TR",
    "sg:address":"Kemalpasa Mh. Emeksizler Sk. No:8 Sefakoy",
    "sg:city":"07100",
    "sg:orig_category":"Aluminium Carpentary",
    "sg:phone":"+90 212 598 1760",
    "sg:province":"Istanbul",
    "wof:name":"Alde Aliminyum Dog. San.a.s.",
    "wof:placetype":"venue"
},
  "geometry": {"coordinates":[28.797246933,41.0025253296],"type":"Point"}
}