{
  "type": "Feature",
  "properties": {
    "addr:full":"Hastane Cad. Kayaoglu Ishani Kat:3 Bayrampasa Denizli 36100",
    "addr:housenumber":"kat 3",
    "addr:postcode":"36100",
    "addr:street":"Hastane Cad. Kayaoglu Ishani;Bayrampasa Denizli",
    "iso:country":"TR",
    "sg:address":"Hastane Cad. Kayaoglu Ishani Kat:3",
    "sg:city":"Bayrampasa",
    "sg:classifiers":[
        {
            "category":"Farming",
            "subcategory":"Farm",
            "type":"Manufacturing & Wholesale Goods"
        }
    ],
    "sg:phone":"+90 258 563 5976",
    "sg:postcode":"36100",
    "sg:province":"Denizli",
    "sg:tags":[
        "agricultural",
        "product"
    ],
    "wof:name":"Sevil Gida Dis Ticaret A.s.",
    "wof:placetype":"venue"
},
  "geometry": {"coordinates":[29.0864906311,37.773525238],"type":"Point"}
}