{
  "type": "Feature",
  "properties": {
    "addr:full":"Muardiye Pamukova Manisa 54900",
    "addr:postcode":"54900",
    "iso:country":"TR",
    "sg:address":"Muardiye",
    "sg:city":"Pamukova",
    "sg:classifiers":[
        {
            "category":"School Buses",
            "type":"Transportation"
        }
    ],
    "sg:phone":"+90 236 246 8014",
    "sg:postcode":"54900",
    "sg:province":"Manisa",
    "sg:tags":[
        "sapling"
    ],
    "wof:name":"Muradiye Orman Fidanlik Mudurlugu",
    "wof:placetype":"venue"
},
  "geometry": {"coordinates":[27.677095,39.100349],"type":"Point"}
}