{
  "type": "Feature",
  "properties": {
    "addr:full":"Nevzemin Sok. No:18 D: 13 Bahariye-kadikoy Mersin Istanbul 33010",
    "addr:housenumber":"no 18 d 13",
    "addr:postcode":"33010",
    "addr:street":"Nevzemin Sok.;Bahariye-Kadikoy",
    "iso:country":"TR",
    "sg:address":"Nevzemin Sok. No:18 D: 13 Bahariye-kadikoy",
    "sg:city":"Mersin",
    "sg:orig_category":"Environment Technolojy",
    "sg:phone":"+90 216 330 9215",
    "sg:postcode":"33010",
    "sg:province":"Istanbul",
    "wof:name":"Ozgun Cevre Aritma San.tic.ltd.sti.",
    "wof:placetype":"venue"
},
  "geometry": {"coordinates":[28.9861831665,41.0408554077],"type":"Point"}
}