{
  "type": "Feature",
  "properties": {
    "addr:full":"Maya Akar Center Buyukdere Caddesi 100-102 Esentepe Istanbul 01930",
    "addr:postcode":"100-102;01930",
    "addr:street":"Buyukdere Caddesi",
    "iso:country":"TR",
    "sg:address":"Maya Akar Center Buyukdere Caddesi 100-102",
    "sg:city":"Esentepe",
    "sg:classifiers":[
        {
            "category":"Banks & Credit Unions",
            "subcategory":"Investment Brokerage",
            "type":"Services"
        }
    ],
    "sg:phone":"+90 212 288 0855",
    "sg:postcode":"01930",
    "sg:province":"Istanbul",
    "sg:tags":[
        "line",
        "air"
    ],
    "wof:name":"Lufthansa",
    "wof:placetype":"venue"
},
  "geometry": {"coordinates":[28.9759254456,41.0123786926],"type":"Point"}
}