{
  "type": "Feature",
  "properties": {
    "addr:full":"Beymersan San.sitesi 10.cad. No:15 Beylikd?? Istanbul Zeytinburnu Istanbul 34020",
    "addr:housenumber":"no 15;? ?",
    "addr:postcode":"34020",
    "addr:street":"Beylikd",
    "iso:country":"TR",
    "sg:address":"Beymersan San.sitesi 10.cad. No:15 Beylikd?? Istanbul",
    "sg:city":"Zeytinburnu",
    "sg:classifiers":[
        {
            "category":"Manufacturing",
            "subcategory":"Leather Goods",
            "type":"Manufacturing & Wholesale Goods"
        }
    ],
    "sg:phone":"+90 212 875 0696",
    "sg:postcode":"34020",
    "sg:province":"Istanbul",
    "wof:name":"Asil Plastik Suni Deri San.ve Tic.a.s",
    "wof:placetype":"venue"
},
  "geometry": {"coordinates":[28.9026374817,40.9924430847],"type":"Point"}
}