{
  "type": "Feature",
  "properties": {
    "addr:full":"Eskis?merbank Cad.3/h Merkez Isparta 32100",
    "addr:postcode":"32100",
    "iso:country":"TR",
    "sg:address":"Eskis?merbank Cad.3/h",
    "sg:city":"Merkez",
    "sg:classifiers":[
        {
            "category":"Wholesale",
            "subcategory":"Medical Equipment & Supplies",
            "type":"Manufacturing & Wholesale Goods"
        }
    ],
    "sg:phone":"+90 246 218 9845",
    "sg:postcode":"32100",
    "sg:province":"Isparta",
    "wof:name":"Ece Dental-medikal",
    "wof:placetype":"venue"
},
  "geometry": {"coordinates":[30.5437049866,37.7885932922],"type":"Point"}
}