{
  "type": "Feature",
  "properties": {
    "addr:full":"Ardi?sk.no.1 Merter Istanbul",
    "addr:housenumber":"?",
    "addr:street":"Sk.No.1 Merter",
    "iso:country":"TR",
    "sg:address":"Ardi?sk.no.1",
    "sg:city":"Merter",
    "sg:classifiers":[
        {
            "category":"Shopping",
            "subcategory":"Clothing, Apparel, & Fashions",
            "type":"Retail Goods"
        }
    ],
    "sg:phone":"+90 212 637 2193",
    "sg:province":"Istanbul",
    "sg:tags":[
        "ready",
        "wear"
    ],
    "wof:name":"Metse Tekstil Ltd.sti.",
    "wof:placetype":"venue"
},
  "geometry": {"coordinates":[29.0547733307,40.9090957642],"type":"Point"}
}