{
  "type": "Feature",
  "properties": {
    "addr:full":"K?r?asi Cd. Verem Savas Sit. No:134/10 Sisli Eskisehir 34620",
    "addr:housenumber":"sit. no 134 / 10",
    "addr:postcode":"34620",
    "addr:street":"Asi Cd. Verem;Eskisehir",
    "iso:country":"TR",
    "sg:address":"K?r?asi Cd. Verem Savas Sit. No:134/10",
    "sg:city":"Sisli",
    "sg:classifiers":[
        {
            "category":"Mining & Drilling",
            "type":"Manufacturing & Wholesale Goods"
        }
    ],
    "sg:phone":"+90 222",
    "sg:postcode":"34620",
    "sg:province":"Eskisehir",
    "sg:tags":[
        "industry",
        "mine"
    ],
    "wof:name":"G?n Madenci. San. Tic. Ltd. Sti.",
    "wof:placetype":"venue"
},
  "geometry": {"coordinates":[30.5175457001,39.7700805664],"type":"Point"}
}