{
  "type": "Feature",
  "properties": {
    "addr:full":"Silahsor Cad. 33/a Sisli Bagdat Cad. 265/2 Goztepe Istanbul 01220",
    "addr:housenumber":"33 / a;265 / 2",
    "addr:postcode":"01220",
    "addr:street":"Silahsor Cad.;Sisli Bagdat Cad.",
    "iso:country":"TR",
    "sg:address":"Silahsor Cad. 33/a Sisli Bagdat Cad. 265/2",
    "sg:city":"Goztepe",
    "sg:classifiers":[
        {
            "category":"Shopping",
            "subcategory":"Clothing, Apparel, & Fashions",
            "type":"Retail Goods"
        }
    ],
    "sg:phone":"+90 212 231 0217",
    "sg:postcode":"01220",
    "sg:province":"Istanbul",
    "sg:tags":[
        "ready",
        "wear"
    ],
    "wof:name":"Senocak Sapka Tekstil Ve Konf. San.tic.ltd.sti.",
    "wof:placetype":"venue"
},
  "geometry": {"coordinates":[29.0103721619,41.0228996277],"type":"Point"}
}