{
  "type": "Feature",
  "properties": {
    "iso:country":"TR",
    "sg:address":"Atat?k C 77 Vize",
    "sg:city":"Istanbul",
    "sg:classifiers":[
        {
            "category":"Banks & Credit Unions",
            "subcategory":"Bank",
            "type":"Services"
        }
    ],
    "sg:phone":"+90 386 712 1079",
    "sg:province":"Kirklareli",
    "wof:name":"Tc Ziraat Bankasi",
    "wof:placetype":"venue"
},
  "geometry": {"coordinates":[27.7644,41.5755],"type":"Point"}
}