{
  "type": "Feature",
  "properties": {
    "addr:full":"1145/10. Sk. No:2 Yenisehir Besiktas Izmir 34350",
    "addr:housenumber":"1145 / 10 sk. no 2",
    "addr:postcode":"34350",
    "addr:street":"Yenisehir Besiktas",
    "iso:country":"TR",
    "sg:address":"1145/10. Sk. No:2 Yenisehir",
    "sg:city":"Besiktas",
    "sg:classifiers":[
        {
            "category":"Banks & Credit Unions",
            "subcategory":"Investment Brokerage",
            "type":"Services"
        }
    ],
    "sg:phone":"+90 232 433 9206",
    "sg:postcode":"34350",
    "sg:province":"Izmir",
    "sg:tags":[
        "-",
        "export",
        "import"
    ],
    "wof:name":"Toyev Dis Tic. Ltd. Sti.",
    "wof:placetype":"venue"
},
  "geometry": {"coordinates":[27.1423015594,38.4251480103],"type":"Point"}
}