{
  "type": "Feature",
  "properties": {
    "addr:full":"Necatibey Cd. Yesilirmak Sk. No:17/20-21 Maltepe Ankara 01000",
    "addr:housenumber":"17 / 20-21",
    "addr:postcode":"01000",
    "addr:street":"Sk. No",
    "iso:country":"TR",
    "sg:address":"Necatibey Cd. Yesilirmak Sk. No:17/20-21",
    "sg:city":"Maltepe",
    "sg:classifiers":[
        {
            "category":"Manufacturing",
            "subcategory":"Building Materials",
            "type":"Manufacturing & Wholesale Goods"
        }
    ],
    "sg:phone":"+90 312 231 6107",
    "sg:postcode":"01000",
    "sg:province":"Ankara",
    "sg:tags":[
        "lifts-elevators"
    ],
    "wof:name":"Kadim Canpolat Kadim Asans?rleri",
    "wof:placetype":"venue"
},
  "geometry": {"coordinates":[32.8502540588,39.9242782593],"type":"Point"}
}