{
  "type": "Feature",
  "properties": {
    "iso:country":"TR",
    "sg:address":"Ataturk Cad. No:420 Alsancak",
    "sg:city":"Mersin",
    "sg:classifiers":[
        {
            "category":"Home & Garden",
            "subcategory":"Hardware",
            "type":"Retail Goods"
        }
    ],
    "sg:phone":"+90 232464597576",
    "sg:postcode":"52750",
    "sg:province":"Izmir",
    "sg:tags":[
        "compressor",
        "pump"
    ],
    "wof:name":"Maksas Makina Sanayi A.s.",
    "wof:placetype":"venue"
},
  "geometry": {"coordinates":[27.1472473145,38.4394874573],"type":"Point"}
}