{
  "type": "Feature",
  "properties": {
    "addr:full":"Klodfarer Cad. A/33 Sultanahmet \u00dcmraniye Istanbul",
    "addr:housenumber":"a / 33",
    "addr:street":"Klodfarer Cad.",
    "iso:country":"TR",
    "sg:address":"Klodfarer Cad. A/33 Sultanahmet",
    "sg:city":"\u00dcmraniye",
    "sg:classifiers":[
        {
            "category":"Utilities",
            "subcategory":"Fuel Oil & Lpg",
            "type":"Services"
        }
    ],
    "sg:phone":"+90 212 638 0707",
    "sg:province":"Istanbul",
    "sg:tags":[
        "gas",
        "system"
    ],
    "wof:name":"Karakus Gaz Donusum Servisi",
    "wof:placetype":"venue"
},
  "geometry": {"coordinates":[28.9731845856,41.0069618225],"type":"Point"}
}