{
  "type": "Feature",
  "properties": {
    "addr:full":"Nevzat G?g? Cad. No 56 Agri Merkez Agri 04100",
    "addr:housenumber":"? g ?",
    "addr:postcode":"04100",
    "addr:street":"Nevzat G;Cad. No;Agri",
    "iso:country":"TR",
    "sg:address":"Nevzat G?g? Cad. No 56 Agri",
    "sg:city":"Merkez",
    "sg:classifiers":[
        {
            "category":"Utilities",
            "subcategory":"Water",
            "type":"Services"
        }
    ],
    "sg:phone":"+90 472 215 4307",
    "sg:postcode":"04100",
    "sg:province":"Agri",
    "sg:tags":[
        "armature"
    ],
    "wof:name":"Has Teknik Tic.",
    "wof:placetype":"venue"
},
  "geometry": {"coordinates":[43.0519104004,39.7215423584],"type":"Point"}
}