{
  "type": "Feature",
  "properties": {
    "addr:full":"Belediye Arkasi Sok.no: 3 Ivrendi Balikesir",
    "addr:housenumber":"3",
    "addr:street":"Sok.No;Balikesir",
    "iso:country":"TR",
    "sg:address":"Belediye Arkasi Sok.no: 3",
    "sg:city":"Ivrendi",
    "sg:classifiers":[
        {
            "category":"Farming",
            "subcategory":"Farm & Veterinary Services",
            "type":"Manufacturing & Wholesale Goods"
        }
    ],
    "sg:phone":"+90 266456106845",
    "sg:province":"Balikesir",
    "sg:tags":[
        "clinic"
    ],
    "wof:name":"Muhittin Findikli",
    "wof:placetype":"venue"
},
  "geometry": {"coordinates":[27.883301,39.6521],"type":"Point"}
}