{
  "type": "Feature",
  "properties": {
    "addr:full":"Bagdat Cd. Nur Apt. No:65 D:13 Kadik? B.cekmece Istanbul",
    "addr:housenumber":"d;?",
    "addr:street":"Bagdat Cd.;13 Kadik",
    "iso:country":"TR",
    "sg:address":"Bagdat Cd. Nur Apt. No:65 D:13 Kadik?",
    "sg:city":"B.cekmece",
    "sg:classifiers":[
        {
            "category":"Building & Trades",
            "subcategory":"Construction",
            "type":"Services"
        }
    ],
    "sg:phone":"+90 216 337 7174",
    "sg:province":"Istanbul",
    "sg:tags":[
        "foundation"
    ],
    "wof:name":"Yayinlari Ceviri Vakfi",
    "wof:placetype":"venue"
},
  "geometry": {"coordinates":[28.9759254456,41.0123786926],"type":"Point"}
}