{
  "type": "Feature",
  "properties": {
    "iso:country":"TR",
    "sg:address":"Mehtap Sk. No. 11",
    "sg:city":"Sefak?",
    "sg:classifiers":[
        {
            "category":"Shopping",
            "subcategory":"Clothing, Apparel, & Fashions",
            "type":"Retail Goods"
        }
    ],
    "sg:phone":"+90 212 580 2802",
    "sg:province":"Istanbul",
    "sg:tags":[
        "ready",
        "wear"
    ],
    "wof:name":"Bozaci Teks.konf.ltd.sti.",
    "wof:placetype":"venue"
},
  "geometry": {"coordinates":[29.0953807831,41.0535011292],"type":"Point"}
}