{
  "type": "Feature",
  "properties": {
    "addr:full":"Yavuzselim Mah. Y?sel Sok. No:32 Yildirim Bursa 16280",
    "addr:housenumber":"no 32",
    "addr:postcode":"16280",
    "addr:street":"Yavuzselim Mah. Y ? Sel Sok.;Bursa",
    "iso:country":"TR",
    "sg:address":"Yavuzselim Mah. Y?sel Sok. No:32",
    "sg:city":"Yildirim",
    "sg:classifiers":[
        {
            "category":"Shopping",
            "subcategory":"Crafts & Fabrics",
            "type":"Retail Goods"
        }
    ],
    "sg:phone":"+90 224367864748",
    "sg:postcode":"16280",
    "sg:province":"Bursa",
    "sg:tags":[
        "knitting"
    ],
    "wof:name":"?zensoy Tekstil San. Tic. Ltd.sti",
    "wof:placetype":"venue"
},
  "geometry": {"coordinates":[29.0798435211,40.199962616],"type":"Point"}
}