{
  "type": "Feature",
  "properties": {
    "addr:full":"Yeni Sehir Mah. 14.sok. Zulkadiroglu Apt.kat:5 No:16 Ikitelli Kahramanmaras 34306",
    "addr:housenumber":"14.sok;5 no 16",
    "addr:postcode":"34306",
    "addr:street":"Sehir Mah.;Apt.Kat;Kahramanmaras",
    "iso:country":"TR",
    "sg:address":"Yeni Sehir Mah. 14.sok. Zulkadiroglu Apt.kat:5 No:16",
    "sg:city":"Ikitelli",
    "sg:classifiers":[
        {
            "category":"Manufacturing",
            "subcategory":"Textiles",
            "type":"Manufacturing & Wholesale Goods"
        }
    ],
    "sg:phone":"+90 344 223 5590",
    "sg:postcode":"34306",
    "sg:province":"Kahramanmaras",
    "sg:tags":[
        "machinery"
    ],
    "wof:name":"As Dahili Tic.-tekstil Makina Ticareti",
    "wof:placetype":"venue"
},
  "geometry": {"coordinates":[36.9280776978,37.5858345032],"type":"Point"}
}