{
  "type": "Feature",
  "properties": {
    "addr:full":"Milli Mudafa Cad. No: 16 Kizilay Marmaris Ankara 48700",
    "addr:housenumber":"16",
    "addr:postcode":"48700",
    "addr:street":"Mudafa Cad. No",
    "iso:country":"TR",
    "sg:address":"Milli Mudafa Cad. No: 16 Kizilay",
    "sg:city":"Marmaris",
    "sg:orig_category":"Hotels: Motels",
    "sg:phone":"+90 312 419 0400",
    "sg:postcode":"48700",
    "sg:province":"Ankara",
    "wof:name":"Ankara Mersin Hoteli",
    "wof:placetype":"venue"
},
  "geometry": {"coordinates":[32.8604812622,39.9429283142],"type":"Point"}
}