{
  "type": "Feature",
  "properties": {
    "addr:full":"Fatih Cd. Ceviz Sk. No:3/1 Merter Kizilay Istanbul 06650",
    "addr:housenumber":"1",
    "addr:postcode":"06650",
    "addr:street":"Fatih;Ceviz Sk. No 3 /",
    "iso:country":"TR",
    "sg:address":"Fatih Cd. Ceviz Sk. No:3/1 Merter",
    "sg:city":"Kizilay",
    "sg:classifiers":[
        {
            "category":"Shopping",
            "subcategory":"Stationery & Office Supplies",
            "type":"Retail Goods"
        }
    ],
    "sg:phone":"+90 212 637 3148",
    "sg:postcode":"06650",
    "sg:province":"Istanbul",
    "wof:name":"Osman Kirtasiye Ve Bilg. Malz. San. Ltd. Sti.",
    "wof:placetype":"venue"
},
  "geometry": {"coordinates":[28.883204,41.013035],"type":"Point"}
}