{
  "type": "Feature",
  "properties": {
    "iso:country":"TR",
    "sg:address":"Gures Cad.barinlar Pasaji Kat.2 No:3",
    "sg:city":"Maltepe",
    "sg:classifiers":[
        {
            "category":"Health Services",
            "subcategory":"Clinic",
            "type":"Services"
        }
    ],
    "sg:phone":"+90 484 223 2992",
    "sg:postcode":"01000",
    "sg:province":"Siirt",
    "wof:name":"?e Sa Medikal",
    "wof:placetype":"venue"
},
  "geometry": {"coordinates":[41.9430389404,37.9270439148],"type":"Point"}
}