{
  "type": "Feature",
  "properties": {
    "iso:country":"TR",
    "sg:address":"Ankaracad. No:1 Cagaloglu",
    "sg:city":"Goztepe",
    "sg:classifiers":[
        {
            "category":"Government",
            "subcategory":"Embassy",
            "type":"Public Place"
        }
    ],
    "sg:phone":"+90 212 513 8230",
    "sg:postcode":"01220",
    "sg:province":"Istanbul",
    "sg:tags":[
        "foreign"
    ],
    "wof:name":"Iran",
    "wof:placetype":"venue"
},
  "geometry": {"coordinates":[28.9749889374,41.0122528076],"type":"Point"}
}