{
  "type": "Feature",
  "properties": {
    "iso:country":"TR",
    "sg:address":"Ege Serbest Bolgesi Ayhan Sok.no:12a-2/f Gaziemir",
    "sg:city":"Ikitelli/K\u00fc\u00e7\u00fck\u00e7ekmece",
    "sg:classifiers":[
        {
            "category":"Manufacturing",
            "subcategory":"Rubber & Plastics",
            "type":"Manufacturing & Wholesale Goods"
        }
    ],
    "sg:phone":"+90 232 252 3723",
    "sg:postcode":"34670",
    "sg:province":"Izmir",
    "sg:tags":[
        "industry"
    ],
    "wof:name":"Gema Elektro Plastik Ve Elektronik San.dis Tic. A.s.",
    "wof:placetype":"venue"
},
  "geometry": {"coordinates":[27.1296863556,38.4186973572],"type":"Point"}
}