{
  "type": "Feature",
  "properties": {
    "iso:country":"TR",
    "sg:address":"Ethemefendi Cd.no1",
    "sg:city":"Erenk?",
    "sg:classifiers":[
        {
            "category":"Freight",
            "type":"Transportation"
        }
    ],
    "sg:phone":"+90 216 363 6877",
    "sg:province":"Istanbul",
    "sg:tags":[
        "agent",
        "shipping",
        "broker"
    ],
    "wof:name":"Omar Denizcilik Ltd.sti.",
    "wof:placetype":"venue"
},
  "geometry": {"coordinates":[28.975925,41.012379],"type":"Point"}
}