{
  "type": "Feature",
  "properties": {
    "addr:full":"1399. Sk. No:3/2 Alsancak Sihhiye Izmir 06120",
    "addr:housenumber":"1399;2",
    "addr:postcode":"06120",
    "addr:street":"Sk. No 3 /",
    "iso:country":"TR",
    "sg:address":"1399. Sk. No:3/2 Alsancak",
    "sg:city":"Sihhiye",
    "sg:classifiers":[
        {
            "category":"Wholesale",
            "subcategory":"Medical Equipment & Supplies",
            "type":"Manufacturing & Wholesale Goods"
        }
    ],
    "sg:phone":"+90 232 463 4924",
    "sg:postcode":"06120",
    "sg:province":"Izmir",
    "sg:tags":[
        "material"
    ],
    "wof:name":"Bilim Tibbi Urn. Ltd. Sti.",
    "wof:placetype":"venue"
},
  "geometry": {"coordinates":[27.1423015594,38.4251480103],"type":"Point"}
}