{
  "type": "Feature",
  "properties": {
    "addr:full":"H.ulusahin Is Merkezi A.blok No:626 Sel?klu Konya",
    "addr:postcode":"626;? klu",
    "addr:street":"A.Blok No",
    "iso:country":"TR",
    "sg:address":"H.ulusahin Is Merkezi A.blok No:626",
    "sg:city":"Sel?klu",
    "sg:classifiers":[
        {
            "category":"Professional",
            "subcategory":"Computer Services",
            "type":"Services"
        }
    ],
    "sg:phone":"+90 332 238 1983",
    "sg:province":"Konya",
    "sg:tags":[
        "application",
        "software"
    ],
    "wof:name":"Allegro Yazilim A.s.",
    "wof:placetype":"venue"
},
  "geometry": {"coordinates":[33.0667152405,39.2111282349],"type":"Point"}
}