{
  "type": "Feature",
  "properties": {
    "iso:country":"TR",
    "sg:address":"Taskopru Cad. No:4 Nizip/izmir",
    "sg:city":"Bak\u0131rk\u00f6y",
    "sg:classifiers":[
        {
            "category":"Shopping",
            "type":"Retail Goods"
        }
    ],
    "sg:phone":"+90 342 513 0098",
    "sg:province":"Gaziantep",
    "sg:tags":[
        "material",
        "cleaning"
    ],
    "wof:name":"N.filik Sabun Ve Mercimek San.tic.pet.urun.tic.nak.ltd.sti.",
    "wof:placetype":"venue"
},
  "geometry": {"coordinates":[37.3781585693,37.0629310608],"type":"Point"}
}