{
  "type": "Feature",
  "properties": {
    "addr:full":"Aydintepe Mh.dostlaroglu Sk.no21/a Pendik Istanbul 34916",
    "addr:housenumber":"a",
    "addr:postcode":"34916",
    "iso:country":"TR",
    "sg:address":"Aydintepe Mh.dostlaroglu Sk.no21/a",
    "sg:city":"Pendik",
    "sg:classifiers":[
        {
            "category":"Bars & Pubs",
            "subcategory":"Nightclub",
            "type":"Food & Drink"
        }
    ],
    "sg:phone":"+90 216 392 2010",
    "sg:postcode":"34916",
    "sg:province":"Istanbul",
    "sg:tags":[
        "oprerators",
        "pier",
        "jetty"
    ],
    "wof:name":"May Gemi Tic.ltd.sti.",
    "wof:placetype":"venue"
},
  "geometry": {"coordinates":[28.9759254456,41.0123786926],"type":"Point"}
}