{
  "type": "Feature",
  "properties": {
    "iso:country":"TR",
    "sg:address":"1201 Sok. No:15 B Teknik Is Merkezi",
    "sg:city":"Yenisehir",
    "sg:classifiers":[
        {
            "category":"Manufacturing",
            "subcategory":"Building Materials",
            "type":"Manufacturing & Wholesale Goods"
        }
    ],
    "sg:phone":"+90 232 458 6464",
    "sg:postcode":"31750",
    "sg:province":"Izmir",
    "sg:tags":[
        "lifts-elevators"
    ],
    "wof:name":"Seckin Asansor Malzemeleri San Ve Tic Ltd Sti",
    "wof:placetype":"venue"
},
  "geometry": {"coordinates":[27.1296863556,38.4186973572],"type":"Point"}
}