{
  "type": "Feature",
  "properties": {
    "addr:full":"?rnek Cad.no:12 Kas Denizli 07580",
    "addr:housenumber":"?;12",
    "addr:postcode":"07580",
    "addr:street":"Rnek Cad.No",
    "iso:country":"TR",
    "sg:address":"?rnek Cad.no:12",
    "sg:city":"Kas",
    "sg:orig_category":"Hotels: Motels",
    "sg:phone":"+90 25826328982",
    "sg:postcode":"07580",
    "sg:province":"Denizli",
    "wof:name":"Ekinci Hotel",
    "wof:placetype":"venue"
},
  "geometry": {"coordinates":[29.0788803101,37.7851867676],"type":"Point"}
}