{
  "type": "Feature",
  "properties": {
    "addr:full":"Ziyabey Cad. No:36 Balgat Ankara 63510",
    "addr:housenumber":"36",
    "addr:postcode":"63510",
    "addr:street":"Ziyabey Cad. No",
    "iso:country":"TR",
    "sg:address":"Ziyabey Cad. No:36",
    "sg:city":"Balgat",
    "sg:classifiers":[
        {
            "category":"Organizations",
            "subcategory":"Non-profit Organization",
            "type":"Services"
        }
    ],
    "sg:phone":"+90 312 287 1737",
    "sg:postcode":"63510",
    "sg:province":"Ankara",
    "sg:tags":[
        "alarm",
        "system"
    ],
    "wof:name":"Simge&savesa Elektronik G?venlik Sistemleri San.",
    "wof:placetype":"venue"
},
  "geometry": {"coordinates":[29.2253704071,40.9020652771],"type":"Point"}
}