{
  "type": "Feature",
  "properties": {
    "addr:full":"Demirbas Sk. No:3 Tarlabasi Beyoglu Silivri Istanbul 34570",
    "addr:postcode":"34570",
    "addr:street":"Demirbas Sk. No 3 Tarlabasi Beyoglu",
    "iso:country":"TR",
    "sg:address":"Demirbas Sk. No:3 Tarlabasi Beyoglu",
    "sg:city":"Silivri",
    "sg:orig_category":"General Industrial Products",
    "sg:phone":"+90 212 256 3619",
    "sg:postcode":"34570",
    "sg:province":"Istanbul",
    "wof:name":"Yak-gaz San. Ve Mutfak Cihaz M?essese.",
    "wof:placetype":"venue"
},
  "geometry": {"coordinates":[28.9776115417,41.0364646912],"type":"Point"}
}