{
  "type": "Feature",
  "properties": {
    "addr:full":"Ulus Cd. No: 4 Menemen Izmir 35660",
    "addr:housenumber":"no 4",
    "addr:postcode":"35660",
    "addr:street":"Cd.;Menemen Izmir",
    "iso:country":"TR",
    "sg:address":"Ulus Cd. No: 4",
    "sg:city":"Menemen",
    "sg:classifiers":[
        {
            "category":"Home & Garden",
            "subcategory":"Household Appliances",
            "type":"Retail Goods"
        }
    ],
    "sg:phone":"+90 232 846 1006",
    "sg:postcode":"35660",
    "sg:province":"Izmir",
    "sg:tags":[
        "conditioner",
        "air"
    ],
    "wof:name":"Momet Ltd. Sti.",
    "wof:placetype":"venue"
},
  "geometry": {"coordinates":[26.4659729004,38.3526954651],"type":"Point"}
}