{
  "type": "Feature",
  "properties": {
    "addr:full":"Ankara Asf. 6 Km Ikitelli/K\u00fc\u00e7\u00fck\u00e7ekmece ?orum 34670",
    "addr:housenumber":"6 km",
    "addr:postcode":"34670",
    "addr:street":"Asf.;Ikitelli",
    "iso:country":"TR",
    "sg:address":"Ankara Asf. 6 Km",
    "sg:city":"Ikitelli/K\u00fc\u00e7\u00fck\u00e7ekmece",
    "sg:classifiers":[
        {
            "category":"Home & Garden",
            "subcategory":"Kitchen Supply",
            "type":"Retail Goods"
        }
    ],
    "sg:phone":"+90 364 235 0101",
    "sg:postcode":"34670",
    "sg:province":"?orum",
    "sg:tags":[
        "wardrobe"
    ],
    "wof:name":"Mas Mutfak Banyo Ofis",
    "wof:placetype":"venue"
},
  "geometry": {"coordinates":[32.8560333252,39.9438743591],"type":"Point"}
}