{
  "type": "Feature",
  "properties": {
    "addr:full":"Kucukbahce Sok. No:29/a Sisli Istanbul 65710",
    "addr:housenumber":"no 29 / a",
    "addr:postcode":"65710",
    "addr:street":"Kucukbahce Sok.",
    "iso:country":"TR",
    "sg:address":"Kucukbahce Sok. No:29/a",
    "sg:city":"Sisli",
    "sg:classifiers":[
        {
            "category":"Shopping",
            "subcategory":"Clothing, Apparel, & Fashions",
            "type":"Retail Goods"
        }
    ],
    "sg:phone":"+90 212 296 9658",
    "sg:postcode":"65710",
    "sg:province":"Istanbul",
    "sg:tags":[
        "ready",
        "wear"
    ],
    "wof:name":"Dogruoz Giy.teks. San.tic. A.s.",
    "wof:placetype":"venue"
},
  "geometry": {"coordinates":[28.9759254456,41.0123786926],"type":"Point"}
}