{
  "type": "Feature",
  "properties": {
    "addr:full":"Halaskargazi Cad. Sima Apt. 270/8 Sisli Gaziosmanpasa Istanbul 06700",
    "addr:housenumber":"270 / 8",
    "addr:postcode":"06700",
    "addr:street":"Halaskargazi Cad. Sima Apt.",
    "iso:country":"TR",
    "sg:address":"Halaskargazi Cad. Sima Apt. 270/8 Sisli",
    "sg:city":"Gaziosmanpasa",
    "sg:classifiers":[
        {
            "category":"Professional",
            "subcategory":"Computer Services",
            "type":"Services"
        }
    ],
    "sg:phone":"+90 212 296 8625",
    "sg:postcode":"06700",
    "sg:province":"Istanbul",
    "sg:tags":[
        "application",
        "software"
    ],
    "wof:name":"Boyut Multimedya",
    "wof:placetype":"venue"
},
  "geometry": {"coordinates":[28.9861831665,41.0408554077],"type":"Point"}
}