{
  "type": "Feature",
  "properties": {
    "addr:full":"Gazcilar Petek Bozkaya Is Merkezi B- Blok No :205 Osmangazi Bursa 16220",
    "addr:postcode":"16220",
    "iso:country":"TR",
    "sg:address":"Gazcilar Petek Bozkaya Is Merkezi B- Blok No :205",
    "sg:city":"Osmangazi",
    "sg:classifiers":[
        {
            "category":"Wholesale",
            "subcategory":"Machinery & Supplies",
            "type":"Manufacturing & Wholesale Goods"
        }
    ],
    "sg:phone":"+90 224 272 8777",
    "sg:postcode":"16220",
    "sg:province":"Bursa",
    "sg:tags":[
        "laboratory",
        "equipment"
    ],
    "wof:name":"Tip-lab",
    "wof:placetype":"venue"
},
  "geometry": {"coordinates":[29.0692653656,40.1923217773],"type":"Point"}
}