{
  "type": "Feature",
  "properties": {
    "addr:full":"Belediye Is Merkezi Kat:3 No:51 Develi Iskenderun Kayseri 31200",
    "addr:housenumber":"kat 3 no 51",
    "addr:postcode":"31200",
    "iso:country":"TR",
    "sg:address":"Belediye Is Merkezi Kat:3 No:51 Develi",
    "sg:city":"Iskenderun",
    "sg:classifiers":[
        {
            "category":"Mining & Drilling",
            "type":"Manufacturing & Wholesale Goods"
        }
    ],
    "sg:phone":"+90 352 621 1802",
    "sg:postcode":"31200",
    "sg:province":"Kayseri",
    "sg:tags":[
        "industry",
        "mine"
    ],
    "wof:name":"Doganay Madencilik Ltd.sti.",
    "wof:placetype":"venue"
},
  "geometry": {"coordinates":[35.4891357422,38.7225761414],"type":"Point"}
}