{
  "type": "Feature",
  "properties": {
    "addr:full":"Bati Mah.kizilay Cad. No:1/b Pendik Istanbul 34916",
    "addr:housenumber":"b",
    "addr:postcode":"34916",
    "addr:street":"Mah.Kizilay Cad. No 1 /",
    "iso:country":"TR",
    "sg:address":"Bati Mah.kizilay Cad. No:1/b",
    "sg:city":"Pendik",
    "sg:classifiers":[
        {
            "category":"Farming",
            "subcategory":"Farm & Veterinary Services",
            "type":"Manufacturing & Wholesale Goods"
        }
    ],
    "sg:phone":"+90 216 390 9317",
    "sg:postcode":"34916",
    "sg:province":"Istanbul",
    "sg:tags":[
        "veterinarian"
    ],
    "wof:name":"Asya Veterinerlik Hizmetleri Tic.ltd.sti.",
    "wof:placetype":"venue"
},
  "geometry": {"coordinates":[29.2258319855,40.8796043396],"type":"Point"}
}