{
  "type": "Feature",
  "properties": {
    "iso:country":"TR",
    "sg:address":"Camli",
    "sg:city":"Guzelbahce",
    "sg:classifiers":[
        {
            "category":"Food & Beverages",
            "subcategory":"Groceries & Convenience Stores",
            "type":"Retail Goods"
        }
    ],
    "sg:phone":"+90 232 236 7840",
    "sg:postcode":"35310",
    "sg:province":"Izmir",
    "sg:tags":[
        "ready"
    ],
    "wof:name":"Pratik Hazir Yemek Gida San. Ve Dis. Tic.ltd.sti.",
    "wof:placetype":"venue"
},
  "geometry": {"coordinates":[27.1670608521,38.3728065491],"type":"Point"}
}