{
  "type": "Feature",
  "properties": {
    "addr:full":"Sefa Cd. 8. Sk. No:13 Ayvalik Balikesir 01680",
    "addr:housenumber":"8",
    "addr:postcode":"01680",
    "addr:street":"Cd.;No 13 Ayvalik Balikesir",
    "iso:country":"TR",
    "sg:address":"Sefa Cd. 8. Sk. No:13",
    "sg:city":"Ayvalik",
    "sg:classifiers":[
        {
            "category":"Wholesale",
            "subcategory":"Machinery & Supplies",
            "type":"Manufacturing & Wholesale Goods"
        }
    ],
    "sg:phone":"+90 266 312 1812",
    "sg:postcode":"01680",
    "sg:province":"Balikesir",
    "sg:tags":[
        "agricultural"
    ],
    "wof:name":"Ege Makina At?lyesi",
    "wof:placetype":"venue"
},
  "geometry": {"coordinates":[26.6690616608,39.3295478821],"type":"Point"}
}