{
  "type": "Feature",
  "properties": {
    "iso:country":"TR",
    "sg:address":"K.ihsaniye Mah.haci Mehmet Sok. No:9/a",
    "sg:city":"Mersin",
    "sg:classifiers":[
        {
            "category":"Professional",
            "subcategory":"Business Services",
            "type":"Services"
        }
    ],
    "sg:phone":"+90 332 321 8913",
    "sg:postcode":"52750",
    "sg:province":"Konya",
    "sg:tags":[
        "food",
        "product",
        "exporter",
        "aricultural"
    ],
    "wof:name":"Aysberk Ltd",
    "wof:placetype":"venue"
},
  "geometry": {"coordinates":[32.4822463989,37.8756103516],"type":"Point"}
}