{
  "type": "Feature",
  "properties": {
    "iso:country":"TR",
    "sg:address":"Hoca Hanim Sk. No:16/3 Karak?",
    "sg:city":"Kozyatagi",
    "sg:classifiers":[
        {
            "category":"Manufacturing",
            "subcategory":"Metals",
            "type":"Manufacturing & Wholesale Goods"
        }
    ],
    "sg:phone":"+90 212 255 6114",
    "sg:postcode":"34742",
    "sg:province":"Istanbul",
    "sg:tags":[
        "iron-steel",
        "peoducts"
    ],
    "wof:name":"Tufan Demir ?elik San. Tic. A.s.",
    "wof:placetype":"venue"
},
  "geometry": {"coordinates":[29.0954437256,40.9691467285],"type":"Point"}
}