{
  "type": "Feature",
  "properties": {
    "addr:full":"Baksan San. Sitesi 20.blok B\u00fcy\u00fck\u00e7ekmece Eskisehir 34905",
    "addr:postcode":"34905",
    "addr:street":"Baksan;Eskisehir",
    "iso:country":"TR",
    "sg:address":"Baksan San. Sitesi 20.blok",
    "sg:city":"B\u00fcy\u00fck\u00e7ekmece",
    "sg:classifiers":[
        {
            "category":"Manufacturing",
            "subcategory":"Tools & Machinery",
            "type":"Manufacturing & Wholesale Goods"
        }
    ],
    "sg:phone":"+90 222 340 0250",
    "sg:postcode":"34905",
    "sg:province":"Eskisehir",
    "sg:tags":[
        "machine",
        "industry"
    ],
    "wof:name":"Perit Makina A.s.",
    "wof:placetype":"venue"
},
  "geometry": {"coordinates":[30.5175457001,39.7700805664],"type":"Point"}
}