{
  "type": "Feature",
  "properties": {
    "iso:country":"TR",
    "sg:address":"Cumhuriyet Mah. Bankalar Cad. No:34/a K:2",
    "sg:city":"Adapazari",
    "sg:classifiers":[
        {
            "category":"Travel",
            "subcategory":"Travel Agent",
            "type":"Entertainment"
        }
    ],
    "sg:phone":"+90 264 273 9743",
    "sg:postcode":"54000",
    "sg:province":"Sakarya",
    "sg:tags":[
        "agency",
        "tourism"
    ],
    "wof:name":"Toprak Turizm ( Adapazari Sb.)",
    "wof:placetype":"venue"
},
  "geometry": {"coordinates":[30.3791446686,40.7734336853],"type":"Point"}
}