{
  "type": "Feature",
  "properties": {
    "addr:full":"Imes San. Sit. A Blok 101 Sk. No:42 ?mraniye Kabatas Istanbul 34427",
    "addr:housenumber":"blok 101;42 ?",
    "addr:postcode":"34427",
    "addr:street":"Sk. No;Mraniye Kabatas",
    "iso:country":"TR",
    "sg:address":"Imes San. Sit. A Blok 101 Sk. No:42 ?mraniye",
    "sg:city":"Kabatas",
    "sg:classifiers":[
        {
            "category":"Manufacturing",
            "subcategory":"Tools & Machinery",
            "type":"Manufacturing & Wholesale Goods"
        }
    ],
    "sg:phone":"+90 216 364 5443",
    "sg:postcode":"34427",
    "sg:province":"Istanbul",
    "sg:tags":[
        "machine",
        "industry"
    ],
    "wof:name":"Birlik-is Makina San. Tic.",
    "wof:placetype":"venue"
},
  "geometry": {"coordinates":[28.9899768829,41.0330963135],"type":"Point"}
}