{
  "type": "Feature",
  "properties": {
    "iso:country":"TR",
    "sg:address":"Nisanca Cad. No:5/a",
    "sg:city":"Fatih",
    "sg:classifiers":[
        {
            "category":"Shopping",
            "subcategory":"Baby Store",
            "type":"Retail Goods"
        }
    ],
    "sg:phone":"+90 212 525 3719",
    "sg:postcode":"01740",
    "sg:province":"Istanbul",
    "sg:tags":[
        "wear"
    ],
    "wof:name":"Feyza Bebe",
    "wof:placetype":"venue"
},
  "geometry": {"coordinates":[28.930483,41.042278],"type":"Point"}
}