{
  "type": "Feature",
  "properties": {
    "addr:full":"Davutpasa Cd. No:133 Topkapi Maltepe Istanbul 01000",
    "addr:housenumber":"no",
    "addr:postcode":"01000",
    "addr:street":"Davutpasa Cd.;Topkapi Maltepe Istanbul",
    "iso:country":"TR",
    "sg:address":"Davutpasa Cd. No:133 Topkapi",
    "sg:city":"Maltepe",
    "sg:classifiers":[
        {
            "category":"Wholesale",
            "subcategory":"Books, Periodicals, & Newspapers",
            "type":"Manufacturing & Wholesale Goods"
        }
    ],
    "sg:phone":"+90 212 577 0531",
    "sg:postcode":"01000",
    "sg:province":"Istanbul",
    "sg:tags":[
        "house",
        "publishing"
    ],
    "wof:name":"Resim Matbaaci. San. Tic. A.s.",
    "wof:placetype":"venue"
},
  "geometry": {"coordinates":[28.9058895111,41.0204277039],"type":"Point"}
}