{
  "type": "Feature",
  "properties": {
    "addr:full":"Zafer Mh. No:38 G??ler \u00dcmraniye Denizli 81260",
    "addr:housenumber":"g ? ?",
    "addr:postcode":"81260",
    "iso:country":"TR",
    "sg:address":"Zafer Mh. No:38 G??ler",
    "sg:city":"\u00dcmraniye",
    "sg:classifiers":[
        {
            "category":"Manufacturing",
            "subcategory":"Tools & Machinery",
            "type":"Manufacturing & Wholesale Goods"
        }
    ],
    "sg:phone":"+90 258 371 0162",
    "sg:postcode":"81260",
    "sg:province":"Denizli",
    "sg:tags":[
        "machine",
        "industry"
    ],
    "wof:name":"Teksmak Makina",
    "wof:placetype":"venue"
},
  "geometry": {"coordinates":[29.0864906311,37.773525238],"type":"Point"}
}