{
  "type": "Feature",
  "properties": {
    "addr:full":"Top?lar Pasmak? San. Sit. No:392 Demirkapi \u00dcmraniye Istanbul",
    "addr:street":"Demirkapi",
    "iso:country":"TR",
    "sg:address":"Top?lar Pasmak? San. Sit. No:392 Demirkapi",
    "sg:city":"\u00dcmraniye",
    "sg:classifiers":[
        {
            "category":"Manufacturing",
            "subcategory":"Tools & Machinery",
            "type":"Manufacturing & Wholesale Goods"
        }
    ],
    "sg:phone":"+90 212 576 4689",
    "sg:province":"Istanbul",
    "sg:tags":[
        "machine",
        "industry"
    ],
    "wof:name":"Kismet Torna Makina Yedek Par?a San.",
    "wof:placetype":"venue"
},
  "geometry": {"coordinates":[28.8385658264,41.0485267639],"type":"Point"}
}