{
  "type": "Feature",
  "properties": {
    "addr:full":"Ebuzziya Cad. No:57/5 Bakirkoy Bah\u00e7elievler Istanbul 34180",
    "addr:housenumber":"57 / 5",
    "addr:postcode":"34180",
    "addr:street":"Ebuzziya Cad. No;Bakirkoy",
    "iso:country":"TR",
    "sg:address":"Ebuzziya Cad. No:57/5 Bakirkoy",
    "sg:city":"Bah\u00e7elievler",
    "sg:classifiers":[
        {
            "category":"Organizations",
            "subcategory":"Professional Association",
            "type":"Services"
        }
    ],
    "sg:phone":"+90 212",
    "sg:postcode":"34180",
    "sg:province":"Istanbul",
    "sg:tags":[
        "fair"
    ],
    "wof:name":"Marmara Tanitim Fuarcilik Organizasyon Reklam Ve Tic.ltd.sti.",
    "wof:placetype":"venue"
},
  "geometry": {"coordinates":[28.8744506836,40.9773025513],"type":"Point"}
}