{
  "type": "Feature",
  "properties": {
    "iso:country":"TR",
    "sg:address":"Karagoz Cami Arkasi Sadirvan Sk. No: 4",
    "sg:city":"Macunkoy",
    "sg:classifiers":[
        {
            "category":"Manufacturing",
            "subcategory":"Food",
            "type":"Manufacturing & Wholesale Goods"
        }
    ],
    "sg:phone":"+90 274 216 6444",
    "sg:postcode":"06105",
    "sg:province":"K?tahya",
    "sg:tags":[
        "wholesaler"
    ],
    "wof:name":"Ege Gida Iml. Tic. .a.s.",
    "wof:placetype":"venue"
},
  "geometry": {"coordinates":[32.8532714844,39.929309845],"type":"Point"}
}