{
  "type": "Feature",
  "properties": {
    "addr:full":"Dumlupinar Cd. No:31/a Cebeci Besevler Ankara 04100",
    "addr:housenumber":"no 31 / a",
    "addr:postcode":"04100",
    "addr:street":"Dumlupinar Cd.",
    "iso:country":"TR",
    "sg:address":"Dumlupinar Cd. No:31/a Cebeci",
    "sg:city":"Besevler",
    "sg:classifiers":[
        {
            "category":"Shopping",
            "subcategory":"Stationery & Office Supplies",
            "type":"Retail Goods"
        }
    ],
    "sg:phone":"+90 312 363 6722",
    "sg:postcode":"04100",
    "sg:province":"Ankara",
    "sg:tags":[
        "paper"
    ],
    "wof:name":"Bolkan Kagit?ilik Ltd. Sti.",
    "wof:placetype":"venue"
},
  "geometry": {"coordinates":[32.8698730469,39.9310874939],"type":"Point"}
}