{
  "type": "Feature",
  "properties": {
    "iso:country":"TR",
    "sg:address":"Ulubat Sk. No:5 Siteler",
    "sg:city":"07100",
    "sg:classifiers":[
        {
            "category":"Manufacturing",
            "subcategory":"Wood Products",
            "type":"Manufacturing & Wholesale Goods"
        }
    ],
    "sg:phone":"+90 312 435 6137",
    "sg:province":"Ankara",
    "sg:tags":[
        "forest"
    ],
    "wof:name":"Alken Orman ?r?nleri San. Tic. Ltd. Sti.",
    "wof:placetype":"venue"
},
  "geometry": {"coordinates":[29.1220607758,40.2027130127],"type":"Point"}
}