{
  "type": "Feature",
  "properties": {
    "addr:full":"Yelkovan Ismerk. K:4/192 Sariyer Eskisehir 33740",
    "addr:housenumber":"4 / 192",
    "addr:postcode":"33740",
    "addr:street":"Sariyer Eskisehir",
    "iso:country":"TR",
    "sg:address":"Yelkovan Ismerk. K:4/192",
    "sg:city":"Sariyer",
    "sg:classifiers":[
        {
            "category":"Mining & Drilling",
            "type":"Manufacturing & Wholesale Goods"
        }
    ],
    "sg:phone":"+90 222 230 7817",
    "sg:postcode":"33740",
    "sg:province":"Eskisehir",
    "sg:tags":[
        "industry",
        "mine"
    ],
    "wof:name":"?st?ner Madenci. Kimya San. Tic. Ltd. Sti.",
    "wof:placetype":"venue"
},
  "geometry": {"coordinates":[30.5175457001,39.7700805664],"type":"Point"}
}