{
  "type": "Feature",
  "properties": {
    "iso:country":"TR",
    "sg:address":"Alaybey Sok. No:15/a -b",
    "sg:city":"Merter",
    "sg:classifiers":[
        {
            "category":"Shopping",
            "subcategory":"Baby Store",
            "type":"Retail Goods"
        }
    ],
    "sg:phone":"+90 364 224 1266",
    "sg:province":"?orum",
    "sg:tags":[
        "wear"
    ],
    "wof:name":"Celikpinar Tekstil",
    "wof:placetype":"venue"
},
  "geometry": {"coordinates":[34.95789,40.553539],"type":"Point"}
}