{
  "type": "Feature",
  "properties": {
    "addr:full":"Ali?tinkaya Cd. Kinay No:33 Merkez Besiktas Antalya 80630",
    "addr:housenumber":"33",
    "addr:postcode":"80630",
    "addr:street":"Tinkaya Cd. Kinay No",
    "iso:country":"TR",
    "sg:address":"Ali?tinkaya Cd. Kinay No:33 Merkez",
    "sg:city":"Besiktas",
    "sg:classifiers":[
        {
            "category":"Organizations",
            "subcategory":"Membership Organization",
            "type":"Services"
        }
    ],
    "sg:phone":"+90 242 321 6511",
    "sg:postcode":"80630",
    "sg:province":"Antalya",
    "wof:name":"Antalya Rek. Dernegi",
    "wof:placetype":"venue"
},
  "geometry": {"coordinates":[30.7092056274,36.8790512085],"type":"Point"}
}