{
  "type": "Feature",
  "properties": {
    "iso:country":"TR",
    "sg:address":"Atat?k Bul 163",
    "sg:city":"Kayseri",
    "sg:classifiers":[
        {
            "category":"Banks & Credit Unions",
            "subcategory":"Bank",
            "type":"Services"
        }
    ],
    "sg:phone":"+90 41254523",
    "sg:postcode":"63600",
    "sg:province":"Ankara",
    "wof:name":"T?kiye ?gretmenler Bankasi",
    "wof:placetype":"venue"
},
  "geometry": {"coordinates":[32.856033,39.943874],"type":"Point"}
}