{
  "type": "Feature",
  "properties": {
    "iso:country":"TR",
    "sg:address":"Baglar Mh. Kores Cd. No:42/13 G?esli",
    "sg:city":"Y. Bosna",
    "sg:orig_category":"General Industrial Products",
    "sg:phone":"+90 212 550 7269",
    "sg:province":"Istanbul",
    "wof:name":"Colombo Mutfak Kiler Sistem.",
    "wof:placetype":"venue"
},
  "geometry": {"coordinates":[28.9759254456,41.0123786926],"type":"Point"}
}