{
  "type": "Feature",
  "properties": {
    "iso:country":"TR",
    "sg:address":"Kazim K.cd. No:27",
    "sg:city":"Sirinevler",
    "sg:classifiers":[
        {
            "category":"Home & Garden",
            "subcategory":"Household Appliances",
            "type":"Retail Goods"
        }
    ],
    "sg:phone":"+90 212 654 8782",
    "sg:postcode":"15040",
    "sg:province":"Istanbul",
    "sg:tags":[
        "conditioner",
        "air"
    ],
    "wof:name":"Computherm Isi Sistem. Ltd.",
    "wof:placetype":"venue"
},
  "geometry": {"coordinates":[28.9464454651,41.069152832],"type":"Point"}
}