{
  "type": "Feature",
  "properties": {
    "addr:full":"Yenik? Bayrampasa Balikesir 36100",
    "addr:postcode":"36100",
    "addr:street":"Balikesir",
    "iso:country":"TR",
    "sg:address":"Yenik?",
    "sg:city":"Bayrampasa",
    "sg:classifiers":[
        {
            "category":"Manufacturing",
            "subcategory":"Rubber & Plastics",
            "type":"Manufacturing & Wholesale Goods"
        }
    ],
    "sg:phone":"+90 266 274 5224",
    "sg:postcode":"36100",
    "sg:province":"Balikesir",
    "sg:tags":[
        "industry"
    ],
    "wof:name":"T?m D?k?m San. A.s.",
    "wof:placetype":"venue"
},
  "geometry": {"coordinates":[28.0026245117,39.7569541931],"type":"Point"}
}