{
  "type": "Feature",
  "properties": {
    "addr:full":"?anakkale Asf. Incirlipinar Mev. Menemen Sefak?/ K???kmece Izmir",
    "addr:housenumber":"?;? / k ?",
    "addr:street":"Anakkale Asf. Incirlipinar Mev.;Sefak;Kmece",
    "iso:country":"TR",
    "sg:address":"?anakkale Asf. Incirlipinar Mev. Menemen",
    "sg:city":"Sefak?/ K???kmece",
    "sg:classifiers":[
        {
            "category":"Wholesale",
            "subcategory":"Petroleum",
            "type":"Manufacturing & Wholesale Goods"
        }
    ],
    "sg:phone":"+90 232 832 0544",
    "sg:province":"Izmir",
    "wof:name":"Isiksan Kimya Tic. San.",
    "wof:placetype":"venue"
},
  "geometry": {"coordinates":[27.0697994232,38.606098175],"type":"Point"}
}