{
  "type": "Feature",
  "properties": {
    "addr:full":"Istiklal Cad.bulvar Is Hani No:1/30 Kutlukent I?el 55330",
    "addr:housenumber":"30;?",
    "addr:postcode":"55330",
    "addr:street":"Kutlukent I;El",
    "iso:country":"TR",
    "sg:address":"Istiklal Cad.bulvar Is Hani No:1/30",
    "sg:city":"Kutlukent",
    "sg:classifiers":[
        {
            "category":"Wholesale",
            "subcategory":"Farm Supplies",
            "type":"Manufacturing & Wholesale Goods"
        }
    ],
    "sg:phone":"+90 324 238 1830",
    "sg:postcode":"55330",
    "sg:province":"I?el",
    "sg:tags":[
        "feed",
        "industry"
    ],
    "wof:name":"Savas Yem Sanayi Ve Tic.ltd.sti.",
    "wof:placetype":"venue"
},
  "geometry": {"coordinates":[36.0349197388,41.2913398743],"type":"Point"}
}