{
  "type": "Feature",
  "properties": {
    "iso:country":"TR",
    "sg:address":"Resit Pasa Cad No: 36",
    "sg:city":"Avcilar",
    "sg:classifiers":[
        {
            "category":"Shopping",
            "subcategory":"Shoes",
            "type":"Retail Goods"
        }
    ],
    "sg:phone":"+90 212 590 9971",
    "sg:postcode":"34840",
    "sg:province":"Istanbul",
    "wof:name":"Eren Kundura",
    "wof:placetype":"venue"
},
  "geometry": {"coordinates":[28.725166,40.979252],"type":"Point"}
}