{
  "type": "Feature",
  "properties": {
    "addr:full":"Rasimpasa Mah. Kasimaga Sok. Demirhan No:7/1 Kadikoy K.?kmece Istanbul",
    "addr:housenumber":"demirhan;1",
    "addr:postcode":"?",
    "addr:street":"Rasimpasa Mah. Kasimaga Sok.;No 7 /",
    "iso:country":"TR",
    "sg:address":"Rasimpasa Mah. Kasimaga Sok. Demirhan No:7/1 Kadikoy",
    "sg:city":"K.?kmece",
    "sg:classifiers":[
        {
            "category":"Insurance",
            "subcategory":"Hazard Insurance",
            "type":"Services"
        }
    ],
    "sg:phone":"+90 216449126263",
    "sg:province":"Istanbul",
    "wof:name":"Onlem Sigorta",
    "wof:placetype":"venue"
},
  "geometry": {"coordinates":[29.0294399261,40.9855613708],"type":"Point"}
}