{
  "type": "Feature",
  "properties": {
    "addr:full":"Ihlamurdere Cd. Yaveraga Sk. No:4 Besiktas Istanbul 75200",
    "addr:postcode":"75200",
    "addr:street":"Ihlamurdere Cd. Yaveraga Sk. No 4",
    "iso:country":"TR",
    "sg:address":"Ihlamurdere Cd. Yaveraga Sk. No:4",
    "sg:city":"Besiktas",
    "sg:classifiers":[
        {
            "category":"Utilities",
            "subcategory":"Natural Gas",
            "type":"Services"
        }
    ],
    "sg:phone":"+90 212 261 0698",
    "sg:postcode":"75200",
    "sg:province":"Istanbul",
    "sg:tags":[
        "tank-heating-natural"
    ],
    "wof:name":"Tesma Ltd. Sti.",
    "wof:placetype":"venue"
},
  "geometry": {"coordinates":[28.9861831665,41.0408554077],"type":"Point"}
}