{
  "type": "Feature",
  "properties": {
    "iso:country":"TR",
    "sg:address":"Muradiye Mah. Murathat Pasa Cad.",
    "sg:city":"Muratli",
    "sg:classifiers":[
        {
            "category":"Food & Beverages",
            "subcategory":"Groceries & Convenience Stores",
            "type":"Retail Goods"
        }
    ],
    "sg:phone":"+90 282 361 7530",
    "sg:postcode":"25850",
    "sg:province":"Tekirdag",
    "sg:tags":[
        "product"
    ],
    "wof:name":"Ogulcan",
    "wof:placetype":"venue"
},
  "geometry": {"coordinates":[27.5144004822,40.9791984558],"type":"Point"}
}