{
  "type": "Feature",
  "properties": {
    "iso:country":"TR",
    "sg:address":"Fuzuli Cad.halet Kurdak Apt. No: 55/d",
    "sg:city":"Seyhan",
    "sg:classifiers":[
        {
            "category":"Manufacturing",
            "subcategory":"Metals",
            "type":"Manufacturing & Wholesale Goods"
        }
    ],
    "sg:phone":"+90 322 453 1156",
    "sg:postcode":"01120",
    "sg:province":"Adana",
    "sg:tags":[
        "industry"
    ],
    "wof:name":"Olusum B?ro Makina Mlz. Ve Servis Hiz.",
    "wof:placetype":"venue"
},
  "geometry": {"coordinates":[35.327419281,36.9982872009],"type":"Point"}
}