{
  "type": "Feature",
  "properties": {
    "iso:country":"TR",
    "sg:address":"Kizillik Sok. No:12",
    "sg:city":"Guzelbahce",
    "sg:classifiers":[
        {
            "category":"Home & Garden",
            "subcategory":"Hardware",
            "type":"Retail Goods"
        }
    ],
    "sg:phone":"+90 232 234 2647",
    "sg:postcode":"35310",
    "sg:province":"Izmir",
    "sg:tags":[
        "store"
    ],
    "wof:name":"Otomatsan A.s.",
    "wof:placetype":"venue"
},
  "geometry": {"coordinates":[27.1423015594,38.4251480103],"type":"Point"}
}