{
  "type": "Feature",
  "properties": {
    "iso:country":"TR",
    "sg:address":"Tersane Cd. Karak?",
    "sg:city":"\u00dcmraniye",
    "sg:classifiers":[
        {
            "category":"Farming",
            "subcategory":"Fish & Marine Products",
            "type":"Manufacturing & Wholesale Goods"
        }
    ],
    "sg:phone":"+90 212 253 4133",
    "sg:province":"Istanbul",
    "sg:tags":[
        "automotive"
    ],
    "wof:name":"Bilmak Rulman A.s.",
    "wof:placetype":"venue"
},
  "geometry": {"coordinates":[29.2745628357,40.8692016602],"type":"Point"}
}