{
  "type": "Feature",
  "properties": {
    "addr:full":"Gencturk Cad. Mahvil Sok. No:4/2 Laleli Istanbul 24300",
    "addr:housenumber":"no 4 / 2",
    "addr:postcode":"24300",
    "addr:street":"Gencturk Cad. Mahvil Sok.",
    "iso:country":"TR",
    "sg:address":"Gencturk Cad. Mahvil Sok. No:4/2",
    "sg:city":"Laleli",
    "sg:classifiers":[
        {
            "category":"Shopping",
            "subcategory":"Clothing, Apparel, & Fashions",
            "type":"Retail Goods"
        }
    ],
    "sg:phone":"+90 212 512 0787",
    "sg:postcode":"24300",
    "sg:province":"Istanbul",
    "sg:tags":[
        "ready",
        "wear"
    ],
    "wof:name":"Akkaya",
    "wof:placetype":"venue"
},
  "geometry": {"coordinates":[28.956073761,41.010761261],"type":"Point"}
}