{
  "type": "Feature",
  "properties": {
    "addr:full":"Cumhuriyet Cad. 173-175 Harbiye Istanbul 31080",
    "addr:postcode":"173-175;31080",
    "addr:street":"Cumhuriyet Cad.",
    "iso:country":"TR",
    "sg:address":"Cumhuriyet Cad. 173-175",
    "sg:city":"Harbiye",
    "sg:classifiers":[
        {
            "category":"Recreation",
            "subcategory":"Boat Charter",
            "type":"Entertainment"
        }
    ],
    "sg:postcode":"31080",
    "sg:province":"Istanbul",
    "sg:tags":[
        "yachting"
    ],
    "wof:name":"?zg?n Turizm",
    "wof:placetype":"venue"
},
  "geometry": {"coordinates":[29.1439170837,41.0792007446],"type":"Point"}
}