{
  "type": "Feature",
  "properties": {
    "addr:full":"Tepebasi Cd. No: 24/28 Beyoglu Bayrampasa Istanbul 36100",
    "addr:housenumber":"no 24 / 28",
    "addr:postcode":"36100",
    "addr:street":"Tepebasi Cd.;Beyoglu Bayrampasa",
    "iso:country":"TR",
    "sg:address":"Tepebasi Cd. No: 24/28 Beyoglu",
    "sg:city":"Bayrampasa",
    "sg:classifiers":[
        {
            "category":"Communications",
            "subcategory":"Film & Video Production",
            "type":"Services"
        }
    ],
    "sg:phone":"+90 212 255 4194",
    "sg:postcode":"36100",
    "sg:province":"Istanbul",
    "sg:tags":[
        "-"
    ],
    "wof:name":"Kare Film A.s.",
    "wof:placetype":"venue"
},
  "geometry": {"coordinates":[28.9716472626,41.0319213867],"type":"Point"}
}