{
  "type": "Feature",
  "properties": {
    "iso:country":"TR",
    "sg:address":"Yucetepe Mah.2.cad. No:26/b",
    "sg:city":"Anittepe",
    "sg:classifiers":[
        {
            "category":"Farming",
            "subcategory":"Farm & Veterinary Services",
            "type":"Manufacturing & Wholesale Goods"
        }
    ],
    "sg:phone":"+90 312 229 1388",
    "sg:postcode":"47570",
    "sg:province":"Ankara",
    "sg:tags":[
        "clinic"
    ],
    "wof:name":"Abdurrahman Koseman",
    "wof:placetype":"venue"
},
  "geometry": {"coordinates":[32.8234710693,39.8940467834],"type":"Point"}
}