{
  "type": "Feature",
  "properties": {
    "iso:country":"TR",
    "sg:address":"Filistin Sk. No:25/4 G.osmanpasa",
    "sg:city":"Uskudar",
    "sg:classifiers":[
        {
            "category":"Banks & Credit Unions",
            "subcategory":"Investment Brokerage",
            "type":"Services"
        }
    ],
    "sg:phone":"+90 312 436 5515",
    "sg:postcode":"34704",
    "sg:province":"Ankara",
    "sg:tags":[
        "-",
        "export",
        "import"
    ],
    "wof:name":"Gempa Dis Tic. Pazarlama Ltd. Sti.",
    "wof:placetype":"venue"
},
  "geometry": {"coordinates":[32.8604812622,39.9429283142],"type":"Point"}
}