{
  "type": "Feature",
  "properties": {
    "addr:full":"Talatpasa Cd. 212-214 K?ithane Maltepe Istanbul 01000",
    "addr:housenumber":"212-214 k ?",
    "addr:postcode":"01000",
    "addr:street":"Talatpasa Cd.;Ithane Maltepe Istanbul",
    "iso:country":"TR",
    "sg:address":"Talatpasa Cd. 212-214 K?ithane",
    "sg:city":"Maltepe",
    "sg:orig_category":"Aluminium Carpentary",
    "sg:phone":"+90 212 279 2679",
    "sg:postcode":"01000",
    "sg:province":"Istanbul",
    "wof:name":"Dogan Yapi Malz. Tic.",
    "wof:placetype":"venue"
},
  "geometry": {"coordinates":[28.9759254456,41.0123786926],"type":"Point"}
}