{
  "type": "Feature",
  "properties": {
    "addr:full":"Eskisaray Cad. Sekercidurdu Ishani 207 Sahinbey 07000 Gaziantep",
    "addr:housenumber":"207",
    "addr:postcode":"07000",
    "addr:street":"Eskisaray Cad. Sekercidurdu Ishani",
    "iso:country":"TR",
    "sg:address":"Eskisaray Cad. Sekercidurdu Ishani 207 Sahinbey",
    "sg:city":"07000",
    "sg:classifiers":[
        {
            "category":"Banks & Credit Unions",
            "subcategory":"Investment Brokerage",
            "type":"Services"
        }
    ],
    "sg:phone":"+90 342 233 1089",
    "sg:province":"Gaziantep",
    "sg:tags":[
        "-",
        "export",
        "import"
    ],
    "wof:name":"Yunus Import & Export",
    "wof:placetype":"venue"
},
  "geometry": {"coordinates":[37.3756790161,37.0623817444],"type":"Point"}
}