{
  "type": "Feature",
  "properties": {
    "iso:country":"TR",
    "sg:address":"Atat?k Cad. No:10",
    "sg:city":"Laleli",
    "sg:orig_category":"Hotels: Motels",
    "sg:phone":"+90 258 264 9293",
    "sg:postcode":"24300",
    "sg:province":"Denizli",
    "wof:name":"Piskin Otel",
    "wof:placetype":"venue"
},
  "geometry": {"coordinates":[29.0788803101,37.7851867676],"type":"Point"}
}