{
  "type": "Feature",
  "properties": {
    "addr:full":"Millet Cad 39/a Kayseri 38040 63600",
    "addr:housenumber":"39 / a",
    "addr:postcode":"38040 63600",
    "addr:street":"Millet Cad",
    "iso:country":"TR",
    "sg:address":"Millet Cad 39/a",
    "sg:city":"Kayseri",
    "sg:classifiers":[
        {
            "category":"Banks & Credit Unions",
            "subcategory":"Bank",
            "type":"Services"
        }
    ],
    "sg:phone":"+90 352 222 6212",
    "sg:postcode":"63600",
    "sg:province":"38040",
    "wof:name":"Toprakbank As",
    "wof:placetype":"venue"
},
  "geometry": {"coordinates":[35.488274,38.717842],"type":"Point"}
}