{
  "type": "Feature",
  "properties": {
    "addr:full":"Perpa Ticaret Merkezi B Blok Kat:9 No:1534 Sisli Istanbul 65710",
    "addr:housenumber":"9 no 1534",
    "addr:postcode":"65710",
    "addr:street":"Sisli Istanbul",
    "iso:country":"TR",
    "sg:address":"Perpa Ticaret Merkezi B Blok Kat:9 No:1534",
    "sg:city":"Sisli",
    "sg:classifiers":[
        {
            "category":"Shopping",
            "subcategory":"Computers & Home Electronics",
            "type":"Retail Goods"
        }
    ],
    "sg:phone":"+90 2214761",
    "sg:postcode":"65710",
    "sg:province":"Istanbul",
    "sg:tags":[
        "used"
    ],
    "wof:name":"Cesi Bilgisayar",
    "wof:placetype":"venue"
},
  "geometry": {"coordinates":[28.9759254456,41.0123786926],"type":"Point"}
}