{
  "type": "Feature",
  "properties": {
    "iso:country":"TR",
    "sg:address":"Ordu Bulvari",
    "sg:city":"Hopa",
    "sg:classifiers":[
        {
            "category":"Banks & Credit Unions",
            "subcategory":"Investment Brokerage",
            "type":"Services"
        }
    ],
    "sg:phone":"+90 272 234 3659",
    "sg:postcode":"08600",
    "sg:province":"Afyon",
    "sg:tags":[
        "-",
        "export",
        "import"
    ],
    "wof:name":"Yelid Co.",
    "wof:placetype":"venue"
},
  "geometry": {"coordinates":[30.5457286835,38.7607421875],"type":"Point"}
}