{
  "type": "Feature",
  "properties": {
    "addr:full":"Istanbul Yolu 12 Km Ergazi \u00dcmraniye Ankara",
    "addr:housenumber":"12 km",
    "addr:street":"Istanbul Yolu;Ergazi",
    "iso:country":"TR",
    "sg:address":"Istanbul Yolu 12 Km Ergazi",
    "sg:city":"\u00dcmraniye",
    "sg:classifiers":[
        {
            "category":"Building & Trades",
            "subcategory":"Construction",
            "type":"Services"
        }
    ],
    "sg:phone":"+90 312 427 8501",
    "sg:province":"Ankara",
    "sg:tags":[
        "industry",
        "mold"
    ],
    "wof:name":"Lamas Kalip Makina San. A.s.",
    "wof:placetype":"venue"
},
  "geometry": {"coordinates":[32.7102165222,39.9545249939],"type":"Point"}
}