{
  "type": "Feature",
  "properties": {
    "addr:full":"Anafartalar ?arsisi No:88 Ulus Ey\u00fcp Ankara",
    "addr:housenumber":"88",
    "addr:street":"Arsisi No",
    "iso:country":"TR",
    "sg:address":"Anafartalar ?arsisi No:88 Ulus",
    "sg:city":"Ey\u00fcp",
    "sg:classifiers":[
        {
            "category":"Wholesale",
            "subcategory":"Durable Goods & Equipment",
            "type":"Manufacturing & Wholesale Goods"
        }
    ],
    "sg:phone":"+90 312 310 9334",
    "sg:province":"Ankara",
    "sg:tags":[
        "consumer"
    ],
    "wof:name":"Kardesler Day. T?ketim Mal. Paz. San. Tic. A.s.",
    "wof:placetype":"venue"
},
  "geometry": {"coordinates":[32.8604812622,39.9429283142],"type":"Point"}
}