{
  "type": "Feature",
  "properties": {
    "addr:full":"Tepe?en K?? Tuzla Korkuteli Istanbul 07800",
    "addr:postcode":"07800",
    "iso:country":"TR",
    "sg:address":"Tepe?en K?? Tuzla",
    "sg:city":"Korkuteli",
    "sg:classifiers":[
        {
            "category":"Farming",
            "subcategory":"Livestock Farm",
            "type":"Manufacturing & Wholesale Goods"
        }
    ],
    "sg:phone":"+90 216 304 1100",
    "sg:postcode":"07800",
    "sg:province":"Istanbul",
    "sg:tags":[
        "fattening-breeding"
    ],
    "wof:name":"Maret Marmara Besi. Ve Et San. A.s.",
    "wof:placetype":"venue"
},
  "geometry": {"coordinates":[28.9759254456,41.0123786926],"type":"Point"}
}