{
  "type": "Feature",
  "properties": {
    "addr:full":"Ankara Cad.no:74 K:1 Turhal Sakarya 60300",
    "addr:housenumber":"74;1",
    "addr:postcode":"60300",
    "addr:street":"K",
    "iso:country":"TR",
    "sg:address":"Ankara Cad.no:74 K:1",
    "sg:city":"Turhal",
    "sg:classifiers":[
        {
            "category":"Wholesale",
            "subcategory":"Farm Supplies",
            "type":"Manufacturing & Wholesale Goods"
        }
    ],
    "sg:phone":"+90 264 281 1636",
    "sg:postcode":"60300",
    "sg:province":"Sakarya",
    "sg:tags":[
        "feed",
        "industry"
    ],
    "wof:name":"Rensan Tav.gida Hy.tic.paz.ltd.sti.",
    "wof:placetype":"venue"
},
  "geometry": {"coordinates":[32.500415802,37.8885498047],"type":"Point"}
}