{
  "type": "Feature",
  "properties": {
    "addr:full":"Zihni Memisoglu Merkez Mah. Gencosman Cad. No:1 Gungoren Istanbul 33630",
    "addr:postcode":"33630",
    "addr:street":"Merkez Mah. Gencosman Cad. No 1 Gungoren",
    "iso:country":"TR",
    "sg:address":"Zihni Memisoglu Merkez Mah. Gencosman Cad. No:1",
    "sg:city":"Gungoren",
    "sg:classifiers":[
        {
            "category":"Marine",
            "type":"Transportation"
        }
    ],
    "sg:phone":"+90 212 677 4884",
    "sg:postcode":"33630",
    "sg:province":"Istanbul",
    "sg:tags":[
        "equipment",
        "maritime"
    ],
    "wof:name":"Gimas Uluslararasi Kumanyacilik Tic. A.s.",
    "wof:placetype":"venue"
},
  "geometry": {"coordinates":[28.9861831665,41.0408554077],"type":"Point"}
}