{
  "type": "Feature",
  "properties": {
    "iso:country":"TR",
    "sg:address":"Bagdat Caddesi No. 333/2",
    "sg:city":"Erenk?",
    "sg:classifiers":[
        {
            "category":"Banks & Credit Unions",
            "subcategory":"Bank",
            "type":"Services"
        }
    ],
    "sg:phone":"+90 216 302 2332",
    "sg:province":"81070",
    "wof:name":"Demirbank Tas",
    "wof:placetype":"venue"
},
  "geometry": {"coordinates":[37.032784,39.737255],"type":"Point"}
}