{
  "type": "Feature",
  "properties": {
    "iso:country":"TR",
    "sg:address":"Muhittin Mah ?etin Eme? Bulvari No.40",
    "sg:city":"\u00c7orlu",
    "sg:orig_category":"Pvc Packing",
    "sg:phone":"+90 282 661 1668",
    "sg:postcode":"59000",
    "sg:province":"Tekirdag",
    "wof:name":"Yal?in Tesisat Santic.a.s",
    "wof:placetype":"venue"
},
  "geometry": {"coordinates":[27.5144004822,40.9791984558],"type":"Point"}
}