{
  "type": "Feature",
  "properties": {
    "iso:country":"TR",
    "sg:address":"Sanayi Cad. Cavus Sok. 3/1",
    "sg:city":"Ulus",
    "sg:classifiers":[
        {
            "category":"Building & Trades",
            "subcategory":"Electrical",
            "type":"Services"
        }
    ],
    "sg:phone":"+90 312 309 3141",
    "sg:postcode":"01940",
    "sg:province":"Ankara",
    "sg:tags":[
        "equipment",
        "lighting"
    ],
    "wof:name":"Kaderoglu Elk. Tic. Taah. Ltd. Sti.",
    "wof:placetype":"venue"
},
  "geometry": {"coordinates":[32.8552360535,39.9376869202],"type":"Point"}
}