{
  "type": "Feature",
  "properties": {
    "addr:full":"Hacilar Mah.konakard Sok.no:5/6 Cagaloglu Bursa 34440",
    "addr:housenumber":"5 / 6",
    "addr:postcode":"34440",
    "addr:street":"Sok.No;Bursa",
    "iso:country":"TR",
    "sg:address":"Hacilar Mah.konakard Sok.no:5/6",
    "sg:city":"Cagaloglu",
    "sg:classifiers":[
        {
            "category":"Banks & Credit Unions",
            "subcategory":"Financial Services",
            "type":"Services"
        }
    ],
    "sg:phone":"+90 224 220 2612",
    "sg:postcode":"34440",
    "sg:province":"Bursa",
    "sg:tags":[
        "consultant"
    ],
    "wof:name":"Yonetim Yeminli Mali Musavirlik Ltd.sti.",
    "wof:placetype":"venue"
},
  "geometry": {"coordinates":[29.0580043793,40.1947555542],"type":"Point"}
}