{
  "type": "Feature",
  "properties": {
    "iso:country":"TR",
    "sg:address":"G.antep Yolu Erkenez Mev.",
    "sg:city":"Avcilar",
    "sg:classifiers":[
        {
            "category":"Shopping",
            "subcategory":"Crafts & Fabrics",
            "type":"Retail Goods"
        }
    ],
    "sg:phone":"+90 344 236 3800",
    "sg:postcode":"34310",
    "sg:province":"Kahramanmaras",
    "sg:tags":[
        "nylon",
        "yarn"
    ],
    "wof:name":"Kipas-kahramanmaras Iplik Pamuk Tic. San. A.s.",
    "wof:placetype":"venue"
},
  "geometry": {"coordinates":[36.9280776978,37.5858345032],"type":"Point"}
}