{
  "type": "Feature",
  "properties": {
    "addr:full":"Halk Sk. No:19/1 Sihhiye Fatih Ankara 01740",
    "addr:housenumber":"19 / 1",
    "addr:postcode":"01740",
    "addr:street":"Halk Sk. No",
    "iso:country":"TR",
    "sg:address":"Halk Sk. No:19/1 Sihhiye",
    "sg:city":"Fatih",
    "sg:classifiers":[
        {
            "category":"Wholesale",
            "subcategory":"Medical Equipment & Supplies",
            "type":"Manufacturing & Wholesale Goods"
        }
    ],
    "sg:phone":"+90 312 435 9420",
    "sg:postcode":"01740",
    "sg:province":"Ankara",
    "sg:tags":[
        "material"
    ],
    "wof:name":"Kocak Ltd. Sti.",
    "wof:placetype":"venue"
},
  "geometry": {"coordinates":[32.8593444824,39.9254798889],"type":"Point"}
}