{
  "type": "Feature",
  "properties": {
    "iso:country":"TR",
    "sg:address":"Recai Dogan",
    "sg:city":"Y?egir",
    "sg:classifiers":[
        {
            "category":"Government",
            "subcategory":"Office",
            "type":"Public Place"
        }
    ],
    "sg:phone":"+90 322 388 4003",
    "sg:province":"Adana",
    "sg:tags":[
        "municipality"
    ],
    "wof:name":"Yunusoglu Belediye Baskani",
    "wof:placetype":"venue"
},
  "geometry": {"coordinates":[35.3137359619,37.0007171631],"type":"Point"}
}