{
  "type": "Feature",
  "properties": {
    "addr:full":"Konya Alti Laleli Antalya 24300",
    "addr:postcode":"24300",
    "iso:country":"TR",
    "sg:address":"Konya Alti",
    "sg:city":"Laleli",
    "sg:orig_category":"Hotels: Motels",
    "sg:phone":"+90 242 229 0270",
    "sg:postcode":"24300",
    "sg:province":"Antalya",
    "wof:name":"Erdem Hotel",
    "wof:placetype":"venue"
},
  "geometry": {"coordinates":[30.6814174652,36.8848686218],"type":"Point"}
}