{
  "type": "Feature",
  "properties": {
    "addr:full":"Kavacik Mah. Ozkan Sok. No:3/8 Kavacik/beykoz Ikitelli/K\u00fc\u00e7\u00fck\u00e7ekmece Istanbul 34670",
    "addr:housenumber":"no 3 / 8",
    "addr:postcode":"34670",
    "addr:street":"Kavacik Mah. Ozkan Sok.",
    "iso:country":"TR",
    "sg:address":"Kavacik Mah. Ozkan Sok. No:3/8 Kavacik/beykoz",
    "sg:city":"Ikitelli/K\u00fc\u00e7\u00fck\u00e7ekmece",
    "sg:classifiers":[
        {
            "category":"Manufacturing",
            "subcategory":"Metals",
            "type":"Manufacturing & Wholesale Goods"
        }
    ],
    "sg:phone":"+90 216 413 8253",
    "sg:postcode":"34670",
    "sg:province":"Istanbul",
    "sg:tags":[
        "iron-steel",
        "peoducts"
    ],
    "wof:name":"Isb Group Of Companies",
    "wof:placetype":"venue"
},
  "geometry": {"coordinates":[29.0891170502,41.0938873291],"type":"Point"}
}