{
  "type": "Feature",
  "properties": {
    "iso:country":"TR",
    "sg:address":"Cem Burak",
    "sg:city":"Kozan",
    "sg:classifiers":[
        {
            "category":"Government",
            "subcategory":"Office",
            "type":"Public Place"
        }
    ],
    "sg:phone":"+90 242 572 1013",
    "sg:postcode":"01500",
    "sg:province":"Antalya",
    "sg:tags":[
        "municipality"
    ],
    "wof:name":"Gazipasa Belediye Baskani",
    "wof:placetype":"venue"
},
  "geometry": {"coordinates":[29.267824173,40.9718437195],"type":"Point"}
}