{
  "type": "Feature",
  "properties": {
    "addr:full":"Org.sanayi Bol.ulubatli Cad.no:5 Kutlukent G?g?en Samsun",
    "addr:housenumber":"5;? g ?",
    "addr:street":"Cad.No;Kutlukent G;En Samsun",
    "iso:country":"TR",
    "sg:address":"Org.sanayi Bol.ulubatli Cad.no:5 Kutlukent",
    "sg:city":"G?g?en",
    "sg:classifiers":[
        {
            "category":"Manufacturing",
            "subcategory":"Rubber & Plastics",
            "type":"Manufacturing & Wholesale Goods"
        }
    ],
    "sg:phone":"+90 362 266 7524",
    "sg:province":"Samsun",
    "sg:tags":[
        "industry"
    ],
    "wof:name":"Po-el Plastik San. Tic. Ve Paz.ltd.sti.",
    "wof:placetype":"venue"
},
  "geometry": {"coordinates":[36.4118118286,41.2170600891],"type":"Point"}
}