{
  "type": "Feature",
  "properties": {
    "iso:country":"TR",
    "sg:address":"Davutpasa Cad. No:12 Topkapi",
    "sg:city":"Seyhan",
    "sg:classifiers":[
        {
            "category":"Manufacturing",
            "subcategory":"Chemicals & Compounds",
            "type":"Manufacturing & Wholesale Goods"
        }
    ],
    "sg:phone":"+90 212 544 4610",
    "sg:postcode":"01120",
    "sg:province":"Istanbul",
    "sg:tags":[
        "pharmaceutical"
    ],
    "wof:name":"I.e. Ulugay Ilac San.",
    "wof:placetype":"venue"
},
  "geometry": {"coordinates":[28.9266090393,41.016872406],"type":"Point"}
}