{
  "type": "Feature",
  "properties": {
    "addr:full":"Karpuzlu Sk. No:99 Osmanbey Ankara 63000",
    "addr:housenumber":"99",
    "addr:postcode":"63000",
    "addr:street":"Karpuzlu Sk. No",
    "iso:country":"TR",
    "sg:address":"Karpuzlu Sk. No:99",
    "sg:city":"Osmanbey",
    "sg:classifiers":[
        {
            "category":"Retail",
            "subcategory":"Car Wash",
            "type":"Services"
        }
    ],
    "sg:phone":"+90 312 351 3696",
    "sg:postcode":"63000",
    "sg:province":"Ankara",
    "sg:tags":[
        "sponge"
    ],
    "wof:name":"Anadolu S?nger",
    "wof:placetype":"venue"
},
  "geometry": {"coordinates":[33.081802,40.129673],"type":"Point"}
}