{
  "type": "Feature",
  "properties": {
    "addr:full":"Adana Cozkoclar Deposu Eregli Erzin Konya 31960",
    "addr:postcode":"31960",
    "iso:country":"TR",
    "sg:address":"Adana Cozkoclar Deposu Eregli",
    "sg:city":"Erzin",
    "sg:classifiers":[
        {
            "category":"Farming",
            "subcategory":"Farm",
            "type":"Manufacturing & Wholesale Goods"
        }
    ],
    "sg:phone":"+90 332 712 1483",
    "sg:postcode":"31960",
    "sg:province":"Konya",
    "sg:tags":[
        "agricultural",
        "product"
    ],
    "wof:name":"Ozkoclar Tarim Urunleri",
    "wof:placetype":"venue"
},
  "geometry": {"coordinates":[32.4990272522,37.8715362549],"type":"Point"}
}