{
  "type": "Feature",
  "properties": {
    "addr:full":"Namik Kemal Mah.tun?sok.no:3 \u00dcmraniye Istanbul 34762",
    "addr:housenumber":"3",
    "addr:postcode":"34762",
    "addr:street":"Sok.No",
    "iso:country":"TR",
    "sg:address":"Namik Kemal Mah.tun?sok.no:3",
    "sg:city":"\u00dcmraniye",
    "sg:classifiers":[
        {
            "category":"Home & Garden",
            "subcategory":"Household Appliances",
            "type":"Retail Goods"
        }
    ],
    "sg:phone":"+90 216 443 2447",
    "sg:postcode":"34762",
    "sg:province":"Istanbul",
    "sg:tags":[
        "conditioner",
        "air"
    ],
    "wof:name":"Alternatif Sogutma Ve Teknik Hizm.san.tic.",
    "wof:placetype":"venue"
},
  "geometry": {"coordinates":[29.0932617188,41.010887146],"type":"Point"}
}