{
  "type": "Feature",
  "properties": {
    "iso:country":"TR",
    "sg:address":"Esentepe Mevkii Gebze",
    "sg:city":"Gebze",
    "sg:orig_category":"Aluminium Carpentary",
    "sg:phone":"+90 262724824546",
    "sg:postcode":"41400",
    "sg:province":"Istanbul",
    "wof:name":"Dogus Alm San Tic As",
    "wof:placetype":"venue"
},
  "geometry": {"coordinates":[28.9759254456,41.0123786926],"type":"Point"}
}