{
  "type": "Feature",
  "properties": {
    "iso:country":"TR",
    "sg:address":"Y.dudulu ,organize San.bol.gencoglu Cad. No:20 Umraniye",
    "sg:city":"Sisli",
    "sg:classifiers":[
        {
            "category":"Home & Garden",
            "subcategory":"Hardware",
            "type":"Retail Goods"
        }
    ],
    "sg:phone":"+90 216 365 2900",
    "sg:postcode":"34418",
    "sg:province":"Istanbul",
    "sg:tags":[
        "generator",
        "power"
    ],
    "wof:name":"Abb Elektrik San. A.s.",
    "wof:placetype":"venue"
},
  "geometry": {"coordinates":[28.9950695038,41.1000099182],"type":"Point"}
}