{
  "type": "Feature",
  "properties": {
    "addr:full":"G?l Cad. Sirma Su Yani No:1 Kirkpinar Sapanca Sakarya 54600",
    "addr:postcode":"54600",
    "addr:street":"L Cad.",
    "iso:country":"TR",
    "sg:address":"G?l Cad. Sirma Su Yani No:1 Kirkpinar",
    "sg:city":"Sapanca",
    "sg:classifiers":[
        {
            "category":"Government",
            "subcategory":"Fire Station",
            "type":"Public Place"
        }
    ],
    "sg:phone":"+90 264 592 6524",
    "sg:postcode":"54600",
    "sg:province":"Sakarya",
    "sg:tags":[
        "decoration"
    ],
    "wof:name":"Umur Dekorasyon",
    "wof:placetype":"venue"
},
  "geometry": {"coordinates":[30.3791446686,40.7734336853],"type":"Point"}
}