{
  "type": "Feature",
  "properties": {
    "iso:country":"TR",
    "sg:address":"Emekciler Mh. Ataturk Bul. No:15",
    "sg:city":"Mersin",
    "sg:classifiers":[
        {
            "category":"Wholesale",
            "subcategory":"Auto Parts",
            "type":"Manufacturing & Wholesale Goods"
        }
    ],
    "sg:phone":"+90 324 221 5679",
    "sg:postcode":"52750",
    "sg:province":"I?el",
    "sg:tags":[
        "spare"
    ],
    "wof:name":"Karakaya A.s.",
    "wof:placetype":"venue"
},
  "geometry": {"coordinates":[28.820690155,40.9821014404],"type":"Point"}
}