{
  "type": "Feature",
  "properties": {
    "iso:country":"TR",
    "sg:address":"Ataturk Cad.no:71 Dudullu",
    "sg:city":"\u00dcmraniye",
    "sg:classifiers":[
        {
            "category":"Utilities",
            "subcategory":"Electric",
            "type":"Services"
        }
    ],
    "sg:phone":"+90 216 420 2363",
    "sg:postcode":"03650",
    "sg:province":"Istanbul",
    "sg:tags":[
        "energy",
        "solar"
    ],
    "wof:name":"?zt?rk Isi",
    "wof:placetype":"venue"
},
  "geometry": {"coordinates":[29.126234,40.971024],"type":"Point"}
}