{
  "type": "Feature",
  "properties": {
    "addr:full":"Anadolu Sanayi No:12 Gaziosmanpasa Konya 34110",
    "addr:housenumber":"sanayi no 12",
    "addr:postcode":"34110",
    "addr:street":"Anadolu;Gaziosmanpasa Konya",
    "iso:country":"TR",
    "sg:address":"Anadolu Sanayi No:12",
    "sg:city":"Gaziosmanpasa",
    "sg:classifiers":[
        {
            "category":"Wholesale",
            "subcategory":"Machinery & Supplies",
            "type":"Manufacturing & Wholesale Goods"
        }
    ],
    "sg:phone":"+90 332 352 2098",
    "sg:postcode":"34110",
    "sg:province":"Konya",
    "sg:tags":[
        "agricultural"
    ],
    "wof:name":"Vaha Tarim Makinalari",
    "wof:placetype":"venue"
},
  "geometry": {"coordinates":[28.9895839691,41.0828514099],"type":"Point"}
}