{
  "type": "Feature",
  "properties": {
    "iso:country":"TR",
    "sg:address":"M.kemalpasa Bulvari No:120 /a-b",
    "sg:city":"Merter",
    "sg:classifiers":[
        {
            "category":"Home & Garden",
            "subcategory":"Household Appliances",
            "type":"Retail Goods"
        }
    ],
    "sg:phone":"+90 352 223 7352",
    "sg:province":"Kayseri",
    "sg:tags":[
        "conditioner",
        "air"
    ],
    "wof:name":"Desibel Muhendisilk",
    "wof:placetype":"venue"
},
  "geometry": {"coordinates":[29.2620620728,40.8785095215],"type":"Point"}
}