{
  "type": "Feature",
  "properties": {
    "iso:country":"TR",
    "sg:address":"Izmir Yolu 7.km.",
    "sg:city":"Kad\u0131k\u00f6y",
    "sg:classifiers":[
        {
            "category":"Home & Garden",
            "subcategory":"Home Furnishings",
            "type":"Retail Goods"
        }
    ],
    "sg:phone":"+90 224 441 7250",
    "sg:province":"Bursa",
    "sg:tags":[
        "textile"
    ],
    "wof:name":"Eser Tekstil A.s.",
    "wof:placetype":"venue"
},
  "geometry": {"coordinates":[29.1685771942,40.2038612366],"type":"Point"}
}