{
  "type": "Feature",
  "properties": {
    "iso:country":"TR",
    "sg:address":"K. M. Pasa Cad. No:94/a Cerrahpasa",
    "sg:city":"Besiktas",
    "sg:classifiers":[
        {
            "category":"Manufacturing",
            "subcategory":"Chemicals & Compounds",
            "type":"Manufacturing & Wholesale Goods"
        }
    ],
    "sg:phone":"+90 212 518 5501",
    "sg:postcode":"75200",
    "sg:province":"Istanbul",
    "sg:tags":[
        "medicine"
    ],
    "wof:name":"Emboy Kimyevi Mad. Ltd. Sti.",
    "wof:placetype":"venue"
},
  "geometry": {"coordinates":[28.9414768219,41.0093574524],"type":"Point"}
}