{
  "type": "Feature",
  "properties": {
    "iso:country":"TR",
    "sg:address":"Posta Cad. Cerkez Sk. No: 52",
    "sg:city":"Ulus",
    "sg:classifiers":[
        {
            "category":"Manufacturing",
            "subcategory":"Textiles",
            "type":"Manufacturing & Wholesale Goods"
        }
    ],
    "sg:phone":"+90 312 311 4112",
    "sg:postcode":"01940",
    "sg:province":"Ankara",
    "sg:tags":[
        "cloth",
        "worker"
    ],
    "wof:name":"Akcay Giyim Textil San. Tic. Ltd. Sti.",
    "wof:placetype":"venue"
},
  "geometry": {"coordinates":[29.1095943451,40.1954917908],"type":"Point"}
}