{
  "type": "Feature",
  "properties": {
    "addr:full":"1.organize San. Bolg. Sihhiye Sok. No:4 Sefakoy Konya 42000",
    "addr:housenumber":"no 4",
    "addr:postcode":"1.organize;42000",
    "addr:street":"San. Bolg. Sihhiye Sok.;Sefakoy Konya",
    "iso:country":"TR",
    "sg:address":"1.organize San. Bolg. Sihhiye Sok. No:4",
    "sg:city":"Sefakoy",
    "sg:classifiers":[
        {
            "category":"Wholesale",
            "subcategory":"Auto Parts",
            "type":"Manufacturing & Wholesale Goods"
        }
    ],
    "sg:phone":"+90 332248236061",
    "sg:postcode":"42000",
    "sg:province":"Konya",
    "sg:tags":[
        "spare"
    ],
    "wof:name":"Koncelik A.s.",
    "wof:placetype":"venue"
},
  "geometry": {"coordinates":[33.0667152405,39.2111282349],"type":"Point"}
}