{
  "type": "Feature",
  "properties": {
    "addr:full":"Anil Apt. No:6 Iskenderun Balikesir 31200",
    "addr:postcode":"31200",
    "addr:street":"Balikesir",
    "iso:country":"TR",
    "sg:address":"Anil Apt. No:6",
    "sg:city":"Iskenderun",
    "sg:classifiers":[
        {
            "category":"Mining & Drilling",
            "type":"Manufacturing & Wholesale Goods"
        }
    ],
    "sg:phone":"+90 266 712 9347",
    "sg:postcode":"31200",
    "sg:province":"Balikesir",
    "sg:tags":[
        "industry",
        "mine"
    ],
    "wof:name":"S?g?t Madencilik A.s.",
    "wof:placetype":"venue"
},
  "geometry": {"coordinates":[27.8840007782,39.6669960022],"type":"Point"}
}