{
  "type": "Feature",
  "properties": {
    "addr:full":"Cumhuriyet Cad.olcek Sok. No. 172 Harbiye Ikitelli/K\u00fc\u00e7\u00fck\u00e7ekmece Istanbul 34670",
    "addr:housenumber":"no.",
    "addr:postcode":"34670",
    "addr:street":"Cad.Olcek Sok.;Harbiye",
    "iso:country":"TR",
    "sg:address":"Cumhuriyet Cad.olcek Sok. No. 172 Harbiye",
    "sg:city":"Ikitelli/K\u00fc\u00e7\u00fck\u00e7ekmece",
    "sg:classifiers":[
        {
            "category":"Professional",
            "subcategory":"Detective & Security Services",
            "type":"Services"
        }
    ],
    "sg:phone":"+90 212 234 3016",
    "sg:postcode":"34670",
    "sg:province":"Istanbul",
    "sg:tags":[
        "material"
    ],
    "wof:name":"A.c.e.grup Guvenlik Ve Temizlik Sosyal Hizm.san.tic.ltd.sti.",
    "wof:placetype":"venue"
},
  "geometry": {"coordinates":[28.985458,41.045704],"type":"Point"}
}