{
  "type": "Feature",
  "properties": {
    "addr:full":"Kusdili Cad. Insaat?ilar Ishani. No:8/2 Kad\u0131k\u00f6y Istanbul 34990",
    "addr:housenumber":"insaat ?;2",
    "addr:postcode":"34990",
    "addr:street":"Kusdili Cad.;Ilar Ishani. No 8 /",
    "iso:country":"TR",
    "sg:address":"Kusdili Cad. Insaat?ilar Ishani. No:8/2",
    "sg:city":"Kad\u0131k\u00f6y",
    "sg:classifiers":[
        {
            "category":"Travel",
            "subcategory":"Travel Agent",
            "type":"Entertainment"
        }
    ],
    "sg:phone":"+90 33883963388869",
    "sg:postcode":"34990",
    "sg:province":"Istanbul",
    "sg:tags":[
        "agency",
        "tourism"
    ],
    "wof:name":"Emreli Turizm",
    "wof:placetype":"venue"
},
  "geometry": {"coordinates":[28.9861831665,41.0408554077],"type":"Point"}
}