{
  "type": "Feature",
  "properties": {
    "iso:country":"TR",
    "sg:address":"Yenibaraj Yolu No:18",
    "sg:city":"Mersin",
    "sg:classifiers":[
        {
            "category":"Wholesale",
            "subcategory":"Medical Equipment & Supplies",
            "type":"Manufacturing & Wholesale Goods"
        }
    ],
    "sg:phone":"+90 212 625 5872",
    "sg:postcode":"52750",
    "sg:province":"Istanbul",
    "wof:name":"Kanca&kanca Tib. Ger. Ltd.",
    "wof:placetype":"venue"
},
  "geometry": {"coordinates":[28.9185638428,41.0634689331],"type":"Point"}
}