{
  "type": "Feature",
  "properties": {
    "addr:full":"Marmara Sk. No:32/6 Sihhiye Sahinbey Ankara 27300",
    "addr:postcode":"27300",
    "iso:country":"TR",
    "sg:address":"Marmara Sk. No:32/6 Sihhiye",
    "sg:city":"Sahinbey",
    "sg:classifiers":[
        {
            "category":"Professional",
            "subcategory":"Testing Lab",
            "type":"Services"
        }
    ],
    "sg:phone":"+90 312 435 4227",
    "sg:postcode":"27300",
    "sg:province":"Ankara",
    "sg:tags":[
        "laboratory",
        "material"
    ],
    "wof:name":"Eray Tip Ltd. Sti.",
    "wof:placetype":"venue"
},
  "geometry": {"coordinates":[32.8583030701,39.9270019531],"type":"Point"}
}