{
  "type": "Feature",
  "properties": {
    "addr:full":"Tabakhaneler No:32 Yalvac Emin?? 34450 Isparta",
    "addr:housenumber":"? ?",
    "addr:postcode":"34450",
    "addr:street":"Yalvac",
    "iso:country":"TR",
    "sg:address":"Tabakhaneler No:32 Yalvac",
    "sg:city":"Emin?? 34450",
    "sg:classifiers":[
        {
            "category":"Shopping",
            "subcategory":"Clothing, Apparel, & Fashions",
            "type":"Retail Goods"
        }
    ],
    "sg:phone":"+90 246 441 3872",
    "sg:province":"Isparta",
    "sg:tags":[
        "bag-belt-accessories"
    ],
    "wof:name":"Ulku Deri San.",
    "wof:placetype":"venue"
},
  "geometry": {"coordinates":[31.1791,38.296501],"type":"Point"}
}