{
  "type": "Feature",
  "properties": {
    "iso:country":"TR",
    "sg:address":"Liman Mah.27.sok.no:5/1",
    "sg:city":"Merkez",
    "sg:classifiers":[
        {
            "category":"Bars & Pubs",
            "subcategory":"Nightclub",
            "type":"Food & Drink"
        }
    ],
    "sg:phone":"+90 242 259 2625",
    "sg:postcode":"07070",
    "sg:province":"Antalya",
    "sg:tags":[
        "oprerators",
        "pier",
        "jetty"
    ],
    "wof:name":"Global Kumanyacilik",
    "wof:placetype":"venue"
},
  "geometry": {"coordinates":[30.6155872345,36.8494148254],"type":"Point"}
}