{
  "type": "Feature",
  "properties": {
    "addr:full":"Yesil Akdeniz San.sit.insaat Malz.bol.5070 Sok.no:1-2-3 Ikitelli/K\u00fc\u00e7\u00fck\u00e7ekmece Antalya 34670",
    "addr:housenumber":"1-2-3",
    "addr:postcode":"34670",
    "addr:street":"Sok.No",
    "iso:country":"TR",
    "sg:address":"Yesil Akdeniz San.sit.insaat Malz.bol.5070 Sok.no:1-2-3",
    "sg:city":"Ikitelli/K\u00fc\u00e7\u00fck\u00e7ekmece",
    "sg:classifiers":[
        {
            "category":"Retail",
            "subcategory":"Storage",
            "type":"Services"
        }
    ],
    "sg:phone":"+90 242 221 6044",
    "sg:postcode":"34670",
    "sg:province":"Antalya",
    "sg:tags":[
        "shelving",
        "system"
    ],
    "wof:name":"Arge Metal San.tic.ltd",
    "wof:placetype":"venue"
},
  "geometry": {"coordinates":[30.703135,36.887505],"type":"Point"}
}