{
  "type": "Feature",
  "properties": {
    "addr:full":"Hilmi Sensoy ?al Bursa",
    "iso:country":"TR",
    "sg:address":"Hilmi Sensoy",
    "sg:city":"?al",
    "sg:classifiers":[
        {
            "category":"Government",
            "subcategory":"Office",
            "type":"Public Place"
        }
    ],
    "sg:phone":"+90 224 220 0158",
    "sg:province":"Bursa",
    "sg:tags":[
        "municipality"
    ],
    "wof:name":"Osmangazi Belediye Baskani",
    "wof:placetype":"venue"
},
  "geometry": {"coordinates":[29.0580043793,40.1947555542],"type":"Point"}
}