{
  "type": "Feature",
  "properties": {
    "addr:full":"Basak Cad. Sahver Ishani Kat:4 No:16 Maltepe Bursa 01000",
    "addr:housenumber":"kat 4 no 16",
    "addr:postcode":"01000",
    "addr:street":"Basak Cad. Sahver Ishani;Bursa",
    "iso:country":"TR",
    "sg:address":"Basak Cad. Sahver Ishani Kat:4 No:16",
    "sg:city":"Maltepe",
    "sg:classifiers":[
        {
            "category":"Wholesale",
            "subcategory":"Books, Periodicals, & Newspapers",
            "type":"Manufacturing & Wholesale Goods"
        }
    ],
    "sg:phone":"+90 224 224 9346",
    "sg:postcode":"01000",
    "sg:province":"Bursa",
    "sg:tags":[
        "house",
        "publishing"
    ],
    "wof:name":"Medikal Bakis Dergisi",
    "wof:placetype":"venue"
},
  "geometry": {"coordinates":[29.0580043793,40.1947555542],"type":"Point"}
}