{
  "type": "Feature",
  "properties": {
    "addr:full":"Azi Bulv. No:82 Nazilli Aydin 65600",
    "addr:housenumber":"no 82",
    "addr:postcode":"65600",
    "addr:street":"Azi Bulv.;Aydin",
    "iso:country":"TR",
    "sg:address":"Azi Bulv. No:82",
    "sg:city":"Nazilli",
    "sg:classifiers":[
        {
            "category":"Shopping",
            "subcategory":"Clothing, Apparel, & Fashions",
            "type":"Retail Goods"
        }
    ],
    "sg:phone":"+90 256 225 2365",
    "sg:postcode":"65600",
    "sg:province":"Aydin",
    "sg:tags":[
        "ready",
        "wear"
    ],
    "wof:name":"Aybek Konf. G",
    "wof:placetype":"venue"
},
  "geometry": {"coordinates":[27.8490772247,37.848487854],"type":"Point"}
}