{
  "type": "Feature",
  "properties": {
    "addr:full":"Buyukdere Cad. No:37 80670 Maslak ?atalca Istanbul 34870",
    "addr:housenumber":"37;?",
    "addr:postcode":"80670;34870",
    "addr:street":"Buyukdere Cad. No",
    "iso:country":"TR",
    "sg:address":"Buyukdere Cad. No:37 80670 Maslak",
    "sg:city":"?atalca",
    "sg:classifiers":[
        {
            "category":"Manufacturing",
            "subcategory":"Leather Goods",
            "type":"Manufacturing & Wholesale Goods"
        }
    ],
    "sg:phone":"+90 212 285 1000",
    "sg:postcode":"34870",
    "sg:province":"Istanbul",
    "sg:tags":[
        "chemical"
    ],
    "wof:name":"Soda San.a.s.-kromsan",
    "wof:placetype":"venue"
},
  "geometry": {"coordinates":[29.0236186981,41.1231155396],"type":"Point"}
}