{
  "type": "Feature",
  "properties": {
    "addr:full":"Mersin Yolu Karayollari. Muayene Ist.kar. Ikitelli Adana 34306",
    "addr:housenumber":"karayollari.",
    "addr:postcode":"34306",
    "addr:street":"Mersin Yolu;Adana",
    "iso:country":"TR",
    "sg:address":"Mersin Yolu Karayollari. Muayene Ist.kar.",
    "sg:city":"Ikitelli",
    "sg:classifiers":[
        {
            "category":"Manufacturing",
            "subcategory":"Rubber & Plastics",
            "type":"Manufacturing & Wholesale Goods"
        }
    ],
    "sg:phone":"+90 322428065960",
    "sg:postcode":"34306",
    "sg:province":"Adana",
    "sg:tags":[
        "industry"
    ],
    "wof:name":"Mimko Plastik Sanayi Ve Ticaret A.s",
    "wof:placetype":"venue"
},
  "geometry": {"coordinates":[35.3137359619,37.0007171631],"type":"Point"}
}