{
  "type": "Feature",
  "properties": {
    "addr:full":"Fulya Cad. No: 29 Mecidiyek\u00f6y Istanbul 34387",
    "addr:housenumber":"29",
    "addr:postcode":"34387",
    "addr:street":"Fulya Cad. No;Istanbul",
    "iso:country":"TR",
    "sg:address":"Fulya Cad. No: 29",
    "sg:city":"Mecidiyek\u00f6y",
    "sg:classifiers":[
        {
            "category":"Travel",
            "subcategory":"Travel Agent",
            "type":"Entertainment"
        }
    ],
    "sg:phone":"+90 2128424",
    "sg:postcode":"34387",
    "sg:province":"Istanbul",
    "sg:tags":[
        "agency",
        "tourism"
    ],
    "wof:name":"Mavi Deryalar Turizm Ltd",
    "wof:placetype":"venue"
},
  "geometry": {"coordinates":[28.994594574,41.0617675781],"type":"Point"}
}