{
  "type": "Feature",
  "properties": {
    "addr:full":"Semaver Sk. No:21 Mercan Fatih Istanbul 01740",
    "addr:housenumber":"21",
    "addr:postcode":"01740",
    "addr:street":"Semaver Sk. No",
    "iso:country":"TR",
    "sg:address":"Semaver Sk. No:21 Mercan",
    "sg:city":"Fatih",
    "sg:classifiers":[
        {
            "category":"Building & Trades",
            "subcategory":"Construction",
            "type":"Services"
        }
    ],
    "sg:phone":"+90 212 528 4145",
    "sg:postcode":"01740",
    "sg:province":"Istanbul",
    "sg:tags":[
        "foundation"
    ],
    "wof:name":"Is Dunyasi Vakfi",
    "wof:placetype":"venue"
},
  "geometry": {"coordinates":[28.9665699005,41.0132446289],"type":"Point"}
}