{
  "type": "Feature",
  "properties": {
    "addr:full":"Galip D. Cd. No:149 D:4 Beyoglu Fatih Istanbul 01740",
    "addr:housenumber":"no 149 d 4",
    "addr:postcode":"01740",
    "addr:street":"Cd.;Beyoglu",
    "iso:country":"TR",
    "sg:address":"Galip D. Cd. No:149 D:4 Beyoglu",
    "sg:city":"Fatih",
    "sg:classifiers":[
        {
            "category":"Building & Trades",
            "subcategory":"Construction",
            "type":"Services"
        }
    ],
    "sg:phone":"+90 212 249 0700",
    "sg:postcode":"01740",
    "sg:province":"Istanbul",
    "sg:tags":[
        "foundation"
    ],
    "wof:name":"Kadin Emegini Degerlendirme Vakfi",
    "wof:placetype":"venue"
},
  "geometry": {"coordinates":[28.9743995667,41.0281143188],"type":"Point"}
}