{
  "type": "Feature",
  "properties": {
    "addr:full":"Istanbul Lara Istanbul 07230",
    "addr:postcode":"07230",
    "iso:country":"TR",
    "sg:address":"Istanbul",
    "sg:city":"Lara",
    "sg:classifiers":[
        {
            "category":"Manufacturing",
            "subcategory":"Building Materials",
            "type":"Manufacturing & Wholesale Goods"
        }
    ],
    "sg:phone":"+90 212 638 8139",
    "sg:postcode":"07230",
    "sg:province":"Istanbul",
    "sg:tags":[
        "promotional"
    ],
    "wof:name":"Medas Reklam Hizmetleri",
    "wof:placetype":"venue"
},
  "geometry": {"coordinates":[29.3950977325,40.9473953247],"type":"Point"}
}