{
  "type": "Feature",
  "properties": {
    "addr:full":"?mer Avni Mah. Set Ustu Kabatas Cikmazi Sok. Saadet Apt. 10/6 Kadikoy Istanbul 01370",
    "addr:housenumber":"?;10 / 6",
    "addr:postcode":"01370",
    "addr:street":"Mer Avni;Set;Cikmazi Sok. Saadet Apt.",
    "iso:country":"TR",
    "sg:address":"?mer Avni Mah. Set Ustu Kabatas Cikmazi Sok. Saadet Apt. 10/6",
    "sg:city":"Kadikoy",
    "sg:classifiers":[
        {
            "category":"Marine",
            "type":"Transportation"
        }
    ],
    "sg:phone":"+90 212 252 9293",
    "sg:postcode":"01370",
    "sg:province":"Istanbul",
    "sg:tags":[
        "shipowner"
    ],
    "wof:name":"Beserler Denizcilik A.s.",
    "wof:placetype":"venue"
},
  "geometry": {"coordinates":[28.975925,41.012379],"type":"Point"}
}