{
  "type": "Feature",
  "properties": {
    "iso:country":"TR",
    "sg:address":"Denizoglu Ishani No:4/44",
    "sg:city":"Mecidiyek\u00f6y",
    "sg:classifiers":[
        {
            "category":"Manufacturing",
            "subcategory":"Wood Products",
            "type":"Manufacturing & Wholesale Goods"
        }
    ],
    "sg:phone":"+90 332 712 8867",
    "sg:province":"Konya",
    "sg:tags":[
        "forest"
    ],
    "wof:name":"Bulent Tarim Tic.",
    "wof:placetype":"venue"
},
  "geometry": {"coordinates":[33.0667152405,39.2111282349],"type":"Point"}
}