{
  "type": "Feature",
  "properties": {
    "addr:full":"Ikitelli Organize San. B?gesi Metal Is San. Sit. 11. Blok No:18-20 Ikitelli/K\u00fc\u00e7\u00fck\u00e7ekmece Istanbul 34670",
    "addr:housenumber":"11 blok no 18-20",
    "addr:postcode":"34670",
    "addr:street":"Organize",
    "iso:country":"TR",
    "sg:address":"Ikitelli Organize San. B?gesi Metal Is San. Sit. 11. Blok No:18-20",
    "sg:city":"Ikitelli/K\u00fc\u00e7\u00fck\u00e7ekmece",
    "sg:orig_category":"Ikitelli Metal-is Ind.site",
    "sg:phone":"+90 21254912262",
    "sg:postcode":"34670",
    "sg:province":"Istanbul",
    "wof:name":"Tunay Plast.metal Ve M?h.hiz.san.tic.ltd.sti.",
    "wof:placetype":"venue"
},
  "geometry": {"coordinates":[28.9861831665,41.0408554077],"type":"Point"}
}