{
  "type": "Feature",
  "properties": {
    "addr:full":"Tersaneler Cad.g 50 Sok.no:6 ?zek Sitesi A Blok Tuzla Istanbul 01900",
    "addr:housenumber":"50;6 ?;blok",
    "addr:postcode":"01900",
    "addr:street":"Sok.No;Zek Sitesi A",
    "iso:country":"TR",
    "sg:address":"Tersaneler Cad.g 50 Sok.no:6 ?zek Sitesi A Blok",
    "sg:city":"Tuzla",
    "sg:classifiers":[
        {
            "category":"Marine",
            "type":"Transportation"
        }
    ],
    "sg:phone":"+90 216 494 2702",
    "sg:postcode":"01900",
    "sg:province":"Istanbul",
    "sg:tags":[
        "equipment",
        "maritime"
    ],
    "wof:name":"Cem&nur Ins.teknik Malz.san.tic.ve Tur.ltd.sti",
    "wof:placetype":"venue"
},
  "geometry": {"coordinates":[28.9861831665,41.0408554077],"type":"Point"}
}