{
  "type": "Feature",
  "properties": {
    "iso:country":"TR",
    "sg:address":"Ikitelli Organize San. B?lgesi Sefak?y Sanayi Sitesi 9 Blok No:8-10-12",
    "sg:city":"Ikitelli",
    "sg:classifiers":[
        {
            "category":"Professional",
            "subcategory":"Detective & Security Services",
            "type":"Services"
        }
    ],
    "sg:phone":"+90 212 671 5000",
    "sg:postcode":"34295",
    "sg:province":"Istanbul",
    "sg:tags":[
        "material"
    ],
    "wof:name":"Tekno Pazarlama Ticaret Ve Yatirim A.s.",
    "wof:placetype":"venue"
},
  "geometry": {"coordinates":[28.802141,41.00679],"type":"Point"}
}