{
  "type": "Feature",
  "properties": {
    "addr:full":"Fener Mah. Tekilioglu Cad 1956 Sok Gedikli Sit A Blok No:68 D:3-4 Alanya Antalya 07400",
    "addr:housenumber":"blok no 68 d 3-4",
    "addr:postcode":"1956;07400",
    "addr:street":"Fener Mah. Tekilioglu Cad;Sok Gedikli",
    "iso:country":"TR",
    "sg:address":"Fener Mah. Tekilioglu Cad 1956 Sok Gedikli Sit A Blok No:68 D:3-4",
    "sg:city":"Alanya",
    "sg:classifiers":[
        {
            "category":"Travel",
            "subcategory":"Travel Agent",
            "type":"Entertainment"
        }
    ],
    "sg:phone":"+90 2423242580729",
    "sg:postcode":"07400",
    "sg:province":"Antalya",
    "sg:tags":[
        "agency",
        "tourism"
    ],
    "wof:name":"Novum Turizm",
    "wof:placetype":"venue"
},
  "geometry": {"coordinates":[30.7092056274,36.8790512085],"type":"Point"}
}