{
  "type": "Feature",
  "properties": {
    "iso:country":"TR",
    "sg:address":"Unaldi Mah. Kavasoglu Sok. No:8",
    "sg:city":"Bayrampasa",
    "sg:classifiers":[
        {
            "category":"Shopping",
            "subcategory":"Crafts & Fabrics",
            "type":"Retail Goods"
        }
    ],
    "sg:phone":"+90 342226780708",
    "sg:postcode":"36100",
    "sg:province":"Gaziantep",
    "sg:tags":[
        "yarn"
    ],
    "wof:name":"Ozan Tekstil",
    "wof:placetype":"venue"
},
  "geometry": {"coordinates":[37.4015045166,37.053478241],"type":"Point"}
}