{
  "type": "Feature",
  "properties": {
    "iso:country":"TR",
    "sg:address":"Bayraklidede Mevkii",
    "sg:city":"Kusadasi",
    "sg:orig_category":"Hotels: Motels",
    "sg:phone":"+90 256614927010",
    "sg:postcode":"09400",
    "sg:province":"Aydin",
    "wof:name":"Adakule Hotel",
    "wof:placetype":"venue"
},
  "geometry": {"coordinates":[27.8324394226,37.8409690857],"type":"Point"}
}