{
  "type": "Feature",
  "properties": {
    "addr:full":"A.nafiz Gurman Mah. Mete Sok. Simitas 17/c Blok No: 04-106 Merter Ulus Istanbul 01940",
    "addr:housenumber":"17 / c blok no",
    "addr:postcode":"04-106;01940",
    "addr:street":"Mah. Mete Sok. Simitas",
    "iso:country":"TR",
    "sg:address":"A.nafiz Gurman Mah. Mete Sok. Simitas 17/c Blok No: 04-106 Merter",
    "sg:city":"Ulus",
    "sg:classifiers":[
        {
            "category":"Social Services",
            "subcategory":"Retirement Home",
            "type":"Services"
        }
    ],
    "sg:phone":"+90 212 556 1641",
    "sg:postcode":"01940",
    "sg:province":"Istanbul",
    "sg:tags":[
        "door"
    ],
    "wof:name":"Nartanesi Reklam Hizm.sin.tic.ltd.sti.",
    "wof:placetype":"venue"
},
  "geometry": {"coordinates":[28.9759254456,41.0123786926],"type":"Point"}
}