{
  "type": "Feature",
  "properties": {
    "addr:full":"Birlik Sanayi Sitesi 2.cad.no:43 B\u00fcy\u00fck\u00e7ekmece Istanbul 34905",
    "addr:housenumber":"43",
    "addr:postcode":"34905",
    "addr:street":"Sitesi;Bueyuekc\u0327Ekmece Istanbul",
    "iso:country":"TR",
    "sg:address":"Birlik Sanayi Sitesi 2.cad.no:43",
    "sg:city":"B\u00fcy\u00fck\u00e7ekmece",
    "sg:classifiers":[
        {
            "category":"Manufacturing",
            "subcategory":"Tools & Machinery",
            "type":"Manufacturing & Wholesale Goods"
        }
    ],
    "sg:phone":"+90 2128751713875",
    "sg:postcode":"34905",
    "sg:province":"Istanbul",
    "sg:tags":[
        "machine",
        "industry"
    ],
    "wof:name":"Anb Makina Sanayi Ve Tic.ltd.sti",
    "wof:placetype":"venue"
},
  "geometry": {"coordinates":[29.1171340942,41.022518158],"type":"Point"}
}