{
  "type": "Feature",
  "properties": {
    "iso:country":"TR",
    "sg:address":"657.sok.no:31/a Seyhan Mah.",
    "sg:city":"Sirinyer",
    "sg:classifiers":[
        {
            "category":"Home & Garden",
            "subcategory":"Household Appliances",
            "type":"Retail Goods"
        }
    ],
    "sg:phone":"+90 232 237 8396",
    "sg:postcode":"35380",
    "sg:province":"Izmir",
    "sg:tags":[
        "conditioner",
        "air"
    ],
    "wof:name":"Butas Klima San.ve Tic.ltd.sti.",
    "wof:placetype":"venue"
},
  "geometry": {"coordinates":[27.1421203613,38.3737030029],"type":"Point"}
}