{
  "type": "Feature",
  "properties": {
    "iso:country":"TR",
    "sg:address":"Karaman Mah. Agustos Cd. H??et Konagi Kat:3 03100",
    "sg:city":"Bayrampasa",
    "sg:classifiers":[
        {
            "category":"Education",
            "subcategory":"University",
            "type":"Public Place"
        }
    ],
    "sg:phone":"+90 2722137603729",
    "sg:postcode":"36100",
    "sg:province":"Afyon",
    "sg:tags":[
        "national",
        "chief"
    ],
    "wof:name":"Afyon Milli Egitim M?d?rl?g?",
    "wof:placetype":"venue"
},
  "geometry": {"coordinates":[30.5382652283,38.7579841614],"type":"Point"}
}