{
  "type": "Feature",
  "properties": {
    "iso:country":"TR",
    "sg:address":"Isto?15.ada No:113",
    "sg:city":"G?esli",
    "sg:classifiers":[
        {
            "category":"Structure",
            "subcategory":"Office Building",
            "type":"Public Place"
        }
    ],
    "sg:phone":"+90 212 659 6829",
    "sg:province":"Istanbul",
    "sg:tags":[
        "satellite",
        "system"
    ],
    "wof:name":"Furkan Elektrik",
    "wof:placetype":"venue"
},
  "geometry": {"coordinates":[28.975925,41.012379],"type":"Point"}
}