{
  "type": "Feature",
  "properties": {
    "addr:full":"Lise Cd. No:24/a Kusadasi Diyarbakir 09400",
    "addr:housenumber":"no 24 / a",
    "addr:postcode":"09400",
    "addr:street":"Lise Cd.;Kusadasi Diyarbakir",
    "iso:country":"TR",
    "sg:address":"Lise Cd. No:24/a",
    "sg:city":"Kusadasi",
    "sg:classifiers":[
        {
            "category":"Landmark",
            "subcategory":"Tourist Information",
            "type":"Public Place"
        }
    ],
    "sg:phone":"+90 412 221 2173",
    "sg:postcode":"09400",
    "sg:province":"Diyarbakir",
    "sg:tags":[
        "tourism"
    ],
    "wof:name":"Turizm Danisma Burosu",
    "wof:placetype":"venue"
},
  "geometry": {"coordinates":[40.2107009888,37.9244651794],"type":"Point"}
}