{
  "type": "Feature",
  "properties": {
    "iso:country":"TR",
    "sg:address":"Demrcikara Mah.b.onat Cad.no:61/3",
    "sg:city":"Kepsut",
    "sg:classifiers":[
        {
            "category":"Farming",
            "subcategory":"Farm & Veterinary Services",
            "type":"Manufacturing & Wholesale Goods"
        }
    ],
    "sg:phone":"+90 242 312 3136",
    "sg:postcode":"10660",
    "sg:province":"Antalya",
    "sg:tags":[
        "clinic"
    ],
    "wof:name":"Selcuk Yilmaz",
    "wof:placetype":"venue"
},
  "geometry": {"coordinates":[30.703135,36.887505],"type":"Point"}
}