{
  "type": "Feature",
  "properties": {
    "iso:country":"TR",
    "sg:address":"G. Hisar Mah. A. Mend. Bulv. 8. Sk. No:5/1",
    "sg:city":"1.levent",
    "sg:classifiers":[
        {
            "category":"Wholesale",
            "subcategory":"Machinery & Supplies",
            "type":"Manufacturing & Wholesale Goods"
        }
    ],
    "sg:phone":"+90 256 212 0367",
    "sg:postcode":"34340",
    "sg:province":"Aydin",
    "sg:tags":[
        "laboratory",
        "equipment"
    ],
    "wof:name":"Ata-kim Laboratuvar Malz. San. Tic.",
    "wof:placetype":"venue"
},
  "geometry": {"coordinates":[28.4863967896,37.8117027283],"type":"Point"}
}