{
  "type": "Feature",
  "properties": {
    "iso:country":"TR",
    "sg:address":"Ziya Gokalp Caddesi Nurettin Bey Ishani No: 6 Kat: 3/302",
    "sg:city":"Kizilay",
    "sg:classifiers":[
        {
            "category":"Travel",
            "subcategory":"Travel Agent",
            "type":"Entertainment"
        }
    ],
    "sg:phone":"+90 312 435 8590",
    "sg:postcode":"23050",
    "sg:province":"Ankara",
    "sg:tags":[
        "agency",
        "tourism"
    ],
    "wof:name":"Oyku Turizm Seyahat Acentasi",
    "wof:placetype":"venue"
},
  "geometry": {"coordinates":[32.8604812622,39.9429283142],"type":"Point"}
}