{
  "type": "Feature",
  "properties": {
    "iso:country":"TR",
    "sg:address":"Abdi Ipekci Cad 63",
    "sg:city":"Istanbul",
    "sg:classifiers":[
        {
            "category":"Banks & Credit Unions",
            "subcategory":"Bank",
            "type":"Services"
        }
    ],
    "sg:phone":"+90 21223140",
    "sg:province":"80200",
    "wof:name":"Sitebank",
    "wof:placetype":"venue"
},
  "geometry": {"coordinates":[27.203135,38.429928],"type":"Point"}
}