{
  "type": "Feature",
  "properties": {
    "iso:country":"TR",
    "sg:address":"2. San. Site. 140. Sk. No:35",
    "sg:city":"Ikitelli/K\u00fc\u00e7\u00fck\u00e7ekmece",
    "sg:classifiers":[
        {
            "category":"Retail",
            "subcategory":"Auto Repair",
            "type":"Services"
        }
    ],
    "sg:phone":"+90 258 371 0266",
    "sg:postcode":"34670",
    "sg:province":"Denizli",
    "sg:tags":[
        "maintenance"
    ],
    "wof:name":"Dilek Tic.",
    "wof:placetype":"venue"
},
  "geometry": {"coordinates":[29.0788803101,37.7851867676],"type":"Point"}
}