{
  "type": "Feature",
  "properties": {
    "iso:country":"TR",
    "sg:address":"Necatibey Cad. 86/1 Kizilay",
    "sg:city":"Lara",
    "sg:classifiers":[
        {
            "category":"Manufacturing",
            "subcategory":"Building Materials",
            "type":"Manufacturing & Wholesale Goods"
        }
    ],
    "sg:phone":"+90 312 231 7917",
    "sg:postcode":"07230",
    "sg:province":"Ankara",
    "sg:tags":[
        "promotional"
    ],
    "wof:name":"Meditas Tanitim Urunleri San . Tic. A.s.",
    "wof:placetype":"venue"
},
  "geometry": {"coordinates":[32.8486061096,39.9231338501],"type":"Point"}
}