{
  "type": "Feature",
  "properties": {
    "addr:full":"Tunus Cad. No:51/9-10 K.dere Mersin Ankara 52750",
    "addr:housenumber":"51 / 9-10",
    "addr:postcode":"52750",
    "addr:street":"Tunus Cad. No;K.Dere",
    "iso:country":"TR",
    "sg:address":"Tunus Cad. No:51/9-10 K.dere",
    "sg:city":"Mersin",
    "sg:classifiers":[
        {
            "category":"Wholesale",
            "subcategory":"Medical Equipment & Supplies",
            "type":"Manufacturing & Wholesale Goods"
        }
    ],
    "sg:phone":"+90 312 467 5981",
    "sg:postcode":"52750",
    "sg:province":"Ankara",
    "wof:name":"Simge Paz. Ltd.",
    "wof:placetype":"venue"
},
  "geometry": {"coordinates":[32.8604812622,39.9429283142],"type":"Point"}
}