{
  "type": "Feature",
  "properties": {
    "addr:full":"Levazim Mah. Armagan Sk. Aktas Sitesi B Blok D.1 1.levent Ikitelli Istanbul 34306",
    "addr:housenumber":"b blok d.1 1.levent",
    "addr:postcode":"34306",
    "addr:street":"Levazim Mah. Armagan Sk. Aktas Sitesi;Ikitelli Istanbul",
    "iso:country":"TR",
    "sg:address":"Levazim Mah. Armagan Sk. Aktas Sitesi B Blok D.1 1.levent",
    "sg:city":"Ikitelli",
    "sg:classifiers":[
        {
            "category":"Professional",
            "subcategory":"Testing Lab",
            "type":"Services"
        }
    ],
    "sg:phone":"+90 212 347 7089",
    "sg:postcode":"34306",
    "sg:province":"Istanbul",
    "sg:tags":[
        "laboratory",
        "material"
    ],
    "wof:name":"Unitay Laboratuvar Sanayi A.s.",
    "wof:placetype":"venue"
},
  "geometry": {"coordinates":[28.7984962463,41.0884017944],"type":"Point"}
}