{
  "type": "Feature",
  "properties": {
    "iso:country":"TR",
    "sg:address":"Kazimkarabekir Cad. Koyunlu Han. No:95/31 Iskitler",
    "sg:city":"Kesan",
    "sg:classifiers":[
        {
            "category":"Shopping",
            "subcategory":"Bicycles & Sporting Goods",
            "type":"Retail Goods"
        }
    ],
    "sg:phone":"+90 312 384 1394",
    "sg:postcode":"22800",
    "sg:province":"Ankara",
    "sg:tags":[
        "equipment",
        "marine",
        "hunting"
    ],
    "wof:name":"Karaca Silah Yaglari",
    "wof:placetype":"venue"
},
  "geometry": {"coordinates":[32.8604812622,39.9429283142],"type":"Point"}
}