{
  "type": "Feature",
  "properties": {
    "iso:country":"TR",
    "sg:address":"Dr. Esat Isik Cad.no:65 Moda Kadikoy",
    "sg:city":"Florya",
    "sg:classifiers":[
        {
            "category":"Shopping",
            "subcategory":"Gifts & Souvenirs",
            "type":"Retail Goods"
        }
    ],
    "sg:phone":"+90 216 449 1826",
    "sg:postcode":"34153",
    "sg:province":"Istanbul",
    "wof:name":"Atelya Keramos Seramik Ve Heykel Sanat Atelyesi",
    "wof:placetype":"venue"
},
  "geometry": {"coordinates":[29.0241546631,40.9802589417],"type":"Point"}
}