{
  "type": "Feature",
  "properties": {
    "iso:country":"TR",
    "sg:address":"Halasgargazi Cad.no:182",
    "sg:city":"Osmanbey",
    "sg:classifiers":[
        {
            "category":"Shopping",
            "subcategory":"Clothing, Apparel, & Fashions",
            "type":"Retail Goods"
        }
    ],
    "sg:phone":"+90 212 291 5070",
    "sg:postcode":"63000",
    "sg:province":"Istanbul",
    "sg:tags":[
        "ready",
        "wear"
    ],
    "wof:name":"Arman Tekstil",
    "wof:placetype":"venue"
},
  "geometry": {"coordinates":[28.9876270294,41.0507469177],"type":"Point"}
}