{
  "type": "Feature",
  "properties": {
    "addr:full":"Modoko Sanayi Sitesi No:234 Y.dudullu \u00dcmraniye Istanbul 34776",
    "addr:housenumber":"234",
    "addr:postcode":"34776",
    "addr:street":"Modoko Sanayi Sitesi No",
    "iso:country":"TR",
    "sg:address":"Modoko Sanayi Sitesi No:234 Y.dudullu",
    "sg:city":"\u00dcmraniye",
    "sg:orig_category":"Modoko Istanbul",
    "sg:phone":"+90 21636421363642",
    "sg:postcode":"34776",
    "sg:province":"Istanbul",
    "wof:name":"Besg?l Mobilya Dekorasyon",
    "wof:placetype":"venue"
},
  "geometry": {"coordinates":[29.175403595,41.0060424805],"type":"Point"}
}