{
  "type": "Feature",
  "properties": {
    "addr:full":"75 Yil Cad. Ataturk Sanayi Bolgesi 34860 Hadimkoy Istanbul Sariyer Istanbul 33740",
    "addr:housenumber":"75",
    "addr:postcode":"34860;33740",
    "addr:street":"Yil Cad. Ataturk Sanayi Bolgesi",
    "iso:country":"TR",
    "sg:address":"75 Yil Cad. Ataturk Sanayi Bolgesi 34860 Hadimkoy Istanbul",
    "sg:city":"Sariyer",
    "sg:orig_category":"Miscellaneous Products",
    "sg:phone":"+90 212 771 4020",
    "sg:postcode":"33740",
    "sg:province":"Istanbul",
    "wof:name":"Guven Celik Makina San Tic Ltd Sti",
    "wof:placetype":"venue"
},
  "geometry": {"coordinates":[28.9759254456,41.0123786926],"type":"Point"}
}