{
  "type": "Feature",
  "properties": {
    "iso:country":"TR",
    "sg:address":"Litros Yolu Hacilar San. Sit. No:1/b-6 Topkapi",
    "sg:city":"\u00dcmraniye",
    "sg:classifiers":[
        {
            "category":"Manufacturing",
            "subcategory":"Tools & Machinery",
            "type":"Manufacturing & Wholesale Goods"
        }
    ],
    "sg:phone":"+90 212 567 0868",
    "sg:postcode":"34776",
    "sg:province":"Istanbul",
    "sg:tags":[
        "machine",
        "industry"
    ],
    "wof:name":"Kartal Makina San. Tic. Ltd. Sti.",
    "wof:placetype":"venue"
},
  "geometry": {"coordinates":[29.175403595,41.0060424805],"type":"Point"}
}