{
  "type": "Feature",
  "properties": {
    "addr:full":"I.m.?. 5. Blok No:5660 Unkapani Istanbul 55020",
    "addr:housenumber":"blok no 5660",
    "addr:postcode":"55020",
    "addr:street":"5;Unkapani Istanbul",
    "iso:country":"TR",
    "sg:address":"I.m.?. 5. Blok No:5660",
    "sg:city":"Unkapani",
    "sg:classifiers":[
        {
            "category":"Shopping",
            "subcategory":"Clothing, Apparel, & Fashions",
            "type":"Retail Goods"
        }
    ],
    "sg:phone":"+90 212 511 4362",
    "sg:postcode":"55020",
    "sg:province":"Istanbul",
    "sg:tags":[
        "woman",
        "wear"
    ],
    "wof:name":"Istanbul Etek",
    "wof:placetype":"venue"
},
  "geometry": {"coordinates":[28.7931404114,41.0928535461],"type":"Point"}
}