{
  "type": "Feature",
  "properties": {
    "addr:full":"Eski Gemlik Yolu Leylak Sok. No:12 Kartal Bursa 46000",
    "addr:housenumber":"no 12",
    "addr:postcode":"46000",
    "addr:street":"Eski Gemlik Yolu Leylak Sok.;Kartal Bursa",
    "iso:country":"TR",
    "sg:address":"Eski Gemlik Yolu Leylak Sok. No:12",
    "sg:city":"Kartal",
    "sg:classifiers":[
        {
            "category":"Farming",
            "subcategory":"Fish & Marine Products",
            "type":"Manufacturing & Wholesale Goods"
        }
    ],
    "sg:phone":"+90 224 254 1510",
    "sg:postcode":"46000",
    "sg:province":"Bursa",
    "sg:tags":[
        "automotive"
    ],
    "wof:name":"Oto ?ig A.s.",
    "wof:placetype":"venue"
},
  "geometry": {"coordinates":[29.0580043793,40.1947555542],"type":"Point"}
}