{
  "type": "Feature",
  "properties": {
    "iso:country":"TR",
    "sg:address":"Yeni Nalbant Sk. No.3/1 Elmadag",
    "sg:city":"Arabayatagi",
    "sg:classifiers":[
        {
            "category":"Social Services",
            "subcategory":"Retirement Home",
            "type":"Services"
        }
    ],
    "sg:phone":"+90 212 241 1223",
    "sg:postcode":"16270",
    "sg:province":"Istanbul",
    "sg:tags":[
        "door"
    ],
    "wof:name":"Cetin Neon",
    "wof:placetype":"venue"
},
  "geometry": {"coordinates":[28.9845142365,41.0428886414],"type":"Point"}
}