{
  "type": "Feature",
  "properties": {
    "addr:full":"Hacimini Mah.bogazkesen Cad.no: 55 Tophane-karakoy Sarigazi Istanbul 34785",
    "addr:housenumber":"55",
    "addr:postcode":"34785",
    "addr:street":"Cad.No",
    "iso:country":"TR",
    "sg:address":"Hacimini Mah.bogazkesen Cad.no: 55 Tophane-karakoy",
    "sg:city":"Sarigazi",
    "sg:classifiers":[
        {
            "category":"Manufacturing",
            "subcategory":"Glass & Minerals",
            "type":"Manufacturing & Wholesale Goods"
        }
    ],
    "sg:phone":"+90 212 245 5441",
    "sg:postcode":"34785",
    "sg:province":"Istanbul",
    "sg:tags":[
        "glassware"
    ],
    "wof:name":"Sena Cam Ve Kristal Urunler Pazarlama Ltd.sti.",
    "wof:placetype":"venue"
},
  "geometry": {"coordinates":[29.2059211731,41.0059738159],"type":"Point"}
}