{
  "type": "Feature",
  "properties": {
    "addr:full":"Sivrihisar Cd. Ikinci Dere Sk. No:10 Rami Eskisehir 34055",
    "addr:housenumber":"10",
    "addr:postcode":"34055",
    "addr:street":"Sivrihisar Cd. Ikinci Dere Sk. No;Eskisehir",
    "iso:country":"TR",
    "sg:address":"Sivrihisar Cd. Ikinci Dere Sk. No:10",
    "sg:city":"Rami",
    "sg:classifiers":[
        {
            "category":"Food & Beverages",
            "subcategory":"Dairy",
            "type":"Retail Goods"
        }
    ],
    "sg:phone":"+90 222 231 1766",
    "sg:postcode":"34055",
    "sg:province":"Eskisehir",
    "sg:tags":[
        "pruducts",
        "milk"
    ],
    "wof:name":"Emrullah Erdogan Mahd?mlari Koll. Sti.",
    "wof:placetype":"venue"
},
  "geometry": {"coordinates":[30.5175457001,39.7700805664],"type":"Point"}
}