{
  "type": "Feature",
  "properties": {
    "iso:country":"TR",
    "sg:address":"231 Irfan Bastug Cad.kecioren",
    "sg:city":"33050",
    "sg:classifiers":[
        {
            "category":"Manufacturing",
            "subcategory":"Building Materials",
            "type":"Manufacturing & Wholesale Goods"
        }
    ],
    "sg:phone":"+90 312 338 0990",
    "sg:province":"Ankara",
    "sg:tags":[
        "hospital"
    ],
    "wof:name":"Stemed",
    "wof:placetype":"venue"
},
  "geometry": {"coordinates":[32.8994255066,39.9946479797],"type":"Point"}
}