{
  "type": "Feature",
  "properties": {
    "iso:country":"TR",
    "sg:address":"Bagdat Cd. No:109/b",
    "sg:city":"Maltepe",
    "sg:classifiers":[
        {
            "category":"Home & Garden",
            "subcategory":"Household Appliances",
            "type":"Retail Goods"
        }
    ],
    "sg:phone":"+90 216 305 7177",
    "sg:postcode":"01000",
    "sg:province":"Istanbul",
    "sg:tags":[
        "conditioner",
        "air"
    ],
    "wof:name":"Eksioglu Dogalgaz Ins. Taah.",
    "wof:placetype":"venue"
},
  "geometry": {"coordinates":[29.1047172546,40.9499092102],"type":"Point"}
}