{
  "type": "Feature",
  "properties": {
    "addr:full":"Doganbey Cad. No:102 Gungoren Istanbul 33630",
    "addr:housenumber":"102",
    "addr:postcode":"33630",
    "addr:street":"Doganbey Cad. No;Istanbul",
    "iso:country":"TR",
    "sg:address":"Doganbey Cad. No:102",
    "sg:city":"Gungoren",
    "sg:classifiers":[
        {
            "category":"Home & Garden",
            "subcategory":"Hardware",
            "type":"Retail Goods"
        }
    ],
    "sg:phone":"+90 2126109313729",
    "sg:postcode":"33630",
    "sg:province":"Istanbul",
    "sg:tags":[
        "store"
    ],
    "wof:name":"Set Vida Ve Civata Sanayi Tic.ltd.sti.",
    "wof:placetype":"venue"
},
  "geometry": {"coordinates":[28.8711166382,41.0375556946],"type":"Point"}
}