{
  "type": "Feature",
  "properties": {
    "addr:full":"Izmir Cd. No:25 Kizilay 10020 Ankara",
    "addr:housenumber":"no 25",
    "addr:postcode":"10020",
    "addr:street":"Cd.;Kizilay",
    "iso:country":"TR",
    "sg:address":"Izmir Cd. No:25 Kizilay",
    "sg:city":"10020",
    "sg:classifiers":[
        {
            "category":"Banks & Credit Unions",
            "subcategory":"Investment Brokerage",
            "type":"Services"
        }
    ],
    "sg:phone":"+90 312 425 7872",
    "sg:province":"Ankara",
    "sg:tags":[
        "-",
        "export",
        "import"
    ],
    "wof:name":"Rom Dis Tic. Ltd. Sti.",
    "wof:placetype":"venue"
},
  "geometry": {"coordinates":[32.8510704041,39.9231300354],"type":"Point"}
}