{
  "type": "Feature",
  "properties": {
    "addr:full":"Iyi Niyet S. No: 15 K. 3 Bomonti \u00c7ankaya Istanbul 06660",
    "addr:housenumber":"no 15;3",
    "addr:postcode":"06660",
    "addr:street":"S.;K.",
    "iso:country":"TR",
    "sg:address":"Iyi Niyet S. No: 15 K. 3 Bomonti",
    "sg:city":"\u00c7ankaya",
    "sg:classifiers":[
        {
            "category":"Home & Garden",
            "subcategory":"Building Materials",
            "type":"Retail Goods"
        }
    ],
    "sg:phone":"+90 212 225 0590",
    "sg:postcode":"06660",
    "sg:province":"Istanbul",
    "sg:tags":[
        "window",
        "door",
        "plastic"
    ],
    "wof:name":"Sampiyon Plastik Ltd. Sti.",
    "wof:placetype":"venue"
},
  "geometry": {"coordinates":[28.9759254456,41.0123786926],"type":"Point"}
}