{
  "type": "Feature",
  "properties": {
    "iso:country":"TR",
    "sg:address":"Zafer Mah. 11.sok. No:24",
    "sg:city":"Sarigazi",
    "sg:classifiers":[
        {
            "category":"Food & Beverages",
            "subcategory":"Groceries & Convenience Stores",
            "type":"Retail Goods"
        }
    ],
    "sg:phone":"+90 422 326 3575",
    "sg:postcode":"34785",
    "sg:province":"Malatya",
    "sg:tags":[
        "product"
    ],
    "wof:name":"Metin Gida San. Ve Tic. Ltd.sti.",
    "wof:placetype":"venue"
},
  "geometry": {"coordinates":[38.3382759094,38.351436615],"type":"Point"}
}