{
  "type": "Feature",
  "properties": {
    "addr:full":"Acibadem ?akmak Sitesi 10/3 Kad\u0131k\u00f6y Istanbul 34990",
    "addr:housenumber":"?;10 / 3",
    "addr:postcode":"34990",
    "addr:street":"Akmak Sitesi",
    "iso:country":"TR",
    "sg:address":"Acibadem ?akmak Sitesi 10/3",
    "sg:city":"Kad\u0131k\u00f6y",
    "sg:classifiers":[
        {
            "category":"Government",
            "subcategory":"Fire Station",
            "type":"Public Place"
        }
    ],
    "sg:phone":"+90 216 428 6669",
    "sg:postcode":"34990",
    "sg:province":"Istanbul",
    "sg:tags":[
        "wall",
        "plast",
        "panel"
    ],
    "wof:name":"Mb Dekorasyon",
    "wof:placetype":"venue"
},
  "geometry": {"coordinates":[29.0428752899,41.0045509338],"type":"Point"}
}