{
  "type": "Feature",
  "properties": {
    "iso:country":"TR",
    "sg:address":"Organize San. B?ge. Altinordu Cd. No:5 Sincan",
    "sg:city":"Merkez",
    "sg:classifiers":[
        {
            "category":"Wholesale",
            "subcategory":"Durable Goods & Equipment",
            "type":"Manufacturing & Wholesale Goods"
        }
    ],
    "sg:phone":"+90 312 267 0570",
    "sg:province":"Ankara",
    "sg:tags":[
        "consumer"
    ],
    "wof:name":"Ar?elik A.s.",
    "wof:placetype":"venue"
},
  "geometry": {"coordinates":[32.577960968,39.958770752],"type":"Point"}
}