{
  "type": "Feature",
  "properties": {
    "addr:full":"Y.camlica Mah. Mithatpasa Cad. No:4 Umraniye Ikitelli/K\u00fc\u00e7\u00fck\u00e7ekmece Istanbul 34670",
    "addr:postcode":"34670",
    "addr:street":"Y.Camlica Mah. Mithatpasa Cad. No 4 Umraniye",
    "iso:country":"TR",
    "sg:address":"Y.camlica Mah. Mithatpasa Cad. No:4 Umraniye",
    "sg:city":"Ikitelli/K\u00fc\u00e7\u00fck\u00e7ekmece",
    "sg:classifiers":[
        {
            "category":"Building & Trades",
            "subcategory":"Plumbing",
            "type":"Services"
        }
    ],
    "sg:phone":"+90 216 314 5766",
    "sg:postcode":"34670",
    "sg:province":"Istanbul",
    "sg:tags":[
        "pipe",
        "industry"
    ],
    "wof:name":"Isil Plastik Boru San.ve Tic.ltd.sti.",
    "wof:placetype":"venue"
},
  "geometry": {"coordinates":[29.1094112396,41.0230407715],"type":"Point"}
}