{
  "type": "Feature",
  "properties": {
    "addr:full":"Nispetiye Cad. Baslik Sok. No:21/3 1.levent Istanbul",
    "addr:housenumber":"no 21 / 3 1.levent",
    "addr:street":"Nispetiye Cad. Baslik Sok.",
    "iso:country":"TR",
    "sg:address":"Nispetiye Cad. Baslik Sok. No:21/3",
    "sg:city":"1.levent",
    "sg:classifiers":[
        {
            "category":"Food & Beverages",
            "subcategory":"Meat & Fish",
            "type":"Retail Goods"
        }
    ],
    "sg:phone":"+90 212 264 0159",
    "sg:province":"Istanbul",
    "sg:tags":[
        "product"
    ],
    "wof:name":"Nursev Lux Et",
    "wof:placetype":"venue"
},
  "geometry": {"coordinates":[28.9861831665,41.0408554077],"type":"Point"}
}