{
  "type": "Feature",
  "properties": {
    "iso:country":"TR",
    "sg:address":"Toptancilar Carsisi 2.blok No:44",
    "sg:city":"Alanya",
    "sg:classifiers":[
        {
            "category":"Manufacturing",
            "subcategory":"Food",
            "type":"Manufacturing & Wholesale Goods"
        }
    ],
    "sg:phone":"+90 332 238 8375",
    "sg:postcode":"07110",
    "sg:province":"Konya",
    "sg:tags":[
        "wholesaler"
    ],
    "wof:name":"Akinsan Gida Ve Iht.mad.ltd.sti.",
    "wof:placetype":"venue"
},
  "geometry": {"coordinates":[32.4990272522,37.8715362549],"type":"Point"}
}