{
  "type": "Feature",
  "properties": {
    "addr:full":"7 Eylul Mah. Aydin-mugla Karayolu Uzeri No:6 Esenler . Atisalani Aydin",
    "addr:housenumber":"7",
    "addr:street":"Eylul Mah. Aydin-Mugla Karayolu Uzeri No 6 Esenler Atisalani Aydin",
    "iso:country":"TR",
    "sg:address":"7 Eylul Mah. Aydin-mugla Karayolu Uzeri No:6",
    "sg:city":"Esenler . Atisalani",
    "sg:classifiers":[
        {
            "category":"Retail",
            "subcategory":"Auto Repair",
            "type":"Services"
        }
    ],
    "sg:phone":"+90 256225135522",
    "sg:province":"Aydin",
    "sg:tags":[
        "maintenance"
    ],
    "wof:name":"Yolcu Oto Ins. San. Tic. A.s.",
    "wof:placetype":"venue"
},
  "geometry": {"coordinates":[27.8324394226,37.8409690857],"type":"Point"}
}