{
  "type": "Feature",
  "properties": {
    "addr:full":"Davutpasa Cad.emintas San.sit. Kat.1 No:350 Topkapi Istanbul 24620",
    "addr:housenumber":"no",
    "addr:postcode":"24620",
    "iso:country":"TR",
    "sg:address":"Davutpasa Cad.emintas San.sit. Kat.1 No:350",
    "sg:city":"Topkapi",
    "sg:classifiers":[
        {
            "category":"Wholesale",
            "subcategory":"Vending Machines",
            "type":"Manufacturing & Wholesale Goods"
        }
    ],
    "sg:phone":"+90 532 787 3771",
    "sg:postcode":"24620",
    "sg:province":"Istanbul",
    "sg:tags":[
        "packing"
    ],
    "wof:name":"Ariak Makine Dis Tic. Ltd. Co.",
    "wof:placetype":"venue"
},
  "geometry": {"coordinates":[28.9759254456,41.0123786926],"type":"Point"}
}