{
  "type": "Feature",
  "properties": {
    "iso:country":"TR",
    "sg:address":"Tersane Cd. Devedikeni Sk. Kavak Han No:304 K:3 Karak?",
    "sg:city":"Kad\u0131k\u00f6y",
    "sg:classifiers":[
        {
            "category":"Home & Garden",
            "subcategory":"Kitchen Supply",
            "type":"Retail Goods"
        }
    ],
    "sg:phone":"+90 212 255 3698",
    "sg:postcode":"34724",
    "sg:province":"Istanbul",
    "sg:tags":[
        "fire",
        "extinguisher"
    ],
    "wof:name":"D?zg?nler Pres D?k?m San.",
    "wof:placetype":"venue"
},
  "geometry": {"coordinates":[29.0467185974,40.9827575684],"type":"Point"}
}