{
  "type": "Feature",
  "properties": {
    "iso:country":"TR",
    "sg:address":"Soganli Cad. Beyaktli Sok. No:17/a",
    "sg:city":"Gungoren",
    "sg:classifiers":[
        {
            "category":"Farming",
            "subcategory":"Farm & Veterinary Services",
            "type":"Manufacturing & Wholesale Goods"
        }
    ],
    "sg:phone":"+90 212 502 3876",
    "sg:postcode":"33630",
    "sg:province":"Istanbul",
    "sg:tags":[
        "veterinarian"
    ],
    "wof:name":"Ted Ecza Dep.(sekip Munga )",
    "wof:placetype":"venue"
},
  "geometry": {"coordinates":[28.8549213409,41.0122871399],"type":"Point"}
}