{
  "type": "Feature",
  "properties": {
    "addr:full":"Bagdat Cd. No:199/34 K??yali Bah\u00e7elievler Istanbul 34590",
    "addr:housenumber":"no;/ 34 k ? ?",
    "addr:postcode":"34590",
    "addr:street":"Bagdat Cd.",
    "iso:country":"TR",
    "sg:address":"Bagdat Cd. No:199/34 K??yali",
    "sg:city":"Bah\u00e7elievler",
    "sg:classifiers":[
        {
            "category":"Home & Garden",
            "subcategory":"Household Appliances",
            "type":"Retail Goods"
        }
    ],
    "sg:phone":"+90 216 367 2514",
    "sg:postcode":"34590",
    "sg:province":"Istanbul",
    "sg:tags":[
        "utensil",
        "electrical"
    ],
    "wof:name":"Meteler Day. T?k. Mal. San.",
    "wof:placetype":"venue"
},
  "geometry": {"coordinates":[28.9861831665,41.0408554077],"type":"Point"}
}