{
  "type": "Feature",
  "properties": {
    "iso:country":"TR",
    "sg:address":"Mahmutbey Cd. No:123 Halkali",
    "sg:city":"Sisli",
    "sg:classifiers":[
        {
            "category":"Home & Garden",
            "subcategory":"Home Furnishings",
            "type":"Retail Goods"
        }
    ],
    "sg:phone":"+90 212 579 6845",
    "sg:postcode":"65710",
    "sg:province":"Istanbul",
    "sg:tags":[
        "curtaining",
        "-",
        "upholstering"
    ],
    "wof:name":"?zgin Dikis Makinalari San. Tic. A.s.",
    "wof:placetype":"venue"
},
  "geometry": {"coordinates":[28.80006,41.040546],"type":"Point"}
}