{
  "type": "Feature",
  "properties": {
    "iso:country":"TR",
    "sg:address":"Bakirk? Kartaltepe Aksu Cad. No. 7 34730 Bakirkoy Istanbul",
    "sg:city":"Ikitelli/K\u00fc\u00e7\u00fck\u00e7ekmece",
    "sg:classifiers":[
        {
            "category":"Shopping",
            "subcategory":"Crafts & Fabrics",
            "type":"Retail Goods"
        }
    ],
    "sg:phone":"+90 212 543 6348",
    "sg:postcode":"34670",
    "sg:province":"Istanbul",
    "wof:name":"Emboy-yuntas Tekstil San. Ve Tic. A.s.",
    "wof:placetype":"venue"
},
  "geometry": {"coordinates":[28.9759254456,41.0123786926],"type":"Point"}
}