{
  "type": "Feature",
  "properties": {
    "iso:country":"TR",
    "sg:address":"Kizlarpinar Cd.no:120/c",
    "sg:city":"Ke??en",
    "sg:classifiers":[
        {
            "category":"Home & Garden",
            "subcategory":"Home Furnishings",
            "type":"Retail Goods"
        }
    ],
    "sg:phone":"+90 312 358 2219",
    "sg:province":"Ankara",
    "sg:tags":[
        "-curtains",
        "upholstery"
    ],
    "wof:name":"??ler Mefrusat Tic. Ltd. Sti.",
    "wof:placetype":"venue"
},
  "geometry": {"coordinates":[32.8753814697,39.9886894226],"type":"Point"}
}