{
  "type": "Feature",
  "properties": {
    "addr:full":"Oto Sanayi Sitesi Ulubas Cad. No:64 Levent \u00dcmraniye Istanbul",
    "addr:housenumber":"64",
    "addr:street":"Ulubas Cad. No",
    "iso:country":"TR",
    "sg:address":"Oto Sanayi Sitesi Ulubas Cad. No:64 Levent",
    "sg:city":"\u00dcmraniye",
    "sg:classifiers":[
        {
            "category":"Farming",
            "subcategory":"Fish & Marine Products",
            "type":"Manufacturing & Wholesale Goods"
        }
    ],
    "sg:phone":"+90 212 270 7229",
    "sg:province":"Istanbul",
    "sg:tags":[
        "automotive"
    ],
    "wof:name":"Erduz Otomotiv Ltd.sti.",
    "wof:placetype":"venue"
},
  "geometry": {"coordinates":[29.0070343018,41.0842628479],"type":"Point"}
}