{
  "type": "Feature",
  "properties": {
    "iso:country":"TR",
    "sg:address":"Atat?rk Alani Merdivenli Sk. S?mer Apt. No:1 K:1",
    "sg:city":"Sisli",
    "sg:classifiers":[
        {
            "category":"Travel",
            "subcategory":"Travel Agent",
            "type":"Entertainment"
        }
    ],
    "sg:phone":"+90 462 321 9424",
    "sg:postcode":"65710",
    "sg:province":"Trabzon",
    "sg:tags":[
        "agency",
        "tourism"
    ],
    "wof:name":"Ceyhun Turizm",
    "wof:placetype":"venue"
},
  "geometry": {"coordinates":[39.7165603638,41.0012931824],"type":"Point"}
}