{
  "type": "Feature",
  "properties": {
    "iso:country":"TR",
    "sg:address":"847. Sk. No:8/6 Konak",
    "sg:city":"Kartal",
    "sg:classifiers":[
        {
            "category":"Wholesale",
            "subcategory":"Medical Equipment & Supplies",
            "type":"Manufacturing & Wholesale Goods"
        }
    ],
    "sg:phone":"+90 232 425 6325",
    "sg:postcode":"46000",
    "sg:province":"Izmir",
    "sg:tags":[
        "material"
    ],
    "wof:name":"Inter Tip Ltd. Sti.",
    "wof:placetype":"venue"
},
  "geometry": {"coordinates":[27.1300868988,38.4169311523],"type":"Point"}
}