{
  "type": "Feature",
  "properties": {
    "iso:country":"TR",
    "sg:address":"Halaskargazi Cd. No: 184 Kat: 1",
    "sg:city":"Osmanbey",
    "sg:classifiers":[
        {
            "category":"Shopping",
            "subcategory":"Clothing, Apparel, & Fashions",
            "type":"Retail Goods"
        }
    ],
    "sg:phone":"+90 532 212 3587",
    "sg:postcode":"63000",
    "sg:province":"Istanbul",
    "sg:tags":[
        "woman",
        "wear"
    ],
    "wof:name":"La Fortuna International Trade Ltd.",
    "wof:placetype":"venue"
},
  "geometry": {"coordinates":[28.9759254456,41.0123786926],"type":"Point"}
}