{
  "type": "Feature",
  "properties": {
    "addr:full":"4. Sokak No:20 06370 Ostim Ankara Beyoglu Ankara 34437",
    "addr:housenumber":"no 20",
    "addr:postcode":"06370;beyoglu;34437",
    "addr:street":"4 Sokak",
    "iso:country":"TR",
    "sg:address":"4. Sokak No:20 06370 Ostim Ankara",
    "sg:city":"Beyoglu",
    "sg:classifiers":[
        {
            "category":"Manufacturing",
            "subcategory":"Metals",
            "type":"Manufacturing & Wholesale Goods"
        }
    ],
    "sg:phone":"+90 312 354 1009",
    "sg:postcode":"34437",
    "sg:province":"Ankara",
    "sg:tags":[
        "metallurgy",
        "metalworking"
    ],
    "wof:name":"Aydinlar Mak Met San Tic Ltd Sti",
    "wof:placetype":"venue"
},
  "geometry": {"coordinates":[32.7474136353,39.9668121338],"type":"Point"}
}