{
  "type": "Feature",
  "properties": {
    "iso:country":"TR",
    "sg:address":"Palanga Cd. 44/7",
    "sg:city":"Ortak?",
    "sg:classifiers":[
        {
            "category":"Building & Trades",
            "subcategory":"Electrical",
            "type":"Services"
        }
    ],
    "sg:phone":"+90 212 227 6800",
    "sg:province":"Istanbul",
    "sg:tags":[
        "equipment",
        "lighting"
    ],
    "wof:name":"Sf Dis Ticaret A.s.",
    "wof:placetype":"venue"
},
  "geometry": {"coordinates":[29.0201816559,41.0497398376],"type":"Point"}
}