{
  "type": "Feature",
  "properties": {
    "iso:country":"TR",
    "sg:address":"?oban?sme Cd. No:2/4",
    "sg:city":"Kagithane",
    "sg:classifiers":[
        {
            "category":"Shopping",
            "subcategory":"Florist",
            "type":"Retail Goods"
        }
    ],
    "sg:phone":"+90 212 294 0464",
    "sg:postcode":"34406",
    "sg:province":"Istanbul",
    "sg:tags":[
        "flower"
    ],
    "wof:name":"Pelin ?i?ek",
    "wof:placetype":"venue"
},
  "geometry": {"coordinates":[28.9681472778,41.0811843872],"type":"Point"}
}