{
  "type": "Feature",
  "properties": {
    "iso:country":"TR",
    "sg:address":"Kartal Cd. Kastelli Sit. Kars. No:33 Yakacik Kartal",
    "sg:city":"Kagithane",
    "sg:orig_category":"Aluminium Carpentary",
    "sg:phone":"+90 216 451 2626",
    "sg:postcode":"34406",
    "sg:province":"Istanbul",
    "wof:name":"Babadag Alum. Sti.",
    "wof:placetype":"venue"
},
  "geometry": {"coordinates":[28.9681472778,41.0811843872],"type":"Point"}
}