{
  "type": "Feature",
  "properties": {
    "addr:full":"Mecidiye Cad.sair Sabri Sok.no:7/2 Mecidiyek\u00f6y Istanbul 34387",
    "addr:housenumber":"7 / 2",
    "addr:postcode":"34387",
    "addr:street":"Sok.No",
    "iso:country":"TR",
    "sg:address":"Mecidiye Cad.sair Sabri Sok.no:7/2",
    "sg:city":"Mecidiyek\u00f6y",
    "sg:classifiers":[
        {
            "category":"Communications",
            "subcategory":"Film & Video Production",
            "type":"Services"
        }
    ],
    "sg:phone":"+90 212 217 3004",
    "sg:postcode":"34387",
    "sg:province":"Istanbul",
    "sg:tags":[
        "packing",
        "material"
    ],
    "wof:name":"Deniz Group",
    "wof:placetype":"venue"
},
  "geometry": {"coordinates":[28.9965133667,41.0676803589],"type":"Point"}
}