{
  "type": "Feature",
  "properties": {
    "addr:full":"Isiklar Cad. No:15 Haramidere 34840 Avcilar Istanbul Fikirtepe Istanbul 81030",
    "addr:housenumber":"15",
    "addr:postcode":"34840;81030",
    "addr:street":"Isiklar Cad. No",
    "iso:country":"TR",
    "sg:address":"Isiklar Cad. No:15 Haramidere 34840 Avcilar Istanbul",
    "sg:city":"Fikirtepe",
    "sg:classifiers":[
        {
            "category":"Manufacturing",
            "subcategory":"Printing",
            "type":"Manufacturing & Wholesale Goods"
        }
    ],
    "sg:phone":"+90 212 422 1037",
    "sg:postcode":"81030",
    "sg:province":"Istanbul",
    "sg:tags":[
        "publishing"
    ],
    "wof:name":"Plaksan Plak San As",
    "wof:placetype":"venue"
},
  "geometry": {"coordinates":[28.9759254456,41.0123786926],"type":"Point"}
}