{
  "type": "Feature",
  "properties": {
    "addr:full":"Cicekpazari Sok.b??g? Han No:2 No:54 -emin?? Sultanhamam Sultanhamam Istanbul",
    "addr:housenumber":"emin ? ?",
    "addr:street":"Sultanhamam Sultanhamam",
    "iso:country":"TR",
    "sg:address":"Cicekpazari Sok.b??g? Han No:2 No:54 -emin?? Sultanhamam",
    "sg:city":"Sultanhamam",
    "sg:classifiers":[
        {
            "category":"Shopping",
            "subcategory":"Clothing, Apparel, & Fashions",
            "type":"Retail Goods"
        }
    ],
    "sg:phone":"+90 212 511 2872",
    "sg:province":"Istanbul",
    "sg:tags":[
        "woman",
        "wear"
    ],
    "wof:name":"M.deniz Esarp",
    "wof:placetype":"venue"
},
  "geometry": {"coordinates":[28.9759254456,41.0123786926],"type":"Point"}
}