{
  "type": "Feature",
  "properties": {
    "addr:full":"Istiklal Cad. Hisartepe Mah. No:98/a Gemlik Bursa 16600",
    "addr:housenumber":"mah. no 98 / a",
    "addr:postcode":"16600",
    "addr:street":"Istiklal Cad. Hisartepe;Bursa",
    "iso:country":"TR",
    "sg:address":"Istiklal Cad. Hisartepe Mah. No:98/a",
    "sg:city":"Gemlik",
    "sg:classifiers":[
        {
            "category":"Shopping",
            "subcategory":"Clothing, Apparel, & Fashions",
            "type":"Retail Goods"
        }
    ],
    "sg:phone":"+90 224 512 2747",
    "sg:postcode":"16600",
    "sg:province":"Bursa",
    "sg:tags":[
        "underwear"
    ],
    "wof:name":"Sude Tekstil",
    "wof:placetype":"venue"
},
  "geometry": {"coordinates":[28.992041,40.244114],"type":"Point"}
}