{
  "type": "Feature",
  "properties": {
    "iso:country":"TR",
    "sg:address":"Sehit Ahmet Benler Cad. No: 97 48770",
    "sg:city":"Marmaris",
    "sg:orig_category":"Hotels: Motels",
    "sg:phone":"+90 252 417 4009",
    "sg:postcode":"48700",
    "sg:province":"Mugla",
    "wof:name":"Club Cettia Resort",
    "wof:placetype":"venue"
},
  "geometry": {"coordinates":[28.3628406525,37.215675354],"type":"Point"}
}