{
  "type": "Feature",
  "properties": {
    "addr:full":"Altintac Sk. No.5 Bahcelievler Kazasker Istanbul",
    "addr:housenumber":"bahcelievler",
    "addr:street":"Altintac Sk. No.5",
    "iso:country":"TR",
    "sg:address":"Altintac Sk. No.5 Bahcelievler",
    "sg:city":"Kazasker",
    "sg:classifiers":[
        {
            "category":"Shopping",
            "subcategory":"Photographic Equipment",
            "type":"Retail Goods"
        }
    ],
    "sg:phone":"+90 535 204 4977",
    "sg:province":"Istanbul",
    "sg:tags":[
        "photo"
    ],
    "wof:name":"Cimcoz Fotografcilik",
    "wof:placetype":"venue"
},
  "geometry": {"coordinates":[29.0947971344,41.0447273254],"type":"Point"}
}