{
  "type": "Feature",
  "properties": {
    "iso:country":"TR",
    "sg:address":"Atat?k Oto Sanayi Sit. 2.kisim 32.sok. No:1342 Maslak",
    "sg:city":"Mersin",
    "sg:classifiers":[
        {
            "category":"Wholesale",
            "subcategory":"Auto Parts",
            "type":"Manufacturing & Wholesale Goods"
        }
    ],
    "sg:phone":"+90 212 276 8515",
    "sg:postcode":"52750",
    "sg:province":"Istanbul",
    "sg:tags":[
        "spare"
    ],
    "wof:name":"Yigit Oto",
    "wof:placetype":"venue"
},
  "geometry": {"coordinates":[28.7926616669,41.0970001221],"type":"Point"}
}