{
  "type": "Feature",
  "properties": {
    "addr:full":"Mevlana Cad 5 Konya 42030",
    "addr:housenumber":"5",
    "addr:postcode":"42030",
    "addr:street":"Mevlana Cad",
    "iso:country":"TR",
    "sg:address":"Mevlana Cad 5",
    "sg:city":"Konya",
    "sg:classifiers":[
        {
            "category":"Banks & Credit Unions",
            "subcategory":"Bank",
            "type":"Services"
        }
    ],
    "sg:phone":"+90 332 352 0530",
    "sg:province":"42030",
    "wof:name":"T?kiye Halk, Bankasi As",
    "wof:placetype":"venue"
},
  "geometry": {"coordinates":[32.494617,37.872509],"type":"Point"}
}