{
  "type": "Feature",
  "properties": {
    "iso:country":"TR",
    "sg:address":"Tepecik Mah. 1202 Sok. No: 1/2",
    "sg:city":"Bodrum",
    "sg:classifiers":[
        {
            "category":"Travel",
            "subcategory":"Travel Agent",
            "type":"Entertainment"
        }
    ],
    "sg:phone":"+90 252313149931",
    "sg:postcode":"48400",
    "sg:province":"Mugla",
    "sg:tags":[
        "agency",
        "tourism"
    ],
    "wof:name":"2000 Tur Turizm ( Bodrum Sb.)",
    "wof:placetype":"venue"
},
  "geometry": {"coordinates":[28.3628406525,37.215675354],"type":"Point"}
}