{
  "type": "Feature",
  "properties": {
    "addr:full":"Baris Mah.e5 Karayolu Yani Giseler Karsisi Gebze Kocaeli 41400",
    "addr:postcode":"41400",
    "addr:street":"Karayolu",
    "iso:country":"TR",
    "sg:address":"Baris Mah.e5 Karayolu Yani Giseler Karsisi",
    "sg:city":"Gebze",
    "sg:classifiers":[
        {
            "category":"Manufacturing",
            "subcategory":"Wood Products",
            "type":"Manufacturing & Wholesale Goods"
        }
    ],
    "sg:phone":"+90 262 759 1820",
    "sg:postcode":"41400",
    "sg:province":"Kocaeli",
    "sg:tags":[
        "forest"
    ],
    "wof:name":"G?ven Dekorasyon San.tic.ltd.sti",
    "wof:placetype":"venue"
},
  "geometry": {"coordinates":[29.881521225,40.8532714844],"type":"Point"}
}