{
  "type": "Feature",
  "properties": {
    "addr:full":"Bagdat Cad. No:122/10 Feneryolu Alsancak Istanbul 01365",
    "addr:housenumber":"122 / 10",
    "addr:postcode":"01365",
    "addr:street":"Bagdat Cad. No;Feneryolu",
    "iso:country":"TR",
    "sg:address":"Bagdat Cad. No:122/10 Feneryolu",
    "sg:city":"Alsancak",
    "sg:classifiers":[
        {
            "category":"Manufacturing",
            "subcategory":"Chemicals & Compounds",
            "type":"Manufacturing & Wholesale Goods"
        }
    ],
    "sg:phone":"+90 216 414 5442",
    "sg:postcode":"01365",
    "sg:province":"Istanbul",
    "sg:tags":[
        "medicine"
    ],
    "wof:name":"Albi Kimyevi Mad. Tic. A.s.",
    "wof:placetype":"venue"
},
  "geometry": {"coordinates":[29.0453472137,40.9789543152],"type":"Point"}
}