{
  "type": "Feature",
  "properties": {
    "iso:country":"TR",
    "sg:address":"?arsi Mah. In??cd.",
    "sg:city":"Bayrampasa",
    "sg:classifiers":[
        {
            "category":"Education",
            "subcategory":"University",
            "type":"Public Place"
        }
    ],
    "sg:postcode":"36100",
    "sg:province":"Artvin",
    "sg:tags":[
        "national",
        "chief"
    ],
    "wof:name":"Artvin Milli Egitim M?d?rl?g?",
    "wof:placetype":"venue"
},
  "geometry": {"coordinates":[41.8213844299,41.1813812256],"type":"Point"}
}