{
  "type": "Feature",
  "properties": {
    "iso:country":"TR",
    "sg:address":"Sincan San. Sitesi 1. Cd. 19. Sk. No:7 Sincan",
    "sg:city":"Rami",
    "sg:classifiers":[
        {
            "category":"Manufacturing",
            "subcategory":"Rubber & Plastics",
            "type":"Manufacturing & Wholesale Goods"
        }
    ],
    "sg:phone":"+90 312 271 8400",
    "sg:postcode":"34140",
    "sg:province":"Ankara",
    "sg:tags":[
        "industry"
    ],
    "wof:name":"Volkan Karaaslan Ari Plastik Kagit San. Tic.",
    "wof:placetype":"venue"
},
  "geometry": {"coordinates":[32.8560333252,39.9438743591],"type":"Point"}
}