{
  "type": "Feature",
  "properties": {
    "iso:country":"TR",
    "sg:address":"29. Sokak No:112",
    "sg:city":"Ostim",
    "sg:orig_category":"Ostim Ankara",
    "sg:phone":"+90 312 354 3555",
    "sg:postcode":"06374",
    "sg:province":"Ankara",
    "wof:name":"?zg?ven D?k?m Ve Mak. San. Tic. Ltd. Sti.",
    "wof:placetype":"venue"
},
  "geometry": {"coordinates":[32.8214454651,39.9909172058],"type":"Point"}
}