{
  "type": "Feature",
  "properties": {
    "addr:full":"Cumh. Mh. H?riyet Sk. No:3-1 Bah?lievler Bornova Istanbul 35040",
    "addr:housenumber":"?;3-1;?",
    "addr:postcode":"35040",
    "addr:street":"Cumh. Mh. H;Riyet Sk. No;Lievler",
    "iso:country":"TR",
    "sg:address":"Cumh. Mh. H?riyet Sk. No:3-1 Bah?lievler",
    "sg:city":"Bornova",
    "sg:classifiers":[
        {
            "category":"Manufacturing",
            "subcategory":"Tools & Machinery",
            "type":"Manufacturing & Wholesale Goods"
        }
    ],
    "sg:phone":"+90 212 553 9479",
    "sg:postcode":"35040",
    "sg:province":"Istanbul",
    "sg:tags":[
        "machine",
        "industry"
    ],
    "wof:name":"Yapici Ogullari Makina San.",
    "wof:placetype":"venue"
},
  "geometry": {"coordinates":[28.9759254456,41.0123786926],"type":"Point"}
}