{
  "type": "Feature",
  "properties": {
    "addr:full":"Ankara Cd. Kastel Ismerk. K3 No:87 Sirkeci Bah\u00e7elievler Istanbul 34590",
    "addr:housenumber":"k3 no 87",
    "addr:postcode":"34590",
    "iso:country":"TR",
    "sg:address":"Ankara Cd. Kastel Ismerk. K3 No:87 Sirkeci",
    "sg:city":"Bah\u00e7elievler",
    "sg:classifiers":[
        {
            "category":"Wholesale",
            "subcategory":"Durable Goods & Equipment",
            "type":"Manufacturing & Wholesale Goods"
        }
    ],
    "sg:phone":"+90 212 512 4014",
    "sg:postcode":"34590",
    "sg:province":"Istanbul",
    "sg:tags":[
        "consumer"
    ],
    "wof:name":"Marmara Elek. Ev Alet. Tic.",
    "wof:placetype":"venue"
},
  "geometry": {"coordinates":[28.9861831665,41.0408554077],"type":"Point"}
}