{
  "type": "Feature",
  "properties": {
    "addr:full":"Organize San. B?.sefak? Sanayi Sitesi 17.blok No:15 Ikitelli Istanbul 34306",
    "addr:housenumber":"17.blok no 15",
    "addr:postcode":"34306",
    "addr:street":"Organize;Sanayi Sitesi;Istanbul",
    "iso:country":"TR",
    "sg:address":"Organize San. B?.sefak? Sanayi Sitesi 17.blok No:15",
    "sg:city":"Ikitelli",
    "sg:classifiers":[
        {
            "category":"Manufacturing",
            "subcategory":"Metals",
            "type":"Manufacturing & Wholesale Goods"
        }
    ],
    "sg:phone":"+90 212 549 1896",
    "sg:postcode":"34306",
    "sg:province":"Istanbul",
    "sg:tags":[
        "iron-steel",
        "peoducts"
    ],
    "wof:name":"Adil Metal Ve Plastik Sanayi Ticaret",
    "wof:placetype":"venue"
},
  "geometry": {"coordinates":[28.7984962463,41.0884017944],"type":"Point"}
}