{
  "type": "Feature",
  "properties": {
    "iso:country":"TR",
    "sg:address":"H?riyet Bulv. Tezol Ismerk. No:5/201-202",
    "sg:city":"\u00c7ankaya",
    "sg:classifiers":[
        {
            "category":"Shopping",
            "subcategory":"Crafts & Fabrics",
            "type":"Retail Goods"
        }
    ],
    "sg:phone":"+90 232 441 9888",
    "sg:postcode":"35280",
    "sg:province":"Izmir",
    "sg:tags":[
        "yarn"
    ],
    "wof:name":"Egs Ege Giyim San. Dis Tic. A.s.",
    "wof:placetype":"venue"
},
  "geometry": {"coordinates":[27.1088256836,38.4058265686],"type":"Point"}
}