{
  "type": "Feature",
  "properties": {
    "iso:country":"TR",
    "sg:address":"Cumhuriyet Meydani 14",
    "sg:city":"Antakya",
    "sg:classifiers":[
        {
            "category":"Banks & Credit Unions",
            "subcategory":"Bank",
            "type":"Services"
        }
    ],
    "sg:phone":"+90 326 613 1600",
    "sg:postcode":"31000",
    "sg:province":"31200",
    "wof:name":"Yapi Ve Kredi, Bankasi As",
    "wof:placetype":"venue"
},
  "geometry": {"coordinates":[39.178898,38.671158],"type":"Point"}
}