{
  "type": "Feature",
  "properties": {
    "addr:full":"Hadimk? Yolu, San-bir Bulvari, 4. B?ge, 9. Yol No.48 B???kmece Istanbul",
    "addr:housenumber":"?;4 b ?;no.48 b ? ? ?",
    "addr:street":"Yolu San-Bir Bulvari;Ge 9 Yol",
    "iso:country":"TR",
    "sg:address":"Hadimk? Yolu, San-bir Bulvari, 4. B?ge, 9. Yol No.48",
    "sg:city":"B???kmece",
    "sg:orig_category":"Pvc Packing",
    "sg:phone":"+90 212 886 5090",
    "sg:province":"Istanbul",
    "sg:website":"zeynelplastik.com",
    "wof:name":"Zeynel Plastik San. Tic. Ltd. Sti.",
    "wof:placetype":"venue"
},
  "geometry": {"coordinates":[28.9759254456,41.0123786926],"type":"Point"}
}