{
  "type": "Feature",
  "properties": {
    "addr:full":"T?itak Yolu ?zeri Gebze Ikitelli/K\u00fc\u00e7\u00fck\u00e7ekmece Kocaeli 34670",
    "addr:housenumber":"?",
    "addr:postcode":"34670",
    "addr:street":"T ? Itak Yolu",
    "iso:country":"TR",
    "sg:address":"T?itak Yolu ?zeri Gebze",
    "sg:city":"Ikitelli/K\u00fc\u00e7\u00fck\u00e7ekmece",
    "sg:classifiers":[
        {
            "category":"Manufacturing",
            "subcategory":"Metals",
            "type":"Manufacturing & Wholesale Goods"
        }
    ],
    "sg:phone":"+90 262 641 1538",
    "sg:postcode":"34670",
    "sg:province":"Kocaeli",
    "sg:tags":[
        "iron-steel",
        "peoducts"
    ],
    "wof:name":"Cenk Demir San. Tic. A.s.",
    "wof:placetype":"venue"
},
  "geometry": {"coordinates":[29.881521225,40.8532714844],"type":"Point"}
}