{
  "type": "Feature",
  "properties": {
    "iso:country":"TR",
    "sg:address":"Yeni Golcuk Yolu Uzeri No:1",
    "sg:city":"Ikitelli/K\u00fc\u00e7\u00fck\u00e7ekmece",
    "sg:classifiers":[
        {
            "category":"Manufacturing",
            "subcategory":"Metals",
            "type":"Manufacturing & Wholesale Goods"
        }
    ],
    "sg:phone":"+90 262 335 2970",
    "sg:postcode":"34670",
    "sg:province":"Kocaeli",
    "sg:tags":[
        "iron-steel",
        "peoducts"
    ],
    "wof:name":"G?rsan Demir Celik San. Tic. A.s.",
    "wof:placetype":"venue"
},
  "geometry": {"coordinates":[29.881521225,40.8532714844],"type":"Point"}
}