{
  "type": "Feature",
  "properties": {
    "iso:country":"TR",
    "sg:address":"Sivas Cd. 7.km.",
    "sg:city":"Esenyurt",
    "sg:classifiers":[
        {
            "category":"Food & Beverages",
            "subcategory":"Candy",
            "type":"Retail Goods"
        }
    ],
    "sg:phone":"+90 352 241 0097",
    "sg:postcode":"07800",
    "sg:province":"Kayseri",
    "sg:tags":[
        "biscuit-chocolate-candy"
    ],
    "wof:name":"Hisar ?ik. Seker. Bisk.san.ltd.sti.",
    "wof:placetype":"venue"
},
  "geometry": {"coordinates":[35.489136,38.722576],"type":"Point"}
}