{
  "type": "Feature",
  "properties": {
    "addr:full":"Gazi Bulvari 128 Basmane Izmir 35230",
    "addr:housenumber":"128",
    "addr:postcode":"35230",
    "addr:street":"Gazi Bulvari",
    "iso:country":"TR",
    "sg:address":"Gazi Bulvari 128",
    "sg:city":"Basmane",
    "sg:orig_category":"Hotels: Motels",
    "sg:phone":"+90 2324835548729",
    "sg:postcode":"35230",
    "sg:province":"Izmir",
    "wof:name":"Atlantis Hotel",
    "wof:placetype":"venue"
},
  "geometry": {"coordinates":[27.1409702301,38.4240150452],"type":"Point"}
}