{
  "type": "Feature",
  "properties": {
    "addr:full":"Orta Mah.sakarya Sok. No. 29 Bayrampasa Istanbul 36100",
    "addr:housenumber":"no. 29",
    "addr:postcode":"36100",
    "addr:street":"Mah.Sakarya Sok.;Istanbul",
    "iso:country":"TR",
    "sg:address":"Orta Mah.sakarya Sok. No. 29",
    "sg:city":"Bayrampasa",
    "sg:classifiers":[
        {
            "category":"Shopping",
            "subcategory":"Crafts & Fabrics",
            "type":"Retail Goods"
        }
    ],
    "sg:phone":"+90 212 493 5075",
    "sg:postcode":"36100",
    "sg:province":"Istanbul",
    "sg:tags":[
        "yarn"
    ],
    "wof:name":"Buniteks Tekstil Urunleri",
    "wof:placetype":"venue"
},
  "geometry": {"coordinates":[28.9172859192,41.0336952209],"type":"Point"}
}