{
  "type": "Feature",
  "properties": {
    "iso:country":"TR",
    "sg:address":"Hocahani Cad.kilimkalfa Hani Kat 5 No:17/38 Yesildirek",
    "sg:city":"Emin\u00f6n\u00fc/Ca\u011falo\u011flu",
    "sg:classifiers":[
        {
            "category":"Professional",
            "subcategory":"Art Services",
            "type":"Services"
        }
    ],
    "sg:phone":"+90 212 528 3687",
    "sg:postcode":"34110",
    "sg:province":"Istanbul",
    "sg:tags":[
        "textile",
        "design"
    ],
    "wof:name":"Mota Moda Tasarim Ofisi",
    "wof:placetype":"venue"
},
  "geometry": {"coordinates":[28.9861831665,41.0408554077],"type":"Point"}
}