{
  "type": "Feature",
  "properties": {
    "addr:full":"Ataturk C. Basakli S. No: 24 Gungoren Istanbul 33630",
    "addr:housenumber":"no 24",
    "addr:postcode":"33630",
    "addr:street":"S.;Istanbul",
    "iso:country":"TR",
    "sg:address":"Ataturk C. Basakli S. No: 24",
    "sg:city":"Gungoren",
    "sg:classifiers":[
        {
            "category":"Building & Trades",
            "subcategory":"Locksmith",
            "type":"Services"
        }
    ],
    "sg:phone":"+90 212 557 3400",
    "sg:postcode":"33630",
    "sg:province":"Istanbul",
    "sg:tags":[
        "lock",
        "key"
    ],
    "wof:name":"Kale Kilit San. A.s.",
    "wof:placetype":"venue"
},
  "geometry": {"coordinates":[28.8822078705,41.0244979858],"type":"Point"}
}