{
  "type": "Feature",
  "properties": {
    "addr:full":"Cumhuriyet Cad. No:131/1 Elmadag Istanbul 65900",
    "addr:housenumber":"131 / 1",
    "addr:postcode":"65900",
    "addr:street":"Cumhuriyet Cad. No",
    "iso:country":"TR",
    "sg:address":"Cumhuriyet Cad. No:131/1",
    "sg:city":"Elmadag",
    "sg:classifiers":[
        {
            "category":"Travel",
            "subcategory":"Travel Agent",
            "type":"Entertainment"
        }
    ],
    "sg:phone":"+90 23022722308118",
    "sg:postcode":"65900",
    "sg:province":"Istanbul",
    "sg:tags":[
        "agency",
        "tourism"
    ],
    "wof:name":"Plan Tours Turizm",
    "wof:placetype":"venue"
},
  "geometry": {"coordinates":[28.9861831665,41.0408554077],"type":"Point"}
}