{
  "type": "Feature",
  "properties": {
    "addr:full":"Inonu Cad. Hafiz Serif Sok. No:33 Izmit \u00c7ankaya Kocaeli 06450",
    "addr:housenumber":"no 33",
    "addr:postcode":"06450",
    "addr:street":"Inonu Cad. Hafiz Serif Sok.;Izmit C\u0327Ankaya",
    "iso:country":"TR",
    "sg:address":"Inonu Cad. Hafiz Serif Sok. No:33 Izmit",
    "sg:city":"\u00c7ankaya",
    "sg:classifiers":[
        {
            "category":"Professional",
            "subcategory":"Computer Services",
            "type":"Services"
        }
    ],
    "sg:phone":"+90 262 323 5107",
    "sg:postcode":"06450",
    "sg:province":"Kocaeli",
    "sg:tags":[
        "application",
        "software"
    ],
    "wof:name":"Sercetin Bilgisayar",
    "wof:placetype":"venue"
},
  "geometry": {"coordinates":[29.9345855713,40.7669563293],"type":"Point"}
}