{
  "type": "Feature",
  "properties": {
    "addr:full":"1422. Sok. No. 14 Doganlar Mah. Bornova ?atalca Izmir 34870",
    "addr:housenumber":"no. 14;?",
    "addr:postcode":"1422;34870",
    "addr:street":"Sok.;Doganlar Mah.;Atalca Izmir",
    "iso:country":"TR",
    "sg:address":"1422. Sok. No. 14 Doganlar Mah. Bornova",
    "sg:city":"?atalca",
    "sg:classifiers":[
        {
            "category":"Manufacturing",
            "subcategory":"Leather Goods",
            "type":"Manufacturing & Wholesale Goods"
        }
    ],
    "sg:phone":"+90 232 479 3135",
    "sg:postcode":"34870",
    "sg:province":"Izmir",
    "sg:tags":[
        "chemical"
    ],
    "wof:name":"Tev-kim Kimya Ith.ihr. San.tic.ltd.sti.",
    "wof:placetype":"venue"
},
  "geometry": {"coordinates":[27.260427475,38.4502410889],"type":"Point"}
}