{
  "type": "Feature",
  "properties": {
    "addr:full":"Muratdede Mah. 357 Sok. G?en?ishani No:58 Bayramyeri Denizli 09110",
    "addr:housenumber":"58",
    "addr:postcode":"09110",
    "addr:street":"Muratdede Mah. 357 Sok. G;Ishani No",
    "iso:country":"TR",
    "sg:address":"Muratdede Mah. 357 Sok. G?en?ishani No:58",
    "sg:city":"Bayramyeri",
    "sg:classifiers":[
        {
            "category":"Manufacturing",
            "subcategory":"Textiles",
            "type":"Manufacturing & Wholesale Goods"
        }
    ],
    "sg:phone":"+90 258 263 7087",
    "sg:postcode":"09110",
    "sg:province":"Denizli",
    "sg:tags":[
        "chemical"
    ],
    "wof:name":"?elebiler Tekstil San Ve Tic Ltd Sti",
    "wof:placetype":"venue"
},
  "geometry": {"coordinates":[29.0788803101,37.7851867676],"type":"Point"}
}