{
  "type": "Feature",
  "properties": {
    "addr:full":"Barinaklar Bulvari 2069.sok. No:2/a Lara Kizilay Antalya 23050",
    "addr:housenumber":"2069.sok no 2 / a",
    "addr:postcode":"23050",
    "addr:street":"Barinaklar Bulvari",
    "iso:country":"TR",
    "sg:address":"Barinaklar Bulvari 2069.sok. No:2/a Lara",
    "sg:city":"Kizilay",
    "sg:classifiers":[
        {
            "category":"Shopping",
            "subcategory":"Party Supplies",
            "type":"Retail Goods"
        }
    ],
    "sg:phone":"+90 242 324 5292",
    "sg:postcode":"23050",
    "sg:province":"Antalya",
    "sg:tags":[
        "sound",
        "light",
        "system"
    ],
    "wof:name":"Atempo Sese Ve Isik Sistemleri Ltd.sti",
    "wof:placetype":"venue"
},
  "geometry": {"coordinates":[30.7782363892,36.8527526855],"type":"Point"}
}