{
  "type": "Feature",
  "properties": {
    "addr:full":"Karacaoglan Mah. 166.sok. No: 27 Isikkent Bah\u00e7elievler Izmir 34590",
    "addr:housenumber":"166.sok no 27",
    "addr:postcode":"34590",
    "addr:street":"Karacaoglan Mah.;Isikkent",
    "iso:country":"TR",
    "sg:address":"Karacaoglan Mah. 166.sok. No: 27 Isikkent",
    "sg:city":"Bah\u00e7elievler",
    "sg:classifiers":[
        {
            "category":"Wholesale",
            "subcategory":"Durable Goods & Equipment",
            "type":"Manufacturing & Wholesale Goods"
        }
    ],
    "sg:phone":"+90 232 472 1000",
    "sg:postcode":"34590",
    "sg:province":"Izmir",
    "sg:tags":[
        "consumer"
    ],
    "wof:name":"Maraton Kondisyonel Elektr.ev Alet.saglik Malz.san.tic.ltd.sti.",
    "wof:placetype":"venue"
},
  "geometry": {"coordinates":[27.1423015594,38.4251480103],"type":"Point"}
}