{
  "type": "Feature",
  "properties": {
    "addr:full":"Hosdere Cd. No:131/b Y.ayranci Nil?fer Ankara",
    "addr:housenumber":"no;/ b",
    "addr:street":"Hosdere Cd.;Nil;Fer",
    "iso:country":"TR",
    "sg:address":"Hosdere Cd. No:131/b Y.ayranci",
    "sg:city":"Nil?fer",
    "sg:classifiers":[
        {
            "category":"Farming",
            "subcategory":"Fish & Marine Products",
            "type":"Manufacturing & Wholesale Goods"
        }
    ],
    "sg:phone":"+90 312 440 4034",
    "sg:province":"Ankara",
    "sg:tags":[
        "automotive"
    ],
    "wof:name":"?z?elik Otomotiv San. Tic. Ltd. Sti.",
    "wof:placetype":"venue"
},
  "geometry": {"coordinates":[32.8469543457,39.889881134],"type":"Point"}
}