{
  "type": "Feature",
  "properties": {
    "addr:full":"Cumhuriyet Meydani. Otogar Ishani. No:1 Emirdag Afyon 03600",
    "addr:postcode":"03600",
    "addr:street":"No 1 Emirdag Afyon",
    "iso:country":"TR",
    "sg:address":"Cumhuriyet Meydani. Otogar Ishani. No:1",
    "sg:city":"Emirdag",
    "sg:classifiers":[
        {
            "category":"Travel",
            "subcategory":"Travel Agent",
            "type":"Entertainment"
        }
    ],
    "sg:phone":"+90 2724425194442",
    "sg:postcode":"03600",
    "sg:province":"Afyon",
    "sg:tags":[
        "agency",
        "tourism"
    ],
    "wof:name":"Gold Turizm",
    "wof:placetype":"venue"
},
  "geometry": {"coordinates":[30.5382652283,38.7579841614],"type":"Point"}
}