{
  "type": "Feature",
  "properties": {
    "iso:country":"TR",
    "sg:address":"Resit Galip Cad. Rabat Sk. No:22/6",
    "sg:city":"Gaziosmanpasa",
    "sg:classifiers":[
        {
            "category":"Wholesale",
            "subcategory":"Medical Equipment & Supplies",
            "type":"Manufacturing & Wholesale Goods"
        }
    ],
    "sg:phone":"+90 312 446 5525",
    "sg:postcode":"06700",
    "sg:province":"Ankara",
    "wof:name":"Orbital Medikal Ltd. Sti.",
    "wof:placetype":"venue"
},
  "geometry": {"coordinates":[32.8604812622,39.9429283142],"type":"Point"}
}