{
  "type": "Feature",
  "properties": {
    "addr:full":"Bankalar Cd. No:47 Karak? Ulus Istanbul 06050",
    "addr:housenumber":"no 47",
    "addr:postcode":"?;06050",
    "addr:street":"Bankalar Cd.",
    "iso:country":"TR",
    "sg:address":"Bankalar Cd. No:47 Karak?",
    "sg:city":"Ulus",
    "sg:classifiers":[
        {
            "category":"Shopping",
            "subcategory":"Computers & Home Electronics",
            "type":"Retail Goods"
        }
    ],
    "sg:phone":"+90 212 244 4120",
    "sg:postcode":"06050",
    "sg:province":"Istanbul",
    "sg:tags":[
        "product",
        "electric-electronic"
    ],
    "wof:name":"Radyopanc Elektrik Cih. Malz.",
    "wof:placetype":"venue"
},
  "geometry": {"coordinates":[28.9861831665,41.0408554077],"type":"Point"}
}