{
  "type": "Feature",
  "properties": {
    "iso:country":"TR",
    "sg:address":"Funda Sok. No:7 Kavacik",
    "sg:city":"Sindirgi",
    "sg:classifiers":[
        {
            "category":"Social Services",
            "subcategory":"Retirement Home",
            "type":"Services"
        }
    ],
    "sg:phone":"+90 216 425 5803",
    "sg:postcode":"10330",
    "sg:province":"Istanbul",
    "sg:tags":[
        "door"
    ],
    "wof:name":"3 Ke Reklam Tanitim A.s.",
    "wof:placetype":"venue"
},
  "geometry": {"coordinates":[29.0904312134,41.0944976807],"type":"Point"}
}