{
  "type": "Feature",
  "properties": {
    "iso:country":"TR",
    "sg:address":"Istiklal Cad.no:276 - Beyoglu",
    "sg:city":"Karak\u00f6y",
    "sg:classifiers":[
        {
            "category":"Organizations",
            "subcategory":"Political Organization",
            "type":"Services"
        }
    ],
    "sg:phone":"+90 212 252 3200",
    "sg:postcode":"34110",
    "sg:province":"Istanbul",
    "sg:tags":[
        "party"
    ],
    "wof:name":"Anavatan Partisi",
    "wof:placetype":"venue"
},
  "geometry": {"coordinates":[28.9762840271,41.0321731567],"type":"Point"}
}