{
  "type": "Feature",
  "properties": {
    "iso:country":"TR",
    "sg:address":"Ortahopa Cd. No: 42",
    "sg:city":"Hopa",
    "sg:classifiers":[
        {
            "category":"Freight",
            "type":"Transportation"
        }
    ],
    "sg:phone":"+90 4663512263729",
    "sg:postcode":"08600",
    "sg:province":"Artvin",
    "sg:tags":[
        "agent",
        "shipping",
        "broker"
    ],
    "wof:name":"Tekin Denizcilik Tic. Ltd. Sti.",
    "wof:placetype":"venue"
},
  "geometry": {"coordinates":[41.82,41.181599],"type":"Point"}
}