{
  "type": "Feature",
  "properties": {
    "addr:full":"Kartal Cd. No:33 Yakacik Seyhan Istanbul 01010",
    "addr:housenumber":"no 33",
    "addr:postcode":"01010",
    "addr:street":"Kartal Cd.;Yakacik",
    "iso:country":"TR",
    "sg:address":"Kartal Cd. No:33 Yakacik",
    "sg:city":"Seyhan",
    "sg:classifiers":[
        {
            "category":"Wholesale",
            "subcategory":"Machinery & Supplies",
            "type":"Manufacturing & Wholesale Goods"
        }
    ],
    "sg:phone":"+90 216 377 3950",
    "sg:postcode":"01010",
    "sg:province":"Istanbul",
    "sg:tags":[
        "heavy",
        "construction",
        "macinery"
    ],
    "wof:name":"Bulut Mak. San. Tic. Ltd. Sti.",
    "wof:placetype":"venue"
},
  "geometry": {"coordinates":[28.9861831665,41.0408554077],"type":"Point"}
}