{
  "type": "Feature",
  "properties": {
    "addr:full":"Evren Oto San.sit. 1.kisim 1585 Sk. No:1, 34511 Esenyurt Istanbul Melikgazi Istanbul 38030",
    "addr:postcode":"34511;38030",
    "addr:street":"1585 Sk. No 1",
    "iso:country":"TR",
    "sg:address":"Evren Oto San.sit. 1.kisim 1585 Sk. No:1, 34511 Esenyurt Istanbul",
    "sg:city":"Melikgazi",
    "sg:classifiers":[
        {
            "category":"Shopping",
            "subcategory":"Computers & Home Electronics",
            "type":"Retail Goods"
        }
    ],
    "sg:phone":"+90 212 672 7314",
    "sg:postcode":"38030",
    "sg:province":"Istanbul",
    "sg:tags":[
        "electronic",
        "electrical",
        "equipment"
    ],
    "wof:name":"2m Kablo San.ve Tic.ltd.sti.",
    "wof:placetype":"venue"
},
  "geometry": {"coordinates":[28.9861831665,41.0408554077],"type":"Point"}
}