{
  "type": "Feature",
  "properties": {
    "addr:full":"Ali Cetinkaya Cad 12 Antalya 07100",
    "addr:housenumber":"12",
    "addr:postcode":"07100",
    "addr:street":"Cetinkaya Cad",
    "iso:country":"TR",
    "sg:address":"Ali Cetinkaya Cad 12",
    "sg:city":"Antalya",
    "sg:classifiers":[
        {
            "category":"Banks & Credit Unions",
            "subcategory":"Bank",
            "type":"Services"
        }
    ],
    "sg:phone":"+90 242 247 0656",
    "sg:province":"07100",
    "wof:name":"Interbank As",
    "wof:placetype":"venue"
},
  "geometry": {"coordinates":[30.708511,36.88776],"type":"Point"}
}