{
  "type": "Feature",
  "properties": {
    "addr:full":"Osman Kavuncu Cad. Tmo Arkas Orta San. Iskenderun Kayseri 31200",
    "addr:postcode":"31200",
    "addr:street":"Kavuncu Cad. Tmo Arkas;San. Iskenderun",
    "iso:country":"TR",
    "sg:address":"Osman Kavuncu Cad. Tmo Arkas Orta San.",
    "sg:city":"Iskenderun",
    "sg:classifiers":[
        {
            "category":"Manufacturing",
            "subcategory":"Tools & Machinery",
            "type":"Manufacturing & Wholesale Goods"
        }
    ],
    "sg:phone":"+90 352320924233",
    "sg:postcode":"31200",
    "sg:province":"Kayseri",
    "sg:tags":[
        "machine",
        "industry"
    ],
    "wof:name":"Eskay Elekt. Motor San. Tic. A.s.",
    "wof:placetype":"venue"
},
  "geometry": {"coordinates":[35.4891357422,38.7225761414],"type":"Point"}
}