{
  "type": "Feature",
  "properties": {
    "addr:full":"Buttim B.blok Kat.3 No:808 Buldan Bursa 20400",
    "addr:housenumber":"no",
    "addr:postcode":"20400",
    "iso:country":"TR",
    "sg:address":"Buttim B.blok Kat.3 No:808",
    "sg:city":"Buldan",
    "sg:classifiers":[
        {
            "category":"Home & Garden",
            "subcategory":"Home Furnishings",
            "type":"Retail Goods"
        }
    ],
    "sg:phone":"+90 224 211 0840",
    "sg:postcode":"20400",
    "sg:province":"Bursa",
    "sg:tags":[
        "textile"
    ],
    "wof:name":"?etintas Mensucat",
    "wof:placetype":"venue"
},
  "geometry": {"coordinates":[29.0586109161,40.1844291687],"type":"Point"}
}