{
  "type": "Feature",
  "properties": {
    "addr:full":"Sezenler Sk. No:4/12 Sihhiye B.cekmece Ankara",
    "addr:housenumber":"12",
    "addr:street":"Sezenler Sk. No 4 /",
    "iso:country":"TR",
    "sg:address":"Sezenler Sk. No:4/12 Sihhiye",
    "sg:city":"B.cekmece",
    "sg:classifiers":[
        {
            "category":"Building & Trades",
            "subcategory":"Construction",
            "type":"Services"
        }
    ],
    "sg:phone":"+90 312 229 6974",
    "sg:province":"Ankara",
    "sg:tags":[
        "foundation"
    ],
    "wof:name":"Yurtdisi Isci Cocuk. Egitim Vakfi",
    "wof:placetype":"venue"
},
  "geometry": {"coordinates":[32.8512496948,39.9273872375],"type":"Point"}
}