{
  "type": "Feature",
  "properties": {
    "addr:full":"Demirtaspasa Mah.selvili Sk.15 Yildirim Bursa 03300",
    "addr:postcode":"03300",
    "iso:country":"TR",
    "sg:address":"Demirtaspasa Mah.selvili Sk.15",
    "sg:city":"Yildirim",
    "sg:classifiers":[
        {
            "category":"Wholesale",
            "subcategory":"Chemicals & Plastics",
            "type":"Manufacturing & Wholesale Goods"
        }
    ],
    "sg:phone":"+90 224 271 4673",
    "sg:postcode":"03300",
    "sg:province":"Bursa",
    "sg:tags":[
        "raw",
        "material"
    ],
    "wof:name":"G?knar I? Ve Dis Tic.ltd.sti.",
    "wof:placetype":"venue"
},
  "geometry": {"coordinates":[29.0732898712,40.1902503967],"type":"Point"}
}