{
  "type": "Feature",
  "properties": {
    "addr:full":"Toptanci Hali No:49 Beypazari Antalya 06730",
    "addr:postcode":"06730",
    "addr:street":"Beypazari",
    "iso:country":"TR",
    "sg:address":"Toptanci Hali No:49",
    "sg:city":"Beypazari",
    "sg:classifiers":[
        {
            "category":"Farming",
            "subcategory":"Berry Farm",
            "type":"Manufacturing & Wholesale Goods"
        }
    ],
    "sg:phone":"+90 242 339 1248",
    "sg:postcode":"06730",
    "sg:province":"Antalya",
    "sg:tags":[
        "citrus"
    ],
    "wof:name":"Boluk Seb. Mey. Ith.ihr. Tic.",
    "wof:placetype":"venue"
},
  "geometry": {"coordinates":[30.7092056274,36.8790512085],"type":"Point"}
}