{
  "type": "Feature",
  "properties": {
    "addr:full":"Ismetpasa Cad.yasar Ishani Kat:5 Nisantasi Usak 25370",
    "addr:housenumber":"kat 5",
    "addr:postcode":"25370",
    "addr:street":"Usak",
    "iso:country":"TR",
    "sg:address":"Ismetpasa Cad.yasar Ishani Kat:5",
    "sg:city":"Nisantasi",
    "sg:classifiers":[
        {
            "category":"Home & Garden",
            "subcategory":"Home Furnishings",
            "type":"Retail Goods"
        }
    ],
    "sg:phone":"+90 276 224 1459",
    "sg:postcode":"25370",
    "sg:province":"Usak",
    "sg:tags":[
        "textile"
    ],
    "wof:name":"Nk Dis Tic.ltd.sti.",
    "wof:placetype":"venue"
},
  "geometry": {"coordinates":[29.4078292847,38.6682548523],"type":"Point"}
}