{
  "type": "Feature",
  "properties": {
    "addr:full":"Yildiz 4. Cad. No:45/c Cankaya Ankara 07080",
    "addr:housenumber":"4;45 / c cankaya",
    "addr:postcode":"07080",
    "addr:street":"Yildiz;Cad. No",
    "iso:country":"TR",
    "sg:address":"Yildiz 4. Cad. No:45/c",
    "sg:city":"Cankaya",
    "sg:classifiers":[
        {
            "category":"Manufacturing",
            "subcategory":"Glass & Minerals",
            "type":"Manufacturing & Wholesale Goods"
        }
    ],
    "sg:phone":"+90 312441479091",
    "sg:postcode":"07080",
    "sg:province":"Ankara",
    "sg:tags":[
        "glass-mirror"
    ],
    "wof:name":"Karina Vitray, Dekoratif Cam ?nite Ve Ayna Ltd. Sti.",
    "wof:placetype":"venue"
},
  "geometry": {"coordinates":[30.7455158234,40.7571563721],"type":"Point"}
}