{
  "type": "Feature",
  "properties": {
    "iso:country":"TR",
    "sg:address":"Darulacize Yolu No:59",
    "sg:city":"Ferikoy",
    "sg:classifiers":[
        {
            "category":"Manufacturing",
            "subcategory":"Building Materials",
            "type":"Manufacturing & Wholesale Goods"
        }
    ],
    "sg:phone":"+90 212 248 8795",
    "sg:postcode":"34377",
    "sg:province":"Istanbul",
    "sg:tags":[
        "lifts-elevators"
    ],
    "wof:name":"Star Asansor",
    "wof:placetype":"venue"
},
  "geometry": {"coordinates":[28.9743022919,41.0545310974],"type":"Point"}
}