{
  "type": "Feature",
  "properties": {
    "iso:country":"TR",
    "sg:address":"Dereboyu Sok. No:22 Ayazaga Maslak",
    "sg:city":"Maltepe",
    "sg:classifiers":[
        {
            "category":"Manufacturing",
            "subcategory":"Metals",
            "type":"Manufacturing & Wholesale Goods"
        }
    ],
    "sg:phone":"+90 212 276 5189",
    "sg:postcode":"01000",
    "sg:province":"Istanbul",
    "sg:tags":[
        "industry"
    ],
    "wof:name":"Mekanik Is Ltd.",
    "wof:placetype":"venue"
},
  "geometry": {"coordinates":[28.9965763092,41.1182594299],"type":"Point"}
}