{
  "type": "Feature",
  "properties": {
    "addr:full":"Vatan Mah.ciftehavuzlar Cad. Ar Sok. No:9 Kat:2 Bayrampasa Iskenderun Istanbul 31200",
    "addr:housenumber":"no 9;2",
    "addr:postcode":"31200",
    "addr:street":"Mah.Ciftehavuzlar Cad.;Sok.;Kat",
    "iso:country":"TR",
    "sg:address":"Vatan Mah.ciftehavuzlar Cad. Ar Sok. No:9 Kat:2 Bayrampasa",
    "sg:city":"Iskenderun",
    "sg:classifiers":[
        {
            "category":"Manufacturing",
            "subcategory":"Metals",
            "type":"Manufacturing & Wholesale Goods"
        }
    ],
    "sg:phone":"+90 212 612 3655",
    "sg:postcode":"31200",
    "sg:province":"Istanbul",
    "sg:tags":[
        "industry"
    ],
    "wof:name":"Tac Kalip Imalat San.tic.ltd.sti.",
    "wof:placetype":"venue"
},
  "geometry": {"coordinates":[28.9759254456,41.0123786926],"type":"Point"}
}