{
  "type": "Feature",
  "properties": {
    "iso:country":"TR",
    "sg:address":"Altinkum Mevkii 481 Sk.",
    "sg:city":"Konya Alti",
    "sg:orig_category":"Hotels: Motels",
    "sg:phone":"+90 24222904442",
    "sg:province":"Antalya",
    "wof:name":"Isinda Hotel",
    "wof:placetype":"venue"
},
  "geometry": {"coordinates":[30.7091999054,36.8790512085],"type":"Point"}
}