{
  "type": "Feature",
  "properties": {
    "iso:country":"TR",
    "sg:address":"1201.sok. No:11/2-m Yenisehir",
    "sg:city":"Okmeydani",
    "sg:classifiers":[
        {
            "category":"Shopping",
            "subcategory":"Stationery & Office Supplies",
            "type":"Retail Goods"
        }
    ],
    "sg:phone":"+90 232 433 8646",
    "sg:postcode":"43050",
    "sg:province":"Izmir",
    "wof:name":"Soner Kirtasiye Ltd.sti.",
    "wof:placetype":"venue"
},
  "geometry": {"coordinates":[27.193487,38.399754],"type":"Point"}
}