{
  "type": "Feature",
  "properties": {
    "addr:full":"Rumeli Cad. Itir Sok. Gungor Apt. No:2/4 K:2 D:5 Osmanbey 103 Istanbul",
    "addr:housenumber":"4 k 2 d 5;103",
    "addr:street":"Rumeli Cad. Itir Sok. Gungor Apt. No 2 /;Osmanbey",
    "iso:country":"TR",
    "sg:address":"Rumeli Cad. Itir Sok. Gungor Apt. No:2/4 K:2 D:5 Osmanbey",
    "sg:city":"103",
    "sg:classifiers":[
        {
            "category":"Professional",
            "subcategory":"Computer Services",
            "type":"Services"
        }
    ],
    "sg:phone":"+90 212 231 6610",
    "sg:province":"Istanbul",
    "sg:tags":[
        "application",
        "software"
    ],
    "wof:name":"Nt Station",
    "wof:placetype":"venue"
},
  "geometry": {"coordinates":[28.9861793518,41.040851593],"type":"Point"}
}