{
  "type": "Feature",
  "properties": {
    "addr:full":"Yeni Tahil Civari No: 11 Etlik K?tahya 06010",
    "addr:postcode":"06010",
    "addr:street":"No 11;K ? Tahya",
    "iso:country":"TR",
    "sg:address":"Yeni Tahil Civari No: 11",
    "sg:city":"Etlik",
    "sg:classifiers":[
        {
            "category":"Manufacturing",
            "subcategory":"Food",
            "type":"Manufacturing & Wholesale Goods"
        }
    ],
    "sg:phone":"+90 274 216 1539",
    "sg:postcode":"06010",
    "sg:province":"K?tahya",
    "sg:tags":[
        "wholesaler"
    ],
    "wof:name":"Yildiz Koll.sti.",
    "wof:placetype":"venue"
},
  "geometry": {"coordinates":[32.8532714844,39.929309845],"type":"Point"}
}