{
  "type": "Feature",
  "properties": {
    "iso:country":"TR",
    "sg:address":"Rihtim Cad. No:245",
    "sg:city":"Karakoy",
    "sg:classifiers":[
        {
            "category":"Food & Beverages",
            "subcategory":"Candy",
            "type":"Retail Goods"
        }
    ],
    "sg:phone":"+90 212 293 5140",
    "sg:postcode":"07700",
    "sg:province":"Istanbul",
    "sg:tags":[
        "biscuit-chocolate-candy"
    ],
    "wof:name":"Tunus Dis Ticaret Ve Gida San. Paz. A.s.",
    "wof:placetype":"venue"
},
  "geometry": {"coordinates":[29.127392,40.922367],"type":"Point"}
}