{
  "type": "Feature",
  "properties": {
    "addr:full":"Numunebag Cd. No:54 K:3-4 Bayrampasa Antakya Istanbul 31000",
    "addr:housenumber":"no 54 k 3-4",
    "addr:postcode":"31000",
    "addr:street":"Numunebag Cd.;Bayrampasa",
    "iso:country":"TR",
    "sg:address":"Numunebag Cd. No:54 K:3-4 Bayrampasa",
    "sg:city":"Antakya",
    "sg:classifiers":[
        {
            "category":"Education",
            "subcategory":"Special Training",
            "type":"Public Place"
        }
    ],
    "sg:phone":"+90 212 612 2574",
    "sg:postcode":"31000",
    "sg:province":"Istanbul",
    "sg:tags":[
        "course"
    ],
    "wof:name":"Olimpiyat Egitim Hizm.",
    "wof:placetype":"venue"
},
  "geometry": {"coordinates":[28.9759254456,41.0123786926],"type":"Point"}
}