{
  "type": "Feature",
  "properties": {
    "addr:full":"Gumussuyu Cad. No:9 Fatih Sehitleri Sokak 34150 Bayrampasa Istanbul Beyoglu Istanbul 34437",
    "addr:postcode":"34150;34437",
    "addr:street":"Gumussuyu Cad. No 9 Fatih Sehitleri Sokak",
    "iso:country":"TR",
    "sg:address":"Gumussuyu Cad. No:9 Fatih Sehitleri Sokak 34150 Bayrampasa Istanbul",
    "sg:city":"Beyoglu",
    "sg:classifiers":[
        {
            "category":"Manufacturing",
            "subcategory":"Metals",
            "type":"Manufacturing & Wholesale Goods"
        }
    ],
    "sg:phone":"+90 212 544 9658",
    "sg:postcode":"34437",
    "sg:province":"Istanbul",
    "sg:tags":[
        "metallurgy",
        "metalworking"
    ],
    "wof:name":"Sipahioglu Profil Boru San",
    "wof:placetype":"venue"
},
  "geometry": {"coordinates":[28.913028717,41.0270690918],"type":"Point"}
}