{
  "type": "Feature",
  "properties": {
    "addr:full":"Kataneler Sok. No:18/13 Erenkoy Istanbul 07060",
    "addr:housenumber":"no 18 / 13",
    "addr:postcode":"07060",
    "addr:street":"Kataneler Sok.;Istanbul",
    "iso:country":"TR",
    "sg:address":"Kataneler Sok. No:18/13",
    "sg:city":"Erenkoy",
    "sg:classifiers":[
        {
            "category":"Building & Trades",
            "subcategory":"Landscaping Services",
            "type":"Services"
        }
    ],
    "sg:phone":"+90 216",
    "sg:postcode":"07060",
    "sg:province":"Istanbul",
    "sg:tags":[
        "landscape"
    ],
    "wof:name":"Peyzaj Tasarim Evi",
    "wof:placetype":"venue"
},
  "geometry": {"coordinates":[29.0633430481,41.049621582],"type":"Point"}
}