{
  "type": "Feature",
  "properties": {
    "addr:full":"Istanbul \u00c7ankaya Istanbul",
    "iso:country":"TR",
    "sg:address":"Istanbul",
    "sg:city":"\u00c7ankaya",
    "sg:classifiers":[
        {
            "category":"Shopping",
            "subcategory":"Gifts & Souvenirs",
            "type":"Retail Goods"
        }
    ],
    "sg:phone":"+90 216 335 1626",
    "sg:province":"Istanbul",
    "wof:name":"Ugur Plastik Ltd.sti.",
    "wof:placetype":"venue"
},
  "geometry": {"coordinates":[28.975925,41.012379],"type":"Point"}
}