{
  "type": "Feature",
  "properties": {
    "iso:country":"TR",
    "sg:address":"Istanbul Cad. Konaltas Ish. No:p/27-28",
    "sg:city":"Ulus",
    "sg:classifiers":[
        {
            "category":"Wholesale",
            "subcategory":"Medical Equipment & Supplies",
            "type":"Manufacturing & Wholesale Goods"
        }
    ],
    "sg:phone":"+90 332 351 4739",
    "sg:postcode":"01940",
    "sg:province":"Konya",
    "wof:name":"Konya Tip Tic.",
    "wof:placetype":"venue"
},
  "geometry": {"coordinates":[33.0667152405,39.2111282349],"type":"Point"}
}