{
  "type": "Feature",
  "properties": {
    "addr:full":"206.sok. No:30/1-a Altindag Merkez Izmir 58070",
    "addr:housenumber":"no 30 / 1-a",
    "addr:postcode":"58070",
    "addr:street":"Altindag Merkez",
    "iso:country":"TR",
    "sg:address":"206.sok. No:30/1-a Altindag",
    "sg:city":"Merkez",
    "sg:classifiers":[
        {
            "category":"Wholesale",
            "subcategory":"Vending Machines",
            "type":"Manufacturing & Wholesale Goods"
        }
    ],
    "sg:phone":"+90 232 469 9035",
    "sg:postcode":"58070",
    "sg:province":"Izmir",
    "sg:tags":[
        "rod",
        "welding"
    ],
    "wof:name":"Nurettin Zaim Mak. San.ltd.sti.",
    "wof:placetype":"venue"
},
  "geometry": {"coordinates":[32.8508834839,39.9209251404],"type":"Point"}
}