{
  "type": "Feature",
  "properties": {
    "iso:country":"TR",
    "sg:address":"Nazmi Akbaci Ismerkezi No:236",
    "sg:city":"Maslak",
    "sg:orig_category":"Tours",
    "sg:phone":"+90 212 262 1990",
    "sg:postcode":"34823",
    "sg:province":"Istanbul",
    "wof:name":"Heybeli Turizm",
    "wof:placetype":"venue"
},
  "geometry": {"coordinates":[28.9861831665,41.0408554077],"type":"Point"}
}