{
  "type": "Feature",
  "properties": {
    "addr:full":"Perpa Tic. Merkz. A-blok Kat:13 No:2161 Okmeydani Fatih Istanbul 01740",
    "addr:housenumber":"13 no 2161",
    "addr:postcode":"01740",
    "addr:street":"Kat;Okmeydani Fatih Istanbul",
    "iso:country":"TR",
    "sg:address":"Perpa Tic. Merkz. A-blok Kat:13 No:2161 Okmeydani",
    "sg:city":"Fatih",
    "sg:classifiers":[
        {
            "category":"Wholesale",
            "subcategory":"Medical Equipment & Supplies",
            "type":"Manufacturing & Wholesale Goods"
        }
    ],
    "sg:phone":"+90 212 210 7557",
    "sg:postcode":"01740",
    "sg:province":"Istanbul",
    "sg:tags":[
        "material"
    ],
    "wof:name":"M.e.g",
    "wof:placetype":"venue"
},
  "geometry": {"coordinates":[28.9759254456,41.0123786926],"type":"Point"}
}