{
  "type": "Feature",
  "properties": {
    "addr:full":"Gumruk?ler Sanayi Sitesi A Blok No:7-9 Umraniye Mersin Istanbul 52750",
    "addr:housenumber":"blok no 7-9",
    "addr:postcode":"52750",
    "addr:street":"Sanayi Sitesi A",
    "iso:country":"TR",
    "sg:address":"Gumruk?ler Sanayi Sitesi A Blok No:7-9 Umraniye",
    "sg:city":"Mersin",
    "sg:classifiers":[
        {
            "category":"Wholesale",
            "subcategory":"Auto Parts",
            "type":"Manufacturing & Wholesale Goods"
        }
    ],
    "sg:phone":"+90 216 328 7977",
    "sg:postcode":"52750",
    "sg:province":"Istanbul",
    "sg:tags":[
        "spare"
    ],
    "wof:name":"Yildirim Otomotiv",
    "wof:placetype":"venue"
},
  "geometry": {"coordinates":[28.9861831665,41.0408554077],"type":"Point"}
}