{
  "type": "Feature",
  "properties": {
    "iso:country":"TR",
    "sg:address":"?niversite Blv. No : 168",
    "sg:city":"Sahinbey",
    "sg:classifiers":[
        {
            "category":"Shopping",
            "subcategory":"Hobbies, Toys, & Games",
            "type":"Retail Goods"
        }
    ],
    "sg:phone":"+90 342 335 7316",
    "sg:postcode":"27010",
    "sg:province":"Gaziantep",
    "sg:tags":[
        "equipment",
        "toy"
    ],
    "wof:name":"Oguz Oyun Parklari",
    "wof:placetype":"venue"
},
  "geometry": {"coordinates":[37.4416732788,36.9459457397],"type":"Point"}
}