{
  "type": "Feature",
  "properties": {
    "addr:full":"Edirne Cad.no:43 Menderes Kirklareli 07170",
    "addr:housenumber":"43",
    "addr:postcode":"07170",
    "addr:street":"Menderes Kirklareli",
    "iso:country":"TR",
    "sg:address":"Edirne Cad.no:43",
    "sg:city":"Menderes",
    "sg:classifiers":[
        {
            "category":"Wholesale",
            "subcategory":"Machinery & Supplies",
            "type":"Manufacturing & Wholesale Goods"
        }
    ],
    "sg:phone":"+90 288 214 1743",
    "sg:postcode":"07170",
    "sg:province":"Kirklareli",
    "sg:tags":[
        "agricultural"
    ],
    "wof:name":"Y?z?ak Zirai Sulama Fiskiyeleri",
    "wof:placetype":"venue"
},
  "geometry": {"coordinates":[27.198923111,41.7180938721],"type":"Point"}
}