{
  "type": "Feature",
  "properties": {
    "addr:full":"Bardakcik Sok. No:93/5 K.esat Merkez Ankara 32100",
    "addr:housenumber":"no 93 / 5",
    "addr:postcode":"32100",
    "addr:street":"Bardakcik Sok.;K.Esat Merkez",
    "iso:country":"TR",
    "sg:address":"Bardakcik Sok. No:93/5 K.esat",
    "sg:city":"Merkez",
    "sg:classifiers":[
        {
            "category":"Wholesale",
            "subcategory":"Medical Equipment & Supplies",
            "type":"Manufacturing & Wholesale Goods"
        }
    ],
    "sg:phone":"+90 312 446 9356",
    "sg:postcode":"32100",
    "sg:province":"Ankara",
    "wof:name":"Elci Tibbi Ve Medikal Cihazlar Ithalat Ihracat San.tic. Ltd.sti.",
    "wof:placetype":"venue"
},
  "geometry": {"coordinates":[32.8604812622,39.9429283142],"type":"Point"}
}