{
  "type": "Feature",
  "properties": {
    "addr:full":"Zindanalti Cad. Darulhadis Sok. 7/2 Etiler Edirne 07010",
    "addr:housenumber":"7 / 2",
    "addr:postcode":"07010",
    "addr:street":"Zindanalti Cad. Darulhadis Sok.;Etiler Edirne",
    "iso:country":"TR",
    "sg:address":"Zindanalti Cad. Darulhadis Sok. 7/2",
    "sg:city":"Etiler",
    "sg:classifiers":[
        {
            "category":"Manufacturing",
            "subcategory":"Wood Products",
            "type":"Manufacturing & Wholesale Goods"
        }
    ],
    "sg:phone":"+90 284 214 2764",
    "sg:postcode":"07010",
    "sg:province":"Edirne",
    "sg:tags":[
        "forest"
    ],
    "wof:name":"Akyol Kerestecilik",
    "wof:placetype":"venue"
},
  "geometry": {"coordinates":[26.5604000092,41.6754989624],"type":"Point"}
}