{
  "type": "Feature",
  "properties": {
    "addr:full":"Kepsut Cad. No.72 Silivri Balikesir 34570",
    "addr:housenumber":"silivri",
    "addr:postcode":"34570",
    "addr:street":"Kepsut Cad. No.72",
    "iso:country":"TR",
    "sg:address":"Kepsut Cad. No.72",
    "sg:city":"Silivri",
    "sg:classifiers":[
        {
            "category":"Home & Garden",
            "subcategory":"Building Materials",
            "type":"Retail Goods"
        }
    ],
    "sg:phone":"+90 266 244 2996",
    "sg:postcode":"34570",
    "sg:province":"Balikesir",
    "sg:tags":[
        "stone",
        "natural",
        "marble"
    ],
    "wof:name":"Yapi Mermer Seramik Yapi ?r?nleri Ins. Ve Tic. Ltd. Sti.",
    "wof:placetype":"venue"
},
  "geometry": {"coordinates":[27.9288406372,39.654335022],"type":"Point"}
}