{
  "type": "Feature",
  "properties": {
    "addr:full":"Cihannuma Mh. Akdogan Sk. No:12 Besiktas Istanbul 75200",
    "addr:housenumber":"12",
    "addr:postcode":"75200",
    "addr:street":"Cihannuma Mh. Akdogan Sk. No",
    "iso:country":"TR",
    "sg:address":"Cihannuma Mh. Akdogan Sk. No:12",
    "sg:city":"Besiktas",
    "sg:classifiers":[
        {
            "category":"Home & Garden",
            "subcategory":"Household Appliances",
            "type":"Retail Goods"
        }
    ],
    "sg:phone":"+90 212 227 0322",
    "sg:postcode":"75200",
    "sg:province":"Istanbul",
    "sg:tags":[
        "conditioner",
        "air"
    ],
    "wof:name":"Dogus Isi San. Tic.",
    "wof:placetype":"venue"
},
  "geometry": {"coordinates":[29.0062160492,41.0455322266],"type":"Point"}
}