{
  "type": "Feature",
  "properties": {
    "iso:country":"TR",
    "sg:address":"Anadolu Bulvari No.9/36",
    "sg:city":"Gimat",
    "sg:classifiers":[
        {
            "category":"Banks & Credit Unions",
            "subcategory":"Bank",
            "type":"Services"
        }
    ],
    "sg:phone":"+90 312 397 1170",
    "sg:province":"06370",
    "wof:name":"S?erbank As",
    "wof:placetype":"venue"
},
  "geometry": {"coordinates":[32.789711,39.970249],"type":"Point"}
}