{
  "type": "Feature",
  "properties": {
    "addr:full":"Yesilbahce Mah. 1462. Sok . Emka Sit.d:3 Kazasker Antalya",
    "addr:housenumber":"3",
    "addr:postcode":"1462",
    "addr:street":"Yesilbahce Mah.;Sok Emka Sit.D",
    "iso:country":"TR",
    "sg:address":"Yesilbahce Mah. 1462. Sok . Emka Sit.d:3",
    "sg:city":"Kazasker",
    "sg:classifiers":[
        {
            "category":"Farming",
            "subcategory":"Farm & Veterinary Services",
            "type":"Manufacturing & Wholesale Goods"
        }
    ],
    "sg:phone":"+90 2423111144311",
    "sg:province":"Antalya",
    "sg:tags":[
        "veterinarian"
    ],
    "wof:name":"Telat Varol",
    "wof:placetype":"venue"
},
  "geometry": {"coordinates":[30.7031345367,36.8875045776],"type":"Point"}
}