{
  "type": "Feature",
  "properties": {
    "addr:full":"Ismetiye Mah.ismetiye Sok. Yasar Kardesler Is Merkezi Kat:2 No:25 Okmeydani/sisli Malatya 80270",
    "addr:housenumber":"kat 2 no 25",
    "addr:postcode":"80270",
    "addr:street":"Mah.Ismetiye Sok. Yasar Kardesler",
    "iso:country":"TR",
    "sg:address":"Ismetiye Mah.ismetiye Sok. Yasar Kardesler Is Merkezi Kat:2 No:25",
    "sg:city":"Okmeydani/sisli",
    "sg:classifiers":[
        {
            "category":"Professional",
            "subcategory":"Detective & Security Services",
            "type":"Services"
        }
    ],
    "sg:phone":"+90 422 325 7335",
    "sg:postcode":"80270",
    "sg:province":"Malatya",
    "sg:tags":[
        "material"
    ],
    "wof:name":"Iris Ltd.sti.",
    "wof:placetype":"venue"
},
  "geometry": {"coordinates":[38.314301,38.3475],"type":"Point"}
}