{
  "type": "Feature",
  "properties": {
    "addr:full":"Bahriye Cd. No: 17 Kasimpasa Beylikduzu Istanbul 34520",
    "addr:housenumber":"no 17",
    "addr:postcode":"34520",
    "addr:street":"Bahriye Cd.",
    "iso:country":"TR",
    "sg:address":"Bahriye Cd. No: 17 Kasimpasa",
    "sg:city":"Beylikduzu",
    "sg:orig_category":"General Industrial Products",
    "sg:phone":"+90 212 237 5118",
    "sg:postcode":"34520",
    "sg:province":"Istanbul",
    "wof:name":"Ozdemir Kardesler San. Tic. Ltd. Sti.",
    "wof:placetype":"venue"
},
  "geometry": {"coordinates":[28.9669208527,41.0351142883],"type":"Point"}
}