{
  "type": "Feature",
  "properties": {
    "addr:full":"Tersane Cad.futuhat Sok.no:34 Rulmak Han Karakoy Karak?y Istanbul -",
    "addr:housenumber":"34",
    "addr:street":"Sok.No",
    "iso:country":"TR",
    "sg:address":"Tersane Cad.futuhat Sok.no:34 Rulmak Han Karakoy",
    "sg:city":"Karak?y",
    "sg:classifiers":[
        {
            "category":"Wholesale",
            "subcategory":"Machinery & Supplies",
            "type":"Manufacturing & Wholesale Goods"
        }
    ],
    "sg:phone":"+90 212 238 8318",
    "sg:postcode":"-",
    "sg:province":"Istanbul",
    "sg:tags":[
        "bearing",
        "ball"
    ],
    "wof:name":"Rulmak Bilya Paz.dis Tic. Ltd. Sti.",
    "wof:placetype":"venue"
},
  "geometry": {"coordinates":[28.975925,41.012379],"type":"Point"}
}