{
  "type": "Feature",
  "properties": {
    "addr:full":"Genclik Mah Tevfik Isik Cad Meltem Sit. (eskii Mezbaha Karsisi) 3.blok No : 47/1-b Merkez Antalya 07100",
    "addr:housenumber":"no 47 / 1-b",
    "addr:postcode":"07100",
    "addr:street":"Genclik Mah Tevfik Isik Cad",
    "iso:country":"TR",
    "sg:address":"Genclik Mah Tevfik Isik Cad Meltem Sit. (eskii Mezbaha Karsisi) 3.blok No : 47/1-b",
    "sg:city":"Merkez",
    "sg:classifiers":[
        {
            "category":"Manufacturing",
            "subcategory":"Rubber & Plastics",
            "type":"Manufacturing & Wholesale Goods"
        }
    ],
    "sg:phone":"+90 242 312 7330",
    "sg:postcode":"07100",
    "sg:province":"Antalya",
    "sg:tags":[
        "flower"
    ],
    "wof:name":"Pagoda Cicek Evi",
    "wof:placetype":"venue"
},
  "geometry": {"coordinates":[30.7134380341,36.8814849854],"type":"Point"}
}