{
  "type": "Feature",
  "properties": {
    "addr:full":"Sirinyali Mahallesi Ismet G?ksen Caddesi Alp Apt. No:397/5 Marmaris Antalya 48700",
    "addr:housenumber":"?;397 / 5",
    "addr:postcode":"48700",
    "addr:street":"Sirinyali Mahallesi Ismet G;Ksen Caddesi Alp Apt. No;Marmaris",
    "iso:country":"TR",
    "sg:address":"Sirinyali Mahallesi Ismet G?ksen Caddesi Alp Apt. No:397/5",
    "sg:city":"Marmaris",
    "sg:classifiers":[
        {
            "category":"Travel",
            "subcategory":"Travel Agent",
            "type":"Entertainment"
        }
    ],
    "sg:phone":"+90 2423237706729",
    "sg:postcode":"48700",
    "sg:province":"Antalya",
    "sg:tags":[
        "agency",
        "tourism"
    ],
    "wof:name":"Cedrus Turizm",
    "wof:placetype":"venue"
},
  "geometry": {"coordinates":[30.7092056274,36.8790512085],"type":"Point"}
}