{
  "type": "Feature",
  "properties": {
    "addr:full":"Yeni Yalova Yolu Buttim Is Merk.no1327 Gebze Bursa 41400",
    "addr:postcode":"merk.no1327;41400",
    "addr:street":"Yalova Yolu Buttim Is",
    "iso:country":"TR",
    "sg:address":"Yeni Yalova Yolu Buttim Is Merk.no1327",
    "sg:city":"Gebze",
    "sg:classifiers":[
        {
            "category":"Home & Garden",
            "subcategory":"Home Furnishings",
            "type":"Retail Goods"
        }
    ],
    "sg:phone":"+90 224 211 1033",
    "sg:postcode":"41400",
    "sg:province":"Bursa",
    "sg:tags":[
        "curtaining",
        "-",
        "upholstering"
    ],
    "wof:name":"Almertia International Home Fdashions",
    "wof:placetype":"venue"
},
  "geometry": {"coordinates":[29.058004,40.194756],"type":"Point"}
}