{
  "type": "Feature",
  "properties": {
    "addr:full":"Yeni Sanayi Sitesi 5, Cad. No:57 Mersin Kayseri 52750",
    "addr:housenumber":"5;57",
    "addr:postcode":"52750",
    "addr:street":"Yeni Sanayi Sitesi;Cad. No",
    "iso:country":"TR",
    "sg:address":"Yeni Sanayi Sitesi 5, Cad. No:57",
    "sg:city":"Mersin",
    "sg:classifiers":[
        {
            "category":"Wholesale",
            "subcategory":"Auto Parts",
            "type":"Manufacturing & Wholesale Goods"
        }
    ],
    "sg:phone":"+90 352331226162",
    "sg:postcode":"52750",
    "sg:province":"Kayseri",
    "sg:tags":[
        "spare"
    ],
    "wof:name":"Sen Otomotiv",
    "wof:placetype":"venue"
},
  "geometry": {"coordinates":[35.4364013672,38.7450408936],"type":"Point"}
}