{
  "type": "Feature",
  "properties": {
    "addr:full":"Osmaniye Fab. Cd. K?oglu Apt. No:11/2 Bak\u0131rk\u00f6y Istanbul",
    "iso:country":"TR",
    "sg:address":"Osmaniye Fab. Cd. K?oglu Apt. No:11/2",
    "sg:city":"Bak\u0131rk\u00f6y",
    "sg:classifiers":[
        {
            "category":"Home & Garden",
            "subcategory":"Household Appliances",
            "type":"Retail Goods"
        }
    ],
    "sg:phone":"+90 212 583 8913",
    "sg:province":"Istanbul",
    "sg:tags":[
        "conditioner",
        "air"
    ],
    "wof:name":"Met M?h. Isi. Sog. San.",
    "wof:placetype":"venue"
},
  "geometry": {"coordinates":[28.9759254456,41.0123786926],"type":"Point"}
}