{
  "type": "Feature",
  "properties": {
    "addr:full":"Fuatpasa Cad. Ibn? Em? Is Hani Kat.2 No:46 Mercan Istanbul 12600",
    "addr:housenumber":"?;no 46",
    "addr:postcode":"?;kat.2;12600",
    "addr:street":"Fuatpasa Cad. Ibn",
    "iso:country":"TR",
    "sg:address":"Fuatpasa Cad. Ibn? Em? Is Hani Kat.2 No:46",
    "sg:city":"Mercan",
    "sg:classifiers":[
        {
            "category":"Shopping",
            "subcategory":"Baby Store",
            "type":"Retail Goods"
        }
    ],
    "sg:phone":"+90 212 527 6536",
    "sg:postcode":"12600",
    "sg:province":"Istanbul",
    "sg:tags":[
        "wear"
    ],
    "wof:name":"Tikir Tekstil San",
    "wof:placetype":"venue"
},
  "geometry": {"coordinates":[28.975925,41.012379],"type":"Point"}
}