{
  "type": "Feature",
  "properties": {
    "addr:full":"Anadolu Sanayi Demirtepe Sok.no: 29 Selcuklu \u00dcmraniye Konya",
    "addr:housenumber":"29",
    "addr:street":"Anadolu Sanayi Demirtepe Sok.No",
    "iso:country":"TR",
    "sg:address":"Anadolu Sanayi Demirtepe Sok.no: 29 Selcuklu",
    "sg:city":"\u00dcmraniye",
    "sg:classifiers":[
        {
            "category":"Building & Trades",
            "subcategory":"Construction",
            "type":"Services"
        }
    ],
    "sg:phone":"+90 332 551 2738",
    "sg:province":"Konya",
    "sg:tags":[
        "industry",
        "mold"
    ],
    "wof:name":"Disbudak Kalip",
    "wof:placetype":"venue"
},
  "geometry": {"coordinates":[32.4922866821,37.8815193176],"type":"Point"}
}