{
  "type": "Feature",
  "properties": {
    "addr:full":"Pekmez Paz. Cad. No: 132 Kavaklidere K?tahya 06660",
    "addr:housenumber":"132;k ?",
    "addr:postcode":"06660",
    "addr:street":"Paz. Cad. No;Tahya",
    "iso:country":"TR",
    "sg:address":"Pekmez Paz. Cad. No: 132",
    "sg:city":"Kavaklidere",
    "sg:classifiers":[
        {
            "category":"Mining & Drilling",
            "type":"Manufacturing & Wholesale Goods"
        }
    ],
    "sg:phone":"+90 274 216 1066",
    "sg:postcode":"06660",
    "sg:province":"K?tahya",
    "sg:tags":[
        "industry",
        "mine"
    ],
    "wof:name":"Asanlar Madencilik A.s.",
    "wof:placetype":"venue"
},
  "geometry": {"coordinates":[32.8532714844,39.929309845],"type":"Point"}
}