{
  "type": "Feature",
  "properties": {
    "addr:full":"Valikonagi Cad. No:173 K:6 Nisantasi Emek Istanbul 01940",
    "addr:housenumber":"173 k 6",
    "addr:postcode":"01940",
    "addr:street":"Valikonagi Cad. No;Nisantasi",
    "iso:country":"TR",
    "sg:address":"Valikonagi Cad. No:173 K:6 Nisantasi",
    "sg:city":"Emek",
    "sg:classifiers":[
        {
            "category":"Manufacturing",
            "subcategory":"Chemicals & Compounds",
            "type":"Manufacturing & Wholesale Goods"
        }
    ],
    "sg:phone":"+90 212 273 3339",
    "sg:postcode":"01940",
    "sg:province":"Istanbul",
    "sg:tags":[
        "pharmaceutical"
    ],
    "wof:name":"Phone - Poulenc A.s.",
    "wof:placetype":"venue"
},
  "geometry": {"coordinates":[28.9759254456,41.0123786926],"type":"Point"}
}