{
  "type": "Feature",
  "properties": {
    "addr:full":"Mustafa Pasa Mah 154 Sok Gebze Kocaeli 41400",
    "addr:postcode":"41400",
    "addr:street":"Mustafa Pasa Mah 154 Sok",
    "iso:country":"TR",
    "sg:address":"Mustafa Pasa Mah 154 Sok",
    "sg:city":"Gebze",
    "sg:classifiers":[
        {
            "category":"Home & Garden",
            "subcategory":"Household Appliances",
            "type":"Retail Goods"
        }
    ],
    "sg:phone":"+90 262 643 7802",
    "sg:postcode":"41400",
    "sg:province":"Kocaeli",
    "sg:tags":[
        "utensil",
        "electrical"
    ],
    "wof:name":"Sultanlar Ticaret Ltd",
    "wof:placetype":"venue"
},
  "geometry": {"coordinates":[29.9345855713,40.7669563293],"type":"Point"}
}