{
  "type": "Feature",
  "properties": {
    "addr:full":"Cark Sanayi Cad. No:26-28 Adapazari Ikitelli/K\u00fc\u00e7\u00fck\u00e7ekmece Sakarya 34670",
    "addr:housenumber":"no 26-28",
    "addr:postcode":"34670",
    "addr:street":"Cark Sanayi Cad.;Adapazari Ikitelli / Kuec\u0327Uekc\u0327Ekmece Sakarya",
    "iso:country":"TR",
    "sg:address":"Cark Sanayi Cad. No:26-28 Adapazari",
    "sg:city":"Ikitelli/K\u00fc\u00e7\u00fck\u00e7ekmece",
    "sg:classifiers":[
        {
            "category":"Wholesale",
            "subcategory":"Auto Parts",
            "type":"Manufacturing & Wholesale Goods"
        }
    ],
    "sg:phone":"+90 264 277 4096",
    "sg:postcode":"34670",
    "sg:province":"Sakarya",
    "sg:tags":[
        "spare"
    ],
    "wof:name":"Cetin-is Oto Yedek Parca Ve Tic Ve San Ltd.sti.",
    "wof:placetype":"venue"
},
  "geometry": {"coordinates":[30.3791446686,40.7734336853],"type":"Point"}
}