{
  "type": "Feature",
  "properties": {
    "iso:country":"TR",
    "sg:address":"2.organize Sanayi Bolgesi C. Dogan Bulvari 104/10",
    "sg:city":"Baspinar",
    "sg:classifiers":[
        {
            "category":"Food & Beverages",
            "subcategory":"Groceries & Convenience Stores",
            "type":"Retail Goods"
        }
    ],
    "sg:phone":"+90 342 337 3333",
    "sg:postcode":"07800",
    "sg:province":"Gaziantep",
    "sg:tags":[
        "product"
    ],
    "wof:name":"Celikler Gida San.tic.ltd.sti.",
    "wof:placetype":"venue"
},
  "geometry": {"coordinates":[37.3761024475,37.0629463196],"type":"Point"}
}