{
  "type": "Feature",
  "properties": {
    "iso:country":"TR",
    "sg:address":"Incirli C. No: 52/2 Bakirk?",
    "sg:city":"Ikitelli/K\u00fc\u00e7\u00fck\u00e7ekmece",
    "sg:classifiers":[
        {
            "category":"Home & Garden",
            "subcategory":"Building Materials",
            "type":"Retail Goods"
        }
    ],
    "sg:phone":"+90 212 583 5441",
    "sg:postcode":"34670",
    "sg:province":"Istanbul",
    "sg:tags":[
        "window",
        "door",
        "plastic"
    ],
    "wof:name":"Pen Kapen Plastik Yapi Elm. San. Tic. A.s.",
    "wof:placetype":"venue"
},
  "geometry": {"coordinates":[28.8722038269,40.9877700806],"type":"Point"}
}