{
  "type": "Feature",
  "properties": {
    "addr:full":"Sehit Pamir Cd. No: 84 Iskenderun Hatay 31200",
    "addr:housenumber":"no 84",
    "addr:postcode":"31200",
    "addr:street":"Sehit Pamir Cd.",
    "iso:country":"TR",
    "sg:address":"Sehit Pamir Cd. No: 84",
    "sg:city":"Iskenderun",
    "sg:classifiers":[
        {
            "category":"Manufacturing",
            "subcategory":"Rubber & Plastics",
            "type":"Manufacturing & Wholesale Goods"
        }
    ],
    "sg:phone":"+90 326 617 2913",
    "sg:postcode":"31200",
    "sg:province":"Hatay",
    "sg:tags":[
        "industry"
    ],
    "wof:name":"Ceylan Plas. San. Ltd.sti.",
    "wof:placetype":"venue"
},
  "geometry": {"coordinates":[36.170337677,36.5870666504],"type":"Point"}
}