{
  "type": "Feature",
  "properties": {
    "addr:full":"Mithatgasa Caddesi 421/b Kartal Izmir 81440",
    "addr:housenumber":"421 / b",
    "addr:postcode":"81440",
    "addr:street":"Mithatgasa Caddesi;Kartal Izmir",
    "iso:country":"TR",
    "sg:address":"Mithatgasa Caddesi 421/b",
    "sg:city":"Kartal",
    "sg:classifiers":[
        {
            "category":"Manufacturing",
            "subcategory":"Building Materials",
            "type":"Manufacturing & Wholesale Goods"
        }
    ],
    "sg:phone":"+90 232 425 2014",
    "sg:postcode":"81440",
    "sg:province":"Izmir",
    "sg:tags":[
        "lifts-elevators"
    ],
    "wof:name":"Yetis Asansorleri",
    "wof:placetype":"venue"
},
  "geometry": {"coordinates":[27.1099128723,38.4085960388],"type":"Point"}
}