{
  "type": "Feature",
  "properties": {
    "iso:country":"TR",
    "sg:address":"Tarak?cafer Sk. No:6",
    "sg:city":"Yesildirek",
    "sg:classifiers":[
        {
            "category":"Shopping",
            "subcategory":"Baby Store",
            "type":"Retail Goods"
        }
    ],
    "sg:phone":"+90 212 520 1658",
    "sg:postcode":"63200",
    "sg:province":"Istanbul",
    "sg:tags":[
        "wear"
    ],
    "wof:name":"Sanbebe",
    "wof:placetype":"venue"
},
  "geometry": {"coordinates":[28.992664,41.036251],"type":"Point"}
}