{
  "type": "Feature",
  "properties": {
    "iso:country":"TR",
    "sg:address":"Dogu San. Sit. 13 Blok No:1",
    "sg:city":"Y.bosna",
    "sg:classifiers":[
        {
            "category":"Home & Garden",
            "subcategory":"Hardware",
            "type":"Retail Goods"
        }
    ],
    "sg:phone":"+90 212 552 0052",
    "sg:province":"Istanbul",
    "sg:tags":[
        "store"
    ],
    "wof:name":"Bigmen Lux Mentese San.",
    "wof:placetype":"venue"
},
  "geometry": {"coordinates":[28.9861831665,41.0408554077],"type":"Point"}
}