{
  "type": "Feature",
  "properties": {
    "addr:full":"Gaziler C. No.26/a Basmane \u00c7orlu Izmir",
    "addr:housenumber":"no.26 / a;c\u0327orlu",
    "addr:street":"C.",
    "iso:country":"TR",
    "sg:address":"Gaziler C. No.26/a Basmane",
    "sg:city":"\u00c7orlu",
    "sg:classifiers":[
        {
            "category":"Shopping",
            "subcategory":"Luggage & Leather Goods",
            "type":"Retail Goods"
        }
    ],
    "sg:phone":"+90 232 425 2715",
    "sg:province":"Izmir",
    "sg:tags":[
        "leather-fur",
        "wear"
    ],
    "wof:name":"Sandersan Deri Giy. Ltd.sti.",
    "wof:placetype":"venue"
},
  "geometry": {"coordinates":[27.156129837,38.423374176],"type":"Point"}
}