{
  "type": "Feature",
  "properties": {
    "addr:full":"Yenidogan Mah. 45.sok. No:2/a Zeytinburnu Beyazit Istanbul 65400",
    "addr:housenumber":"45.sok no 2 / a",
    "addr:postcode":"65400",
    "addr:street":"Yenidogan Mah.;Zeytinburnu Beyazit",
    "iso:country":"TR",
    "sg:address":"Yenidogan Mah. 45.sok. No:2/a Zeytinburnu",
    "sg:city":"Beyazit",
    "sg:classifiers":[
        {
            "category":"Manufacturing",
            "subcategory":"Leather Goods",
            "type":"Manufacturing & Wholesale Goods"
        }
    ],
    "sg:phone":"+90 212 510 7255",
    "sg:postcode":"65400",
    "sg:province":"Istanbul",
    "wof:name":"Terzioglu Deri Tekstil Ve San.ltd.sti.",
    "wof:placetype":"venue"
},
  "geometry": {"coordinates":[28.906993866,40.988861084],"type":"Point"}
}