{
  "type": "Feature",
  "properties": {
    "iso:country":"TR",
    "sg:address":"E-90 Karayolu Uzeri Renoult Servisi Karsisi",
    "sg:city":"Nizip",
    "sg:classifiers":[
        {
            "category":"Food & Beverages",
            "subcategory":"Groceries & Convenience Stores",
            "type":"Retail Goods"
        }
    ],
    "sg:phone":"+90 342 513 0036",
    "sg:postcode":"27700",
    "sg:province":"Gaziantep",
    "sg:tags":[
        "olive",
        "oil"
    ],
    "wof:name":"Erdogan Fistik",
    "wof:placetype":"venue"
},
  "geometry": {"coordinates":[37.3761024475,37.0629463196],"type":"Point"}
}