{
  "type": "Feature",
  "properties": {
    "addr:full":"Ankara Asfalti Yan Yol No:23 Pendik Kagithane Istanbul 34406",
    "addr:postcode":"34406",
    "iso:country":"TR",
    "sg:address":"Ankara Asfalti Yan Yol No:23 Pendik",
    "sg:city":"Kagithane",
    "sg:classifiers":[
        {
            "category":"Home & Garden",
            "subcategory":"Hardware",
            "type":"Retail Goods"
        }
    ],
    "sg:phone":"+90 216 396 3264",
    "sg:postcode":"34406",
    "sg:province":"Istanbul",
    "sg:tags":[
        "generator",
        "power"
    ],
    "wof:name":"Barlas Makine End?st. Tic. A.s.",
    "wof:placetype":"venue"
},
  "geometry": {"coordinates":[29.3715019226,40.8925857544],"type":"Point"}
}