{
  "type": "Feature",
  "properties": {
    "iso:country":"TR",
    "sg:address":"7.cad.no:17/4",
    "sg:city":"B.evler",
    "sg:classifiers":[
        {
            "category":"Farming",
            "subcategory":"Farm & Veterinary Services",
            "type":"Manufacturing & Wholesale Goods"
        }
    ],
    "sg:phone":"+90 3122220589222",
    "sg:postcode":"03120",
    "sg:province":"Ankara",
    "sg:tags":[
        "clinic"
    ],
    "wof:name":"Osman Ic",
    "wof:placetype":"venue"
},
  "geometry": {"coordinates":[32.747002,39.95982],"type":"Point"}
}