{
  "type": "Feature",
  "properties": {
    "addr:full":"Sidali Pasaji 2.kat No: Mersin I?el 52750",
    "addr:housenumber":"no;?",
    "addr:postcode":"52750",
    "addr:street":"Mersin I;El",
    "iso:country":"TR",
    "sg:address":"Sidali Pasaji 2.kat No:",
    "sg:city":"Mersin",
    "sg:classifiers":[
        {
            "category":"Professional",
            "subcategory":"Business Services",
            "type":"Services"
        }
    ],
    "sg:phone":"+90 324 231 1322",
    "sg:postcode":"52750",
    "sg:province":"I?el",
    "sg:tags":[
        "food",
        "product",
        "exporter",
        "aricultural"
    ],
    "wof:name":"Akay Koll.sti.",
    "wof:placetype":"venue"
},
  "geometry": {"coordinates":[37.7128486633,41.0530204773],"type":"Point"}
}