{
  "type": "Feature",
  "properties": {
    "iso:country":"TR",
    "sg:address":"Tarsus Yolu Uzeri Yakakoy Civari",
    "sg:city":"Seyhan",
    "sg:classifiers":[
        {
            "category":"Farming",
            "subcategory":"Berry Farm",
            "type":"Manufacturing & Wholesale Goods"
        }
    ],
    "sg:phone":"+90 324 221 5003",
    "sg:postcode":"01000",
    "sg:province":"I?el",
    "sg:tags":[
        "citrus"
    ],
    "wof:name":"Yasemin Gida Ltd.sti.",
    "wof:placetype":"venue"
},
  "geometry": {"coordinates":[35.3823394775,36.9937705994],"type":"Point"}
}