{
  "type": "Feature",
  "properties": {
    "iso:country":"TR",
    "sg:address":"Girne Cad.diken Sok. No:4 4",
    "sg:city":"Levent",
    "sg:classifiers":[
        {
            "category":"Shopping",
            "subcategory":"Clothing, Apparel, & Fashions",
            "type":"Retail Goods"
        }
    ],
    "sg:phone":"+90 212 284 3335",
    "sg:postcode":"01310",
    "sg:province":"Istanbul",
    "sg:tags":[
        "ready",
        "wear"
    ],
    "wof:name":"Jan Tekstil San.dis Tic.ltd.sti.",
    "wof:placetype":"venue"
},
  "geometry": {"coordinates":[29.0038833618,41.0936126709],"type":"Point"}
}