{
  "type": "Feature",
  "properties": {
    "iso:country":"TR",
    "sg:address":"K.sehitleri Cad. No:37/3 D:8 Zincirlikuyu",
    "sg:city":"G?esli",
    "sg:classifiers":[
        {
            "category":"Wholesale",
            "subcategory":"Auto Parts",
            "type":"Manufacturing & Wholesale Goods"
        }
    ],
    "sg:phone":"+90 212 274 1252",
    "sg:postcode":"34540",
    "sg:province":"Istanbul",
    "sg:tags":[
        "spare"
    ],
    "wof:name":"Astas Dis Ticaret Ltd.",
    "wof:placetype":"venue"
},
  "geometry": {"coordinates":[28.9861831665,41.0408554077],"type":"Point"}
}