{
  "type": "Feature",
  "properties": {
    "addr:full":"Fizik Tedavi Rehabilitasyon Y?sek Okulu Sihhiye Mecidiyek\u00f6y Ankara",
    "addr:street":"Sihhiye",
    "iso:country":"TR",
    "sg:address":"Fizik Tedavi Rehabilitasyon Y?sek Okulu Sihhiye",
    "sg:city":"Mecidiyek\u00f6y",
    "sg:classifiers":[
        {
            "category":"Organizations",
            "subcategory":"Membership Organization",
            "type":"Services"
        }
    ],
    "sg:phone":"+90 312 324 3847",
    "sg:province":"Ankara",
    "wof:name":"Turkiye Fizyoterapistler Dernegi Hu",
    "wof:placetype":"venue"
},
  "geometry": {"coordinates":[32.8666992188,39.9333000183],"type":"Point"}
}