{
  "type": "Feature",
  "properties": {
    "iso:country":"TR",
    "sg:address":"Ahmet Vefik Pasa Mah. Degirmen Cad. No: 16",
    "sg:city":"Kestel",
    "sg:classifiers":[
        {
            "category":"Shopping",
            "subcategory":"Clothing, Apparel, & Fashions",
            "type":"Retail Goods"
        }
    ],
    "sg:phone":"+90 224 373 0779",
    "sg:postcode":"09800",
    "sg:province":"Bursa",
    "sg:tags":[
        "ready",
        "wear"
    ],
    "wof:name":"Akipek Tekstil San. Ve Tic. A.s.",
    "wof:placetype":"venue"
},
  "geometry": {"coordinates":[29.1888523102,40.2072257996],"type":"Point"}
}