{
  "type": "Feature",
  "properties": {
    "addr:full":"Feridiye Cad. No. 14 Taksim Osmangazi Istanbul 16170",
    "addr:housenumber":"14",
    "addr:postcode":"16170",
    "addr:street":"Feridiye Cad. No.",
    "iso:country":"TR",
    "sg:address":"Feridiye Cad. No. 14 Taksim",
    "sg:city":"Osmangazi",
    "sg:classifiers":[
        {
            "category":"Farming",
            "subcategory":"Fish & Marine Products",
            "type":"Manufacturing & Wholesale Goods"
        }
    ],
    "sg:phone":"+90 212 250 6000",
    "sg:postcode":"16170",
    "sg:province":"Istanbul",
    "sg:tags":[
        "automotive"
    ],
    "wof:name":"Oto Irfan",
    "wof:placetype":"venue"
},
  "geometry": {"coordinates":[28.9820804596,41.0375938416],"type":"Point"}
}