{
  "type": "Feature",
  "properties": {
    "iso:country":"TR",
    "sg:address":"Ikitelli Organize Sanayi B?gesi Metal Is Sanayi Sitesi 6.blok No:33-35",
    "sg:city":"Ikitelli/K\u00fc\u00e7\u00fck\u00e7ekmece",
    "sg:classifiers":[
        {
            "category":"Manufacturing",
            "subcategory":"Motor Vehicles & Parts",
            "type":"Manufacturing & Wholesale Goods"
        }
    ],
    "sg:phone":"+90 212 671 2551",
    "sg:postcode":"34660",
    "sg:province":"Istanbul",
    "sg:tags":[
        "machine",
        "spare"
    ],
    "sg:website":"sertsan.com",
    "wof:name":"Sertsan Sert Krom Kaplama San.ve Tic.ltd.sti",
    "wof:placetype":"venue"
},
  "geometry": {"coordinates":[28.9861831665,41.0408554077],"type":"Point"}
}