{
  "type": "Feature",
  "properties": {
    "addr:full":"Ulu Cd. No:22/1 Tuzla Bursa 01900",
    "addr:housenumber":"no 22 / 1",
    "addr:postcode":"01900",
    "addr:street":"Ulu Cd.;Bursa",
    "iso:country":"TR",
    "sg:address":"Ulu Cd. No:22/1",
    "sg:city":"Tuzla",
    "sg:classifiers":[
        {
            "category":"Wholesale",
            "subcategory":"Petroleum",
            "type":"Manufacturing & Wholesale Goods"
        }
    ],
    "sg:phone":"+90 224 254 5000",
    "sg:postcode":"01900",
    "sg:province":"Bursa",
    "wof:name":"Aman Petrol A.s.",
    "wof:placetype":"venue"
},
  "geometry": {"coordinates":[28.9796867371,40.2328529358],"type":"Point"}
}