{
  "type": "Feature",
  "properties": {
    "iso:country":"TR",
    "sg:address":"Tesvikiye Ihlamur Yolu Ihlamur Apartmani No:74 - Sisli",
    "sg:city":"Macunk?y",
    "sg:classifiers":[
        {
            "category":"Banks & Credit Unions",
            "subcategory":"Investment Brokerage",
            "type":"Services"
        }
    ],
    "sg:phone":"+90 212231114430",
    "sg:province":"Istanbul",
    "sg:tags":[
        "aid",
        "material",
        "first"
    ],
    "wof:name":"Istanbul Saglik Hizmetleri",
    "wof:placetype":"venue"
},
  "geometry": {"coordinates":[28.987903595,41.0586929321],"type":"Point"}
}