{
  "type": "Feature",
  "properties": {
    "iso:country":"TR",
    "sg:address":"Murat Mah.inan Sk.no:80",
    "sg:city":"Bayrampasa",
    "sg:classifiers":[
        {
            "category":"Manufacturing",
            "subcategory":"Tools & Machinery",
            "type":"Manufacturing & Wholesale Goods"
        }
    ],
    "sg:phone":"+90 212 417 3383",
    "sg:postcode":"36100",
    "sg:province":"Istanbul",
    "sg:tags":[
        "machine",
        "industry"
    ],
    "wof:name":"Fast Baglanti Elemanlari Ve Makina San.tic.ltd.",
    "wof:placetype":"venue"
},
  "geometry": {"coordinates":[32.8594665527,39.9355583191],"type":"Point"}
}