{
  "type": "Feature",
  "properties": {
    "addr:full":"Merkez Mah.onur Sokak No:13/15 34080 G.o.p. Istanbul Emin\u00f6n\u00fc/Ca\u011falo\u011flu Istanbul 34245",
    "addr:housenumber":"no 13 / 15",
    "addr:postcode":"34080;34245",
    "addr:street":"Mah.Onur Sokak",
    "iso:country":"TR",
    "sg:address":"Merkez Mah.onur Sokak No:13/15 34080 G.o.p. Istanbul",
    "sg:city":"Emin\u00f6n\u00fc/Ca\u011falo\u011flu",
    "sg:classifiers":[
        {
            "category":"Personal",
            "subcategory":"Shoe Repair & Shine",
            "type":"Services"
        }
    ],
    "sg:phone":"+90 212 615 2029",
    "sg:postcode":"34245",
    "sg:province":"Istanbul",
    "sg:tags":[
        "leather"
    ],
    "wof:name":"Oskar Ayakkabi Espadril Terlik",
    "wof:placetype":"venue"
},
  "geometry": {"coordinates":[29.1105232239,40.9574546814],"type":"Point"}
}