{
  "type": "Feature",
  "properties": {
    "iso:country":"TR",
    "sg:address":"Sair Nigar Sk. No:30/3 D:2",
    "sg:city":"Osmanbey",
    "sg:classifiers":[
        {
            "category":"Shopping",
            "subcategory":"Clothing, Apparel, & Fashions",
            "type":"Retail Goods"
        }
    ],
    "sg:phone":"+90 212 241 0664",
    "sg:postcode":"63000",
    "sg:province":"Istanbul",
    "sg:tags":[
        "men",
        "wear"
    ],
    "wof:name":"Nur Giyim San.",
    "wof:placetype":"venue"
},
  "geometry": {"coordinates":[28.9646854401,41.0793304443],"type":"Point"}
}