{
  "type": "Feature",
  "properties": {
    "iso:country":"TR",
    "sg:address":"Dershane Sk. No:20 Harbiye",
    "sg:city":"Ikitelli",
    "sg:classifiers":[
        {
            "category":"Farming",
            "subcategory":"Fish & Marine Products",
            "type":"Manufacturing & Wholesale Goods"
        }
    ],
    "sg:phone":"+90 212 230 5330",
    "sg:postcode":"34306",
    "sg:province":"Istanbul",
    "sg:tags":[
        "automotive"
    ],
    "wof:name":"Suzuki Otomobil Pazarlama Tic. A.s.",
    "wof:placetype":"venue"
},
  "geometry": {"coordinates":[28.9878902435,41.049659729],"type":"Point"}
}