{
  "type": "Feature",
  "properties": {
    "addr:full":"Faruk Akar Karasu Cad.no:8 Yesilyurt Izmir 01955",
    "addr:housenumber":"8",
    "addr:postcode":"01955",
    "addr:street":"Cad.No",
    "iso:country":"TR",
    "sg:address":"Faruk Akar Karasu Cad.no:8",
    "sg:city":"Yesilyurt",
    "sg:classifiers":[
        {
            "category":"Farming",
            "subcategory":"Poultry Farm",
            "type":"Manufacturing & Wholesale Goods"
        }
    ],
    "sg:phone":"+90 232 243 8737",
    "sg:postcode":"01955",
    "sg:province":"Izmir",
    "sg:tags":[
        "poultry-turkey-ostrich"
    ],
    "wof:name":"Guventav Tavukculuk Ekipmanlari",
    "wof:placetype":"venue"
},
  "geometry": {"coordinates":[27.106464386,38.3964500427],"type":"Point"}
}