{
  "type": "Feature",
  "properties": {
    "iso:country":"TR",
    "sg:address":"Meydan Yeri No: 42",
    "sg:city":"Yildirim",
    "sg:classifiers":[
        {
            "category":"Farming",
            "subcategory":"Poultry Farm",
            "type":"Manufacturing & Wholesale Goods"
        }
    ],
    "sg:phone":"+90 354 217 5397",
    "sg:postcode":"03300",
    "sg:province":"Yozgat",
    "sg:tags":[
        "poultry-turkey-ostrich"
    ],
    "wof:name":"Ciftlik Tavukculuk Gida San.tic.ltd.sti.",
    "wof:placetype":"venue"
},
  "geometry": {"coordinates":[34.8055000305,39.8212013245],"type":"Point"}
}