{
  "type": "Feature",
  "properties": {
    "addr:full":"Modern Crs. No:308 Ulus Nazilli Ankara 65600",
    "addr:postcode":"65600",
    "addr:street":"Ulus;Ankara",
    "iso:country":"TR",
    "sg:address":"Modern Crs. No:308 Ulus",
    "sg:city":"Nazilli",
    "sg:classifiers":[
        {
            "category":"Wholesale",
            "subcategory":"Medical Equipment & Supplies",
            "type":"Manufacturing & Wholesale Goods"
        }
    ],
    "sg:phone":"+90 312 310 6086",
    "sg:postcode":"65600",
    "sg:province":"Ankara",
    "wof:name":"Onur Tibbi Mlz. Ltd.",
    "wof:placetype":"venue"
},
  "geometry": {"coordinates":[32.8604812622,39.9429283142],"type":"Point"}
}