{
  "type": "Feature",
  "properties": {
    "addr:full":"Cumhuriyet Bulvari No:278 D:1 Alsancak Iskenderun Izmir 31200",
    "addr:housenumber":"no 278 d 1",
    "addr:postcode":"31200",
    "addr:street":"Cumhuriyet Bulvari",
    "iso:country":"TR",
    "sg:address":"Cumhuriyet Bulvari No:278 D:1 Alsancak",
    "sg:city":"Iskenderun",
    "sg:classifiers":[
        {
            "category":"Mining & Drilling",
            "type":"Manufacturing & Wholesale Goods"
        }
    ],
    "sg:phone":"+90 232 465 2384",
    "sg:postcode":"31200",
    "sg:province":"Izmir",
    "sg:tags":[
        "industry",
        "mine"
    ],
    "wof:name":"Ertan Madencilik",
    "wof:placetype":"venue"
},
  "geometry": {"coordinates":[27.1427402496,38.4396286011],"type":"Point"}
}