{
  "type": "Feature",
  "properties": {
    "iso:country":"TR",
    "sg:address":"I.m.?. 1.blok No:1226-1227-1133",
    "sg:city":"Unkapani",
    "sg:classifiers":[
        {
            "category":"Home & Garden",
            "subcategory":"Home Furnishings",
            "type":"Retail Goods"
        }
    ],
    "sg:phone":"+90 21252074125",
    "sg:postcode":"34470",
    "sg:province":"Istanbul",
    "sg:tags":[
        "-curtains",
        "upholstery"
    ],
    "wof:name":"Prestige Tekstil Pazarlama Tic. Ltd. Sti.",
    "wof:placetype":"venue"
},
  "geometry": {"coordinates":[28.7931404114,41.0928535461],"type":"Point"}
}