{
  "type": "Feature",
  "properties": {
    "iso:country":"TR",
    "sg:address":"Ordu Caddesi 206/1",
    "sg:city":"Laleli",
    "sg:classifiers":[
        {
            "category":"Banks & Credit Unions",
            "subcategory":"Investment Brokerage",
            "type":"Services"
        }
    ],
    "sg:phone":"+90 212 512 4231",
    "sg:postcode":"24300",
    "sg:province":"Istanbul",
    "sg:tags":[
        "line",
        "air"
    ],
    "wof:name":"Adria (slavonian) Airways",
    "wof:placetype":"venue"
},
  "geometry": {"coordinates":[28.9538021088,41.0096511841],"type":"Point"}
}