{
  "type": "Feature",
  "properties": {
    "addr:full":"Prof. Cemil B. Cd. No:5/3 Emin?? Istanbul Ikitelli/K\u00fc\u00e7\u00fck\u00e7ekmece Istanbul 34670",
    "addr:housenumber":"no 5 / 3;? ?",
    "addr:postcode":"34670",
    "addr:street":"Prof. Cemil B. Cd.;Emin",
    "iso:country":"TR",
    "sg:address":"Prof. Cemil B. Cd. No:5/3 Emin?? Istanbul",
    "sg:city":"Ikitelli/K\u00fc\u00e7\u00fck\u00e7ekmece",
    "sg:classifiers":[
        {
            "category":"Manufacturing",
            "subcategory":"Rubber & Plastics",
            "type":"Manufacturing & Wholesale Goods"
        }
    ],
    "sg:phone":"+90 212 526 7661",
    "sg:postcode":"34670",
    "sg:province":"Istanbul",
    "sg:tags":[
        "industry"
    ],
    "wof:name":"Firat Plastik Kau?uk San. Tic. A.s.",
    "wof:placetype":"venue"
},
  "geometry": {"coordinates":[28.9690895081,41.0065994263],"type":"Point"}
}