{
  "type": "Feature",
  "properties": {
    "iso:country":"TR",
    "sg:address":"Istiklal Cad. Asmali Mescit Sok. 101/46",
    "sg:city":"Kalamis",
    "sg:classifiers":[
        {
            "category":"Building & Trades",
            "subcategory":"Pest Control",
            "type":"Services"
        }
    ],
    "sg:phone":"+90 212 251 6117",
    "sg:province":"Istanbul",
    "sg:tags":[
        "quality"
    ],
    "wof:name":"Rosstandart",
    "wof:placetype":"venue"
},
  "geometry": {"coordinates":[29.2613811493,40.9810714722],"type":"Point"}
}