{
  "type": "Feature",
  "properties": {
    "addr:full":"Ali Nihat Tarlan Cad. Kartal Sok. No:13 Bostanci Osmangazi Istanbul 16370",
    "addr:housenumber":"no 13",
    "addr:postcode":"16370",
    "addr:street":"Tarlan Cad. Kartal Sok.;Bostanci Osmangazi",
    "iso:country":"TR",
    "sg:address":"Ali Nihat Tarlan Cad. Kartal Sok. No:13 Bostanci",
    "sg:city":"Osmangazi",
    "sg:classifiers":[
        {
            "category":"Farming",
            "subcategory":"Fish & Marine Products",
            "type":"Manufacturing & Wholesale Goods"
        }
    ],
    "sg:phone":"+90 216 362 3500",
    "sg:postcode":"16370",
    "sg:province":"Istanbul",
    "sg:tags":[
        "automotive"
    ],
    "wof:name":"Iveco Otoyol Pazarlama A.s",
    "wof:placetype":"venue"
},
  "geometry": {"coordinates":[29.104675293,40.9663963318],"type":"Point"}
}