{
  "type": "Feature",
  "properties": {
    "addr:full":"Ceyhan Karayolu 21.km. Suluca Beld Adana",
    "addr:street":"Karayolu;Suluca",
    "iso:country":"TR",
    "sg:address":"Ceyhan Karayolu 21.km.",
    "sg:city":"Suluca Beld",
    "sg:classifiers":[
        {
            "category":"Shopping",
            "subcategory":"Crafts & Fabrics",
            "type":"Retail Goods"
        }
    ],
    "sg:phone":"+90 322 394 3371",
    "sg:province":"Adana",
    "sg:tags":[
        "embroidery"
    ],
    "wof:name":"Sell South East Linens Teks San.ve Tic.ltd.sti",
    "wof:placetype":"venue"
},
  "geometry": {"coordinates":[35.3250198364,36.9854202271],"type":"Point"}
}