{
  "type": "Feature",
  "properties": {
    "iso:country":"TR",
    "sg:address":"Abdullah Azam Cad. No:22 A.dudulu-",
    "sg:city":"\u00dcmraniye",
    "sg:classifiers":[
        {
            "category":"Food & Beverages",
            "subcategory":"Supermarket",
            "type":"Retail Goods"
        }
    ],
    "sg:phone":"+90 216499336670",
    "sg:postcode":"03650",
    "sg:province":"Istanbul",
    "sg:tags":[
        "frozen"
    ],
    "wof:name":"Onur Gida Imalat Ve Pazarlama Ltd.sti.",
    "wof:placetype":"venue"
},
  "geometry": {"coordinates":[29.1583385468,41.0298309326],"type":"Point"}
}