{
  "type": "Feature",
  "properties": {
    "addr:full":"Mahatma Gandhi Cad.no:103 G.o.pasa Yenibosna - Bah?elievler Ankara",
    "addr:housenumber":"103;?",
    "addr:street":"Mahatma;G.O.Pasa Yenibosna Bah",
    "iso:country":"TR",
    "sg:address":"Mahatma Gandhi Cad.no:103 G.o.pasa",
    "sg:city":"Yenibosna - Bah?elievler",
    "sg:classifiers":[
        {
            "category":"Banks & Credit Unions",
            "subcategory":"Investment Brokerage",
            "type":"Services"
        }
    ],
    "sg:phone":"+90 31244727405",
    "sg:province":"Ankara",
    "sg:tags":[
        "exporter"
    ],
    "wof:name":"Orta Anadolu Ihracat?i Birlikleri Genel Sekreterligi",
    "wof:placetype":"venue"
},
  "geometry": {"coordinates":[32.872196,39.889713],"type":"Point"}
}