{
  "type": "Feature",
  "properties": {
    "addr:full":"Sevketpasa Cd. Hafik Sk. No:6 Okmeydani 26110 Istanbul",
    "addr:postcode":"26110",
    "addr:street":"Sevketpasa Cd. Hafik Sk. No 6 Okmeydani",
    "iso:country":"TR",
    "sg:address":"Sevketpasa Cd. Hafik Sk. No:6 Okmeydani",
    "sg:city":"26110",
    "sg:classifiers":[
        {
            "category":"Building & Trades",
            "subcategory":"Construction",
            "type":"Services"
        }
    ],
    "sg:phone":"+90 212 256 4239",
    "sg:province":"Istanbul",
    "sg:tags":[
        "industry",
        "mold"
    ],
    "wof:name":"Oba Kalip M.",
    "wof:placetype":"venue"
},
  "geometry": {"coordinates":[28.9735145569,41.033618927],"type":"Point"}
}