{
  "type": "Feature",
  "properties": {
    "addr:full":"Rami Kisla Cd. Pasmakci San. Sit. No:125/127 Topcular Ikitelli/K\u00fc\u00e7\u00fck\u00e7ekmece Istanbul 34670",
    "addr:housenumber":"no;/ 127",
    "addr:postcode":"34670",
    "addr:street":"Kisla Cd. Pasmakci San. Sit.;Topcular Ikitelli / Kuec\u0327Uekc\u0327Ekmece",
    "iso:country":"TR",
    "sg:address":"Rami Kisla Cd. Pasmakci San. Sit. No:125/127 Topcular",
    "sg:city":"Ikitelli/K\u00fc\u00e7\u00fck\u00e7ekmece",
    "sg:classifiers":[
        {
            "category":"Building & Trades",
            "subcategory":"Construction",
            "type":"Services"
        }
    ],
    "sg:phone":"+90 212 613 0646",
    "sg:postcode":"34670",
    "sg:province":"Istanbul",
    "sg:tags":[
        "industry",
        "mold"
    ],
    "wof:name":"Erturk Kalip Sanayi",
    "wof:placetype":"venue"
},
  "geometry": {"coordinates":[28.9759254456,41.0123786926],"type":"Point"}
}