{
  "type": "Feature",
  "properties": {
    "iso:country":"TR",
    "sg:address":"Gencosman Mah. Cincin Deresi Cad. No:111 Gungoren",
    "sg:city":"Mersin",
    "sg:classifiers":[
        {
            "category":"Manufacturing",
            "subcategory":"Tools & Machinery",
            "type":"Manufacturing & Wholesale Goods"
        }
    ],
    "sg:phone":"+90 212 569 9388",
    "sg:postcode":"52750",
    "sg:province":"Istanbul",
    "sg:tags":[
        "machine",
        "industry"
    ],
    "wof:name":"Censel Buharli Utu Makinalari San. Tic.ltd.sti.",
    "wof:placetype":"venue"
},
  "geometry": {"coordinates":[28.8843479156,41.0346641541],"type":"Point"}
}