{
  "type": "Feature",
  "properties": {
    "addr:full":"Yenidogan Mh. Ersan Sk. No:4 Bayrampasa 35400 Istanbul",
    "addr:housenumber":"sk.",
    "addr:postcode":"35400",
    "addr:street":"Yenidogan Mh. Ersan;No 4 Bayrampasa",
    "iso:country":"TR",
    "sg:address":"Yenidogan Mh. Ersan Sk. No:4 Bayrampasa",
    "sg:city":"35400",
    "sg:classifiers":[
        {
            "category":"Wholesale",
            "subcategory":"Home Furnishings",
            "type":"Manufacturing & Wholesale Goods"
        }
    ],
    "sg:phone":"+90 212 501 3080",
    "sg:province":"Istanbul",
    "sg:tags":[
        "furniture"
    ],
    "wof:name":"Gamze Aktas",
    "wof:placetype":"venue"
},
  "geometry": {"coordinates":[28.912109375,41.0438117981],"type":"Point"}
}