{
  "type": "Feature",
  "properties": {
    "addr:full":"Sehit Muhtar Cd. No:4-5 Taksim Nazilli Istanbul 65600",
    "addr:housenumber":"no",
    "addr:postcode":"65600",
    "addr:street":"Sehit Muhtar Cd.",
    "iso:country":"TR",
    "sg:address":"Sehit Muhtar Cd. No:4-5 Taksim",
    "sg:city":"Nazilli",
    "sg:classifiers":[
        {
            "category":"Home & Garden",
            "subcategory":"Household Appliances",
            "type":"Retail Goods"
        }
    ],
    "sg:phone":"+90 212 293 1019",
    "sg:postcode":"65600",
    "sg:province":"Istanbul",
    "sg:tags":[
        "utensil",
        "electrical"
    ],
    "wof:name":"Electrolux Day. T?k. San.",
    "wof:placetype":"venue"
},
  "geometry": {"coordinates":[28.9861831665,41.0408554077],"type":"Point"}
}