{
  "type": "Feature",
  "properties": {
    "addr:full":"Sinanpasa Mescidi Sk. No.12 Besiktas Istanbul 80700",
    "addr:postcode":"80700",
    "addr:street":"Sk. No.12",
    "iso:country":"TR",
    "sg:address":"Sinanpasa Mescidi Sk. No.12",
    "sg:city":"Besiktas",
    "sg:classifiers":[
        {
            "category":"Home & Garden",
            "subcategory":"Building Materials",
            "type":"Retail Goods"
        }
    ],
    "sg:phone":"+90 212 258 5520",
    "sg:postcode":"80700",
    "sg:province":"Istanbul",
    "sg:tags":[
        "stone",
        "natural",
        "marble"
    ],
    "wof:name":"Gramer Granit Mermer Tic. Ve San.ltd.sti.",
    "wof:placetype":"venue"
},
  "geometry": {"coordinates":[29.0123462677,41.0444602966],"type":"Point"}
}