{
  "type": "Feature",
  "properties": {
    "addr:full":"S?eyman Top? Yumurtalik Antalya 01680",
    "addr:housenumber":"?",
    "addr:postcode":"01680",
    "addr:street":"S;Yumurtalik",
    "iso:country":"TR",
    "sg:address":"S?eyman Top?",
    "sg:city":"Yumurtalik",
    "sg:classifiers":[
        {
            "category":"Government",
            "subcategory":"Office",
            "type":"Public Place"
        }
    ],
    "sg:phone":"+90 242 871 5051",
    "sg:postcode":"01680",
    "sg:province":"Antalya",
    "sg:tags":[
        "municipality"
    ],
    "wof:name":"Kale Belediye Baskani",
    "wof:placetype":"venue"
},
  "geometry": {"coordinates":[30.7031345367,36.8875045776],"type":"Point"}
}