{
  "type": "Feature",
  "properties": {
    "addr:full":"?amyolu Mevk?kestel Kemer Antalya 07980",
    "addr:housenumber":"?;?",
    "addr:postcode":"07980",
    "addr:street":"Amyolu Mevk",
    "iso:country":"TR",
    "sg:address":"?amyolu Mevk?kestel",
    "sg:city":"Kemer",
    "sg:orig_category":"Hotels: Motels",
    "sg:phone":"+90 2425181240415",
    "sg:postcode":"07980",
    "sg:province":"Antalya",
    "wof:name":"Sunshine (alanya/antalya)",
    "wof:placetype":"venue"
},
  "geometry": {"coordinates":[30.7092056274,36.8790512085],"type":"Point"}
}