{
  "type": "Feature",
  "properties": {
    "iso:country":"TR",
    "sg:address":"G?han Ishani K:2 No:16",
    "sg:city":"Osmangazi",
    "sg:classifiers":[
        {
            "category":"Banks & Credit Unions",
            "subcategory":"Investment Brokerage",
            "type":"Services"
        }
    ],
    "sg:phone":"+90 324 232 2478",
    "sg:postcode":"16240",
    "sg:province":"I?el",
    "sg:tags":[
        "-",
        "export",
        "import"
    ],
    "wof:name":"Murat Dis Tic. Ltd. Sti.",
    "wof:placetype":"venue"
},
  "geometry": {"coordinates":[29.0749702454,40.1961784363],"type":"Point"}
}