{
  "type": "Feature",
  "properties": {
    "addr:full":"Halaskargazi Cad. Bag-kur Is Merkezi B-5 Osmanbey Istanbul 63000",
    "addr:housenumber":"b-5",
    "addr:postcode":"63000",
    "addr:street":"Halaskargazi Cad. Bag-Kur;Osmanbey Istanbul",
    "iso:country":"TR",
    "sg:address":"Halaskargazi Cad. Bag-kur Is Merkezi B-5",
    "sg:city":"Osmanbey",
    "sg:classifiers":[
        {
            "category":"Shopping",
            "subcategory":"Crafts & Fabrics",
            "type":"Retail Goods"
        }
    ],
    "sg:phone":"+90 212 219 2640",
    "sg:postcode":"63000",
    "sg:province":"Istanbul",
    "sg:tags":[
        "weaving"
    ],
    "wof:name":"Altinyun Tekstil Sanayi Tic.ltd.sti.",
    "wof:placetype":"venue"
},
  "geometry": {"coordinates":[28.9759254456,41.0123786926],"type":"Point"}
}