{
  "type": "Feature",
  "properties": {
    "iso:country":"TR",
    "sg:address":"Gazi Bulvari No:66/401",
    "sg:city":"Cankaya",
    "sg:classifiers":[
        {
            "category":"Airport",
            "subcategory":"International",
            "type":"Transportation"
        }
    ],
    "sg:phone":"+90 232 441 7075",
    "sg:postcode":"07080",
    "sg:province":"Izmir",
    "wof:name":"Ba-ka Transport",
    "wof:placetype":"venue"
},
  "geometry": {"coordinates":[27.1423015594,38.4251480103],"type":"Point"}
}