{
  "type": "Feature",
  "properties": {
    "addr:full":"Sebze Bah?leri 2 Iskitler \u00dcmraniye Ankara 81260",
    "addr:housenumber":"2",
    "addr:postcode":"81260",
    "addr:street":"Leri",
    "iso:country":"TR",
    "sg:address":"Sebze Bah?leri 2 Iskitler",
    "sg:city":"\u00dcmraniye",
    "sg:classifiers":[
        {
            "category":"Farming",
            "subcategory":"Fish & Marine Products",
            "type":"Manufacturing & Wholesale Goods"
        }
    ],
    "sg:phone":"+90 312 341 4900",
    "sg:postcode":"81260",
    "sg:province":"Ankara",
    "sg:tags":[
        "automotive"
    ],
    "wof:name":"Merkezman Otomotiv Tic. Ltd. Sti.",
    "wof:placetype":"venue"
},
  "geometry": {"coordinates":[32.8560333252,39.9438743591],"type":"Point"}
}