{
  "type": "Feature",
  "properties": {
    "iso:country":"TR",
    "sg:address":"Gazi Mah. Milli Egemenlik Bulvari No:47",
    "sg:city":"G.o.pasa",
    "sg:classifiers":[
        {
            "category":"Airport",
            "subcategory":"International",
            "type":"Transportation"
        }
    ],
    "sg:phone":"+90 342312010102",
    "sg:province":"Gaziantep",
    "wof:name":"Askar Petroleum International Transportation Company",
    "wof:placetype":"venue"
},
  "geometry": {"coordinates":[37.4416732788,36.9459457397],"type":"Point"}
}