{
  "type": "Feature",
  "properties": {
    "addr:full":"Haciey?l?k??no:18 20100 Denizli",
    "addr:postcode":"20100",
    "iso:country":"TR",
    "sg:address":"Haciey?l?k??no:18",
    "sg:city":"20100",
    "sg:classifiers":[
        {
            "category":"Shopping",
            "subcategory":"Clothing, Apparel, & Fashions",
            "type":"Retail Goods"
        }
    ],
    "sg:phone":"+90 258 372 0050",
    "sg:province":"Denizli",
    "sg:tags":[
        "-",
        "towel",
        "bathrobe"
    ],
    "wof:name":"Aksay Tekstil San.tic.ltd.sti",
    "wof:placetype":"venue"
},
  "geometry": {"coordinates":[29.0788803101,37.7851867676],"type":"Point"}
}