{
  "type": "Feature",
  "properties": {
    "addr:full":"Bursa Yolu 13.km. G.o.pasa Eskisehir",
    "addr:housenumber":"13.km",
    "addr:street":"Bursa Yolu",
    "iso:country":"TR",
    "sg:address":"Bursa Yolu 13.km.",
    "sg:city":"G.o.pasa",
    "sg:classifiers":[
        {
            "category":"Wholesale",
            "subcategory":"Home Furnishings",
            "type":"Manufacturing & Wholesale Goods"
        }
    ],
    "sg:phone":"+90 222 411 2206",
    "sg:province":"Eskisehir",
    "sg:tags":[
        "furniture"
    ],
    "wof:name":"Ader Mobilya San. Ve Tic. Ltd.sti.",
    "wof:placetype":"venue"
},
  "geometry": {"coordinates":[31.0192203522,39.6195106506],"type":"Point"}
}