{
  "type": "Feature",
  "properties": {
    "iso:country":"TR",
    "sg:address":"Nosab Mine Cd.33 Sk.n:265",
    "sg:city":"Nil?fer",
    "sg:classifiers":[
        {
            "category":"Wholesale",
            "subcategory":"Auto Parts",
            "type":"Manufacturing & Wholesale Goods"
        }
    ],
    "sg:phone":"+90 2242428620729",
    "sg:province":"Bursa",
    "sg:tags":[
        "spare"
    ],
    "wof:name":"Balap Tekstil Otomotiv As.",
    "wof:placetype":"venue"
},
  "geometry": {"coordinates":[29.0586109161,40.1844291687],"type":"Point"}
}