{
  "type": "Feature",
  "properties": {
    "addr:full":"Keresteciler Sitesi Fatih Caddesi Zafer Sk. No:7 Merter Istanbul",
    "addr:street":"Fatih Caddesi;Sk. No 7 Merter",
    "iso:country":"TR",
    "sg:address":"Keresteciler Sitesi Fatih Caddesi Zafer Sk. No:7",
    "sg:city":"Merter",
    "sg:classifiers":[
        {
            "category":"Sports & Exercise",
            "subcategory":"Ski Slope",
            "type":"Entertainment"
        }
    ],
    "sg:phone":"+90 212 505 3093",
    "sg:province":"Istanbul",
    "sg:tags":[
        "wear"
    ],
    "wof:name":"Leo Teks. San. Tic.",
    "wof:placetype":"venue"
},
  "geometry": {"coordinates":[28.975925,41.012379],"type":"Point"}
}