{
  "type": "Feature",
  "properties": {
    "iso:country":"TR",
    "sg:address":"Ali Ak?n",
    "sg:city":"Haymana",
    "sg:classifiers":[
        {
            "category":"Government",
            "subcategory":"Office",
            "type":"Public Place"
        }
    ],
    "sg:phone":"+90 242 428 6606",
    "sg:postcode":"43274",
    "sg:province":"Antalya",
    "sg:tags":[
        "municipality"
    ],
    "wof:name":"Yurtpinar Belediye Baskani",
    "wof:placetype":"venue"
},
  "geometry": {"coordinates":[32.8381690979,39.9448890686],"type":"Point"}
}