{
  "type": "Feature",
  "properties": {
    "iso:country":"TR",
    "sg:address":"Kaledere Mahallesi Niksar Caddesi No16",
    "sg:city":"Unye",
    "sg:classifiers":[
        {
            "category":"Manufacturing",
            "subcategory":"Lumber",
            "type":"Manufacturing & Wholesale Goods"
        }
    ],
    "sg:phone":"+90 452 323 1082",
    "sg:postcode":"52300",
    "sg:province":"Ordu",
    "sg:tags":[
        "timber"
    ],
    "wof:name":"Aslan Parke Ve Kereste Fabrikasi",
    "wof:placetype":"venue"
},
  "geometry": {"coordinates":[37.8740005493,40.9880981445],"type":"Point"}
}