{
  "type": "Feature",
  "properties": {
    "iso:country":"TR",
    "sg:address":"Istasyon Cad.no:12/13 Ak Is Merkezi",
    "sg:city":"Sisli",
    "sg:classifiers":[
        {
            "category":"Professional",
            "subcategory":"Employment Agencies",
            "type":"Services"
        }
    ],
    "sg:phone":"+90 352 221 1825",
    "sg:postcode":"34387",
    "sg:province":"Kayseri",
    "sg:tags":[
        "machine"
    ],
    "wof:name":"Abs Ltd.sti.",
    "wof:placetype":"venue"
},
  "geometry": {"coordinates":[35.4891357422,38.7225761414],"type":"Point"}
}