{
  "type": "Feature",
  "properties": {
    "iso:country":"TR",
    "sg:address":"Sultanhamam Asirefendi Cad. Hobyar Han Kat.4 No:402-403",
    "sg:city":"Sirkeci-eminonu",
    "sg:classifiers":[
        {
            "category":"Banks & Credit Unions",
            "subcategory":"Financial Services",
            "type":"Services"
        }
    ],
    "sg:phone":"+90 212 527 1104",
    "sg:province":"Istanbul",
    "sg:tags":[
        "consultant"
    ],
    "wof:name":"S.m. Mali Musavir",
    "wof:placetype":"venue"
},
  "geometry": {"coordinates":[28.9759254456,41.0123786926],"type":"Point"}
}