{
  "type": "Feature",
  "properties": {
    "addr:full":"Fidan Sk.no.19/2 Merter Istanbul",
    "iso:country":"TR",
    "sg:address":"Fidan Sk.no.19/2",
    "sg:city":"Merter",
    "sg:classifiers":[
        {
            "category":"Shopping",
            "subcategory":"Clothing, Apparel, & Fashions",
            "type":"Retail Goods"
        }
    ],
    "sg:phone":"+90 212 642 0944",
    "sg:province":"Istanbul",
    "sg:tags":[
        "ready",
        "wear"
    ],
    "wof:name":"Perfection Tekstil Ltd.sti.",
    "wof:placetype":"venue"
},
  "geometry": {"coordinates":[29.1267700195,40.9706230164],"type":"Point"}
}