{
  "type": "Feature",
  "properties": {
    "iso:country":"TR",
    "sg:address":"G?tepe Mah. Reyhan Cad. Sahinler Apt. No: 5 D:8 Sefakoy",
    "sg:city":"Melikgazi",
    "sg:classifiers":[
        {
            "category":"Manufacturing",
            "subcategory":"Metals",
            "type":"Manufacturing & Wholesale Goods"
        }
    ],
    "sg:phone":"+90 212 592 1494",
    "sg:postcode":"38070",
    "sg:province":"Istanbul",
    "sg:tags":[
        "aluminium",
        "industry"
    ],
    "wof:name":"Ortadogu Elektronik San. Ve Dis. Tic. A.s.",
    "wof:placetype":"venue"
},
  "geometry": {"coordinates":[28.8061275482,41.0005226135],"type":"Point"}
}