{
  "type": "Feature",
  "properties": {
    "iso:country":"TR",
    "sg:address":"46.sk. No.95-c Zeytinburnu",
    "sg:city":"\u00c7orlu",
    "sg:classifiers":[
        {
            "category":"Shopping",
            "subcategory":"Luggage & Leather Goods",
            "type":"Retail Goods"
        }
    ],
    "sg:phone":"+90 212 510 4350",
    "sg:province":"Istanbul",
    "sg:tags":[
        "leather-fur",
        "wear"
    ],
    "wof:name":"Narin Deri Konf. Ltd.sti.",
    "wof:placetype":"venue"
},
  "geometry": {"coordinates":[28.9063777924,40.9896774292],"type":"Point"}
}