{
  "type": "Feature",
  "properties": {
    "iso:country":"TR",
    "sg:address":"Hayboyu 9/9 G?ztepe",
    "sg:city":"Kad\u0131k\u00f6y",
    "sg:classifiers":[
        {
            "category":"Transit Center",
            "subcategory":"Freight",
            "type":"Transportation"
        }
    ],
    "sg:phone":"+90 216 457 5821",
    "sg:postcode":"34730",
    "sg:province":"Istanbul",
    "wof:name":"Elit Logistics Services Transport & Foreign Trade",
    "wof:placetype":"venue"
},
  "geometry": {"coordinates":[29.0627193451,40.9783554077],"type":"Point"}
}