{
  "type": "Feature",
  "properties": {
    "iso:country":"TR",
    "sg:address":"Emeksiz Cad. Devami Ismetiye Mah. Emeksiz Apt. Alti No:18",
    "sg:city":"Ey\u00fcp",
    "sg:classifiers":[
        {
            "category":"Shopping",
            "subcategory":"Computers & Home Electronics",
            "type":"Retail Goods"
        }
    ],
    "sg:phone":"+90 422 324 3771",
    "sg:province":"Malatya",
    "sg:tags":[
        "animal"
    ],
    "wof:name":"Emeksiz Orman Ciftligi",
    "wof:placetype":"venue"
},
  "geometry": {"coordinates":[38.3195266724,38.3488922119],"type":"Point"}
}