{
  "type": "Feature",
  "properties": {
    "iso:country":"TR",
    "sg:address":"Ataturk Cad. Ravza Apt. No:121",
    "sg:city":"Seyhan",
    "sg:classifiers":[
        {
            "category":"Home & Garden",
            "subcategory":"Building Materials",
            "type":"Retail Goods"
        }
    ],
    "sg:phone":"+90 272 213 0102",
    "sg:postcode":"01000",
    "sg:province":"Afyon",
    "sg:tags":[
        "window",
        "door"
    ],
    "wof:name":"Dekorpen Yapi Ve Malzemeleri Tic.ltd.sti.",
    "wof:placetype":"venue"
},
  "geometry": {"coordinates":[30.5382652283,38.7579841614],"type":"Point"}
}