{
  "type": "Feature",
  "properties": {
    "iso:country":"TR",
    "sg:address":"Gunes Cad. No:3/1 Terazidere Mah. Sinan Sokak 34150 Bayrampasa Istanbul",
    "sg:city":"Sariyer",
    "sg:orig_category":"Miscellaneous Products",
    "sg:phone":"+90 212 576 5639",
    "sg:postcode":"33740",
    "sg:province":"Istanbul",
    "wof:name":"Serif Dis Tic Ve Teks Ltd Sti",
    "wof:placetype":"venue"
},
  "geometry": {"coordinates":[28.8993721008,41.0300827026],"type":"Point"}
}