{
  "type": "Feature",
  "properties": {
    "addr:full":"Necatibey Cad.no:58/22 Kizilay Ankara 23050",
    "addr:housenumber":"58 / 22",
    "addr:postcode":"23050",
    "iso:country":"TR",
    "sg:address":"Necatibey Cad.no:58/22",
    "sg:city":"Kizilay",
    "sg:classifiers":[
        {
            "category":"Airport",
            "subcategory":"International",
            "type":"Transportation"
        }
    ],
    "sg:phone":"+90 312 230 1285",
    "sg:postcode":"23050",
    "sg:province":"Ankara",
    "wof:name":"Efe Lojistik Ve Uluslararsi Nakliyat Ltd.sti.",
    "wof:placetype":"venue"
},
  "geometry": {"coordinates":[32.8604812622,39.9429283142],"type":"Point"}
}