{
  "type": "Feature",
  "properties": {
    "addr:full":"M.kemalpasa Cad. No:24 Yuvam Pansion Uzeri Besiktas Amasya 80630",
    "addr:housenumber":"24",
    "addr:postcode":"80630",
    "addr:street":"M.Kemalpasa Cad. No",
    "iso:country":"TR",
    "sg:address":"M.kemalpasa Cad. No:24 Yuvam Pansion Uzeri",
    "sg:city":"Besiktas",
    "sg:classifiers":[
        {
            "category":"Organizations",
            "subcategory":"Membership Organization",
            "type":"Services"
        }
    ],
    "sg:phone":"+90 358 218 1342",
    "sg:postcode":"80630",
    "sg:province":"Amasya",
    "wof:name":"Amasya Turk Japon Dostluk Dernegi",
    "wof:placetype":"venue"
},
  "geometry": {"coordinates":[35.8135032654,40.6473884583],"type":"Point"}
}