{
  "type": "Feature",
  "properties": {
    "addr:full":"Atat?k Cad. M.s?er Apt. Asma Kat. Daire 2 Maltepe Adana 01000",
    "addr:housenumber":"m.s ?;2",
    "addr:postcode":"01000",
    "addr:street":"K Cad.;Er Apt. Asma;Daire;Adana",
    "iso:country":"TR",
    "sg:address":"Atat?k Cad. M.s?er Apt. Asma Kat. Daire 2",
    "sg:city":"Maltepe",
    "sg:classifiers":[
        {
            "category":"Professional",
            "subcategory":"Employment Agencies",
            "type":"Services"
        }
    ],
    "sg:phone":"+90 322 459 2532",
    "sg:postcode":"01000",
    "sg:province":"Adana",
    "sg:tags":[
        "machine"
    ],
    "wof:name":"B?ro Market",
    "wof:placetype":"venue"
},
  "geometry": {"coordinates":[35.3137359619,37.0007171631],"type":"Point"}
}