{
  "type": "Feature",
  "properties": {
    "addr:full":"Imes Yonetim Merkezi Binasi E Blok 504 / 2 Umraniye Ikitelli/K\u00fc\u00e7\u00fck\u00e7ekmece Istanbul 34660",
    "addr:housenumber":"blok 504 / 2",
    "addr:postcode":"34660",
    "addr:street":"Binasi",
    "iso:country":"TR",
    "sg:address":"Imes Yonetim Merkezi Binasi E Blok 504 / 2 Umraniye",
    "sg:city":"Ikitelli/K\u00fc\u00e7\u00fck\u00e7ekmece",
    "sg:classifiers":[
        {
            "category":"Manufacturing",
            "subcategory":"Tools & Machinery",
            "type":"Manufacturing & Wholesale Goods"
        }
    ],
    "sg:phone":"+90 2163643347329",
    "sg:postcode":"34660",
    "sg:province":"Istanbul",
    "sg:tags":[
        "machine",
        "industry"
    ],
    "wof:name":"Imes Sanayi Sitesi Yapi Kooperatifi",
    "wof:placetype":"venue"
},
  "geometry": {"coordinates":[29.0496292114,41.0075798035],"type":"Point"}
}