{
  "type": "Feature",
  "properties": {
    "iso:country":"TR",
    "sg:address":"Demirciler Sit. 2. Cd. No:32 Zeytinburnu",
    "sg:city":"Bagcilar",
    "sg:classifiers":[
        {
            "category":"Manufacturing",
            "subcategory":"Tools & Machinery",
            "type":"Manufacturing & Wholesale Goods"
        }
    ],
    "sg:phone":"+90 212 558 1966",
    "sg:postcode":"34540",
    "sg:province":"Istanbul",
    "sg:tags":[
        "machine",
        "industry"
    ],
    "wof:name":"K?seoglu Paslanmaz Makina San.",
    "wof:placetype":"venue"
},
  "geometry": {"coordinates":[28.9759254456,41.0123786926],"type":"Point"}
}