{
  "type": "Feature",
  "properties": {
    "iso:country":"TR",
    "sg:address":"Besocak Mah.9.sok.",
    "sg:city":"Seyhan",
    "sg:classifiers":[
        {
            "category":"Airport",
            "subcategory":"International",
            "type":"Transportation"
        }
    ],
    "sg:phone":"+90 322 351 8195",
    "sg:postcode":"01000",
    "sg:province":"Adana",
    "wof:name":"Bursa Konya Tasimacilik",
    "wof:placetype":"venue"
},
  "geometry": {"coordinates":[35.3250198364,36.9854202271],"type":"Point"}
}