{
  "type": "Feature",
  "properties": {
    "addr:full":"Necatibey Cd. No:46/2 Karak\u00f6y Istanbul",
    "addr:housenumber":"no 46 / 2",
    "iso:country":"TR",
    "sg:address":"Necatibey Cd. No:46/2",
    "sg:city":"Karak\u00f6y",
    "sg:classifiers":[
        {
            "category":"Transit Center",
            "subcategory":"Freight",
            "type":"Transportation"
        }
    ],
    "sg:phone":"+90 212 244 0117",
    "sg:province":"Istanbul",
    "wof:name":"Tun? Denizcilik Tic. Ltd. Sti.",
    "wof:placetype":"venue"
},
  "geometry": {"coordinates":[28.9764518738,41.0234298706],"type":"Point"}
}