{
  "type": "Feature",
  "properties": {
    "iso:country":"TR",
    "sg:address":"Dr. Ihsan Aksoy Sk. No:7/1 Etiler",
    "sg:city":"Maltepe",
    "sg:classifiers":[
        {
            "category":"Wholesale",
            "subcategory":"Books, Periodicals, & Newspapers",
            "type":"Manufacturing & Wholesale Goods"
        }
    ],
    "sg:phone":"+90 212 257 9529",
    "sg:postcode":"01000",
    "sg:province":"Istanbul",
    "sg:tags":[
        "house",
        "publishing"
    ],
    "wof:name":"Uluslararasi Kitap?ilik Ltd. Sti.",
    "wof:placetype":"venue"
},
  "geometry": {"coordinates":[29.0229263306,41.083568573],"type":"Point"}
}