{
  "type": "Feature",
  "properties": {
    "iso:country":"TR",
    "sg:address":"Organize San. Bolgesi 7.cad.",
    "sg:city":"Bornova",
    "sg:classifiers":[
        {
            "category":"Home & Garden",
            "subcategory":"Building Materials",
            "type":"Retail Goods"
        }
    ],
    "sg:phone":"+90 222236041819",
    "sg:postcode":"35040",
    "sg:province":"Eskisehir",
    "sg:tags":[
        "stone",
        "natural",
        "marble"
    ],
    "wof:name":"Kamer Karo Mermer San. Ve Tic. Ltd.sti.",
    "wof:placetype":"venue"
},
  "geometry": {"coordinates":[30.5154705048,39.7782936096],"type":"Point"}
}