{
  "type": "Feature",
  "properties": {
    "iso:country":"TR",
    "sg:address":"1202/10 Sok. No:28 Gida Carsisi Yenisehir",
    "sg:city":"Merkez",
    "sg:classifiers":[
        {
            "category":"Shopping",
            "type":"Retail Goods"
        }
    ],
    "sg:phone":"+90 232 469 2996",
    "sg:postcode":"61200",
    "sg:province":"Izmir",
    "sg:tags":[
        "material",
        "cleaning"
    ],
    "wof:name":"Cagdas Firca",
    "wof:placetype":"venue"
},
  "geometry": {"coordinates":[27.1423015594,38.4251480103],"type":"Point"}
}