{
  "type": "Feature",
  "properties": {
    "iso:country":"TR",
    "sg:address":"Sanayi Sitesi 14.sok. No:5",
    "sg:city":"Merkez",
    "sg:classifiers":[
        {
            "category":"Manufacturing",
            "subcategory":"Wood Products",
            "type":"Manufacturing & Wholesale Goods"
        }
    ],
    "sg:phone":"+90 424 224 8800",
    "sg:postcode":"53100",
    "sg:province":"Elazig",
    "sg:tags":[
        "forest"
    ],
    "wof:name":"Polat Ltd.sti.",
    "wof:placetype":"venue"
},
  "geometry": {"coordinates":[29.2997703552,40.9002418518],"type":"Point"}
}