{
  "type": "Feature",
  "properties": {
    "iso:country":"TR",
    "sg:address":"Fikret Y?atli Cad. No.6 Osmaniye",
    "sg:city":"Bak\u0131rk\u00f6y",
    "sg:classifiers":[
        {
            "category":"Shopping",
            "subcategory":"Crafts & Fabrics",
            "type":"Retail Goods"
        }
    ],
    "sg:phone":"+90 212 543 6320",
    "sg:province":"Istanbul",
    "sg:tags":[
        "weaving"
    ],
    "wof:name":"Akfil Tekstil Turizm Insaat San. Tic. A.s.",
    "wof:placetype":"venue"
},
  "geometry": {"coordinates":[28.8745765686,41.021282196],"type":"Point"}
}