{
  "type": "Feature",
  "properties": {
    "iso:country":"TR",
    "sg:address":"Bomonti, Birahane Sk. No.17/1 Sisli",
    "sg:city":"Ikitelli/K\u00fc\u00e7\u00fck\u00e7ekmece",
    "sg:classifiers":[
        {
            "category":"Shopping",
            "subcategory":"Stationery & Office Supplies",
            "type":"Retail Goods"
        }
    ],
    "sg:phone":"+90 212 247 2068",
    "sg:postcode":"34670",
    "sg:province":"Istanbul",
    "sg:tags":[
        "furniture"
    ],
    "wof:name":"Buromob San. Tic. A.s.",
    "wof:placetype":"venue"
},
  "geometry": {"coordinates":[28.9809093475,41.0582809448],"type":"Point"}
}