{
  "type": "Feature",
  "properties": {
    "addr:full":"Sanayi Carsisi 1. Arabacilar Sk. No:25 B???kmece Eskisehir",
    "addr:housenumber":"1;25 b ? ? ?",
    "addr:street":"Carsisi;Sk. No;Kmece Eskisehir",
    "iso:country":"TR",
    "sg:address":"Sanayi Carsisi 1. Arabacilar Sk. No:25",
    "sg:city":"B???kmece",
    "sg:orig_category":"Non-classified Establishments",
    "sg:phone":"+90 222 217 3949",
    "sg:province":"Eskisehir",
    "wof:name":"Ucalar Otomotiv San. Tic. A.s.",
    "wof:placetype":"venue"
},
  "geometry": {"coordinates":[30.5154705048,39.7782936096],"type":"Point"}
}