{
  "type": "Feature",
  "properties": {
    "iso:country":"TR",
    "sg:address":"Beytepe K??no. 3 06530 Bilkent Ankara",
    "sg:city":"Ikitelli/K\u00fc\u00e7\u00fck\u00e7ekmece",
    "sg:classifiers":[
        {
            "category":"Professional",
            "subcategory":"Printing & Photocopies",
            "type":"Services"
        }
    ],
    "sg:phone":"+90 312 266 4410",
    "sg:postcode":"34670",
    "sg:province":"Ankara",
    "wof:name":"Meteksan Matbaacilik Ve Teknik San Tic As",
    "wof:placetype":"venue"
},
  "geometry": {"coordinates":[32.7647705078,39.8658714294],"type":"Point"}
}