{
  "type": "Feature",
  "properties": {
    "addr:full":"Yumurtaci Abdibey Cd.yilmaz Sok. No:6 Merdivenkoy -goztepe \u00dcmraniye Istanbul",
    "addr:housenumber":"no 6",
    "addr:street":"Cd.Yilmaz Sok.;Goztepe",
    "iso:country":"TR",
    "sg:address":"Yumurtaci Abdibey Cd.yilmaz Sok. No:6 Merdivenkoy -goztepe",
    "sg:city":"\u00dcmraniye",
    "sg:classifiers":[
        {
            "category":"Farming",
            "subcategory":"Fish & Marine Products",
            "type":"Manufacturing & Wholesale Goods"
        }
    ],
    "sg:phone":"+90 216 565 4119",
    "sg:province":"Istanbul",
    "sg:tags":[
        "automotive"
    ],
    "wof:name":"Erdoganlar Talasli Imalati",
    "wof:placetype":"venue"
},
  "geometry": {"coordinates":[29.0690345764,40.987701416],"type":"Point"}
}