{
  "type": "Feature",
  "properties": {
    "addr:full":"Mersin Serbest Istanbul Mersin",
    "iso:country":"TR",
    "sg:address":"Mersin Serbest",
    "sg:city":"Istanbul",
    "sg:classifiers":[
        {
            "category":"Banks & Credit Unions",
            "subcategory":"Bank",
            "type":"Services"
        }
    ],
    "sg:phone":"+90 324 233 4239",
    "sg:province":"Mersin",
    "wof:name":"T?kiye Vakiflar, Bankasi Tao",
    "wof:placetype":"venue"
},
  "geometry": {"coordinates":[34.673267,36.824162],"type":"Point"}
}