{
  "type": "Feature",
  "properties": {
    "iso:country":"TR",
    "sg:address":"Cengiz Topel Cad. Y?el Apt. No:1",
    "sg:city":"Mersin",
    "sg:classifiers":[
        {
            "category":"Wholesale",
            "subcategory":"Medical Equipment & Supplies",
            "type":"Manufacturing & Wholesale Goods"
        }
    ],
    "sg:phone":"+90 414 313 5177",
    "sg:postcode":"52750",
    "sg:province":"Sanlurfa",
    "wof:name":"Caglar Medikal",
    "wof:placetype":"venue"
},
  "geometry": {"coordinates":[38.785369873,37.1567001343],"type":"Point"}
}