{
  "type": "Feature",
  "properties": {
    "addr:full":"T. Ozal Cad. Karag? Ism. No:128 Findikzade \u00c7ankaya Istanbul 06420",
    "addr:housenumber":"?;no;findikzade",
    "addr:postcode":"06420",
    "addr:street":"T. Ozal Cad. Karag",
    "iso:country":"TR",
    "sg:address":"T. Ozal Cad. Karag? Ism. No:128 Findikzade",
    "sg:city":"\u00c7ankaya",
    "sg:classifiers":[
        {
            "category":"Wholesale",
            "subcategory":"Medical Equipment & Supplies",
            "type":"Manufacturing & Wholesale Goods"
        }
    ],
    "sg:phone":"+90 212 533 6171",
    "sg:postcode":"06420",
    "sg:province":"Istanbul",
    "sg:tags":[
        "material"
    ],
    "wof:name":"Mine Medikal",
    "wof:placetype":"venue"
},
  "geometry": {"coordinates":[28.9759254456,41.0123786926],"type":"Point"}
}