{
  "type": "Feature",
  "properties": {
    "iso:country":"TR",
    "sg:address":"Halitpasa Cd. No:34/a",
    "sg:city":"G.o.pasa",
    "sg:classifiers":[
        {
            "category":"Shopping",
            "subcategory":"Florist",
            "type":"Retail Goods"
        }
    ],
    "sg:phone":"+90 212 578 6730",
    "sg:province":"Istanbul",
    "sg:tags":[
        "flower"
    ],
    "wof:name":"Asri ?i?ek Evi",
    "wof:placetype":"venue"
},
  "geometry": {"coordinates":[28.9299583435,41.0463256836],"type":"Point"}
}