{
  "type": "Feature",
  "properties": {
    "iso:country":"TR",
    "sg:address":"Nuhkuyusu Cd. No:52 ?sk?ar",
    "sg:city":"Yenikent",
    "sg:classifiers":[
        {
            "category":"Home & Garden",
            "subcategory":"Kitchen Supply",
            "type":"Retail Goods"
        }
    ],
    "sg:phone":"+90 216 333 0873",
    "sg:postcode":"06938",
    "sg:province":"Istanbul",
    "sg:tags":[
        "wardrobe"
    ],
    "wof:name":"Yunuslar Ins.",
    "wof:placetype":"venue"
},
  "geometry": {"coordinates":[28.9759254456,41.0123786926],"type":"Point"}
}