{
  "type": "Feature",
  "properties": {
    "addr:full":"Karab?k Karabaglar Karab?k 44210",
    "addr:postcode":"44210",
    "iso:country":"TR",
    "sg:address":"Karab?k",
    "sg:city":"Karabaglar",
    "sg:classifiers":[
        {
            "category":"Government",
            "subcategory":"Office",
            "type":"Public Place"
        }
    ],
    "sg:phone":"+90 370 412 8788",
    "sg:postcode":"44210",
    "sg:province":"Karab?k",
    "sg:tags":[
        "army"
    ],
    "wof:name":"Karab?k (yenice,eskipazar,ovacik ) Askerlik Subesi",
    "wof:placetype":"venue"
},
  "geometry": {"coordinates":[38.4896812439,38.455280304],"type":"Point"}
}