{
  "type": "Feature",
  "properties": {
    "iso:country":"TR",
    "sg:address":"Bahcelievler Mah. Mithatpasa Cad. No: 10",
    "sg:city":"Vezirkopru",
    "sg:classifiers":[
        {
            "category":"Food & Beverages",
            "subcategory":"Meat & Fish",
            "type":"Retail Goods"
        }
    ],
    "sg:phone":"+90 362 647 2852",
    "sg:postcode":"55900",
    "sg:province":"Samsun",
    "sg:tags":[
        "product"
    ],
    "wof:name":"Akdemir Ticaret",
    "wof:placetype":"venue"
},
  "geometry": {"coordinates":[36.3381233215,41.2815742493],"type":"Point"}
}