{
  "type": "Feature",
  "properties": {
    "iso:country":"TR",
    "sg:address":"Azakoglu Sahil Sitesi Deniz Kent D Bl. No. 3 / 4 Alanya",
    "sg:city":"Bayrampasa",
    "sg:classifiers":[
        {
            "category":"Personal",
            "subcategory":"Sauna",
            "type":"Services"
        }
    ],
    "sg:phone":"+90 242 514 0786",
    "sg:postcode":"36100",
    "sg:province":"Antalya",
    "sg:tags":[
        "pool"
    ],
    "wof:name":"Ak Havuz San. Tic. A.s.",
    "wof:placetype":"venue"
},
  "geometry": {"coordinates":[30.703135,36.887505],"type":"Point"}
}