{
  "type": "Feature",
  "properties": {
    "addr:full":"Lise Cd. No:3 Kestel Bursa 09800",
    "addr:housenumber":"no 3",
    "addr:postcode":"09800",
    "addr:street":"Lise Cd.;Bursa",
    "iso:country":"TR",
    "sg:address":"Lise Cd. No:3",
    "sg:city":"Kestel",
    "sg:classifiers":[
        {
            "category":"Shopping",
            "subcategory":"Clothing, Apparel, & Fashions",
            "type":"Retail Goods"
        }
    ],
    "sg:phone":"+90 224 372 3209",
    "sg:postcode":"09800",
    "sg:province":"Bursa",
    "sg:tags":[
        "house"
    ],
    "wof:name":"Ak?eyiz Ltd. Sti.",
    "wof:placetype":"venue"
},
  "geometry": {"coordinates":[29.0045375824,40.2286605835],"type":"Point"}
}