{
  "type": "Feature",
  "properties": {
    "addr:full":"Yali Cad. 36b Zonguldak Karadeniz Eregli 67320",
    "addr:housenumber":"36b",
    "addr:postcode":"67320",
    "addr:street":"Yali Cad.;Eregli",
    "iso:country":"TR",
    "sg:address":"Yali Cad. 36b Zonguldak",
    "sg:city":"Karadeniz Eregli",
    "sg:classifiers":[
        {
            "category":"Banks & Credit Unions",
            "subcategory":"Bank",
            "type":"Services"
        }
    ],
    "sg:phone":"+90 372 323 0888",
    "sg:province":"67320",
    "wof:name":"Bank Ekspres As",
    "wof:placetype":"venue"
},
  "geometry": {"coordinates":[31.411869,41.212254],"type":"Point"}
}