{
  "type": "Feature",
  "properties": {
    "addr:full":"Inebey Mah Inklap Cad Emre Is Merkezi No: 53-55 Aksaray Istanbul 31030",
    "addr:housenumber":"no 53-55",
    "addr:postcode":"31030",
    "addr:street":"Inebey Mah Inklap Cad Emre",
    "iso:country":"TR",
    "sg:address":"Inebey Mah Inklap Cad Emre Is Merkezi No: 53-55",
    "sg:city":"Aksaray",
    "sg:classifiers":[
        {
            "category":"Wholesale",
            "subcategory":"Auto Parts",
            "type":"Manufacturing & Wholesale Goods"
        }
    ],
    "sg:phone":"+90 212 621 5970",
    "sg:postcode":"31030",
    "sg:province":"Istanbul",
    "sg:tags":[
        "spare"
    ],
    "wof:name":"International Boss Ltd.sti",
    "wof:placetype":"venue"
},
  "geometry": {"coordinates":[28.9861831665,41.0408554077],"type":"Point"}
}