{
  "type": "Feature",
  "properties": {
    "addr:full":"Rihtim Cad. Iskele Sk. No:10 Kadik? Kartal Istanbul 46000",
    "addr:housenumber":"10;?",
    "addr:postcode":"46000",
    "addr:street":"Rihtim Cad. Iskele Sk. No",
    "iso:country":"TR",
    "sg:address":"Rihtim Cad. Iskele Sk. No:10 Kadik?",
    "sg:city":"Kartal",
    "sg:classifiers":[
        {
            "category":"Wholesale",
            "subcategory":"Medical Equipment & Supplies",
            "type":"Manufacturing & Wholesale Goods"
        }
    ],
    "sg:phone":"+90 212",
    "sg:postcode":"46000",
    "sg:province":"Istanbul",
    "sg:tags":[
        "material"
    ],
    "wof:name":"Kadik?y Medikal",
    "wof:placetype":"venue"
},
  "geometry": {"coordinates":[29.0251197815,40.9959869385],"type":"Point"}
}