{
  "type": "Feature",
  "properties": {
    "iso:country":"TR",
    "sg:address":"Ataturk Bulvari Eren Apt. 3/8",
    "sg:city":"Iskenderun",
    "sg:classifiers":[
        {
            "category":"Mining & Drilling",
            "type":"Manufacturing & Wholesale Goods"
        }
    ],
    "sg:phone":"+90 326 613 2585",
    "sg:postcode":"31200",
    "sg:province":"Hatay",
    "sg:tags":[
        "industry",
        "mine"
    ],
    "wof:name":"Kromtas Madencilik",
    "wof:placetype":"venue"
},
  "geometry": {"coordinates":[28.8274230957,40.9806747437],"type":"Point"}
}