{
  "type": "Feature",
  "properties": {
    "addr:full":"Eminalipasa Cad. No. 30 / 3-4-5-6-7 Suadiye \u00c7ankaya Istanbul",
    "addr:housenumber":"30 / 3-4-5-6-7",
    "addr:street":"Eminalipasa Cad. No.;Suadiye",
    "iso:country":"TR",
    "sg:address":"Eminalipasa Cad. No. 30 / 3-4-5-6-7 Suadiye",
    "sg:city":"\u00c7ankaya",
    "sg:classifiers":[
        {
            "category":"Personal",
            "subcategory":"Sauna",
            "type":"Services"
        }
    ],
    "sg:phone":"+90 216388965154",
    "sg:province":"Istanbul",
    "sg:tags":[
        "pool"
    ],
    "wof:name":"Villa Havuz Yapi Organizasyon Ltd.",
    "wof:placetype":"venue"
},
  "geometry": {"coordinates":[29.081493,40.961082],"type":"Point"}
}