{
  "type": "Feature",
  "properties": {
    "addr:full":"Kusget A-blok 1.cad. No:47 Ikitelli/K\u00fc\u00e7\u00fck\u00e7ekmece Gaziantep 34670",
    "addr:housenumber":"no 47",
    "addr:postcode":"34670",
    "iso:country":"TR",
    "sg:address":"Kusget A-blok 1.cad. No:47",
    "sg:city":"Ikitelli/K\u00fc\u00e7\u00fck\u00e7ekmece",
    "sg:classifiers":[
        {
            "category":"Manufacturing",
            "subcategory":"Metals",
            "type":"Manufacturing & Wholesale Goods"
        }
    ],
    "sg:phone":"+90 342 235 0225",
    "sg:postcode":"34670",
    "sg:province":"Gaziantep",
    "sg:tags":[
        "industry"
    ],
    "wof:name":"Guven Metal San.tic. Ltd.sti.",
    "wof:placetype":"venue"
},
  "geometry": {"coordinates":[37.3761024475,37.0629463196],"type":"Point"}
}