{
  "type": "Feature",
  "properties": {
    "iso:country":"TR",
    "sg:address":"Halkali Cd. No:243 Sefak?",
    "sg:city":"Iskitler",
    "sg:classifiers":[
        {
            "category":"Shopping",
            "subcategory":"Stationery & Office Supplies",
            "type":"Retail Goods"
        }
    ],
    "sg:phone":"+90 212 697 9070",
    "sg:postcode":"06070",
    "sg:province":"Istanbul",
    "sg:tags":[
        "paper"
    ],
    "wof:name":"Ve-ge Hassas Kagit Yapistirici Bant San. Tic.",
    "wof:placetype":"venue"
},
  "geometry": {"coordinates":[28.9759254456,41.0123786926],"type":"Point"}
}