{
  "type": "Feature",
  "properties": {
    "iso:country":"TR",
    "sg:address":"Sarayalti Mah. 12.tabakhane Sok. No:4",
    "sg:city":"\u00c7orlu",
    "sg:classifiers":[
        {
            "category":"Social Services",
            "subcategory":"Job Training",
            "type":"Services"
        }
    ],
    "sg:phone":"+90 276 215 3036",
    "sg:province":"Usak",
    "sg:tags":[
        "tannery"
    ],
    "wof:name":"Demirsan Deri Tekstil Ticaret Ltd.sti.",
    "wof:placetype":"venue"
},
  "geometry": {"coordinates":[29.4078292847,38.6682548523],"type":"Point"}
}