{
  "type": "Feature",
  "properties": {
    "addr:full":"Degol Cad. No: 59 K: 1 Besevler Ankara 04100",
    "addr:housenumber":"59 k 1",
    "addr:postcode":"04100",
    "addr:street":"Degol Cad. No;Besevler Ankara",
    "iso:country":"TR",
    "sg:address":"Degol Cad. No: 59 K: 1",
    "sg:city":"Besevler",
    "sg:classifiers":[
        {
            "category":"Travel",
            "subcategory":"Travel Agent",
            "type":"Entertainment"
        }
    ],
    "sg:phone":"+90 312 431 8494",
    "sg:postcode":"04100",
    "sg:province":"Ankara",
    "sg:tags":[
        "agency",
        "tourism"
    ],
    "wof:name":"Surf Turizm",
    "wof:placetype":"venue"
},
  "geometry": {"coordinates":[32.8604812622,39.9429283142],"type":"Point"}
}