{
  "type": "Feature",
  "properties": {
    "addr:full":"Inkilap Sk. No:31/10 Kizilay Mersin Ankara 52750",
    "addr:housenumber":"31 / 10",
    "addr:postcode":"52750",
    "addr:street":"Inkilap Sk. No;Kizilay",
    "iso:country":"TR",
    "sg:address":"Inkilap Sk. No:31/10 Kizilay",
    "sg:city":"Mersin",
    "sg:classifiers":[
        {
            "category":"Mining & Drilling",
            "type":"Manufacturing & Wholesale Goods"
        }
    ],
    "sg:phone":"+90 312 417 4630",
    "sg:postcode":"52750",
    "sg:province":"Ankara",
    "sg:tags":[
        "industry",
        "mine"
    ],
    "wof:name":"Baris Hafriyat Ve Madencilik A.s.",
    "wof:placetype":"venue"
},
  "geometry": {"coordinates":[32.856842041,39.9209022522],"type":"Point"}
}