{
  "type": "Feature",
  "properties": {
    "iso:country":"TR",
    "sg:address":"Istanbul Cd. Mektep Ark. Sk. No:6/1",
    "sg:city":"Bakirkoy",
    "sg:classifiers":[
        {
            "category":"Farming",
            "subcategory":"Farm & Veterinary Services",
            "type":"Manufacturing & Wholesale Goods"
        }
    ],
    "sg:phone":"+90 212 583 7723",
    "sg:postcode":"35790",
    "sg:province":"Istanbul",
    "sg:tags":[
        "veterinarian"
    ],
    "wof:name":"Seckin Veteriner Klinigi",
    "wof:placetype":"venue"
},
  "geometry": {"coordinates":[28.2110881805,41.0835494995],"type":"Point"}
}