{
  "type": "Feature",
  "properties": {
    "iso:country":"TR",
    "sg:address":"Yeni San.sitesi",
    "sg:city":"Y.dudullu",
    "sg:orig_category":"General Industrial Products",
    "sg:phone":"+90 344 236 2391",
    "sg:province":"Kahramanmaras",
    "wof:name":"Ozen Endustri Makina A.s.",
    "wof:placetype":"venue"
},
  "geometry": {"coordinates":[36.9282989502,37.5894012451],"type":"Point"}
}