{
  "type": "Feature",
  "properties": {
    "iso:country":"TR",
    "sg:address":"Kibris Sehitler Cad.",
    "sg:city":"Trabzon",
    "sg:classifiers":[
        {
            "category":"Banks & Credit Unions",
            "subcategory":"Bank",
            "type":"Services"
        }
    ],
    "sg:phone":"+90 462 326 6356",
    "sg:postcode":"61000",
    "sg:province":"61030",
    "wof:name":"T?kiye Halk, Bankasi As",
    "wof:placetype":"venue"
},
  "geometry": {"coordinates":[37.38998,37.058662],"type":"Point"}
}