{
  "type": "Feature",
  "properties": {
    "iso:country":"TR",
    "sg:address":"Sidali Pasaji 2.kat No:",
    "sg:city":"Serik",
    "sg:classifiers":[
        {
            "category":"Food & Beverages",
            "subcategory":"Fruits & Vegetables",
            "type":"Retail Goods"
        }
    ],
    "sg:phone":"+90 324 231 1322",
    "sg:postcode":"07500",
    "sg:province":"I?el",
    "sg:tags":[
        "fresh"
    ],
    "wof:name":"Akay Koll.sti.",
    "wof:placetype":"venue"
},
  "geometry": {"coordinates":[31.0073604584,37.1061401367],"type":"Point"}
}