{
  "type": "Feature",
  "properties": {
    "iso:country":"TR",
    "sg:address":"Biskek Cd. 65. Sok. No:21/2 Emek",
    "sg:city":"Kad\u0131k\u00f6y",
    "sg:classifiers":[
        {
            "category":"Mining & Drilling",
            "type":"Manufacturing & Wholesale Goods"
        }
    ],
    "sg:phone":"+90 312 223 0247",
    "sg:postcode":"34718",
    "sg:province":"Ankara",
    "sg:tags":[
        "industry",
        "mine"
    ],
    "wof:name":"Km Madencilik Ltd. Sti.",
    "wof:placetype":"venue"
},
  "geometry": {"coordinates":[32.8194541931,39.9260635376],"type":"Point"}
}