{
  "type": "Feature",
  "properties": {
    "addr:full":"Gazibey Cad. 31/10 Anatamir Fb. Kars. Eski San. Kad\u0131k\u00f6y Kayseri",
    "addr:housenumber":"31 / 10",
    "addr:street":"Gazibey Cad.;Anatamir Fb. Kars. Eski San. Kadikoey",
    "iso:country":"TR",
    "sg:address":"Gazibey Cad. 31/10 Anatamir Fb. Kars. Eski San.",
    "sg:city":"Kad\u0131k\u00f6y",
    "sg:classifiers":[
        {
            "category":"Professional",
            "subcategory":"Business Services",
            "type":"Services"
        }
    ],
    "sg:phone":"+90 352336495832",
    "sg:province":"Kayseri",
    "sg:tags":[
        "industry",
        "casting"
    ],
    "wof:name":"Ergin Mak. Model Dokum San. Tic. Ltd. Sti.",
    "wof:placetype":"venue"
},
  "geometry": {"coordinates":[35.4364013672,38.7450408936],"type":"Point"}
}