{
  "type": "Feature",
  "properties": {
    "addr:full":"Trabzon Cad. Seyran Apt. 21/3 Mersin Kahramanmaras 52750",
    "addr:housenumber":"seyran;21 / 3",
    "addr:postcode":"52750",
    "addr:street":"Trabzon Cad.",
    "iso:country":"TR",
    "sg:address":"Trabzon Cad. Seyran Apt. 21/3",
    "sg:city":"Mersin",
    "sg:classifiers":[
        {
            "category":"Professional",
            "subcategory":"Art Services",
            "type":"Services"
        }
    ],
    "sg:phone":"+90 344 231 3131",
    "sg:postcode":"52750",
    "sg:province":"Kahramanmaras",
    "sg:tags":[
        "marketing"
    ],
    "wof:name":"Kent Maras Dis Ticaret A.s.",
    "wof:placetype":"venue"
},
  "geometry": {"coordinates":[36.9280776978,37.5858345032],"type":"Point"}
}