{
  "type": "Feature",
  "properties": {
    "iso:country":"TR",
    "sg:address":"Karaman Cad.hancerli Sk. No:16",
    "sg:city":"Ayvalik",
    "sg:classifiers":[
        {
            "category":"Wholesale",
            "subcategory":"Machinery & Supplies",
            "type":"Manufacturing & Wholesale Goods"
        }
    ],
    "sg:phone":"+90 332 352 2098",
    "sg:postcode":"01680",
    "sg:province":"Konya",
    "sg:tags":[
        "agricultural"
    ],
    "wof:name":"Cagri Tarim Ltd. Sti.",
    "wof:placetype":"venue"
},
  "geometry": {"coordinates":[32.4991722107,37.8671226501],"type":"Point"}
}