{
  "type": "Feature",
  "properties": {
    "iso:country":"TR",
    "sg:address":"Nuh Sanayi Sitesi B-blok No:16",
    "sg:city":"Tuzla",
    "sg:classifiers":[
        {
            "category":"Manufacturing",
            "subcategory":"Watercraft",
            "type":"Manufacturing & Wholesale Goods"
        }
    ],
    "sg:phone":"+90 216 395 0657",
    "sg:postcode":"01900",
    "sg:province":"Istanbul",
    "sg:tags":[
        "builder",
        "yacht",
        "trough"
    ],
    "wof:name":"Ozdemir Yatcilik",
    "wof:placetype":"venue"
},
  "geometry": {"coordinates":[28.975925,41.012379],"type":"Point"}
}