{
  "type": "Feature",
  "properties": {
    "iso:country":"TR",
    "sg:address":"98/1 Sok.no:7",
    "sg:city":"Pinarbasi",
    "sg:classifiers":[
        {
            "category":"Manufacturing",
            "subcategory":"Food",
            "type":"Manufacturing & Wholesale Goods"
        }
    ],
    "sg:phone":"+90 232 479 1363",
    "sg:postcode":"35060",
    "sg:province":"Izmir",
    "sg:tags":[
        "product",
        "floury",
        "macaroni"
    ],
    "wof:name":"Kadioglu Degirmencilk A.s",
    "wof:placetype":"venue"
},
  "geometry": {"coordinates":[27.1423015594,38.4251480103],"type":"Point"}
}