{
  "type": "Feature",
  "properties": {
    "addr:full":"?ifte Havuzlar Cad. Askeri Firin Sok. Bi?ak San. Sit. A Blok Kat 2 Davutpasa Istanbul 31500",
    "addr:housenumber":"?;bi ?;blok kat 2",
    "addr:postcode":"31500",
    "addr:street":"Ifte Havuzlar Cad. Askeri Firin Sok.",
    "iso:country":"TR",
    "sg:address":"?ifte Havuzlar Cad. Askeri Firin Sok. Bi?ak San. Sit. A Blok Kat 2",
    "sg:city":"Davutpasa",
    "sg:classifiers":[
        {
            "category":"Shopping",
            "subcategory":"Crafts & Fabrics",
            "type":"Retail Goods"
        }
    ],
    "sg:postcode":"31500",
    "sg:province":"Istanbul",
    "sg:tags":[
        "knitting"
    ],
    "wof:name":"Alteks Tekstil",
    "wof:placetype":"venue"
},
  "geometry": {"coordinates":[28.9759254456,41.0123786926],"type":"Point"}
}