{
  "type": "Feature",
  "properties": {
    "iso:country":"TR",
    "sg:address":"Cumh. Bulv.no: 84/404 Alsancak",
    "sg:city":"Ke??en",
    "sg:classifiers":[
        {
            "category":"Organizations",
            "subcategory":"Membership Organization",
            "type":"Services"
        }
    ],
    "sg:phone":"+90 232 425 7273",
    "sg:province":"Izmir",
    "wof:name":"Pansiyoncular Bir. Genel Baskan.",
    "wof:placetype":"venue"
},
  "geometry": {"coordinates":[27.1450805664,38.438419342],"type":"Point"}
}