{
  "type": "Feature",
  "properties": {
    "addr:full":"677/33 Sk. No:10 6.sanayi Sitesi Impo Arkasi Karabaglar Gayrettepe/besiktas Izmir 80280",
    "addr:housenumber":"677 / 33;6.sanayi",
    "addr:postcode":"80280",
    "addr:street":"Sk. No 10",
    "iso:country":"TR",
    "sg:address":"677/33 Sk. No:10 6.sanayi Sitesi Impo Arkasi Karabaglar",
    "sg:city":"Gayrettepe/besiktas",
    "sg:classifiers":[
        {
            "category":"Retail",
            "subcategory":"Auto Repair",
            "type":"Services"
        }
    ],
    "sg:phone":"+90 232 282 1010",
    "sg:postcode":"80280",
    "sg:province":"Izmir",
    "sg:tags":[
        "maintenance"
    ],
    "wof:name":"Barut?u Otomotiv Karas?r Oto Boya Ins. Turz. San. Ve Tic. Ltd. Sti.",
    "wof:placetype":"venue"
},
  "geometry": {"coordinates":[27.1423015594,38.4251480103],"type":"Point"}
}