{
  "type": "Feature",
  "properties": {
    "iso:country":"TR",
    "sg:address":"San. Mh. Zafer Sk. No:41/a 4.levent",
    "sg:city":"Edremit",
    "sg:classifiers":[
        {
            "category":"Wholesale",
            "subcategory":"Furniture",
            "type":"Manufacturing & Wholesale Goods"
        }
    ],
    "sg:phone":"+90 212 279 9695",
    "sg:postcode":"04500",
    "sg:province":"Istanbul",
    "sg:tags":[
        "school"
    ],
    "wof:name":"?izgi Tasarim Mobilya",
    "wof:placetype":"venue"
},
  "geometry": {"coordinates":[29.038778,41.093491],"type":"Point"}
}