{
  "type": "Feature",
  "properties": {
    "addr:full":"Halkali Cd. No:247 Sefak? \u00dcmraniye Istanbul",
    "addr:housenumber":"no",
    "addr:street":"Halkali Cd.;Sefak",
    "iso:country":"TR",
    "sg:address":"Halkali Cd. No:247 Sefak?",
    "sg:city":"\u00dcmraniye",
    "sg:classifiers":[
        {
            "category":"Home & Garden",
            "subcategory":"Hardware",
            "type":"Retail Goods"
        }
    ],
    "sg:phone":"+90 212 698 9190",
    "sg:province":"Istanbul",
    "sg:tags":[
        "generator",
        "power"
    ],
    "wof:name":"Eti Elektroteknik A.s.",
    "wof:placetype":"venue"
},
  "geometry": {"coordinates":[28.7924251556,40.9708900452],"type":"Point"}
}