{
  "type": "Feature",
  "properties": {
    "addr:full":"Saltak Cad. Topcular Denizli 07300",
    "addr:postcode":"07300",
    "addr:street":"Saltak Cad. Topcular",
    "iso:country":"TR",
    "sg:address":"Saltak Cad.",
    "sg:city":"Topcular",
    "sg:classifiers":[
        {
            "category":"Shopping",
            "subcategory":"Clothing, Apparel, & Fashions",
            "type":"Retail Goods"
        }
    ],
    "sg:phone":"+90 258 264 9479",
    "sg:postcode":"07300",
    "sg:province":"Denizli",
    "sg:tags":[
        "ready",
        "wear"
    ],
    "wof:name":"Sierra Tekstil San.tic.ltd.sti.",
    "wof:placetype":"venue"
},
  "geometry": {"coordinates":[29.0822238922,37.7785568237],"type":"Point"}
}