{
  "type": "Feature",
  "properties": {
    "addr:full":"Ilker 1 Cad. 155.sok. 9/a Dikmen Besiktas Ankara 75200",
    "addr:housenumber":"1;155.sok 9 / a",
    "addr:postcode":"75200",
    "addr:street":"Ilker;Cad.;Dikmen Besiktas",
    "iso:country":"TR",
    "sg:address":"Ilker 1 Cad. 155.sok. 9/a Dikmen",
    "sg:city":"Besiktas",
    "sg:classifiers":[
        {
            "category":"Shopping",
            "subcategory":"Party Supplies",
            "type":"Retail Goods"
        }
    ],
    "sg:phone":"+90 312 480 4352",
    "sg:postcode":"75200",
    "sg:province":"Ankara",
    "sg:tags":[
        "sound",
        "light",
        "system"
    ],
    "wof:name":"Sestra Ses Ve Isik Sistemleri Kiralama Hizmetleri",
    "wof:placetype":"venue"
},
  "geometry": {"coordinates":[32.8377151489,39.8649711609],"type":"Point"}
}