{
  "type": "Feature",
  "properties": {
    "iso:country":"TR",
    "sg:address":"1202/2 Sk. No.22",
    "sg:city":"Yenisehir",
    "sg:classifiers":[
        {
            "category":"Utilities",
            "subcategory":"Water",
            "type":"Services"
        }
    ],
    "sg:phone":"+90 232 433 9097",
    "sg:postcode":"31750",
    "sg:province":"Izmir",
    "sg:tags":[
        "vegetable",
        "margarine",
        "oil"
    ],
    "wof:name":"Merdar Koll.sti.",
    "wof:placetype":"venue"
},
  "geometry": {"coordinates":[27.1971855164,38.4027938843],"type":"Point"}
}