{
  "type": "Feature",
  "properties": {
    "iso:country":"TR",
    "sg:address":"Kisikli Cad. No:1 Ak Is Mrk.",
    "sg:city":"Altunizade",
    "sg:classifiers":[
        {
            "category":"Shopping",
            "subcategory":"Clothing, Apparel, & Fashions",
            "type":"Retail Goods"
        }
    ],
    "sg:phone":"+90 216 391 0934",
    "sg:postcode":"34662",
    "sg:province":"Istanbul",
    "sg:tags":[
        "ready",
        "wear"
    ],
    "wof:name":"Enteks Tekstil Url. San. Ltd.sti.",
    "wof:placetype":"venue"
},
  "geometry": {"coordinates":[29.0853233337,41.0209999084],"type":"Point"}
}