{
  "type": "Feature",
  "properties": {
    "iso:country":"TR",
    "sg:address":"Mete Cad. No.22/1-2 Taksim",
    "sg:city":"Iskenderun",
    "sg:classifiers":[
        {
            "category":"Banks & Credit Unions",
            "subcategory":"Financial Services",
            "type":"Services"
        }
    ],
    "sg:phone":"+90 212 311 1000",
    "sg:postcode":"31200",
    "sg:province":"Istanbul",
    "sg:tags":[
        "finance"
    ],
    "wof:name":"Abn Amro Yatirim Menkul Degerler",
    "wof:placetype":"venue"
},
  "geometry": {"coordinates":[28.9737319946,41.0474052429],"type":"Point"}
}