{
  "type": "Feature",
  "properties": {
    "iso:country":"TR",
    "sg:address":"Karliktepe Mah. Fahri Korut?k Sok. No: 10",
    "sg:city":"Kartal",
    "sg:classifiers":[
        {
            "category":"Building & Trades",
            "subcategory":"Construction",
            "type":"Services"
        }
    ],
    "sg:phone":"+90 21638721013",
    "sg:postcode":"34870",
    "sg:province":"Istanbul",
    "sg:tags":[
        "steel"
    ],
    "wof:name":"Alu?lar Mak. Ve Ins. Ltd. Sti.",
    "wof:placetype":"venue"
},
  "geometry": {"coordinates":[29.194298,40.900539],"type":"Point"}
}