{
  "type": "Feature",
  "properties": {
    "addr:full":"Fahrettin Kerim G?ay Cad. 190/4 ?emenzar Apt. K:1 Daire:4 Kad\u0131k\u00f6y Istanbul 34990",
    "addr:housenumber":"?;190 / 4 ?;1;4",
    "addr:postcode":"34990",
    "addr:street":"Fahrettin Kerim G;Ay Cad.;Emenzar;Daire",
    "iso:country":"TR",
    "sg:address":"Fahrettin Kerim G?ay Cad. 190/4 ?emenzar Apt. K:1 Daire:4",
    "sg:city":"Kad\u0131k\u00f6y",
    "sg:classifiers":[
        {
            "category":"Home & Garden",
            "subcategory":"Building Materials",
            "type":"Retail Goods"
        }
    ],
    "sg:phone":"+90 216 567 7085",
    "sg:postcode":"34990",
    "sg:province":"Istanbul",
    "sg:tags":[
        "window",
        "door"
    ],
    "wof:name":"Dorkay Yapi Otomasyon",
    "wof:placetype":"venue"
},
  "geometry": {"coordinates":[28.9861831665,41.0408554077],"type":"Point"}
}