{
  "type": "Feature",
  "properties": {
    "addr:full":"Boztepe Yenibosna Kayseri 43270",
    "addr:postcode":"43270",
    "addr:street":"Yenibosna",
    "iso:country":"TR",
    "sg:address":"Boztepe",
    "sg:city":"Yenibosna",
    "sg:classifiers":[
        {
            "category":"Food & Beverages",
            "subcategory":"Dairy",
            "type":"Retail Goods"
        }
    ],
    "sg:phone":"+90 352 339 9652",
    "sg:postcode":"43270",
    "sg:province":"Kayseri",
    "sg:tags":[
        "pruducts",
        "milk"
    ],
    "wof:name":"Mazmanoglu",
    "wof:placetype":"venue"
},
  "geometry": {"coordinates":[35.4813499451,38.7647247314],"type":"Point"}
}