{
  "type": "Feature",
  "properties": {
    "iso:country":"TR",
    "sg:address":"Sani Konukoglu Bulvari",
    "sg:city":"Merter",
    "sg:classifiers":[
        {
            "category":"Manufacturing",
            "subcategory":"Textiles",
            "type":"Manufacturing & Wholesale Goods"
        }
    ],
    "sg:phone":"+90 342 241 2000",
    "sg:province":"Gaziantep",
    "sg:tags":[
        "product"
    ],
    "wof:name":"Sanko Tekstil San. Ve Tic. A.s.",
    "wof:placetype":"venue"
},
  "geometry": {"coordinates":[37.3873062134,37.0746917725],"type":"Point"}
}