{
  "type": "Feature",
  "properties": {
    "iso:country":"TR",
    "sg:address":"1204.sokak No:41/1e",
    "sg:city":"Yenisehir",
    "sg:classifiers":[
        {
            "category":"Manufacturing",
            "subcategory":"Building Materials",
            "type":"Manufacturing & Wholesale Goods"
        }
    ],
    "sg:phone":"+90 232 457 8528",
    "sg:postcode":"31750",
    "sg:province":"Izmir",
    "sg:tags":[
        "lifts-elevators"
    ],
    "wof:name":"Erteknik Elektrik Elektronik Ltd.sti.",
    "wof:placetype":"venue"
},
  "geometry": {"coordinates":[27.1598415375,38.4320678711],"type":"Point"}
}