{
  "type": "Feature",
  "properties": {
    "addr:full":"Ataturk Bulvari No: 31 Kartal Istanbul 46000",
    "addr:housenumber":"no 31",
    "addr:postcode":"46000",
    "addr:street":"Ataturk Bulvari",
    "iso:country":"TR",
    "sg:address":"Ataturk Bulvari No: 31",
    "sg:city":"Kartal",
    "sg:classifiers":[
        {
            "category":"Farming",
            "subcategory":"Farm & Veterinary Services",
            "type":"Manufacturing & Wholesale Goods"
        }
    ],
    "sg:phone":"+90 216 387 3034",
    "sg:postcode":"46000",
    "sg:province":"Istanbul",
    "sg:tags":[
        "veterinarian"
    ],
    "wof:name":"Pet-evin Veteriner Klinigi",
    "wof:placetype":"venue"
},
  "geometry": {"coordinates":[28.5359859467,41.0101318359],"type":"Point"}
}