{
  "type": "Feature",
  "properties": {
    "iso:country":"TR",
    "sg:address":"Cumhuriyet Cad 163/a",
    "sg:city":"Mersin",
    "sg:classifiers":[
        {
            "category":"Banks & Credit Unions",
            "subcategory":"Bank",
            "type":"Services"
        }
    ],
    "sg:phone":"+90 212 240 6326",
    "sg:postcode":"52750",
    "sg:province":"Elmadag",
    "wof:name":"T?k Ticaret, Bankasi As",
    "wof:placetype":"venue"
},
  "geometry": {"coordinates":[33.166641,39.977417],"type":"Point"}
}