{
  "type": "Feature",
  "properties": {
    "iso:country":"TR",
    "sg:address":"Yildiz Posta Cad 54",
    "sg:city":"Gayrettepe",
    "sg:classifiers":[
        {
            "category":"Banks & Credit Unions",
            "subcategory":"Bank",
            "type":"Services"
        }
    ],
    "sg:phone":"+90 212 274 4280",
    "sg:postcode":"34349",
    "sg:province":"80280",
    "wof:name":"T?k Dis Ticaret, Bankasi As",
    "wof:placetype":"venue"
},
  "geometry": {"coordinates":[29.008381,41.065689],"type":"Point"}
}