{
  "type": "Feature",
  "properties": {
    "addr:full":"Akdeniz Cd. No:8/405 Iskenderun Izmir 31200",
    "addr:housenumber":"no 8 / 405",
    "addr:postcode":"31200",
    "addr:street":"Cd.",
    "iso:country":"TR",
    "sg:address":"Akdeniz Cd. No:8/405",
    "sg:city":"Iskenderun",
    "sg:classifiers":[
        {
            "category":"Mining & Drilling",
            "type":"Manufacturing & Wholesale Goods"
        }
    ],
    "sg:phone":"+90 232 483 5076",
    "sg:postcode":"31200",
    "sg:province":"Izmir",
    "sg:tags":[
        "industry",
        "mine"
    ],
    "wof:name":"Imaj Madencilik San. Tic. A.s.",
    "wof:placetype":"venue"
},
  "geometry": {"coordinates":[27.1340675354,38.4272346497],"type":"Point"}
}