{
  "type": "Feature",
  "properties": {
    "addr:full":"Ist.d?ya Tic.merk.cobancesme Kavsagi A-1 Blok K:14 No:440 Bakirkoy Istanbul 35790",
    "addr:housenumber":"14 no 440",
    "addr:postcode":"35790",
    "addr:street":"A-1;Bakirkoy Istanbul",
    "iso:country":"TR",
    "sg:address":"Ist.d?ya Tic.merk.cobancesme Kavsagi A-1 Blok K:14 No:440",
    "sg:city":"Bakirkoy",
    "sg:classifiers":[
        {
            "category":"Shopping",
            "subcategory":"Clothing, Apparel, & Fashions",
            "type":"Retail Goods"
        }
    ],
    "sg:phone":"+90 2124656956729",
    "sg:postcode":"35790",
    "sg:province":"Istanbul",
    "sg:tags":[
        "ready",
        "wear"
    ],
    "wof:name":"Subem Tekstil San.tic.a.s",
    "wof:placetype":"venue"
},
  "geometry": {"coordinates":[28.9759254456,41.0123786926],"type":"Point"}
}