{
  "type": "Feature",
  "properties": {
    "addr:full":"Haramidere San. Sitesi F.blok No:301 Avcilar Istanbul 01350",
    "addr:housenumber":"301",
    "addr:postcode":"01350",
    "addr:street":"F.Blok No;Istanbul",
    "iso:country":"TR",
    "sg:address":"Haramidere San. Sitesi F.blok No:301",
    "sg:city":"Avcilar",
    "sg:classifiers":[
        {
            "category":"Manufacturing",
            "subcategory":"Textiles",
            "type":"Manufacturing & Wholesale Goods"
        }
    ],
    "sg:phone":"+90 212 422 0438",
    "sg:postcode":"01350",
    "sg:province":"Istanbul",
    "sg:tags":[
        "sizing",
        "dye"
    ],
    "wof:name":"Aykur Empirme Tekstil Ltd.sti.",
    "wof:placetype":"venue"
},
  "geometry": {"coordinates":[28.9861831665,41.0408554077],"type":"Point"}
}