{
  "type": "Feature",
  "properties": {
    "addr:full":"Nisanca Mah. Nisanca Yokusu Sok. No:19 Laleli Koska Cad. Mesih Pasa Mah. No:16 Laleli Osmangazi Istanbul 46050",
    "addr:housenumber":"no 19;16",
    "addr:postcode":"46050",
    "addr:street":"Nisanca Mah. Nisanca Yokusu Sok.;Koska Cad. Mesih Pasa Mah. No",
    "iso:country":"TR",
    "sg:address":"Nisanca Mah. Nisanca Yokusu Sok. No:19 Laleli Koska Cad. Mesih Pasa Mah. No:16 Laleli",
    "sg:city":"Osmangazi",
    "sg:classifiers":[
        {
            "category":"Manufacturing",
            "subcategory":"Leather Goods",
            "type":"Manufacturing & Wholesale Goods"
        }
    ],
    "sg:phone":"+90 212 517 4330",
    "sg:postcode":"46050",
    "sg:province":"Istanbul",
    "wof:name":"Demiroklar Deri Urunleri Ithalat Ihracat Ticaret Ltd.sti.",
    "wof:placetype":"venue"
},
  "geometry": {"coordinates":[28.9759254456,41.0123786926],"type":"Point"}
}