{
  "type": "Feature",
  "properties": {
    "iso:country":"TR",
    "sg:address":"Bahariye Cad. Sakizgulu Sok. Beyazsaray Apt. No:34/2 Kadikoy",
    "sg:city":"Beyoglu",
    "sg:classifiers":[
        {
            "category":"Professional",
            "subcategory":"Detective & Security Services",
            "type":"Services"
        }
    ],
    "sg:phone":"+90 2163304005729",
    "sg:postcode":"46810",
    "sg:province":"Istanbul",
    "sg:tags":[
        "material"
    ],
    "wof:name":"Kvs Guvenlik Sistemleri San.tic. Ltd.sti.",
    "wof:placetype":"venue"
},
  "geometry": {"coordinates":[28.975925,41.012379],"type":"Point"}
}