{
  "type": "Feature",
  "properties": {
    "iso:country":"TR",
    "sg:address":"Hastane. ?arsisi. No:12 Kizilay",
    "sg:city":"Haramidere/avcilar",
    "sg:orig_category":"Printinh House",
    "sg:phone":"+90 312 435 2211",
    "sg:postcode":"84310",
    "sg:province":"Ankara",
    "wof:name":"Ada Yayincilik",
    "wof:placetype":"venue"
},
  "geometry": {"coordinates":[32.8581619263,39.9323348999],"type":"Point"}
}