{
  "type": "Feature",
  "properties": {
    "addr:full":"Gumussuyu Cad. Karaarslan Is Hani No: 5/22 Topkapi Beylikd?? 34905 Istanbul",
    "addr:housenumber":"22",
    "addr:postcode":"34905",
    "addr:street":"Gumussuyu Cad. Karaarslan Is;No 5 /;Beylikd;?",
    "iso:country":"TR",
    "sg:address":"Gumussuyu Cad. Karaarslan Is Hani No: 5/22 Topkapi",
    "sg:city":"Beylikd?? 34905",
    "sg:classifiers":[
        {
            "category":"Manufacturing",
            "subcategory":"Tools & Machinery",
            "type":"Manufacturing & Wholesale Goods"
        }
    ],
    "sg:phone":"+90 212 482 4107",
    "sg:province":"Istanbul",
    "sg:tags":[
        "machine",
        "industry"
    ],
    "wof:name":"Dural Makina",
    "wof:placetype":"venue"
},
  "geometry": {"coordinates":[28.9759254456,41.0123786926],"type":"Point"}
}