{
  "type": "Feature",
  "properties": {
    "iso:country":"TR",
    "sg:address":"Ali Emiri 2. Sok. Birlik Apt.k:1 No:2",
    "sg:city":"Merter/g?g?en",
    "sg:classifiers":[
        {
            "category":"Banks & Credit Unions",
            "subcategory":"Financial Services",
            "type":"Services"
        }
    ],
    "sg:phone":"+90 412 228 0065",
    "sg:province":"Diyarbakir",
    "sg:tags":[
        "consultant"
    ],
    "wof:name":"S.m. Mali Musavir",
    "wof:placetype":"venue"
},
  "geometry": {"coordinates":[40.2253341675,37.9158096313],"type":"Point"}
}