{
  "type": "Feature",
  "properties": {
    "addr:full":"Yeni Mah.171.sok. No:102/a Nazilli Izmir 65600",
    "addr:housenumber":"no;/ a",
    "addr:postcode":"65600",
    "addr:street":"Nazilli Izmir",
    "iso:country":"TR",
    "sg:address":"Yeni Mah.171.sok. No:102/a",
    "sg:city":"Nazilli",
    "sg:classifiers":[
        {
            "category":"Farming",
            "subcategory":"Farm",
            "type":"Manufacturing & Wholesale Goods"
        }
    ],
    "sg:phone":"+90 232 313 3200",
    "sg:postcode":"65600",
    "sg:province":"Izmir",
    "sg:tags":[
        "agricultural",
        "product"
    ],
    "wof:name":"Karaoglu Incir Isletmesi",
    "wof:placetype":"venue"
},
  "geometry": {"coordinates":[33.4901351929,39.8290748596],"type":"Point"}
}