{
  "type": "Feature",
  "properties": {
    "addr:full":"Kizilelma Caddesi No:7 - Fatih Ikitelli Istanbul 34306",
    "addr:postcode":"34306",
    "addr:street":"Kizilelma Caddesi No 7 Fatih",
    "iso:country":"TR",
    "sg:address":"Kizilelma Caddesi No:7 - Fatih",
    "sg:city":"Ikitelli",
    "sg:classifiers":[
        {
            "category":"Banks & Credit Unions",
            "subcategory":"Investment Brokerage",
            "type":"Services"
        }
    ],
    "sg:phone":"+90 212 632 1200",
    "sg:postcode":"34306",
    "sg:province":"Istanbul",
    "sg:tags":[
        "aid",
        "material",
        "first"
    ],
    "wof:name":"Megamar Spira Tomografi G??t?eme Merkezi",
    "wof:placetype":"venue"
},
  "geometry": {"coordinates":[28.9385700226,41.0111885071],"type":"Point"}
}