{
  "type": "Feature",
  "properties": {
    "addr:full":"Gunduz Cad. Kantarma Sok. No: 7 Antakya Hatay 31000",
    "addr:housenumber":"no 7",
    "addr:postcode":"31000",
    "addr:street":"Gunduz Cad. Kantarma Sok.",
    "iso:country":"TR",
    "sg:address":"Gunduz Cad. Kantarma Sok. No: 7",
    "sg:city":"Antakya",
    "sg:classifiers":[
        {
            "category":"Farming",
            "subcategory":"Farm & Veterinary Services",
            "type":"Manufacturing & Wholesale Goods"
        }
    ],
    "sg:phone":"+90 326 213 9757",
    "sg:postcode":"31000",
    "sg:province":"Hatay",
    "sg:tags":[
        "veterinarian"
    ],
    "wof:name":"Ali Karacay",
    "wof:placetype":"venue"
},
  "geometry": {"coordinates":[36.1551704407,36.2015533447],"type":"Point"}
}