{
  "type": "Feature",
  "properties": {
    "addr:full":"Fevziye Cad.38 Laleli Istanbul 24300",
    "addr:postcode":"24300",
    "iso:country":"TR",
    "sg:address":"Fevziye Cad.38",
    "sg:city":"Laleli",
    "sg:orig_category":"Hotels: Motels",
    "sg:phone":"+90 21252810212",
    "sg:postcode":"24300",
    "sg:province":"Istanbul",
    "wof:name":"Florida Hotel",
    "wof:placetype":"venue"
},
  "geometry": {"coordinates":[28.9574127197,41.0124473572],"type":"Point"}
}