{
  "type": "Feature",
  "properties": {
    "iso:country":"TR",
    "sg:address":"Kocayaka Ish. No:105 D?t?sme Mev. Merkez",
    "sg:city":"K.?ekmece",
    "sg:classifiers":[
        {
            "category":"Organizations",
            "subcategory":"Membership Organization",
            "type":"Services"
        }
    ],
    "sg:phone":"+90 258 264 6548",
    "sg:postcode":"34670",
    "sg:province":"Denizli",
    "wof:name":"Denizli Iplik Tuccar. Yard. Yasat. Dernegi",
    "wof:placetype":"venue"
},
  "geometry": {"coordinates":[29.0788803101,37.7851867676],"type":"Point"}
}