{
  "type": "Feature",
  "properties": {
    "addr:full":"Yeni Toptasi Cd.no:28 \u00dcsk\u00fcdar Istanbul 34672",
    "addr:housenumber":"28",
    "addr:postcode":"34672",
    "addr:street":"Cd.No;Istanbul",
    "iso:country":"TR",
    "sg:address":"Yeni Toptasi Cd.no:28",
    "sg:city":"\u00dcsk\u00fcdar",
    "sg:classifiers":[
        {
            "category":"Home & Garden",
            "subcategory":"Home Furnishings",
            "type":"Retail Goods"
        }
    ],
    "sg:phone":"+90 216 310 5045",
    "sg:postcode":"34672",
    "sg:province":"Istanbul",
    "sg:tags":[
        "-curtains",
        "upholstery"
    ],
    "wof:name":"Istanbul ?eyiz Mefrusat San. Tic. Ltd. Sti.",
    "wof:placetype":"venue"
},
  "geometry": {"coordinates":[29.0154418945,41.0218315125],"type":"Point"}
}