{
  "type": "Feature",
  "properties": {
    "iso:country":"TR",
    "sg:address":"Beylikduzu Buyuksehir Sit. B13 D:21 B.?ekmece",
    "sg:city":"G?ztepe",
    "sg:classifiers":[
        {
            "category":"Banks & Credit Unions",
            "subcategory":"Investment Brokerage",
            "type":"Services"
        }
    ],
    "sg:phone":"+90 212 873 7468",
    "sg:province":"Istanbul",
    "sg:tags":[
        "-",
        "export",
        "import"
    ],
    "wof:name":"Busra Dis Tic.",
    "wof:placetype":"venue"
},
  "geometry": {"coordinates":[28.9861793518,41.040851593],"type":"Point"}
}