{
  "type": "Feature",
  "properties": {
    "addr:full":"Eregli Sk. No:49/2 Siteler L?eburgaz Ankara",
    "addr:housenumber":"49 / 2 siteler;?",
    "addr:street":"Eregli Sk. No;L",
    "iso:country":"TR",
    "sg:address":"Eregli Sk. No:49/2 Siteler",
    "sg:city":"L?eburgaz",
    "sg:classifiers":[
        {
            "category":"Manufacturing",
            "subcategory":"Glass & Minerals",
            "type":"Manufacturing & Wholesale Goods"
        }
    ],
    "sg:phone":"+90 312 348 7792",
    "sg:province":"Ankara",
    "sg:tags":[
        "glassware"
    ],
    "wof:name":"Limca Dekoratif Cam Ayna San. Tic. A.s.",
    "wof:placetype":"venue"
},
  "geometry": {"coordinates":[32.9107933044,39.9650268555],"type":"Point"}
}