{
  "type": "Feature",
  "properties": {
    "addr:full":"Necatibey Cad. Aynali Lokanta Sok. No: 32 Karakoy Seyrantepe Istanbul 34418",
    "addr:housenumber":"no 32",
    "addr:postcode":"34418",
    "addr:street":"Necatibey Cad. Aynali Lokanta Sok.",
    "iso:country":"TR",
    "sg:address":"Necatibey Cad. Aynali Lokanta Sok. No: 32 Karakoy",
    "sg:city":"Seyrantepe",
    "sg:orig_category":"Environment Technolojy",
    "sg:phone":"+90 212 243 8636",
    "sg:postcode":"34418",
    "sg:province":"Istanbul",
    "wof:name":"Startek Aritim Sistemleri Ve Cevre Teknolojileri San.tic.ltd.sti.",
    "wof:placetype":"venue"
},
  "geometry": {"coordinates":[28.9861831665,41.0408554077],"type":"Point"}
}