{
  "type": "Feature",
  "properties": {
    "iso:country":"TR",
    "sg:address":"Acibadem Bayir Sok. No:23-b",
    "sg:city":"Uskudar",
    "sg:classifiers":[
        {
            "category":"Freight",
            "type":"Transportation"
        }
    ],
    "sg:phone":"+90 21633910793274",
    "sg:postcode":"34672",
    "sg:province":"Istanbul",
    "sg:tags":[
        "agent",
        "shipping",
        "broker"
    ],
    "wof:name":"Uzun Maritime S.a-istanbul",
    "wof:placetype":"venue"
},
  "geometry": {"coordinates":[29.049635,41.010956],"type":"Point"}
}