{
  "type": "Feature",
  "properties": {
    "addr:full":"Gazcilar Cd Abdal Sk No:72/a Mecidiyek\u00f6y Bursa",
    "addr:street":"Gazcilar;Abdal",
    "iso:country":"TR",
    "sg:address":"Gazcilar Cd Abdal Sk No:72/a",
    "sg:city":"Mecidiyek\u00f6y",
    "sg:classifiers":[
        {
            "category":"Government",
            "subcategory":"Fire Station",
            "type":"Public Place"
        }
    ],
    "sg:phone":"+90 224 220 5758",
    "sg:province":"Bursa",
    "sg:tags":[
        "decoration"
    ],
    "wof:name":"Yildirim Dekorasyon",
    "wof:placetype":"venue"
},
  "geometry": {"coordinates":[29.0398807526,40.1076583862],"type":"Point"}
}