{
  "type": "Feature",
  "properties": {
    "iso:country":"TR",
    "sg:address":"Imc 1 Blok No:1602 Unkapani",
    "sg:city":"Mersin",
    "sg:classifiers":[
        {
            "category":"Wholesale",
            "subcategory":"Medical Equipment & Supplies",
            "type":"Manufacturing & Wholesale Goods"
        }
    ],
    "sg:phone":"+90 212 513 2350",
    "sg:postcode":"52750",
    "sg:province":"Istanbul",
    "wof:name":"Cakman Tib. Cih. Ltd.",
    "wof:placetype":"venue"
},
  "geometry": {"coordinates":[28.9861831665,41.0408554077],"type":"Point"}
}