{
  "type": "Feature",
  "properties": {
    "iso:country":"TR",
    "sg:address":"Barbaros Bulvari Sinmaz Apt.no.68 Kat:4",
    "sg:city":"Kadikoy",
    "sg:classifiers":[
        {
            "category":"Airport",
            "subcategory":"International",
            "type":"Transportation"
        }
    ],
    "sg:phone":"+90 212 236 4461",
    "sg:postcode":"01370",
    "sg:province":"Istanbul",
    "wof:name":"Benli Uluslararasi Nakliyat",
    "wof:placetype":"venue"
},
  "geometry": {"coordinates":[28.9861831665,41.0408554077],"type":"Point"}
}