{
  "type": "Feature",
  "properties": {
    "iso:country":"TR",
    "sg:address":"Ismetiye Cd. No:9 Mercan",
    "sg:city":"Yildirim",
    "sg:classifiers":[
        {
            "category":"Manufacturing",
            "subcategory":"Rubber & Plastics",
            "type":"Manufacturing & Wholesale Goods"
        }
    ],
    "sg:phone":"+90 212 512 3282",
    "sg:postcode":"03300",
    "sg:province":"Istanbul",
    "sg:tags":[
        "industry"
    ],
    "wof:name":"Bayraktar Plastik Ltd. Sti.",
    "wof:placetype":"venue"
},
  "geometry": {"coordinates":[28.967086792,41.0151290894],"type":"Point"}
}