{
  "type": "Feature",
  "properties": {
    "addr:full":"Kayik? Sk. No.22/2 Merter Acipayam Istanbul 20873",
    "addr:housenumber":"2",
    "addr:postcode":"20873",
    "addr:street":"Sk. No.22 /",
    "iso:country":"TR",
    "sg:address":"Kayik? Sk. No.22/2 Merter",
    "sg:city":"Acipayam",
    "sg:classifiers":[
        {
            "category":"Shopping",
            "subcategory":"Luggage & Leather Goods",
            "type":"Retail Goods"
        }
    ],
    "sg:phone":"+90 212 506 8186",
    "sg:postcode":"20873",
    "sg:province":"Istanbul",
    "sg:tags":[
        "leather-fur",
        "wear"
    ],
    "wof:name":"Alyans Deri San.ltd.sti.",
    "wof:placetype":"venue"
},
  "geometry": {"coordinates":[28.8751049042,41.0212173462],"type":"Point"}
}