{
  "type": "Feature",
  "properties": {
    "iso:country":"TR",
    "sg:address":"A.menderes Bulv.",
    "sg:city":"Gumusler",
    "sg:classifiers":[
        {
            "category":"Shopping",
            "subcategory":"Crafts & Fabrics",
            "type":"Retail Goods"
        }
    ],
    "sg:phone":"+90 258 371 0929",
    "sg:postcode":"20085",
    "sg:province":"Denizli",
    "sg:tags":[
        "weaving"
    ],
    "wof:name":"Kocaer Tekstil A.s.",
    "wof:placetype":"venue"
},
  "geometry": {"coordinates":[29.0671253204,37.8096580505],"type":"Point"}
}