{
  "type": "Feature",
  "properties": {
    "iso:country":"TR",
    "sg:address":"Ahmet Erg?",
    "sg:city":"Alanya",
    "sg:classifiers":[
        {
            "category":"Government",
            "subcategory":"Office",
            "type":"Public Place"
        }
    ],
    "sg:phone":"+90 442 218 4972",
    "sg:postcode":"07400",
    "sg:province":"Erzurum",
    "sg:tags":[
        "municipality"
    ],
    "wof:name":"Dadaskent Belediye Baskani",
    "wof:placetype":"venue"
},
  "geometry": {"coordinates":[41.2623214722,39.9037857056],"type":"Point"}
}