{
  "type": "Feature",
  "properties": {
    "iso:country":"TR",
    "sg:address":"Postahane Mh. Esentepe Cd. No:178",
    "sg:city":"Tuzla",
    "sg:classifiers":[
        {
            "category":"Freight",
            "type":"Transportation"
        }
    ],
    "sg:phone":"+90 216 446 2056",
    "sg:postcode":"01900",
    "sg:province":"Istanbul",
    "sg:tags":[
        "agent",
        "shipping",
        "broker"
    ],
    "wof:name":"Hazar Denizcilik",
    "wof:placetype":"venue"
},
  "geometry": {"coordinates":[28.975925,41.012379],"type":"Point"}
}