{
  "type": "Feature",
  "properties": {
    "addr:full":"Tatlikuyu Hamam Sok. Ufuk Apt. No: 22/24 -3 Beyazit Beyazit Istanbul 65400",
    "addr:housenumber":"ufuk;24 -3",
    "addr:postcode":"65400",
    "addr:street":"Hamam Sok.;No 22 /",
    "iso:country":"TR",
    "sg:address":"Tatlikuyu Hamam Sok. Ufuk Apt. No: 22/24 -3 Beyazit",
    "sg:city":"Beyazit",
    "sg:classifiers":[
        {
            "category":"Manufacturing",
            "subcategory":"Leather Goods",
            "type":"Manufacturing & Wholesale Goods"
        }
    ],
    "sg:phone":"+90 212 638 7808",
    "sg:postcode":"65400",
    "sg:province":"Istanbul",
    "wof:name":"Mehmet Agca",
    "wof:placetype":"venue"
},
  "geometry": {"coordinates":[28.9759254456,41.0123786926],"type":"Point"}
}