{
  "type": "Feature",
  "properties": {
    "iso:country":"TR",
    "sg:address":"Ortabah? C. B?? Besiktas ?rs. No: 26/41 Besiktas",
    "sg:city":"Eminonu",
    "sg:orig_category":"Bijouterie",
    "sg:phone":"+90 212 261 7373",
    "sg:province":"Istanbul",
    "wof:name":"G?l?s Parf?meri & Bijuteri",
    "wof:placetype":"venue"
},
  "geometry": {"coordinates":[29.023275,41.071552],"type":"Point"}
}