{
  "type": "Feature",
  "properties": {
    "iso:country":"TR",
    "sg:address":"Istiklal Cad.no:60",
    "sg:city":"Gemlik",
    "sg:classifiers":[
        {
            "category":"Manufacturing",
            "subcategory":"Food",
            "type":"Manufacturing & Wholesale Goods"
        }
    ],
    "sg:phone":"+90 224 514 5300",
    "sg:postcode":"16600",
    "sg:province":"Bursa",
    "sg:tags":[
        "wholesaler"
    ],
    "wof:name":"Bucukogullari Gida Pazarlama Ltd.sti.",
    "wof:placetype":"venue"
},
  "geometry": {"coordinates":[29.3084774017,40.4848670959],"type":"Point"}
}