{
  "type": "Feature",
  "properties": {
    "addr:full":"100. Yil Bulvari 41/a Sokak No:1/p-2 Ostim Ankara 06374",
    "addr:housenumber":"100;41 / a;no 1 / p-2",
    "addr:postcode":"06374",
    "addr:street":"Yil Bulvari;Sokak",
    "iso:country":"TR",
    "sg:address":"100. Yil Bulvari 41/a Sokak No:1/p-2",
    "sg:city":"Ostim",
    "sg:orig_category":"Ostim Ankara",
    "sg:phone":"+90 312 354 1042",
    "sg:postcode":"06374",
    "sg:province":"Ankara",
    "wof:name":"Bronz Mak. Ve D?k?m San.",
    "wof:placetype":"venue"
},
  "geometry": {"coordinates":[32.8906364441,39.9037475586],"type":"Point"}
}