{
  "type": "Feature",
  "properties": {
    "iso:country":"TR",
    "sg:address":"Sehit Murat Cad. No:5 Resadiyekoyu-alemdag",
    "sg:city":"Mersin",
    "sg:classifiers":[
        {
            "category":"Manufacturing",
            "subcategory":"Glass & Minerals",
            "type":"Manufacturing & Wholesale Goods"
        }
    ],
    "sg:phone":"+90 216 429 3890",
    "sg:postcode":"52750",
    "sg:province":"Istanbul",
    "sg:tags":[
        "glassware"
    ],
    "wof:name":"D.k.m.",
    "wof:placetype":"venue"
},
  "geometry": {"coordinates":[29.2372608185,41.0589408875],"type":"Point"}
}