{
  "type": "Feature",
  "properties": {
    "addr:full":"Atat?rk Cad. No:406 53100 Rize",
    "addr:housenumber":"406",
    "addr:postcode":"53100",
    "addr:street":"Rk Cad. No",
    "iso:country":"TR",
    "sg:address":"Atat?rk Cad. No:406",
    "sg:city":"53100",
    "sg:classifiers":[
        {
            "category":"Shopping",
            "subcategory":"Clothing, Apparel, & Fashions",
            "type":"Retail Goods"
        }
    ],
    "sg:phone":"+90 464 217 1848",
    "sg:province":"Rize",
    "sg:tags":[
        "ready",
        "wear"
    ],
    "wof:name":"Altintas Giyim",
    "wof:placetype":"venue"
},
  "geometry": {"coordinates":[40.5214004517,41.0223999023],"type":"Point"}
}