{
  "type": "Feature",
  "properties": {
    "addr:full":"M. Sinan Cad. No:29/3 Alsancak Emek Izmir 01940",
    "addr:housenumber":"29 / 3",
    "addr:postcode":"01940",
    "addr:street":"M. Sinan Cad. No",
    "iso:country":"TR",
    "sg:address":"M. Sinan Cad. No:29/3 Alsancak",
    "sg:city":"Emek",
    "sg:classifiers":[
        {
            "category":"Manufacturing",
            "subcategory":"Chemicals & Compounds",
            "type":"Manufacturing & Wholesale Goods"
        }
    ],
    "sg:phone":"+90 232 463 3945",
    "sg:postcode":"01940",
    "sg:province":"Izmir",
    "sg:tags":[
        "pharmaceutical"
    ],
    "wof:name":"Knoll Alman Ilac Tic.",
    "wof:placetype":"venue"
},
  "geometry": {"coordinates":[27.1508235931,38.4320869446],"type":"Point"}
}