{
  "type": "Feature",
  "properties": {
    "addr:full":"Osmangazi Cad. No:94/a Bornova Harbiye Izmir 31080",
    "addr:housenumber":"94 / a",
    "addr:postcode":"31080",
    "addr:street":"Osmangazi Cad. No;Bornova Harbiye",
    "iso:country":"TR",
    "sg:address":"Osmangazi Cad. No:94/a Bornova",
    "sg:city":"Harbiye",
    "sg:classifiers":[
        {
            "category":"Shopping",
            "subcategory":"Party Supplies",
            "type":"Retail Goods"
        }
    ],
    "sg:phone":"+90 232 342 0292",
    "sg:postcode":"31080",
    "sg:province":"Izmir",
    "sg:tags":[
        "sound",
        "light",
        "system"
    ],
    "wof:name":"Gediz Elektronik",
    "wof:placetype":"venue"
},
  "geometry": {"coordinates":[27.1949481964,38.4713134766],"type":"Point"}
}