{
  "type": "Feature",
  "properties": {
    "iso:country":"TR",
    "sg:address":"Yenidogan Mah. 41/5sk No32",
    "sg:city":"Zeytinburnu",
    "sg:classifiers":[
        {
            "category":"Shopping",
            "subcategory":"Luggage & Leather Goods",
            "type":"Retail Goods"
        }
    ],
    "sg:phone":"+90 212 558 2651",
    "sg:postcode":"41000",
    "sg:province":"Istanbul",
    "sg:tags":[
        "leather-fur",
        "wear"
    ],
    "wof:name":"Netderi",
    "wof:placetype":"venue"
},
  "geometry": {"coordinates":[28.907995224,40.9903526306],"type":"Point"}
}