{
  "type": "Feature",
  "properties": {
    "iso:country":"TR",
    "sg:address":"Atat?k Cd. Ekim Pasaji No:174/1 K:4 D:8 Pasaport",
    "sg:city":"Alsancak",
    "sg:classifiers":[
        {
            "category":"Professional",
            "subcategory":"Computer Services",
            "type":"Services"
        }
    ],
    "sg:phone":"+90 232 463 7205",
    "sg:postcode":"35220",
    "sg:province":"Izmir",
    "sg:tags":[
        "application",
        "software"
    ],
    "wof:name":"Info Bilg .sistemleri A .s . (s)",
    "wof:placetype":"venue"
},
  "geometry": {"coordinates":[27.1423015594,38.4251480103],"type":"Point"}
}