{
  "type": "Feature",
  "properties": {
    "addr:full":"Akdeniz San.sit. 5032.sok.no:19 Etiler Antalya 07010",
    "addr:housenumber":"19",
    "addr:postcode":"07010",
    "addr:street":"Etiler",
    "iso:country":"TR",
    "sg:address":"Akdeniz San.sit. 5032.sok.no:19",
    "sg:city":"Etiler",
    "sg:classifiers":[
        {
            "category":"Manufacturing",
            "subcategory":"Wood Products",
            "type":"Manufacturing & Wholesale Goods"
        }
    ],
    "sg:phone":"+90 242 221 1596",
    "sg:postcode":"07010",
    "sg:province":"Antalya",
    "sg:tags":[
        "forest"
    ],
    "wof:name":"Akdeniz Kerestecilik Entegre Kurutma Ltd.sti.",
    "wof:placetype":"venue"
},
  "geometry": {"coordinates":[30.6947536469,36.9024467468],"type":"Point"}
}