{
  "type": "Feature",
  "properties": {
    "addr:full":"Selvili Sok. 15/3 4.levent Istanbul",
    "addr:housenumber":"15 / 3 4.levent",
    "addr:street":"Selvili Sok.",
    "iso:country":"TR",
    "sg:address":"Selvili Sok. 15/3",
    "sg:city":"4.levent",
    "sg:classifiers":[
        {
            "category":"Freight",
            "type":"Transportation"
        }
    ],
    "sg:phone":"+90 212 281 0300",
    "sg:province":"Istanbul",
    "sg:tags":[
        "cargo",
        "air"
    ],
    "wof:name":"Pilot Havacilik Hizmetleri Ve Turizm Ltd.sti.",
    "wof:placetype":"venue"
},
  "geometry": {"coordinates":[29.0830898285,40.9578132629],"type":"Point"}
}