{
  "type": "Feature",
  "properties": {
    "iso:country":"TR",
    "sg:address":"Zafer Mh. G?l?sk. No:8",
    "sg:city":"Emin\u00f6n\u00fc/Ca\u011falo\u011flu",
    "sg:classifiers":[
        {
            "category":"Shopping",
            "subcategory":"Stationery & Office Supplies",
            "type":"Retail Goods"
        }
    ],
    "sg:phone":"+90 222 322 4742",
    "sg:postcode":"34460",
    "sg:province":"Eskisehir",
    "sg:tags":[
        "paper"
    ],
    "wof:name":"?z?etin Kagit?ilik Ltd. Sti.",
    "wof:placetype":"venue"
},
  "geometry": {"coordinates":[30.5306835175,39.7762985229],"type":"Point"}
}