{
  "type": "Feature",
  "properties": {
    "addr:full":"Mimar Sinan Cad 2/a Isparta 32100 32000",
    "addr:housenumber":"2 / a",
    "addr:postcode":"32100 32000",
    "addr:street":"Mimar Sinan Cad",
    "iso:country":"TR",
    "sg:address":"Mimar Sinan Cad 2/a",
    "sg:city":"Isparta",
    "sg:classifiers":[
        {
            "category":"Banks & Credit Unions",
            "subcategory":"Bank",
            "type":"Services"
        }
    ],
    "sg:phone":"+90 246 218 1095",
    "sg:postcode":"32000",
    "sg:province":"32100",
    "wof:name":"Esbank Eskisehir, Bankasi Tas",
    "wof:placetype":"venue"
},
  "geometry": {"coordinates":[30.552948,37.76823],"type":"Point"}
}