{
  "type": "Feature",
  "properties": {
    "addr:full":"Cumhuriyet Mah.dr.kamil Sok. No:21 Silifke Sakarya 33940",
    "addr:housenumber":"no 21",
    "addr:postcode":"33940",
    "addr:street":"Mah.Dr.Kamil Sok.;Silifke Sakarya",
    "iso:country":"TR",
    "sg:address":"Cumhuriyet Mah.dr.kamil Sok. No:21",
    "sg:city":"Silifke",
    "sg:classifiers":[
        {
            "category":"Farming",
            "subcategory":"Farm & Veterinary Services",
            "type":"Manufacturing & Wholesale Goods"
        }
    ],
    "sg:phone":"+90 264 273 2803",
    "sg:postcode":"33940",
    "sg:province":"Sakarya",
    "sg:tags":[
        "veterinarian"
    ],
    "wof:name":"Kucuk Hayvan Klinigi",
    "wof:placetype":"venue"
},
  "geometry": {"coordinates":[30.3968219757,40.7791366577],"type":"Point"}
}