{
  "type": "Feature",
  "properties": {
    "addr:full":"Emirhan Cd. Barbaros Sk. No:2/d Besiktas Istanbul 75200",
    "addr:housenumber":"/ d",
    "addr:postcode":"75200",
    "addr:street":"Emirhan Cd.;Sk. No 2",
    "iso:country":"TR",
    "sg:address":"Emirhan Cd. Barbaros Sk. No:2/d",
    "sg:city":"Besiktas",
    "sg:classifiers":[
        {
            "category":"Shopping",
            "subcategory":"Florist",
            "type":"Retail Goods"
        }
    ],
    "sg:phone":"+90 212 227 2143",
    "sg:postcode":"75200",
    "sg:province":"Istanbul",
    "sg:tags":[
        "flower"
    ],
    "wof:name":"Clivia ?i?ek Galeri.",
    "wof:placetype":"venue"
},
  "geometry": {"coordinates":[29.0029506683,41.0513763428],"type":"Point"}
}