{
  "type": "Feature",
  "properties": {
    "addr:full":"Osmaniye Mah. Yenisehir Cad. No:4 Gemlik Bursa 16600",
    "addr:postcode":"16600",
    "addr:street":"Mah. Yenisehir Cad. No 4 Gemlik Bursa",
    "iso:country":"TR",
    "sg:address":"Osmaniye Mah. Yenisehir Cad. No:4",
    "sg:city":"Gemlik",
    "sg:classifiers":[
        {
            "category":"Farming",
            "subcategory":"Farm & Veterinary Services",
            "type":"Manufacturing & Wholesale Goods"
        }
    ],
    "sg:phone":"+90 224 513 1112",
    "sg:postcode":"16600",
    "sg:province":"Bursa",
    "sg:tags":[
        "veterinarian"
    ],
    "wof:name":"Cevdet Tosun",
    "wof:placetype":"venue"
},
  "geometry": {"coordinates":[29.5138607025,40.107170105],"type":"Point"}
}