{
  "type": "Feature",
  "properties": {
    "iso:country":"TR",
    "sg:address":"Intizam Mah.tabak Sok. No:70/a",
    "sg:city":"Bostanci",
    "sg:classifiers":[
        {
            "category":"Manufacturing",
            "subcategory":"Building Materials",
            "type":"Manufacturing & Wholesale Goods"
        }
    ],
    "sg:phone":"+90 224 272 4540",
    "sg:postcode":"25900",
    "sg:province":"Bursa",
    "sg:tags":[
        "lifts-elevators"
    ],
    "wof:name":"Asar Asansor Makine Ins San Ve Tic As",
    "wof:placetype":"venue"
},
  "geometry": {"coordinates":[29.0551548004,40.1938476562],"type":"Point"}
}