{
  "type": "Feature",
  "properties": {
    "addr:full":"Gursel Mah. Funda Sok. No:7 Kat:2 Okmeydani Istanbul 43050",
    "addr:housenumber":"no 7;2",
    "addr:postcode":"43050",
    "addr:street":"Gursel Mah. Funda Sok.;Kat",
    "iso:country":"TR",
    "sg:address":"Gursel Mah. Funda Sok. No:7 Kat:2",
    "sg:city":"Okmeydani",
    "sg:classifiers":[
        {
            "category":"Professional",
            "subcategory":"Employment Agencies",
            "type":"Services"
        }
    ],
    "sg:phone":"+90 212 320 2440",
    "sg:postcode":"43050",
    "sg:province":"Istanbul",
    "sg:tags":[
        "personnel"
    ],
    "wof:name":"Baris Turizm Organizasyon Tasimacilik & Tic. Ltd.sti.",
    "wof:placetype":"venue"
},
  "geometry": {"coordinates":[28.9759254456,41.0123786926],"type":"Point"}
}