{
  "type": "Feature",
  "properties": {
    "addr:full":"Haciveli Camii Cad. No:46 Yenibosna Gaziantep 43270",
    "addr:housenumber":"no 46",
    "addr:postcode":"43270",
    "addr:street":"Cad.;Yenibosna Gaziantep",
    "iso:country":"TR",
    "sg:address":"Haciveli Camii Cad. No:46",
    "sg:city":"Yenibosna",
    "sg:classifiers":[
        {
            "category":"Shopping",
            "subcategory":"Clothing, Apparel, & Fashions",
            "type":"Retail Goods"
        }
    ],
    "sg:phone":"+90 342 234 5962",
    "sg:postcode":"43270",
    "sg:province":"Gaziantep",
    "sg:tags":[
        "men",
        "wear"
    ],
    "wof:name":"Suat Gomlekleri",
    "wof:placetype":"venue"
},
  "geometry": {"coordinates":[37.3761024475,37.0629463196],"type":"Point"}
}