{
  "type": "Feature",
  "properties": {
    "iso:country":"TR",
    "sg:address":"B?l? Sk. No:36/3 K.dere",
    "sg:city":"Yenimahalle",
    "sg:classifiers":[
        {
            "category":"Home & Garden",
            "subcategory":"Kitchen Supply",
            "type":"Retail Goods"
        }
    ],
    "sg:phone":"+90 312 428 5473",
    "sg:postcode":"15030",
    "sg:province":"Ankara",
    "sg:tags":[
        "wardrobe"
    ],
    "wof:name":"Ekip Ins. Tic. A.s.",
    "wof:placetype":"venue"
},
  "geometry": {"coordinates":[34.0169525146,38.351726532],"type":"Point"}
}