{
  "type": "Feature",
  "properties": {
    "iso:country":"TR",
    "sg:address":"Resitpasa,sirin Sk.no26/4",
    "sg:city":"Emirgan",
    "sg:classifiers":[
        {
            "category":"Freight",
            "type":"Transportation"
        }
    ],
    "sg:phone":"+90 212 277 8197",
    "sg:postcode":"61570",
    "sg:province":"Istanbul",
    "sg:tags":[
        "agent",
        "shipping",
        "broker"
    ],
    "wof:name":"Gursoylar Deniz Nakl.ltd.sti.",
    "wof:placetype":"venue"
},
  "geometry": {"coordinates":[28.975925,41.012379],"type":"Point"}
}