{
  "type": "Feature",
  "properties": {
    "addr:full":"Perpa Tic. Merk. B Blok K:11 No:1680 Okmeydani \u00dcmraniye Istanbul",
    "addr:housenumber":"blok k 11 no 1680",
    "addr:street":"Okmeydani",
    "iso:country":"TR",
    "sg:address":"Perpa Tic. Merk. B Blok K:11 No:1680 Okmeydani",
    "sg:city":"\u00dcmraniye",
    "sg:classifiers":[
        {
            "category":"Wholesale",
            "subcategory":"Machinery & Supplies",
            "type":"Manufacturing & Wholesale Goods"
        }
    ],
    "sg:phone":"+90 212 222 0607",
    "sg:province":"Istanbul",
    "sg:tags":[
        "press",
        "hydraulic"
    ],
    "wof:name":"Hidropar Hidrolik Pnomatik Muh. Mak. San.tic. Ltd. Sti.",
    "wof:placetype":"venue"
},
  "geometry": {"coordinates":[28.9861793518,41.040851593],"type":"Point"}
}