{
  "type": "Feature",
  "properties": {
    "addr:full":"Kuzey Mah. Cahit Zrifoglu Cad. B?y?k?ekmece Kocaeli 34900",
    "addr:housenumber":"b ? y ? k ?",
    "addr:postcode":"34900",
    "addr:street":"Mah. Cahit Zrifoglu Cad.;Ekmece Kocaeli",
    "iso:country":"TR",
    "sg:address":"Kuzey Mah. Cahit Zrifoglu Cad.",
    "sg:city":"B?y?k?ekmece",
    "sg:classifiers":[
        {
            "category":"Building & Trades",
            "subcategory":"Plumbing",
            "type":"Services"
        }
    ],
    "sg:phone":"+90 262 527 5424",
    "sg:postcode":"34900",
    "sg:province":"Kocaeli",
    "wof:name":"Aktif Aritma Teknolojileri Ltd. Sti.",
    "wof:placetype":"venue"
},
  "geometry": {"coordinates":[29.7917976379,40.7595176697],"type":"Point"}
}