{
  "type": "Feature",
  "properties": {
    "iso:country":"TR",
    "sg:address":"Incirli Cad. No.29",
    "sg:city":"Incirli",
    "sg:classifiers":[
        {
            "category":"Farming",
            "subcategory":"Farm",
            "type":"Manufacturing & Wholesale Goods"
        }
    ],
    "sg:phone":"+90 212 572 6872",
    "sg:postcode":"01920",
    "sg:province":"Istanbul",
    "sg:tags":[
        "agricultural",
        "product"
    ],
    "wof:name":"Denizhan Tarim ?rl. A.s.",
    "wof:placetype":"venue"
},
  "geometry": {"coordinates":[28.8722896576,40.9851493835],"type":"Point"}
}