{
  "type": "Feature",
  "properties": {
    "addr:full":"Yukari Mah. Bahar Sok. Emin Bey Apt. No:5/a Kartal Okmeydani Istanbul 34384",
    "addr:housenumber":"a",
    "addr:postcode":"34384",
    "addr:street":"Yukari Mah. Bahar Sok.;No 5 /",
    "iso:country":"TR",
    "sg:address":"Yukari Mah. Bahar Sok. Emin Bey Apt. No:5/a Kartal",
    "sg:city":"Okmeydani",
    "sg:orig_category":"Orthopedical Materials",
    "sg:phone":"+90 216 387 6564",
    "sg:postcode":"34384",
    "sg:province":"Istanbul",
    "wof:name":"Promer Ortopedi Ltd.sti.",
    "wof:placetype":"venue"
},
  "geometry": {"coordinates":[29.2215099335,40.8996009827],"type":"Point"}
}