{
  "type": "Feature",
  "properties": {
    "iso:country":"TR",
    "sg:address":"E-5 Karayolu ?st?no:51 Gebze",
    "sg:city":"Karak\u00f6y",
    "sg:classifiers":[
        {
            "category":"Manufacturing",
            "subcategory":"Textiles",
            "type":"Manufacturing & Wholesale Goods"
        }
    ],
    "sg:phone":"+90 212 653 2556",
    "sg:postcode":"34110",
    "sg:province":"Istanbul",
    "sg:tags":[
        "fiberglass",
        "polyester"
    ],
    "wof:name":"Adlin Polyester Ins. Malz. San. Tic",
    "wof:placetype":"venue"
},
  "geometry": {"coordinates":[29.4511299133,40.7994041443],"type":"Point"}
}