{
  "type": "Feature",
  "properties": {
    "iso:country":"TR",
    "sg:address":"Kadiyoran Cad.",
    "sg:city":"Buyukada",
    "sg:orig_category":"Hotels: Motels",
    "sg:phone":"+90 216 382 6857",
    "sg:postcode":"28300",
    "sg:province":"Istanbul",
    "wof:name":"Ideal Pansiyon",
    "wof:placetype":"venue"
},
  "geometry": {"coordinates":[29.1895561218,40.8941345215],"type":"Point"}
}