{
  "type": "Feature",
  "properties": {
    "addr:full":"Abide-i H?riyet Cd. N.249 Murat Apt.d.1 K.1 - Sisli Merkez Istanbul 43020",
    "addr:housenumber":"n.249 murat apt.d.1 k.1",
    "addr:postcode":"43020",
    "addr:street":"Riyet Cd.",
    "iso:country":"TR",
    "sg:address":"Abide-i H?riyet Cd. N.249 Murat Apt.d.1 K.1 - Sisli",
    "sg:city":"Merkez",
    "sg:classifiers":[
        {
            "category":"Health Services",
            "subcategory":"Clinic",
            "type":"Services"
        }
    ],
    "sg:phone":"+90 212 233 6235",
    "sg:postcode":"43020",
    "sg:province":"Istanbul",
    "wof:name":"?zel Kardiyoson G?.merk.",
    "wof:placetype":"venue"
},
  "geometry": {"coordinates":[28.9861831665,41.0408554077],"type":"Point"}
}