{
  "type": "Feature",
  "properties": {
    "addr:full":"Oto San. Sit. Sul. Selim Cd. Basamak Sk. No:12 4.levent Mersin Istanbul 52750",
    "addr:housenumber":"4.levent",
    "addr:postcode":"52750",
    "addr:street":"Selim Cd. Basamak Sk. No 12",
    "iso:country":"TR",
    "sg:address":"Oto San. Sit. Sul. Selim Cd. Basamak Sk. No:12 4.levent",
    "sg:city":"Mersin",
    "sg:classifiers":[
        {
            "category":"Wholesale",
            "subcategory":"Home Furnishings",
            "type":"Manufacturing & Wholesale Goods"
        }
    ],
    "sg:phone":"+90 212 272 3422",
    "sg:postcode":"52750",
    "sg:province":"Istanbul",
    "sg:tags":[
        "furniture"
    ],
    "wof:name":"Yapdek",
    "wof:placetype":"venue"
},
  "geometry": {"coordinates":[28.9861831665,41.0408554077],"type":"Point"}
}