{
  "type": "Feature",
  "properties": {
    "addr:full":"Kisla Cad.top?lar Oto San.sit. D Blok No:97 Topcular Iskenderun Istanbul 31200",
    "addr:housenumber":"blok no 97",
    "addr:postcode":"31200",
    "iso:country":"TR",
    "sg:address":"Kisla Cad.top?lar Oto San.sit. D Blok No:97 Topcular",
    "sg:city":"Iskenderun",
    "sg:classifiers":[
        {
            "category":"Manufacturing",
            "subcategory":"Metals",
            "type":"Manufacturing & Wholesale Goods"
        }
    ],
    "sg:phone":"+90 212 612 0010",
    "sg:postcode":"31200",
    "sg:province":"Istanbul",
    "sg:tags":[
        "industry"
    ],
    "wof:name":"Kacmaz Metal San.tic.ltd.sti.",
    "wof:placetype":"venue"
},
  "geometry": {"coordinates":[28.9759254456,41.0123786926],"type":"Point"}
}