{
  "type": "Feature",
  "properties": {
    "addr:full":"Tesvikiye, Haci Emin Efendi Sokak, No. 5/2 Saadet Istanbul 80200",
    "addr:housenumber":"no. 5 / 2",
    "addr:postcode":"80200",
    "addr:street":"Efendi Sokak",
    "iso:country":"TR",
    "sg:address":"Tesvikiye, Haci Emin Efendi Sokak, No. 5/2 Saadet",
    "sg:city":"Istanbul",
    "sg:classifiers":[
        {
            "category":"Travel",
            "subcategory":"Travel Agent",
            "type":"Entertainment"
        }
    ],
    "sg:phone":"+90 902 122 3432",
    "sg:province":"80200",
    "sg:website":"www.istanbulreservations.net",
    "wof:name":"Saten Travel Agency",
    "wof:placetype":"venue"
},
  "geometry": {"coordinates":[32.4852905273,37.8587646484],"type":"Point"}
}