{
  "type": "Feature",
  "properties": {
    "iso:country":"TR",
    "sg:address":"Meseli Sk. 38/1 4. Levent",
    "sg:city":"B\u00fcy\u00fck\u00e7ekmece",
    "sg:orig_category":"Aluminium Carpentary",
    "sg:phone":"+90 212 282 8256",
    "sg:postcode":"34905",
    "sg:province":"Istanbul",
    "wof:name":"Fibrobeton",
    "wof:placetype":"venue"
},
  "geometry": {"coordinates":[29.0097522736,41.0873680115],"type":"Point"}
}