{
  "type": "Feature",
  "properties": {
    "iso:country":"TR",
    "sg:address":"Yeniyol Mah. Ilica Is Merkezi Kat.2",
    "sg:city":"G.o.pasa",
    "sg:classifiers":[
        {
            "category":"Shopping",
            "subcategory":"Computers & Home Electronics",
            "type":"Retail Goods"
        }
    ],
    "sg:phone":"+90 364 212 7905",
    "sg:province":"?orum",
    "sg:tags":[
        "animal"
    ],
    "wof:name":"Alfa Sus Baligi Uretim Ltd.sti.",
    "wof:placetype":"venue"
},
  "geometry": {"coordinates":[41.6800003052,41.3624992371],"type":"Point"}
}