{
  "type": "Feature",
  "properties": {
    "addr:full":"Tuzcular 3. Is Mrkz. Altkaynarca Pendik Istanbul 34916",
    "addr:housenumber":"3",
    "addr:postcode":"34916",
    "addr:street":"Tuzcular",
    "iso:country":"TR",
    "sg:address":"Tuzcular 3. Is Mrkz. Altkaynarca",
    "sg:city":"Pendik",
    "sg:classifiers":[
        {
            "category":"Shopping",
            "subcategory":"Crafts & Fabrics",
            "type":"Retail Goods"
        }
    ],
    "sg:phone":"+90 216 483 3801",
    "sg:postcode":"34916",
    "sg:province":"Istanbul",
    "sg:tags":[
        "weaving"
    ],
    "wof:name":"Gen? Tekstil San. Tic. Ltd. Sti",
    "wof:placetype":"venue"
},
  "geometry": {"coordinates":[28.9759254456,41.0123786926],"type":"Point"}
}