{
  "type": "Feature",
  "properties": {
    "addr:full":"Bagdat Cd. Gedik Ismerk. No:126 K:3 D:28 Maltepe Sisli Istanbul 65710",
    "addr:housenumber":"126 k 3 d 28",
    "addr:postcode":"65710",
    "addr:street":"Bagdat Cd. Gedik Ismerk. No;Maltepe Sisli",
    "iso:country":"TR",
    "sg:address":"Bagdat Cd. Gedik Ismerk. No:126 K:3 D:28 Maltepe",
    "sg:city":"Sisli",
    "sg:orig_category":"Beaty Parlors",
    "sg:phone":"+90 216 399 4338",
    "sg:postcode":"65710",
    "sg:province":"Istanbul",
    "wof:name":"Sindy G?zellik-ll",
    "wof:placetype":"venue"
},
  "geometry": {"coordinates":[28.975925,41.012379],"type":"Point"}
}