{
  "type": "Feature",
  "properties": {
    "iso:country":"TR",
    "sg:address":"Sehitler Cad. No:31 Alsancak Stad Krs",
    "sg:city":"Alsancak",
    "sg:classifiers":[
        {
            "category":"Building & Trades",
            "subcategory":"Electrical",
            "type":"Services"
        }
    ],
    "sg:phone":"+90 232 463 9882",
    "sg:postcode":"01365",
    "sg:province":"Izmir",
    "sg:tags":[
        "equipment",
        "lighting"
    ],
    "wof:name":"Artez Aydinlatma",
    "wof:placetype":"venue"
},
  "geometry": {"coordinates":[27.1296863556,38.4186973572],"type":"Point"}
}