{
  "type": "Feature",
  "properties": {
    "addr:full":"Ikitelli Organize Sanayi B?gesi Eskoop Sanayi Sitesi C-2 Blok No:49-51 Ikitelli/K\u00fc\u00e7\u00fck\u00e7ekmece Istanbul 34670",
    "addr:housenumber":"?;c-2 blok no 49-51",
    "addr:postcode":"34670",
    "addr:street":"Organize Sanayi B;Eskoop Sanayi Sitesi",
    "iso:country":"TR",
    "sg:address":"Ikitelli Organize Sanayi B?gesi Eskoop Sanayi Sitesi C-2 Blok No:49-51",
    "sg:city":"Ikitelli/K\u00fc\u00e7\u00fck\u00e7ekmece",
    "sg:classifiers":[
        {
            "category":"Autos & Motor Vehicles",
            "subcategory":"Auto Supplies",
            "type":"Retail Goods"
        }
    ],
    "sg:phone":"+90 212 549 6034",
    "sg:postcode":"34670",
    "sg:province":"Istanbul",
    "sg:tags":[
        "accessory"
    ],
    "wof:name":"Ay-san Cant Kapaklari Ve ?elik San.ltd.sti.",
    "wof:placetype":"venue"
},
  "geometry": {"coordinates":[28.9674797058,41.0096588135],"type":"Point"}
}