{
  "type": "Feature",
  "properties": {
    "addr:full":"K?ahya Yolu 5.km. Alsancak Eskisehir 01365",
    "addr:housenumber":"5.km",
    "addr:postcode":"01365",
    "addr:street":"Ahya Yolu;Eskisehir",
    "iso:country":"TR",
    "sg:address":"K?ahya Yolu 5.km.",
    "sg:city":"Alsancak",
    "sg:classifiers":[
        {
            "category":"Wholesale",
            "subcategory":"Farm Supplies",
            "type":"Manufacturing & Wholesale Goods"
        }
    ],
    "sg:phone":"+90 222 324 1175",
    "sg:postcode":"01365",
    "sg:province":"Eskisehir",
    "sg:tags":[
        "feed",
        "industry"
    ],
    "wof:name":"Esyem Eskisehir Yem Sanayii A.s.",
    "wof:placetype":"venue"
},
  "geometry": {"coordinates":[30.5175457001,39.7700805664],"type":"Point"}
}