{
  "type": "Feature",
  "properties": {
    "addr:full":"1657 .sok. No:9/4 Bayrakli Mersin Izmir 52750",
    "addr:housenumber":"no 9 / 4",
    "addr:postcode":"1657;52750",
    "addr:street":"Sok.;Bayrakli Mersin",
    "iso:country":"TR",
    "sg:address":"1657 .sok. No:9/4 Bayrakli",
    "sg:city":"Mersin",
    "sg:classifiers":[
        {
            "category":"Manufacturing",
            "subcategory":"Tools & Machinery",
            "type":"Manufacturing & Wholesale Goods"
        }
    ],
    "sg:phone":"+90 232 341 1933",
    "sg:postcode":"52750",
    "sg:province":"Izmir",
    "sg:tags":[
        "machine",
        "industry"
    ],
    "wof:name":"Safak Makina Model Sanayii",
    "wof:placetype":"venue"
},
  "geometry": {"coordinates":[27.1602458954,38.4686088562],"type":"Point"}
}