{
  "type": "Feature",
  "properties": {
    "addr:full":"Kirklar Cad. Altay Sok. No:18 Merzifon Amasya 05300",
    "addr:housenumber":"no 18",
    "addr:postcode":"05300",
    "addr:street":"Kirklar Cad. Altay Sok.",
    "iso:country":"TR",
    "sg:address":"Kirklar Cad. Altay Sok. No:18",
    "sg:city":"Merzifon",
    "sg:classifiers":[
        {
            "category":"Building & Trades",
            "subcategory":"Electrical",
            "type":"Services"
        }
    ],
    "sg:phone":"+90 358 513 0100",
    "sg:postcode":"05300",
    "sg:province":"Amasya",
    "sg:tags":[
        "equipment",
        "lighting"
    ],
    "wof:name":"Meraysan Aydinlatma Turker Mak. Muh. Mus. Ltd.sti.",
    "wof:placetype":"venue"
},
  "geometry": {"coordinates":[29.271987915,40.9809036255],"type":"Point"}
}