{
  "type": "Feature",
  "properties": {
    "addr:full":"Fahrettin Kerim G?ay Cad.no:57 - Kadik? 07100 Istanbul",
    "addr:housenumber":"?;57;?",
    "addr:postcode":"07100",
    "addr:street":"Fahrettin Kerim G;Cad.No",
    "iso:country":"TR",
    "sg:address":"Fahrettin Kerim G?ay Cad.no:57 - Kadik?",
    "sg:city":"07100",
    "sg:classifiers":[
        {
            "category":"Health Services",
            "subcategory":"Clinic",
            "type":"Services"
        }
    ],
    "sg:phone":"+90 216 348 4027",
    "sg:province":"Istanbul",
    "wof:name":"Kasdav Saglik Merkezi",
    "wof:placetype":"venue"
},
  "geometry": {"coordinates":[29.0748081207,40.9804801941],"type":"Point"}
}