{
  "type": "Feature",
  "properties": {
    "addr:full":"Serdar ?. Cd. No:21 Dolapdere Istanbul 42030",
    "addr:housenumber":"?;no 21",
    "addr:postcode":"42030",
    "addr:street":"Cd.;Istanbul",
    "iso:country":"TR",
    "sg:address":"Serdar ?. Cd. No:21",
    "sg:city":"Dolapdere",
    "sg:classifiers":[
        {
            "category":"Home & Garden",
            "subcategory":"Household Appliances",
            "type":"Retail Goods"
        }
    ],
    "sg:phone":"+90 212 254 0552",
    "sg:postcode":"42030",
    "sg:province":"Istanbul",
    "sg:tags":[
        "conditioner",
        "air"
    ],
    "wof:name":"G?rb?z Sog.",
    "wof:placetype":"venue"
},
  "geometry": {"coordinates":[29.2686424255,40.9749259949],"type":"Point"}
}