{
  "type": "Feature",
  "properties": {
    "addr:full":"Musalla Mah. T. ?zal Bulvari No: 3 A/b ?esme Izmir",
    "addr:housenumber":"?;no 3 a / b ?",
    "addr:street":"Musalla Mah. T.;Zal Bulvari;Esme",
    "iso:country":"TR",
    "sg:address":"Musalla Mah. T. ?zal Bulvari No: 3 A/b",
    "sg:city":"?esme",
    "sg:classifiers":[
        {
            "category":"Travel",
            "subcategory":"Travel Agent",
            "type":"Entertainment"
        }
    ],
    "sg:phone":"+90 232712079871",
    "sg:province":"Izmir",
    "sg:tags":[
        "agency",
        "tourism"
    ],
    "wof:name":"Karavan Turizm (?esme/izmir Sb.)",
    "wof:placetype":"venue"
},
  "geometry": {"coordinates":[27.1422595978,38.4252090454],"type":"Point"}
}