{
  "type": "Feature",
  "properties": {
    "addr:full":"A. Ipek? Cd. No:132 Bayrampasa Yukari Dudullu Istanbul 34776",
    "addr:housenumber":"?;no;bayrampasa",
    "addr:postcode":"34776",
    "addr:street":"A.;Cd.",
    "iso:country":"TR",
    "sg:address":"A. Ipek? Cd. No:132 Bayrampasa",
    "sg:city":"Yukari Dudullu",
    "sg:classifiers":[
        {
            "category":"Manufacturing",
            "subcategory":"Tools & Machinery",
            "type":"Manufacturing & Wholesale Goods"
        }
    ],
    "sg:phone":"+90 212 501 6070",
    "sg:postcode":"34776",
    "sg:province":"Istanbul",
    "sg:tags":[
        "machine",
        "industry"
    ],
    "wof:name":"??san Makina San. Tic. Ltd. Sti.",
    "wof:placetype":"venue"
},
  "geometry": {"coordinates":[28.9051380157,41.0486373901],"type":"Point"}
}