{
  "type": "Feature",
  "properties": {
    "addr:full":"Birlik San. Sitesi 2.cad. No:54 Beylikduzu B\u00fcy\u00fck\u00e7ekmece Istanbul 34905",
    "addr:housenumber":"no 54",
    "addr:postcode":"34905",
    "iso:country":"TR",
    "sg:address":"Birlik San. Sitesi 2.cad. No:54 Beylikduzu",
    "sg:city":"B\u00fcy\u00fck\u00e7ekmece",
    "sg:classifiers":[
        {
            "category":"Home & Garden",
            "subcategory":"Hardware",
            "type":"Retail Goods"
        }
    ],
    "sg:phone":"+90 212875039697",
    "sg:postcode":"34905",
    "sg:province":"Istanbul",
    "sg:tags":[
        "compressor",
        "pump"
    ],
    "wof:name":"Universal Sizdirmazlik Ve Pompa Elemanlari San.tic.",
    "wof:placetype":"venue"
},
  "geometry": {"coordinates":[28.9759254456,41.0123786926],"type":"Point"}
}