{
  "type": "Feature",
  "properties": {
    "addr:full":"Istiklal Cad.borsa Sarayi Kat:1 No:111 Mersin G?tepe I?el",
    "addr:housenumber":"kat 1 no 111;?;?",
    "addr:street":"Mersin G;I;El",
    "iso:country":"TR",
    "sg:address":"Istiklal Cad.borsa Sarayi Kat:1 No:111 Mersin",
    "sg:city":"G?tepe",
    "sg:classifiers":[
        {
            "category":"Wholesale",
            "subcategory":"Medical Equipment & Supplies",
            "type":"Manufacturing & Wholesale Goods"
        }
    ],
    "sg:phone":"+90 324 237 7469",
    "sg:province":"I?el",
    "sg:tags":[
        "material"
    ],
    "wof:name":"Atiseri Tibbi Aromatik Bitkilir Ith.ihr.tic.san.ltd.sti.",
    "wof:placetype":"venue"
},
  "geometry": {"coordinates":[34.6096916199,36.8215293884],"type":"Point"}
}