{
  "type": "Feature",
  "properties": {
    "addr:full":"Esentepe Mah. Yunusemre Bulv. Sanko Sit. No:213 G.o.pasa Bah\u00e7elievler Istanbul 34180",
    "addr:housenumber":"sit. no 213",
    "addr:postcode":"34180",
    "addr:street":"Esentepe Mah. Yunusemre Bulv.;G.O.Pasa",
    "iso:country":"TR",
    "sg:address":"Esentepe Mah. Yunusemre Bulv. Sanko Sit. No:213 G.o.pasa",
    "sg:city":"Bah\u00e7elievler",
    "sg:classifiers":[
        {
            "category":"Manufacturing",
            "subcategory":"Chemicals & Compounds",
            "type":"Manufacturing & Wholesale Goods"
        }
    ],
    "sg:phone":"+90 212668343435",
    "sg:postcode":"34180",
    "sg:province":"Istanbul",
    "sg:tags":[
        "industry"
    ],
    "wof:name":"Yeykim Yunusemre Yapi Kimyasallari",
    "wof:placetype":"venue"
},
  "geometry": {"coordinates":[28.9861831665,41.0408554077],"type":"Point"}
}