{
  "type": "Feature",
  "properties": {
    "iso:country":"TR",
    "sg:address":"Sanayi Cad.kurucesme Sok. No:6/19 Ulus",
    "sg:city":"\u00c7ankaya",
    "sg:classifiers":[
        {
            "category":"Professional",
            "subcategory":"Detective & Security Services",
            "type":"Services"
        }
    ],
    "sg:phone":"+90 312 312 3715",
    "sg:postcode":"06550",
    "sg:province":"Ankara",
    "sg:tags":[
        "material"
    ],
    "wof:name":"Cem Anten Ve Elektrik Malzemeleri",
    "wof:placetype":"venue"
},
  "geometry": {"coordinates":[32.848999,39.941708],"type":"Point"}
}