{
  "type": "Feature",
  "properties": {
    "addr:full":"Atat?k Bulvari Vilayet Konagi 02100 Bayrampasa Adiyaman 36100",
    "addr:housenumber":"vilayet",
    "addr:postcode":"02100;36100",
    "addr:street":"K Bulvari;Adiyaman",
    "iso:country":"TR",
    "sg:address":"Atat?k Bulvari Vilayet Konagi 02100",
    "sg:city":"Bayrampasa",
    "sg:classifiers":[
        {
            "category":"Education",
            "subcategory":"University",
            "type":"Public Place"
        }
    ],
    "sg:phone":"+90 4162161021216",
    "sg:postcode":"36100",
    "sg:province":"Adiyaman",
    "sg:tags":[
        "national",
        "chief"
    ],
    "wof:name":"Adiyaman Milli Egitim M?d?rl?g?",
    "wof:placetype":"venue"
},
  "geometry": {"coordinates":[38.2764396667,37.7605743408],"type":"Point"}
}