{
  "type": "Feature",
  "properties": {
    "iso:country":"TR",
    "sg:address":"Atat?k Blok No:71 Acipayam",
    "sg:city":"Alsancak",
    "sg:classifiers":[
        {
            "category":"Wholesale",
            "subcategory":"Petroleum",
            "type":"Manufacturing & Wholesale Goods"
        }
    ],
    "sg:phone":"+90 258 518 1473",
    "sg:postcode":"01365",
    "sg:province":"Denizli",
    "wof:name":"?zcan Gaz. San.",
    "wof:placetype":"venue"
},
  "geometry": {"coordinates":[29.0864906311,37.773525238],"type":"Point"}
}