{
  "type": "Feature",
  "properties": {
    "addr:full":"Kucuk Balikli Karadeniz Sok.no:14 Tuzla Bursa 01900",
    "addr:housenumber":"14",
    "addr:postcode":"01900",
    "addr:street":"Bursa",
    "iso:country":"TR",
    "sg:address":"Kucuk Balikli Karadeniz Sok.no:14",
    "sg:city":"Tuzla",
    "sg:classifiers":[
        {
            "category":"Shopping",
            "subcategory":"Clothing, Apparel, & Fashions",
            "type":"Retail Goods"
        }
    ],
    "sg:phone":"+90 224272221516",
    "sg:postcode":"01900",
    "sg:province":"Bursa",
    "sg:tags":[
        "ready",
        "wear"
    ],
    "wof:name":"Nursel Tekstil San. Ve Tic. Ltd.sti.",
    "wof:placetype":"venue"
},
  "geometry": {"coordinates":[29.1016159058,40.2013969421],"type":"Point"}
}