{
  "type": "Feature",
  "properties": {
    "iso:country":"TR",
    "sg:address":"Konaklar Mah. Meseli Sok. No: 5 80620 Besiktas Istanbul",
    "sg:city":"Ikitelli/K\u00fc\u00e7\u00fck\u00e7ekmece",
    "sg:classifiers":[
        {
            "category":"Shopping",
            "subcategory":"Crafts & Fabrics",
            "type":"Retail Goods"
        }
    ],
    "sg:phone":"+90 212 283 8989",
    "sg:postcode":"34670",
    "sg:province":"Istanbul",
    "wof:name":"Arsan Tekstil Tic Ve San As",
    "wof:placetype":"venue"
},
  "geometry": {"coordinates":[29.0090332031,41.0872039795],"type":"Point"}
}