{
  "type": "Feature",
  "properties": {
    "addr:full":"Selimiye Mh.hamam Sk.no6/2 Dilek Apt. \u00dcsk\u00fcdar Istanbul 34672",
    "addr:housenumber":"2",
    "addr:postcode":"34672",
    "addr:street":"Dilek",
    "iso:country":"TR",
    "sg:address":"Selimiye Mh.hamam Sk.no6/2 Dilek Apt.",
    "sg:city":"\u00dcsk\u00fcdar",
    "sg:classifiers":[
        {
            "category":"Freight",
            "type":"Transportation"
        }
    ],
    "sg:phone":"+90 216 333 3587",
    "sg:postcode":"34672",
    "sg:province":"Istanbul",
    "sg:tags":[
        "agent",
        "shipping",
        "broker"
    ],
    "wof:name":"G?nes Deniz Ltd.sti.",
    "wof:placetype":"venue"
},
  "geometry": {"coordinates":[29.015442,41.021832],"type":"Point"}
}