{
  "type": "Feature",
  "properties": {
    "addr:full":"Nargileci Sok. Havanci Han No. 412 Mercan Istanbul 12600",
    "addr:housenumber":"412",
    "addr:postcode":"12600",
    "addr:street":"Nargileci Sok. Havanci Han No.",
    "iso:country":"TR",
    "sg:address":"Nargileci Sok. Havanci Han No. 412",
    "sg:city":"Mercan",
    "sg:classifiers":[
        {
            "category":"Manufacturing",
            "subcategory":"Building Materials",
            "type":"Manufacturing & Wholesale Goods"
        }
    ],
    "sg:phone":"+90 212 512 7501",
    "sg:postcode":"12600",
    "sg:province":"Istanbul",
    "sg:tags":[
        "promotional"
    ],
    "wof:name":"Kozan Saraciye ?anta",
    "wof:placetype":"venue"
},
  "geometry": {"coordinates":[28.9759254456,41.0123786926],"type":"Point"}
}