{
  "type": "Feature",
  "properties": {
    "addr:full":"Pazar Mah.necipbey Cad. Meseret Sok.no:21/2 Sariyer Samsun 33740",
    "addr:housenumber":"21 / 2",
    "addr:postcode":"33740",
    "addr:street":"Mah.Necipbey Cad. Meseret Sok.No;Sariyer Samsun",
    "iso:country":"TR",
    "sg:address":"Pazar Mah.necipbey Cad. Meseret Sok.no:21/2",
    "sg:city":"Sariyer",
    "sg:classifiers":[
        {
            "category":"Building & Trades",
            "subcategory":"Landscaping Services",
            "type":"Services"
        }
    ],
    "sg:phone":"+90 3624313565431",
    "sg:postcode":"33740",
    "sg:province":"Samsun",
    "sg:tags":[
        "landscape"
    ],
    "wof:name":"Emka Tasarim Peyzaj",
    "wof:placetype":"venue"
},
  "geometry": {"coordinates":[36.3378410339,41.2897186279],"type":"Point"}
}