{
  "type": "Feature",
  "properties": {
    "iso:country":"TR",
    "sg:address":"Kurtulus Mh. Vatan Cd. No:66",
    "sg:city":"Kad\u0131k\u00f6y",
    "sg:classifiers":[
        {
            "category":"Shopping",
            "subcategory":"Stationery & Office Supplies",
            "type":"Retail Goods"
        }
    ],
    "sg:phone":"+90 222 231 5505",
    "sg:province":"Eskisehir",
    "sg:tags":[
        "furniture"
    ],
    "wof:name":"Kale Insaat Mobilya San. Tic. A.s.",
    "wof:placetype":"venue"
},
  "geometry": {"coordinates":[30.530090332,39.7716522217],"type":"Point"}
}