{
  "type": "Feature",
  "properties": {
    "iso:country":"TR",
    "sg:address":"Marmaracik K?? ?orlu",
    "sg:city":"Fatih",
    "sg:classifiers":[
        {
            "category":"Shopping",
            "subcategory":"Clothing, Apparel, & Fashions",
            "type":"Retail Goods"
        }
    ],
    "sg:phone":"+90 282 686 2484",
    "sg:postcode":"01740",
    "sg:province":"Tekirdag",
    "sg:tags":[
        "ready",
        "wear"
    ],
    "wof:name":"Dinateks Dinamik Tekstil Ltd.sti.",
    "wof:placetype":"venue"
},
  "geometry": {"coordinates":[27.8069286346,41.1795196533],"type":"Point"}
}