{
  "type": "Feature",
  "properties": {
    "addr:full":"Bagdat Caddesi No:520/13 Bostanci Kad\u0131k\u00f6y Istanbul 34990",
    "addr:housenumber":"no 520 / 13",
    "addr:postcode":"34990",
    "addr:street":"Bagdat Caddesi",
    "iso:country":"TR",
    "sg:address":"Bagdat Caddesi No:520/13 Bostanci",
    "sg:city":"Kad\u0131k\u00f6y",
    "sg:classifiers":[
        {
            "category":"Travel",
            "subcategory":"Travel Agent",
            "type":"Entertainment"
        }
    ],
    "sg:phone":"+90 44551453428",
    "sg:postcode":"34990",
    "sg:province":"Istanbul",
    "sg:tags":[
        "agency",
        "tourism"
    ],
    "wof:name":"Araxa Turizm",
    "wof:placetype":"venue"
},
  "geometry": {"coordinates":[28.9861831665,41.0408554077],"type":"Point"}
}