{
  "type": "Feature",
  "properties": {
    "addr:full":"Oto San. Sit. Yunus Emre Cad. Dalgic Sok. No: 7/a 80660 4.levent Istanbul Kartal Istanbul 46000",
    "addr:housenumber":"no 7 / a",
    "addr:postcode":"80660;46000",
    "addr:street":"Yunus Emre Cad. Dalgic Sok.",
    "iso:country":"TR",
    "sg:address":"Oto San. Sit. Yunus Emre Cad. Dalgic Sok. No: 7/a 80660 4.levent Istanbul",
    "sg:city":"Kartal",
    "sg:classifiers":[
        {
            "category":"Professional",
            "subcategory":"Engineering",
            "type":"Services"
        }
    ],
    "sg:phone":"+90 212 283 8008",
    "sg:postcode":"46000",
    "sg:province":"Istanbul",
    "sg:tags":[
        "machine",
        "-",
        "mechanical"
    ],
    "wof:name":"Resit Makina San. Tic. As.",
    "wof:placetype":"venue"
},
  "geometry": {"coordinates":[28.9861831665,41.0408554077],"type":"Point"}
}