{
  "type": "Feature",
  "properties": {
    "addr:full":"Ceyhun Atif Kansu Cad. No:55/a Balgat Sefak?/ K???kmece Ankara",
    "addr:housenumber":"55 / a",
    "addr:street":"Kansu Cad. No",
    "iso:country":"TR",
    "sg:address":"Ceyhun Atif Kansu Cad. No:55/a Balgat",
    "sg:city":"Sefak?/ K???kmece",
    "sg:classifiers":[
        {
            "category":"Wholesale",
            "subcategory":"Petroleum",
            "type":"Manufacturing & Wholesale Goods"
        }
    ],
    "sg:phone":"+90 312 284 5961",
    "sg:province":"Ankara",
    "wof:name":"Guney-pen Muhendislik Ltd.sti.",
    "wof:placetype":"venue"
},
  "geometry": {"coordinates":[32.8155097961,39.8844490051],"type":"Point"}
}