{
  "type": "Feature",
  "properties": {
    "addr:full":"Mahmut Uykusuz Aricak Erzurum 23510",
    "addr:postcode":"23510",
    "addr:street":"Erzurum",
    "iso:country":"TR",
    "sg:address":"Mahmut Uykusuz",
    "sg:city":"Aricak",
    "sg:classifiers":[
        {
            "category":"Government",
            "subcategory":"Office",
            "type":"Public Place"
        }
    ],
    "sg:phone":"+90 442 218 2504",
    "sg:postcode":"23510",
    "sg:province":"Erzurum",
    "sg:tags":[
        "municipality"
    ],
    "wof:name":"Erzurum Ili B??sehir Belediye Baskani",
    "wof:placetype":"venue"
},
  "geometry": {"coordinates":[41.2743911743,39.9088630676],"type":"Point"}
}