{
  "type": "Feature",
  "properties": {
    "iso:country":"TR",
    "sg:address":"Ulu Cd. No:9 Osmangazi",
    "sg:city":"Merkez",
    "sg:classifiers":[
        {
            "category":"Wholesale",
            "subcategory":"Vending Machines",
            "type":"Manufacturing & Wholesale Goods"
        }
    ],
    "sg:phone":"+90 224 251 5004",
    "sg:postcode":"58070",
    "sg:province":"Bursa",
    "sg:tags":[
        "rod",
        "welding"
    ],
    "wof:name":"Kaynak Merk. San. Tic.",
    "wof:placetype":"venue"
},
  "geometry": {"coordinates":[28.97382164,40.2321090698],"type":"Point"}
}