{
  "type": "Feature",
  "properties": {
    "iso:country":"TR",
    "sg:address":"?ankaya Cd. No:24/4",
    "sg:city":"\u00c7ankaya",
    "sg:classifiers":[
        {
            "category":"Transit Center",
            "subcategory":"Freight",
            "type":"Transportation"
        }
    ],
    "sg:phone":"+90 312 440 5541",
    "sg:postcode":"06105",
    "sg:province":"Ankara",
    "wof:name":"Aslan Trans Mari Gemicilik Tic. End?strisi A.s.",
    "wof:placetype":"venue"
},
  "geometry": {"coordinates":[32.8580131531,39.8873176575],"type":"Point"}
}