{
  "type": "Feature",
  "properties": {
    "iso:country":"TR",
    "sg:address":"Laleli",
    "sg:city":"Osmanbey",
    "sg:classifiers":[
        {
            "category":"Shopping",
            "subcategory":"Clothing, Apparel, & Fashions",
            "type":"Retail Goods"
        }
    ],
    "sg:phone":"+90 212 518 3818",
    "sg:postcode":"63000",
    "sg:province":"Istanbul",
    "sg:tags":[
        "ready",
        "wear"
    ],
    "wof:name":"Lokris Ltd.",
    "wof:placetype":"venue"
},
  "geometry": {"coordinates":[28.9566669464,41.0099983215],"type":"Point"}
}