{
  "type": "Feature",
  "properties": {
    "addr:full":"Refik Tulga Cad. 401/2 Sok. No. 3 K:1 Kanat Is. Mrkz. ?amdibi Izmir",
    "addr:housenumber":"401 / 2;no. 3 k 1;?",
    "addr:street":"Tulga Cad.;Sok.;Kanat Is. Mrkz.",
    "iso:country":"TR",
    "sg:address":"Refik Tulga Cad. 401/2 Sok. No. 3 K:1 Kanat Is. Mrkz.",
    "sg:city":"?amdibi",
    "sg:classifiers":[
        {
            "category":"Farming",
            "subcategory":"Farm",
            "type":"Manufacturing & Wholesale Goods"
        }
    ],
    "sg:phone":"+90 232 461 7547",
    "sg:province":"Izmir",
    "sg:tags":[
        "agricultural",
        "product"
    ],
    "wof:name":"Kaneks Limited",
    "wof:placetype":"venue"
},
  "geometry": {"coordinates":[27.1296863556,38.4186973572],"type":"Point"}
}