{
  "type": "Feature",
  "properties": {
    "iso:country":"TR",
    "sg:address":"42/a Sk. No:52 Yeni",
    "sg:city":"Ostim",
    "sg:classifiers":[
        {
            "category":"Building & Trades",
            "subcategory":"Electrical",
            "type":"Services"
        }
    ],
    "sg:phone":"+90 312 385 3315",
    "sg:postcode":"06374",
    "sg:province":"Ankara",
    "sg:tags":[
        "equipment",
        "lighting"
    ],
    "wof:name":"Arlight Ltd.sti.",
    "wof:placetype":"venue"
},
  "geometry": {"coordinates":[32.9625701904,39.9137573242],"type":"Point"}
}