{
  "type": "Feature",
  "properties": {
    "addr:full":"Altiyol Karadut Sk. No:12 Kad\u0131k\u00f6y Istanbul 34990",
    "addr:housenumber":"12",
    "addr:postcode":"34990",
    "addr:street":"Karadut Sk. No;Istanbul",
    "iso:country":"TR",
    "sg:address":"Altiyol Karadut Sk. No:12",
    "sg:city":"Kad\u0131k\u00f6y",
    "sg:classifiers":[
        {
            "category":"Home & Garden",
            "subcategory":"Home Furnishings",
            "type":"Retail Goods"
        }
    ],
    "sg:phone":"+90 216 349 8975",
    "sg:postcode":"34990",
    "sg:province":"Istanbul",
    "sg:tags":[
        "-curtains",
        "upholstery"
    ],
    "wof:name":"Bi?ici Stor Perde Sistemleri",
    "wof:placetype":"venue"
},
  "geometry": {"coordinates":[28.975925,41.012379],"type":"Point"}
}