{
  "type": "Feature",
  "properties": {
    "iso:country":"TR",
    "sg:address":"19 Mayis Cd.no50 Kirdar Ismerk.k4/4",
    "sg:city":"Pendik",
    "sg:classifiers":[
        {
            "category":"Freight",
            "type":"Transportation"
        }
    ],
    "sg:phone":"+90 216 390 9133",
    "sg:postcode":"34916",
    "sg:province":"Istanbul",
    "sg:tags":[
        "agent",
        "shipping",
        "broker"
    ],
    "wof:name":"Aydos Denizcilik Ltd.sti.",
    "wof:placetype":"venue"
},
  "geometry": {"coordinates":[28.975925,41.012379],"type":"Point"}
}