{
  "type": "Feature",
  "properties": {
    "iso:country":"TR",
    "sg:address":"Necatibey Bulv. No: 4 Kamil Is Hani Kat:3/302",
    "sg:city":"Cankaya",
    "sg:classifiers":[
        {
            "category":"Shopping",
            "subcategory":"Clothing, Apparel, & Fashions",
            "type":"Retail Goods"
        }
    ],
    "sg:phone":"+90 232 445 2749",
    "sg:postcode":"07080",
    "sg:province":"Izmir",
    "sg:tags":[
        "woman",
        "wear"
    ],
    "wof:name":"Liz Moda Tekstil",
    "wof:placetype":"venue"
},
  "geometry": {"coordinates":[27.1296863556,38.4186973572],"type":"Point"}
}