{
  "type": "Feature",
  "properties": {
    "iso:country":"TR",
    "sg:address":"Tarlabasi Zambak Sk. No:10",
    "sg:city":"Taksim",
    "sg:classifiers":[
        {
            "category":"Home & Garden",
            "subcategory":"Household Appliances",
            "type":"Retail Goods"
        }
    ],
    "sg:phone":"+90 212 245 5312",
    "sg:postcode":"24040",
    "sg:province":"Istanbul",
    "sg:tags":[
        "conditioner",
        "air"
    ],
    "wof:name":"Frigoteknik Sog. San.",
    "wof:placetype":"venue"
},
  "geometry": {"coordinates":[28.9542427063,41.0583534241],"type":"Point"}
}