{
  "type": "Feature",
  "properties": {
    "iso:country":"TR",
    "sg:address":"Alsancak",
    "sg:city":"Macunk?",
    "sg:classifiers":[
        {
            "category":"Farming",
            "subcategory":"Farm",
            "type":"Manufacturing & Wholesale Goods"
        }
    ],
    "sg:province":"Izmir",
    "sg:tags":[
        "agricultural",
        "product"
    ],
    "wof:name":"Yagmur Ihracat",
    "wof:placetype":"venue"
},
  "geometry": {"coordinates":[27.1447296143,38.4409103394],"type":"Point"}
}