{
  "type": "Feature",
  "properties": {
    "iso:country":"TR",
    "sg:address":"Organize San. B?. 9. Cad. No:41 Organize San. B?.",
    "sg:city":"Yakutiye",
    "sg:classifiers":[
        {
            "category":"Home & Garden",
            "subcategory":"Household Appliances",
            "type":"Retail Goods"
        }
    ],
    "sg:phone":"+90 352321123732",
    "sg:postcode":"25200",
    "sg:province":"Kayseri",
    "sg:tags":[
        "kitchenware"
    ],
    "wof:name":"Ekincioglu Emaye San.",
    "wof:placetype":"venue"
},
  "geometry": {"coordinates":[35.4891357422,38.7225761414],"type":"Point"}
}