{
  "type": "Feature",
  "properties": {
    "addr:full":"Bagdat C. 158/a Kardesler Apt. D: 10 Feneryolu Istanbul 34724",
    "addr:housenumber":"158 / a;10",
    "addr:postcode":"34724",
    "addr:street":"Kardesler Apt. D",
    "iso:country":"TR",
    "sg:address":"Bagdat C. 158/a Kardesler Apt. D: 10",
    "sg:city":"Feneryolu",
    "sg:classifiers":[
        {
            "category":"Manufacturing",
            "subcategory":"Building Materials",
            "type":"Manufacturing & Wholesale Goods"
        }
    ],
    "sg:phone":"+90 216 356 1073",
    "sg:postcode":"34724",
    "sg:province":"Istanbul",
    "sg:tags":[
        "floor-wall",
        "covering"
    ],
    "wof:name":"Belfa International",
    "wof:placetype":"venue"
},
  "geometry": {"coordinates":[29.2330799103,41.0183029175],"type":"Point"}
}