{
  "type": "Feature",
  "properties": {
    "iso:country":"TR",
    "sg:address":"Sehzadebasi Cad. No:17",
    "sg:city":"Sehzadebasi",
    "sg:orig_category":"Hotels: Motels",
    "sg:phone":"+90 2125125842729",
    "sg:province":"Istanbul",
    "wof:name":"Grand Hotel Gulsoy",
    "wof:placetype":"venue"
},
  "geometry": {"coordinates":[28.9583034515,41.0125389099],"type":"Point"}
}