{
  "type": "Feature",
  "properties": {
    "iso:country":"TR",
    "sg:address":"Hacikadin Mah No : 34/1",
    "sg:city":"Unkapani",
    "sg:classifiers":[
        {
            "category":"Wholesale",
            "subcategory":"Vending Machines",
            "type":"Manufacturing & Wholesale Goods"
        }
    ],
    "sg:phone":"+90 212 519 4688",
    "sg:postcode":"55020",
    "sg:province":"Istanbul",
    "sg:tags":[
        "used"
    ],
    "wof:name":"Atmaca Makina",
    "wof:placetype":"venue"
},
  "geometry": {"coordinates":[28.9315319061,41.0396499634],"type":"Point"}
}