{
  "type": "Feature",
  "properties": {
    "addr:full":"Keskin Kalem Sk. No:6/9 Esentepe B.pasa Istanbul 34440",
    "addr:housenumber":"9",
    "addr:postcode":"34440",
    "addr:street":"Kalem Sk. No 6 /",
    "iso:country":"TR",
    "sg:address":"Keskin Kalem Sk. No:6/9 Esentepe",
    "sg:city":"B.pasa",
    "sg:classifiers":[
        {
            "category":"Building & Trades",
            "subcategory":"Plumbing",
            "type":"Services"
        }
    ],
    "sg:phone":"+90 212 274 4457",
    "sg:postcode":"34440",
    "sg:province":"Istanbul",
    "wof:name":"Ulusoy Mekanik Tesisat Taahh?t Tic. A.s.",
    "wof:placetype":"venue"
},
  "geometry": {"coordinates":[29.0080471039,41.0685348511],"type":"Point"}
}