{
  "type": "Feature",
  "properties": {
    "addr:full":"Elmali Mah. 15. Sok.no:5/11 Esentepe Antalya 03456",
    "addr:housenumber":"15;5 / 11",
    "addr:postcode":"03456",
    "addr:street":"Elmali Mah.;Sok.No;Esentepe",
    "iso:country":"TR",
    "sg:address":"Elmali Mah. 15. Sok.no:5/11",
    "sg:city":"Esentepe",
    "sg:classifiers":[
        {
            "category":"Professional",
            "subcategory":"Computer Services",
            "type":"Services"
        }
    ],
    "sg:phone":"+90 242 248 5780",
    "sg:postcode":"03456",
    "sg:province":"Antalya",
    "sg:tags":[
        "application",
        "software"
    ],
    "wof:name":"Ak-bim Bilgi Islem Ltd.",
    "wof:placetype":"venue"
},
  "geometry": {"coordinates":[30.7092056274,36.8790512085],"type":"Point"}
}