{
  "type": "Feature",
  "properties": {
    "addr:full":"Kemalpasa Yolu Hayitlikir Mevki Kemalpasa Izmir 01340",
    "addr:housenumber":"hayitlikir",
    "addr:postcode":"01340",
    "addr:street":"Kemalpasa Yolu",
    "iso:country":"TR",
    "sg:address":"Kemalpasa Yolu Hayitlikir Mevki",
    "sg:city":"Kemalpasa",
    "sg:classifiers":[
        {
            "category":"Manufacturing",
            "subcategory":"Textiles",
            "type":"Manufacturing & Wholesale Goods"
        }
    ],
    "sg:phone":"+90 232 878 1527",
    "sg:postcode":"01340",
    "sg:province":"Izmir",
    "sg:tags":[
        "sizing",
        "dye"
    ],
    "wof:name":"Rute Grup",
    "wof:placetype":"venue"
},
  "geometry": {"coordinates":[27.1423015594,38.4251480103],"type":"Point"}
}