{
  "type": "Feature",
  "properties": {
    "iso:country":"TR",
    "sg:address":"Halide Edip Adivar Mah. Halide Edip Adivar Cad. No:59/a",
    "sg:city":"Sisli",
    "sg:classifiers":[
        {
            "category":"Manufacturing",
            "subcategory":"Building Materials",
            "type":"Manufacturing & Wholesale Goods"
        }
    ],
    "sg:phone":"+90 212 222 5736",
    "sg:postcode":"65710",
    "sg:province":"Istanbul",
    "sg:tags":[
        "floor-wall",
        "covering"
    ],
    "wof:name":"Kale Insaat",
    "wof:placetype":"venue"
},
  "geometry": {"coordinates":[28.9759254456,41.0123786926],"type":"Point"}
}