{
  "type": "Feature",
  "properties": {
    "iso:country":"TR",
    "sg:address":"0-1 Otoyolu Hadimkoy Cikisi Al-kop Sitesi A-6 Blok No:1-2-3-18 Buyukcekmece",
    "sg:city":"Kozyatagi",
    "sg:classifiers":[
        {
            "category":"Professional",
            "type":"Services"
        }
    ],
    "sg:phone":"+90 21285803464428",
    "sg:postcode":"34742",
    "sg:province":"Istanbul",
    "sg:tags":[
        "catering"
    ],
    "wof:name":"Defne Yemek",
    "wof:placetype":"venue"
},
  "geometry": {"coordinates":[28.9861831665,41.0408554077],"type":"Point"}
}