{
  "type": "Feature",
  "properties": {
    "iso:country":"TR",
    "sg:address":"Yunusemre Mah. Kiymet Sok.",
    "sg:city":"Ikitelli/K\u00fc\u00e7\u00fck\u00e7ekmece",
    "sg:classifiers":[
        {
            "category":"Manufacturing",
            "subcategory":"Rubber & Plastics",
            "type":"Manufacturing & Wholesale Goods"
        }
    ],
    "sg:phone":"+90 224 362 0211",
    "sg:postcode":"34670",
    "sg:province":"Bursa",
    "sg:tags":[
        "industry"
    ],
    "wof:name":"Formplast",
    "wof:placetype":"venue"
},
  "geometry": {"coordinates":[29.1064338684,40.1990013123],"type":"Point"}
}