{
  "type": "Feature",
  "properties": {
    "addr:full":"Selimiye Mh. Atat?k Bulvari U?r Is Merk. Altinova- Ayvalik Balikesir 01680",
    "addr:housenumber":"u ? r",
    "addr:postcode":"01680",
    "addr:street":"K Bulvari;Is Merk. Altinova Ayvalik Balikesir",
    "iso:country":"TR",
    "sg:address":"Selimiye Mh. Atat?k Bulvari U?r Is Merk. Altinova-",
    "sg:city":"Ayvalik",
    "sg:classifiers":[
        {
            "category":"Home & Garden",
            "subcategory":"Building Materials",
            "type":"Retail Goods"
        }
    ],
    "sg:phone":"+90 266 338 3285",
    "sg:postcode":"01680",
    "sg:province":"Balikesir",
    "sg:tags":[
        "stone",
        "natural",
        "marble"
    ],
    "wof:name":"U?ar Mermer Pazarlama San. Tic. A.s.",
    "wof:placetype":"venue"
},
  "geometry": {"coordinates":[27.8853626251,39.6448822021],"type":"Point"}
}