{
  "type": "Feature",
  "properties": {
    "iso:country":"TR",
    "sg:address":"Merhaba Cad. Camcak Sok. No:42",
    "sg:city":"Kocamustafapasa",
    "sg:classifiers":[
        {
            "category":"Freight",
            "type":"Transportation"
        }
    ],
    "sg:phone":"+90 212530224445",
    "sg:postcode":"34098",
    "sg:province":"Istanbul",
    "sg:tags":[
        "packing",
        "industry"
    ],
    "wof:name":"Aksu Tanitim Insaat Tekstil Ve Muhendislik Hiz. San.tic. Ltd.sti.",
    "wof:placetype":"venue"
},
  "geometry": {"coordinates":[28.928653717,40.9987602234],"type":"Point"}
}