{
  "type": "Feature",
  "properties": {
    "addr:full":"Cumhuriyet Mah.kervan Yolu No:230 /5 Turgutlu ?igli Manisa 35620",
    "addr:housenumber":"no;/ 5 turgutlu ?",
    "addr:postcode":"35620",
    "addr:street":"Mah.Kervan Yolu",
    "iso:country":"TR",
    "sg:address":"Cumhuriyet Mah.kervan Yolu No:230 /5 Turgutlu",
    "sg:city":"?igli",
    "sg:classifiers":[
        {
            "category":"Shopping",
            "subcategory":"Luggage & Leather Goods",
            "type":"Retail Goods"
        }
    ],
    "sg:phone":"+90 236",
    "sg:postcode":"35620",
    "sg:province":"Manisa",
    "sg:tags":[
        "leather-fur",
        "wear"
    ],
    "wof:name":"Lightleather",
    "wof:placetype":"venue"
},
  "geometry": {"coordinates":[27.4297008514,38.6222000122],"type":"Point"}
}