{
  "type": "Feature",
  "properties": {
    "iso:country":"TR",
    "sg:address":"Eski Sanayi Bolgesi Tavsanli Yolu No:361",
    "sg:city":"Mecidiyek\u00f6y",
    "sg:classifiers":[
        {
            "category":"Manufacturing",
            "subcategory":"Wood Products",
            "type":"Manufacturing & Wholesale Goods"
        }
    ],
    "sg:phone":"+90 274 231 1083",
    "sg:province":"K?tahya",
    "sg:tags":[
        "forest"
    ],
    "wof:name":"Camsan Kereste Ve Palet Sanayii",
    "wof:placetype":"venue"
},
  "geometry": {"coordinates":[29.491569519,39.544380188],"type":"Point"}
}