{
  "type": "Feature",
  "properties": {
    "addr:full":"Ertem Sk. No:4 Nil Apt. D:9 K:4 Gayrettepe Ikitelli/K\u00fc\u00e7\u00fck\u00e7ekmece Istanbul 34670",
    "addr:housenumber":"4",
    "addr:postcode":"34670",
    "addr:street":"Ertem Sk. No;Nil;D;K",
    "iso:country":"TR",
    "sg:address":"Ertem Sk. No:4 Nil Apt. D:9 K:4 Gayrettepe",
    "sg:city":"Ikitelli/K\u00fc\u00e7\u00fck\u00e7ekmece",
    "sg:classifiers":[
        {
            "category":"Wholesale",
            "subcategory":"Machinery & Supplies",
            "type":"Manufacturing & Wholesale Goods"
        }
    ],
    "sg:phone":"+90 212 247 4843",
    "sg:postcode":"34670",
    "sg:province":"Istanbul",
    "sg:tags":[
        "press",
        "hydraulic"
    ],
    "wof:name":"Karisim Tic. Ltd. Sti.",
    "wof:placetype":"venue"
},
  "geometry": {"coordinates":[28.9861831665,41.0408554077],"type":"Point"}
}