{
  "type": "Feature",
  "properties": {
    "iso:country":"TR",
    "sg:address":"Yeni Sire Pazari C.blk. No: 12",
    "sg:city":"Torbali",
    "sg:orig_category":"Dryfood-dried Nuts",
    "sg:phone":"+90 422 326 2712",
    "sg:postcode":"35860",
    "sg:province":"Malatya",
    "wof:name":"Altunisik Gida Sanayi Ve Ihr. Ltd. Sti.",
    "wof:placetype":"venue"
},
  "geometry": {"coordinates":[38.3195266724,38.3488922119],"type":"Point"}
}