{
  "type": "Feature",
  "properties": {
    "addr:full":"Kocasinan Merkez Mah. ?ag Sk. Emek Is Mrk. 16/1 Bah\u00e7elievler Istanbul 34180",
    "addr:housenumber":"?;16 / 1",
    "addr:postcode":"34180",
    "addr:street":"Merkez Mah.;Sk.",
    "iso:country":"TR",
    "sg:address":"Kocasinan Merkez Mah. ?ag Sk. Emek Is Mrk. 16/1",
    "sg:city":"Bah\u00e7elievler",
    "sg:classifiers":[
        {
            "category":"Home & Garden",
            "subcategory":"Home Furnishings",
            "type":"Retail Goods"
        }
    ],
    "sg:phone":"+90 212 639 5973",
    "sg:postcode":"34180",
    "sg:province":"Istanbul",
    "sg:tags":[
        "textile"
    ],
    "wof:name":"Novateks Tekstil Ltd. Sti.",
    "wof:placetype":"venue"
},
  "geometry": {"coordinates":[28.9861831665,41.0408554077],"type":"Point"}
}