{
  "type": "Feature",
  "properties": {
    "addr:full":"Seyrantepe Mah. Ibrahim Karaoglanoglu Cad. Ispar Is Merekezi No: 105/98 4.levent Istanbul",
    "addr:housenumber":"/ 98 4.levent",
    "addr:street":"Ibrahim Karaoglanoglu Cad. Ispar;No 105",
    "iso:country":"TR",
    "sg:address":"Seyrantepe Mah. Ibrahim Karaoglanoglu Cad. Ispar Is Merekezi No: 105/98",
    "sg:city":"4.levent",
    "sg:classifiers":[
        {
            "category":"Manufacturing",
            "subcategory":"Building Materials",
            "type":"Manufacturing & Wholesale Goods"
        }
    ],
    "sg:phone":"+90 212 325 8753",
    "sg:province":"Istanbul",
    "sg:tags":[
        "floor-wall",
        "covering"
    ],
    "wof:name":"Tolker Group Co.",
    "wof:placetype":"venue"
},
  "geometry": {"coordinates":[28.9759254456,41.0123786926],"type":"Point"}
}