{
  "type": "Feature",
  "properties": {
    "addr:full":"Misaki Milli Cd. No:87 Kadik? ?aglayan Istanbul",
    "addr:housenumber":"no 87;? ?",
    "addr:street":"Misaki Milli Cd.;Kadik",
    "iso:country":"TR",
    "sg:address":"Misaki Milli Cd. No:87 Kadik?",
    "sg:city":"?aglayan",
    "sg:orig_category":"Aluminium Carpentary",
    "sg:phone":"+90 216 349 0185",
    "sg:province":"Istanbul",
    "wof:name":"Befa Yapi Ins. San.a.s.",
    "wof:placetype":"venue"
},
  "geometry": {"coordinates":[29.0294342041,40.9932594299],"type":"Point"}
}