{
  "type": "Feature",
  "properties": {
    "addr:full":"Demirhendek Cd. No:40-42 Siteler Ikitelli Ankara 34306",
    "addr:housenumber":"no 40-42",
    "addr:postcode":"34306",
    "addr:street":"Demirhendek Cd.",
    "iso:country":"TR",
    "sg:address":"Demirhendek Cd. No:40-42 Siteler",
    "sg:city":"Ikitelli",
    "sg:classifiers":[
        {
            "category":"Shopping",
            "subcategory":"Stationery & Office Supplies",
            "type":"Retail Goods"
        }
    ],
    "sg:phone":"+90 312 350 9830",
    "sg:postcode":"34306",
    "sg:province":"Ankara",
    "sg:tags":[
        "furniture"
    ],
    "wof:name":"Gozubuyuk Orman Urn. A.s.",
    "wof:placetype":"venue"
},
  "geometry": {"coordinates":[32.8942298889,39.9579582214],"type":"Point"}
}