{
  "type": "Feature",
  "properties": {
    "addr:full":"Ataturk Org.san.bol. 10010.sok. No:8 Cigli-karsiyaka Karatay Izmir 42000",
    "addr:housenumber":"no",
    "addr:postcode":"42000",
    "iso:country":"TR",
    "sg:address":"Ataturk Org.san.bol. 10010.sok. No:8 Cigli-karsiyaka",
    "sg:city":"Karatay",
    "sg:classifiers":[
        {
            "category":"Home & Garden",
            "subcategory":"Hardware",
            "type":"Retail Goods"
        }
    ],
    "sg:phone":"+90 232 376 7984",
    "sg:postcode":"42000",
    "sg:province":"Izmir",
    "sg:tags":[
        "compressor",
        "pump"
    ],
    "wof:name":"Ulusoy Su Pompalari San.tic.ltd.sti.",
    "wof:placetype":"venue"
},
  "geometry": {"coordinates":[27.1296863556,38.4186973572],"type":"Point"}
}