{
  "type": "Feature",
  "properties": {
    "addr:full":"Uskup Sk. No:23 Bayrampasa 07100 Istanbul",
    "addr:housenumber":"23",
    "addr:postcode":"07100",
    "addr:street":"Uskup Sk. No",
    "iso:country":"TR",
    "sg:address":"Uskup Sk. No:23 Bayrampasa",
    "sg:city":"07100",
    "sg:classifiers":[
        {
            "category":"Manufacturing",
            "subcategory":"Wood Products",
            "type":"Manufacturing & Wholesale Goods"
        }
    ],
    "sg:phone":"+90 212 565 9030",
    "sg:province":"Istanbul",
    "sg:tags":[
        "forest"
    ],
    "wof:name":"Kastamonu Entegre Agac San. Tic. A.s.",
    "wof:placetype":"venue"
},
  "geometry": {"coordinates":[28.9111595154,41.0398368835],"type":"Point"}
}