{
  "type": "Feature",
  "properties": {
    "iso:country":"TR",
    "sg:address":"Tiryaki Hasan Pasa Cad. No:38 Aksaray 34220 Fatih Istanbul",
    "sg:city":"Karsiyaka",
    "sg:classifiers":[
        {
            "category":"Autos & Motor Vehicles",
            "subcategory":"Automobile Sales",
            "type":"Retail Goods"
        }
    ],
    "sg:phone":"+90 212 671 0299",
    "sg:postcode":"01900",
    "sg:province":"Istanbul",
    "sg:tags":[
        "motor-cars"
    ],
    "wof:name":"Stil Oto Kilif Ve Aksesuarlari",
    "wof:placetype":"venue"
},
  "geometry": {"coordinates":[28.9502429962,41.0075874329],"type":"Point"}
}