{
  "type": "Feature",
  "properties": {
    "addr:full":"?niversite Cad.no.85 ?inarli Bornova Izmir 35040",
    "addr:housenumber":"?;cad.no.85 ?;bornova",
    "addr:postcode":"35040",
    "addr:street":"Niversite;Inarli",
    "iso:country":"TR",
    "sg:address":"?niversite Cad.no.85 ?inarli",
    "sg:city":"Bornova",
    "sg:classifiers":[
        {
            "category":"Freight",
            "type":"Transportation"
        }
    ],
    "sg:phone":"+90 232 462 6570",
    "sg:postcode":"35040",
    "sg:province":"Izmir",
    "sg:tags":[
        "cargo",
        "parcel"
    ],
    "wof:name":"Akint?rk Nakliyat",
    "wof:placetype":"venue"
},
  "geometry": {"coordinates":[27.2117557526,38.4634437561],"type":"Point"}
}