{
  "type": "Feature",
  "properties": {
    "addr:full":"Famora, F. Cakmak Cd. No:49/c ?aglayan/sisli Bursa 80340",
    "addr:housenumber":"no 49 / c ?",
    "addr:postcode":"80340",
    "addr:street":"Cakmak Cd.;Aglayan",
    "iso:country":"TR",
    "sg:address":"Famora, F. Cakmak Cd. No:49/c",
    "sg:city":"?aglayan/sisli",
    "sg:classifiers":[
        {
            "category":"Shopping",
            "subcategory":"Stationery & Office Supplies",
            "type":"Retail Goods"
        }
    ],
    "sg:phone":"+90 224 251 0322",
    "sg:postcode":"80340",
    "sg:province":"Bursa",
    "sg:tags":[
        "furniture"
    ],
    "wof:name":"Cimtas Celik Imal. Tic.",
    "wof:placetype":"venue"
},
  "geometry": {"coordinates":[29.0580043793,40.1947555542],"type":"Point"}
}