{
  "type": "Feature",
  "properties": {
    "iso:country":"TR",
    "sg:address":"?renyeri",
    "sg:city":"Pamukkale",
    "sg:classifiers":[
        {
            "category":"Utilities",
            "subcategory":"Water",
            "type":"Services"
        }
    ],
    "sg:phone":"+90 25827220143",
    "sg:postcode":"20280",
    "sg:province":"Denizli",
    "sg:tags":[
        "spring"
    ],
    "wof:name":"Palmiye Hotel",
    "wof:placetype":"venue"
},
  "geometry": {"coordinates":[29.086491,37.773525],"type":"Point"}
}