{
  "type": "Feature",
  "properties": {
    "addr:full":"Nispetiye Cad. No:19/2-4 Peker Sokak Ucler Apt. 80600 1.levent Istanbul Sariyer Istanbul 33740",
    "addr:housenumber":"19 / 2-4;ucler",
    "addr:postcode":"80600;33740",
    "addr:street":"Nispetiye Cad. No;Peker Sokak;1.Levent",
    "iso:country":"TR",
    "sg:address":"Nispetiye Cad. No:19/2-4 Peker Sokak Ucler Apt. 80600 1.levent Istanbul",
    "sg:city":"Sariyer",
    "sg:orig_category":"Miscellaneous Products",
    "sg:phone":"+90 212 268 1567",
    "sg:postcode":"33740",
    "sg:province":"Istanbul",
    "wof:name":"Reanimed Teknik Ve Tibbi Sistem San Ve Tic San Ltd Sti",
    "wof:placetype":"venue"
},
  "geometry": {"coordinates":[28.9759254456,41.0123786926],"type":"Point"}
}