{
  "type": "Feature",
  "properties": {
    "iso:country":"TR",
    "sg:address":"Mine Sok.minareli Cavus Mevkii Nilufer Sanayi Bolgesi",
    "sg:city":"Kad\u0131k\u00f6y",
    "sg:classifiers":[
        {
            "category":"Utilities",
            "subcategory":"Natural Gas",
            "type":"Services"
        }
    ],
    "sg:phone":"+90 224 242 2300",
    "sg:province":"Bursa",
    "sg:tags":[
        "tank-heating-natural"
    ],
    "wof:name":"Mastas Makina Kalip San. Tic. A.s.",
    "wof:placetype":"venue"
},
  "geometry": {"coordinates":[29.0398807526,40.1076583862],"type":"Point"}
}