{
  "type": "Feature",
  "properties": {
    "iso:country":"TR",
    "sg:address":"Tokmak K??altinova 77700",
    "sg:city":"Bak\u0131rk\u00f6y",
    "sg:classifiers":[
        {
            "category":"Shopping",
            "subcategory":"Stationery & Office Supplies",
            "type":"Retail Goods"
        }
    ],
    "sg:phone":"+90 226 462 8523",
    "sg:province":"Yalova",
    "sg:tags":[
        "paper"
    ],
    "wof:name":"Ipek Kagit San Tic A.s",
    "wof:placetype":"venue"
},
  "geometry": {"coordinates":[29.5516433716,40.6850395203],"type":"Point"}
}