{
  "type": "Feature",
  "properties": {
    "iso:country":"TR",
    "sg:address":"Eski Bugday Pazari Cad.no:7",
    "sg:city":"Eregli",
    "sg:classifiers":[
        {
            "category":"Home & Garden",
            "subcategory":"Hardware",
            "type":"Retail Goods"
        }
    ],
    "sg:phone":"+90 332 713 1655",
    "sg:postcode":"42310",
    "sg:province":"Konya",
    "sg:tags":[
        "store"
    ],
    "wof:name":"Topbaslar Ltd.sti.",
    "wof:placetype":"venue"
},
  "geometry": {"coordinates":[33.0667152405,39.2111282349],"type":"Point"}
}