{
  "type": "Feature",
  "properties": {
    "addr:full":"Ikitelli Organize San.bol.esot Yapi Koop L Blok No: 9 Ikitelli Istanbul 34306",
    "addr:housenumber":"blok no 9",
    "addr:postcode":"34306",
    "addr:street":"L",
    "iso:country":"TR",
    "sg:address":"Ikitelli Organize San.bol.esot Yapi Koop L Blok No: 9",
    "sg:city":"Ikitelli",
    "sg:classifiers":[
        {
            "category":"Travel",
            "subcategory":"Travel Agent",
            "type":"Entertainment"
        }
    ],
    "sg:phone":"+90 21254986583",
    "sg:postcode":"34306",
    "sg:province":"Istanbul",
    "sg:tags":[
        "agency",
        "tourism"
    ],
    "wof:name":"Senocak Dis Ticaret Turizm San.ltd.sti.",
    "wof:placetype":"venue"
},
  "geometry": {"coordinates":[28.9861831665,41.0408554077],"type":"Point"}
}