{
  "type": "Feature",
  "properties": {
    "iso:country":"TR",
    "sg:address":"Yeni Sanayi Sit. 48. Sok. No:9 4. Kapi",
    "sg:city":"10020",
    "sg:classifiers":[
        {
            "category":"Home & Garden",
            "subcategory":"Home Furnishings",
            "type":"Retail Goods"
        }
    ],
    "sg:phone":"+90 266246204924",
    "sg:province":"Balikesir",
    "sg:tags":[
        "textile"
    ],
    "wof:name":"Endez Ev Tekstil Ltd.sti.",
    "wof:placetype":"venue"
},
  "geometry": {"coordinates":[27.8793792725,39.6555595398],"type":"Point"}
}