{
  "type": "Feature",
  "properties": {
    "iso:country":"TR",
    "sg:address":"Tunel Pasaji No:13 Beyoglu",
    "sg:city":"Okmeydani/beyoglu",
    "sg:classifiers":[
        {
            "category":"Shopping",
            "subcategory":"Stationery & Office Supplies",
            "type":"Retail Goods"
        }
    ],
    "sg:phone":"+90 212 244 0753",
    "sg:postcode":"34440",
    "sg:province":"Istanbul",
    "wof:name":"Kohen Hemsireler Kitap Evi",
    "wof:placetype":"venue"
},
  "geometry": {"coordinates":[28.967318,41.043106],"type":"Point"}
}