{
  "type": "Feature",
  "properties": {
    "addr:full":"Kuru Gida Sitesi P.1 Blok No:16 Rami Ikitelli Istanbul 34306",
    "addr:housenumber":"blok no 16",
    "addr:postcode":"kuru;34306",
    "addr:street":"P.1;Rami Ikitelli",
    "iso:country":"TR",
    "sg:address":"Kuru Gida Sitesi P.1 Blok No:16 Rami",
    "sg:city":"Ikitelli",
    "sg:classifiers":[
        {
            "category":"Farming",
            "subcategory":"Fish & Marine Products",
            "type":"Manufacturing & Wholesale Goods"
        }
    ],
    "sg:phone":"+90 212 581 6545",
    "sg:postcode":"34306",
    "sg:province":"Istanbul",
    "sg:tags":[
        "automotive"
    ],
    "wof:name":"Ufuklar Otomotiv Tic.ltd.sti.",
    "wof:placetype":"venue"
},
  "geometry": {"coordinates":[28.7984962463,41.0884017944],"type":"Point"}
}