{
  "type": "Feature",
  "properties": {
    "addr:full":"Kibris Sk. No:24 ?ankaya Kad\u0131k\u00f6y Ankara 34726",
    "addr:housenumber":"24 ?",
    "addr:postcode":"34726",
    "addr:street":"Sk. No;Ankaya Kadikoey",
    "iso:country":"TR",
    "sg:address":"Kibris Sk. No:24 ?ankaya",
    "sg:city":"Kad\u0131k\u00f6y",
    "sg:classifiers":[
        {
            "category":"Communications",
            "subcategory":"Film & Video Production",
            "type":"Services"
        }
    ],
    "sg:phone":"+90 312 426 9173",
    "sg:postcode":"34726",
    "sg:province":"Ankara",
    "sg:tags":[
        "-"
    ],
    "wof:name":"Ava Tv Haber Prod?ksiyon San. A.s.",
    "wof:placetype":"venue"
},
  "geometry": {"coordinates":[32.855178833,39.8961257935],"type":"Point"}
}