{
  "type": "Feature",
  "properties": {
    "addr:full":"Sinop Ikitelli/K\u00fc\u00e7\u00fck\u00e7ekmece Sinop 34660",
    "addr:postcode":"34660",
    "addr:street":"Sinop",
    "iso:country":"TR",
    "sg:address":"Sinop",
    "sg:city":"Ikitelli/K\u00fc\u00e7\u00fck\u00e7ekmece",
    "sg:classifiers":[
        {
            "category":"Health Services",
            "subcategory":"Hospital",
            "type":"Services"
        }
    ],
    "sg:phone":"+90 368 271 4464",
    "sg:postcode":"34660",
    "sg:province":"Sinop",
    "sg:tags":[
        "state"
    ],
    "wof:name":"Ssk Hastanesi",
    "wof:placetype":"venue"
},
  "geometry": {"coordinates":[35.082912,42.019974],"type":"Point"}
}