{
  "type": "Feature",
  "properties": {
    "addr:full":"Hisar Mh. Gemsas Yolu Gemlik Y. Bosna Bursa",
    "addr:housenumber":"gemlik",
    "addr:street":"Gemsas Yolu;Y. Bosna",
    "iso:country":"TR",
    "sg:address":"Hisar Mh. Gemsas Yolu Gemlik",
    "sg:city":"Y. Bosna",
    "sg:orig_category":"General Industrial Products",
    "sg:phone":"+90 224 251 3410",
    "sg:province":"Bursa",
    "wof:name":"Borusan Mak. Imal. A.s.",
    "wof:placetype":"venue"
},
  "geometry": {"coordinates":[29.1594009399,40.4277992249],"type":"Point"}
}