{
  "type": "Feature",
  "properties": {
    "iso:country":"TR",
    "sg:address":"Yunusemre Cad.no:5/b Maltepe",
    "sg:city":"Kizilay",
    "sg:classifiers":[
        {
            "category":"Building & Trades",
            "subcategory":"Plumbing",
            "type":"Services"
        }
    ],
    "sg:phone":"+90 216 399 2015",
    "sg:postcode":"06640",
    "sg:province":"Istanbul",
    "wof:name":"Harput Tesisat",
    "wof:placetype":"venue"
},
  "geometry": {"coordinates":[28.9034729004,41.0611419678],"type":"Point"}
}