{
  "type": "Feature",
  "properties": {
    "addr:full":"Birlik Sanayi Sitesi 3.cad.no:89-91-93 B\u00fcy\u00fck\u00e7ekmece Istanbul 34905",
    "addr:housenumber":"89-91-93",
    "addr:postcode":"34905",
    "addr:street":"Sitesi;Bueyuekc\u0327Ekmece Istanbul",
    "iso:country":"TR",
    "sg:address":"Birlik Sanayi Sitesi 3.cad.no:89-91-93",
    "sg:city":"B\u00fcy\u00fck\u00e7ekmece",
    "sg:classifiers":[
        {
            "category":"Home & Garden",
            "subcategory":"Kitchen Supply",
            "type":"Retail Goods"
        }
    ],
    "sg:phone":"+90 21287535754",
    "sg:postcode":"34905",
    "sg:province":"Istanbul",
    "sg:tags":[
        "wardrobe"
    ],
    "sg:website":"arikollektif.com.tr",
    "wof:name":"Ari Koll.sti-erhan Geyisi Ve Ort.",
    "wof:placetype":"venue"
},
  "geometry": {"coordinates":[28.9026298523,41.0180053711],"type":"Point"}
}