{
  "type": "Feature",
  "properties": {
    "addr:full":"Diyarbakir Cad. No:305/c ?igli Batman 35610",
    "addr:housenumber":"305 / c ?",
    "addr:postcode":"35610",
    "addr:street":"Diyarbakir Cad. No",
    "iso:country":"TR",
    "sg:address":"Diyarbakir Cad. No:305/c",
    "sg:city":"?igli",
    "sg:classifiers":[
        {
            "category":"Wholesale",
            "subcategory":"Petroleum",
            "type":"Manufacturing & Wholesale Goods"
        }
    ],
    "sg:phone":"+90 488 311 2572",
    "sg:postcode":"35610",
    "sg:province":"Batman",
    "wof:name":"Mehmetogllari Petrol",
    "wof:placetype":"venue"
},
  "geometry": {"coordinates":[41.4181861877,38.1603660583],"type":"Point"}
}