{
  "type": "Feature",
  "properties": {
    "iso:country":"TR",
    "sg:address":"S. G?altay Cd. No:201/3",
    "sg:city":"Erenk?",
    "sg:classifiers":[
        {
            "category":"Manufacturing",
            "subcategory":"Glass & Minerals",
            "type":"Manufacturing & Wholesale Goods"
        }
    ],
    "sg:phone":"+90 216 360 3612",
    "sg:province":"Istanbul",
    "sg:tags":[
        "glass-mirror"
    ],
    "wof:name":"?izgi Dekoratif Cam Ltd. Sti.",
    "wof:placetype":"venue"
},
  "geometry": {"coordinates":[29.1138839722,40.967124939],"type":"Point"}
}