{
  "type": "Feature",
  "properties": {
    "addr:full":"Korfez Cad.no:6 Anadoluhisari Istanbul 34810",
    "addr:housenumber":"6",
    "addr:postcode":"34810",
    "addr:street":"Cad.No",
    "iso:country":"TR",
    "sg:address":"Korfez Cad.no:6",
    "sg:city":"Anadoluhisari",
    "sg:classifiers":[
        {
            "category":"Freight",
            "type":"Transportation"
        }
    ],
    "sg:phone":"+90 216 308 6770",
    "sg:postcode":"34810",
    "sg:province":"Istanbul",
    "sg:tags":[
        "agent",
        "shipping",
        "broker"
    ],
    "wof:name":"Lufer Tekneleri",
    "wof:placetype":"venue"
},
  "geometry": {"coordinates":[29.067097,41.083351],"type":"Point"}
}