{
  "type": "Feature",
  "properties": {
    "addr:full":"Sarig?el Cd. Kizancik Sk. No:23 Aksaray Nazilli Istanbul 65600",
    "addr:housenumber":"23",
    "addr:postcode":"65600",
    "addr:street":"El Cd. Kizancik Sk. No",
    "iso:country":"TR",
    "sg:address":"Sarig?el Cd. Kizancik Sk. No:23 Aksaray",
    "sg:city":"Nazilli",
    "sg:classifiers":[
        {
            "category":"Wholesale",
            "subcategory":"Durable Goods & Equipment",
            "type":"Manufacturing & Wholesale Goods"
        }
    ],
    "sg:phone":"+90 212 521 8007",
    "sg:postcode":"65600",
    "sg:province":"Istanbul",
    "sg:tags":[
        "consumer"
    ],
    "wof:name":"G?naylar Day. T?k. Mal. Tic.",
    "wof:placetype":"venue"
},
  "geometry": {"coordinates":[28.9861831665,41.0408554077],"type":"Point"}
}