{
  "type": "Feature",
  "properties": {
    "iso:country":"TR",
    "sg:address":"San. B?. 3. Cad. No.50 Eski San.",
    "sg:city":"Seyhan",
    "sg:classifiers":[
        {
            "category":"Manufacturing",
            "subcategory":"Metals",
            "type":"Manufacturing & Wholesale Goods"
        }
    ],
    "sg:phone":"+90 352336350133",
    "sg:postcode":"01120",
    "sg:province":"Kayseri",
    "sg:tags":[
        "industry"
    ],
    "wof:name":"Ozdemir Celik Esya San.",
    "wof:placetype":"venue"
},
  "geometry": {"coordinates":[35.4891357422,38.7225761414],"type":"Point"}
}