{
  "type": "Feature",
  "properties": {
    "addr:full":"?ankaya Cd. No:17/5 Maltepe Ankara 01000",
    "addr:housenumber":"?;no 17 / 5",
    "addr:postcode":"01000",
    "addr:street":"Ankaya Cd.",
    "iso:country":"TR",
    "sg:address":"?ankaya Cd. No:17/5",
    "sg:city":"Maltepe",
    "sg:classifiers":[
        {
            "category":"Home & Garden",
            "subcategory":"Home Furnishings",
            "type":"Retail Goods"
        }
    ],
    "sg:phone":"+90 312 437 8787",
    "sg:postcode":"01000",
    "sg:province":"Ankara",
    "sg:tags":[
        "quilt",
        "bed"
    ],
    "wof:name":"Ergo Yataklari",
    "wof:placetype":"venue"
},
  "geometry": {"coordinates":[32.868069,39.893005],"type":"Point"}
}