{
  "type": "Feature",
  "properties": {
    "addr:full":"Nakliyeciler Sit. 7 Blok No:704 Zeytinburnu Istanbul 41000",
    "addr:housenumber":"7 blok no 704",
    "addr:postcode":"41000",
    "addr:street":"Sit.",
    "iso:country":"TR",
    "sg:address":"Nakliyeciler Sit. 7 Blok No:704",
    "sg:city":"Zeytinburnu",
    "sg:classifiers":[
        {
            "category":"Retail",
            "subcategory":"Driving School",
            "type":"Services"
        }
    ],
    "sg:phone":"+90 212 582 4235",
    "sg:postcode":"41000",
    "sg:province":"Istanbul",
    "sg:tags":[
        "cargo"
    ],
    "wof:name":"Rize Kargo Tasima. Dagitim Tic. Ltd. Sti.",
    "wof:placetype":"venue"
},
  "geometry": {"coordinates":[28.9861831665,41.0408554077],"type":"Point"}
}