{
  "type": "Feature",
  "properties": {
    "addr:full":"Ataurk Cad. No:161 Arifiye Sakarya 26010",
    "addr:housenumber":"161",
    "addr:postcode":"26010",
    "addr:street":"Ataurk Cad. No;Sakarya",
    "iso:country":"TR",
    "sg:address":"Ataurk Cad. No:161",
    "sg:city":"Arifiye",
    "sg:classifiers":[
        {
            "category":"Farming",
            "subcategory":"Farm & Veterinary Services",
            "type":"Manufacturing & Wholesale Goods"
        }
    ],
    "sg:phone":"+90 264 229 0990",
    "sg:postcode":"26010",
    "sg:province":"Sakarya",
    "sg:tags":[
        "veterinarian"
    ],
    "wof:name":"?zel Sakarya Veteriner Klinigi Ve Hastanesi",
    "wof:placetype":"venue"
},
  "geometry": {"coordinates":[26.6950893402,39.3244171143],"type":"Point"}
}