{
  "type": "Feature",
  "properties": {
    "iso:country":"TR",
    "sg:address":"Komsu Sk.no:7/2 ?ankaya",
    "sg:city":"Cankaya",
    "sg:classifiers":[
        {
            "category":"Government",
            "subcategory":"Embassy",
            "type":"Public Place"
        }
    ],
    "sg:phone":"+90 312 439 4110",
    "sg:postcode":"07080",
    "sg:province":"Ankara",
    "sg:tags":[
        "foreign"
    ],
    "wof:name":"K?ba Cumh.b?y?kel?iligi",
    "wof:placetype":"venue"
},
  "geometry": {"coordinates":[32.8560333252,39.9438743591],"type":"Point"}
}