{
  "type": "Feature",
  "properties": {
    "iso:country":"TR",
    "sg:address":"Cennet Mh. Yavuzselim Cd. No:23 K???kmece",
    "sg:city":"Sisli",
    "sg:classifiers":[
        {
            "category":"Mining & Drilling",
            "type":"Manufacturing & Wholesale Goods"
        }
    ],
    "sg:phone":"+90 212 592 1414",
    "sg:postcode":"34620",
    "sg:province":"Istanbul",
    "sg:tags":[
        "industry",
        "mine"
    ],
    "wof:name":"Gofal Madencilik",
    "wof:placetype":"venue"
},
  "geometry": {"coordinates":[28.9759254456,41.0123786926],"type":"Point"}
}