{
  "type": "Feature",
  "properties": {
    "iso:country":"TR",
    "sg:address":"Akinci Bayiri Sk. Ali Sami Yen Stadi Yani No:4 K:6 Mecidiyek?",
    "sg:city":"Sapanca",
    "sg:classifiers":[
        {
            "category":"Building & Trades",
            "subcategory":"Construction",
            "type":"Services"
        }
    ],
    "sg:phone":"+90 212 274 1502",
    "sg:postcode":"54600",
    "sg:province":"Istanbul",
    "sg:tags":[
        "foundation"
    ],
    "wof:name":"21. Yuzyil Egitim Ve Kultur Vakfi",
    "wof:placetype":"venue"
},
  "geometry": {"coordinates":[28.9759254456,41.0123786926],"type":"Point"}
}