{
  "type": "Feature",
  "properties": {
    "addr:full":"Keresteciler Sitesi Y?sek Sok. No: 17/2/ 34010 Merter Istanbul Ikitelli/K\u00fc\u00e7\u00fck\u00e7ekmece Istanbul 34670",
    "addr:housenumber":"no 17 / 2 / 34010",
    "addr:postcode":"34670",
    "addr:street":"Sek Sok.",
    "iso:country":"TR",
    "sg:address":"Keresteciler Sitesi Y?sek Sok. No: 17/2/ 34010 Merter Istanbul",
    "sg:city":"Ikitelli/K\u00fc\u00e7\u00fck\u00e7ekmece",
    "sg:classifiers":[
        {
            "category":"Shopping",
            "subcategory":"Crafts & Fabrics",
            "type":"Retail Goods"
        }
    ],
    "sg:phone":"+90 212 637 0505",
    "sg:postcode":"34670",
    "sg:province":"Istanbul",
    "sg:tags":[
        "linen"
    ],
    "wof:name":"Evoteks Ev Ve Otel Tekstil San. Tic. Ltd. Sti.",
    "wof:placetype":"venue"
},
  "geometry": {"coordinates":[28.9759254456,41.0123786926],"type":"Point"}
}