{
  "type": "Feature",
  "properties": {
    "iso:country":"TR",
    "sg:address":"Besiktas",
    "sg:city":"Kadikoy",
    "sg:orig_category":"Art Galeries",
    "sg:phone":"+90 212 259 4739",
    "sg:postcode":"01370",
    "sg:province":"Istanbul",
    "wof:name":"Resim Heykel M?zesi",
    "wof:placetype":"venue"
},
  "geometry": {"coordinates":[29.0062255859,41.0419273376],"type":"Point"}
}