{
  "type": "Feature",
  "properties": {
    "addr:full":"I. Murat Cad. 24, ?ekirge Bursa 16090",
    "addr:housenumber":"24 ?",
    "addr:postcode":"16090",
    "addr:street":"I. Murat Cad.;Bursa",
    "iso:country":"TR",
    "sg:address":"I. Murat Cad. 24,",
    "sg:city":"?ekirge",
    "sg:orig_category":"Hotels: Motels",
    "sg:phone":"+90 22423392108",
    "sg:postcode":"16090",
    "sg:province":"Bursa",
    "wof:name":"G?nl?ferah Termal Hotel",
    "wof:placetype":"venue"
},
  "geometry": {"coordinates":[29.0586109161,40.1844291687],"type":"Point"}
}