{
  "type": "Feature",
  "properties": {
    "addr:full":"2. San. Sit. 153. Sk. No:4 Incesu Denizli 32765",
    "addr:housenumber":"2;153",
    "addr:postcode":"32765",
    "addr:street":"San. Sit.;Sk. No 4 Incesu",
    "iso:country":"TR",
    "sg:address":"2. San. Sit. 153. Sk. No:4",
    "sg:city":"Incesu",
    "sg:classifiers":[
        {
            "category":"Home & Garden",
            "subcategory":"Hardware",
            "type":"Retail Goods"
        }
    ],
    "sg:phone":"+90 258 262 2839",
    "sg:postcode":"32765",
    "sg:province":"Denizli",
    "sg:tags":[
        "lathe"
    ],
    "wof:name":"Teknik Torna",
    "wof:placetype":"venue"
},
  "geometry": {"coordinates":[29.0864906311,37.773525238],"type":"Point"}
}