{
  "type": "Feature",
  "properties": {
    "iso:country":"TR",
    "sg:address":"Yeni Sanayi Sitesi 40 Blok Karsisi No:3",
    "sg:city":"Kad\u0131k\u00f6y",
    "sg:classifiers":[
        {
            "category":"Shopping",
            "type":"Retail Goods"
        }
    ],
    "sg:phone":"+90 422 336 3246",
    "sg:postcode":"34752",
    "sg:province":"Malatya",
    "sg:tags":[
        "material",
        "cleaning"
    ],
    "wof:name":"Piriprk Kimya",
    "wof:placetype":"venue"
},
  "geometry": {"coordinates":[38.3195266724,38.3488922119],"type":"Point"}
}