{
  "type": "Feature",
  "properties": {
    "iso:country":"TR",
    "sg:address":"Barbaros Bul 89/1",
    "sg:city":"Istanbul",
    "sg:classifiers":[
        {
            "category":"Banks & Credit Unions",
            "subcategory":"Bank",
            "type":"Services"
        }
    ],
    "sg:phone":"+90 212 258 6586",
    "sg:province":"80960",
    "wof:name":"Sekerbank T?k, Anonim Sirketi",
    "wof:placetype":"venue"
},
  "geometry": {"coordinates":[29.006935,41.043308],"type":"Point"}
}