{
  "type": "Feature",
  "properties": {
    "iso:country":"TR",
    "sg:address":"E.esadbey Cad.no:128/d",
    "sg:city":"Ineg?",
    "sg:classifiers":[
        {
            "category":"Government",
            "subcategory":"Fire Station",
            "type":"Public Place"
        }
    ],
    "sg:phone":"+90 224 715 7408",
    "sg:province":"Bursa",
    "sg:tags":[
        "decoration"
    ],
    "wof:name":"Ozuturk Ltd.sti.",
    "wof:placetype":"venue"
},
  "geometry": {"coordinates":[29.0398807526,40.1076583862],"type":"Point"}
}