{
  "type": "Feature",
  "properties": {
    "addr:full":"Mahmutpasa Cad. Irfaniye ?ar. No:56 Mahmutpasa Istanbul 60100",
    "addr:housenumber":"irfaniye ?;56",
    "addr:postcode":"60100",
    "addr:street":"Mahmutpasa Cad.;Ar. No;Istanbul",
    "iso:country":"TR",
    "sg:address":"Mahmutpasa Cad. Irfaniye ?ar. No:56",
    "sg:city":"Mahmutpasa",
    "sg:classifiers":[
        {
            "category":"Shopping",
            "subcategory":"Clothing, Apparel, & Fashions",
            "type":"Retail Goods"
        }
    ],
    "sg:phone":"+90 212522721252",
    "sg:postcode":"60100",
    "sg:province":"Istanbul",
    "sg:tags":[
        "woman",
        "wear"
    ],
    "wof:name":"?zen Esarp",
    "wof:placetype":"venue"
},
  "geometry": {"coordinates":[28.9759254456,41.0123786926],"type":"Point"}
}