{
  "type": "Feature",
  "properties": {
    "iso:country":"TR",
    "sg:address":"6312 Sk.no:7/a",
    "sg:city":"Semikler",
    "sg:classifiers":[
        {
            "category":"Wholesale",
            "subcategory":"Machinery & Supplies",
            "type":"Manufacturing & Wholesale Goods"
        }
    ],
    "sg:phone":"+90 232 330 4305",
    "sg:postcode":"20085",
    "sg:province":"Izmir",
    "sg:tags":[
        "agricultural"
    ],
    "wof:name":"Herma Makina Insaat Turizm Sanayi Ve Ticaret Ltd.sti.",
    "wof:placetype":"venue"
},
  "geometry": {"coordinates":[27.0890769958,38.4809265137],"type":"Point"}
}