{
  "type": "Feature",
  "properties": {
    "addr:full":"B.dere Cd. C Blok 1.levent Alsancak Istanbul 01365",
    "addr:housenumber":"1.levent",
    "addr:postcode":"01365",
    "addr:street":"B.Dere Cd. C Blok",
    "iso:country":"TR",
    "sg:address":"B.dere Cd. C Blok 1.levent",
    "sg:city":"Alsancak",
    "sg:classifiers":[
        {
            "category":"Manufacturing",
            "subcategory":"Tools & Machinery",
            "type":"Manufacturing & Wholesale Goods"
        }
    ],
    "sg:phone":"+90 212 280 0769",
    "sg:postcode":"01365",
    "sg:province":"Istanbul",
    "sg:tags":[
        "machine",
        "industry"
    ],
    "wof:name":"Dekar Dis Tic. Makina San. A.s.",
    "wof:placetype":"venue"
},
  "geometry": {"coordinates":[28.9759254456,41.0123786926],"type":"Point"}
}