{
  "type": "Feature",
  "properties": {
    "addr:full":"Organize San. 64100 Usak",
    "addr:postcode":"64100",
    "addr:street":"Organize San.",
    "iso:country":"TR",
    "sg:address":"Organize San.",
    "sg:city":"64100",
    "sg:classifiers":[
        {
            "category":"Shopping",
            "subcategory":"Crafts & Fabrics",
            "type":"Retail Goods"
        }
    ],
    "sg:phone":"+90 533 652 0881",
    "sg:province":"Usak",
    "sg:tags":[
        "yarn"
    ],
    "wof:name":"Zeki Tekstil Y?n San. A.s.",
    "wof:placetype":"venue"
},
  "geometry": {"coordinates":[29.4055995941,38.6716003418],"type":"Point"}
}