{
  "type": "Feature",
  "properties": {
    "iso:country":"TR",
    "sg:address":"Monalya Sk. No:24/2 Sisli",
    "sg:city":"Sarigazi",
    "sg:classifiers":[
        {
            "category":"Manufacturing",
            "subcategory":"Glass & Minerals",
            "type":"Manufacturing & Wholesale Goods"
        }
    ],
    "sg:phone":"+90 212 241 2317",
    "sg:postcode":"34785",
    "sg:province":"Istanbul",
    "sg:tags":[
        "glassware"
    ],
    "wof:name":"Sertas Cam Tic. Koll. Sti.",
    "wof:placetype":"venue"
},
  "geometry": {"coordinates":[29.0055770874,41.0542678833],"type":"Point"}
}