{
  "type": "Feature",
  "properties": {
    "addr:full":"Nergis Sok. Tunel Is Hani No: 6 Beyoglu 21100 Istanbul",
    "addr:postcode":"21100",
    "addr:street":"Nergis Sok. Tunel Is;No 6 Beyoglu",
    "iso:country":"TR",
    "sg:address":"Nergis Sok. Tunel Is Hani No: 6 Beyoglu",
    "sg:city":"21100",
    "sg:classifiers":[
        {
            "category":"Professional",
            "subcategory":"Detective & Security Services",
            "type":"Services"
        }
    ],
    "sg:phone":"+90 212 252 8052",
    "sg:province":"Istanbul",
    "sg:tags":[
        "material"
    ],
    "wof:name":"Elsan Guvenlik Sistemleri",
    "wof:placetype":"venue"
},
  "geometry": {"coordinates":[28.967318,41.043106],"type":"Point"}
}