{
  "type": "Feature",
  "properties": {
    "iso:country":"TR",
    "sg:address":"Babayigit Sok. No:1/a Kumkapi",
    "sg:city":"Koca Mustafa Pasa",
    "sg:orig_category":"Printinh House",
    "sg:phone":"+90 212 516 4589",
    "sg:postcode":"34310",
    "sg:province":"Istanbul",
    "wof:name":"Lutuf Yayincilik Ltd.sti.",
    "wof:placetype":"venue"
},
  "geometry": {"coordinates":[28.7125110626,40.9874076843],"type":"Point"}
}