{
  "type": "Feature",
  "properties": {
    "iso:country":"TR",
    "sg:address":"H?revgerede Cd. Sairnazim Sk. No: 3 Tesvikiye",
    "sg:city":"G?ztepe",
    "sg:classifiers":[
        {
            "category":"Banks & Credit Unions",
            "subcategory":"Investment Brokerage",
            "type":"Services"
        }
    ],
    "sg:phone":"+90 212 259 7581",
    "sg:province":"Istanbul",
    "sg:tags":[
        "-",
        "export",
        "import"
    ],
    "wof:name":"C-itc International Trade Communication Center",
    "wof:placetype":"venue"
},
  "geometry": {"coordinates":[29.0004405975,41.0529289246],"type":"Point"}
}