{
  "type": "Feature",
  "properties": {
    "addr:full":"Mustafa Kemal Bulvari 609,sok. No: 8 Fethiye \u00c7orlu Mugla",
    "addr:housenumber":"609;no 8",
    "addr:street":"Mustafa Kemal Bulvari;Sok.",
    "iso:country":"TR",
    "sg:address":"Mustafa Kemal Bulvari 609,sok. No: 8 Fethiye",
    "sg:city":"\u00c7orlu",
    "sg:classifiers":[
        {
            "category":"Shopping",
            "subcategory":"Luggage & Leather Goods",
            "type":"Retail Goods"
        }
    ],
    "sg:phone":"+90 252 612 5789",
    "sg:province":"Mugla",
    "sg:tags":[
        "leather-fur",
        "wear"
    ],
    "wof:name":"Proledo",
    "wof:placetype":"venue"
},
  "geometry": {"coordinates":[29.1249351501,36.6303596497],"type":"Point"}
}