{
  "type": "Feature",
  "properties": {
    "iso:country":"TR",
    "sg:address":"Baris Meydani",
    "sg:city":"Bodrum",
    "sg:classifiers":[
        {
            "category":"Landmark",
            "subcategory":"Tourist Information",
            "type":"Public Place"
        }
    ],
    "sg:phone":"+90 252 316 1091",
    "sg:postcode":"48400",
    "sg:province":"Mugla",
    "sg:tags":[
        "tourism"
    ],
    "wof:name":"Turizm Danisma Burosu",
    "wof:placetype":"venue"
},
  "geometry": {"coordinates":[28.3628406525,37.215675354],"type":"Point"}
}