{
  "type": "Feature",
  "properties": {
    "addr:full":"Ihlamur Nisantasi Yolu No.36/3 Tesvikiye Istanbul 43270",
    "addr:housenumber":"no.36 / 3",
    "addr:postcode":"43270",
    "addr:street":"Nisantasi Yolu",
    "iso:country":"TR",
    "sg:address":"Ihlamur Nisantasi Yolu No.36/3",
    "sg:city":"Tesvikiye",
    "sg:classifiers":[
        {
            "category":"Freight",
            "type":"Transportation"
        }
    ],
    "sg:phone":"+90 212 230 1487",
    "sg:postcode":"43270",
    "sg:province":"Istanbul",
    "sg:tags":[
        "agent",
        "shipping",
        "broker"
    ],
    "wof:name":"Avrasya Ekspres Denizcilik Ltd.sti.",
    "wof:placetype":"venue"
},
  "geometry": {"coordinates":[28.993668,41.050251],"type":"Point"}
}