{
  "type": "Feature",
  "properties": {
    "addr:full":"Cevizli Mah. Muhtar Halit Kral Sok. Sekizler Apt. D:10 Bakirkoy Ikitelli/K\u00fc\u00e7\u00fck\u00e7ekmece Istanbul 34670",
    "addr:housenumber":"10",
    "addr:postcode":"34670",
    "addr:street":"Mah. Muhtar Halit Kral Sok. Sekizler Apt. D",
    "iso:country":"TR",
    "sg:address":"Cevizli Mah. Muhtar Halit Kral Sok. Sekizler Apt. D:10 Bakirkoy",
    "sg:city":"Ikitelli/K\u00fc\u00e7\u00fck\u00e7ekmece",
    "sg:orig_category":"Printinh House",
    "sg:phone":"+90 212 660 7744",
    "sg:postcode":"34670",
    "sg:province":"Istanbul",
    "wof:name":"Hologram Etiket Aksesuar San.tic.a.s.",
    "wof:placetype":"venue"
},
  "geometry": {"coordinates":[28.9759254456,41.0123786926],"type":"Point"}
}