{
  "type": "Feature",
  "properties": {
    "iso:country":"TR",
    "sg:address":"Aksaray Cad.no:3/1",
    "sg:city":"Laleli",
    "sg:classifiers":[
        {
            "category":"Shopping",
            "subcategory":"Clothing, Apparel, & Fashions",
            "type":"Retail Goods"
        }
    ],
    "sg:phone":"+90 212 518 7676",
    "sg:postcode":"24300",
    "sg:province":"Istanbul",
    "sg:tags":[
        "men",
        "wear"
    ],
    "wof:name":"Kusanal Konfeksiyon",
    "wof:placetype":"venue"
},
  "geometry": {"coordinates":[28.9552135468,41.0093345642],"type":"Point"}
}