{
  "type": "Feature",
  "properties": {
    "iso:country":"TR",
    "sg:address":"1202/2 Sok. No:4 Gida Carsisi",
    "sg:city":"Mersin",
    "sg:classifiers":[
        {
            "category":"Wholesale",
            "subcategory":"Plants",
            "type":"Manufacturing & Wholesale Goods"
        }
    ],
    "sg:phone":"+90 232 433 5465",
    "sg:postcode":"52750",
    "sg:province":"Izmir",
    "sg:tags":[
        "natural",
        "spice"
    ],
    "wof:name":"Aydoganlar Kahve Baharat Gida San.ltd.",
    "wof:placetype":"venue"
},
  "geometry": {"coordinates":[27.129686,38.418697],"type":"Point"}
}