{
  "type": "Feature",
  "properties": {
    "iso:country":"TR",
    "sg:address":"Gumussuyu Cad.hastane Yolu No.1 Maltepe-topkapi",
    "sg:city":"Kavaklidere",
    "sg:classifiers":[
        {
            "category":"Banks & Credit Unions",
            "subcategory":"Financial Services",
            "type":"Services"
        }
    ],
    "sg:phone":"+90 212 567 9550",
    "sg:postcode":"35040",
    "sg:province":"Istanbul",
    "sg:tags":[
        "consultant"
    ],
    "wof:name":"Hasan Gurses",
    "wof:placetype":"venue"
},
  "geometry": {"coordinates":[28.9082984924,41.0285644531],"type":"Point"}
}