{
  "type": "Feature",
  "properties": {
    "addr:full":"Sururi Mah.h.k?? Sok.havuzlu Han.no 20/20 Sultanhamam Emin\u00f6n\u00fc/Ca\u011falo\u011flu Istanbul 34110",
    "addr:housenumber":"20 / 20",
    "addr:postcode":"34110",
    "addr:street":"Han.No",
    "iso:country":"TR",
    "sg:address":"Sururi Mah.h.k?? Sok.havuzlu Han.no 20/20 Sultanhamam",
    "sg:city":"Emin\u00f6n\u00fc/Ca\u011falo\u011flu",
    "sg:classifiers":[
        {
            "category":"Shopping",
            "subcategory":"Clothing, Apparel, & Fashions",
            "type":"Retail Goods"
        }
    ],
    "sg:phone":"+90 212 513 4822",
    "sg:postcode":"34110",
    "sg:province":"Istanbul",
    "sg:tags":[
        "night",
        "-engagement",
        "dress",
        "wedding"
    ],
    "sg:website":"ipekteks.com",
    "wof:name":"Ipek Tex Aplik Dantel Gip?r Imalat",
    "wof:placetype":"venue"
},
  "geometry": {"coordinates":[28.9759254456,41.0123786926],"type":"Point"}
}