{
  "type": "Feature",
  "properties": {
    "addr:full":"Organize San.bol.9.cad. Samandra Eskisehir",
    "addr:housenumber":"san.bol.9.cad",
    "addr:street":"Organize",
    "iso:country":"TR",
    "sg:address":"Organize San.bol.9.cad.",
    "sg:city":"Samandra",
    "sg:classifiers":[
        {
            "category":"Food & Beverages",
            "subcategory":"Candy",
            "type":"Retail Goods"
        }
    ],
    "sg:phone":"+90 222 236 0255",
    "sg:province":"Eskisehir",
    "sg:tags":[
        "biscuit-chocolate-candy"
    ],
    "wof:name":"Aslan Susam Ve Tahin Gida Mad.san.tic.ltd.sti.",
    "wof:placetype":"venue"
},
  "geometry": {"coordinates":[30.517546,39.770081],"type":"Point"}
}