{
  "type": "Feature",
  "properties": {
    "iso:country":"TR",
    "sg:address":"Karaman",
    "sg:city":"Karabaglar",
    "sg:classifiers":[
        {
            "category":"Government",
            "subcategory":"Office",
            "type":"Public Place"
        }
    ],
    "sg:phone":"+90 338 213 1674",
    "sg:postcode":"44210",
    "sg:province":"Karaman",
    "sg:tags":[
        "army"
    ],
    "wof:name":"Karaman (ayranci, K.k.bekir) Askerlik Subesi",
    "wof:placetype":"venue"
},
  "geometry": {"coordinates":[33.2233543396,37.1807861328],"type":"Point"}
}