{
  "type": "Feature",
  "properties": {
    "addr:full":"Yat Limani Karsisi Ayvalik Balikesir 01680",
    "addr:postcode":"01680",
    "addr:street":"Balikesir",
    "iso:country":"TR",
    "sg:address":"Yat Limani Karsisi",
    "sg:city":"Ayvalik",
    "sg:classifiers":[
        {
            "category":"Landmark",
            "subcategory":"Tourist Information",
            "type":"Public Place"
        }
    ],
    "sg:phone":"+90 266 324 2122",
    "sg:postcode":"01680",
    "sg:province":"Balikesir",
    "sg:tags":[
        "tourism"
    ],
    "wof:name":"Turizm Danisma Burosu",
    "wof:placetype":"venue"
},
  "geometry": {"coordinates":[27.8853626251,39.6448822021],"type":"Point"}
}