{
  "type": "Feature",
  "properties": {
    "addr:full":"Vahapbey Sok. 12/4 Kadik? G?g?en Istanbul 34000",
    "addr:housenumber":"12 / 4 kadik ? g ? g ?",
    "addr:postcode":"34000",
    "addr:street":"Vahapbey Sok.",
    "iso:country":"TR",
    "sg:address":"Vahapbey Sok. 12/4 Kadik?",
    "sg:city":"G?g?en",
    "sg:classifiers":[
        {
            "category":"Manufacturing",
            "subcategory":"Leather Goods",
            "type":"Manufacturing & Wholesale Goods"
        }
    ],
    "sg:phone":"+90 216 336 2841",
    "sg:postcode":"34000",
    "sg:province":"Istanbul",
    "wof:name":"Kitaplioglu Leather Ltd.sti.",
    "wof:placetype":"venue"
},
  "geometry": {"coordinates":[28.9759254456,41.0123786926],"type":"Point"}
}