{
  "type": "Feature",
  "properties": {
    "addr:full":"Hasanpasa Mah. Kurbaglidere Cad. No: 25/2-a K: 1 D: 2 Kad\u0131k\u00f6y Istanbul 34990",
    "addr:housenumber":"25 / 2-a k 1 d 2",
    "addr:postcode":"34990",
    "addr:street":"Hasanpasa Mah. Kurbaglidere Cad. No",
    "iso:country":"TR",
    "sg:address":"Hasanpasa Mah. Kurbaglidere Cad. No: 25/2-a K: 1 D: 2",
    "sg:city":"Kad\u0131k\u00f6y",
    "sg:classifiers":[
        {
            "category":"Travel",
            "subcategory":"Travel Agent",
            "type":"Entertainment"
        }
    ],
    "sg:phone":"+90 414623839",
    "sg:postcode":"34990",
    "sg:province":"Istanbul",
    "sg:tags":[
        "agency",
        "tourism"
    ],
    "wof:name":"Meteor Turizm",
    "wof:placetype":"venue"
},
  "geometry": {"coordinates":[28.9861831665,41.0408554077],"type":"Point"}
}