{
  "type": "Feature",
  "properties": {
    "iso:country":"TR",
    "sg:address":"Akdeniz Cad. H?revpasa Sk. No:5",
    "sg:city":"Fatih",
    "sg:classifiers":[
        {
            "category":"Shopping",
            "subcategory":"Clothing, Apparel, & Fashions",
            "type":"Retail Goods"
        }
    ],
    "sg:phone":"+90 212 524 5582",
    "sg:postcode":"01740",
    "sg:province":"Istanbul",
    "sg:tags":[
        "woman",
        "wear"
    ],
    "wof:name":"G?rler Giyim",
    "wof:placetype":"venue"
},
  "geometry": {"coordinates":[28.9759254456,41.0123786926],"type":"Point"}
}