{
  "type": "Feature",
  "properties": {
    "iso:country":"TR",
    "sg:address":"A. Ipek? Cd. Polat Sk. No:33-5/10 Bayrampasa",
    "sg:city":"\u00dcmraniye",
    "sg:classifiers":[
        {
            "category":"Manufacturing",
            "subcategory":"Tools & Machinery",
            "type":"Manufacturing & Wholesale Goods"
        }
    ],
    "sg:phone":"+90 212 567 7426",
    "sg:province":"Istanbul",
    "sg:tags":[
        "machine",
        "industry"
    ],
    "wof:name":"?ava Makina San.",
    "wof:placetype":"venue"
},
  "geometry": {"coordinates":[28.8756809235,41.0159187317],"type":"Point"}
}