{
  "type": "Feature",
  "properties": {
    "addr:full":"Cebeci Cd. No:115 K??k? Bornova Istanbul 35040",
    "addr:housenumber":"no 115 k ? ? k ?",
    "addr:postcode":"35040",
    "addr:street":"Cebeci Cd.",
    "iso:country":"TR",
    "sg:address":"Cebeci Cd. No:115 K??k?",
    "sg:city":"Bornova",
    "sg:classifiers":[
        {
            "category":"Manufacturing",
            "subcategory":"Tools & Machinery",
            "type":"Manufacturing & Wholesale Goods"
        }
    ],
    "sg:phone":"+90 2125780106329",
    "sg:postcode":"35040",
    "sg:province":"Istanbul",
    "sg:tags":[
        "machine",
        "industry"
    ],
    "wof:name":"Yaparlar Ins. Tarim Alet. San. Tic. Ltd. Sti.",
    "wof:placetype":"venue"
},
  "geometry": {"coordinates":[28.5338592529,41.0272712708],"type":"Point"}
}