{
  "type": "Feature",
  "properties": {
    "iso:country":"TR",
    "sg:address":"Dua?nar Mah. Ugur Sk. No:7",
    "sg:city":"Yildirim",
    "sg:classifiers":[
        {
            "category":"Professional",
            "subcategory":"Business Services",
            "type":"Services"
        }
    ],
    "sg:phone":"+90 224 361 1618",
    "sg:postcode":"03300",
    "sg:province":"Bursa",
    "sg:tags":[
        "industry",
        "casting"
    ],
    "wof:name":"Aydin Oto ?zd??",
    "wof:placetype":"venue"
},
  "geometry": {"coordinates":[29.0586109161,40.1844291687],"type":"Point"}
}