{
  "type": "Feature",
  "properties": {
    "addr:full":"Cumhuriyet Cad. No: 295 Harbiye Istanbul 31080",
    "addr:housenumber":"295",
    "addr:postcode":"31080",
    "addr:street":"Cumhuriyet Cad. No",
    "iso:country":"TR",
    "sg:address":"Cumhuriyet Cad. No: 295",
    "sg:city":"Harbiye",
    "sg:classifiers":[
        {
            "category":"Travel",
            "subcategory":"Travel Agent",
            "type":"Entertainment"
        }
    ],
    "sg:phone":"+90 2344300",
    "sg:postcode":"31080",
    "sg:province":"Istanbul",
    "sg:tags":[
        "agency",
        "tourism"
    ],
    "wof:name":"Ekin Turizm",
    "wof:placetype":"venue"
},
  "geometry": {"coordinates":[29.1112823486,41.0926208496],"type":"Point"}
}