{
  "type": "Feature",
  "properties": {
    "addr:full":"2. San. Sit. 140. Sk. Ikitelli/K\u00fc\u00e7\u00fck\u00e7ekmece Denizli 34660",
    "addr:housenumber":"2;140",
    "addr:postcode":"34660",
    "addr:street":"San. Sit.",
    "iso:country":"TR",
    "sg:address":"2. San. Sit. 140. Sk.",
    "sg:city":"Ikitelli/K\u00fc\u00e7\u00fck\u00e7ekmece",
    "sg:classifiers":[
        {
            "category":"Home & Garden",
            "subcategory":"Hardware",
            "type":"Retail Goods"
        }
    ],
    "sg:phone":"+90 258 371 1515",
    "sg:postcode":"34660",
    "sg:province":"Denizli",
    "sg:tags":[
        "lathe"
    ],
    "wof:name":"G?nes Torna",
    "wof:placetype":"venue"
},
  "geometry": {"coordinates":[29.0864906311,37.773525238],"type":"Point"}
}