{
  "type": "Feature",
  "properties": {
    "addr:full":"Ragip Bey Mah. 151.sok. No:65 Akhisar Salipazari Manisa 80040",
    "addr:housenumber":"65",
    "addr:postcode":"80040",
    "addr:street":"Mah. 151.Sok No",
    "iso:country":"TR",
    "sg:address":"Ragip Bey Mah. 151.sok. No:65 Akhisar",
    "sg:city":"Salipazari",
    "sg:classifiers":[
        {
            "category":"Building & Trades",
            "subcategory":"Construction",
            "type":"Services"
        }
    ],
    "sg:phone":"+90 236 414 9524",
    "sg:postcode":"80040",
    "sg:province":"Manisa",
    "sg:tags":[
        "foundation"
    ],
    "wof:name":"Hilaliye Egitim Vakfi",
    "wof:placetype":"venue"
},
  "geometry": {"coordinates":[27.4297008514,38.6222000122],"type":"Point"}
}