{
  "type": "Feature",
  "properties": {
    "iso:country":"TR",
    "sg:address":"B??dere Cad. No. 155 / 6 Zincirlikuyu",
    "sg:city":"Mersin",
    "sg:classifiers":[
        {
            "category":"Personal",
            "subcategory":"Sauna",
            "type":"Services"
        }
    ],
    "sg:phone":"+90 212 274 0350",
    "sg:postcode":"52750",
    "sg:province":"Istanbul",
    "sg:tags":[
        "pool"
    ],
    "wof:name":"Bedsamak Turizm Tic.ltd.sti.",
    "wof:placetype":"venue"
},
  "geometry": {"coordinates":[28.953873,41.040646],"type":"Point"}
}