{
  "type": "Feature",
  "properties": {
    "iso:country":"TR",
    "sg:address":"Altiayak Mah. Fevzi ?kmak Cad. No :181",
    "sg:city":"Varsak",
    "sg:classifiers":[
        {
            "category":"Farming",
            "subcategory":"Poultry Farm",
            "type":"Manufacturing & Wholesale Goods"
        }
    ],
    "sg:phone":"+90 242 464 1411",
    "sg:postcode":"07210",
    "sg:province":"Antalya",
    "sg:tags":[
        "poultry-turkey-ostrich"
    ],
    "wof:name":"Imsanay",
    "wof:placetype":"venue"
},
  "geometry": {"coordinates":[30.7091274261,36.9560546875],"type":"Point"}
}