{
  "type": "Feature",
  "properties": {
    "iso:country":"TR",
    "sg:address":"Mesrutiyet Cd. No:10/22 Kizilay",
    "sg:city":"Mecidiyek\u00f6y",
    "sg:classifiers":[
        {
            "category":"Shopping",
            "subcategory":"Photographic Equipment",
            "type":"Retail Goods"
        }
    ],
    "sg:phone":"+90 312 418 7143",
    "sg:province":"Ankara",
    "sg:tags":[
        "photo"
    ],
    "wof:name":"Slayt Fotograf. Tanitim",
    "wof:placetype":"venue"
},
  "geometry": {"coordinates":[32.8581085205,39.9183082581],"type":"Point"}
}