{
  "type": "Feature",
  "properties": {
    "addr:full":"859.sk. No: 4 Kat: 1/102 Sogutlu Is Hani Konak Sirkeci Izmir 34102",
    "addr:housenumber":"no 4 kat 1 / 102",
    "addr:postcode":"34102",
    "addr:street":"859.Sk;Sogutlu Is",
    "iso:country":"TR",
    "sg:address":"859.sk. No: 4 Kat: 1/102 Sogutlu Is Hani Konak",
    "sg:city":"Sirkeci",
    "sg:classifiers":[
        {
            "category":"Banks & Credit Unions",
            "subcategory":"Investment Brokerage",
            "type":"Services"
        }
    ],
    "sg:phone":"+90 232 425 5517",
    "sg:postcode":"34102",
    "sg:province":"Izmir",
    "sg:tags":[
        "-",
        "export",
        "import"
    ],
    "wof:name":"Dac Sanayi Ticaret Ltd. Sti.",
    "wof:placetype":"venue"
},
  "geometry": {"coordinates":[27.1423015594,38.4251480103],"type":"Point"}
}