{
  "type": "Feature",
  "properties": {
    "addr:full":"Haciorta Mevkii Y.kucuk San.sit.d Blok Ada No:12 Merkez Kastamonu 10100",
    "addr:housenumber":"blok ada no 12",
    "addr:postcode":"10100",
    "addr:street":"Haciorta Mevkii Y.Kucuk San.Sit.D;Merkez",
    "iso:country":"TR",
    "sg:address":"Haciorta Mevkii Y.kucuk San.sit.d Blok Ada No:12",
    "sg:city":"Merkez",
    "sg:classifiers":[
        {
            "category":"Food & Beverages",
            "subcategory":"Candy",
            "type":"Retail Goods"
        }
    ],
    "sg:phone":"+90 366 215 1501",
    "sg:postcode":"10100",
    "sg:province":"Kastamonu",
    "sg:tags":[
        "biscuit-chocolate-candy"
    ],
    "wof:name":"Sipahioglu Gida Iml.paz Ic Ve Dis Tic.ltd.sti.",
    "wof:placetype":"venue"
},
  "geometry": {"coordinates":[33.7719,41.372299],"type":"Point"}
}