{
  "type": "Feature",
  "properties": {
    "addr:full":"Semsettin G. Cd. No: 219/21 Erenk? Istanbul",
    "addr:housenumber":"no;/ 21;?",
    "addr:street":"Semsettin G. Cd.;Erenk",
    "iso:country":"TR",
    "sg:address":"Semsettin G. Cd. No: 219/21",
    "sg:city":"Erenk?",
    "sg:classifiers":[
        {
            "category":"Home & Garden",
            "subcategory":"Household Appliances",
            "type":"Retail Goods"
        }
    ],
    "sg:phone":"+90 216 368 1722",
    "sg:province":"Istanbul",
    "sg:tags":[
        "conditioner",
        "air"
    ],
    "wof:name":"Yapites Dogalgaz Isi Sistem. Ltd.",
    "wof:placetype":"venue"
},
  "geometry": {"coordinates":[29.0928344727,40.9613723755],"type":"Point"}
}