{
  "type": "Feature",
  "properties": {
    "addr:full":"Bakircilar San. Sitesi Merkez Mah. Orkide Cad. No:13/15 Buyukcekmece Istanbul 34500",
    "addr:housenumber":"13 / 15",
    "addr:postcode":"34500",
    "addr:street":"Merkez Mah. Orkide Cad. No;Istanbul",
    "iso:country":"TR",
    "sg:address":"Bakircilar San. Sitesi Merkez Mah. Orkide Cad. No:13/15",
    "sg:city":"Buyukcekmece",
    "sg:classifiers":[
        {
            "category":"Manufacturing",
            "subcategory":"Textiles",
            "type":"Manufacturing & Wholesale Goods"
        }
    ],
    "sg:phone":"+90 212 875 7180",
    "sg:postcode":"34500",
    "sg:province":"Istanbul",
    "sg:tags":[
        "product"
    ],
    "wof:name":"Genel Tekstil Sanayi Ve Ticaret A.s.",
    "wof:placetype":"venue"
},
  "geometry": {"coordinates":[28.9759254456,41.0123786926],"type":"Point"}
}