{
  "type": "Feature",
  "properties": {
    "iso:country":"TR",
    "sg:address":"Izmir Asfalti ?zeri 5.km. 09020",
    "sg:city":"Top?lar",
    "sg:classifiers":[
        {
            "category":"Wholesale",
            "subcategory":"Machinery & Supplies",
            "type":"Manufacturing & Wholesale Goods"
        }
    ],
    "sg:phone":"+90 256 225 1257",
    "sg:province":"Aydin",
    "sg:tags":[
        "agricultural"
    ],
    "wof:name":"Alpler Ziraat Aletleri San.ve Tic.a.s.",
    "wof:placetype":"venue"
},
  "geometry": {"coordinates":[27.8230819702,37.8370056152],"type":"Point"}
}