{
  "type": "Feature",
  "properties": {
    "addr:full":"Haskoy Yolu 1500 Ml. Bademli Bursa 07665",
    "addr:housenumber":"1500",
    "addr:postcode":"ml.;07665",
    "addr:street":"Haskoy Yolu",
    "iso:country":"TR",
    "sg:address":"Haskoy Yolu 1500 Ml.",
    "sg:city":"Bademli",
    "sg:classifiers":[
        {
            "category":"Home & Garden",
            "subcategory":"Building Materials",
            "type":"Retail Goods"
        }
    ],
    "sg:phone":"+90 224 244 9461",
    "sg:postcode":"07665",
    "sg:province":"Bursa",
    "sg:tags":[
        "stone",
        "natural",
        "marble"
    ],
    "wof:name":"Mertop Mermer Toprak San.ve Tic.tic.a.s.",
    "wof:placetype":"venue"
},
  "geometry": {"coordinates":[29.0586109161,40.1844291687],"type":"Point"}
}