{
  "type": "Feature",
  "properties": {
    "addr:full":"Dogancilar Cd. No:32 \u00dcsk\u00fcdar Istanbul 34672",
    "addr:housenumber":"no 32",
    "addr:postcode":"34672",
    "addr:street":"Dogancilar Cd.;Istanbul",
    "iso:country":"TR",
    "sg:address":"Dogancilar Cd. No:32",
    "sg:city":"\u00dcsk\u00fcdar",
    "sg:classifiers":[
        {
            "category":"Utilities",
            "subcategory":"Natural Gas",
            "type":"Services"
        }
    ],
    "sg:phone":"+90 216 333 0437",
    "sg:postcode":"34672",
    "sg:province":"Istanbul",
    "sg:tags":[
        "tank-heating-natural"
    ],
    "wof:name":"Karakulluk?ular Insaat Tic. Koll. Sti.",
    "wof:placetype":"venue"
},
  "geometry": {"coordinates":[29.01288414,41.0248146057],"type":"Point"}
}