{
  "type": "Feature",
  "properties": {
    "addr:full":"39. Sk.no.90/2 Zeytinburnu Zeytinburnu Istanbul 34020",
    "addr:housenumber":"sk.no.90 / 2",
    "addr:postcode":"34020",
    "addr:street":"Zeytinburnu",
    "iso:country":"TR",
    "sg:address":"39. Sk.no.90/2 Zeytinburnu",
    "sg:city":"Zeytinburnu",
    "sg:classifiers":[
        {
            "category":"Manufacturing",
            "subcategory":"Leather Goods",
            "type":"Manufacturing & Wholesale Goods"
        }
    ],
    "sg:phone":"+90 212 582 9670",
    "sg:postcode":"34020",
    "sg:province":"Istanbul",
    "wof:name":"Atik Deri San.ltd.sti.",
    "wof:placetype":"venue"
},
  "geometry": {"coordinates":[28.9102840424,40.9917831421],"type":"Point"}
}