{
  "type": "Feature",
  "properties": {
    "iso:country":"TR",
    "sg:address":"?iftehavuzlar Yolu No.3 Topkapi",
    "sg:city":"Gebze",
    "sg:classifiers":[
        {
            "category":"Shopping",
            "subcategory":"Shoes",
            "type":"Retail Goods"
        }
    ],
    "sg:phone":"+90 212 576 0716",
    "sg:postcode":"41400",
    "sg:province":"Istanbul",
    "wof:name":"Ziylan Ayakk. San. A.s.",
    "wof:placetype":"venue"
},
  "geometry": {"coordinates":[28.926207,41.016487],"type":"Point"}
}