{
  "type": "Feature",
  "properties": {
    "iso:country":"TR",
    "sg:address":"Tahtakale Uzun?rsi Cd. B??okur Han No:10/1 Emin?? Istanbul",
    "sg:city":"Yukari Dudullu",
    "sg:classifiers":[
        {
            "category":"Manufacturing",
            "subcategory":"Rubber & Plastics",
            "type":"Manufacturing & Wholesale Goods"
        }
    ],
    "sg:phone":"+90 212 513 0219",
    "sg:postcode":"34776",
    "sg:province":"Istanbul",
    "sg:tags":[
        "industry"
    ],
    "wof:name":"Altun Plastik Kagit Ambalaj San. Tic.",
    "wof:placetype":"venue"
},
  "geometry": {"coordinates":[29.175403595,41.0060424805],"type":"Point"}
}