{
  "type": "Feature",
  "properties": {
    "iso:country":"TR",
    "sg:address":"Yayalar Mh. Tuncel Sk. Pendik",
    "sg:city":"Konak",
    "sg:classifiers":[
        {
            "category":"Wholesale",
            "subcategory":"Furniture",
            "type":"Manufacturing & Wholesale Goods"
        }
    ],
    "sg:phone":"+90 216 307 2848",
    "sg:postcode":"07110",
    "sg:province":"Istanbul",
    "sg:tags":[
        "school"
    ],
    "wof:name":"Akkus Sandalye",
    "wof:placetype":"venue"
},
  "geometry": {"coordinates":[29.266747,40.896454],"type":"Point"}
}