{
  "type": "Feature",
  "properties": {
    "addr:full":"Ankara Yolu 7. Km. Gunesli Denizli 01660",
    "addr:housenumber":"7 km.",
    "addr:postcode":"01660",
    "addr:street":"Ankara Yolu;Gunesli Denizli",
    "iso:country":"TR",
    "sg:address":"Ankara Yolu 7. Km.",
    "sg:city":"Gunesli",
    "sg:classifiers":[
        {
            "category":"Shopping",
            "subcategory":"Clothing, Apparel, & Fashions",
            "type":"Retail Goods"
        }
    ],
    "sg:phone":"+90 258 268 3290",
    "sg:postcode":"01660",
    "sg:province":"Denizli",
    "sg:tags":[
        "ready",
        "wear"
    ],
    "wof:name":"Akdem Tekstil Boya Ve Konfeksiyon Ltd.sti.",
    "wof:placetype":"venue"
},
  "geometry": {"coordinates":[29.0864906311,37.773525238],"type":"Point"}
}