{
  "type": "Feature",
  "properties": {
    "iso:country":"TR",
    "sg:address":"Prof. Cemil B. Cd. No:26/1306",
    "sg:city":"Tahtakale",
    "sg:classifiers":[
        {
            "category":"Manufacturing",
            "subcategory":"Glass & Minerals",
            "type":"Manufacturing & Wholesale Goods"
        }
    ],
    "sg:phone":"+90 212 528 3866",
    "sg:postcode":"16040",
    "sg:province":"Istanbul",
    "sg:tags":[
        "glass-mirror"
    ],
    "wof:name":"?elik Ayna San. A.s.",
    "wof:placetype":"venue"
},
  "geometry": {"coordinates":[28.9668426514,41.0169754028],"type":"Point"}
}