{
  "type": "Feature",
  "properties": {
    "addr:full":"Tepecik Mah.in??cad. Kural Apt.no:122/1 Findikzade Kocaeli 34270",
    "addr:housenumber":"122 / 1",
    "addr:postcode":"34270",
    "addr:street":"? Cad. Kural Apt.No;Findikzade Kocaeli",
    "iso:country":"TR",
    "sg:address":"Tepecik Mah.in??cad. Kural Apt.no:122/1",
    "sg:city":"Findikzade",
    "sg:classifiers":[
        {
            "category":"Wholesale",
            "subcategory":"Medical Equipment & Supplies",
            "type":"Manufacturing & Wholesale Goods"
        }
    ],
    "sg:phone":"+90 262 332 3037",
    "sg:postcode":"34270",
    "sg:province":"Kocaeli",
    "wof:name":"Beray Isitme Merkezi",
    "wof:placetype":"venue"
},
  "geometry": {"coordinates":[29.9345855713,40.7669563293],"type":"Point"}
}