{
  "type": "Feature",
  "properties": {
    "addr:full":"Eski Kepsut Yolu Koseler Koyu Karsisi Benzinlik Arkasi Tarsus Balikesir 33400",
    "addr:housenumber":"koseler koyu",
    "addr:postcode":"33400",
    "addr:street":"Eski Kepsut Yolu;Balikesir",
    "iso:country":"TR",
    "sg:address":"Eski Kepsut Yolu Koseler Koyu Karsisi Benzinlik Arkasi",
    "sg:city":"Tarsus",
    "sg:classifiers":[
        {
            "category":"Farming",
            "subcategory":"Livestock Farm",
            "type":"Manufacturing & Wholesale Goods"
        }
    ],
    "sg:phone":"+90 266 246 4844",
    "sg:postcode":"33400",
    "sg:province":"Balikesir",
    "sg:tags":[
        "fattening-breeding"
    ],
    "wof:name":"Deger Besi Ciftligi",
    "wof:placetype":"venue"
},
  "geometry": {"coordinates":[27.8833007812,39.6520996094],"type":"Point"}
}