{
  "type": "Feature",
  "properties": {
    "iso:country":"TR",
    "sg:address":"Belediye ?rs. No.70",
    "sg:city":"Kapilar",
    "sg:classifiers":[
        {
            "category":"Farming",
            "subcategory":"Poultry Farm",
            "type":"Manufacturing & Wholesale Goods"
        }
    ],
    "sg:phone":"+90 272 215 3092",
    "sg:province":"Afyon",
    "sg:tags":[
        "poultry-turkey-ostrich"
    ],
    "wof:name":"Birlik Tavuk?uluk A.s.",
    "wof:placetype":"venue"
},
  "geometry": {"coordinates":[30.5417995453,38.7557983398],"type":"Point"}
}