{
  "type": "Feature",
  "properties": {
    "iso:country":"TR",
    "sg:address":"2296.sok.alyaz Is Merkezi No: 1 Kibrishane",
    "sg:city":"Ikitelli/K\u00fc\u00e7\u00fck\u00e7ekmece",
    "sg:classifiers":[
        {
            "category":"Wholesale",
            "subcategory":"Machinery & Supplies",
            "type":"Manufacturing & Wholesale Goods"
        }
    ],
    "sg:phone":"+90 258 251 6027",
    "sg:postcode":"34670",
    "sg:province":"Denizli",
    "sg:tags":[
        "heavy",
        "construction",
        "macinery"
    ],
    "wof:name":"Sahlan Tarim Is Mak. San. A.s.",
    "wof:placetype":"venue"
},
  "geometry": {"coordinates":[29.0788803101,37.7851867676],"type":"Point"}
}