{
  "type": "Feature",
  "properties": {
    "iso:country":"TR",
    "sg:address":"Mithatpasa Cad.1987 Sok. No:22 Bal?va",
    "sg:city":"Bayrampasa",
    "sg:classifiers":[
        {
            "category":"Sports & Exercise",
            "subcategory":"Ski Slope",
            "type":"Entertainment"
        }
    ],
    "sg:phone":"+90 232 462 0589",
    "sg:postcode":"36100",
    "sg:province":"Izmir",
    "sg:tags":[
        "wear"
    ],
    "wof:name":"Prenses Nakis Konf.ltd.",
    "wof:placetype":"venue"
},
  "geometry": {"coordinates":[27.129686,38.418697],"type":"Point"}
}