{
  "type": "Feature",
  "properties": {
    "addr:full":"Uzuncayir Cad. No: 26 /2 Hasanpasa- Kadikoy Istanbul 01370",
    "addr:housenumber":"26 / 2",
    "addr:postcode":"01370",
    "addr:street":"Uzuncayir Cad. No;Hasanpasa Kadikoy",
    "iso:country":"TR",
    "sg:address":"Uzuncayir Cad. No: 26 /2 Hasanpasa-",
    "sg:city":"Kadikoy",
    "sg:classifiers":[
        {
            "category":"Manufacturing",
            "subcategory":"Food",
            "type":"Manufacturing & Wholesale Goods"
        }
    ],
    "sg:phone":"+90 216 545 0273",
    "sg:postcode":"01370",
    "sg:province":"Istanbul",
    "sg:tags":[
        "wholesaler"
    ],
    "wof:name":"Temsilciler Gida Itriyat Kirt.san.tic. Ltd.sti.",
    "wof:placetype":"venue"
},
  "geometry": {"coordinates":[29.0448627472,40.9957809448],"type":"Point"}
}