{
  "type": "Feature",
  "properties": {
    "iso:country":"TR",
    "sg:address":"Huzur Mah.3.cad.no:51/b A.ovecler",
    "sg:city":"Alsancak",
    "sg:classifiers":[
        {
            "category":"Professional",
            "subcategory":"Detective & Security Services",
            "type":"Services"
        }
    ],
    "sg:phone":"+90 312 475 2200",
    "sg:postcode":"35210",
    "sg:province":"Ankara",
    "sg:tags":[
        "material"
    ],
    "wof:name":"Globalnet Global Internet Teknolojileri Ltd.",
    "wof:placetype":"venue"
},
  "geometry": {"coordinates":[32.821163,39.882557],"type":"Point"}
}