{
  "type": "Feature",
  "properties": {
    "iso:country":"TR",
    "sg:address":"Sirer Cad. Saglik Sitesi Kat: 3 No: 21",
    "sg:city":"Merkez",
    "sg:classifiers":[
        {
            "category":"Wholesale",
            "subcategory":"Medical Equipment & Supplies",
            "type":"Manufacturing & Wholesale Goods"
        }
    ],
    "sg:phone":"+90 346 223 9845",
    "sg:postcode":"26000",
    "sg:province":"Sivas",
    "sg:tags":[
        "material"
    ],
    "wof:name":"Seray Medikal",
    "wof:placetype":"venue"
},
  "geometry": {"coordinates":[37.01720047,39.751499176],"type":"Point"}
}