{
  "type": "Feature",
  "properties": {
    "addr:full":"Cark San.no: 50 Bandirma Sakarya 10200",
    "addr:housenumber":"50",
    "addr:postcode":"10200",
    "iso:country":"TR",
    "sg:address":"Cark San.no: 50",
    "sg:city":"Bandirma",
    "sg:classifiers":[
        {
            "category":"Wholesale",
            "subcategory":"Machinery & Supplies",
            "type":"Manufacturing & Wholesale Goods"
        }
    ],
    "sg:phone":"+90 264 273 4140",
    "sg:postcode":"10200",
    "sg:province":"Sakarya",
    "sg:tags":[
        "agricultural"
    ],
    "wof:name":"Kronmak Tic.san.ltd.sti.",
    "wof:placetype":"venue"
},
  "geometry": {"coordinates":[30.3950271606,40.7656021118],"type":"Point"}
}