{
  "type": "Feature",
  "properties": {
    "addr:full":"Cilek Mah. 1455.sok. No:24 Yenimahalle I?el 06",
    "addr:housenumber":"1455.sok no 24;?;06",
    "addr:street":"Cilek Mah.;Yenimahalle I;El",
    "iso:country":"TR",
    "sg:address":"Cilek Mah. 1455.sok. No:24",
    "sg:city":"Yenimahalle",
    "sg:classifiers":[
        {
            "category":"Shopping",
            "subcategory":"Stationery & Office Supplies",
            "type":"Retail Goods"
        }
    ],
    "sg:phone":"+90 324 337 2044",
    "sg:postcode":"06",
    "sg:province":"I?el",
    "sg:tags":[
        "paper"
    ],
    "wof:name":"Cemka Ltd.sti.",
    "wof:placetype":"venue"
},
  "geometry": {"coordinates":[34.6754493713,36.8316497803],"type":"Point"}
}