{
  "type": "Feature",
  "properties": {
    "iso:country":"TR",
    "sg:address":"Kececiler Cad.no.11",
    "sg:city":"Kocadere Mevkii",
    "sg:classifiers":[
        {
            "category":"Shopping",
            "subcategory":"Computers & Home Electronics",
            "type":"Retail Goods"
        }
    ],
    "sg:phone":"+90 376 213 1053",
    "sg:province":"Cankiri",
    "sg:tags":[
        "chamber",
        "commerce"
    ],
    "wof:name":"Cankiri Chamber Of Commerce And Industry",
    "wof:placetype":"venue"
},
  "geometry": {"coordinates":[33.6089744568,40.5607719421],"type":"Point"}
}