{
  "type": "Feature",
  "properties": {
    "iso:country":"TR",
    "sg:address":"Istanbul Cd. No:113 Bakirk?",
    "sg:city":"Bakirk?y",
    "sg:orig_category":"Beaty Parlors",
    "sg:phone":"+90 212 543 7299",
    "sg:province":"Istanbul",
    "wof:name":"Turkuaz G?zellik Salonu",
    "wof:placetype":"venue"
},
  "geometry": {"coordinates":[28.883368,40.979359],"type":"Point"}
}