{
  "type": "Feature",
  "properties": {
    "addr:full":"Sanayi Sitesi Yukari Sanayi Cad. No:35 Mersin K?tahya 52750",
    "addr:housenumber":"35;k ?",
    "addr:postcode":"52750",
    "addr:street":"Sanayi Sitesi Yukari Sanayi Cad. No;Tahya",
    "iso:country":"TR",
    "sg:address":"Sanayi Sitesi Yukari Sanayi Cad. No:35",
    "sg:city":"Mersin",
    "sg:classifiers":[
        {
            "category":"Wholesale",
            "subcategory":"Auto Parts",
            "type":"Manufacturing & Wholesale Goods"
        }
    ],
    "sg:phone":"+90 2317777",
    "sg:postcode":"52750",
    "sg:province":"K?tahya",
    "sg:tags":[
        "spare"
    ],
    "wof:name":"Motor Sanayi Ticaret",
    "wof:placetype":"venue"
},
  "geometry": {"coordinates":[37.7128486633,41.0530204773],"type":"Point"}
}