{
  "type": "Feature",
  "properties": {
    "addr:full":"Marmara San Sit L Blok No:250-251- Ikitelli Istanbul 34306",
    "addr:housenumber":"blok no 250-251",
    "addr:postcode":"34306",
    "addr:street":"Ikitelli Istanbul",
    "iso:country":"TR",
    "sg:address":"Marmara San Sit L Blok No:250-251-",
    "sg:city":"Ikitelli",
    "sg:classifiers":[
        {
            "category":"Manufacturing",
            "subcategory":"Glass & Minerals",
            "type":"Manufacturing & Wholesale Goods"
        }
    ],
    "sg:phone":"+90 212 472 0729",
    "sg:postcode":"34306",
    "sg:province":"Istanbul",
    "sg:tags":[
        "glass-mirror"
    ],
    "wof:name":"Standart Ayna Ltd.",
    "wof:placetype":"venue"
},
  "geometry": {"coordinates":[28.7984962463,41.0884017944],"type":"Point"}
}