{
  "type": "Feature",
  "properties": {
    "iso:country":"TR",
    "sg:address":"Meclisi Mebusan Yokusu, Selime Hatun Camii Sk. S?ran Apt. No.11/2 Findikli",
    "sg:city":"Kalamis",
    "sg:classifiers":[
        {
            "category":"Organizations",
            "subcategory":"Professional Association",
            "type":"Services"
        }
    ],
    "sg:phone":"+90 212",
    "sg:province":"Istanbul",
    "sg:tags":[
        "fair"
    ],
    "wof:name":"Standart Mimarlik Ltd.sti.",
    "wof:placetype":"venue"
},
  "geometry": {"coordinates":[29.1326770782,40.9687385559],"type":"Point"}
}