{
  "type": "Feature",
  "properties": {
    "addr:full":"Istoc Tic.merkezi 16.ada No:64 Mahmutbey Merkez Istanbul 71100",
    "addr:housenumber":"no 64",
    "addr:postcode":"71100",
    "addr:street":"Mahmutbey",
    "iso:country":"TR",
    "sg:address":"Istoc Tic.merkezi 16.ada No:64 Mahmutbey",
    "sg:city":"Merkez",
    "sg:classifiers":[
        {
            "category":"Health Services",
            "subcategory":"Clinic",
            "type":"Services"
        }
    ],
    "sg:phone":"+90 212 659 3006",
    "sg:postcode":"71100",
    "sg:province":"Istanbul",
    "wof:name":"Marmara Medikal Ltd.sti.",
    "wof:placetype":"venue"
},
  "geometry": {"coordinates":[28.9861831665,41.0408554077],"type":"Point"}
}