{
  "type": "Feature",
  "properties": {
    "iso:country":"TR",
    "sg:address":"K.karabekir C. Bakirk?",
    "sg:city":"Merkez",
    "sg:classifiers":[
        {
            "category":"Shopping",
            "subcategory":"Shoes",
            "type":"Retail Goods"
        }
    ],
    "sg:phone":"+90 212 550 4980",
    "sg:province":"Istanbul",
    "wof:name":"Mekap Ayakkabi San. A.s.",
    "wof:placetype":"venue"
},
  "geometry": {"coordinates":[28.846125,40.998096],"type":"Point"}
}