{
  "type": "Feature",
  "properties": {
    "iso:country":"TR",
    "sg:address":"Cinnah Cd. No:67/7",
    "sg:city":"Pendik",
    "sg:classifiers":[
        {
            "category":"Military Area",
            "subcategory":"Coast Guard Base",
            "type":"Public Place"
        }
    ],
    "sg:phone":"+90 312 439 3125",
    "sg:postcode":"34916",
    "sg:province":"Ankara",
    "sg:tags":[
        "industry",
        "defence"
    ],
    "wof:name":"S T M Savunma Teknolojileri M?hendis. Tic. A.s.",
    "wof:placetype":"venue"
},
  "geometry": {"coordinates":[32.8604812622,39.9429283142],"type":"Point"}
}