{
  "type": "Feature",
  "properties": {
    "iso:country":"TR",
    "sg:address":"Menekse 1.sok Giris 8/b Kat:3 No:21 Kizilay",
    "sg:city":"K???k?ekmece",
    "sg:classifiers":[
        {
            "category":"Banks & Credit Unions",
            "subcategory":"Financial Services",
            "type":"Services"
        }
    ],
    "sg:phone":"+90 312 418 3606",
    "sg:postcode":"34620",
    "sg:province":"Ankara",
    "sg:tags":[
        "consultant"
    ],
    "wof:name":"4m Musavirlik Tic. Ltd.sti",
    "wof:placetype":"venue"
},
  "geometry": {"coordinates":[32.8560333252,39.9438743591],"type":"Point"}
}