{
  "type": "Feature",
  "properties": {
    "addr:full":"Modeka Is Merkz. No:230/114 Karabaglar Maltepe Izmir 01000",
    "addr:housenumber":"/ 114",
    "addr:postcode":"01000",
    "addr:street":"No;Karabaglar Maltepe",
    "iso:country":"TR",
    "sg:address":"Modeka Is Merkz. No:230/114 Karabaglar",
    "sg:city":"Maltepe",
    "sg:classifiers":[
        {
            "category":"Home & Garden",
            "subcategory":"Kitchen Supply",
            "type":"Retail Goods"
        }
    ],
    "sg:phone":"+90 232 254 0616",
    "sg:postcode":"01000",
    "sg:province":"Izmir",
    "sg:tags":[
        "fire",
        "extinguisher"
    ],
    "wof:name":"Dalgic Yangin S?nd?rme Cihazlari",
    "wof:placetype":"venue"
},
  "geometry": {"coordinates":[27.1296863556,38.4186973572],"type":"Point"}
}