{
  "type": "Feature",
  "properties": {
    "addr:full":"3.org.san.bol.konya Karatay Konya 42300",
    "addr:postcode":"42300",
    "iso:country":"TR",
    "sg:address":"3.org.san.bol.konya",
    "sg:city":"Karatay",
    "sg:classifiers":[
        {
            "category":"Wholesale",
            "subcategory":"Auto Parts",
            "type":"Manufacturing & Wholesale Goods"
        }
    ],
    "sg:phone":"+90 332 239 1420",
    "sg:postcode":"42300",
    "sg:province":"Konya",
    "sg:tags":[
        "spare"
    ],
    "wof:name":"B.eker Bijon A.s.",
    "wof:placetype":"venue"
},
  "geometry": {"coordinates":[33.0667152405,39.2111282349],"type":"Point"}
}