{
  "type": "Feature",
  "properties": {
    "iso:country":"TR",
    "sg:address":"Gemlik Yolu",
    "sg:city":"Gumusler",
    "sg:classifiers":[
        {
            "category":"Shopping",
            "subcategory":"Crafts & Fabrics",
            "type":"Retail Goods"
        }
    ],
    "sg:phone":"+90 224 261 0712",
    "sg:postcode":"20085",
    "sg:province":"Bursa",
    "sg:tags":[
        "weaving"
    ],
    "wof:name":"Kervansaray Tekstil A.s",
    "wof:placetype":"venue"
},
  "geometry": {"coordinates":[29.094909668,40.1877593994],"type":"Point"}
}