{
  "type": "Feature",
  "properties": {
    "addr:full":"Gen?lik Mah. 19 Mayis Cad. No: 55/a 07100 Bodrum Antalya 48400",
    "addr:housenumber":"19;55 / a",
    "addr:postcode":"07100;48400",
    "addr:street":"Gen ?;Mah.;Mayis Cad. No",
    "iso:country":"TR",
    "sg:address":"Gen?lik Mah. 19 Mayis Cad. No: 55/a 07100",
    "sg:city":"Bodrum",
    "sg:classifiers":[
        {
            "category":"Travel",
            "subcategory":"Travel Agent",
            "type":"Entertainment"
        }
    ],
    "sg:phone":"+90 24231214213234",
    "sg:postcode":"48400",
    "sg:province":"Antalya",
    "sg:tags":[
        "agency",
        "tourism"
    ],
    "wof:name":"Idil Turizm",
    "wof:placetype":"venue"
},
  "geometry": {"coordinates":[30.7092056274,36.8790512085],"type":"Point"}
}