{
  "type": "Feature",
  "properties": {
    "iso:country":"TR",
    "sg:address":"Muhurdar Cd.no44/2",
    "sg:city":"Kad\u0131k\u00f6y",
    "sg:classifiers":[
        {
            "category":"Freight",
            "type":"Transportation"
        }
    ],
    "sg:phone":"+90 216 414 2246",
    "sg:postcode":"34990",
    "sg:province":"Istanbul",
    "sg:tags":[
        "agent",
        "shipping",
        "broker"
    ],
    "wof:name":"Nova Gemi Acent.ltd.sti.",
    "wof:placetype":"venue"
},
  "geometry": {"coordinates":[28.975925,41.012379],"type":"Point"}
}