{
  "type": "Feature",
  "properties": {
    "iso:country":"TR",
    "sg:address":"Kss 16. Bl. No: 59",
    "sg:city":"Besevler",
    "sg:classifiers":[
        {
            "category":"Manufacturing",
            "subcategory":"Chemicals & Compounds",
            "type":"Manufacturing & Wholesale Goods"
        }
    ],
    "sg:phone":"+90 224 441 5508",
    "sg:postcode":"04100",
    "sg:province":"Bursa",
    "sg:tags":[
        "industry"
    ],
    "wof:name":"Teknopak Ltd. Sti",
    "wof:placetype":"venue"
},
  "geometry": {"coordinates":[29.0586109161,40.1844291687],"type":"Point"}
}