{
  "type": "Feature",
  "properties": {
    "addr:full":"Sanayi Cad. 35/1 Ulus Kesan Ankara 22800",
    "addr:housenumber":"35 / 1",
    "addr:postcode":"22800",
    "addr:street":"Sanayi Cad.;Ulus Kesan",
    "iso:country":"TR",
    "sg:address":"Sanayi Cad. 35/1 Ulus",
    "sg:city":"Kesan",
    "sg:classifiers":[
        {
            "category":"Shopping",
            "subcategory":"Bicycles & Sporting Goods",
            "type":"Retail Goods"
        }
    ],
    "sg:phone":"+90 312 311 1800",
    "sg:postcode":"22800",
    "sg:province":"Ankara",
    "sg:tags":[
        "equipment",
        "marine",
        "hunting"
    ],
    "wof:name":"Man-av Av Malz. San. Tic. Ltd.sti.",
    "wof:placetype":"venue"
},
  "geometry": {"coordinates":[32.8604812622,39.9429283142],"type":"Point"}
}