{
  "type": "Feature",
  "properties": {
    "iso:country":"TR",
    "sg:address":"E. B??dere Cd. ?zen Ismerk. No:29",
    "sg:city":"Maslak",
    "sg:classifiers":[
        {
            "category":"Home & Garden",
            "subcategory":"Household Appliances",
            "type":"Retail Goods"
        }
    ],
    "sg:phone":"+90 212 285 0247",
    "sg:postcode":"34398",
    "sg:province":"Istanbul",
    "sg:tags":[
        "conditioner",
        "air"
    ],
    "wof:name":"?zk?seoglu Isi San.",
    "wof:placetype":"venue"
},
  "geometry": {"coordinates":[29.0198059082,41.1222839355],"type":"Point"}
}