{
  "type": "Feature",
  "properties": {
    "iso:country":"TR",
    "sg:address":"H?eyin Ikiz",
    "sg:city":"Y?egir",
    "sg:classifiers":[
        {
            "category":"Government",
            "subcategory":"Office",
            "type":"Public Place"
        }
    ],
    "sg:phone":"+90 228 371 2251",
    "sg:province":"Bilecik",
    "sg:tags":[
        "municipality"
    ],
    "wof:name":"Inhisar Belediye Baskani",
    "wof:placetype":"venue"
},
  "geometry": {"coordinates":[29.9804992676,40.1426010132],"type":"Point"}
}