{
  "type": "Feature",
  "properties": {
    "iso:country":"TR",
    "sg:address":"Izmir-aydin Karayolu Menderes Havaalani G?ergahi",
    "sg:city":"?amlica - ?sk?ar",
    "sg:orig_category":"Prefabric Construction",
    "sg:phone":"+90 232 782 3840",
    "sg:postcode":"34187",
    "sg:province":"Izmir",
    "wof:name":"Bahce Dekor Ltd.sti.",
    "wof:placetype":"venue"
},
  "geometry": {"coordinates":[27.1296863556,38.4186973572],"type":"Point"}
}