{
  "type": "Feature",
  "properties": {
    "iso:country":"TR",
    "sg:address":"Kazim Orbay Cad. No.41",
    "sg:city":"Sisli",
    "sg:classifiers":[
        {
            "category":"Shopping",
            "subcategory":"Clothing, Apparel, & Fashions",
            "type":"Retail Goods"
        }
    ],
    "sg:phone":"+90 212 247 0702",
    "sg:postcode":"65710",
    "sg:province":"Istanbul",
    "sg:tags":[
        "ready",
        "wear"
    ],
    "wof:name":"Seval Giyim A.s.",
    "wof:placetype":"venue"
},
  "geometry": {"coordinates":[28.9834289551,41.0606918335],"type":"Point"}
}