{
  "type": "Feature",
  "properties": {
    "addr:full":"Kazim Karabekir Cad Surcuoglu Ishan. 37/80 Yenimahalle Ankara 06180",
    "addr:housenumber":"37 / 80",
    "addr:postcode":"06180",
    "addr:street":"Karabekir Cad Surcuoglu Ishan.",
    "iso:country":"TR",
    "sg:address":"Kazim Karabekir Cad Surcuoglu Ishan. 37/80",
    "sg:city":"Yenimahalle",
    "sg:classifiers":[
        {
            "category":"Home & Garden",
            "subcategory":"Kitchen Supply",
            "type":"Retail Goods"
        }
    ],
    "sg:phone":"+90 312 341 4442",
    "sg:postcode":"06180",
    "sg:province":"Ankara",
    "sg:tags":[
        "fire",
        "extinguisher"
    ],
    "wof:name":"Sarikaya Yangin Sondurme Sanayi",
    "wof:placetype":"venue"
},
  "geometry": {"coordinates":[32.8070373535,39.9695243835],"type":"Point"}
}