{
  "type": "Feature",
  "properties": {
    "iso:country":"TR",
    "sg:address":"Fevzi Cakmak Mah.15 Sok No.89",
    "sg:city":"Esenler",
    "sg:classifiers":[
        {
            "category":"Retail",
            "subcategory":"Auto Repair",
            "type":"Services"
        }
    ],
    "sg:phone":"+90 212 429 4070",
    "sg:postcode":"34200",
    "sg:province":"Istanbul",
    "sg:tags":[
        "maintenance"
    ],
    "wof:name":"Gokhan Otomotiv",
    "wof:placetype":"venue"
},
  "geometry": {"coordinates":[28.9861831665,41.0408554077],"type":"Point"}
}