{
  "type": "Feature",
  "properties": {
    "addr:full":"Ataturk Cad. No:384 Resat Berin Aksoy Plaza D:12 Alsancak Izmir 01365",
    "addr:housenumber":"384",
    "addr:postcode":"01365",
    "addr:street":"Ataturk Cad. No;D 12",
    "iso:country":"TR",
    "sg:address":"Ataturk Cad. No:384 Resat Berin Aksoy Plaza D:12",
    "sg:city":"Alsancak",
    "sg:classifiers":[
        {
            "category":"Manufacturing",
            "subcategory":"Glass & Minerals",
            "type":"Manufacturing & Wholesale Goods"
        }
    ],
    "sg:phone":"+90 232 465 0056",
    "sg:postcode":"01365",
    "sg:province":"Izmir",
    "sg:tags":[
        "glass-mirror"
    ],
    "wof:name":"Mayimpeks Dis Tic.ltd.sti.",
    "wof:placetype":"venue"
},
  "geometry": {"coordinates":[27.1296863556,38.4186973572],"type":"Point"}
}