{
  "type": "Feature",
  "properties": {
    "addr:full":"Barbaros Bulv. No:40 Balmumcu Istanbul 34349",
    "addr:housenumber":"no 40",
    "addr:postcode":"34349",
    "addr:street":"Barbaros Bulv.;Istanbul",
    "iso:country":"TR",
    "sg:address":"Barbaros Bulv. No:40",
    "sg:city":"Balmumcu",
    "sg:classifiers":[
        {
            "category":"Airport",
            "subcategory":"International",
            "type":"Transportation"
        }
    ],
    "sg:phone":"+90 212 252 9090",
    "sg:postcode":"34349",
    "sg:province":"Istanbul",
    "wof:name":"Oval Uluslararasi Nakliyat Tic.",
    "wof:placetype":"venue"
},
  "geometry": {"coordinates":[29.0116539001,41.0615921021],"type":"Point"}
}