{
  "type": "Feature",
  "properties": {
    "addr:full":"Anadolu Mah. Tuter Sok. No:9 Sirkeci Bursa 34112",
    "addr:housenumber":"no 9",
    "addr:postcode":"34112",
    "addr:street":"Mah. Tuter Sok.",
    "iso:country":"TR",
    "sg:address":"Anadolu Mah. Tuter Sok. No:9",
    "sg:city":"Sirkeci",
    "sg:classifiers":[
        {
            "category":"Shopping",
            "subcategory":"Clothing, Apparel, & Fashions",
            "type":"Retail Goods"
        }
    ],
    "sg:phone":"+90 224 363 3792",
    "sg:postcode":"34112",
    "sg:province":"Bursa",
    "sg:tags":[
        "-",
        "towel",
        "bathrobe"
    ],
    "wof:name":"Hapas Havlu San. A.s.",
    "wof:placetype":"venue"
},
  "geometry": {"coordinates":[29.0586109161,40.1844291687],"type":"Point"}
}