{
  "type": "Feature",
  "properties": {
    "iso:country":"TR",
    "sg:address":"Halaskargazi Cad. 289/10 Sisli",
    "sg:city":"Kad\u0131k\u00f6y",
    "sg:classifiers":[
        {
            "category":"Professional",
            "subcategory":"Computer Services",
            "type":"Services"
        }
    ],
    "sg:phone":"+90 212 234 2513",
    "sg:postcode":"34990",
    "sg:province":"Istanbul",
    "sg:tags":[
        "application",
        "software"
    ],
    "wof:name":"Cizge Bilgisayar Destekli Cizim Tasarim",
    "wof:placetype":"venue"
},
  "geometry": {"coordinates":[28.9861831665,41.0408554077],"type":"Point"}
}