{
  "type": "Feature",
  "properties": {
    "addr:full":"Mrk.(fabrika)?rnek San.sit. 363.sk.no.7 Ostim Ankara 06374",
    "addr:postcode":"06374",
    "iso:country":"TR",
    "sg:address":"Mrk.(fabrika)?rnek San.sit. 363.sk.no.7",
    "sg:city":"Ostim",
    "sg:classifiers":[
        {
            "category":"Home & Garden",
            "subcategory":"Kitchen Supply",
            "type":"Retail Goods"
        }
    ],
    "sg:phone":"+90 312 354 1373",
    "sg:postcode":"06374",
    "sg:province":"Ankara",
    "sg:tags":[
        "fire",
        "extinguisher"
    ],
    "wof:name":"Universal Yangin S?nd?rme Cihazlari San.tic. As.",
    "wof:placetype":"venue"
},
  "geometry": {"coordinates":[32.8560333252,39.9438743591],"type":"Point"}
}