{
  "type": "Feature",
  "properties": {
    "addr:full":"Bugday Paz. No.2 Alanya Amasya 07110",
    "addr:postcode":"07110",
    "iso:country":"TR",
    "sg:address":"Bugday Paz. No.2",
    "sg:city":"Alanya",
    "sg:classifiers":[
        {
            "category":"Manufacturing",
            "subcategory":"Food",
            "type":"Manufacturing & Wholesale Goods"
        }
    ],
    "sg:phone":"+90 358 513 1401",
    "sg:postcode":"07110",
    "sg:province":"Amasya",
    "sg:tags":[
        "wholesaler"
    ],
    "wof:name":"Aktan Gida San. A.s.",
    "wof:placetype":"venue"
},
  "geometry": {"coordinates":[35.8320007324,40.6543998718],"type":"Point"}
}