{
  "type": "Feature",
  "properties": {
    "iso:country":"TR",
    "sg:address":"Alemdag Cad. No:130 S.ciftligi",
    "sg:city":"\u00dcmraniye",
    "sg:classifiers":[
        {
            "category":"Shopping",
            "subcategory":"Clothing, Apparel, & Fashions",
            "type":"Retail Goods"
        }
    ],
    "sg:phone":"+90 216 312 2330",
    "sg:postcode":"03650",
    "sg:province":"Istanbul",
    "sg:tags":[
        "ready",
        "wear"
    ],
    "wof:name":"Erteks Konfeksiyon Tekstil San. A.s.",
    "wof:placetype":"venue"
},
  "geometry": {"coordinates":[29.9279155731,40.7663116455],"type":"Point"}
}