{
  "type": "Feature",
  "properties": {
    "addr:full":"Merkez Mah.ugur Mumcu Cad.no:2 Kirac- B.cekmece Istanbul",
    "addr:housenumber":"2",
    "addr:street":"Mah.Ugur;Cad.No",
    "iso:country":"TR",
    "sg:address":"Merkez Mah.ugur Mumcu Cad.no:2 Kirac-",
    "sg:city":"B.cekmece",
    "sg:classifiers":[
        {
            "category":"Shopping",
            "subcategory":"Clothing, Apparel, & Fashions",
            "type":"Retail Goods"
        }
    ],
    "sg:phone":"+90 212 886 7708",
    "sg:province":"Istanbul",
    "sg:tags":[
        "ready",
        "wear"
    ],
    "wof:name":"Iki As Tekstil San.tic.a.s.",
    "wof:placetype":"venue"
},
  "geometry": {"coordinates":[28.6582870483,41.0575561523],"type":"Point"}
}