{
  "type": "Feature",
  "properties": {
    "addr:full":"Ballibaba Sk. No: 49/ A Seyranbaglari Ankara 06660",
    "addr:housenumber":"49 / a",
    "addr:postcode":"06660",
    "addr:street":"Ballibaba Sk. No;Seyranbaglari Ankara",
    "iso:country":"TR",
    "sg:address":"Ballibaba Sk. No: 49/ A",
    "sg:city":"Seyranbaglari",
    "sg:classifiers":[
        {
            "category":"Shopping",
            "subcategory":"Computers & Home Electronics",
            "type":"Retail Goods"
        }
    ],
    "sg:phone":"+90 312 435 0486",
    "sg:postcode":"06660",
    "sg:province":"Ankara",
    "sg:tags":[
        "product",
        "electric-electronic"
    ],
    "wof:name":"Arikan Baski Devre Tasarim Ve ?retimi (pcb)",
    "wof:placetype":"venue"
},
  "geometry": {"coordinates":[32.8604812622,39.9429283142],"type":"Point"}
}