{
  "type": "Feature",
  "properties": {
    "iso:country":"TR",
    "sg:address":"Varlik Mah.teomanpasa Cad. Oba Apt. No.88/c",
    "sg:city":"Merkez",
    "sg:classifiers":[
        {
            "category":"Shopping",
            "subcategory":"Stationery & Office Supplies",
            "type":"Retail Goods"
        }
    ],
    "sg:phone":"+90 242 248 6062",
    "sg:postcode":"58040",
    "sg:province":"Antalya",
    "wof:name":"Apsis Ticaret Ltd.sti.",
    "wof:placetype":"venue"
},
  "geometry": {"coordinates":[30.703135,36.887505],"type":"Point"}
}