{
  "type": "Feature",
  "properties": {
    "addr:full":"Mersin Asf. 14. Km. Yolge?n K??civari Saraykoy Adana 20300",
    "addr:housenumber":"14 km.",
    "addr:postcode":"20300",
    "addr:street":"Yolge ? N K ? ? Civari Saraykoy",
    "iso:country":"TR",
    "sg:address":"Mersin Asf. 14. Km. Yolge?n K??civari",
    "sg:city":"Saraykoy",
    "sg:classifiers":[
        {
            "category":"Shopping",
            "subcategory":"Crafts & Fabrics",
            "type":"Retail Goods"
        }
    ],
    "sg:phone":"+90 322 441 0047",
    "sg:postcode":"20300",
    "sg:province":"Adana",
    "sg:tags":[
        "yarn"
    ],
    "wof:name":"Mensa Mensucat San. Tic. A.s.",
    "wof:placetype":"venue"
},
  "geometry": {"coordinates":[35.3137359619,37.0007171631],"type":"Point"}
}