{
  "type": "Feature",
  "properties": {
    "iso:country":"TR",
    "sg:address":"Bahar Mh. H?riyet Cd. No:5",
    "sg:city":"Ineg?",
    "sg:classifiers":[
        {
            "category":"Home & Garden",
            "subcategory":"Furniture",
            "type":"Retail Goods"
        }
    ],
    "sg:phone":"+90 224 255 8215",
    "sg:postcode":"16410",
    "sg:province":"Bursa",
    "sg:tags":[
        "armchair",
        "sofa"
    ],
    "wof:name":"Enustun Mensucat Ltd. Sti.",
    "wof:placetype":"venue"
},
  "geometry": {"coordinates":[29.0586109161,40.1844291687],"type":"Point"}
}