{
  "type": "Feature",
  "properties": {
    "addr:full":"Necatibey Cd. Leblebici Saban Sk. No:24 Karak? K.?ekmece Istanbul 34670",
    "addr:housenumber":"24;? k. ?",
    "addr:postcode":"34670",
    "addr:street":"Saban Sk. No;Karak",
    "iso:country":"TR",
    "sg:address":"Necatibey Cd. Leblebici Saban Sk. No:24 Karak?",
    "sg:city":"K.?ekmece",
    "sg:classifiers":[
        {
            "category":"Building & Trades",
            "subcategory":"Plumbing",
            "type":"Services"
        }
    ],
    "sg:phone":"+90 212 252 6899",
    "sg:postcode":"34670",
    "sg:province":"Istanbul",
    "sg:tags":[
        "gasket"
    ],
    "wof:name":"Sespa Sizdirmazlik Elem. San. Tic. Paz.",
    "wof:placetype":"venue"
},
  "geometry": {"coordinates":[28.9759254456,41.0123786926],"type":"Point"}
}