{
  "type": "Feature",
  "properties": {
    "addr:full":"Eskisehir Yolu S???? Ankara \u00dcmraniye Ankara 81260",
    "addr:housenumber":"? ?",
    "addr:postcode":"81260",
    "addr:street":"Eskisehir Yolu S ? ?",
    "iso:country":"TR",
    "sg:address":"Eskisehir Yolu S???? Ankara",
    "sg:city":"\u00dcmraniye",
    "sg:classifiers":[
        {
            "category":"Farming",
            "subcategory":"Fish & Marine Products",
            "type":"Manufacturing & Wholesale Goods"
        }
    ],
    "sg:phone":"+90 312 223 8523",
    "sg:postcode":"81260",
    "sg:province":"Ankara",
    "sg:tags":[
        "automotive"
    ],
    "wof:name":"Mais Motor. Ara?. Imal. Satis A.s.",
    "wof:placetype":"venue"
},
  "geometry": {"coordinates":[32.6623725891,39.8839263916],"type":"Point"}
}