{
  "type": "Feature",
  "properties": {
    "iso:country":"TR",
    "sg:address":"C. Topel Cd. No:115/a",
    "sg:city":"K??k?",
    "sg:classifiers":[
        {
            "category":"Building & Trades",
            "subcategory":"Electrical",
            "type":"Services"
        }
    ],
    "sg:phone":"+90 212 618 4478",
    "sg:province":"Istanbul",
    "sg:tags":[
        "equipment",
        "lighting"
    ],
    "wof:name":"Akay Kristal Avize San. Tic. Ltd. Sti.",
    "wof:placetype":"venue"
},
  "geometry": {"coordinates":[28.9026908875,41.0684623718],"type":"Point"}
}