{
  "type": "Feature",
  "properties": {
    "iso:country":"TR",
    "sg:address":"Uluyol No:25",
    "sg:city":"Findikli",
    "sg:classifiers":[
        {
            "category":"Utilities",
            "subcategory":"Electric",
            "type":"Services"
        }
    ],
    "sg:phone":"+90 224 254 8914",
    "sg:postcode":"80040",
    "sg:province":"Bursa",
    "sg:tags":[
        "accumulator",
        "-",
        "batery"
    ],
    "wof:name":"Deger Ak?l?mat?r San. Ltd. Sti.",
    "wof:placetype":"venue"
},
  "geometry": {"coordinates":[29.030693,40.209736],"type":"Point"}
}