{
  "type": "Feature",
  "properties": {
    "addr:full":"Gemalmaz Mah. D??c?sok No:7 Meram Konya 42000",
    "addr:housenumber":"? ? c;no 7",
    "addr:postcode":"42000",
    "addr:street":"Gemalmaz Mah. D;? Sok",
    "iso:country":"TR",
    "sg:address":"Gemalmaz Mah. D??c?sok No:7",
    "sg:city":"Meram",
    "sg:classifiers":[
        {
            "category":"Health Services",
            "subcategory":"Hospital",
            "type":"Services"
        }
    ],
    "sg:phone":"+90 332 322 9410",
    "sg:postcode":"42000",
    "sg:province":"Konya",
    "wof:name":"Konya Vakif Hastanesi",
    "wof:placetype":"venue"
},
  "geometry": {"coordinates":[33.0667152405,39.2111282349],"type":"Point"}
}