{
  "type": "Feature",
  "properties": {
    "addr:full":"Iett Sit. Hilton Blok Alti No:1 Okmeydani Zeytinburnu Istanbul 41000",
    "addr:postcode":"41000",
    "addr:street":"Okmeydani",
    "iso:country":"TR",
    "sg:address":"Iett Sit. Hilton Blok Alti No:1 Okmeydani",
    "sg:city":"Zeytinburnu",
    "sg:classifiers":[
        {
            "category":"Professional",
            "subcategory":"Business Services",
            "type":"Services"
        }
    ],
    "sg:phone":"+90 212 221 3171",
    "sg:postcode":"41000",
    "sg:province":"Istanbul",
    "sg:tags":[
        "industry",
        "casting"
    ],
    "wof:name":"?z Model D?k?m Takim San.",
    "wof:placetype":"venue"
},
  "geometry": {"coordinates":[28.9861831665,41.0408554077],"type":"Point"}
}