{
  "type": "Feature",
  "properties": {
    "addr:full":"H??et Cad.no.29 Aydin Alapli 01513",
    "addr:postcode":"01513",
    "addr:street":"Aydin Alapli",
    "iso:country":"TR",
    "sg:address":"H??et Cad.no.29",
    "sg:city":"Aydin",
    "sg:classifiers":[
        {
            "category":"Banks & Credit Unions",
            "subcategory":"Bank",
            "type":"Services"
        }
    ],
    "sg:phone":"+90 372 378 1262",
    "sg:postcode":"01513",
    "sg:province":"Alapli",
    "wof:name":"T?kiye Is Bankasi As",
    "wof:placetype":"venue"
},
  "geometry": {"coordinates":[31.3874,41.182098],"type":"Point"}
}