{
  "type": "Feature",
  "properties": {
    "iso:country":"TR",
    "sg:address":"2819 Sok. No:9 1.san.sitesi",
    "sg:city":"Merkez",
    "sg:classifiers":[
        {
            "category":"Wholesale",
            "subcategory":"Machinery & Supplies",
            "type":"Manufacturing & Wholesale Goods"
        }
    ],
    "sg:phone":"+90 232 433 6938",
    "sg:province":"Izmir",
    "sg:tags":[
        "bearing",
        "ball"
    ],
    "wof:name":"Duyar Rulman (bearings) Ltd.sti.",
    "wof:placetype":"venue"
},
  "geometry": {"coordinates":[27.129686,38.418697],"type":"Point"}
}