{
  "type": "Feature",
  "properties": {
    "addr:full":"Kalafatli Dagi G?ek Mevkii Kusadasi Tel :(256)6145548 B. ?ekmece Aydin 34400",
    "addr:housenumber":"?;?",
    "addr:postcode":"34400",
    "addr:street":"Dagi G;Kusadasi Tel (256)6145548 B.;Aydin",
    "iso:country":"TR",
    "sg:address":"Kalafatli Dagi G?ek Mevkii Kusadasi Tel :(256)6145548",
    "sg:city":"B. ?ekmece",
    "sg:classifiers":[
        {
            "category":"Manufacturing",
            "subcategory":"Metals",
            "type":"Manufacturing & Wholesale Goods"
        }
    ],
    "sg:phone":"+90 256 554 6304",
    "sg:postcode":"34400",
    "sg:province":"Aydin",
    "sg:tags":[
        "industry"
    ],
    "wof:name":"Kubetas Insaat Taah.tic.ve San A.s.",
    "wof:placetype":"venue"
},
  "geometry": {"coordinates":[28.4863967896,37.8117027283],"type":"Point"}
}