{
  "type": "Feature",
  "properties": {
    "addr:full":"F. ?akmak Sk. No:20/b Kizilay Kizilay Ankara 23050",
    "addr:housenumber":"?;20 / b",
    "addr:postcode":"23050",
    "addr:street":"F.;Akmak Sk. No",
    "iso:country":"TR",
    "sg:address":"F. ?akmak Sk. No:20/b Kizilay",
    "sg:city":"Kizilay",
    "sg:classifiers":[
        {
            "category":"Wholesale",
            "subcategory":"Books, Periodicals, & Newspapers",
            "type":"Manufacturing & Wholesale Goods"
        }
    ],
    "sg:phone":"+90 312 229 3696",
    "sg:postcode":"23050",
    "sg:province":"Ankara",
    "sg:tags":[
        "house",
        "publishing"
    ],
    "wof:name":"Feryal Matbaaci. Ltd. Sti.",
    "wof:placetype":"venue"
},
  "geometry": {"coordinates":[32.8517951965,39.9241867065],"type":"Point"}
}