{
  "type": "Feature",
  "properties": {
    "iso:country":"TR",
    "sg:address":"Abidinpasa Cad. No.15",
    "sg:city":"K??esat",
    "sg:classifiers":[
        {
            "category":"Banks & Credit Unions",
            "subcategory":"Bank",
            "type":"Services"
        }
    ],
    "sg:phone":"+90 322 351 6564",
    "sg:province":"01010",
    "wof:name":"T?kiye Emlak, Bankasi As",
    "wof:placetype":"venue"
},
  "geometry": {"coordinates":[35.331436,36.986195],"type":"Point"}
}