{
  "type": "Feature",
  "properties": {
    "addr:full":"Haramidere Sanayi Sitesi E Blok No: 217 B.cekmece Beyazit Istanbul 34130",
    "addr:housenumber":"blok no 217",
    "addr:postcode":"34130",
    "addr:street":"Haramidere Sanayi Sitesi E;B.Cekmece Beyazit",
    "iso:country":"TR",
    "sg:address":"Haramidere Sanayi Sitesi E Blok No: 217 B.cekmece",
    "sg:city":"Beyazit",
    "sg:classifiers":[
        {
            "category":"Shopping",
            "subcategory":"Clothing, Apparel, & Fashions",
            "type":"Retail Goods"
        }
    ],
    "sg:phone":"+90 2124222182729",
    "sg:postcode":"34130",
    "sg:province":"Istanbul",
    "sg:tags":[
        "bag-belt-accessories"
    ],
    "wof:name":"Darka Palstik Makinalari San.tic.ltd.sti.",
    "wof:placetype":"venue"
},
  "geometry": {"coordinates":[28.959414,41.00576],"type":"Point"}
}