{
  "type": "Feature",
  "properties": {
    "iso:country":"TR",
    "sg:address":"Devekaldirimi Cad. No:6",
    "sg:city":"Mahmutbey",
    "sg:classifiers":[
        {
            "category":"Shopping",
            "subcategory":"Crafts & Fabrics",
            "type":"Retail Goods"
        }
    ],
    "sg:phone":"+90 212 657 1300",
    "sg:postcode":"46600",
    "sg:province":"Istanbul",
    "sg:tags":[
        "yarn"
    ],
    "wof:name":"Koza Iplik Ve Dokuma",
    "wof:placetype":"venue"
},
  "geometry": {"coordinates":[28.8278541565,41.0454597473],"type":"Point"}
}