{
  "type": "Feature",
  "properties": {
    "iso:country":"TR",
    "sg:address":"Dogu Sanayi Sitesi 12 Blok No:12-14 34520 Yenibosna Istanbul",
    "sg:city":"Sariyer",
    "sg:orig_category":"Miscellaneous Products",
    "sg:phone":"+90 212 552 2869",
    "sg:postcode":"33740",
    "sg:province":"Istanbul",
    "wof:name":"Buro- Mekaniker Armatur Ve Ekipman San Tic As",
    "wof:placetype":"venue"
},
  "geometry": {"coordinates":[28.9759254456,41.0123786926],"type":"Point"}
}