{
  "type": "Feature",
  "properties": {
    "addr:full":"B??dere Cd. No:12/2 Mecidiyek\u00f6y Istanbul 34387",
    "addr:housenumber":"? ?;no 12 / 2",
    "addr:postcode":"34387",
    "addr:street":"B;Dere Cd.",
    "iso:country":"TR",
    "sg:address":"B??dere Cd. No:12/2",
    "sg:city":"Mecidiyek\u00f6y",
    "sg:classifiers":[
        {
            "category":"Manufacturing",
            "subcategory":"Glass & Minerals",
            "type":"Manufacturing & Wholesale Goods"
        }
    ],
    "sg:phone":"+90 212 246 2730",
    "sg:postcode":"34387",
    "sg:province":"Istanbul",
    "sg:tags":[
        "glass-mirror"
    ],
    "wof:name":"Cam Elyaf San. A.s.",
    "wof:placetype":"venue"
},
  "geometry": {"coordinates":[28.9964122772,41.0725517273],"type":"Point"}
}