{
  "type": "Feature",
  "properties": {
    "iso:country":"TR",
    "sg:address":"Ayvansarayi Cad. Cember Sok.no:2 Fatih",
    "sg:city":"Edremit",
    "sg:classifiers":[
        {
            "category":"Wholesale",
            "subcategory":"Plants",
            "type":"Manufacturing & Wholesale Goods"
        }
    ],
    "sg:phone":"+90 212 635 5861",
    "sg:postcode":"04500",
    "sg:province":"Istanbul",
    "sg:tags":[
        "natural",
        "spice"
    ],
    "wof:name":"Pas-mar (mister) Gida San.tic.ltd.sti.",
    "wof:placetype":"venue"
},
  "geometry": {"coordinates":[28.975925,41.012379],"type":"Point"}
}