{
  "type": "Feature",
  "properties": {
    "addr:full":"Ankara Cad. Polat Is Merkezi No:108 D:77 Kartal Z.burnu Istanbul",
    "addr:housenumber":"77",
    "addr:street":"Ankara Cad. Polat;No;D",
    "iso:country":"TR",
    "sg:address":"Ankara Cad. Polat Is Merkezi No:108 D:77 Kartal",
    "sg:city":"Z.burnu",
    "sg:classifiers":[
        {
            "category":"Manufacturing",
            "subcategory":"Metals",
            "type":"Manufacturing & Wholesale Goods"
        }
    ],
    "sg:phone":"+90 216 387 3731",
    "sg:province":"Istanbul",
    "sg:tags":[
        "aluminium",
        "industry"
    ],
    "wof:name":"T?rkiye Al?minyum Sanayiceleri Dernegi Talsad",
    "wof:placetype":"venue"
},
  "geometry": {"coordinates":[29.1595001221,40.9112014771],"type":"Point"}
}