{
  "type": "Feature",
  "properties": {
    "iso:country":"TR",
    "sg:address":"Karacakaya Cad. No:10 Siteler",
    "sg:city":"\u00dcmraniye",
    "sg:classifiers":[
        {
            "category":"Shopping",
            "subcategory":"Stationery & Office Supplies",
            "type":"Retail Goods"
        }
    ],
    "sg:phone":"+90 312 353 5821",
    "sg:postcode":"81230",
    "sg:province":"Ankara",
    "sg:tags":[
        "furniture"
    ],
    "wof:name":"Tekmosan Ofis Mobilya San. Ve Tic. Ltd.sti.",
    "wof:placetype":"venue"
},
  "geometry": {"coordinates":[32.8914375305,39.9602661133],"type":"Point"}
}