{
  "type": "Feature",
  "properties": {
    "addr:full":"Organize San. B?. 15. Cad. No:6 Ikitelli/K\u00fc\u00e7\u00fck\u00e7ekmece Kayseri 34670",
    "addr:housenumber":"15",
    "addr:postcode":"34670",
    "addr:street":"Organize;Cad. No 6",
    "iso:country":"TR",
    "sg:address":"Organize San. B?. 15. Cad. No:6",
    "sg:city":"Ikitelli/K\u00fc\u00e7\u00fck\u00e7ekmece",
    "sg:classifiers":[
        {
            "category":"Manufacturing",
            "subcategory":"Tools & Machinery",
            "type":"Manufacturing & Wholesale Goods"
        }
    ],
    "sg:phone":"+90 352321135051",
    "sg:postcode":"34670",
    "sg:province":"Kayseri",
    "sg:tags":[
        "machine",
        "industry"
    ],
    "wof:name":"Dener Mak. San. Tic. Ltd. Sti.",
    "wof:placetype":"venue"
},
  "geometry": {"coordinates":[35.4891357422,38.7225761414],"type":"Point"}
}