{
  "type": "Feature",
  "properties": {
    "addr:full":"R?garli Sk. Katar Han No:20/8 Ulus Kizilay Ankara 06640",
    "addr:housenumber":"20 / 8",
    "addr:postcode":"06640",
    "addr:street":"Garli Sk.;Han No;Ulus Kizilay",
    "iso:country":"TR",
    "sg:address":"R?garli Sk. Katar Han No:20/8 Ulus",
    "sg:city":"Kizilay",
    "sg:classifiers":[
        {
            "category":"Building & Trades",
            "subcategory":"Plumbing",
            "type":"Services"
        }
    ],
    "sg:phone":"+90 312 310 5598",
    "sg:postcode":"06640",
    "sg:province":"Ankara",
    "wof:name":"Iklim Ltd. Sti.",
    "wof:placetype":"venue"
},
  "geometry": {"coordinates":[32.8563957214,39.9164428711],"type":"Point"}
}