{
  "type": "Feature",
  "properties": {
    "addr:full":"G??ler 1049 Sk. No:5 Pendik Denizli 34916",
    "addr:housenumber":"? ?",
    "addr:postcode":"34916",
    "addr:street":"1049 Sk. No 5",
    "iso:country":"TR",
    "sg:address":"G??ler 1049 Sk. No:5",
    "sg:city":"Pendik",
    "sg:classifiers":[
        {
            "category":"Manufacturing",
            "subcategory":"Tools & Machinery",
            "type":"Manufacturing & Wholesale Goods"
        }
    ],
    "sg:phone":"+90 258 371 4954",
    "sg:postcode":"34916",
    "sg:province":"Denizli",
    "sg:tags":[
        "machine",
        "industry"
    ],
    "wof:name":"Altintas Makina",
    "wof:placetype":"venue"
},
  "geometry": {"coordinates":[29.0864906311,37.773525238],"type":"Point"}
}