{
  "type": "Feature",
  "properties": {
    "addr:full":"Kizilay Blv.toprak Yol No:30 - Kartal 07100 Istanbul",
    "addr:postcode":"07100",
    "addr:street":"Kartal",
    "iso:country":"TR",
    "sg:address":"Kizilay Blv.toprak Yol No:30 - Kartal",
    "sg:city":"07100",
    "sg:classifiers":[
        {
            "category":"Health Services",
            "subcategory":"Clinic",
            "type":"Services"
        }
    ],
    "sg:phone":"+90 216 374 6869",
    "sg:province":"Istanbul",
    "wof:name":"Kartal Kizilay Tip Merkezi",
    "wof:placetype":"venue"
},
  "geometry": {"coordinates":[29.2189102173,40.9053115845],"type":"Point"}
}