{
  "type": "Feature",
  "properties": {
    "addr:full":"Hilmipasa Cd. G?man Apt. No:32 D:9-10 Kadik? Fatih Istanbul 01740",
    "addr:housenumber":"?;d;?",
    "addr:postcode":"01740",
    "addr:street":"Hilmipasa Cd. G;9-10 Kadik",
    "iso:country":"TR",
    "sg:address":"Hilmipasa Cd. G?man Apt. No:32 D:9-10 Kadik?",
    "sg:city":"Fatih",
    "sg:classifiers":[
        {
            "category":"Organizations",
            "subcategory":"Membership Organization",
            "type":"Services"
        }
    ],
    "sg:phone":"+90 216 373 2275",
    "sg:postcode":"01740",
    "sg:province":"Istanbul",
    "wof:name":"Tasit Araclari Yan San. Dernegi",
    "wof:placetype":"venue"
},
  "geometry": {"coordinates":[28.9861831665,41.0408554077],"type":"Point"}
}