{
  "type": "Feature",
  "properties": {
    "iso:country":"TR",
    "sg:address":"Cevat Sakir Cad. No:30",
    "sg:city":"Bodrum",
    "sg:classifiers":[
        {
            "category":"Recreation",
            "subcategory":"Boat Charter",
            "type":"Entertainment"
        }
    ],
    "sg:phone":"+90 252 412 0736",
    "sg:postcode":"48400",
    "sg:province":"Mugla",
    "sg:tags":[
        "yachting"
    ],
    "wof:name":"Veritas Yachting",
    "wof:placetype":"venue"
},
  "geometry": {"coordinates":[27.4360923767,37.0389404297],"type":"Point"}
}