{
  "type": "Feature",
  "properties": {
    "addr:full":"Ataturk Cad. No:46 Yukariayranci Amasya",
    "addr:housenumber":"46;amasya",
    "addr:street":"Ataturk Cad. No",
    "iso:country":"TR",
    "sg:address":"Ataturk Cad. No:46",
    "sg:city":"Yukariayranci",
    "sg:classifiers":[
        {
            "category":"Home & Garden",
            "subcategory":"Household Appliances",
            "type":"Retail Goods"
        }
    ],
    "sg:phone":"+90 358 218 7778",
    "sg:province":"Amasya",
    "sg:tags":[
        "conditioner",
        "air"
    ],
    "wof:name":"Zafer Muhendislik Ltd.sti.",
    "wof:placetype":"venue"
},
  "geometry": {"coordinates":[35.8361816406,40.6536598206],"type":"Point"}
}