{
  "type": "Feature",
  "properties": {
    "addr:full":"Pavlonya Sk. No:18 Kadik? Maltepe Istanbul 01000",
    "addr:housenumber":"18;?",
    "addr:postcode":"01000",
    "addr:street":"Pavlonya Sk. No;Maltepe Istanbul",
    "iso:country":"TR",
    "sg:address":"Pavlonya Sk. No:18 Kadik?",
    "sg:city":"Maltepe",
    "sg:classifiers":[
        {
            "category":"Wholesale",
            "subcategory":"Books, Periodicals, & Newspapers",
            "type":"Manufacturing & Wholesale Goods"
        }
    ],
    "sg:phone":"+90 216 348 0526",
    "sg:postcode":"01000",
    "sg:province":"Istanbul",
    "sg:tags":[
        "house",
        "publishing"
    ],
    "wof:name":"Yeni Yasim Yayinlari Tic. Ltd. Sti.",
    "wof:placetype":"venue"
},
  "geometry": {"coordinates":[29.0262813568,40.9898834229],"type":"Point"}
}