{
  "type": "Feature",
  "properties": {
    "addr:full":"Organize Sanayi B?gesi 1. Cadde No:2 07100 Antalya",
    "addr:housenumber":"?;no 2",
    "addr:postcode":"07100",
    "addr:street":"Organize Sanayi B;Gesi 1 Cadde",
    "iso:country":"TR",
    "sg:address":"Organize Sanayi B?gesi 1. Cadde No:2",
    "sg:city":"07100",
    "sg:classifiers":[
        {
            "category":"Home & Garden",
            "subcategory":"Building Materials",
            "type":"Retail Goods"
        }
    ],
    "sg:phone":"+90 242 258 1620",
    "sg:province":"Antalya",
    "sg:tags":[
        "stone",
        "natural",
        "marble"
    ],
    "wof:name":"Akdeniz Marble",
    "wof:placetype":"venue"
},
  "geometry": {"coordinates":[30.7092056274,36.8790512085],"type":"Point"}
}