{
  "type": "Feature",
  "properties": {
    "addr:full":"Soylemis Koyu Yenisehir Bursa 31750",
    "addr:postcode":"31750",
    "iso:country":"TR",
    "sg:address":"Soylemis Koyu",
    "sg:city":"Yenisehir",
    "sg:classifiers":[
        {
            "category":"Food & Beverages",
            "subcategory":"Ethnic Foods",
            "type":"Retail Goods"
        }
    ],
    "sg:phone":"+90 224 793 4048",
    "sg:postcode":"31750",
    "sg:province":"Bursa",
    "sg:tags":[
        "canned"
    ],
    "wof:name":"Egesan Gida Ve Teks. Ur. San. Motolu Motorsuz Arac Ve Mak. Taah. Tic.ltd.sti.",
    "wof:placetype":"venue"
},
  "geometry": {"coordinates":[29.0586109161,40.1844291687],"type":"Point"}
}