{
  "type": "Feature",
  "properties": {
    "addr:full":"Samsun Yolu Mersin ?orum 52750",
    "addr:housenumber":"?",
    "addr:postcode":"52750",
    "addr:street":"Samsun Yolu",
    "iso:country":"TR",
    "sg:address":"Samsun Yolu",
    "sg:city":"Mersin",
    "sg:classifiers":[
        {
            "category":"Home & Garden",
            "subcategory":"Building Materials",
            "type":"Retail Goods"
        }
    ],
    "sg:phone":"+90 364 213 8396",
    "sg:postcode":"52750",
    "sg:province":"?orum",
    "sg:tags":[
        "plaster",
        "cement-concrete"
    ],
    "wof:name":"Corum Cimento San.a.s",
    "wof:placetype":"venue"
},
  "geometry": {"coordinates":[37.7128486633,41.0530204773],"type":"Point"}
}