{
  "type": "Feature",
  "properties": {
    "addr:full":"Meram San. Meram Cad. No:125 Yakutiye Konya 25200",
    "addr:housenumber":"125",
    "addr:postcode":"25200",
    "addr:street":"Meram Cad. No",
    "iso:country":"TR",
    "sg:address":"Meram San. Meram Cad. No:125",
    "sg:city":"Yakutiye",
    "sg:classifiers":[
        {
            "category":"Home & Garden",
            "subcategory":"Household Appliances",
            "type":"Retail Goods"
        }
    ],
    "sg:phone":"+90 3323222287320",
    "sg:postcode":"25200",
    "sg:province":"Konya",
    "sg:tags":[
        "kitchenware"
    ],
    "wof:name":"Ersoz&gonca Mutfak Mak.ve Ekipmn.san.tic.a.s.",
    "wof:placetype":"venue"
},
  "geometry": {"coordinates":[32.4990272522,37.8715362549],"type":"Point"}
}