{
  "type": "Feature",
  "properties": {
    "addr:full":"Menderes Mah.1.cad.no.35 Esenler Istanbul 01350",
    "addr:housenumber":"mah.1.cad.no.35",
    "addr:postcode":"01350",
    "addr:street":"Menderes",
    "iso:country":"TR",
    "sg:address":"Menderes Mah.1.cad.no.35",
    "sg:city":"Esenler",
    "sg:classifiers":[
        {
            "category":"Home & Garden",
            "subcategory":"Building Materials",
            "type":"Retail Goods"
        }
    ],
    "sg:phone":"+90 212 645 4149",
    "sg:postcode":"01350",
    "sg:province":"Istanbul",
    "sg:tags":[
        "window",
        "door",
        "plastic"
    ],
    "wof:name":"Y?e Kardesler Pensa ?retlcl Bayll",
    "wof:placetype":"venue"
},
  "geometry": {"coordinates":[28.847951889,41.0368347168],"type":"Point"}
}