{
  "type": "Feature",
  "properties": {
    "iso:country":"TR",
    "sg:address":"Seyhadil Cad.platin Sitesi No:67",
    "sg:city":"?nye",
    "sg:classifiers":[
        {
            "category":"Health Services",
            "subcategory":"Clinic",
            "type":"Services"
        }
    ],
    "sg:phone":"+90 344 225 7000",
    "sg:postcode":"52300",
    "sg:province":"Kahramanmaras",
    "wof:name":"Akdeniz Polikklinigi Ozel Saglik",
    "wof:placetype":"venue"
},
  "geometry": {"coordinates":[36.9280776978,37.5858345032],"type":"Point"}
}