{
  "type": "Feature",
  "properties": {
    "iso:country":"TR",
    "sg:address":"Kiremithane Mh. Kozan Cd. No:469",
    "sg:city":"Ara?",
    "sg:classifiers":[
        {
            "category":"Shopping",
            "subcategory":"Stationery & Office Supplies",
            "type":"Retail Goods"
        }
    ],
    "sg:phone":"+90 322 351 8439",
    "sg:postcode":"37800",
    "sg:province":"Adana",
    "sg:tags":[
        "furniture"
    ],
    "wof:name":"Keser Tic.",
    "wof:placetype":"venue"
},
  "geometry": {"coordinates":[35.3706817627,37.0056190491],"type":"Point"}
}