{
  "type": "Feature",
  "properties": {
    "addr:full":"Aytar Cd. Ufuk Apt. No:314 1.levent Osmangazi Istanbul 16240",
    "addr:housenumber":"314",
    "addr:postcode":"1.levent;16240",
    "addr:street":"Aytar Cd. Ufuk Apt. No",
    "iso:country":"TR",
    "sg:address":"Aytar Cd. Ufuk Apt. No:314 1.levent",
    "sg:city":"Osmangazi",
    "sg:classifiers":[
        {
            "category":"Professional",
            "subcategory":"Art Services",
            "type":"Services"
        }
    ],
    "sg:phone":"+90 212 270 1147",
    "sg:postcode":"16240",
    "sg:province":"Istanbul",
    "sg:tags":[
        "marketing"
    ],
    "wof:name":"Otokar Pazarlama A.s.",
    "wof:placetype":"venue"
},
  "geometry": {"coordinates":[28.9861831665,41.0408554077],"type":"Point"}
}