{
  "type": "Feature",
  "properties": {
    "addr:full":"Hosdere Cad. No:179/6 Y. Ayranci \u00dcmraniye Ankara",
    "addr:housenumber":"179 / 6 y.",
    "addr:street":"Hosdere Cad. No;Ayranci",
    "iso:country":"TR",
    "sg:address":"Hosdere Cad. No:179/6 Y. Ayranci",
    "sg:city":"\u00dcmraniye",
    "sg:classifiers":[
        {
            "category":"Manufacturing",
            "subcategory":"Chemicals & Compounds",
            "type":"Manufacturing & Wholesale Goods"
        }
    ],
    "sg:phone":"+90 312 441 6213",
    "sg:province":"Ankara",
    "sg:tags":[
        "pharmaceutical"
    ],
    "wof:name":"Berk Ith. Ihr. Ltd. Sti.",
    "wof:placetype":"venue"
},
  "geometry": {"coordinates":[32.8498725891,39.903465271],"type":"Point"}
}