{
  "type": "Feature",
  "properties": {
    "addr:full":"Hidiraga Mah. Aksosy Sok. No:14 Corlu Tekirdag 01770",
    "addr:housenumber":"no 14",
    "addr:postcode":"01770",
    "addr:street":"Hidiraga Mah. Aksosy Sok.",
    "iso:country":"TR",
    "sg:address":"Hidiraga Mah. Aksosy Sok. No:14",
    "sg:city":"Corlu",
    "sg:classifiers":[
        {
            "category":"Shopping",
            "subcategory":"Crafts & Fabrics",
            "type":"Retail Goods"
        }
    ],
    "sg:phone":"+90 282 650 1336",
    "sg:postcode":"01770",
    "sg:province":"Tekirdag",
    "sg:tags":[
        "weaving"
    ],
    "wof:name":"Aypa Tekstil Uretim Ve Pazarlama",
    "wof:placetype":"venue"
},
  "geometry": {"coordinates":[27.7870788574,41.1646690369],"type":"Point"}
}