{
  "type": "Feature",
  "properties": {
    "addr:full":"Abdulahaga Cad.no:1/a Arabayatagi Istanbul 16270",
    "addr:housenumber":"1 / a",
    "addr:postcode":"16270",
    "addr:street":"Cad.No",
    "iso:country":"TR",
    "sg:address":"Abdulahaga Cad.no:1/a",
    "sg:city":"Arabayatagi",
    "sg:classifiers":[
        {
            "category":"Social Services",
            "subcategory":"Retirement Home",
            "type":"Services"
        }
    ],
    "sg:phone":"+90 216 422 6050",
    "sg:postcode":"16270",
    "sg:province":"Istanbul",
    "sg:tags":[
        "door"
    ],
    "wof:name":"Copilot Reklam",
    "wof:placetype":"venue"
},
  "geometry": {"coordinates":[29.0438728333,41.0436973572],"type":"Point"}
}