{
  "type": "Feature",
  "properties": {
    "iso:country":"TR",
    "sg:address":"Dereboyu Sk. No:8/4 Istinye",
    "sg:city":"G.o.p.",
    "sg:classifiers":[
        {
            "category":"Home & Garden",
            "subcategory":"Furniture",
            "type":"Retail Goods"
        }
    ],
    "sg:phone":"+90 212 277 6327",
    "sg:province":"Istanbul",
    "sg:tags":[
        "armchair",
        "sofa"
    ],
    "wof:name":"Sehl Mobilya San.",
    "wof:placetype":"venue"
},
  "geometry": {"coordinates":[28.9861793518,41.040851593],"type":"Point"}
}