{
  "type": "Feature",
  "properties": {
    "addr:full":"Litros Yolu 2 Matbaacilar Sit. F Blok No:15 Topkapi Bak\u0131rk\u00f6y Istanbul",
    "addr:housenumber":"2;blok no 15",
    "addr:street":"Litros Yolu;Topkapi Bakirkoey",
    "iso:country":"TR",
    "sg:address":"Litros Yolu 2 Matbaacilar Sit. F Blok No:15 Topkapi",
    "sg:city":"Bak\u0131rk\u00f6y",
    "sg:classifiers":[
        {
            "category":"Shopping",
            "subcategory":"Stationery & Office Supplies",
            "type":"Retail Goods"
        }
    ],
    "sg:phone":"+90 212 576 5320",
    "sg:province":"Istanbul",
    "sg:tags":[
        "paper"
    ],
    "wof:name":"Konyalioglu Nakl. Ve Kagit. San. Tic.",
    "wof:placetype":"venue"
},
  "geometry": {"coordinates":[28.9759254456,41.0123786926],"type":"Point"}
}