{
  "type": "Feature",
  "properties": {
    "addr:full":"Spor Cad. Ma?a Meydani Sok. Simsek Apt. No 19/kat 4 Valide?sme/besiktas Mecidiyek\u00f6y Istanbul 34387",
    "addr:housenumber":"19 / kat 4 valide ?;/",
    "addr:postcode":"?;34387",
    "addr:street":"Spor Cad.;Meydani Sok. Simsek Apt. No;Sme",
    "iso:country":"TR",
    "sg:address":"Spor Cad. Ma?a Meydani Sok. Simsek Apt. No 19/kat 4 Valide?sme/besiktas",
    "sg:city":"Mecidiyek\u00f6y",
    "sg:classifiers":[
        {
            "category":"Shopping",
            "subcategory":"Photographic Equipment",
            "type":"Retail Goods"
        }
    ],
    "sg:phone":"+90 212 227 8114",
    "sg:postcode":"34387",
    "sg:province":"Istanbul",
    "sg:tags":[
        "photo"
    ],
    "wof:name":"Sudutyo Fotograf Hizmetleri",
    "wof:placetype":"venue"
},
  "geometry": {"coordinates":[28.9921588898,41.0720214844],"type":"Point"}
}