{
  "type": "Feature",
  "properties": {
    "iso:country":"TR",
    "sg:address":"Maltepe Cd. No.6",
    "sg:city":"Bayrampasa",
    "sg:classifiers":[
        {
            "category":"Food & Beverages",
            "subcategory":"Dairy",
            "type":"Retail Goods"
        }
    ],
    "sg:phone":"+90 212 576 4700",
    "sg:postcode":"36100",
    "sg:province":"Istanbul",
    "sg:tags":[
        "pruducts",
        "milk"
    ],
    "wof:name":"Yapas S?t ?rnleri",
    "wof:placetype":"venue"
},
  "geometry": {"coordinates":[29.2025585175,40.9701423645],"type":"Point"}
}