{
  "type": "Feature",
  "properties": {
    "addr:full":"Otosanayi Sitesi ?elik Sk.no.67 4.levent Istanbul",
    "iso:country":"TR",
    "sg:address":"Otosanayi Sitesi ?elik Sk.no.67",
    "sg:city":"4.levent",
    "sg:classifiers":[
        {
            "category":"Utilities",
            "subcategory":"Cable",
            "type":"Services"
        }
    ],
    "sg:phone":"+90 212 280 7000",
    "sg:province":"Istanbul",
    "sg:tags":[
        "cardboard",
        "corrugate"
    ],
    "wof:name":"Altug Ambalaj San.tic.ltd.sti.",
    "wof:placetype":"venue"
},
  "geometry": {"coordinates":[29.1157741547,41.0250778198],"type":"Point"}
}