{
  "type": "Feature",
  "properties": {
    "addr:full":"Dutlu Bahce M Fatih C No: 16 Sisli Antalya 65710",
    "addr:postcode":"65710",
    "addr:street":"Sisli",
    "iso:country":"TR",
    "sg:address":"Dutlu Bahce M Fatih C No: 16",
    "sg:city":"Sisli",
    "sg:classifiers":[
        {
            "category":"Government",
            "subcategory":"Fire Station",
            "type":"Public Place"
        }
    ],
    "sg:phone":"+90 242 334 9413",
    "sg:postcode":"65710",
    "sg:province":"Antalya",
    "sg:tags":[
        "decoration"
    ],
    "wof:name":"Yukseller Alci Dekorasyon",
    "wof:placetype":"venue"
},
  "geometry": {"coordinates":[30.7092056274,36.8790512085],"type":"Point"}
}