{
  "type": "Feature",
  "properties": {
    "addr:full":"Ali Cetinkaya Blv. No:54/1 Alsancak 07000 Izmir",
    "addr:housenumber":"54 / 1",
    "addr:postcode":"07000",
    "addr:street":"Blv. No",
    "iso:country":"TR",
    "sg:address":"Ali Cetinkaya Blv. No:54/1 Alsancak",
    "sg:city":"07000",
    "sg:classifiers":[
        {
            "category":"Wholesale",
            "subcategory":"Medical Equipment & Supplies",
            "type":"Manufacturing & Wholesale Goods"
        }
    ],
    "sg:phone":"+90 232 422 1323",
    "sg:province":"Izmir",
    "sg:tags":[
        "material"
    ],
    "wof:name":"Egemed Medikal",
    "wof:placetype":"venue"
},
  "geometry": {"coordinates":[27.1450805664,38.438419342],"type":"Point"}
}