{
  "type": "Feature",
  "properties": {
    "addr:full":"Kadir Topbas ?ivril Istanbul",
    "iso:country":"TR",
    "sg:address":"Kadir Topbas",
    "sg:city":"?ivril",
    "sg:classifiers":[
        {
            "category":"Government",
            "subcategory":"Office",
            "type":"Public Place"
        }
    ],
    "sg:phone":"+90 212 512 5500",
    "sg:province":"Istanbul",
    "sg:tags":[
        "municipality"
    ],
    "wof:name":"Istanbul B?y?ksehir Belediyesi",
    "wof:placetype":"venue"
},
  "geometry": {"coordinates":[28.4642353058,41.0329246521],"type":"Point"}
}