{
  "type": "Feature",
  "properties": {
    "iso:country":"TR",
    "sg:address":"Talatpasa Cd. No:28 B.evler",
    "sg:city":"Ikitelli",
    "sg:classifiers":[
        {
            "category":"Farming",
            "subcategory":"Fish & Marine Products",
            "type":"Manufacturing & Wholesale Goods"
        }
    ],
    "sg:phone":"+90 212 554 2202",
    "sg:postcode":"34306",
    "sg:province":"Istanbul",
    "sg:tags":[
        "automotive"
    ],
    "wof:name":"Seref Otomotiv San. Tic. Ltd. Sti.",
    "wof:placetype":"venue"
},
  "geometry": {"coordinates":[28.895450592,40.9856491089],"type":"Point"}
}