{
  "type": "Feature",
  "properties": {
    "iso:country":"TR",
    "sg:address":"Bolvadin",
    "sg:city":"Ankara",
    "sg:classifiers":[
        {
            "category":"Banks & Credit Unions",
            "subcategory":"Bank",
            "type":"Services"
        }
    ],
    "sg:phone":"+90 272 212 0905",
    "sg:postcode":"63570",
    "sg:province":"Afyon",
    "wof:name":"T?kiye Emlak Bankasi As",
    "wof:placetype":"venue"
},
  "geometry": {"coordinates":[31.590467,38.320854],"type":"Point"}
}