{
  "type": "Feature",
  "properties": {
    "addr:full":"Sair Nigar Cad. No:91 Osmanbey Istanbul 63000",
    "addr:postcode":"63000",
    "addr:street":"Sair Nigar",
    "iso:country":"TR",
    "sg:address":"Sair Nigar Cad. No:91",
    "sg:city":"Osmanbey",
    "sg:classifiers":[
        {
            "category":"Shopping",
            "subcategory":"Clothing, Apparel, & Fashions",
            "type":"Retail Goods"
        }
    ],
    "sg:phone":"+90 212 240 5278",
    "sg:postcode":"63000",
    "sg:province":"Istanbul",
    "sg:tags":[
        "men",
        "wear"
    ],
    "wof:name":"Aydinli New Classic",
    "wof:placetype":"venue"
},
  "geometry": {"coordinates":[28.9904079437,41.0532722473],"type":"Point"}
}