{
  "type": "Feature",
  "properties": {
    "addr:full":"Santral Sk.no.12 G?tepe Istanbul",
    "addr:housenumber":"santral;?",
    "addr:street":"Sk.No.12 G",
    "iso:country":"TR",
    "sg:address":"Santral Sk.no.12",
    "sg:city":"G?tepe",
    "sg:orig_category":"Non-classified Establishments",
    "sg:phone":"+90 212 283 1870",
    "sg:province":"Istanbul",
    "wof:name":"?st?nel Yumurta San.",
    "wof:placetype":"venue"
},
  "geometry": {"coordinates":[29.0038948059,41.0784187317],"type":"Point"}
}