{
  "type": "Feature",
  "properties": {
    "addr:full":"Garaj Cad.no: 35 Salihli Manisa 24600",
    "addr:housenumber":"35",
    "addr:postcode":"24600",
    "addr:street":"Salihli Manisa",
    "iso:country":"TR",
    "sg:address":"Garaj Cad.no: 35",
    "sg:city":"Salihli",
    "sg:classifiers":[
        {
            "category":"Farming",
            "subcategory":"Farm",
            "type":"Manufacturing & Wholesale Goods"
        }
    ],
    "sg:phone":"+90 236 714 4300",
    "sg:postcode":"24600",
    "sg:province":"Manisa",
    "sg:tags":[
        "agricultural",
        "product"
    ],
    "wof:name":"Tepe Circir Ve Tarim Urunleri Ith.ihr.ltd.sti.",
    "wof:placetype":"venue"
},
  "geometry": {"coordinates":[32.4871101379,37.8469772339],"type":"Point"}
}