{
  "type": "Feature",
  "properties": {
    "addr:full":"Ataturk Cad. Ruspazari Sok. Nilgun-1 Is Merkz. Kat:2 No:35 Merter Bursa 34010",
    "addr:housenumber":"nilgun-1;kat 2 no 35",
    "addr:postcode":"34010",
    "addr:street":"Ataturk Cad. Ruspazari Sok.;Bursa",
    "iso:country":"TR",
    "sg:address":"Ataturk Cad. Ruspazari Sok. Nilgun-1 Is Merkz. Kat:2 No:35",
    "sg:city":"Merter",
    "sg:orig_category":"Orthopedical Materials",
    "sg:phone":"+90 224 225 3820",
    "sg:postcode":"34010",
    "sg:province":"Bursa",
    "wof:name":"Has Medikal Tibbi Malzeme",
    "wof:placetype":"venue"
},
  "geometry": {"coordinates":[29.0580043793,40.1947555542],"type":"Point"}
}