{
  "type": "Feature",
  "properties": {
    "addr:full":"Hacimansur Sok.no:61 Osmanbey Istanbul 63000",
    "addr:housenumber":"61",
    "addr:postcode":"63000",
    "addr:street":"Osmanbey Istanbul",
    "iso:country":"TR",
    "sg:address":"Hacimansur Sok.no:61",
    "sg:city":"Osmanbey",
    "sg:classifiers":[
        {
            "category":"Shopping",
            "subcategory":"Clothing, Apparel, & Fashions",
            "type":"Retail Goods"
        }
    ],
    "sg:phone":"+90 212 233 6757",
    "sg:postcode":"63000",
    "sg:province":"Istanbul",
    "sg:tags":[
        "ready",
        "wear"
    ],
    "wof:name":"Modakon Koleksiyon Giyim San.tic.ltd.sti.",
    "wof:placetype":"venue"
},
  "geometry": {"coordinates":[28.9759254456,41.0123786926],"type":"Point"}
}