{
  "type": "Feature",
  "properties": {
    "iso:country":"TR",
    "sg:address":"Osmanaga Mah, Kusdili",
    "sg:city":"Kad\u0131k\u00f6y",
    "sg:classifiers":[
        {
            "category":"Banks & Credit Unions",
            "subcategory":"Bank",
            "type":"Services"
        }
    ],
    "sg:phone":"+90 216 337 3850",
    "sg:province":"81310",
    "wof:name":"T?kiye Emlak, Bankasi As",
    "wof:placetype":"venue"
},
  "geometry": {"coordinates":[29.031893,40.989494],"type":"Point"}
}