{
  "type": "Feature",
  "properties": {
    "iso:country":"TR",
    "sg:address":"Kisla Cd. No:81 Top?lar",
    "sg:city":"Kartal",
    "sg:classifiers":[
        {
            "category":"Manufacturing",
            "subcategory":"Tools & Machinery",
            "type":"Manufacturing & Wholesale Goods"
        }
    ],
    "sg:phone":"+90 212 567 6337",
    "sg:postcode":"34873",
    "sg:province":"Istanbul",
    "sg:tags":[
        "machine",
        "industry"
    ],
    "wof:name":"Burses Makina Disli San. Tic. Koll. Sti.",
    "wof:placetype":"venue"
},
  "geometry": {"coordinates":[29.2088298798,40.8937530518],"type":"Point"}
}