{
  "type": "Feature",
  "properties": {
    "addr:full":"Vatan Mh. Ar Sk. G?dallar 11 San. Sit. No:31 Bayrampasa \u00dcmraniye Istanbul",
    "addr:housenumber":"?;11;sit. no 31",
    "addr:street":"Mh.;Sk. G;Dallar;Bayrampasa",
    "iso:country":"TR",
    "sg:address":"Vatan Mh. Ar Sk. G?dallar 11 San. Sit. No:31 Bayrampasa",
    "sg:city":"\u00dcmraniye",
    "sg:classifiers":[
        {
            "category":"Building & Trades",
            "subcategory":"Construction",
            "type":"Services"
        }
    ],
    "sg:phone":"+90 212 567 5434",
    "sg:province":"Istanbul",
    "sg:tags":[
        "industry",
        "mold"
    ],
    "wof:name":"Ecem Kalip",
    "wof:placetype":"venue"
},
  "geometry": {"coordinates":[28.9011554718,41.0516204834],"type":"Point"}
}