{
  "type": "Feature",
  "properties": {
    "addr:full":"Mehmet Boran Sinanpasa Afyon 01220",
    "addr:postcode":"01220",
    "addr:street":"Afyon",
    "iso:country":"TR",
    "sg:address":"Mehmet Boran",
    "sg:city":"Sinanpasa",
    "sg:classifiers":[
        {
            "category":"Government",
            "subcategory":"Office",
            "type":"Public Place"
        }
    ],
    "sg:phone":"+90 272 249 4025",
    "sg:postcode":"01220",
    "sg:province":"Afyon",
    "sg:tags":[
        "municipality"
    ],
    "wof:name":"Nuribey Belediye Baskani",
    "wof:placetype":"venue"
},
  "geometry": {"coordinates":[37.0179252625,39.7512054443],"type":"Point"}
}