{
  "type": "Feature",
  "properties": {
    "iso:country":"TR",
    "sg:address":"Sehit Yarbay Cesur Cad.no:11 Sirinevler",
    "sg:city":"Besiktas",
    "sg:classifiers":[
        {
            "category":"Shopping",
            "subcategory":"Stationery & Office Supplies",
            "type":"Retail Goods"
        }
    ],
    "sg:phone":"+90 212 442 7390",
    "sg:postcode":"34347",
    "sg:province":"Istanbul",
    "wof:name":"Candas Buro Malz.san.tic.ltd.sti.",
    "wof:placetype":"venue"
},
  "geometry": {"coordinates":[28.848431,40.997208],"type":"Point"}
}