{
  "type": "Feature",
  "properties": {
    "iso:country":"TR",
    "sg:address":"Ibrahimpasa Mah.eski Sanayi Meydani Ikinci Blok No:54 50100",
    "sg:city":"\u00dcsk\u00fcdar",
    "sg:classifiers":[
        {
            "category":"Building & Trades",
            "subcategory":"Construction",
            "type":"Services"
        }
    ],
    "sg:phone":"+90 384 213 5563",
    "sg:province":"Nevsehir",
    "sg:tags":[
        "foundation"
    ],
    "wof:name":"Enderun Egitim Vakfi",
    "wof:placetype":"venue"
},
  "geometry": {"coordinates":[34.7140007019,38.6245994568],"type":"Point"}
}