{
  "type": "Feature",
  "properties": {
    "addr:full":"Bostanci San. Sit. Ilker Sok. Ilker2 Is Mrk. No:6/11 I?renk? Bostanci Istanbul 25900",
    "addr:housenumber":"ilker2;11 i ?;?",
    "addr:postcode":"25900",
    "addr:street":"Ilker Sok.;No 6 /",
    "iso:country":"TR",
    "sg:address":"Bostanci San. Sit. Ilker Sok. Ilker2 Is Mrk. No:6/11 I?renk?",
    "sg:city":"Bostanci",
    "sg:classifiers":[
        {
            "category":"Shopping",
            "type":"Retail Goods"
        }
    ],
    "sg:phone":"+90 216574828586",
    "sg:postcode":"25900",
    "sg:province":"Istanbul",
    "sg:tags":[
        "material",
        "cleaning"
    ],
    "wof:name":"Zeyd Chemical",
    "wof:placetype":"venue"
},
  "geometry": {"coordinates":[28.9861831665,41.0408554077],"type":"Point"}
}