{
  "type": "Feature",
  "properties": {
    "iso:country":"TR",
    "sg:address":"Kayseri Ankara Asfalti 25.km.",
    "sg:city":"Rami",
    "sg:classifiers":[
        {
            "category":"Manufacturing",
            "subcategory":"Food",
            "type":"Manufacturing & Wholesale Goods"
        }
    ],
    "sg:phone":"+90 352 385 1182",
    "sg:postcode":"34055",
    "sg:province":"Kayseri",
    "sg:tags":[
        "product",
        "floury",
        "macaroni"
    ],
    "wof:name":"S.erdem Un Sanayi Ve Tic.a.s.",
    "wof:placetype":"venue"
},
  "geometry": {"coordinates":[35.4364013672,38.7450408936],"type":"Point"}
}