{
  "type": "Feature",
  "properties": {
    "addr:full":"Moda C. Agabey Sk.no.24/3 Kad\u0131k\u00f6y Istanbul 34990",
    "addr:postcode":"34990",
    "iso:country":"TR",
    "sg:address":"Moda C. Agabey Sk.no.24/3",
    "sg:city":"Kad\u0131k\u00f6y",
    "sg:classifiers":[
        {
            "category":"Food & Beverages",
            "subcategory":"Meat & Fish",
            "type":"Retail Goods"
        }
    ],
    "sg:phone":"+90 216 349 4691",
    "sg:postcode":"34990",
    "sg:province":"Istanbul",
    "sg:tags":[
        "seafood"
    ],
    "wof:name":"Er-ku Gida San. Ve Dis Tic. Ltd.sti.",
    "wof:placetype":"venue"
},
  "geometry": {"coordinates":[29.025970459,40.984210968],"type":"Point"}
}