{
  "type": "Feature",
  "properties": {
    "iso:country":"TR",
    "sg:address":"Seda Sok.belediye Bloklari Kat:1 Blok D:13 Kozyatagi",
    "sg:city":"Y.dudullu",
    "sg:orig_category":"General Industrial Products",
    "sg:phone":"+90 216 349 4680",
    "sg:province":"Istanbul",
    "wof:name":"Premiere Products Mega Ltd.sti.",
    "wof:placetype":"venue"
},
  "geometry": {"coordinates":[29.0956859589,40.9689788818],"type":"Point"}
}