{
  "type": "Feature",
  "properties": {
    "addr:full":"Aksu Cd. Kayik? Sok. No:2 K.5 Deniz Apt. Bak\u0131rk\u00f6y Istanbul",
    "addr:housenumber":"no 2 k.5",
    "addr:street":"Cd.;? Sok.",
    "iso:country":"TR",
    "sg:address":"Aksu Cd. Kayik? Sok. No:2 K.5 Deniz Apt.",
    "sg:city":"Bak\u0131rk\u00f6y",
    "sg:classifiers":[
        {
            "category":"Professional",
            "subcategory":"Engineering",
            "type":"Services"
        }
    ],
    "sg:phone":"+90 5835961",
    "sg:province":"Istanbul",
    "sg:tags":[
        "architect"
    ],
    "wof:name":"Serart Mimarlik Tasarim Proje Tic. Ltd. Sti.",
    "wof:placetype":"venue"
},
  "geometry": {"coordinates":[28.9861793518,41.040851593],"type":"Point"}
}