{
  "type": "Feature",
  "properties": {
    "addr:full":"Dilovasi Gebze Gaziosmanpasa Kocaeli 34240",
    "addr:postcode":"34240",
    "addr:street":"Kocaeli",
    "iso:country":"TR",
    "sg:address":"Dilovasi Gebze",
    "sg:city":"Gaziosmanpasa",
    "sg:classifiers":[
        {
            "category":"Manufacturing",
            "subcategory":"Metals",
            "type":"Manufacturing & Wholesale Goods"
        }
    ],
    "sg:phone":"+90 262 641 2672",
    "sg:postcode":"34240",
    "sg:province":"Kocaeli",
    "sg:tags":[
        "iron-steel",
        "peoducts"
    ],
    "wof:name":"Yazici Demir ?elik San. A.s.",
    "wof:placetype":"venue"
},
  "geometry": {"coordinates":[29.5498218536,40.7742271423],"type":"Point"}
}