{
  "type": "Feature",
  "properties": {
    "iso:country":"TR",
    "sg:address":"Abana",
    "sg:city":"Denizli",
    "sg:classifiers":[
        {
            "category":"Banks & Credit Unions",
            "subcategory":"Bank",
            "type":"Services"
        }
    ],
    "sg:phone":"+90 366 214 1089",
    "sg:postcode":"01130",
    "sg:province":"Kastamonu",
    "wof:name":"T?kiye Halk Bankasi As",
    "wof:placetype":"venue"
},
  "geometry": {"coordinates":[33.7719,41.372299],"type":"Point"}
}