{
  "type": "Feature",
  "properties": {
    "addr:full":"Lamartin Cad. Gonul Apt. 16/2 Taksim Sahinbey Istanbul 27700",
    "addr:housenumber":"16 / 2",
    "addr:postcode":"27700",
    "addr:street":"Lamartin Cad. Gonul Apt.",
    "iso:country":"TR",
    "sg:address":"Lamartin Cad. Gonul Apt. 16/2 Taksim",
    "sg:city":"Sahinbey",
    "sg:classifiers":[
        {
            "category":"Shopping",
            "subcategory":"Crafts & Fabrics",
            "type":"Retail Goods"
        }
    ],
    "sg:phone":"+90 212 238 8744",
    "sg:postcode":"27700",
    "sg:province":"Istanbul",
    "sg:tags":[
        "textile",
        "-leather",
        "exporter"
    ],
    "wof:name":"Plasteltext Textile Goods Import & Export",
    "wof:placetype":"venue"
},
  "geometry": {"coordinates":[28.9861831665,41.0408554077],"type":"Point"}
}