{
  "type": "Feature",
  "properties": {
    "addr:full":"Izmir Yolu 17. Km. Beylerbeyi Koyu Selcuklu Denizli 32650",
    "addr:housenumber":"17 km.;koyu",
    "addr:postcode":"32650",
    "addr:street":"Izmir Yolu;Beylerbeyi",
    "iso:country":"TR",
    "sg:address":"Izmir Yolu 17. Km. Beylerbeyi Koyu",
    "sg:city":"Selcuklu",
    "sg:classifiers":[
        {
            "category":"Home & Garden",
            "subcategory":"Building Materials",
            "type":"Retail Goods"
        }
    ],
    "sg:phone":"+90 258 421 6366",
    "sg:postcode":"32650",
    "sg:province":"Denizli",
    "sg:tags":[
        "stone",
        "natural",
        "marble"
    ],
    "wof:name":"Subasioglu Marble Ind.",
    "wof:placetype":"venue"
},
  "geometry": {"coordinates":[29.0788803101,37.7851867676],"type":"Point"}
}