{
  "type": "Feature",
  "properties": {
    "iso:country":"TR",
    "sg:address":"Onur Sok.62/b-",
    "sg:city":"Maltepe",
    "sg:classifiers":[
        {
            "category":"Manufacturing",
            "subcategory":"Glass & Minerals",
            "type":"Manufacturing & Wholesale Goods"
        }
    ],
    "sg:phone":"+90 312 230 4040",
    "sg:postcode":"01000",
    "sg:province":"Ankara",
    "sg:tags":[
        "glass-mirror"
    ],
    "wof:name":"Aytac Cam",
    "wof:placetype":"venue"
},
  "geometry": {"coordinates":[32.8429641724,39.9309196472],"type":"Point"}
}