{
  "type": "Feature",
  "properties": {
    "addr:full":"Oto San. Sit. Celik Sk. No:30/a 4.levent Istanbul",
    "addr:housenumber":"30 / a 4.levent",
    "addr:street":"Sk. No",
    "iso:country":"TR",
    "sg:address":"Oto San. Sit. Celik Sk. No:30/a",
    "sg:city":"4.levent",
    "sg:classifiers":[
        {
            "category":"Government",
            "subcategory":"Fire Station",
            "type":"Public Place"
        }
    ],
    "sg:phone":"+90 212 269 4118",
    "sg:province":"Istanbul",
    "sg:tags":[
        "decoration"
    ],
    "wof:name":"Neo Donatim",
    "wof:placetype":"venue"
},
  "geometry": {"coordinates":[28.9861831665,41.0408554077],"type":"Point"}
}