{
  "type": "Feature",
  "properties": {
    "iso:country":"TR",
    "sg:address":"Eregli Yali Cd.no 19",
    "sg:city":"Kdz.eregli",
    "sg:classifiers":[
        {
            "category":"Freight",
            "type":"Transportation"
        }
    ],
    "sg:phone":"+90 372 323 7455",
    "sg:province":"Zonguldak",
    "sg:tags":[
        "agent",
        "shipping",
        "broker"
    ],
    "wof:name":"Oz-nak Denizcilik Ltd.sti.",
    "wof:placetype":"venue"
},
  "geometry": {"coordinates":[31.416052,41.28273],"type":"Point"}
}