{
  "type": "Feature",
  "properties": {
    "iso:country":"TR",
    "sg:address":"Ihsaniye Mah. Kirim Cad. No: 42/c",
    "sg:city":"Tuzla",
    "sg:classifiers":[
        {
            "category":"Manufacturing",
            "subcategory":"Building Materials",
            "type":"Manufacturing & Wholesale Goods"
        }
    ],
    "sg:phone":"+90 222 230 2415",
    "sg:postcode":"01900",
    "sg:province":"Eskisehir",
    "sg:tags":[
        "lifts-elevators"
    ],
    "wof:name":"Enis Asansor",
    "wof:placetype":"venue"
},
  "geometry": {"coordinates":[30.52318573,39.7792015076],"type":"Point"}
}