{
  "type": "Feature",
  "properties": {
    "addr:full":"Alemdag Cd. No:342 ?mraniye Yenibosna Istanbul 43270",
    "addr:housenumber":"no;?",
    "addr:postcode":"43270",
    "addr:street":"Alemdag Cd.;Mraniye Yenibosna",
    "iso:country":"TR",
    "sg:address":"Alemdag Cd. No:342 ?mraniye",
    "sg:city":"Yenibosna",
    "sg:classifiers":[
        {
            "category":"Manufacturing",
            "subcategory":"Rubber & Plastics",
            "type":"Manufacturing & Wholesale Goods"
        }
    ],
    "sg:phone":"+90 216 335 7519",
    "sg:postcode":"43270",
    "sg:province":"Istanbul",
    "sg:tags":[
        "industry"
    ],
    "wof:name":"Borplast Plastik San. Tic. Ltd. Sti.",
    "wof:placetype":"venue"
},
  "geometry": {"coordinates":[29.1885261536,41.0055923462],"type":"Point"}
}