{
  "type": "Feature",
  "properties": {
    "iso:country":"TR",
    "sg:address":"S. G?altay Cd. No:80 Bostanci",
    "sg:city":"Ikitelli",
    "sg:classifiers":[
        {
            "category":"Farming",
            "subcategory":"Fish & Marine Products",
            "type":"Manufacturing & Wholesale Goods"
        }
    ],
    "sg:phone":"+90 216 372 3700",
    "sg:postcode":"34550",
    "sg:province":"Istanbul",
    "sg:tags":[
        "automotive"
    ],
    "wof:name":"Demaks Otomotiv San. Tic. A.s.",
    "wof:placetype":"venue"
},
  "geometry": {"coordinates":[29.101480484,40.9702568054],"type":"Point"}
}