{
  "type": "Feature",
  "properties": {
    "iso:country":"TR",
    "sg:address":"Aktekke Mah. Egitim Fak.araligi No:26",
    "sg:city":"Emin\u00f6n\u00fc/Ca\u011falo\u011flu",
    "sg:classifiers":[
        {
            "category":"Shopping",
            "subcategory":"Stationery & Office Supplies",
            "type":"Retail Goods"
        }
    ],
    "sg:phone":"+90 366 212 8553",
    "sg:province":"Kastamonu",
    "wof:name":"Tore Kirtasiye-fotokopi",
    "wof:placetype":"venue"
},
  "geometry": {"coordinates":[33.7719,41.372299],"type":"Point"}
}