{
  "type": "Feature",
  "properties": {
    "addr:full":"Selvili Sk. C Bl. No:13 K:3 4. Levent 07100 Istanbul",
    "addr:housenumber":"bl. no 13 k 3 4",
    "addr:postcode":"07100",
    "addr:street":"Selvili Sk. C",
    "iso:country":"TR",
    "sg:address":"Selvili Sk. C Bl. No:13 K:3 4. Levent",
    "sg:city":"07100",
    "sg:orig_category":"Aluminium Carpentary",
    "sg:phone":"+90 212 280 7324",
    "sg:province":"Istanbul",
    "wof:name":"Alpi Dog A.s.",
    "wof:placetype":"venue"
},
  "geometry": {"coordinates":[29.0159626007,41.0816841125],"type":"Point"}
}