{
  "type": "Feature",
  "properties": {
    "iso:country":"TR",
    "sg:address":"Mahmuriye Mah. Feritpasa Cad. No: 197/b Istasyon Karsisi Meram",
    "sg:city":"Mecidiyek\u00f6y",
    "sg:classifiers":[
        {
            "category":"Sports & Exercise",
            "subcategory":"Tennis Court",
            "type":"Entertainment"
        }
    ],
    "sg:phone":"+90 332 321 1265",
    "sg:province":"Konya",
    "sg:tags":[
        "equipment",
        "material"
    ],
    "wof:name":"Fitnes Spor",
    "wof:placetype":"venue"
},
  "geometry": {"coordinates":[32.494499,37.870499],"type":"Point"}
}