{
  "type": "Feature",
  "properties": {
    "addr:full":"Atat?k Bul. Hastahane Yani Iskenderun Nevsehir 31200",
    "addr:postcode":"31200",
    "addr:street":"Bul. Hastahane Yani",
    "iso:country":"TR",
    "sg:address":"Atat?k Bul. Hastahane Yani",
    "sg:city":"Iskenderun",
    "sg:classifiers":[
        {
            "category":"Landmark",
            "subcategory":"Tourist Information",
            "type":"Public Place"
        }
    ],
    "sg:postcode":"31200",
    "sg:province":"Nevsehir",
    "sg:tags":[
        "tourism"
    ],
    "wof:name":"Turizm Danisma Burosu",
    "wof:placetype":"venue"
},
  "geometry": {"coordinates":[34.7110939026,38.6325645447],"type":"Point"}
}