{
  "type": "Feature",
  "properties": {
    "addr:full":"Atat?k Cd. Emek No:7/a D:1 Ey\u00fcp Kastamonu",
    "addr:housenumber":"a d 1;kastamonu",
    "addr:street":"K Cd.",
    "iso:country":"TR",
    "sg:address":"Atat?k Cd. Emek No:7/a D:1",
    "sg:city":"Ey\u00fcp",
    "sg:classifiers":[
        {
            "category":"Organizations",
            "subcategory":"Membership Organization",
            "type":"Services"
        }
    ],
    "sg:phone":"+90 366 214 3738",
    "sg:province":"Kastamonu",
    "wof:name":"Fotografcilar Dernegi",
    "wof:placetype":"venue"
},
  "geometry": {"coordinates":[33.8337211609,40.9265403748],"type":"Point"}
}