{
  "type": "Feature",
  "properties": {
    "addr:full":"Hanimeli Sok.no:21/21 Sihhiye Ankara 06410",
    "addr:housenumber":"21 / 21",
    "addr:postcode":"06410",
    "addr:street":"Sihhiye Ankara",
    "iso:country":"TR",
    "sg:address":"Hanimeli Sok.no:21/21",
    "sg:city":"Sihhiye",
    "sg:classifiers":[
        {
            "category":"Government",
            "subcategory":"Post Office",
            "type":"Public Place"
        }
    ],
    "sg:phone":"+90 312 232 3213",
    "sg:postcode":"06410",
    "sg:province":"Ankara",
    "sg:tags":[
        "distribution"
    ],
    "wof:name":"Ulusal Arastirma Dagitim Hizm.ltd.sti.",
    "wof:placetype":"venue"
},
  "geometry": {"coordinates":[32.8520622253,39.9258117676],"type":"Point"}
}