{
  "type": "Feature",
  "properties": {
    "addr:full":"Cakmak Mh. Harman Sk. 8/2 Umraniye ?aglayan/kagithane Istanbul 80300",
    "addr:housenumber":"8 / 2 umraniye ?",
    "addr:postcode":"80300",
    "addr:street":"Cakmak Mh. Harman Sk.;Aglayan",
    "iso:country":"TR",
    "sg:address":"Cakmak Mh. Harman Sk. 8/2 Umraniye",
    "sg:city":"?aglayan/kagithane",
    "sg:orig_category":"Aluminium Carpentary",
    "sg:phone":"+90 216 328 5635",
    "sg:postcode":"80300",
    "sg:province":"Istanbul",
    "wof:name":"Kut Al Alum. Dog. San. A.s.",
    "wof:placetype":"venue"
},
  "geometry": {"coordinates":[29.117181778,41.0203590393],"type":"Point"}
}