{
  "type": "Feature",
  "properties": {
    "addr:full":"Rihtim Cd. No:28/5 Derya Ismerk. Topkapi Okmeydani Istanbul 43050",
    "addr:housenumber":"no 28 / 5",
    "addr:postcode":"43050",
    "addr:street":"Rihtim Cd.;Derya Ismerk.",
    "iso:country":"TR",
    "sg:address":"Rihtim Cd. No:28/5 Derya Ismerk. Topkapi",
    "sg:city":"Okmeydani",
    "sg:classifiers":[
        {
            "category":"Shopping",
            "subcategory":"Stationery & Office Supplies",
            "type":"Retail Goods"
        }
    ],
    "sg:phone":"+90 212 346 1491",
    "sg:postcode":"43050",
    "sg:province":"Istanbul",
    "wof:name":"Simge Kirtasiye B?ro Malz.",
    "wof:placetype":"venue"
},
  "geometry": {"coordinates":[28.975925,41.012379],"type":"Point"}
}