{
  "type": "Feature",
  "properties": {
    "addr:full":"Edremit Belediyesi Edremit Balikesir 04500",
    "addr:postcode":"04500",
    "addr:street":"Balikesir",
    "iso:country":"TR",
    "sg:address":"Edremit Belediyesi",
    "sg:city":"Edremit",
    "sg:classifiers":[
        {
            "category":"Farming",
            "subcategory":"Farm & Veterinary Services",
            "type":"Manufacturing & Wholesale Goods"
        }
    ],
    "sg:phone":"+90 2663731235372",
    "sg:postcode":"04500",
    "sg:province":"Balikesir",
    "sg:tags":[
        "veterinarian"
    ],
    "wof:name":"Ali Enisi Isparta",
    "wof:placetype":"venue"
},
  "geometry": {"coordinates":[27.8833007812,39.6520996094],"type":"Point"}
}