{
  "type": "Feature",
  "properties": {
    "iso:country":"TR",
    "sg:address":"Necatibey Cad. No.22/1 Sihhiye",
    "sg:city":"\u00c7orlu",
    "sg:classifiers":[
        {
            "category":"Shopping",
            "subcategory":"Luggage & Leather Goods",
            "type":"Retail Goods"
        }
    ],
    "sg:phone":"+90 312 229 0063",
    "sg:province":"Ankara",
    "sg:tags":[
        "leather-fur",
        "wear"
    ],
    "wof:name":"Defile Deri Giyim San. Ltd.sti.",
    "wof:placetype":"venue"
},
  "geometry": {"coordinates":[32.8477630615,39.9471130371],"type":"Point"}
}