{
  "type": "Feature",
  "properties": {
    "addr:full":"Numunebag Cad. No:28/b Maltepe- B.pasa Istanbul",
    "addr:housenumber":"28 / b",
    "addr:street":"Numunebag Cad. No;Maltepe B.Pasa",
    "iso:country":"TR",
    "sg:address":"Numunebag Cad. No:28/b Maltepe-",
    "sg:city":"B.pasa",
    "sg:classifiers":[
        {
            "category":"Shopping",
            "subcategory":"Clothing, Apparel, & Fashions",
            "type":"Retail Goods"
        }
    ],
    "sg:phone":"+90 212567104361",
    "sg:province":"Istanbul",
    "sg:tags":[
        "manikin"
    ],
    "wof:name":"Temiz-is Dekorasyon",
    "wof:placetype":"venue"
},
  "geometry": {"coordinates":[29.1554393768,40.9500617981],"type":"Point"}
}