{
  "type": "Feature",
  "properties": {
    "addr:full":"San. Cd. No:29/7 Ulus Ankara 01940",
    "addr:housenumber":"no 29 / 7",
    "addr:postcode":"01940",
    "addr:street":"San. Cd.;Ulus Ankara",
    "iso:country":"TR",
    "sg:address":"San. Cd. No:29/7",
    "sg:city":"Ulus",
    "sg:classifiers":[
        {
            "category":"Building & Trades",
            "subcategory":"Electrical",
            "type":"Services"
        }
    ],
    "sg:phone":"+90 312 310 5144",
    "sg:postcode":"01940",
    "sg:province":"Ankara",
    "sg:tags":[
        "equipment",
        "lighting"
    ],
    "wof:name":"Akdekor Aydinlatma San. Tic.",
    "wof:placetype":"venue"
},
  "geometry": {"coordinates":[33.2379150391,39.9171562195],"type":"Point"}
}