{
  "type": "Feature",
  "properties": {
    "addr:full":"Cetin Emec Bulvari 4.cad. 94.sok.no:15 A.ovecler Ankara",
    "addr:housenumber":"4.cad;15",
    "addr:street":"Emec Bulvari;A.Ovecler",
    "iso:country":"TR",
    "sg:address":"Cetin Emec Bulvari 4.cad. 94.sok.no:15",
    "sg:city":"A.ovecler",
    "sg:classifiers":[
        {
            "category":"Home & Garden",
            "subcategory":"Garden Supply",
            "type":"Retail Goods"
        }
    ],
    "sg:phone":"+90 312 478 2601",
    "sg:province":"Ankara",
    "sg:tags":[
        "fertilize",
        "soil"
    ],
    "wof:name":"Dog-al Gubre Ve Tarim Urunleri A.s.",
    "wof:placetype":"venue"
},
  "geometry": {"coordinates":[32.8290061951,39.9234428406],"type":"Point"}
}