{
  "type": "Feature",
  "properties": {
    "addr:full":"Muttalip Cd. No:331 Istiklal Mh. Ertugrulbey Sk. No:9 Rami Eskisehir 34055",
    "addr:housenumber":"no",
    "addr:postcode":"34055",
    "addr:street":"Muttalip Cd.;Istiklal Mh. Ertugrulbey Sk. No 9 Rami Eskisehir",
    "iso:country":"TR",
    "sg:address":"Muttalip Cd. No:331 Istiklal Mh. Ertugrulbey Sk. No:9",
    "sg:city":"Rami",
    "sg:classifiers":[
        {
            "category":"Food & Beverages",
            "subcategory":"Dairy",
            "type":"Retail Goods"
        }
    ],
    "sg:phone":"+90 222 231 3341",
    "sg:postcode":"34055",
    "sg:province":"Eskisehir",
    "sg:tags":[
        "pruducts",
        "milk"
    ],
    "wof:name":"Necdet Alpata-gida Madde. Paz. Ltd. Sti.",
    "wof:placetype":"venue"
},
  "geometry": {"coordinates":[30.5175457001,39.7700805664],"type":"Point"}
}