{
  "type": "Feature",
  "properties": {
    "iso:country":"TR",
    "sg:address":"Iskitler Cd. No:35 Iskitler",
    "sg:city":"Task?r? 77100",
    "sg:classifiers":[
        {
            "category":"Retail",
            "subcategory":"Auto Repair",
            "type":"Services"
        }
    ],
    "sg:phone":"+90 312 342 1536",
    "sg:province":"Ankara",
    "sg:tags":[
        "maintenance"
    ],
    "wof:name":"Ergenler Oto Tic. Ltd. Sti.",
    "wof:placetype":"venue"
},
  "geometry": {"coordinates":[32.8499984741,39.9500007629],"type":"Point"}
}