{
  "type": "Feature",
  "properties": {
    "iso:country":"TR",
    "sg:address":"50.yil Mah. N Cad. 2273.sok. No:6 Sultanciftligi-g.o.pasa",
    "sg:city":"Merkez",
    "sg:classifiers":[
        {
            "category":"Wholesale",
            "subcategory":"Vending Machines",
            "type":"Manufacturing & Wholesale Goods"
        }
    ],
    "sg:phone":"+90 212 668 6333",
    "sg:postcode":"58070",
    "sg:province":"Istanbul",
    "sg:tags":[
        "rod",
        "welding"
    ],
    "wof:name":"Kanaat Kutu Makina San.tic. Ltd.sti.",
    "wof:placetype":"venue"
},
  "geometry": {"coordinates":[28.8710517883,41.0999984741],"type":"Point"}
}