{
  "type": "Feature",
  "properties": {
    "iso:country":"TR",
    "sg:address":"Ankara Asfalti ?zeri 5. Km. P.k. 214, 20100 Denizli",
    "sg:city":"Zeytinburnu",
    "sg:classifiers":[
        {
            "category":"Shopping",
            "subcategory":"Clothing, Apparel, & Fashions",
            "type":"Retail Goods"
        }
    ],
    "sg:phone":"+90 258 268 2822",
    "sg:postcode":"34020",
    "sg:province":"Ankara",
    "sg:tags":[
        "clothes"
    ],
    "sg:website":"http://www.egedemirteks.com",
    "wof:name":"Ege Demirteks Tekstil San. Ve Tic.ltd.sti.",
    "wof:placetype":"venue"
},
  "geometry": {"coordinates":[32.8604812622,39.9429283142],"type":"Point"}
}