{
  "type": "Feature",
  "properties": {
    "addr:full":"42. Sk. No:6 Merter Adana",
    "addr:housenumber":"42",
    "addr:street":"Sk. No 6 Merter",
    "iso:country":"TR",
    "sg:address":"42. Sk. No:6",
    "sg:city":"Merter",
    "sg:classifiers":[
        {
            "category":"Wholesale",
            "subcategory":"Machinery & Supplies",
            "type":"Manufacturing & Wholesale Goods"
        }
    ],
    "sg:phone":"+90 322 354 0314",
    "sg:province":"Adana",
    "sg:tags":[
        "heavy",
        "construction",
        "macinery"
    ],
    "wof:name":"?agri Is Mak.",
    "wof:placetype":"venue"
},
  "geometry": {"coordinates":[35.3250198364,36.9854202271],"type":"Point"}
}