{
  "type": "Feature",
  "properties": {
    "addr:full":"Nabizade Sok.no:42 Hasanpasa B???kmece Istanbul 34900",
    "addr:housenumber":"42;b ? ? ?",
    "addr:postcode":"34900",
    "addr:street":"Hasanpasa",
    "iso:country":"TR",
    "sg:address":"Nabizade Sok.no:42 Hasanpasa",
    "sg:city":"B???kmece",
    "sg:classifiers":[
        {
            "category":"Building & Trades",
            "subcategory":"Electrical",
            "type":"Services"
        }
    ],
    "sg:phone":"+90 216 345 0335",
    "sg:postcode":"34900",
    "sg:province":"Istanbul",
    "sg:tags":[
        "equipment",
        "electric"
    ],
    "wof:name":"Barsel Elektrik Ticaret Ve Sanayi Ltd.",
    "wof:placetype":"venue"
},
  "geometry": {"coordinates":[28.9861831665,41.0408554077],"type":"Point"}
}