{
  "type": "Feature",
  "properties": {
    "iso:country":"TR",
    "sg:address":"Konak Mahallesi",
    "sg:city":"S?e",
    "sg:classifiers":[
        {
            "category":"Banks & Credit Unions",
            "subcategory":"Bank",
            "type":"Services"
        }
    ],
    "sg:phone":"+90 256 518 1390",
    "sg:province":"09200",
    "wof:name":"Milli Aydin Bankasi Tas, Tarisbank",
    "wof:placetype":"venue"
},
  "geometry": {"coordinates":[28.980848,40.204781],"type":"Point"}
}