{
  "type": "Feature",
  "properties": {
    "iso:country":"TR",
    "sg:address":"Uluyol Sezen Sok. No:30/b",
    "sg:city":"Ikitelli/K\u00fc\u00e7\u00fck\u00e7ekmece",
    "sg:classifiers":[
        {
            "category":"Shopping",
            "subcategory":"Stationery & Office Supplies",
            "type":"Retail Goods"
        }
    ],
    "sg:phone":"+90 224 253 1097",
    "sg:postcode":"34660",
    "sg:province":"Bursa",
    "wof:name":"Akofset",
    "wof:placetype":"venue"
},
  "geometry": {"coordinates":[29.058004,40.194756],"type":"Point"}
}