{
  "type": "Feature",
  "properties": {
    "addr:full":"Ankara Yolu 12.km.kestel Ikitelli Bursa 34306",
    "addr:housenumber":"12.km.kestel",
    "addr:postcode":"34306",
    "addr:street":"Ankara Yolu;Bursa",
    "iso:country":"TR",
    "sg:address":"Ankara Yolu 12.km.kestel",
    "sg:city":"Ikitelli",
    "sg:classifiers":[
        {
            "category":"Farming",
            "subcategory":"Fish & Marine Products",
            "type":"Manufacturing & Wholesale Goods"
        }
    ],
    "sg:phone":"+90 224 372 9600",
    "sg:postcode":"34306",
    "sg:province":"Bursa",
    "sg:tags":[
        "automotive"
    ],
    "wof:name":"Turkkar Karasor San.tic.ltd.sti.",
    "wof:placetype":"venue"
},
  "geometry": {"coordinates":[29.0580043793,40.1947555542],"type":"Point"}
}