{
  "type": "Feature",
  "properties": {
    "addr:full":"Sara? Ishak Mah Mithatpasa Cadisbasi Sok.no:15-3 Beyazit Emin?n? 10020 Istanbul",
    "addr:housenumber":"15-3;emin ?;?",
    "addr:postcode":"10020",
    "addr:street":"Ishak Mah Mithatpasa Cadisbasi Sok.No;N",
    "iso:country":"TR",
    "sg:address":"Sara? Ishak Mah Mithatpasa Cadisbasi Sok.no:15-3 Beyazit Emin?n?",
    "sg:city":"10020",
    "sg:classifiers":[
        {
            "category":"Banks & Credit Unions",
            "subcategory":"Investment Brokerage",
            "type":"Services"
        }
    ],
    "sg:phone":"+90 212 638 4807",
    "sg:province":"Istanbul",
    "sg:tags":[
        "-",
        "export",
        "import"
    ],
    "wof:name":"Sahinler Ulusl.ve Dah.nak.tur.",
    "wof:placetype":"venue"
},
  "geometry": {"coordinates":[28.9861793518,41.040851593],"type":"Point"}
}