{
  "type": "Feature",
  "properties": {
    "iso:country":"TR",
    "sg:address":"Siteler Mah.selcukbey Cad.no:112",
    "sg:city":"Kartal",
    "sg:classifiers":[
        {
            "category":"Home & Garden",
            "subcategory":"Household Appliances",
            "type":"Retail Goods"
        }
    ],
    "sg:phone":"+90 224 368 4849",
    "sg:postcode":"46000",
    "sg:province":"Bursa",
    "sg:tags":[
        "conditioner",
        "air"
    ],
    "wof:name":"Imtay Klima",
    "wof:placetype":"venue"
},
  "geometry": {"coordinates":[29.0580043793,40.1947555542],"type":"Point"}
}