{
  "type": "Feature",
  "properties": {
    "iso:country":"TR",
    "sg:address":"Bilal G?demir",
    "sg:city":"Dazkiri",
    "sg:classifiers":[
        {
            "category":"Government",
            "subcategory":"Office",
            "type":"Public Place"
        }
    ],
    "sg:phone":"+90 272 423 5255",
    "sg:postcode":"03950",
    "sg:province":"Afyon",
    "sg:tags":[
        "municipality"
    ],
    "wof:name":"Y?egil Belediye Baskani",
    "wof:placetype":"venue"
},
  "geometry": {"coordinates":[29.2701835632,40.9512710571],"type":"Point"}
}