{
  "type": "Feature",
  "properties": {
    "addr:full":"Ataturk Bulvari Yurtbas Is Merkezi Kat:4 No:21 Bayrampasa Karaman 36100",
    "addr:housenumber":"kat 4 no 21",
    "addr:postcode":"36100",
    "addr:street":"Ataturk Bulvari Yurtbas;Bayrampasa Karaman",
    "iso:country":"TR",
    "sg:address":"Ataturk Bulvari Yurtbas Is Merkezi Kat:4 No:21",
    "sg:city":"Bayrampasa",
    "sg:classifiers":[
        {
            "category":"Manufacturing",
            "subcategory":"Tools & Machinery",
            "type":"Manufacturing & Wholesale Goods"
        }
    ],
    "sg:phone":"+90 338 414 9600",
    "sg:postcode":"36100",
    "sg:province":"Karaman",
    "sg:tags":[
        "machine",
        "industry"
    ],
    "wof:name":"Feza Mekanik Makina Sanayi",
    "wof:placetype":"venue"
},
  "geometry": {"coordinates":[33.2219009399,37.1814002991],"type":"Point"}
}