{
  "type": "Feature",
  "properties": {
    "iso:country":"TR",
    "sg:address":"Cobangulu Sok. 14/14 Gop",
    "sg:city":"Ikitelli",
    "sg:orig_category":"Beaty Parlors",
    "sg:phone":"+90 312 466 4646",
    "sg:postcode":"34306",
    "sg:province":"Ankara",
    "wof:name":"Cobangulu Guzellik Merkezi",
    "wof:placetype":"venue"
},
  "geometry": {"coordinates":[32.856033,39.943874],"type":"Point"}
}