{
  "type": "Feature",
  "properties": {
    "iso:country":"TR",
    "sg:address":"Halkali Cd. No:184/17 Sefakk?",
    "sg:city":"Mecidiyek\u00f6y",
    "sg:classifiers":[
        {
            "category":"Manufacturing",
            "subcategory":"Rubber & Plastics",
            "type":"Manufacturing & Wholesale Goods"
        }
    ],
    "sg:phone":"+90 212 698 2816",
    "sg:postcode":"34387",
    "sg:province":"Istanbul",
    "sg:tags":[
        "industry"
    ],
    "wof:name":"Plas-mas Plastik Mak. San. Tic. Ltd. Sti.",
    "wof:placetype":"venue"
},
  "geometry": {"coordinates":[28.7924251556,40.9708900452],"type":"Point"}
}