{
  "type": "Feature",
  "properties": {
    "addr:full":"Milli Egemenlik Cad. Ali ?zen Apt. No. 23 Mersin Antalya 52750",
    "addr:postcode":"52750",
    "addr:street":"Egemenlik Cad. Ali",
    "iso:country":"TR",
    "sg:address":"Milli Egemenlik Cad. Ali ?zen Apt. No. 23",
    "sg:city":"Mersin",
    "sg:classifiers":[
        {
            "category":"Personal",
            "subcategory":"Sauna",
            "type":"Services"
        }
    ],
    "sg:phone":"+90 242 248 9510",
    "sg:postcode":"52750",
    "sg:province":"Antalya",
    "sg:tags":[
        "pool"
    ],
    "wof:name":"Kulvar Havuzculuk Ltd. Sti.",
    "wof:placetype":"venue"
},
  "geometry": {"coordinates":[30.703135,36.887505],"type":"Point"}
}