{
  "type": "Feature",
  "properties": {
    "addr:full":"M. Kemalettin Cad. No:107/607 Cankaya Kartal Izmir 46000",
    "addr:housenumber":"107 / 607",
    "addr:postcode":"46000",
    "addr:street":"Kemalettin Cad. No;Cankaya Kartal",
    "iso:country":"TR",
    "sg:address":"M. Kemalettin Cad. No:107/607 Cankaya",
    "sg:city":"Kartal",
    "sg:classifiers":[
        {
            "category":"Wholesale",
            "subcategory":"Medical Equipment & Supplies",
            "type":"Manufacturing & Wholesale Goods"
        }
    ],
    "sg:phone":"+90 232 441 4208",
    "sg:postcode":"46000",
    "sg:province":"Izmir",
    "sg:tags":[
        "material"
    ],
    "wof:name":"Kardelen Medikal Ltd. Sti.",
    "wof:placetype":"venue"
},
  "geometry": {"coordinates":[27.1370582581,38.4233093262],"type":"Point"}
}