{
  "type": "Feature",
  "properties": {
    "iso:country":"TR",
    "sg:address":"Demirkapi Cad. Avas San. Sitesi No: 125 -topcular",
    "sg:city":"Eyup",
    "sg:classifiers":[
        {
            "category":"Arena",
            "subcategory":"Indoor Arena",
            "type":"Entertainment"
        }
    ],
    "sg:phone":"+90 212 544 3340",
    "sg:postcode":"60700",
    "sg:province":"Istanbul",
    "sg:tags":[
        "tent-canvas"
    ],
    "wof:name":"Kismet Plastik",
    "wof:placetype":"venue"
},
  "geometry": {"coordinates":[28.9861831665,41.0408554077],"type":"Point"}
}