{
  "type": "Feature",
  "properties": {
    "addr:full":"Hamidiye Mah.ataturk Cad. Besiktas I?el 80630",
    "addr:housenumber":"?",
    "addr:postcode":"80630",
    "addr:street":"Mah.Ataturk Cad. Besiktas I;El",
    "iso:country":"TR",
    "sg:address":"Hamidiye Mah.ataturk Cad.",
    "sg:city":"Besiktas",
    "sg:classifiers":[
        {
            "category":"Organizations",
            "subcategory":"Membership Organization",
            "type":"Services"
        }
    ],
    "sg:phone":"+90 324237446823",
    "sg:postcode":"80630",
    "sg:province":"I?el",
    "wof:name":"1925 Mersin Idmanyurdu Taraftarlar Dernegi",
    "wof:placetype":"venue"
},
  "geometry": {"coordinates":[28.9674797058,41.0096588135],"type":"Point"}
}