{
  "type": "Feature",
  "properties": {
    "iso:country":"TR",
    "sg:address":"Nizami Cedit Sk. No:6/1 Kadik?",
    "sg:city":"Okmeydani",
    "sg:orig_category":"Scavening Services",
    "sg:phone":"+90 216 346 8072",
    "sg:postcode":"43050",
    "sg:province":"Istanbul",
    "wof:name":"Akkent Hasere Ila?lama Servisi",
    "wof:placetype":"venue"
},
  "geometry": {"coordinates":[29.026339,40.994236],"type":"Point"}
}