{
  "type": "Feature",
  "properties": {
    "addr:full":"Uzun?rsi Cd. Tesbih? Sk. No:4 Emin?? Istanbul Eskigaraj Istanbul",
    "addr:housenumber":"?;? ?",
    "addr:street":"Uzun;Rsi Cd. Tesbih ? Sk. No 4 Emin",
    "iso:country":"TR",
    "sg:address":"Uzun?rsi Cd. Tesbih? Sk. No:4 Emin?? Istanbul",
    "sg:city":"Eskigaraj",
    "sg:classifiers":[
        {
            "category":"Manufacturing",
            "subcategory":"Rubber & Plastics",
            "type":"Manufacturing & Wholesale Goods"
        }
    ],
    "sg:phone":"+90 212 522 6965",
    "sg:province":"Istanbul",
    "sg:tags":[
        "industry"
    ],
    "wof:name":"Ser-bay Plastik San.",
    "wof:placetype":"venue"
},
  "geometry": {"coordinates":[28.9759254456,41.0123786926],"type":"Point"}
}