{
  "type": "Feature",
  "properties": {
    "iso:country":"TR",
    "sg:address":"Rauf Orbay Cad.g-47 No:26 Alticesmeler/",
    "sg:city":"Tuzla",
    "sg:classifiers":[
        {
            "category":"Airport",
            "subcategory":"International",
            "type":"Transportation"
        }
    ],
    "sg:phone":"+90 216 446 4706",
    "sg:postcode":"01900",
    "sg:province":"Istanbul",
    "wof:name":"G?ney Makina San.ve Tic.ltd.sti.",
    "wof:placetype":"venue"
},
  "geometry": {"coordinates":[28.9861831665,41.0408554077],"type":"Point"}
}