{
  "type": "Feature",
  "properties": {
    "addr:full":"Telsiz Mah. 84/1 Sk. No.44/a Zeytinburnu Merkez Istanbul 26120",
    "addr:housenumber":"84 / 1;a",
    "addr:postcode":"26120",
    "addr:street":"Telsiz Mah.;Sk. No.44 /",
    "iso:country":"TR",
    "sg:address":"Telsiz Mah. 84/1 Sk. No.44/a Zeytinburnu",
    "sg:city":"Merkez",
    "sg:classifiers":[
        {
            "category":"Shopping",
            "subcategory":"Clothing, Apparel, & Fashions",
            "type":"Retail Goods"
        }
    ],
    "sg:phone":"+90 212 546 3433",
    "sg:postcode":"26120",
    "sg:province":"Istanbul",
    "sg:tags":[
        "bag-belt-accessories"
    ],
    "wof:name":"Erya Ltd.sti.",
    "wof:placetype":"venue"
},
  "geometry": {"coordinates":[28.91326,40.998089],"type":"Point"}
}