{
  "type": "Feature",
  "properties": {
    "addr:full":"Arpasuyu Sk. No:10 Bomanti Istanbul",
    "addr:housenumber":"10",
    "addr:street":"Arpasuyu Sk. No",
    "iso:country":"TR",
    "sg:address":"Arpasuyu Sk. No:10",
    "sg:city":"Bomanti",
    "sg:classifiers":[
        {
            "category":"Airport",
            "subcategory":"International",
            "type":"Transportation"
        }
    ],
    "sg:phone":"+90 212 244 7916",
    "sg:province":"Istanbul",
    "wof:name":"Enko Nakliyat Tic. Ltd.",
    "wof:placetype":"venue"
},
  "geometry": {"coordinates":[28.9846725464,41.0553779602],"type":"Point"}
}