{
  "type": "Feature",
  "properties": {
    "addr:full":"Leylak Sok.murat Ismrk.b-blok K:11 D:36 Mecidiyek\u00f6y Istanbul 34387",
    "addr:housenumber":"11",
    "addr:postcode":"34387",
    "addr:street":"D 36 Mecidiyekoey",
    "iso:country":"TR",
    "sg:address":"Leylak Sok.murat Ismrk.b-blok K:11 D:36",
    "sg:city":"Mecidiyek\u00f6y",
    "sg:classifiers":[
        {
            "category":"Home & Garden",
            "subcategory":"Building Materials",
            "type":"Retail Goods"
        }
    ],
    "sg:phone":"+90 2122127240729",
    "sg:postcode":"34387",
    "sg:province":"Istanbul",
    "sg:tags":[
        "plaster",
        "cement-concrete"
    ],
    "wof:name":"Yildirim Dis Ticaret Ve Pazarlama A.s",
    "wof:placetype":"venue"
},
  "geometry": {"coordinates":[28.9861831665,41.0408554077],"type":"Point"}
}