{
  "type": "Feature",
  "properties": {
    "addr:full":"Ismetpasa Cd. No:29/c Siteler Antalya 07070",
    "addr:housenumber":"no 29 / c siteler",
    "addr:postcode":"07070",
    "addr:street":"Ismetpasa Cd.",
    "iso:country":"TR",
    "sg:address":"Ismetpasa Cd. No:29/c",
    "sg:city":"Siteler",
    "sg:classifiers":[
        {
            "category":"Manufacturing",
            "subcategory":"Glass & Minerals",
            "type":"Manufacturing & Wholesale Goods"
        }
    ],
    "sg:phone":"+90 242 241 7045",
    "sg:postcode":"07070",
    "sg:province":"Antalya",
    "sg:tags":[
        "glassware"
    ],
    "wof:name":"Ak Kaya Cam Koll. Ltd. Sti.",
    "wof:placetype":"venue"
},
  "geometry": {"coordinates":[30.7059688568,36.8899688721],"type":"Point"}
}