{
  "type": "Feature",
  "properties": {
    "addr:full":"Gavremoglu Mah. Tavlusun Cad. Nur Sk. Sitas Ishani No:7/9 Melikgazi Kayseri 38030",
    "addr:housenumber":"9",
    "addr:postcode":"38030",
    "addr:street":"Gavremoglu Mah. Tavlusun Cad.;Sk.;Ishani No 7 /",
    "iso:country":"TR",
    "sg:address":"Gavremoglu Mah. Tavlusun Cad. Nur Sk. Sitas Ishani No:7/9",
    "sg:city":"Melikgazi",
    "sg:orig_category":"Electric Contracter",
    "sg:phone":"+90 352 231 3979",
    "sg:postcode":"38030",
    "sg:province":"Kayseri",
    "wof:name":"Sila M?endislik",
    "wof:placetype":"venue"
},
  "geometry": {"coordinates":[36.4393234253,38.2791290283],"type":"Point"}
}