{
  "type": "Feature",
  "properties": {
    "addr:full":"Katircioglu Han K:4 No:401-402 Sultanhamam Istanbul",
    "addr:housenumber":"4",
    "addr:postcode":"401-402",
    "addr:street":"No",
    "iso:country":"TR",
    "sg:address":"Katircioglu Han K:4 No:401-402",
    "sg:city":"Sultanhamam",
    "sg:classifiers":[
        {
            "category":"Shopping",
            "subcategory":"Clothing, Apparel, & Fashions",
            "type":"Retail Goods"
        }
    ],
    "sg:phone":"+90 212 512 4950",
    "sg:province":"Istanbul",
    "sg:tags":[
        "men",
        "wear"
    ],
    "wof:name":"Sima Giyim",
    "wof:placetype":"venue"
},
  "geometry": {"coordinates":[28.9759254456,41.0123786926],"type":"Point"}
}