{
  "type": "Feature",
  "properties": {
    "addr:full":"1.organize San. Bolgesi Istikamet Cad. No:19 Selcuklu \u00dcmraniye Konya 81260",
    "addr:housenumber":"19",
    "addr:postcode":"1.organize;81260",
    "addr:street":"Istikamet Cad. No",
    "iso:country":"TR",
    "sg:address":"1.organize San. Bolgesi Istikamet Cad. No:19 Selcuklu",
    "sg:city":"\u00dcmraniye",
    "sg:classifiers":[
        {
            "category":"Manufacturing",
            "subcategory":"Tools & Machinery",
            "type":"Manufacturing & Wholesale Goods"
        }
    ],
    "sg:phone":"+90 332 251 4141",
    "sg:postcode":"81260",
    "sg:province":"Konya",
    "sg:tags":[
        "machine",
        "industry"
    ],
    "wof:name":"Mansur Dis Ticaret Ltd.sti.",
    "wof:placetype":"venue"
},
  "geometry": {"coordinates":[32.4990272522,37.8715362549],"type":"Point"}
}