{
  "type": "Feature",
  "properties": {
    "addr:full":"Yeni Sanayi Sitesi 4.blok No.1 Yesiloba Seyhan Adana 01100",
    "addr:housenumber":"4.blok no.1 yesiloba seyhan",
    "addr:postcode":"01100",
    "addr:street":"Yeni Sanayi Sitesi",
    "iso:country":"TR",
    "sg:address":"Yeni Sanayi Sitesi 4.blok No.1 Yesiloba",
    "sg:city":"Seyhan",
    "sg:classifiers":[
        {
            "category":"Shopping",
            "subcategory":"Stationery & Office Supplies",
            "type":"Retail Goods"
        }
    ],
    "sg:phone":"+90 322 429 1546",
    "sg:postcode":"01100",
    "sg:province":"Adana",
    "sg:tags":[
        "paper"
    ],
    "wof:name":"Safak Kagit Sanayi",
    "wof:placetype":"venue"
},
  "geometry": {"coordinates":[35.25025177,36.984413147],"type":"Point"}
}