{
  "type": "Feature",
  "properties": {
    "addr:full":"Valikonagi Caddesi Basaranlar . Istanbul 34365",
    "addr:postcode":"34365",
    "addr:street":"Valikonagi Caddesi",
    "iso:country":"TR",
    "sg:address":"Valikonagi Caddesi Basaranlar .",
    "sg:city":"Istanbul",
    "sg:classifiers":[
        {
            "category":"Travel",
            "subcategory":"Travel Agent",
            "type":"Entertainment"
        }
    ],
    "sg:phone":"+90 212 219 5307",
    "sg:province":"34365",
    "sg:website":"danytur.com",
    "wof:name":"Danytur Toursim And Travel",
    "wof:placetype":"venue"
},
  "geometry": {"coordinates":[28.5672702789,41.2639083862],"type":"Point"}
}