{
  "type": "Feature",
  "properties": {
    "addr:full":"Adnan Saygun Cad. Canan Sok. No:2/1 Ulus 80840 Cankaya Istanbul 07080",
    "addr:housenumber":"no 2 / 1",
    "addr:postcode":"80840;07080",
    "addr:street":"Saygun Cad. Canan Sok.;Ulus",
    "iso:country":"TR",
    "sg:address":"Adnan Saygun Cad. Canan Sok. No:2/1 Ulus 80840",
    "sg:city":"Cankaya",
    "sg:classifiers":[
        {
            "category":"Banks & Credit Unions",
            "subcategory":"Financial Services",
            "type":"Services"
        }
    ],
    "sg:phone":"+90 212 257 1355",
    "sg:postcode":"07080",
    "sg:province":"Istanbul",
    "sg:tags":[
        "finance"
    ],
    "wof:name":"Istanbul Finansal Danismanlik Hizmetleri A.s.",
    "wof:placetype":"venue"
},
  "geometry": {"coordinates":[29.0304374695,41.0608062744],"type":"Point"}
}