{
  "type": "Feature",
  "properties": {
    "iso:country":"TR",
    "sg:address":"2.bolge Tavsanli Koyu Esentepe Mevkii",
    "sg:city":"Gebze",
    "sg:classifiers":[
        {
            "category":"Home & Garden",
            "subcategory":"Building Materials",
            "type":"Retail Goods"
        }
    ],
    "sg:phone":"+90 262 724 9011",
    "sg:postcode":"41400",
    "sg:province":"Kocaeli",
    "sg:tags":[
        "stone",
        "natural",
        "marble"
    ],
    "wof:name":"Mendel Metalurji San.tic.ltd.sti.",
    "wof:placetype":"venue"
},
  "geometry": {"coordinates":[29.9345855713,40.7669563293],"type":"Point"}
}