{
  "type": "Feature",
  "properties": {
    "addr:full":"Millet Cd. Karag? Ishani K:3 No:202 Findikzade Istanbul",
    "addr:housenumber":"?;202",
    "addr:street":"Millet Cd. Karag;K 3 No",
    "iso:country":"TR",
    "sg:address":"Millet Cd. Karag? Ishani K:3 No:202",
    "sg:city":"Findikzade",
    "sg:classifiers":[
        {
            "category":"Airport",
            "subcategory":"International",
            "type":"Transportation"
        }
    ],
    "sg:phone":"+90 212 534 8176",
    "sg:province":"Istanbul",
    "wof:name":"Cemtir Uluslararasi Tasima. Tic.",
    "wof:placetype":"venue"
},
  "geometry": {"coordinates":[28.9861831665,41.0408554077],"type":"Point"}
}