{
  "type": "Feature",
  "properties": {
    "addr:full":"Atat?k Bul 167/a Baskent 06140 25700",
    "addr:housenumber":"167 / a",
    "addr:postcode":"06140 25700",
    "addr:street":"Bul;Baskent",
    "iso:country":"TR",
    "sg:address":"Atat?k Bul 167/a",
    "sg:city":"Baskent",
    "sg:classifiers":[
        {
            "category":"Banks & Credit Unions",
            "subcategory":"Bank",
            "type":"Services"
        }
    ],
    "sg:phone":"+90 312 419 0290",
    "sg:postcode":"25700",
    "sg:province":"06140",
    "wof:name":"Demirbank Tas",
    "wof:placetype":"venue"
},
  "geometry": {"coordinates":[34.628223,36.797989],"type":"Point"}
}