{
  "type": "Feature",
  "properties": {
    "addr:full":"Dervisoglu Sok. No:13 Besiktas Giresun 75200",
    "addr:housenumber":"no 13",
    "addr:postcode":"75200",
    "addr:street":"Dervisoglu Sok.;Besiktas",
    "iso:country":"TR",
    "sg:address":"Dervisoglu Sok. No:13",
    "sg:city":"Besiktas",
    "sg:classifiers":[
        {
            "category":"Freight",
            "type":"Transportation"
        }
    ],
    "sg:phone":"+90 454 212 6984",
    "sg:postcode":"75200",
    "sg:province":"Giresun",
    "sg:tags":[
        "agent",
        "shipping",
        "broker"
    ],
    "wof:name":"Ak & Diz Tic. Ltd.",
    "wof:placetype":"venue"
},
  "geometry": {"coordinates":[38.383411,40.915855],"type":"Point"}
}