{
  "type": "Feature",
  "properties": {
    "addr:full":"Atat?k Oto Sanayii Sit. 2. K1s1m. No:989 Maslak Istanbul 34398",
    "addr:housenumber":"2 k1s1m no 989",
    "addr:postcode":"34398",
    "addr:street":"Sit.",
    "iso:country":"TR",
    "sg:address":"Atat?k Oto Sanayii Sit. 2. K1s1m. No:989",
    "sg:city":"Maslak",
    "sg:classifiers":[
        {
            "category":"Farming",
            "subcategory":"Fish & Marine Products",
            "type":"Manufacturing & Wholesale Goods"
        }
    ],
    "sg:phone":"+90 532 543 1900",
    "sg:postcode":"34398",
    "sg:province":"Istanbul",
    "sg:tags":[
        "automotive"
    ],
    "wof:name":"?akir G?-ser Oto Pet.?r.ltd.sti.",
    "wof:placetype":"venue"
},
  "geometry": {"coordinates":[29.0198059082,41.1222839355],"type":"Point"}
}