{
  "type": "Feature",
  "properties": {
    "iso:country":"TR",
    "sg:address":"Cihannuma Mh. Bostanci Basi Sk. No:12/16 A Besiktas",
    "sg:city":"Emin\u00f6n\u00fc/Ca\u011falo\u011flu",
    "sg:classifiers":[
        {
            "category":"Shopping",
            "subcategory":"Stationery & Office Supplies",
            "type":"Retail Goods"
        }
    ],
    "sg:phone":"+90 212 261 7132",
    "sg:postcode":"34110",
    "sg:province":"Istanbul",
    "wof:name":"Turfan Kirtasiye",
    "wof:placetype":"venue"
},
  "geometry": {"coordinates":[29.007967,41.043674],"type":"Point"}
}