{
  "type": "Feature",
  "properties": {
    "addr:full":"Sahabiye, Otok Sok. No:38 /c Expo-karakoy Kayseri",
    "addr:housenumber":"no 38 / c expo-karakoy",
    "addr:street":"Otok Sok.",
    "iso:country":"TR",
    "sg:address":"Sahabiye, Otok Sok. No:38 /c",
    "sg:city":"Expo-karakoy",
    "sg:classifiers":[
        {
            "category":"Wholesale",
            "subcategory":"Home Furnishings",
            "type":"Manufacturing & Wholesale Goods"
        }
    ],
    "sg:phone":"+90 352 221 0718",
    "sg:province":"Kayseri",
    "sg:tags":[
        "furniture"
    ],
    "wof:name":"On Export",
    "wof:placetype":"venue"
},
  "geometry": {"coordinates":[36.4393234253,38.2791290283],"type":"Point"}
}