{
  "type": "Feature",
  "properties": {
    "addr:full":"F.kerim G?ay Cad.no:50/23 Kadik? Kad\u0131k\u00f6y Istanbul 34724",
    "addr:housenumber":"?;50 / 23;?",
    "addr:postcode":"34724",
    "addr:street":"F.Kerim G;Cad.No;Kadik",
    "iso:country":"TR",
    "sg:address":"F.kerim G?ay Cad.no:50/23 Kadik?",
    "sg:city":"Kad\u0131k\u00f6y",
    "sg:classifiers":[
        {
            "category":"Home & Garden",
            "subcategory":"Kitchen Supply",
            "type":"Retail Goods"
        }
    ],
    "sg:phone":"+90 216 348 0693",
    "sg:postcode":"34724",
    "sg:province":"Istanbul",
    "sg:tags":[
        "fire",
        "extinguisher"
    ],
    "wof:name":"Denge Yapi Ltd.",
    "wof:placetype":"venue"
},
  "geometry": {"coordinates":[29.0467185974,40.9827575684],"type":"Point"}
}