{
  "type": "Feature",
  "properties": {
    "iso:country":"TR",
    "sg:address":"Seyhli Mah. Kaynarca Cad. No:42",
    "sg:city":"Pendik",
    "sg:classifiers":[
        {
            "category":"Building & Trades",
            "subcategory":"Electrical",
            "type":"Services"
        }
    ],
    "sg:phone":"+90 216 378 8388",
    "sg:postcode":"34916",
    "sg:province":"Istanbul",
    "sg:tags":[
        "equipment",
        "lighting"
    ],
    "wof:name":"Eda Aydinlatma San. Ve Tic. Ltd.sti.",
    "wof:placetype":"venue"
},
  "geometry": {"coordinates":[29.2848148346,40.9044380188],"type":"Point"}
}