{
  "type": "Feature",
  "properties": {
    "addr:full":"Kalender Sok.no:9 Bakiroy Maltepe Istanbul 01000",
    "addr:housenumber":"9",
    "addr:postcode":"01000",
    "addr:street":"Sok.No;Maltepe",
    "iso:country":"TR",
    "sg:address":"Kalender Sok.no:9 Bakiroy",
    "sg:city":"Maltepe",
    "sg:classifiers":[
        {
            "category":"Wholesale",
            "subcategory":"Auto Parts",
            "type":"Manufacturing & Wholesale Goods"
        }
    ],
    "sg:phone":"+90 212 571 0882",
    "sg:postcode":"01000",
    "sg:province":"Istanbul",
    "sg:tags":[
        "spare"
    ],
    "wof:name":"Derby Lastik A.s",
    "wof:placetype":"venue"
},
  "geometry": {"coordinates":[28.9861831665,41.0408554077],"type":"Point"}
}