{
  "type": "Feature",
  "properties": {
    "addr:full":"Kagithane Cad. No:2/a 80360 Sisli Istanbul Merkez Istanbul 25000",
    "addr:housenumber":"a",
    "addr:postcode":"80360;25000",
    "addr:street":"Kagithane Cad. No 2 /",
    "iso:country":"TR",
    "sg:address":"Kagithane Cad. No:2/a 80360 Sisli Istanbul",
    "sg:city":"Merkez",
    "sg:classifiers":[
        {
            "category":"Manufacturing",
            "subcategory":"Wood Products",
            "type":"Manufacturing & Wholesale Goods"
        }
    ],
    "sg:phone":"+90 212 295 2930",
    "sg:postcode":"25000",
    "sg:province":"Istanbul",
    "sg:tags":[
        "furniture"
    ],
    "wof:name":"Demeter Dekorasyon Tasarim San Tic Ltd Sti",
    "wof:placetype":"venue"
},
  "geometry": {"coordinates":[28.9733314514,41.0742912292],"type":"Point"}
}