{
  "type": "Feature",
  "properties": {
    "iso:country":"TR",
    "sg:address":"Hamitler Mah. Neslihan Sok. No:36 Mudanya Yolu Uzeri",
    "sg:city":"Kartal",
    "sg:classifiers":[
        {
            "category":"Utilities",
            "subcategory":"Natural Gas",
            "type":"Services"
        }
    ],
    "sg:phone":"+90 224 242 5862",
    "sg:postcode":"46000",
    "sg:province":"Bursa",
    "sg:tags":[
        "tank-heating-natural"
    ],
    "wof:name":"Sirena Havuz & Sauna M.k.a Ins. Tes. Bilg. San. Ve Tic. Ltd.sti.",
    "wof:placetype":"venue"
},
  "geometry": {"coordinates":[29.0586109161,40.1844291687],"type":"Point"}
}