{
  "type": "Feature",
  "properties": {
    "iso:country":"TR",
    "sg:address":"Ticaret Sarayi No:30",
    "sg:city":"Topkapi",
    "sg:classifiers":[
        {
            "category":"Shopping",
            "subcategory":"Crafts & Fabrics",
            "type":"Retail Goods"
        }
    ],
    "sg:phone":"+90 224 221 2108",
    "sg:postcode":"24620",
    "sg:province":"Bursa",
    "sg:tags":[
        "yarn"
    ],
    "wof:name":"Gokdas Teks. ?rn. Gere?. Dis Tic.",
    "wof:placetype":"venue"
},
  "geometry": {"coordinates":[28.9638900757,40.244972229],"type":"Point"}
}