{
  "type": "Feature",
  "properties": {
    "iso:country":"TR",
    "sg:address":"Muvakkithane Cad.no.43",
    "sg:city":"Istanbul",
    "sg:classifiers":[
        {
            "category":"Banks & Credit Unions",
            "subcategory":"Bank",
            "type":"Services"
        }
    ],
    "sg:phone":"+90 216 348 9613",
    "sg:province":"Kadik?",
    "wof:name":"T?kiye Vakiflar, Bankasi Tao",
    "wof:placetype":"venue"
},
  "geometry": {"coordinates":[29.023432,40.990437],"type":"Point"}
}