{
  "type": "Feature",
  "properties": {
    "addr:full":"Eskikuyumcular Mah. ?avus Sok. No:13 Sirinevler Balikesir 15040",
    "addr:housenumber":"?;no 13",
    "addr:postcode":"15040",
    "addr:street":"Eskikuyumcular Mah.;Avus Sok.;Balikesir",
    "iso:country":"TR",
    "sg:address":"Eskikuyumcular Mah. ?avus Sok. No:13",
    "sg:city":"Sirinevler",
    "sg:classifiers":[
        {
            "category":"Home & Garden",
            "subcategory":"Household Appliances",
            "type":"Retail Goods"
        }
    ],
    "sg:phone":"+90 266 245 9413",
    "sg:postcode":"15040",
    "sg:province":"Balikesir",
    "sg:tags":[
        "conditioner",
        "air"
    ],
    "wof:name":"Savaslar Ltd.sti. Tekno-sav Sogutma Sanayi",
    "wof:placetype":"venue"
},
  "geometry": {"coordinates":[27.8830909729,39.6469230652],"type":"Point"}
}