{
  "type": "Feature",
  "properties": {
    "addr:full":"4.sok. No:7 Kisikkoy Izmir",
    "addr:housenumber":"no",
    "addr:street":"Kisikkoy",
    "iso:country":"TR",
    "sg:address":"4.sok. No:7",
    "sg:city":"Kisikkoy",
    "sg:classifiers":[
        {
            "category":"Home & Garden",
            "subcategory":"Household Appliances",
            "type":"Retail Goods"
        }
    ],
    "sg:phone":"+90 232 257 5562",
    "sg:province":"Izmir",
    "sg:tags":[
        "conditioner",
        "air"
    ],
    "wof:name":"Simka Makina Ltd.sti.",
    "wof:placetype":"venue"
},
  "geometry": {"coordinates":[27.2204399109,38.4675712585],"type":"Point"}
}