{
  "type": "Feature",
  "properties": {
    "addr:full":"Sanayi Sitesi 310 Sokak No:9 Iskenderun Hatay 31300",
    "addr:housenumber":"310;no 9",
    "addr:postcode":"31300",
    "addr:street":"Sanayi Sitesi;Sokak",
    "iso:country":"TR",
    "sg:address":"Sanayi Sitesi 310 Sokak No:9",
    "sg:city":"Iskenderun",
    "sg:classifiers":[
        {
            "category":"Utilities",
            "subcategory":"Electric",
            "type":"Services"
        }
    ],
    "sg:phone":"+90 326 615 1770",
    "sg:postcode":"31300",
    "sg:province":"Hatay",
    "sg:tags":[
        "accumulator",
        "-",
        "batery"
    ],
    "wof:name":"I.a.s. Iskenderun Ak?m?lat?r Sanayi",
    "wof:placetype":"venue"
},
  "geometry": {"coordinates":[29.301844,40.850857],"type":"Point"}
}