{
  "type": "Feature",
  "properties": {
    "iso:country":"TR",
    "sg:address":"Atak? 9 Kisim Atak?",
    "sg:city":"Kusadasi",
    "sg:orig_category":"Art Galeries",
    "sg:phone":"+90 212 559 8063",
    "sg:postcode":"09400",
    "sg:province":"Istanbul",
    "wof:name":"Atrium Sinemasi",
    "wof:placetype":"venue"
},
  "geometry": {"coordinates":[28.8492851257,40.9891548157],"type":"Point"}
}