{
  "type": "Feature",
  "properties": {
    "iso:country":"TR",
    "sg:address":"Istanbul Cad 19",
    "sg:city":"Kayseri",
    "sg:classifiers":[
        {
            "category":"Banks & Credit Unions",
            "subcategory":"Bank",
            "type":"Services"
        }
    ],
    "sg:phone":"+90 15613425",
    "sg:postcode":"63600",
    "sg:province":"Istanbul",
    "wof:name":"T?k Dis Ticaret, Bankasi As",
    "wof:placetype":"venue"
},
  "geometry": {"coordinates":[28.771137,40.990658],"type":"Point"}
}