{
  "type": "Feature",
  "properties": {
    "addr:full":"Koruma San. Sit. C-47 Kavakpinar Kaynarca - Pendik Merkez Istanbul 58070",
    "addr:housenumber":"c-47",
    "addr:postcode":"58070",
    "iso:country":"TR",
    "sg:address":"Koruma San. Sit. C-47 Kavakpinar Kaynarca - Pendik",
    "sg:city":"Merkez",
    "sg:classifiers":[
        {
            "category":"Wholesale",
            "subcategory":"Vending Machines",
            "type":"Manufacturing & Wholesale Goods"
        }
    ],
    "sg:phone":"+90 216 396 4622",
    "sg:postcode":"58070",
    "sg:province":"Istanbul",
    "sg:tags":[
        "rod",
        "welding"
    ],
    "wof:name":"Procon Makine Imalat Ltd.sti.",
    "wof:placetype":"venue"
},
  "geometry": {"coordinates":[28.9759254456,41.0123786926],"type":"Point"}
}