{
  "type": "Feature",
  "properties": {
    "iso:country":"TR",
    "sg:address":"Tahsin Tekoglu Cad. Bahar Sok. No: 3-5 /b Sefakoy",
    "sg:city":"Merkez",
    "sg:classifiers":[
        {
            "category":"Manufacturing",
            "subcategory":"Building Materials",
            "type":"Manufacturing & Wholesale Goods"
        }
    ],
    "sg:phone":"+90 212 424 5904",
    "sg:postcode":"07100",
    "sg:province":"Istanbul",
    "sg:tags":[
        "promotional"
    ],
    "wof:name":"Sindoma Promasyon Tekstil Ltd.sti.",
    "wof:placetype":"venue"
},
  "geometry": {"coordinates":[28.833480835,41.0055541992],"type":"Point"}
}