{
  "type": "Feature",
  "properties": {
    "addr:full":"Tasdelen Cd. No:27 Zemin Kat Siteler Gebze Ankara 41400",
    "addr:housenumber":"no 27;kat",
    "addr:postcode":"41400",
    "addr:street":"Tasdelen Cd.;Zemin",
    "iso:country":"TR",
    "sg:address":"Tasdelen Cd. No:27 Zemin Kat Siteler",
    "sg:city":"Gebze",
    "sg:classifiers":[
        {
            "category":"Manufacturing",
            "subcategory":"Metals",
            "type":"Manufacturing & Wholesale Goods"
        }
    ],
    "sg:phone":"+90 312 351 5665",
    "sg:postcode":"41400",
    "sg:province":"Ankara",
    "sg:tags":[
        "aluminium",
        "industry"
    ],
    "wof:name":"Can Al?minyum San. Tic. Ltd. Sti.",
    "wof:placetype":"venue"
},
  "geometry": {"coordinates":[32.8560333252,39.9438743591],"type":"Point"}
}