{
  "type": "Feature",
  "properties": {
    "iso:country":"TR",
    "sg:address":"2. Ata?sk. No:46/2 Kizilay",
    "sg:city":"Besiktas",
    "sg:classifiers":[
        {
            "category":"Manufacturing",
            "subcategory":"Chemicals & Compounds",
            "type":"Manufacturing & Wholesale Goods"
        }
    ],
    "sg:phone":"+90 312 431 4455",
    "sg:postcode":"75200",
    "sg:province":"Ankara",
    "sg:tags":[
        "medicine"
    ],
    "wof:name":"Elif Tic.",
    "wof:placetype":"venue"
},
  "geometry": {"coordinates":[32.8391685486,39.9221305847],"type":"Point"}
}