{
  "type": "Feature",
  "properties": {
    "addr:full":"Ismetpasa Mah. Ilk Belediye Baskani Cad. No.1/a-b Avcilar Gaziantep 01350",
    "addr:housenumber":"no.1 / a-b",
    "addr:postcode":"01350",
    "addr:street":"Ismetpasa Mah. Ilk Belediye Baskani Cad.;Avcilar Gaziantep",
    "iso:country":"TR",
    "sg:address":"Ismetpasa Mah. Ilk Belediye Baskani Cad. No.1/a-b",
    "sg:city":"Avcilar",
    "sg:classifiers":[
        {
            "category":"Real Estate",
            "subcategory":"Surveying",
            "type":"Services"
        }
    ],
    "sg:phone":"+90 342 230 7909",
    "sg:postcode":"01350",
    "sg:province":"Gaziantep",
    "sg:tags":[
        "adhesive",
        "glue"
    ],
    "wof:name":"Osman K?lekcioglu Tek.mak.san.mlz.ltd.sti.",
    "wof:placetype":"venue"
},
  "geometry": {"coordinates":[37.3829612732,37.0576972961],"type":"Point"}
}