{
  "type": "Feature",
  "properties": {
    "iso:country":"TR",
    "sg:address":"Yavuzturk Sok. Huzur Apt. 18/5 Kadikoy",
    "sg:city":"?emberlitas",
    "sg:classifiers":[
        {
            "category":"Shopping",
            "subcategory":"Jewelry",
            "type":"Retail Goods"
        }
    ],
    "sg:phone":"+90 216 347 1786",
    "sg:postcode":"34440",
    "sg:province":"Istanbul",
    "sg:tags":[
        "-",
        "golg-silver"
    ],
    "wof:name":"Realgold Veri Ve Kuyumculuk",
    "wof:placetype":"venue"
},
  "geometry": {"coordinates":[29.061788559,41.0254974365],"type":"Point"}
}