{
  "type": "Feature",
  "properties": {
    "addr:full":"Esat Cad. No:67-a/21 Kucukesat B Cigli Ankara",
    "addr:housenumber":"67-a / 21;b",
    "addr:street":"Esat Cad. No;Cigli",
    "iso:country":"TR",
    "sg:address":"Esat Cad. No:67-a/21 Kucukesat",
    "sg:city":"B Cigli",
    "sg:orig_category":"General Industrial Products",
    "sg:phone":"+90 312 425 5202",
    "sg:province":"Ankara",
    "wof:name":"Tuncel Silikon San.tic. Ltd.sti.",
    "wof:placetype":"venue"
},
  "geometry": {"coordinates":[32.861511,39.910538],"type":"Point"}
}