{
  "type": "Feature",
  "properties": {
    "addr:full":"Soganyemez Mah. Sitki Pasa Cad. Edremit Balikesir 04500",
    "addr:postcode":"04500",
    "addr:street":"Soganyemez Mah. Sitki Pasa Cad.",
    "iso:country":"TR",
    "sg:address":"Soganyemez Mah. Sitki Pasa Cad.",
    "sg:city":"Edremit",
    "sg:classifiers":[
        {
            "category":"Farming",
            "subcategory":"Farm & Veterinary Services",
            "type":"Manufacturing & Wholesale Goods"
        }
    ],
    "sg:phone":"+90 266 372 3701",
    "sg:postcode":"04500",
    "sg:province":"Balikesir",
    "sg:tags":[
        "clinic"
    ],
    "wof:name":"Ersin Hadimi Demirtas Korfez Vet .klinigi.",
    "wof:placetype":"venue"
},
  "geometry": {"coordinates":[27.8833007812,39.6520996094],"type":"Point"}
}