{
  "type": "Feature",
  "properties": {
    "iso:country":"TR",
    "sg:address":"Yayalar Mah. Sanayi Cad. Tuncel Sok. No:8",
    "sg:city":"Kurtkoy",
    "sg:classifiers":[
        {
            "category":"Shopping",
            "subcategory":"Clothing, Apparel, & Fashions",
            "type":"Retail Goods"
        }
    ],
    "sg:phone":"+90 216 307 4698",
    "sg:postcode":"74000",
    "sg:province":"Istanbul",
    "sg:tags":[
        "ready",
        "wear"
    ],
    "wof:name":"Canavar Tekstil San.tic. Ltd.sti.",
    "wof:placetype":"venue"
},
  "geometry": {"coordinates":[29.2656822205,40.8969078064],"type":"Point"}
}