{
  "type": "Feature",
  "properties": {
    "addr:full":"Yesil Cd. No:21 \u00dcmraniye Bursa 81240",
    "addr:housenumber":"no 21",
    "addr:postcode":"81240",
    "addr:street":"Yesil Cd.",
    "iso:country":"TR",
    "sg:address":"Yesil Cd. No:21",
    "sg:city":"\u00dcmraniye",
    "sg:classifiers":[
        {
            "category":"Home & Garden",
            "subcategory":"Kitchen Supply",
            "type":"Retail Goods"
        }
    ],
    "sg:phone":"+90 224 243 1905",
    "sg:postcode":"81240",
    "sg:province":"Bursa",
    "sg:tags":[
        "steel",
        "utensil"
    ],
    "wof:name":"Has Mak. San. Tic. A.s.",
    "wof:placetype":"venue"
},
  "geometry": {"coordinates":[29.071442,40.180679],"type":"Point"}
}