{
  "type": "Feature",
  "properties": {
    "addr:full":"Iskele Mey. No:8 ?esme Izmir",
    "addr:housenumber":"no 8 ?",
    "addr:street":"Mey.;Esme",
    "iso:country":"TR",
    "sg:address":"Iskele Mey. No:8",
    "sg:city":"?esme",
    "sg:classifiers":[
        {
            "category":"Landmark",
            "subcategory":"Tourist Information",
            "type":"Public Place"
        }
    ],
    "sg:phone":"+90 232 712 6653",
    "sg:province":"Izmir",
    "sg:tags":[
        "tourism"
    ],
    "wof:name":"Turizm Danisma Burosu",
    "wof:placetype":"venue"
},
  "geometry": {"coordinates":[27.1423015594,38.4251480103],"type":"Point"}
}