{
  "type": "Feature",
  "properties": {
    "iso:country":"TR",
    "sg:address":"B??dere Cad Meseli Sok No 9, 4 Levent, 80620 Istanbul",
    "sg:city":"Ankara",
    "sg:classifiers":[
        {
            "category":"Banks & Credit Unions",
            "subcategory":"Bank",
            "type":"Services"
        }
    ],
    "sg:postcode":"63570",
    "sg:province":"Istanbul",
    "wof:name":"Park Yatirim Bankasi As",
    "wof:placetype":"venue"
},
  "geometry": {"coordinates":[29.008299,41.087082],"type":"Point"}
}