{
  "type": "Feature",
  "properties": {
    "iso:country":"TR",
    "sg:address":"Feyzullah Efendi Sk. No: 16/b Fatih",
    "sg:city":"Kizilay",
    "sg:classifiers":[
        {
            "category":"Shopping",
            "subcategory":"Stationery & Office Supplies",
            "type":"Retail Goods"
        }
    ],
    "sg:phone":"+90 212 520 8310",
    "sg:postcode":"06650",
    "sg:province":"Istanbul",
    "wof:name":"Papi Kirtasiye Ve Oyuncak",
    "wof:placetype":"venue"
},
  "geometry": {"coordinates":[28.94886,41.016354],"type":"Point"}
}