{
  "type": "Feature",
  "properties": {
    "iso:country":"TR",
    "sg:address":"Davutpasa Cad. Emintas Kazim Dincol San. Sit. 81/98 Topkapi",
    "sg:city":"Ikitelli/K\u00fc\u00e7\u00fck\u00e7ekmece",
    "sg:orig_category":"General Industrial Products",
    "sg:phone":"+90 212 612 9508",
    "sg:postcode":"34670",
    "sg:province":"Istanbul",
    "wof:name":"Al-krom Sanayi Ve Ticaret",
    "wof:placetype":"venue"
},
  "geometry": {"coordinates":[28.9759254456,41.0123786926],"type":"Point"}
}