{
  "type": "Feature",
  "properties": {
    "addr:full":"Nuripasa Mah. 62.sok. No:36 Zeytinburnu Beyazit Istanbul 65400",
    "addr:housenumber":"62.sok no 36",
    "addr:postcode":"65400",
    "addr:street":"Nuripasa Mah.",
    "iso:country":"TR",
    "sg:address":"Nuripasa Mah. 62.sok. No:36 Zeytinburnu",
    "sg:city":"Beyazit",
    "sg:classifiers":[
        {
            "category":"Manufacturing",
            "subcategory":"Leather Goods",
            "type":"Manufacturing & Wholesale Goods"
        }
    ],
    "sg:phone":"+90 212 546 6183",
    "sg:postcode":"65400",
    "sg:province":"Istanbul",
    "wof:name":"Ugur Deri Deri Mam. San. Ve Tic. Ltd.sti.",
    "wof:placetype":"venue"
},
  "geometry": {"coordinates":[28.8992862701,40.986289978],"type":"Point"}
}