{
  "type": "Feature",
  "properties": {
    "iso:country":"TR",
    "sg:address":"Fener C. No.49/a",
    "sg:city":"Kiziltoprak",
    "sg:classifiers":[
        {
            "category":"Wholesale",
            "subcategory":"Machinery & Supplies",
            "type":"Manufacturing & Wholesale Goods"
        }
    ],
    "sg:phone":"+90 216 345 3355",
    "sg:postcode":"07300",
    "sg:province":"Istanbul",
    "sg:tags":[
        "agricultural"
    ],
    "wof:name":"Agro Teknik Zir.?rn. A.s.",
    "wof:placetype":"venue"
},
  "geometry": {"coordinates":[29.3005752563,40.8683624268],"type":"Point"}
}