{
  "type": "Feature",
  "properties": {
    "iso:country":"TR",
    "sg:address":"Manifaturacilar Sit. 746.sok. No:29",
    "sg:city":"Altindag",
    "sg:classifiers":[
        {
            "category":"Shopping",
            "subcategory":"Crafts & Fabrics",
            "type":"Retail Goods"
        }
    ],
    "sg:phone":"+90 232431047879",
    "sg:postcode":"07050",
    "sg:province":"Izmir",
    "sg:tags":[
        "embroidery"
    ],
    "wof:name":"Nema Tekstil Nakis Triko San. Ve Tic. Ltd.sti.",
    "wof:placetype":"venue"
},
  "geometry": {"coordinates":[27.1423015594,38.4251480103],"type":"Point"}
}