{
  "type": "Feature",
  "properties": {
    "iso:country":"TR",
    "sg:address":"Hattat Halim Sok. No:20 Gayrettepe",
    "sg:city":"Alsancak",
    "sg:classifiers":[
        {
            "category":"Professional",
            "subcategory":"Employment Agencies",
            "type":"Services"
        }
    ],
    "sg:phone":"+90 212 267 2016",
    "sg:postcode":"35221",
    "sg:province":"Istanbul",
    "sg:tags":[
        "machine"
    ],
    "wof:name":"Teknoser Ltd.sti.",
    "wof:placetype":"venue"
},
  "geometry": {"coordinates":[29.0088157654,41.0607414246],"type":"Point"}
}