{
  "type": "Feature",
  "properties": {
    "iso:country":"TR",
    "sg:address":"Paris Cad. No:6/6 K.dere",
    "sg:city":"Okmeydani/sisli",
    "sg:classifiers":[
        {
            "category":"Wholesale",
            "subcategory":"Medical Equipment & Supplies",
            "type":"Manufacturing & Wholesale Goods"
        }
    ],
    "sg:phone":"+90 312 425 4543",
    "sg:province":"Ankara",
    "wof:name":"Alfa Tek Ltd. Sti.",
    "wof:placetype":"venue"
},
  "geometry": {"coordinates":[32.8604812622,39.9429283142],"type":"Point"}
}