{
  "type": "Feature",
  "properties": {
    "addr:full":"Horozlu Han Mah.vaj-kur Sok. No: 2342300 Ikitelli/K\u00fc\u00e7\u00fck\u00e7ekmece Konya 34670",
    "addr:housenumber":"no",
    "addr:postcode":"34670",
    "addr:street":"Mah.Vaj-Kur Sok.",
    "iso:country":"TR",
    "sg:address":"Horozlu Han Mah.vaj-kur Sok. No: 2342300",
    "sg:city":"Ikitelli/K\u00fc\u00e7\u00fck\u00e7ekmece",
    "sg:classifiers":[
        {
            "category":"Wholesale",
            "subcategory":"Machinery & Supplies",
            "type":"Manufacturing & Wholesale Goods"
        }
    ],
    "sg:phone":"+90 332 248 0707",
    "sg:postcode":"34670",
    "sg:province":"Konya",
    "sg:tags":[
        "press",
        "hydraulic"
    ],
    "wof:name":"Global Hidrolik Otomotiv San.tic.ltd.sti.",
    "wof:placetype":"venue"
},
  "geometry": {"coordinates":[33.0667152405,39.2111282349],"type":"Point"}
}