{
  "type": "Feature",
  "properties": {
    "iso:country":"TR",
    "sg:address":"Organize San.bolg.8.cad.",
    "sg:city":"Pendik",
    "sg:classifiers":[
        {
            "category":"Home & Garden",
            "subcategory":"Building Materials",
            "type":"Retail Goods"
        }
    ],
    "sg:phone":"+90 352 321 1562",
    "sg:postcode":"34916",
    "sg:province":"Kayseri",
    "sg:tags":[
        "window",
        "door"
    ],
    "wof:name":"Ceka Celik Kapi",
    "wof:placetype":"venue"
},
  "geometry": {"coordinates":[36.4393234253,38.2791290283],"type":"Point"}
}