{
  "type": "Feature",
  "properties": {
    "addr:full":"Van Tatvan Yolu 35 -55 Ve 75.km. Alsancak Van 01365",
    "addr:housenumber":"35 -55;75.km",
    "addr:postcode":"01365",
    "addr:street":"Tatvan Yolu;Ve;Alsancak Van",
    "iso:country":"TR",
    "sg:address":"Van Tatvan Yolu 35 -55 Ve 75.km.",
    "sg:city":"Alsancak",
    "sg:classifiers":[
        {
            "category":"Manufacturing",
            "subcategory":"Chemicals & Compounds",
            "type":"Manufacturing & Wholesale Goods"
        }
    ],
    "sg:phone":"+90 432 217 8960",
    "sg:postcode":"01365",
    "sg:province":"Van",
    "sg:tags":[
        "industry"
    ],
    "wof:name":"Hakan Petrolleri A.s.",
    "wof:placetype":"venue"
},
  "geometry": {"coordinates":[43.3754463196,38.5082168579],"type":"Point"}
}