{
  "type": "Feature",
  "properties": {
    "iso:country":"TR",
    "sg:address":"100.yil Mh.ziraat Sk.no2/a",
    "sg:city":"Gayrettepe",
    "sg:classifiers":[
        {
            "category":"Freight",
            "type":"Transportation"
        }
    ],
    "sg:phone":"+90 282 261 6460",
    "sg:postcode":"34349",
    "sg:province":"Tekirdag",
    "sg:tags":[
        "agent",
        "shipping",
        "broker"
    ],
    "wof:name":"Atlantik Denizcilik Ltd.sti.",
    "wof:placetype":"venue"
},
  "geometry": {"coordinates":[27.5144,40.979198],"type":"Point"}
}