{
  "type": "Feature",
  "properties": {
    "iso:country":"TR",
    "sg:address":"Karaoglanoglu Cd. No:93/7 4.levent",
    "sg:city":"B.?ekmece",
    "sg:classifiers":[
        {
            "category":"Farming",
            "subcategory":"Fish & Marine Products",
            "type":"Manufacturing & Wholesale Goods"
        }
    ],
    "sg:phone":"+90 212 283 6647",
    "sg:province":"Istanbul",
    "sg:tags":[
        "automotive"
    ],
    "wof:name":"Gizem Otomotiv San. Tic. Ltd. Sti.",
    "wof:placetype":"venue"
},
  "geometry": {"coordinates":[28.996219635,41.099357605],"type":"Point"}
}