{
  "type": "Feature",
  "properties": {
    "iso:country":"TR",
    "sg:address":"Sumer Mah. No:9/b",
    "sg:city":"Zeytinburnu",
    "sg:classifiers":[
        {
            "category":"Manufacturing",
            "subcategory":"Building Materials",
            "type":"Manufacturing & Wholesale Goods"
        }
    ],
    "sg:phone":"+90 322 224 4006",
    "sg:postcode":"41000",
    "sg:province":"Adana",
    "sg:tags":[
        "lifts-elevators"
    ],
    "wof:name":"Kental Asansor",
    "wof:placetype":"venue"
},
  "geometry": {"coordinates":[35.3352775574,36.9861106873],"type":"Point"}
}