{
  "type": "Feature",
  "properties": {
    "addr:full":"Necip Mahmut Cad. No:71 Nizip Gaziantep 27700",
    "addr:housenumber":"71",
    "addr:postcode":"27700",
    "addr:street":"Mahmut Cad. No",
    "iso:country":"TR",
    "sg:address":"Necip Mahmut Cad. No:71",
    "sg:city":"Nizip",
    "sg:classifiers":[
        {
            "category":"Home & Garden",
            "subcategory":"Garden Supply",
            "type":"Retail Goods"
        }
    ],
    "sg:phone":"+90 342 517 3542",
    "sg:postcode":"27700",
    "sg:province":"Gaziantep",
    "sg:tags":[
        "fertilize",
        "soil"
    ],
    "wof:name":"Korkmaz Tarim Ticaret",
    "wof:placetype":"venue"
},
  "geometry": {"coordinates":[37.3715057373,37.0567970276],"type":"Point"}
}