{
  "type": "Feature",
  "properties": {
    "iso:country":"TR",
    "sg:address":"Ismetpasa Cad. Kilit 1 Ish. No:88",
    "sg:city":"Bornova",
    "sg:classifiers":[
        {
            "category":"Wholesale",
            "subcategory":"Machinery & Supplies",
            "type":"Manufacturing & Wholesale Goods"
        }
    ],
    "sg:phone":"+90 242 242 4493",
    "sg:postcode":"35040",
    "sg:province":"Antalya",
    "sg:tags":[
        "laboratory",
        "equipment"
    ],
    "wof:name":"Nur Medikal",
    "wof:placetype":"venue"
},
  "geometry": {"coordinates":[30.7031345367,36.8875045776],"type":"Point"}
}