{
  "type": "Feature",
  "properties": {
    "iso:country":"TR",
    "sg:address":"Istiklal Cd. No:14",
    "sg:city":"Kizilay",
    "sg:classifiers":[
        {
            "category":"Shopping",
            "subcategory":"Stationery & Office Supplies",
            "type":"Retail Goods"
        }
    ],
    "sg:phone":"+90 258 264 8262",
    "sg:postcode":"06650",
    "sg:province":"Denizli",
    "wof:name":"Palmiye Kitap Kirtasiye",
    "wof:placetype":"venue"
},
  "geometry": {"coordinates":[29.089491,37.772537],"type":"Point"}
}