{
  "type": "Feature",
  "properties": {
    "iso:country":"TR",
    "sg:address":"Mihrabat Cad. Ozkan Sk. Celik Is Merkezi, No.5 K.6 D.11",
    "sg:city":"Kavacik",
    "sg:classifiers":[
        {
            "category":"Building & Trades",
            "subcategory":"Landscaping Services",
            "type":"Services"
        }
    ],
    "sg:phone":"+90 216425757172",
    "sg:postcode":"15325",
    "sg:province":"Istanbul",
    "sg:tags":[
        "landscape"
    ],
    "wof:name":"Mega Servis Hizmetleri Ltd.sti.",
    "wof:placetype":"venue"
},
  "geometry": {"coordinates":[28.9759254456,41.0123786926],"type":"Point"}
}