{
  "type": "Feature",
  "properties": {
    "addr:full":"Oto Sanayi Sitesi, ?elik Cad. Zemin Kat No:39 4. Levent Istanbul 80660",
    "addr:housenumber":"kat no 39 4",
    "addr:postcode":"80660",
    "addr:street":"Sitesi;Elik Cad. Zemin",
    "iso:country":"TR",
    "sg:address":"Oto Sanayi Sitesi, ?elik Cad. Zemin Kat No:39",
    "sg:city":"4. Levent",
    "sg:classifiers":[
        {
            "category":"Wholesale",
            "subcategory":"Auto Parts",
            "type":"Manufacturing & Wholesale Goods"
        }
    ],
    "sg:phone":"+90 21228326670",
    "sg:postcode":"80660",
    "sg:province":"Istanbul",
    "sg:tags":[
        "spare"
    ],
    "wof:name":"T?mpar Yedek Par?a Sanayi Ve Ticaret",
    "wof:placetype":"venue"
},
  "geometry": {"coordinates":[28.9861831665,41.0408554077],"type":"Point"}
}