{
  "type": "Feature",
  "properties": {
    "addr:full":"Abdullah Cevdet Sok. No.13 Cankaya Y. Bosna Ankara",
    "addr:housenumber":"no.13",
    "addr:street":"Cevdet Sok.;Cankaya Y. Bosna",
    "iso:country":"TR",
    "sg:address":"Abdullah Cevdet Sok. No.13 Cankaya",
    "sg:city":"Y. Bosna",
    "sg:orig_category":"General Industrial Products",
    "sg:phone":"+90 312 440 9700",
    "sg:province":"Ankara",
    "wof:name":"Atilla Dogan Construction & Installation Co.inc.",
    "wof:placetype":"venue"
},
  "geometry": {"coordinates":[32.8566169739,39.8849105835],"type":"Point"}
}