{
  "type": "Feature",
  "properties": {
    "addr:full":"Ata Mail Alt Sanayi 3.sok.no:30 Hadimk? Aydin 34555",
    "addr:housenumber":"30;?",
    "addr:postcode":"34555",
    "addr:street":"Alt Sanayi 3.Sok.No;Aydin",
    "iso:country":"TR",
    "sg:address":"Ata Mail Alt Sanayi 3.sok.no:30",
    "sg:city":"Hadimk?",
    "sg:classifiers":[
        {
            "category":"Home & Garden",
            "subcategory":"Kitchen Supply",
            "type":"Retail Goods"
        }
    ],
    "sg:phone":"+90 256 211 3503",
    "sg:postcode":"34555",
    "sg:province":"Aydin",
    "sg:tags":[
        "wardrobe"
    ],
    "wof:name":"Dogsan",
    "wof:placetype":"venue"
},
  "geometry": {"coordinates":[28.4863967896,37.8117027283],"type":"Point"}
}