{
  "type": "Feature",
  "properties": {
    "addr:full":"G?ltepe Talatpasa Caddesi No:80 K:2 Kagithane Istanbul 34406",
    "addr:housenumber":"no 80 k 2",
    "addr:postcode":"34406",
    "addr:street":"Talatpasa Caddesi",
    "iso:country":"TR",
    "sg:address":"G?ltepe Talatpasa Caddesi No:80 K:2",
    "sg:city":"Kagithane",
    "sg:classifiers":[
        {
            "category":"Travel",
            "subcategory":"Travel Agent",
            "type":"Entertainment"
        }
    ],
    "sg:phone":"+90 279292372902123",
    "sg:postcode":"34406",
    "sg:province":"Istanbul",
    "sg:tags":[
        "agency",
        "tourism"
    ],
    "wof:name":"Asel Turizm",
    "wof:placetype":"venue"
},
  "geometry": {"coordinates":[28.9861831665,41.0408554077],"type":"Point"}
}