{
  "type": "Feature",
  "properties": {
    "iso:country":"TR",
    "sg:address":"1.organize San.cibi Sok.no:8 Selcuklu",
    "sg:city":"Ikitelli/K\u00fc\u00e7\u00fck\u00e7ekmece",
    "sg:classifiers":[
        {
            "category":"Manufacturing",
            "subcategory":"Tools & Machinery",
            "type":"Manufacturing & Wholesale Goods"
        }
    ],
    "sg:phone":"+90 332 251 8497",
    "sg:postcode":"34670",
    "sg:province":"Konya",
    "sg:tags":[
        "machine",
        "industry"
    ],
    "wof:name":"Taral-san Imalat",
    "wof:placetype":"venue"
},
  "geometry": {"coordinates":[32.4990272522,37.8715362549],"type":"Point"}
}