{
  "type": "Feature",
  "properties": {
    "iso:country":"TR",
    "sg:address":"Hosdere Cad.manolya Apt. No:51/9",
    "sg:city":"Sisli",
    "sg:classifiers":[
        {
            "category":"Professional",
            "subcategory":"Detective & Security Services",
            "type":"Services"
        }
    ],
    "sg:phone":"+90 3124662666466",
    "sg:postcode":"65710",
    "sg:province":"Ankara",
    "sg:tags":[
        "material"
    ],
    "wof:name":"Cosmo Guvenlik Ve Iletisim Sist.ve Servis Hizmetlei Ltd.sti.",
    "wof:placetype":"venue"
},
  "geometry": {"coordinates":[32.841389,39.889027],"type":"Point"}
}