{
  "type": "Feature",
  "properties": {
    "iso:country":"TR",
    "sg:address":"Sanayi Mah.boz Sok.no:14 4. Levent",
    "sg:city":"\u00dcmraniye",
    "sg:classifiers":[
        {
            "category":"Manufacturing",
            "subcategory":"Metals",
            "type":"Manufacturing & Wholesale Goods"
        }
    ],
    "sg:phone":"+90 212 282 3918",
    "sg:postcode":"34775",
    "sg:province":"Istanbul",
    "sg:tags":[
        "industry"
    ],
    "wof:name":"Begen Metal",
    "wof:placetype":"venue"
},
  "geometry": {"coordinates":[29.003370285,41.089969635],"type":"Point"}
}