{
  "type": "Feature",
  "properties": {
    "addr:full":"Numune Bag Cd. M?endisler Is Hani No: 8/26 Bayrampasa Istanbul 36100",
    "addr:housenumber":"numune;?;26",
    "addr:postcode":"36100",
    "addr:street":"Bag Cd. M;Bayrampasa Istanbul",
    "iso:country":"TR",
    "sg:address":"Numune Bag Cd. M?endisler Is Hani No: 8/26",
    "sg:city":"Bayrampasa",
    "sg:orig_category":"Tricot",
    "sg:phone":"+90 212 544 3626",
    "sg:postcode":"36100",
    "sg:province":"Istanbul",
    "wof:name":"Demsi Tekstil Sanayi Ve Dis Ticaret Ltd. Sti.",
    "wof:placetype":"venue"
},
  "geometry": {"coordinates":[28.9861831665,41.0408554077],"type":"Point"}
}