{
  "type": "Feature",
  "properties": {
    "iso:country":"TR",
    "sg:address":"Izmir Aydin Asfalti Menderes",
    "sg:city":"B?y?k?ekmece",
    "sg:classifiers":[
        {
            "category":"Food & Beverages",
            "subcategory":"Meat & Fish",
            "type":"Retail Goods"
        }
    ],
    "sg:phone":"+90 232 257 5815",
    "sg:province":"Izmir",
    "sg:tags":[
        "seafood"
    ],
    "wof:name":"Gur-ol Ltd.",
    "wof:placetype":"venue"
},
  "geometry": {"coordinates":[27.1539726257,38.1587333679],"type":"Point"}
}