{
  "type": "Feature",
  "properties": {
    "addr:full":"Ikitelli Org.san.bol.esot Sanayi Sit.r.blok No:5 Ikitelli Istanbul 34306",
    "addr:postcode":"34306",
    "addr:street":"Org.San.Bol.Esot Sanayi Sit.R.Blok No 5 Ikitelli",
    "iso:country":"TR",
    "sg:address":"Ikitelli Org.san.bol.esot Sanayi Sit.r.blok No:5",
    "sg:city":"Ikitelli",
    "sg:classifiers":[
        {
            "category":"Manufacturing",
            "subcategory":"Textiles",
            "type":"Manufacturing & Wholesale Goods"
        }
    ],
    "sg:phone":"+90 212 549 5084",
    "sg:postcode":"34306",
    "sg:province":"Istanbul",
    "sg:tags":[
        "cloth",
        "worker"
    ],
    "wof:name":"Aydin Is Guvenligi",
    "wof:placetype":"venue"
},
  "geometry": {"coordinates":[28.7984962463,41.0884017944],"type":"Point"}
}