{
  "type": "Feature",
  "properties": {
    "addr:full":"Bagdat Cad. No.92 Kiziltoprak Istanbul 07300",
    "addr:postcode":"07300",
    "addr:street":"Bagdat Cad. No.92 Kiziltoprak",
    "iso:country":"TR",
    "sg:address":"Bagdat Cad. No.92",
    "sg:city":"Kiziltoprak",
    "sg:classifiers":[
        {
            "category":"Farming",
            "subcategory":"Farm",
            "type":"Manufacturing & Wholesale Goods"
        }
    ],
    "sg:phone":"+90 212 371 9135",
    "sg:postcode":"07300",
    "sg:province":"Istanbul",
    "sg:tags":[
        "agricultural",
        "product"
    ],
    "wof:name":"Tarimsan Tarim ?r?nleri Ltd.sti.",
    "wof:placetype":"venue"
},
  "geometry": {"coordinates":[29.042383194,40.9804534912],"type":"Point"}
}