{
  "type": "Feature",
  "properties": {
    "addr:full":"Semsettin Gunaltay Cad. Kaya Sultan Sk. No: 37/4 Suadiye ?atalca Istanbul",
    "addr:housenumber":"37 / 4 suadiye ?",
    "addr:street":"Gunaltay Cad. Kaya Sultan Sk. No",
    "iso:country":"TR",
    "sg:address":"Semsettin Gunaltay Cad. Kaya Sultan Sk. No: 37/4 Suadiye",
    "sg:city":"?atalca",
    "sg:classifiers":[
        {
            "category":"Shopping",
            "subcategory":"Stationery & Office Supplies",
            "type":"Retail Goods"
        }
    ],
    "sg:phone":"+90 216 380 3979",
    "sg:province":"Istanbul",
    "wof:name":"Me & Ce Kirtasiye Ve Ofis Malzemeleri",
    "wof:placetype":"venue"
},
  "geometry": {"coordinates":[29.09063,40.965164],"type":"Point"}
}