{
  "type": "Feature",
  "properties": {
    "iso:country":"TR",
    "sg:address":"Istanbul Yolu No:18 ?ayirova",
    "sg:city":"Karak\u00f6y",
    "sg:classifiers":[
        {
            "category":"Mining & Drilling",
            "type":"Manufacturing & Wholesale Goods"
        }
    ],
    "sg:phone":"+90 262 641 1593",
    "sg:postcode":"80030",
    "sg:province":"Kocaeli",
    "sg:tags":[
        "industry",
        "mine"
    ],
    "wof:name":"Algaz Galvaniz A.s.",
    "wof:placetype":"venue"
},
  "geometry": {"coordinates":[29.3840827942,40.8114776611],"type":"Point"}
}