{
  "type": "Feature",
  "properties": {
    "iso:country":"TR",
    "sg:address":"Samanyolu Sk.no.18",
    "sg:city":"Osmanbey",
    "sg:classifiers":[
        {
            "category":"Shopping",
            "subcategory":"Clothing, Apparel, & Fashions",
            "type":"Retail Goods"
        }
    ],
    "sg:phone":"+90 212 247 2173",
    "sg:postcode":"63000",
    "sg:province":"Istanbul",
    "sg:tags":[
        "ready",
        "wear"
    ],
    "wof:name":"Lois-lucky Jeans",
    "wof:placetype":"venue"
},
  "geometry": {"coordinates":[28.8357200623,41.006439209],"type":"Point"}
}