{
  "type": "Feature",
  "properties": {
    "iso:country":"TR",
    "sg:address":"G?sel Cad Turhan Sok No:30 ?engelk?",
    "sg:city":"\u00dcsk\u00fcdar",
    "sg:classifiers":[
        {
            "category":"Utilities",
            "subcategory":"Water",
            "type":"Services"
        }
    ],
    "sg:phone":"+90 216 422 6430",
    "sg:postcode":"34680",
    "sg:province":"Istanbul",
    "sg:tags":[
        "waste",
        "treatment"
    ],
    "wof:name":"Nero Aritim Ltd",
    "wof:placetype":"venue"
},
  "geometry": {"coordinates":[29.0663566589,41.0437660217],"type":"Point"}
}