{
  "type": "Feature",
  "properties": {
    "addr:full":"Bagcilar Cd. No:15 Sishane Bursa",
    "addr:housenumber":"no 15",
    "addr:street":"Bagcilar Cd.",
    "iso:country":"TR",
    "sg:address":"Bagcilar Cd. No:15",
    "sg:city":"Sishane",
    "sg:classifiers":[
        {
            "category":"Building & Trades",
            "subcategory":"Electrical",
            "type":"Services"
        }
    ],
    "sg:phone":"+90 224 220 2702",
    "sg:province":"Bursa",
    "sg:tags":[
        "equipment",
        "lighting"
    ],
    "wof:name":"Aksam Aydinlatma",
    "wof:placetype":"venue"
},
  "geometry": {"coordinates":[29.0631160736,40.2073440552],"type":"Point"}
}