{
  "type": "Feature",
  "properties": {
    "addr:full":"Sehit Sok.no:45 Y.dudullu-umraniye Sehitkamil Istanbul 27120",
    "addr:housenumber":"45",
    "addr:postcode":"27120",
    "addr:street":"Sok.No",
    "iso:country":"TR",
    "sg:address":"Sehit Sok.no:45 Y.dudullu-umraniye",
    "sg:city":"Sehitkamil",
    "sg:classifiers":[
        {
            "category":"Shopping",
            "subcategory":"Stationery & Office Supplies",
            "type":"Retail Goods"
        }
    ],
    "sg:phone":"+90 216 415 4634",
    "sg:postcode":"27120",
    "sg:province":"Istanbul",
    "sg:tags":[
        "furniture"
    ],
    "wof:name":"Altineller Metal Mobilya San.ve Tic.ltd.sti.",
    "wof:placetype":"venue"
},
  "geometry": {"coordinates":[29.154592514,40.999458313],"type":"Point"}
}