{
  "type": "Feature",
  "properties": {
    "addr:full":"Rami Kisla Cad Apek ?retmen Is Merkezi C Blok No 262 Bayrampasa Istanbul 34610",
    "addr:housenumber":"apek ?;blok no 262",
    "addr:postcode":"34610",
    "addr:street":"Kisla Cad;Retmen;C;Bayrampasa Istanbul",
    "iso:country":"TR",
    "sg:address":"Rami Kisla Cad Apek ?retmen Is Merkezi C Blok No 262",
    "sg:city":"Bayrampasa",
    "sg:orig_category":"Pvc Packing",
    "sg:phone":"+90 212 493 0735",
    "sg:postcode":"34610",
    "sg:province":"Istanbul",
    "wof:name":"Istanbul Plastik Ambalaj Sanayi",
    "wof:placetype":"venue"
},
  "geometry": {"coordinates":[28.9759254456,41.0123786926],"type":"Point"}
}