{
  "type": "Feature",
  "properties": {
    "addr:full":"K. Mahmut Pehlivan Cd. No:17 Buca Eskisehir 35390",
    "addr:housenumber":"no 17",
    "addr:postcode":"35390",
    "addr:street":"Pehlivan Cd.;Buca Eskisehir",
    "iso:country":"TR",
    "sg:address":"K. Mahmut Pehlivan Cd. No:17",
    "sg:city":"Buca",
    "sg:classifiers":[
        {
            "category":"Professional",
            "subcategory":"Art Services",
            "type":"Services"
        }
    ],
    "sg:phone":"+90 222 233 0944",
    "sg:postcode":"35390",
    "sg:province":"Eskisehir",
    "sg:tags":[
        "marketing"
    ],
    "wof:name":"?nvak Genel Pazarlama Dagitim San. Tic. Ltd. Sti.",
    "wof:placetype":"venue"
},
  "geometry": {"coordinates":[30.5154705048,39.7782936096],"type":"Point"}
}