{
  "type": "Feature",
  "properties": {
    "addr:full":"Hisarpark Cad. Cantacilar Sok. 12/1 Ulus Ikitelli/K\u00fc\u00e7\u00fck\u00e7ekmece Ankara 34670",
    "addr:housenumber":"12 / 1",
    "addr:postcode":"34670",
    "addr:street":"Hisarpark Cad. Cantacilar Sok.;Ulus",
    "iso:country":"TR",
    "sg:address":"Hisarpark Cad. Cantacilar Sok. 12/1 Ulus",
    "sg:city":"Ikitelli/K\u00fc\u00e7\u00fck\u00e7ekmece",
    "sg:classifiers":[
        {
            "category":"Shopping",
            "subcategory":"Clothing, Apparel, & Fashions",
            "type":"Retail Goods"
        }
    ],
    "sg:phone":"+90 312 311 0931",
    "sg:postcode":"34670",
    "sg:province":"Ankara",
    "sg:tags":[
        "bag-belt-accessories"
    ],
    "wof:name":"Kenan Canta Deri Mamulleri Ltd.sti.",
    "wof:placetype":"venue"
},
  "geometry": {"coordinates":[32.856033,39.943874],"type":"Point"}
}