{
  "type": "Feature",
  "properties": {
    "addr:full":"Nafizbey Sok.yuvuz Apt. No:28/2 Hasanpasa-kadikoy G?ztepe Istanbul",
    "addr:housenumber":"?",
    "addr:street":"Hasanpasa-Kadikoy G",
    "iso:country":"TR",
    "sg:address":"Nafizbey Sok.yuvuz Apt. No:28/2 Hasanpasa-kadikoy",
    "sg:city":"G?ztepe",
    "sg:classifiers":[
        {
            "category":"Banks & Credit Unions",
            "subcategory":"Investment Brokerage",
            "type":"Services"
        }
    ],
    "sg:phone":"+90 216 348 7444",
    "sg:province":"Istanbul",
    "sg:tags":[
        "-",
        "export",
        "import"
    ],
    "wof:name":"Bosphorus Ic Ve Dis Tic.ltd.",
    "wof:placetype":"venue"
},
  "geometry": {"coordinates":[29.0294399261,40.9855613708],"type":"Point"}
}