{
  "type": "Feature",
  "properties": {
    "addr:full":"Baksan San. Sit. 55.blok No:2 Iskenderun Eskisehir 31200",
    "addr:housenumber":"no",
    "addr:postcode":"31200",
    "addr:street":"Baksan;Eskisehir",
    "iso:country":"TR",
    "sg:address":"Baksan San. Sit. 55.blok No:2",
    "sg:city":"Iskenderun",
    "sg:classifiers":[
        {
            "category":"Mining & Drilling",
            "type":"Manufacturing & Wholesale Goods"
        }
    ],
    "sg:phone":"+90 222 320 7172",
    "sg:postcode":"31200",
    "sg:province":"Eskisehir",
    "sg:tags":[
        "industry",
        "mine"
    ],
    "wof:name":"Teksim Seramik ?r?n. San. Tic. Ltd. Sti.",
    "wof:placetype":"venue"
},
  "geometry": {"coordinates":[30.5175457001,39.7700805664],"type":"Point"}
}