{
  "type": "Feature",
  "properties": {
    "addr:full":"1570 Sk. 16/404 Cinarli Ikitelli/K\u00fc\u00e7\u00fck\u00e7ekmece Izmir 34670",
    "addr:housenumber":"404",
    "addr:postcode":"34670",
    "addr:street":"1570 Sk. 16 /",
    "iso:country":"TR",
    "sg:address":"1570 Sk. 16/404 Cinarli",
    "sg:city":"Ikitelli/K\u00fc\u00e7\u00fck\u00e7ekmece",
    "sg:classifiers":[
        {
            "category":"Manufacturing",
            "subcategory":"Tools & Machinery",
            "type":"Manufacturing & Wholesale Goods"
        }
    ],
    "sg:phone":"+90 232 461 9497",
    "sg:postcode":"34670",
    "sg:province":"Izmir",
    "sg:tags":[
        "machine",
        "industry"
    ],
    "wof:name":"Siskon Endustriyel Otomasyon Sistemleri Ltd. Sti.",
    "wof:placetype":"venue"
},
  "geometry": {"coordinates":[27.1709003448,38.4406890869],"type":"Point"}
}