{
  "type": "Feature",
  "properties": {
    "iso:country":"TR",
    "sg:address":"G.o.pasa Blv. No.3/512",
    "sg:city":"Bandirma",
    "sg:classifiers":[
        {
            "category":"Home & Garden",
            "subcategory":"Garden Supply",
            "type":"Retail Goods"
        }
    ],
    "sg:phone":"+90 232 484 1135",
    "sg:postcode":"10200",
    "sg:province":"Izmir",
    "sg:tags":[
        "fertilize",
        "soil"
    ],
    "wof:name":"Unaldi Org. Likid Gubre San.ve Tic.a.s.",
    "wof:placetype":"venue"
},
  "geometry": {"coordinates":[27.1313705444,38.4225463867],"type":"Point"}
}