{
  "type": "Feature",
  "properties": {
    "addr:full":"Bahariye Caddesi No:83 - Kadik? Sisli Istanbul 65710",
    "addr:housenumber":"no 83;?",
    "addr:postcode":"65710",
    "addr:street":"Bahariye Caddesi;Kadik",
    "iso:country":"TR",
    "sg:address":"Bahariye Caddesi No:83 - Kadik?",
    "sg:city":"Sisli",
    "sg:classifiers":[
        {
            "category":"Health Services",
            "subcategory":"Medical Lab",
            "type":"Services"
        }
    ],
    "sg:phone":"+90 216 330 6224",
    "sg:postcode":"65710",
    "sg:province":"Istanbul",
    "wof:name":"?mit Tibbi Tahliller Laboratuvari",
    "wof:placetype":"venue"
},
  "geometry": {"coordinates":[28.9861831665,41.0408554077],"type":"Point"}
}