{
  "type": "Feature",
  "properties": {
    "addr:full":"615/1 No: 35 Camdibi Sisli Izmir 80260",
    "addr:housenumber":"615 / 1 no 35",
    "addr:postcode":"80260",
    "addr:street":"Camdibi Sisli",
    "iso:country":"TR",
    "sg:address":"615/1 No: 35 Camdibi",
    "sg:city":"Sisli",
    "sg:classifiers":[
        {
            "category":"Freight",
            "type":"Transportation"
        }
    ],
    "sg:phone":"+90 232 433 6731",
    "sg:postcode":"80260",
    "sg:province":"Izmir",
    "sg:tags":[
        "packing",
        "industry"
    ],
    "wof:name":"Yilmaz Ofset Matbaa Ve Ambalaj San.tic.a.s.",
    "wof:placetype":"venue"
},
  "geometry": {"coordinates":[27.1723747253,38.4367637634],"type":"Point"}
}