{
  "type": "Feature",
  "properties": {
    "iso:country":"TR",
    "sg:address":"Demirciler Sit. 6. Yol No:24",
    "sg:city":"Zeytinburnu",
    "sg:classifiers":[
        {
            "category":"Home & Garden",
            "subcategory":"Hardware",
            "type":"Retail Goods"
        }
    ],
    "sg:phone":"+90 212 510 9920",
    "sg:postcode":"41000",
    "sg:province":"Istanbul",
    "sg:tags":[
        "store"
    ],
    "wof:name":"Imer Hirdavat ?rt. Paz. A.s.",
    "wof:placetype":"venue"
},
  "geometry": {"coordinates":[28.8984298706,41.0040588379],"type":"Point"}
}