{
  "type": "Feature",
  "properties": {
    "iso:country":"TR",
    "sg:address":"Hatay",
    "sg:city":"Ikitelli/K\u00fc\u00e7\u00fck\u00e7ekmece",
    "sg:classifiers":[
        {
            "category":"Health Services",
            "subcategory":"Hospital",
            "type":"Services"
        }
    ],
    "sg:phone":"+90 326 613 3570",
    "sg:postcode":"34660",
    "sg:province":"Hatay",
    "sg:tags":[
        "state"
    ],
    "wof:name":"Iskenderun Devlet Hastanesi",
    "wof:placetype":"venue"
},
  "geometry": {"coordinates":[36.174168,36.430279],"type":"Point"}
}