{
  "type": "Feature",
  "properties": {
    "iso:country":"TR",
    "sg:address":"Saydam Cd. No:139",
    "sg:city":"Kazasker",
    "sg:classifiers":[
        {
            "category":"Manufacturing",
            "subcategory":"Chemicals & Compounds",
            "type":"Manufacturing & Wholesale Goods"
        }
    ],
    "sg:phone":"+90 322 352 1021",
    "sg:province":"Adana",
    "sg:tags":[
        "pharmaceutical"
    ],
    "wof:name":"?zaltin Ecza Depo San. Tic. A.s.",
    "wof:placetype":"venue"
},
  "geometry": {"coordinates":[35.324848175,36.9842605591],"type":"Point"}
}