{
  "type": "Feature",
  "properties": {
    "iso:country":"TR",
    "sg:address":"?engelk?- Kirazlitepe Mah.kazdal Cad. Oral Apt. No:28/2",
    "sg:city":"\u00dcsk\u00fcdar",
    "sg:classifiers":[
        {
            "category":"Manufacturing",
            "subcategory":"Textiles",
            "type":"Manufacturing & Wholesale Goods"
        }
    ],
    "sg:phone":"+90 216 422 5055",
    "sg:postcode":"34672",
    "sg:province":"Istanbul",
    "sg:tags":[
        "cloth",
        "worker"
    ],
    "wof:name":"Oral Imalat At?lyesi",
    "wof:placetype":"venue"
},
  "geometry": {"coordinates":[29.0154418945,41.0218315125],"type":"Point"}
}