{
  "type": "Feature",
  "properties": {
    "iso:country":"TR",
    "sg:address":"Nigde",
    "sg:city":"Ikitelli/K\u00fc\u00e7\u00fck\u00e7ekmece",
    "sg:classifiers":[
        {
            "category":"Health Services",
            "subcategory":"Hospital",
            "type":"Services"
        }
    ],
    "sg:phone":"+90 388 311 7887",
    "sg:postcode":"34660",
    "sg:province":"Nigde",
    "sg:tags":[
        "state"
    ],
    "wof:name":"Bor Devlet Hastanesi",
    "wof:placetype":"venue"
},
  "geometry": {"coordinates":[34.672867,37.96854],"type":"Point"}
}