{
  "type": "Feature",
  "properties": {
    "addr:full":"Mega Center 12.sok C-22 Blok No:180 Kocatepe Bayrampasa Istanbul 34045",
    "addr:housenumber":"12.sok c-22 blok no 180",
    "addr:postcode":"34045",
    "iso:country":"TR",
    "sg:address":"Mega Center 12.sok C-22 Blok No:180 Kocatepe",
    "sg:city":"Bayrampasa",
    "sg:classifiers":[
        {
            "category":"Food & Beverages",
            "subcategory":"Groceries & Convenience Stores",
            "type":"Retail Goods"
        }
    ],
    "sg:phone":"+90 212 640 4571",
    "sg:postcode":"34045",
    "sg:province":"Istanbul",
    "sg:tags":[
        "product"
    ],
    "wof:name":"Kahvecioglu Gida San.dis Tic.ltd. Sti",
    "wof:placetype":"venue"
},
  "geometry": {"coordinates":[28.8922977448,41.0516815186],"type":"Point"}
}