{
  "type": "Feature",
  "properties": {
    "iso:country":"TR",
    "sg:address":"Estim 4.cad. No:39",
    "sg:city":"Kisikk?",
    "sg:orig_category":"Food Machinies",
    "sg:phone":"+90 232 257 6878",
    "sg:postcode":"35410",
    "sg:province":"Izmir",
    "wof:name":"Ormepms Packaging Machines",
    "wof:placetype":"venue"
},
  "geometry": {"coordinates":[27.1264743805,38.3336257935],"type":"Point"}
}