{
  "type": "Feature",
  "properties": {
    "iso:country":"TR",
    "sg:address":"Cumhuriyet Cad. Kavakli Sok. No:2 Koscagiz",
    "sg:city":"Sirinyer",
    "sg:classifiers":[
        {
            "category":"Organizations",
            "subcategory":"Membership Organization",
            "type":"Services"
        }
    ],
    "sg:phone":"+90 378 233 2050",
    "sg:postcode":"35140",
    "sg:province":"Bartin",
    "wof:name":"Kozcagiz Gencligi Kultur Ve Dayanisma Dern.",
    "wof:placetype":"venue"
},
  "geometry": {"coordinates":[32.351776123,41.6294212341],"type":"Point"}
}