{
  "type": "Feature",
  "properties": {
    "addr:full":"Yildirim Mah.zafer Cad. No:26 Bayrampasa Etiler Istanbul 07010",
    "addr:housenumber":"26",
    "addr:postcode":"07010",
    "addr:street":"Mah.Zafer Cad. No",
    "iso:country":"TR",
    "sg:address":"Yildirim Mah.zafer Cad. No:26 Bayrampasa",
    "sg:city":"Etiler",
    "sg:classifiers":[
        {
            "category":"Manufacturing",
            "subcategory":"Wood Products",
            "type":"Manufacturing & Wholesale Goods"
        }
    ],
    "sg:phone":"+90 212 618 0378",
    "sg:postcode":"07010",
    "sg:province":"Istanbul",
    "sg:tags":[
        "forest"
    ],
    "wof:name":"Akcam Orman Urunleri San. Ltd.sti.",
    "wof:placetype":"venue"
},
  "geometry": {"coordinates":[28.8993873596,41.0648880005],"type":"Point"}
}