{
  "type": "Feature",
  "properties": {
    "addr:full":"Atat?k Cad. No:328/a Alsancak Izmir 01365",
    "addr:housenumber":"328 / a",
    "addr:postcode":"01365",
    "addr:street":"K Cad. No",
    "iso:country":"TR",
    "sg:address":"Atat?k Cad. No:328/a",
    "sg:city":"Alsancak",
    "sg:classifiers":[
        {
            "category":"Recreation",
            "subcategory":"Boat Charter",
            "type":"Entertainment"
        }
    ],
    "sg:phone":"+90 23242154564",
    "sg:postcode":"01365",
    "sg:province":"Izmir",
    "sg:tags":[
        "yachting"
    ],
    "wof:name":"Kasmir Yachting",
    "wof:placetype":"venue"
},
  "geometry": {"coordinates":[27.1296863556,38.4186973572],"type":"Point"}
}