{
  "type": "Feature",
  "properties": {
    "addr:full":"E.5 Karayolu ?eri Vakiflar K?? ?orlu Alsancak Tekirdag 01365",
    "addr:postcode":"01365",
    "addr:street":"Karayolu;Tekirdag",
    "iso:country":"TR",
    "sg:address":"E.5 Karayolu ?eri Vakiflar K?? ?orlu",
    "sg:city":"Alsancak",
    "sg:classifiers":[
        {
            "category":"Wholesale",
            "subcategory":"Petroleum",
            "type":"Manufacturing & Wholesale Goods"
        }
    ],
    "sg:phone":"+90 282 672 2238",
    "sg:postcode":"01365",
    "sg:province":"Tekirdag",
    "wof:name":"?avusogullari Hafriyat Petrol.a.s",
    "wof:placetype":"venue"
},
  "geometry": {"coordinates":[27.5144004822,40.9791984558],"type":"Point"}
}