{
  "type": "Feature",
  "properties": {
    "addr:full":"Istiklal Caddesi No:44 ?rg?p Nevsehir",
    "addr:housenumber":"no 44 ?;? p",
    "addr:street":"Istiklal Caddesi;Rg;Nevsehir",
    "iso:country":"TR",
    "sg:address":"Istiklal Caddesi No:44",
    "sg:city":"?rg?p",
    "sg:classifiers":[
        {
            "category":"Travel",
            "subcategory":"Travel Agent",
            "type":"Entertainment"
        }
    ],
    "sg:phone":"+90 384 341 6135",
    "sg:province":"Nevsehir",
    "sg:tags":[
        "agency",
        "tourism"
    ],
    "wof:name":"Ekstra Turizm (?rg? Sb)",
    "wof:placetype":"venue"
},
  "geometry": {"coordinates":[34.7063560486,38.6147613525],"type":"Point"}
}