{
  "type": "Feature",
  "properties": {
    "addr:full":"Ozanadolu Organize San. Sitesi 682 .sok. No:15 Ostim Ankara 06374",
    "addr:housenumber":"no 15",
    "addr:postcode":"06374",
    "addr:street":"Organize;682 Sok.;Ostim Ankara",
    "iso:country":"TR",
    "sg:address":"Ozanadolu Organize San. Sitesi 682 .sok. No:15",
    "sg:city":"Ostim",
    "sg:classifiers":[
        {
            "category":"Building & Trades",
            "subcategory":"Landscaping Services",
            "type":"Services"
        }
    ],
    "sg:phone":"+90 312 395 4379",
    "sg:postcode":"06374",
    "sg:province":"Ankara",
    "sg:tags":[
        "landscape"
    ],
    "wof:name":"Sebat Insaat Ltd.sti.",
    "wof:placetype":"venue"
},
  "geometry": {"coordinates":[32.8560333252,39.9438743591],"type":"Point"}
}