{
  "type": "Feature",
  "properties": {
    "iso:country":"TR",
    "sg:address":"Alacammescit Mah.yeniyol Tek.sok.akin Cikmazi Apt.no:7/2a Heykel",
    "sg:city":"Mecidiyek\u00f6y",
    "sg:classifiers":[
        {
            "category":"Shopping",
            "subcategory":"Computers & Home Electronics",
            "type":"Retail Goods"
        }
    ],
    "sg:phone":"+90 224 220 5699",
    "sg:province":"Bursa",
    "sg:tags":[
        "product",
        "electric-electronic"
    ],
    "wof:name":"Mar-tek Elektronik Hizm.& Saglik Cihazl.teknik Servisi",
    "wof:placetype":"venue"
},
  "geometry": {"coordinates":[29.0398807526,40.1076583862],"type":"Point"}
}