{
  "type": "Feature",
  "properties": {
    "iso:country":"TR",
    "sg:address":"Cakmakcilar Yokusu No:7/2",
    "sg:city":"Mercan",
    "sg:classifiers":[
        {
            "category":"Shopping",
            "subcategory":"Clothing, Apparel, & Fashions",
            "type":"Retail Goods"
        }
    ],
    "sg:phone":"+90 212 526 6170",
    "sg:postcode":"12600",
    "sg:province":"Istanbul",
    "sg:tags":[
        "men",
        "wear"
    ],
    "wof:name":"Fikir Gomlek Imalat San.tic.",
    "wof:placetype":"venue"
},
  "geometry": {"coordinates":[28.9700031281,41.0113067627],"type":"Point"}
}