{
  "type": "Feature",
  "properties": {
    "iso:country":"TR",
    "sg:address":"Cumhuriyet Mah. 986 Sok.no:10",
    "sg:city":"Cigli",
    "sg:classifiers":[
        {
            "category":"Wholesale",
            "subcategory":"Machinery & Supplies",
            "type":"Manufacturing & Wholesale Goods"
        }
    ],
    "sg:phone":"+90 322 351 5767",
    "sg:postcode":"46000",
    "sg:province":"Adana",
    "sg:tags":[
        "agricultural"
    ],
    "wof:name":"S.birlik San.koll",
    "wof:placetype":"venue"
},
  "geometry": {"coordinates":[35.3637695312,36.9830131531],"type":"Point"}
}