{
  "type": "Feature",
  "properties": {
    "iso:country":"TR",
    "sg:address":"Karatay Sanayi Freze Sok. No:58",
    "sg:city":"Merkez",
    "sg:orig_category":"Food Machinies",
    "sg:phone":"+90 332 238 2856",
    "sg:postcode":"68100",
    "sg:province":"Konya",
    "wof:name":"?z ??ler Vals Sanayi",
    "wof:placetype":"venue"
},
  "geometry": {"coordinates":[32.4990272522,37.8715362549],"type":"Point"}
}