{
  "type": "Feature",
  "properties": {
    "addr:full":"Evren Mh. G?bahar C. No.60 G?esli Istanbul",
    "addr:housenumber":"?;?",
    "addr:street":"Mh. G;Bahar C. No.60 G",
    "iso:country":"TR",
    "sg:address":"Evren Mh. G?bahar C. No.60",
    "sg:city":"G?esli",
    "sg:classifiers":[
        {
            "category":"Food & Beverages",
            "subcategory":"Groceries & Convenience Stores",
            "type":"Retail Goods"
        }
    ],
    "sg:phone":"+90 212 656 6280",
    "sg:province":"Istanbul",
    "sg:tags":[
        "drink-",
        "soft"
    ],
    "wof:name":"Tamek Gida San. A.s.",
    "wof:placetype":"venue"
},
  "geometry": {"coordinates":[28.811155,41.036751],"type":"Point"}
}