{
  "type": "Feature",
  "properties": {
    "addr:full":"Atat?k Bulvari No:211/27 Kavaklidere B???kmece Ankara",
    "addr:housenumber":"no;/ 27;b ? ? ?",
    "addr:street":"K Bulvari;Kmece",
    "iso:country":"TR",
    "sg:address":"Atat?k Bulvari No:211/27 Kavaklidere",
    "sg:city":"B???kmece",
    "sg:classifiers":[
        {
            "category":"Banks & Credit Unions",
            "subcategory":"Investment Brokerage",
            "type":"Services"
        }
    ],
    "sg:phone":"+90 312 467 1244",
    "sg:province":"Ankara",
    "sg:tags":[
        "-",
        "export",
        "import"
    ],
    "wof:name":"Pant?rk Tic. Ltd. Sti.",
    "wof:placetype":"venue"
},
  "geometry": {"coordinates":[32.8576202393,39.9128990173],"type":"Point"}
}