{
  "type": "Feature",
  "properties": {
    "addr:full":"Fatih San.sit.1824 Blok 117 Sok.no:32-33 Turgutlu Sel?uklu Manisa",
    "addr:housenumber":"blok 117;32-33",
    "addr:postcode":"? uklu",
    "addr:street":"Sok.No",
    "iso:country":"TR",
    "sg:address":"Fatih San.sit.1824 Blok 117 Sok.no:32-33 Turgutlu",
    "sg:city":"Sel?uklu",
    "sg:classifiers":[
        {
            "category":"Wholesale",
            "subcategory":"Auto Parts",
            "type":"Manufacturing & Wholesale Goods"
        }
    ],
    "sg:phone":"+90 236 313 4982",
    "sg:province":"Manisa",
    "sg:tags":[
        "spare"
    ],
    "wof:name":"Esen Otomotiv",
    "wof:placetype":"venue"
},
  "geometry": {"coordinates":[27.7029800415,38.4922485352],"type":"Point"}
}