{
  "type": "Feature",
  "properties": {
    "addr:full":"Mithatpasa Cd. No:65/a Mersin Izmir 52750",
    "addr:housenumber":"no 65 / a",
    "addr:postcode":"52750",
    "addr:street":"Mithatpasa Cd.",
    "iso:country":"TR",
    "sg:address":"Mithatpasa Cd. No:65/a",
    "sg:city":"Mersin",
    "sg:classifiers":[
        {
            "category":"Manufacturing",
            "subcategory":"Metals",
            "type":"Manufacturing & Wholesale Goods"
        }
    ],
    "sg:phone":"+90 232 227 3667",
    "sg:postcode":"52750",
    "sg:province":"Izmir",
    "sg:tags":[
        "iron-steel",
        "peoducts"
    ],
    "wof:name":"Erdil Demir Tic. Ltd. Sti.",
    "wof:placetype":"venue"
},
  "geometry": {"coordinates":[27.121887207,38.411945343],"type":"Point"}
}