{
  "type": "Feature",
  "properties": {
    "addr:full":"Bahariye Cadde No:5/2 - Kadik? Merkez Istanbul",
    "addr:housenumber":"no 5 / 2 kadik ?",
    "addr:street":"Bahariye Cadde",
    "iso:country":"TR",
    "sg:address":"Bahariye Cadde No:5/2 - Kadik?",
    "sg:city":"Merkez",
    "sg:classifiers":[
        {
            "category":"Health Services",
            "subcategory":"Medical Lab",
            "type":"Services"
        }
    ],
    "sg:phone":"+90 216 349 8607",
    "sg:province":"Istanbul",
    "wof:name":"Dr.yavuz G?en Tibbi Tahliller Laboratuvari",
    "wof:placetype":"venue"
},
  "geometry": {"coordinates":[28.8699531555,41.038860321],"type":"Point"}
}