{
  "type": "Feature",
  "properties": {
    "addr:full":"Sanayi Bolgesi Konya Yolu Uzeri Aksehir Ikitelli Konya 34670",
    "addr:housenumber":"uzeri",
    "addr:postcode":"34670",
    "addr:street":"Konya Yolu",
    "iso:country":"TR",
    "sg:address":"Sanayi Bolgesi Konya Yolu Uzeri Aksehir",
    "sg:city":"Ikitelli",
    "sg:classifiers":[
        {
            "category":"Wholesale",
            "subcategory":"Auto Parts",
            "type":"Manufacturing & Wholesale Goods"
        }
    ],
    "sg:phone":"+90 332 813 8396",
    "sg:postcode":"34670",
    "sg:province":"Konya",
    "sg:tags":[
        "spare"
    ],
    "wof:name":"Akkomsan San. Ve Tic.",
    "wof:placetype":"venue"
},
  "geometry": {"coordinates":[33.0667152405,39.2111282349],"type":"Point"}
}