{
  "type": "Feature",
  "properties": {
    "addr:full":"M?errih Ali Cd. No:66 Hask? Nazilli Istanbul 65600",
    "addr:housenumber":"no 66;?",
    "addr:postcode":"65600",
    "addr:street":"Ali Cd.;Hask",
    "iso:country":"TR",
    "sg:address":"M?errih Ali Cd. No:66 Hask?",
    "sg:city":"Nazilli",
    "sg:classifiers":[
        {
            "category":"Home & Garden",
            "subcategory":"Household Appliances",
            "type":"Retail Goods"
        }
    ],
    "sg:phone":"+90 212 250 1250",
    "sg:postcode":"65600",
    "sg:province":"Istanbul",
    "sg:tags":[
        "utensil",
        "electrical"
    ],
    "wof:name":"Gamsiz Tic. A.s.",
    "wof:placetype":"venue"
},
  "geometry": {"coordinates":[28.9861831665,41.0408554077],"type":"Point"}
}