{
  "type": "Feature",
  "properties": {
    "iso:country":"TR",
    "sg:address":"Camikebir Mah.mektep Cad.11.sok. No:11",
    "sg:city":"Seferhisari",
    "sg:classifiers":[
        {
            "category":"Utilities",
            "subcategory":"Natural Gas",
            "type":"Services"
        }
    ],
    "sg:phone":"+90 232743246",
    "sg:province":"Izmir",
    "sg:tags":[
        "tank-heating-natural"
    ],
    "wof:name":"Erci Emlak Turizm Tic.ltd. Sti.",
    "wof:placetype":"venue"
},
  "geometry": {"coordinates":[27.1423015594,38.4251480103],"type":"Point"}
}