{
  "type": "Feature",
  "properties": {
    "iso:country":"TR",
    "sg:address":"Toros Cad.feriha Yalcin Apt.",
    "sg:city":"Sisli",
    "sg:classifiers":[
        {
            "category":"Home & Garden",
            "subcategory":"Kitchen Supply",
            "type":"Retail Goods"
        }
    ],
    "sg:phone":"+90 322 457 5216",
    "sg:postcode":"34400",
    "sg:province":"Adana",
    "sg:tags":[
        "wardrobe"
    ],
    "wof:name":"Sipal Mutfak Banyo",
    "wof:placetype":"venue"
},
  "geometry": {"coordinates":[35.3137359619,37.0007171631],"type":"Point"}
}