{
  "type": "Feature",
  "properties": {
    "addr:full":"Istanbul Nazilli Istanbul 65600",
    "addr:postcode":"65600",
    "iso:country":"TR",
    "sg:address":"Istanbul",
    "sg:city":"Nazilli",
    "sg:classifiers":[
        {
            "category":"Home & Garden",
            "subcategory":"Household Appliances",
            "type":"Retail Goods"
        }
    ],
    "sg:phone":"+90 2165218837329",
    "sg:postcode":"65600",
    "sg:province":"Istanbul",
    "sg:tags":[
        "utensil",
        "electrical"
    ],
    "wof:name":"?ztekin Electronics",
    "wof:placetype":"venue"
},
  "geometry": {"coordinates":[29.1482200623,40.9827156067],"type":"Point"}
}