{
  "type": "Feature",
  "properties": {
    "addr:full":"Yavuz Selim Cad.no:2 ?amdibi Osmanbey Izmir 63000",
    "addr:housenumber":"2 ?",
    "addr:postcode":"63000",
    "addr:street":"Amdibi Osmanbey",
    "iso:country":"TR",
    "sg:address":"Yavuz Selim Cad.no:2 ?amdibi",
    "sg:city":"Osmanbey",
    "sg:classifiers":[
        {
            "category":"Sports & Exercise",
            "subcategory":"Ski Slope",
            "type":"Entertainment"
        }
    ],
    "sg:phone":"+90 232 435 0700",
    "sg:postcode":"63000",
    "sg:province":"Izmir",
    "sg:tags":[
        "wear"
    ],
    "wof:name":"Tac Tekstil A.s",
    "wof:placetype":"venue"
},
  "geometry": {"coordinates":[27.129686,38.418697],"type":"Point"}
}