{
  "type": "Feature",
  "properties": {
    "iso:country":"TR",
    "sg:address":"Atat?k Cad.no:204",
    "sg:city":"Yazihan",
    "sg:classifiers":[
        {
            "category":"Manufacturing",
            "subcategory":"Food",
            "type":"Manufacturing & Wholesale Goods"
        }
    ],
    "sg:phone":"+90 346 221 4548",
    "sg:postcode":"44350",
    "sg:province":"Sivas",
    "sg:tags":[
        "wholesaler"
    ],
    "wof:name":"Malatya Gida Pazari",
    "wof:placetype":"venue"
},
  "geometry": {"coordinates":[37.01720047,39.751499176],"type":"Point"}
}