{
  "type": "Feature",
  "properties": {
    "addr:full":"Tarsus Karayolu 16 Km.cam San. Kar. Mersin I?el 52750",
    "addr:housenumber":"16",
    "addr:postcode":"? el 52750",
    "addr:street":"Karayolu;San. Kar.",
    "iso:country":"TR",
    "sg:address":"Tarsus Karayolu 16 Km.cam San. Kar.",
    "sg:city":"Mersin",
    "sg:classifiers":[
        {
            "category":"Professional",
            "subcategory":"Business Services",
            "type":"Services"
        }
    ],
    "sg:phone":"+90 324 452 2520",
    "sg:postcode":"52750",
    "sg:province":"I?el",
    "sg:tags":[
        "food",
        "product",
        "exporter",
        "aricultural"
    ],
    "wof:name":"Yilpa Tic.ltd.",
    "wof:placetype":"venue"
},
  "geometry": {"coordinates":[34.900100708,36.9201011658],"type":"Point"}
}