{
  "type": "Feature",
  "properties": {
    "addr:full":"Oto Plaza Horozlu Han Mah. Senyurt Sok.no:22 Gaziosmanpasa Konya 34100",
    "addr:housenumber":"22",
    "addr:postcode":"34100",
    "addr:street":"Mah. Senyurt Sok.No",
    "iso:country":"TR",
    "sg:address":"Oto Plaza Horozlu Han Mah. Senyurt Sok.no:22",
    "sg:city":"Gaziosmanpasa",
    "sg:classifiers":[
        {
            "category":"Autos & Motor Vehicles",
            "subcategory":"Auto Supplies",
            "type":"Retail Goods"
        }
    ],
    "sg:phone":"+90 332 249 6670",
    "sg:postcode":"34100",
    "sg:province":"Konya",
    "sg:tags":[
        "accessory"
    ],
    "wof:name":"Tetik Pazarlama Ve Tanitim A.s.",
    "wof:placetype":"venue"
},
  "geometry": {"coordinates":[33.0667152405,39.2111282349],"type":"Point"}
}