{
  "type": "Feature",
  "properties": {
    "addr:full":"Yesilyurt Sipahioglu Cad. No:12/5 Etlik Istanbul 06010",
    "addr:housenumber":"12 / 5",
    "addr:postcode":"06010",
    "addr:street":"Sipahioglu Cad. No",
    "iso:country":"TR",
    "sg:address":"Yesilyurt Sipahioglu Cad. No:12/5",
    "sg:city":"Etlik",
    "sg:classifiers":[
        {
            "category":"Home & Garden",
            "subcategory":"Household Appliances",
            "type":"Retail Goods"
        }
    ],
    "sg:phone":"+90 212 662 6021",
    "sg:postcode":"06010",
    "sg:province":"Istanbul",
    "sg:tags":[
        "conditioner",
        "air"
    ],
    "wof:name":"Alaybey Dis Tic.ltd.",
    "wof:placetype":"venue"
},
  "geometry": {"coordinates":[28.8378582001,40.9643707275],"type":"Point"}
}