{
  "type": "Feature",
  "properties": {
    "iso:country":"TR",
    "sg:address":"Rami Kisla Cad. G?dogar Is Mrk. No:84/125 34140 Top?lar",
    "sg:city":"Kartal",
    "sg:classifiers":[
        {
            "category":"Manufacturing",
            "subcategory":"Tools & Machinery",
            "type":"Manufacturing & Wholesale Goods"
        }
    ],
    "sg:phone":"+90 212 544 6302",
    "sg:postcode":"46000",
    "sg:province":"Istanbul",
    "sg:tags":[
        "machine",
        "industry"
    ],
    "wof:name":"Tet Makina Metal Sanayi",
    "wof:placetype":"venue"
},
  "geometry": {"coordinates":[28.975925,41.012379],"type":"Point"}
}