{
  "type": "Feature",
  "properties": {
    "addr:full":"Kisla Cad. Pasmakci San. Sit. No.102/a Rami Bayrampasa Istanbul 34160",
    "addr:housenumber":"no.102 / a",
    "addr:postcode":"34160",
    "addr:street":"Kisla Cad. Pasmakci San. Sit.;Rami Bayrampasa",
    "iso:country":"TR",
    "sg:address":"Kisla Cad. Pasmakci San. Sit. No.102/a Rami",
    "sg:city":"Bayrampasa",
    "sg:classifiers":[
        {
            "category":"Manufacturing",
            "subcategory":"Tools & Machinery",
            "type":"Manufacturing & Wholesale Goods"
        }
    ],
    "sg:phone":"+90 212544188",
    "sg:postcode":"34160",
    "sg:province":"Istanbul",
    "sg:tags":[
        "machine",
        "industry"
    ],
    "wof:name":"Mekanik Kalip",
    "wof:placetype":"venue"
},
  "geometry": {"coordinates":[28.869146347,41.0144004822],"type":"Point"}
}