{
  "type": "Feature",
  "properties": {
    "addr:full":"Nispetiye Cd. No:45 Etiler Istanbul 07010",
    "addr:housenumber":"no 45",
    "addr:postcode":"07010",
    "addr:street":"Nispetiye Cd.",
    "iso:country":"TR",
    "sg:address":"Nispetiye Cd. No:45",
    "sg:city":"Etiler",
    "sg:classifiers":[
        {
            "category":"Shopping",
            "subcategory":"Florist",
            "type":"Retail Goods"
        }
    ],
    "sg:phone":"+90 212 265 2925",
    "sg:postcode":"07010",
    "sg:province":"Istanbul",
    "sg:tags":[
        "flower"
    ],
    "wof:name":"?zlem ?i?ek",
    "wof:placetype":"venue"
},
  "geometry": {"coordinates":[29.0490837097,41.0862617493],"type":"Point"}
}