{
  "type": "Feature",
  "properties": {
    "iso:country":"TR",
    "sg:address":"Istiklal Cd.81 Sk.akkizoglu Ishani K:4/16",
    "sg:city":"Gevye",
    "sg:classifiers":[
        {
            "category":"Food & Beverages",
            "subcategory":"Fruits & Vegetables",
            "type":"Retail Goods"
        }
    ],
    "sg:phone":"+90 324 133 7230",
    "sg:postcode":"54700",
    "sg:province":"I?el",
    "sg:tags":[
        "fresh"
    ],
    "wof:name":"Oz Gida Ltd.sti",
    "wof:placetype":"venue"
},
  "geometry": {"coordinates":[30.2998008728,40.5089988708],"type":"Point"}
}