{
  "type": "Feature",
  "properties": {
    "iso:country":"TR",
    "sg:address":"Seyhan Mah. 4 Sok. No:142",
    "sg:city":"Y?egir",
    "sg:classifiers":[
        {
            "category":"Farming",
            "subcategory":"Farm",
            "type":"Manufacturing & Wholesale Goods"
        }
    ],
    "sg:phone":"+90 322 311 2566",
    "sg:province":"Adana",
    "sg:tags":[
        "agricultural",
        "product"
    ],
    "wof:name":"Karaman Gida San ??leri Tic.ltd.sti.",
    "wof:placetype":"venue"
},
  "geometry": {"coordinates":[35.3316078186,36.9624557495],"type":"Point"}
}