{
  "type": "Feature",
  "properties": {
    "iso:country":"TR",
    "sg:address":"Istanbul Yolu 13.km .gersan San.sitesi 656. Sok. No:34",
    "sg:city":"Yenisehir",
    "sg:classifiers":[
        {
            "category":"Utilities",
            "subcategory":"Electric",
            "type":"Services"
        }
    ],
    "sg:phone":"+90 312 256 3906",
    "sg:postcode":"31750",
    "sg:province":"Ankara",
    "sg:tags":[
        "energy",
        "solar"
    ],
    "wof:name":"G?n Isi San. Tic. Ltd.",
    "wof:placetype":"venue"
},
  "geometry": {"coordinates":[32.856033,39.943874],"type":"Point"}
}