{
  "type": "Feature",
  "properties": {
    "addr:full":"Istanbul Cd. Muhasebeci Sk. No:1/15 Bakirk? Iskenderun Istanbul 31200",
    "addr:housenumber":"15;?",
    "addr:postcode":"31200",
    "addr:street":"Cd. Muhasebeci Sk. No 1 /",
    "iso:country":"TR",
    "sg:address":"Istanbul Cd. Muhasebeci Sk. No:1/15 Bakirk?",
    "sg:city":"Iskenderun",
    "sg:classifiers":[
        {
            "category":"Mining & Drilling",
            "type":"Manufacturing & Wholesale Goods"
        }
    ],
    "sg:phone":"+90 212 570 6176",
    "sg:postcode":"31200",
    "sg:province":"Istanbul",
    "sg:tags":[
        "industry",
        "mine"
    ],
    "wof:name":"?aglar Madencilik San. Tic. Ltd. Sti.",
    "wof:placetype":"venue"
},
  "geometry": {"coordinates":[28.9759254456,41.0123786926],"type":"Point"}
}