{
  "type": "Feature",
  "properties": {
    "addr:full":"Dokumculer Sit. 3.sok. No:25 Sincan Iskitler Ankara 06070",
    "addr:housenumber":"no 25",
    "addr:postcode":"06070",
    "addr:street":"Sincan Iskitler",
    "iso:country":"TR",
    "sg:address":"Dokumculer Sit. 3.sok. No:25 Sincan",
    "sg:city":"Iskitler",
    "sg:classifiers":[
        {
            "category":"Utilities",
            "subcategory":"Fuel Oil & Lpg",
            "type":"Services"
        }
    ],
    "sg:phone":"+90 312 267 2652",
    "sg:postcode":"06070",
    "sg:province":"Ankara",
    "sg:tags":[
        "gas",
        "system"
    ],
    "wof:name":"Udt Elektronik Makina San. Ic Ve Dis Ticaret",
    "wof:placetype":"venue"
},
  "geometry": {"coordinates":[32.5745506287,39.9594116211],"type":"Point"}
}