{
  "type": "Feature",
  "properties": {
    "iso:country":"TR",
    "sg:address":"K. Karabekir Cd. No:7/36 Iskitler",
    "sg:city":"B.?ekmece",
    "sg:classifiers":[
        {
            "category":"Farming",
            "subcategory":"Fish & Marine Products",
            "type":"Manufacturing & Wholesale Goods"
        }
    ],
    "sg:phone":"+90 312 342 0796",
    "sg:province":"Ankara",
    "sg:tags":[
        "automotive"
    ],
    "wof:name":"G?nhan Otomotiv Tic. A.s.",
    "wof:placetype":"venue"
},
  "geometry": {"coordinates":[36.3196144104,41.2798347473],"type":"Point"}
}