{
  "type": "Feature",
  "properties": {
    "addr:full":"Perpa Ticaret Merkezi B Blok 9. Kat No: 1514 Okmeydani Istanbul 80270",
    "addr:housenumber":"9 kat no 1514",
    "addr:postcode":"80270",
    "addr:street":"Okmeydani Istanbul",
    "iso:country":"TR",
    "sg:address":"Perpa Ticaret Merkezi B Blok 9. Kat No: 1514",
    "sg:city":"Okmeydani",
    "sg:classifiers":[
        {
            "category":"Sports & Exercise",
            "subcategory":"Tennis Court",
            "type":"Entertainment"
        }
    ],
    "sg:phone":"+90 212222555453",
    "sg:postcode":"80270",
    "sg:province":"Istanbul",
    "sg:tags":[
        "equipment",
        "material"
    ],
    "wof:name":"Spor ?it",
    "wof:placetype":"venue"
},
  "geometry": {"coordinates":[28.975925,41.012379],"type":"Point"}
}