{
  "type": "Feature",
  "properties": {
    "addr:full":"Organize San. Bolgesi 7.cad. Bayrampasa Eskisehir 36100",
    "addr:postcode":"36100",
    "addr:street":"Organize;Eskisehir",
    "iso:country":"TR",
    "sg:address":"Organize San. Bolgesi 7.cad.",
    "sg:city":"Bayrampasa",
    "sg:classifiers":[
        {
            "category":"Shopping",
            "subcategory":"Clothing, Apparel, & Fashions",
            "type":"Retail Goods"
        }
    ],
    "sg:phone":"+90 222 236 0909",
    "sg:postcode":"36100",
    "sg:province":"Eskisehir",
    "sg:tags":[
        "ready",
        "wear"
    ],
    "wof:name":"Esteks Tekstil Urunleri San. Ve Tic. A.s.",
    "wof:placetype":"venue"
},
  "geometry": {"coordinates":[30.5175457001,39.7700805664],"type":"Point"}
}