{
  "type": "Feature",
  "properties": {
    "addr:full":"Ugur Mumcu Cd. No:64/3 G.osmanpasa Ankara",
    "addr:housenumber":"no 64 / 3",
    "addr:street":"Mumcu Cd.;G.Osmanpasa",
    "iso:country":"TR",
    "sg:address":"Ugur Mumcu Cd. No:64/3",
    "sg:city":"G.osmanpasa",
    "sg:classifiers":[
        {
            "category":"Professional",
            "subcategory":"Engineering",
            "type":"Services"
        }
    ],
    "sg:phone":"+90 312 447 2702",
    "sg:province":"Ankara",
    "sg:tags":[
        "architect"
    ],
    "wof:name":"Bildem Bilgisayar Destek. M?hendis. Ltd. Sti.",
    "wof:placetype":"venue"
},
  "geometry": {"coordinates":[32.8604812622,39.9429283142],"type":"Point"}
}