{
  "type": "Feature",
  "properties": {
    "iso:country":"TR",
    "sg:address":"Cum. Cad.354 Sk.no:26",
    "sg:city":"Kavaklidere",
    "sg:classifiers":[
        {
            "category":"Home & Garden",
            "subcategory":"Home Furnishings",
            "type":"Retail Goods"
        }
    ],
    "sg:phone":"+90 258 261 9825",
    "sg:postcode":"35040",
    "sg:province":"Denizli",
    "sg:tags":[
        "textile"
    ],
    "wof:name":"Ufuk Kiraz Tekstil Ltd.sti.",
    "wof:placetype":"venue"
},
  "geometry": {"coordinates":[29.0788803101,37.7851867676],"type":"Point"}
}