{
  "type": "Feature",
  "properties": {
    "addr:full":"Yildizposta Cad. No.26 Yesil Apt. B Blok K.13 D.41 Gayrettepe \u00c7ankaya Istanbul",
    "addr:street":"Yildizposta Cad. No.26 Yesil Apt. B Blok K.13 D.41",
    "iso:country":"TR",
    "sg:address":"Yildizposta Cad. No.26 Yesil Apt. B Blok K.13 D.41 Gayrettepe",
    "sg:city":"\u00c7ankaya",
    "sg:classifiers":[
        {
            "category":"Organizations",
            "subcategory":"Professional Association",
            "type":"Services"
        }
    ],
    "sg:phone":"+90 212 216 0890",
    "sg:province":"Istanbul",
    "sg:tags":[
        "fair"
    ],
    "wof:name":"D?nya Fuar Yapim Ltd.sti.",
    "wof:placetype":"venue"
},
  "geometry": {"coordinates":[29.0063343048,41.0620994568],"type":"Point"}
}