{
  "type": "Feature",
  "properties": {
    "iso:country":"TR",
    "sg:address":"31/a Sk. No:37 Ostim",
    "sg:city":"Yenisehir",
    "sg:classifiers":[
        {
            "category":"Wholesale",
            "subcategory":"Machinery & Supplies",
            "type":"Manufacturing & Wholesale Goods"
        }
    ],
    "sg:phone":"+90 312 354 3161",
    "sg:postcode":"35110",
    "sg:province":"Ankara",
    "sg:tags":[
        "bearing",
        "ball"
    ],
    "wof:name":"G?ner Mak. Red?kt?r San.",
    "wof:placetype":"venue"
},
  "geometry": {"coordinates":[32.749584,39.974556],"type":"Point"}
}