{
  "type": "Feature",
  "properties": {
    "addr:full":"Atat?k Cd. Aydin Pasaji No:133 Bandirma Balikesir 10200",
    "addr:housenumber":"133",
    "addr:postcode":"10200",
    "addr:street":"K Cd. Aydin Pasaji No",
    "iso:country":"TR",
    "sg:address":"Atat?k Cd. Aydin Pasaji No:133",
    "sg:city":"Bandirma",
    "sg:classifiers":[
        {
            "category":"Manufacturing",
            "subcategory":"Building Materials",
            "type":"Manufacturing & Wholesale Goods"
        }
    ],
    "sg:phone":"+90 266 718 1564",
    "sg:postcode":"10200",
    "sg:province":"Balikesir",
    "sg:tags":[
        "lifts-elevators"
    ],
    "wof:name":"Local Asans?rleri",
    "wof:placetype":"venue"
},
  "geometry": {"coordinates":[27.8833007812,39.6520996094],"type":"Point"}
}