{
  "type": "Feature",
  "properties": {
    "iso:country":"TR",
    "sg:address":"Davutpasa Cd. G?en San. Sit. C Blok No:232 Topkapi",
    "sg:city":"?skudar",
    "sg:classifiers":[
        {
            "category":"Freight",
            "type":"Transportation"
        }
    ],
    "sg:phone":"+90 212 501 4701",
    "sg:postcode":"34000",
    "sg:province":"Istanbul",
    "sg:tags":[
        "packing",
        "industry"
    ],
    "wof:name":"Mikro Ofset Ambalaj San. Tic. Ltd. Sti.",
    "wof:placetype":"venue"
},
  "geometry": {"coordinates":[28.9759254456,41.0123786926],"type":"Point"}
}