{
  "type": "Feature",
  "properties": {
    "addr:full":"Ahmet Kutsi Tecer Istanbul 34010",
    "addr:postcode":"34010",
    "iso:country":"TR",
    "sg:address":"Ahmet Kutsi Tecer",
    "sg:city":"Istanbul",
    "sg:classifiers":[
        {
            "category":"Banks & Credit Unions",
            "subcategory":"Bank",
            "type":"Services"
        }
    ],
    "sg:phone":"+90 212 643 3556",
    "sg:province":"34010",
    "wof:name":"Sekerbank T?k, Anonim Sirketi",
    "wof:placetype":"venue"
},
  "geometry": {"coordinates":[28.888187,41.006596],"type":"Point"}
}