{
  "type": "Feature",
  "properties": {
    "addr:full":"A.s. Topkapi Tic. Merk.-2 No:160 Topkapi Istanbul 24620",
    "addr:housenumber":"no",
    "addr:postcode":"24620",
    "iso:country":"TR",
    "sg:address":"A.s. Topkapi Tic. Merk.-2 No:160",
    "sg:city":"Topkapi",
    "sg:classifiers":[
        {
            "category":"Retail",
            "subcategory":"Driving School",
            "type":"Services"
        }
    ],
    "sg:phone":"+90 212 612 8603",
    "sg:postcode":"24620",
    "sg:province":"Istanbul",
    "sg:tags":[
        "cargo"
    ],
    "wof:name":"Star Kargo Serv.",
    "wof:placetype":"venue"
},
  "geometry": {"coordinates":[28.9861831665,41.0408554077],"type":"Point"}
}