{
  "type": "Feature",
  "properties": {
    "iso:country":"TR",
    "sg:address":"Istanbul Cad Serefsirin Sok.?esmeli ?arsi No:35",
    "sg:city":"58010",
    "sg:classifiers":[
        {
            "category":"Wholesale",
            "subcategory":"Medical Equipment & Supplies",
            "type":"Manufacturing & Wholesale Goods"
        }
    ],
    "sg:phone":"+90 332 353 1392",
    "sg:province":"Konya",
    "sg:tags":[
        "material"
    ],
    "wof:name":"Allerkan Medikal Elektronik",
    "wof:placetype":"venue"
},
  "geometry": {"coordinates":[33.0667152405,39.2111282349],"type":"Point"}
}