{
  "type": "Feature",
  "properties": {
    "addr:full":"Ulubatli Hasan Blv.sinirtas Is Merkezi.46/25 Osmangazi Bursa 16000",
    "addr:housenumber":"merkezi.46 / 25",
    "addr:postcode":"16000",
    "addr:street":"Ulubatli Hasan Blv.Sinirtas Is;Osmangazi Bursa",
    "iso:country":"TR",
    "sg:address":"Ulubatli Hasan Blv.sinirtas Is Merkezi.46/25",
    "sg:city":"Osmangazi",
    "sg:classifiers":[
        {
            "category":"Farming",
            "subcategory":"Fish & Marine Products",
            "type":"Manufacturing & Wholesale Goods"
        }
    ],
    "sg:phone":"+90 224 256 9910",
    "sg:postcode":"16000",
    "sg:province":"Bursa",
    "sg:tags":[
        "automotive"
    ],
    "wof:name":"Apeks Metal/ ?el Boru",
    "wof:placetype":"venue"
},
  "geometry": {"coordinates":[29.0580043793,40.1947555542],"type":"Point"}
}