{
  "type": "Feature",
  "properties": {
    "addr:full":"Halaskargazi Cad. 184/5 Pangalti Istanbul 34373",
    "addr:housenumber":"184 / 5",
    "addr:postcode":"34373",
    "addr:street":"Halaskargazi Cad.",
    "iso:country":"TR",
    "sg:address":"Halaskargazi Cad. 184/5",
    "sg:city":"Pangalti",
    "sg:orig_category":"Tricot",
    "sg:phone":"+90 212 241 4299",
    "sg:postcode":"34373",
    "sg:province":"Istanbul",
    "wof:name":"Atalay Tekstil Ve Tic. Ltd. Sti.",
    "wof:placetype":"venue"
},
  "geometry": {"coordinates":[28.9861831665,41.0408554077],"type":"Point"}
}