{
  "type": "Feature",
  "properties": {
    "addr:full":"Kasap Sok. Kilic Apt.no:13 D:3 Esentepe Istanbul 01930",
    "addr:housenumber":"13 d 3",
    "addr:postcode":"01930",
    "addr:street":"Kasap Sok. Kilic Apt.No",
    "iso:country":"TR",
    "sg:address":"Kasap Sok. Kilic Apt.no:13 D:3",
    "sg:city":"Esentepe",
    "sg:classifiers":[
        {
            "category":"Professional",
            "subcategory":"Employment Agencies",
            "type":"Services"
        }
    ],
    "sg:phone":"+90 212 212 9204",
    "sg:postcode":"01930",
    "sg:province":"Istanbul",
    "sg:tags":[
        "model",
        "fashion"
    ],
    "wof:name":"Planet Reklam Organizasyon Ve Mankenlik Ajansi",
    "wof:placetype":"venue"
},
  "geometry": {"coordinates":[29.0112018585,41.0170822144],"type":"Point"}
}