{
  "type": "Feature",
  "properties": {
    "addr:full":"Pembe Ay Sk. No:36 Incirli 38070 Istanbul",
    "addr:postcode":"38070",
    "addr:street":"Incirli",
    "iso:country":"TR",
    "sg:address":"Pembe Ay Sk. No:36 Incirli",
    "sg:city":"38070",
    "sg:orig_category":"Aluminium Carpentary",
    "sg:phone":"+90 212 571 8471",
    "sg:province":"Istanbul",
    "wof:name":"Golge Pancur San. Tic.",
    "wof:placetype":"venue"
},
  "geometry": {"coordinates":[28.8719940186,40.9967193604],"type":"Point"}
}