{
  "type": "Feature",
  "properties": {
    "addr:full":"C.emec Bulvari 74.sok. No:4/4 A.ovecler A.?ve?ler Ankara 06460",
    "addr:housenumber":"74.sok no 4 / 4",
    "addr:postcode":"?;?;06460",
    "addr:street":"C.Emec Bulvari;Ve",
    "iso:country":"TR",
    "sg:address":"C.emec Bulvari 74.sok. No:4/4 A.ovecler",
    "sg:city":"A.?ve?ler",
    "sg:classifiers":[
        {
            "category":"Manufacturing",
            "subcategory":"Chemicals & Compounds",
            "type":"Manufacturing & Wholesale Goods"
        }
    ],
    "sg:phone":"+90 312 472 7878",
    "sg:postcode":"06460",
    "sg:province":"Ankara",
    "sg:tags":[
        "medicine"
    ],
    "wof:name":"Cbc Med Medikal Ltd. Sti.",
    "wof:placetype":"venue"
},
  "geometry": {"coordinates":[32.8216018677,39.9217529297],"type":"Point"}
}