{
  "type": "Feature",
  "properties": {
    "addr:full":"Kayisdagi Cd. No.253/3 G?tepe \u00dcmraniye Istanbul 34500",
    "addr:housenumber":"no.253 / 3 g ?",
    "addr:postcode":"34500",
    "addr:street":"Kayisdagi Cd.",
    "iso:country":"TR",
    "sg:address":"Kayisdagi Cd. No.253/3 G?tepe",
    "sg:city":"\u00dcmraniye",
    "sg:classifiers":[
        {
            "category":"Home & Garden",
            "subcategory":"Kitchen Supply",
            "type":"Retail Goods"
        }
    ],
    "sg:phone":"+90 216 356 6933",
    "sg:postcode":"34500",
    "sg:province":"Istanbul",
    "sg:tags":[
        "wardrobe"
    ],
    "wof:name":"Mopa Mutfak Paz.",
    "wof:placetype":"venue"
},
  "geometry": {"coordinates":[29.1212291718,40.9706115723],"type":"Point"}
}