{
  "type": "Feature",
  "properties": {
    "addr:full":"Askeri Firin Yolu 2 Davutpasa \u00dcmraniye Istanbul 81260",
    "addr:housenumber":"2",
    "addr:postcode":"81260",
    "addr:street":"Firin Yolu",
    "iso:country":"TR",
    "sg:address":"Askeri Firin Yolu 2 Davutpasa",
    "sg:city":"\u00dcmraniye",
    "sg:classifiers":[
        {
            "category":"Farming",
            "subcategory":"Fish & Marine Products",
            "type":"Manufacturing & Wholesale Goods"
        }
    ],
    "sg:phone":"+90 212 559 0440",
    "sg:postcode":"81260",
    "sg:province":"Istanbul",
    "sg:tags":[
        "automotive"
    ],
    "wof:name":"Mercedes-benz T?rk A.s.",
    "wof:placetype":"venue"
},
  "geometry": {"coordinates":[28.9016647339,41.023601532],"type":"Point"}
}