{
  "type": "Feature",
  "properties": {
    "addr:full":"Imes C/307-1 Y.dudullu Istanbul 34776",
    "addr:housenumber":"307-1",
    "addr:postcode":"34776",
    "addr:street":"C /",
    "iso:country":"TR",
    "sg:address":"Imes C/307-1",
    "sg:city":"Y.dudullu",
    "sg:classifiers":[
        {
            "category":"Government",
            "subcategory":"Fire Station",
            "type":"Public Place"
        }
    ],
    "sg:phone":"+90 216 364 3084",
    "sg:postcode":"34776",
    "sg:province":"Istanbul",
    "sg:tags":[
        "decoration"
    ],
    "wof:name":"Sinter Teknik Ltd.sti.",
    "wof:placetype":"venue"
},
  "geometry": {"coordinates":[29.1590270996,40.9995155334],"type":"Point"}
}