{
  "type": "Feature",
  "properties": {
    "addr:full":"Cinnah Cad. No: 34/4 Karamursel Ankara 18280",
    "addr:housenumber":"34 / 4",
    "addr:postcode":"18280",
    "addr:street":"Cinnah Cad. No;Karamursel Ankara",
    "iso:country":"TR",
    "sg:address":"Cinnah Cad. No: 34/4",
    "sg:city":"Karamursel",
    "sg:classifiers":[
        {
            "category":"Insurance",
            "subcategory":"Hazard Insurance",
            "type":"Services"
        }
    ],
    "sg:phone":"+90 312 468 2800",
    "sg:postcode":"18280",
    "sg:province":"Ankara",
    "wof:name":"Mehmetcik Vakfi Sigorta Ltd.sti.",
    "wof:placetype":"venue"
},
  "geometry": {"coordinates":[32.8604812622,39.9429283142],"type":"Point"}
}