{
  "type": "Feature",
  "properties": {
    "iso:country":"TR",
    "sg:address":"A.h.tanpinar Cad. Yardimcilar Is Hani No:8/8 Fomara",
    "sg:city":"Kizilay",
    "sg:classifiers":[
        {
            "category":"Shopping",
            "subcategory":"Party Supplies",
            "type":"Retail Goods"
        }
    ],
    "sg:phone":"+90 224 224 6338",
    "sg:postcode":"23050",
    "sg:province":"Bursa",
    "sg:tags":[
        "sound",
        "light",
        "system"
    ],
    "wof:name":"As Elektronik",
    "wof:placetype":"venue"
},
  "geometry": {"coordinates":[29.0580043793,40.1947555542],"type":"Point"}
}