{
  "type": "Feature",
  "properties": {
    "iso:country":"TR",
    "sg:address":"Yakuplu Merkez Mah.bakircilar Sit.m.kurtoglu Cad.no:21",
    "sg:city":"B\u00fcy\u00fck\u00e7ekmece",
    "sg:classifiers":[
        {
            "category":"Sports & Exercise",
            "subcategory":"Ski Slope",
            "type":"Entertainment"
        }
    ],
    "sg:phone":"+90 2128762121729",
    "sg:postcode":"34520",
    "sg:province":"Istanbul",
    "sg:tags":[
        "wear"
    ],
    "wof:name":"Baykanlar Tekstil San.ve Tic.ltd.sti",
    "wof:placetype":"venue"
},
  "geometry": {"coordinates":[28.975925,41.012379],"type":"Point"}
}