{
  "type": "Feature",
  "properties": {
    "addr:full":"Aydintepe Mh. Tersane Sk. No:8/a Tuzla Iskenderun Istanbul 31200",
    "addr:housenumber":"a",
    "addr:postcode":"31200",
    "addr:street":"Aydintepe Mh. Tersane Sk. No 8 /",
    "iso:country":"TR",
    "sg:address":"Aydintepe Mh. Tersane Sk. No:8/a Tuzla",
    "sg:city":"Iskenderun",
    "sg:classifiers":[
        {
            "category":"Manufacturing",
            "subcategory":"Metals",
            "type":"Manufacturing & Wholesale Goods"
        }
    ],
    "sg:phone":"+90 216 392 3144",
    "sg:postcode":"31200",
    "sg:province":"Istanbul",
    "sg:tags":[
        "industry"
    ],
    "wof:name":"Altin ?ipa Metal San. Tic. Ltd. Sti.",
    "wof:placetype":"venue"
},
  "geometry": {"coordinates":[29.2995204926,40.8505706787],"type":"Point"}
}