{
  "type": "Feature",
  "properties": {
    "addr:full":"Kisla Cd. Top?lar Ismerk. No:88/199 Top?lar B\u00fcy\u00fck\u00e7ekmece Istanbul 34905",
    "addr:housenumber":"199",
    "addr:postcode":"?;?;34905",
    "addr:street":"Kisla Cd.;No 88 /",
    "iso:country":"TR",
    "sg:address":"Kisla Cd. Top?lar Ismerk. No:88/199 Top?lar",
    "sg:city":"B\u00fcy\u00fck\u00e7ekmece",
    "sg:classifiers":[
        {
            "category":"Building & Trades",
            "subcategory":"Construction",
            "type":"Services"
        }
    ],
    "sg:phone":"+90 212 501 4952",
    "sg:postcode":"34905",
    "sg:province":"Istanbul",
    "sg:tags":[
        "industry",
        "mold"
    ],
    "wof:name":"Hadid Mak. San. Tic. Ltd. Sti.",
    "wof:placetype":"venue"
},
  "geometry": {"coordinates":[28.9759254456,41.0123786926],"type":"Point"}
}