{
  "type": "Feature",
  "properties": {
    "iso:country":"TR",
    "sg:address":"3.sanayi Sitesi 40.cad.59.sok. No:3/5",
    "sg:city":"-k.cekmece",
    "sg:classifiers":[
        {
            "category":"Shopping",
            "subcategory":"Clothing, Apparel, & Fashions",
            "type":"Retail Goods"
        }
    ],
    "sg:phone":"+90 258 268 4760",
    "sg:province":"Denizli",
    "sg:tags":[
        "ready",
        "wear"
    ],
    "wof:name":"Hazirel Tekstil Turizm Ve Tvk. Ltd.sti.",
    "wof:placetype":"venue"
},
  "geometry": {"coordinates":[32.5774116516,39.9775314331],"type":"Point"}
}