{
  "type": "Feature",
  "properties": {
    "iso:country":"TR",
    "sg:address":"Beyazgul Cad. No:76 Arnavutkoy",
    "sg:city":"Nisantasi",
    "sg:classifiers":[
        {
            "category":"Shopping",
            "subcategory":"Gifts & Souvenirs",
            "type":"Retail Goods"
        }
    ],
    "sg:phone":"+90 212 257 6575",
    "sg:postcode":"80200",
    "sg:province":"Istanbul",
    "wof:name":"Birce Reklam Promosyon Ltd.sti.",
    "wof:placetype":"venue"
},
  "geometry": {"coordinates":[29.0417709351,41.0690917969],"type":"Point"}
}