{
  "type": "Feature",
  "properties": {
    "addr:full":"Ahmet Suayip Sk.17 Laleli Istanbul 24300",
    "addr:postcode":"24300",
    "iso:country":"TR",
    "sg:address":"Ahmet Suayip Sk.17",
    "sg:city":"Laleli",
    "sg:orig_category":"Hotels: Motels",
    "sg:phone":"+90 21252064482",
    "sg:postcode":"24300",
    "sg:province":"Istanbul",
    "wof:name":"Metro Hotel",
    "wof:placetype":"venue"
},
  "geometry": {"coordinates":[28.9579257965,41.0106658936],"type":"Point"}
}