{
  "type": "Feature",
  "properties": {
    "addr:full":"Topcu Caddesi Uygun Apt. 2/1 Taksim Istanbul 24040",
    "addr:housenumber":"2 / 1",
    "addr:postcode":"24040",
    "addr:street":"Topcu Caddesi Uygun Apt.",
    "iso:country":"TR",
    "sg:address":"Topcu Caddesi Uygun Apt. 2/1",
    "sg:city":"Taksim",
    "sg:classifiers":[
        {
            "category":"Banks & Credit Unions",
            "subcategory":"Investment Brokerage",
            "type":"Services"
        }
    ],
    "sg:phone":"+90 212 254 7254",
    "sg:postcode":"24040",
    "sg:province":"Istanbul",
    "sg:tags":[
        "line",
        "air"
    ],
    "wof:name":"Sabena",
    "wof:placetype":"venue"
},
  "geometry": {"coordinates":[29.1856594086,40.9989738464],"type":"Point"}
}