{
  "type": "Feature",
  "properties": {
    "addr:full":"S.s Marangozlar San.sit. 4.cad. No:63 Beypazari Sel?klu Ankara",
    "addr:housenumber":"no 63",
    "addr:postcode":"? klu",
    "addr:street":"S.S;San.Sit.",
    "iso:country":"TR",
    "sg:address":"S.s Marangozlar San.sit. 4.cad. No:63 Beypazari",
    "sg:city":"Sel?klu",
    "sg:classifiers":[
        {
            "category":"Wholesale",
            "subcategory":"Auto Parts",
            "type":"Manufacturing & Wholesale Goods"
        }
    ],
    "sg:phone":"+90 31276313497625",
    "sg:province":"Ankara",
    "sg:tags":[
        "spare"
    ],
    "wof:name":"??eller Karoser Oto.ins. San. Ve Tic. Ltd.sti.",
    "wof:placetype":"venue"
},
  "geometry": {"coordinates":[31.9211006165,40.1674995422],"type":"Point"}
}