{
  "type": "Feature",
  "properties": {
    "addr:full":"Armagan Sok. 16/3 Besiktas 19300 Istanbul",
    "addr:housenumber":"16 / 3",
    "addr:postcode":"19300",
    "addr:street":"Armagan Sok.;Besiktas",
    "iso:country":"TR",
    "sg:address":"Armagan Sok. 16/3 Besiktas",
    "sg:city":"19300",
    "sg:classifiers":[
        {
            "category":"Shopping",
            "subcategory":"Gifts & Souvenirs",
            "type":"Retail Goods"
        }
    ],
    "sg:phone":"+90 212 259 7013",
    "sg:province":"Istanbul",
    "wof:name":"Minik Japonya",
    "wof:placetype":"venue"
},
  "geometry": {"coordinates":[28.9974002838,41.044670105],"type":"Point"}
}