{
  "type": "Feature",
  "properties": {
    "addr:full":"Yeni Mah. Devlet Yolu No: 110 Nazilli Aydin 65600",
    "addr:housenumber":"no",
    "addr:postcode":"65600",
    "addr:street":"Yeni Mah. Devlet Yolu;Nazilli Aydin",
    "iso:country":"TR",
    "sg:address":"Yeni Mah. Devlet Yolu No: 110",
    "sg:city":"Nazilli",
    "sg:classifiers":[
        {
            "category":"Farming",
            "subcategory":"Farm",
            "type":"Manufacturing & Wholesale Goods"
        }
    ],
    "sg:phone":"+90 256 313 2302",
    "sg:postcode":"65600",
    "sg:province":"Aydin",
    "sg:tags":[
        "agricultural",
        "product"
    ],
    "wof:name":"Asan Yerli ?r?n. Tic. San Ltd Sti.",
    "wof:placetype":"venue"
},
  "geometry": {"coordinates":[39.6284828186,41.0046424866],"type":"Point"}
}