{
  "type": "Feature",
  "properties": {
    "iso:country":"TR",
    "sg:address":"Merkez Mah. Cinar Cad. Kavak Sok. No:26",
    "sg:city":"Yenibosna",
    "sg:classifiers":[
        {
            "category":"Shopping",
            "subcategory":"Crafts & Fabrics",
            "type":"Retail Goods"
        }
    ],
    "sg:phone":"+90 212 654 6303",
    "sg:postcode":"43270",
    "sg:province":"Istanbul",
    "sg:tags":[
        "knitting"
    ],
    "wof:name":"Gruplar Tekstil",
    "wof:placetype":"venue"
},
  "geometry": {"coordinates":[29.0827865601,40.9692001343],"type":"Point"}
}