{
  "type": "Feature",
  "properties": {
    "addr:full":"Sahrayi Cedit Atat?k Cd.saray Apt.no13 D2 Kad\u0131k\u00f6y Istanbul 34990",
    "addr:housenumber":"d2",
    "addr:postcode":"34990",
    "addr:street":"Apt.No13;Istanbul",
    "iso:country":"TR",
    "sg:address":"Sahrayi Cedit Atat?k Cd.saray Apt.no13 D2",
    "sg:city":"Kad\u0131k\u00f6y",
    "sg:classifiers":[
        {
            "category":"Landmark",
            "subcategory":"Square",
            "type":"Public Place"
        }
    ],
    "sg:phone":"+90 216 361 0980",
    "sg:postcode":"34990",
    "sg:province":"Istanbul",
    "sg:tags":[
        "surveyor"
    ],
    "wof:name":"Yeditepe G?zetim Ltd.sti.",
    "wof:placetype":"venue"
},
  "geometry": {"coordinates":[28.975925,41.012379],"type":"Point"}
}