{
  "type": "Feature",
  "properties": {
    "iso:country":"TR",
    "sg:address":"Kartal C. No: 57 Yakacik",
    "sg:city":"Ikitelli/K\u00fc\u00e7\u00fck\u00e7ekmece",
    "sg:orig_category":"Prefabric Construction",
    "sg:phone":"+90 216 377 1600",
    "sg:postcode":"34670",
    "sg:province":"Istanbul",
    "wof:name":"Kosedag Tel San. A.s.",
    "wof:placetype":"venue"
},
  "geometry": {"coordinates":[29.1975021362,40.894203186],"type":"Point"}
}