{
  "type": "Feature",
  "properties": {
    "iso:country":"TR",
    "sg:address":"Eski Londra Asfalti No: 5/9 Sirinevler",
    "sg:city":"Kad\u0131k\u00f6y",
    "sg:classifiers":[
        {
            "category":"Shopping",
            "subcategory":"Crafts & Fabrics",
            "type":"Retail Goods"
        }
    ],
    "sg:phone":"+90 212 552 7703",
    "sg:postcode":"34734",
    "sg:province":"Istanbul",
    "sg:tags":[
        "textile",
        "-leather",
        "exporter"
    ],
    "wof:name":"Dekortas",
    "wof:placetype":"venue"
},
  "geometry": {"coordinates":[28.6092910767,41.0271873474],"type":"Point"}
}