{
  "type": "Feature",
  "properties": {
    "iso:country":"TR",
    "sg:address":"Habibler Mah.2690 Sok. No.45",
    "sg:city":"G.o.pasa",
    "sg:classifiers":[
        {
            "category":"Home & Garden",
            "subcategory":"Building Materials",
            "type":"Retail Goods"
        }
    ],
    "sg:phone":"+90 212 595 1385",
    "sg:province":"Istanbul",
    "sg:tags":[
        "stone",
        "natural",
        "marble"
    ],
    "wof:name":"Nurtas Mermer Sanayi Tic.a.s.",
    "wof:placetype":"venue"
},
  "geometry": {"coordinates":[28.9861831665,41.0408554077],"type":"Point"}
}