{
  "type": "Feature",
  "properties": {
    "iso:country":"TR",
    "sg:address":"San. Sitesi No:13/6",
    "sg:city":"Edremit",
    "sg:classifiers":[
        {
            "category":"Utilities",
            "subcategory":"Electric",
            "type":"Services"
        }
    ],
    "sg:phone":"+90 266 373 1841",
    "sg:postcode":"04500",
    "sg:province":"Balikesir",
    "sg:tags":[
        "energy",
        "solar"
    ],
    "wof:name":"G?nes Enerjisi Su Isitma Sistem.",
    "wof:placetype":"venue"
},
  "geometry": {"coordinates":[27.883301,39.6521],"type":"Point"}
}