{
  "type": "Feature",
  "properties": {
    "addr:full":"Ataturk Bulvari No:281 Turgutlu \u00c7orlu Manisa",
    "addr:housenumber":"no",
    "addr:street":"Ataturk Bulvari",
    "iso:country":"TR",
    "sg:address":"Ataturk Bulvari No:281 Turgutlu",
    "sg:city":"\u00c7orlu",
    "sg:classifiers":[
        {
            "category":"Shopping",
            "subcategory":"Luggage & Leather Goods",
            "type":"Retail Goods"
        }
    ],
    "sg:phone":"+90 236 313 9117",
    "sg:province":"Manisa",
    "sg:tags":[
        "leather-fur",
        "wear"
    ],
    "wof:name":"Asil Deri Konfeksiyon",
    "wof:placetype":"venue"
},
  "geometry": {"coordinates":[27.4349079132,38.616645813],"type":"Point"}
}