{
  "type": "Feature",
  "properties": {
    "iso:country":"TR",
    "sg:address":"100.yil Mah.mas-sit.5.cad.no:35 Bagcilar",
    "sg:city":"Mecidiyek\u00f6y",
    "sg:orig_category":"Printinh House",
    "sg:phone":"+90 2126290710729",
    "sg:postcode":"34387",
    "sg:province":"Istanbul",
    "wof:name":"Egemen Matbaacilik Yayincilik Tic.ltd.sti.",
    "wof:placetype":"venue"
},
  "geometry": {"coordinates":[28.9921588898,41.0720214844],"type":"Point"}
}