{
  "type": "Feature",
  "properties": {
    "addr:full":"Buklum Sk. No: 22/5 Kavaklidere Antakya Ankara 31000",
    "addr:housenumber":"22 / 5",
    "addr:postcode":"31000",
    "addr:street":"Buklum Sk. No;Kavaklidere",
    "iso:country":"TR",
    "sg:address":"Buklum Sk. No: 22/5 Kavaklidere",
    "sg:city":"Antakya",
    "sg:classifiers":[
        {
            "category":"Education",
            "subcategory":"Special Training",
            "type":"Public Place"
        }
    ],
    "sg:phone":"+90 312 417 8456",
    "sg:postcode":"31000",
    "sg:province":"Ankara",
    "sg:tags":[
        "course"
    ],
    "wof:name":"Olusum Tiyatrosu Ve Drama Atolyesi",
    "wof:placetype":"venue"
},
  "geometry": {"coordinates":[32.8584785461,39.9117736816],"type":"Point"}
}