{
  "type": "Feature",
  "properties": {
    "addr:full":"Talatpasa Blv. No:9/13 Samanpazari 27020 Ankara",
    "addr:housenumber":"13",
    "addr:postcode":"27020",
    "addr:street":"Blv. No 9 /",
    "iso:country":"TR",
    "sg:address":"Talatpasa Blv. No:9/13 Samanpazari",
    "sg:city":"27020",
    "sg:classifiers":[
        {
            "category":"Wholesale",
            "subcategory":"Medical Equipment & Supplies",
            "type":"Manufacturing & Wholesale Goods"
        }
    ],
    "sg:phone":"+90 312 312 6642",
    "sg:province":"Ankara",
    "wof:name":"Biyofarma Medikal",
    "wof:placetype":"venue"
},
  "geometry": {"coordinates":[32.8666992188,39.9333000183],"type":"Point"}
}