{
  "type": "Feature",
  "properties": {
    "addr:full":"Fatih Caddesi No:121/b - Sultanbeyli Macunk?y Istanbul",
    "addr:housenumber":"no;/ b",
    "addr:street":"Fatih Caddesi",
    "iso:country":"TR",
    "sg:address":"Fatih Caddesi No:121/b - Sultanbeyli",
    "sg:city":"Macunk?y",
    "sg:classifiers":[
        {
            "category":"Banks & Credit Unions",
            "subcategory":"Investment Brokerage",
            "type":"Services"
        }
    ],
    "sg:phone":"+90 216 398 4104",
    "sg:province":"Istanbul",
    "sg:tags":[
        "aid",
        "material",
        "first"
    ],
    "wof:name":"Elif Saglik Hizmetleri",
    "wof:placetype":"venue"
},
  "geometry": {"coordinates":[29.2652168274,40.9676818848],"type":"Point"}
}