{
  "type": "Feature",
  "properties": {
    "iso:country":"TR",
    "sg:address":"Fatih Cad.keresteciler Sitesi,",
    "sg:city":"Istanbul",
    "sg:classifiers":[
        {
            "category":"Banks & Credit Unions",
            "subcategory":"Bank",
            "type":"Services"
        }
    ],
    "sg:phone":"+90 212 637 1000",
    "sg:province":"30410",
    "wof:name":"Osmanli Bankasi As",
    "wof:placetype":"venue"
},
  "geometry": {"coordinates":[28.783052,41.07119],"type":"Point"}
}