{
  "type": "Feature",
  "properties": {
    "addr:full":"Mustafa Kurtoglu Cad. No:8 Bakir Pirinc San. Sit. 34900 B.cekmece Istanbul Zeytinburnu Istanbul 34020",
    "addr:postcode":"34900;34020",
    "addr:street":"Kurtoglu Cad. No 8 Bakir Pirinc San. Sit.",
    "iso:country":"TR",
    "sg:address":"Mustafa Kurtoglu Cad. No:8 Bakir Pirinc San. Sit. 34900 B.cekmece Istanbul",
    "sg:city":"Zeytinburnu",
    "sg:classifiers":[
        {
            "category":"Shopping",
            "subcategory":"Clothing, Apparel, & Fashions",
            "type":"Retail Goods"
        }
    ],
    "sg:phone":"+90 212 876 1939",
    "sg:postcode":"34020",
    "sg:province":"Istanbul",
    "sg:tags":[
        "clothes"
    ],
    "wof:name":"A.c.k Spor Giyim Tekstil Urunleri San",
    "wof:placetype":"venue"
},
  "geometry": {"coordinates":[28.9861831665,41.0408554077],"type":"Point"}
}