{
  "type": "Feature",
  "properties": {
    "addr:full":"Bodrum Karayolu ?eri Yenidogan Beldesi- S?e Aydin",
    "addr:street":"Karayolu;S;E",
    "iso:country":"TR",
    "sg:address":"Bodrum Karayolu ?eri Yenidogan Beldesi-",
    "sg:city":"S?e",
    "sg:classifiers":[
        {
            "category":"Wholesale",
            "subcategory":"Machinery & Supplies",
            "type":"Manufacturing & Wholesale Goods"
        }
    ],
    "sg:phone":"+90 256 521 0224",
    "sg:province":"Aydin",
    "sg:tags":[
        "agricultural"
    ],
    "wof:name":"D?nder Tarim Makinalari",
    "wof:placetype":"venue"
},
  "geometry": {"coordinates":[28.4863967896,37.8117027283],"type":"Point"}
}