{
  "type": "Feature",
  "properties": {
    "iso:country":"TR",
    "sg:address":"Vatan Cd. Park Sk. Emek ?ikmazi No: 14 ?aglayan",
    "sg:city":"Emin?? 34450",
    "sg:classifiers":[
        {
            "category":"Shopping",
            "subcategory":"Clothing, Apparel, & Fashions",
            "type":"Retail Goods"
        }
    ],
    "sg:phone":"+90 212 224 1298",
    "sg:province":"Istanbul",
    "sg:tags":[
        "bag-belt-accessories"
    ],
    "wof:name":"Tarkan Deri Mamulleri San. Tic. Ltd. Sti.",
    "wof:placetype":"venue"
},
  "geometry": {"coordinates":[28.975925,41.012379],"type":"Point"}
}