{
  "type": "Feature",
  "properties": {
    "iso:country":"TR",
    "sg:address":"B?? San. 1. Cd. No:99/38",
    "sg:city":"Ikitelli/K\u00fc\u00e7\u00fck\u00e7ekmece",
    "sg:classifiers":[
        {
            "category":"Retail",
            "subcategory":"Auto Repair",
            "type":"Services"
        }
    ],
    "sg:phone":"+90 312 341 8721",
    "sg:postcode":"34670",
    "sg:province":"Ankara",
    "sg:tags":[
        "maintenance"
    ],
    "wof:name":"Onur Oto San. Ltd. Sti.",
    "wof:placetype":"venue"
},
  "geometry": {"coordinates":[32.8604812622,39.9429283142],"type":"Point"}
}