{
  "type": "Feature",
  "properties": {
    "iso:country":"TR",
    "sg:address":"Cemal Sururi Sok. No.10",
    "sg:city":"Mecidiyek\u00f6y",
    "sg:classifiers":[
        {
            "category":"Government",
            "subcategory":"Post Office",
            "type":"Public Place"
        }
    ],
    "sg:phone":"+90 212 267 0103",
    "sg:postcode":"34387",
    "sg:province":"Istanbul",
    "sg:tags":[
        "distribution"
    ],
    "wof:name":"Gungor Turizm Kargo Emlak Ltd.sti.",
    "wof:placetype":"venue"
},
  "geometry": {"coordinates":[29.0007324219,41.0713882446],"type":"Point"}
}