{
  "type": "Feature",
  "properties": {
    "addr:full":"Gazcilar Cad.sakarya Mah. Yavuz Sok. No: 11/a 07100 Bursa",
    "addr:housenumber":"no 11 / a",
    "addr:postcode":"07100",
    "addr:street":"Cad.Sakarya Mah. Yavuz Sok.",
    "iso:country":"TR",
    "sg:address":"Gazcilar Cad.sakarya Mah. Yavuz Sok. No: 11/a",
    "sg:city":"07100",
    "sg:classifiers":[
        {
            "category":"Home & Garden",
            "subcategory":"Building Materials",
            "type":"Retail Goods"
        }
    ],
    "sg:phone":"+90 224 273 1155",
    "sg:province":"Bursa",
    "sg:tags":[
        "insulation"
    ],
    "wof:name":"Nokta Yalitim San.tic.",
    "wof:placetype":"venue"
},
  "geometry": {"coordinates":[29.0398807526,40.1076583862],"type":"Point"}
}