{
  "type": "Feature",
  "properties": {
    "iso:country":"TR",
    "sg:address":"Piyerloti Cad.17/4 Cemberlitas",
    "sg:city":"K??k?",
    "sg:orig_category":"Printinh House",
    "sg:phone":"+90 212 516 8464",
    "sg:postcode":"34760",
    "sg:province":"Istanbul",
    "wof:name":"Alev Yayinlari",
    "wof:placetype":"venue"
},
  "geometry": {"coordinates":[29.1056232452,41.0173683167],"type":"Point"}
}