{
  "type": "Feature",
  "properties": {
    "iso:country":"TR",
    "sg:address":"Selanik Bulvari. G?sin Sokak No:4",
    "sg:city":"Kemerburgaz/ey?",
    "sg:classifiers":[
        {
            "category":"Freight",
            "type":"Transportation"
        }
    ],
    "sg:phone":"+90 212 360 0049",
    "sg:postcode":"34075",
    "sg:province":"Istanbul",
    "sg:tags":[
        "packing",
        "industry"
    ],
    "wof:name":"Arpak Paketleme Malz. San. Tic.",
    "wof:placetype":"venue"
},
  "geometry": {"coordinates":[29.1616230011,40.9071311951],"type":"Point"}
}