{
  "type": "Feature",
  "properties": {
    "iso:country":"TR",
    "sg:address":"Hurriyet Mah. Sumbul Sok. No:24",
    "sg:city":"Sirinevler",
    "sg:classifiers":[
        {
            "category":"Sports & Exercise",
            "subcategory":"Ski Slope",
            "type":"Entertainment"
        }
    ],
    "sg:phone":"+90 212 552 4573",
    "sg:postcode":"15040",
    "sg:province":"Istanbul",
    "sg:tags":[
        "wear"
    ],
    "wof:name":"Biaggi Sport",
    "wof:placetype":"venue"
},
  "geometry": {"coordinates":[28.839815,40.99284],"type":"Point"}
}