{
  "type": "Feature",
  "properties": {
    "iso:country":"TR",
    "sg:address":"Ismetiye Cd. No:28 Mercan",
    "sg:city":"Mersin",
    "sg:classifiers":[
        {
            "category":"Manufacturing",
            "subcategory":"Rubber & Plastics",
            "type":"Manufacturing & Wholesale Goods"
        }
    ],
    "sg:phone":"+90 212 513 3383",
    "sg:postcode":"52750",
    "sg:province":"Istanbul",
    "sg:tags":[
        "industry"
    ],
    "wof:name":"Melsan Melamin Plastik San.",
    "wof:placetype":"venue"
},
  "geometry": {"coordinates":[28.9666938782,41.0150642395],"type":"Point"}
}