{
  "type": "Feature",
  "properties": {
    "iso:country":"TR",
    "sg:address":"Seyrantepe Mah. Celikay Cad. No.2",
    "sg:city":"4.levent",
    "sg:classifiers":[
        {
            "category":"Manufacturing",
            "subcategory":"Rubber & Plastics",
            "type":"Manufacturing & Wholesale Goods"
        }
    ],
    "sg:phone":"+90 212 270 1320",
    "sg:postcode":"80660",
    "sg:province":"Istanbul",
    "sg:tags":[
        "machinery"
    ],
    "wof:name":"Tepro Makine Ve Otomasyon Sist. Tic. Ltd.",
    "wof:placetype":"venue"
},
  "geometry": {"coordinates":[28.997303009,41.0979957581],"type":"Point"}
}