{
  "type": "Feature",
  "properties": {
    "iso:country":"TR",
    "sg:address":"Atat?k Cd. 123. Sk. No:1/6",
    "sg:city":"Mersin",
    "sg:classifiers":[
        {
            "category":"Transit Center",
            "subcategory":"Freight",
            "type":"Transportation"
        }
    ],
    "sg:phone":"+90 324 233 6634",
    "sg:postcode":"52750",
    "sg:province":"I?el",
    "wof:name":"Nakkas Denizcilik Tic. Ltd. Sti.",
    "wof:placetype":"venue"
},
  "geometry": {"coordinates":[37.7128486633,41.0530204773],"type":"Point"}
}