{
  "type": "Feature",
  "properties": {
    "addr:full":"Izmir Yolu 4 Km. Nisantasi ?anakkale 25370",
    "addr:housenumber":"4 km.;?",
    "addr:postcode":"25370",
    "addr:street":"Izmir Yolu;Nisantasi;Anakkale",
    "iso:country":"TR",
    "sg:address":"Izmir Yolu 4 Km.",
    "sg:city":"Nisantasi",
    "sg:classifiers":[
        {
            "category":"Food & Beverages",
            "subcategory":"Meat & Fish",
            "type":"Retail Goods"
        }
    ],
    "sg:phone":"+90 286 263 6666",
    "sg:postcode":"25370",
    "sg:province":"?anakkale",
    "sg:tags":[
        "seafood"
    ],
    "wof:name":"Dardanel Onentas Gida Sanayi A.s",
    "wof:placetype":"venue"
},
  "geometry": {"coordinates":[27.1296863556,38.4186973572],"type":"Point"}
}