{
  "type": "Feature",
  "properties": {
    "addr:full":"Eski Cankiri Yolu 1.km. Balikhisar Koyu Akyurt P.k.8 \u00dcmraniye Ankara",
    "addr:housenumber":"1.km;koyu",
    "addr:street":"Eski Cankiri Yolu;Akyurt P.K.8",
    "iso:country":"TR",
    "sg:address":"Eski Cankiri Yolu 1.km. Balikhisar Koyu Akyurt P.k.8",
    "sg:city":"\u00dcmraniye",
    "sg:classifiers":[
        {
            "category":"Manufacturing",
            "subcategory":"Wood Products",
            "type":"Manufacturing & Wholesale Goods"
        }
    ],
    "sg:phone":"+90 312 841 6490",
    "sg:province":"Ankara",
    "sg:tags":[
        "forest"
    ],
    "wof:name":"Erginay Kereste Ve Ambalaj San.tic. Ltd.sti.",
    "wof:placetype":"venue"
},
  "geometry": {"coordinates":[32.8560333252,39.9438743591],"type":"Point"}
}