{
  "type": "Feature",
  "properties": {
    "addr:full":"5 Telsiz Mah. 104.sok. No:39 Merter Istanbul",
    "addr:housenumber":"5;104.sok no 39",
    "addr:street":"Telsiz Mah.",
    "iso:country":"TR",
    "sg:address":"5 Telsiz Mah. 104.sok. No:39",
    "sg:city":"Merter",
    "sg:classifiers":[
        {
            "category":"Shopping",
            "subcategory":"Crafts & Fabrics",
            "type":"Retail Goods"
        }
    ],
    "sg:phone":"+90 212 547 2597",
    "sg:province":"Istanbul",
    "sg:tags":[
        "knitting"
    ],
    "wof:name":"Yagmur Tekstil",
    "wof:placetype":"venue"
},
  "geometry": {"coordinates":[28.9090633392,40.9917526245],"type":"Point"}
}