{
  "type": "Feature",
  "properties": {
    "addr:full":"Molla Feneri Sok. No:19/3 Cagaloglu Basinevleri Istanbul 06010",
    "addr:housenumber":"no 19 / 3",
    "addr:postcode":"06010",
    "addr:street":"Feneri Sok.",
    "iso:country":"TR",
    "sg:address":"Molla Feneri Sok. No:19/3 Cagaloglu",
    "sg:city":"Basinevleri",
    "sg:classifiers":[
        {
            "category":"Wholesale",
            "subcategory":"Books, Periodicals, & Newspapers",
            "type":"Manufacturing & Wholesale Goods"
        }
    ],
    "sg:phone":"+90 212 512 8121",
    "sg:postcode":"06010",
    "sg:province":"Istanbul",
    "sg:tags":[
        "house",
        "publishing"
    ],
    "wof:name":"Dharma Yayinlar",
    "wof:placetype":"venue"
},
  "geometry": {"coordinates":[28.9750175476,41.0128822327],"type":"Point"}
}