{
  "type": "Feature",
  "properties": {
    "addr:full":"Beysan Sanayi Sitesi Birlik Caddesi No: 26 Haramidere/avcilar Istanbul 84310",
    "addr:housenumber":"no 26",
    "addr:postcode":"84310",
    "addr:street":"Beysan Sanayi Sitesi Birlik Caddesi",
    "iso:country":"TR",
    "sg:address":"Beysan Sanayi Sitesi Birlik Caddesi No: 26",
    "sg:city":"Haramidere/avcilar",
    "sg:orig_category":"Printinh House",
    "sg:phone":"+90 212 422 1834",
    "sg:postcode":"84310",
    "sg:province":"Istanbul",
    "wof:name":"Acar Matbaacilik Yayincilik A.s.",
    "wof:placetype":"venue"
},
  "geometry": {"coordinates":[28.6845092773,41.00258255],"type":"Point"}
}