{
  "type": "Feature",
  "properties": {
    "addr:full":"Izmir Asfalti Uzeri Sarayk? Denizli",
    "iso:country":"TR",
    "sg:address":"Izmir Asfalti Uzeri",
    "sg:city":"Sarayk?",
    "sg:classifiers":[
        {
            "category":"Shopping",
            "subcategory":"Clothing, Apparel, & Fashions",
            "type":"Retail Goods"
        }
    ],
    "sg:phone":"+90 258 261 8727",
    "sg:province":"Denizli",
    "sg:tags":[
        "ready",
        "wear"
    ],
    "wof:name":"Ak?ay Tekstil A.s.",
    "wof:placetype":"venue"
},
  "geometry": {"coordinates":[29.0864906311,37.773525238],"type":"Point"}
}