{
  "type": "Feature",
  "properties": {
    "addr:full":"Atat?k Cad. Deniz Apt. Alti No:31/c Kad\u0131k\u00f6y Malatya",
    "addr:housenumber":"no 31 / c kadikoey",
    "addr:street":"K Cad. Deniz Apt. Alti",
    "iso:country":"TR",
    "sg:address":"Atat?k Cad. Deniz Apt. Alti No:31/c",
    "sg:city":"Kad\u0131k\u00f6y",
    "sg:classifiers":[
        {
            "category":"Professional",
            "subcategory":"Computer Services",
            "type":"Services"
        }
    ],
    "sg:phone":"+90 422 321 6711",
    "sg:province":"Malatya",
    "sg:tags":[
        "application",
        "software"
    ],
    "wof:name":"Deha Bilgisayar",
    "wof:placetype":"venue"
},
  "geometry": {"coordinates":[38.3195266724,38.3488922119],"type":"Point"}
}