{
  "type": "Feature",
  "properties": {
    "iso:country":"TR",
    "sg:address":"1079 Sk.no:19",
    "sg:city":"Torbali",
    "sg:classifiers":[
        {
            "category":"Shopping",
            "subcategory":"Crafts & Fabrics",
            "type":"Retail Goods"
        }
    ],
    "sg:phone":"+90 232 856 1266",
    "sg:postcode":"35860",
    "sg:province":"Izmir",
    "sg:tags":[
        "knitting"
    ],
    "wof:name":"Sel ?rme A.s",
    "wof:placetype":"venue"
},
  "geometry": {"coordinates":[27.155620575,38.4131240845],"type":"Point"}
}