{
  "type": "Feature",
  "properties": {
    "addr:full":"Mus Karabaglar Mus 44210",
    "addr:postcode":"44210",
    "iso:country":"TR",
    "sg:address":"Mus",
    "sg:city":"Karabaglar",
    "sg:classifiers":[
        {
            "category":"Government",
            "subcategory":"Office",
            "type":"Public Place"
        }
    ],
    "sg:phone":"+90 436 511 2008",
    "sg:postcode":"44210",
    "sg:province":"Mus",
    "sg:tags":[
        "army"
    ],
    "wof:name":"Malazgirt Askerlik Subesi",
    "wof:placetype":"venue"
},
  "geometry": {"coordinates":[41.4843902588,38.7321777344],"type":"Point"}
}