{
  "type": "Feature",
  "properties": {
    "addr:full":"Altunizade Mahir Iz Cad. No:28 Kat:2 D.6 \u00dcsk\u00fcdar Istanbul 34662",
    "addr:housenumber":"28 kat 2 d.6",
    "addr:postcode":"34662",
    "addr:street":"Iz Cad. No;Istanbul",
    "iso:country":"TR",
    "sg:address":"Altunizade Mahir Iz Cad. No:28 Kat:2 D.6",
    "sg:city":"\u00dcsk\u00fcdar",
    "sg:classifiers":[
        {
            "category":"Home & Garden",
            "subcategory":"Hardware",
            "type":"Retail Goods"
        }
    ],
    "sg:phone":"+90 2164742067729",
    "sg:postcode":"34662",
    "sg:province":"Istanbul",
    "sg:tags":[
        "compressor",
        "pump"
    ],
    "sg:website":"cankatonline.com",
    "wof:name":"Cankat M?messillik Ve Dis Tic. Ltd. Sti.",
    "wof:placetype":"venue"
},
  "geometry": {"coordinates":[29.0423545837,41.0168533325],"type":"Point"}
}