{
  "type": "Feature",
  "properties": {
    "iso:country":"TR",
    "sg:address":"Top?lar Kisla Cd. Seferaga San. Sit. B Blok Rami",
    "sg:city":"\u00dcmraniye",
    "sg:classifiers":[
        {
            "category":"Building & Trades",
            "subcategory":"Construction",
            "type":"Services"
        }
    ],
    "sg:phone":"+90 212 576 0780",
    "sg:province":"Istanbul",
    "sg:tags":[
        "industry",
        "mold"
    ],
    "wof:name":"Demircioglu Kalip?ilik San. Tic. Ltd. Sti.",
    "wof:placetype":"venue"
},
  "geometry": {"coordinates":[28.9759254456,41.0123786926],"type":"Point"}
}