{
  "type": "Feature",
  "properties": {
    "iso:country":"TR",
    "sg:address":"Tepecik Mah.kemal ?z Sok.imo Ishani No:1 Kat 1",
    "sg:city":"Izmit",
    "sg:classifiers":[
        {
            "category":"Insurance",
            "subcategory":"Hazard Insurance",
            "type":"Services"
        }
    ],
    "sg:phone":"+90 262 331 0210",
    "sg:postcode":"41200",
    "sg:province":"Kocaeli",
    "wof:name":"Alara Sigorta Ar.hiz.ltd.sti.",
    "wof:placetype":"venue"
},
  "geometry": {"coordinates":[29.9345855713,40.7669563293],"type":"Point"}
}