{
  "type": "Feature",
  "properties": {
    "addr:full":"Organize San. B?ge. 2. Cd. No:34 Kad\u0131k\u00f6y Istanbul 34990",
    "addr:housenumber":"2 cd. no 34",
    "addr:postcode":"34990",
    "addr:street":"Organize;Ge.;Istanbul",
    "iso:country":"TR",
    "sg:address":"Organize San. B?ge. 2. Cd. No:34",
    "sg:city":"Kad\u0131k\u00f6y",
    "sg:classifiers":[
        {
            "category":"Home & Garden",
            "subcategory":"Home Furnishings",
            "type":"Retail Goods"
        }
    ],
    "sg:phone":"+90 216 337 1140",
    "sg:postcode":"34990",
    "sg:province":"Istanbul",
    "sg:tags":[
        "-curtains",
        "upholstery"
    ],
    "wof:name":"Serbet?i Nakis Ve Konfeksiyon Tekstil San. Tic. A.s.",
    "wof:placetype":"venue"
},
  "geometry": {"coordinates":[28.9759254456,41.0123786926],"type":"Point"}
}