{
  "type": "Feature",
  "properties": {
    "addr:full":"1721.sok. No:4 Kat:1/105 Melek Ishani K.yaka Ulus Izmir 06030",
    "addr:housenumber":"no;kat 1 / 105",
    "addr:postcode":"06030",
    "addr:street":"Melek Ishani K.Yaka",
    "iso:country":"TR",
    "sg:address":"1721.sok. No:4 Kat:1/105 Melek Ishani K.yaka",
    "sg:city":"Ulus",
    "sg:classifiers":[
        {
            "category":"Banks & Credit Unions",
            "subcategory":"Financial Services",
            "type":"Services"
        }
    ],
    "sg:phone":"+90 232 323 1100",
    "sg:postcode":"06030",
    "sg:province":"Izmir",
    "sg:tags":[
        "consultant"
    ],
    "wof:name":"Muz-ok Ltd.sti.",
    "wof:placetype":"venue"
},
  "geometry": {"coordinates":[27.1296863556,38.4186973572],"type":"Point"}
}