{
  "type": "Feature",
  "properties": {
    "addr:full":"Kizilay Cad. Gorgun Pasaji No: 8 Seyhan \u00dcmraniye Adana",
    "addr:street":"Kizilay Cad. Gorgun Pasaji No 8 Seyhan",
    "iso:country":"TR",
    "sg:address":"Kizilay Cad. Gorgun Pasaji No: 8 Seyhan",
    "sg:city":"\u00dcmraniye",
    "sg:classifiers":[
        {
            "category":"Manufacturing",
            "subcategory":"Rubber & Plastics",
            "type":"Manufacturing & Wholesale Goods"
        }
    ],
    "sg:phone":"+90 322 359 1838",
    "sg:province":"Adana",
    "sg:tags":[
        "industry"
    ],
    "wof:name":"Inan Plastik Tic.",
    "wof:placetype":"venue"
},
  "geometry": {"coordinates":[35.3329734802,36.970500946],"type":"Point"}
}