{
  "type": "Feature",
  "properties": {
    "addr:full":"Karpuzlu Sk. 16 Siteler G?c? Ankara",
    "addr:housenumber":"? c ?",
    "addr:street":"Karpuzlu Sk. 16 Siteler G",
    "iso:country":"TR",
    "sg:address":"Karpuzlu Sk. 16 Siteler",
    "sg:city":"G?c?",
    "sg:classifiers":[
        {
            "category":"Manufacturing",
            "subcategory":"Wood Products",
            "type":"Manufacturing & Wholesale Goods"
        }
    ],
    "sg:phone":"+90 312 348 0701",
    "sg:province":"Ankara",
    "sg:tags":[
        "forest"
    ],
    "wof:name":"Salih Orman ?r?n. San. Tic. Ltd.",
    "wof:placetype":"venue"
},
  "geometry": {"coordinates":[29.1006603241,40.1823120117],"type":"Point"}
}