{
  "type": "Feature",
  "properties": {
    "addr:full":"1467. Sk. No:6/3 Alsancak Fatih Izmir 01740",
    "addr:housenumber":"1467;3",
    "addr:postcode":"01740",
    "addr:street":"Sk. No 6 /",
    "iso:country":"TR",
    "sg:address":"1467. Sk. No:6/3 Alsancak",
    "sg:city":"Fatih",
    "sg:classifiers":[
        {
            "category":"Wholesale",
            "subcategory":"Medical Equipment & Supplies",
            "type":"Manufacturing & Wholesale Goods"
        }
    ],
    "sg:phone":"+90 232 463 4834",
    "sg:postcode":"01740",
    "sg:province":"Izmir",
    "sg:tags":[
        "material"
    ],
    "wof:name":"Kutalmis Tibbi Mlz. Ltd. Sti.",
    "wof:placetype":"venue"
},
  "geometry": {"coordinates":[27.1451053619,38.4388275146],"type":"Point"}
}