{
  "type": "Feature",
  "properties": {
    "addr:full":"Bagdat Cad. No:98-7 Kucukyali Istanbul 35280",
    "addr:housenumber":"98-7",
    "addr:postcode":"35280",
    "addr:street":"Bagdat Cad. No;Istanbul",
    "iso:country":"TR",
    "sg:address":"Bagdat Cad. No:98-7",
    "sg:city":"Kucukyali",
    "sg:classifiers":[
        {
            "category":"Manufacturing",
            "subcategory":"Building Materials",
            "type":"Manufacturing & Wholesale Goods"
        }
    ],
    "sg:phone":"+90 216 388 3069",
    "sg:postcode":"35280",
    "sg:province":"Istanbul",
    "sg:tags":[
        "floor-wall",
        "covering"
    ],
    "wof:name":"Itm Muhendislik Mumessillik Ve Dis.tic. Ltd.sti.",
    "wof:placetype":"venue"
},
  "geometry": {"coordinates":[29.0977535248,40.9520111084],"type":"Point"}
}