{
  "type": "Feature",
  "properties": {
    "addr:full":"Eskisehir Istanbul Eskisehir",
    "iso:country":"TR",
    "sg:address":"Eskisehir",
    "sg:city":"Istanbul",
    "sg:classifiers":[
        {
            "category":"Banks & Credit Unions",
            "subcategory":"Bank",
            "type":"Services"
        }
    ],
    "sg:province":"Eskisehir",
    "wof:name":"Eston Eskisehir Beton San Ve Tic As",
    "wof:placetype":"venue"
},
  "geometry": {"coordinates":[30.517546,39.770081],"type":"Point"}
}