{
  "type": "Feature",
  "properties": {
    "iso:country":"TR",
    "sg:address":"Sira Magazalar No:2/a",
    "sg:city":"Merkez",
    "sg:classifiers":[
        {
            "category":"Manufacturing",
            "subcategory":"Leather Goods",
            "type":"Manufacturing & Wholesale Goods"
        }
    ],
    "sg:phone":"+90 462 322 3866",
    "sg:postcode":"61100",
    "sg:province":"Trabzon",
    "sg:tags":[
        "raw"
    ],
    "wof:name":"Antilop Deri",
    "wof:placetype":"venue"
},
  "geometry": {"coordinates":[39.7411804199,40.9852218628],"type":"Point"}
}