{
  "type": "Feature",
  "properties": {
    "iso:country":"TR",
    "sg:address":"Bayar Cd. Riza ?emberci Ismerk. No.72 K:1 Kozyatagi",
    "sg:city":"Sisli",
    "sg:classifiers":[
        {
            "category":"Shopping",
            "subcategory":"Stationery & Office Supplies",
            "type":"Retail Goods"
        }
    ],
    "sg:phone":"+90 216 410 9514",
    "sg:postcode":"34200",
    "sg:province":"Istanbul",
    "sg:tags":[
        "paper"
    ],
    "wof:name":"Levpa Kagit San. Ve Dis Tic. Ltd. Sti.",
    "wof:placetype":"venue"
},
  "geometry": {"coordinates":[28.860408783,41.0367050171],"type":"Point"}
}