{
  "type": "Feature",
  "properties": {
    "addr:full":"Yeni?rsi Cd. No:54 Beyoglu Fatih Istanbul 01740",
    "addr:housenumber":"no 54",
    "addr:postcode":"01740",
    "addr:street":"Rsi Cd.;Beyoglu",
    "iso:country":"TR",
    "sg:address":"Yeni?rsi Cd. No:54 Beyoglu",
    "sg:city":"Fatih",
    "sg:classifiers":[
        {
            "category":"Building & Trades",
            "subcategory":"Construction",
            "type":"Services"
        }
    ],
    "sg:phone":"+90 212 293 1605",
    "sg:postcode":"01740",
    "sg:province":"Istanbul",
    "sg:tags":[
        "foundation"
    ],
    "wof:name":"Insan Kaynagi Gelistirme Vakfi",
    "wof:placetype":"venue"
},
  "geometry": {"coordinates":[28.9759254456,41.0123786926],"type":"Point"}
}