{
  "type": "Feature",
  "properties": {
    "iso:country":"TR",
    "sg:address":"Siraselviler Cad. No.152/5 Taksim",
    "sg:city":"Lara",
    "sg:classifiers":[
        {
            "category":"Professional",
            "subcategory":"Detective & Security Services",
            "type":"Services"
        }
    ],
    "sg:phone":"+90 212 249 9127",
    "sg:postcode":"07400",
    "sg:province":"Istanbul",
    "sg:tags":[
        "material"
    ],
    "wof:name":"Medcom Elek. Tic.san.ltd.",
    "wof:placetype":"venue"
},
  "geometry": {"coordinates":[28.98378,41.036797],"type":"Point"}
}