{
  "type": "Feature",
  "properties": {
    "addr:full":"Calislar Cad.no:68/7 Bahcelievler Kazasker Istanbul",
    "addr:housenumber":"68 / 7",
    "addr:street":"Bahcelievler Kazasker",
    "iso:country":"TR",
    "sg:address":"Calislar Cad.no:68/7 Bahcelievler",
    "sg:city":"Kazasker",
    "sg:classifiers":[
        {
            "category":"Manufacturing",
            "subcategory":"Chemicals & Compounds",
            "type":"Manufacturing & Wholesale Goods"
        }
    ],
    "sg:phone":"+90 212 556 1359",
    "sg:province":"Istanbul",
    "sg:tags":[
        "pharmaceutical"
    ],
    "wof:name":"Tib Tek Galenik Laboratuari",
    "wof:placetype":"venue"
},
  "geometry": {"coordinates":[28.8711452484,41.0042915344],"type":"Point"}
}