{
  "type": "Feature",
  "properties": {
    "addr:full":"H??et Cd. No:25 ?skudar Adana 34000",
    "addr:housenumber":"?",
    "addr:postcode":"34000",
    "addr:street":"Skudar Adana",
    "iso:country":"TR",
    "sg:address":"H??et Cd. No:25",
    "sg:city":"?skudar",
    "sg:classifiers":[
        {
            "category":"Freight",
            "type":"Transportation"
        }
    ],
    "sg:phone":"+90 322 613 6195",
    "sg:postcode":"34000",
    "sg:province":"Adana",
    "sg:tags":[
        "packing",
        "industry"
    ],
    "wof:name":"Mosas Metal Ofset Ambalaj San. As.",
    "wof:placetype":"venue"
},
  "geometry": {"coordinates":[35.3137359619,37.0007171631],"type":"Point"}
}