{
  "type": "Feature",
  "properties": {
    "iso:country":"TR",
    "sg:address":"Dr. Cemil Bengu Cad. No:11/3 Hurriyet Mah. Dulger Sokak Caglayan 80360 Kagithane Istanbul",
    "sg:city":"Ikitelli",
    "sg:classifiers":[
        {
            "category":"Sports & Exercise",
            "subcategory":"Playing Field",
            "type":"Entertainment"
        }
    ],
    "sg:phone":"+90 212 224 3098",
    "sg:postcode":"34306",
    "sg:province":"Istanbul",
    "sg:tags":[
        "game"
    ],
    "wof:name":"Simge Bayrak San Tic Ltd Sti",
    "wof:placetype":"venue"
},
  "geometry": {"coordinates":[28.9857769012,41.0726890564],"type":"Point"}
}