{
  "type": "Feature",
  "properties": {
    "addr:full":"Kefeli Cd. No:130 Tarabya \u00dcmraniye Istanbul 81260",
    "addr:housenumber":"no",
    "addr:postcode":"81260",
    "addr:street":"Kefeli Cd.;Tarabya",
    "iso:country":"TR",
    "sg:address":"Kefeli Cd. No:130 Tarabya",
    "sg:city":"\u00dcmraniye",
    "sg:classifiers":[
        {
            "category":"Farming",
            "subcategory":"Fish & Marine Products",
            "type":"Manufacturing & Wholesale Goods"
        }
    ],
    "sg:phone":"+90 212 262 2972",
    "sg:postcode":"81260",
    "sg:province":"Istanbul",
    "sg:tags":[
        "automotive"
    ],
    "wof:name":"Mat Motorlu Ara?. I? Dis Ltd. Sti.",
    "wof:placetype":"venue"
},
  "geometry": {"coordinates":[29.0357112885,41.1511383057],"type":"Point"}
}