{
  "type": "Feature",
  "properties": {
    "iso:country":"TR",
    "sg:address":"Gaziosmanpasa Bul 2",
    "sg:city":"Izmir",
    "sg:classifiers":[
        {
            "category":"Banks & Credit Unions",
            "subcategory":"Bank",
            "type":"Services"
        }
    ],
    "sg:phone":"+90 232 464 1471",
    "sg:province":"35210",
    "wof:name":"Yapi Ve Kredi, Bankasi As",
    "wof:placetype":"venue"
},
  "geometry": {"coordinates":[29.286436,40.655308],"type":"Point"}
}