{
  "type": "Feature",
  "properties": {
    "addr:full":"Modesa Mobilyacilar Sit. Munzevi Kisla Cad. No:63 Eyup \u00dcmraniye Istanbul",
    "addr:housenumber":"63",
    "addr:street":"Kisla Cad. No;Eyup",
    "iso:country":"TR",
    "sg:address":"Modesa Mobilyacilar Sit. Munzevi Kisla Cad. No:63 Eyup",
    "sg:city":"\u00dcmraniye",
    "sg:classifiers":[
        {
            "category":"Building & Trades",
            "subcategory":"Construction",
            "type":"Services"
        }
    ],
    "sg:phone":"+90 212 612 6008",
    "sg:province":"Istanbul",
    "sg:tags":[
        "industry",
        "mold"
    ],
    "wof:name":"Aydin Kalip Yedek Parca Ve Mobilya Sanayi Tic.ltd.sti.",
    "wof:placetype":"venue"
},
  "geometry": {"coordinates":[28.9283294678,41.0411567688],"type":"Point"}
}