{
  "type": "Feature",
  "properties": {
    "addr:full":"30.sok.no:32 Ostim Mahmutbey Ankara 46600",
    "addr:housenumber":"32",
    "addr:postcode":"46600",
    "addr:street":"Ostim Mahmutbey",
    "iso:country":"TR",
    "sg:address":"30.sok.no:32 Ostim",
    "sg:city":"Mahmutbey",
    "sg:classifiers":[
        {
            "category":"Utilities",
            "subcategory":"Electric",
            "type":"Services"
        }
    ],
    "sg:phone":"+90 312 354 2972",
    "sg:postcode":"46600",
    "sg:province":"Ankara",
    "sg:tags":[
        "accumulator",
        "-",
        "batery"
    ],
    "wof:name":"Guclu Aku San.a.s",
    "wof:placetype":"venue"
},
  "geometry": {"coordinates":[32.740742,39.971226],"type":"Point"}
}