{
  "type": "Feature",
  "properties": {
    "addr:full":"Samanyolu Sk. No:71/a Osmanbey Istanbul 63000",
    "addr:housenumber":"71 / a",
    "addr:postcode":"63000",
    "addr:street":"Samanyolu Sk. No",
    "iso:country":"TR",
    "sg:address":"Samanyolu Sk. No:71/a",
    "sg:city":"Osmanbey",
    "sg:classifiers":[
        {
            "category":"Shopping",
            "subcategory":"Clothing, Apparel, & Fashions",
            "type":"Retail Goods"
        }
    ],
    "sg:phone":"+90 212248511724",
    "sg:postcode":"63000",
    "sg:province":"Istanbul",
    "sg:tags":[
        "men",
        "wear"
    ],
    "wof:name":"Ron Collection",
    "wof:placetype":"venue"
},
  "geometry": {"coordinates":[28.3423500061,41.0966300964],"type":"Point"}
}