{
  "type": "Feature",
  "properties": {
    "iso:country":"TR",
    "sg:address":"?amlitepe Sk. No:45/1 Siteler",
    "sg:city":"Edremit",
    "sg:classifiers":[
        {
            "category":"Home & Garden",
            "subcategory":"Household Appliances",
            "type":"Retail Goods"
        }
    ],
    "sg:phone":"+90 312 348 9246",
    "sg:postcode":"04500",
    "sg:province":"Ankara",
    "sg:tags":[
        "utensil",
        "electrical"
    ],
    "wof:name":"Dolgusan Elektrikli Isitici San. Tic. Ltd. Sti.",
    "wof:placetype":"venue"
},
  "geometry": {"coordinates":[32.8604812622,39.9429283142],"type":"Point"}
}