{
  "type": "Feature",
  "properties": {
    "addr:full":"Yeni Hal Kompleksi A\\\\blok No:46 Aksaray Diyarbakir 12345",
    "addr:housenumber":"blok no 46",
    "addr:postcode":"12345",
    "addr:street":"Diyarbakir",
    "iso:country":"TR",
    "sg:address":"Yeni Hal Kompleksi A\\\\blok No:46",
    "sg:city":"Aksaray",
    "sg:classifiers":[
        {
            "category":"Food & Beverages",
            "subcategory":"Fruits & Vegetables",
            "type":"Retail Goods"
        }
    ],
    "sg:phone":"+90 412 251 1188",
    "sg:postcode":"12345",
    "sg:province":"Diyarbakir",
    "sg:tags":[
        "fresh"
    ],
    "wof:name":"Muzcular Ticaret",
    "wof:placetype":"venue"
},
  "geometry": {"coordinates":[40.2253341675,37.9158096313],"type":"Point"}
}