{
  "type": "Feature",
  "properties": {
    "addr:full":"Yavuz Selim Mah.baris Cad. No:7/a-b Kadikoy Bursa 01370",
    "addr:housenumber":"a-b",
    "addr:postcode":"01370",
    "addr:street":"Mah.Baris Cad. No 7 /;Bursa",
    "iso:country":"TR",
    "sg:address":"Yavuz Selim Mah.baris Cad. No:7/a-b",
    "sg:city":"Kadikoy",
    "sg:classifiers":[
        {
            "category":"Manufacturing",
            "subcategory":"Building Materials",
            "type":"Manufacturing & Wholesale Goods"
        }
    ],
    "sg:phone":"+90 224368348586",
    "sg:postcode":"01370",
    "sg:province":"Bursa",
    "sg:tags":[
        "lifts-elevators"
    ],
    "wof:name":"Seref Tekstil",
    "wof:placetype":"venue"
},
  "geometry": {"coordinates":[36.3283004761,41.2879180908],"type":"Point"}
}