{
  "type": "Feature",
  "properties": {
    "iso:country":"TR",
    "sg:address":"Termal Yolu 3. Km 77200",
    "sg:city":"Caddebostan",
    "sg:classifiers":[
        {
            "category":"Shopping",
            "subcategory":"Florist",
            "type":"Retail Goods"
        }
    ],
    "sg:phone":"+90 226 818 3374",
    "sg:postcode":"34728",
    "sg:province":"Yalova",
    "sg:tags":[
        "flower"
    ],
    "wof:name":"Karaduman Fidancilik",
    "wof:placetype":"venue"
},
  "geometry": {"coordinates":[29.2712001801,40.65599823],"type":"Point"}
}