{
  "type": "Feature",
  "properties": {
    "addr:full":"Topraksarnic Mah.esenbel Sok. No:12 Aysekadin Konya",
    "addr:housenumber":"no 12",
    "addr:street":"Mah.Esenbel Sok.;Aysekadin",
    "iso:country":"TR",
    "sg:address":"Topraksarnic Mah.esenbel Sok. No:12",
    "sg:city":"Aysekadin",
    "sg:classifiers":[
        {
            "category":"Manufacturing",
            "subcategory":"Building Materials",
            "type":"Manufacturing & Wholesale Goods"
        }
    ],
    "sg:phone":"+90 332 320 6086",
    "sg:province":"Konya",
    "sg:tags":[
        "lifts-elevators"
    ],
    "wof:name":"Metropol Asansor",
    "wof:placetype":"venue"
},
  "geometry": {"coordinates":[32.4599113464,37.885887146],"type":"Point"}
}