{
  "type": "Feature",
  "properties": {
    "addr:full":"Bagdat Cad.selin Apt. No: 90/6 Maltepe Istanbul 01000",
    "addr:housenumber":"6",
    "addr:postcode":"01000",
    "addr:street":"Maltepe Istanbul",
    "iso:country":"TR",
    "sg:address":"Bagdat Cad.selin Apt. No: 90/6",
    "sg:city":"Maltepe",
    "sg:classifiers":[
        {
            "category":"Manufacturing",
            "subcategory":"Building Materials",
            "type":"Manufacturing & Wholesale Goods"
        }
    ],
    "sg:phone":"+90 216 441 4244",
    "sg:postcode":"01000",
    "sg:province":"Istanbul",
    "sg:tags":[
        "floor-wall",
        "covering"
    ],
    "wof:name":"Safir Tekstil Hali Ve Yer Dosemeleri San.tic.ltd.sti.",
    "wof:placetype":"venue"
},
  "geometry": {"coordinates":[29.0690822601,40.9655227661],"type":"Point"}
}