{
  "type": "Feature",
  "properties": {
    "addr:full":"Cobancesme Merkez Istanbul 46010",
    "addr:postcode":"46010",
    "iso:country":"TR",
    "sg:address":"Cobancesme",
    "sg:city":"Merkez",
    "sg:classifiers":[
        {
            "category":"Home & Garden",
            "subcategory":"Household Appliances",
            "type":"Retail Goods"
        }
    ],
    "sg:phone":"+90 212 503 1317",
    "sg:postcode":"46010",
    "sg:province":"Istanbul",
    "sg:tags":[
        "kitchenware"
    ],
    "wof:name":"Onur Polluretan Terlik",
    "wof:placetype":"venue"
},
  "geometry": {"coordinates":[28.8196868896,40.9930381775],"type":"Point"}
}