{
  "type": "Feature",
  "properties": {
    "addr:full":"Iskele Sk. No:3 Sisli Mecidiyek\u00f6y Istanbul 34387",
    "addr:postcode":"34387",
    "addr:street":"Iskele Sk. No 3 Sisli Mecidiyekoey",
    "iso:country":"TR",
    "sg:address":"Iskele Sk. No:3 Sisli",
    "sg:city":"Mecidiyek\u00f6y",
    "sg:classifiers":[
        {
            "category":"Shopping",
            "subcategory":"Photographic Equipment",
            "type":"Retail Goods"
        }
    ],
    "sg:phone":"+90 212 241 1010",
    "sg:postcode":"34387",
    "sg:province":"Istanbul",
    "sg:tags":[
        "photo"
    ],
    "wof:name":"Spot Foto Ltd.",
    "wof:placetype":"venue"
},
  "geometry": {"coordinates":[29.012430191,41.0246429443],"type":"Point"}
}