{
  "type": "Feature",
  "properties": {
    "addr:full":"Burhaniye Cad. Acar Sitesi No:5 Susurluk Balikesir 10600",
    "addr:housenumber":"sitesi no 5",
    "addr:postcode":"10600",
    "addr:street":"Burhaniye Cad. Acar;Balikesir",
    "iso:country":"TR",
    "sg:address":"Burhaniye Cad. Acar Sitesi No:5",
    "sg:city":"Susurluk",
    "sg:classifiers":[
        {
            "category":"Farming",
            "subcategory":"Farm & Veterinary Services",
            "type":"Manufacturing & Wholesale Goods"
        }
    ],
    "sg:phone":"+90 266875567087",
    "sg:postcode":"10600",
    "sg:province":"Balikesir",
    "sg:tags":[
        "clinic"
    ],
    "wof:name":"Fikret Egemen",
    "wof:placetype":"venue"
},
  "geometry": {"coordinates":[27.8833007812,39.6520996094],"type":"Point"}
}