{
  "type": "Feature",
  "properties": {
    "addr:full":"Y.selim Cd. Armagan Apt. Antakya Maltepe Hatay 34843",
    "addr:postcode":"34843",
    "addr:street":"Y.Selim Cd. Armagan Apt. Antakya Maltepe",
    "iso:country":"TR",
    "sg:address":"Y.selim Cd. Armagan Apt. Antakya",
    "sg:city":"Maltepe",
    "sg:classifiers":[
        {
            "category":"Banks & Credit Unions",
            "subcategory":"Investment Brokerage",
            "type":"Services"
        }
    ],
    "sg:phone":"+90 326 215 4755",
    "sg:postcode":"34843",
    "sg:province":"Hatay",
    "sg:tags":[
        "-",
        "export",
        "import"
    ],
    "wof:name":"Someks Ltd. Sti.",
    "wof:placetype":"venue"
},
  "geometry": {"coordinates":[36.2382698059,36.4112091064],"type":"Point"}
}