{
  "type": "Feature",
  "properties": {
    "addr:full":"847. Sk. No:25/a Konak Osmangazi Izmir 16220",
    "addr:housenumber":"25 / a",
    "addr:postcode":"16220",
    "addr:street":"847 Sk. No;Konak Osmangazi",
    "iso:country":"TR",
    "sg:address":"847. Sk. No:25/a Konak",
    "sg:city":"Osmangazi",
    "sg:classifiers":[
        {
            "category":"Wholesale",
            "subcategory":"Medical Equipment & Supplies",
            "type":"Manufacturing & Wholesale Goods"
        }
    ],
    "sg:phone":"+90 232 484 0713",
    "sg:postcode":"16220",
    "sg:province":"Izmir",
    "sg:tags":[
        "material"
    ],
    "wof:name":"Tolga Medikal Ltd. Sti.",
    "wof:placetype":"venue"
},
  "geometry": {"coordinates":[27.130941391,38.4168510437],"type":"Point"}
}