{
  "type": "Feature",
  "properties": {
    "addr:full":"Cumhuriyet Cad 70 Erzurum 25100 25750",
    "addr:housenumber":"70",
    "addr:postcode":"25100 25750",
    "addr:street":"Cumhuriyet Cad",
    "iso:country":"TR",
    "sg:address":"Cumhuriyet Cad 70",
    "sg:city":"Erzurum",
    "sg:classifiers":[
        {
            "category":"Banks & Credit Unions",
            "subcategory":"Bank",
            "type":"Services"
        }
    ],
    "sg:phone":"+90 442 233 6203",
    "sg:postcode":"25750",
    "sg:province":"25100",
    "wof:name":"Etibank Bao",
    "wof:placetype":"venue"
},
  "geometry": {"coordinates":[41.272541,39.905956],"type":"Point"}
}