{
  "type": "Feature",
  "properties": {
    "iso:country":"TR",
    "sg:address":"Menderes Cd. No:282/a",
    "sg:city":"Yenimahalle",
    "sg:classifiers":[
        {
            "category":"Shopping",
            "subcategory":"Stationery & Office Supplies",
            "type":"Retail Goods"
        }
    ],
    "sg:phone":"+90 232 487 0848",
    "sg:postcode":"06",
    "sg:province":"Izmir",
    "sg:tags":[
        "paper"
    ],
    "wof:name":"Dakkas Kagit?ilik Ltd. Sti.",
    "wof:placetype":"venue"
},
  "geometry": {"coordinates":[27.1644935608,38.2957801819],"type":"Point"}
}