{
  "type": "Feature",
  "properties": {
    "addr:full":"Perpa Is Merkezi Kat:5 No:195 Okmeydani Istanbul 43050",
    "addr:housenumber":"kat 5 no 195",
    "addr:postcode":"43050",
    "addr:street":"Okmeydani Istanbul",
    "iso:country":"TR",
    "sg:address":"Perpa Is Merkezi Kat:5 No:195",
    "sg:city":"Okmeydani",
    "sg:classifiers":[
        {
            "category":"Food & Beverages",
            "subcategory":"Specialty",
            "type":"Retail Goods"
        }
    ],
    "sg:phone":"+90 212 210 0028",
    "sg:postcode":"43050",
    "sg:province":"Istanbul",
    "sg:tags":[
        "materials-spices",
        "additive"
    ],
    "wof:name":"Ad-ay Kimyevi Mad. San. Tic.",
    "wof:placetype":"venue"
},
  "geometry": {"coordinates":[28.9759254456,41.0123786926],"type":"Point"}
}