{
  "type": "Feature",
  "properties": {
    "addr:full":"Rihtim Sok. No:6 Bayrampasa \u00c7orlu Istanbul",
    "addr:housenumber":"no 6",
    "addr:street":"Rihtim Sok.",
    "iso:country":"TR",
    "sg:address":"Rihtim Sok. No:6 Bayrampasa",
    "sg:city":"\u00c7orlu",
    "sg:classifiers":[
        {
            "category":"Shopping",
            "subcategory":"Luggage & Leather Goods",
            "type":"Retail Goods"
        }
    ],
    "sg:phone":"+90 21256706233",
    "sg:province":"Istanbul",
    "sg:tags":[
        "leather-fur",
        "wear"
    ],
    "wof:name":"Matras Deri A.s.",
    "wof:placetype":"venue"
},
  "geometry": {"coordinates":[28.9140300751,41.0344467163],"type":"Point"}
}