{
  "type": "Feature",
  "properties": {
    "iso:country":"TR",
    "sg:address":"Gunesli Evren Mah. Gulbahar Cad. No: 30",
    "sg:city":"Osmanbey",
    "sg:classifiers":[
        {
            "category":"Sports & Exercise",
            "subcategory":"Ski Slope",
            "type":"Entertainment"
        }
    ],
    "sg:phone":"+90 21263000633428",
    "sg:postcode":"63000",
    "sg:province":"Istanbul",
    "sg:tags":[
        "wear"
    ],
    "wof:name":"Ender Spor Malz. Tekstil Turz. Insaat. Ic Ve Dis Tic. A.s.",
    "wof:placetype":"venue"
},
  "geometry": {"coordinates":[28.814512,41.032829],"type":"Point"}
}