{
  "type": "Feature",
  "properties": {
    "addr:full":"Kemeralti Cad. No:27 Karakoy Istanbul 07700",
    "addr:housenumber":"27",
    "addr:postcode":"07700",
    "addr:street":"Kemeralti Cad. No",
    "iso:country":"TR",
    "sg:address":"Kemeralti Cad. No:27",
    "sg:city":"Karakoy",
    "sg:classifiers":[
        {
            "category":"Manufacturing",
            "subcategory":"Building Materials",
            "type":"Manufacturing & Wholesale Goods"
        }
    ],
    "sg:phone":"+90 212 293 9317",
    "sg:postcode":"07700",
    "sg:province":"Istanbul",
    "sg:tags":[
        "lifts-elevators"
    ],
    "wof:name":"Astes Asansor A.s.",
    "wof:placetype":"venue"
},
  "geometry": {"coordinates":[28.9766311646,41.0245780945],"type":"Point"}
}