{
  "type": "Feature",
  "properties": {
    "iso:country":"TR",
    "sg:address":"Yolcuzade Iskender Cd. Sishane Sk. No:49",
    "sg:city":"Sishane",
    "sg:classifiers":[
        {
            "category":"Building & Trades",
            "subcategory":"Electrical",
            "type":"Services"
        }
    ],
    "sg:phone":"+90 212 237 5236",
    "sg:province":"Istanbul",
    "sg:tags":[
        "equipment",
        "lighting"
    ],
    "wof:name":"?ztas Aydinlatma San. Dis Tic. Ltd. Sti.",
    "wof:placetype":"venue"
},
  "geometry": {"coordinates":[28.9716148376,41.0272254944],"type":"Point"}
}