{
  "type": "Feature",
  "properties": {
    "addr:full":"Gazi Bulvari No:93/303 Basmene Izmir",
    "addr:housenumber":"no 93 / 303",
    "addr:street":"Gazi Bulvari;Basmene",
    "iso:country":"TR",
    "sg:address":"Gazi Bulvari No:93/303",
    "sg:city":"Basmene",
    "sg:classifiers":[
        {
            "category":"Home & Garden",
            "subcategory":"Building Materials",
            "type":"Retail Goods"
        }
    ],
    "sg:phone":"+90 232 484 9355",
    "sg:province":"Izmir",
    "sg:tags":[
        "plaster",
        "cement-concrete"
    ],
    "wof:name":"Mer-cim Ltd.sti. Izmir Bolge Mudurlugu",
    "wof:placetype":"venue"
},
  "geometry": {"coordinates":[27.1423015594,38.4251480103],"type":"Point"}
}