{
  "type": "Feature",
  "properties": {
    "iso:country":"TR",
    "sg:address":"Pazar Cad. No:67/5",
    "sg:city":"Bandirma",
    "sg:classifiers":[
        {
            "category":"Home & Garden",
            "subcategory":"Garden Supply",
            "type":"Retail Goods"
        }
    ],
    "sg:phone":"+90 266 713 5126",
    "sg:postcode":"10200",
    "sg:province":"Balikesir",
    "sg:tags":[
        "fertilize",
        "soil"
    ],
    "wof:name":"Turkmen Tic.",
    "wof:placetype":"venue"
},
  "geometry": {"coordinates":[27.974067688,40.3544235229],"type":"Point"}
}