{
  "type": "Feature",
  "properties": {
    "iso:country":"TR",
    "sg:address":"Yeni Maltepe Yolu Emintas Akel San.sit.no:10/11",
    "sg:city":"Bayrampasa",
    "sg:classifiers":[
        {
            "category":"Utilities",
            "subcategory":"Cable",
            "type":"Services"
        }
    ],
    "sg:phone":"+90 212 501 7076",
    "sg:postcode":"36100",
    "sg:province":"Istanbul",
    "sg:tags":[
        "cardboard",
        "corrugate"
    ],
    "wof:name":"Pinar Amb.ltd.sti.",
    "wof:placetype":"venue"
},
  "geometry": {"coordinates":[28.9861831665,41.0408554077],"type":"Point"}
}