{
  "type": "Feature",
  "properties": {
    "iso:country":"TR",
    "sg:address":"K.pasa Mh.eski Ptt Sk.?aglayan Ismerk.no19 K3",
    "sg:city":"Izmit",
    "sg:classifiers":[
        {
            "category":"Freight",
            "type":"Transportation"
        }
    ],
    "sg:phone":"+90 262 331 2969",
    "sg:postcode":"41000",
    "sg:province":"Kocaeli",
    "sg:tags":[
        "agent",
        "shipping",
        "broker"
    ],
    "wof:name":"Ozne Denizcilik Ltd.sti.",
    "wof:placetype":"venue"
},
  "geometry": {"coordinates":[29.881521,40.853271],"type":"Point"}
}