{
  "type": "Feature",
  "properties": {
    "addr:full":"Tersane Cd. Kardesim Sk. Grifin Han K:3 No:20/21 Karak? Kabatas Istanbul 34427",
    "addr:housenumber":"3 no 20 / 21;?",
    "addr:postcode":"34427",
    "addr:street":"Tersane Cd. Kardesim Sk.;Karak",
    "iso:country":"TR",
    "sg:address":"Tersane Cd. Kardesim Sk. Grifin Han K:3 No:20/21 Karak?",
    "sg:city":"Kabatas",
    "sg:classifiers":[
        {
            "category":"Manufacturing",
            "subcategory":"Tools & Machinery",
            "type":"Manufacturing & Wholesale Goods"
        }
    ],
    "sg:phone":"+90 212 245 6371",
    "sg:postcode":"34427",
    "sg:province":"Istanbul",
    "sg:tags":[
        "machine",
        "industry"
    ],
    "wof:name":"Birlik Rulman Paz. Tic. San. Sti.",
    "wof:placetype":"venue"
},
  "geometry": {"coordinates":[28.9899768829,41.0330963135],"type":"Point"}
}