{
  "type": "Feature",
  "properties": {
    "iso:country":"TR",
    "sg:address":"Perpa Tic.merkezi B Blok No:1360 Okmeydani",
    "sg:city":"Karak?y",
    "sg:classifiers":[
        {
            "category":"Wholesale",
            "subcategory":"Machinery & Supplies",
            "type":"Manufacturing & Wholesale Goods"
        }
    ],
    "sg:phone":"+90 212 222 2810",
    "sg:postcode":"-",
    "sg:province":"Istanbul",
    "sg:tags":[
        "bearing",
        "ball"
    ],
    "wof:name":"Soylu Otomotiv Ve Rulman San.tic.ltd.sti.",
    "wof:placetype":"venue"
},
  "geometry": {"coordinates":[28.975925,41.012379],"type":"Point"}
}