{
  "type": "Feature",
  "properties": {
    "iso:country":"TR",
    "sg:address":"Telsiz Mah.asim Kazancigil Cad.no:8 Z.burnu",
    "sg:city":"Karatay",
    "sg:classifiers":[
        {
            "category":"Wholesale",
            "subcategory":"Auto Parts",
            "type":"Manufacturing & Wholesale Goods"
        }
    ],
    "sg:phone":"+90 212 510 9451",
    "sg:postcode":"42100",
    "sg:province":"Istanbul",
    "sg:tags":[
        "spare"
    ],
    "wof:name":"Isik Boya Paz.san.tic.ltd.sti.",
    "wof:placetype":"venue"
},
  "geometry": {"coordinates":[28.9861831665,41.0408554077],"type":"Point"}
}