{
  "type": "Feature",
  "properties": {
    "addr:full":"Mustafa Kurdoglu Cad. Baksav Sanayi Sitesi No:7 Beylikduzu Istanbul 34520",
    "addr:postcode":"34520",
    "addr:street":"Kurdoglu Cad. Baksav Sanayi Sitesi No 7 Beylikduzu",
    "iso:country":"TR",
    "sg:address":"Mustafa Kurdoglu Cad. Baksav Sanayi Sitesi No:7",
    "sg:city":"Beylikduzu",
    "sg:classifiers":[
        {
            "category":"Brewery",
            "type":"Food & Drink"
        }
    ],
    "sg:phone":"+90 212 875 4370",
    "sg:postcode":"34520",
    "sg:province":"Istanbul",
    "sg:tags":[
        "chewing",
        "gum"
    ],
    "wof:name":"Misbis Gida San. Ve Tic. A.s.",
    "wof:placetype":"venue"
},
  "geometry": {"coordinates":[28.9861831665,41.0408554077],"type":"Point"}
}