{
  "type": "Feature",
  "properties": {
    "iso:country":"TR",
    "sg:address":"Aydinlar Cd. Mumay Ish. No:1 D:4 Yeni Mh. Merkez",
    "sg:city":"Ke??en",
    "sg:classifiers":[
        {
            "category":"Organizations",
            "subcategory":"Membership Organization",
            "type":"Services"
        }
    ],
    "sg:phone":"+90 484 223 3040",
    "sg:province":"Siirt",
    "wof:name":"Siirt Genc Isadam. Dernegi",
    "wof:placetype":"venue"
},
  "geometry": {"coordinates":[41.9449539185,37.9304695129],"type":"Point"}
}