{
  "type": "Feature",
  "properties": {
    "iso:country":"TR",
    "sg:address":"Kemal Sakar",
    "sg:city":"Suhut",
    "sg:classifiers":[
        {
            "category":"Government",
            "subcategory":"Office",
            "type":"Public Place"
        }
    ],
    "sg:phone":"+90 272778769277",
    "sg:postcode":"03800",
    "sg:province":"Afyon",
    "sg:tags":[
        "municipality"
    ],
    "wof:name":"Karaca?en Belediye Baskani",
    "wof:placetype":"venue"
},
  "geometry": {"coordinates":[30.5297622681,38.7541923523],"type":"Point"}
}