{
  "type": "Feature",
  "properties": {
    "iso:country":"TR",
    "sg:address":"?amlitepe Sk. No:51 Siteler",
    "sg:city":"Mecidiyekoy",
    "sg:classifiers":[
        {
            "category":"Manufacturing",
            "subcategory":"Glass & Minerals",
            "type":"Manufacturing & Wholesale Goods"
        }
    ],
    "sg:phone":"+90 312 351 8699",
    "sg:postcode":"34387",
    "sg:province":"Ankara",
    "sg:tags":[
        "glassware"
    ],
    "wof:name":"?ztas Cam Ltd. Sti.",
    "wof:placetype":"venue"
},
  "geometry": {"coordinates":[29.1172008514,40.2046127319],"type":"Point"}
}