{
  "type": "Feature",
  "properties": {
    "addr:full":"4.gazeteciler Sit.no.22/a Levent \u00c7orlu Istanbul",
    "addr:housenumber":"a",
    "iso:country":"TR",
    "sg:address":"4.gazeteciler Sit.no.22/a Levent",
    "sg:city":"\u00c7orlu",
    "sg:classifiers":[
        {
            "category":"Shopping",
            "subcategory":"Luggage & Leather Goods",
            "type":"Retail Goods"
        }
    ],
    "sg:phone":"+90 212 269 7801",
    "sg:province":"Istanbul",
    "sg:tags":[
        "leather-fur",
        "wear"
    ],
    "wof:name":"Secondo Teks.san. A.s.",
    "wof:placetype":"venue"
},
  "geometry": {"coordinates":[29.0159626007,41.0816841125],"type":"Point"}
}