{
  "type": "Feature",
  "properties": {
    "addr:full":"Akdeniz Cad.no:6/6 Fatih Salipazari Istanbul 80040",
    "addr:housenumber":"6 / 6",
    "addr:postcode":"80040",
    "addr:street":"Fatih Salipazari",
    "iso:country":"TR",
    "sg:address":"Akdeniz Cad.no:6/6 Fatih",
    "sg:city":"Salipazari",
    "sg:classifiers":[
        {
            "category":"Building & Trades",
            "subcategory":"Construction",
            "type":"Services"
        }
    ],
    "sg:phone":"+90 212 534 4161",
    "sg:postcode":"80040",
    "sg:province":"Istanbul",
    "sg:tags":[
        "foundation"
    ],
    "wof:name":"Insan Egitimi Kultur Ve Yardimlasma Vakfi",
    "wof:placetype":"venue"
},
  "geometry": {"coordinates":[29.155046463,41.0859985352],"type":"Point"}
}