{
  "type": "Feature",
  "properties": {
    "iso:country":"TR",
    "sg:address":"Devlet Hastanesi Doktor Otoparki Yani",
    "sg:city":"Kocasinan",
    "sg:classifiers":[
        {
            "category":"Wholesale",
            "subcategory":"Medical Equipment & Supplies",
            "type":"Manufacturing & Wholesale Goods"
        }
    ],
    "sg:phone":"+90 454 212 4021",
    "sg:postcode":"38010",
    "sg:province":"Giresun",
    "sg:tags":[
        "material"
    ],
    "wof:name":"Cem Tibbi Malzeme",
    "wof:placetype":"venue"
},
  "geometry": {"coordinates":[38.384601593,40.9175300598],"type":"Point"}
}