{
  "type": "Feature",
  "properties": {
    "addr:full":"Kisik Sanayi Sit. (estim) Metal Isleri B???4.cad. No:123 Menderes Izmir 07170",
    "addr:housenumber":"? ? 4.cad no 123",
    "addr:postcode":"07170",
    "addr:street":"Kisik Sanayi Sit.",
    "iso:country":"TR",
    "sg:address":"Kisik Sanayi Sit. (estim) Metal Isleri B???4.cad. No:123",
    "sg:city":"Menderes",
    "sg:classifiers":[
        {
            "category":"Manufacturing",
            "subcategory":"Building Materials",
            "type":"Manufacturing & Wholesale Goods"
        }
    ],
    "sg:phone":"+90 232 257 5750",
    "sg:postcode":"07170",
    "sg:province":"Izmir",
    "sg:tags":[
        "lifts-elevators"
    ],
    "wof:name":"A.b.r. Asans?r Makina San.tic. Ltd.sti.",
    "wof:placetype":"venue"
},
  "geometry": {"coordinates":[27.1296863556,38.4186973572],"type":"Point"}
}