{
  "type": "Feature",
  "properties": {
    "addr:full":"Nesli Mah.narduzu Beldesi 31200 Iskenderun Hatay 31200",
    "addr:postcode":"31200;31200",
    "addr:street":"Beldesi",
    "iso:country":"TR",
    "sg:address":"Nesli Mah.narduzu Beldesi 31200",
    "sg:city":"Iskenderun",
    "sg:classifiers":[
        {
            "category":"Building & Trades",
            "subcategory":"Plumbing",
            "type":"Services"
        }
    ],
    "sg:phone":"+90 326 618 3019",
    "sg:postcode":"31200",
    "sg:province":"Hatay",
    "sg:tags":[
        "filter",
        "industry"
    ],
    "wof:name":"Onfil Filter",
    "wof:placetype":"venue"
},
  "geometry": {"coordinates":[36.349811554,36.4018478394],"type":"Point"}
}