{
  "type": "Feature",
  "properties": {
    "iso:country":"TR",
    "sg:address":"Egilmez Pasaji K: 2 B?y?k Cami Yani",
    "sg:city":"D?zce",
    "sg:classifiers":[
        {
            "category":"Travel",
            "subcategory":"Travel Agent",
            "type":"Entertainment"
        }
    ],
    "sg:phone":"+90 374 514 3820",
    "sg:province":"Bolu",
    "sg:tags":[
        "agency",
        "tourism"
    ],
    "wof:name":"?zbakir Turizm",
    "wof:placetype":"venue"
},
  "geometry": {"coordinates":[31.5552597046,40.5684394836],"type":"Point"}
}