{
  "type": "Feature",
  "properties": {
    "addr:full":"Abd?hak Hamit Cd. No:80/1 D:2-3 Taksim Istanbul 24040",
    "addr:housenumber":"no 80 / 1 d 2-3",
    "addr:postcode":"24040",
    "addr:street":"Cd.",
    "iso:country":"TR",
    "sg:address":"Abd?hak Hamit Cd. No:80/1 D:2-3",
    "sg:city":"Taksim",
    "sg:classifiers":[
        {
            "category":"Professional",
            "subcategory":"Engineering",
            "type":"Services"
        }
    ],
    "sg:phone":"+90 212 256 1119",
    "sg:postcode":"24040",
    "sg:province":"Istanbul",
    "sg:tags":[
        "architect"
    ],
    "wof:name":"Kent-tur M?hendis. Pazarlama A.s.",
    "wof:placetype":"venue"
},
  "geometry": {"coordinates":[28.9861831665,41.0408554077],"type":"Point"}
}