{
  "type": "Feature",
  "properties": {
    "addr:full":"Kurudere Cad. 4 Manisa 45300 45000",
    "addr:housenumber":"4",
    "addr:postcode":"45300 45000",
    "addr:street":"Kurudere Cad.;Manisa",
    "iso:country":"TR",
    "sg:address":"Kurudere Cad. 4",
    "sg:city":"Manisa",
    "sg:classifiers":[
        {
            "category":"Banks & Credit Unions",
            "subcategory":"Bank",
            "type":"Services"
        }
    ],
    "sg:phone":"+90 236 713 7250",
    "sg:postcode":"45000",
    "sg:province":"45300",
    "wof:name":"T?kiye T??c?er, Bankasi Yasarbank As",
    "wof:placetype":"venue"
},
  "geometry": {"coordinates":[28.860628,41.063217],"type":"Point"}
}