{
  "type": "Feature",
  "properties": {
    "addr:full":"Org. Deri Sanayi Bolgesi Yan. San. 14/5 Tuzla Iznik Istanbul 16860",
    "addr:housenumber":"14 / 5",
    "addr:postcode":"16860",
    "addr:street":"Yan. San.;Iznik",
    "iso:country":"TR",
    "sg:address":"Org. Deri Sanayi Bolgesi Yan. San. 14/5 Tuzla",
    "sg:city":"Iznik",
    "sg:classifiers":[
        {
            "category":"Manufacturing",
            "subcategory":"Leather Goods",
            "type":"Manufacturing & Wholesale Goods"
        }
    ],
    "sg:phone":"+90 216591003536",
    "sg:postcode":"16860",
    "sg:province":"Istanbul",
    "sg:tags":[
        "raw"
    ],
    "wof:name":"Deriland Dericilik San Ve Tic. Ltd.sti.",
    "wof:placetype":"venue"
},
  "geometry": {"coordinates":[28.9759254456,41.0123786926],"type":"Point"}
}