{
  "type": "Feature",
  "properties": {
    "addr:full":"Ataturk Cd. Adil Kanun Ish. K:4/13 Mersin I?el 52750",
    "addr:housenumber":"4 / 13",
    "addr:postcode":"? el 52750",
    "addr:street":"Ataturk Cd. Adil Kanun Ish. K",
    "iso:country":"TR",
    "sg:address":"Ataturk Cd. Adil Kanun Ish. K:4/13",
    "sg:city":"Mersin",
    "sg:orig_category":"Dryfood-dried Nuts",
    "sg:phone":"+90 324 232 0063",
    "sg:postcode":"52750",
    "sg:province":"I?el",
    "wof:name":"Agroexport Ith.ihr.ltd.sti.",
    "wof:placetype":"venue"
},
  "geometry": {"coordinates":[37.7128486633,41.0530204773],"type":"Point"}
}