{
  "type": "Feature",
  "properties": {
    "iso:country":"TR",
    "sg:address":"Marmaris",
    "sg:city":"Alsancak",
    "sg:classifiers":[
        {
            "category":"Recreation",
            "subcategory":"Boat Charter",
            "type":"Entertainment"
        }
    ],
    "sg:phone":"+90 252 412 3430",
    "sg:postcode":"01365",
    "sg:province":"Mugla",
    "sg:tags":[
        "yachting"
    ],
    "wof:name":"Top Leisure",
    "wof:placetype":"venue"
},
  "geometry": {"coordinates":[28.2583026886,36.8546791077],"type":"Point"}
}