{
  "type": "Feature",
  "properties": {
    "iso:country":"TR",
    "sg:address":"D-100 Karayolu Kargali Hanbaba Bp Karsisi",
    "sg:city":"Hendek",
    "sg:classifiers":[
        {
            "category":"Home & Garden",
            "subcategory":"Building Materials",
            "type":"Retail Goods"
        }
    ],
    "sg:phone":"+90 264 654 5105",
    "sg:postcode":"21950",
    "sg:province":"Sakarya",
    "sg:tags":[
        "stone",
        "natural",
        "marble"
    ],
    "wof:name":"Hendek Mermer San. Ve Tic. A.s.",
    "wof:placetype":"venue"
},
  "geometry": {"coordinates":[30.3791446686,40.7734336853],"type":"Point"}
}