{
  "type": "Feature",
  "properties": {
    "iso:country":"TR",
    "sg:address":"E. Edirne Asfalti No:120 Bayrampasa",
    "sg:city":"Kad\u0131k\u00f6y",
    "sg:classifiers":[
        {
            "category":"Building & Trades",
            "subcategory":"Plumbing",
            "type":"Services"
        }
    ],
    "sg:phone":"+90 212 563 5068",
    "sg:postcode":"34714",
    "sg:province":"Istanbul",
    "wof:name":"Tatarlilar Yapi Malzeme. San. Tic. A.s.",
    "wof:placetype":"venue"
},
  "geometry": {"coordinates":[28.8983840942,41.0664100647],"type":"Point"}
}