{
  "type": "Feature",
  "properties": {
    "addr:full":"Bah?lievler Mh. Mehmet?k Cd. Karanfil Sk. Ferit Apt. No:9 \u00dcsk\u00fcdar Balikesir",
    "addr:housenumber":"? k",
    "addr:street":"Lievler Mh. Mehmet;Cd. Karanfil Sk.",
    "iso:country":"TR",
    "sg:address":"Bah?lievler Mh. Mehmet?k Cd. Karanfil Sk. Ferit Apt. No:9",
    "sg:city":"\u00dcsk\u00fcdar",
    "sg:classifiers":[
        {
            "category":"Food & Beverages",
            "subcategory":"Dairy",
            "type":"Retail Goods"
        }
    ],
    "sg:phone":"+90 266 267 2146",
    "sg:province":"Balikesir",
    "sg:tags":[
        "pruducts",
        "milk"
    ],
    "wof:name":"Onurlu S?t San.",
    "wof:placetype":"venue"
},
  "geometry": {"coordinates":[27.8833007812,39.6520996094],"type":"Point"}
}