{
  "type": "Feature",
  "properties": {
    "addr:full":"1378 Sokak No 4/1 D105, Kordon Ishani Alsancak Izmir 35220",
    "addr:housenumber":"1 d105",
    "addr:postcode":"35220",
    "addr:street":"1378 Sokak No 4 /;Kordon Ishani",
    "iso:country":"TR",
    "sg:address":"1378 Sokak No 4/1 D105, Kordon Ishani Alsancak",
    "sg:city":"Izmir",
    "sg:classifiers":[
        {
            "category":"Travel",
            "subcategory":"Travel Agent",
            "type":"Entertainment"
        }
    ],
    "sg:phone":"+90 902 324 2195",
    "sg:province":"35220",
    "sg:website":"www.karavantravel.com",
    "wof:name":"Karavan",
    "wof:placetype":"venue"
},
  "geometry": {"coordinates":[27.1450805664,38.438419342],"type":"Point"}
}