{
  "type": "Feature",
  "properties": {
    "iso:country":"TR",
    "sg:address":"Organize San. Bolg.",
    "sg:city":"Baspinar",
    "sg:classifiers":[
        {
            "category":"Manufacturing",
            "subcategory":"Textiles",
            "type":"Manufacturing & Wholesale Goods"
        }
    ],
    "sg:phone":"+90 342 337 1792",
    "sg:postcode":"07800",
    "sg:province":"Gaziantep",
    "sg:tags":[
        "product"
    ],
    "wof:name":"Dort-er Tekstil Konfeksiyon A.s.",
    "wof:placetype":"venue"
},
  "geometry": {"coordinates":[37.3761024475,37.0629463196],"type":"Point"}
}