{
  "type": "Feature",
  "properties": {
    "iso:country":"TR",
    "sg:address":"2.tic .yol",
    "sg:city":"Beyazit",
    "sg:classifiers":[
        {
            "category":"Manufacturing",
            "subcategory":"Leather Goods",
            "type":"Manufacturing & Wholesale Goods"
        }
    ],
    "sg:phone":"+90 258 262 2235",
    "sg:postcode":"34490",
    "sg:province":"Denizli",
    "wof:name":"Gursoylar Deri",
    "wof:placetype":"venue"
},
  "geometry": {"coordinates":[29.0864906311,37.773525238],"type":"Point"}
}