{
  "type": "Feature",
  "properties": {
    "iso:country":"TR",
    "sg:address":"Ismet Inonu Cad. Basak Is Merkz. Kat:6 D:23",
    "sg:city":"Selcuklu",
    "sg:classifiers":[
        {
            "category":"Food & Beverages",
            "subcategory":"Candy",
            "type":"Retail Goods"
        }
    ],
    "sg:phone":"+90 222 236 0330",
    "sg:postcode":"32650",
    "sg:province":"Eskisehir",
    "sg:tags":[
        "biscuit-chocolate-candy"
    ],
    "wof:name":"Ozge Gida San. Ve Tic. Ltd.sti.",
    "wof:placetype":"venue"
},
  "geometry": {"coordinates":[30.517546,39.770081],"type":"Point"}
}