{
  "type": "Feature",
  "properties": {
    "addr:full":"Arabaci Alani Mah. Eski Kazimpasa Cad. No: 93 Serdivan 16020 Sakarya",
    "addr:housenumber":"93",
    "addr:postcode":"16020",
    "addr:street":"Alani Mah. Eski Kazimpasa Cad. No",
    "iso:country":"TR",
    "sg:address":"Arabaci Alani Mah. Eski Kazimpasa Cad. No: 93 Serdivan",
    "sg:city":"16020",
    "sg:classifiers":[
        {
            "category":"Wholesale",
            "subcategory":"Plants",
            "type":"Manufacturing & Wholesale Goods"
        }
    ],
    "sg:phone":"+90 264 277 7607",
    "sg:province":"Sakarya",
    "sg:tags":[
        "natural",
        "spice"
    ],
    "wof:name":"Ozyil Tuz Isletmeciligi Gida.nakl.mak.ins.san.tic.ltd.sti.",
    "wof:placetype":"venue"
},
  "geometry": {"coordinates":[30.359077,40.7635],"type":"Point"}
}