{
  "type": "Feature",
  "properties": {
    "addr:full":"Yunus Emre Cad. No: 108/a Hakimler Ilac Mad. Bandirma Eskisehir 10200",
    "addr:housenumber":"108 / a",
    "addr:postcode":"10200",
    "addr:street":"Yunus Emre Cad. No;Eskisehir",
    "iso:country":"TR",
    "sg:address":"Yunus Emre Cad. No: 108/a Hakimler Ilac Mad.",
    "sg:city":"Bandirma",
    "sg:classifiers":[
        {
            "category":"Farming",
            "subcategory":"Farm & Veterinary Services",
            "type":"Manufacturing & Wholesale Goods"
        }
    ],
    "sg:phone":"+90 2222334653233",
    "sg:postcode":"10200",
    "sg:province":"Eskisehir",
    "sg:tags":[
        "veterinarian"
    ],
    "wof:name":"Omer Kamisli",
    "wof:placetype":"venue"
},
  "geometry": {"coordinates":[30.5175457001,39.7700805664],"type":"Point"}
}