{
  "type": "Feature",
  "properties": {
    "addr:full":"Iskele Mah. Ova Mevkii Finike \u00dcmraniye Antalya",
    "addr:street":"Iskele Mah. Ova;Finike",
    "iso:country":"TR",
    "sg:address":"Iskele Mah. Ova Mevkii Finike",
    "sg:city":"\u00dcmraniye",
    "sg:classifiers":[
        {
            "category":"Manufacturing",
            "subcategory":"Rubber & Plastics",
            "type":"Manufacturing & Wholesale Goods"
        }
    ],
    "sg:phone":"+90 242 855 5601",
    "sg:province":"Antalya",
    "sg:tags":[
        "industry"
    ],
    "wof:name":"Kizilca Plastik San. Ins. Tarim Turizm Ve Tic. Ltd.sti.",
    "wof:placetype":"venue"
},
  "geometry": {"coordinates":[30.146320343,36.2954826355],"type":"Point"}
}