{
  "type": "Feature",
  "properties": {
    "iso:country":"TR",
    "sg:address":"Anadolu Mah. Ova Sok. No:30",
    "sg:city":"\u00dcmraniye",
    "sg:classifiers":[
        {
            "category":"Farming",
            "subcategory":"Fish & Marine Products",
            "type":"Manufacturing & Wholesale Goods"
        }
    ],
    "sg:phone":"+90 224 363 8328",
    "sg:postcode":"81260",
    "sg:province":"Bursa",
    "sg:tags":[
        "automotive"
    ],
    "wof:name":"Mirday Ticaret",
    "wof:placetype":"venue"
},
  "geometry": {"coordinates":[29.08934021,40.1954040527],"type":"Point"}
}