{
  "type": "Feature",
  "properties": {
    "addr:full":"Bayildim Cad. No:2 Macka Besiktas Istanbul 75200",
    "addr:postcode":"75200",
    "addr:street":"Bayildim Cad. No 2 Macka",
    "iso:country":"TR",
    "sg:address":"Bayildim Cad. No:2 Macka",
    "sg:city":"Besiktas",
    "sg:classifiers":[
        {
            "category":"Utilities",
            "subcategory":"Water",
            "type":"Services"
        }
    ],
    "sg:phone":"+90 212 326 1100",
    "sg:postcode":"75200",
    "sg:province":"Istanbul",
    "sg:tags":[
        "spring"
    ],
    "wof:name":"Swissotel The Bosphorus",
    "wof:placetype":"venue"
},
  "geometry": {"coordinates":[28.996778,41.044182],"type":"Point"}
}