{
  "type": "Feature",
  "properties": {
    "iso:country":"TR",
    "sg:address":"Kucuk Sanayi Sit.86.sok. No: 54-59 Esentepe",
    "sg:city":"Hasanpasa/kadik?",
    "sg:classifiers":[
        {
            "category":"Wholesale",
            "subcategory":"Medical Equipment & Supplies",
            "type":"Manufacturing & Wholesale Goods"
        }
    ],
    "sg:phone":"+90 352 240 3284",
    "sg:postcode":"34722",
    "sg:province":"Kayseri",
    "sg:tags":[
        "material"
    ],
    "wof:name":"Sms Medical Urun.san.ltd.sti.",
    "wof:placetype":"venue"
},
  "geometry": {"coordinates":[35.4891357422,38.7225761414],"type":"Point"}
}