{
  "type": "Feature",
  "properties": {
    "addr:full":"Im? 4. Blok No:4310 Unkapani Sisli Istanbul 81610",
    "addr:housenumber":"4 blok no 4310",
    "addr:postcode":"81610",
    "addr:street":"Im ?;Unkapani Sisli",
    "iso:country":"TR",
    "sg:address":"Im? 4. Blok No:4310 Unkapani",
    "sg:city":"Sisli",
    "sg:classifiers":[
        {
            "category":"Manufacturing",
            "subcategory":"Tools & Machinery",
            "type":"Manufacturing & Wholesale Goods"
        }
    ],
    "sg:phone":"+90 212 512 8833",
    "sg:postcode":"81610",
    "sg:province":"Istanbul",
    "sg:tags":[
        "machine",
        "industry"
    ],
    "wof:name":"Eltas Makina San. Tic. Ltd. Sti.",
    "wof:placetype":"venue"
},
  "geometry": {"coordinates":[28.9759254456,41.0123786926],"type":"Point"}
}