{
  "type": "Feature",
  "properties": {
    "iso:country":"TR",
    "sg:address":"K. Mahmut Pehlivan Cd. No:13/7",
    "sg:city":"Eregli",
    "sg:classifiers":[
        {
            "category":"Food & Beverages",
            "subcategory":"Dairy",
            "type":"Retail Goods"
        }
    ],
    "sg:phone":"+90 222 231 8000",
    "sg:postcode":"42310",
    "sg:province":"Eskisehir",
    "sg:tags":[
        "pruducts",
        "milk"
    ],
    "wof:name":"Kanat Gida San. Tic. Isletmeci. A.s.",
    "wof:placetype":"venue"
},
  "geometry": {"coordinates":[30.4680862427,39.7949295044],"type":"Point"}
}