{
  "type": "Feature",
  "properties": {
    "iso:country":"TR",
    "sg:address":"Sair Esref Bulvari No:50 K?t?park",
    "sg:city":"Nisantasi",
    "sg:classifiers":[
        {
            "category":"Organizations",
            "subcategory":"Professional Association",
            "type":"Services"
        }
    ],
    "sg:phone":"+90 232",
    "sg:postcode":"25370",
    "sg:province":"Izmir",
    "sg:tags":[
        "fair"
    ],
    "wof:name":"Izfas Izmir Fuarcilik Hizmetleri K?lt?r Ve Sanat Etkinlikleri A.s.",
    "wof:placetype":"venue"
},
  "geometry": {"coordinates":[27.170589447,38.3966903687],"type":"Point"}
}