{
  "type": "Feature",
  "properties": {
    "addr:full":"Onur Sk. No.64/3 Maltepe Ankara 01000",
    "addr:housenumber":"3",
    "addr:postcode":"01000",
    "addr:street":"Sk. No.64 /",
    "iso:country":"TR",
    "sg:address":"Onur Sk. No.64/3",
    "sg:city":"Maltepe",
    "sg:classifiers":[
        {
            "category":"Food & Beverages",
            "subcategory":"Dairy",
            "type":"Retail Goods"
        }
    ],
    "sg:phone":"+90 312 231 8924",
    "sg:postcode":"01000",
    "sg:province":"Ankara",
    "sg:tags":[
        "pruducts",
        "milk"
    ],
    "wof:name":"Agazade Dis Tic.ltd.sti.",
    "wof:placetype":"venue"
},
  "geometry": {"coordinates":[32.5852470398,39.9626274109],"type":"Point"}
}