{
  "type": "Feature",
  "properties": {
    "addr:full":"Karpuzlu Sk. No:7 Siteler Mersin Ankara 52750",
    "addr:postcode":"52750",
    "addr:street":"Karpuzlu Sk. No 7 Siteler",
    "iso:country":"TR",
    "sg:address":"Karpuzlu Sk. No:7 Siteler",
    "sg:city":"Mersin",
    "sg:classifiers":[
        {
            "category":"Manufacturing",
            "subcategory":"Metals",
            "type":"Manufacturing & Wholesale Goods"
        }
    ],
    "sg:phone":"+90 312 348 2984",
    "sg:postcode":"52750",
    "sg:province":"Ankara",
    "sg:tags":[
        "iron-steel",
        "peoducts"
    ],
    "wof:name":"?zy?n ?elik San. Tic. Ltd. Sti.",
    "wof:placetype":"venue"
},
  "geometry": {"coordinates":[29.1007862091,40.1826438904],"type":"Point"}
}