{
  "type": "Feature",
  "properties": {
    "addr:full":"Sisli Halaskargazi Caddesi No:369/1 Sisli Istanbul 65710",
    "addr:housenumber":"no;/ 1",
    "addr:postcode":"65710",
    "addr:street":"Halaskargazi Caddesi",
    "iso:country":"TR",
    "sg:address":"Sisli Halaskargazi Caddesi No:369/1",
    "sg:city":"Sisli",
    "sg:orig_category":"Beaty Parlors",
    "sg:phone":"+90 212 219 6406",
    "sg:postcode":"65710",
    "sg:province":"Istanbul",
    "wof:name":"Last Point",
    "wof:placetype":"venue"
},
  "geometry": {"coordinates":[28.987059,41.059063],"type":"Point"}
}