{
  "type": "Feature",
  "properties": {
    "iso:country":"TR",
    "sg:address":"Hisarpark Cad. No:12/9 Ulus",
    "sg:city":"Nisantasi",
    "sg:classifiers":[
        {
            "category":"Manufacturing",
            "subcategory":"Chemicals & Compounds",
            "type":"Manufacturing & Wholesale Goods"
        }
    ],
    "sg:phone":"+90 312 310 6066",
    "sg:postcode":"25370",
    "sg:province":"Ankara",
    "sg:tags":[
        "medicine"
    ],
    "wof:name":"Tek Kimyevi Lab. Mlz.",
    "wof:placetype":"venue"
},
  "geometry": {"coordinates":[32.8560333252,39.9438743591],"type":"Point"}
}