{
  "type": "Feature",
  "properties": {
    "addr:full":"S?er Mh. 30. Sk. No:26 Zeytinburnu Merkez Istanbul 07100",
    "addr:housenumber":"30;26",
    "addr:postcode":"?;07100",
    "addr:street":"S;Er Mh.;Sk. No",
    "iso:country":"TR",
    "sg:address":"S?er Mh. 30. Sk. No:26 Zeytinburnu",
    "sg:city":"Merkez",
    "sg:classifiers":[
        {
            "category":"Mining & Drilling",
            "type":"Manufacturing & Wholesale Goods"
        }
    ],
    "sg:phone":"+90 212 510 6310",
    "sg:postcode":"07100",
    "sg:province":"Istanbul",
    "sg:tags":[
        "industry",
        "mine"
    ],
    "wof:name":"Agaoglu Madencilik",
    "wof:placetype":"venue"
},
  "geometry": {"coordinates":[28.9759254456,41.0123786926],"type":"Point"}
}