{
  "type": "Feature",
  "properties": {
    "addr:full":"1.busan Ozel Organize Sanayi 6.sok. No:15 Ikitelli/K\u00fc\u00e7\u00fck\u00e7ekmece Konya 34660",
    "addr:housenumber":"6.sok no 15",
    "addr:postcode":"34660",
    "addr:street":"Organize Sanayi",
    "iso:country":"TR",
    "sg:address":"1.busan Ozel Organize Sanayi 6.sok. No:15",
    "sg:city":"Ikitelli/K\u00fc\u00e7\u00fck\u00e7ekmece",
    "sg:classifiers":[
        {
            "category":"Manufacturing",
            "subcategory":"Tools & Machinery",
            "type":"Manufacturing & Wholesale Goods"
        }
    ],
    "sg:phone":"+90 332 345 0838",
    "sg:postcode":"34660",
    "sg:province":"Konya",
    "sg:tags":[
        "machine",
        "industry"
    ],
    "wof:name":"I.m.c Mak. San.tic. Ltd.sti.",
    "wof:placetype":"venue"
},
  "geometry": {"coordinates":[32.4990272522,37.8715362549],"type":"Point"}
}