{
  "type": "Feature",
  "properties": {
    "addr:full":"Kokici Mevkii Patara Antalya",
    "addr:street":"Kokici Mevkii",
    "iso:country":"TR",
    "sg:address":"Kokici Mevkii",
    "sg:city":"Patara",
    "sg:classifiers":[
        {
            "category":"Travel",
            "subcategory":"Travel Agent",
            "type":"Entertainment"
        }
    ],
    "sg:phone":"+90 242 843 5308",
    "sg:province":"Antalya",
    "sg:tags":[
        "agency",
        "tourism"
    ],
    "wof:name":"Saint Nicholas Sey.acentasi",
    "wof:placetype":"venue"
},
  "geometry": {"coordinates":[30.6798324585,36.928150177],"type":"Point"}
}