{
  "type": "Feature",
  "properties": {
    "iso:country":"TR",
    "sg:address":"Talatpasa Caddesi Hayran Sok No:6",
    "sg:city":"G?tepe",
    "sg:classifiers":[
        {
            "category":"Wholesale",
            "subcategory":"Vending Machines",
            "type":"Manufacturing & Wholesale Goods"
        }
    ],
    "sg:phone":"+90 212 325 6832",
    "sg:province":"Istanbul",
    "sg:tags":[
        "packing"
    ],
    "wof:name":"?etin Makine Sanayii",
    "wof:placetype":"venue"
},
  "geometry": {"coordinates":[28.9916744232,41.0799942017],"type":"Point"}
}