{
  "type": "Feature",
  "properties": {
    "iso:country":"TR",
    "sg:address":"Ugur Mumcu Cad. 1597.sok. No:2",
    "sg:city":"Esenyurt",
    "sg:classifiers":[
        {
            "category":"Manufacturing",
            "subcategory":"Chemicals & Compounds",
            "type":"Manufacturing & Wholesale Goods"
        }
    ],
    "sg:phone":"+90 212 672 1818",
    "sg:postcode":"07800",
    "sg:province":"Istanbul",
    "sg:tags":[
        "agricultural"
    ],
    "wof:name":"Impa",
    "wof:placetype":"venue"
},
  "geometry": {"coordinates":[28.5792350769,41.0240020752],"type":"Point"}
}