{
  "type": "Feature",
  "properties": {
    "addr:full":"Y.mudanya Cad. Esenket Site A-4 Blok Ihsaniye- Nilufer Bursa 16370",
    "addr:housenumber":"esenket;a-4 blok ihsaniye",
    "addr:postcode":"16370",
    "addr:street":"Y.Mudanya Cad.;Bursa",
    "iso:country":"TR",
    "sg:address":"Y.mudanya Cad. Esenket Site A-4 Blok Ihsaniye-",
    "sg:city":"Nilufer",
    "sg:classifiers":[
        {
            "category":"Home & Garden",
            "subcategory":"Household Appliances",
            "type":"Retail Goods"
        }
    ],
    "sg:phone":"+90 224 247 3783",
    "sg:postcode":"16370",
    "sg:province":"Bursa",
    "sg:tags":[
        "conditioner",
        "air"
    ],
    "wof:name":"Isitet Ltd.sti.",
    "wof:placetype":"venue"
},
  "geometry": {"coordinates":[29.0580043793,40.1947555542],"type":"Point"}
}