{
  "type": "Feature",
  "properties": {
    "addr:full":"Tarsus Yolu Akdeniz Tugla Fb. Arkasi Bagcilar Beldesi Mersin I?el 52750",
    "addr:housenumber":"akdeniz",
    "addr:postcode":"? el 52750",
    "addr:street":"Tarsus Yolu;Fb. Arkasi Bagcilar Beldesi",
    "iso:country":"TR",
    "sg:address":"Tarsus Yolu Akdeniz Tugla Fb. Arkasi Bagcilar Beldesi",
    "sg:city":"Mersin",
    "sg:classifiers":[
        {
            "category":"Home & Garden",
            "subcategory":"Building Materials",
            "type":"Retail Goods"
        }
    ],
    "sg:phone":"+90 324 645 4304",
    "sg:postcode":"52750",
    "sg:province":"I?el",
    "sg:tags":[
        "window",
        "door",
        "plastic"
    ],
    "wof:name":"Akbulut Demir Ltd.sti.",
    "wof:placetype":"venue"
},
  "geometry": {"coordinates":[34.900100708,36.9201011658],"type":"Point"}
}