{
  "type": "Feature",
  "properties": {
    "addr:full":"Sumer Sok. 20/5 Kizilay Ankara 06440",
    "addr:housenumber":"20 / 5",
    "addr:postcode":"06440",
    "addr:street":"Sumer Sok.;Kizilay Ankara",
    "iso:country":"TR",
    "sg:address":"Sumer Sok. 20/5",
    "sg:city":"Kizilay",
    "sg:classifiers":[
        {
            "category":"Ice Cream",
            "type":"Food & Drink"
        }
    ],
    "sg:phone":"+90 312 231 3244",
    "sg:postcode":"06440",
    "sg:province":"Ankara",
    "sg:tags":[
        "sugar"
    ],
    "wof:name":"Anadolu Seker A.s.",
    "wof:placetype":"venue"
},
  "geometry": {"coordinates":[32.852757,39.924023],"type":"Point"}
}