{
  "type": "Feature",
  "properties": {
    "addr:full":"Kemalpasa Mah.adil Sok.no:16 Bayrampasa Istanbul 36100",
    "addr:housenumber":"16",
    "addr:postcode":"36100",
    "addr:street":"Sok.No;Istanbul",
    "iso:country":"TR",
    "sg:address":"Kemalpasa Mah.adil Sok.no:16",
    "sg:city":"Bayrampasa",
    "sg:classifiers":[
        {
            "category":"Shopping",
            "subcategory":"Baby Store",
            "type":"Retail Goods"
        }
    ],
    "sg:phone":"+90 212 526 4947",
    "sg:postcode":"36100",
    "sg:province":"Istanbul",
    "sg:tags":[
        "wear"
    ],
    "wof:name":"Aydin Bebe Giyim",
    "wof:placetype":"venue"
},
  "geometry": {"coordinates":[28.794807,41.002342],"type":"Point"}
}