{
  "type": "Feature",
  "properties": {
    "iso:country":"TR",
    "sg:address":"Ankara Asfalti K?ek? Mevkii Pk:319 41135 Izmit",
    "sg:city":"Seyhan",
    "sg:classifiers":[
        {
            "category":"Manufacturing",
            "subcategory":"Chemicals & Compounds",
            "type":"Manufacturing & Wholesale Goods"
        }
    ],
    "sg:phone":"+90 262 321 1958",
    "sg:postcode":"01120",
    "sg:province":"Kocaeli",
    "sg:tags":[
        "pharmaceutical"
    ],
    "wof:name":"Depa Ilac Aktif Maddeleri San.ve Pazarlama A.s.",
    "wof:placetype":"venue"
},
  "geometry": {"coordinates":[29.881521225,40.8532714844],"type":"Point"}
}