{
  "type": "Feature",
  "properties": {
    "addr:full":"Sanayi Sitesi Ptt Sk.24/a Kad\u0131k\u00f6y Diyarbakir",
    "addr:housenumber":"sk.24 / a",
    "addr:street":"Sanayi Sitesi Ptt;Diyarbakir",
    "iso:country":"TR",
    "sg:address":"Sanayi Sitesi Ptt Sk.24/a",
    "sg:city":"Kad\u0131k\u00f6y",
    "sg:classifiers":[
        {
            "category":"Home & Garden",
            "subcategory":"Kitchen Supply",
            "type":"Retail Goods"
        }
    ],
    "sg:phone":"+90 412 237 9583",
    "sg:province":"Diyarbakir",
    "sg:tags":[
        "wardrobe"
    ],
    "wof:name":"Kardesler Mobilya Ins.tic.ltd.sti",
    "wof:placetype":"venue"
},
  "geometry": {"coordinates":[40.2253341675,37.9158096313],"type":"Point"}
}