{
  "type": "Feature",
  "properties": {
    "iso:country":"TR",
    "sg:address":"Cumra",
    "sg:city":"?demis",
    "sg:classifiers":[
        {
            "category":"Manufacturing",
            "subcategory":"Chemicals & Compounds",
            "type":"Manufacturing & Wholesale Goods"
        }
    ],
    "sg:phone":"+90 332 447 8036",
    "sg:province":"Konya",
    "sg:tags":[
        "agricultural"
    ],
    "wof:name":"Yalcinlar 2000 Ltd.sti.",
    "wof:placetype":"venue"
},
  "geometry": {"coordinates":[32.7801017761,37.5735015869],"type":"Point"}
}