{
  "type": "Feature",
  "properties": {
    "iso:country":"TR",
    "sg:address":"Ahmet Pasa Mah. Bursali Tahir Cad. No:1",
    "sg:city":"Isikkent",
    "sg:classifiers":[
        {
            "category":"Wholesale",
            "subcategory":"Plants",
            "type":"Manufacturing & Wholesale Goods"
        }
    ],
    "sg:phone":"+90 224 220 6424",
    "sg:postcode":"32100",
    "sg:province":"Bursa",
    "sg:tags":[
        "natural",
        "spice"
    ],
    "wof:name":"Ekol Otomotiv Ve Baharat Sanayi",
    "wof:placetype":"venue"
},
  "geometry": {"coordinates":[29.058531,40.203575],"type":"Point"}
}