{
  "type": "Feature",
  "properties": {
    "iso:country":"TR",
    "sg:address":"Sair Fuzuli Cd. Istiklal Mh. No:44",
    "sg:city":"Nil?fer",
    "sg:classifiers":[
        {
            "category":"Home & Garden",
            "subcategory":"Kitchen Supply",
            "type":"Retail Goods"
        }
    ],
    "sg:phone":"+90 222 234 3159",
    "sg:postcode":"19285",
    "sg:province":"Eskisehir",
    "sg:tags":[
        "steel",
        "utensil"
    ],
    "wof:name":"Alpes End?stri Elektrik Teks. San. Tic. A.s.",
    "wof:placetype":"venue"
},
  "geometry": {"coordinates":[30.515648,39.775322],"type":"Point"}
}