{
  "type": "Feature",
  "properties": {
    "addr:full":"Caglayan, Vatan Cad. Aktas Is Merkezi, No.110/10 Kagithane Istanbul 34406",
    "addr:housenumber":"no.110 / 10",
    "addr:postcode":"34406",
    "addr:street":"Vatan Cad.;Istanbul",
    "iso:country":"TR",
    "sg:address":"Caglayan, Vatan Cad. Aktas Is Merkezi, No.110/10",
    "sg:city":"Kagithane",
    "sg:orig_category":"Technic Textile",
    "sg:phone":"+90 212 296 1790",
    "sg:postcode":"34406",
    "sg:province":"Istanbul",
    "wof:name":"Klavuz Reklam Hizmetleri Ltd.sti.",
    "wof:placetype":"venue"
},
  "geometry": {"coordinates":[28.9861831665,41.0408554077],"type":"Point"}
}