{
  "type": "Feature",
  "properties": {
    "iso:country":"TR",
    "sg:address":"Samsun",
    "sg:city":"Karabaglar",
    "sg:classifiers":[
        {
            "category":"Government",
            "subcategory":"Office",
            "type":"Public Place"
        }
    ],
    "sg:phone":"+90 362 440 2847",
    "sg:postcode":"44210",
    "sg:province":"Samsun",
    "sg:tags":[
        "army"
    ],
    "wof:name":"Samsun (tekkek?y) Askerlik Subesi",
    "wof:placetype":"venue"
},
  "geometry": {"coordinates":[36.3381233215,41.2815742493],"type":"Point"}
}