{
  "type": "Feature",
  "properties": {
    "addr:full":"6 Sk. No:5 Pinarbasi Izmir 07630",
    "addr:housenumber":"6",
    "addr:postcode":"07630",
    "addr:street":"Sk. No 5 Pinarbasi",
    "iso:country":"TR",
    "sg:address":"6 Sk. No:5",
    "sg:city":"Pinarbasi",
    "sg:orig_category":"Muhtarliklar",
    "sg:phone":"+90 232 479 5896",
    "sg:postcode":"07630",
    "sg:province":"Izmir",
    "wof:name":"G?pinar Mahallesi Muhtar: Mustafa Tatis",
    "wof:placetype":"venue"
},
  "geometry": {"coordinates":[27.1671619415,38.2957839966],"type":"Point"}
}