{
  "type": "Feature",
  "properties": {
    "iso:country":"TR",
    "sg:address":"Aymakoop Sitesi C 7 Blok No:115",
    "sg:city":"Ikitelli",
    "sg:classifiers":[
        {
            "category":"Shopping",
            "subcategory":"Crafts & Fabrics",
            "type":"Retail Goods"
        }
    ],
    "sg:phone":"+90 212 549 9506",
    "sg:postcode":"34306",
    "sg:province":"Istanbul",
    "sg:tags":[
        "yarn"
    ],
    "wof:name":"Muteks Tekstil Sanayi Ve Ticaret",
    "wof:placetype":"venue"
},
  "geometry": {"coordinates":[28.7984962463,41.0884017944],"type":"Point"}
}