{
  "type": "Feature",
  "properties": {
    "iso:country":"TR",
    "sg:address":"Izmir Cad. Necip Bey Apt. 22/6-7 Kizilay",
    "sg:city":"Fatih",
    "sg:classifiers":[
        {
            "category":"Organizations",
            "subcategory":"Membership Organization",
            "type":"Services"
        }
    ],
    "sg:phone":"+90 312 419 5170",
    "sg:postcode":"01740",
    "sg:province":"Ankara",
    "wof:name":"Denetde (devlet Denetim Elemanlari Dernegi)",
    "wof:placetype":"venue"
},
  "geometry": {"coordinates":[32.8604812622,39.9429283142],"type":"Point"}
}