{
  "type": "Feature",
  "properties": {
    "iso:country":"TR",
    "sg:address":"Cahit Zarf Oglu Cad. Nno:40/a",
    "sg:city":"Kizilay",
    "sg:classifiers":[
        {
            "category":"Shopping",
            "subcategory":"Clothing, Apparel, & Fashions",
            "type":"Retail Goods"
        }
    ],
    "sg:phone":"+90 344 223 8583",
    "sg:postcode":"23050",
    "sg:province":"Kahramanmaras",
    "sg:tags":[
        "house"
    ],
    "wof:name":"?z Izgi Tekstil",
    "wof:placetype":"venue"
},
  "geometry": {"coordinates":[36.9294624329,37.5721588135],"type":"Point"}
}