{
  "type": "Feature",
  "properties": {
    "addr:full":"Nursatiye Mh. Hastene Cd.hamdi Olgun Ish. K:6 Turuncova I?el 07880",
    "addr:housenumber":"6;?",
    "addr:postcode":"07880",
    "addr:street":"Nursatiye Mh. Hastene Cd.Hamdi Olgun Ish. K;I;El",
    "iso:country":"TR",
    "sg:address":"Nursatiye Mh. Hastene Cd.hamdi Olgun Ish. K:6",
    "sg:city":"Turuncova",
    "sg:classifiers":[
        {
            "category":"Food & Beverages",
            "subcategory":"Fruits & Vegetables",
            "type":"Retail Goods"
        }
    ],
    "sg:phone":"+90 324 233 4350",
    "sg:postcode":"07880",
    "sg:province":"I?el",
    "sg:tags":[
        "fresh"
    ],
    "wof:name":"Sec Ltd. Sti",
    "wof:placetype":"venue"
},
  "geometry": {"coordinates":[30.1224193573,36.3515396118],"type":"Point"}
}