{
  "type": "Feature",
  "properties": {
    "iso:country":"TR",
    "sg:address":"Ahi Evren Cad.maslak Polaris Plaza No:1 Kat:8 D:39 Maslak",
    "sg:city":"Alsancak",
    "sg:classifiers":[
        {
            "category":"Government",
            "subcategory":"Office",
            "type":"Public Place"
        }
    ],
    "sg:phone":"+90 2123460260729",
    "sg:postcode":"35220",
    "sg:province":"Istanbul",
    "sg:tags":[
        "patent",
        "mark"
    ],
    "wof:name":"Destek Patent Ltd.sti.",
    "wof:placetype":"venue"
},
  "geometry": {"coordinates":[28.9861831665,41.0408554077],"type":"Point"}
}