{
  "type": "Feature",
  "properties": {
    "addr:full":"Sahrayi Cedid Ataturk Cad.atakilic Apt. No: 36 K: 4 D:18/b Kadikoy Emin?? 34280 Istanbul",
    "addr:housenumber":"4 d 18 / b;? ?",
    "addr:postcode":"34280",
    "addr:street":"K;Kadikoy Emin",
    "iso:country":"TR",
    "sg:address":"Sahrayi Cedid Ataturk Cad.atakilic Apt. No: 36 K: 4 D:18/b Kadikoy",
    "sg:city":"Emin?? 34280",
    "sg:classifiers":[
        {
            "category":"Manufacturing",
            "subcategory":"Building Materials",
            "type":"Manufacturing & Wholesale Goods"
        }
    ],
    "sg:phone":"+90 216 363 9763",
    "sg:province":"Istanbul",
    "sg:tags":[
        "promotional"
    ],
    "wof:name":"Proteks",
    "wof:placetype":"venue"
},
  "geometry": {"coordinates":[29.087726593,40.9811820984],"type":"Point"}
}