{
  "type": "Feature",
  "properties": {
    "iso:country":"TR",
    "sg:address":"Kayhan 3509 Sk. No.33",
    "sg:city":"Gumusler",
    "sg:classifiers":[
        {
            "category":"Shopping",
            "subcategory":"Crafts & Fabrics",
            "type":"Retail Goods"
        }
    ],
    "sg:phone":"+90 258 266 0012",
    "sg:postcode":"20085",
    "sg:province":"Denizli",
    "sg:tags":[
        "weaving"
    ],
    "wof:name":"Kayteks Kadife Ltd.sti.",
    "wof:placetype":"venue"
},
  "geometry": {"coordinates":[29.0932693481,37.7962875366],"type":"Point"}
}