{
  "type": "Feature",
  "properties": {
    "addr:full":"Sogutlu Cesme Cad. No:20 Kadikoy Istanbul 01370",
    "addr:housenumber":"20",
    "addr:postcode":"01370",
    "addr:street":"Cesme Cad. No",
    "iso:country":"TR",
    "sg:address":"Sogutlu Cesme Cad. No:20",
    "sg:city":"Kadikoy",
    "sg:classifiers":[
        {
            "category":"Food & Beverages",
            "subcategory":"Groceries & Convenience Stores",
            "type":"Retail Goods"
        }
    ],
    "sg:phone":"+90 216 349 2317",
    "sg:postcode":"01370",
    "sg:province":"Istanbul",
    "sg:tags":[
        "ready"
    ],
    "wof:name":"Kervansaray Nak.rest. Isl.san.tic.ltd. Sti.",
    "wof:placetype":"venue"
},
  "geometry": {"coordinates":[29.0294380188,40.990688324],"type":"Point"}
}