{
  "type": "Feature",
  "properties": {
    "iso:country":"TR",
    "sg:address":"Celebi Hamami Sok. No:10 Kaptan Han",
    "sg:city":"Findikli",
    "sg:classifiers":[
        {
            "category":"Freight",
            "type":"Transportation"
        }
    ],
    "sg:phone":"+90 212245231314",
    "sg:postcode":"01470",
    "sg:province":"Istanbul",
    "sg:tags":[
        "agent",
        "shipping",
        "broker"
    ],
    "wof:name":"Bebek Yachting & Marimite Agency",
    "wof:placetype":"venue"
},
  "geometry": {"coordinates":[28.988731,41.047634],"type":"Point"}
}