{
  "type": "Feature",
  "properties": {
    "addr:full":"Gaziosmanpasa Bulv.no.3 Kat.1 Daire.102 ?ankaya Maltepe Izmir 01000",
    "addr:postcode":"01000",
    "addr:street":"Ankaya Maltepe",
    "iso:country":"TR",
    "sg:address":"Gaziosmanpasa Bulv.no.3 Kat.1 Daire.102 ?ankaya",
    "sg:city":"Maltepe",
    "sg:classifiers":[
        {
            "category":"Manufacturing",
            "subcategory":"Metals",
            "type":"Manufacturing & Wholesale Goods"
        }
    ],
    "sg:phone":"+90 232 484 4466",
    "sg:postcode":"01000",
    "sg:province":"Izmir",
    "sg:tags":[
        "industry"
    ],
    "wof:name":"Mervetur Turizm Insaat Mobilya San.tic.ltd.sti.",
    "wof:placetype":"venue"
},
  "geometry": {"coordinates":[27.1296863556,38.4186973572],"type":"Point"}
}