{
  "type": "Feature",
  "properties": {
    "addr:full":"G?r? Meyd. Cd. 101 Sk. Atako Apt. No:3 Sirinyer I?el 35140",
    "addr:housenumber":"101;?",
    "addr:postcode":"35140",
    "addr:street":"Meyd. Cd.;Sk. Atako Apt. No 3 Sirinyer I;El",
    "iso:country":"TR",
    "sg:address":"G?r? Meyd. Cd. 101 Sk. Atako Apt. No:3",
    "sg:city":"Sirinyer",
    "sg:classifiers":[
        {
            "category":"Organizations",
            "subcategory":"Membership Organization",
            "type":"Services"
        }
    ],
    "sg:phone":"+90 324 231 4217",
    "sg:postcode":"35140",
    "sg:province":"I?el",
    "wof:name":"Mersin Kultur Merk. Dernegi",
    "wof:placetype":"venue"
},
  "geometry": {"coordinates":[27.145980835,38.4284286499],"type":"Point"}
}