{
  "type": "Feature",
  "properties": {
    "addr:full":"Yildiz Posta Cd. No:35/a Esentepe \u00dcmraniye Istanbul",
    "addr:housenumber":"no 35 / a",
    "addr:street":"Posta Cd.;Esentepe",
    "iso:country":"TR",
    "sg:address":"Yildiz Posta Cd. No:35/a Esentepe",
    "sg:city":"\u00dcmraniye",
    "sg:classifiers":[
        {
            "category":"Farming",
            "subcategory":"Fish & Marine Products",
            "type":"Manufacturing & Wholesale Goods"
        }
    ],
    "sg:phone":"+90 212 272 3628",
    "sg:province":"Istanbul",
    "sg:tags":[
        "automotive"
    ],
    "wof:name":"Dumar Oto Mam?l. Pazarlama Tic. A.s.",
    "wof:placetype":"venue"
},
  "geometry": {"coordinates":[29.0089225769,41.0653114319],"type":"Point"}
}