{
  "type": "Feature",
  "properties": {
    "addr:full":"??lek? ?ukuru No:19 Merdivenk? Mecidiyekoy Istanbul 34387",
    "addr:housenumber":"? ?;? ?;19;?",
    "addr:postcode":"34387",
    "addr:street":"Lek;Ukuru No;Mecidiyekoy Istanbul",
    "iso:country":"TR",
    "sg:address":"??lek? ?ukuru No:19 Merdivenk?",
    "sg:city":"Mecidiyekoy",
    "sg:classifiers":[
        {
            "category":"Manufacturing",
            "subcategory":"Glass & Minerals",
            "type":"Manufacturing & Wholesale Goods"
        }
    ],
    "sg:phone":"+90 216 369 6673",
    "sg:postcode":"34387",
    "sg:province":"Istanbul",
    "sg:tags":[
        "glassware"
    ],
    "wof:name":"?zler Cam Tic. A.s.",
    "wof:placetype":"venue"
},
  "geometry": {"coordinates":[28.9921588898,41.0720214844],"type":"Point"}
}