{
  "type": "Feature",
  "properties": {
    "addr:full":"4. Gazeteciler Sit. A 5 Blok D:3 Besiktas Ey\u00fcp Istanbul 34050",
    "addr:housenumber":"4;5;3",
    "addr:postcode":"34050",
    "addr:street":"Gazeteciler Sit. A;Blok D",
    "iso:country":"TR",
    "sg:address":"4. Gazeteciler Sit. A 5 Blok D:3 Besiktas",
    "sg:city":"Ey\u00fcp",
    "sg:classifiers":[
        {
            "category":"Organizations",
            "subcategory":"Membership Organization",
            "type":"Services"
        }
    ],
    "sg:phone":"+90 212 280 4592",
    "sg:postcode":"34050",
    "sg:province":"Istanbul",
    "wof:name":"Istanbul Motor Spor. Kulubu Dernegi",
    "wof:placetype":"venue"
},
  "geometry": {"coordinates":[28.910326004,41.049079895],"type":"Point"}
}