{
  "type": "Feature",
  "properties": {
    "addr:full":"Gen?lik Mah. Fevzi ?akmak Cad. No: 12/4 Levent Antalya 01310",
    "addr:housenumber":"?;12 / 4",
    "addr:postcode":"01310",
    "addr:street":"Gen ?;Fevzi;Akmak Cad. No",
    "iso:country":"TR",
    "sg:address":"Gen?lik Mah. Fevzi ?akmak Cad. No: 12/4",
    "sg:city":"Levent",
    "sg:classifiers":[
        {
            "category":"Travel",
            "subcategory":"Travel Agent",
            "type":"Entertainment"
        }
    ],
    "sg:phone":"+90 242 281 0114",
    "sg:postcode":"01310",
    "sg:province":"Antalya",
    "sg:tags":[
        "agency",
        "tourism"
    ],
    "wof:name":"Allegro Turizm San. Ve Tic. A.s.(antalya Sb.)",
    "wof:placetype":"venue"
},
  "geometry": {"coordinates":[30.7092056274,36.8790512085],"type":"Point"}
}