{
  "type": "Feature",
  "properties": {
    "addr:full":"Kanatli Cd. No:65/2 Antakya Hatay 31000",
    "addr:housenumber":"no 65 / 2",
    "addr:postcode":"31000",
    "addr:street":"Kanatli Cd.",
    "iso:country":"TR",
    "sg:address":"Kanatli Cd. No:65/2",
    "sg:city":"Antakya",
    "sg:classifiers":[
        {
            "category":"Home & Garden",
            "subcategory":"Kitchen Supply",
            "type":"Retail Goods"
        }
    ],
    "sg:phone":"+90 326 215 7839",
    "sg:postcode":"31000",
    "sg:province":"Hatay",
    "sg:tags":[
        "wardrobe"
    ],
    "wof:name":"Us Kardesler",
    "wof:placetype":"venue"
},
  "geometry": {"coordinates":[36.1615371704,36.2030143738],"type":"Point"}
}