{
  "type": "Feature",
  "properties": {
    "iso:country":"TR",
    "sg:address":"?ayir Sokak 20, Altinkumi",
    "sg:city":"Didim",
    "sg:orig_category":"Hotels: Motels",
    "sg:phone":"+90 256 813 1373",
    "sg:province":"Aydin",
    "wof:name":"Agais Pansiyon",
    "wof:placetype":"venue"
},
  "geometry": {"coordinates":[27.9407291412,37.7271881104],"type":"Point"}
}