{
  "type": "Feature",
  "properties": {
    "addr:full":"Organize San. B?gesi 2. Kisim Mersin Manisa 52750",
    "addr:housenumber":"2",
    "addr:postcode":"52750",
    "addr:street":"Organize;Gesi",
    "iso:country":"TR",
    "sg:address":"Organize San. B?gesi 2. Kisim",
    "sg:city":"Mersin",
    "sg:classifiers":[
        {
            "category":"Freight",
            "type":"Transportation"
        }
    ],
    "sg:phone":"+90 236 233 7449",
    "sg:postcode":"52750",
    "sg:province":"Manisa",
    "sg:tags":[
        "packing",
        "industry"
    ],
    "wof:name":"Petpak Ambalaj Sanayi Ticaret A.s",
    "wof:placetype":"venue"
},
  "geometry": {"coordinates":[27.4297008514,38.6222000122],"type":"Point"}
}