{
  "type": "Feature",
  "properties": {
    "addr:full":"Ulas Isiklar Mevkii ?rlu Tekirdag Ulas Tekirdag 33400",
    "addr:postcode":"33400",
    "addr:street":"Isiklar Mevkii ? Rlu;Ulas",
    "iso:country":"TR",
    "sg:address":"Ulas Isiklar Mevkii ?rlu Tekirdag",
    "sg:city":"Ulas",
    "sg:classifiers":[
        {
            "category":"Communications",
            "subcategory":"Film & Video Production",
            "type":"Services"
        }
    ],
    "sg:phone":"+90 282 655 6664",
    "sg:postcode":"33400",
    "sg:province":"Tekirdag",
    "sg:tags":[
        "packing",
        "material"
    ],
    "wof:name":"Rumeli Ambalaj Nakliye Ve Makine San.tic.ltd.sti.",
    "wof:placetype":"venue"
},
  "geometry": {"coordinates":[27.5144004822,40.9791984558],"type":"Point"}
}