{
  "type": "Feature",
  "properties": {
    "addr:full":"Gazi Bulv. No:3 \u00c7orlu Aydin",
    "addr:street":"Gazi Bulv. No 3 C\u0327Orlu Aydin",
    "iso:country":"TR",
    "sg:address":"Gazi Bulv. No:3",
    "sg:city":"\u00c7orlu",
    "sg:classifiers":[
        {
            "category":"Shopping",
            "subcategory":"Luggage & Leather Goods",
            "type":"Retail Goods"
        }
    ],
    "sg:phone":"+90 256 225 6635",
    "sg:province":"Aydin",
    "sg:tags":[
        "leather-fur",
        "wear"
    ],
    "wof:name":"Tavaslilar Deri San. Tic. Ltd. Sti.",
    "wof:placetype":"venue"
},
  "geometry": {"coordinates":[27.8441314697,37.8499946594],"type":"Point"}
}