{
  "type": "Feature",
  "properties": {
    "iso:country":"TR",
    "sg:address":"1420. Sk. No:106/1",
    "sg:city":"Alsancak",
    "sg:classifiers":[
        {
            "category":"Shopping",
            "subcategory":"Optical Goods",
            "type":"Retail Goods"
        }
    ],
    "sg:phone":"+90 232 421 0220",
    "sg:postcode":"01365",
    "sg:province":"Izmir",
    "sg:tags":[
        "material"
    ],
    "wof:name":"Mediko-lens Tip Mlz.",
    "wof:placetype":"venue"
},
  "geometry": {"coordinates":[27.1492576599,38.4341468811],"type":"Point"}
}