{
  "type": "Feature",
  "properties": {
    "iso:country":"TR",
    "sg:address":"899 Sk. No.30 K.5/507",
    "sg:city":"Silivri",
    "sg:classifiers":[
        {
            "category":"Wholesale",
            "subcategory":"Farm Supplies",
            "type":"Manufacturing & Wholesale Goods"
        }
    ],
    "sg:phone":"+90 232 484 2824",
    "sg:postcode":"34570",
    "sg:province":"Izmir",
    "sg:tags":[
        "feed",
        "industry"
    ],
    "wof:name":"Anadolu Yem San. Ltd.sti.",
    "wof:placetype":"venue"
},
  "geometry": {"coordinates":[27.1329708099,38.4223899841],"type":"Point"}
}