{
  "type": "Feature",
  "properties": {
    "addr:full":"Alemdag Cd. No:428 ?mraniye Merkez Istanbul 55020",
    "addr:housenumber":"no;?",
    "addr:postcode":"55020",
    "addr:street":"Alemdag Cd.;Mraniye",
    "iso:country":"TR",
    "sg:address":"Alemdag Cd. No:428 ?mraniye",
    "sg:city":"Merkez",
    "sg:classifiers":[
        {
            "category":"Manufacturing",
            "subcategory":"Wood Products",
            "type":"Manufacturing & Wholesale Goods"
        }
    ],
    "sg:phone":"+90 216 335 9518",
    "sg:postcode":"55020",
    "sg:province":"Istanbul",
    "sg:tags":[
        "forest"
    ],
    "wof:name":"Sanlioglu Orman ?r?n. Insaat Malzeme. San. Ltd.",
    "wof:placetype":"venue"
},
  "geometry": {"coordinates":[29.1885261536,41.0055923462],"type":"Point"}
}