{
  "type": "Feature",
  "properties": {
    "iso:country":"TR",
    "sg:address":"Otosan Sit. 37. Bulv. No:2 Yildirim",
    "sg:city":"Merkez",
    "sg:classifiers":[
        {
            "category":"Wholesale",
            "subcategory":"Vending Machines",
            "type":"Manufacturing & Wholesale Goods"
        }
    ],
    "sg:phone":"+90 224 346 0296",
    "sg:postcode":"58070",
    "sg:province":"Bursa",
    "sg:tags":[
        "rod",
        "welding"
    ],
    "wof:name":"Remak Muhendislik",
    "wof:placetype":"venue"
},
  "geometry": {"coordinates":[29.0580043793,40.1947555542],"type":"Point"}
}