{
  "type": "Feature",
  "properties": {
    "addr:full":"Gursel Mah Dunur Sokak No:2 80360 Kagithane Istanbul Sariyer Istanbul 33740",
    "addr:postcode":"80360;33740",
    "addr:street":"Gursel Mah Dunur Sokak No 2",
    "iso:country":"TR",
    "sg:address":"Gursel Mah Dunur Sokak No:2 80360 Kagithane Istanbul",
    "sg:city":"Sariyer",
    "sg:orig_category":"Miscellaneous Products",
    "sg:phone":"+90 212 210 2848",
    "sg:postcode":"33740",
    "sg:province":"Istanbul",
    "wof:name":"Pirint Komputer Dis Tic Sanltd Sti",
    "wof:placetype":"venue"
},
  "geometry": {"coordinates":[28.9690933228,41.0664482117],"type":"Point"}
}