{
  "type": "Feature",
  "properties": {
    "addr:full":"Org. San. B?g. Haseyad Koop. No:112 Ikitelli Beylikd?? 34905 Istanbul",
    "addr:postcode":"34905",
    "addr:street":"Org.",
    "iso:country":"TR",
    "sg:address":"Org. San. B?g. Haseyad Koop. No:112 Ikitelli",
    "sg:city":"Beylikd?? 34905",
    "sg:classifiers":[
        {
            "category":"Manufacturing",
            "subcategory":"Tools & Machinery",
            "type":"Manufacturing & Wholesale Goods"
        }
    ],
    "sg:phone":"+90 212 549 2703",
    "sg:province":"Istanbul",
    "sg:tags":[
        "machine",
        "industry"
    ],
    "wof:name":"Eae Electronics",
    "wof:placetype":"venue"
},
  "geometry": {"coordinates":[28.9759254456,41.0123786926],"type":"Point"}
}