{
  "type": "Feature",
  "properties": {
    "iso:country":"TR",
    "sg:address":"Dumlupinar Mah.s.g?cer Cad.32/a Oyakbank Karsisi",
    "sg:city":"Merkez",
    "sg:classifiers":[
        {
            "category":"Wholesale",
            "subcategory":"Medical Equipment & Supplies",
            "type":"Manufacturing & Wholesale Goods"
        }
    ],
    "sg:phone":"+90 272 214 0565",
    "sg:postcode":"03300",
    "sg:province":"Afyon",
    "wof:name":"Candan Medikal",
    "wof:placetype":"venue"
},
  "geometry": {"coordinates":[30.5382652283,38.7579841614],"type":"Point"}
}