{
  "type": "Feature",
  "properties": {
    "addr:full":"Prof. Cemil B. Cd. No:12 Emin?? Istanbul Yukari Dudullu Istanbul 34776",
    "addr:housenumber":"no 12;? ?",
    "addr:postcode":"34776",
    "addr:street":"Prof. Cemil B. Cd.;Emin",
    "iso:country":"TR",
    "sg:address":"Prof. Cemil B. Cd. No:12 Emin?? Istanbul",
    "sg:city":"Yukari Dudullu",
    "sg:classifiers":[
        {
            "category":"Manufacturing",
            "subcategory":"Rubber & Plastics",
            "type":"Manufacturing & Wholesale Goods"
        }
    ],
    "sg:phone":"+90 212 520 9442",
    "sg:postcode":"34776",
    "sg:province":"Istanbul",
    "sg:tags":[
        "industry"
    ],
    "wof:name":"Aky?z Plastik San. Tic. A.s.",
    "wof:placetype":"venue"
},
  "geometry": {"coordinates":[28.9697589874,41.0070457458],"type":"Point"}
}