{
  "type": "Feature",
  "properties": {
    "iso:country":"TR",
    "sg:address":"Ziya Gokalp Mah. 42/1 Sok. No:8 Zeytinburnu",
    "sg:city":"\u00c7orlu",
    "sg:classifiers":[
        {
            "category":"Shopping",
            "subcategory":"Luggage & Leather Goods",
            "type":"Retail Goods"
        }
    ],
    "sg:phone":"+90 212 510 7997",
    "sg:province":"Istanbul",
    "sg:tags":[
        "leather-fur",
        "wear"
    ],
    "wof:name":"Rialto Pelle",
    "wof:placetype":"venue"
},
  "geometry": {"coordinates":[28.9063796997,40.9906234741],"type":"Point"}
}