{
  "type": "Feature",
  "properties": {
    "addr:full":"H. Efendi Mah. Gazi Bulv. No:85 Sel?klu Aydin 42060",
    "addr:housenumber":"no 85;?",
    "addr:postcode":"42060",
    "addr:street":"H. Efendi Mah. Gazi Bulv.;Klu Aydin",
    "iso:country":"TR",
    "sg:address":"H. Efendi Mah. Gazi Bulv. No:85",
    "sg:city":"Sel?klu",
    "sg:classifiers":[
        {
            "category":"Wholesale",
            "subcategory":"Medical Equipment & Supplies",
            "type":"Manufacturing & Wholesale Goods"
        }
    ],
    "sg:phone":"+90 256 225 6883",
    "sg:postcode":"42060",
    "sg:province":"Aydin",
    "wof:name":"Yildirim Itriyat Deposu",
    "wof:placetype":"venue"
},
  "geometry": {"coordinates":[27.8324394226,37.8409690857],"type":"Point"}
}