{
  "type": "Feature",
  "properties": {
    "iso:country":"TR",
    "sg:address":"Ata?sk. No:54/1",
    "sg:city":"Kizilay",
    "sg:classifiers":[
        {
            "category":"Professional",
            "subcategory":"Engineering",
            "type":"Services"
        }
    ],
    "sg:phone":"+90 312 433 1735",
    "sg:postcode":"23050",
    "sg:province":"Ankara",
    "sg:tags":[
        "architect"
    ],
    "wof:name":"Dogan M?hendis. Tic. Ltd. Sti.",
    "wof:placetype":"venue"
},
  "geometry": {"coordinates":[32.8604812622,39.9429283142],"type":"Point"}
}