{
  "type": "Feature",
  "properties": {
    "addr:full":"Fermeneciler Cad. No:41 Karak\u00f6y Istanbul",
    "addr:housenumber":"41",
    "addr:street":"Fermeneciler Cad. No",
    "iso:country":"TR",
    "sg:address":"Fermeneciler Cad. No:41",
    "sg:city":"Karak\u00f6y",
    "sg:classifiers":[
        {
            "category":"Manufacturing",
            "subcategory":"Textiles",
            "type":"Manufacturing & Wholesale Goods"
        }
    ],
    "sg:phone":"+90 212 292 8880",
    "sg:province":"Istanbul",
    "sg:tags":[
        "cloth",
        "worker"
    ],
    "wof:name":"Guven Tic. Is Guvenligi Malz. & Is Elbiseleri",
    "wof:placetype":"venue"
},
  "geometry": {"coordinates":[28.9727897644,41.0222053528],"type":"Point"}
}