{
  "type": "Feature",
  "properties": {
    "addr:full":"Lise Cd. Yeni ?gretmenevi Binasi Kat:3 4 Bayrampasa Siirt 36100",
    "addr:housenumber":"kat 3 4",
    "addr:postcode":"36100",
    "addr:street":"Lise;Yeni;Bayrampasa Siirt",
    "iso:country":"TR",
    "sg:address":"Lise Cd. Yeni ?gretmenevi Binasi Kat:3 4",
    "sg:city":"Bayrampasa",
    "sg:classifiers":[
        {
            "category":"Education",
            "subcategory":"University",
            "type":"Public Place"
        }
    ],
    "sg:postcode":"36100",
    "sg:province":"Siirt",
    "sg:tags":[
        "national",
        "chief"
    ],
    "wof:name":"Siirt Milli Egitim M?d?rl?g?",
    "wof:placetype":"venue"
},
  "geometry": {"coordinates":[41.9430389404,37.9270439148],"type":"Point"}
}