{
  "type": "Feature",
  "properties": {
    "iso:country":"TR",
    "sg:address":"Buttim D Blok K:5 No:1552",
    "sg:city":"Yesilk?y",
    "sg:classifiers":[
        {
            "category":"Travel",
            "subcategory":"Travel Agent",
            "type":"Entertainment"
        }
    ],
    "sg:phone":"+90 224211198182",
    "sg:province":"Bursa",
    "sg:tags":[
        "agency",
        "tourism"
    ],
    "wof:name":"Gift Turizm",
    "wof:placetype":"venue"
},
  "geometry": {"coordinates":[29.0586109161,40.1844291687],"type":"Point"}
}