{
  "type": "Feature",
  "properties": {
    "addr:full":"Pamukkale Yolu Kizilay Denizli 23050",
    "addr:housenumber":"kizilay",
    "addr:postcode":"23050",
    "addr:street":"Pamukkale Yolu",
    "iso:country":"TR",
    "sg:address":"Pamukkale Yolu",
    "sg:city":"Kizilay",
    "sg:classifiers":[
        {
            "category":"Home & Garden",
            "subcategory":"Home Furnishings",
            "type":"Retail Goods"
        }
    ],
    "sg:phone":"+90 258 279 2320",
    "sg:postcode":"23050",
    "sg:province":"Denizli",
    "sg:tags":[
        "textile"
    ],
    "wof:name":"Kayalar Nakis A.s.",
    "wof:placetype":"venue"
},
  "geometry": {"coordinates":[29.1141757965,37.8164749146],"type":"Point"}
}