{
  "type": "Feature",
  "properties": {
    "addr:full":"Organize San No:1 Merzifon Amasya 05300",
    "addr:postcode":"05300",
    "addr:street":"Organize San No 1",
    "iso:country":"TR",
    "sg:address":"Organize San No:1",
    "sg:city":"Merzifon",
    "sg:classifiers":[
        {
            "category":"Wholesale",
            "subcategory":"Machinery & Supplies",
            "type":"Manufacturing & Wholesale Goods"
        }
    ],
    "sg:phone":"+90 358 513 1420",
    "sg:postcode":"05300",
    "sg:province":"Amasya",
    "sg:tags":[
        "agricultural"
    ],
    "wof:name":"Kervan Makina Sanayi",
    "wof:placetype":"venue"
},
  "geometry": {"coordinates":[35.8320007324,40.6543998718],"type":"Point"}
}