{
  "type": "Feature",
  "properties": {
    "iso:country":"TR",
    "sg:address":"Zindan Sk. No:12/1",
    "sg:city":"Karak\u00f6y",
    "sg:classifiers":[
        {
            "category":"Marine",
            "type":"Transportation"
        }
    ],
    "sg:phone":"+90 212 245 1753",
    "sg:province":"Istanbul",
    "sg:tags":[
        "equipment",
        "maritime"
    ],
    "wof:name":"Metal Teknik Tic. San. Ltd. Sti.",
    "wof:placetype":"venue"
},
  "geometry": {"coordinates":[28.9861831665,41.0408554077],"type":"Point"}
}