{
  "type": "Feature",
  "properties": {
    "addr:full":"1202/3. Sk. No:25 Karatay Izmir 42000",
    "addr:housenumber":"1202 / 3;25",
    "addr:postcode":"42000",
    "addr:street":"Sk. No",
    "iso:country":"TR",
    "sg:address":"1202/3. Sk. No:25",
    "sg:city":"Karatay",
    "sg:classifiers":[
        {
            "category":"Professional",
            "subcategory":"Art Services",
            "type":"Services"
        }
    ],
    "sg:phone":"+90 232 457 6183",
    "sg:postcode":"42000",
    "sg:province":"Izmir",
    "sg:tags":[
        "marketing"
    ],
    "wof:name":"Ugurlu Pazarlama Ltd. Sti.",
    "wof:placetype":"venue"
},
  "geometry": {"coordinates":[27.1423015594,38.4251480103],"type":"Point"}
}