{
  "type": "Feature",
  "properties": {
    "addr:full":"Kuzgun Sok. No:83/3 A.ayranci Ankara",
    "addr:housenumber":"no 83 / 3",
    "addr:street":"Kuzgun Sok.;A.Ayranci",
    "iso:country":"TR",
    "sg:address":"Kuzgun Sok. No:83/3",
    "sg:city":"A.ayranci",
    "sg:classifiers":[
        {
            "category":"Professional",
            "subcategory":"Engineering",
            "type":"Services"
        }
    ],
    "sg:phone":"+90 312 427 8780",
    "sg:province":"Ankara",
    "sg:tags":[
        "architect"
    ],
    "wof:name":"Boyut Kesif-metraj Ltd.sti.",
    "wof:placetype":"venue"
},
  "geometry": {"coordinates":[32.8604812622,39.9429283142],"type":"Point"}
}