{
  "type": "Feature",
  "properties": {
    "iso:country":"TR",
    "sg:address":"Ankara Cad 35",
    "sg:city":"Adapazari",
    "sg:classifiers":[
        {
            "category":"Banks & Credit Unions",
            "subcategory":"Bank",
            "type":"Services"
        }
    ],
    "sg:phone":"+90 264 277 5964",
    "sg:postcode":"54000",
    "sg:province":"54100",
    "wof:name":"T?kiye Vakiflar, Bankasi Tao",
    "wof:placetype":"venue"
},
  "geometry": {"coordinates":[30.40427,40.779053],"type":"Point"}
}