{
  "type": "Feature",
  "properties": {
    "addr:full":"Molla Feneri Sk. Inan Ishani K:2 No:203 Cagaloglu Emin\u00f6n\u00fc/Ca\u011falo\u011flu Istanbul 34110",
    "addr:housenumber":"2",
    "addr:postcode":"34110",
    "addr:street":"Feneri Sk. Inan Ishani K;No 203 Cagaloglu",
    "iso:country":"TR",
    "sg:address":"Molla Feneri Sk. Inan Ishani K:2 No:203 Cagaloglu",
    "sg:city":"Emin\u00f6n\u00fc/Ca\u011falo\u011flu",
    "sg:classifiers":[
        {
            "category":"Shopping",
            "subcategory":"Stationery & Office Supplies",
            "type":"Retail Goods"
        }
    ],
    "sg:phone":"+90 212 513 2517",
    "sg:postcode":"34110",
    "sg:province":"Istanbul",
    "wof:name":"?cal Ith. Kirtasiye",
    "wof:placetype":"venue"
},
  "geometry": {"coordinates":[28.975925,41.012379],"type":"Point"}
}