{
  "type": "Feature",
  "properties": {
    "addr:full":"11.sk. No.37/39 Ostim Karak\u00f6y Ankara 06710",
    "addr:housenumber":"no.37 / 39",
    "addr:postcode":"06710",
    "addr:street":"11.Sk",
    "iso:country":"TR",
    "sg:address":"11.sk. No.37/39 Ostim",
    "sg:city":"Karak\u00f6y",
    "sg:classifiers":[
        {
            "category":"Wholesale",
            "subcategory":"Vending Machines",
            "type":"Manufacturing & Wholesale Goods"
        }
    ],
    "sg:phone":"+90 312 354 2161",
    "sg:postcode":"06710",
    "sg:province":"Ankara",
    "sg:tags":[
        "rod",
        "welding"
    ],
    "wof:name":"Bugra Kaynak Makinalari Uretim Ve Pazarlama",
    "wof:placetype":"venue"
},
  "geometry": {"coordinates":[32.7909965515,39.9706268311],"type":"Point"}
}