{
  "type": "Feature",
  "properties": {
    "iso:country":"TR",
    "sg:address":"Mithatpasa Cad. No:62/a Kizilay 06420 Cankaya Ankara",
    "sg:city":"Ikitelli/K\u00fc\u00e7\u00fck\u00e7ekmece",
    "sg:classifiers":[
        {
            "category":"Professional",
            "subcategory":"Printing & Photocopies",
            "type":"Services"
        }
    ],
    "sg:phone":"+90 312 418 7094",
    "sg:postcode":"34670",
    "sg:province":"Ankara",
    "wof:name":"Pelin Ofset Tipo Matbaacilik Ve Tic Ltd Sti",
    "wof:placetype":"venue"
},
  "geometry": {"coordinates":[32.8590545654,39.9200210571],"type":"Point"}
}