{
  "type": "Feature",
  "properties": {
    "iso:country":"TR",
    "sg:address":"Saraylar Mah 37",
    "sg:city":"Denizli",
    "sg:classifiers":[
        {
            "category":"Banks & Credit Unions",
            "subcategory":"Bank",
            "type":"Services"
        }
    ],
    "sg:phone":"+90 258 265 0489",
    "sg:postcode":"01130",
    "sg:province":"20100",
    "wof:name":"Egebank As",
    "wof:placetype":"venue"
},
  "geometry": {"coordinates":[29.091885,37.794189],"type":"Point"}
}