{
  "type": "Feature",
  "properties": {
    "iso:country":"TR",
    "sg:address":"Kayisdagi Cad. No:88 Icerenkoy",
    "sg:city":"\u00dcmraniye",
    "sg:classifiers":[
        {
            "category":"Manufacturing",
            "subcategory":"Metals",
            "type":"Manufacturing & Wholesale Goods"
        }
    ],
    "sg:phone":"+90 216 362 9707",
    "sg:province":"Istanbul",
    "sg:tags":[
        "iron-steel",
        "peoducts"
    ],
    "wof:name":"Aktan Demir",
    "wof:placetype":"venue"
},
  "geometry": {"coordinates":[29.1221351624,40.9754638672],"type":"Point"}
}