{
  "type": "Feature",
  "properties": {
    "iso:country":"TR",
    "sg:address":"Mehmet Ilhan",
    "sg:city":"Ineg?",
    "sg:classifiers":[
        {
            "category":"Government",
            "subcategory":"Office",
            "type":"Public Place"
        }
    ],
    "sg:phone":"+90 224 721 2008",
    "sg:province":"Bursa",
    "sg:tags":[
        "municipality"
    ],
    "wof:name":"Kursunlu Belediye Baskani",
    "wof:placetype":"venue"
},
  "geometry": {"coordinates":[29.1290912628,40.1924819946],"type":"Point"}
}