{
  "type": "Feature",
  "properties": {
    "addr:full":"Halkali Cd. No:190-29 Sefak? Beypazari Istanbul 06730",
    "addr:housenumber":"no;sefak",
    "addr:postcode":"06730",
    "addr:street":"Halkali Cd.",
    "iso:country":"TR",
    "sg:address":"Halkali Cd. No:190-29 Sefak?",
    "sg:city":"Beypazari",
    "sg:classifiers":[
        {
            "category":"Freight",
            "type":"Transportation"
        }
    ],
    "sg:phone":"+90 212 696 9493",
    "sg:postcode":"06730",
    "sg:province":"Istanbul",
    "sg:tags":[
        "packing",
        "industry"
    ],
    "wof:name":"Bilkut Ambalaj San. Tic. Ltd. Sti.",
    "wof:placetype":"venue"
},
  "geometry": {"coordinates":[28.7924251556,40.9708900452],"type":"Point"}
}