{
  "type": "Feature",
  "properties": {
    "addr:full":"Atat?k Bulv. 191/b Osmanbey Denizli 63000",
    "addr:housenumber":"191 / b",
    "addr:postcode":"63000",
    "addr:street":"K Bulv.;Osmanbey Denizli",
    "iso:country":"TR",
    "sg:address":"Atat?k Bulv. 191/b",
    "sg:city":"Osmanbey",
    "sg:classifiers":[
        {
            "category":"Shopping",
            "subcategory":"Crafts & Fabrics",
            "type":"Retail Goods"
        }
    ],
    "sg:phone":"+90 258 265 0705",
    "sg:postcode":"63000",
    "sg:province":"Denizli",
    "sg:tags":[
        "knitting"
    ],
    "wof:name":"Turteks Tekstil A.s.",
    "wof:placetype":"venue"
},
  "geometry": {"coordinates":[29.0864906311,37.773525238],"type":"Point"}
}