{
  "type": "Feature",
  "properties": {
    "iso:country":"TR",
    "sg:address":"Ray Sk. Murat Apt. No.19/2 Bakirk?",
    "sg:city":"Okmeydani/sisli",
    "sg:classifiers":[
        {
            "category":"Professional",
            "subcategory":"Detective & Security Services",
            "type":"Services"
        }
    ],
    "sg:phone":"+90 212 660 7585",
    "sg:postcode":"80270",
    "sg:province":"Istanbul",
    "sg:tags":[
        "material"
    ],
    "wof:name":"Invest Arastirma Ve Bilgi Toplama Ltd.sti.",
    "wof:placetype":"venue"
},
  "geometry": {"coordinates":[28.975925,41.012379],"type":"Point"}
}