{
  "type": "Feature",
  "properties": {
    "iso:country":"TR",
    "sg:address":"Ahi Evran Cd. No:10 Ostim",
    "sg:city":"Esenler",
    "sg:classifiers":[
        {
            "category":"Manufacturing",
            "subcategory":"Rubber & Plastics",
            "type":"Manufacturing & Wholesale Goods"
        }
    ],
    "sg:phone":"+90 312 354 3874",
    "sg:postcode":"01350",
    "sg:province":"Ankara",
    "sg:tags":[
        "industry"
    ],
    "wof:name":"G?nd?z Plastik San. Tic. Ltd. Sti.",
    "wof:placetype":"venue"
},
  "geometry": {"coordinates":[32.7470779419,39.9774169922],"type":"Point"}
}