{
  "type": "Feature",
  "properties": {
    "addr:full":"Muradiye Bayiri Sok. 43/16 Tesvikiye Meram Istanbul 42100",
    "addr:housenumber":"43 / 16",
    "addr:postcode":"42100",
    "addr:street":"Bayiri Sok.;Tesvikiye",
    "iso:country":"TR",
    "sg:address":"Muradiye Bayiri Sok. 43/16 Tesvikiye",
    "sg:city":"Meram",
    "sg:classifiers":[
        {
            "category":"Professional",
            "subcategory":"Business Services",
            "type":"Services"
        }
    ],
    "sg:phone":"+90 212 327 4045",
    "sg:postcode":"42100",
    "sg:province":"Istanbul",
    "wof:name":"Bics Danismanlik Ve Organizasyon Hizm. Ltd.sti.",
    "wof:placetype":"venue"
},
  "geometry": {"coordinates":[28.9976673126,41.0485839844],"type":"Point"}
}