{
  "type": "Feature",
  "properties": {
    "addr:full":"Selmani Pak Cad. Atlas Sok. No: 13 /23 Kaya Is Merkezi \u00dcsk\u00fcdar Istanbul 34672",
    "addr:housenumber":"no 13 / 23",
    "addr:postcode":"34672",
    "addr:street":"Cad. Atlas Sok.;Kaya Is;U\u0308Skuedar",
    "iso:country":"TR",
    "sg:address":"Selmani Pak Cad. Atlas Sok. No: 13 /23 Kaya Is Merkezi",
    "sg:city":"\u00dcsk\u00fcdar",
    "sg:classifiers":[
        {
            "category":"Shopping",
            "subcategory":"Gifts & Souvenirs",
            "type":"Retail Goods"
        }
    ],
    "sg:phone":"+90 216 334 8573",
    "sg:postcode":"34672",
    "sg:province":"Istanbul",
    "wof:name":"Eprogrup Ltd.sti",
    "wof:placetype":"venue"
},
  "geometry": {"coordinates":[29.0154418945,41.0218315125],"type":"Point"}
}