{
  "type": "Feature",
  "properties": {
    "addr:full":"Beymersan Sanayi Sitesi 8.cad. No:11 Yakuplu-b.cekmece B?y?k?ekmece Istanbul",
    "addr:housenumber":"8.cad no 11;b ? y ? k ?",
    "addr:street":"Beymersan Sanayi Sitesi",
    "iso:country":"TR",
    "sg:address":"Beymersan Sanayi Sitesi 8.cad. No:11 Yakuplu-b.cekmece",
    "sg:city":"B?y?k?ekmece",
    "sg:classifiers":[
        {
            "category":"Wholesale",
            "subcategory":"Auto Parts",
            "type":"Manufacturing & Wholesale Goods"
        }
    ],
    "sg:phone":"+90 212 875 8500",
    "sg:province":"Istanbul",
    "sg:tags":[
        "spare"
    ],
    "wof:name":"Pobusan Debriyaj San.tic.ltd.sti.",
    "wof:placetype":"venue"
},
  "geometry": {"coordinates":[28.9861793518,41.040851593],"type":"Point"}
}