{
  "type": "Feature",
  "properties": {
    "addr:full":"Kazim Karabekir Mah. K.karabekir Cad. No:87 Esenler Nazilli Istanbul 65600",
    "addr:housenumber":"87",
    "addr:postcode":"65600",
    "addr:street":"Karabekir Mah. K.Karabekir Cad. No",
    "iso:country":"TR",
    "sg:address":"Kazim Karabekir Mah. K.karabekir Cad. No:87 Esenler",
    "sg:city":"Nazilli",
    "sg:classifiers":[
        {
            "category":"Home & Garden",
            "subcategory":"Household Appliances",
            "type":"Retail Goods"
        }
    ],
    "sg:phone":"+90 212 610 1099",
    "sg:postcode":"65600",
    "sg:province":"Istanbul",
    "sg:tags":[
        "utensil",
        "electrical"
    ],
    "wof:name":"Uslu Spot",
    "wof:placetype":"venue"
},
  "geometry": {"coordinates":[28.9861831665,41.0408554077],"type":"Point"}
}