{
  "type": "Feature",
  "properties": {
    "iso:country":"TR",
    "sg:address":"Mehmet Bozkaya",
    "sg:city":"Serik",
    "sg:classifiers":[
        {
            "category":"Government",
            "subcategory":"Office",
            "type":"Public Place"
        }
    ],
    "sg:phone":"+90 258 762 1249",
    "sg:postcode":"07500",
    "sg:province":"Denizli",
    "sg:tags":[
        "municipality"
    ],
    "wof:name":"Belevi Belediye Baskani",
    "wof:placetype":"venue"
},
  "geometry": {"coordinates":[29.0864906311,37.773525238],"type":"Point"}
}