{
  "type": "Feature",
  "properties": {
    "addr:full":"2 Ulus G?m?s Sokak Beyazg?l Apt No:8 D:11 Besiktas/etiler Istanbul 80600",
    "addr:housenumber":"2;?;beyazg ?;11",
    "addr:postcode":"80600",
    "addr:street":"Ulus G;M ? S Sokak;L Apt No 8 D",
    "iso:country":"TR",
    "sg:address":"2 Ulus G?m?s Sokak Beyazg?l Apt No:8 D:11",
    "sg:city":"Besiktas/etiler",
    "sg:classifiers":[
        {
            "category":"Building & Trades",
            "subcategory":"Plumbing",
            "type":"Services"
        }
    ],
    "sg:phone":"+90 212 270 0380",
    "sg:postcode":"80600",
    "sg:province":"Istanbul",
    "wof:name":"Beyaz Insaat",
    "wof:placetype":"venue"
},
  "geometry": {"coordinates":[28.9759254456,41.0123786926],"type":"Point"}
}