{
  "type": "Feature",
  "properties": {
    "iso:country":"TR",
    "sg:address":"Istoc 41.ada No:44 Bagcilar",
    "sg:city":"Kizilay",
    "sg:classifiers":[
        {
            "category":"Manufacturing",
            "subcategory":"Chemicals & Compounds",
            "type":"Manufacturing & Wholesale Goods"
        }
    ],
    "sg:phone":"+90 212659601617",
    "sg:postcode":"23050",
    "sg:province":"Istanbul",
    "sg:tags":[
        "medicine"
    ],
    "wof:name":"Kilic Kimya Tekstil Sanayi Ve Dis Ticaret Ltd.sti.",
    "wof:placetype":"venue"
},
  "geometry": {"coordinates":[28.9759254456,41.0123786926],"type":"Point"}
}