{
  "type": "Feature",
  "properties": {
    "addr:full":"Kusadasi Bodrum Aydin 48400",
    "addr:postcode":"48400",
    "addr:street":"Aydin",
    "iso:country":"TR",
    "sg:address":"Kusadasi",
    "sg:city":"Bodrum",
    "sg:classifiers":[
        {
            "category":"Social Services",
            "subcategory":"Retirement Home",
            "type":"Services"
        }
    ],
    "sg:phone":"+90 256614939161",
    "sg:postcode":"48400",
    "sg:province":"Aydin",
    "sg:tags":[
        "holiday",
        "village"
    ],
    "wof:name":"Club Mediterranee Holiday Village",
    "wof:placetype":"venue"
},
  "geometry": {"coordinates":[27.8324394226,37.8409690857],"type":"Point"}
}