{
  "type": "Feature",
  "properties": {
    "iso:country":"TR",
    "sg:address":"Cinnah Cd. No:29/b-5 ?ankaya",
    "sg:city":"Osmangazi",
    "sg:classifiers":[
        {
            "category":"Farming",
            "subcategory":"Fish & Marine Products",
            "type":"Manufacturing & Wholesale Goods"
        }
    ],
    "sg:phone":"+90 312 467 6062",
    "sg:postcode":"16170",
    "sg:province":"Ankara",
    "sg:tags":[
        "automotive"
    ],
    "wof:name":"Orka Insaat Turizm Otomotiv Ltd. Sti.",
    "wof:placetype":"venue"
},
  "geometry": {"coordinates":[32.8577651978,39.8964080811],"type":"Point"}
}