{
  "type": "Feature",
  "properties": {
    "addr:full":"Kazim Karabekir M Kartal Sok. No:2 Unkapani Bursa 55020",
    "addr:housenumber":"no 2",
    "addr:postcode":"55020",
    "addr:street":"Kartal Sok.;Bursa",
    "iso:country":"TR",
    "sg:address":"Kazim Karabekir M Kartal Sok. No:2",
    "sg:city":"Unkapani",
    "sg:classifiers":[
        {
            "category":"Government",
            "subcategory":"Fire Station",
            "type":"Public Place"
        }
    ],
    "sg:phone":"+90 224 364 5372",
    "sg:postcode":"55020",
    "sg:province":"Bursa",
    "sg:tags":[
        "decoration"
    ],
    "wof:name":"Serge Mobilya San Ve Tic",
    "wof:placetype":"venue"
},
  "geometry": {"coordinates":[29.0586109161,40.1844291687],"type":"Point"}
}