{
  "type": "Feature",
  "properties": {
    "addr:full":"Yeni Cami Sk. No: 18 Karam?sel Kocaeli",
    "addr:housenumber":"18;?",
    "addr:street":"Sk. No;Karam",
    "iso:country":"TR",
    "sg:address":"Yeni Cami Sk. No: 18",
    "sg:city":"Karam?sel",
    "sg:classifiers":[
        {
            "category":"Sports & Exercise",
            "subcategory":"Ski Slope",
            "type":"Entertainment"
        }
    ],
    "sg:phone":"+90 262 454 4594",
    "sg:province":"Kocaeli",
    "sg:tags":[
        "wear"
    ],
    "wof:name":"Muk Online Jeans Center",
    "wof:placetype":"venue"
},
  "geometry": {"coordinates":[29.882446,40.764271],"type":"Point"}
}