{
  "type": "Feature",
  "properties": {
    "addr:full":"Haci Kundak Caddesi H?riyet Mah. No:35, 20100 Kayhan Denizli Ikitelli/K\u00fc\u00e7\u00fck\u00e7ekmece Denizli 34670",
    "addr:housenumber":"?;mah. no 35",
    "addr:postcode":"20100;34670",
    "addr:street":"Kundak Caddesi H;Riyet",
    "iso:country":"TR",
    "sg:address":"Haci Kundak Caddesi H?riyet Mah. No:35, 20100 Kayhan Denizli",
    "sg:city":"Ikitelli/K\u00fc\u00e7\u00fck\u00e7ekmece",
    "sg:classifiers":[
        {
            "category":"Shopping",
            "subcategory":"Crafts & Fabrics",
            "type":"Retail Goods"
        }
    ],
    "sg:phone":"+90 258 213 1111",
    "sg:postcode":"34670",
    "sg:province":"Denizli",
    "wof:name":"Kayteks Kadife Tekstil San.ve Tic.ltd.sti.",
    "wof:placetype":"venue"
},
  "geometry": {"coordinates":[29.0864906311,37.773525238],"type":"Point"}
}