{
  "type": "Feature",
  "properties": {
    "addr:full":"Imam Hatip Lisesi Bitisigi Mersin Bayrampasa I?el 36100",
    "addr:postcode":"36100",
    "addr:street":"Bitisigi;El",
    "iso:country":"TR",
    "sg:address":"Imam Hatip Lisesi Bitisigi Mersin",
    "sg:city":"Bayrampasa",
    "sg:orig_category":"Non-classified Establishments",
    "sg:phone":"+90 324 328 1229",
    "sg:postcode":"36100",
    "sg:province":"I?el",
    "wof:name":"Burak Ticaret",
    "wof:placetype":"venue"
},
  "geometry": {"coordinates":[34.6096916199,36.8215293884],"type":"Point"}
}