{
  "type": "Feature",
  "properties": {
    "iso:country":"TR",
    "sg:address":"In??cd. No:10/c Esenler",
    "sg:city":"Okmeydani/beyoglu",
    "sg:classifiers":[
        {
            "category":"Shopping",
            "subcategory":"Stationery & Office Supplies",
            "type":"Retail Goods"
        }
    ],
    "sg:phone":"+90 212 568 3137",
    "sg:postcode":"34440",
    "sg:province":"Istanbul",
    "wof:name":"K?lt?r Kirtasiye",
    "wof:placetype":"venue"
},
  "geometry": {"coordinates":[29.11359,40.953365],"type":"Point"}
}