{
  "type": "Feature",
  "properties": {
    "addr:full":"Mehmet G??r Ihsaniye Afyon 07110",
    "addr:housenumber":"? ? r",
    "addr:postcode":"07110",
    "addr:street":"Mehmet G;Afyon",
    "iso:country":"TR",
    "sg:address":"Mehmet G??r",
    "sg:city":"Ihsaniye",
    "sg:classifiers":[
        {
            "category":"Government",
            "subcategory":"Office",
            "type":"Public Place"
        }
    ],
    "sg:phone":"+90 272 273 6294",
    "sg:postcode":"07110",
    "sg:province":"Afyon",
    "sg:tags":[
        "municipality"
    ],
    "wof:name":"Gazlig? Belediye Baskani",
    "wof:placetype":"venue"
},
  "geometry": {"coordinates":[30.5362815857,38.7586631775],"type":"Point"}
}