{
  "type": "Feature",
  "properties": {
    "addr:full":"Ozel Idare Ish. No:105 G?tepe Amasya",
    "addr:housenumber":"105 g ?",
    "addr:street":"Ish. No",
    "iso:country":"TR",
    "sg:address":"Ozel Idare Ish. No:105",
    "sg:city":"G?tepe",
    "sg:classifiers":[
        {
            "category":"Wholesale",
            "subcategory":"Medical Equipment & Supplies",
            "type":"Manufacturing & Wholesale Goods"
        }
    ],
    "sg:phone":"+90 358 212 3417",
    "sg:province":"Amasya",
    "sg:tags":[
        "material"
    ],
    "wof:name":"Amasya Medikal Ltd. Sti.",
    "wof:placetype":"venue"
},
  "geometry": {"coordinates":[35.8135032654,40.6473884583],"type":"Point"}
}