{
  "type": "Feature",
  "properties": {
    "addr:full":"?orum Karabaglar ?orum 44210",
    "addr:housenumber":"?;?",
    "addr:postcode":"44210",
    "addr:street":"Orum Karabaglar",
    "iso:country":"TR",
    "sg:address":"?orum",
    "sg:city":"Karabaglar",
    "sg:classifiers":[
        {
            "category":"Government",
            "subcategory":"Office",
            "type":"Public Place"
        }
    ],
    "sg:phone":"+90 364 511 6005",
    "sg:postcode":"44210",
    "sg:province":"?orum",
    "sg:tags":[
        "army"
    ],
    "wof:name":"Iskilip (oguzlar, Ugurludag) Askerlik Subesi",
    "wof:placetype":"venue"
},
  "geometry": {"coordinates":[38.4896812439,38.455280304],"type":"Point"}
}