{
  "type": "Feature",
  "properties": {
    "iso:country":"TR",
    "sg:address":"Esentepe Mh. Ilgaz Sk. No:31/a Kartal",
    "sg:city":"B\u00fcy\u00fck\u00e7ekmece",
    "sg:orig_category":"Aluminium Carpentary",
    "sg:phone":"+90 216 353 1546",
    "sg:postcode":"34900",
    "sg:province":"Istanbul",
    "wof:name":"Atas Plas. Penc. San.a.s.",
    "wof:placetype":"venue"
},
  "geometry": {"coordinates":[29.1886730194,40.9047317505],"type":"Point"}
}