{
  "type": "Feature",
  "properties": {
    "iso:country":"TR",
    "sg:address":"H?riyet Mah. Cumhuriyet Cad Hisar Sk. No:1",
    "sg:city":"G?esli",
    "sg:classifiers":[
        {
            "category":"Shopping",
            "subcategory":"Clothing, Apparel, & Fashions",
            "type":"Retail Goods"
        }
    ],
    "sg:phone":"+90 212 655 5538",
    "sg:postcode":"34209",
    "sg:province":"Istanbul",
    "sg:tags":[
        "ready",
        "wear"
    ],
    "sg:website":"kaliteksgiyim.com.tr",
    "wof:name":"Kaliteks Giyim Sanayi Ve Ticaret Ltd",
    "wof:placetype":"venue"
},
  "geometry": {"coordinates":[28.8254489899,41.0255737305],"type":"Point"}
}