{
  "type": "Feature",
  "properties": {
    "addr:full":"Pamukkale Is Hani No:81/82 Buyukada Denizli 28300",
    "addr:housenumber":"82",
    "addr:postcode":"28300",
    "addr:street":"Buyukada Denizli",
    "iso:country":"TR",
    "sg:address":"Pamukkale Is Hani No:81/82",
    "sg:city":"Buyukada",
    "sg:orig_category":"Carpet-kilim-blanket",
    "sg:phone":"+90 258 264 4294",
    "sg:postcode":"28300",
    "sg:province":"Denizli",
    "wof:name":"Oren Hali Kilim",
    "wof:placetype":"venue"
},
  "geometry": {"coordinates":[29.0788803101,37.7851867676],"type":"Point"}
}