{
  "type": "Feature",
  "properties": {
    "addr:full":"Y. Dudullu Imes San. Sit. A Blok 103. Sk. ?mraniye Ikitelli/K\u00fc\u00e7\u00fck\u00e7ekmece Istanbul 34670",
    "addr:housenumber":"blok 103",
    "addr:postcode":"34670",
    "addr:street":"Imes;Sk. ? Mraniye",
    "iso:country":"TR",
    "sg:address":"Y. Dudullu Imes San. Sit. A Blok 103. Sk. ?mraniye",
    "sg:city":"Ikitelli/K\u00fc\u00e7\u00fck\u00e7ekmece",
    "sg:classifiers":[
        {
            "category":"Manufacturing",
            "subcategory":"Tools & Machinery",
            "type":"Manufacturing & Wholesale Goods"
        }
    ],
    "sg:phone":"+90 216 364 5353",
    "sg:postcode":"34670",
    "sg:province":"Istanbul",
    "sg:tags":[
        "machine",
        "industry"
    ],
    "wof:name":"Entegre Makina San. Tic.",
    "wof:placetype":"venue"
},
  "geometry": {"coordinates":[28.9759254456,41.0123786926],"type":"Point"}
}