{
  "type": "Feature",
  "properties": {
    "iso:country":"TR",
    "sg:address":"S.pasa K?r??sk. No:12 K:3-4",
    "sg:city":"Besiktas",
    "sg:classifiers":[
        {
            "category":"Transit Center",
            "subcategory":"Freight",
            "type":"Transportation"
        }
    ],
    "sg:phone":"+90 212 260 5372",
    "sg:postcode":"75200",
    "sg:province":"Istanbul",
    "wof:name":"?ztrans Denizcilik Tic. A.s.",
    "wof:placetype":"venue"
},
  "geometry": {"coordinates":[28.9920425415,41.0574607849],"type":"Point"}
}