{
  "type": "Feature",
  "properties": {
    "iso:country":"TR",
    "sg:address":"Mithatpasa Cad. No:116",
    "sg:city":"Izmit Bekirpasa",
    "sg:classifiers":[
        {
            "category":"Shopping",
            "subcategory":"Computers & Home Electronics",
            "type":"Retail Goods"
        }
    ],
    "sg:phone":"+90 232 234 2892",
    "sg:postcode":"41100",
    "sg:province":"Izmir",
    "sg:tags":[
        "product",
        "electric-electronic"
    ],
    "wof:name":"G?n Elektronik",
    "wof:placetype":"venue"
},
  "geometry": {"coordinates":[26.8663330078,38.3740158081],"type":"Point"}
}