{
  "type": "Feature",
  "properties": {
    "addr:full":"Kuveyt Cad. No: 32 A.ayranci Pendik Ankara 34916",
    "addr:housenumber":"32",
    "addr:postcode":"34916",
    "addr:street":"Kuveyt Cad. No",
    "iso:country":"TR",
    "sg:address":"Kuveyt Cad. No: 32 A.ayranci",
    "sg:city":"Pendik",
    "sg:orig_category":"Non-classified Establishments",
    "sg:phone":"+90 312 467 5852",
    "sg:postcode":"34916",
    "sg:province":"Ankara",
    "wof:name":"Altinordu Ticaret",
    "wof:placetype":"venue"
},
  "geometry": {"coordinates":[32.8604812622,39.9429283142],"type":"Point"}
}