{
  "type": "Feature",
  "properties": {
    "addr:full":"Turgut Reis Mh.427 Sk.no:110 Turuncova I?el 07880",
    "addr:housenumber":"mh.427;110;?",
    "addr:postcode":"07880",
    "addr:street":"Turgut Reis;Turuncova I;El",
    "iso:country":"TR",
    "sg:address":"Turgut Reis Mh.427 Sk.no:110",
    "sg:city":"Turuncova",
    "sg:classifiers":[
        {
            "category":"Food & Beverages",
            "subcategory":"Fruits & Vegetables",
            "type":"Retail Goods"
        }
    ],
    "sg:phone":"+90 324 231 8953",
    "sg:postcode":"07880",
    "sg:province":"I?el",
    "sg:tags":[
        "fresh"
    ],
    "wof:name":"Rizk Ith.ihr.",
    "wof:placetype":"venue"
},
  "geometry": {"coordinates":[30.1224193573,36.3515396118],"type":"Point"}
}