{
  "type": "Feature",
  "properties": {
    "iso:country":"TR",
    "sg:address":"H?eyin Demirel",
    "sg:city":"Ezine",
    "sg:classifiers":[
        {
            "category":"Government",
            "subcategory":"Office",
            "type":"Public Place"
        }
    ],
    "sg:phone":"+90 286 628 7777",
    "sg:postcode":"17600",
    "sg:province":"?anakkale",
    "sg:tags":[
        "municipality"
    ],
    "wof:name":"Mahmudiye Belediye Baskani",
    "wof:placetype":"venue"
},
  "geometry": {"coordinates":[26.2975502014,39.7889900208],"type":"Point"}
}