{
  "type": "Feature",
  "properties": {
    "addr:full":"1249.sok. No:9/201 Yenisehir Izmir 31750",
    "addr:housenumber":"no;/ 201",
    "addr:postcode":"31750",
    "addr:street":"Yenisehir Izmir",
    "iso:country":"TR",
    "sg:address":"1249.sok. No:9/201",
    "sg:city":"Yenisehir",
    "sg:classifiers":[
        {
            "category":"Shopping",
            "subcategory":"Clothing, Apparel, & Fashions",
            "type":"Retail Goods"
        }
    ],
    "sg:phone":"+90 232 433 0792",
    "sg:postcode":"31750",
    "sg:province":"Izmir",
    "sg:tags":[
        "ready",
        "wear"
    ],
    "wof:name":"Prizma Tekstil San.tic.ltd.",
    "wof:placetype":"venue"
},
  "geometry": {"coordinates":[27.1645717621,38.4267158508],"type":"Point"}
}