{
  "type": "Feature",
  "properties": {
    "iso:country":"TR",
    "sg:address":"Yildirim",
    "sg:city":"Merkez",
    "sg:classifiers":[
        {
            "category":"Sports & Exercise",
            "subcategory":"Athletic Track",
            "type":"Entertainment"
        }
    ],
    "sg:phone":"+90 224 368 2329",
    "sg:postcode":"63100",
    "sg:province":"Bursa",
    "sg:tags":[
        "shoulder",
        "padding"
    ],
    "wof:name":"Atlilar Tekstil Vatka Iml.san.",
    "wof:placetype":"venue"
},
  "geometry": {"coordinates":[29.133396,40.191765],"type":"Point"}
}