{
  "type": "Feature",
  "properties": {
    "addr:full":"Seyrantepe Mah. Cinarli Sok. No: 16 Seyrantepe-levent Beyoglu Istanbul 46810",
    "addr:housenumber":"no 16",
    "addr:postcode":"46810",
    "addr:street":"Mah. Cinarli Sok.;Seyrantepe-Levent Beyoglu",
    "iso:country":"TR",
    "sg:address":"Seyrantepe Mah. Cinarli Sok. No: 16 Seyrantepe-levent",
    "sg:city":"Beyoglu",
    "sg:classifiers":[
        {
            "category":"Wholesale",
            "subcategory":"Books, Periodicals, & Newspapers",
            "type":"Manufacturing & Wholesale Goods"
        }
    ],
    "sg:phone":"+90 212 283 6938",
    "sg:postcode":"46810",
    "sg:province":"Istanbul",
    "sg:tags":[
        "house",
        "publishing"
    ],
    "wof:name":"Avci Matbaacilik Ltd.sti.",
    "wof:placetype":"venue"
},
  "geometry": {"coordinates":[28.9759254456,41.0123786926],"type":"Point"}
}