{
  "type": "Feature",
  "properties": {
    "addr:full":"Yenidogan Mah. 42 Sk. No.130/3 Zeytinburnu Bornova Istanbul 35040",
    "addr:housenumber":"42;3",
    "addr:postcode":"35040",
    "addr:street":"Yenidogan Mah.;Sk. No.130 /;Zeytinburnu",
    "iso:country":"TR",
    "sg:address":"Yenidogan Mah. 42 Sk. No.130/3 Zeytinburnu",
    "sg:city":"Bornova",
    "sg:classifiers":[
        {
            "category":"Manufacturing",
            "subcategory":"Tools & Machinery",
            "type":"Manufacturing & Wholesale Goods"
        }
    ],
    "sg:phone":"+90 212 510 8549",
    "sg:postcode":"35040",
    "sg:province":"Istanbul",
    "sg:tags":[
        "machine",
        "industry"
    ],
    "wof:name":"Yavuz Makina San.",
    "wof:placetype":"venue"
},
  "geometry": {"coordinates":[28.9086990356,40.9905853271],"type":"Point"}
}