{
  "type": "Feature",
  "properties": {
    "iso:country":"TR",
    "sg:address":"Osmanaga Mh. Arayicibasi Sk. No:24/1",
    "sg:city":"Kad\u0131k\u00f6y",
    "sg:classifiers":[
        {
            "category":"Professional",
            "subcategory":"Engineering",
            "type":"Services"
        }
    ],
    "sg:phone":"+90 216 414 7887",
    "sg:postcode":"34990",
    "sg:province":"Istanbul",
    "sg:tags":[
        "architect"
    ],
    "wof:name":"Eyak M?hendis. Insaat San. Ltd. Sti.",
    "wof:placetype":"venue"
},
  "geometry": {"coordinates":[28.9861831665,41.0408554077],"type":"Point"}
}