{
  "type": "Feature",
  "properties": {
    "iso:country":"TR",
    "sg:address":"1375. Sk. No:17/3 Alsancak",
    "sg:city":"\u00dcmraniye",
    "sg:classifiers":[
        {
            "category":"Manufacturing",
            "subcategory":"Chemicals & Compounds",
            "type":"Manufacturing & Wholesale Goods"
        }
    ],
    "sg:phone":"+90 232 421 0718",
    "sg:province":"Izmir",
    "sg:tags":[
        "pharmaceutical"
    ],
    "wof:name":"Bayer Turk Kim. San.",
    "wof:placetype":"venue"
},
  "geometry": {"coordinates":[27.1375427246,38.4291038513],"type":"Point"}
}