{
  "type": "Feature",
  "properties": {
    "addr:full":"Iskitler Cd. No:62 Kozyatagi Ankara 34742",
    "addr:housenumber":"no 62",
    "addr:postcode":"34742",
    "addr:street":"Iskitler Cd.;Kozyatagi Ankara",
    "iso:country":"TR",
    "sg:address":"Iskitler Cd. No:62",
    "sg:city":"Kozyatagi",
    "sg:classifiers":[
        {
            "category":"Manufacturing",
            "subcategory":"Metals",
            "type":"Manufacturing & Wholesale Goods"
        }
    ],
    "sg:phone":"+90 312 342 0663",
    "sg:postcode":"34742",
    "sg:province":"Ankara",
    "sg:tags":[
        "iron-steel",
        "peoducts"
    ],
    "wof:name":"Tugcu Demir San. Tic. Ltd. Sti.",
    "wof:placetype":"venue"
},
  "geometry": {"coordinates":[36.3196144104,41.2798347473],"type":"Point"}
}