{
  "type": "Feature",
  "properties": {
    "addr:full":"Merkez K?? San. Sitesi 55/1 Ada, No:26 S?e Balikesir",
    "addr:housenumber":"55 / 1;?",
    "addr:street":"Ada No 26 S",
    "iso:country":"TR",
    "sg:address":"Merkez K?? San. Sitesi 55/1 Ada, No:26",
    "sg:city":"S?e",
    "sg:classifiers":[
        {
            "category":"Wholesale",
            "subcategory":"Machinery & Supplies",
            "type":"Manufacturing & Wholesale Goods"
        }
    ],
    "sg:phone":"+90 266 246 2800",
    "sg:province":"Balikesir",
    "sg:tags":[
        "agricultural"
    ],
    "wof:name":"?elmak Tarim Makina Tic. San. Ltd. Sti.",
    "wof:placetype":"venue"
},
  "geometry": {"coordinates":[27.8833007812,39.6520996094],"type":"Point"}
}