{
  "type": "Feature",
  "properties": {
    "iso:country":"TR",
    "sg:address":"Maltepe",
    "sg:city":"Gebze",
    "sg:classifiers":[
        {
            "category":"Marine",
            "type":"Transportation"
        }
    ],
    "sg:phone":"+90 216 441 7954",
    "sg:postcode":"41400",
    "sg:province":"Istanbul",
    "sg:tags":[
        "equipment",
        "maritime"
    ],
    "wof:name":"Shipdata",
    "wof:placetype":"venue"
},
  "geometry": {"coordinates":[28.919090271,41.032459259],"type":"Point"}
}