{
  "type": "Feature",
  "properties": {
    "iso:country":"TR",
    "sg:address":"Organize San.bol.",
    "sg:city":"Sungurlu",
    "sg:classifiers":[
        {
            "category":"Food & Beverages",
            "subcategory":"Candy",
            "type":"Retail Goods"
        }
    ],
    "sg:phone":"+90 338 224 1230",
    "sg:postcode":"19300",
    "sg:province":"Karaman",
    "sg:tags":[
        "biscuit-chocolate-candy"
    ],
    "wof:name":"Ani Biskuvi Ve Gida Sanayi Ve Ticaret A.s.",
    "wof:placetype":"venue"
},
  "geometry": {"coordinates":[33.221901,37.1814],"type":"Point"}
}