{
  "type": "Feature",
  "properties": {
    "addr:full":"Bagdat Pasaji No:101 Saray?n? Sanlurfa 63100",
    "addr:housenumber":"?;?",
    "addr:postcode":"63100",
    "addr:street":"No;Saray;N;Sanlurfa",
    "iso:country":"TR",
    "sg:address":"Bagdat Pasaji No:101",
    "sg:city":"Saray?n?",
    "sg:orig_category":"Bijouterie",
    "sg:phone":"+90 414 215 4501",
    "sg:postcode":"63100",
    "sg:province":"Sanlurfa",
    "wof:name":"Sedat Bijuteri",
    "wof:placetype":"venue"
},
  "geometry": {"coordinates":[44.3922,33.315701],"type":"Point"}
}