{
  "type": "Feature",
  "properties": {
    "addr:full":"Anadolu San. B?g. Demirtepe Sk. No:16 Gemlik Konya 16600",
    "addr:housenumber":"16",
    "addr:postcode":"16600",
    "addr:street":"Demirtepe Sk. No",
    "iso:country":"TR",
    "sg:address":"Anadolu San. B?g. Demirtepe Sk. No:16",
    "sg:city":"Gemlik",
    "sg:classifiers":[
        {
            "category":"Manufacturing",
            "subcategory":"Tools & Machinery",
            "type":"Manufacturing & Wholesale Goods"
        }
    ],
    "sg:phone":"+90 332 248 8000",
    "sg:postcode":"16600",
    "sg:province":"Konya",
    "sg:tags":[
        "machine",
        "industry"
    ],
    "wof:name":"Asya Motor Subaplari San. Sti.",
    "wof:placetype":"venue"
},
  "geometry": {"coordinates":[32.4990272522,37.8715362549],"type":"Point"}
}