{
  "type": "Feature",
  "properties": {
    "addr:full":"Millet Caddesi Mavi Saray Apartmani No:10 - Fatih Merkez Istanbul",
    "addr:housenumber":"mavi;apartmani no 10",
    "addr:street":"Millet Caddesi;Fatih",
    "iso:country":"TR",
    "sg:address":"Millet Caddesi Mavi Saray Apartmani No:10 - Fatih",
    "sg:city":"Merkez",
    "sg:classifiers":[
        {
            "category":"Health Services",
            "subcategory":"Medical Lab",
            "type":"Services"
        }
    ],
    "sg:phone":"+90 212 632 0409",
    "sg:province":"Istanbul",
    "wof:name":"Besen Tibbi Tahliller Laboratuvari",
    "wof:placetype":"venue"
},
  "geometry": {"coordinates":[28.9501304626,41.0054702759],"type":"Point"}
}