{
  "type": "Feature",
  "properties": {
    "addr:full":"Mithatpasa Cd. G?b? Sk. No:5 Kasimpasa Tuzla Istanbul 81700",
    "addr:housenumber":"? b ?",
    "addr:postcode":"81700",
    "addr:street":"Mithatpasa Cd. G;Sk. No 5 Kasimpasa",
    "iso:country":"TR",
    "sg:address":"Mithatpasa Cd. G?b? Sk. No:5 Kasimpasa",
    "sg:city":"Tuzla",
    "sg:classifiers":[
        {
            "category":"Home & Garden",
            "subcategory":"Household Appliances",
            "type":"Retail Goods"
        }
    ],
    "sg:phone":"+90 212 255 4053",
    "sg:postcode":"81700",
    "sg:province":"Istanbul",
    "sg:tags":[
        "kitchenware"
    ],
    "wof:name":"Istanbul ?elik Mutfak Imal. San.",
    "wof:placetype":"venue"
},
  "geometry": {"coordinates":[28.9995632172,41.0692329407],"type":"Point"}
}