{
  "type": "Feature",
  "properties": {
    "addr:full":"Sincap Sok. No:1 Esenkent-maltepe Iskenderun Istanbul 326",
    "addr:housenumber":"no 1;326",
    "addr:street":"Sincap Sok.;Esenkent-Maltepe",
    "iso:country":"TR",
    "sg:address":"Sincap Sok. No:1 Esenkent-maltepe",
    "sg:city":"Iskenderun",
    "sg:classifiers":[
        {
            "category":"Professional",
            "subcategory":"Employment Agencies",
            "type":"Services"
        }
    ],
    "sg:phone":"+90 216 376 6126",
    "sg:postcode":"326",
    "sg:province":"Istanbul",
    "sg:tags":[
        "machine"
    ],
    "wof:name":"Mse Buro Kirtasiye Dagitim",
    "wof:placetype":"venue"
},
  "geometry": {"coordinates":[29.1619434357,40.923625946],"type":"Point"}
}