{
  "type": "Feature",
  "properties": {
    "addr:full":"F.gizden Sk. Gayrettepe Bayrampasa Istanbul 36100",
    "addr:postcode":"36100",
    "addr:street":"F.Gizden Sk.",
    "iso:country":"TR",
    "sg:address":"F.gizden Sk. Gayrettepe",
    "sg:city":"Bayrampasa",
    "sg:classifiers":[
        {
            "category":"Communications",
            "subcategory":"Film & Video Production",
            "type":"Services"
        }
    ],
    "sg:phone":"+90 212 272 8602",
    "sg:postcode":"36100",
    "sg:province":"Istanbul",
    "sg:tags":[
        "-"
    ],
    "wof:name":"Mtv Film Video A.s.",
    "wof:placetype":"venue"
},
  "geometry": {"coordinates":[29.0048961639,41.0643348694],"type":"Point"}
}