{
  "type": "Feature",
  "properties": {
    "addr:full":"Yeni Cami Mh.zafer Cd.no59 Yenik? B?gesi Orhangazi Bursa 01000",
    "addr:postcode":"01000",
    "addr:street":"Mh.Zafer;Yenik;B",
    "iso:country":"TR",
    "sg:address":"Yeni Cami Mh.zafer Cd.no59 Yenik? B?gesi",
    "sg:city":"Orhangazi",
    "sg:classifiers":[
        {
            "category":"Freight",
            "type":"Transportation"
        }
    ],
    "sg:phone":"+90 224 585 4756",
    "sg:postcode":"01000",
    "sg:province":"Bursa",
    "sg:tags":[
        "agent",
        "shipping",
        "broker"
    ],
    "wof:name":"Meridyen Gida San.ltd.sti.",
    "wof:placetype":"venue"
},
  "geometry": {"coordinates":[29.058004,40.194756],"type":"Point"}
}