{
  "type": "Feature",
  "properties": {
    "iso:country":"TR",
    "sg:address":"At. Cad. 3.sk. No:11",
    "sg:city":"Dalaman",
    "sg:classifiers":[
        {
            "category":"Professional",
            "subcategory":"Engineering",
            "type":"Services"
        }
    ],
    "sg:phone":"+90 252 692 1113",
    "sg:postcode":"48770",
    "sg:province":"Mugla",
    "sg:tags":[
        "architect"
    ],
    "wof:name":"Altin Muhendislik",
    "wof:placetype":"venue"
},
  "geometry": {"coordinates":[28.3628406525,37.215675354],"type":"Point"}
}