{
  "type": "Feature",
  "properties": {
    "addr:full":"Necatibey Cad. No:88/7 Sihhiye Sisli Ankara 80270",
    "addr:housenumber":"88 / 7",
    "addr:postcode":"80270",
    "addr:street":"Necatibey Cad. No",
    "iso:country":"TR",
    "sg:address":"Necatibey Cad. No:88/7 Sihhiye",
    "sg:city":"Sisli",
    "sg:classifiers":[
        {
            "category":"Wholesale",
            "subcategory":"Machinery & Supplies",
            "type":"Manufacturing & Wholesale Goods"
        }
    ],
    "sg:phone":"+90 312 229 9323",
    "sg:postcode":"80270",
    "sg:province":"Ankara",
    "sg:tags":[
        "laboratory",
        "equipment"
    ],
    "wof:name":"Duzen San. Tic. Ltd. Sti.",
    "wof:placetype":"venue"
},
  "geometry": {"coordinates":[32.842048645,39.9196357727],"type":"Point"}
}