{
  "type": "Feature",
  "properties": {
    "addr:full":"Semsettin G. Cd. No:121/1 Erenk? Esenler Istanbul 34200",
    "addr:housenumber":"no;/ 1 erenk ?",
    "addr:postcode":"34200",
    "addr:street":"Semsettin G. Cd.",
    "iso:country":"TR",
    "sg:address":"Semsettin G. Cd. No:121/1 Erenk?",
    "sg:city":"Esenler",
    "sg:classifiers":[
        {
            "category":"Wholesale",
            "subcategory":"Durable Goods & Equipment",
            "type":"Manufacturing & Wholesale Goods"
        }
    ],
    "sg:phone":"+90 216 362 0690",
    "sg:postcode":"34200",
    "sg:province":"Istanbul",
    "sg:tags":[
        "consumer"
    ],
    "wof:name":"Top?ular Bina Donat. Malz. Tic.",
    "wof:placetype":"venue"
},
  "geometry": {"coordinates":[28.9861831665,41.0408554077],"type":"Point"}
}