{
  "type": "Feature",
  "properties": {
    "iso:country":"TR",
    "sg:address":"Baglarbasi Cd. Akincilar Sok.no:16",
    "sg:city":"Gaziosmanpasa",
    "sg:classifiers":[
        {
            "category":"Food & Beverages",
            "subcategory":"Groceries & Convenience Stores",
            "type":"Retail Goods"
        }
    ],
    "sg:phone":"+90 212 564 3051",
    "sg:postcode":"01950",
    "sg:province":"Istanbul",
    "sg:tags":[
        "drink-",
        "soft"
    ],
    "wof:name":"?obanpinar I?me Suyu",
    "wof:placetype":"venue"
},
  "geometry": {"coordinates":[28.924641,41.05595],"type":"Point"}
}