{
  "type": "Feature",
  "properties": {
    "iso:country":"TR",
    "sg:address":"Resatbey Mah. Ordu Cad. Meziyet Hanim Apt. Zemin Kat Seyhan",
    "sg:city":"Erenkoy",
    "sg:classifiers":[
        {
            "category":"Professional",
            "subcategory":"Computer Services",
            "type":"Services"
        }
    ],
    "sg:phone":"+90 322 458 9950",
    "sg:postcode":"07060",
    "sg:province":"Adana",
    "sg:tags":[
        "application",
        "software"
    ],
    "wof:name":"Ayser Bilgisayar",
    "wof:placetype":"venue"
},
  "geometry": {"coordinates":[35.3250198364,36.9854202271],"type":"Point"}
}