{
  "type": "Feature",
  "properties": {
    "iso:country":"TR",
    "sg:address":"Inkilap Mah. Cumhuriyet Cad. No:10 Umraniye",
    "sg:city":"Ikitelli/K\u00fc\u00e7\u00fck\u00e7ekmece",
    "sg:orig_category":"Aluminium Carpentary",
    "sg:phone":"+90 216 461 7825",
    "sg:postcode":"34670",
    "sg:province":"Istanbul",
    "wof:name":"Yapisan Aluminyum Mimarlik Ve Dekorasyon Ltd.sti.",
    "wof:placetype":"venue"
},
  "geometry": {"coordinates":[29.1099872589,41.0362472534],"type":"Point"}
}