{
  "type": "Feature",
  "properties": {
    "iso:country":"TR",
    "sg:address":"Org. San. B?g. 1.cad. No:1 Ineg?",
    "sg:city":"Kagithane",
    "sg:classifiers":[
        {
            "category":"Wholesale",
            "subcategory":"Home Furnishings",
            "type":"Manufacturing & Wholesale Goods"
        }
    ],
    "sg:phone":"+90 224 714 8068",
    "sg:postcode":"34406",
    "sg:province":"Bursa",
    "sg:tags":[
        "furniture"
    ],
    "wof:name":"Nurhas Mobilya San. Tic.",
    "wof:placetype":"venue"
},
  "geometry": {"coordinates":[29.0586109161,40.1844291687],"type":"Point"}
}