{
  "type": "Feature",
  "properties": {
    "iso:country":"TR",
    "sg:address":"Amasya",
    "sg:city":"Karabaglar",
    "sg:classifiers":[
        {
            "category":"Government",
            "subcategory":"Office",
            "type":"Public Place"
        }
    ],
    "sg:phone":"+90 358 513 1158",
    "sg:postcode":"44210",
    "sg:province":"Amasya",
    "sg:tags":[
        "army"
    ],
    "wof:name":"Merzifon (g?m?shacik?y, Hamam?z?) Askerlik Subesi",
    "wof:placetype":"venue"
},
  "geometry": {"coordinates":[35.8135032654,40.6473884583],"type":"Point"}
}