{
  "type": "Feature",
  "properties": {
    "iso:country":"TR",
    "sg:address":"Bursa Yolu 5. Km.",
    "sg:city":"Harbiye",
    "sg:classifiers":[
        {
            "category":"Home & Garden",
            "subcategory":"Kitchen Supply",
            "type":"Retail Goods"
        }
    ],
    "sg:phone":"+90 222 320 1738",
    "sg:postcode":"31080",
    "sg:province":"Eskisehir",
    "sg:tags":[
        "steel",
        "utensil"
    ],
    "wof:name":"Ko?ak Mak. ?elik Esya San. Tic. A.s.",
    "wof:placetype":"venue"
},
  "geometry": {"coordinates":[30.517546,39.770081],"type":"Point"}
}