{
  "type": "Feature",
  "properties": {
    "addr:full":"B??dere Cad. No:8 K.6 Sisli Asagi Ayranci Istanbul",
    "addr:housenumber":"? ?",
    "addr:street":"B;Dere Cad. No 8 K.6 Sisli Asagi",
    "iso:country":"TR",
    "sg:address":"B??dere Cad. No:8 K.6 Sisli",
    "sg:city":"Asagi Ayranci",
    "sg:classifiers":[
        {
            "category":"Banks & Credit Unions",
            "subcategory":"Financial Services",
            "type":"Services"
        }
    ],
    "sg:phone":"+90 212 241 1822",
    "sg:province":"Istanbul",
    "sg:tags":[
        "finance"
    ],
    "wof:name":"Can Menkul Degerler A.s",
    "wof:placetype":"venue"
},
  "geometry": {"coordinates":[29.0041370392,41.0473022461],"type":"Point"}
}