{
  "type": "Feature",
  "properties": {
    "addr:full":"Rihtim Cad. No:69/a Karak? Fomara Istanbul",
    "addr:housenumber":"69 / a;?",
    "addr:street":"Rihtim Cad. No;Karak",
    "iso:country":"TR",
    "sg:address":"Rihtim Cad. No:69/a Karak?",
    "sg:city":"Fomara",
    "sg:classifiers":[
        {
            "category":"Wholesale",
            "subcategory":"Medical Equipment & Supplies",
            "type":"Manufacturing & Wholesale Goods"
        }
    ],
    "sg:phone":"+90 212 244 6959",
    "sg:province":"Istanbul",
    "sg:tags":[
        "material"
    ],
    "wof:name":"Ozcan Kardesler Tip A.s.",
    "wof:placetype":"venue"
},
  "geometry": {"coordinates":[28.9759254456,41.0123786926],"type":"Point"}
}