{
  "type": "Feature",
  "properties": {
    "addr:full":"Sumer Mah. 2508 Sok. No:28 Fatih Denizli 34280",
    "addr:housenumber":"no",
    "addr:postcode":"2508;34280",
    "addr:street":"Mah.;Sok.;Fatih",
    "iso:country":"TR",
    "sg:address":"Sumer Mah. 2508 Sok. No:28",
    "sg:city":"Fatih",
    "sg:classifiers":[
        {
            "category":"Manufacturing",
            "subcategory":"Metals",
            "type":"Manufacturing & Wholesale Goods"
        }
    ],
    "sg:phone":"+90 258 264 0598",
    "sg:postcode":"34280",
    "sg:province":"Denizli",
    "sg:tags":[
        "iron-steel",
        "peoducts"
    ],
    "wof:name":"Ademsan",
    "wof:placetype":"venue"
},
  "geometry": {"coordinates":[29.0852451324,37.7921676636],"type":"Point"}
}