{
  "type": "Feature",
  "properties": {
    "addr:full":"Organize Sanayi B?gesi 5. Cadde Bayrampasa Malatya 36100",
    "addr:housenumber":"?;bayrampasa",
    "addr:postcode":"36100",
    "addr:street":"Organize Sanayi B;Gesi 5 Cadde",
    "iso:country":"TR",
    "sg:address":"Organize Sanayi B?gesi 5. Cadde",
    "sg:city":"Bayrampasa",
    "sg:classifiers":[
        {
            "category":"Shopping",
            "subcategory":"Crafts & Fabrics",
            "type":"Retail Goods"
        }
    ],
    "sg:phone":"+90 422 237 5500",
    "sg:postcode":"36100",
    "sg:province":"Malatya",
    "sg:tags":[
        "yarn"
    ],
    "wof:name":"Penteks Iplik",
    "wof:placetype":"venue"
},
  "geometry": {"coordinates":[38.3143005371,38.3474998474],"type":"Point"}
}