{
  "type": "Feature",
  "properties": {
    "iso:country":"TR",
    "sg:address":"Izzetpasa Mah Gazi",
    "sg:city":"Elazig",
    "sg:classifiers":[
        {
            "category":"Banks & Credit Unions",
            "subcategory":"Bank",
            "type":"Services"
        }
    ],
    "sg:phone":"+90 424 238 7050",
    "sg:postcode":"23000",
    "sg:province":"23200",
    "wof:name":"S?erbank As",
    "wof:placetype":"venue"
},
  "geometry": {"coordinates":[39.215679,38.675396],"type":"Point"}
}