{
  "type": "Feature",
  "properties": {
    "iso:country":"TR",
    "sg:address":"Yeni Sanayi Sitesi D -14 Blok No:19-20",
    "sg:city":"Nazilli",
    "sg:classifiers":[
        {
            "category":"Home & Garden",
            "subcategory":"Hardware",
            "type":"Retail Goods"
        }
    ],
    "sg:phone":"+90 256 316 1634",
    "sg:postcode":"65600",
    "sg:province":"Aydin",
    "sg:tags":[
        "store"
    ],
    "wof:name":"Ozkanlar Testere Sanayi",
    "wof:placetype":"venue"
},
  "geometry": {"coordinates":[27.8324394226,37.8409690857],"type":"Point"}
}