{
  "type": "Feature",
  "properties": {
    "addr:full":"Bah?lievler Mah. Camlik Sk. No:30/a Mersin ?orum 52750",
    "addr:housenumber":"30 / a;?",
    "addr:postcode":"52750",
    "addr:street":"Lievler Mah. Camlik Sk. No",
    "iso:country":"TR",
    "sg:address":"Bah?lievler Mah. Camlik Sk. No:30/a",
    "sg:city":"Mersin",
    "sg:classifiers":[
        {
            "category":"Wholesale",
            "subcategory":"Medical Equipment & Supplies",
            "type":"Manufacturing & Wholesale Goods"
        }
    ],
    "sg:phone":"+90 364 224 6119",
    "sg:postcode":"52750",
    "sg:province":"?orum",
    "wof:name":"Asya Medikal",
    "wof:placetype":"venue"
},
  "geometry": {"coordinates":[37.7128486633,41.0530204773],"type":"Point"}
}