{
  "type": "Feature",
  "properties": {
    "iso:country":"TR",
    "sg:address":"Istiklal Cad 89",
    "sg:city":"Mersin",
    "sg:classifiers":[
        {
            "category":"Banks & Credit Unions",
            "subcategory":"Bank",
            "type":"Services"
        }
    ],
    "sg:phone":"+90 324 233 9308",
    "sg:postcode":"52750",
    "sg:province":"33070",
    "wof:name":"Esbank Eskisehir, Bankasi Tas",
    "wof:placetype":"venue"
},
  "geometry": {"coordinates":[29.093771,37.769001],"type":"Point"}
}