{
  "type": "Feature",
  "properties": {
    "addr:full":"Cebeci Cad.594.sok.no:7 G.o.pasa Istanbul",
    "addr:housenumber":"7",
    "addr:street":"G.O.Pasa",
    "iso:country":"TR",
    "sg:address":"Cebeci Cad.594.sok.no:7",
    "sg:city":"G.o.pasa",
    "sg:classifiers":[
        {
            "category":"Building & Trades",
            "subcategory":"Electrical",
            "type":"Services"
        }
    ],
    "sg:phone":"+90 212 649 4998",
    "sg:province":"Istanbul",
    "sg:tags":[
        "equipment",
        "lighting"
    ],
    "wof:name":"Dortler Avize Cam San.tic.ltd.sti.",
    "wof:placetype":"venue"
},
  "geometry": {"coordinates":[28.9027690887,41.0778083801],"type":"Point"}
}