{
  "type": "Feature",
  "properties": {
    "addr:full":"Imes San. Sit. E 501/21 ?mraniye Bayrampasa Istanbul 36100",
    "addr:housenumber":"501 / 21 ?",
    "addr:postcode":"36100",
    "addr:street":"Mraniye Bayrampasa",
    "iso:country":"TR",
    "sg:address":"Imes San. Sit. E 501/21 ?mraniye",
    "sg:city":"Bayrampasa",
    "sg:classifiers":[
        {
            "category":"Manufacturing",
            "subcategory":"Rubber & Plastics",
            "type":"Manufacturing & Wholesale Goods"
        }
    ],
    "sg:phone":"+90 216 374 3486",
    "sg:postcode":"36100",
    "sg:province":"Istanbul",
    "sg:tags":[
        "industry"
    ],
    "wof:name":"Tekno Polimer M?hendis. Plastik San. Tic. A.s.",
    "wof:placetype":"venue"
},
  "geometry": {"coordinates":[28.9759254456,41.0123786926],"type":"Point"}
}