{
  "type": "Feature",
  "properties": {
    "iso:country":"TR",
    "sg:address":"Demirciler San. No:15",
    "sg:city":"Iskenderun",
    "sg:classifiers":[
        {
            "category":"Mining & Drilling",
            "type":"Manufacturing & Wholesale Goods"
        }
    ],
    "sg:phone":"+90 332 233 3415",
    "sg:postcode":"31200",
    "sg:province":"Konya",
    "sg:tags":[
        "industry",
        "mine"
    ],
    "wof:name":"Seka San Seri Krom San. A.s.",
    "wof:placetype":"venue"
},
  "geometry": {"coordinates":[32.4990272522,37.8715362549],"type":"Point"}
}