{
  "type": "Feature",
  "properties": {
    "addr:full":"Ziyabey Cad. No:62/4 Balgat Pendik Ankara 34916",
    "addr:housenumber":"62 / 4",
    "addr:postcode":"34916",
    "addr:street":"Ziyabey Cad. No;Balgat",
    "iso:country":"TR",
    "sg:address":"Ziyabey Cad. No:62/4 Balgat",
    "sg:city":"Pendik",
    "sg:classifiers":[
        {
            "category":"Military Area",
            "subcategory":"Coast Guard Base",
            "type":"Public Place"
        }
    ],
    "sg:phone":"+90 312 284 6385",
    "sg:postcode":"34916",
    "sg:province":"Ankara",
    "sg:tags":[
        "industry",
        "defence"
    ],
    "wof:name":"Mft Group",
    "wof:placetype":"venue"
},
  "geometry": {"coordinates":[32.8604812622,39.9429283142],"type":"Point"}
}