{
  "type": "Feature",
  "properties": {
    "iso:country":"TR",
    "sg:address":"Adnan Menderes Hava Limani Teknik Blok Yan Girisi",
    "sg:city":"Ikitelli",
    "sg:classifiers":[
        {
            "category":"Banks & Credit Unions",
            "subcategory":"Investment Brokerage",
            "type":"Services"
        }
    ],
    "sg:phone":"+90 232 274 2259",
    "sg:postcode":"34306",
    "sg:province":"Izmir",
    "sg:tags":[
        "aid",
        "material",
        "first"
    ],
    "wof:name":"Redstar Havacilik",
    "wof:placetype":"venue"
},
  "geometry": {"coordinates":[27.1296863556,38.4186973572],"type":"Point"}
}