{
  "type": "Feature",
  "properties": {
    "addr:full":"Mehmet Atay Bolvadin Antalya 03300",
    "addr:postcode":"03300",
    "iso:country":"TR",
    "sg:address":"Mehmet Atay",
    "sg:city":"Bolvadin",
    "sg:classifiers":[
        {
            "category":"Government",
            "subcategory":"Office",
            "type":"Public Place"
        }
    ],
    "sg:phone":"+90 242 334 8259",
    "sg:postcode":"03300",
    "sg:province":"Antalya",
    "sg:tags":[
        "municipality"
    ],
    "wof:name":"Kepez Belediye Baskani",
    "wof:placetype":"venue"
},
  "geometry": {"coordinates":[32.48387146,37.9245910645],"type":"Point"}
}