{
  "type": "Feature",
  "properties": {
    "addr:full":"Tesvikiye Cad. Ikbal Is Mrk. No.103 K.7 Sisli Iskenderun Istanbul 31200",
    "addr:housenumber":"no.103 k.7",
    "addr:postcode":"31200",
    "addr:street":"Tesvikiye Cad. Ikbal;Mrk.",
    "iso:country":"TR",
    "sg:address":"Tesvikiye Cad. Ikbal Is Mrk. No.103 K.7 Sisli",
    "sg:city":"Iskenderun",
    "sg:classifiers":[
        {
            "category":"Banks & Credit Unions",
            "subcategory":"Financial Services",
            "type":"Services"
        }
    ],
    "sg:phone":"+90 212 236 6869",
    "sg:postcode":"31200",
    "sg:province":"Istanbul",
    "sg:tags":[
        "finance"
    ],
    "wof:name":"Alan Menkul Degerler",
    "wof:placetype":"venue"
},
  "geometry": {"coordinates":[28.9759254456,41.0123786926],"type":"Point"}
}