{
  "type": "Feature",
  "properties": {
    "addr:full":"Bagdat Cad. 106. Feneryolu Istanbul 34724",
    "addr:housenumber":"106",
    "addr:postcode":"34724",
    "addr:street":"Bagdat Cad.",
    "iso:country":"TR",
    "sg:address":"Bagdat Cad. 106.",
    "sg:city":"Feneryolu",
    "sg:classifiers":[
        {
            "category":"Manufacturing",
            "subcategory":"Food",
            "type":"Manufacturing & Wholesale Goods"
        }
    ],
    "sg:phone":"+90 216 469 0698",
    "sg:postcode":"34724",
    "sg:province":"Istanbul",
    "sg:tags":[
        "product",
        "floury",
        "macaroni"
    ],
    "wof:name":"Degirmen Unlu Mamuller A.s.",
    "wof:placetype":"venue"
},
  "geometry": {"coordinates":[29.0950565338,40.9536437988],"type":"Point"}
}