{
  "type": "Feature",
  "properties": {
    "addr:full":"E.b??dere Cad. No.17 4.levent Istanbul",
    "addr:housenumber":"? ?;4.levent",
    "addr:street":"Dere Cad. No.17",
    "iso:country":"TR",
    "sg:address":"E.b??dere Cad. No.17",
    "sg:city":"4.levent",
    "sg:classifiers":[
        {
            "category":"Shopping",
            "subcategory":"Clothing, Apparel, & Fashions",
            "type":"Retail Goods"
        }
    ],
    "sg:phone":"+90 212 280 6056",
    "sg:province":"Istanbul",
    "sg:tags":[
        "ready",
        "wear"
    ],
    "wof:name":"Model Giyim A.s.",
    "wof:placetype":"venue"
},
  "geometry": {"coordinates":[29.2392463684,41.0333061218],"type":"Point"}
}