{
  "type": "Feature",
  "properties": {
    "addr:full":"Medeni Aziz Efendi Sok. Yeniyol Cik. 1/7 Topkapi-maltepe Istanbul Mersin Istanbul 52750",
    "addr:housenumber":"1 / 7",
    "addr:postcode":"52750",
    "addr:street":"Efendi Sok. Yeniyol Cik.",
    "iso:country":"TR",
    "sg:address":"Medeni Aziz Efendi Sok. Yeniyol Cik. 1/7 Topkapi-maltepe Istanbul",
    "sg:city":"Mersin",
    "sg:classifiers":[
        {
            "category":"Wholesale",
            "subcategory":"Auto Parts",
            "type":"Manufacturing & Wholesale Goods"
        }
    ],
    "sg:phone":"+90 212 567 2172",
    "sg:postcode":"52750",
    "sg:province":"Istanbul",
    "sg:tags":[
        "spare"
    ],
    "wof:name":"Yenig?n Rondela Iml.ltd.sti.",
    "wof:placetype":"venue"
},
  "geometry": {"coordinates":[28.9861831665,41.0408554077],"type":"Point"}
}