{
  "type": "Feature",
  "properties": {
    "addr:full":"Kazim Ozalp Cad. Cumhuriyet Apt. No:38/5 Sahinbakkal Sisli Istanbul 65710",
    "addr:postcode":"65710",
    "addr:street":"Ozalp Cad.",
    "iso:country":"TR",
    "sg:address":"Kazim Ozalp Cad. Cumhuriyet Apt. No:38/5 Sahinbakkal",
    "sg:city":"Sisli",
    "sg:orig_category":"Beaty Parlors",
    "sg:phone":"+90 21635695723695",
    "sg:postcode":"65710",
    "sg:province":"Istanbul",
    "wof:name":"Pelin Estetik",
    "wof:placetype":"venue"
},
  "geometry": {"coordinates":[28.975925,41.012379],"type":"Point"}
}