{
  "type": "Feature",
  "properties": {
    "iso:country":"TR",
    "sg:address":"Org. San. B?g. 8. Cd.",
    "sg:city":"Ikitelli/K\u00fc\u00e7\u00fck\u00e7ekmece",
    "sg:classifiers":[
        {
            "category":"Home & Garden",
            "subcategory":"Kitchen Supply",
            "type":"Retail Goods"
        }
    ],
    "sg:phone":"+90 222 236 0167",
    "sg:postcode":"34670",
    "sg:province":"Eskisehir",
    "sg:tags":[
        "wardrobe"
    ],
    "wof:name":"Femosan Mutfak Dolap San.",
    "wof:placetype":"venue"
},
  "geometry": {"coordinates":[30.5175457001,39.7700805664],"type":"Point"}
}