{
  "type": "Feature",
  "properties": {
    "iso:country":"TR",
    "sg:address":"Gatem Sekerciler Ve Kuruyemisciler Sit. 13.blok No:29-31",
    "sg:city":"G.o.pasa",
    "sg:orig_category":"Dryfood-dried Nuts",
    "sg:phone":"+90 34223815402310",
    "sg:province":"Gaziantep",
    "wof:name":"Me-as Tarim Urunleri Gida Sanayi Ticaret Ltd.",
    "wof:placetype":"venue"
},
  "geometry": {"coordinates":[37.4416732788,36.9459457397],"type":"Point"}
}