{
  "type": "Feature",
  "properties": {
    "addr:full":"Dikmen Cad.no: 323/2 Dikmen \u00c7ankaya Ankara 06450",
    "addr:housenumber":"323 / 2",
    "addr:postcode":"06450",
    "iso:country":"TR",
    "sg:address":"Dikmen Cad.no: 323/2 Dikmen",
    "sg:city":"\u00c7ankaya",
    "sg:classifiers":[
        {
            "category":"Home & Garden",
            "subcategory":"Garden Supply",
            "type":"Retail Goods"
        }
    ],
    "sg:phone":"+90 31248123214831",
    "sg:postcode":"06450",
    "sg:province":"Ankara",
    "sg:tags":[
        "transport"
    ],
    "wof:name":"?amoglu Nakliyat Ve Tic.ltd.sti",
    "wof:placetype":"venue"
},
  "geometry": {"coordinates":[32.8604812622,39.9429283142],"type":"Point"}
}