{
  "type": "Feature",
  "properties": {
    "addr:full":"Demirhane Cad. No:182 34770 Zeytinburnu Istanbul Adalar Istanbul 81340",
    "addr:housenumber":"182",
    "addr:postcode":"34770;81340",
    "addr:street":"Demirhane Cad. No",
    "iso:country":"TR",
    "sg:address":"Demirhane Cad. No:182 34770 Zeytinburnu Istanbul",
    "sg:city":"Adalar",
    "sg:classifiers":[
        {
            "category":"Manufacturing",
            "subcategory":"Paper Products",
            "type":"Manufacturing & Wholesale Goods"
        }
    ],
    "sg:phone":"+90 212 679 9818",
    "sg:postcode":"81340",
    "sg:province":"Istanbul",
    "sg:tags":[
        "cardboard"
    ],
    "wof:name":"Ciasan Kraft Torba Mablaj San Tic As",
    "wof:placetype":"venue"
},
  "geometry": {"coordinates":[28.8862075806,40.9811592102],"type":"Point"}
}