{
  "type": "Feature",
  "properties": {
    "addr:full":"Ali ?etinkaya Cd. Mersin Antalya 52750",
    "addr:postcode":"52750",
    "addr:street":"Etinkaya Cd.",
    "iso:country":"TR",
    "sg:address":"Ali ?etinkaya Cd.",
    "sg:city":"Mersin",
    "sg:classifiers":[
        {
            "category":"Manufacturing",
            "subcategory":"Glass & Minerals",
            "type":"Manufacturing & Wholesale Goods"
        }
    ],
    "sg:phone":"+90 242 321 6835",
    "sg:postcode":"52750",
    "sg:province":"Antalya",
    "sg:tags":[
        "glassware"
    ],
    "wof:name":"Yavuz Cam Pazarlama A.s.",
    "wof:placetype":"venue"
},
  "geometry": {"coordinates":[30.7182064056,36.8887214661],"type":"Point"}
}