{
  "type": "Feature",
  "properties": {
    "addr:full":"Istanbul Hilton Girisi Harbiye Istanbul 31080",
    "addr:postcode":"31080",
    "iso:country":"TR",
    "sg:address":"Istanbul Hilton Girisi",
    "sg:city":"Harbiye",
    "sg:classifiers":[
        {
            "category":"Banks & Credit Unions",
            "subcategory":"Investment Brokerage",
            "type":"Services"
        }
    ],
    "sg:phone":"+90 212 233 3820",
    "sg:postcode":"31080",
    "sg:province":"Istanbul",
    "sg:tags":[
        "line",
        "air"
    ],
    "wof:name":"Delta Airlines",
    "wof:placetype":"venue"
},
  "geometry": {"coordinates":[28.9759254456,41.0123786926],"type":"Point"}
}