{
  "type": "Feature",
  "properties": {
    "addr:full":"Postane Mh.rauf Orbay Cd.no2 Tuzla Istanbul 01900",
    "addr:postcode":"01900",
    "iso:country":"TR",
    "sg:address":"Postane Mh.rauf Orbay Cd.no2",
    "sg:city":"Tuzla",
    "sg:classifiers":[
        {
            "category":"Manufacturing",
            "subcategory":"Watercraft",
            "type":"Manufacturing & Wholesale Goods"
        }
    ],
    "sg:phone":"+90 216 395 7575",
    "sg:postcode":"01900",
    "sg:province":"Istanbul",
    "sg:tags":[
        "builder",
        "yacht",
        "trough"
    ],
    "wof:name":"Dearsan Gemi San.a.s.",
    "wof:placetype":"venue"
},
  "geometry": {"coordinates":[28.9759254456,41.0123786926],"type":"Point"}
}