{
  "type": "Feature",
  "properties": {
    "addr:full":"D?rt Yol Sanayi ?rs.b?lge Trafik Karsisi Hanli Sakarya 38700",
    "addr:housenumber":"sanayi ?;?",
    "addr:postcode":"38700",
    "addr:street":"Rt Yol;Rs.B",
    "iso:country":"TR",
    "sg:address":"D?rt Yol Sanayi ?rs.b?lge Trafik Karsisi",
    "sg:city":"Hanli",
    "sg:classifiers":[
        {
            "category":"Wholesale",
            "subcategory":"Auto Parts",
            "type":"Manufacturing & Wholesale Goods"
        }
    ],
    "sg:phone":"+90 264 275 2944",
    "sg:postcode":"38700",
    "sg:province":"Sakarya",
    "sg:tags":[
        "spare"
    ],
    "wof:name":"G?? Bir Isuzu Yedek Par?a Bayii",
    "wof:placetype":"venue"
},
  "geometry": {"coordinates":[30.3791446686,40.7734336853],"type":"Point"}
}