{
  "type": "Feature",
  "properties": {
    "addr:full":"Litros Yolu 4/1 Topkapi 27020 Istanbul",
    "addr:housenumber":"4 / 1",
    "addr:postcode":"27020",
    "addr:street":"Litros Yolu;Topkapi",
    "iso:country":"TR",
    "sg:address":"Litros Yolu 4/1 Topkapi",
    "sg:city":"27020",
    "sg:classifiers":[
        {
            "category":"Wholesale",
            "subcategory":"Medical Equipment & Supplies",
            "type":"Manufacturing & Wholesale Goods"
        }
    ],
    "sg:phone":"+90 212 613 1527",
    "sg:province":"Istanbul",
    "wof:name":"Bursan A.s.",
    "wof:placetype":"venue"
},
  "geometry": {"coordinates":[28.9364204407,41.0178985596],"type":"Point"}
}