{
  "type": "Feature",
  "properties": {
    "iso:country":"TR",
    "sg:address":"G??suyu Cd. Bestekar Medeni Aziz Efen. Sk. Karakaya Han No:58/1 Maltepe",
    "sg:city":"\u00dcmraniye",
    "sg:orig_category":"General Industrial Products",
    "sg:phone":"+90 212 501 3452",
    "sg:province":"Istanbul",
    "wof:name":"G.m.p. Genel Motor Pazar.",
    "wof:placetype":"venue"
},
  "geometry": {"coordinates":[28.9126701355,41.0204658508],"type":"Point"}
}