{
  "type": "Feature",
  "properties": {
    "iso:country":"TR",
    "sg:address":"Muradiye Mah. Konak Ishani 16/37 Orhangazi",
    "sg:city":"Altindag",
    "sg:classifiers":[
        {
            "category":"Utilities",
            "subcategory":"Recycling",
            "type":"Services"
        }
    ],
    "sg:phone":"+90 224 573 9352",
    "sg:postcode":"35380",
    "sg:province":"Bursa",
    "sg:tags":[
        "measuring",
        "weighing"
    ],
    "wof:name":"K.r.c. Elektronik Ltd.sti.",
    "wof:placetype":"venue"
},
  "geometry": {"coordinates":[29.0586109161,40.1844291687],"type":"Point"}
}