{
  "type": "Feature",
  "properties": {
    "addr:full":"Yeni Yalova Yolu 100 Ikitelli Bursa 34306",
    "addr:housenumber":"100",
    "addr:postcode":"34306",
    "addr:street":"Yalova Yolu;Bursa",
    "iso:country":"TR",
    "sg:address":"Yeni Yalova Yolu 100",
    "sg:city":"Ikitelli",
    "sg:classifiers":[
        {
            "category":"Farming",
            "subcategory":"Fish & Marine Products",
            "type":"Manufacturing & Wholesale Goods"
        }
    ],
    "sg:phone":"+90 224 254 1136",
    "sg:postcode":"34306",
    "sg:province":"Bursa",
    "sg:tags":[
        "automotive"
    ],
    "wof:name":"Seyhoglu Otomotiv San. Tic. A.s.",
    "wof:placetype":"venue"
},
  "geometry": {"coordinates":[29.0608615875,40.2032012939],"type":"Point"}
}