{
  "type": "Feature",
  "properties": {
    "iso:country":"TR",
    "sg:address":"Adnan Menderes Terminali No:2",
    "sg:city":"Karatay",
    "sg:classifiers":[
        {
            "category":"Travel",
            "subcategory":"Travel Agent",
            "type":"Entertainment"
        }
    ],
    "sg:phone":"+90 384 212 8275",
    "sg:postcode":"42000",
    "sg:province":"Nevsehir",
    "sg:tags":[
        "agency",
        "tourism"
    ],
    "wof:name":"Rock Town Turizm",
    "wof:placetype":"venue"
},
  "geometry": {"coordinates":[34.7110939026,38.6325645447],"type":"Point"}
}