{
  "type": "Feature",
  "properties": {
    "addr:full":"C G?sel Cad. 10. Sk. B??an Apt. No:42/1 Alsancak Adana 01365",
    "addr:housenumber":"?;10;b ? ?;42 / 1",
    "addr:postcode":"01365",
    "addr:street":"C G;Cad.;An Apt. No",
    "iso:country":"TR",
    "sg:address":"C G?sel Cad. 10. Sk. B??an Apt. No:42/1",
    "sg:city":"Alsancak",
    "sg:classifiers":[
        {
            "category":"Manufacturing",
            "subcategory":"Chemicals & Compounds",
            "type":"Manufacturing & Wholesale Goods"
        }
    ],
    "sg:phone":"+90 322 351 8870",
    "sg:postcode":"01365",
    "sg:province":"Adana",
    "sg:tags":[
        "medicine"
    ],
    "wof:name":"Altay Kimya Tic. Ltd.",
    "wof:placetype":"venue"
},
  "geometry": {"coordinates":[35.3137359619,37.0007171631],"type":"Point"}
}