{
  "type": "Feature",
  "properties": {
    "addr:full":"Acibadem Sarayardi Cad.no:58 D: 3 Kad\u0131k\u00f6y Istanbul 34990",
    "addr:housenumber":"58 d 3",
    "addr:postcode":"34990",
    "addr:street":"Cad.No",
    "iso:country":"TR",
    "sg:address":"Acibadem Sarayardi Cad.no:58 D: 3",
    "sg:city":"Kad\u0131k\u00f6y",
    "sg:classifiers":[
        {
            "category":"Home & Garden",
            "subcategory":"Household Appliances",
            "type":"Retail Goods"
        }
    ],
    "sg:phone":"+90 216 428 7259",
    "sg:postcode":"34990",
    "sg:province":"Istanbul",
    "sg:tags":[
        "conditioner",
        "air"
    ],
    "wof:name":"Oztas Insaat Makina Elekt.tahh.tic.ltd.sti.",
    "wof:placetype":"venue"
},
  "geometry": {"coordinates":[29.0327301025,40.9977912903],"type":"Point"}
}