{
  "type": "Feature",
  "properties": {
    "addr:full":"136.sok.no:5 Koyundere -menemen Mersin Izmir 52750",
    "addr:housenumber":"5",
    "addr:postcode":"52750",
    "addr:street":"Koyundere Menemen",
    "iso:country":"TR",
    "sg:address":"136.sok.no:5 Koyundere -menemen",
    "sg:city":"Mersin",
    "sg:classifiers":[
        {
            "category":"Manufacturing",
            "subcategory":"Tools & Machinery",
            "type":"Manufacturing & Wholesale Goods"
        }
    ],
    "sg:phone":"+90 232 846 1616",
    "sg:postcode":"52750",
    "sg:province":"Izmir",
    "sg:tags":[
        "machine",
        "industry"
    ],
    "wof:name":"Izmir Muhndislik Musavirlik Makina Ve Demir Celik San.tic.ltd.sti.",
    "wof:placetype":"venue"
},
  "geometry": {"coordinates":[27.0563907623,38.5774612427],"type":"Point"}
}