{
  "type": "Feature",
  "properties": {
    "addr:full":"Baglar Mevkii Sarigul Cad. Guney Sok. No:24 Firuzkoy- Avcilar Istanbul 01350",
    "addr:housenumber":"no 24",
    "addr:postcode":"01350",
    "addr:street":"Baglar Mevkii Sarigul Cad. Guney Sok.",
    "iso:country":"TR",
    "sg:address":"Baglar Mevkii Sarigul Cad. Guney Sok. No:24 Firuzkoy-",
    "sg:city":"Avcilar",
    "sg:classifiers":[
        {
            "category":"Shopping",
            "subcategory":"Crafts & Fabrics",
            "type":"Retail Goods"
        }
    ],
    "sg:phone":"+90 2124283323279",
    "sg:postcode":"01350",
    "sg:province":"Istanbul",
    "sg:tags":[
        "knitting"
    ],
    "wof:name":"Pinar Orme San.tic.a.s.",
    "wof:placetype":"venue"
},
  "geometry": {"coordinates":[28.9759254456,41.0123786926],"type":"Point"}
}