{
  "type": "Feature",
  "properties": {
    "addr:full":"Sel?k Bey.mah.emeki.sk.no:10 Yildirim/mesken Bursa 16310",
    "addr:housenumber":"? k;10",
    "addr:postcode":"16310",
    "addr:street":"Sel;Bey.Mah.Emeki.Sk.No",
    "iso:country":"TR",
    "sg:address":"Sel?k Bey.mah.emeki.sk.no:10",
    "sg:city":"Yildirim/mesken",
    "sg:classifiers":[
        {
            "category":"Manufacturing",
            "subcategory":"Textiles",
            "type":"Manufacturing & Wholesale Goods"
        }
    ],
    "sg:phone":"+90 224 368 3601",
    "sg:postcode":"16310",
    "sg:province":"Bursa",
    "sg:tags":[
        "promotion",
        "printed"
    ],
    "wof:name":"K?ra ?anta Ve Promosyon ?r?leri",
    "wof:placetype":"venue"
},
  "geometry": {"coordinates":[29.1216163635,40.1824798584],"type":"Point"}
}