{
  "type": "Feature",
  "properties": {
    "addr:full":"Sanayi Sitesi 1 Blok No:19-12 Kiraz 35890 Bornova Izmir 35040",
    "addr:housenumber":"1 blok no 19-12",
    "addr:postcode":"35890;35040",
    "addr:street":"Sanayi Sitesi;Kiraz",
    "iso:country":"TR",
    "sg:address":"Sanayi Sitesi 1 Blok No:19-12 Kiraz 35890",
    "sg:city":"Bornova",
    "sg:classifiers":[
        {
            "category":"Manufacturing",
            "subcategory":"Tools & Machinery",
            "type":"Manufacturing & Wholesale Goods"
        }
    ],
    "sg:phone":"+90 232 572 3254",
    "sg:postcode":"35040",
    "sg:province":"Izmir",
    "sg:tags":[
        "machine",
        "industry"
    ],
    "wof:name":"Yildiz Rom?rk-seref Erkan",
    "wof:placetype":"venue"
},
  "geometry": {"coordinates":[27.2117557526,38.4634437561],"type":"Point"}
}