{
  "type": "Feature",
  "properties": {
    "iso:country":"TR",
    "sg:address":"Nazmi Toker Cad 15",
    "sg:city":"Kayseri",
    "sg:classifiers":[
        {
            "category":"Banks & Credit Unions",
            "subcategory":"Bank",
            "type":"Services"
        }
    ],
    "sg:phone":"+90 352 222 4695",
    "sg:postcode":"63600",
    "sg:province":"38040",
    "wof:name":"Osmanli Bankasi As",
    "wof:placetype":"venue"
},
  "geometry": {"coordinates":[35.488323,38.719925],"type":"Point"}
}