{
  "type": "Feature",
  "properties": {
    "addr:full":"Kale Mah.gazi Cad.g?han Is Hani No:51 Kat:1/2 Mersin Samsun 52750",
    "addr:housenumber":"?;no 51 kat 1 / 2",
    "addr:postcode":"52750",
    "addr:street":"Kale Mah.Gazi Cad.G;Is",
    "iso:country":"TR",
    "sg:address":"Kale Mah.gazi Cad.g?han Is Hani No:51 Kat:1/2",
    "sg:city":"Mersin",
    "sg:classifiers":[
        {
            "category":"Wholesale",
            "subcategory":"Medical Equipment & Supplies",
            "type":"Manufacturing & Wholesale Goods"
        }
    ],
    "sg:phone":"+90 362 435 5056",
    "sg:postcode":"52750",
    "sg:province":"Samsun",
    "wof:name":"Isitsel Elektro Medikal ?r?nler Tic.ve San.ltd.sti",
    "wof:placetype":"venue"
},
  "geometry": {"coordinates":[36.3381233215,41.2815742493],"type":"Point"}
}