{
  "type": "Feature",
  "properties": {
    "addr:full":"Ebekizi Sok No:6/4 Osmanbey Istanbul 63000",
    "addr:housenumber":"no 6 / 4",
    "addr:postcode":"63000",
    "addr:street":"Ebekizi Sok",
    "iso:country":"TR",
    "sg:address":"Ebekizi Sok No:6/4",
    "sg:city":"Osmanbey",
    "sg:classifiers":[
        {
            "category":"Shopping",
            "subcategory":"Clothing, Apparel, & Fashions",
            "type":"Retail Goods"
        }
    ],
    "sg:phone":"+90 212 219 4593",
    "sg:postcode":"63000",
    "sg:province":"Istanbul",
    "sg:tags":[
        "men",
        "wear"
    ],
    "wof:name":"Aytekstil Ins.turizm.san.tic.ltd.sti.",
    "wof:placetype":"venue"
},
  "geometry": {"coordinates":[28.9759254456,41.0123786926],"type":"Point"}
}