{
  "type": "Feature",
  "properties": {
    "iso:country":"TR",
    "sg:address":"4 Sor. No:6 Ostim",
    "sg:city":"Y.dudullu",
    "sg:orig_category":"General Industrial Products",
    "sg:phone":"+90 312 354 0443",
    "sg:province":"Ankara",
    "wof:name":"Tay ?elik Sogutma Mutfak Cihaz. San. Tic. Ltd. Sti.",
    "wof:placetype":"venue"
},
  "geometry": {"coordinates":[32.7929077148,39.9679489136],"type":"Point"}
}