{
  "type": "Feature",
  "properties": {
    "iso:country":"TR",
    "sg:address":"Naipli Mah. Aydin-izmir Asfalti Uzeri No:5/b",
    "sg:city":"Ortaklar",
    "sg:classifiers":[
        {
            "category":"Shopping",
            "subcategory":"Clothing, Apparel, & Fashions",
            "type":"Retail Goods"
        }
    ],
    "sg:phone":"+90 256 577 1787",
    "sg:postcode":"25320",
    "sg:province":"Aydin",
    "sg:tags":[
        "ready",
        "wear"
    ],
    "wof:name":"Efes Konf.",
    "wof:placetype":"venue"
},
  "geometry": {"coordinates":[27.470199585,37.8838996887],"type":"Point"}
}