{
  "type": "Feature",
  "properties": {
    "addr:full":"Organize Sanayi B?lgesi 3 Nolu Yol Merkez Elazig 23100",
    "addr:housenumber":"?;3",
    "addr:postcode":"23100",
    "addr:street":"Organize Sanayi B;Lgesi;Yol",
    "iso:country":"TR",
    "sg:address":"Organize Sanayi B?lgesi 3 Nolu Yol",
    "sg:city":"Merkez",
    "sg:classifiers":[
        {
            "category":"Banks & Credit Unions",
            "subcategory":"Investment Brokerage",
            "type":"Services"
        }
    ],
    "sg:phone":"+90 424 255 1221",
    "sg:postcode":"23100",
    "sg:province":"Elazig",
    "sg:tags":[
        "injection",
        "plastic"
    ],
    "wof:name":"Dagy?ce",
    "wof:placetype":"venue"
},
  "geometry": {"coordinates":[39.2229003906,38.6754989624],"type":"Point"}
}