{
  "type": "Feature",
  "properties": {
    "addr:full":"Santral Garaj ?iks. Iskenderun Denizli 31200",
    "addr:postcode":"? iks.;31200",
    "iso:country":"TR",
    "sg:address":"Santral Garaj ?iks.",
    "sg:city":"Iskenderun",
    "sg:classifiers":[
        {
            "category":"Wholesale",
            "subcategory":"Petroleum",
            "type":"Manufacturing & Wholesale Goods"
        }
    ],
    "sg:phone":"+90 258 262 1120",
    "sg:postcode":"31200",
    "sg:province":"Denizli",
    "wof:name":"Aydemir Petrol",
    "wof:placetype":"venue"
},
  "geometry": {"coordinates":[29.0864906311,37.773525238],"type":"Point"}
}