{
  "type": "Feature",
  "properties": {
    "addr:full":"Anafartalar Cad. 147/23 Kemeralti Izmit Izmir 41000",
    "addr:housenumber":"147 / 23",
    "addr:postcode":"41000",
    "addr:street":"Anafartalar Cad.;Izmit",
    "iso:country":"TR",
    "sg:address":"Anafartalar Cad. 147/23 Kemeralti",
    "sg:city":"Izmit",
    "sg:classifiers":[
        {
            "category":"Shopping",
            "subcategory":"Shoes",
            "type":"Retail Goods"
        }
    ],
    "sg:phone":"+90 232 441 7465",
    "sg:postcode":"41000",
    "sg:province":"Izmir",
    "wof:name":"Nezih Bebe",
    "wof:placetype":"venue"
},
  "geometry": {"coordinates":[27.129686,38.418697],"type":"Point"}
}