{
  "type": "Feature",
  "properties": {
    "addr:full":"Muratpasa Mh.muratpasa Sok. No:21/1 Aksaray Mersin Istanbul 52750",
    "addr:housenumber":"no 21 / 1",
    "addr:postcode":"52750",
    "addr:street":"Mh.Muratpasa Sok.",
    "iso:country":"TR",
    "sg:address":"Muratpasa Mh.muratpasa Sok. No:21/1 Aksaray",
    "sg:city":"Mersin",
    "sg:classifiers":[
        {
            "category":"Professional",
            "subcategory":"Business Services",
            "type":"Services"
        }
    ],
    "sg:phone":"+90 212 631 9166",
    "sg:postcode":"52750",
    "sg:province":"Istanbul",
    "sg:tags":[
        "food",
        "product",
        "exporter",
        "aricultural"
    ],
    "wof:name":"Kosova Company",
    "wof:placetype":"venue"
},
  "geometry": {"coordinates":[28.9476928711,41.0111808777],"type":"Point"}
}