{
  "type": "Feature",
  "properties": {
    "addr:full":"Kartalcik Sok. No:95 Siteler \u00dcmraniye Ankara",
    "addr:housenumber":"no 95",
    "addr:street":"Kartalcik Sok.",
    "iso:country":"TR",
    "sg:address":"Kartalcik Sok. No:95 Siteler",
    "sg:city":"\u00dcmraniye",
    "sg:orig_category":"Furniture Supplamentary",
    "sg:phone":"+90 312 349 4199",
    "sg:province":"Ankara",
    "wof:name":"Kutay Mobilya Ltd.sti.",
    "wof:placetype":"venue"
},
  "geometry": {"coordinates":[32.9021110535,39.956577301],"type":"Point"}
}