{
  "type": "Feature",
  "properties": {
    "addr:full":"Ataturk Bulvari No:30 Kemalpasa Izmir 01340",
    "addr:housenumber":"no 30",
    "addr:postcode":"01340",
    "addr:street":"Ataturk Bulvari;Kemalpasa Izmir",
    "iso:country":"TR",
    "sg:address":"Ataturk Bulvari No:30",
    "sg:city":"Kemalpasa",
    "sg:classifiers":[
        {
            "category":"Farming",
            "subcategory":"Farm",
            "type":"Manufacturing & Wholesale Goods"
        }
    ],
    "sg:phone":"+90 232 878 1040",
    "sg:postcode":"01340",
    "sg:province":"Izmir",
    "sg:tags":[
        "agricultural",
        "product"
    ],
    "wof:name":"Tekinler Tarim Ltd.sti.",
    "wof:placetype":"venue"
},
  "geometry": {"coordinates":[27.1719017029,38.2936973572],"type":"Point"}
}