{
  "type": "Feature",
  "properties": {
    "addr:full":"Ankara Asfalti Uzeri No:230 Akincilar Izmir 01220",
    "addr:postcode":"01220",
    "addr:street":"No;Akincilar",
    "iso:country":"TR",
    "sg:address":"Ankara Asfalti Uzeri No:230",
    "sg:city":"Akincilar",
    "sg:classifiers":[
        {
            "category":"Manufacturing",
            "subcategory":"Glass & Minerals",
            "type":"Manufacturing & Wholesale Goods"
        }
    ],
    "sg:phone":"+90 232 478 1212",
    "sg:postcode":"01220",
    "sg:province":"Izmir",
    "sg:tags":[
        "glass-mirror"
    ],
    "wof:name":"Gayret Cam Sanayi",
    "wof:placetype":"venue"
},
  "geometry": {"coordinates":[27.1296863556,38.4186973572],"type":"Point"}
}