{
  "type": "Feature",
  "properties": {
    "iso:country":"TR",
    "sg:address":"Rami Kisla Cd. G?dogar Ismerk. No:84/125 Top?lar",
    "sg:city":"Iskenderun",
    "sg:classifiers":[
        {
            "category":"Manufacturing",
            "subcategory":"Metals",
            "type":"Manufacturing & Wholesale Goods"
        }
    ],
    "sg:phone":"+90 212 544 6301",
    "sg:postcode":"31200",
    "sg:province":"Istanbul",
    "sg:tags":[
        "industry"
    ],
    "wof:name":"Tet Mak. Metal San.",
    "wof:placetype":"venue"
},
  "geometry": {"coordinates":[28.9759254456,41.0123786926],"type":"Point"}
}