{
  "type": "Feature",
  "properties": {
    "iso:country":"TR",
    "sg:address":"Seyrantepe Mah.ibrahim Karaoglanoglu Cad.?zden Sok.no:5 Oto Sanayi 4 Levent",
    "sg:city":"Kagithane",
    "sg:classifiers":[
        {
            "category":"Manufacturing",
            "subcategory":"Textiles",
            "type":"Manufacturing & Wholesale Goods"
        }
    ],
    "sg:phone":"+90 212 325 3524",
    "sg:postcode":"34406",
    "sg:province":"Istanbul",
    "sg:tags":[
        "cloth",
        "worker"
    ],
    "wof:name":"Oguz Is Giyim",
    "wof:placetype":"venue"
},
  "geometry": {"coordinates":[28.9681472778,41.0811843872],"type":"Point"}
}