{
  "type": "Feature",
  "properties": {
    "addr:full":"Mete Sk. No:5/2 Merter/ist. Mersin Ankara 52750",
    "addr:housenumber":"2",
    "addr:postcode":"52750",
    "addr:street":"Mete Sk. No 5 /",
    "iso:country":"TR",
    "sg:address":"Mete Sk. No:5/2 Merter/ist.",
    "sg:city":"Mersin",
    "sg:classifiers":[
        {
            "category":"Home & Garden",
            "subcategory":"Building Materials",
            "type":"Retail Goods"
        }
    ],
    "sg:phone":"+90 312 556 0087",
    "sg:postcode":"52750",
    "sg:province":"Ankara",
    "sg:tags":[
        "window",
        "door",
        "plastic"
    ],
    "wof:name":"Handan-pen Yapi San. Tic. Ltd. Sti.",
    "wof:placetype":"venue"
},
  "geometry": {"coordinates":[32.8560333252,39.9438743591],"type":"Point"}
}