{
  "type": "Feature",
  "properties": {
    "iso:country":"TR",
    "sg:address":"Etlik Cd. No:39 Altindag",
    "sg:city":"Fatih",
    "sg:classifiers":[
        {
            "category":"Building & Trades",
            "subcategory":"Construction",
            "type":"Services"
        }
    ],
    "sg:phone":"+90 312 342 1134",
    "sg:postcode":"01740",
    "sg:province":"Ankara",
    "sg:tags":[
        "foundation"
    ],
    "wof:name":"Karayollari Vakfi",
    "wof:placetype":"venue"
},
  "geometry": {"coordinates":[32.8438301086,39.9629020691],"type":"Point"}
}