{
  "type": "Feature",
  "properties": {
    "addr:full":"Selimiye Iskele Cd. Selvik??sk. No:18 Selimiye Istanbul 01920",
    "addr:housenumber":"? ?;18",
    "addr:postcode":"01920",
    "addr:street":"Iskele Cd. Selvik;Sk. No",
    "iso:country":"TR",
    "sg:address":"Selimiye Iskele Cd. Selvik??sk. No:18",
    "sg:city":"Selimiye",
    "sg:classifiers":[
        {
            "category":"Airport",
            "subcategory":"International",
            "type":"Transportation"
        }
    ],
    "sg:phone":"+90 216 310 9175",
    "sg:postcode":"01920",
    "sg:province":"Istanbul",
    "wof:name":"Gedem Uluslararasi Tasima. Turizm Dis. Tic.",
    "wof:placetype":"venue"
},
  "geometry": {"coordinates":[28.9861831665,41.0408554077],"type":"Point"}
}