{
  "type": "Feature",
  "properties": {
    "iso:country":"TR",
    "sg:address":"Kodaman Sk. No:98/4 Seref Apt. Osmanbey",
    "sg:city":"Sultanhamam",
    "sg:classifiers":[
        {
            "category":"Home & Garden",
            "subcategory":"Home Furnishings",
            "type":"Retail Goods"
        }
    ],
    "sg:phone":"+90 212 248 1289",
    "sg:province":"Istanbul",
    "sg:tags":[
        "curtaining",
        "-",
        "upholstering"
    ],
    "wof:name":"G?zde Kumas Tic. San. A.s.",
    "wof:placetype":"venue"
},
  "geometry": {"coordinates":[28.987904,41.058693],"type":"Point"}
}