{
  "type": "Feature",
  "properties": {
    "iso:country":"TR",
    "sg:address":"Tepe Mah. 48.sok. No:1/37 Marmaris",
    "sg:city":"Bah\u00e7elievler",
    "sg:classifiers":[
        {
            "category":"Organizations",
            "subcategory":"Professional Association",
            "type":"Services"
        }
    ],
    "sg:phone":"+90 252 412 3220",
    "sg:postcode":"48230",
    "sg:province":"Mugla",
    "sg:tags":[
        "fair"
    ],
    "wof:name":"Marin Fuarcilik Ltd.sti.",
    "wof:placetype":"venue"
},
  "geometry": {"coordinates":[28.2715358734,36.855632782],"type":"Point"}
}