{
  "type": "Feature",
  "properties": {
    "addr:full":"Millet Cad. Eregli Mah. Kerpi?ane Sk. 12/1 Sehremini 22/306 Istanbul",
    "addr:housenumber":"?;1;22 / 306",
    "addr:street":"Millet Cad. Eregli Mah. Kerpi;Sk. 12 /",
    "iso:country":"TR",
    "sg:address":"Millet Cad. Eregli Mah. Kerpi?ane Sk. 12/1 Sehremini",
    "sg:city":"22/306",
    "sg:classifiers":[
        {
            "category":"Wholesale",
            "subcategory":"Medical Equipment & Supplies",
            "type":"Manufacturing & Wholesale Goods"
        }
    ],
    "sg:phone":"+90 212 529 2568",
    "sg:province":"Istanbul",
    "wof:name":"Guraylar Med. Ith. Ihr. Ltd.",
    "wof:placetype":"venue"
},
  "geometry": {"coordinates":[28.9351291656,41.009349823],"type":"Point"}
}