{
  "type": "Feature",
  "properties": {
    "iso:country":"TR",
    "sg:address":"Istanbul",
    "sg:city":"Kad\u0131k\u00f6y",
    "sg:classifiers":[
        {
            "category":"Shopping",
            "subcategory":"Gifts & Souvenirs",
            "type":"Retail Goods"
        }
    ],
    "sg:phone":"+90 212 280 9282",
    "sg:postcode":"34990",
    "sg:province":"Istanbul",
    "wof:name":"Ozalay Reklam",
    "wof:placetype":"venue"
},
  "geometry": {"coordinates":[29.3950977325,40.9473953247],"type":"Point"}
}