{
  "type": "Feature",
  "properties": {
    "addr:full":"Ankara Asfalti Uzeri Sahrayi Cedid Mengu Sok. No:21 Erenkoy Istanbul 07060",
    "addr:housenumber":"no 21",
    "addr:postcode":"07060",
    "addr:street":"Mengu Sok.;Istanbul",
    "iso:country":"TR",
    "sg:address":"Ankara Asfalti Uzeri Sahrayi Cedid Mengu Sok. No:21",
    "sg:city":"Erenkoy",
    "sg:classifiers":[
        {
            "category":"Arena",
            "subcategory":"Indoor Arena",
            "type":"Entertainment"
        }
    ],
    "sg:phone":"+90 216 302 0043",
    "sg:postcode":"07060",
    "sg:province":"Istanbul",
    "sg:tags":[
        "tent-canvas"
    ],
    "wof:name":"Gul Branda Tekstil Urunleri San. Ve Tic. Ltd.sti.",
    "wof:placetype":"venue"
},
  "geometry": {"coordinates":[28.9861831665,41.0408554077],"type":"Point"}
}