{
  "type": "Feature",
  "properties": {
    "addr:full":"2.organize Sanayi B?lgesi Kirim Cd No.3 Sel?uklu Konya",
    "addr:housenumber":"?;cd",
    "addr:street":"2.Organize Sanayi B;Kirim",
    "iso:country":"TR",
    "sg:address":"2.organize Sanayi B?lgesi Kirim Cd No.3",
    "sg:city":"Sel?uklu",
    "sg:classifiers":[
        {
            "category":"Manufacturing",
            "subcategory":"Chemicals & Compounds",
            "type":"Manufacturing & Wholesale Goods"
        }
    ],
    "sg:phone":"+90 332 239 0682",
    "sg:province":"Konya",
    "sg:tags":[
        "agricultural"
    ],
    "wof:name":"Topraksu Kimya Ve Tarim ?r?nleri San.tic.a.s.",
    "wof:placetype":"venue"
},
  "geometry": {"coordinates":[32.4990272522,37.8715362549],"type":"Point"}
}