{
  "type": "Feature",
  "properties": {
    "addr:full":"Eski San B?.5.cad.sok.no:29 Erb Aa Kayseri 60500",
    "addr:housenumber":"?;29",
    "addr:postcode":"60500",
    "addr:street":"Eski San B;Erb Aa",
    "iso:country":"TR",
    "sg:address":"Eski San B?.5.cad.sok.no:29",
    "sg:city":"Erb Aa",
    "sg:classifiers":[
        {
            "category":"Manufacturing",
            "subcategory":"Wood Products",
            "type":"Manufacturing & Wholesale Goods"
        }
    ],
    "sg:phone":"+90 352 336 3218",
    "sg:postcode":"60500",
    "sg:province":"Kayseri",
    "sg:tags":[
        "forest"
    ],
    "wof:name":"Baktiroglu Orman Urunleri A.s",
    "wof:placetype":"venue"
},
  "geometry": {"coordinates":[36.4393234253,38.2791290283],"type":"Point"}
}