{
  "type": "Feature",
  "properties": {
    "addr:full":"Fazil Pasa Cd. ?ztoprak San. Sit. No:14/10 Topkapi Eskigaraj Istanbul",
    "addr:housenumber":"fazil;?;10",
    "addr:street":"Pasa Cd.;Topkapi Eskigaraj",
    "iso:country":"TR",
    "sg:address":"Fazil Pasa Cd. ?ztoprak San. Sit. No:14/10 Topkapi",
    "sg:city":"Eskigaraj",
    "sg:classifiers":[
        {
            "category":"Manufacturing",
            "subcategory":"Rubber & Plastics",
            "type":"Manufacturing & Wholesale Goods"
        }
    ],
    "sg:phone":"+90 212 577 3591",
    "sg:province":"Istanbul",
    "sg:tags":[
        "industry"
    ],
    "wof:name":"Selveroglu Plastik Gran?r San. Tic. A.s.",
    "wof:placetype":"venue"
},
  "geometry": {"coordinates":[28.9759254456,41.0123786926],"type":"Point"}
}