{
  "type": "Feature",
  "properties": {
    "addr:full":"Astim Org. San. Sitesi Pk.55 Merkez Aydin 61200",
    "addr:postcode":"61200",
    "addr:street":"Org.;Aydin",
    "iso:country":"TR",
    "sg:address":"Astim Org. San. Sitesi Pk.55",
    "sg:city":"Merkez",
    "sg:classifiers":[
        {
            "category":"Shopping",
            "type":"Retail Goods"
        }
    ],
    "sg:phone":"+90 256 225 3120",
    "sg:postcode":"61200",
    "sg:province":"Aydin",
    "sg:tags":[
        "material",
        "cleaning"
    ],
    "wof:name":"Bosnali Sabun Ve Yag San.tic. Ltd.sti.",
    "wof:placetype":"venue"
},
  "geometry": {"coordinates":[27.8324394226,37.8409690857],"type":"Point"}
}