{
  "type": "Feature",
  "properties": {
    "iso:country":"TR",
    "sg:address":"Farabi Sk. No:3/3 ?ankaya",
    "sg:city":"Bucak",
    "sg:classifiers":[
        {
            "category":"Mining & Drilling",
            "type":"Manufacturing & Wholesale Goods"
        }
    ],
    "sg:phone":"+90 312 468 4841",
    "sg:postcode":"15300",
    "sg:province":"Ankara",
    "sg:tags":[
        "industry",
        "mine"
    ],
    "wof:name":"Cominco Madencilik San. A.s.",
    "wof:placetype":"venue"
},
  "geometry": {"coordinates":[32.8609352112,39.8965950012],"type":"Point"}
}