{
  "type": "Feature",
  "properties": {
    "addr:full":"Gmk Bulv. Onur Ishani K:4 No:91 Demirtepe Mecidiyek\u00f6y Ankara 80300",
    "addr:housenumber":"4 no 91",
    "addr:postcode":"80300",
    "addr:street":"Gmk Bulv. Onur Ishani K;Demirtepe Mecidiyekoey",
    "iso:country":"TR",
    "sg:address":"Gmk Bulv. Onur Ishani K:4 No:91 Demirtepe",
    "sg:city":"Mecidiyek\u00f6y",
    "sg:orig_category":"Translation Servies",
    "sg:phone":"+90 312 418 4683",
    "sg:postcode":"80300",
    "sg:province":"Ankara",
    "wof:name":"Uz Terc?me",
    "wof:placetype":"venue"
},
  "geometry": {"coordinates":[32.8604812622,39.9429283142],"type":"Point"}
}