{
  "type": "Feature",
  "properties": {
    "iso:country":"TR",
    "sg:address":"Ortabah? Cd. No:22/4 Besiktas",
    "sg:city":"?aglayan",
    "sg:classifiers":[
        {
            "category":"Shopping",
            "subcategory":"Stationery & Office Supplies",
            "type":"Retail Goods"
        }
    ],
    "sg:phone":"+90 212 261 6744",
    "sg:province":"Istanbul",
    "wof:name":"Kabalci Kitabevi",
    "wof:placetype":"venue"
},
  "geometry": {"coordinates":[29.023275,41.071552],"type":"Point"}
}