{
  "type": "Feature",
  "properties": {
    "addr:full":"Yesil Yol Cd. Er?lik Sit. No:2 \u00dcmraniye Afyon",
    "addr:housenumber":"sit. no 2",
    "addr:street":"Cd. Er ?",
    "iso:country":"TR",
    "sg:address":"Yesil Yol Cd. Er?lik Sit. No:2",
    "sg:city":"\u00dcmraniye",
    "sg:classifiers":[
        {
            "category":"Wholesale",
            "subcategory":"Home Furnishings",
            "type":"Manufacturing & Wholesale Goods"
        }
    ],
    "sg:phone":"+90 272 213 6919",
    "sg:province":"Afyon",
    "sg:tags":[
        "furniture"
    ],
    "wof:name":"G + U Dog. Ltd.",
    "wof:placetype":"venue"
},
  "geometry": {"coordinates":[30.5382652283,38.7579841614],"type":"Point"}
}