{
  "type": "Feature",
  "properties": {
    "iso:country":"TR",
    "sg:address":"Kosgeb Ayazaga, Sariyer",
    "sg:city":"Beyoglu",
    "sg:classifiers":[
        {
            "category":"Building & Trades",
            "subcategory":"Construction",
            "type":"Services"
        }
    ],
    "sg:phone":"+90 212 252 4757",
    "sg:postcode":"46810",
    "sg:province":"Istanbul",
    "sg:tags":[
        "foundation"
    ],
    "wof:name":"Turk. Yangindan Kor. Vakfi Itu",
    "wof:placetype":"venue"
},
  "geometry": {"coordinates":[28.9759254456,41.0123786926],"type":"Point"}
}