{
  "type": "Feature",
  "properties": {
    "addr:full":"Sulun Sk. 18 Levent Kad\u0131k\u00f6y Istanbul 34990",
    "addr:postcode":"34990",
    "addr:street":"Sulun Sk. 18",
    "iso:country":"TR",
    "sg:address":"Sulun Sk. 18 Levent",
    "sg:city":"Kad\u0131k\u00f6y",
    "sg:classifiers":[
        {
            "category":"Professional",
            "type":"Services"
        }
    ],
    "sg:phone":"+90 212 280 2214",
    "sg:postcode":"34990",
    "sg:province":"Istanbul",
    "sg:tags":[
        "industrial",
        "automation"
    ],
    "wof:name":"Eliar Elektronik San. A.s.",
    "wof:placetype":"venue"
},
  "geometry": {"coordinates":[28.9861831665,41.0408554077],"type":"Point"}
}