{
  "type": "Feature",
  "properties": {
    "addr:full":"Yesillik Cad. 230/102 Modeko Is Merkezi Karabaglar Izmir 35270",
    "addr:housenumber":"230 / 102",
    "addr:postcode":"35270",
    "addr:street":"Yesillik Cad.;Modeko;Karabaglar",
    "iso:country":"TR",
    "sg:address":"Yesillik Cad. 230/102 Modeko Is Merkezi",
    "sg:city":"Karabaglar",
    "sg:classifiers":[
        {
            "category":"Manufacturing",
            "subcategory":"Textiles",
            "type":"Manufacturing & Wholesale Goods"
        }
    ],
    "sg:phone":"+90 232 237 2727",
    "sg:postcode":"35270",
    "sg:province":"Izmir",
    "sg:tags":[
        "cloth",
        "worker"
    ],
    "wof:name":"Oteks Otel Ekipmanlari Ve Tekstil",
    "wof:placetype":"venue"
},
  "geometry": {"coordinates":[27.1389751434,38.4062995911],"type":"Point"}
}