{
  "type": "Feature",
  "properties": {
    "addr:full":"Millet Cd. Iu Ist. Tip Fak. Cocuk Klin. Fatih Ke??en Istanbul",
    "addr:street":"Millet Cd.;Ist.",
    "iso:country":"TR",
    "sg:address":"Millet Cd. Iu Ist. Tip Fak. Cocuk Klin. Fatih",
    "sg:city":"Ke??en",
    "sg:classifiers":[
        {
            "category":"Organizations",
            "subcategory":"Membership Organization",
            "type":"Services"
        }
    ],
    "sg:phone":"+90 212 532 4233",
    "sg:province":"Istanbul",
    "wof:name":"Pediatrik Endokrinoloji Oksoloji Dernegi",
    "wof:placetype":"venue"
},
  "geometry": {"coordinates":[28.9501304626,41.0054702759],"type":"Point"}
}