{
  "type": "Feature",
  "properties": {
    "addr:full":"Bozkurt Cd. No:25 Akyurt Izmir 24800",
    "addr:housenumber":"no 25",
    "addr:postcode":"24800",
    "addr:street":"Akyurt Izmir",
    "iso:country":"TR",
    "sg:address":"Bozkurt Cd. No:25",
    "sg:city":"Akyurt",
    "sg:orig_category":"Carpet-kilim-blanket",
    "sg:phone":"+90 232 483 0320",
    "sg:postcode":"24800",
    "sg:province":"Izmir",
    "wof:name":"San Hali Tic. San. A.s.",
    "wof:placetype":"venue"
},
  "geometry": {"coordinates":[27.1423015594,38.4251480103],"type":"Point"}
}