{
  "type": "Feature",
  "properties": {
    "iso:country":"TR",
    "sg:address":"Ahmet Fatoglu Cad. No:15",
    "sg:city":"Bulancak",
    "sg:classifiers":[
        {
            "category":"Food & Beverages",
            "subcategory":"Groceries & Convenience Stores",
            "type":"Retail Goods"
        }
    ],
    "sg:phone":"+90 454 318 0262",
    "sg:postcode":"63850",
    "sg:province":"Giresun",
    "sg:tags":[
        "drink-",
        "soft"
    ],
    "wof:name":"Fatsu Mesrubat San Tic.a.s.",
    "wof:placetype":"venue"
},
  "geometry": {"coordinates":[38.390301,40.9175],"type":"Point"}
}