{
  "type": "Feature",
  "properties": {
    "addr:full":"M. Egemenlik Cd. Saray No:22/32 Yesilk?y Antalya 34830",
    "addr:housenumber":"32;?",
    "addr:postcode":"34830",
    "addr:street":"Cd.;No 22 /;Y",
    "iso:country":"TR",
    "sg:address":"M. Egemenlik Cd. Saray No:22/32",
    "sg:city":"Yesilk?y",
    "sg:classifiers":[
        {
            "category":"Organizations",
            "subcategory":"Membership Organization",
            "type":"Services"
        }
    ],
    "sg:phone":"+90 242 242 3735",
    "sg:postcode":"34830",
    "sg:province":"Antalya",
    "wof:name":"Noel Baba Dunya Barisina Cagri Dernegi",
    "wof:placetype":"venue"
},
  "geometry": {"coordinates":[30.7092056274,36.8790512085],"type":"Point"}
}