{
  "type": "Feature",
  "properties": {
    "addr:full":"Binbircicek Sokak 1 Istanbul Istanbul",
    "addr:housenumber":"1",
    "addr:street":"Binbircicek Sokak",
    "iso:country":"TR",
    "sg:address":"Binbircicek Sokak 1",
    "sg:city":"Istanbul",
    "sg:classifiers":[
        {
            "category":"Banks & Credit Unions",
            "subcategory":"Bank",
            "type":"Services"
        }
    ],
    "sg:phone":"+90 212 268 4307",
    "sg:province":"Istanbul",
    "wof:name":"Bank Mellat",
    "wof:placetype":"venue"
},
  "geometry": {"coordinates":[28.975925,41.012379],"type":"Point"}
}