{
  "type": "Feature",
  "properties": {
    "iso:country":"TR",
    "sg:address":"Girne Bulvari 1735 Sok. No:106 A",
    "sg:city":"Karsiyaka",
    "sg:classifiers":[
        {
            "category":"Manufacturing",
            "subcategory":"Building Materials",
            "type":"Manufacturing & Wholesale Goods"
        }
    ],
    "sg:phone":"+90 232 323 5421",
    "sg:postcode":"01900",
    "sg:province":"Izmir",
    "sg:tags":[
        "lifts-elevators"
    ],
    "wof:name":"Ozcan Asansorleri San Ve Tic Ltd Sti",
    "wof:placetype":"venue"
},
  "geometry": {"coordinates":[27.1087989807,38.4564170837],"type":"Point"}
}