{
  "type": "Feature",
  "properties": {
    "iso:country":"TR",
    "sg:address":"M.fevzi Cakmak Cad. 5.sok. No:15 Sirinevler",
    "sg:city":"Ikitelli",
    "sg:classifiers":[
        {
            "category":"Home & Garden",
            "subcategory":"Kitchen Supply",
            "type":"Retail Goods"
        }
    ],
    "sg:phone":"+90 212 654 6744",
    "sg:postcode":"34306",
    "sg:province":"Istanbul",
    "sg:tags":[
        "wardrobe"
    ],
    "wof:name":"Trak Dis Tic.",
    "wof:placetype":"venue"
},
  "geometry": {"coordinates":[28.8443584442,40.9974937439],"type":"Point"}
}