{
  "type": "Feature",
  "properties": {
    "iso:country":"TR",
    "sg:address":"G.m.k. Bulvari 52/18 Maltepe/cankaya",
    "sg:city":"Fatih",
    "sg:classifiers":[
        {
            "category":"Wholesale",
            "subcategory":"Medical Equipment & Supplies",
            "type":"Manufacturing & Wholesale Goods"
        }
    ],
    "sg:phone":"+90 312 232 6720",
    "sg:postcode":"01740",
    "sg:province":"Ankara",
    "sg:tags":[
        "material"
    ],
    "wof:name":"Med-an Tip Teknik",
    "wof:placetype":"venue"
},
  "geometry": {"coordinates":[32.8714485168,39.8838539124],"type":"Point"}
}