{
  "type": "Feature",
  "properties": {
    "addr:full":"Perpa Tic. Merkezi A Blok K.4-5-6 No.182-184 Okmeydani Okmeydani Istanbul 43050",
    "addr:postcode":"43050",
    "addr:street":"A",
    "iso:country":"TR",
    "sg:address":"Perpa Tic. Merkezi A Blok K.4-5-6 No.182-184 Okmeydani",
    "sg:city":"Okmeydani",
    "sg:classifiers":[
        {
            "category":"Professional",
            "type":"Services"
        }
    ],
    "sg:phone":"+90 212 210 9361",
    "sg:postcode":"43050",
    "sg:province":"Istanbul",
    "sg:tags":[
        "industrial",
        "automation"
    ],
    "wof:name":"Ant Muhendislik San. Ve Tic.ltd.sti.",
    "wof:placetype":"venue"
},
  "geometry": {"coordinates":[28.9861831665,41.0408554077],"type":"Point"}
}