{
  "type": "Feature",
  "properties": {
    "iso:country":"TR",
    "sg:address":"Kocasinan Merkez Mah. Mahmutbey Asfalti",
    "sg:city":"Bah\u00e7elievler",
    "sg:classifiers":[
        {
            "category":"Sports & Exercise",
            "subcategory":"Ski Slope",
            "type":"Entertainment"
        }
    ],
    "sg:phone":"+90 212 630 3252",
    "sg:postcode":"34180",
    "sg:province":"Istanbul",
    "sg:tags":[
        "wear"
    ],
    "wof:name":"Geteks Tekstil San. Ve Tic. Ltd. Sti.",
    "wof:placetype":"venue"
},
  "geometry": {"coordinates":[28.868418,41.003963],"type":"Point"}
}