{
  "type": "Feature",
  "properties": {
    "iso:country":"TR",
    "sg:address":"Yeni Sanayi Sitesi 58 C Blok No:12",
    "sg:city":"Ikitelli/K\u00fc\u00e7\u00fck\u00e7ekmece",
    "sg:classifiers":[
        {
            "category":"Manufacturing",
            "subcategory":"Tools & Machinery",
            "type":"Manufacturing & Wholesale Goods"
        }
    ],
    "sg:phone":"+90 326 221 2348",
    "sg:postcode":"34670",
    "sg:province":"Hatay",
    "sg:tags":[
        "machine",
        "industry"
    ],
    "wof:name":"Pres-is Makina",
    "wof:placetype":"venue"
},
  "geometry": {"coordinates":[36.349811554,36.4018478394],"type":"Point"}
}