{
  "type": "Feature",
  "properties": {
    "addr:full":"Cumhuriyet Cad. No. 295 D.15, Harbiye Istanbul 34373",
    "addr:housenumber":"295 d.15",
    "addr:postcode":"34373",
    "addr:street":"Cumhuriyet Cad. No.",
    "iso:country":"TR",
    "sg:address":"Cumhuriyet Cad. No. 295 D.15, Harbiye",
    "sg:city":"Istanbul",
    "sg:classifiers":[
        {
            "category":"Travel",
            "subcategory":"Travel Agent",
            "type":"Entertainment"
        }
    ],
    "sg:phone":"+90 902 122 3127",
    "sg:province":"34373",
    "sg:website":"www.kongresist.com",
    "wof:name":"Kongresist Travel Co",
    "wof:placetype":"venue"
},
  "geometry": {"coordinates":[28.9892692566,41.0421638489],"type":"Point"}
}