{
  "type": "Feature",
  "properties": {
    "addr:full":"Fethibey Mah. 1 Temuz Cad. Bigadic Balikesir 10440",
    "addr:housenumber":"1",
    "addr:postcode":"10440",
    "addr:street":"Fethibey Mah.;Temuz Cad. Bigadic Balikesir",
    "iso:country":"TR",
    "sg:address":"Fethibey Mah. 1 Temuz Cad.",
    "sg:city":"Bigadic",
    "sg:classifiers":[
        {
            "category":"Farming",
            "subcategory":"Farm & Veterinary Services",
            "type":"Manufacturing & Wholesale Goods"
        }
    ],
    "sg:phone":"+90 2666145585614",
    "sg:postcode":"10440",
    "sg:province":"Balikesir",
    "sg:tags":[
        "veterinarian"
    ],
    "wof:name":"Hikmet Kayman",
    "wof:placetype":"venue"
},
  "geometry": {"coordinates":[27.8833007812,39.6520996094],"type":"Point"}
}