{
  "type": "Feature",
  "properties": {
    "addr:full":"Basvekil Caddesi No:5 - Fatih Okmeydani/sisli Istanbul 80380",
    "addr:postcode":"80380",
    "addr:street":"Basvekil Caddesi No 5 Fatih",
    "iso:country":"TR",
    "sg:address":"Basvekil Caddesi No:5 - Fatih",
    "sg:city":"Okmeydani/sisli",
    "sg:classifiers":[
        {
            "category":"Banks & Credit Unions",
            "subcategory":"Investment Brokerage",
            "type":"Services"
        }
    ],
    "sg:phone":"+90 212 529 9181",
    "sg:postcode":"80380",
    "sg:province":"Istanbul",
    "sg:tags":[
        "aid",
        "material",
        "first"
    ],
    "wof:name":"Ultra Emar",
    "wof:placetype":"venue"
},
  "geometry": {"coordinates":[28.9333839417,41.0146636963],"type":"Point"}
}