{
  "type": "Feature",
  "properties": {
    "addr:full":"Kurtulus Mh. Onur Sk. No:44/a ?aglayan Eskisehir 80340",
    "addr:housenumber":"44 / a ?",
    "addr:postcode":"80340",
    "addr:street":"Sk. No;Aglayan Eskisehir",
    "iso:country":"TR",
    "sg:address":"Kurtulus Mh. Onur Sk. No:44/a",
    "sg:city":"?aglayan",
    "sg:classifiers":[
        {
            "category":"Shopping",
            "subcategory":"Stationery & Office Supplies",
            "type":"Retail Goods"
        }
    ],
    "sg:phone":"+90 222 234 4041",
    "sg:postcode":"80340",
    "sg:province":"Eskisehir",
    "sg:tags":[
        "furniture"
    ],
    "wof:name":"Mokap Orman ?r?n. San. Tic. Ltd. Sti.",
    "wof:placetype":"venue"
},
  "geometry": {"coordinates":[30.5268516541,39.7696800232],"type":"Point"}
}