{
  "type": "Feature",
  "properties": {
    "iso:country":"TR",
    "sg:address":"Demiryolu Cd. No:84 Yildirim",
    "sg:city":"Harbiye",
    "sg:classifiers":[
        {
            "category":"Home & Garden",
            "subcategory":"Kitchen Supply",
            "type":"Retail Goods"
        }
    ],
    "sg:phone":"+90 224 254 2190",
    "sg:postcode":"31080",
    "sg:province":"Bursa",
    "sg:tags":[
        "steel",
        "utensil"
    ],
    "wof:name":"Kms Metal San. Tic. Ltd. Sti.",
    "wof:placetype":"venue"
},
  "geometry": {"coordinates":[29.045464,40.208412],"type":"Point"}
}