{
  "type": "Feature",
  "properties": {
    "iso:country":"TR",
    "sg:address":"Bagdat Cd. No:305 Cevizli",
    "sg:city":"38070",
    "sg:orig_category":"Aluminium Carpentary",
    "sg:phone":"+90 216 441 6323",
    "sg:province":"Istanbul",
    "wof:name":"Gurpen Ins. Plas. San.",
    "wof:placetype":"venue"
},
  "geometry": {"coordinates":[29.1478233337,40.9155654907],"type":"Point"}
}