{
  "type": "Feature",
  "properties": {
    "addr:full":"Pendik Tersane Yani Derici. Enstit??bitis. Pendik B.cekmece Istanbul",
    "iso:country":"TR",
    "sg:address":"Pendik Tersane Yani Derici. Enstit??bitis. Pendik",
    "sg:city":"B.cekmece",
    "sg:classifiers":[
        {
            "category":"Home & Garden",
            "subcategory":"Kitchen Supply",
            "type":"Retail Goods"
        }
    ],
    "sg:phone":"+90 216 396 2216",
    "sg:province":"Istanbul",
    "sg:tags":[
        "steel",
        "utensil"
    ],
    "wof:name":"S?perteknik Otomatik Kont. Eleman. Tic. San. A.s.",
    "wof:placetype":"venue"
},
  "geometry": {"coordinates":[29.256001,40.8787],"type":"Point"}
}