{
  "type": "Feature",
  "properties": {
    "iso:country":"TR",
    "sg:address":"Org.san.bol.4.cad.",
    "sg:city":"Kumarli",
    "sg:classifiers":[
        {
            "category":"Home & Garden",
            "subcategory":"Building Materials",
            "type":"Retail Goods"
        }
    ],
    "sg:phone":"+90 352 231 1425",
    "sg:postcode":"46400",
    "sg:province":"Kayseri",
    "sg:tags":[
        "window",
        "door"
    ],
    "wof:name":"Emek Celik Kapi",
    "wof:placetype":"venue"
},
  "geometry": {"coordinates":[36.4393234253,38.2791290283],"type":"Point"}
}