{
  "type": "Feature",
  "properties": {
    "iso:country":"TR",
    "sg:address":"Halakali Cad.ataturk Mah.haymazi Is Han No: 23/16",
    "sg:city":"Ikitelli",
    "sg:classifiers":[
        {
            "category":"Manufacturing",
            "subcategory":"Building Materials",
            "type":"Manufacturing & Wholesale Goods"
        }
    ],
    "sg:phone":"+90 212 471 7296",
    "sg:postcode":"34306",
    "sg:province":"Istanbul",
    "sg:tags":[
        "lifts-elevators"
    ],
    "wof:name":"Deha Asansor",
    "wof:placetype":"venue"
},
  "geometry": {"coordinates":[28.7984962463,41.0884017944],"type":"Point"}
}