{
  "type": "Feature",
  "properties": {
    "iso:country":"TR",
    "sg:address":"Cengiz Topel Cd. No:208/27 K??k?",
    "sg:city":"Iskenderun",
    "sg:classifiers":[
        {
            "category":"Mining & Drilling",
            "type":"Manufacturing & Wholesale Goods"
        }
    ],
    "sg:phone":"+90 212 538 1129",
    "sg:postcode":"31200",
    "sg:province":"Istanbul",
    "sg:tags":[
        "industry",
        "mine"
    ],
    "wof:name":"Dalbay Tas Imal. San. Tic. Ltd. Sti.",
    "wof:placetype":"venue"
},
  "geometry": {"coordinates":[28.9027118683,41.0637207031],"type":"Point"}
}