{
  "type": "Feature",
  "properties": {
    "addr:full":"M. Kemalpasa Mh. Uygur Sk. No:33 Ikitelli/K\u00fc\u00e7\u00fck\u00e7ekmece Eskisehir 34660",
    "addr:housenumber":"33",
    "addr:postcode":"34660",
    "addr:street":"Mh. Uygur Sk. No;Eskisehir",
    "iso:country":"TR",
    "sg:address":"M. Kemalpasa Mh. Uygur Sk. No:33",
    "sg:city":"Ikitelli/K\u00fc\u00e7\u00fck\u00e7ekmece",
    "sg:classifiers":[
        {
            "category":"Home & Garden",
            "subcategory":"Kitchen Supply",
            "type":"Retail Goods"
        }
    ],
    "sg:phone":"+90 222 230 4025",
    "sg:postcode":"34660",
    "sg:province":"Eskisehir",
    "sg:tags":[
        "steel",
        "utensil"
    ],
    "wof:name":"Seyhan Karton Ambalaj Kalip San. Tic. Ltd. Sti.",
    "wof:placetype":"venue"
},
  "geometry": {"coordinates":[30.517546,39.770081],"type":"Point"}
}