{
  "type": "Feature",
  "properties": {
    "addr:full":"K.m.pasa Cad. No. 227 K.m.pasa Istanbul",
    "addr:housenumber":"227",
    "addr:street":"K.M.Pasa Cad. No.",
    "iso:country":"TR",
    "sg:address":"K.m.pasa Cad. No. 227",
    "sg:city":"K.m.pasa",
    "sg:classifiers":[
        {
            "category":"Food & Beverages",
            "subcategory":"Meat & Fish",
            "type":"Retail Goods"
        }
    ],
    "sg:phone":"+90 212 587 8806",
    "sg:province":"Istanbul",
    "sg:tags":[
        "seafood"
    ],
    "wof:name":"Aquarium & Pet Centre",
    "wof:placetype":"venue"
},
  "geometry": {"coordinates":[28.9407730103,41.0250816345],"type":"Point"}
}