{
  "type": "Feature",
  "properties": {
    "addr:full":"Alemdag Sile Asf. No:129 Kartal I?renk? Istanbul 81120",
    "addr:housenumber":"?",
    "addr:postcode":"?;81120",
    "addr:street":"Kartal I",
    "iso:country":"TR",
    "sg:address":"Alemdag Sile Asf. No:129 Kartal",
    "sg:city":"I?renk?",
    "sg:classifiers":[
        {
            "category":"Shopping",
            "subcategory":"Computers & Home Electronics",
            "type":"Retail Goods"
        }
    ],
    "sg:phone":"+90 216 304 6216",
    "sg:postcode":"81120",
    "sg:province":"Istanbul",
    "sg:tags":[
        "product",
        "electric-electronic"
    ],
    "wof:name":"Akbul Elek. San.",
    "wof:placetype":"venue"
},
  "geometry": {"coordinates":[28.9861831665,41.0408554077],"type":"Point"}
}