{
  "type": "Feature",
  "properties": {
    "iso:country":"TR",
    "sg:address":"Sirma Sok. No:14 Siteler",
    "sg:city":"Beyoglu",
    "sg:classifiers":[
        {
            "category":"Wholesale",
            "subcategory":"Home Furnishings",
            "type":"Manufacturing & Wholesale Goods"
        }
    ],
    "sg:phone":"+90 312 350 4391",
    "sg:postcode":"80320",
    "sg:province":"Ankara",
    "sg:tags":[
        "furniture"
    ],
    "wof:name":"Nora Mobilya Pazarlama A.s.",
    "wof:placetype":"venue"
},
  "geometry": {"coordinates":[32.8604812622,39.9429283142],"type":"Point"}
}