{
  "type": "Feature",
  "properties": {
    "iso:country":"TR",
    "sg:address":"Kazim Ozalp Cad. No:119,",
    "sg:city":"07040",
    "sg:orig_category":"Hotels: Motels",
    "sg:phone":"+90 24224345704",
    "sg:province":"Antalya",
    "wof:name":"Goksoy Hotel",
    "wof:placetype":"venue"
},
  "geometry": {"coordinates":[30.7046642303,36.8889465332],"type":"Point"}
}