{
  "type": "Feature",
  "properties": {
    "iso:country":"TR",
    "sg:address":"710.sok. No: 12 Buca",
    "sg:city":"Maltepe",
    "sg:classifiers":[
        {
            "category":"Home & Garden",
            "subcategory":"Building Materials",
            "type":"Retail Goods"
        }
    ],
    "sg:phone":"+90 232 264 8142",
    "sg:postcode":"01000",
    "sg:province":"Izmir",
    "sg:tags":[
        "window",
        "door",
        "plastic"
    ],
    "wof:name":"Tel Metal",
    "wof:placetype":"venue"
},
  "geometry": {"coordinates":[27.1880893707,38.4148597717],"type":"Point"}
}