{
  "type": "Feature",
  "properties": {
    "iso:country":"TR",
    "sg:address":"60. Sk. No:133/3",
    "sg:city":"Emek",
    "sg:classifiers":[
        {
            "category":"Professional",
            "subcategory":"Engineering",
            "type":"Services"
        }
    ],
    "sg:phone":"+90 312 223 0046",
    "sg:postcode":"01940",
    "sg:province":"Ankara",
    "sg:tags":[
        "architect"
    ],
    "wof:name":"Atilla Eser M?hendis. M?savir. Ltd. Sti.",
    "wof:placetype":"venue"
},
  "geometry": {"coordinates":[32.8604812622,39.9429283142],"type":"Point"}
}