{
  "type": "Feature",
  "properties": {
    "addr:full":"K.sanayi Sit.10.blok No:18 K.koy Cagaloglu Istanbul 34410",
    "addr:housenumber":"no 18",
    "addr:postcode":"34410",
    "iso:country":"TR",
    "sg:address":"K.sanayi Sit.10.blok No:18 K.koy",
    "sg:city":"Cagaloglu",
    "sg:classifiers":[
        {
            "category":"Freight",
            "type":"Transportation"
        }
    ],
    "sg:phone":"+90 212475095556",
    "sg:postcode":"34410",
    "sg:province":"Istanbul",
    "sg:tags":[
        "packing",
        "industry"
    ],
    "wof:name":"?nal Ambalaj",
    "wof:placetype":"venue"
},
  "geometry": {"coordinates":[28.9957962036,41.0822792053],"type":"Point"}
}