{
  "type": "Feature",
  "properties": {
    "iso:country":"TR",
    "sg:address":"Gumussuyu Cad. No:38/1 Cifte Havuzlar Yolu Siteyolu Sokak 34150 Bayrampasa Istanbul",
    "sg:city":"K???k?ekmece",
    "sg:classifiers":[
        {
            "category":"Manufacturing",
            "subcategory":"Textiles",
            "type":"Manufacturing & Wholesale Goods"
        }
    ],
    "sg:phone":"+90 212 576 2610",
    "sg:postcode":"34620",
    "sg:province":"Istanbul",
    "sg:tags":[
        "leather",
        "raw",
        "material",
        "-"
    ],
    "wof:name":"Meb Deri Esya San Tic As",
    "wof:placetype":"venue"
},
  "geometry": {"coordinates":[28.9759254456,41.0123786926],"type":"Point"}
}