{
  "type": "Feature",
  "properties": {
    "addr:full":"Kenan Evren Bulvari No: 40 Siteler Marmaris Mugla 48700",
    "addr:housenumber":"no 40",
    "addr:postcode":"48700",
    "addr:street":"Kenan Evren Bulvari",
    "iso:country":"TR",
    "sg:address":"Kenan Evren Bulvari No: 40 Siteler",
    "sg:city":"Marmaris",
    "sg:orig_category":"Hotels: Motels",
    "sg:phone":"+90 252 412 9589",
    "sg:postcode":"48700",
    "sg:province":"Mugla",
    "wof:name":"Pasa Bey",
    "wof:placetype":"venue"
},
  "geometry": {"coordinates":[28.3628406525,37.215675354],"type":"Point"}
}