{
  "type": "Feature",
  "properties": {
    "addr:full":"Aytar C. Etiler Mersin Istanbul 52750",
    "addr:postcode":"52750",
    "iso:country":"TR",
    "sg:address":"Aytar C. Etiler",
    "sg:city":"Mersin",
    "sg:classifiers":[
        {
            "category":"Home & Garden",
            "subcategory":"Building Materials",
            "type":"Retail Goods"
        }
    ],
    "sg:phone":"+90 212 269 2230",
    "sg:postcode":"52750",
    "sg:province":"Istanbul",
    "sg:tags":[
        "window",
        "door",
        "plastic"
    ],
    "wof:name":"G?npen Plastik Dograma San. Ltd. Sti.",
    "wof:placetype":"venue"
},
  "geometry": {"coordinates":[29.0175952911,41.074306488],"type":"Point"}
}