{
  "type": "Feature",
  "properties": {
    "addr:full":"Ozgur Mah.hidirilyas Cad.no:2 Korkuteli Burdur 07800",
    "addr:housenumber":"2",
    "addr:postcode":"07800",
    "addr:street":"Cad.No",
    "iso:country":"TR",
    "sg:address":"Ozgur Mah.hidirilyas Cad.no:2",
    "sg:city":"Korkuteli",
    "sg:classifiers":[
        {
            "category":"Farming",
            "subcategory":"Livestock Farm",
            "type":"Manufacturing & Wholesale Goods"
        }
    ],
    "sg:phone":"+90 248 212 4437",
    "sg:postcode":"07800",
    "sg:province":"Burdur",
    "sg:tags":[
        "fattening-breeding"
    ],
    "wof:name":"Murat Tic.",
    "wof:placetype":"venue"
},
  "geometry": {"coordinates":[30.2842998505,37.7192993164],"type":"Point"}
}