{
  "type": "Feature",
  "properties": {
    "addr:full":"Istiklal Cad 261 Istanbul 80060",
    "addr:housenumber":"261",
    "addr:postcode":"80060",
    "addr:street":"Istiklal Cad",
    "iso:country":"TR",
    "sg:address":"Istiklal Cad 261",
    "sg:city":"Istanbul",
    "sg:classifiers":[
        {
            "category":"Banks & Credit Unions",
            "subcategory":"Bank",
            "type":"Services"
        }
    ],
    "sg:phone":"+90 212 245 7432",
    "sg:province":"80060",
    "wof:name":"Pamukbank Tas",
    "wof:placetype":"venue"
},
  "geometry": {"coordinates":[37.100838,36.717472],"type":"Point"}
}