{
  "type": "Feature",
  "properties": {
    "addr:full":"Demirciler Sitesi C4 Blok No: 233 Ikitelli Okmeydani Istanbul 34900",
    "addr:housenumber":"blok no 233",
    "addr:postcode":"34900",
    "addr:street":"Demirciler;C4;Ikitelli Okmeydani",
    "iso:country":"TR",
    "sg:address":"Demirciler Sitesi C4 Blok No: 233 Ikitelli",
    "sg:city":"Okmeydani",
    "sg:classifiers":[
        {
            "category":"Professional",
            "subcategory":"Detective & Security Services",
            "type":"Services"
        }
    ],
    "sg:phone":"+90 212 549 8090",
    "sg:postcode":"34900",
    "sg:province":"Istanbul",
    "sg:tags":[
        "material"
    ],
    "wof:name":"Kks Enginnering",
    "wof:placetype":"venue"
},
  "geometry": {"coordinates":[28.975925,41.012379],"type":"Point"}
}