{
  "type": "Feature",
  "properties": {
    "iso:country":"TR",
    "sg:address":"Fatih Cad. Dereboyu Sok.no:3",
    "sg:city":"Halkali",
    "sg:classifiers":[
        {
            "category":"Shopping",
            "subcategory":"Crafts & Fabrics",
            "type":"Retail Goods"
        }
    ],
    "sg:phone":"+90 212 470 9740",
    "sg:postcode":"23410",
    "sg:province":"Istanbul",
    "sg:tags":[
        "weaving"
    ],
    "wof:name":"Kumash Tekstil San.ve Tic.a.s.",
    "wof:placetype":"venue"
},
  "geometry": {"coordinates":[29.1061897278,41.0948181152],"type":"Point"}
}