{
  "type": "Feature",
  "properties": {
    "addr:full":"?r?c?ler Cad. Hasanbaba ?arsisi. K: 2 Marmaris Balikesir 48700",
    "addr:housenumber":"2",
    "addr:postcode":"48700",
    "addr:street":"Balikesir",
    "iso:country":"TR",
    "sg:address":"?r?c?ler Cad. Hasanbaba ?arsisi. K: 2",
    "sg:city":"Marmaris",
    "sg:classifiers":[
        {
            "category":"Travel",
            "subcategory":"Travel Agent",
            "type":"Entertainment"
        }
    ],
    "sg:phone":"+90 266241175724",
    "sg:postcode":"48700",
    "sg:province":"Balikesir",
    "sg:tags":[
        "agency",
        "tourism"
    ],
    "wof:name":"Beks Turizm",
    "wof:placetype":"venue"
},
  "geometry": {"coordinates":[27.8853626251,39.6448822021],"type":"Point"}
}