{
  "type": "Feature",
  "properties": {
    "addr:full":"K?? San. Sit. B Blok No:24 K:2 ?mraniye Sisli Istanbul 34384",
    "addr:housenumber":"? ?;b blok no 24 k 2 ?",
    "addr:postcode":"34384",
    "addr:street":"San. Sit.;Mraniye Sisli",
    "iso:country":"TR",
    "sg:address":"K?? San. Sit. B Blok No:24 K:2 ?mraniye",
    "sg:city":"Sisli",
    "sg:classifiers":[
        {
            "category":"Manufacturing",
            "subcategory":"Metals",
            "type":"Manufacturing & Wholesale Goods"
        }
    ],
    "sg:phone":"+90 216 329 9728",
    "sg:postcode":"34384",
    "sg:province":"Istanbul",
    "sg:tags":[
        "industry"
    ],
    "wof:name":"Can Metal San.",
    "wof:placetype":"venue"
},
  "geometry": {"coordinates":[28.9688739777,41.0575942993],"type":"Point"}
}