{
  "type": "Feature",
  "properties": {
    "iso:country":"TR",
    "sg:address":"10015 Sk.no:11 A.o.s.b.",
    "sg:city":"?igli",
    "sg:classifiers":[
        {
            "category":"Parking",
            "subcategory":"Garage",
            "type":"Transportation"
        }
    ],
    "sg:phone":"+90 232 376 7635",
    "sg:province":"Izmir",
    "sg:tags":[
        "zipper"
    ],
    "wof:name":"Enis Fermuar Tic.san.ltd.sti.",
    "wof:placetype":"venue"
},
  "geometry": {"coordinates":[27.0420188904,38.4900474548],"type":"Point"}
}