{
  "type": "Feature",
  "properties": {
    "addr:full":"Des San.sit.a 09 B. 105.sok. No: 18 Y.dudullu Istanbul",
    "addr:housenumber":"09;18",
    "addr:street":"B. 105.Sok No",
    "iso:country":"TR",
    "sg:address":"Des San.sit.a 09 B. 105.sok. No: 18",
    "sg:city":"Y.dudullu",
    "sg:classifiers":[
        {
            "category":"Professional",
            "subcategory":"Engineering",
            "type":"Services"
        }
    ],
    "sg:phone":"+90 216 313 6171",
    "sg:province":"Istanbul",
    "sg:tags":[
        "architect"
    ],
    "wof:name":"Rota Muhendislik Mak.san.tic.ltd.sti.",
    "wof:placetype":"venue"
},
  "geometry": {"coordinates":[28.9861831665,41.0408554077],"type":"Point"}
}