{
  "type": "Feature",
  "properties": {
    "iso:country":"TR",
    "sg:address":"Cabbar Leygara",
    "sg:city":"Tortum",
    "sg:classifiers":[
        {
            "category":"Government",
            "subcategory":"Office",
            "type":"Public Place"
        }
    ],
    "sg:phone":"+90 412 236 2100",
    "sg:postcode":"25430",
    "sg:province":"Diyarbakir",
    "sg:tags":[
        "municipality"
    ],
    "wof:name":"Baglar Belediye Baskani",
    "wof:placetype":"venue"
},
  "geometry": {"coordinates":[40.2253341675,37.9158096313],"type":"Point"}
}