{
  "type": "Feature",
  "properties": {
    "iso:country":"TR",
    "sg:address":"Gaziosmanpasa Bulv. No: 3/3-305",
    "sg:city":"Saraylar",
    "sg:classifiers":[
        {
            "category":"Travel",
            "subcategory":"Travel Agent",
            "type":"Entertainment"
        }
    ],
    "sg:phone":"+90 232441867677",
    "sg:postcode":"20100",
    "sg:province":"Izmir",
    "sg:tags":[
        "agency",
        "tourism"
    ],
    "wof:name":"Tutku Turizm Seyahat Acentasi Ltd. Sti.",
    "wof:placetype":"venue"
},
  "geometry": {"coordinates":[27.1423015594,38.4251480103],"type":"Point"}
}