{
  "type": "Feature",
  "properties": {
    "addr:full":"B??dere Cd.kale Seramik Binasi K.6 Levent Istanbul 01310",
    "addr:housenumber":"? ?",
    "addr:postcode":"01310",
    "addr:street":"B;Dere Cd.Kale Seramik Binasi K.6",
    "iso:country":"TR",
    "sg:address":"B??dere Cd.kale Seramik Binasi K.6",
    "sg:city":"Levent",
    "sg:classifiers":[
        {
            "category":"Marine",
            "type":"Transportation"
        }
    ],
    "sg:phone":"+90 212 313 8819",
    "sg:postcode":"01310",
    "sg:province":"Istanbul",
    "sg:tags":[
        "shipowner"
    ],
    "wof:name":"Kale Nakl.a.s. .",
    "wof:placetype":"venue"
},
  "geometry": {"coordinates":[28.975925,41.012379],"type":"Point"}
}