{
  "type": "Feature",
  "properties": {
    "iso:country":"TR",
    "sg:address":"42/a Sk. No:48, 06370 Ostim Ankara",
    "sg:city":"Cagaloglu",
    "sg:classifiers":[
        {
            "category":"Shopping",
            "type":"Retail Goods"
        }
    ],
    "sg:phone":"+90 312 354 7352",
    "sg:postcode":"34440",
    "sg:province":"Ankara",
    "sg:tags":[
        "finished",
        "-",
        "metallic"
    ],
    "wof:name":"Odak End?stri Kontrol Makina San.ve Tic.ltd.sti",
    "wof:placetype":"venue"
},
  "geometry": {"coordinates":[32.7435188293,39.974357605],"type":"Point"}
}