{
  "type": "Feature",
  "properties": {
    "iso:country":"TR",
    "sg:address":"Eski Lara Yolu Fener Mah. Muhsin Adiyaman Sitesi E Blok Daire:3-4",
    "sg:city":"Eregli",
    "sg:classifiers":[
        {
            "category":"Manufacturing",
            "subcategory":"Food",
            "type":"Manufacturing & Wholesale Goods"
        }
    ],
    "sg:phone":"+90 242 323 6991",
    "sg:postcode":"42310",
    "sg:province":"Antalya",
    "sg:tags":[
        "wholesaler"
    ],
    "wof:name":"Palmar Su ?r?nleri End. A.s.",
    "wof:placetype":"venue"
},
  "geometry": {"coordinates":[30.7031345367,36.8875045776],"type":"Point"}
}