{
  "type": "Feature",
  "properties": {
    "iso:country":"TR",
    "sg:address":"Kelebek Sok.no:26/6 G.o.p",
    "sg:city":"Sapanca",
    "sg:classifiers":[
        {
            "category":"Manufacturing",
            "subcategory":"Wood Products",
            "type":"Manufacturing & Wholesale Goods"
        }
    ],
    "sg:phone":"+90 312 446 2322",
    "sg:postcode":"54600",
    "sg:province":"Ankara",
    "sg:tags":[
        "forest"
    ],
    "wof:name":"Uzakdogu Ticaret Insaat San. Tic. Ltd. Sti.",
    "wof:placetype":"venue"
},
  "geometry": {"coordinates":[32.8685531616,39.8913536072],"type":"Point"}
}