{
  "type": "Feature",
  "properties": {
    "iso:country":"TR",
    "sg:address":"Kocaali Cad. No:8 Samanli Mah. Sevinc Sokak 16280 Yildirim Bursa",
    "sg:city":"Ikitelli/K\u00fc\u00e7\u00fck\u00e7ekmece",
    "sg:classifiers":[
        {
            "category":"Shopping",
            "subcategory":"Crafts & Fabrics",
            "type":"Retail Goods"
        }
    ],
    "sg:phone":"+90 224 351 0223",
    "sg:postcode":"34670",
    "sg:province":"Bursa",
    "wof:name":"Dizdarlar Tekstil Boya Apre Plastikleme Tic Ve San As",
    "wof:placetype":"venue"
},
  "geometry": {"coordinates":[29.0580043793,40.1947555542],"type":"Point"}
}