{
  "type": "Feature",
  "properties": {
    "iso:country":"TR",
    "sg:address":"1819 Sk. No:94/4",
    "sg:city":"Karsiyaka",
    "sg:classifiers":[
        {
            "category":"Food & Beverages",
            "subcategory":"Groceries & Convenience Stores",
            "type":"Retail Goods"
        }
    ],
    "sg:phone":"+90 232 369 5645",
    "sg:postcode":"01900",
    "sg:province":"Izmir",
    "sg:tags":[
        "product"
    ],
    "wof:name":"Etna Dis Ticaret San.ltd.sti.",
    "wof:placetype":"venue"
},
  "geometry": {"coordinates":[27.1010932922,38.4620323181],"type":"Point"}
}