{
  "type": "Feature",
  "properties": {
    "addr:full":"Yerkvy/yozgat 2nd Floor, Bury House Yerkvy/yozgat LONDON",
    "addr:housenumber":"2nd floor bury house yerkvy",
    "iso:country":"TR",
    "sg:address":"Yerkvy/yozgat",
    "sg:city":"2nd Floor, Bury House",
    "sg:classifiers":[
        {
            "category":"Shopping",
            "subcategory":"Computers & Home Electronics",
            "type":"Retail Goods"
        }
    ],
    "sg:phone":"+90 354 516 1188",
    "sg:postcode":"LONDON",
    "sg:province":"Yerkvy/yozgat",
    "sg:tags":[
        "chamber",
        "commerce"
    ],
    "wof:name":"Yerkvy Ticaret Ve Sanayi Odasi",
    "wof:placetype":"venue"
},
  "geometry": {"coordinates":[35.096660614,39.6012802124],"type":"Point"}
}