{
  "type": "Feature",
  "properties": {
    "addr:full":"Babadaglilir Ish. Yildirim Denizli 16280",
    "addr:postcode":"16280",
    "iso:country":"TR",
    "sg:address":"Babadaglilir Ish.",
    "sg:city":"Yildirim",
    "sg:classifiers":[
        {
            "category":"Shopping",
            "subcategory":"Crafts & Fabrics",
            "type":"Retail Goods"
        }
    ],
    "sg:phone":"+90 258 265 0346",
    "sg:postcode":"16280",
    "sg:province":"Denizli",
    "sg:tags":[
        "knitting"
    ],
    "wof:name":"?zinci Tekstil Ltd.sti.",
    "wof:placetype":"venue"
},
  "geometry": {"coordinates":[29.0864906311,37.773525238],"type":"Point"}
}