{
  "type": "Feature",
  "properties": {
    "addr:full":"Muhittin Mah. Haci Saluh Sk. No: 6 Corlu Tekirdag 01770",
    "addr:postcode":"01770",
    "addr:street":"Muhittin Mah. Haci Saluh Sk. No 6",
    "iso:country":"TR",
    "sg:address":"Muhittin Mah. Haci Saluh Sk. No: 6",
    "sg:city":"Corlu",
    "sg:classifiers":[
        {
            "category":"Utilities",
            "subcategory":"Water",
            "type":"Services"
        }
    ],
    "sg:phone":"+90 282 653 8631",
    "sg:postcode":"01770",
    "sg:province":"Tekirdag",
    "sg:tags":[
        "spring"
    ],
    "wof:name":"Elut Otel",
    "wof:placetype":"venue"
},
  "geometry": {"coordinates":[27.800215,41.160698],"type":"Point"}
}