{
  "type": "Feature",
  "properties": {
    "addr:full":"3. Cd. No:115/c Demetevler Topkapi Ankara 24620",
    "addr:housenumber":"3;no;/ c",
    "addr:postcode":"24620",
    "addr:street":"Cd.;Demetevler",
    "iso:country":"TR",
    "sg:address":"3. Cd. No:115/c Demetevler",
    "sg:city":"Topkapi",
    "sg:orig_category":"Printinh House",
    "sg:phone":"+90 312 345 3533",
    "sg:postcode":"24620",
    "sg:province":"Ankara",
    "wof:name":"Anadolu Kagit Makina San. Tic. Ltd. Sti.",
    "wof:placetype":"venue"
},
  "geometry": {"coordinates":[29.1462192535,40.1967430115],"type":"Point"}
}