{
  "type": "Feature",
  "properties": {
    "addr:full":"Kisla Cd. G?bilek Ishani No:58/4 Bayrampasa Karak\u00f6y Istanbul 80000",
    "addr:housenumber":"?;58 / 4",
    "addr:postcode":"80000",
    "addr:street":"Kisla Cd. G;Ishani No",
    "iso:country":"TR",
    "sg:address":"Kisla Cd. G?bilek Ishani No:58/4 Bayrampasa",
    "sg:city":"Karak\u00f6y",
    "sg:classifiers":[
        {
            "category":"Wholesale",
            "subcategory":"Machinery & Supplies",
            "type":"Manufacturing & Wholesale Goods"
        }
    ],
    "sg:phone":"+90 212 565 0079",
    "sg:postcode":"80000",
    "sg:province":"Istanbul",
    "sg:tags":[
        "bearing",
        "ball"
    ],
    "wof:name":"Erol Rulman",
    "wof:placetype":"venue"
},
  "geometry": {"coordinates":[28.975925,41.012379],"type":"Point"}
}