{
  "type": "Feature",
  "properties": {
    "iso:country":"TR",
    "sg:address":"Kazim Karebekir",
    "sg:city":"Iskitler",
    "sg:classifiers":[
        {
            "category":"Banks & Credit Unions",
            "subcategory":"Bank",
            "type":"Services"
        }
    ],
    "sg:phone":"+90 312 309 4675",
    "sg:postcode":"06070",
    "sg:province":"06060",
    "wof:name":"T?k Dis Ticaret, Bankasi As",
    "wof:placetype":"venue"
},
  "geometry": {"coordinates":[32.845715,39.943459],"type":"Point"}
}