{
  "type": "Feature",
  "properties": {
    "iso:country":"TR",
    "sg:address":"E.evler Mah. Billur Cad. No:109",
    "sg:city":"Sapanca",
    "sg:classifiers":[
        {
            "category":"Manufacturing",
            "subcategory":"Wood Products",
            "type":"Manufacturing & Wholesale Goods"
        }
    ],
    "sg:phone":"+90 352 235 5853",
    "sg:postcode":"54600",
    "sg:province":"Kayseri",
    "sg:tags":[
        "forest"
    ],
    "wof:name":"?inar Insaat San. Dis. Ticaret Ltd.sti",
    "wof:placetype":"venue"
},
  "geometry": {"coordinates":[34.7059555054,38.6323547363],"type":"Point"}
}