{
  "type": "Feature",
  "properties": {
    "addr:full":"Kucukbakkalkoy Maslak Istanbul 34398",
    "addr:postcode":"34398",
    "iso:country":"TR",
    "sg:address":"Kucukbakkalkoy",
    "sg:city":"Maslak",
    "sg:orig_category":"Food Machinies",
    "sg:phone":"+90 212 527 6460",
    "sg:postcode":"34398",
    "sg:province":"Istanbul",
    "wof:name":"Intersoy Gida Ambalaj San.tic.ltd.sti.",
    "wof:placetype":"venue"
},
  "geometry": {"coordinates":[29.1115131378,40.9746398926],"type":"Point"}
}