{
  "type": "Feature",
  "properties": {
    "iso:country":"TR",
    "sg:address":"Ordu Cad.no: 90",
    "sg:city":"G.o.pasa",
    "sg:classifiers":[
        {
            "category":"Government",
            "subcategory":"Fire Station",
            "type":"Public Place"
        }
    ],
    "sg:phone":"+90 212 616 8464",
    "sg:province":"Istanbul",
    "sg:tags":[
        "decoration"
    ],
    "wof:name":"Cagdas Parke",
    "wof:placetype":"venue"
},
  "geometry": {"coordinates":[29.1040000916,41.0389900208],"type":"Point"}
}