{
  "type": "Feature",
  "properties": {
    "iso:country":"TR",
    "sg:address":"301 Sk.no.53 2. Sanayi Sitesi 35100",
    "sg:city":"Iskenderun",
    "sg:classifiers":[
        {
            "category":"Manufacturing",
            "subcategory":"Metals",
            "type":"Manufacturing & Wholesale Goods"
        }
    ],
    "sg:phone":"+90 232 486 6726",
    "sg:postcode":"31200",
    "sg:province":"Izmir",
    "sg:tags":[
        "industry"
    ],
    "wof:name":"S?mer G?nay Al?minyum San.ve Tic. Ltd.sti.",
    "wof:placetype":"venue"
},
  "geometry": {"coordinates":[26.3224525452,38.322681427],"type":"Point"}
}