{
  "type": "Feature",
  "properties": {
    "iso:country":"TR",
    "sg:address":"Yenidogan K???duragi No:1/b",
    "sg:city":"Emin\u00f6n\u00fc/Ca\u011falo\u011flu",
    "sg:classifiers":[
        {
            "category":"Shopping",
            "subcategory":"Stationery & Office Supplies",
            "type":"Retail Goods"
        }
    ],
    "sg:phone":"+90 262 321 9484",
    "sg:postcode":"34460",
    "sg:province":"Kocaeli",
    "sg:tags":[
        "paper"
    ],
    "wof:name":"?nder Kagit San. Tic. A.s.",
    "wof:placetype":"venue"
},
  "geometry": {"coordinates":[29.881521225,40.8532714844],"type":"Point"}
}