{
  "type": "Feature",
  "properties": {
    "iso:country":"TR",
    "sg:address":"Imam Ramiz Sok.ozcan Apt.no:75/3",
    "sg:city":"Sahrayicedid",
    "sg:classifiers":[
        {
            "category":"Food & Beverages",
            "subcategory":"Candy",
            "type":"Retail Goods"
        }
    ],
    "sg:phone":"+90 216 302 5195",
    "sg:province":"Istanbul",
    "sg:tags":[
        "biscuit-chocolate-candy"
    ],
    "wof:name":"Ege Serek",
    "wof:placetype":"venue"
},
  "geometry": {"coordinates":[29.072474,40.979073],"type":"Point"}
}