{
  "type": "Feature",
  "properties": {
    "addr:full":"Ali Nazim Sok.no:30 Kosuyolu-kadikoy Mecidiyek\u00f6y Istanbul 34387",
    "addr:housenumber":"30",
    "addr:postcode":"34387",
    "addr:street":"Sok.No",
    "iso:country":"TR",
    "sg:address":"Ali Nazim Sok.no:30 Kosuyolu-kadikoy",
    "sg:city":"Mecidiyek\u00f6y",
    "sg:orig_category":"Printinh House",
    "sg:phone":"+90 216 327 8010",
    "sg:postcode":"34387",
    "sg:province":"Istanbul",
    "wof:name":"Doga Sektorel Yayincilik Ltd.sti",
    "wof:placetype":"venue"
},
  "geometry": {"coordinates":[29.0389289856,41.0085830688],"type":"Point"}
}