{
  "type": "Feature",
  "properties": {
    "iso:country":"TR",
    "sg:address":"Buttim Tekstil Is Merkz. B-blok Kat:1 No:101",
    "sg:city":"Kestel",
    "sg:classifiers":[
        {
            "category":"Shopping",
            "subcategory":"Crafts & Fabrics",
            "type":"Retail Goods"
        }
    ],
    "sg:phone":"+90 224211110607",
    "sg:postcode":"09800",
    "sg:province":"Bursa",
    "sg:tags":[
        "weaving"
    ],
    "wof:name":"Vinyon Tekstil San. Ve Tic. Ltd.sti.",
    "wof:placetype":"venue"
},
  "geometry": {"coordinates":[29.0580043793,40.1947555542],"type":"Point"}
}