{
  "type": "Feature",
  "properties": {
    "addr:full":"Atat?k Cad. Koruyucu Ish. Kat 1, No 119 Heykel(gima Karsisi) Osmangazi Bursa 16010",
    "addr:housenumber":"kat 1 no 119",
    "addr:postcode":"16010",
    "addr:street":"K Cad. Koruyucu Ish.;Heykel Gima Karsisi",
    "iso:country":"TR",
    "sg:address":"Atat?k Cad. Koruyucu Ish. Kat 1, No 119 Heykel(gima Karsisi)",
    "sg:city":"Osmangazi",
    "sg:orig_category":"Translation Servies",
    "sg:phone":"+90 224 224 5714",
    "sg:postcode":"16010",
    "sg:province":"Bursa",
    "wof:name":"Orient Terc?me B?rosu",
    "wof:placetype":"venue"
},
  "geometry": {"coordinates":[29.0586109161,40.1844291687],"type":"Point"}
}