{
  "type": "Feature",
  "properties": {
    "iso:country":"TR",
    "sg:address":"La Maison Hotel. M?ezzi Cd. No:63 Besiktas",
    "sg:city":"Bayrampasa",
    "sg:classifiers":[
        {
            "category":"Communications",
            "subcategory":"Film & Video Production",
            "type":"Services"
        }
    ],
    "sg:phone":"+90 212 227 4291",
    "sg:postcode":"36100",
    "sg:province":"Istanbul",
    "sg:tags":[
        "-"
    ],
    "wof:name":"Radio Contact Istanbul 91.1 Fm",
    "wof:placetype":"venue"
},
  "geometry": {"coordinates":[28.9759254456,41.0123786926],"type":"Point"}
}