{
  "type": "Feature",
  "properties": {
    "addr:full":"Emirhan Cd. Bayindir Cikm. Sk. Uygarapt. No:1/3 D:3 Besiktas Karak\u00f6y Istanbul",
    "addr:housenumber":"3 d 3",
    "addr:street":"Emirhan Cd. Bayindir Cikm. Sk. Uygarapt. No 1 /;Besiktas Karakoey",
    "iso:country":"TR",
    "sg:address":"Emirhan Cd. Bayindir Cikm. Sk. Uygarapt. No:1/3 D:3 Besiktas",
    "sg:city":"Karak\u00f6y",
    "sg:classifiers":[
        {
            "category":"Organizations",
            "subcategory":"Membership Organization",
            "type":"Services"
        }
    ],
    "sg:phone":"+90 212 273 1632",
    "sg:province":"Istanbul",
    "wof:name":"Cagdas Yasami Destek. Dernegi",
    "wof:placetype":"venue"
},
  "geometry": {"coordinates":[29.0283794403,41.0764884949],"type":"Point"}
}