{
  "type": "Feature",
  "properties": {
    "addr:full":"E-5 Kartal K?r??yakacik Yanyol Murat Sok.no:2 Kartal Nil?fer Istanbul",
    "addr:housenumber":"2",
    "addr:street":"Sok.No",
    "iso:country":"TR",
    "sg:address":"E-5 Kartal K?r??yakacik Yanyol Murat Sok.no:2 Kartal",
    "sg:city":"Nil?fer",
    "sg:classifiers":[
        {
            "category":"Wholesale",
            "subcategory":"Auto Parts",
            "type":"Manufacturing & Wholesale Goods"
        }
    ],
    "sg:phone":"+90 216 451 1553",
    "sg:province":"Istanbul",
    "sg:tags":[
        "spare"
    ],
    "wof:name":"Basari Oto A.s",
    "wof:placetype":"venue"
},
  "geometry": {"coordinates":[29.2189102173,40.9053115845],"type":"Point"}
}