{
  "type": "Feature",
  "properties": {
    "addr:full":"Adana Ceyhan Karayolu 21. Km 01434 Suluca Adana Ikitelli/K\u00fc\u00e7\u00fck\u00e7ekmece Adana 34670",
    "addr:housenumber":"21 km",
    "addr:postcode":"01434;34670",
    "addr:street":"Karayolu;Adana",
    "iso:country":"TR",
    "sg:address":"Adana Ceyhan Karayolu 21. Km 01434 Suluca Adana",
    "sg:city":"Ikitelli/K\u00fc\u00e7\u00fck\u00e7ekmece",
    "sg:classifiers":[
        {
            "category":"Shopping",
            "subcategory":"Crafts & Fabrics",
            "type":"Retail Goods"
        }
    ],
    "sg:phone":"+90 322 394 3371",
    "sg:postcode":"34670",
    "sg:province":"Adana",
    "sg:tags":[
        "linen"
    ],
    "wof:name":"Pibay Tekstil San Ve Tic As",
    "wof:placetype":"venue"
},
  "geometry": {"coordinates":[35.3137359619,37.0007171631],"type":"Point"}
}