{
  "type": "Feature",
  "properties": {
    "iso:country":"TR",
    "sg:address":"Musallabaglari Mah.uludag Sokak No:90/113",
    "sg:city":"Sel?klu",
    "sg:classifiers":[
        {
            "category":"Wholesale",
            "subcategory":"Chemicals & Plastics",
            "type":"Manufacturing & Wholesale Goods"
        }
    ],
    "sg:phone":"+90 332 236 0547",
    "sg:postcode":"42060",
    "sg:province":"Konya",
    "wof:name":"Dergah Plastik",
    "wof:placetype":"venue"
},
  "geometry": {"coordinates":[32.5060386658,37.8974685669],"type":"Point"}
}