{
  "type": "Feature",
  "properties": {
    "addr:full":"K. Karabekir Cd. No:105/d Topkapi Ankara 24620",
    "addr:housenumber":"no;/ d",
    "addr:postcode":"24620",
    "addr:street":"K. Karabekir Cd.;Topkapi Ankara",
    "iso:country":"TR",
    "sg:address":"K. Karabekir Cd. No:105/d",
    "sg:city":"Topkapi",
    "sg:classifiers":[
        {
            "category":"Farming",
            "subcategory":"Fish & Marine Products",
            "type":"Manufacturing & Wholesale Goods"
        }
    ],
    "sg:phone":"+90 312 341 0878",
    "sg:postcode":"24620",
    "sg:province":"Ankara",
    "sg:tags":[
        "automotive"
    ],
    "wof:name":"Ankara Otomotiv A.s.",
    "wof:placetype":"venue"
},
  "geometry": {"coordinates":[32.8457145691,39.9434585571],"type":"Point"}
}