{
  "type": "Feature",
  "properties": {
    "addr:full":"Bagdat Caddesi No:371 Kinayman Sitesi B-blok K:4 D:10/11 34740 Erenkoy Istanbul Karsiyaka Istanbul 01900",
    "addr:housenumber":"no;4;11",
    "addr:postcode":"34740;01900",
    "addr:street":"Bagdat Caddesi;Kinayman;B-Blok;D 10 /",
    "iso:country":"TR",
    "sg:address":"Bagdat Caddesi No:371 Kinayman Sitesi B-blok K:4 D:10/11 34740 Erenkoy Istanbul",
    "sg:city":"Karsiyaka",
    "sg:classifiers":[
        {
            "category":"Autos & Motor Vehicles",
            "subcategory":"Automobile Sales",
            "type":"Retail Goods"
        }
    ],
    "sg:phone":"+90 216 411 4940",
    "sg:postcode":"01900",
    "sg:province":"Istanbul",
    "sg:tags":[
        "motor-cars"
    ],
    "wof:name":"Mapar Makina Pazarlama Ve Tur Ltd Sti",
    "wof:placetype":"venue"
},
  "geometry": {"coordinates":[28.9759254456,41.0123786926],"type":"Point"}
}