{
  "type": "Feature",
  "properties": {
    "iso:country":"TR",
    "sg:address":"Izmir2 Cad. 45/4 Kizilay",
    "sg:city":"Sisli",
    "sg:classifiers":[
        {
            "category":"Shopping",
            "subcategory":"Stationery & Office Supplies",
            "type":"Retail Goods"
        }
    ],
    "sg:phone":"+90 312 425 3020",
    "sg:postcode":"65710",
    "sg:province":"Ankara",
    "wof:name":"Aydin Ins. San.tic. Ltd.sti.",
    "wof:placetype":"venue"
},
  "geometry": {"coordinates":[32.850533,39.9203],"type":"Point"}
}