{
  "type": "Feature",
  "properties": {
    "addr:full":"Atat?k Cd. No:150 Bandirma 38070 Balikesir",
    "addr:housenumber":"no",
    "addr:postcode":"38070",
    "addr:street":"K Cd.",
    "iso:country":"TR",
    "sg:address":"Atat?k Cd. No:150 Bandirma",
    "sg:city":"38070",
    "sg:orig_category":"Aluminium Carpentary",
    "sg:phone":"+90 266 713 6903",
    "sg:province":"Balikesir",
    "wof:name":"Gulden Alum. Panjur San.",
    "wof:placetype":"venue"
},
  "geometry": {"coordinates":[27.9706001282,40.3487014771],"type":"Point"}
}