{
  "type": "Feature",
  "properties": {
    "addr:full":"Atat?k Oto San. 2. Kisim 33. Sk. No.1387 Maslak Yenimahalle Istanbul 06170",
    "addr:housenumber":"2;33",
    "addr:postcode":"06170",
    "addr:street":"San.;Sk. No.1387",
    "iso:country":"TR",
    "sg:address":"Atat?k Oto San. 2. Kisim 33. Sk. No.1387 Maslak",
    "sg:city":"Yenimahalle",
    "sg:classifiers":[
        {
            "category":"Retail",
            "subcategory":"Auto Repair",
            "type":"Services"
        }
    ],
    "sg:phone":"+90 212 328 0958",
    "sg:postcode":"06170",
    "sg:province":"Istanbul",
    "sg:tags":[
        "maintenance"
    ],
    "wof:name":"A&s Dizel",
    "wof:placetype":"venue"
},
  "geometry": {"coordinates":[28.9861831665,41.0408554077],"type":"Point"}
}