{
  "type": "Feature",
  "properties": {
    "addr:full":"Des Sanayi Sitesi 112 Sk.d03 Blok No 8 Y.dudullu Istanbul",
    "addr:housenumber":"112;blok no 8",
    "addr:postcode":"sk.d03",
    "addr:street":"Des Sanayi Sitesi",
    "iso:country":"TR",
    "sg:address":"Des Sanayi Sitesi 112 Sk.d03 Blok No 8",
    "sg:city":"Y.dudullu",
    "sg:classifiers":[
        {
            "category":"Manufacturing",
            "subcategory":"Metals",
            "type":"Manufacturing & Wholesale Goods"
        }
    ],
    "sg:phone":"+90 21652609865",
    "sg:province":"Istanbul",
    "sg:tags":[
        "processing"
    ],
    "wof:name":"Tesmak Daire Ve Seritli Testere Tezgahlari Ve Mak.san.tic.ltd.sti",
    "wof:placetype":"venue"
},
  "geometry": {"coordinates":[28.9759254456,41.0123786926],"type":"Point"}
}