{
  "type": "Feature",
  "properties": {
    "iso:country":"TR",
    "sg:address":"Eskisehir Yolu",
    "sg:city":"G?basi",
    "sg:classifiers":[
        {
            "category":"Professional",
            "subcategory":"Engineering",
            "type":"Services"
        }
    ],
    "sg:phone":"+90 312 439 1824",
    "sg:province":"Ankara",
    "sg:tags":[
        "architect"
    ],
    "wof:name":"Unitek M?hendis. Isleri Ltd. Sti.",
    "wof:placetype":"venue"
},
  "geometry": {"coordinates":[32.7766532898,39.9084243774],"type":"Point"}
}