{
  "type": "Feature",
  "properties": {
    "addr:full":"Bahariye Cd. ?nertan Pasj. Kadik? Kusadasi Istanbul 09400",
    "addr:housenumber":"?",
    "addr:postcode":"09400",
    "addr:street":"Bahariye Cd.",
    "iso:country":"TR",
    "sg:address":"Bahariye Cd. ?nertan Pasj. Kadik?",
    "sg:city":"Kusadasi",
    "sg:orig_category":"Art Galeries",
    "sg:phone":"+90 216 418 5491",
    "sg:postcode":"09400",
    "sg:province":"Istanbul",
    "wof:name":"Atlantis Sinemasi",
    "wof:placetype":"venue"
},
  "geometry": {"coordinates":[28.9861831665,41.0408554077],"type":"Point"}
}