{
  "type": "Feature",
  "properties": {
    "addr:full":"Basak Sok. No:41/1-a Kucukesat Sisli Ankara 80270",
    "addr:housenumber":"no 41 / 1-a",
    "addr:postcode":"80270",
    "addr:street":"Basak Sok.;Kucukesat Sisli",
    "iso:country":"TR",
    "sg:address":"Basak Sok. No:41/1-a Kucukesat",
    "sg:city":"Sisli",
    "sg:orig_category":"Scavening Services",
    "sg:phone":"+90 312 418 8540",
    "sg:postcode":"80270",
    "sg:province":"Ankara",
    "wof:name":"Ak-su Temizlik Hizmetleri Tic.ltd.sti.",
    "wof:placetype":"venue"
},
  "geometry": {"coordinates":[32.864948,39.911129],"type":"Point"}
}