{
  "type": "Feature",
  "properties": {
    "iso:country":"TR",
    "sg:address":"Istanbul Cad. No:64 Yeldegirmeni Mevkii Gurpinar 34902 Buyukcekmece Istanbul",
    "sg:city":"Bayrampasa",
    "sg:classifiers":[
        {
            "category":"Manufacturing",
            "subcategory":"Metals",
            "type":"Manufacturing & Wholesale Goods"
        }
    ],
    "sg:phone":"+90 212 880 5471",
    "sg:postcode":"36100",
    "sg:province":"Istanbul",
    "sg:tags":[
        "processing"
    ],
    "wof:name":"Ozgur Metal Urunleri San Tic Ltd Sti",
    "wof:placetype":"venue"
},
  "geometry": {"coordinates":[28.9759254456,41.0123786926],"type":"Point"}
}