{
  "type": "Feature",
  "properties": {
    "addr:full":"Kemankes Mah. Karamustafapasa Sok. No:59-60 -beyoglu Krak? Istanbul",
    "addr:housenumber":"no 59-60;?",
    "addr:street":"Kemankes Mah. Karamustafapasa Sok.;Beyoglu Krak",
    "iso:country":"TR",
    "sg:address":"Kemankes Mah. Karamustafapasa Sok. No:59-60 -beyoglu",
    "sg:city":"Krak?",
    "sg:classifiers":[
        {
            "category":"Marine",
            "type":"Transportation"
        }
    ],
    "sg:phone":"+90 212 251 8559",
    "sg:province":"Istanbul",
    "sg:tags":[
        "equipment",
        "maritime"
    ],
    "wof:name":"Akademi Denizcilik Danismanlik Egitim Ve Yayincilik",
    "wof:placetype":"venue"
},
  "geometry": {"coordinates":[28.9745006561,41.0350418091],"type":"Point"}
}