{
  "type": "Feature",
  "properties": {
    "iso:country":"TR",
    "sg:address":"Bakkal Sok. No:13",
    "sg:city":"Yesildirek",
    "sg:classifiers":[
        {
            "category":"Shopping",
            "subcategory":"Clothing, Apparel, & Fashions",
            "type":"Retail Goods"
        }
    ],
    "sg:phone":"+90 212 511 5031",
    "sg:postcode":"63200",
    "sg:province":"Istanbul",
    "sg:tags":[
        "underwear"
    ],
    "wof:name":"Tengulu Camasirlari",
    "wof:placetype":"venue"
},
  "geometry": {"coordinates":[28.985582,41.084469],"type":"Point"}
}