{
  "type": "Feature",
  "properties": {
    "addr:full":"Mesudiye Mh. 102 Sk.no:3/c Beypazari I?el 06730",
    "addr:housenumber":"102;3 / c;?",
    "addr:postcode":"06730",
    "addr:street":"Mh.;Sk.No;I;El",
    "iso:country":"TR",
    "sg:address":"Mesudiye Mh. 102 Sk.no:3/c",
    "sg:city":"Beypazari",
    "sg:classifiers":[
        {
            "category":"Farming",
            "subcategory":"Berry Farm",
            "type":"Manufacturing & Wholesale Goods"
        }
    ],
    "sg:phone":"+90 324 336 5377",
    "sg:postcode":"06730",
    "sg:province":"I?el",
    "sg:tags":[
        "citrus"
    ],
    "wof:name":"Cemal Gida A.s.",
    "wof:placetype":"venue"
},
  "geometry": {"coordinates":[31.9300098419,40.1387710571],"type":"Point"}
}