{
  "type": "Feature",
  "properties": {
    "addr:full":"Ertem Sk. K:4 No:4/9 Gayrettepe Esenler Istanbul 34200",
    "addr:housenumber":"4;9",
    "addr:postcode":"34200",
    "addr:street":"Ertem Sk. K;No 4 /",
    "iso:country":"TR",
    "sg:address":"Ertem Sk. K:4 No:4/9 Gayrettepe",
    "sg:city":"Esenler",
    "sg:classifiers":[
        {
            "category":"Wholesale",
            "subcategory":"Durable Goods & Equipment",
            "type":"Manufacturing & Wholesale Goods"
        }
    ],
    "sg:phone":"+90 212 240 6780",
    "sg:postcode":"34200",
    "sg:province":"Istanbul",
    "sg:tags":[
        "consumer"
    ],
    "wof:name":"Temiz Tic. Ltd.",
    "wof:placetype":"venue"
},
  "geometry": {"coordinates":[28.9861831665,41.0408554077],"type":"Point"}
}