{
  "type": "Feature",
  "properties": {
    "addr:full":"Menekse 2. Sk. No:32/12 Kizilay Merkez Ankara 77200",
    "addr:housenumber":"2;32 / 12",
    "addr:postcode":"77200",
    "addr:street":"Menekse;Sk. No;Kizilay Merkez",
    "iso:country":"TR",
    "sg:address":"Menekse 2. Sk. No:32/12 Kizilay",
    "sg:city":"Merkez",
    "sg:classifiers":[
        {
            "category":"Shopping",
            "subcategory":"Music",
            "type":"Retail Goods"
        }
    ],
    "sg:phone":"+90 312 309 0605",
    "sg:postcode":"77200",
    "sg:province":"Ankara",
    "sg:tags":[
        "record",
        "casette"
    ],
    "wof:name":"Vimpa Toptan Video M?zik Kaset Paz.",
    "wof:placetype":"venue"
},
  "geometry": {"coordinates":[32.851020813,39.9219360352],"type":"Point"}
}