{
  "type": "Feature",
  "properties": {
    "iso:country":"TR",
    "sg:address":"Ulubatli Hasan",
    "sg:city":"Garajlar",
    "sg:classifiers":[
        {
            "category":"Banks & Credit Unions",
            "subcategory":"Bank",
            "type":"Services"
        }
    ],
    "sg:phone":"+90 224 255 4014",
    "sg:province":"16240",
    "wof:name":"T?kiye Halk, Bankasi As",
    "wof:placetype":"venue"
},
  "geometry": {"coordinates":[29.065725,40.196068],"type":"Point"}
}