{
  "type": "Feature",
  "properties": {
    "iso:country":"TR",
    "sg:address":"Hanlar Girisi No:1/18 Amasya",
    "sg:city":"Merkez",
    "sg:classifiers":[
        {
            "category":"Mining & Drilling",
            "type":"Manufacturing & Wholesale Goods"
        }
    ],
    "sg:phone":"+90 2185977",
    "sg:province":"Amasya",
    "sg:tags":[
        "industry",
        "mine"
    ],
    "wof:name":"Merttas K?m?r Nak. Paz.",
    "wof:placetype":"venue"
},
  "geometry": {"coordinates":[35.8320007324,40.6543998718],"type":"Point"}
}