{
  "type": "Feature",
  "properties": {
    "addr:full":"Gazi Bulvari No:85 Kat:5 Beyoglu Izmir 46810",
    "addr:housenumber":"no 85 kat 5",
    "addr:postcode":"46810",
    "addr:street":"Gazi Bulvari;Beyoglu Izmir",
    "iso:country":"TR",
    "sg:address":"Gazi Bulvari No:85 Kat:5",
    "sg:city":"Beyoglu",
    "sg:classifiers":[
        {
            "category":"Shopping",
            "subcategory":"Clothing, Apparel, & Fashions",
            "type":"Retail Goods"
        }
    ],
    "sg:phone":"+90 232 445 1253",
    "sg:postcode":"46810",
    "sg:province":"Izmir",
    "sg:tags":[
        "ready",
        "wear"
    ],
    "wof:name":"Lilac Textil Inc.",
    "wof:placetype":"venue"
},
  "geometry": {"coordinates":[27.1296863556,38.4186973572],"type":"Point"}
}