{
  "type": "Feature",
  "properties": {
    "addr:full":"Yali Mah .esma Sok. No:5/5 Maltepe Beypazari Istanbul 06730",
    "addr:housenumber":"sok. no 5 / 5",
    "addr:postcode":"06730",
    "addr:street":"Mah Esma;Maltepe Beypazari",
    "iso:country":"TR",
    "sg:address":"Yali Mah .esma Sok. No:5/5 Maltepe",
    "sg:city":"Beypazari",
    "sg:classifiers":[
        {
            "category":"Manufacturing",
            "subcategory":"Wood Products",
            "type":"Manufacturing & Wholesale Goods"
        }
    ],
    "sg:phone":"+90 216 383 9770",
    "sg:postcode":"06730",
    "sg:province":"Istanbul",
    "sg:tags":[
        "forest"
    ],
    "wof:name":"Birgul Orman Urunleri",
    "wof:placetype":"venue"
},
  "geometry": {"coordinates":[28.9861831665,41.0408554077],"type":"Point"}
}