{
  "type": "Feature",
  "properties": {
    "addr:full":"Yarhasanlar Mah. Yeni Hasaga Sok. No:17/a Mecidiyek\u00f6y Manisa",
    "addr:housenumber":"no 17 / a;manisa",
    "addr:street":"Yarhasanlar Mah. Yeni Hasaga Sok.",
    "iso:country":"TR",
    "sg:address":"Yarhasanlar Mah. Yeni Hasaga Sok. No:17/a",
    "sg:city":"Mecidiyek\u00f6y",
    "sg:classifiers":[
        {
            "category":"Shopping",
            "subcategory":"Computers & Home Electronics",
            "type":"Retail Goods"
        }
    ],
    "sg:phone":"+90 236 234 1153",
    "sg:province":"Manisa",
    "sg:tags":[
        "product",
        "electric-electronic"
    ],
    "wof:name":"Manelsan Muhendislik Hizmetleri",
    "wof:placetype":"venue"
},
  "geometry": {"coordinates":[28.1065292358,38.7328796387],"type":"Point"}
}