{
  "type": "Feature",
  "properties": {
    "addr:full":"Tersane Cd. Fatih ?ars. No:19/9 Karak\u00f6y Istanbul",
    "addr:housenumber":"no 19 / 9",
    "addr:street":"Tersane;Fatih;Ars.",
    "iso:country":"TR",
    "sg:address":"Tersane Cd. Fatih ?ars. No:19/9",
    "sg:city":"Karak\u00f6y",
    "sg:classifiers":[
        {
            "category":"Home & Garden",
            "subcategory":"Hardware",
            "type":"Retail Goods"
        }
    ],
    "sg:phone":"+90 212 243 1584",
    "sg:province":"Istanbul",
    "sg:tags":[
        "store"
    ],
    "wof:name":"Sekerciler Mak. & Teknik Hirdavat Ltd. Sti.",
    "wof:placetype":"venue"
},
  "geometry": {"coordinates":[28.9861831665,41.0408554077],"type":"Point"}
}