{
  "type": "Feature",
  "properties": {
    "iso:country":"TR",
    "sg:address":"Ziyabey Cd. No:61/b",
    "sg:city":"Balgat",
    "sg:classifiers":[
        {
            "category":"Utilities",
            "subcategory":"Natural Gas",
            "type":"Services"
        }
    ],
    "sg:phone":"+90 312 286 4251",
    "sg:postcode":"63510",
    "sg:province":"Ankara",
    "sg:tags":[
        "tank-heating-natural"
    ],
    "wof:name":"Bol-fer Isitma San. Tic. Ltd. Sti.",
    "wof:placetype":"venue"
},
  "geometry": {"coordinates":[32.8604812622,39.9429283142],"type":"Point"}
}