{
  "type": "Feature",
  "properties": {
    "addr:full":"Miralay Tevik Sok.no:13/3 Taksim 26000 Istanbul",
    "addr:housenumber":"13 / 3",
    "addr:postcode":"26000",
    "addr:street":"Sok.No",
    "iso:country":"TR",
    "sg:address":"Miralay Tevik Sok.no:13/3 Taksim",
    "sg:city":"26000",
    "sg:classifiers":[
        {
            "category":"Manufacturing",
            "subcategory":"Leather Goods",
            "type":"Manufacturing & Wholesale Goods"
        }
    ],
    "sg:phone":"+90 212 292 9802",
    "sg:province":"Istanbul",
    "sg:tags":[
        "machine"
    ],
    "wof:name":"Vinder Deri Tekstil Kimya San.ve Tic.a.s.",
    "wof:placetype":"venue"
},
  "geometry": {"coordinates":[28.9759254456,41.0123786926],"type":"Point"}
}