{
  "type": "Feature",
  "properties": {
    "iso:country":"TR",
    "sg:address":"H??et Bulv. 7 Sk. Vakif Duk. No:40",
    "sg:city":"Gediz",
    "sg:classifiers":[
        {
            "category":"Food & Beverages",
            "subcategory":"Dairy",
            "type":"Retail Goods"
        }
    ],
    "sg:phone":"+90 256225312921",
    "sg:postcode":"43600",
    "sg:province":"Aydin",
    "sg:tags":[
        "pruducts",
        "milk"
    ],
    "wof:name":"Gonulacar Sut San. Tic. Ltd. Sti.",
    "wof:placetype":"venue"
},
  "geometry": {"coordinates":[28.4863967896,37.8117027283],"type":"Point"}
}