{
  "type": "Feature",
  "properties": {
    "iso:country":"TR",
    "sg:address":"Karliktepe 2.soganlik Cad. Ayabakan Sk. No.20 Kartal",
    "sg:city":"Merkez",
    "sg:classifiers":[
        {
            "category":"Social Services",
            "subcategory":"Retirement Home",
            "type":"Services"
        }
    ],
    "sg:phone":"+90 21638772636428",
    "sg:postcode":"07050",
    "sg:province":"Istanbul",
    "sg:tags":[
        "door"
    ],
    "wof:name":"Penta Reklam San. Ve Tic.ltd.sti.",
    "wof:placetype":"venue"
},
  "geometry": {"coordinates":[29.1931419373,40.9012489319],"type":"Point"}
}