{
  "type": "Feature",
  "properties": {
    "addr:full":"Ihlamurdere Cad.misirli Bahce Sk No:20 A Besiktas Istanbul 75200",
    "addr:housenumber":"20 a",
    "addr:postcode":"75200",
    "addr:street":"Bahce",
    "iso:country":"TR",
    "sg:address":"Ihlamurdere Cad.misirli Bahce Sk No:20 A",
    "sg:city":"Besiktas",
    "sg:classifiers":[
        {
            "category":"Manufacturing",
            "subcategory":"Glass & Minerals",
            "type":"Manufacturing & Wholesale Goods"
        }
    ],
    "sg:phone":"+90 212 261 0646",
    "sg:postcode":"75200",
    "sg:province":"Istanbul",
    "sg:tags":[
        "glass-mirror"
    ],
    "wof:name":"Teknik Cam Ticaret",
    "wof:placetype":"venue"
},
  "geometry": {"coordinates":[29.0017299652,41.0447654724],"type":"Point"}
}