{
  "type": "Feature",
  "properties": {
    "addr:full":"Gursel Mah. Ilkem Sk. No: 5 Kagithane Kazasker Istanbul",
    "addr:street":"Gursel Mah. Ilkem Sk. No 5 Kagithane Kazasker",
    "iso:country":"TR",
    "sg:address":"Gursel Mah. Ilkem Sk. No: 5 Kagithane",
    "sg:city":"Kazasker",
    "sg:classifiers":[
        {
            "category":"Manufacturing",
            "subcategory":"Chemicals & Compounds",
            "type":"Manufacturing & Wholesale Goods"
        }
    ],
    "sg:phone":"+90 212 220 6160",
    "sg:province":"Istanbul",
    "sg:tags":[
        "pharmaceutical"
    ],
    "wof:name":"Unipharm Ilac San. Ve Tic. A.s.",
    "wof:placetype":"venue"
},
  "geometry": {"coordinates":[28.9787101746,41.0829963684],"type":"Point"}
}