{
  "type": "Feature",
  "properties": {
    "iso:country":"TR",
    "sg:address":"1.organize Sanayi B?gesi G?t?k Cad. No:11 Sincan",
    "sg:city":"16020",
    "sg:classifiers":[
        {
            "category":"Wholesale",
            "subcategory":"Plants",
            "type":"Manufacturing & Wholesale Goods"
        }
    ],
    "sg:phone":"+90 312 267 0170",
    "sg:province":"Ankara",
    "sg:tags":[
        "natural",
        "spice"
    ],
    "wof:name":"Musan Gida San.ve Tic.a.s.(food Ind Tra.co.)",
    "wof:placetype":"venue"
},
  "geometry": {"coordinates":[32.5797,39.964199],"type":"Point"}
}