{
  "type": "Feature",
  "properties": {
    "addr:full":"Silivri Cad. No: 6 Mimarsinan - B.cekmece Istanbul",
    "addr:street":"Silivri Cad. No 6",
    "iso:country":"TR",
    "sg:address":"Silivri Cad. No: 6 Mimarsinan -",
    "sg:city":"B.cekmece",
    "sg:classifiers":[
        {
            "category":"Food & Beverages",
            "subcategory":"Ethnic Foods",
            "type":"Retail Goods"
        }
    ],
    "sg:phone":"+90 212 883 5099",
    "sg:province":"Istanbul",
    "sg:tags":[
        "canned"
    ],
    "wof:name":"Istanbul Gida Sanayi Ve Tic. A.s.",
    "wof:placetype":"venue"
},
  "geometry": {"coordinates":[28.5521354675,41.0173301697],"type":"Point"}
}