{
  "type": "Feature",
  "properties": {
    "addr:full":"San. Sit. Yesiloba Mh. 5.blok No:7 Mudanya Adana 1600",
    "addr:housenumber":"1600",
    "addr:street":"Mh. 5.Blok No 7 Mudanya Adana",
    "iso:country":"TR",
    "sg:address":"San. Sit. Yesiloba Mh. 5.blok No:7",
    "sg:city":"Mudanya",
    "sg:classifiers":[
        {
            "category":"Home & Garden",
            "subcategory":"Hardware",
            "type":"Retail Goods"
        }
    ],
    "sg:phone":"+90 322 428 2954",
    "sg:postcode":"1600",
    "sg:province":"Adana",
    "sg:tags":[
        "compressor",
        "pump"
    ],
    "wof:name":"G?zel Kompres?r San. Tic. Ltd. Sti.",
    "wof:placetype":"venue"
},
  "geometry": {"coordinates":[35.3137359619,37.0007171631],"type":"Point"}
}