{
  "type": "Feature",
  "properties": {
    "addr:full":"Saray Mah. Sipahioglu Apt. B:128 D:8 Alanya Ikitelli/K\u00fc\u00e7\u00fck\u00e7ekmece Antalya 34670",
    "addr:housenumber":"128 d 8",
    "addr:postcode":"34670",
    "addr:street":"Mah. Sipahioglu Apt. B",
    "iso:country":"TR",
    "sg:address":"Saray Mah. Sipahioglu Apt. B:128 D:8 Alanya",
    "sg:city":"Ikitelli/K\u00fc\u00e7\u00fck\u00e7ekmece",
    "sg:classifiers":[
        {
            "category":"Shopping",
            "subcategory":"Clothing, Apparel, & Fashions",
            "type":"Retail Goods"
        }
    ],
    "sg:phone":"+90 242 513 9464",
    "sg:postcode":"34670",
    "sg:province":"Antalya",
    "sg:tags":[
        "bag-belt-accessories"
    ],
    "wof:name":"Hakim Ltd.",
    "wof:placetype":"venue"
},
  "geometry": {"coordinates":[31.985443,36.546688],"type":"Point"}
}