{
  "type": "Feature",
  "properties": {
    "addr:full":"Sekerciler Cd. No:9 Kad\u0131k\u00f6y Kayseri 34000",
    "addr:housenumber":"no 9",
    "addr:postcode":"34000",
    "addr:street":"Sekerciler Cd.",
    "iso:country":"TR",
    "sg:address":"Sekerciler Cd. No:9",
    "sg:city":"Kad\u0131k\u00f6y",
    "sg:classifiers":[
        {
            "category":"Shopping",
            "subcategory":"Computers & Home Electronics",
            "type":"Retail Goods"
        }
    ],
    "sg:phone":"+90 352 231 2584",
    "sg:postcode":"34000",
    "sg:province":"Kayseri",
    "sg:tags":[
        "product",
        "electric-electronic"
    ],
    "wof:name":"Elmas Elektrik San. Tic. A.s.",
    "wof:placetype":"venue"
},
  "geometry": {"coordinates":[36.4393234253,38.2791290283],"type":"Point"}
}