{
  "type": "Feature",
  "properties": {
    "iso:country":"TR",
    "sg:address":"Ismet Pasa Mah. 96. Sok. No:19",
    "sg:city":"G.o.p",
    "sg:classifiers":[
        {
            "category":"Manufacturing",
            "subcategory":"Textiles",
            "type":"Manufacturing & Wholesale Goods"
        }
    ],
    "sg:phone":"+90 212 476 2944",
    "sg:province":"Istanbul",
    "sg:tags":[
        "cloth",
        "worker"
    ],
    "wof:name":"Has Temizlik Md.ith.ihr.paz.ltd.sti.",
    "wof:placetype":"venue"
},
  "geometry": {"coordinates":[28.9618301392,41.0775032043],"type":"Point"}
}