{
  "type": "Feature",
  "properties": {
    "addr:full":"Eskop Sanayi Sitesi C5 -269 Ikitelli Karatay Istanbul 42300",
    "addr:housenumber":"c5 -269",
    "addr:postcode":"42300",
    "addr:street":"Eskop Sanayi Sitesi;Ikitelli",
    "iso:country":"TR",
    "sg:address":"Eskop Sanayi Sitesi C5 -269 Ikitelli",
    "sg:city":"Karatay",
    "sg:classifiers":[
        {
            "category":"Building & Trades",
            "subcategory":"Construction",
            "type":"Services"
        }
    ],
    "sg:phone":"+90 212 549 8467",
    "sg:postcode":"42300",
    "sg:province":"Istanbul",
    "sg:tags":[
        "industry",
        "mold"
    ],
    "wof:name":"Arc Kalip Ve Tasarim Ltd.sti.",
    "wof:placetype":"venue"
},
  "geometry": {"coordinates":[28.8057422638,41.0732727051],"type":"Point"}
}