{
  "type": "Feature",
  "properties": {
    "addr:full":"K. Karabekir Cd. No:120/2 Iskitler Mersin Ankara 52750",
    "addr:housenumber":"no;/ 2",
    "addr:postcode":"52750",
    "addr:street":"K. Karabekir Cd.;Iskitler",
    "iso:country":"TR",
    "sg:address":"K. Karabekir Cd. No:120/2 Iskitler",
    "sg:city":"Mersin",
    "sg:classifiers":[
        {
            "category":"Professional",
            "subcategory":"Art Services",
            "type":"Services"
        }
    ],
    "sg:phone":"+90 312 312 3181",
    "sg:postcode":"52750",
    "sg:province":"Ankara",
    "sg:tags":[
        "marketing"
    ],
    "wof:name":"Biltur Turizm Insaat San. A.s.",
    "wof:placetype":"venue"
},
  "geometry": {"coordinates":[32.8604812622,39.9429283142],"type":"Point"}
}