{
  "type": "Feature",
  "properties": {
    "addr:full":"S?eyman Bey Sok. 7/1 Maltepe Mecidiyek\u00f6y Ankara",
    "addr:housenumber":"?;7 / 1",
    "addr:street":"S;Bey Sok.;Maltepe Mecidiyekoey",
    "iso:country":"TR",
    "sg:address":"S?eyman Bey Sok. 7/1 Maltepe",
    "sg:city":"Mecidiyek\u00f6y",
    "sg:classifiers":[
        {
            "category":"Shopping",
            "subcategory":"Computers & Home Electronics",
            "type":"Retail Goods"
        }
    ],
    "sg:phone":"+90 312 230 8414",
    "sg:province":"Ankara",
    "sg:tags":[
        "product",
        "electric-electronic"
    ],
    "wof:name":"Maya Muhendislik Ltd.sti.",
    "wof:placetype":"venue"
},
  "geometry": {"coordinates":[32.8455581665,39.9274291992],"type":"Point"}
}