{
  "type": "Feature",
  "properties": {
    "addr:full":"Yolcuzade Iskender Cd. No:14 Sishane Istanbul",
    "addr:housenumber":"no 14",
    "addr:street":"Cd.",
    "iso:country":"TR",
    "sg:address":"Yolcuzade Iskender Cd. No:14",
    "sg:city":"Sishane",
    "sg:classifiers":[
        {
            "category":"Building & Trades",
            "subcategory":"Electrical",
            "type":"Services"
        }
    ],
    "sg:phone":"+90 212 255 5505",
    "sg:province":"Istanbul",
    "sg:tags":[
        "equipment",
        "lighting"
    ],
    "wof:name":"Ta? Avize San. Dis Tic. Ltd. Sti.",
    "wof:placetype":"venue"
},
  "geometry": {"coordinates":[28.9692649841,41.0268325806],"type":"Point"}
}