{
  "type": "Feature",
  "properties": {
    "iso:country":"TR",
    "sg:address":"Yenimahalle",
    "sg:city":"Ankara",
    "sg:classifiers":[
        {
            "category":"Banks & Credit Unions",
            "subcategory":"Bank",
            "type":"Services"
        }
    ],
    "sg:phone":"+90 41153618",
    "sg:postcode":"63570",
    "sg:province":"Ankara",
    "wof:name":"T\u00fcrkiye Emlak Bankasi As",
    "wof:placetype":"venue"
},
  "geometry": {"coordinates":[36.353649,41.265987],"type":"Point"}
}