{
  "type": "Feature",
  "properties": {
    "addr:full":"Ulubatli Hasan Bulv. No:20 G?su Bursa",
    "addr:housenumber":"no 20 g ?",
    "addr:street":"Ulubatli Hasan Bulv.",
    "iso:country":"TR",
    "sg:address":"Ulubatli Hasan Bulv. No:20",
    "sg:city":"G?su",
    "sg:classifiers":[
        {
            "category":"Shopping",
            "subcategory":"Crafts & Fabrics",
            "type":"Retail Goods"
        }
    ],
    "sg:phone":"+90 224 251 7838",
    "sg:province":"Bursa",
    "sg:tags":[
        "yarn"
    ],
    "wof:name":"Epiriler Teks. San. Tic. A.s.",
    "wof:placetype":"venue"
},
  "geometry": {"coordinates":[29.0657253265,40.1960678101],"type":"Point"}
}