{
  "type": "Feature",
  "properties": {
    "addr:full":"Liman Cd. No:19 Kumkapi Ikitelli Istanbul 34306",
    "addr:housenumber":"no 19",
    "addr:postcode":"34306",
    "addr:street":"Liman Cd.",
    "iso:country":"TR",
    "sg:address":"Liman Cd. No:19 Kumkapi",
    "sg:city":"Ikitelli",
    "sg:classifiers":[
        {
            "category":"Shopping",
            "subcategory":"Stationery & Office Supplies",
            "type":"Retail Goods"
        }
    ],
    "sg:phone":"+90 212 516 5317",
    "sg:postcode":"34306",
    "sg:province":"Istanbul",
    "sg:tags":[
        "furniture"
    ],
    "wof:name":"Gurgen Tic.",
    "wof:placetype":"venue"
},
  "geometry": {"coordinates":[36.3446617126,41.2718200684],"type":"Point"}
}