{
  "type": "Feature",
  "properties": {
    "iso:country":"TR",
    "sg:address":"Task?pr? Cad.no:52",
    "sg:city":"Nizip",
    "sg:classifiers":[
        {
            "category":"Shopping",
            "type":"Retail Goods"
        }
    ],
    "sg:phone":"+90 342 513 0560",
    "sg:postcode":"27700",
    "sg:province":"Gaziantep",
    "sg:tags":[
        "material",
        "cleaning"
    ],
    "wof:name":"?zyurt Gida Ve Kimya San.ve Tic.ltd.sti",
    "wof:placetype":"venue"
},
  "geometry": {"coordinates":[37.4416732788,36.9459457397],"type":"Point"}
}