{
  "type": "Feature",
  "properties": {
    "addr:full":"Bayindir 1. S. 27/39 Kizilay Ankara 23050",
    "addr:housenumber":"1;27 / 39",
    "addr:postcode":"23050",
    "addr:street":"Bayindir;S.;Kizilay Ankara",
    "iso:country":"TR",
    "sg:address":"Bayindir 1. S. 27/39",
    "sg:city":"Kizilay",
    "sg:classifiers":[
        {
            "category":"Shopping",
            "subcategory":"Party Supplies",
            "type":"Retail Goods"
        }
    ],
    "sg:phone":"+90 312 435 7887",
    "sg:postcode":"23050",
    "sg:province":"Ankara",
    "sg:tags":[
        "sound",
        "light",
        "system"
    ],
    "wof:name":"Art M?zik Ses-isik-org.",
    "wof:placetype":"venue"
},
  "geometry": {"coordinates":[32.9604873657,39.9221687317],"type":"Point"}
}