{
  "type": "Feature",
  "properties": {
    "iso:country":"TR",
    "sg:address":"Sivas Yolu 8.km.",
    "sg:city":"Senirkent",
    "sg:classifiers":[
        {
            "category":"Utilities",
            "subcategory":"Electric",
            "type":"Services"
        }
    ],
    "sg:phone":"+90 352 233 9611",
    "sg:postcode":"32600",
    "sg:province":"Kayseri",
    "sg:tags":[
        "accumulator",
        "-",
        "batery"
    ],
    "wof:name":"Akusan Aku San.a.s",
    "wof:placetype":"venue"
},
  "geometry": {"coordinates":[35.489136,38.722576],"type":"Point"}
}