{
  "type": "Feature",
  "properties": {
    "iso:country":"TR",
    "sg:address":"Atat?k Bul 46",
    "sg:city":"Ankara",
    "sg:classifiers":[
        {
            "category":"Banks & Credit Unions",
            "subcategory":"Bank",
            "type":"Services"
        }
    ],
    "sg:phone":"+90 312 310 4815",
    "sg:postcode":"63570",
    "sg:province":"06041",
    "wof:name":"Osmali Bankasi As",
    "wof:placetype":"venue"
},
  "geometry": {"coordinates":[34.628223,36.797989],"type":"Point"}
}