{
  "type": "Feature",
  "properties": {
    "addr:full":"Camlik Dagi Mevkii, Osmaniye Koyu Karamursel Kocaeli 18280",
    "addr:housenumber":"koyu",
    "addr:postcode":"18280",
    "addr:street":"Dagi Mevkii Osmaniye;Kocaeli",
    "iso:country":"TR",
    "sg:address":"Camlik Dagi Mevkii, Osmaniye Koyu",
    "sg:city":"Karamursel",
    "sg:classifiers":[
        {
            "category":"Utilities",
            "subcategory":"Water",
            "type":"Services"
        }
    ],
    "sg:phone":"+90 262 468 0090",
    "sg:postcode":"18280",
    "sg:province":"Kocaeli",
    "sg:tags":[
        "mineral"
    ],
    "wof:name":"Meri Spring Dogal Kaynak Suyu",
    "wof:placetype":"venue"
},
  "geometry": {"coordinates":[29.881521225,40.8532714844],"type":"Point"}
}