{
  "type": "Feature",
  "properties": {
    "addr:full":"Receppeker Cad. Gezici Sitesi No:42/b Kiziltoprak- Kadikoy Istanbul 01370",
    "addr:housenumber":"no 42 / b",
    "addr:postcode":"01370",
    "addr:street":"Receppeker Cad. Gezici Sitesi;Kiziltoprak Kadikoy",
    "iso:country":"TR",
    "sg:address":"Receppeker Cad. Gezici Sitesi No:42/b Kiziltoprak-",
    "sg:city":"Kadikoy",
    "sg:classifiers":[
        {
            "category":"Government",
            "subcategory":"Fire Station",
            "type":"Public Place"
        }
    ],
    "sg:phone":"+90 216 346 0722",
    "sg:postcode":"01370",
    "sg:province":"Istanbul",
    "sg:tags":[
        "decoration"
    ],
    "wof:name":"Oz Stil Celikkapi",
    "wof:placetype":"venue"
},
  "geometry": {"coordinates":[28.9861831665,41.0408554077],"type":"Point"}
}