{
  "type": "Feature",
  "properties": {
    "iso:country":"TR",
    "sg:address":"Mikail Erdayamis",
    "sg:city":"G?oymak",
    "sg:classifiers":[
        {
            "category":"Government",
            "subcategory":"Office",
            "type":"Public Place"
        }
    ],
    "sg:phone":"+90 434 511 2367",
    "sg:province":"Bitlis",
    "sg:tags":[
        "municipality"
    ],
    "wof:name":"G?kiri Belediye Baskani",
    "wof:placetype":"venue"
},
  "geometry": {"coordinates":[42.1083984375,38.3997001648],"type":"Point"}
}