{
  "type": "Feature",
  "properties": {
    "addr:full":"Mudanya Yolu 10 Km. Ikitelli Bursa 34306",
    "addr:housenumber":"10",
    "addr:postcode":"34306",
    "addr:street":"Mudanya Yolu",
    "iso:country":"TR",
    "sg:address":"Mudanya Yolu 10 Km.",
    "sg:city":"Ikitelli",
    "sg:classifiers":[
        {
            "category":"Home & Garden",
            "subcategory":"Building Materials",
            "type":"Retail Goods"
        }
    ],
    "sg:phone":"+90 224 244 6483",
    "sg:postcode":"34306",
    "sg:province":"Bursa",
    "sg:tags":[
        "stone",
        "natural",
        "marble"
    ],
    "wof:name":"Elikat Ltd.",
    "wof:placetype":"venue"
},
  "geometry": {"coordinates":[29.0586109161,40.1844291687],"type":"Point"}
}