{
  "type": "Feature",
  "properties": {
    "iso:country":"TR",
    "sg:address":"Cemil T. Cd. Kastelli Malikaneleri 1. Blok ?iftehavuzlar",
    "sg:city":"Ikitelli/K\u00fc\u00e7\u00fck\u00e7ekmece",
    "sg:orig_category":"Furniture Supplamentary",
    "sg:phone":"+90 216 358 2551",
    "sg:postcode":"34660",
    "sg:province":"Istanbul",
    "wof:name":"Dimaro Mobilya Dekor.",
    "wof:placetype":"venue"
},
  "geometry": {"coordinates":[29.0496292114,41.0075798035],"type":"Point"}
}