{
  "type": "Feature",
  "properties": {
    "addr:full":"Ceyhan Sarimazi K?? P.k. 83 Ceyhan Adana 01920",
    "addr:postcode":"01920",
    "addr:street":"P.K. 83",
    "iso:country":"TR",
    "sg:address":"Ceyhan Sarimazi K?? P.k. 83",
    "sg:city":"Ceyhan",
    "sg:classifiers":[
        {
            "category":"Home & Garden",
            "subcategory":"Garden Supply",
            "type":"Retail Goods"
        }
    ],
    "sg:phone":"+90 322 613 5001",
    "sg:postcode":"01920",
    "sg:province":"Adana",
    "sg:tags":[
        "fertilize",
        "soil"
    ],
    "wof:name":"Toros Gubre Ve Kimya Endustrisi A.s.",
    "wof:placetype":"venue"
},
  "geometry": {"coordinates":[35.9855232239,36.9897956848],"type":"Point"}
}