{
  "type": "Feature",
  "properties": {
    "iso:country":"TR",
    "sg:address":"Kukurtlu Cad. Tan Is Merkezi C Blok No: 67/10 Cekirge",
    "sg:city":"Ikitelli/K\u00fc\u00e7\u00fck\u00e7ekmece",
    "sg:classifiers":[
        {
            "category":"Manufacturing",
            "subcategory":"Chemicals & Compounds",
            "type":"Manufacturing & Wholesale Goods"
        }
    ],
    "sg:phone":"+90 224 234 2553",
    "sg:province":"Bursa",
    "sg:tags":[
        "industry"
    ],
    "wof:name":"Sandeks Imp. Exp.ltd.co.",
    "wof:placetype":"venue"
},
  "geometry": {"coordinates":[29.0398807526,40.1076583862],"type":"Point"}
}