{
  "type": "Feature",
  "properties": {
    "iso:country":"TR",
    "sg:address":"G??suyu Cd. 18/2 Topkapi",
    "sg:city":"Siteler",
    "sg:orig_category":"Aluminium Carpentary",
    "sg:phone":"+90 2126129697577",
    "sg:postcode":"06160",
    "sg:province":"Istanbul",
    "wof:name":"Metanser Mak. Mad. San.a.s.",
    "wof:placetype":"venue"
},
  "geometry": {"coordinates":[28.9410171509,41.0077667236],"type":"Point"}
}