{
  "type": "Feature",
  "properties": {
    "iso:country":"TR",
    "sg:address":"1368.sok. No:1-505 Basmane",
    "sg:city":"Kizilay",
    "sg:classifiers":[
        {
            "category":"Wholesale",
            "subcategory":"Books, Periodicals, & Newspapers",
            "type":"Manufacturing & Wholesale Goods"
        }
    ],
    "sg:phone":"+90 232",
    "sg:postcode":"23050",
    "sg:province":"Izmir",
    "sg:tags":[
        "house",
        "publishing"
    ],
    "wof:name":"Gizem Etiket",
    "wof:placetype":"venue"
},
  "geometry": {"coordinates":[27.4878196716,38.1427764893],"type":"Point"}
}