{
  "type": "Feature",
  "properties": {
    "addr:full":"R. Pasa Huk. Bulv. 14. Sk. No:11/a Ulus Aydin 01940",
    "addr:housenumber":"14;11 / a",
    "addr:postcode":"01940",
    "addr:street":"Huk. Bulv.;Sk. No;Ulus Aydin",
    "iso:country":"TR",
    "sg:address":"R. Pasa Huk. Bulv. 14. Sk. No:11/a",
    "sg:city":"Ulus",
    "sg:classifiers":[
        {
            "category":"Shopping",
            "subcategory":"Computers & Home Electronics",
            "type":"Retail Goods"
        }
    ],
    "sg:phone":"+90 256 225 6044",
    "sg:postcode":"01940",
    "sg:province":"Aydin",
    "sg:tags":[
        "product",
        "electric-electronic"
    ],
    "wof:name":"Aka Elekt.",
    "wof:placetype":"venue"
},
  "geometry": {"coordinates":[27.8324394226,37.8409690857],"type":"Point"}
}