{
  "type": "Feature",
  "properties": {
    "addr:full":"Inonu Cad. No:430 Hatay Izmir 35840",
    "addr:postcode":"430;35840",
    "addr:street":"Inonu Cad. No",
    "iso:country":"TR",
    "sg:address":"Inonu Cad. No:430",
    "sg:city":"Hatay",
    "sg:classifiers":[
        {
            "category":"Utilities",
            "subcategory":"Electric",
            "type":"Services"
        }
    ],
    "sg:phone":"+90 23224491932326",
    "sg:postcode":"35840",
    "sg:province":"Izmir",
    "sg:tags":[
        "energy",
        "solar"
    ],
    "wof:name":"Goksu Gunay Muh. Yerden Isitma Klima Ins. Ltd.sti.",
    "wof:placetype":"venue"
},
  "geometry": {"coordinates":[27.09446,38.397568],"type":"Point"}
}