{
  "type": "Feature",
  "properties": {
    "addr:full":"B??dere Cad. No:18 Osmanbey Eminonu Istanbul",
    "addr:housenumber":"? ?;18",
    "addr:street":"B;Dere Cad. No",
    "iso:country":"TR",
    "sg:address":"B??dere Cad. No:18 Osmanbey",
    "sg:city":"Eminonu",
    "sg:classifiers":[
        {
            "category":"Banks & Credit Unions",
            "subcategory":"Financial Services",
            "type":"Services"
        }
    ],
    "sg:phone":"+90 212 230 9808",
    "sg:province":"Istanbul",
    "sg:tags":[
        "finance"
    ],
    "wof:name":"?nder Menkul Degerler A.s",
    "wof:placetype":"venue"
},
  "geometry": {"coordinates":[28.9923610687,41.0801239014],"type":"Point"}
}