{
  "type": "Feature",
  "properties": {
    "addr:full":"Rizapasa Yokusu No:23/4 Emin?? 34420 Istanbul",
    "addr:housenumber":"4;? ?",
    "addr:postcode":"34420",
    "addr:street":"No 23 /;Emin",
    "iso:country":"TR",
    "sg:address":"Rizapasa Yokusu No:23/4",
    "sg:city":"Emin?? 34420",
    "sg:classifiers":[
        {
            "category":"Shopping",
            "subcategory":"Computers & Home Electronics",
            "type":"Retail Goods"
        }
    ],
    "sg:phone":"+90 212 519 2753",
    "sg:province":"Istanbul",
    "sg:tags":[
        "product",
        "electric-electronic"
    ],
    "wof:name":"Birikim Elektronik Ltd.sti.",
    "wof:placetype":"venue"
},
  "geometry": {"coordinates":[28.9861831665,41.0408554077],"type":"Point"}
}