{
  "type": "Feature",
  "properties": {
    "iso:country":"TR",
    "sg:address":"Sair Nedim Cad. No: 133",
    "sg:city":"Besiktas",
    "sg:classifiers":[
        {
            "category":"Manufacturing",
            "subcategory":"Building Materials",
            "type":"Manufacturing & Wholesale Goods"
        }
    ],
    "sg:phone":"+90 212 259 6611",
    "sg:postcode":"75200",
    "sg:province":"Istanbul",
    "sg:tags":[
        "floor-wall",
        "covering"
    ],
    "wof:name":"Arkadas Yer Dosemeleri Ltd.sti.",
    "wof:placetype":"venue"
},
  "geometry": {"coordinates":[29.0002975464,41.0454216003],"type":"Point"}
}