{
  "type": "Feature",
  "properties": {
    "iso:country":"TR",
    "sg:address":"Ankara Cd. No:310",
    "sg:city":"Okmeydani",
    "sg:classifiers":[
        {
            "category":"Sports & Exercise",
            "subcategory":"Tennis Court",
            "type":"Entertainment"
        }
    ],
    "sg:phone":"+90 224 366 5790",
    "sg:postcode":"80270",
    "sg:province":"Bursa",
    "sg:tags":[
        "equipment",
        "material"
    ],
    "wof:name":"Vema Teks. Ltd. Sti.",
    "wof:placetype":"venue"
},
  "geometry": {"coordinates":[29.113264,40.191479],"type":"Point"}
}