{
  "type": "Feature",
  "properties": {
    "addr:full":"Esenboga Havalimani Kuzguncuk Ankara 42310",
    "addr:postcode":"42310",
    "iso:country":"TR",
    "sg:address":"Esenboga Havalimani",
    "sg:city":"Kuzguncuk",
    "sg:classifiers":[
        {
            "category":"Freight",
            "type":"Transportation"
        }
    ],
    "sg:phone":"+90 3123980141398",
    "sg:postcode":"42310",
    "sg:province":"Ankara",
    "sg:tags":[
        "cargo",
        "air"
    ],
    "wof:name":"Turkish Airlines (thy)",
    "wof:placetype":"venue"
},
  "geometry": {"coordinates":[32.996509552,40.1227111816],"type":"Point"}
}