{
  "type": "Feature",
  "properties": {
    "addr:full":"Ivedik Organize Sanayi Karak\u00f6y Ankara 06710",
    "addr:postcode":"06710",
    "addr:street":"Organize Sanayi Karakoey",
    "iso:country":"TR",
    "sg:address":"Ivedik Organize Sanayi",
    "sg:city":"Karak\u00f6y",
    "sg:classifiers":[
        {
            "category":"Home & Garden",
            "subcategory":"Household Appliances",
            "type":"Retail Goods"
        }
    ],
    "sg:phone":"+90 312 395 2524",
    "sg:postcode":"06710",
    "sg:province":"Ankara",
    "sg:tags":[
        "conditioner",
        "air"
    ],
    "wof:name":"Ozfan Havalandirma Cihazlari Sanayi",
    "wof:placetype":"venue"
},
  "geometry": {"coordinates":[32.7471733093,39.992816925],"type":"Point"}
}