{
  "type": "Feature",
  "properties": {
    "addr:full":"Mercan Yokusu Caferiye Han Mercan Istanbul 12600",
    "addr:postcode":"12600",
    "iso:country":"TR",
    "sg:address":"Mercan Yokusu Caferiye Han",
    "sg:city":"Mercan",
    "sg:classifiers":[
        {
            "category":"Sports & Exercise",
            "subcategory":"Ski Slope",
            "type":"Entertainment"
        }
    ],
    "sg:phone":"+90 212 527 6749",
    "sg:postcode":"12600",
    "sg:province":"Istanbul",
    "sg:tags":[
        "wear"
    ],
    "wof:name":"Omat Konf. San. Tic.",
    "wof:placetype":"venue"
},
  "geometry": {"coordinates":[28.975925,41.012379],"type":"Point"}
}