{
  "type": "Feature",
  "properties": {
    "addr:full":"Cinnah Cd. No:37/17 \u00c7ankaya Ankara 06105",
    "addr:housenumber":"no 37 / 17",
    "addr:postcode":"06105",
    "addr:street":"Cinnah Cd.;C\u0327Ankaya Ankara",
    "iso:country":"TR",
    "sg:address":"Cinnah Cd. No:37/17",
    "sg:city":"\u00c7ankaya",
    "sg:classifiers":[
        {
            "category":"Professional",
            "subcategory":"Engineering",
            "type":"Services"
        }
    ],
    "sg:phone":"+90 312 438 3329",
    "sg:postcode":"06105",
    "sg:province":"Ankara",
    "sg:tags":[
        "architect"
    ],
    "wof:name":"Emte M?savir. M?messil. Elektrik San. Ltd. Sti.",
    "wof:placetype":"venue"
},
  "geometry": {"coordinates":[32.8604812622,39.9429283142],"type":"Point"}
}