{
  "type": "Feature",
  "properties": {
    "iso:country":"TR",
    "sg:address":"Cemal G?sel Cd. No:106/23 Cebeci",
    "sg:city":"Mersin",
    "sg:classifiers":[
        {
            "category":"Home & Garden",
            "subcategory":"Building Materials",
            "type":"Retail Goods"
        }
    ],
    "sg:phone":"+90 312 363 1345",
    "sg:postcode":"52750",
    "sg:province":"Ankara",
    "sg:tags":[
        "window",
        "door",
        "plastic"
    ],
    "wof:name":"Botes Ltd. Sti.",
    "wof:placetype":"venue"
},
  "geometry": {"coordinates":[32.8426818848,39.9528617859],"type":"Point"}
}