{
  "type": "Feature",
  "properties": {
    "addr:full":"Eski Tabakhaneler Mevki No.28 \u00c7orlu Tekirdag 59850",
    "addr:housenumber":"no.28 c\u0327orlu",
    "addr:postcode":"59850",
    "addr:street":"Eski;Mevki;Tekirdag",
    "iso:country":"TR",
    "sg:address":"Eski Tabakhaneler Mevki No.28",
    "sg:city":"\u00c7orlu",
    "sg:classifiers":[
        {
            "category":"Shopping",
            "subcategory":"Luggage & Leather Goods",
            "type":"Retail Goods"
        }
    ],
    "sg:phone":"+90 282 686 1870",
    "sg:postcode":"59850",
    "sg:province":"Tekirdag",
    "sg:tags":[
        "leather-fur",
        "wear"
    ],
    "wof:name":"As Deri San.ltd.sti.",
    "wof:placetype":"venue"
},
  "geometry": {"coordinates":[27.5144004822,40.9791984558],"type":"Point"}
}