{
  "type": "Feature",
  "properties": {
    "addr:full":"Rumeli Caddesi Matbaaci Osmanbey Sok. No:48 K:3 Osmanbey Sisli Istanbul 65710",
    "addr:housenumber":"no 48 k 3",
    "addr:postcode":"65710",
    "addr:street":"Rumeli Caddesi Matbaaci Osmanbey Sok.",
    "iso:country":"TR",
    "sg:address":"Rumeli Caddesi Matbaaci Osmanbey Sok. No:48 K:3 Osmanbey",
    "sg:city":"Sisli",
    "sg:classifiers":[
        {
            "category":"Travel",
            "subcategory":"Travel Agent",
            "type":"Entertainment"
        }
    ],
    "sg:phone":"+90 22490102489098",
    "sg:postcode":"65710",
    "sg:province":"Istanbul",
    "sg:tags":[
        "agency",
        "tourism"
    ],
    "wof:name":"Selmar Turizm",
    "wof:placetype":"venue"
},
  "geometry": {"coordinates":[28.9861831665,41.0408554077],"type":"Point"}
}