{
  "type": "Feature",
  "properties": {
    "iso:country":"TR",
    "sg:address":"Eregli Sk. No:67 Siteler",
    "sg:city":"24000",
    "sg:classifiers":[
        {
            "category":"Manufacturing",
            "subcategory":"Wood Products",
            "type":"Manufacturing & Wholesale Goods"
        }
    ],
    "sg:phone":"+90 312 350 7881",
    "sg:province":"Ankara",
    "sg:tags":[
        "forest"
    ],
    "wof:name":"Dogsan Orman ?r?n. Tic. San. A.s.",
    "wof:placetype":"venue"
},
  "geometry": {"coordinates":[32.9390220642,39.9652023315],"type":"Point"}
}