{
  "type": "Feature",
  "properties": {
    "addr:full":"Mithatpasa Cad. No:28/15 Yenisehir Kocasinan Ankara 38010",
    "addr:housenumber":"28 / 15",
    "addr:postcode":"38010",
    "addr:street":"Mithatpasa Cad. No;Yenisehir Kocasinan",
    "iso:country":"TR",
    "sg:address":"Mithatpasa Cad. No:28/15 Yenisehir",
    "sg:city":"Kocasinan",
    "sg:classifiers":[
        {
            "category":"Wholesale",
            "subcategory":"Medical Equipment & Supplies",
            "type":"Manufacturing & Wholesale Goods"
        }
    ],
    "sg:phone":"+90 312 431 0034",
    "sg:postcode":"38010",
    "sg:province":"Ankara",
    "sg:tags":[
        "material"
    ],
    "wof:name":"Buro Ortopedik Ltd. Sti.",
    "wof:placetype":"venue"
},
  "geometry": {"coordinates":[32.8604812622,39.9429283142],"type":"Point"}
}