{
  "type": "Feature",
  "properties": {
    "addr:full":"Veysel Karani Mah.fevzi Cakmak Cad.no:15 Samandra Istanbul",
    "addr:housenumber":"15",
    "addr:street":"Veysel;Cad.No",
    "iso:country":"TR",
    "sg:address":"Veysel Karani Mah.fevzi Cakmak Cad.no:15",
    "sg:city":"Samandra",
    "sg:classifiers":[
        {
            "category":"Food & Beverages",
            "subcategory":"Candy",
            "type":"Retail Goods"
        }
    ],
    "sg:province":"Istanbul",
    "sg:tags":[
        "biscuit-chocolate-candy"
    ],
    "wof:name":"Aslan Chocolate",
    "wof:placetype":"venue"
},
  "geometry": {"coordinates":[28.975925,41.012379],"type":"Point"}
}