{
  "type": "Feature",
  "properties": {
    "iso:country":"TR",
    "sg:address":"Yildiz M. Akdogan Sk.no.26/3 Besiktas",
    "sg:city":"Merter",
    "sg:classifiers":[
        {
            "category":"Shopping",
            "subcategory":"Shoes",
            "type":"Retail Goods"
        }
    ],
    "sg:phone":"+90 212 258 5028",
    "sg:province":"Istanbul",
    "wof:name":"Silkroad Dis Tic.ltd.sti.",
    "wof:placetype":"venue"
},
  "geometry": {"coordinates":[29.006155,41.045174],"type":"Point"}
}