{
  "type": "Feature",
  "properties": {
    "iso:country":"TR",
    "sg:address":"Orhaniye Caddesi No:9",
    "sg:city":"Sirkeci",
    "sg:classifiers":[
        {
            "category":"Travel",
            "subcategory":"Travel Agent",
            "type":"Entertainment"
        }
    ],
    "sg:phone":"+90 5121806",
    "sg:postcode":"34112",
    "sg:province":"Istanbul",
    "sg:tags":[
        "agency",
        "tourism"
    ],
    "wof:name":"Anil Turizm",
    "wof:placetype":"venue"
},
  "geometry": {"coordinates":[28.9764461517,41.0133476257],"type":"Point"}
}