{
  "type": "Feature",
  "properties": {
    "addr:full":"101. Sk. No:70 Zeytinburnu Esenler . Atisalani Istanbul",
    "addr:housenumber":"70;esenler",
    "addr:street":"101 Sk. No",
    "iso:country":"TR",
    "sg:address":"101. Sk. No:70 Zeytinburnu",
    "sg:city":"Esenler . Atisalani",
    "sg:classifiers":[
        {
            "category":"Mining & Drilling",
            "type":"Manufacturing & Wholesale Goods"
        }
    ],
    "sg:phone":"+90 212 547 2373",
    "sg:province":"Istanbul",
    "sg:tags":[
        "industry",
        "mine"
    ],
    "wof:name":"3 As Madencilik",
    "wof:placetype":"venue"
},
  "geometry": {"coordinates":[28.9076728821,41.0008544922],"type":"Point"}
}