{
  "type": "Feature",
  "properties": {
    "addr:full":"Atat?k Cd. No:140 Bandirma Maltepe Balikesir 01000",
    "addr:housenumber":"no",
    "addr:postcode":"01000",
    "addr:street":"K Cd.;Maltepe Balikesir",
    "iso:country":"TR",
    "sg:address":"Atat?k Cd. No:140 Bandirma",
    "sg:city":"Maltepe",
    "sg:orig_category":"Aluminium Carpentary",
    "sg:phone":"+90 266 718 3865",
    "sg:postcode":"01000",
    "sg:province":"Balikesir",
    "wof:name":"Tuksallar Alum.",
    "wof:placetype":"venue"
},
  "geometry": {"coordinates":[27.8833007812,39.6520996094],"type":"Point"}
}