{
  "type": "Feature",
  "properties": {
    "iso:country":"TR",
    "sg:address":"2131/19. Sok. No:6/3",
    "sg:city":"Karsiyaka",
    "sg:classifiers":[
        {
            "category":"Food & Beverages",
            "subcategory":"Groceries & Convenience Stores",
            "type":"Retail Goods"
        }
    ],
    "sg:phone":"+90 232 346 3450",
    "sg:postcode":"01900",
    "sg:province":"Izmir",
    "sg:tags":[
        "ready"
    ],
    "wof:name":"Beltur A.s.",
    "wof:placetype":"venue"
},
  "geometry": {"coordinates":[27.222366333,38.4682693481],"type":"Point"}
}