{
  "type": "Feature",
  "properties": {
    "addr:full":"Cumhuriyet Caddesi No:135 K:3 D:3 Elmadag Istanbul 65900",
    "addr:housenumber":"no 135 k 3 d 3",
    "addr:postcode":"65900",
    "addr:street":"Cumhuriyet Caddesi",
    "iso:country":"TR",
    "sg:address":"Cumhuriyet Caddesi No:135 K:3 D:3",
    "sg:city":"Elmadag",
    "sg:classifiers":[
        {
            "category":"Travel",
            "subcategory":"Travel Agent",
            "type":"Entertainment"
        }
    ],
    "sg:phone":"+90 22513872488149",
    "sg:postcode":"65900",
    "sg:province":"Istanbul",
    "sg:tags":[
        "agency",
        "tourism"
    ],
    "wof:name":"Expert Turizm",
    "wof:placetype":"venue"
},
  "geometry": {"coordinates":[28.9861831665,41.0408554077],"type":"Point"}
}