{
  "type": "Feature",
  "properties": {
    "iso:country":"TR",
    "sg:address":"Ruzgarlik Sok. No:2/7 Ulus",
    "sg:city":"Iskenderun",
    "sg:classifiers":[
        {
            "category":"Mining & Drilling",
            "type":"Manufacturing & Wholesale Goods"
        }
    ],
    "sg:phone":"+90 312 312 2277",
    "sg:postcode":"31200",
    "sg:province":"Ankara",
    "sg:tags":[
        "industry",
        "mine"
    ],
    "wof:name":"Boztepe Ltd.sti.",
    "wof:placetype":"venue"
},
  "geometry": {"coordinates":[29.1179084778,40.1848258972],"type":"Point"}
}