{
  "type": "Feature",
  "properties": {
    "addr:full":"1196 Sok No:6 Yenisehir Uskudar Izmir 81100",
    "addr:housenumber":"no 6",
    "addr:postcode":"1196;81100",
    "addr:street":"Sok;Yenisehir Uskudar",
    "iso:country":"TR",
    "sg:address":"1196 Sok No:6 Yenisehir",
    "sg:city":"Uskudar",
    "sg:classifiers":[
        {
            "category":"Shopping",
            "subcategory":"Crafts & Fabrics",
            "type":"Retail Goods"
        }
    ],
    "sg:phone":"+90 232 433 8000",
    "sg:postcode":"81100",
    "sg:province":"Izmir",
    "sg:tags":[
        "textile",
        "-leather",
        "exporter"
    ],
    "wof:name":"Koza Tekstil A.s",
    "wof:placetype":"venue"
},
  "geometry": {"coordinates":[27.1423015594,38.4251480103],"type":"Point"}
}