{
  "type": "Feature",
  "properties": {
    "addr:full":"Tavsanli Mah. 85. Sok.un Pasaji Karacabey Bursa 38800",
    "addr:housenumber":"85",
    "addr:postcode":"38800",
    "addr:street":"Tavsanli Mah.",
    "iso:country":"TR",
    "sg:address":"Tavsanli Mah. 85. Sok.un Pasaji",
    "sg:city":"Karacabey",
    "sg:classifiers":[
        {
            "category":"Farming",
            "subcategory":"Farm & Veterinary Services",
            "type":"Manufacturing & Wholesale Goods"
        }
    ],
    "sg:phone":"+90 224 676 3845",
    "sg:postcode":"38800",
    "sg:province":"Bursa",
    "sg:tags":[
        "veterinarian"
    ],
    "wof:name":"Zeki Cengiz",
    "wof:placetype":"venue"
},
  "geometry": {"coordinates":[29.0580043793,40.1947555542],"type":"Point"}
}