{
  "type": "Feature",
  "properties": {
    "addr:full":"Baglarbasi Mh. K??k? Yolu No:74 G.osmanpasa Istanbul",
    "addr:housenumber":"no 74",
    "addr:street":"Baglarbasi Mh. K ? ? K ? Yolu",
    "iso:country":"TR",
    "sg:address":"Baglarbasi Mh. K??k? Yolu No:74",
    "sg:city":"G.osmanpasa",
    "sg:classifiers":[
        {
            "category":"Shopping",
            "subcategory":"Florist",
            "type":"Retail Goods"
        }
    ],
    "sg:phone":"+90 212 563 3861",
    "sg:province":"Istanbul",
    "sg:tags":[
        "flower"
    ],
    "wof:name":"Leydi ?i?ek Evi",
    "wof:placetype":"venue"
},
  "geometry": {"coordinates":[29.1549606323,40.9185371399],"type":"Point"}
}