{
  "type": "Feature",
  "properties": {
    "addr:full":"Anafartalar Cad. No: 29 Konak Izmir 07110",
    "addr:postcode":"07110",
    "addr:street":"Anafartalar Cad. No",
    "iso:country":"TR",
    "sg:address":"Anafartalar Cad. No: 29",
    "sg:city":"Konak",
    "sg:classifiers":[
        {
            "category":"Shopping",
            "subcategory":"Clothing, Apparel, & Fashions",
            "type":"Retail Goods"
        }
    ],
    "sg:phone":"+90 232 425 8753",
    "sg:postcode":"07110",
    "sg:province":"Izmir",
    "sg:tags":[
        "woman",
        "wear"
    ],
    "wof:name":"Bertiz Giyim",
    "wof:placetype":"venue"
},
  "geometry": {"coordinates":[27.1309204102,38.4182624817],"type":"Point"}
}