{
  "type": "Feature",
  "properties": {
    "addr:full":"Cihar Sok. 1/4 Sihhiye Fatih Ankara 01740",
    "addr:housenumber":"1 / 4",
    "addr:postcode":"01740",
    "addr:street":"Cihar Sok.",
    "iso:country":"TR",
    "sg:address":"Cihar Sok. 1/4 Sihhiye",
    "sg:city":"Fatih",
    "sg:classifiers":[
        {
            "category":"Wholesale",
            "subcategory":"Medical Equipment & Supplies",
            "type":"Manufacturing & Wholesale Goods"
        }
    ],
    "sg:phone":"+90 312 231 1191",
    "sg:postcode":"01740",
    "sg:province":"Ankara",
    "sg:tags":[
        "material"
    ],
    "wof:name":"Leton Tibbi Malzeme",
    "wof:placetype":"venue"
},
  "geometry": {"coordinates":[36.3210983276,41.2973098755],"type":"Point"}
}