{
  "type": "Feature",
  "properties": {
    "iso:country":"TR",
    "sg:address":"Cevizlidere 3. Sk. No:15 Balgat",
    "sg:city":"Ikitelli/K\u00fc\u00e7\u00fck\u00e7ekmece",
    "sg:classifiers":[
        {
            "category":"Wholesale",
            "subcategory":"Machinery & Supplies",
            "type":"Manufacturing & Wholesale Goods"
        }
    ],
    "sg:phone":"+90 312 222 1700",
    "sg:postcode":"34670",
    "sg:province":"Ankara",
    "sg:tags":[
        "press",
        "hydraulic"
    ],
    "wof:name":"Ko?aklar Hidrolik A.s.",
    "wof:placetype":"venue"
},
  "geometry": {"coordinates":[32.8604812622,39.9429283142],"type":"Point"}
}