{
  "type": "Feature",
  "properties": {
    "iso:country":"TR",
    "sg:address":"Kutucular Cad. No:9 34460 Emin?? Istanbul",
    "sg:city":"Cagaloglu",
    "sg:classifiers":[
        {
            "category":"Freight",
            "type":"Transportation"
        }
    ],
    "sg:phone":"+90 212 527 4535",
    "sg:postcode":"34410",
    "sg:province":"Istanbul",
    "sg:tags":[
        "packing",
        "industry"
    ],
    "wof:name":"?nal Ticaret",
    "wof:placetype":"venue"
},
  "geometry": {"coordinates":[28.9698543549,41.0070724487],"type":"Point"}
}