{
  "type": "Feature",
  "properties": {
    "addr:full":"Meram Sanayi Meram Eskiyol Uzeri No:135 Gaziosmanpasa Konya 34170",
    "addr:postcode":"34170",
    "addr:street":"Meram Sanayi;No 135 Gaziosmanpasa",
    "iso:country":"TR",
    "sg:address":"Meram Sanayi Meram Eskiyol Uzeri No:135",
    "sg:city":"Gaziosmanpasa",
    "sg:classifiers":[
        {
            "category":"Building & Trades",
            "subcategory":"Electrical",
            "type":"Services"
        }
    ],
    "sg:phone":"+90 332 322 7196",
    "sg:postcode":"34170",
    "sg:province":"Konya",
    "sg:tags":[
        "equipment",
        "lighting"
    ],
    "wof:name":"Niyazi Usta Aydinlatma Armaturleri San.tic.ltd.sti.",
    "wof:placetype":"venue"
},
  "geometry": {"coordinates":[32.4990272522,37.8715362549],"type":"Point"}
}