{
  "type": "Feature",
  "properties": {
    "addr:full":"Buyuk Sanayi Sit.girisi 8.blok No:8 D.dere Gemlik Trabzon 16600",
    "addr:housenumber":"8.blok no 8;gemlik",
    "addr:postcode":"16600",
    "addr:street":"Buyuk Sanayi Sit.Girisi;Trabzon",
    "iso:country":"TR",
    "sg:address":"Buyuk Sanayi Sit.girisi 8.blok No:8 D.dere",
    "sg:city":"Gemlik",
    "sg:classifiers":[
        {
            "category":"Manufacturing",
            "subcategory":"Tools & Machinery",
            "type":"Manufacturing & Wholesale Goods"
        }
    ],
    "sg:phone":"+90 462328114445",
    "sg:postcode":"16600",
    "sg:province":"Trabzon",
    "sg:tags":[
        "machine",
        "industry"
    ],
    "wof:name":"Atasoy Makinatekstil Turz.insaat Tic.ltd.sti.",
    "wof:placetype":"venue"
},
  "geometry": {"coordinates":[39.7191009521,41.0060997009],"type":"Point"}
}