{
  "type": "Feature",
  "properties": {
    "iso:country":"TR",
    "sg:address":"Emekyemez Mah.mektep Sok.no:49-4",
    "sg:city":"Pangalti",
    "sg:classifiers":[
        {
            "category":"Building & Trades",
            "subcategory":"Electrical",
            "type":"Services"
        }
    ],
    "sg:phone":"+90 212 254 0825",
    "sg:postcode":"34373",
    "sg:province":"Istanbul",
    "sg:tags":[
        "equipment",
        "lighting"
    ],
    "wof:name":"Oznur Avize & Aydinlatma Ith.ihr.san.tic.ltd.sti.",
    "wof:placetype":"venue"
},
  "geometry": {"coordinates":[28.9605083466,41.047832489],"type":"Point"}
}