{
  "type": "Feature",
  "properties": {
    "iso:country":"TR",
    "sg:address":"Fatih Mehmet G?er",
    "sg:city":"Gemlik",
    "sg:classifiers":[
        {
            "category":"Government",
            "subcategory":"Office",
            "type":"Public Place"
        }
    ],
    "sg:phone":"+90 224525000552",
    "sg:postcode":"16600",
    "sg:province":"Bursa",
    "sg:tags":[
        "municipality"
    ],
    "wof:name":"Umurbey Belediye Baskani",
    "wof:placetype":"venue"
},
  "geometry": {"coordinates":[29.0563678741,40.2177886963],"type":"Point"}
}