{
  "type": "Feature",
  "properties": {
    "iso:country":"TR",
    "sg:address":"8780/11 .sok. No:19 Atasanayi/cigli",
    "sg:city":"Bayrampasa",
    "sg:classifiers":[
        {
            "category":"Manufacturing",
            "subcategory":"Rubber & Plastics",
            "type":"Manufacturing & Wholesale Goods"
        }
    ],
    "sg:phone":"+90 232 328 2319",
    "sg:postcode":"36100",
    "sg:province":"Izmir",
    "sg:tags":[
        "industry"
    ],
    "wof:name":"Tinsa Ltd.sti.",
    "wof:placetype":"venue"
},
  "geometry": {"coordinates":[27.1296863556,38.4186973572],"type":"Point"}
}