{
  "type": "Feature",
  "properties": {
    "iso:country":"TR",
    "sg:address":"Ferahevler, Adnan Kahveci Caddesi No. 108",
    "sg:city":"Tarabya",
    "sg:classifiers":[
        {
            "category":"Wholesale",
            "subcategory":"Medical Equipment & Supplies",
            "type":"Manufacturing & Wholesale Goods"
        }
    ],
    "sg:phone":"+90 212 299 5400",
    "sg:postcode":"80820",
    "sg:province":"Istanbul",
    "wof:name":"Spiromed Ltd.sti.",
    "wof:placetype":"venue"
},
  "geometry": {"coordinates":[29.0517997742,41.1287269592],"type":"Point"}
}