{
  "type": "Feature",
  "properties": {
    "addr:full":"Atat?k Blv. Terzioglu Ish. No:53 Sihhiye \u00c7ankaya Ankara 06690",
    "addr:housenumber":"53",
    "addr:postcode":"06690",
    "addr:street":"K Blv. Terzioglu Ish. No",
    "iso:country":"TR",
    "sg:address":"Atat?k Blv. Terzioglu Ish. No:53 Sihhiye",
    "sg:city":"\u00c7ankaya",
    "sg:classifiers":[
        {
            "category":"Wholesale",
            "subcategory":"Medical Equipment & Supplies",
            "type":"Manufacturing & Wholesale Goods"
        }
    ],
    "sg:phone":"+90 312 433 0406",
    "sg:postcode":"06690",
    "sg:province":"Ankara",
    "wof:name":"Medtek A.s.",
    "wof:placetype":"venue"
},
  "geometry": {"coordinates":[32.8604812622,39.9429283142],"type":"Point"}
}