{
  "type": "Feature",
  "properties": {
    "addr:full":"Asirefendi Cad. No.40 Sultanhamam Istanbul",
    "addr:street":"Asirefendi Cad. No.40 Sultanhamam",
    "iso:country":"TR",
    "sg:address":"Asirefendi Cad. No.40",
    "sg:city":"Sultanhamam",
    "sg:classifiers":[
        {
            "category":"Shopping",
            "subcategory":"Clothing, Apparel, & Fashions",
            "type":"Retail Goods"
        }
    ],
    "sg:phone":"+90 212 511 6006",
    "sg:province":"Istanbul",
    "sg:tags":[
        "ready",
        "wear"
    ],
    "wof:name":"Pala Tekstil A.s.",
    "wof:placetype":"venue"
},
  "geometry": {"coordinates":[28.9731750488,41.0144119263],"type":"Point"}
}