{
  "type": "Feature",
  "properties": {
    "addr:full":"1145/10 Sok. No:17 Yenisehir Merkez Izmir",
    "addr:housenumber":"1145 / 10;no 17",
    "addr:street":"Sok.;Yenisehir Merkez",
    "iso:country":"TR",
    "sg:address":"1145/10 Sok. No:17 Yenisehir",
    "sg:city":"Merkez",
    "sg:classifiers":[
        {
            "category":"Mining & Drilling",
            "type":"Manufacturing & Wholesale Goods"
        }
    ],
    "sg:phone":"+90 232 433 9262",
    "sg:province":"Izmir",
    "sg:tags":[
        "industry",
        "mine"
    ],
    "wof:name":"Nam Ic Ve Dis Ticaret A.s.",
    "wof:placetype":"venue"
},
  "geometry": {"coordinates":[27.1677055359,38.4260520935],"type":"Point"}
}