{
  "type": "Feature",
  "properties": {
    "addr:full":"Harmanlar Mah.muftu Vehbi Sok. No:7/a 212 Merzifon MERSIN",
    "addr:housenumber":"no 7 / a 212",
    "addr:street":"Vehbi Sok.",
    "iso:country":"TR",
    "sg:address":"Harmanlar Mah.muftu Vehbi Sok. No:7/a",
    "sg:city":"212",
    "sg:classifiers":[
        {
            "category":"Shopping",
            "subcategory":"Computers & Home Electronics",
            "type":"Retail Goods"
        }
    ],
    "sg:phone":"+90 358 513 8096",
    "sg:postcode":"MERSIN",
    "sg:province":"Merzifon",
    "sg:tags":[
        "chamber",
        "commerce"
    ],
    "wof:name":"Merzifon Chamber Of Commerce And Industry",
    "wof:placetype":"venue"
},
  "geometry": {"coordinates":[35.4372291565,40.8654289246],"type":"Point"}
}