{
  "type": "Feature",
  "properties": {
    "iso:country":"TR",
    "sg:address":"Izmir Cd. 93 Sk. No.4",
    "sg:city":"Pinarbasi",
    "sg:classifiers":[
        {
            "category":"Wholesale",
            "subcategory":"Farm Supplies",
            "type":"Manufacturing & Wholesale Goods"
        }
    ],
    "sg:phone":"+90 232 388 2450",
    "sg:postcode":"07630",
    "sg:province":"Izmir",
    "sg:tags":[
        "feed",
        "industry"
    ],
    "wof:name":"Gida Yem San. A.s.",
    "wof:placetype":"venue"
},
  "geometry": {"coordinates":[27.0921573639,38.3894577026],"type":"Point"}
}