{
  "type": "Feature",
  "properties": {
    "iso:country":"TR",
    "sg:address":"Akdeniz San.sitesi 5037.sok. No:71",
    "sg:city":"Ikitelli/K\u00fc\u00e7\u00fck\u00e7ekmece",
    "sg:classifiers":[
        {
            "category":"Manufacturing",
            "subcategory":"Tools & Machinery",
            "type":"Manufacturing & Wholesale Goods"
        }
    ],
    "sg:phone":"+90 242 221 4195",
    "sg:postcode":"34670",
    "sg:province":"Antalya",
    "sg:tags":[
        "machine",
        "industry"
    ],
    "wof:name":"Ucler Makina Ins.tur.san.ve Tic.ltd.",
    "wof:placetype":"venue"
},
  "geometry": {"coordinates":[30.7031345367,36.8875045776],"type":"Point"}
}