{
  "type": "Feature",
  "properties": {
    "iso:country":"TR",
    "sg:address":"Fatih Cd. No:173 Kartaltepe",
    "sg:city":"Besiktas",
    "sg:classifiers":[
        {
            "category":"Communications",
            "subcategory":"Film & Video Production",
            "type":"Services"
        }
    ],
    "sg:phone":"+90 212 278 8630",
    "sg:postcode":"80200",
    "sg:province":"Istanbul",
    "sg:tags":[
        "-"
    ],
    "wof:name":"Ekrem Video Tv Laboratuvari",
    "wof:placetype":"venue"
},
  "geometry": {"coordinates":[28.8964290619,41.0603713989],"type":"Point"}
}