{
  "type": "Feature",
  "properties": {
    "addr:full":"Jandarma Mektebi Sk. No:28 Abbasaga Mh. Besiktas Kad\u0131k\u00f6y Istanbul 34990",
    "addr:housenumber":"28",
    "addr:postcode":"34990",
    "addr:street":"Jandarma Mektebi Sk. No;Mh.",
    "iso:country":"TR",
    "sg:address":"Jandarma Mektebi Sk. No:28 Abbasaga Mh. Besiktas",
    "sg:city":"Kad\u0131k\u00f6y",
    "sg:classifiers":[
        {
            "category":"Organizations",
            "subcategory":"Membership Organization",
            "type":"Services"
        }
    ],
    "sg:phone":"+90 212 259 5809",
    "sg:postcode":"34990",
    "sg:province":"Istanbul",
    "wof:name":"Uluslararasi Lisansli Radyo Elek. Dernegi",
    "wof:placetype":"venue"
},
  "geometry": {"coordinates":[28.9861831665,41.0408554077],"type":"Point"}
}