{
  "type": "Feature",
  "properties": {
    "iso:country":"TR",
    "sg:address":"Altintas Mah. 131. Sok.no.15/a",
    "sg:city":"Nazilli",
    "sg:classifiers":[
        {
            "category":"Shopping",
            "subcategory":"Baby Store",
            "type":"Retail Goods"
        }
    ],
    "sg:phone":"+90 256 315 9485",
    "sg:postcode":"65600",
    "sg:province":"Aydin",
    "sg:tags":[
        "wear"
    ],
    "wof:name":"Nur Bebe-nur Souvenier",
    "wof:placetype":"venue"
},
  "geometry": {"coordinates":[27.166473,38.385612],"type":"Point"}
}