{
  "type": "Feature",
  "properties": {
    "iso:country":"TR",
    "sg:address":"Camli Koyu Guzelbahce",
    "sg:city":"Ikitelli/K\u00fc\u00e7\u00fck\u00e7ekmece",
    "sg:classifiers":[
        {
            "category":"Wholesale",
            "subcategory":"Durable Goods & Equipment",
            "type":"Manufacturing & Wholesale Goods"
        }
    ],
    "sg:phone":"+90 232 236 7880",
    "sg:postcode":"34670",
    "sg:province":"Izmir",
    "sg:tags":[
        "consumer"
    ],
    "wof:name":"Egenova Plastik Elektronik Montaj Pazarlama San.tic.ltd.sti.",
    "wof:placetype":"venue"
},
  "geometry": {"coordinates":[27.1423015594,38.4251480103],"type":"Point"}
}