{
  "type": "Feature",
  "properties": {
    "addr:full":"M.k.p. Caddesi Sekerbank ?st? No:47/3 Maltepe Amasya 01000",
    "addr:housenumber":"sekerbank ?;47 / 3",
    "addr:postcode":"01000",
    "addr:street":"M.K.P. Caddesi;St ? No;Maltepe Amasya",
    "iso:country":"TR",
    "sg:address":"M.k.p. Caddesi Sekerbank ?st? No:47/3",
    "sg:city":"Maltepe",
    "sg:classifiers":[
        {
            "category":"Travel",
            "subcategory":"Travel Agent",
            "type":"Entertainment"
        }
    ],
    "sg:phone":"+90 358 212 2228",
    "sg:postcode":"01000",
    "sg:province":"Amasya",
    "sg:tags":[
        "agency",
        "tourism"
    ],
    "wof:name":"Ay-safak Air Turizm (amasya Sb)",
    "wof:placetype":"venue"
},
  "geometry": {"coordinates":[35.8135032654,40.6473884583],"type":"Point"}
}