{
  "type": "Feature",
  "properties": {
    "addr:full":"Icadiye Mah. Cumhuriyet Cad.no: 41 Buro:2 Uskudar Fatih Istanbul 34089",
    "addr:housenumber":"41;2",
    "addr:postcode":"34089",
    "addr:street":"Icadiye Mah. Cumhuriyet Cad.No",
    "iso:country":"TR",
    "sg:address":"Icadiye Mah. Cumhuriyet Cad.no: 41 Buro:2 Uskudar",
    "sg:city":"Fatih",
    "sg:classifiers":[
        {
            "category":"Wholesale",
            "subcategory":"Medical Equipment & Supplies",
            "type":"Manufacturing & Wholesale Goods"
        }
    ],
    "sg:phone":"+90 216 333 4932",
    "sg:postcode":"34089",
    "sg:province":"Istanbul",
    "sg:tags":[
        "material"
    ],
    "wof:name":"E.d.a. Ithalat Ihracat Turizm San.tic.",
    "wof:placetype":"venue"
},
  "geometry": {"coordinates":[28.9861831665,41.0408554077],"type":"Point"}
}