{
  "type": "Feature",
  "properties": {
    "addr:full":"Ahmet Yasevi Cd. No: 181 Yenibosna Iskenderun Istanbul 31200",
    "addr:housenumber":"no",
    "addr:postcode":"31200",
    "addr:street":"Cd.;Yenibosna",
    "iso:country":"TR",
    "sg:address":"Ahmet Yasevi Cd. No: 181 Yenibosna",
    "sg:city":"Iskenderun",
    "sg:classifiers":[
        {
            "category":"Mining & Drilling",
            "type":"Manufacturing & Wholesale Goods"
        }
    ],
    "sg:phone":"+90 212 552 1924",
    "sg:postcode":"31200",
    "sg:province":"Istanbul",
    "sg:tags":[
        "industry",
        "mine"
    ],
    "wof:name":"Bulut Madencilik Ltd. Sti.",
    "wof:placetype":"venue"
},
  "geometry": {"coordinates":[28.824136734,41.0147399902],"type":"Point"}
}