{
  "type": "Feature",
  "properties": {
    "addr:full":"Besyol Fatih Mah. Basaran Sok. No:15 Cagaloglu Bursa",
    "addr:housenumber":"no 15",
    "addr:street":"Fatih Mah. Basaran Sok.",
    "iso:country":"TR",
    "sg:address":"Besyol Fatih Mah. Basaran Sok. No:15",
    "sg:city":"Cagaloglu",
    "sg:classifiers":[
        {
            "category":"Shopping",
            "subcategory":"Baby Store",
            "type":"Retail Goods"
        }
    ],
    "sg:phone":"+90 224 252 7878",
    "sg:province":"Bursa",
    "sg:tags":[
        "wear"
    ],
    "wof:name":"Busra Bebe",
    "wof:placetype":"venue"
},
  "geometry": {"coordinates":[29.070326,40.203636],"type":"Point"}
}