{
  "type": "Feature",
  "properties": {
    "addr:full":"Natoyolu Cd. Ispar Merk. No:93/271 4.levent Istanbul",
    "addr:housenumber":"93 / 271",
    "addr:postcode":"4.levent",
    "addr:street":"Natoyolu Cd. Ispar Merk. No",
    "iso:country":"TR",
    "sg:address":"Natoyolu Cd. Ispar Merk. No:93/271",
    "sg:city":"4.levent",
    "sg:classifiers":[
        {
            "category":"Government",
            "subcategory":"Post Office",
            "type":"Public Place"
        }
    ],
    "sg:phone":"+90 2122834433835",
    "sg:province":"Istanbul",
    "sg:tags":[
        "distribution"
    ],
    "wof:name":"Er-saf Dagitim & Kurye Hizm.",
    "wof:placetype":"venue"
},
  "geometry": {"coordinates":[28.9759254456,41.0123786926],"type":"Point"}
}