{
  "type": "Feature",
  "properties": {
    "iso:country":"TR",
    "sg:address":"Alemdar Beldesi Resadiye Koyu Yolu 8.sok. No:2",
    "sg:city":"\u00dcmraniye",
    "sg:classifiers":[
        {
            "category":"Home & Garden",
            "subcategory":"Building Materials",
            "type":"Retail Goods"
        }
    ],
    "sg:phone":"+90 216 429 9696",
    "sg:province":"Istanbul",
    "sg:tags":[
        "plaster",
        "cement-concrete"
    ],
    "wof:name":"Hazer M?messillik Ve Pazarlama Insaat A.s.",
    "wof:placetype":"venue"
},
  "geometry": {"coordinates":[28.9861831665,41.0408554077],"type":"Point"}
}