{
  "type": "Feature",
  "properties": {
    "addr:full":"Selmanaga Mah. Cesme Sok. No: 2/d Uskudar Istanbul 34672",
    "addr:housenumber":"no 2 / d",
    "addr:postcode":"34672",
    "addr:street":"Selmanaga Mah. Cesme Sok.",
    "iso:country":"TR",
    "sg:address":"Selmanaga Mah. Cesme Sok. No: 2/d",
    "sg:city":"Uskudar",
    "sg:classifiers":[
        {
            "category":"Manufacturing",
            "subcategory":"Chemicals & Compounds",
            "type":"Manufacturing & Wholesale Goods"
        }
    ],
    "sg:phone":"+90 336 334 2376",
    "sg:postcode":"34672",
    "sg:province":"Istanbul",
    "sg:tags":[
        "agricultural"
    ],
    "wof:name":"Cagin Ziraat Binmarsesi",
    "wof:placetype":"venue"
},
  "geometry": {"coordinates":[29.0162677765,41.0259132385],"type":"Point"}
}