{
  "type": "Feature",
  "properties": {
    "addr:full":"Pirincli Mahalesi Durucasu Yazihan Yazihan Malatya 44350",
    "addr:postcode":"44350",
    "iso:country":"TR",
    "sg:address":"Pirincli Mahalesi Durucasu Yazihan",
    "sg:city":"Yazihan",
    "sg:classifiers":[
        {
            "category":"Shopping",
            "subcategory":"Clothing, Apparel, & Fashions",
            "type":"Retail Goods"
        }
    ],
    "sg:phone":"+90 552254544",
    "sg:postcode":"44350",
    "sg:province":"Malatya",
    "sg:tags":[
        "men",
        "wear"
    ],
    "wof:name":"Gocer Ticaret",
    "wof:placetype":"venue"
},
  "geometry": {"coordinates":[38.3143005371,38.3474998474],"type":"Point"}
}