{
  "type": "Feature",
  "properties": {
    "iso:country":"TR",
    "sg:address":"Cumhuriyet Mah. A.haydar ?ner Cad. No:3",
    "sg:city":"Erbaa",
    "sg:classifiers":[
        {
            "category":"Manufacturing",
            "subcategory":"Leather Goods",
            "type":"Manufacturing & Wholesale Goods"
        }
    ],
    "sg:phone":"+90 356 715 1086",
    "sg:postcode":"60500",
    "sg:province":"Tokat",
    "sg:tags":[
        "raw"
    ],
    "wof:name":"?zg?r Deri Ambalaj Malz. Tic.ve San Ltd.sti.",
    "wof:placetype":"venue"
},
  "geometry": {"coordinates":[36.5559005737,40.3063011169],"type":"Point"}
}