{
  "type": "Feature",
  "properties": {
    "addr:full":"Celik Sk. 32/4 4.levent Istanbul",
    "addr:housenumber":"4",
    "addr:street":"Celik Sk. 32 /",
    "iso:country":"TR",
    "sg:address":"Celik Sk. 32/4",
    "sg:city":"4.levent",
    "sg:classifiers":[
        {
            "category":"Recreation",
            "subcategory":"Boat Charter",
            "type":"Entertainment"
        }
    ],
    "sg:phone":"+90 212 284 5572",
    "sg:province":"Istanbul",
    "sg:tags":[
        "yachting"
    ],
    "wof:name":"Onurbey Yatcilik Ltd.sti.",
    "wof:placetype":"venue"
},
  "geometry": {"coordinates":[29.0479698181,41.1267776489],"type":"Point"}
}