{
  "type": "Feature",
  "properties": {
    "iso:country":"TR",
    "sg:address":"Bozkurt Cad. No: 200 Kurtulus",
    "sg:city":"Mersin",
    "sg:classifiers":[
        {
            "category":"Manufacturing",
            "subcategory":"Glass & Minerals",
            "type":"Manufacturing & Wholesale Goods"
        }
    ],
    "sg:phone":"+90 212 219 6504",
    "sg:postcode":"52750",
    "sg:province":"Istanbul",
    "sg:tags":[
        "glassware"
    ],
    "wof:name":"Desay Cam Ltd.sti.",
    "wof:placetype":"venue"
},
  "geometry": {"coordinates":[28.9791793823,41.0473136902],"type":"Point"}
}