{
  "type": "Feature",
  "properties": {
    "addr:full":"Yahya Cavus Cad. Yapici Ism. C Blok No:12 Yenisehir Konya 35110",
    "addr:housenumber":"blok no 12",
    "addr:postcode":"35110",
    "addr:street":"Cavus Cad. Yapici Ism. C;Yenisehir Konya",
    "iso:country":"TR",
    "sg:address":"Yahya Cavus Cad. Yapici Ism. C Blok No:12",
    "sg:city":"Yenisehir",
    "sg:classifiers":[
        {
            "category":"Wholesale",
            "subcategory":"Medical Equipment & Supplies",
            "type":"Manufacturing & Wholesale Goods"
        }
    ],
    "sg:phone":"+90 332 321 3955",
    "sg:postcode":"35110",
    "sg:province":"Konya",
    "sg:tags":[
        "material"
    ],
    "wof:name":"Nobel Medikal Ltd. Sti.",
    "wof:placetype":"venue"
},
  "geometry": {"coordinates":[32.4990272522,37.8715362549],"type":"Point"}
}