{
  "type": "Feature",
  "properties": {
    "iso:country":"TR",
    "sg:address":"Yuzbasilar Cad. Kumali Apt. Alti No:4 Golcuk",
    "sg:city":"Degirmendere",
    "sg:classifiers":[
        {
            "category":"Farming",
            "subcategory":"Farm & Veterinary Services",
            "type":"Manufacturing & Wholesale Goods"
        }
    ],
    "sg:phone":"+90 262 426 6565",
    "sg:postcode":"01920",
    "sg:province":"Kocaeli",
    "sg:tags":[
        "veterinarian"
    ],
    "wof:name":"Medikal Klinik Veteriner Hekim Hizm.",
    "wof:placetype":"venue"
},
  "geometry": {"coordinates":[29.881521225,40.8532714844],"type":"Point"}
}