{
  "type": "Feature",
  "properties": {
    "addr:full":"Hosdere Cd. No:133/a Y.ayranci Merkez Ankara 43100",
    "addr:housenumber":"no;/ a",
    "addr:postcode":"43100",
    "addr:street":"Hosdere Cd.;Y.Ayranci Merkez",
    "iso:country":"TR",
    "sg:address":"Hosdere Cd. No:133/a Y.ayranci",
    "sg:city":"Merkez",
    "sg:classifiers":[
        {
            "category":"Home & Garden",
            "subcategory":"Kitchen Supply",
            "type":"Retail Goods"
        }
    ],
    "sg:phone":"+90 312 438 3236",
    "sg:postcode":"43100",
    "sg:province":"Ankara",
    "sg:tags":[
        "wardrobe"
    ],
    "wof:name":"Gokmen Mutfak Banyo",
    "wof:placetype":"venue"
},
  "geometry": {"coordinates":[32.846988678,39.8900794983],"type":"Point"}
}