{
  "type": "Feature",
  "properties": {
    "iso:country":"TR",
    "sg:address":"Ankara Cd. No:123 Sirkeci",
    "sg:city":"Okmeydani",
    "sg:classifiers":[
        {
            "category":"Shopping",
            "subcategory":"Stationery & Office Supplies",
            "type":"Retail Goods"
        }
    ],
    "sg:phone":"+90 212 527 2482",
    "sg:postcode":"43050",
    "sg:province":"Istanbul",
    "wof:name":"Teknik El Kirtasiye",
    "wof:placetype":"venue"
},
  "geometry": {"coordinates":[28.976213,41.01556],"type":"Point"}
}