{
  "type": "Feature",
  "properties": {
    "addr:full":"Sanayi Sitesi Cad.no:1 S?e Ikitelli/K\u00fc\u00e7\u00fck\u00e7ekmece Aydin 34670",
    "addr:housenumber":"1;?",
    "addr:postcode":"34670",
    "addr:street":"Sanayi Sitesi Cad.No;E Ikitelli / Kuec\u0327Uekc\u0327Ekmece Aydin",
    "iso:country":"TR",
    "sg:address":"Sanayi Sitesi Cad.no:1 S?e",
    "sg:city":"Ikitelli/K\u00fc\u00e7\u00fck\u00e7ekmece",
    "sg:classifiers":[
        {
            "category":"Professional",
            "subcategory":"Business Services",
            "type":"Services"
        }
    ],
    "sg:phone":"+90 256 518 1794",
    "sg:postcode":"34670",
    "sg:province":"Aydin",
    "sg:tags":[
        "industry",
        "casting"
    ],
    "wof:name":"Emek Pik D?k?m",
    "wof:placetype":"venue"
},
  "geometry": {"coordinates":[27.8324394226,37.8409690857],"type":"Point"}
}