{
  "type": "Feature",
  "properties": {
    "addr:full":"M.nafiz Gurman Mah.kasim Sok.no:4 Merter Istanbul",
    "addr:housenumber":"4",
    "addr:street":"Sok.No",
    "iso:country":"TR",
    "sg:address":"M.nafiz Gurman Mah.kasim Sok.no:4",
    "sg:city":"Merter",
    "sg:classifiers":[
        {
            "category":"Shopping",
            "subcategory":"Clothing, Apparel, & Fashions",
            "type":"Retail Goods"
        }
    ],
    "sg:phone":"+90 212 507 3323",
    "sg:province":"Istanbul",
    "sg:tags":[
        "ready",
        "wear"
    ],
    "wof:name":"Renteks Tekstil Urunleri Paz.dis Tic.a.s.",
    "wof:placetype":"venue"
},
  "geometry": {"coordinates":[28.9529724121,41.020526886],"type":"Point"}
}