{
  "type": "Feature",
  "properties": {
    "addr:full":"G?b? Sk. No 8/1-2 G?g?en Istanbul",
    "addr:housenumber":"1-2 g ? g ?",
    "addr:street":"Sk. No 8 /",
    "iso:country":"TR",
    "sg:address":"G?b? Sk. No 8/1-2",
    "sg:city":"G?g?en",
    "sg:orig_category":"Textile Suplementaries",
    "sg:phone":"+90 212 643 3610",
    "sg:province":"Istanbul",
    "wof:name":"Akpa Konf.yan ?r?nleri A.s.",
    "wof:placetype":"venue"
},
  "geometry": {"coordinates":[28.9861831665,41.0408554077],"type":"Point"}
}