{
  "type": "Feature",
  "properties": {
    "iso:country":"TR",
    "sg:address":"Pazar Mah. Muftu Sok.9/c",
    "sg:city":"Gazipasa",
    "sg:classifiers":[
        {
            "category":"Manufacturing",
            "subcategory":"Chemicals & Compounds",
            "type":"Manufacturing & Wholesale Goods"
        }
    ],
    "sg:phone":"+90 362 432 7727",
    "sg:postcode":"01120",
    "sg:province":"Samsun",
    "sg:tags":[
        "agricultural"
    ],
    "wof:name":"Karadeniz Tarim Urunleri Ltd.sti.",
    "wof:placetype":"venue"
},
  "geometry": {"coordinates":[36.3300514221,41.2928009033],"type":"Point"}
}