{
  "type": "Feature",
  "properties": {
    "iso:country":"TR",
    "sg:address":"Fevzi Cakmak Mah.ataturk Cad.zafer Sok. No: 11 Bagcilar-",
    "sg:city":"Kirazli",
    "sg:classifiers":[
        {
            "category":"Manufacturing",
            "subcategory":"Glass & Minerals",
            "type":"Manufacturing & Wholesale Goods"
        }
    ],
    "sg:phone":"+90 212 651 6919",
    "sg:postcode":"25940",
    "sg:province":"Istanbul",
    "sg:tags":[
        "glass-mirror"
    ],
    "wof:name":"Nural Isi Cam",
    "wof:placetype":"venue"
},
  "geometry": {"coordinates":[28.8556938171,41.0426902771],"type":"Point"}
}