{
  "type": "Feature",
  "properties": {
    "iso:country":"TR",
    "sg:address":"Oto Center Galericiler Sit. P-blok No:101 Bagcilar",
    "sg:city":"Erenk?y",
    "sg:orig_category":"Auto Galeries",
    "sg:phone":"+90 212 673 3182",
    "sg:province":"Istanbul",
    "wof:name":"Sonmez Otomotiv",
    "wof:placetype":"venue"
},
  "geometry": {"coordinates":[28.8513698578,41.0430297852],"type":"Point"}
}