{
  "type": "Feature",
  "properties": {
    "iso:country":"TR",
    "sg:address":"Fistikcilar Sitesi 6. Blok No:86 Gatem",
    "sg:city":"Mersin",
    "sg:classifiers":[
        {
            "category":"Professional",
            "subcategory":"Business Services",
            "type":"Services"
        }
    ],
    "sg:phone":"+90 342238221213",
    "sg:postcode":"52750",
    "sg:province":"Gaziantep",
    "sg:tags":[
        "food",
        "product",
        "exporter",
        "aricultural"
    ],
    "wof:name":"Kurtoglu Gida San.tic.ltd.sti.",
    "wof:placetype":"venue"
},
  "geometry": {"coordinates":[37.3761024475,37.0629463196],"type":"Point"}
}