{
  "type": "Feature",
  "properties": {
    "addr:full":"1675 Sok. No:141-b Karsiyaka 06060 Izmir",
    "addr:housenumber":"no 141-b",
    "addr:postcode":"1675;06060",
    "addr:street":"Sok.;Karsiyaka",
    "iso:country":"TR",
    "sg:address":"1675 Sok. No:141-b Karsiyaka",
    "sg:city":"06060",
    "sg:classifiers":[
        {
            "category":"Professional",
            "subcategory":"Detective & Security Services",
            "type":"Services"
        }
    ],
    "sg:phone":"+90 232 365 1788",
    "sg:province":"Izmir",
    "sg:tags":[
        "material"
    ],
    "wof:name":"Izmir Serigrafi Ikaz Ve Trafik Levhalari.",
    "wof:placetype":"venue"
},
  "geometry": {"coordinates":[27.127455,38.461994],"type":"Point"}
}