{
  "type": "Feature",
  "properties": {
    "addr:full":"Imes San. Sit. C Blok 307/16 ?mraniye \u00dcmraniye Istanbul 34776",
    "addr:housenumber":"blok 307 / 16 ?",
    "addr:postcode":"34776",
    "addr:street":"Mraniye",
    "iso:country":"TR",
    "sg:address":"Imes San. Sit. C Blok 307/16 ?mraniye",
    "sg:city":"\u00dcmraniye",
    "sg:classifiers":[
        {
            "category":"Manufacturing",
            "subcategory":"Tools & Machinery",
            "type":"Manufacturing & Wholesale Goods"
        }
    ],
    "sg:phone":"+90 216 364 2803",
    "sg:postcode":"34776",
    "sg:province":"Istanbul",
    "sg:tags":[
        "machine",
        "industry"
    ],
    "wof:name":"Kates Makina San.",
    "wof:placetype":"venue"
},
  "geometry": {"coordinates":[29.175403595,41.0060424805],"type":"Point"}
}