{
  "type": "Feature",
  "properties": {
    "addr:full":"Belediye Pasaji No: 23-27 Kusadasi Aydin 09400",
    "addr:housenumber":"no 23-27",
    "addr:postcode":"09400",
    "iso:country":"TR",
    "sg:address":"Belediye Pasaji No: 23-27",
    "sg:city":"Kusadasi",
    "sg:classifiers":[
        {
            "category":"Travel",
            "subcategory":"Travel Agent",
            "type":"Entertainment"
        }
    ],
    "sg:phone":"+90 256 614 6839",
    "sg:postcode":"09400",
    "sg:province":"Aydin",
    "sg:tags":[
        "agency",
        "tourism"
    ],
    "wof:name":"Platon Travel And Shipping Co.",
    "wof:placetype":"venue"
},
  "geometry": {"coordinates":[27.8324394226,37.8409690857],"type":"Point"}
}