{
  "type": "Feature",
  "properties": {
    "addr:full":"Turgut Reis Mah. Cengiz Topel Cad.no:30 Atesalani / Esenler Istanbul",
    "addr:housenumber":"30",
    "addr:street":"Turgut Reis;Topel Cad.No",
    "iso:country":"TR",
    "sg:address":"Turgut Reis Mah. Cengiz Topel Cad.no:30",
    "sg:city":"Atesalani / Esenler",
    "sg:classifiers":[
        {
            "category":"Banks & Credit Unions",
            "subcategory":"Investment Brokerage",
            "type":"Services"
        }
    ],
    "sg:phone":"+90 21243128194",
    "sg:province":"Istanbul",
    "sg:tags":[
        "shirt",
        "necktie"
    ],
    "wof:name":"Serhat Tekstil",
    "wof:placetype":"venue"
},
  "geometry": {"coordinates":[28.863306,41.056545],"type":"Point"}
}