{
  "type": "Feature",
  "properties": {
    "iso:country":"TR",
    "sg:address":"Terazidere Mah.esenler Cad.tas Sok. No: 3 Bayrampasa",
    "sg:city":"24000",
    "sg:classifiers":[
        {
            "category":"Manufacturing",
            "subcategory":"Wood Products",
            "type":"Manufacturing & Wholesale Goods"
        }
    ],
    "sg:phone":"+90 212 577 4515",
    "sg:province":"Istanbul",
    "sg:tags":[
        "forest"
    ],
    "wof:name":"Durust Orman Urn. San.tic.ltd.sti.",
    "wof:placetype":"venue"
},
  "geometry": {"coordinates":[28.898557663,41.0336380005],"type":"Point"}
}