{
  "type": "Feature",
  "properties": {
    "addr:full":"Ali Nihat Tarlan Cad 103 Bostanci 91120 25900",
    "addr:housenumber":"103",
    "addr:postcode":"91120 25900",
    "addr:street":"Tarlan Cad",
    "iso:country":"TR",
    "sg:address":"Ali Nihat Tarlan Cad 103",
    "sg:city":"Bostanci",
    "sg:classifiers":[
        {
            "category":"Banks & Credit Unions",
            "subcategory":"Bank",
            "type":"Services"
        }
    ],
    "sg:phone":"+90 216 416 5656",
    "sg:postcode":"25900",
    "sg:province":"91120",
    "wof:name":"Kentbank As",
    "wof:placetype":"venue"
},
  "geometry": {"coordinates":[29.107008,40.967407],"type":"Point"}
}