{
  "type": "Feature",
  "properties": {
    "iso:country":"TR",
    "sg:address":"Sanayi Bolgesi 3, Cad. No:133",
    "sg:city":"Osmangazi",
    "sg:classifiers":[
        {
            "category":"Home & Garden",
            "subcategory":"Furniture",
            "type":"Retail Goods"
        }
    ],
    "sg:phone":"+90 352 336 5730",
    "sg:postcode":"16200",
    "sg:province":"Kayseri",
    "sg:tags":[
        "armchair",
        "sofa"
    ],
    "wof:name":"Oba Mobilya Kanepe Sanayi Ve Tic.ltd.",
    "wof:placetype":"venue"
},
  "geometry": {"coordinates":[35.4364013672,38.7450408936],"type":"Point"}
}