{
  "type": "Feature",
  "properties": {
    "addr:full":"Oto Sanayi Sitesi Ulubas Cad. No.64 Levent Iskitler Istanbul 06070",
    "addr:housenumber":"no.64",
    "addr:postcode":"06070",
    "addr:street":"Ulubas Cad.",
    "iso:country":"TR",
    "sg:address":"Oto Sanayi Sitesi Ulubas Cad. No.64 Levent",
    "sg:city":"Iskitler",
    "sg:classifiers":[
        {
            "category":"Wholesale",
            "subcategory":"Auto Parts",
            "type":"Manufacturing & Wholesale Goods"
        }
    ],
    "sg:phone":"+90 212 270 7229",
    "sg:postcode":"06070",
    "sg:province":"Istanbul",
    "sg:tags":[
        "spare"
    ],
    "wof:name":"Erduz Otomotiv Ltd.sti.",
    "wof:placetype":"venue"
},
  "geometry": {"coordinates":[28.9861831665,41.0408554077],"type":"Point"}
}