{
  "type": "Feature",
  "properties": {
    "iso:country":"TR",
    "sg:address":"Ramazanpasa Mah 7/a",
    "sg:city":"Aydin",
    "sg:classifiers":[
        {
            "category":"Banks & Credit Unions",
            "subcategory":"Bank",
            "type":"Services"
        }
    ],
    "sg:phone":"+90 256 212 4116",
    "sg:postcode":"01513",
    "sg:province":"09020",
    "wof:name":"S?erbank As",
    "wof:placetype":"venue"
},
  "geometry": {"coordinates":[27.841085,37.827686],"type":"Point"}
}