{
  "type": "Feature",
  "properties": {
    "addr:full":"Asarcikli Cd. No:44/a Osmangazi Eskisehir 16170",
    "addr:housenumber":"no 44 / a",
    "addr:postcode":"16170",
    "addr:street":"Asarcikli Cd.;Osmangazi Eskisehir",
    "iso:country":"TR",
    "sg:address":"Asarcikli Cd. No:44/a",
    "sg:city":"Osmangazi",
    "sg:classifiers":[
        {
            "category":"Farming",
            "subcategory":"Fish & Marine Products",
            "type":"Manufacturing & Wholesale Goods"
        }
    ],
    "sg:phone":"+90 222 231 4033",
    "sg:postcode":"16170",
    "sg:province":"Eskisehir",
    "sg:tags":[
        "automotive"
    ],
    "wof:name":"Ormaci Otomotiv Ltd. Sti.",
    "wof:placetype":"venue"
},
  "geometry": {"coordinates":[30.5230522156,39.7732429504],"type":"Point"}
}