{
  "type": "Feature",
  "properties": {
    "addr:full":"K.karabekir C.no.13 G?eslik? Beyazit Istanbul 65400",
    "addr:housenumber":"?;?",
    "addr:postcode":"65400",
    "addr:street":"C.No.13 G;Beyazit Istanbul",
    "iso:country":"TR",
    "sg:address":"K.karabekir C.no.13 G?eslik?",
    "sg:city":"Beyazit",
    "sg:classifiers":[
        {
            "category":"Manufacturing",
            "subcategory":"Leather Goods",
            "type":"Manufacturing & Wholesale Goods"
        }
    ],
    "sg:phone":"+90 212 550 2896",
    "sg:postcode":"65400",
    "sg:province":"Istanbul",
    "wof:name":"Yusuf ?anta San. Ltd.sti.",
    "wof:placetype":"venue"
},
  "geometry": {"coordinates":[32.8457145691,39.9434585571],"type":"Point"}
}