{
  "type": "Feature",
  "properties": {
    "iso:country":"TR",
    "sg:address":"Room 375 Yeillik Cad.",
    "sg:city":"Karabaglar",
    "sg:classifiers":[
        {
            "category":"Banks & Credit Unions",
            "subcategory":"Bank",
            "type":"Services"
        }
    ],
    "sg:phone":"+90 232 265 3636",
    "sg:postcode":"44210",
    "sg:province":"35400",
    "wof:name":"T?k Dis Ticaret, Bankasi As",
    "wof:placetype":"venue"
},
  "geometry": {"coordinates":[27.134663,38.382755],"type":"Point"}
}