{
  "type": "Feature",
  "properties": {
    "iso:country":"TR",
    "sg:address":"Ibrahim Kayhan",
    "sg:city":"Emirdag",
    "sg:classifiers":[
        {
            "category":"Government",
            "subcategory":"Office",
            "type":"Public Place"
        }
    ],
    "sg:phone":"+90 258 381 7008",
    "sg:postcode":"03600",
    "sg:province":"Denizli",
    "sg:tags":[
        "municipality"
    ],
    "wof:name":"Asagisamli Belediye Baskani",
    "wof:placetype":"venue"
},
  "geometry": {"coordinates":[29.112197876,37.7460632324],"type":"Point"}
}