{
  "type": "Feature",
  "properties": {
    "addr:full":"Top.gida Mrk. No.10 Rami Istanbul 34055",
    "addr:housenumber":"no.10",
    "addr:postcode":"34055",
    "addr:street":"Rami Istanbul",
    "iso:country":"TR",
    "sg:address":"Top.gida Mrk. No.10",
    "sg:city":"Rami",
    "sg:classifiers":[
        {
            "category":"Food & Beverages",
            "subcategory":"Groceries & Convenience Stores",
            "type":"Retail Goods"
        }
    ],
    "sg:phone":"+90 212 581 6568",
    "sg:postcode":"34055",
    "sg:province":"Istanbul",
    "sg:tags":[
        "olive",
        "oil"
    ],
    "wof:name":"?zaydin Zeytin Ve Yag San.",
    "wof:placetype":"venue"
},
  "geometry": {"coordinates":[28.9230213165,41.0406188965],"type":"Point"}
}