{
  "type": "Feature",
  "properties": {
    "iso:country":"TR",
    "sg:address":"Tarlabasi Cd. No:60/2 Taksim",
    "sg:city":"Kartal",
    "sg:classifiers":[
        {
            "category":"Farming",
            "subcategory":"Fish & Marine Products",
            "type":"Manufacturing & Wholesale Goods"
        }
    ],
    "sg:phone":"+90 212 253 8759",
    "sg:postcode":"46000",
    "sg:province":"Istanbul",
    "sg:tags":[
        "automotive"
    ],
    "wof:name":"Sapmaz Otomotiv San. Tic. A.s.",
    "wof:placetype":"venue"
},
  "geometry": {"coordinates":[28.9823093414,41.037689209],"type":"Point"}
}