{
  "type": "Feature",
  "properties": {
    "addr:full":"Tongucbaba Cad. No:15 Saadetdere Mah. 34900 B.cekmece Istanbul Hadimk? Istanbul 34500",
    "addr:housenumber":"15 saadetdere mah.",
    "addr:postcode":"34900;?;34500",
    "addr:street":"Tongucbaba Cad. No",
    "iso:country":"TR",
    "sg:address":"Tongucbaba Cad. No:15 Saadetdere Mah. 34900 B.cekmece Istanbul",
    "sg:city":"Hadimk?",
    "sg:classifiers":[
        {
            "category":"Manufacturing",
            "subcategory":"Rubber & Plastics",
            "type":"Manufacturing & Wholesale Goods"
        }
    ],
    "sg:phone":"+90 212 690 7060",
    "sg:postcode":"34500",
    "sg:province":"Istanbul",
    "wof:name":"Surtas Madeni Ve Plastik Esya",
    "wof:placetype":"venue"
},
  "geometry": {"coordinates":[28.9759254456,41.0123786926],"type":"Point"}
}