{
  "type": "Feature",
  "properties": {
    "addr:full":"Ambar K??h?tas Tesis. Ambar \u00dcmraniye Kayseri 81260",
    "addr:postcode":"81260",
    "addr:street":"Tesis. Ambar",
    "iso:country":"TR",
    "sg:address":"Ambar K??h?tas Tesis. Ambar",
    "sg:city":"\u00dcmraniye",
    "sg:classifiers":[
        {
            "category":"Manufacturing",
            "subcategory":"Tools & Machinery",
            "type":"Manufacturing & Wholesale Goods"
        }
    ],
    "sg:phone":"+90 352 321 1436",
    "sg:postcode":"81260",
    "sg:province":"Kayseri",
    "sg:tags":[
        "machine",
        "industry"
    ],
    "wof:name":"Maken-makina Endust.",
    "wof:placetype":"venue"
},
  "geometry": {"coordinates":[35.4891357422,38.7225761414],"type":"Point"}
}