{
  "type": "Feature",
  "properties": {
    "iso:country":"TR",
    "sg:address":"Dr. N. Tarlan Cd. Kadik?",
    "sg:city":"Bayrampasa",
    "sg:classifiers":[
        {
            "category":"Communications",
            "subcategory":"Film & Video Production",
            "type":"Services"
        }
    ],
    "sg:phone":"+90 216 361 6165",
    "sg:postcode":"36100",
    "sg:province":"Istanbul",
    "sg:tags":[
        "-"
    ],
    "wof:name":"Merih Video Film San. Tic. A.s.",
    "wof:placetype":"venue"
},
  "geometry": {"coordinates":[29.1029415131,40.9615592957],"type":"Point"}
}