{
  "type": "Feature",
  "properties": {
    "addr:full":"Piri Reis Cd. ?inar San. Sit. B Blok No:66 Maltepe 07230 Istanbul",
    "addr:housenumber":"blok no 66",
    "addr:postcode":"07230",
    "addr:street":"Piri Reis;Inar;Maltepe",
    "iso:country":"TR",
    "sg:address":"Piri Reis Cd. ?inar San. Sit. B Blok No:66 Maltepe",
    "sg:city":"07230",
    "sg:classifiers":[
        {
            "category":"Sports & Exercise",
            "subcategory":"Tennis Court",
            "type":"Entertainment"
        }
    ],
    "sg:phone":"+90 216 441 6214",
    "sg:province":"Istanbul",
    "sg:tags":[
        "equipment",
        "material"
    ],
    "wof:name":"Alkim Spor Malz. Imal.",
    "wof:placetype":"venue"
},
  "geometry": {"coordinates":[28.91267,41.020466],"type":"Point"}
}