{
  "type": "Feature",
  "properties": {
    "addr:full":"Cumhuriyet Mah. Yildirim Sok. No:27 Yenimahalle Eskisehir 06",
    "addr:housenumber":"no 27;06",
    "addr:street":"Cumhuriyet Mah. Yildirim Sok.;Yenimahalle Eskisehir",
    "iso:country":"TR",
    "sg:address":"Cumhuriyet Mah. Yildirim Sok. No:27",
    "sg:city":"Yenimahalle",
    "sg:classifiers":[
        {
            "category":"Shopping",
            "subcategory":"Stationery & Office Supplies",
            "type":"Retail Goods"
        }
    ],
    "sg:phone":"+90 222 233 5522",
    "sg:postcode":"06",
    "sg:province":"Eskisehir",
    "sg:tags":[
        "paper"
    ],
    "wof:name":"Donatim Uretim Insaat Paz. Ith.ihr. San. Ve Tic. Ltd.sti.",
    "wof:placetype":"venue"
},
  "geometry": {"coordinates":[30.5397472382,39.7899093628],"type":"Point"}
}