{
  "type": "Feature",
  "properties": {
    "addr:full":"Benli Nalbant G?basi Ankara",
    "addr:housenumber":"?",
    "addr:street":"Nalbant G",
    "iso:country":"TR",
    "sg:address":"Benli Nalbant",
    "sg:city":"G?basi",
    "sg:classifiers":[
        {
            "category":"Government",
            "subcategory":"Office",
            "type":"Public Place"
        }
    ],
    "sg:phone":"+90 312 613 5051",
    "sg:province":"Ankara",
    "sg:tags":[
        "municipality"
    ],
    "wof:name":"Selametli Belediye Baskani",
    "wof:placetype":"venue"
},
  "geometry": {"coordinates":[32.8560333252,39.9438743591],"type":"Point"}
}