{
  "type": "Feature",
  "properties": {
    "iso:country":"TR",
    "sg:address":"Fahrettin Kerim G?ay Cad.no:260",
    "sg:city":"G?ztepe",
    "sg:orig_category":"Auto Galeries",
    "sg:phone":"+90 216 369 9844",
    "sg:postcode":"81080",
    "sg:province":"Istanbul",
    "wof:name":"Akbay Otomotiv Ve Ithalat",
    "wof:placetype":"venue"
},
  "geometry": {"coordinates":[29.0725898743,40.98072052],"type":"Point"}
}