{
  "type": "Feature",
  "properties": {
    "addr:full":"Fevzi Pasa Cad. Feyzullah Efendi Sok. No:6/2 Fatih 07100 Istanbul",
    "addr:housenumber":"no 6 / 2",
    "addr:postcode":"07100",
    "addr:street":"Fevzi Pasa Cad.;Efendi Sok.;Fatih",
    "iso:country":"TR",
    "sg:address":"Fevzi Pasa Cad. Feyzullah Efendi Sok. No:6/2 Fatih",
    "sg:city":"07100",
    "sg:classifiers":[
        {
            "category":"Shopping",
            "subcategory":"Optical Goods",
            "type":"Retail Goods"
        }
    ],
    "sg:phone":"+90 212 635 4109",
    "sg:province":"Istanbul",
    "sg:tags":[
        "material"
    ],
    "wof:name":"Ata Medikal",
    "wof:placetype":"venue"
},
  "geometry": {"coordinates":[28.9493293762,41.0168266296],"type":"Point"}
}