{
  "type": "Feature",
  "properties": {
    "addr:full":"Koza Sk. 144/2 Gaziosmanpasa Kadikoy Ankara 01370",
    "addr:housenumber":"144 / 2",
    "addr:postcode":"01370",
    "addr:street":"Koza Sk.;Gaziosmanpasa Kadikoy",
    "iso:country":"TR",
    "sg:address":"Koza Sk. 144/2 Gaziosmanpasa",
    "sg:city":"Kadikoy",
    "sg:orig_category":"Art Galeries",
    "sg:phone":"+90 312 436 3787",
    "sg:postcode":"01370",
    "sg:province":"Ankara",
    "wof:name":"Tiyatro Hayal Perdesi",
    "wof:placetype":"venue"
},
  "geometry": {"coordinates":[32.8604812622,39.9429283142],"type":"Point"}
}