{
  "type": "Feature",
  "properties": {
    "addr:full":"Istiklal Cd.galatasaray Ish.no230 K4 Beyoglu Istanbul 46810",
    "addr:postcode":"46810",
    "iso:country":"TR",
    "sg:address":"Istiklal Cd.galatasaray Ish.no230 K4",
    "sg:city":"Beyoglu",
    "sg:classifiers":[
        {
            "category":"Marine",
            "type":"Transportation"
        }
    ],
    "sg:phone":"+90 212 249 5152",
    "sg:postcode":"46810",
    "sg:province":"Istanbul",
    "sg:tags":[
        "shipowner"
    ],
    "wof:name":"Und Denizcilik A.s.",
    "wof:placetype":"venue"
},
  "geometry": {"coordinates":[28.975925,41.012379],"type":"Point"}
}