{
  "type": "Feature",
  "properties": {
    "addr:full":"Atat?k Bulv. Im? 2.blok No: 2522 Unkapani Istanbul 55020",
    "addr:housenumber":"2.blok no 2522",
    "addr:postcode":"55020",
    "addr:street":"K Bulv. Im ?;Unkapani Istanbul",
    "iso:country":"TR",
    "sg:address":"Atat?k Bulv. Im? 2.blok No: 2522",
    "sg:city":"Unkapani",
    "sg:classifiers":[
        {
            "category":"Home & Garden",
            "subcategory":"Home Furnishings",
            "type":"Retail Goods"
        }
    ],
    "sg:phone":"+90 212 512 2209",
    "sg:postcode":"55020",
    "sg:province":"Istanbul",
    "sg:tags":[
        "-curtains",
        "upholstery"
    ],
    "wof:name":"Sinka Tekstil",
    "wof:placetype":"venue"
},
  "geometry": {"coordinates":[28.9759254456,41.0123786926],"type":"Point"}
}