{
  "type": "Feature",
  "properties": {
    "addr:full":"Org. San. B?g. Cumh. Bulv. Ikitelli/K\u00fc\u00e7\u00fck\u00e7ekmece Manisa 34670",
    "addr:housenumber":"ikitelli / kuec\u0327uekc\u0327ekmece",
    "addr:postcode":"34670",
    "addr:street":"Org.;Cumh. Bulv.",
    "iso:country":"TR",
    "sg:address":"Org. San. B?g. Cumh. Bulv.",
    "sg:city":"Ikitelli/K\u00fc\u00e7\u00fck\u00e7ekmece",
    "sg:classifiers":[
        {
            "category":"Manufacturing",
            "subcategory":"Tools & Machinery",
            "type":"Manufacturing & Wholesale Goods"
        }
    ],
    "sg:phone":"+90 236 233 0444",
    "sg:postcode":"34670",
    "sg:province":"Manisa",
    "sg:tags":[
        "machine",
        "industry"
    ],
    "wof:name":"Olgun ?elik San. Tic. Ltd. Sti.",
    "wof:placetype":"venue"
},
  "geometry": {"coordinates":[27.4297008514,38.6222000122],"type":"Point"}
}