{
  "type": "Feature",
  "properties": {
    "iso:country":"TR",
    "sg:address":"K?alti Mevkii Oru?sk. No:21 Yenibosna",
    "sg:city":"Yukari Dudullu",
    "sg:classifiers":[
        {
            "category":"Manufacturing",
            "subcategory":"Rubber & Plastics",
            "type":"Manufacturing & Wholesale Goods"
        }
    ],
    "sg:phone":"+90 212 552 1334",
    "sg:postcode":"34776",
    "sg:province":"Istanbul",
    "sg:tags":[
        "industry"
    ],
    "wof:name":"Aktek Plastik San. Tic. A.s.",
    "wof:placetype":"venue"
},
  "geometry": {"coordinates":[29.175403595,41.0060424805],"type":"Point"}
}