{
  "type": "Feature",
  "properties": {
    "iso:country":"TR",
    "sg:address":"Yeni Carsi Deftedar Sok. No:8",
    "sg:city":"Isikkent",
    "sg:classifiers":[
        {
            "category":"Shopping",
            "subcategory":"Shoes",
            "type":"Retail Goods"
        }
    ],
    "sg:phone":"+90 372 253 7171",
    "sg:postcode":"35070",
    "sg:province":"Zonguldak",
    "wof:name":"Kar Ticaret",
    "wof:placetype":"venue"
},
  "geometry": {"coordinates":[31.7925,41.451401],"type":"Point"}
}