{
  "type": "Feature",
  "properties": {
    "iso:country":"TR",
    "sg:address":"?akmak Mh. Mithatpasa Cd. No:114/3",
    "sg:city":"\u00dcmraniye",
    "sg:classifiers":[
        {
            "category":"Manufacturing",
            "subcategory":"Textiles",
            "type":"Manufacturing & Wholesale Goods"
        }
    ],
    "sg:phone":"+90 216 443 1688",
    "sg:province":"Istanbul",
    "sg:tags":[
        "cloth",
        "worker"
    ],
    "wof:name":"Gen?ler Is Elbise. San. Imal. Ve Paz.",
    "wof:placetype":"venue"
},
  "geometry": {"coordinates":[29.0991153717,41.0244369507],"type":"Point"}
}