{
  "type": "Feature",
  "properties": {
    "addr:full":"Mahir ?ner Altindag Ankara 07050",
    "addr:postcode":"07050",
    "iso:country":"TR",
    "sg:address":"Mahir ?ner",
    "sg:city":"Altindag",
    "sg:classifiers":[
        {
            "category":"Government",
            "subcategory":"Office",
            "type":"Public Place"
        }
    ],
    "sg:phone":"+90 312 399 2345",
    "sg:postcode":"07050",
    "sg:province":"Ankara",
    "sg:tags":[
        "municipality"
    ],
    "wof:name":"Altinova Belediye Baskani",
    "wof:placetype":"venue"
},
  "geometry": {"coordinates":[32.5678100586,39.9557571411],"type":"Point"}
}