{
  "type": "Feature",
  "properties": {
    "iso:country":"TR",
    "sg:address":"Sanlurfa",
    "sg:city":"Karabaglar",
    "sg:classifiers":[
        {
            "category":"Government",
            "subcategory":"Office",
            "type":"Public Place"
        }
    ],
    "sg:phone":"+90 414 552 1037",
    "sg:postcode":"44210",
    "sg:province":"Sanlurfa",
    "sg:tags":[
        "army"
    ],
    "wof:name":"Siverek Askerlik Subesi",
    "wof:placetype":"venue"
},
  "geometry": {"coordinates":[38.785369873,37.1567001343],"type":"Point"}
}