{
  "type": "Feature",
  "properties": {
    "addr:full":"Adnan Menderes Blv. No:303 Y. Dudullu Denizli",
    "addr:street":"Adnan Menderes Blv. No 303 Y. Dudullu",
    "iso:country":"TR",
    "sg:address":"Adnan Menderes Blv. No:303",
    "sg:city":"Y. Dudullu",
    "sg:classifiers":[
        {
            "category":"Manufacturing",
            "subcategory":"Metals",
            "type":"Manufacturing & Wholesale Goods"
        }
    ],
    "sg:phone":"+90 258 269 1664",
    "sg:province":"Denizli",
    "sg:tags":[
        "iron-steel",
        "peoducts"
    ],
    "wof:name":"Yavuz Ferforje A.s.",
    "wof:placetype":"venue"
},
  "geometry": {"coordinates":[29.1355361938,37.8388290405],"type":"Point"}
}