{
  "type": "Feature",
  "properties": {
    "iso:country":"TR",
    "sg:address":"Kosuyolu Tophanelioglu Cd. Pinar ?ikm. A Blok ?sk?ar",
    "sg:city":"Sisli",
    "sg:classifiers":[
        {
            "category":"Professional",
            "subcategory":"Detective & Security Services",
            "type":"Services"
        }
    ],
    "sg:phone":"+90 212392611",
    "sg:postcode":"80270",
    "sg:province":"Istanbul",
    "sg:tags":[
        "material"
    ],
    "wof:name":"Tugal Proje M?s-m?m Ltd. Sti.",
    "wof:placetype":"venue"
},
  "geometry": {"coordinates":[28.975925,41.012379],"type":"Point"}
}