{
  "type": "Feature",
  "properties": {
    "addr:full":"B Onat Cad Ali Zeybek Ap No:102 Adapazari Antalya 54000",
    "addr:housenumber":"ap",
    "addr:postcode":"54000",
    "addr:street":"Onat Cad Ali;No 102 Adapazari",
    "iso:country":"TR",
    "sg:address":"B Onat Cad Ali Zeybek Ap No:102",
    "sg:city":"Adapazari",
    "sg:classifiers":[
        {
            "category":"Building & Trades",
            "subcategory":"Locksmith",
            "type":"Services"
        }
    ],
    "sg:phone":"+90 242 311 3642",
    "sg:postcode":"54000",
    "sg:province":"Antalya",
    "sg:tags":[
        "lock",
        "key"
    ],
    "wof:name":"Anahtarciniz Cem",
    "wof:placetype":"venue"
},
  "geometry": {"coordinates":[30.7031345367,36.8875045776],"type":"Point"}
}