{
  "type": "Feature",
  "properties": {
    "addr:full":"Bagdat Cad. T?bent? ?ikmazi No.541 Bostanci Istanbul 25900",
    "addr:housenumber":"?;? ?;no.541",
    "addr:postcode":"25900",
    "addr:street":"Bagdat Cad. T;Ikmazi;Istanbul",
    "iso:country":"TR",
    "sg:address":"Bagdat Cad. T?bent? ?ikmazi No.541",
    "sg:city":"Bostanci",
    "sg:orig_category":"Non-classified Establishments",
    "sg:phone":"+90 216 410 5422",
    "sg:postcode":"25900",
    "sg:province":"Istanbul",
    "wof:name":"Anadolu Tohumculuk A.s.",
    "wof:placetype":"venue"
},
  "geometry": {"coordinates":[28.9861831665,41.0408554077],"type":"Point"}
}