{
  "type": "Feature",
  "properties": {
    "iso:country":"TR",
    "sg:address":"Tersane Cd. No:27 Karak?",
    "sg:city":"Beyoglu",
    "sg:classifiers":[
        {
            "category":"Wholesale",
            "subcategory":"Machinery & Supplies",
            "type":"Manufacturing & Wholesale Goods"
        }
    ],
    "sg:phone":"+90 212 244 2161",
    "sg:postcode":"34420",
    "sg:province":"Istanbul",
    "sg:tags":[
        "bearing",
        "ball"
    ],
    "wof:name":"Can Rulman",
    "wof:placetype":"venue"
},
  "geometry": {"coordinates":[28.972513,41.025505],"type":"Point"}
}