{
  "type": "Feature",
  "properties": {
    "iso:country":"TR",
    "sg:address":"Aksemseddin Cd. No:116",
    "sg:city":"Fatih",
    "sg:classifiers":[
        {
            "category":"Home & Garden",
            "subcategory":"Home Furnishings",
            "type":"Retail Goods"
        }
    ],
    "sg:phone":"+90 212 532 3987",
    "sg:postcode":"01740",
    "sg:province":"Istanbul",
    "sg:tags":[
        "-curtains",
        "upholstery"
    ],
    "wof:name":"Merve Mefrusat San. Tic. Ltd. Sti.",
    "wof:placetype":"venue"
},
  "geometry": {"coordinates":[29.406370163,40.7832603455],"type":"Point"}
}