{
  "type": "Feature",
  "properties": {
    "addr:full":"Sogutlucesme Cad. No: 70/36 Kadikoy 07100 Istanbul",
    "addr:housenumber":"70 / 36",
    "addr:postcode":"07100",
    "addr:street":"Sogutlucesme Cad. No;Kadikoy",
    "iso:country":"TR",
    "sg:address":"Sogutlucesme Cad. No: 70/36 Kadikoy",
    "sg:city":"07100",
    "sg:classifiers":[
        {
            "category":"Shopping",
            "subcategory":"Optical Goods",
            "type":"Retail Goods"
        }
    ],
    "sg:phone":"+90 216 336 5757",
    "sg:province":"Istanbul",
    "sg:tags":[
        "material"
    ],
    "wof:name":"Bulvar Optik Saglik Hizmetleri",
    "wof:placetype":"venue"
},
  "geometry": {"coordinates":[29.106836319,40.9738082886],"type":"Point"}
}