{
  "type": "Feature",
  "properties": {
    "iso:country":"TR",
    "sg:address":"Hamidiye Mah.igde Sok. No:5",
    "sg:city":"Kagithane",
    "sg:classifiers":[
        {
            "category":"Shopping",
            "subcategory":"Clothing, Apparel, & Fashions",
            "type":"Retail Goods"
        }
    ],
    "sg:phone":"+90 212 295 8898",
    "sg:postcode":"34406",
    "sg:province":"Istanbul",
    "sg:tags":[
        "ready",
        "wear"
    ],
    "wof:name":"Ceren Tekstil Konfeksiyon San.tic.ltd.sti.",
    "wof:placetype":"venue"
},
  "geometry": {"coordinates":[28.9774513245,41.0924911499],"type":"Point"}
}