{
  "type": "Feature",
  "properties": {
    "addr:full":"629. Sk. No:79 Sirinyer Izmir 35380",
    "addr:housenumber":"79",
    "addr:postcode":"35380",
    "addr:street":"629 Sk. No",
    "iso:country":"TR",
    "sg:address":"629. Sk. No:79",
    "sg:city":"Sirinyer",
    "sg:classifiers":[
        {
            "category":"Manufacturing",
            "subcategory":"Glass & Minerals",
            "type":"Manufacturing & Wholesale Goods"
        }
    ],
    "sg:phone":"+90 232 253 5090",
    "sg:postcode":"35380",
    "sg:province":"Izmir",
    "sg:tags":[
        "glass-mirror"
    ],
    "wof:name":"?amkur Ltd. Sti.",
    "wof:placetype":"venue"
},
  "geometry": {"coordinates":[27.1390266418,38.3786964417],"type":"Point"}
}