{
  "type": "Feature",
  "properties": {
    "iso:country":"TR",
    "sg:address":"K?? Bah? Sk. No:23/4",
    "sg:city":"Osmanbey",
    "sg:classifiers":[
        {
            "category":"Shopping",
            "subcategory":"Clothing, Apparel, & Fashions",
            "type":"Retail Goods"
        }
    ],
    "sg:phone":"+90 212 247 9984",
    "sg:postcode":"63000",
    "sg:province":"Istanbul",
    "sg:tags":[
        "men",
        "wear"
    ],
    "wof:name":"Koray Kem. Erkek Aksesuar",
    "wof:placetype":"venue"
},
  "geometry": {"coordinates":[28.8346252441,41.0055236816],"type":"Point"}
}