{
  "type": "Feature",
  "properties": {
    "addr:full":"Agir Sanayi B?g. Tabakaneler Mev. Isikkent Balikesir 35070",
    "addr:postcode":"35070",
    "addr:street":"Balikesir",
    "iso:country":"TR",
    "sg:address":"Agir Sanayi B?g. Tabakaneler Mev.",
    "sg:city":"Isikkent",
    "sg:classifiers":[
        {
            "category":"Shopping",
            "subcategory":"Shoes",
            "type":"Retail Goods"
        }
    ],
    "sg:phone":"+90 266 241 1858",
    "sg:postcode":"35070",
    "sg:province":"Balikesir",
    "wof:name":"Istanbulluoglu Kosele Deri San.a.s",
    "wof:placetype":"venue"
},
  "geometry": {"coordinates":[27.883301,39.6521],"type":"Point"}
}