{
  "type": "Feature",
  "properties": {
    "iso:country":"TR",
    "sg:address":"1453 Sk.no:3/4 Alsancak",
    "sg:city":"Iskenderun",
    "sg:classifiers":[
        {
            "category":"Manufacturing",
            "subcategory":"Tools & Machinery",
            "type":"Manufacturing & Wholesale Goods"
        }
    ],
    "sg:phone":"+90 232 842 6445",
    "sg:postcode":"31200",
    "sg:province":"Izmir",
    "sg:tags":[
        "machine",
        "industry"
    ],
    "wof:name":"Turkuaz Makina Kimya San.ve Tic.ltd.sti.",
    "wof:placetype":"venue"
},
  "geometry": {"coordinates":[27.1415309906,38.4375267029],"type":"Point"}
}