{
  "type": "Feature",
  "properties": {
    "addr:full":"Molla Husrev Mah. Revani Celebi Sok. No.210 Vefa Istanbul 43020",
    "addr:housenumber":"no.210",
    "addr:postcode":"43020",
    "addr:street":"Husrev Mah. Revani Celebi Sok.;Istanbul",
    "iso:country":"TR",
    "sg:address":"Molla Husrev Mah. Revani Celebi Sok. No.210",
    "sg:city":"Vefa",
    "sg:classifiers":[
        {
            "category":"Arena",
            "subcategory":"Indoor Arena",
            "type":"Entertainment"
        }
    ],
    "sg:phone":"+90 212 514 0174",
    "sg:postcode":"43020",
    "sg:province":"Istanbul",
    "sg:tags":[
        "tent-canvas"
    ],
    "wof:name":"Onur Cadir Branda",
    "wof:placetype":"venue"
},
  "geometry": {"coordinates":[28.9861831665,41.0408554077],"type":"Point"}
}