{
  "type": "Feature",
  "properties": {
    "addr:full":"Istiklal Cad. Birsen Sok. Ozyasam Sit. A.blok D.23 Maltepe Istanbul 01000",
    "addr:housenumber":"ozyasam;d.23",
    "addr:postcode":"01000",
    "addr:street":"Istiklal Cad. Birsen Sok.;Maltepe Istanbul",
    "iso:country":"TR",
    "sg:address":"Istiklal Cad. Birsen Sok. Ozyasam Sit. A.blok D.23",
    "sg:city":"Maltepe",
    "sg:classifiers":[
        {
            "category":"Manufacturing",
            "subcategory":"Textiles",
            "type":"Manufacturing & Wholesale Goods"
        }
    ],
    "sg:phone":"+90 216 399 4413",
    "sg:postcode":"01000",
    "sg:province":"Istanbul",
    "sg:tags":[
        "product"
    ],
    "wof:name":"Kotteks Ltd.",
    "wof:placetype":"venue"
},
  "geometry": {"coordinates":[28.9759254456,41.0123786926],"type":"Point"}
}