{
  "type": "Feature",
  "properties": {
    "iso:country":"TR",
    "sg:address":"Dokumculer Sit. 3.sok. No:10 Organize San. Bolgesi",
    "sg:city":"Sincan",
    "sg:classifiers":[
        {
            "category":"Home & Garden",
            "subcategory":"Building Materials",
            "type":"Retail Goods"
        }
    ],
    "sg:phone":"+90 312267096162",
    "sg:postcode":"31900",
    "sg:province":"Ankara",
    "sg:tags":[
        "stone",
        "natural",
        "marble"
    ],
    "wof:name":"Mm Muhendisler Mermer San. Ve Tic. Ltd.sti.",
    "wof:placetype":"venue"
},
  "geometry": {"coordinates":[32.8604812622,39.9429283142],"type":"Point"}
}