{
  "type": "Feature",
  "properties": {
    "iso:country":"TR",
    "sg:address":"Sivas Yolu 8.km Kumarli Mevkii",
    "sg:city":"Kocasinan",
    "sg:classifiers":[
        {
            "category":"Utilities",
            "subcategory":"Electric",
            "type":"Services"
        }
    ],
    "sg:phone":"+90 352 241 0770",
    "sg:postcode":"38110",
    "sg:province":"Kayseri",
    "sg:tags":[
        "accumulator",
        "-",
        "batery"
    ],
    "wof:name":"Ak?san A.s",
    "wof:placetype":"venue"
},
  "geometry": {"coordinates":[35.528145,38.755348],"type":"Point"}
}