{
  "type": "Feature",
  "properties": {
    "addr:full":"Omeraga Mah. Sabri Erkmen Sok No:10 Kat.2 \u00dcmraniye Kocaeli 34785",
    "addr:housenumber":"no;kat.2",
    "addr:postcode":"34785",
    "addr:street":"Omeraga Mah. Sabri Erkmen Sok",
    "iso:country":"TR",
    "sg:address":"Omeraga Mah. Sabri Erkmen Sok No:10 Kat.2",
    "sg:city":"\u00dcmraniye",
    "sg:classifiers":[
        {
            "category":"Professional",
            "subcategory":"Detective & Security Services",
            "type":"Services"
        }
    ],
    "sg:phone":"+90 262 324 5575",
    "sg:postcode":"34785",
    "sg:province":"Kocaeli",
    "sg:tags":[
        "material"
    ],
    "wof:name":"Ekip G?venlik San.tic. Ltd.sti.",
    "wof:placetype":"venue"
},
  "geometry": {"coordinates":[29.881521,40.853271],"type":"Point"}
}