{
  "type": "Feature",
  "properties": {
    "addr:full":"Perpa Tic.merkezi A Blok Kat:5 No:424 Okmeydani Ikitelli/K\u00fc\u00e7\u00fck\u00e7ekmece Istanbul 34660",
    "addr:housenumber":"blok kat 5 no 424",
    "addr:postcode":"34660",
    "addr:street":"Okmeydani Ikitelli / Kuec\u0327Uekc\u0327Ekmece",
    "iso:country":"TR",
    "sg:address":"Perpa Tic.merkezi A Blok Kat:5 No:424 Okmeydani",
    "sg:city":"Ikitelli/K\u00fc\u00e7\u00fck\u00e7ekmece",
    "sg:orig_category":"Furniture Supplamentary",
    "sg:phone":"+90 212 222 0653",
    "sg:postcode":"34660",
    "sg:province":"Istanbul",
    "wof:name":"Sezgin Bronz San.tic.ltd.sti.",
    "wof:placetype":"venue"
},
  "geometry": {"coordinates":[29.0496292114,41.0075798035],"type":"Point"}
}