{
  "type": "Feature",
  "properties": {
    "iso:country":"TR",
    "sg:address":"60.sok. 97/c Emek",
    "sg:city":"Yenimahalle",
    "sg:classifiers":[
        {
            "category":"Banks & Credit Unions",
            "subcategory":"Investment Brokerage",
            "type":"Services"
        }
    ],
    "sg:phone":"+90 312 251 7485",
    "sg:postcode":"15030",
    "sg:province":"Ankara",
    "sg:tags":[
        "-",
        "export",
        "import"
    ],
    "wof:name":"Melis Ltd.ithalat Ve Ihracat",
    "wof:placetype":"venue"
},
  "geometry": {"coordinates":[32.8604812622,39.9429283142],"type":"Point"}
}