{
  "type": "Feature",
  "properties": {
    "addr:full":"Sivas Yolu 7 Km. Kumarli Yakutiye Kayseri 25200",
    "addr:housenumber":"7 km.",
    "addr:postcode":"25200",
    "addr:street":"Sivas Yolu;Kumarli Yakutiye",
    "iso:country":"TR",
    "sg:address":"Sivas Yolu 7 Km. Kumarli",
    "sg:city":"Yakutiye",
    "sg:classifiers":[
        {
            "category":"Home & Garden",
            "subcategory":"Household Appliances",
            "type":"Retail Goods"
        }
    ],
    "sg:phone":"+90 352 241 0798",
    "sg:postcode":"25200",
    "sg:province":"Kayseri",
    "sg:tags":[
        "kitchenware"
    ],
    "wof:name":"Erciyes Elekt. Ev Alet.",
    "wof:placetype":"venue"
},
  "geometry": {"coordinates":[35.4891357422,38.7225761414],"type":"Point"}
}