{
  "type": "Feature",
  "properties": {
    "iso:country":"TR",
    "sg:address":"Calislar Cad.genc Apt. No: 3",
    "sg:city":"Bahcelievler",
    "sg:classifiers":[
        {
            "category":"Utilities",
            "subcategory":"Electric",
            "type":"Services"
        }
    ],
    "sg:phone":"+90 212 555 6448",
    "sg:postcode":"01980",
    "sg:province":"Istanbul",
    "sg:tags":[
        "energy",
        "solar"
    ],
    "wof:name":"Prizma Gunes Enerji Sistemleri Ltd.sti.",
    "wof:placetype":"venue"
},
  "geometry": {"coordinates":[28.90983,41.003815],"type":"Point"}
}