{
  "type": "Feature",
  "properties": {
    "iso:country":"TR",
    "sg:address":"280. Sok.no:27/a",
    "sg:city":"Hatay-ucyol",
    "sg:classifiers":[
        {
            "category":"Professional",
            "subcategory":"Detective & Security Services",
            "type":"Services"
        }
    ],
    "sg:phone":"+90 232 262 6878",
    "sg:postcode":"35280",
    "sg:province":"Izmir",
    "sg:tags":[
        "material"
    ],
    "wof:name":"Aslan Elektronik",
    "wof:placetype":"venue"
},
  "geometry": {"coordinates":[27.116947,38.4072],"type":"Point"}
}