{
  "type": "Feature",
  "properties": {
    "addr:full":"Ikitelli Organize Sanayi B?gesi Galvano Teknik Sanayi Sitesi F Blok No:30 Ikitelli/K\u00fc\u00e7\u00fck\u00e7ekmece Istanbul 34670",
    "addr:housenumber":"?;blok no 30",
    "addr:postcode":"34670",
    "addr:street":"Organize Sanayi B",
    "iso:country":"TR",
    "sg:address":"Ikitelli Organize Sanayi B?gesi Galvano Teknik Sanayi Sitesi F Blok No:30",
    "sg:city":"Ikitelli/K\u00fc\u00e7\u00fck\u00e7ekmece",
    "sg:classifiers":[
        {
            "category":"Wholesale",
            "subcategory":"Metals & Minerals",
            "type":"Manufacturing & Wholesale Goods"
        }
    ],
    "sg:phone":"+90 212 549 2933",
    "sg:postcode":"34670",
    "sg:province":"Istanbul",
    "sg:tags":[
        "coating"
    ],
    "sg:website":"em-metal.com",
    "wof:name":"Em Metal San Ve Tic Ltd. Sti.",
    "wof:placetype":"venue"
},
  "geometry": {"coordinates":[28.9759254456,41.0123786926],"type":"Point"}
}