{
  "type": "Feature",
  "properties": {
    "iso:country":"TR",
    "sg:address":"5 Telsiz Mah. 109 Sok. No:39",
    "sg:city":"Zeytinburnu",
    "sg:classifiers":[
        {
            "category":"Shopping",
            "subcategory":"Clothing, Apparel, & Fashions",
            "type":"Retail Goods"
        }
    ],
    "sg:phone":"+90 212 558 2404",
    "sg:postcode":"41000",
    "sg:province":"Istanbul",
    "sg:tags":[
        "woman",
        "wear"
    ],
    "wof:name":"Seyle Tekstil",
    "wof:placetype":"venue"
},
  "geometry": {"coordinates":[28.9065227509,40.9990539551],"type":"Point"}
}