{
  "type": "Feature",
  "properties": {
    "addr:full":"Semsettin Gunaltay Cad.no:24/4 Bostanci 10 Sirinevler Istanbul",
    "addr:housenumber":"24 / 4;10",
    "addr:street":"Cad.No;Bostanci",
    "iso:country":"TR",
    "sg:address":"Semsettin Gunaltay Cad.no:24/4 Bostanci",
    "sg:city":"10 Sirinevler",
    "sg:orig_category":"Translation Servies",
    "sg:phone":"+90 216 384 7246",
    "sg:province":"Istanbul",
    "wof:name":"Mirora",
    "wof:placetype":"venue"
},
  "geometry": {"coordinates":[28.9861793518,41.040851593],"type":"Point"}
}