{
  "type": "Feature",
  "properties": {
    "addr:full":"Istoc 5. Ada No.31-33, Mahmutbey Istanbul 46600",
    "addr:housenumber":"5;no.31-33",
    "addr:postcode":"46600",
    "addr:street":"Istoc",
    "iso:country":"TR",
    "sg:address":"Istoc 5. Ada No.31-33,",
    "sg:city":"Mahmutbey",
    "sg:classifiers":[
        {
            "category":"Manufacturing",
            "subcategory":"Food",
            "type":"Manufacturing & Wholesale Goods"
        }
    ],
    "sg:phone":"+90 21265945216594",
    "sg:postcode":"46600",
    "sg:province":"Istanbul",
    "sg:tags":[
        "wholesaler"
    ],
    "wof:name":"Gidasan Gida Urunleri Paz., Ambalaj San. Ve Dis Tic.ltd.sti.",
    "wof:placetype":"venue"
},
  "geometry": {"coordinates":[28.9759254456,41.0123786926],"type":"Point"}
}