{
  "type": "Feature",
  "properties": {
    "addr:full":"19 Mayis San.sitesi Karadenis Bulv.no:26 Kutlukent 07100 Samsun",
    "addr:housenumber":"19;26",
    "addr:postcode":"07100",
    "addr:street":"Mayis San.Sitesi Karadenis Bulv.No",
    "iso:country":"TR",
    "sg:address":"19 Mayis San.sitesi Karadenis Bulv.no:26 Kutlukent",
    "sg:city":"07100",
    "sg:classifiers":[
        {
            "category":"Manufacturing",
            "subcategory":"Wood Products",
            "type":"Manufacturing & Wholesale Goods"
        }
    ],
    "sg:phone":"+90 362 266 9827",
    "sg:province":"Samsun",
    "sg:tags":[
        "forest"
    ],
    "wof:name":"Kaya Orman Urunleri",
    "wof:placetype":"venue"
},
  "geometry": {"coordinates":[36.4118118286,41.2170600891],"type":"Point"}
}