{
  "type": "Feature",
  "properties": {
    "addr:full":"Balmumcu Barbaros Bulvari No:127 Besiktas \u00dcmraniye Istanbul 81260",
    "addr:housenumber":"bulvari no 127",
    "addr:postcode":"81260",
    "addr:street":"Barbaros;Besiktas",
    "iso:country":"TR",
    "sg:address":"Balmumcu Barbaros Bulvari No:127 Besiktas",
    "sg:city":"\u00dcmraniye",
    "sg:classifiers":[
        {
            "category":"Farming",
            "subcategory":"Fish & Marine Products",
            "type":"Manufacturing & Wholesale Goods"
        }
    ],
    "sg:phone":"+90 212 211 3589",
    "sg:postcode":"81260",
    "sg:province":"Istanbul",
    "sg:tags":[
        "automotive"
    ],
    "wof:name":"Merbil Otomotiv Mam?l. Tic. San. A.s.",
    "wof:placetype":"venue"
},
  "geometry": {"coordinates":[29.0111885071,41.0614051819],"type":"Point"}
}