{
  "type": "Feature",
  "properties": {
    "addr:full":"Ankara Cd. Emirler Hani Sk. No:13 Sirkeci Hadimk? Istanbul",
    "addr:housenumber":"13;hadimk ?",
    "addr:street":"Hani Sk. No",
    "iso:country":"TR",
    "sg:address":"Ankara Cd. Emirler Hani Sk. No:13 Sirkeci",
    "sg:city":"Hadimk?",
    "sg:classifiers":[
        {
            "category":"Banks & Credit Unions",
            "subcategory":"Investment Brokerage",
            "type":"Services"
        }
    ],
    "sg:phone":"+90 212 513 7589",
    "sg:province":"Istanbul",
    "sg:tags":[
        "-",
        "export",
        "import"
    ],
    "wof:name":"Kolbasi I? Dis Tic. Ltd. Sti.",
    "wof:placetype":"venue"
},
  "geometry": {"coordinates":[28.9793300629,41.0136184692],"type":"Point"}
}