{
  "type": "Feature",
  "properties": {
    "addr:full":"Sariyer Merkez - Sariyer Ikitelli Istanbul 34306",
    "addr:postcode":"34306",
    "iso:country":"TR",
    "sg:address":"Sariyer Merkez - Sariyer",
    "sg:city":"Ikitelli",
    "sg:classifiers":[
        {
            "category":"Banks & Credit Unions",
            "subcategory":"Investment Brokerage",
            "type":"Services"
        }
    ],
    "sg:phone":"+90 212 242 6788",
    "sg:postcode":"34306",
    "sg:province":"Istanbul",
    "sg:tags":[
        "aid",
        "material",
        "first"
    ],
    "wof:name":"Sariyer Devlet Hastanesi",
    "wof:placetype":"venue"
},
  "geometry": {"coordinates":[29.0534057617,41.1704826355],"type":"Point"}
}