{
  "type": "Feature",
  "properties": {
    "iso:country":"TR",
    "sg:address":"Kuyubasi Kayisdagi Cad. No:133",
    "sg:city":"Feneryolu",
    "sg:classifiers":[
        {
            "category":"Home & Garden",
            "subcategory":"Household Appliances",
            "type":"Retail Goods"
        }
    ],
    "sg:phone":"+90 216 348 8319",
    "sg:postcode":"34724",
    "sg:province":"Istanbul",
    "sg:tags":[
        "conditioner",
        "air"
    ],
    "wof:name":"Birtes Sogutma Ltd.sti.",
    "wof:placetype":"venue"
},
  "geometry": {"coordinates":[29.0467185974,40.9827575684],"type":"Point"}
}