{
  "type": "Feature",
  "properties": {
    "iso:country":"TR",
    "sg:address":"Ipek Yolu Uzeri No:43/a I",
    "sg:city":"Yuksekova",
    "sg:classifiers":[
        {
            "category":"Food & Beverages",
            "subcategory":"Dairy",
            "type":"Retail Goods"
        }
    ],
    "sg:phone":"+90 438 351 4343",
    "sg:postcode":"30300",
    "sg:province":"Hakkari",
    "sg:tags":[
        "pruducts",
        "milk"
    ],
    "wof:name":"Baskin Kardesler Gida Sut Hay.san.tic.ltd.sti.",
    "wof:placetype":"venue"
},
  "geometry": {"coordinates":[43.739200592,37.5760993958],"type":"Point"}
}