{
  "type": "Feature",
  "properties": {
    "iso:country":"TR",
    "sg:address":"S.esref Bulvan 5/105 1371. Sokak Alkan Han",
    "sg:city":"Cankaya",
    "sg:classifiers":[
        {
            "category":"Freight",
            "type":"Transportation"
        }
    ],
    "sg:phone":"+90 2324259722425",
    "sg:postcode":"07080",
    "sg:province":"Izmir",
    "sg:tags":[
        "cargo",
        "air"
    ],
    "wof:name":"Austrian Airlines",
    "wof:placetype":"venue"
},
  "geometry": {"coordinates":[27.1296863556,38.4186973572],"type":"Point"}
}