{
  "type": "Feature",
  "properties": {
    "iso:country":"TR",
    "sg:address":"Toptan Manifaturacilar Sit.d Blk No 71",
    "sg:city":"Selcuklu",
    "sg:classifiers":[
        {
            "category":"Shopping",
            "subcategory":"Clothing, Apparel, & Fashions",
            "type":"Retail Goods"
        }
    ],
    "sg:phone":"+90 332 233 5959",
    "sg:postcode":"42060",
    "sg:province":"Konya",
    "sg:tags":[
        "ready",
        "wear"
    ],
    "wof:name":"Karababa Giyim San.tic.ltd.sti.",
    "wof:placetype":"venue"
},
  "geometry": {"coordinates":[32.4969596863,37.8920593262],"type":"Point"}
}