{
  "type": "Feature",
  "properties": {
    "addr:full":"Turistik Camlica Cd. Cigdem Sk. No:26 Usk?ar Salipazari Istanbul 80040",
    "addr:housenumber":"26",
    "addr:postcode":"?;istanbul 80040",
    "addr:street":"Cd. Cigdem Sk. No",
    "iso:country":"TR",
    "sg:address":"Turistik Camlica Cd. Cigdem Sk. No:26 Usk?ar",
    "sg:city":"Salipazari",
    "sg:classifiers":[
        {
            "category":"Building & Trades",
            "subcategory":"Construction",
            "type":"Services"
        }
    ],
    "sg:phone":"+90 216 443 6603",
    "sg:postcode":"80040",
    "sg:province":"Istanbul",
    "sg:tags":[
        "foundation"
    ],
    "wof:name":"Hakyol Egitim Yard. Dost. Vakfi",
    "wof:placetype":"venue"
},
  "geometry": {"coordinates":[28.9759254456,41.0123786926],"type":"Point"}
}