{
  "type": "Feature",
  "properties": {
    "iso:country":"TR",
    "sg:address":"Tulay Aktas Cad. No:1 Narlidere",
    "sg:city":"Besy?evler",
    "sg:classifiers":[
        {
            "category":"Personal",
            "subcategory":"Sauna",
            "type":"Services"
        }
    ],
    "sg:phone":"+90 232 234 3370",
    "sg:province":"Izmir",
    "sg:tags":[
        "pool"
    ],
    "wof:name":"Pekcan Havuz & Aritma",
    "wof:placetype":"venue"
},
  "geometry": {"coordinates":[27.003834,38.395905],"type":"Point"}
}