{
  "type": "Feature",
  "properties": {
    "iso:country":"TR",
    "sg:address":"Semerciler Mah.yuvam Sok.no:26/5",
    "sg:city":"Kavaklidere",
    "sg:classifiers":[
        {
            "category":"Mining & Drilling",
            "type":"Manufacturing & Wholesale Goods"
        }
    ],
    "sg:phone":"+90 264 281 3331",
    "sg:postcode":"06660",
    "sg:province":"Sakarya",
    "sg:tags":[
        "industry",
        "mine"
    ],
    "wof:name":"Ay Ticaret Ithalat Ihracat",
    "wof:placetype":"venue"
},
  "geometry": {"coordinates":[30.3982582092,40.7770347595],"type":"Point"}
}