{
  "type": "Feature",
  "properties": {
    "addr:full":"Pinarcik Mah. Istiklal Cad.no: 58 Serinhisar Denizli 20430",
    "addr:housenumber":"58",
    "addr:postcode":"20430",
    "addr:street":"Pinarcik Mah. Istiklal Cad.No",
    "iso:country":"TR",
    "sg:address":"Pinarcik Mah. Istiklal Cad.no: 58",
    "sg:city":"Serinhisar",
    "sg:orig_category":"Dryfood-dried Nuts",
    "sg:phone":"+90 258 591 3154",
    "sg:postcode":"20430",
    "sg:province":"Denizli",
    "wof:name":"Uzunoglu Gida Ve Kuruyemis Ur.nak.ltd.sti.",
    "wof:placetype":"venue"
},
  "geometry": {"coordinates":[29.0788803101,37.7851867676],"type":"Point"}
}