{
  "type": "Feature",
  "properties": {
    "addr:full":"117 Sok. No:7 Y Dudullu Istanbul",
    "addr:housenumber":"no;y",
    "addr:street":"117 Sok.",
    "iso:country":"TR",
    "sg:address":"117 Sok. No:7",
    "sg:city":"Y Dudullu",
    "sg:classifiers":[
        {
            "category":"Manufacturing",
            "subcategory":"Building Materials",
            "type":"Manufacturing & Wholesale Goods"
        }
    ],
    "sg:phone":"+90 216 365 6927",
    "sg:province":"Istanbul",
    "sg:tags":[
        "lifts-elevators"
    ],
    "wof:name":"Hursan Asans? San Tic Ltd Sti",
    "wof:placetype":"venue"
},
  "geometry": {"coordinates":[28.9028167725,40.9994049072],"type":"Point"}
}