{
  "type": "Feature",
  "properties": {
    "addr:full":"Rumeli Cad.zafer Sok.48/601 Nisantasi Tuzla Istanbul 01900",
    "addr:housenumber":"601",
    "addr:postcode":"01900",
    "addr:street":"Nisantasi",
    "iso:country":"TR",
    "sg:address":"Rumeli Cad.zafer Sok.48/601 Nisantasi",
    "sg:city":"Tuzla",
    "sg:classifiers":[
        {
            "category":"Social Services",
            "subcategory":"Retirement Home",
            "type":"Services"
        }
    ],
    "sg:phone":"+90 212 240 6646",
    "sg:postcode":"01900",
    "sg:province":"Istanbul",
    "sg:tags":[
        "door"
    ],
    "wof:name":"Mana Iletisim Ltd.",
    "wof:placetype":"venue"
},
  "geometry": {"coordinates":[28.9891300201,41.0509033203],"type":"Point"}
}