{
  "type": "Feature",
  "properties": {
    "iso:country":"TR",
    "sg:address":"Eski Sehir Yolu Uzeri 3.km.",
    "sg:city":"Seyhan",
    "sg:classifiers":[
        {
            "category":"Manufacturing",
            "subcategory":"Food",
            "type":"Manufacturing & Wholesale Goods"
        }
    ],
    "sg:phone":"+90 274 224 7105",
    "sg:postcode":"01180",
    "sg:province":"K?tahya",
    "sg:tags":[
        "wholesaler"
    ],
    "wof:name":"Ozcinar Gida San. A.s.",
    "wof:placetype":"venue"
},
  "geometry": {"coordinates":[35.3243713379,36.9999885559],"type":"Point"}
}