{
  "type": "Feature",
  "properties": {
    "addr:full":"Soguksu Cad. No:25 Hamidiye Mah. 80360 Kagithane Istanbul Ikitelli/K\u00fc\u00e7\u00fck\u00e7ekmece Istanbul 34670",
    "addr:housenumber":"25",
    "addr:postcode":"80360;34670",
    "addr:street":"Soguksu Cad. No",
    "iso:country":"TR",
    "sg:address":"Soguksu Cad. No:25 Hamidiye Mah. 80360 Kagithane Istanbul",
    "sg:city":"Ikitelli/K\u00fc\u00e7\u00fck\u00e7ekmece",
    "sg:classifiers":[
        {
            "category":"Shopping",
            "subcategory":"Crafts & Fabrics",
            "type":"Retail Goods"
        }
    ],
    "sg:phone":"+90 212 321 0810",
    "sg:postcode":"34670",
    "sg:province":"Istanbul",
    "wof:name":"Aksoy Tekstil Orme Dok. Konf. San.",
    "wof:placetype":"venue"
},
  "geometry": {"coordinates":[28.9767341614,41.0945205688],"type":"Point"}
}