{
  "type": "Feature",
  "properties": {
    "addr:full":"Kursunlu Yolu 100.metre Engurukcu Koyu Gemlik Yenidogan Bursa 81270",
    "addr:housenumber":"100.metre;koyu gemlik",
    "addr:postcode":"81270",
    "addr:street":"Kursunlu Yolu;Bursa",
    "iso:country":"TR",
    "sg:address":"Kursunlu Yolu 100.metre Engurukcu Koyu Gemlik",
    "sg:city":"Yenidogan",
    "sg:orig_category":"Furniture Supplamentary",
    "sg:phone":"+90 224 524 7140",
    "sg:postcode":"81270",
    "sg:province":"Bursa",
    "wof:name":"Demircioglu Otomotiv",
    "wof:placetype":"venue"
},
  "geometry": {"coordinates":[29.0580043793,40.1947555542],"type":"Point"}
}