{
  "type": "Feature",
  "properties": {
    "iso:country":"TR",
    "sg:address":"Adnan Menderes Bulvari No:52 Cine",
    "sg:city":"Merkez",
    "sg:classifiers":[
        {
            "category":"Mining & Drilling",
            "type":"Manufacturing & Wholesale Goods"
        }
    ],
    "sg:phone":"+90 256 711 6215",
    "sg:province":"Aydin",
    "sg:tags":[
        "industry",
        "mine"
    ],
    "wof:name":"Ocaklar Madencilik Ins. Nak. Ltd.sti.",
    "wof:placetype":"venue"
},
  "geometry": {"coordinates":[27.8373908997,37.834487915],"type":"Point"}
}