{
  "type": "Feature",
  "properties": {
    "addr:full":"Nispetiye Cd. No:14 Zincirlikuyu B.pasa Istanbul 34440",
    "addr:housenumber":"no 14",
    "addr:postcode":"34440",
    "addr:street":"Nispetiye Cd.",
    "iso:country":"TR",
    "sg:address":"Nispetiye Cd. No:14 Zincirlikuyu",
    "sg:city":"B.pasa",
    "sg:classifiers":[
        {
            "category":"Building & Trades",
            "subcategory":"Plumbing",
            "type":"Services"
        }
    ],
    "sg:phone":"+90 212 270 0104",
    "sg:postcode":"34440",
    "sg:province":"Istanbul",
    "wof:name":"Valf San. A.s.",
    "wof:placetype":"venue"
},
  "geometry": {"coordinates":[29.0093860626,41.0741348267],"type":"Point"}
}