{
  "type": "Feature",
  "properties": {
    "addr:full":"Milli Egemenlik Bulvari No:69 Sehitkamil Gaziantep 27000",
    "addr:housenumber":"no 69",
    "addr:postcode":"27000",
    "addr:street":"Egemenlik Bulvari;Sehitkamil Gaziantep",
    "iso:country":"TR",
    "sg:address":"Milli Egemenlik Bulvari No:69",
    "sg:city":"Sehitkamil",
    "sg:classifiers":[
        {
            "category":"Home & Garden",
            "subcategory":"Building Materials",
            "type":"Retail Goods"
        }
    ],
    "sg:phone":"+90 342 339 2115",
    "sg:postcode":"27000",
    "sg:province":"Gaziantep",
    "sg:tags":[
        "insulation"
    ],
    "wof:name":"Odak Insaat Ticaret Ltd. Sti.",
    "wof:placetype":"venue"
},
  "geometry": {"coordinates":[37.3560600281,37.0741844177],"type":"Point"}
}