{
  "type": "Feature",
  "properties": {
    "iso:country":"TR",
    "sg:address":"Balmumcu Barbaros Bulvari No.48/2-3",
    "sg:city":"Besiktas",
    "sg:classifiers":[
        {
            "category":"Marine",
            "type":"Transportation"
        }
    ],
    "sg:phone":"+90 212 275 2956",
    "sg:postcode":"75200",
    "sg:province":"Istanbul",
    "sg:tags":[
        "shipowner"
    ],
    "wof:name":"Bigtas Ihr. A.s. .",
    "wof:placetype":"venue"
},
  "geometry": {"coordinates":[29.011425,41.061371],"type":"Point"}
}