{
  "type": "Feature",
  "properties": {
    "iso:country":"TR",
    "sg:address":"Valikonagi Cad.no:86 - Sisli",
    "sg:city":"Merkez",
    "sg:classifiers":[
        {
            "category":"Health Services",
            "subcategory":"Medical Lab",
            "type":"Services"
        }
    ],
    "sg:phone":"+90 212 247 0042",
    "sg:province":"Istanbul",
    "wof:name":"Dr.pakize Tarzi Lab.-nisantasi",
    "wof:placetype":"venue"
},
  "geometry": {"coordinates":[28.9923667908,41.0526428223],"type":"Point"}
}