{
  "type": "Feature",
  "properties": {
    "iso:country":"TR",
    "sg:address":"Izzetpasa Mah. Ayazma Sok. Ozturk Apt. No:7/2 Sisli",
    "sg:city":"42200",
    "sg:classifiers":[
        {
            "category":"Banks & Credit Unions",
            "subcategory":"Investment Brokerage",
            "type":"Services"
        }
    ],
    "sg:phone":"+90 212 225 4272",
    "sg:province":"Istanbul",
    "sg:tags":[
        "course",
        "language"
    ],
    "wof:name":"Set Yurtdisi Danismanlik Ve Egitim Hizmetleri",
    "wof:placetype":"venue"
},
  "geometry": {"coordinates":[28.987903595,41.0586929321],"type":"Point"}
}