{
  "type": "Feature",
  "properties": {
    "addr:full":"Sanayi Mah. Sancakli Cad. Carsu Sk. No:4 Gungoren Istanbul 33630",
    "addr:postcode":"33630",
    "addr:street":"Sanayi Mah. Sancakli Cad. Carsu Sk. No 4 Gungoren",
    "iso:country":"TR",
    "sg:address":"Sanayi Mah. Sancakli Cad. Carsu Sk. No:4",
    "sg:city":"Gungoren",
    "sg:classifiers":[
        {
            "category":"Shopping",
            "subcategory":"Clothing, Apparel, & Fashions",
            "type":"Retail Goods"
        }
    ],
    "sg:phone":"+90 212 509 9485",
    "sg:postcode":"33630",
    "sg:province":"Istanbul",
    "sg:tags":[
        "woman",
        "wear"
    ],
    "wof:name":"Piramit Esarp .",
    "wof:placetype":"venue"
},
  "geometry": {"coordinates":[28.9759254456,41.0123786926],"type":"Point"}
}