{
  "type": "Feature",
  "properties": {
    "iso:country":"TR",
    "sg:address":"Ebe Kizi Sk. No:14/b",
    "sg:city":"Osmanbey",
    "sg:classifiers":[
        {
            "category":"Shopping",
            "subcategory":"Clothing, Apparel, & Fashions",
            "type":"Retail Goods"
        }
    ],
    "sg:phone":"+90 212230891783533",
    "sg:postcode":"63000",
    "sg:province":"Istanbul",
    "sg:tags":[
        "men",
        "wear"
    ],
    "wof:name":"Depar Sport",
    "wof:placetype":"venue"
},
  "geometry": {"coordinates":[28.9899692535,41.0561141968],"type":"Point"}
}