{
  "type": "Feature",
  "properties": {
    "iso:country":"TR",
    "sg:address":"Tophanelioglu Cad. No.30",
    "sg:city":"\u00dcsk\u00fcdar",
    "sg:classifiers":[
        {
            "category":"Farming",
            "subcategory":"Farm",
            "type":"Manufacturing & Wholesale Goods"
        }
    ],
    "sg:phone":"+90 216 342 5510",
    "sg:postcode":"34672",
    "sg:province":"Istanbul",
    "sg:tags":[
        "agricultural",
        "product"
    ],
    "wof:name":"Cargill Tarim A.s.",
    "wof:placetype":"venue"
},
  "geometry": {"coordinates":[29.0457077026,41.0204696655],"type":"Point"}
}