{
  "type": "Feature",
  "properties": {
    "addr:full":"Organize San. Bolgesi 7.yol No:35 Yukari Dudullu Elazig 34776",
    "addr:housenumber":"no 35",
    "addr:postcode":"34776",
    "addr:street":"Organize;Yukari Dudullu Elazig",
    "iso:country":"TR",
    "sg:address":"Organize San. Bolgesi 7.yol No:35",
    "sg:city":"Yukari Dudullu",
    "sg:classifiers":[
        {
            "category":"Shopping",
            "subcategory":"Computers & Home Electronics",
            "type":"Retail Goods"
        }
    ],
    "sg:phone":"+90 424 255 5252",
    "sg:postcode":"34776",
    "sg:province":"Elazig",
    "sg:tags":[
        "product",
        "electric-electronic"
    ],
    "wof:name":"Emsas Elektrik Motorlari Ve Pompa",
    "wof:placetype":"venue"
},
  "geometry": {"coordinates":[39.2357254028,38.6678085327],"type":"Point"}
}