{
  "type": "Feature",
  "properties": {
    "iso:country":"TR",
    "sg:address":"Unkapani Cd. No:33",
    "sg:city":"Unkapani",
    "sg:classifiers":[
        {
            "category":"Manufacturing",
            "subcategory":"Textiles",
            "type":"Manufacturing & Wholesale Goods"
        }
    ],
    "sg:phone":"+90 212 520 9894",
    "sg:postcode":"55020",
    "sg:province":"Istanbul",
    "sg:tags":[
        "cloth",
        "worker"
    ],
    "wof:name":"Koparan Teks. San. Tic. Ltd. Sti.",
    "wof:placetype":"venue"
},
  "geometry": {"coordinates":[28.9613170624,41.0215377808],"type":"Point"}
}