{
  "type": "Feature",
  "properties": {
    "iso:country":"TR",
    "sg:address":"Astim San Sitesi Havaalani Mevkii 3. Sok. No:12",
    "sg:city":"\u00dcmraniye",
    "sg:classifiers":[
        {
            "category":"Wholesale",
            "subcategory":"Auto Parts",
            "type":"Manufacturing & Wholesale Goods"
        }
    ],
    "sg:phone":"+90 256 225 5713",
    "sg:province":"Aydin",
    "sg:tags":[
        "spare"
    ],
    "wof:name":"Ok Kardesler",
    "wof:placetype":"venue"
},
  "geometry": {"coordinates":[27.8324394226,37.8409690857],"type":"Point"}
}