{
  "type": "Feature",
  "properties": {
    "iso:country":"TR",
    "sg:address":"E. Edirne Asf. No:46/48 G.o.pasa",
    "sg:city":"B.cekmece",
    "sg:classifiers":[
        {
            "category":"Home & Garden",
            "subcategory":"Kitchen Supply",
            "type":"Retail Goods"
        }
    ],
    "sg:phone":"+90 212 563 4710",
    "sg:province":"Istanbul",
    "sg:tags":[
        "steel",
        "utensil"
    ],
    "wof:name":"Ta? Madeni Esya Mak. San. A.s.",
    "wof:placetype":"venue"
},
  "geometry": {"coordinates":[28.901011,41.063763],"type":"Point"}
}