{
  "type": "Feature",
  "properties": {
    "iso:country":"TR",
    "sg:address":"Selanik Caddesi No:41/3 Kizilay",
    "sg:city":"G??suyu / Taksim",
    "sg:classifiers":[
        {
            "category":"Organizations",
            "subcategory":"Professional Association",
            "type":"Services"
        }
    ],
    "sg:phone":"+90 312 418 0059",
    "sg:postcode":"34439",
    "sg:province":"Ankara",
    "sg:tags":[
        "fair"
    ],
    "wof:name":"Imbat Fuarcilik A.s.",
    "wof:placetype":"venue"
},
  "geometry": {"coordinates":[32.8551483154,39.9221878052],"type":"Point"}
}