{
  "type": "Feature",
  "properties": {
    "addr:full":"Sirinyali Mah.sinanoglu Cad. 1515.sok. Aysel Koseler Apt. No: 14/3 Nazilli Antalya 65600",
    "addr:housenumber":"1515.sok",
    "addr:postcode":"65600",
    "addr:street":"Mah.Sinanoglu Cad.;Nazilli",
    "iso:country":"TR",
    "sg:address":"Sirinyali Mah.sinanoglu Cad. 1515.sok. Aysel Koseler Apt. No: 14/3",
    "sg:city":"Nazilli",
    "sg:classifiers":[
        {
            "category":"Manufacturing",
            "subcategory":"Food",
            "type":"Manufacturing & Wholesale Goods"
        }
    ],
    "sg:phone":"+90 242 316 4526",
    "sg:postcode":"65600",
    "sg:province":"Antalya",
    "sg:tags":[
        "wholesaler"
    ],
    "wof:name":"Mag Gida Pazarlama",
    "wof:placetype":"venue"
},
  "geometry": {"coordinates":[30.7031345367,36.8875045776],"type":"Point"}
}