{
  "type": "Feature",
  "properties": {
    "iso:country":"TR",
    "sg:address":"Kina Sok. No:78/a",
    "sg:city":"Sapanca",
    "sg:classifiers":[
        {
            "category":"Manufacturing",
            "subcategory":"Wood Products",
            "type":"Manufacturing & Wholesale Goods"
        }
    ],
    "sg:phone":"+90 312 348 4091",
    "sg:postcode":"54600",
    "sg:province":"Ankara",
    "sg:tags":[
        "forest"
    ],
    "wof:name":"Yildiz Orman Urunleri",
    "wof:placetype":"venue"
},
  "geometry": {"coordinates":[32.892036438,39.9647521973],"type":"Point"}
}