{
  "type": "Feature",
  "properties": {
    "iso:country":"TR",
    "sg:address":"Egitim Mah.muratpasa Cad.no:77/2 G?tepe",
    "sg:city":"07100",
    "sg:orig_category":"Scavening Services",
    "sg:phone":"+90 216 330 4048",
    "sg:province":"Istanbul",
    "wof:name":"Tuana Temizlik Hizmetleri",
    "wof:placetype":"venue"
},
  "geometry": {"coordinates":[28.975925,41.012379],"type":"Point"}
}