{
  "type": "Feature",
  "properties": {
    "iso:country":"TR",
    "sg:address":"Kurtulus Mah. Annac Sk. 3/c",
    "sg:city":"Kanlica",
    "sg:classifiers":[
        {
            "category":"Manufacturing",
            "subcategory":"Textiles",
            "type":"Manufacturing & Wholesale Goods"
        }
    ],
    "sg:phone":"+90 276 212 2836",
    "sg:postcode":"18800",
    "sg:province":"Usak",
    "sg:tags":[
        "product"
    ],
    "wof:name":"Acarturk Reklam Tekstil",
    "wof:placetype":"venue"
},
  "geometry": {"coordinates":[29.406211853,38.6755714417],"type":"Point"}
}