{
  "type": "Feature",
  "properties": {
    "addr:full":"2.organize San. Bolgesi Baspinar Topkapi Gaziantep 34020",
    "addr:postcode":"2.organize;34020",
    "iso:country":"TR",
    "sg:address":"2.organize San. Bolgesi Baspinar",
    "sg:city":"Topkapi",
    "sg:classifiers":[
        {
            "category":"Shopping",
            "subcategory":"Stationery & Office Supplies",
            "type":"Retail Goods"
        }
    ],
    "sg:phone":"+90 34233726003428",
    "sg:postcode":"34020",
    "sg:province":"Gaziantep",
    "sg:tags":[
        "paper"
    ],
    "wof:name":"Asten Oluklu Mukavva San.tic. A.s.",
    "wof:placetype":"venue"
},
  "geometry": {"coordinates":[37.3761024475,37.0629463196],"type":"Point"}
}