{
  "type": "Feature",
  "properties": {
    "addr:full":"Turan Gunes Bulvari 88.sok.no.1/8 Yildizevler- Cankaya Ankara 07080",
    "addr:housenumber":"88.sok.no.1 / 8",
    "addr:postcode":"07080",
    "addr:street":"Gunes Bulvari",
    "iso:country":"TR",
    "sg:address":"Turan Gunes Bulvari 88.sok.no.1/8 Yildizevler-",
    "sg:city":"Cankaya",
    "sg:classifiers":[
        {
            "category":"Building & Trades",
            "subcategory":"Landscaping Services",
            "type":"Services"
        }
    ],
    "sg:phone":"+90 312 442 0992",
    "sg:postcode":"07080",
    "sg:province":"Ankara",
    "sg:tags":[
        "landscape"
    ],
    "wof:name":"Damla Peyzaj Tasarim Proje Uygulama San.tic.ltd.sti.",
    "wof:placetype":"venue"
},
  "geometry": {"coordinates":[32.8605613708,39.8733634949],"type":"Point"}
}