{
  "type": "Feature",
  "properties": {
    "addr:full":"Eski Gemlik Yolu Ege Sok. No:30 Kartal Bursa 46000",
    "addr:housenumber":"no 30",
    "addr:postcode":"46000",
    "addr:street":"Eski Gemlik Yolu Ege Sok.;Kartal Bursa",
    "iso:country":"TR",
    "sg:address":"Eski Gemlik Yolu Ege Sok. No:30",
    "sg:city":"Kartal",
    "sg:classifiers":[
        {
            "category":"Farming",
            "subcategory":"Fish & Marine Products",
            "type":"Manufacturing & Wholesale Goods"
        }
    ],
    "sg:phone":"+90 224 253 0519",
    "sg:postcode":"46000",
    "sg:province":"Bursa",
    "sg:tags":[
        "automotive"
    ],
    "wof:name":"Oztac Karoser Otomotiv San.tic.a.s.",
    "wof:placetype":"venue"
},
  "geometry": {"coordinates":[29.0580043793,40.1947555542],"type":"Point"}
}