{
  "type": "Feature",
  "properties": {
    "addr:full":"Havaalani Karsisi 07100 Antalya",
    "addr:postcode":"07100",
    "iso:country":"TR",
    "sg:address":"Havaalani Karsisi",
    "sg:city":"07100",
    "sg:classifiers":[
        {
            "category":"Wholesale",
            "subcategory":"Auto Parts",
            "type":"Manufacturing & Wholesale Goods"
        }
    ],
    "sg:phone":"+90 242 340 2200",
    "sg:province":"Antalya",
    "sg:tags":[
        "spare"
    ],
    "wof:name":"G?noto A.s. (tofas-fiat-otoyol-iveco)",
    "wof:placetype":"venue"
},
  "geometry": {"coordinates":[30.6798324585,36.928150177],"type":"Point"}
}