{
  "type": "Feature",
  "properties": {
    "addr:full":"Cavusoglu M. Secenler Sk. No: 17 Kartal Melikgazi Istanbul 38070",
    "addr:housenumber":"17",
    "addr:postcode":"38070",
    "addr:street":"Secenler Sk. No",
    "iso:country":"TR",
    "sg:address":"Cavusoglu M. Secenler Sk. No: 17 Kartal",
    "sg:city":"Melikgazi",
    "sg:classifiers":[
        {
            "category":"Manufacturing",
            "subcategory":"Metals",
            "type":"Manufacturing & Wholesale Goods"
        }
    ],
    "sg:phone":"+90 216 387 3154",
    "sg:postcode":"38070",
    "sg:province":"Istanbul",
    "sg:tags":[
        "aluminium",
        "industry"
    ],
    "wof:name":"Promio Aluminyum San. Ltd.sti.",
    "wof:placetype":"venue"
},
  "geometry": {"coordinates":[29.2101211548,40.8991203308],"type":"Point"}
}