{
  "type": "Feature",
  "properties": {
    "iso:country":"TR",
    "sg:address":"Yazanlar Sk. No:7/2 A.ayranci",
    "sg:city":"Sariyer",
    "sg:classifiers":[
        {
            "category":"Mining & Drilling",
            "type":"Manufacturing & Wholesale Goods"
        }
    ],
    "sg:phone":"+90 312 310 7186",
    "sg:postcode":"33740",
    "sg:province":"Ankara",
    "sg:tags":[
        "industry",
        "mine"
    ],
    "wof:name":"?zmutlu Madencilik Insaat Tic. A.s.",
    "wof:placetype":"venue"
},
  "geometry": {"coordinates":[32.855178833,39.9017562866],"type":"Point"}
}