{
  "type": "Feature",
  "properties": {
    "addr:full":"Atat?k Bulvari Bulvar Ishani Kat:1 Daire:19/20 Adapazari Sakarya 54030",
    "addr:housenumber":"kat 1;19 / 20",
    "addr:postcode":"54030",
    "addr:street":"K Bulvari Bulvar Ishani;Daire;Adapazari Sakarya",
    "iso:country":"TR",
    "sg:address":"Atat?k Bulvari Bulvar Ishani Kat:1 Daire:19/20",
    "sg:city":"Adapazari",
    "sg:classifiers":[
        {
            "category":"Professional",
            "subcategory":"Detective & Security Services",
            "type":"Services"
        }
    ],
    "sg:phone":"+90 264 281 7193",
    "sg:postcode":"54030",
    "sg:province":"Sakarya",
    "sg:tags":[
        "private"
    ],
    "wof:name":"Bir ?zel G?venlik Hizmetleri A.s.",
    "wof:placetype":"venue"
},
  "geometry": {"coordinates":[30.3082332611,40.7416114807],"type":"Point"}
}