{
  "type": "Feature",
  "properties": {
    "iso:country":"TR",
    "sg:address":"Kiziltoprak,ihlamur ?ikmazi No1/2",
    "sg:city":"Kad\u0131k\u00f6y",
    "sg:classifiers":[
        {
            "category":"Freight",
            "type":"Transportation"
        }
    ],
    "sg:phone":"+90 216 348 1312",
    "sg:postcode":"34990",
    "sg:province":"Istanbul",
    "sg:tags":[
        "agent",
        "shipping",
        "broker"
    ],
    "wof:name":"Ni-mar Ul.denizcilik Ltd.sti.",
    "wof:placetype":"venue"
},
  "geometry": {"coordinates":[29.018038,41.008312],"type":"Point"}
}