{
  "type": "Feature",
  "properties": {
    "addr:full":"Perpa Tic.merk. A Blok Kat:5 No:283 Okmeydani/sisli Istanbul",
    "addr:housenumber":"blok kat 5 no 283",
    "iso:country":"TR",
    "sg:address":"Perpa Tic.merk. A Blok Kat:5 No:283",
    "sg:city":"Okmeydani/sisli",
    "sg:classifiers":[
        {
            "category":"Shopping",
            "subcategory":"Crafts & Fabrics",
            "type":"Retail Goods"
        }
    ],
    "sg:phone":"+90 212 320 9150",
    "sg:province":"Istanbul",
    "sg:tags":[
        "textile",
        "-leather",
        "exporter"
    ],
    "wof:name":"Market Tic. Ltd. Sti.",
    "wof:placetype":"venue"
},
  "geometry": {"coordinates":[28.9861831665,41.0408554077],"type":"Point"}
}