{
  "type": "Feature",
  "properties": {
    "addr:full":"Cami Cedit Mah. Yeni Pazar Sok. No:14 Kepsut Balikesir 10660",
    "addr:housenumber":"no 14",
    "addr:postcode":"10660",
    "addr:street":"Cedit Mah. Yeni Pazar Sok.;Balikesir",
    "iso:country":"TR",
    "sg:address":"Cami Cedit Mah. Yeni Pazar Sok. No:14",
    "sg:city":"Kepsut",
    "sg:classifiers":[
        {
            "category":"Farming",
            "subcategory":"Farm & Veterinary Services",
            "type":"Manufacturing & Wholesale Goods"
        }
    ],
    "sg:phone":"+90 26657614305",
    "sg:postcode":"10660",
    "sg:province":"Balikesir",
    "sg:tags":[
        "veterinarian"
    ],
    "wof:name":"Salih Gurbuz",
    "wof:placetype":"venue"
},
  "geometry": {"coordinates":[27.8833007812,39.6520996094],"type":"Point"}
}