{
  "type": "Feature",
  "properties": {
    "addr:full":"Birlik San. Sit. 1. Cd. No:6 B.?ekmece Ulus Istanbul 01940",
    "addr:housenumber":"1;no 6 b. ?",
    "addr:postcode":"01940",
    "addr:street":"Cd.;Ekmece",
    "iso:country":"TR",
    "sg:address":"Birlik San. Sit. 1. Cd. No:6 B.?ekmece",
    "sg:city":"Ulus",
    "sg:classifiers":[
        {
            "category":"Wholesale",
            "subcategory":"Machinery & Supplies",
            "type":"Manufacturing & Wholesale Goods"
        }
    ],
    "sg:phone":"+90 212 875 2954",
    "sg:postcode":"01940",
    "sg:province":"Istanbul",
    "sg:tags":[
        "bearing",
        "ball"
    ],
    "wof:name":"Yavuz Rulman Otomotiv San. Rulmanlari",
    "wof:placetype":"venue"
},
  "geometry": {"coordinates":[28.975925,41.012379],"type":"Point"}
}