{
  "type": "Feature",
  "properties": {
    "addr:full":"Altintas Mahallesi 159 Sk No:10/2 Nazilli Aydin 65600",
    "addr:housenumber":"159;no 10 / 2",
    "addr:postcode":"65600",
    "addr:street":"Altintas Mahallesi;Nazilli Aydin",
    "iso:country":"TR",
    "sg:address":"Altintas Mahallesi 159 Sk No:10/2",
    "sg:city":"Nazilli",
    "sg:classifiers":[
        {
            "category":"Home & Garden",
            "subcategory":"Building Materials",
            "type":"Retail Goods"
        }
    ],
    "sg:phone":"+90 256 313 7311",
    "sg:postcode":"65600",
    "sg:province":"Aydin",
    "sg:tags":[
        "stone",
        "natural",
        "marble"
    ],
    "wof:name":"Ar Tun Tur Taaahh?t Insaat Mermer Ve Granit Isletmeleri",
    "wof:placetype":"venue"
},
  "geometry": {"coordinates":[27.8324394226,37.8409690857],"type":"Point"}
}