{
  "type": "Feature",
  "properties": {
    "addr:full":"3. Organize San. B?. Celal Dogan Bul. Baspinar Gaziantep 07800",
    "addr:housenumber":"3;?",
    "addr:postcode":"07800",
    "addr:street":"Organize San. B;Celal Dogan Bul. Baspinar",
    "iso:country":"TR",
    "sg:address":"3. Organize San. B?. Celal Dogan Bul.",
    "sg:city":"Baspinar",
    "sg:classifiers":[
        {
            "category":"Shopping",
            "subcategory":"Crafts & Fabrics",
            "type":"Retail Goods"
        }
    ],
    "sg:phone":"+90 34233793306",
    "sg:postcode":"07800",
    "sg:province":"Gaziantep",
    "sg:tags":[
        "yarn"
    ],
    "wof:name":"?zsoy ?rg? Ve Iplik San. Tic. Ltd.",
    "wof:placetype":"venue"
},
  "geometry": {"coordinates":[37.3761024475,37.0629463196],"type":"Point"}
}