{
  "type": "Feature",
  "properties": {
    "addr:full":"Cumhuriyet Cad 22-24, Elmadag, 80200 Istanbul Sirkeci Istanbul 34112",
    "addr:housenumber":"22-24",
    "addr:postcode":"80200;34112",
    "addr:street":"Cumhuriyet Cad",
    "iso:country":"TR",
    "sg:address":"Cumhuriyet Cad 22-24, Elmadag, 80200 Istanbul",
    "sg:city":"Sirkeci",
    "sg:classifiers":[
        {
            "category":"Banks & Credit Unions",
            "subcategory":"Bank",
            "type":"Services"
        }
    ],
    "sg:phone":"+90 2123156500729",
    "sg:postcode":"34112",
    "sg:province":"Istanbul",
    "sg:website":"http://www.abank.com.tr",
    "wof:name":"Alternatifbank As",
    "wof:placetype":"venue"
},
  "geometry": {"coordinates":[29.183216,40.905846],"type":"Point"}
}