{
  "type": "Feature",
  "properties": {
    "iso:country":"TR",
    "sg:address":"Fevzipasa Mh. 939/54. Sk. No:10",
    "sg:city":"?aycuma",
    "sg:classifiers":[
        {
            "category":"Manufacturing",
            "subcategory":"Glass & Minerals",
            "type":"Manufacturing & Wholesale Goods"
        }
    ],
    "sg:phone":"+90 322 428 0681",
    "sg:postcode":"67900",
    "sg:province":"Adana",
    "sg:tags":[
        "glass-mirror"
    ],
    "wof:name":"Camkiran Cam Tic. San. Ltd. Sti.",
    "wof:placetype":"venue"
},
  "geometry": {"coordinates":[35.3103103638,36.9742126465],"type":"Point"}
}