{
  "type": "Feature",
  "properties": {
    "addr:full":"Demirciler ?ars. No:45 Bayrampasa B\u00fcy\u00fck\u00e7ekmece Istanbul 34905",
    "addr:housenumber":"no 45",
    "addr:postcode":"34905",
    "addr:street":"Demirciler;Ars.",
    "iso:country":"TR",
    "sg:address":"Demirciler ?ars. No:45 Bayrampasa",
    "sg:city":"B\u00fcy\u00fck\u00e7ekmece",
    "sg:classifiers":[
        {
            "category":"Manufacturing",
            "subcategory":"Tools & Machinery",
            "type":"Manufacturing & Wholesale Goods"
        }
    ],
    "sg:phone":"+90 212 567 1118",
    "sg:postcode":"34905",
    "sg:province":"Istanbul",
    "sg:tags":[
        "machine",
        "industry"
    ],
    "wof:name":"Hakki Tuncel Makina San.",
    "wof:placetype":"venue"
},
  "geometry": {"coordinates":[28.9759254456,41.0123786926],"type":"Point"}
}