{
  "type": "Feature",
  "properties": {
    "addr:full":"Dereotu Sk. No:70 Beyoglu Kagithane Istanbul 34406",
    "addr:housenumber":"70",
    "addr:postcode":"34406",
    "addr:street":"Dereotu Sk. No",
    "iso:country":"TR",
    "sg:address":"Dereotu Sk. No:70 Beyoglu",
    "sg:city":"Kagithane",
    "sg:orig_category":"Furniture Supplamentary",
    "sg:phone":"+90 212 256 1416",
    "sg:postcode":"34406",
    "sg:province":"Istanbul",
    "wof:name":"Tun? Mobilya",
    "wof:placetype":"venue"
},
  "geometry": {"coordinates":[28.9791793823,41.0389900208],"type":"Point"}
}