{
  "type": "Feature",
  "properties": {
    "iso:country":"TR",
    "sg:address":"Yeni Sanayi Ertugrulgazi Cad. No:83",
    "sg:city":"Mersin",
    "sg:classifiers":[
        {
            "category":"Wholesale",
            "subcategory":"Home Furnishings",
            "type":"Manufacturing & Wholesale Goods"
        }
    ],
    "sg:phone":"+90 224 715 4780",
    "sg:postcode":"52750",
    "sg:province":"Bursa",
    "sg:tags":[
        "furniture"
    ],
    "wof:name":"Umut Mobilya San",
    "wof:placetype":"venue"
},
  "geometry": {"coordinates":[29.0586109161,40.1844291687],"type":"Point"}
}