{
  "type": "Feature",
  "properties": {
    "addr:full":"Yavuz Bahar Sok. No:12 Avcilar Istanbul 01350",
    "addr:housenumber":"no 12",
    "addr:postcode":"01350",
    "addr:street":"Bahar Sok.;Istanbul",
    "iso:country":"TR",
    "sg:address":"Yavuz Bahar Sok. No:12",
    "sg:city":"Avcilar",
    "sg:classifiers":[
        {
            "category":"Shopping",
            "subcategory":"Clothing, Apparel, & Fashions",
            "type":"Retail Goods"
        }
    ],
    "sg:phone":"+90 21269003215",
    "sg:postcode":"01350",
    "sg:province":"Istanbul",
    "sg:tags":[
        "ready",
        "wear"
    ],
    "wof:name":"Rimteks Orme Sanayii A.s.",
    "wof:placetype":"venue"
},
  "geometry": {"coordinates":[28.8346118927,41.0248641968],"type":"Point"}
}