{
  "type": "Feature",
  "properties": {
    "addr:full":"Uzuncarsi Havanci Sok. No:15/1 Mercan Mersin Istanbul 52750",
    "addr:housenumber":"no 15 / 1",
    "addr:postcode":"52750",
    "addr:street":"Havanci Sok.;Mercan",
    "iso:country":"TR",
    "sg:address":"Uzuncarsi Havanci Sok. No:15/1 Mercan",
    "sg:city":"Mersin",
    "sg:classifiers":[
        {
            "category":"Manufacturing",
            "subcategory":"Glass & Minerals",
            "type":"Manufacturing & Wholesale Goods"
        }
    ],
    "sg:phone":"+90 212 528 3702",
    "sg:postcode":"52750",
    "sg:province":"Istanbul",
    "sg:tags":[
        "glassware"
    ],
    "wof:name":"Guzelis Porselen San.tic. A.s.",
    "wof:placetype":"venue"
},
  "geometry": {"coordinates":[28.9759254456,41.0123786926],"type":"Point"}
}