{
  "type": "Feature",
  "properties": {
    "iso:country":"TR",
    "sg:address":"Masko Mob.sit.16/a Blok No:14 Ikitelli",
    "sg:city":"G?g?en",
    "sg:classifiers":[
        {
            "category":"Shopping",
            "subcategory":"Stationery & Office Supplies",
            "type":"Retail Goods"
        }
    ],
    "sg:phone":"+90 212675075556",
    "sg:postcode":"34104",
    "sg:province":"Istanbul",
    "sg:tags":[
        "furniture"
    ],
    "wof:name":"Ardeko Mimarlik Dekorasyon Ins.ltd.sti.",
    "wof:placetype":"venue"
},
  "geometry": {"coordinates":[28.9310283661,41.0126113892],"type":"Point"}
}