{
  "type": "Feature",
  "properties": {
    "iso:country":"TR",
    "sg:address":"Cumhuriyet Cd. Platin Apt. No:43/1",
    "sg:city":"Taksim",
    "sg:classifiers":[
        {
            "category":"Marine",
            "type":"Transportation"
        }
    ],
    "sg:phone":"+90 212 253 6580",
    "sg:postcode":"24040",
    "sg:province":"Istanbul",
    "sg:tags":[
        "shipowner"
    ],
    "wof:name":"Denmar Denizcilik.a.s.",
    "wof:placetype":"venue"
},
  "geometry": {"coordinates":[29.211624,40.891857],"type":"Point"}
}