{
  "type": "Feature",
  "properties": {
    "iso:country":"TR",
    "sg:address":"S?g?tl??esme Cad.m?rver ?i?egi Sk.g?l Apt.no:6/2 Altiyol",
    "sg:city":"Kad\u0131k\u00f6y",
    "sg:classifiers":[
        {
            "category":"Building & Trades",
            "subcategory":"Plumbing",
            "type":"Services"
        }
    ],
    "sg:phone":"+90 216 414 4315",
    "sg:postcode":"34714",
    "sg:province":"Istanbul",
    "wof:name":"Sargut Insaat Isi Ve Tesisat Mlz.san.tic.ltd.sti",
    "wof:placetype":"venue"
},
  "geometry": {"coordinates":[29.0285358429,40.9890937805],"type":"Point"}
}