{
  "type": "Feature",
  "properties": {
    "addr:full":"G.o.pasa Mah.ugur Mumcu Cad.aktuna Is Merkezi No:54 Cerkezkoy Merkez Tekirdag 55020",
    "addr:housenumber":"no 54",
    "addr:postcode":"55020",
    "addr:street":"Cerkezkoy Merkez Tekirdag",
    "iso:country":"TR",
    "sg:address":"G.o.pasa Mah.ugur Mumcu Cad.aktuna Is Merkezi No:54 Cerkezkoy",
    "sg:city":"Merkez",
    "sg:classifiers":[
        {
            "category":"Manufacturing",
            "subcategory":"Wood Products",
            "type":"Manufacturing & Wholesale Goods"
        }
    ],
    "sg:phone":"+90 282 725 1948",
    "sg:postcode":"55020",
    "sg:province":"Tekirdag",
    "sg:tags":[
        "forest"
    ],
    "wof:name":"Senel Ticaret",
    "wof:placetype":"venue"
},
  "geometry": {"coordinates":[27.5144004822,40.9791984558],"type":"Point"}
}