{
  "type": "Feature",
  "properties": {
    "iso:country":"TR",
    "sg:address":"Sehitler Cd. No.60",
    "sg:city":"Alsancak",
    "sg:classifiers":[
        {
            "category":"Wholesale",
            "subcategory":"Farm Supplies",
            "type":"Manufacturing & Wholesale Goods"
        }
    ],
    "sg:phone":"+90 232 421 6502",
    "sg:postcode":"01365",
    "sg:province":"Izmir",
    "sg:tags":[
        "feed",
        "industry"
    ],
    "wof:name":"?agatay Yag Ve Yem Urn.ltd.sti.",
    "wof:placetype":"venue"
},
  "geometry": {"coordinates":[27.088092804,38.3879776001],"type":"Point"}
}