{
  "type": "Feature",
  "properties": {
    "iso:country":"TR",
    "sg:address":"Mimar Sinan Cad. Sehsamil Sok. No:2 Yenidogan-",
    "sg:city":"Sultanbeyli",
    "sg:classifiers":[
        {
            "category":"Manufacturing",
            "subcategory":"Building Materials",
            "type":"Manufacturing & Wholesale Goods"
        }
    ],
    "sg:phone":"+90 216 311 6884",
    "sg:province":"Istanbul",
    "sg:tags":[
        "floor-wall",
        "covering"
    ],
    "wof:name":"Bakir Yapi Malzemeleri Tic.paz.",
    "wof:placetype":"venue"
},
  "geometry": {"coordinates":[29.236700058,40.9841384888],"type":"Point"}
}