{
  "type": "Feature",
  "properties": {
    "iso:country":"TR",
    "sg:address":"Leyla Atakan Cad. No:49",
    "sg:city":"Mersin",
    "sg:classifiers":[
        {
            "category":"Personal",
            "subcategory":"Sauna",
            "type":"Services"
        }
    ],
    "sg:phone":"+90 262 426 1272",
    "sg:postcode":"52750",
    "sg:province":"Kocaeli",
    "sg:tags":[
        "pool"
    ],
    "wof:name":"Kal-ger Havuz Insaat Kimya Mal. Tic.ltd.sti.",
    "wof:placetype":"venue"
},
  "geometry": {"coordinates":[29.934769,40.76614],"type":"Point"}
}