{
  "type": "Feature",
  "properties": {
    "addr:full":"Vodina Cd. Kire?ane Sk. No:6 Fener Acipayam Istanbul 23000",
    "addr:housenumber":"?",
    "addr:postcode":"23000",
    "addr:street":"Vodina Cd. Kire;Sk. No 6 Fener Acipayam",
    "iso:country":"TR",
    "sg:address":"Vodina Cd. Kire?ane Sk. No:6 Fener",
    "sg:city":"Acipayam",
    "sg:classifiers":[
        {
            "category":"Home & Garden",
            "subcategory":"Hardware",
            "type":"Retail Goods"
        }
    ],
    "sg:phone":"+90 212 521 1027",
    "sg:postcode":"23000",
    "sg:province":"Istanbul",
    "sg:tags":[
        "lathe"
    ],
    "wof:name":"G??l? Torna",
    "wof:placetype":"venue"
},
  "geometry": {"coordinates":[28.9759254456,41.0123786926],"type":"Point"}
}