{
  "type": "Feature",
  "properties": {
    "iso:country":"TR",
    "sg:address":"Ali Kiyan? Besiri",
    "sg:city":"G?elyurt",
    "sg:classifiers":[
        {
            "category":"Government",
            "subcategory":"Office",
            "type":"Public Place"
        }
    ],
    "sg:phone":"+90 488 317 7244",
    "sg:province":"Batman",
    "sg:tags":[
        "municipality"
    ],
    "wof:name":"Ikik?r?belediye Baskani",
    "wof:placetype":"venue"
},
  "geometry": {"coordinates":[41.293598175,37.9164009094],"type":"Point"}
}