{
  "type": "Feature",
  "properties": {
    "iso:country":"TR",
    "sg:address":"Kocatepe Cad. No:45",
    "sg:city":"Bayrampasa",
    "sg:classifiers":[
        {
            "category":"Shopping",
            "subcategory":"Florist",
            "type":"Retail Goods"
        }
    ],
    "sg:phone":"+90 212 640 1314",
    "sg:postcode":"36100",
    "sg:province":"Istanbul",
    "sg:tags":[
        "flower"
    ],
    "wof:name":"Parlak Uluslararasi Cicekcilik",
    "wof:placetype":"venue"
},
  "geometry": {"coordinates":[28.8981266022,41.0518112183],"type":"Point"}
}