{
  "type": "Feature",
  "properties": {
    "iso:country":"TR",
    "sg:address":"Toprak Han K:2",
    "sg:city":"Mersin",
    "sg:classifiers":[
        {
            "category":"Wholesale",
            "subcategory":"Medical Equipment & Supplies",
            "type":"Manufacturing & Wholesale Goods"
        }
    ],
    "sg:phone":"+90 464 217 4177",
    "sg:postcode":"52750",
    "sg:province":"Rize",
    "wof:name":"Taskan Medikal",
    "wof:placetype":"venue"
},
  "geometry": {"coordinates":[40.525718689,41.0242195129],"type":"Point"}
}