{
  "type": "Feature",
  "properties": {
    "addr:full":"Fevzi Cakmak Bulvari No:147 Baspinar Gaziantep 07800",
    "addr:housenumber":"no",
    "addr:postcode":"07800",
    "addr:street":"Cakmak Bulvari;Baspinar",
    "iso:country":"TR",
    "sg:address":"Fevzi Cakmak Bulvari No:147",
    "sg:city":"Baspinar",
    "sg:classifiers":[
        {
            "category":"Shopping",
            "subcategory":"Crafts & Fabrics",
            "type":"Retail Goods"
        }
    ],
    "sg:phone":"+90 342 321 6000",
    "sg:postcode":"07800",
    "sg:province":"Gaziantep",
    "sg:tags":[
        "yarn"
    ],
    "wof:name":"Mag Tekstil Uretim Paz.san.tic.ltd.sti.",
    "wof:placetype":"venue"
},
  "geometry": {"coordinates":[37.3568954468,37.0741958618],"type":"Point"}
}