{
  "type": "Feature",
  "properties": {
    "iso:country":"TR",
    "sg:address":"1775/2 Sok. No: 15/a Nergiz Tansas Arkasi Pazaryeri Ici",
    "sg:city":"Karsiyaka",
    "sg:classifiers":[
        {
            "category":"Manufacturing",
            "subcategory":"Glass & Minerals",
            "type":"Manufacturing & Wholesale Goods"
        }
    ],
    "sg:phone":"+90 232 368 1675",
    "sg:postcode":"01900",
    "sg:province":"Izmir",
    "sg:tags":[
        "glass-mirror"
    ],
    "wof:name":"Bereket Cam",
    "wof:placetype":"venue"
},
  "geometry": {"coordinates":[27.1296863556,38.4186973572],"type":"Point"}
}