{
  "type": "Feature",
  "properties": {
    "iso:country":"TR",
    "sg:address":"Mehmet Akif Cad. No:40/42 Keresteciler-",
    "sg:city":"Merter",
    "sg:classifiers":[
        {
            "category":"Shopping",
            "subcategory":"Clothing, Apparel, & Fashions",
            "type":"Retail Goods"
        }
    ],
    "sg:phone":"+90 212 637 0911",
    "sg:province":"Istanbul",
    "sg:tags":[
        "ready",
        "wear"
    ],
    "wof:name":"Servet Tekstil San. Ve Tic. A.s.",
    "wof:placetype":"venue"
},
  "geometry": {"coordinates":[28.999080658,41.0460548401],"type":"Point"}
}