{
  "type": "Feature",
  "properties": {
    "addr:full":"Millet Cad. No.26 Selcuklu Nazilli Konya 65600",
    "addr:housenumber":"selcuklu",
    "addr:postcode":"65600",
    "addr:street":"Millet Cad. No.26",
    "iso:country":"TR",
    "sg:address":"Millet Cad. No.26 Selcuklu",
    "sg:city":"Nazilli",
    "sg:classifiers":[
        {
            "category":"Wholesale",
            "subcategory":"Durable Goods & Equipment",
            "type":"Manufacturing & Wholesale Goods"
        }
    ],
    "sg:phone":"+90 332 320 1213",
    "sg:postcode":"65600",
    "sg:province":"Konya",
    "sg:tags":[
        "consumer"
    ],
    "wof:name":"Ugurel Pazarlama Koll.sti.",
    "wof:placetype":"venue"
},
  "geometry": {"coordinates":[33.0667152405,39.2111282349],"type":"Point"}
}