{
  "type": "Feature",
  "properties": {
    "iso:country":"TR",
    "sg:address":"1.organize San.bolgesi 10.cad.no:4",
    "sg:city":"Kartal",
    "sg:classifiers":[
        {
            "category":"Utilities",
            "subcategory":"Natural Gas",
            "type":"Services"
        }
    ],
    "sg:phone":"+90 352321202324",
    "sg:postcode":"46000",
    "sg:province":"Kayseri",
    "sg:tags":[
        "tank-heating-natural"
    ],
    "wof:name":"Teknik-is Dokum Sanayi",
    "wof:placetype":"venue"
},
  "geometry": {"coordinates":[35.3756904602,38.7385253906],"type":"Point"}
}