{
  "type": "Feature",
  "properties": {
    "addr:full":"Sekerpinar Beldesi Ataturk Mah. Turgut ?zal Cad. No:136 Gebze Kocaeli 41400",
    "addr:housenumber":"136",
    "addr:postcode":"?;41400",
    "addr:street":"Ataturk Mah.;Zal Cad. No",
    "iso:country":"TR",
    "sg:address":"Sekerpinar Beldesi Ataturk Mah. Turgut ?zal Cad. No:136",
    "sg:city":"Gebze",
    "sg:classifiers":[
        {
            "category":"Airport",
            "subcategory":"International",
            "type":"Transportation"
        }
    ],
    "sg:phone":"+90 262 658 8800",
    "sg:postcode":"41400",
    "sg:province":"Kocaeli",
    "wof:name":"Il?e Lojistik",
    "wof:placetype":"venue"
},
  "geometry": {"coordinates":[29.9345855713,40.7669563293],"type":"Point"}
}