{
  "type": "Feature",
  "properties": {
    "addr:full":"Yenidogan Mah. Kizilay Sok. No:3/a Bayrampasa Tuzla Istanbul 01900",
    "addr:housenumber":"no 3 / a",
    "addr:postcode":"01900",
    "addr:street":"Yenidogan Mah. Kizilay Sok.;Bayrampasa",
    "iso:country":"TR",
    "sg:address":"Yenidogan Mah. Kizilay Sok. No:3/a Bayrampasa",
    "sg:city":"Tuzla",
    "sg:classifiers":[
        {
            "category":"Manufacturing",
            "subcategory":"Leather Goods",
            "type":"Manufacturing & Wholesale Goods"
        }
    ],
    "sg:phone":"+90 212501712930",
    "sg:postcode":"01900",
    "sg:province":"Istanbul",
    "sg:tags":[
        "machine"
    ],
    "wof:name":"Gundogdu Makina San.tic. Ltd.sti.",
    "wof:placetype":"venue"
},
  "geometry": {"coordinates":[28.9132080078,41.0381965637],"type":"Point"}
}