{
  "type": "Feature",
  "properties": {
    "addr:full":"Mersin Cad. 37 Tarsus 33401 33400",
    "addr:housenumber":"37",
    "addr:postcode":"33401",
    "addr:street":"Mersin Cad.",
    "iso:country":"TR",
    "sg:address":"Mersin Cad. 37",
    "sg:city":"Tarsus",
    "sg:classifiers":[
        {
            "category":"Banks & Credit Unions",
            "subcategory":"Bank",
            "type":"Services"
        }
    ],
    "sg:phone":"+90 324 613 3327",
    "sg:postcode":"33400",
    "sg:province":"33401",
    "wof:name":"Etibank Bao",
    "wof:placetype":"venue"
},
  "geometry": {"coordinates":[34.550541,36.765347],"type":"Point"}
}