{
  "type": "Feature",
  "properties": {
    "iso:country":"TR",
    "sg:address":"Sanayi Cad.altay Sok.no:7",
    "sg:city":"Yenibosna",
    "sg:classifiers":[
        {
            "category":"Home & Garden",
            "subcategory":"Household Appliances",
            "type":"Retail Goods"
        }
    ],
    "sg:phone":"+90 212 551 0500",
    "sg:postcode":"43270",
    "sg:province":"Istanbul",
    "sg:tags":[
        "conditioner",
        "air"
    ],
    "wof:name":"Erensan Isi Sanayi A.s",
    "wof:placetype":"venue"
},
  "geometry": {"coordinates":[28.9868717194,41.0844345093],"type":"Point"}
}