{
  "type": "Feature",
  "properties": {
    "iso:country":"TR",
    "sg:address":"Seyrantepe M. Nato C. No: 62 4.levent",
    "sg:city":"Beyoglu",
    "sg:classifiers":[
        {
            "category":"Building & Trades",
            "subcategory":"Plumbing",
            "type":"Services"
        }
    ],
    "sg:phone":"+90 212 270 9916",
    "sg:postcode":"34000",
    "sg:province":"Istanbul",
    "wof:name":"Kalite Ahsap Mal. San. Ltd.sti.",
    "wof:placetype":"venue"
},
  "geometry": {"coordinates":[29.0012168884,41.0998153687],"type":"Point"}
}