{
  "type": "Feature",
  "properties": {
    "iso:country":"TR",
    "sg:address":"Gmk Bulvari No:31/15 Demirtepe",
    "sg:city":"Iskenderun",
    "sg:classifiers":[
        {
            "category":"Mining & Drilling",
            "type":"Manufacturing & Wholesale Goods"
        }
    ],
    "sg:phone":"+90 312 230 7626",
    "sg:postcode":"31200",
    "sg:province":"Ankara",
    "sg:tags":[
        "industry",
        "mine"
    ],
    "wof:name":"Teknomad Madencilik M?hendis. Tic. A.s.",
    "wof:placetype":"venue"
},
  "geometry": {"coordinates":[32.8560333252,39.9438743591],"type":"Point"}
}