{
  "type": "Feature",
  "properties": {
    "iso:country":"TR",
    "sg:address":"Cebeci Cd. 542/1 Sk. No: 6",
    "sg:city":"K??k?",
    "sg:classifiers":[
        {
            "category":"Shopping",
            "subcategory":"Crafts & Fabrics",
            "type":"Retail Goods"
        }
    ],
    "sg:phone":"+90 212 617 4300",
    "sg:province":"Istanbul",
    "sg:tags":[
        "yarn"
    ],
    "wof:name":"T?r-ip Tekstil San. Tic. Ltd. Sti.",
    "wof:placetype":"venue"
},
  "geometry": {"coordinates":[28.8958854675,41.0810890198],"type":"Point"}
}