{
  "type": "Feature",
  "properties": {
    "addr:full":"Ataturk Cd. No: 193/f Antakya Bodrum Hatay 48400",
    "addr:housenumber":"no;/ f",
    "addr:postcode":"48400",
    "addr:street":"Ataturk Cd.",
    "iso:country":"TR",
    "sg:address":"Ataturk Cd. No: 193/f Antakya",
    "sg:city":"Bodrum",
    "sg:classifiers":[
        {
            "category":"Banks & Credit Unions",
            "subcategory":"Investment Brokerage",
            "type":"Services"
        }
    ],
    "sg:phone":"+90 326 221 4014",
    "sg:postcode":"48400",
    "sg:province":"Hatay",
    "sg:tags":[
        "-",
        "export",
        "import"
    ],
    "wof:name":"Yildiras Ith.ihr.nak.tur.ins.oto.ltd.sti.",
    "wof:placetype":"venue"
},
  "geometry": {"coordinates":[36.2382698059,36.4112091064],"type":"Point"}
}