{
  "type": "Feature",
  "properties": {
    "addr:full":"Beylikd??gali Ayazma Mev. G?pinar K? Yolu B.?ekmece Izmit Bekirpasa Istanbul 41100",
    "addr:housenumber":"?;?",
    "addr:postcode":"?;41100",
    "addr:street":"Gali Ayazma Mev. G;Yolu B.",
    "iso:country":"TR",
    "sg:address":"Beylikd??gali Ayazma Mev. G?pinar K? Yolu B.?ekmece",
    "sg:city":"Izmit Bekirpasa",
    "sg:classifiers":[
        {
            "category":"Shopping",
            "subcategory":"Computers & Home Electronics",
            "type":"Retail Goods"
        }
    ],
    "sg:phone":"+90 212 880 1809",
    "sg:postcode":"41100",
    "sg:province":"Istanbul",
    "sg:tags":[
        "product",
        "electric-electronic"
    ],
    "wof:name":"G?ven Kalip Elektrik San.",
    "wof:placetype":"venue"
},
  "geometry": {"coordinates":[28.9861831665,41.0408554077],"type":"Point"}
}