{
  "type": "Feature",
  "properties": {
    "iso:country":"TR",
    "sg:address":"Hasanpasa Mah. Selimiye Cad. Orkide Sok. No:6/1 Sultanbeyli",
    "sg:city":"Gaziosmanpasa",
    "sg:classifiers":[
        {
            "category":"Manufacturing",
            "subcategory":"Building Materials",
            "type":"Manufacturing & Wholesale Goods"
        }
    ],
    "sg:phone":"+90 216 398 9983",
    "sg:postcode":"34100",
    "sg:province":"Istanbul",
    "sg:tags":[
        "promotional"
    ],
    "wof:name":"Osmanli Taki Biju. Hed.esya Ith.ihr.ltd.sti.",
    "wof:placetype":"venue"
},
  "geometry": {"coordinates":[29.2482337952,40.9685897827],"type":"Point"}
}