{
  "type": "Feature",
  "properties": {
    "addr:full":"Mithatpasa Cd. No:13-15 Bayrampasa Ankara 36100",
    "addr:housenumber":"no 13-15",
    "addr:postcode":"36100",
    "addr:street":"Mithatpasa Cd.;Bayrampasa Ankara",
    "iso:country":"TR",
    "sg:address":"Mithatpasa Cd. No:13-15",
    "sg:city":"Bayrampasa",
    "sg:classifiers":[
        {
            "category":"Manufacturing",
            "subcategory":"Rubber & Plastics",
            "type":"Manufacturing & Wholesale Goods"
        }
    ],
    "sg:phone":"+90 312 431 1180",
    "sg:postcode":"36100",
    "sg:province":"Ankara",
    "sg:tags":[
        "industry"
    ],
    "wof:name":"Tel-sibor Spiral Tel Boru San. A.s.",
    "wof:placetype":"venue"
},
  "geometry": {"coordinates":[32.856533,39.924591],"type":"Point"}
}