{
  "type": "Feature",
  "properties": {
    "iso:country":"TR",
    "sg:address":"Kartal Cd. No:55 Yakacik",
    "sg:city":"Osmanbey",
    "sg:classifiers":[
        {
            "category":"Retail",
            "subcategory":"Car Wash",
            "type":"Services"
        }
    ],
    "sg:phone":"+90 216 377 0243",
    "sg:postcode":"63000",
    "sg:province":"Istanbul",
    "sg:tags":[
        "sponge"
    ],
    "wof:name":"Goya S?nger San. Ltd.",
    "wof:placetype":"venue"
},
  "geometry": {"coordinates":[29.217041,40.912071],"type":"Point"}
}