{
  "type": "Feature",
  "properties": {
    "iso:country":"TR",
    "sg:address":"Yesiltepe Mah.sehit Ilhanyurt Sk.no:60 Daire 19 Kat 7",
    "sg:city":"Sisli",
    "sg:classifiers":[
        {
            "category":"Building & Trades",
            "subcategory":"Locksmith",
            "type":"Services"
        }
    ],
    "sg:phone":"+90 212 289 8946",
    "sg:postcode":"34397",
    "sg:province":"Istanbul",
    "sg:tags":[
        "repair",
        "ship"
    ],
    "wof:name":"Asia's Best Shipping & Trading Co.",
    "wof:placetype":"venue"
},
  "geometry": {"coordinates":[28.975925,41.012379],"type":"Point"}
}