{
  "type": "Feature",
  "properties": {
    "addr:full":"Kultur Mah.hurriyet Cad. No:28 Kat:2 Gaziemir Antalya 35410",
    "addr:housenumber":"28 kat 2",
    "addr:postcode":"35410",
    "addr:street":"Mah.Hurriyet Cad. No;Gaziemir",
    "iso:country":"TR",
    "sg:address":"Kultur Mah.hurriyet Cad. No:28 Kat:2",
    "sg:city":"Gaziemir",
    "sg:classifiers":[
        {
            "category":"Home & Garden",
            "subcategory":"Garden Supply",
            "type":"Retail Goods"
        }
    ],
    "sg:phone":"+90 242 226 1117",
    "sg:postcode":"35410",
    "sg:province":"Antalya",
    "sg:tags":[
        "fertilize",
        "soil"
    ],
    "wof:name":"Bioglobal Consulting Co.ltd.",
    "wof:placetype":"venue"
},
  "geometry": {"coordinates":[30.7031345367,36.8875045776],"type":"Point"}
}