{
  "type": "Feature",
  "properties": {
    "addr:full":"Organize San.bolg. Fatih Denizli 01740",
    "addr:postcode":"01740",
    "iso:country":"TR",
    "sg:address":"Organize San.bolg.",
    "sg:city":"Fatih",
    "sg:classifiers":[
        {
            "category":"Shopping",
            "subcategory":"Clothing, Apparel, & Fashions",
            "type":"Retail Goods"
        }
    ],
    "sg:phone":"+90 258 269 1298",
    "sg:postcode":"01740",
    "sg:province":"Denizli",
    "sg:tags":[
        "ready",
        "wear"
    ],
    "wof:name":"Gunes Tekstil",
    "wof:placetype":"venue"
},
  "geometry": {"coordinates":[29.0864906311,37.773525238],"type":"Point"}
}