{
  "type": "Feature",
  "properties": {
    "addr:full":"Ethemefendi Cd. No:7/1 Erenk? Kad\u0131k\u00f6y Istanbul 34990",
    "addr:housenumber":"no 7 / 1 erenk ?",
    "addr:postcode":"34990",
    "addr:street":"Ethemefendi Cd.",
    "iso:country":"TR",
    "sg:address":"Ethemefendi Cd. No:7/1 Erenk?",
    "sg:city":"Kad\u0131k\u00f6y",
    "sg:classifiers":[
        {
            "category":"Utilities",
            "subcategory":"Natural Gas",
            "type":"Services"
        }
    ],
    "sg:phone":"+90 216 411 2143",
    "sg:postcode":"34990",
    "sg:province":"Istanbul",
    "sg:tags":[
        "tank-heating-natural"
    ],
    "wof:name":"Ok-tes M?hendis. San. Tic. Ltd. Sti.",
    "wof:placetype":"venue"
},
  "geometry": {"coordinates":[28.9861831665,41.0408554077],"type":"Point"}
}