{
  "type": "Feature",
  "properties": {
    "addr:full":"Y.dudullu Org.san.b?g. \u00dcmraniye Istanbul",
    "addr:street":"G.",
    "iso:country":"TR",
    "sg:address":"Y.dudullu Org.san.b?g.",
    "sg:city":"\u00dcmraniye",
    "sg:classifiers":[
        {
            "category":"Food & Beverages",
            "subcategory":"Groceries & Convenience Stores",
            "type":"Retail Goods"
        }
    ],
    "sg:phone":"+90 216 420 6700",
    "sg:province":"Istanbul",
    "sg:tags":[
        "drink-",
        "soft"
    ],
    "wof:name":"Meysu Meyva Suyu Gida A.s.",
    "wof:placetype":"venue"
},
  "geometry": {"coordinates":[28.975925,41.012379],"type":"Point"}
}