{
  "type": "Feature",
  "properties": {
    "iso:country":"TR",
    "sg:address":"G?elhisar Mah.armen Bul.7.sok.no:5/1",
    "sg:city":"Silifke",
    "sg:classifiers":[
        {
            "category":"Farming",
            "subcategory":"Farm & Veterinary Services",
            "type":"Manufacturing & Wholesale Goods"
        }
    ],
    "sg:phone":"+90 256 214 9715",
    "sg:postcode":"33940",
    "sg:province":"Aydin",
    "sg:tags":[
        "veterinarian"
    ],
    "wof:name":"Cagdas Veterinerlik",
    "wof:placetype":"venue"
},
  "geometry": {"coordinates":[28.4863967896,37.8117027283],"type":"Point"}
}