{
  "type": "Feature",
  "properties": {
    "addr:full":"Anithan Sisli Denizli 65710",
    "addr:postcode":"65710",
    "iso:country":"TR",
    "sg:address":"Anithan",
    "sg:city":"Sisli",
    "sg:classifiers":[
        {
            "category":"Shopping",
            "subcategory":"Florist",
            "type":"Retail Goods"
        }
    ],
    "sg:phone":"+90 258 264 2559",
    "sg:postcode":"65710",
    "sg:province":"Denizli",
    "sg:tags":[
        "flower"
    ],
    "wof:name":"?i?ek Dekorasyon",
    "wof:placetype":"venue"
},
  "geometry": {"coordinates":[29.0864906311,37.773525238],"type":"Point"}
}