{
  "type": "Feature",
  "properties": {
    "addr:full":"Semsettin G?altay Caddesi(minib? Cad.)etemefendi Sitesi B Blok No.217/20 Erenk?y Istanbul",
    "addr:housenumber":"?;minib ?;b blok no.217 / 20;?",
    "addr:street":"Semsettin G;Caddesi;Cad. Etemefendi Sitesi;Erenk;Y",
    "iso:country":"TR",
    "sg:address":"Semsettin G?altay Caddesi(minib? Cad.)etemefendi Sitesi B Blok No.217/20",
    "sg:city":"Erenk?y",
    "sg:classifiers":[
        {
            "category":"Wholesale",
            "subcategory":"Home Furnishings",
            "type":"Manufacturing & Wholesale Goods"
        }
    ],
    "sg:phone":"+90 216 355 0586",
    "sg:province":"Istanbul",
    "sg:tags":[
        "furniture"
    ],
    "sg:website":"raydolap.org",
    "wof:name":"Ray Dolap Dekarasyon",
    "wof:placetype":"venue"
},
  "geometry": {"coordinates":[28.9861831665,41.0408554077],"type":"Point"}
}