{
  "type": "Feature",
  "properties": {
    "iso:country":"TR",
    "sg:address":"Istiklal Cad.3. Ada Crs.no:15",
    "sg:city":"Kuyucak",
    "sg:classifiers":[
        {
            "category":"Utilities",
            "subcategory":"Water",
            "type":"Services"
        }
    ],
    "sg:phone":"+90 326 212 7112",
    "sg:postcode":"07655",
    "sg:province":"Hatay",
    "sg:tags":[
        "vegetable",
        "margarine",
        "oil"
    ],
    "wof:name":"Kahraman Yag Ve Gida Sanayi Ltd.",
    "wof:placetype":"venue"
},
  "geometry": {"coordinates":[36.1627693176,36.2060203552],"type":"Point"}
}