{
  "type": "Feature",
  "properties": {
    "iso:country":"TR",
    "sg:address":"I.m.?. 1. Blok No:1245",
    "sg:city":"Unkapani",
    "sg:classifiers":[
        {
            "category":"Home & Garden",
            "subcategory":"Home Furnishings",
            "type":"Retail Goods"
        }
    ],
    "sg:phone":"+90 212 519 2396",
    "sg:postcode":"34470",
    "sg:province":"Istanbul",
    "sg:tags":[
        "-curtains",
        "upholstery"
    ],
    "wof:name":"Alya Deri & Kumas",
    "wof:placetype":"venue"
},
  "geometry": {"coordinates":[28.79314,41.092854],"type":"Point"}
}