{
  "type": "Feature",
  "properties": {
    "iso:country":"TR",
    "sg:address":"Arifiye Mah.sencer Sok.pirinc Is Hani No:1/31",
    "sg:city":"Mersin",
    "sg:classifiers":[
        {
            "category":"Professional",
            "subcategory":"Detective & Security Services",
            "type":"Services"
        }
    ],
    "sg:phone":"+90 222 220 4081",
    "sg:postcode":"52750",
    "sg:province":"Eskisehir",
    "sg:tags":[
        "material"
    ],
    "wof:name":"Radar G?venlik",
    "wof:placetype":"venue"
},
  "geometry": {"coordinates":[30.517546,39.770081],"type":"Point"}
}