{
  "type": "Feature",
  "properties": {
    "addr:full":"Turizm Hatay Altinozu Hatay 31750",
    "addr:postcode":"31750",
    "iso:country":"TR",
    "sg:address":"Turizm Hatay",
    "sg:city":"Altinozu",
    "sg:classifiers":[
        {
            "category":"Travel",
            "subcategory":"Travel Agent",
            "type":"Entertainment"
        }
    ],
    "sg:phone":"+90 326 311 2739",
    "sg:postcode":"31750",
    "sg:province":"Hatay",
    "sg:tags":[
        "agency",
        "tourism"
    ],
    "wof:name":"Avea Turizm",
    "wof:placetype":"venue"
},
  "geometry": {"coordinates":[36.2817611694,36.0736312866],"type":"Point"}
}