{
  "type": "Feature",
  "properties": {
    "addr:full":"Millet Cad. Karag? Ism. No:84/77 Findikzade Merter Istanbul 34010",
    "addr:housenumber":"?;no 84 / 77",
    "addr:postcode":"34010",
    "addr:street":"Millet Cad. Karag",
    "iso:country":"TR",
    "sg:address":"Millet Cad. Karag? Ism. No:84/77 Findikzade",
    "sg:city":"Merter",
    "sg:orig_category":"Orthopedical Materials",
    "sg:phone":"+90 212 533 3372",
    "sg:postcode":"34010",
    "sg:province":"Istanbul",
    "wof:name":"Aycelik Ortopedi Mlz. Tic.",
    "wof:placetype":"venue"
},
  "geometry": {"coordinates":[28.91355896,41.0233802795],"type":"Point"}
}