{
  "type": "Feature",
  "properties": {
    "addr:full":"Bagdat Cad.yasemin Pasaji No:116/10 K.yali K.cekmece Istanbul",
    "addr:housenumber":"/ 10",
    "addr:street":"No 116",
    "iso:country":"TR",
    "sg:address":"Bagdat Cad.yasemin Pasaji No:116/10 K.yali",
    "sg:city":"K.cekmece",
    "sg:classifiers":[
        {
            "category":"Professional",
            "subcategory":"Testing Lab",
            "type":"Services"
        }
    ],
    "sg:phone":"+90 216 417 3261",
    "sg:province":"Istanbul",
    "sg:tags":[
        "laboratory",
        "material"
    ],
    "wof:name":"Biofarmatik Market C & C Ltd.",
    "wof:placetype":"venue"
},
  "geometry": {"coordinates":[29.1307792664,40.9203033447],"type":"Point"}
}