{
  "type": "Feature",
  "properties": {
    "addr:full":"Bati Mah. Ihlamur Sok. 18/95 Cadirci Is Merkz. Pendik Istanbul 34916",
    "addr:housenumber":"mah.;18 / 95",
    "addr:postcode":"34916",
    "addr:street":"Ihlamur Sok.;Cadirci Is Merkz.",
    "iso:country":"TR",
    "sg:address":"Bati Mah. Ihlamur Sok. 18/95 Cadirci Is Merkz.",
    "sg:city":"Pendik",
    "sg:classifiers":[
        {
            "category":"Building & Trades",
            "subcategory":"Pest Control",
            "type":"Services"
        }
    ],
    "sg:phone":"+90 216 491 3516",
    "sg:postcode":"34916",
    "sg:province":"Istanbul",
    "sg:tags":[
        "quality"
    ],
    "wof:name":"Kaizentec Kalite Sistem Yonetimi Teknik Danismanlik Hizmetleri",
    "wof:placetype":"venue"
},
  "geometry": {"coordinates":[28.9759254456,41.0123786926],"type":"Point"}
}