{
  "type": "Feature",
  "properties": {
    "addr:full":"Selcuk Cad.no:67/a Siteler-onder Mecidiyek\u00f6y Ankara",
    "addr:housenumber":"67 / a",
    "iso:country":"TR",
    "sg:address":"Selcuk Cad.no:67/a Siteler-onder",
    "sg:city":"Mecidiyek\u00f6y",
    "sg:classifiers":[
        {
            "category":"Shopping",
            "subcategory":"Photographic Equipment",
            "type":"Retail Goods"
        }
    ],
    "sg:phone":"+90 312 348 1499",
    "sg:province":"Ankara",
    "sg:tags":[
        "photo"
    ],
    "wof:name":"Ozturk Fotografcilik",
    "wof:placetype":"venue"
},
  "geometry": {"coordinates":[32.9126586914,39.9608726501],"type":"Point"}
}