{
  "type": "Feature",
  "properties": {
    "addr:full":"Turabey Mah, Bankalar Istanbul Bergama",
    "addr:street":"Turabey Mah Bankalar",
    "iso:country":"TR",
    "sg:address":"Turabey Mah, Bankalar",
    "sg:city":"Istanbul",
    "sg:classifiers":[
        {
            "category":"Banks & Credit Unions",
            "subcategory":"Bank",
            "type":"Services"
        }
    ],
    "sg:phone":"+90 232 632 4039",
    "sg:province":"Bergama",
    "wof:name":"Osmanli Bankasi As",
    "wof:placetype":"venue"
},
  "geometry": {"coordinates":[27.178301,39.1227],"type":"Point"}
}