{
  "type": "Feature",
  "properties": {
    "addr:full":"Rami Kisla Cad. Uzakciftlik Sok. Yesil Camii Vakfi Is Merkezi No:9 Topcular-eyup G?g?en Istanbul",
    "addr:housenumber":"? g ?",
    "addr:street":"Kisla Cad. Uzakciftlik Sok. Yesil;Vakfi;No 9 Topcular-Eyup G",
    "iso:country":"TR",
    "sg:address":"Rami Kisla Cad. Uzakciftlik Sok. Yesil Camii Vakfi Is Merkezi No:9 Topcular-eyup",
    "sg:city":"G?g?en",
    "sg:classifiers":[
        {
            "category":"Manufacturing",
            "subcategory":"Rubber & Plastics",
            "type":"Manufacturing & Wholesale Goods"
        }
    ],
    "sg:phone":"+90 212674322324",
    "sg:province":"Istanbul",
    "sg:tags":[
        "industry"
    ],
    "wof:name":"Platsan Plastik",
    "wof:placetype":"venue"
},
  "geometry": {"coordinates":[28.9219303131,41.0354995728],"type":"Point"}
}