{
  "type": "Feature",
  "properties": {
    "iso:country":"TR",
    "sg:address":"Konur Sok.12/8 Kizilay",
    "sg:city":"Emin\u00f6n\u00fc/Ca\u011falo\u011flu",
    "sg:classifiers":[
        {
            "category":"Sports & Exercise",
            "subcategory":"Tennis Court",
            "type":"Entertainment"
        }
    ],
    "sg:phone":"+90 312 418 3602",
    "sg:province":"Ankara",
    "sg:tags":[
        "equipment",
        "material"
    ],
    "wof:name":"Prizma Onur Day. T?k.mal. Ltd. Sti.",
    "wof:placetype":"venue"
},
  "geometry": {"coordinates":[32.856152,39.918697],"type":"Point"}
}