{
  "type": "Feature",
  "properties": {
    "addr:full":"M.kemal Cad. 132/1-2 Bornova Ikitelli/K\u00fc\u00e7\u00fck\u00e7ekmece Izmir 34670",
    "addr:housenumber":"132 / 1-2",
    "addr:postcode":"34670",
    "addr:street":"M.Kemal Cad.",
    "iso:country":"TR",
    "sg:address":"M.kemal Cad. 132/1-2 Bornova",
    "sg:city":"Ikitelli/K\u00fc\u00e7\u00fck\u00e7ekmece",
    "sg:classifiers":[
        {
            "category":"Mining & Drilling",
            "type":"Manufacturing & Wholesale Goods"
        }
    ],
    "sg:phone":"+90 232 388 4751",
    "sg:postcode":"34670",
    "sg:province":"Izmir",
    "wof:name":"Gimet Sondaj San. Tic.ltd. Sti.",
    "wof:placetype":"venue"
},
  "geometry": {"coordinates":[27.1423015594,38.4251480103],"type":"Point"}
}