{
  "type": "Feature",
  "properties": {
    "addr:full":"Vatan Cad. Selay Is Hani Kat:2 No: 206 Zeytinburnu Konya 41000",
    "addr:housenumber":"kat 2 no 206",
    "addr:postcode":"41000",
    "addr:street":"Vatan Cad. Selay Is",
    "iso:country":"TR",
    "sg:address":"Vatan Cad. Selay Is Hani Kat:2 No: 206",
    "sg:city":"Zeytinburnu",
    "sg:classifiers":[
        {
            "category":"Professional",
            "subcategory":"Employment Agencies",
            "type":"Services"
        }
    ],
    "sg:phone":"+90 332 322 1264",
    "sg:postcode":"41000",
    "sg:province":"Konya",
    "sg:tags":[
        "machine"
    ],
    "wof:name":"Komedya 42 Buro Makineleri",
    "wof:placetype":"venue"
},
  "geometry": {"coordinates":[32.4990272522,37.8715362549],"type":"Point"}
}