{
  "type": "Feature",
  "properties": {
    "addr:full":"Turkcell Plaza, Mesrutiyet Cad. No. 153 Tepebasi 80050 Istanbu",
    "addr:housenumber":"153",
    "addr:postcode":"80050",
    "addr:street":"Mesrutiyet Cad. No.",
    "iso:country":"TR",
    "sg:address":"Turkcell Plaza, Mesrutiyet Cad. No. 153",
    "sg:city":"Tepebasi",
    "sg:classifiers":[
        {
            "category":"Industrial Area",
            "type":"Public Place"
        }
    ],
    "sg:phone":"+90 212 313 1888",
    "sg:postcode":"Istanbu",
    "sg:province":"80050",
    "sg:tags":[
        "large",
        "private"
    ],
    "sg:website":"www.turkcell.com.tr",
    "wof:name":"Turkcell Iletisim Hizmetleri A.s.",
    "wof:placetype":"venue"
},
  "geometry": {"coordinates":[28.9861831665,41.0408554077],"type":"Point"}
}