{
  "type": "Feature",
  "properties": {
    "addr:full":"Atat?k Bulvari No:11 Izmit Kocaeli 41100",
    "addr:housenumber":"no 11",
    "addr:postcode":"41100",
    "addr:street":"K Bulvari;Izmit Kocaeli",
    "iso:country":"TR",
    "sg:address":"Atat?k Bulvari No:11",
    "sg:city":"Izmit",
    "sg:classifiers":[
        {
            "category":"Shopping",
            "subcategory":"Computers & Home Electronics",
            "type":"Retail Goods"
        }
    ],
    "sg:phone":"+90 262 332 5613",
    "sg:postcode":"41100",
    "sg:province":"Kocaeli",
    "sg:tags":[
        "used"
    ],
    "wof:name":"Academy Bilgisayar",
    "wof:placetype":"venue"
},
  "geometry": {"coordinates":[29.8873004913,40.7713546753],"type":"Point"}
}