{
  "type": "Feature",
  "properties": {
    "addr:full":"In??cd. Isik Apt. K:7 No:69/71 D:13 Beyoglu Karak\u00f6y Istanbul",
    "addr:housenumber":"7 no 69 / 71 d 13",
    "addr:street":"In ? ? Cd. Isik Apt. K;Beyoglu Karakoey",
    "iso:country":"TR",
    "sg:address":"In??cd. Isik Apt. K:7 No:69/71 D:13 Beyoglu",
    "sg:city":"Karak\u00f6y",
    "sg:classifiers":[
        {
            "category":"Organizations",
            "subcategory":"Membership Organization",
            "type":"Services"
        }
    ],
    "sg:phone":"+90 212 245 0036",
    "sg:province":"Istanbul",
    "wof:name":"Cevre Gonulluleri Dernegi",
    "wof:placetype":"venue"
},
  "geometry": {"coordinates":[28.9745006561,41.0350418091],"type":"Point"}
}