{
  "type": "Feature",
  "properties": {
    "iso:country":"TR",
    "sg:address":"S?b? Sk. No:33 Levent",
    "sg:city":"Maltepe",
    "sg:classifiers":[
        {
            "category":"Wholesale",
            "subcategory":"Books, Periodicals, & Newspapers",
            "type":"Manufacturing & Wholesale Goods"
        }
    ],
    "sg:phone":"+90 212 264 3960",
    "sg:postcode":"01000",
    "sg:province":"Istanbul",
    "sg:tags":[
        "house",
        "publishing"
    ],
    "wof:name":"Profil Yayinci. A.s.",
    "wof:placetype":"venue"
},
  "geometry": {"coordinates":[28.9959144592,41.1189651489],"type":"Point"}
}