{
  "type": "Feature",
  "properties": {
    "addr:full":"Yenidogan Mh. 50 Sk. No:28/a Zeytinburnu Sisli Istanbul 81610",
    "addr:housenumber":"50;28 / a",
    "addr:postcode":"81610",
    "addr:street":"Yenidogan Mh.;Sk. No;Zeytinburnu Sisli",
    "iso:country":"TR",
    "sg:address":"Yenidogan Mh. 50 Sk. No:28/a Zeytinburnu",
    "sg:city":"Sisli",
    "sg:classifiers":[
        {
            "category":"Manufacturing",
            "subcategory":"Tools & Machinery",
            "type":"Manufacturing & Wholesale Goods"
        }
    ],
    "sg:phone":"+90 212 546 8338",
    "sg:postcode":"81610",
    "sg:province":"Istanbul",
    "sg:tags":[
        "machine",
        "industry"
    ],
    "wof:name":"Elif Makina San. Tic. Ltd. Sti.",
    "wof:placetype":"venue"
},
  "geometry": {"coordinates":[28.9046916962,40.9882240295],"type":"Point"}
}