{
  "type": "Feature",
  "properties": {
    "addr:full":"Doganlar Mah.tura Sok. No:44/3-p Findikli Izmir 80040",
    "addr:housenumber":"no 44 / 3-p",
    "addr:postcode":"80040",
    "addr:street":"Mah.Tura Sok.",
    "iso:country":"TR",
    "sg:address":"Doganlar Mah.tura Sok. No:44/3-p",
    "sg:city":"Findikli",
    "sg:classifiers":[
        {
            "category":"Utilities",
            "subcategory":"Electric",
            "type":"Services"
        }
    ],
    "sg:phone":"+90 232478182838",
    "sg:postcode":"80040",
    "sg:province":"Izmir",
    "sg:tags":[
        "accumulator",
        "-",
        "batery"
    ],
    "wof:name":"Cicekci Aku",
    "wof:placetype":"venue"
},
  "geometry": {"coordinates":[27.129686,38.418697],"type":"Point"}
}