{
  "type": "Feature",
  "properties": {
    "iso:country":"TR",
    "sg:address":"Ali Pasa Mh. Sebilerenler Cd. Cakmak Apt. No: 1/1",
    "sg:city":"Beyazit",
    "sg:classifiers":[
        {
            "category":"Home & Garden",
            "subcategory":"Carpets & Floor Coverings",
            "type":"Retail Goods"
        }
    ],
    "sg:phone":"+90 274 224 0180",
    "sg:postcode":"65400",
    "sg:province":"K?tahya",
    "sg:tags":[
        "wall",
        "ceramics-porcelain",
        "tile",
        "-"
    ],
    "wof:name":"El Sam Cini San. Ltd.sti.",
    "wof:placetype":"venue"
},
  "geometry": {"coordinates":[43.3356399536,39.0304489136],"type":"Point"}
}