{
  "type": "Feature",
  "properties": {
    "addr:full":"Dogu San. Sit. 4 Blok No:18 Y.bosna Kabatas Istanbul 34427",
    "addr:housenumber":"4 blok no 18",
    "addr:postcode":"34427",
    "addr:street":"Sit.",
    "iso:country":"TR",
    "sg:address":"Dogu San. Sit. 4 Blok No:18 Y.bosna",
    "sg:city":"Kabatas",
    "sg:classifiers":[
        {
            "category":"Manufacturing",
            "subcategory":"Tools & Machinery",
            "type":"Manufacturing & Wholesale Goods"
        }
    ],
    "sg:phone":"+90 212 552 4005",
    "sg:postcode":"34427",
    "sg:province":"Istanbul",
    "sg:tags":[
        "machine",
        "industry"
    ],
    "wof:name":"Boteks Makina San. Tic. Ltd. Sti.",
    "wof:placetype":"venue"
},
  "geometry": {"coordinates":[28.9899768829,41.0330963135],"type":"Point"}
}