{
  "type": "Feature",
  "properties": {
    "addr:full":"Hastane Cad. Gurcak Han G?su Denizli",
    "addr:housenumber":"?",
    "addr:street":"Hastane Cad. Gurcak Han G",
    "iso:country":"TR",
    "sg:address":"Hastane Cad. Gurcak Han",
    "sg:city":"G?su",
    "sg:classifiers":[
        {
            "category":"Shopping",
            "subcategory":"Crafts & Fabrics",
            "type":"Retail Goods"
        }
    ],
    "sg:phone":"+90 258 261 2964",
    "sg:province":"Denizli",
    "sg:tags":[
        "weaving"
    ],
    "wof:name":"Mustafa Eken Ltd.sti.",
    "wof:placetype":"venue"
},
  "geometry": {"coordinates":[29.0864906311,37.773525238],"type":"Point"}
}