{
  "type": "Feature",
  "properties": {
    "addr:full":"Kizilay Cad.no:108 Osmangazi Adana 46050",
    "addr:housenumber":"108",
    "addr:postcode":"46050",
    "addr:street":"Osmangazi Adana",
    "iso:country":"TR",
    "sg:address":"Kizilay Cad.no:108",
    "sg:city":"Osmangazi",
    "sg:classifiers":[
        {
            "category":"Wholesale",
            "subcategory":"Auto Parts",
            "type":"Manufacturing & Wholesale Goods"
        }
    ],
    "sg:phone":"+90 322 359 8027",
    "sg:postcode":"46050",
    "sg:province":"Adana",
    "sg:tags":[
        "spare"
    ],
    "wof:name":"Onpar Ticaret",
    "wof:placetype":"venue"
},
  "geometry": {"coordinates":[35.330039978,36.9851913452],"type":"Point"}
}