{
  "type": "Feature",
  "properties": {
    "iso:country":"TR",
    "sg:address":"Kizil Saray Mah. Milli Egemenlilik Cad. Atik Apt. 17/a",
    "sg:city":"07100",
    "sg:classifiers":[
        {
            "category":"Home & Garden",
            "subcategory":"Home Furnishings",
            "type":"Retail Goods"
        }
    ],
    "sg:phone":"+90 242 244 7098",
    "sg:province":"Antalya",
    "sg:tags":[
        "curtaining",
        "-",
        "upholstering"
    ],
    "wof:name":"Platin Yapi Ltd. Sti.",
    "wof:placetype":"venue"
},
  "geometry": {"coordinates":[30.703135,36.887505],"type":"Point"}
}