{
  "type": "Feature",
  "properties": {
    "iso:country":"TR",
    "sg:address":"Ferhatpasa Mah. G:3 Sok. No:60",
    "sg:city":"Maltepe",
    "sg:classifiers":[
        {
            "category":"Home & Garden",
            "subcategory":"Building Materials",
            "type":"Retail Goods"
        }
    ],
    "sg:phone":"+90 216 365 8538",
    "sg:postcode":"01000",
    "sg:province":"Istanbul",
    "sg:tags":[
        "stone",
        "natural",
        "marble"
    ],
    "wof:name":"Bay-mer Bayrak Muh.ve San.tic.ltd.sti.",
    "wof:placetype":"venue"
},
  "geometry": {"coordinates":[28.9861831665,41.0408554077],"type":"Point"}
}