{
  "type": "Feature",
  "properties": {
    "addr:full":"Fatih Sultan Mehmet Cd. No: 72/a Macunkoy K?tahya 06105",
    "addr:housenumber":"no 72 / a",
    "addr:postcode":"06105",
    "addr:street":"Fatih Sultan Mehmet Cd.;K ? Tahya",
    "iso:country":"TR",
    "sg:address":"Fatih Sultan Mehmet Cd. No: 72/a",
    "sg:city":"Macunkoy",
    "sg:classifiers":[
        {
            "category":"Manufacturing",
            "subcategory":"Food",
            "type":"Manufacturing & Wholesale Goods"
        }
    ],
    "sg:phone":"+90 274 216 1349",
    "sg:postcode":"06105",
    "sg:province":"K?tahya",
    "sg:tags":[
        "wholesaler"
    ],
    "wof:name":"Dursunlar Gida Ltd.sti.",
    "wof:placetype":"venue"
},
  "geometry": {"coordinates":[32.8532714844,39.929309845],"type":"Point"}
}