{
  "type": "Feature",
  "properties": {
    "addr:full":"Yesillik Cad 389 Izmir 35400",
    "addr:housenumber":"389",
    "addr:postcode":"35400",
    "addr:street":"Yesillik Cad",
    "iso:country":"TR",
    "sg:address":"Yesillik Cad 389",
    "sg:city":"Izmir",
    "sg:classifiers":[
        {
            "category":"Banks & Credit Unions",
            "subcategory":"Bank",
            "type":"Services"
        }
    ],
    "sg:phone":"+90 232 254 5926",
    "sg:province":"35400",
    "wof:name":"Toprakbank As",
    "wof:placetype":"venue"
},
  "geometry": {"coordinates":[27.134663,38.382755],"type":"Point"}
}