{
  "type": "Feature",
  "properties": {
    "addr:full":"Prof. Cemil B. Cd. Aralik Sk. Mecitbey ?ars. Emin?? Istanbul ?atalca Istanbul",
    "addr:housenumber":"?;? ?;?",
    "addr:street":"Prof. Cemil B. Cd. Aralik Sk. Mecitbey;Istanbul",
    "iso:country":"TR",
    "sg:address":"Prof. Cemil B. Cd. Aralik Sk. Mecitbey ?ars. Emin?? Istanbul",
    "sg:city":"?atalca",
    "sg:classifiers":[
        {
            "category":"Shopping",
            "subcategory":"Stationery & Office Supplies",
            "type":"Retail Goods"
        }
    ],
    "sg:phone":"+90 212 511 8151",
    "sg:province":"Istanbul",
    "wof:name":"Mecitoglu Dis Tic. Kirtasiye Hirdavat San. Paz.",
    "wof:placetype":"venue"
},
  "geometry": {"coordinates":[28.975925,41.012379],"type":"Point"}
}