{
  "type": "Feature",
  "properties": {
    "iso:country":"TR",
    "sg:address":"Ilica Mah. Gurhan Sok.no:9 Narlidere",
    "sg:city":"07100",
    "sg:orig_category":"Scavening Services",
    "sg:phone":"+90 232 239 0066",
    "sg:province":"Izmir",
    "wof:name":"Tempas Endustriyel Temizlik Makina Ve Malaz.tic.",
    "wof:placetype":"venue"
},
  "geometry": {"coordinates":[27.02758,38.392067],"type":"Point"}
}