{
  "type": "Feature",
  "properties": {
    "addr:full":"Mebus Evleri Ayten Skk 20/12-13 Tandogan \u00c7ankaya Ankara 06580",
    "addr:housenumber":"20 / 12-13",
    "addr:postcode":"06580",
    "addr:street":"Skk;Tandogan C\u0327Ankaya",
    "iso:country":"TR",
    "sg:address":"Mebus Evleri Ayten Skk 20/12-13 Tandogan",
    "sg:city":"\u00c7ankaya",
    "sg:classifiers":[
        {
            "category":"Government",
            "subcategory":"Fire Station",
            "type":"Public Place"
        }
    ],
    "sg:phone":"+90 312 213 2727",
    "sg:postcode":"06580",
    "sg:province":"Ankara",
    "sg:tags":[
        "weapon"
    ],
    "wof:name":"Gizem Geri ?r?nleri Ve Av Malz.san.tic.ltd",
    "wof:placetype":"venue"
},
  "geometry": {"coordinates":[32.8380661011,39.925365448],"type":"Point"}
}