{
  "type": "Feature",
  "properties": {
    "iso:country":"TR",
    "sg:address":"Babalik Mh. Yapici Is Merkezi B Blok Kat:1 No:103",
    "sg:city":"Sel?klu",
    "sg:classifiers":[
        {
            "category":"Wholesale",
            "subcategory":"Medical Equipment & Supplies",
            "type":"Manufacturing & Wholesale Goods"
        }
    ],
    "sg:phone":"+90 332 320 1414",
    "sg:postcode":"42060",
    "sg:province":"Konya",
    "wof:name":"Yenal Medikal Ltd. Sti.",
    "wof:placetype":"venue"
},
  "geometry": {"coordinates":[33.0667152405,39.2111282349],"type":"Point"}
}