{
  "type": "Feature",
  "properties": {
    "iso:country":"TR",
    "sg:address":"Rihtim Cad. No:231-233 Karakoy",
    "sg:city":"Cankaya",
    "sg:classifiers":[
        {
            "category":"Banks & Credit Unions",
            "subcategory":"Financial Services",
            "type":"Services"
        }
    ],
    "sg:phone":"+90 212 292 6600",
    "sg:postcode":"07080",
    "sg:province":"Istanbul",
    "sg:tags":[
        "finance"
    ],
    "wof:name":"Istanbul Altin Borsasi",
    "wof:placetype":"venue"
},
  "geometry": {"coordinates":[28.9749679565,41.0221138],"type":"Point"}
}