{
  "type": "Feature",
  "properties": {
    "addr:full":"Kuledibi B.hendek Cd. No:79 Karak\u00f6y Istanbul",
    "addr:housenumber":"no 79",
    "addr:street":"Cd.",
    "iso:country":"TR",
    "sg:address":"Kuledibi B.hendek Cd. No:79",
    "sg:city":"Karak\u00f6y",
    "sg:classifiers":[
        {
            "category":"Building & Trades",
            "subcategory":"Electrical",
            "type":"Services"
        }
    ],
    "sg:phone":"+90 212 567 0607",
    "sg:province":"Istanbul",
    "sg:tags":[
        "equipment",
        "lighting"
    ],
    "wof:name":"Ekol Aydinlatma San. Tic. A.s.",
    "wof:placetype":"venue"
},
  "geometry": {"coordinates":[28.9759254456,41.0123786926],"type":"Point"}
}