{
  "type": "Feature",
  "properties": {
    "iso:country":"TR",
    "sg:address":"Koca Ragip Pasa Cad. Ikbal Sok. Megapol Center",
    "sg:city":"Laleli",
    "sg:classifiers":[
        {
            "category":"Sports & Exercise",
            "subcategory":"Ski Slope",
            "type":"Entertainment"
        }
    ],
    "sg:phone":"+90 212 638 6285",
    "sg:postcode":"24300",
    "sg:province":"Istanbul",
    "sg:tags":[
        "wear"
    ],
    "wof:name":"Kentavr Sportswear",
    "wof:placetype":"venue"
},
  "geometry": {"coordinates":[28.975925,41.012379],"type":"Point"}
}