{
  "type": "Feature",
  "properties": {
    "addr:full":"Yesilli Cd. No:436/a Karabaglar Ikitelli Izmir 34306",
    "addr:housenumber":"no 436 / a",
    "addr:postcode":"34306",
    "addr:street":"Yesilli Cd.",
    "iso:country":"TR",
    "sg:address":"Yesilli Cd. No:436/a Karabaglar",
    "sg:city":"Ikitelli",
    "sg:classifiers":[
        {
            "category":"Wholesale",
            "subcategory":"Home Furnishings",
            "type":"Manufacturing & Wholesale Goods"
        }
    ],
    "sg:phone":"+90 232 237 4988",
    "sg:postcode":"34306",
    "sg:province":"Izmir",
    "sg:tags":[
        "furniture"
    ],
    "wof:name":"Gonca Mobilya",
    "wof:placetype":"venue"
},
  "geometry": {"coordinates":[27.1423015594,38.4251480103],"type":"Point"}
}