{
  "type": "Feature",
  "properties": {
    "iso:country":"TR",
    "sg:address":"Turgut Reis Cad. No:66/1",
    "sg:city":"Gonen",
    "sg:classifiers":[
        {
            "category":"Farming",
            "subcategory":"Farm & Veterinary Services",
            "type":"Manufacturing & Wholesale Goods"
        }
    ],
    "sg:phone":"+90 3122313838230",
    "sg:postcode":"32090",
    "sg:province":"Ankara",
    "sg:tags":[
        "veterinarian"
    ],
    "wof:name":"Ahmet Kiremitci",
    "wof:placetype":"venue"
},
  "geometry": {"coordinates":[32.8415718079,39.9289627075],"type":"Point"}
}