{
  "type": "Feature",
  "properties": {
    "addr:full":"Eski Gemlik Ay Sok.no:31 Kucukbalikli Bursa 16250",
    "addr:housenumber":"31",
    "addr:postcode":"16250",
    "addr:street":"Eski Gemlik;Sok.No;Bursa",
    "iso:country":"TR",
    "sg:address":"Eski Gemlik Ay Sok.no:31",
    "sg:city":"Kucukbalikli",
    "sg:classifiers":[
        {
            "category":"Shopping",
            "subcategory":"Clothing, Apparel, & Fashions",
            "type":"Retail Goods"
        }
    ],
    "sg:phone":"+90 224 215 2256",
    "sg:postcode":"16250",
    "sg:province":"Bursa",
    "sg:tags":[
        "-",
        "towel",
        "bathrobe"
    ],
    "wof:name":"Sahin Havlu Tekstil Yan .san.tic.",
    "wof:placetype":"venue"
},
  "geometry": {"coordinates":[29.0586109161,40.1844291687],"type":"Point"}
}