{
  "type": "Feature",
  "properties": {
    "addr:full":"Bisnezade Camii Meyd. Sk. Efe Apt. No:2 D:7 Besiktas Beyoglu Istanbul 46810",
    "addr:housenumber":"7",
    "addr:postcode":"46810",
    "addr:street":"Meyd. Sk. Efe Apt. No 2 D",
    "iso:country":"TR",
    "sg:address":"Bisnezade Camii Meyd. Sk. Efe Apt. No:2 D:7 Besiktas",
    "sg:city":"Beyoglu",
    "sg:classifiers":[
        {
            "category":"Building & Trades",
            "subcategory":"Construction",
            "type":"Services"
        }
    ],
    "sg:phone":"+90 212 260 1405",
    "sg:postcode":"46810",
    "sg:province":"Istanbul",
    "sg:tags":[
        "foundation"
    ],
    "wof:name":"Turk Tekstil Vakfi",
    "wof:placetype":"venue"
},
  "geometry": {"coordinates":[28.9759254456,41.0123786926],"type":"Point"}
}