{
  "type": "Feature",
  "properties": {
    "addr:full":"Ikitelli Organize Sanayi B?gesi Metal Is Sanayi Sitesi 17 Blok No:40 Ikitelli/K\u00fc\u00e7\u00fck\u00e7ekmece Istanbul 34670",
    "addr:housenumber":"?;17 blok no 40",
    "addr:postcode":"34670",
    "addr:street":"Organize Sanayi B;Sitesi",
    "iso:country":"TR",
    "sg:address":"Ikitelli Organize Sanayi B?gesi Metal Is Sanayi Sitesi 17 Blok No:40",
    "sg:city":"Ikitelli/K\u00fc\u00e7\u00fck\u00e7ekmece",
    "sg:classifiers":[
        {
            "category":"Home & Garden",
            "subcategory":"Hardware",
            "type":"Retail Goods"
        }
    ],
    "sg:phone":"+90 212549620203",
    "sg:postcode":"34670",
    "sg:province":"Istanbul",
    "sg:tags":[
        "steel",
        "pipe"
    ],
    "sg:website":"egedemir.net",
    "wof:name":"Ege Demir ?elik Ve Makina San.tic.ltd.sti",
    "wof:placetype":"venue"
},
  "geometry": {"coordinates":[28.975925,41.012379],"type":"Point"}
}