{
  "type": "Feature",
  "properties": {
    "addr:full":"Fikret Arslan Kursunlu Eskisehir 07110",
    "addr:postcode":"07110",
    "addr:street":"Eskisehir",
    "iso:country":"TR",
    "sg:address":"Fikret Arslan",
    "sg:city":"Kursunlu",
    "sg:classifiers":[
        {
            "category":"Government",
            "subcategory":"Office",
            "type":"Public Place"
        }
    ],
    "sg:phone":"+90 222 711 4147",
    "sg:postcode":"07110",
    "sg:province":"Eskisehir",
    "sg:tags":[
        "municipality"
    ],
    "wof:name":"Sivrihisar Belediye Baskani",
    "wof:placetype":"venue"
},
  "geometry": {"coordinates":[28.9660816193,41.0505256653],"type":"Point"}
}