{
  "type": "Feature",
  "properties": {
    "addr:full":"Akbaba K??no:115 Beykoz Cankaya Istanbul 06570",
    "addr:postcode":"06570",
    "iso:country":"TR",
    "sg:address":"Akbaba K??no:115 Beykoz",
    "sg:city":"Cankaya",
    "sg:classifiers":[
        {
            "category":"Professional",
            "subcategory":"Testing Lab",
            "type":"Services"
        }
    ],
    "sg:phone":"+90 216 320 4550",
    "sg:postcode":"06570",
    "sg:province":"Istanbul",
    "sg:tags":[
        "laboratory",
        "material"
    ],
    "wof:name":"Medi Glass Tib Urn. A.s.",
    "wof:placetype":"venue"
},
  "geometry": {"coordinates":[29.0924034119,41.1498794556],"type":"Point"}
}