{
  "type": "Feature",
  "properties": {
    "iso:country":"TR",
    "sg:address":"Organize San.bolg.7. Cad. No:41",
    "sg:city":"Nazilli",
    "sg:classifiers":[
        {
            "category":"Wholesale",
            "subcategory":"Durable Goods & Equipment",
            "type":"Manufacturing & Wholesale Goods"
        }
    ],
    "sg:phone":"+90 352 321 2808",
    "sg:postcode":"65600",
    "sg:province":"Kayseri",
    "sg:tags":[
        "consumer"
    ],
    "wof:name":"Cennet Elektrikli Ev Aletleri",
    "wof:placetype":"venue"
},
  "geometry": {"coordinates":[36.4393234253,38.2791290283],"type":"Point"}
}