{
  "type": "Feature",
  "properties": {
    "addr:full":"Posta Cd. ?ncel Han No:46/47 Ulus Merkez Ankara 77200",
    "addr:housenumber":"?;47",
    "addr:postcode":"77200",
    "addr:street":"Posta Cd.",
    "iso:country":"TR",
    "sg:address":"Posta Cd. ?ncel Han No:46/47 Ulus",
    "sg:city":"Merkez",
    "sg:classifiers":[
        {
            "category":"Shopping",
            "subcategory":"Music",
            "type":"Retail Goods"
        }
    ],
    "sg:phone":"+90 312 311 6778",
    "sg:postcode":"77200",
    "sg:province":"Ankara",
    "sg:tags":[
        "record",
        "casette"
    ],
    "wof:name":"Kardesler Toptan Bant Satis Tic. Ltd.",
    "wof:placetype":"venue"
},
  "geometry": {"coordinates":[32.8560333252,39.9438743591],"type":"Point"}
}