{
  "type": "Feature",
  "properties": {
    "addr:full":"Ortaklar Cad. Aksu Apt. No: 4 K:8 D:21 Mecidiyekoy 38010 Istanbul",
    "addr:housenumber":"aksu;8 d 21",
    "addr:postcode":"38010",
    "addr:street":"Ortaklar Cad.;No 4 K;Mecidiyekoy",
    "iso:country":"TR",
    "sg:address":"Ortaklar Cad. Aksu Apt. No: 4 K:8 D:21 Mecidiyekoy",
    "sg:city":"38010",
    "sg:classifiers":[
        {
            "category":"Professional",
            "subcategory":"Computer Services",
            "type":"Services"
        }
    ],
    "sg:phone":"+90 212 213 5190",
    "sg:province":"Istanbul",
    "sg:tags":[
        "application",
        "software"
    ],
    "wof:name":"Caretta Bilgisayar Tic. San. Ltd. Sti.",
    "wof:placetype":"venue"
},
  "geometry": {"coordinates":[28.9968395233,41.0705795288],"type":"Point"}
}