{
  "type": "Feature",
  "properties": {
    "iso:country":"TR",
    "sg:address":"Nizip Caddesi",
    "sg:city":"Sehitkamil",
    "sg:classifiers":[
        {
            "category":"Personal",
            "subcategory":"Shoe Repair & Shine",
            "type":"Services"
        }
    ],
    "sg:phone":"+90 342 324 5747",
    "sg:postcode":"27000",
    "sg:province":"Gaziantep",
    "sg:tags":[
        "slipper"
    ],
    "wof:name":"Roza Terlik Slipper",
    "wof:placetype":"venue"
},
  "geometry": {"coordinates":[37.387459,37.070679],"type":"Point"}
}