{
  "type": "Feature",
  "properties": {
    "addr:full":"Kore Sehit. Cd. No:50 Zincirlikuyu Bak\u0131rk\u00f6y Istanbul 34140",
    "addr:housenumber":"no 50",
    "addr:postcode":"34140",
    "addr:street":"Sehit. Cd.",
    "iso:country":"TR",
    "sg:address":"Kore Sehit. Cd. No:50 Zincirlikuyu",
    "sg:city":"Bak\u0131rk\u00f6y",
    "sg:orig_category":"Printinh House",
    "sg:phone":"+90 212 288 3404",
    "sg:postcode":"34140",
    "sg:province":"Istanbul",
    "wof:name":"Turgut Yayinci. San. Tic. A.s.",
    "wof:placetype":"venue"
},
  "geometry": {"coordinates":[28.8713321686,40.9776382446],"type":"Point"}
}