{
  "type": "Feature",
  "properties": {
    "iso:country":"TR",
    "sg:address":"Ibrahimaga Cad.no:14 Maltepe",
    "sg:city":"Topkapi",
    "sg:classifiers":[
        {
            "category":"Shopping",
            "subcategory":"Stationery & Office Supplies",
            "type":"Retail Goods"
        }
    ],
    "sg:phone":"+90 212 612 6800",
    "sg:postcode":"34020",
    "sg:province":"Istanbul",
    "sg:tags":[
        "paper"
    ],
    "wof:name":"As Defter San.ve Tic.ltd.sti",
    "wof:placetype":"venue"
},
  "geometry": {"coordinates":[28.9185295105,41.0301399231],"type":"Point"}
}