{
  "type": "Feature",
  "properties": {
    "iso:country":"TR",
    "sg:address":"Rihtim Cad. Electronic Center",
    "sg:city":"Karakoy",
    "sg:classifiers":[
        {
            "category":"Food & Beverages",
            "subcategory":"Candy",
            "type":"Retail Goods"
        }
    ],
    "sg:phone":"+90 212 251 1898",
    "sg:postcode":"07700",
    "sg:province":"Istanbul",
    "sg:tags":[
        "biscuit-chocolate-candy"
    ],
    "wof:name":"Irfa Export & Import",
    "wof:placetype":"venue"
},
  "geometry": {"coordinates":[28.975925,41.012379],"type":"Point"}
}