{
  "type": "Feature",
  "properties": {
    "iso:country":"TR",
    "sg:address":"G?tepe Soyat Sit. 16 Blok No:314 Usk?ar",
    "sg:city":"Mersin",
    "sg:classifiers":[
        {
            "category":"Wholesale",
            "subcategory":"Medical Equipment & Supplies",
            "type":"Manufacturing & Wholesale Goods"
        }
    ],
    "sg:phone":"+90 216 324 5650",
    "sg:postcode":"52750",
    "sg:province":"Istanbul",
    "wof:name":"Metkur Dis Tic. A.s.",
    "wof:placetype":"venue"
},
  "geometry": {"coordinates":[28.9861831665,41.0408554077],"type":"Point"}
}