{
  "type": "Feature",
  "properties": {
    "iso:country":"TR",
    "sg:address":"Istanbul Cd. No:46 E-5 Gebze",
    "sg:city":"B\u00fcy\u00fck\u00e7ekmece",
    "sg:classifiers":[
        {
            "category":"Home & Garden",
            "subcategory":"Building Materials",
            "type":"Retail Goods"
        }
    ],
    "sg:phone":"+90 262 641 9305",
    "sg:postcode":"34905",
    "sg:province":"Kocaeli",
    "sg:tags":[
        "window",
        "door",
        "plastic"
    ],
    "wof:name":"Pilapen A.s.",
    "wof:placetype":"venue"
},
  "geometry": {"coordinates":[29.4254798889,40.7918624878],"type":"Point"}
}