{
  "type": "Feature",
  "properties": {
    "iso:country":"TR",
    "sg:address":"Nispetiye Cad.birlik Sk.no:28/9 1.levent",
    "sg:city":"Besiktas",
    "sg:classifiers":[
        {
            "category":"Manufacturing",
            "subcategory":"Building Materials",
            "type":"Manufacturing & Wholesale Goods"
        }
    ],
    "sg:phone":"+90 2123254303729",
    "sg:postcode":"75200",
    "sg:province":"Istanbul",
    "sg:tags":[
        "promotional"
    ],
    "wof:name":"Form Stratejik Tanitim Danismanlik Reklamcilik",
    "wof:placetype":"venue"
},
  "geometry": {"coordinates":[29.0186748505,41.0731620789],"type":"Point"}
}