{
  "type": "Feature",
  "properties": {
    "iso:country":"TR",
    "sg:address":"In??bulvari Gazioglu Apt. No:71/5",
    "sg:city":"Cagaloglu",
    "sg:orig_category":"Carpet-kilim-blanket",
    "sg:phone":"+90 352 321 1295",
    "sg:province":"Kayseri",
    "wof:name":"Atlantik Halicilik San. A.s.",
    "wof:placetype":"venue"
},
  "geometry": {"coordinates":[36.4393234253,38.2791290283],"type":"Point"}
}