{
  "type": "Feature",
  "properties": {
    "addr:full":"Milli Egemenlik Cad. Zafer Ishani K: 4/10 G?ercinlik Afyon",
    "addr:housenumber":"4 / 10 g ?",
    "addr:street":"Egemenlik Cad. Zafer Ishani K;Ercinlik Afyon",
    "iso:country":"TR",
    "sg:address":"Milli Egemenlik Cad. Zafer Ishani K: 4/10",
    "sg:city":"G?ercinlik",
    "sg:classifiers":[
        {
            "category":"Food & Beverages",
            "subcategory":"Meat & Fish",
            "type":"Retail Goods"
        }
    ],
    "sg:phone":"+90 272 213 5950",
    "sg:province":"Afyon",
    "sg:tags":[
        "product"
    ],
    "wof:name":"Topcuoglu Et Ve Et Urunleri San. Ve Tic. Ltd. Sti.",
    "wof:placetype":"venue"
},
  "geometry": {"coordinates":[30.5382652283,38.7579841614],"type":"Point"}
}