{
  "type": "Feature",
  "properties": {
    "addr:full":"Denizb?k? Mevkii Turgut ?zal Cad. No:8 Side Manavgat Antalya 07600",
    "addr:housenumber":"?",
    "addr:postcode":"07600",
    "addr:street":"Turgut;Zal Cad. No 8 Side",
    "iso:country":"TR",
    "sg:address":"Denizb?k? Mevkii Turgut ?zal Cad. No:8 Side",
    "sg:city":"Manavgat",
    "sg:classifiers":[
        {
            "category":"Travel",
            "subcategory":"Travel Agent",
            "type":"Entertainment"
        }
    ],
    "sg:phone":"+90 2427532510756",
    "sg:postcode":"07600",
    "sg:province":"Antalya",
    "sg:tags":[
        "agency",
        "tourism"
    ],
    "wof:name":"Ora Tour Turizm (denizb??sb.)",
    "wof:placetype":"venue"
},
  "geometry": {"coordinates":[30.7092056274,36.8790512085],"type":"Point"}
}