{
  "type": "Feature",
  "properties": {
    "iso:country":"TR",
    "sg:address":"Organize San. Bolgesi 2.cad.",
    "sg:city":"Inegol",
    "sg:classifiers":[
        {
            "category":"Shopping",
            "subcategory":"Crafts & Fabrics",
            "type":"Retail Goods"
        }
    ],
    "sg:phone":"+90 22471482192021",
    "sg:postcode":"16400",
    "sg:province":"Bursa",
    "sg:tags":[
        "weaving"
    ],
    "wof:name":"Asipek Tekstil San. Ve Tic. A.s.",
    "wof:placetype":"venue"
},
  "geometry": {"coordinates":[29.0580043793,40.1947555542],"type":"Point"}
}