{
  "type": "Feature",
  "properties": {
    "addr:full":"Sanayi Mah. Sultan Selim Cad. Ozturk Is Hani No.93/3 4 Levent Istanbul 01310",
    "addr:housenumber":"no.93 / 3 4",
    "addr:postcode":"01310",
    "addr:street":"Sanayi Mah. Sultan Selim Cad. Ozturk Is Hani",
    "iso:country":"TR",
    "sg:address":"Sanayi Mah. Sultan Selim Cad. Ozturk Is Hani No.93/3 4",
    "sg:city":"Levent",
    "sg:classifiers":[
        {
            "category":"Shopping",
            "subcategory":"Clothing, Apparel, & Fashions",
            "type":"Retail Goods"
        }
    ],
    "sg:phone":"+90 212 281 5634",
    "sg:postcode":"01310",
    "sg:province":"Istanbul",
    "sg:tags":[
        "underwear"
    ],
    "wof:name":"Sebnem Saten Ic Giyim San.tic.ltd.sti.",
    "wof:placetype":"venue"
},
  "geometry": {"coordinates":[28.975925,41.012379],"type":"Point"}
}