{
  "type": "Feature",
  "properties": {
    "iso:country":"TR",
    "sg:address":"Ilicabasi Mevkii Devlet Karayolu ?zeri No:47",
    "sg:city":"Iskenderun",
    "sg:classifiers":[
        {
            "category":"Manufacturing",
            "subcategory":"Tools & Machinery",
            "type":"Manufacturing & Wholesale Goods"
        }
    ],
    "sg:phone":"+90 256 225 2707",
    "sg:postcode":"31200",
    "sg:province":"Aydin",
    "sg:tags":[
        "machine",
        "industry"
    ],
    "wof:name":"Balkan Tekstil Makinalari Sanayi Ve Ticaret Ltd.sti.",
    "wof:placetype":"venue"
},
  "geometry": {"coordinates":[28.4863967896,37.8117027283],"type":"Point"}
}