{
  "type": "Feature",
  "properties": {
    "iso:country":"TR",
    "sg:address":"Terazidere Mah. Gunes Cad. Karaman Sok. No:20",
    "sg:city":"Bayrampasa",
    "sg:classifiers":[
        {
            "category":"Shopping",
            "subcategory":"Crafts & Fabrics",
            "type":"Retail Goods"
        }
    ],
    "sg:phone":"+90 212 493 3420",
    "sg:postcode":"36100",
    "sg:province":"Istanbul",
    "sg:tags":[
        "yarn"
    ],
    "wof:name":"Lik-las Tekstil San.tic.ltd.sti.",
    "wof:placetype":"venue"
},
  "geometry": {"coordinates":[28.9017944336,41.0308914185],"type":"Point"}
}