{
  "type": "Feature",
  "properties": {
    "addr:full":"Ferit Selim Pasa Cd. Sebboy Sk. No:59 Bah\u00e7elievler Istanbul 34180",
    "addr:housenumber":"59",
    "addr:postcode":"34180",
    "addr:street":"Pasa Cd. Sebboy Sk. No",
    "iso:country":"TR",
    "sg:address":"Ferit Selim Pasa Cd. Sebboy Sk. No:59",
    "sg:city":"Bah\u00e7elievler",
    "sg:classifiers":[
        {
            "category":"Shopping",
            "subcategory":"Florist",
            "type":"Retail Goods"
        }
    ],
    "sg:phone":"+90 212 504 4883",
    "sg:postcode":"34180",
    "sg:province":"Istanbul",
    "sg:tags":[
        "flower"
    ],
    "wof:name":"Yayla ?i?ek?ilik",
    "wof:placetype":"venue"
},
  "geometry": {"coordinates":[28.8429107666,41.0448150635],"type":"Point"}
}