{
  "type": "Feature",
  "properties": {
    "addr:full":"Biskek Cad. K?e Apt. No :217 / 10 Emek Ankara 06510",
    "addr:housenumber":"k ? e apt.;/ 10",
    "addr:postcode":"06510",
    "addr:street":"Biskek Cad.;No 217;Emek",
    "iso:country":"TR",
    "sg:address":"Biskek Cad. K?e Apt. No :217 / 10",
    "sg:city":"Emek",
    "sg:classifiers":[
        {
            "category":"Food & Beverages",
            "subcategory":"Dairy",
            "type":"Retail Goods"
        }
    ],
    "sg:phone":"+90 542 421 8848",
    "sg:postcode":"06510",
    "sg:province":"Ankara",
    "sg:tags":[
        "pruducts",
        "milk"
    ],
    "wof:name":"Murat Ayg?n S? Mam?leri Danismanlik A.s.",
    "wof:placetype":"venue"
},
  "geometry": {"coordinates":[32.818031311,39.9247360229],"type":"Point"}
}