{
  "type": "Feature",
  "properties": {
    "addr:full":"Ergenekon Cad. Muratoglu ?arsisi 83/85 A Blok No:39 Pangalti Istanbul 34373",
    "addr:housenumber":"muratoglu ?;83 / 85 a blok no 39",
    "addr:postcode":"34373",
    "addr:street":"Ergenekon Cad.;Arsisi;Istanbul",
    "iso:country":"TR",
    "sg:address":"Ergenekon Cad. Muratoglu ?arsisi 83/85 A Blok No:39",
    "sg:city":"Pangalti",
    "sg:orig_category":"Textile Suplementaries",
    "sg:phone":"+90 212 241 5470",
    "sg:postcode":"34373",
    "sg:province":"Istanbul",
    "wof:name":"G?ney Tic. Konf.",
    "wof:placetype":"venue"
},
  "geometry": {"coordinates":[28.9861831665,41.0408554077],"type":"Point"}
}