{
  "type": "Feature",
  "properties": {
    "addr:full":"T?lbent?i H?samettin Mah. Mermerciler Cad. No:13/15 K:1 Emin\u00f6n\u00fc/Ca\u011falo\u011flu Istanbul 34110",
    "addr:housenumber":"?;?;13 / 15 k 1",
    "addr:postcode":"34110",
    "addr:street":"T ? Lbent;I H;Samettin Mah. Mermerciler Cad. No",
    "iso:country":"TR",
    "sg:address":"T?lbent?i H?samettin Mah. Mermerciler Cad. No:13/15 K:1",
    "sg:city":"Emin\u00f6n\u00fc/Ca\u011falo\u011flu",
    "sg:classifiers":[
        {
            "category":"Travel",
            "subcategory":"Travel Agent",
            "type":"Entertainment"
        }
    ],
    "sg:phone":"+90 51673374581061",
    "sg:postcode":"34110",
    "sg:province":"Istanbul",
    "sg:tags":[
        "agency",
        "tourism"
    ],
    "wof:name":"Ukray Turizm",
    "wof:placetype":"venue"
},
  "geometry": {"coordinates":[28.9861831665,41.0408554077],"type":"Point"}
}