{
  "type": "Feature",
  "properties": {
    "iso:country":"TR",
    "sg:address":"Ceyhan Yolu Mobilyacilar Sitesi 2.blok. No:1",
    "sg:city":"Tarsus",
    "sg:classifiers":[
        {
            "category":"Wholesale",
            "subcategory":"Home Furnishings",
            "type":"Manufacturing & Wholesale Goods"
        }
    ],
    "sg:phone":"+90 32234625253462",
    "sg:postcode":"33400",
    "sg:province":"Adana",
    "sg:tags":[
        "furniture"
    ],
    "wof:name":"Pasa Mobilya Tic. Ve San Ltd.sti.",
    "wof:placetype":"venue"
},
  "geometry": {"coordinates":[35.3250198364,36.9854202271],"type":"Point"}
}