{
  "type": "Feature",
  "properties": {
    "addr:full":"Ataturk Mah.555.sok.no:19 Salihli \u00c7orlu Manisa",
    "addr:housenumber":"19",
    "addr:street":"Ataturk;Salihli C\u0327Orlu",
    "iso:country":"TR",
    "sg:address":"Ataturk Mah.555.sok.no:19 Salihli",
    "sg:city":"\u00c7orlu",
    "sg:classifiers":[
        {
            "category":"Shopping",
            "subcategory":"Luggage & Leather Goods",
            "type":"Retail Goods"
        }
    ],
    "sg:phone":"+90 236 714 7264",
    "sg:province":"Manisa",
    "sg:tags":[
        "leather-fur",
        "wear"
    ],
    "wof:name":"Yilmazlar Giyisilik Deri San.tic.ltd.sti.",
    "wof:placetype":"venue"
},
  "geometry": {"coordinates":[28.1390991211,38.4812011719],"type":"Point"}
}