{
  "type": "Feature",
  "properties": {
    "addr:full":"N?hetiye Cad. Ugur Palas No:7/3 Besiktas Bornova Istanbul 3500",
    "addr:housenumber":"?;3",
    "addr:postcode":"3500",
    "addr:street":"N;Hetiye Cad. Ugur;No 7 /;Besiktas",
    "iso:country":"TR",
    "sg:address":"N?hetiye Cad. Ugur Palas No:7/3 Besiktas",
    "sg:city":"Bornova",
    "sg:classifiers":[
        {
            "category":"Wholesale",
            "subcategory":"Medical Equipment & Supplies",
            "type":"Manufacturing & Wholesale Goods"
        }
    ],
    "sg:phone":"+90 212 631 1852",
    "sg:postcode":"3500",
    "sg:province":"Istanbul",
    "wof:name":"Magnet Paz.",
    "wof:placetype":"venue"
},
  "geometry": {"coordinates":[28.9861831665,41.0408554077],"type":"Point"}
}