{
  "type": "Feature",
  "properties": {
    "iso:country":"TR",
    "sg:address":"Gazi Cad Kaptanoglu",
    "sg:city":"Samsun",
    "sg:classifiers":[
        {
            "category":"Banks & Credit Unions",
            "subcategory":"Bank",
            "type":"Services"
        }
    ],
    "sg:phone":"+90 362 432 1904",
    "sg:postcode":"61420",
    "sg:province":"55020",
    "wof:name":"T?kiye Halk, Bankasi As",
    "wof:placetype":"venue"
},
  "geometry": {"coordinates":[36.330437,41.287083],"type":"Point"}
}