{
  "type": "Feature",
  "properties": {
    "iso:country":"TR",
    "sg:address":"Zafer San. G?en Cd. Mutluol Sk. No:5-7",
    "sg:city":"Yenisehir",
    "sg:classifiers":[
        {
            "category":"Wholesale",
            "subcategory":"Machinery & Supplies",
            "type":"Manufacturing & Wholesale Goods"
        }
    ],
    "sg:phone":"+90 332 248 8298",
    "sg:postcode":"35110",
    "sg:province":"Konya",
    "sg:tags":[
        "bearing",
        "ball"
    ],
    "wof:name":"Genmot Genel Motor Krank Saft End?stri San. Tic. Ltd. Sti.",
    "wof:placetype":"venue"
},
  "geometry": {"coordinates":[32.499027,37.871536],"type":"Point"}
}