{
  "type": "Feature",
  "properties": {
    "addr:full":"Selimiye Cad. No: 196 Karatay Konya 42000",
    "addr:housenumber":"196",
    "addr:postcode":"42000",
    "addr:street":"Selimiye Cad. No;Karatay",
    "iso:country":"TR",
    "sg:address":"Selimiye Cad. No: 196",
    "sg:city":"Karatay",
    "sg:classifiers":[
        {
            "category":"Home & Garden",
            "subcategory":"Building Materials",
            "type":"Retail Goods"
        }
    ],
    "sg:phone":"+90 332 351 2811",
    "sg:postcode":"42000",
    "sg:province":"Konya",
    "sg:tags":[
        "insulation"
    ],
    "wof:name":"Unalacak Ins.izolasyon Ltd.sti.",
    "wof:placetype":"venue"
},
  "geometry": {"coordinates":[32.4950904846,37.8679275513],"type":"Point"}
}