{
  "type": "Feature",
  "properties": {
    "iso:country":"TR",
    "sg:address":"Sanayi Cad.no:45",
    "sg:city":"Bornova",
    "sg:classifiers":[
        {
            "category":"Wholesale",
            "subcategory":"Tobacco Products",
            "type":"Manufacturing & Wholesale Goods"
        }
    ],
    "sg:phone":"+90 232 381 6055",
    "sg:postcode":"35040",
    "sg:province":"Izmir",
    "sg:tags":[
        "cigarette"
    ],
    "wof:name":"Tutuntex Tic.a.s",
    "wof:placetype":"venue"
},
  "geometry": {"coordinates":[27.2030029297,38.4532623291],"type":"Point"}
}