{
  "type": "Feature",
  "properties": {
    "addr:full":"Mahmutbey Yolu Y. Selim Kardesleri Mh. Bagcilar Mersin Istanbul 52750",
    "addr:postcode":"52750",
    "addr:street":"Mahmutbey Yolu Y. Selim Kardesleri Mh. Bagcilar",
    "iso:country":"TR",
    "sg:address":"Mahmutbey Yolu Y. Selim Kardesleri Mh. Bagcilar",
    "sg:city":"Mersin",
    "sg:classifiers":[
        {
            "category":"Freight",
            "type":"Transportation"
        }
    ],
    "sg:phone":"+90 212 568 9450",
    "sg:postcode":"52750",
    "sg:province":"Istanbul",
    "sg:tags":[
        "packing",
        "industry"
    ],
    "wof:name":"Primeks Ambalaj Metal San. Dis Tic. Ltd. Sti.",
    "wof:placetype":"venue"
},
  "geometry": {"coordinates":[28.828502655,41.0232276917],"type":"Point"}
}