{
  "type": "Feature",
  "properties": {
    "addr:full":"Kayisdagi Cad.in?n? Mah. No:76 D:4 Kat : I?erenk?y Istanbul",
    "addr:housenumber":"? mah. no 76 d 4 kat i ?;?",
    "addr:street":"N;Erenk;Y",
    "iso:country":"TR",
    "sg:address":"Kayisdagi Cad.in?n? Mah. No:76 D:4 Kat :",
    "sg:city":"I?erenk?y",
    "sg:classifiers":[
        {
            "category":"Freight",
            "type":"Transportation"
        }
    ],
    "sg:phone":"+90 216 574 3852",
    "sg:province":"Istanbul",
    "sg:tags":[
        "cargo",
        "parcel"
    ],
    "wof:name":"Kozak Ulus.tas.hiz.tic.ltd.sti.",
    "wof:placetype":"venue"
},
  "geometry": {"coordinates":[28.9759254456,41.0123786926],"type":"Point"}
}