{
  "type": "Feature",
  "properties": {
    "iso:country":"TR",
    "sg:address":"Fevzi Cakmak Mah. Yeni Hurd. Sitesi 9.sok. No:20",
    "sg:city":"Karakoy",
    "sg:classifiers":[
        {
            "category":"Home & Garden",
            "subcategory":"Hardware",
            "type":"Retail Goods"
        }
    ],
    "sg:phone":"+90 332 342 0124",
    "sg:postcode":"07700",
    "sg:province":"Konya",
    "sg:tags":[
        "store"
    ],
    "wof:name":"Sedka Sanayi Ve Endustri Urunleri Dagitim & Pazarlama",
    "wof:placetype":"venue"
},
  "geometry": {"coordinates":[33.0667152405,39.2111282349],"type":"Point"}
}