{
  "type": "Feature",
  "properties": {
    "iso:country":"TR",
    "sg:address":"Karakoy P.pazari Cad.no:55/1",
    "sg:city":"Karakoy",
    "sg:classifiers":[
        {
            "category":"Food & Beverages",
            "subcategory":"Groceries & Convenience Stores",
            "type":"Retail Goods"
        }
    ],
    "sg:phone":"+90 212 249 4305",
    "sg:postcode":"07700",
    "sg:province":"Istanbul",
    "sg:tags":[
        "ready"
    ],
    "wof:name":"Ertek Ltd.sti.",
    "wof:placetype":"venue"
},
  "geometry": {"coordinates":[36.3302383423,41.2744636536],"type":"Point"}
}