{
  "type": "Feature",
  "properties": {
    "addr:full":"Halkali Cad. Ozbey Sok. No:119 Genc Ishani Kat:3/119 Sefakoy Beyoglu Istanbul 46810",
    "addr:housenumber":"no;kat 3 / 119",
    "addr:postcode":"46810",
    "addr:street":"Halkali Cad. Ozbey Sok.;Genc;Sefakoy Beyoglu",
    "iso:country":"TR",
    "sg:address":"Halkali Cad. Ozbey Sok. No:119 Genc Ishani Kat:3/119 Sefakoy",
    "sg:city":"Beyoglu",
    "sg:classifiers":[
        {
            "category":"Organizations",
            "subcategory":"Membership Organization",
            "type":"Services"
        }
    ],
    "sg:phone":"+90 21259861635987",
    "sg:postcode":"46810",
    "sg:province":"Istanbul",
    "wof:name":"Sokak Cocuklarini Koruma Egitme Ve Yardimlasma Dernegi",
    "wof:placetype":"venue"
},
  "geometry": {"coordinates":[28.9861831665,41.0408554077],"type":"Point"}
}