{
  "type": "Feature",
  "properties": {
    "addr:full":"N?ethane Cd. No:9 Sirkeci Mecidiyek\u00f6y Istanbul 34387",
    "addr:housenumber":"?;no 9",
    "addr:postcode":"34387",
    "addr:street":"N;Ethane Cd.",
    "iso:country":"TR",
    "sg:address":"N?ethane Cd. No:9 Sirkeci",
    "sg:city":"Mecidiyek\u00f6y",
    "sg:classifiers":[
        {
            "category":"Shopping",
            "subcategory":"Photographic Equipment",
            "type":"Retail Goods"
        }
    ],
    "sg:phone":"+90 212 513 9440",
    "sg:postcode":"34387",
    "sg:province":"Istanbul",
    "sg:tags":[
        "photo"
    ],
    "wof:name":"Turbo Filtre San. Tic. A.s.",
    "wof:placetype":"venue"
},
  "geometry": {"coordinates":[28.9921588898,41.0720214844],"type":"Point"}
}