{
  "type": "Feature",
  "properties": {
    "addr:full":"Kocasinan Sanayi Sitesi 202.sok. No:10 Ostim 26020 Ankara",
    "addr:housenumber":"202.sok no 10",
    "addr:postcode":"26020",
    "addr:street":"Kocasinan Sanayi Sitesi;Ostim",
    "iso:country":"TR",
    "sg:address":"Kocasinan Sanayi Sitesi 202.sok. No:10 Ostim",
    "sg:city":"26020",
    "sg:classifiers":[
        {
            "category":"Shopping",
            "subcategory":"Gifts & Souvenirs",
            "type":"Retail Goods"
        }
    ],
    "sg:phone":"+90 312 354 5991",
    "sg:province":"Ankara",
    "wof:name":"Mehtap Maddeni Esya Insaat San. Tic.ltd.sti.",
    "wof:placetype":"venue"
},
  "geometry": {"coordinates":[32.7503318787,39.9790267944],"type":"Point"}
}