{
  "type": "Feature",
  "properties": {
    "addr:full":"Barbaros Bulvari Seyan Apt. No:33 Besiktas Mecidiyek\u00f6y Istanbul 34387",
    "addr:housenumber":"33",
    "addr:postcode":"34387",
    "addr:street":"Barbaros Bulvari Seyan Apt. No",
    "iso:country":"TR",
    "sg:address":"Barbaros Bulvari Seyan Apt. No:33 Besiktas",
    "sg:city":"Mecidiyek\u00f6y",
    "sg:classifiers":[
        {
            "category":"Manufacturing",
            "subcategory":"Rubber & Plastics",
            "type":"Manufacturing & Wholesale Goods"
        }
    ],
    "sg:phone":"+90 212 396 3789",
    "sg:postcode":"34387",
    "sg:province":"Istanbul",
    "sg:tags":[
        "industry"
    ],
    "wof:name":"Plas Plastik Ambalaj San. Tic. A.s.",
    "wof:placetype":"venue"
},
  "geometry": {"coordinates":[28.9777793884,41.073387146],"type":"Point"}
}