{
  "type": "Feature",
  "properties": {
    "iso:country":"TR",
    "sg:address":"Uzuncarsi Cad. No: 139",
    "sg:city":"Mercan",
    "sg:classifiers":[
        {
            "category":"Parking",
            "subcategory":"Garage",
            "type":"Transportation"
        }
    ],
    "sg:phone":"+90 212 513 2487",
    "sg:postcode":"12600",
    "sg:province":"Istanbul",
    "sg:tags":[
        "zipper"
    ],
    "wof:name":"Bir Textile",
    "wof:placetype":"venue"
},
  "geometry": {"coordinates":[28.9674301147,41.0148696899],"type":"Point"}
}