{
  "type": "Feature",
  "properties": {
    "iso:country":"TR",
    "sg:address":"S?eyman Yilmaz",
    "sg:city":"Haymana",
    "sg:classifiers":[
        {
            "category":"Government",
            "subcategory":"Office",
            "type":"Public Place"
        }
    ],
    "sg:phone":"+90 242 426 3049",
    "sg:postcode":"43274",
    "sg:province":"Antalya",
    "sg:tags":[
        "municipality"
    ],
    "wof:name":"?alkaya Belediye Baskani",
    "wof:placetype":"venue"
},
  "geometry": {"coordinates":[32.8563842773,39.9355163574],"type":"Point"}
}