{
  "type": "Feature",
  "properties": {
    "iso:country":"TR",
    "sg:address":"Bayindir Sk. No:7/4 Ankara",
    "sg:city":"G.osmanpasa",
    "sg:classifiers":[
        {
            "category":"Shopping",
            "subcategory":"Florist",
            "type":"Retail Goods"
        }
    ],
    "sg:phone":"+90 312 431 1112",
    "sg:province":"Ankara",
    "sg:tags":[
        "flower"
    ],
    "wof:name":"Ankara Sanat ?i?ek?ilik Ltd. Sti.",
    "wof:placetype":"venue"
},
  "geometry": {"coordinates":[32.9590835571,39.9190673828],"type":"Point"}
}