{
  "type": "Feature",
  "properties": {
    "iso:country":"TR",
    "sg:address":"Ankara Asfalti ?zeri Istanbul Cad. No: 111 41400 ?ayirova",
    "sg:city":"Gebze",
    "sg:classifiers":[
        {
            "category":"Food & Beverages",
            "subcategory":"Candy",
            "type":"Retail Goods"
        }
    ],
    "sg:phone":"+90 262 653 8090",
    "sg:postcode":"41400",
    "sg:province":"Kocaeli",
    "sg:tags":[
        "biscuit-chocolate-candy"
    ],
    "wof:name":"Kent Gida Maddeleri San. Ve Tic. A.s.",
    "wof:placetype":"venue"
},
  "geometry": {"coordinates":[29.881521,40.853271],"type":"Point"}
}