{
  "type": "Feature",
  "properties": {
    "iso:country":"TR",
    "sg:address":"Konur Sok. No:45 Bakanliklar",
    "sg:city":"Ulus",
    "sg:classifiers":[
        {
            "category":"Professional",
            "subcategory":"Detective & Security Services",
            "type":"Services"
        }
    ],
    "sg:phone":"+90 312 422 2222",
    "sg:postcode":"06200",
    "sg:province":"Ankara",
    "sg:tags":[
        "material"
    ],
    "wof:name":"Atilim G?venlik Hizmetleri Ltd.sti.",
    "wof:placetype":"venue"
},
  "geometry": {"coordinates":[32.77953,39.962021],"type":"Point"}
}