{
  "type": "Feature",
  "properties": {
    "addr:full":"Bahriye Cd. No:112 Kasimpasa Y.dudullu Istanbul",
    "addr:housenumber":"no",
    "addr:street":"Bahriye Cd.",
    "iso:country":"TR",
    "sg:address":"Bahriye Cd. No:112 Kasimpasa",
    "sg:city":"Y.dudullu",
    "sg:orig_category":"General Industrial Products",
    "sg:phone":"+90 212 253 5527",
    "sg:province":"Istanbul",
    "wof:name":"Senur Elek. Ve B?tangazli Cihaz. San. Tic. A.s.",
    "wof:placetype":"venue"
},
  "geometry": {"coordinates":[28.9660110474,41.0372772217],"type":"Point"}
}