{
  "type": "Feature",
  "properties": {
    "iso:country":"TR",
    "sg:address":"Istoc 13.ada No:161-163 Mahmutbeykoy-bagcilar",
    "sg:city":"Sihhiye",
    "sg:classifiers":[
        {
            "category":"Professional",
            "subcategory":"Testing Lab",
            "type":"Services"
        }
    ],
    "sg:phone":"+90 21265905072849",
    "sg:postcode":"06410",
    "sg:province":"Istanbul",
    "sg:tags":[
        "laboratory",
        "material"
    ],
    "wof:name":"Raftel Kimya Sanayi Ve Ticaret A.s.",
    "wof:placetype":"venue"
},
  "geometry": {"coordinates":[28.9759254456,41.0123786926],"type":"Point"}
}