{
  "type": "Feature",
  "properties": {
    "addr:full":"Perpa Tic. Merk. K:2 No:49 Okmeydani Karak?y Istanbul -",
    "addr:housenumber":"49;karak ? y",
    "addr:street":"K 2 No;Istanbul",
    "iso:country":"TR",
    "sg:address":"Perpa Tic. Merk. K:2 No:49 Okmeydani",
    "sg:city":"Karak?y",
    "sg:classifiers":[
        {
            "category":"Wholesale",
            "subcategory":"Machinery & Supplies",
            "type":"Manufacturing & Wholesale Goods"
        }
    ],
    "sg:phone":"+90 212 222 1066",
    "sg:postcode":"-",
    "sg:province":"Istanbul",
    "sg:tags":[
        "bearing",
        "ball"
    ],
    "wof:name":"Rultas Rulman San. Tic. A.s.",
    "wof:placetype":"venue"
},
  "geometry": {"coordinates":[28.975925,41.012379],"type":"Point"}
}