{
  "type": "Feature",
  "properties": {
    "addr:full":"Org.san. B?g. Demirciler Sitesi B-8 Blok No:173 Ikitelli / Istanbul Ikitelli Istanbul 34303",
    "addr:postcode":"34303",
    "iso:country":"TR",
    "sg:address":"Org.san. B?g. Demirciler Sitesi B-8 Blok No:173 Ikitelli / Istanbul",
    "sg:city":"Ikitelli",
    "sg:classifiers":[
        {
            "category":"Banks & Credit Unions",
            "subcategory":"Investment Brokerage",
            "type":"Services"
        }
    ],
    "sg:phone":"+90 2126712626729",
    "sg:postcode":"34303",
    "sg:province":"Istanbul",
    "sg:tags":[
        "-",
        "export",
        "import"
    ],
    "wof:name":"Jet Otomotik Kapi Sis. (euro Turizm Otomotiv Ins.gida Ith.ihr.san.tic.ltd,)",
    "wof:placetype":"venue"
},
  "geometry": {"coordinates":[28.9861831665,41.0408554077],"type":"Point"}
}