{
  "type": "Feature",
  "properties": {
    "addr:full":"Ikitelli Organize Sanayi B?gesi Galvano Teknik Sanayi Sitesi C Blok No:57 Ikitelli/K\u00fc\u00e7\u00fck\u00e7ekmece Istanbul 34670",
    "addr:housenumber":"?;blok no 57",
    "addr:postcode":"34670",
    "addr:street":"Organize Sanayi B",
    "iso:country":"TR",
    "sg:address":"Ikitelli Organize Sanayi B?gesi Galvano Teknik Sanayi Sitesi C Blok No:57",
    "sg:city":"Ikitelli/K\u00fc\u00e7\u00fck\u00e7ekmece",
    "sg:classifiers":[
        {
            "category":"Retail",
            "subcategory":"Storage",
            "type":"Services"
        }
    ],
    "sg:phone":"+90 2125491736549",
    "sg:postcode":"34670",
    "sg:province":"Istanbul",
    "sg:tags":[
        "shelving",
        "system"
    ],
    "sg:website":"kocakraf.com",
    "wof:name":"Ko?ak Madeni Dekorasyon San.tic.ltd.sti",
    "wof:placetype":"venue"
},
  "geometry": {"coordinates":[28.975925,41.012379],"type":"Point"}
}