{
  "type": "Feature",
  "properties": {
    "iso:country":"TR",
    "sg:address":"Tasdelen Cad.169.sok. No:62/a",
    "sg:city":"Siteler",
    "sg:classifiers":[
        {
            "category":"Government",
            "subcategory":"Fire Station",
            "type":"Public Place"
        }
    ],
    "sg:phone":"+90 312 348 8098",
    "sg:postcode":"07070",
    "sg:province":"Ankara",
    "sg:tags":[
        "decoration"
    ],
    "wof:name":"Duman Dekorasyon Insaat Ltd.sti.",
    "wof:placetype":"venue"
},
  "geometry": {"coordinates":[32.8604812622,39.9429283142],"type":"Point"}
}