{
  "type": "Feature",
  "properties": {
    "addr:full":"Atat?k Cd. No:33 Ikitelli/K\u00fc\u00e7\u00fck\u00e7ekmece Denizli 34660",
    "addr:housenumber":"no 33",
    "addr:postcode":"34660",
    "addr:street":"K Cd.",
    "iso:country":"TR",
    "sg:address":"Atat?k Cd. No:33",
    "sg:city":"Ikitelli/K\u00fc\u00e7\u00fck\u00e7ekmece",
    "sg:classifiers":[
        {
            "category":"Manufacturing",
            "subcategory":"Tools & Machinery",
            "type":"Manufacturing & Wholesale Goods"
        }
    ],
    "sg:phone":"+90 258 261 7816",
    "sg:postcode":"34660",
    "sg:province":"Denizli",
    "sg:tags":[
        "machine",
        "industry"
    ],
    "wof:name":"Kulis Makina",
    "wof:placetype":"venue"
},
  "geometry": {"coordinates":[29.0864906311,37.773525238],"type":"Point"}
}