{
  "type": "Feature",
  "properties": {
    "iso:country":"TR",
    "sg:address":"Karaman",
    "sg:city":"Ikitelli/K\u00fc\u00e7\u00fck\u00e7ekmece",
    "sg:classifiers":[
        {
            "category":"Health Services",
            "subcategory":"Hospital",
            "type":"Services"
        }
    ],
    "sg:phone":"+90 338 212 9564",
    "sg:postcode":"34660",
    "sg:province":"Karaman",
    "sg:tags":[
        "state"
    ],
    "wof:name":"Devlet Hastanesi",
    "wof:placetype":"venue"
},
  "geometry": {"coordinates":[33.094166,37.023056],"type":"Point"}
}