{
  "type": "Feature",
  "properties": {
    "iso:country":"TR",
    "sg:address":"Hosdere Cd. Resat N. Sk. G?es Apt. No:11 D:1 Y. Ayranci, Cankaya",
    "sg:city":"Findikzade- Fatih",
    "sg:classifiers":[
        {
            "category":"Building & Trades",
            "subcategory":"Construction",
            "type":"Services"
        }
    ],
    "sg:phone":"+90 312 468 7927",
    "sg:province":"Ankara",
    "sg:tags":[
        "foundation"
    ],
    "wof:name":"Av Ve Yaban Hayatini Koruma Gelistirme Tanitmavakfi",
    "wof:placetype":"venue"
},
  "geometry": {"coordinates":[32.8482971191,39.896900177],"type":"Point"}
}