{
  "type": "Feature",
  "properties": {
    "iso:country":"TR",
    "sg:address":"Dereboyu Cad. No:56",
    "sg:city":"Halkali",
    "sg:classifiers":[
        {
            "category":"Manufacturing",
            "subcategory":"Food",
            "type":"Manufacturing & Wholesale Goods"
        }
    ],
    "sg:phone":"+90 212 696 3430",
    "sg:postcode":"23410",
    "sg:province":"Istanbul",
    "sg:tags":[
        "product",
        "floury",
        "macaroni"
    ],
    "wof:name":"Sinangil Unlari San.tic. A.s.",
    "wof:placetype":"venue"
},
  "geometry": {"coordinates":[29.1046981812,41.0451660156],"type":"Point"}
}