{
  "type": "Feature",
  "properties": {
    "iso:country":"TR",
    "sg:address":"Zafer Mah. 85 Sokak No: 34",
    "sg:city":"Nazilli",
    "sg:classifiers":[
        {
            "category":"Manufacturing",
            "subcategory":"Food",
            "type":"Manufacturing & Wholesale Goods"
        }
    ],
    "sg:phone":"+90 256 313 1803",
    "sg:postcode":"65600",
    "sg:province":"Aydin",
    "sg:tags":[
        "wholesaler"
    ],
    "wof:name":"Nept?n Tic. Ltd. Sti.",
    "wof:placetype":"venue"
},
  "geometry": {"coordinates":[27.8527946472,37.8245239258],"type":"Point"}
}