{
  "type": "Feature",
  "properties": {
    "iso:country":"TR",
    "sg:address":"644 Sok. No:17 Akincilar-",
    "sg:city":"Sirinyer",
    "sg:classifiers":[
        {
            "category":"Manufacturing",
            "subcategory":"Glass & Minerals",
            "type":"Manufacturing & Wholesale Goods"
        }
    ],
    "sg:phone":"+90 232 237 7532",
    "sg:postcode":"35380",
    "sg:province":"Izmir",
    "sg:tags":[
        "glass-mirror"
    ],
    "wof:name":"Idil Elmas Uclu Daire Testere San Ve Tic Ltd.",
    "wof:placetype":"venue"
},
  "geometry": {"coordinates":[27.1406135559,38.3712997437],"type":"Point"}
}