{
  "type": "Feature",
  "properties": {
    "addr:full":"Demirtas Organize San. Bolgesi Cumhuriyet Cad. No:7 Demirtas Bursa 01680",
    "addr:postcode":"01680",
    "addr:street":"Organize;Cumhuriyet Cad. No 7 Demirtas Bursa",
    "iso:country":"TR",
    "sg:address":"Demirtas Organize San. Bolgesi Cumhuriyet Cad. No:7",
    "sg:city":"Demirtas",
    "sg:classifiers":[
        {
            "category":"Shopping",
            "subcategory":"Crafts & Fabrics",
            "type":"Retail Goods"
        }
    ],
    "sg:phone":"+90 224 262 2330",
    "sg:postcode":"01680",
    "sg:province":"Bursa",
    "sg:tags":[
        "knitting"
    ],
    "wof:name":"?r-sa ?rme",
    "wof:placetype":"venue"
},
  "geometry": {"coordinates":[29.0580043793,40.1947555542],"type":"Point"}
}