{
  "type": "Feature",
  "properties": {
    "addr:full":"Mustafa Irmak Ortak? Aksaray",
    "addr:street":"Mustafa;Ortak",
    "iso:country":"TR",
    "sg:address":"Mustafa Irmak",
    "sg:city":"Ortak?",
    "sg:classifiers":[
        {
            "category":"Government",
            "subcategory":"Office",
            "type":"Public Place"
        }
    ],
    "sg:phone":"+90 382 363 5045",
    "sg:province":"Aksaray",
    "sg:tags":[
        "municipality"
    ],
    "wof:name":"?iftevi Belediye Baskani",
    "wof:placetype":"venue"
},
  "geometry": {"coordinates":[39.2190437317,38.663860321],"type":"Point"}
}