{
  "type": "Feature",
  "properties": {
    "addr:full":"Mesrutiyet Mah. Kodaman Sk. No:31/3 Osmanbey Istanbul 63000",
    "addr:housenumber":"31 / 3",
    "addr:postcode":"63000",
    "addr:street":"Mesrutiyet Mah. Kodaman Sk. No",
    "iso:country":"TR",
    "sg:address":"Mesrutiyet Mah. Kodaman Sk. No:31/3",
    "sg:city":"Osmanbey",
    "sg:classifiers":[
        {
            "category":"Shopping",
            "subcategory":"Clothing, Apparel, & Fashions",
            "type":"Retail Goods"
        }
    ],
    "sg:phone":"+90 212 234 2606",
    "sg:postcode":"63000",
    "sg:province":"Istanbul",
    "sg:tags":[
        "woman",
        "wear"
    ],
    "wof:name":"Hikki Ipek Giyim San. Tic. Ltd. Sti.",
    "wof:placetype":"venue"
},
  "geometry": {"coordinates":[28.9912910461,41.054107666],"type":"Point"}
}