{
  "type": "Feature",
  "properties": {
    "addr:full":"R?garli Sk. No:14/12 Ulus Kizilay Ankara 06640",
    "addr:housenumber":"14 / 12",
    "addr:postcode":"06640",
    "addr:street":"Garli Sk. No;Ulus Kizilay",
    "iso:country":"TR",
    "sg:address":"R?garli Sk. No:14/12 Ulus",
    "sg:city":"Kizilay",
    "sg:classifiers":[
        {
            "category":"Building & Trades",
            "subcategory":"Plumbing",
            "type":"Services"
        }
    ],
    "sg:phone":"+90 312 312 7132",
    "sg:postcode":"06640",
    "sg:province":"Ankara",
    "wof:name":"G?roz Ltd. Sti.",
    "wof:placetype":"venue"
},
  "geometry": {"coordinates":[32.8563957214,39.9164428711],"type":"Point"}
}