{
  "type": "Feature",
  "properties": {
    "addr:full":"Eski Edirne Asfalti 2599.sok. No:8 Sultanciftligi- G.o.pasa Istanbul",
    "addr:housenumber":"no",
    "addr:street":"Eski",
    "iso:country":"TR",
    "sg:address":"Eski Edirne Asfalti 2599.sok. No:8 Sultanciftligi-",
    "sg:city":"G.o.pasa",
    "sg:classifiers":[
        {
            "category":"Building & Trades",
            "subcategory":"Landscaping Services",
            "type":"Services"
        }
    ],
    "sg:phone":"+90 21268318136191",
    "sg:province":"Istanbul",
    "sg:tags":[
        "landscape"
    ],
    "wof:name":"Bespinar Beton Boru Sanayi Ltd.sti.",
    "wof:placetype":"venue"
},
  "geometry": {"coordinates":[28.8288249969,41.135597229],"type":"Point"}
}