{
  "type": "Feature",
  "properties": {
    "iso:country":"TR",
    "sg:address":"10006. Sokak No:8/a Aosb.?igli",
    "sg:city":"Ikitelli/K\u00fc\u00e7\u00fck\u00e7ekmece",
    "sg:classifiers":[
        {
            "category":"Manufacturing",
            "subcategory":"Tools & Machinery",
            "type":"Manufacturing & Wholesale Goods"
        }
    ],
    "sg:phone":"+90 232 328 0089",
    "sg:postcode":"34670",
    "sg:province":"Izmir",
    "sg:tags":[
        "machine",
        "industry"
    ],
    "wof:name":"Skot Oil Makina Sanayi Ve Ticaret A.s.",
    "wof:placetype":"venue"
},
  "geometry": {"coordinates":[27.0387496948,38.4761390686],"type":"Point"}
}