{
  "type": "Feature",
  "properties": {
    "iso:country":"TR",
    "sg:address":"B??dere Cd. Levent",
    "sg:city":"Beyoglu",
    "sg:classifiers":[
        {
            "category":"Building & Trades",
            "subcategory":"Plumbing",
            "type":"Services"
        }
    ],
    "sg:phone":"+90 212 269 8339",
    "sg:postcode":"34000",
    "sg:province":"Istanbul",
    "wof:name":"Kalebodur A.s.",
    "wof:placetype":"venue"
},
  "geometry": {"coordinates":[29.0308074951,41.0980834961],"type":"Point"}
}