{
  "type": "Feature",
  "properties": {
    "addr:full":"Org. San. B?g. Aslim Sk. No:7 Kad\u0131k\u00f6y Konya",
    "addr:street":"Org.;Aslim Sk. No 7 Kadikoey",
    "iso:country":"TR",
    "sg:address":"Org. San. B?g. Aslim Sk. No:7",
    "sg:city":"Kad\u0131k\u00f6y",
    "sg:classifiers":[
        {
            "category":"Manufacturing",
            "subcategory":"Tools & Machinery",
            "type":"Manufacturing & Wholesale Goods"
        }
    ],
    "sg:phone":"+90 332 248 2240",
    "sg:province":"Konya",
    "sg:tags":[
        "machine",
        "industry"
    ],
    "wof:name":"Ceylan Mak. San. Tic. Ltd. Sti.",
    "wof:placetype":"venue"
},
  "geometry": {"coordinates":[32.4990272522,37.8715362549],"type":"Point"}
}