{
  "type": "Feature",
  "properties": {
    "iso:country":"TR",
    "sg:address":"Tibas Is Hani 1476. Sok. No:1/13 Alsancak",
    "sg:city":"Osmanbey",
    "sg:classifiers":[
        {
            "category":"Wholesale",
            "subcategory":"Plants",
            "type":"Manufacturing & Wholesale Goods"
        }
    ],
    "sg:phone":"+90 232 463 1740",
    "sg:postcode":"63000",
    "sg:province":"Izmir",
    "sg:tags":[
        "natural",
        "spice"
    ],
    "wof:name":"?zsezen Gida San.tic.ve Dagitim Ltd.sti.",
    "wof:placetype":"venue"
},
  "geometry": {"coordinates":[27.129686,38.418697],"type":"Point"}
}