{
  "type": "Feature",
  "properties": {
    "iso:country":"TR",
    "sg:address":"Guvenlik Cad.esenlik Sok. No:13/a A.ayranci",
    "sg:city":"Besiktas",
    "sg:classifiers":[
        {
            "category":"Shopping",
            "subcategory":"Stationery & Office Supplies",
            "type":"Retail Goods"
        }
    ],
    "sg:phone":"+90 312 426 7652",
    "sg:postcode":"34347",
    "sg:province":"Ankara",
    "wof:name":"Boyut Kirtasiye Bilgi.insaat.turz.ic Ve Dis.tic. Ltd. Sti.",
    "wof:placetype":"venue"
},
  "geometry": {"coordinates":[32.855206,39.899792],"type":"Point"}
}