{
  "type": "Feature",
  "properties": {
    "addr:full":"1373 Sk.suat Manisali Ishani No:8 K:2 D:202 Cankaya Merkez Izmir 22100",
    "addr:housenumber":"1373;2 d 202",
    "addr:postcode":"22100",
    "addr:street":"Sk.Suat Manisali Ishani No 8 K;Cankaya Merkez",
    "iso:country":"TR",
    "sg:address":"1373 Sk.suat Manisali Ishani No:8 K:2 D:202 Cankaya",
    "sg:city":"Merkez",
    "sg:classifiers":[
        {
            "category":"Professional",
            "subcategory":"Computer Services",
            "type":"Services"
        }
    ],
    "sg:phone":"+90 232 484 7375",
    "sg:postcode":"22100",
    "sg:province":"Izmir",
    "sg:tags":[
        "application",
        "software"
    ],
    "wof:name":"Servus Bilgisayar A .s .",
    "wof:placetype":"venue"
},
  "geometry": {"coordinates":[27.1423015594,38.4251480103],"type":"Point"}
}