{
  "type": "Feature",
  "properties": {
    "addr:full":"Tersane Cd. Kardesim Sk. Kursunlu Han Karak\u00f6y Istanbul",
    "addr:street":"Tersane Cd. Kardesim Sk.",
    "iso:country":"TR",
    "sg:address":"Tersane Cd. Kardesim Sk. Kursunlu Han",
    "sg:city":"Karak\u00f6y",
    "sg:classifiers":[
        {
            "category":"Home & Garden",
            "subcategory":"Hardware",
            "type":"Retail Goods"
        }
    ],
    "sg:phone":"+90 212 243 5289",
    "sg:province":"Istanbul",
    "sg:tags":[
        "store"
    ],
    "wof:name":"Yildiz Kardesler Hirdavat Mak. San. Tic. Ltd. Sti.",
    "wof:placetype":"venue"
},
  "geometry": {"coordinates":[28.9861793518,41.040851593],"type":"Point"}
}