{
  "type": "Feature",
  "properties": {
    "addr:full":"1722.sok. No:9 Gunesli Is Hani K: 2-207 Karsiyaka Mersin Izmir 52750",
    "addr:housenumber":"no;2-207",
    "addr:postcode":"52750",
    "addr:street":"Gunesli;Karsiyaka Mersin",
    "iso:country":"TR",
    "sg:address":"1722.sok. No:9 Gunesli Is Hani K: 2-207 Karsiyaka",
    "sg:city":"Mersin",
    "sg:classifiers":[
        {
            "category":"Professional",
            "subcategory":"Business Services",
            "type":"Services"
        }
    ],
    "sg:phone":"+90 232 369 6922",
    "sg:postcode":"52750",
    "sg:province":"Izmir",
    "sg:tags":[
        "food",
        "product",
        "exporter",
        "aricultural"
    ],
    "wof:name":"Cagim Ltd.sti.",
    "wof:placetype":"venue"
},
  "geometry": {"coordinates":[27.1296863556,38.4186973572],"type":"Point"}
}