{
  "type": "Feature",
  "properties": {
    "addr:full":"Anadolu Mah.mercan Sok.no:12 Kirkayak Bursa",
    "addr:housenumber":"12",
    "addr:street":"Sok.No",
    "iso:country":"TR",
    "sg:address":"Anadolu Mah.mercan Sok.no:12",
    "sg:city":"Kirkayak",
    "sg:classifiers":[
        {
            "category":"Shopping",
            "subcategory":"Clothing, Apparel, & Fashions",
            "type":"Retail Goods"
        }
    ],
    "sg:phone":"+90 224 360 7327",
    "sg:province":"Bursa",
    "sg:tags":[
        "ready",
        "wear"
    ],
    "wof:name":"Korkmazlar Tekstil San.ve Tic.ltd.sti.",
    "wof:placetype":"venue"
},
  "geometry": {"coordinates":[29.0876998901,40.1930732727],"type":"Point"}
}