{
  "type": "Feature",
  "properties": {
    "addr:full":"Cumhuriyet Mah. Dr. Cemal Kozanoglu Cd. No 141 Parkk?y Silivri Istanbul 34570",
    "addr:housenumber":"no",
    "addr:postcode":"34570",
    "addr:street":"Cumhuriyet Mah. Dr. Cemal Kozanoglu Cd.;Parkk;Y",
    "iso:country":"TR",
    "sg:address":"Cumhuriyet Mah. Dr. Cemal Kozanoglu Cd. No 141 Parkk?y",
    "sg:city":"Silivri",
    "sg:classifiers":[
        {
            "category":"Farming",
            "subcategory":"Poultry Farm",
            "type":"Manufacturing & Wholesale Goods"
        }
    ],
    "sg:phone":"+90 2127283323729",
    "sg:postcode":"34570",
    "sg:province":"Istanbul",
    "sg:tags":[
        "poultry-turkey-ostrich"
    ],
    "wof:name":"Vgs Veyisogullari Kulu?ka Makinalari Dis Tic. Ltd.",
    "wof:placetype":"venue"
},
  "geometry": {"coordinates":[28.9759254456,41.0123786926],"type":"Point"}
}