{
  "type": "Feature",
  "properties": {
    "addr:full":"Recai G?el Cd. 5 Aksaray Mugla 31030",
    "addr:housenumber":"?;5",
    "addr:postcode":"31030",
    "addr:street":"Recai G;El Cd.",
    "iso:country":"TR",
    "sg:address":"Recai G?el Cd. 5",
    "sg:city":"Aksaray",
    "sg:orig_category":"Hotels: Motels",
    "sg:phone":"+90 252 214 4629",
    "sg:postcode":"31030",
    "sg:province":"Mugla",
    "wof:name":"?zalp Otel",
    "wof:placetype":"venue"
},
  "geometry": {"coordinates":[28.3628406525,37.215675354],"type":"Point"}
}