{
  "type": "Feature",
  "properties": {
    "addr:full":"Elmadag Cd. No:111 Taksim B.?ekmece Istanbul",
    "addr:housenumber":"no;?",
    "addr:street":"Elmadag Cd.;B.",
    "iso:country":"TR",
    "sg:address":"Elmadag Cd. No:111 Taksim",
    "sg:city":"B.?ekmece",
    "sg:classifiers":[
        {
            "category":"Farming",
            "subcategory":"Fish & Marine Products",
            "type":"Manufacturing & Wholesale Goods"
        }
    ],
    "sg:phone":"+90 212 231 7656",
    "sg:province":"Istanbul",
    "sg:tags":[
        "automotive"
    ],
    "wof:name":"G?ven Otomotiv Makina San. Tic. A.s.",
    "wof:placetype":"venue"
},
  "geometry": {"coordinates":[28.9837837219,41.0367660522],"type":"Point"}
}