{
  "type": "Feature",
  "properties": {
    "iso:country":"TR",
    "sg:address":"Baris Mah.kosuyolu Cad.no:6 Gebze",
    "sg:city":"Ikitelli/K\u00fc\u00e7\u00fck\u00e7ekmece",
    "sg:classifiers":[
        {
            "category":"Manufacturing",
            "subcategory":"Tools & Machinery",
            "type":"Manufacturing & Wholesale Goods"
        }
    ],
    "sg:phone":"+90 262 641 2101",
    "sg:postcode":"34670",
    "sg:province":"Kocaeli",
    "sg:tags":[
        "machine",
        "industry"
    ],
    "wof:name":"Sultan Makina A.s.",
    "wof:placetype":"venue"
},
  "geometry": {"coordinates":[29.4639358521,40.7965049744],"type":"Point"}
}