{
  "type": "Feature",
  "properties": {
    "iso:country":"TR",
    "sg:address":"Bagdat Cd. Plaj Yolu No:4 Kartal",
    "sg:city":"B?y?k?ekmece",
    "sg:classifiers":[
        {
            "category":"Building & Trades",
            "subcategory":"Plumbing",
            "type":"Services"
        }
    ],
    "sg:phone":"+90 216 370 0744",
    "sg:postcode":"34900",
    "sg:province":"Istanbul",
    "wof:name":"Aktes Insaat Tesisat Ltd. Sti.",
    "wof:placetype":"venue"
},
  "geometry": {"coordinates":[29.0975627899,40.9515266418],"type":"Point"}
}