{
  "type": "Feature",
  "properties": {
    "addr:full":"Mesudiye Mh. 102 Sk.no:3/c Mersin I?el 52750",
    "addr:housenumber":"102;3 / c",
    "addr:postcode":"? el 52750",
    "addr:street":"Mh.;Sk.No",
    "iso:country":"TR",
    "sg:address":"Mesudiye Mh. 102 Sk.no:3/c",
    "sg:city":"Mersin",
    "sg:classifiers":[
        {
            "category":"Professional",
            "subcategory":"Business Services",
            "type":"Services"
        }
    ],
    "sg:phone":"+90 324 336 5377",
    "sg:postcode":"52750",
    "sg:province":"I?el",
    "sg:tags":[
        "food",
        "product",
        "exporter",
        "aricultural"
    ],
    "wof:name":"Cemal Gida A.s.",
    "wof:placetype":"venue"
},
  "geometry": {"coordinates":[37.7128486633,41.0530204773],"type":"Point"}
}