{
  "type": "Feature",
  "properties": {
    "iso:country":"TR",
    "sg:address":"Ala?m K?u",
    "sg:city":"Milas",
    "sg:classifiers":[
        {
            "category":"Food & Beverages",
            "subcategory":"Groceries & Convenience Stores",
            "type":"Retail Goods"
        }
    ],
    "sg:phone":"+90 252 512 1434",
    "sg:postcode":"48200",
    "sg:province":"Mugla",
    "sg:tags":[
        "olive",
        "oil"
    ],
    "wof:name":"Tireli Zeytinyagi Fab.",
    "wof:placetype":"venue"
},
  "geometry": {"coordinates":[28.3658008575,37.2196006775],"type":"Point"}
}