{
  "type": "Feature",
  "properties": {
    "addr:full":"Atakoy 9.kisim Atrium Carsi \u00c7orlu Istanbul",
    "iso:country":"TR",
    "sg:address":"Atakoy 9.kisim Atrium Carsi",
    "sg:city":"\u00c7orlu",
    "sg:classifiers":[
        {
            "category":"Shopping",
            "subcategory":"Pharmacy",
            "type":"Retail Goods"
        }
    ],
    "sg:phone":"+90 212 560 6282",
    "sg:province":"Istanbul",
    "sg:tags":[
        "store",
        "drug"
    ],
    "wof:name":"Yonca Eczanesi",
    "wof:placetype":"venue"
},
  "geometry": {"coordinates":[28.9861793518,41.040851593],"type":"Point"}
}