{
  "type": "Feature",
  "properties": {
    "iso:country":"TR",
    "sg:address":"275/4 Sok.no:2 D:9 Camkiran-",
    "sg:city":"Bornova",
    "sg:classifiers":[
        {
            "category":"Food & Beverages",
            "subcategory":"Groceries & Convenience Stores",
            "type":"Retail Goods"
        }
    ],
    "sg:phone":"+90 232 433 7928",
    "sg:postcode":"35040",
    "sg:province":"Izmir",
    "sg:tags":[
        "ready"
    ],
    "wof:name":"Firuz San. Ve Tic.",
    "wof:placetype":"venue"
},
  "geometry": {"coordinates":[27.2117557526,38.4634437561],"type":"Point"}
}