{
  "type": "Feature",
  "properties": {
    "addr:full":"Eski B??dere Cad No 22, Park Plaza Kat 3-19, 80670 Istanbul Esentepe Istanbul 01930",
    "addr:housenumber":"? ?;22;3-19",
    "addr:postcode":"80670;01930",
    "addr:street":"Eski B;Dere Cad No;Park Plaza Kat",
    "iso:country":"TR",
    "sg:address":"Eski B??dere Cad No 22, Park Plaza Kat 3-19, 80670 Istanbul",
    "sg:city":"Esentepe",
    "sg:classifiers":[
        {
            "category":"Banks & Credit Unions",
            "subcategory":"Bank",
            "type":"Services"
        }
    ],
    "sg:phone":"+90 21234503457",
    "sg:postcode":"01930",
    "sg:province":"Istanbul",
    "sg:website":"http://www.bayindirbank.com.tr",
    "wof:name":"Bayindirbank As",
    "wof:placetype":"venue"
},
  "geometry": {"coordinates":[28.975925,41.012379],"type":"Point"}
}