{
  "type": "Feature",
  "properties": {
    "addr:full":"Mehmet Turgut G?n?ek Bursa",
    "addr:housenumber":"?;?",
    "addr:street":"Turgut G;N",
    "iso:country":"TR",
    "sg:address":"Mehmet Turgut",
    "sg:city":"G?n?ek",
    "sg:classifiers":[
        {
            "category":"Government",
            "subcategory":"Office",
            "type":"Public Place"
        }
    ],
    "sg:phone":"+90 224 513 4520",
    "sg:province":"Bursa",
    "sg:tags":[
        "municipality"
    ],
    "wof:name":"Gemlik Belediye Baskani",
    "wof:placetype":"venue"
},
  "geometry": {"coordinates":[29.0532855988,40.2016792297],"type":"Point"}
}