{
  "type": "Feature",
  "properties": {
    "iso:country":"TR",
    "sg:address":"Demirtas Organize Sanayi B?gesi Orkide Sok. No. 11 16369 Demirtas Bursa",
    "sg:city":"Ikitelli/K\u00fc\u00e7\u00fck\u00e7ekmece",
    "sg:classifiers":[
        {
            "category":"Shopping",
            "subcategory":"Crafts & Fabrics",
            "type":"Retail Goods"
        }
    ],
    "sg:phone":"+90 224 261 0532",
    "sg:postcode":"34670",
    "sg:province":"Bursa",
    "wof:name":"Moral Tekstil San Ve Tic As",
    "wof:placetype":"venue"
},
  "geometry": {"coordinates":[29.0580043793,40.1947555542],"type":"Point"}
}