{
  "type": "Feature",
  "properties": {
    "addr:full":"Abd?lahedip Cad. No:1/a \u00c7ankaya Gaziantep",
    "addr:street":"Lahedip Cad. No 1 / A C\u0327Ankaya",
    "iso:country":"TR",
    "sg:address":"Abd?lahedip Cad. No:1/a",
    "sg:city":"\u00c7ankaya",
    "sg:classifiers":[
        {
            "category":"Wholesale",
            "subcategory":"Medical Equipment & Supplies",
            "type":"Manufacturing & Wholesale Goods"
        }
    ],
    "sg:phone":"+90 342 232 3133",
    "sg:province":"Gaziantep",
    "wof:name":"Hayat Ortopedi",
    "wof:placetype":"venue"
},
  "geometry": {"coordinates":[37.3781585693,37.0629348755],"type":"Point"}
}