{
  "type": "Feature",
  "properties": {
    "iso:country":"TR",
    "sg:address":"Asarcikli Cad. No:88",
    "sg:city":"Mersin",
    "sg:classifiers":[
        {
            "category":"Wholesale",
            "subcategory":"Home Furnishings",
            "type":"Manufacturing & Wholesale Goods"
        }
    ],
    "sg:phone":"+90 22223189392309",
    "sg:postcode":"52750",
    "sg:province":"Eskisehir",
    "sg:tags":[
        "furniture"
    ],
    "wof:name":"Yasar Aydogan-aydogan Mobilya",
    "wof:placetype":"venue"
},
  "geometry": {"coordinates":[30.5205249786,39.7728614807],"type":"Point"}
}