{
  "type": "Feature",
  "properties": {
    "addr:full":"Yesil Civril San.ustu Karabedirler Yolu Civril Denizli 44000",
    "addr:housenumber":"civril",
    "addr:postcode":"44000",
    "addr:street":"Karabedirler Yolu",
    "iso:country":"TR",
    "sg:address":"Yesil Civril San.ustu Karabedirler Yolu",
    "sg:city":"Civril",
    "sg:classifiers":[
        {
            "category":"Farming",
            "subcategory":"Farm",
            "type":"Manufacturing & Wholesale Goods"
        }
    ],
    "sg:phone":"+90 258 713 5598",
    "sg:postcode":"44000",
    "sg:province":"Denizli",
    "sg:tags":[
        "agricultural",
        "product"
    ],
    "wof:name":"Cavdaroglu Soguk Hava Deposu",
    "wof:placetype":"venue"
},
  "geometry": {"coordinates":[29.0864906311,37.773525238],"type":"Point"}
}