{
  "type": "Feature",
  "properties": {
    "addr:full":"60.yil Ishani No.11 Sisli ?ankiri 65710",
    "addr:housenumber":"no.11 sisli ?",
    "addr:postcode":"65710",
    "addr:street":"Ishani;Ankiri",
    "iso:country":"TR",
    "sg:address":"60.yil Ishani No.11",
    "sg:city":"Sisli",
    "sg:classifiers":[
        {
            "category":"Shopping",
            "subcategory":"Stationery & Office Supplies",
            "type":"Retail Goods"
        }
    ],
    "sg:phone":"+90 376 213 2648",
    "sg:postcode":"65710",
    "sg:province":"?ankiri",
    "wof:name":"Atilgan Kirtasiyecilik",
    "wof:placetype":"venue"
},
  "geometry": {"coordinates":[32.855591,39.921734],"type":"Point"}
}