{
  "type": "Feature",
  "properties": {
    "addr:full":"Anafartalar Cd. Ankara Pasaji No:44/116 Ulus Ankara 01940",
    "addr:housenumber":"116",
    "addr:postcode":"01940",
    "addr:street":"Anafartalar Cd.;No 44 /",
    "iso:country":"TR",
    "sg:address":"Anafartalar Cd. Ankara Pasaji No:44/116",
    "sg:city":"Ulus",
    "sg:classifiers":[
        {
            "category":"Manufacturing",
            "subcategory":"Building Materials",
            "type":"Manufacturing & Wholesale Goods"
        }
    ],
    "sg:phone":"+90 312 324 4318",
    "sg:postcode":"01940",
    "sg:province":"Ankara",
    "sg:tags":[
        "lifts-elevators"
    ],
    "wof:name":"Birlik Asans?r Makine Insaat San. Tic. Ltd. Sti.",
    "wof:placetype":"venue"
},
  "geometry": {"coordinates":[32.8560333252,39.9438743591],"type":"Point"}
}