{
  "type": "Feature",
  "properties": {
    "addr:full":"Nispetiye Cd. No:15 Etiler B.pasa Istanbul 34440",
    "addr:housenumber":"no 15",
    "addr:postcode":"34440",
    "addr:street":"Nispetiye Cd.;Etiler B.Pasa",
    "iso:country":"TR",
    "sg:address":"Nispetiye Cd. No:15 Etiler",
    "sg:city":"B.pasa",
    "sg:classifiers":[
        {
            "category":"Building & Trades",
            "subcategory":"Plumbing",
            "type":"Services"
        }
    ],
    "sg:phone":"+90 212 257 0401",
    "sg:postcode":"34440",
    "sg:province":"Istanbul",
    "wof:name":"Toros M?hendis. Taahh?t San. Tic. Ltd. Sti.",
    "wof:placetype":"venue"
},
  "geometry": {"coordinates":[29.026971817,41.0775299072],"type":"Point"}
}