{
  "type": "Feature",
  "properties": {
    "addr:full":"Buyukdere Cad. No: 3/4 Sisli Sisli Istanbul 65710",
    "addr:housenumber":"4",
    "addr:postcode":"65710",
    "addr:street":"Buyukdere Cad. No 3 /",
    "iso:country":"TR",
    "sg:address":"Buyukdere Cad. No: 3/4 Sisli",
    "sg:city":"Sisli",
    "sg:classifiers":[
        {
            "category":"Banks & Credit Unions",
            "subcategory":"Investment Brokerage",
            "type":"Services"
        }
    ],
    "sg:phone":"+90 212 247 4744",
    "sg:postcode":"65710",
    "sg:province":"Istanbul",
    "sg:tags":[
        "course",
        "language"
    ],
    "wof:name":"Yes English",
    "wof:placetype":"venue"
},
  "geometry": {"coordinates":[29.0139007568,41.0773048401],"type":"Point"}
}