{
  "type": "Feature",
  "properties": {
    "addr:full":"Selmanipak Cad Sedef Han 55/2 Uskudar Istanbul 34672",
    "addr:housenumber":"55 / 2",
    "addr:postcode":"34672",
    "addr:street":"Selmanipak Cad Sedef Han",
    "iso:country":"TR",
    "sg:address":"Selmanipak Cad Sedef Han 55/2",
    "sg:city":"Uskudar",
    "sg:classifiers":[
        {
            "category":"Airport",
            "subcategory":"International",
            "type":"Transportation"
        }
    ],
    "sg:phone":"+90 212495619293",
    "sg:postcode":"34672",
    "sg:province":"Istanbul",
    "wof:name":"S.s.avrasya Deniz Ve Turizm Motorlu Tasiyicilari Kooperatifi",
    "wof:placetype":"venue"
},
  "geometry": {"coordinates":[28.9861831665,41.0408554077],"type":"Point"}
}