{
  "type": "Feature",
  "properties": {
    "iso:country":"TR",
    "sg:address":"Istanbul Organize Deri Sanayi Bolgesi 12/5 Parsel Tuzla/istanbul",
    "sg:city":"64100",
    "sg:classifiers":[
        {
            "category":"Manufacturing",
            "subcategory":"Leather Goods",
            "type":"Manufacturing & Wholesale Goods"
        }
    ],
    "sg:phone":"+90 216 394 2074",
    "sg:province":"Istanbul",
    "sg:tags":[
        "machine"
    ],
    "wof:name":"As Deri Makina Iml. San.tic. Ltd",
    "wof:placetype":"venue"
},
  "geometry": {"coordinates":[28.9759254456,41.0123786926],"type":"Point"}
}