{
  "type": "Feature",
  "properties": {
    "addr:full":"Ishakpasa Mah. Ibrahimpasa Yokusu No:1 Kat:2 D:12 Nisanca-kumkapi 07100 Istanbul",
    "addr:housenumber":"kat 2 d 12",
    "addr:postcode":"07100",
    "addr:street":"Ishakpasa Mah. Ibrahimpasa Yokusu No 1;Nisanca-Kumkapi",
    "iso:country":"TR",
    "sg:address":"Ishakpasa Mah. Ibrahimpasa Yokusu No:1 Kat:2 D:12 Nisanca-kumkapi",
    "sg:city":"07100",
    "sg:classifiers":[
        {
            "category":"Professional",
            "subcategory":"Detective & Security Services",
            "type":"Services"
        }
    ],
    "sg:phone":"+90 212 518 4632",
    "sg:province":"Istanbul",
    "sg:tags":[
        "material"
    ],
    "wof:name":"Artoy Guvenlik Sistemleri Temizlik Hizmetleri Tic. A.s.",
    "wof:placetype":"venue"
},
  "geometry": {"coordinates":[28.975925,41.012379],"type":"Point"}
}