{
  "type": "Feature",
  "properties": {
    "iso:country":"TR",
    "sg:address":"Bagdat Cad. No:371 C.blok D:2",
    "sg:city":"Erenk?",
    "sg:classifiers":[
        {
            "category":"Marine",
            "type":"Transportation"
        }
    ],
    "sg:phone":"+90 216 356 2901",
    "sg:province":"Istanbul",
    "sg:tags":[
        "shipowner"
    ],
    "wof:name":"Dolphin Marine Shipping & Trading Ltd.",
    "wof:placetype":"venue"
},
  "geometry": {"coordinates":[31.155762,40.846657],"type":"Point"}
}