{
  "type": "Feature",
  "properties": {
    "addr:full":"Abdi Ipekci Cad. 1.emintas Sanayi Sitesi No: 158/83/84 Bayrampasa B\u00fcy\u00fck\u00e7ekmece Istanbul 34905",
    "addr:housenumber":"1.emintas;no;/ 83 / 84",
    "addr:postcode":"34905",
    "addr:street":"Ipekci Cad.;Sitesi",
    "iso:country":"TR",
    "sg:address":"Abdi Ipekci Cad. 1.emintas Sanayi Sitesi No: 158/83/84 Bayrampasa",
    "sg:city":"B\u00fcy\u00fck\u00e7ekmece",
    "sg:classifiers":[
        {
            "category":"Manufacturing",
            "subcategory":"Tools & Machinery",
            "type":"Manufacturing & Wholesale Goods"
        }
    ],
    "sg:phone":"+90 212 567 4520",
    "sg:postcode":"34905",
    "sg:province":"Istanbul",
    "sg:tags":[
        "machine",
        "industry"
    ],
    "wof:name":"G?rkap Makina Sanayi Ve Ticaret Ltd.sti.",
    "wof:placetype":"venue"
},
  "geometry": {"coordinates":[28.9759254456,41.0123786926],"type":"Point"}
}