{
  "type": "Feature",
  "properties": {
    "iso:country":"TR",
    "sg:address":"Hereke Halicilik San",
    "sg:city":"Gayrettepe",
    "sg:classifiers":[
        {
            "category":"Banks & Credit Unions",
            "subcategory":"Bank",
            "type":"Services"
        }
    ],
    "sg:phone":"+90 262 511 1042",
    "sg:postcode":"34349",
    "sg:province":"Izmit",
    "wof:name":"S?erbank Holding As",
    "wof:placetype":"venue"
},
  "geometry": {"coordinates":[29.948357,40.775986],"type":"Point"}
}