{
  "type": "Feature",
  "properties": {
    "addr:full":"Saim ?ikrik? Cadde No:83 Kisikk? Sanayi Sitesi Konak Izmir 35652",
    "addr:housenumber":"no 83;?",
    "addr:postcode":"35652",
    "addr:street":"Cadde;Kisikk;Sitesi",
    "iso:country":"TR",
    "sg:address":"Saim ?ikrik? Cadde No:83 Kisikk? Sanayi Sitesi",
    "sg:city":"Konak",
    "sg:classifiers":[
        {
            "category":"Shopping",
            "subcategory":"Computers & Home Electronics",
            "type":"Retail Goods"
        }
    ],
    "sg:phone":"+90 232 257 6162",
    "sg:postcode":"35652",
    "sg:province":"Izmir",
    "sg:tags":[
        "product",
        "electric-electronic"
    ],
    "wof:name":"Tosun Metal Elektronik Ve Insaat Sanayi Ticaret",
    "wof:placetype":"venue"
},
  "geometry": {"coordinates":[27.1423015594,38.4251480103],"type":"Point"}
}