{
  "type": "Feature",
  "properties": {
    "addr:full":"Imes San. Sit. C Blok No:304 Y.dudullu \u00dcmraniye Istanbul",
    "addr:housenumber":"blok no 304",
    "addr:street":"Y.Dudullu",
    "iso:country":"TR",
    "sg:address":"Imes San. Sit. C Blok No:304 Y.dudullu",
    "sg:city":"\u00dcmraniye",
    "sg:classifiers":[
        {
            "category":"Wholesale",
            "subcategory":"Machinery & Supplies",
            "type":"Manufacturing & Wholesale Goods"
        }
    ],
    "sg:phone":"+90 216 364 9201",
    "sg:province":"Istanbul",
    "sg:tags":[
        "press",
        "hydraulic"
    ],
    "wof:name":"Ihtiyar Hidrolik",
    "wof:placetype":"venue"
},
  "geometry": {"coordinates":[28.9861793518,41.040851593],"type":"Point"}
}