{
  "type": "Feature",
  "properties": {
    "addr:full":"Beyazkosk Cad. Murat Sok. No:7/3 Atalar Osmangazi Istanbul 16130",
    "addr:housenumber":"no 7 / 3",
    "addr:postcode":"16130",
    "addr:street":"Beyazkosk Cad. Murat Sok.;Atalar Osmangazi",
    "iso:country":"TR",
    "sg:address":"Beyazkosk Cad. Murat Sok. No:7/3 Atalar",
    "sg:city":"Osmangazi",
    "sg:classifiers":[
        {
            "category":"Wholesale",
            "subcategory":"Medical Equipment & Supplies",
            "type":"Manufacturing & Wholesale Goods"
        }
    ],
    "sg:phone":"+90 216 387 8083",
    "sg:postcode":"16130",
    "sg:province":"Istanbul",
    "sg:tags":[
        "material"
    ],
    "wof:name":"Ayca Medikal",
    "wof:placetype":"venue"
},
  "geometry": {"coordinates":[28.9861831665,41.0408554077],"type":"Point"}
}