{
  "type": "Feature",
  "properties": {
    "addr:full":"1202. Sok. No:46 Gida Carsisi Beypazari Izmir 06730",
    "addr:housenumber":"no 46",
    "addr:postcode":"06730",
    "addr:street":"Sok.",
    "iso:country":"TR",
    "sg:address":"1202. Sok. No:46 Gida Carsisi",
    "sg:city":"Beypazari",
    "sg:classifiers":[
        {
            "category":"Freight",
            "type":"Transportation"
        }
    ],
    "sg:phone":"+90 232 469 8686",
    "sg:postcode":"06730",
    "sg:province":"Izmir",
    "sg:tags":[
        "packing",
        "industry"
    ],
    "wof:name":"Caffaroglu Ambalaj Temizlik Ltd.sti.",
    "wof:placetype":"venue"
},
  "geometry": {"coordinates":[27.1296863556,38.4186973572],"type":"Point"}
}