{
  "type": "Feature",
  "properties": {
    "addr:full":"Buyukdere Cad.no.115-12 Zincirlikuyu Ikitelli/K\u00fc\u00e7\u00fck\u00e7ekmece Istanbul 34670",
    "addr:postcode":"34670",
    "addr:street":"Zincirlikuyu",
    "iso:country":"TR",
    "sg:address":"Buyukdere Cad.no.115-12 Zincirlikuyu",
    "sg:city":"Ikitelli/K\u00fc\u00e7\u00fck\u00e7ekmece",
    "sg:classifiers":[
        {
            "category":"Manufacturing",
            "subcategory":"Metals",
            "type":"Manufacturing & Wholesale Goods"
        }
    ],
    "sg:phone":"+90 212 211 3300",
    "sg:postcode":"34670",
    "sg:province":"Istanbul",
    "sg:tags":[
        "iron-steel",
        "peoducts"
    ],
    "wof:name":"Dokum-izabe Musavirlik Ve Mumessillik Ltd.sti.",
    "wof:placetype":"venue"
},
  "geometry": {"coordinates":[29.0144462585,41.0596199036],"type":"Point"}
}