{
  "type": "Feature",
  "properties": {
    "addr:full":"Dereagzi Mevkii Gurpinar Besiktas Istanbul 34350",
    "addr:postcode":"34350",
    "addr:street":"Dereagzi Mevkii Gurpinar",
    "iso:country":"TR",
    "sg:address":"Dereagzi Mevkii Gurpinar",
    "sg:city":"Besiktas",
    "sg:classifiers":[
        {
            "category":"Banks & Credit Unions",
            "subcategory":"Investment Brokerage",
            "type":"Services"
        }
    ],
    "sg:phone":"+90 212 880 0282",
    "sg:postcode":"34350",
    "sg:province":"Istanbul",
    "sg:tags":[
        "-",
        "export",
        "import"
    ],
    "wof:name":"Trans-sintez Dis Ticaret.ltd.",
    "wof:placetype":"venue"
},
  "geometry": {"coordinates":[28.9861831665,41.0408554077],"type":"Point"}
}