{
  "type": "Feature",
  "properties": {
    "iso:country":"TR",
    "sg:address":"Terazidere Mah.manastir Cad.barbaros Sok.no:53",
    "sg:city":"Bayrampasa",
    "sg:classifiers":[
        {
            "category":"Manufacturing",
            "subcategory":"Chemicals & Compounds",
            "type":"Manufacturing & Wholesale Goods"
        }
    ],
    "sg:phone":"+90 212 565 8946",
    "sg:postcode":"36100",
    "sg:province":"Istanbul",
    "sg:tags":[
        "galvanize"
    ],
    "wof:name":"Barut Galvano Kimya Sanayi",
    "wof:placetype":"venue"
},
  "geometry": {"coordinates":[28.8985118866,41.031955719],"type":"Point"}
}