{
  "type": "Feature",
  "properties": {
    "addr:full":"Hasim Iscan Bursa 16030",
    "addr:postcode":"16030",
    "iso:country":"TR",
    "sg:address":"Hasim Iscan",
    "sg:city":"Bursa",
    "sg:classifiers":[
        {
            "category":"Banks & Credit Unions",
            "subcategory":"Bank",
            "type":"Services"
        }
    ],
    "sg:phone":"+90 224 220 9191",
    "sg:province":"16030",
    "wof:name":"Turkish Bank As",
    "wof:placetype":"venue"
},
  "geometry": {"coordinates":[29.065571,40.187973],"type":"Point"}
}