{
  "type": "Feature",
  "properties": {
    "addr:full":"Manyasizade Cad. No:50/2 ?arsamba Fatih Fatih Istanbul 01740",
    "addr:housenumber":"50 / 2 ?",
    "addr:postcode":"01740",
    "addr:street":"Manyasizade Cad. No",
    "iso:country":"TR",
    "sg:address":"Manyasizade Cad. No:50/2 ?arsamba Fatih",
    "sg:city":"Fatih",
    "sg:classifiers":[
        {
            "category":"Building & Trades",
            "subcategory":"Construction",
            "type":"Services"
        }
    ],
    "sg:phone":"+90 212635112663",
    "sg:postcode":"01740",
    "sg:province":"Istanbul",
    "sg:tags":[
        "foundation"
    ],
    "wof:name":"Ismail Aga Camii Ilme Hizmet Vakfi",
    "wof:placetype":"venue"
},
  "geometry": {"coordinates":[28.9472465515,41.0246429443],"type":"Point"}
}