{
  "type": "Feature",
  "properties": {
    "iso:country":"TR",
    "sg:address":"H.sabanci Org. San B?.",
    "sg:city":"Suluca",
    "sg:classifiers":[
        {
            "category":"Shopping",
            "subcategory":"Crafts & Fabrics",
            "type":"Retail Goods"
        }
    ],
    "sg:phone":"+90 322 394 3711",
    "sg:postcode":"01350",
    "sg:province":"Adana",
    "sg:tags":[
        "yarn"
    ],
    "wof:name":"Isik Tekstil Sanayi Ve Ticaret Ltd.sti.",
    "wof:placetype":"venue"
},
  "geometry": {"coordinates":[35.3137359619,37.0007171631],"type":"Point"}
}