{
  "type": "Feature",
  "properties": {
    "iso:country":"TR",
    "sg:address":"Sair Nedim Cad.no:35",
    "sg:city":"Besiktas",
    "sg:classifiers":[
        {
            "category":"Personal",
            "subcategory":"Adult",
            "type":"Services"
        }
    ],
    "sg:phone":"+90 212 327 7072",
    "sg:postcode":"35400",
    "sg:province":"Istanbul",
    "sg:tags":[
        "material",
        "sexual"
    ],
    "wof:name":"Atlantis Shop",
    "wof:placetype":"venue"
},
  "geometry": {"coordinates":[29.001766,41.043861],"type":"Point"}
}