{
  "type": "Feature",
  "properties": {
    "addr:full":"Adana-ceyhan Yolu 10. Km Temsa Kars. Ikitelli/K\u00fc\u00e7\u00fck\u00e7ekmece Adana 34670",
    "addr:housenumber":"10 km;ikitelli / kuec\u0327uekc\u0327ekmece",
    "addr:postcode":"34670",
    "addr:street":"Adana-Ceyhan Yolu;Temsa Kars.;Adana",
    "iso:country":"TR",
    "sg:address":"Adana-ceyhan Yolu 10. Km Temsa Kars.",
    "sg:city":"Ikitelli/K\u00fc\u00e7\u00fck\u00e7ekmece",
    "sg:classifiers":[
        {
            "category":"Professional",
            "subcategory":"Business Services",
            "type":"Services"
        }
    ],
    "sg:phone":"+90 322 346 5058",
    "sg:postcode":"34670",
    "sg:province":"Adana",
    "sg:tags":[
        "industry",
        "casting"
    ],
    "wof:name":"?nl? D?k?m Ltd. Sti.",
    "wof:placetype":"venue"
},
  "geometry": {"coordinates":[35.3250198364,36.9854202271],"type":"Point"}
}