{
  "type": "Feature",
  "properties": {
    "addr:full":"Cagaloglu Ceridehane Sok. Aydin Han 5/2 Bayrampasa Istanbul 36100",
    "addr:housenumber":"5 / 2",
    "addr:postcode":"36100",
    "addr:street":"Ceridehane Sok. Aydin Han",
    "iso:country":"TR",
    "sg:address":"Cagaloglu Ceridehane Sok. Aydin Han 5/2",
    "sg:city":"Bayrampasa",
    "sg:classifiers":[
        {
            "category":"Shopping",
            "subcategory":"Crafts & Fabrics",
            "type":"Retail Goods"
        }
    ],
    "sg:phone":"+90 212 513 6858",
    "sg:postcode":"36100",
    "sg:province":"Istanbul",
    "sg:tags":[
        "yarn"
    ],
    "wof:name":"Doteks Iplik Elyaf Dis Tic.ltd.sti.",
    "wof:placetype":"venue"
},
  "geometry": {"coordinates":[28.9759254456,41.0123786926],"type":"Point"}
}