{
  "type": "Feature",
  "properties": {
    "iso:country":"TR",
    "sg:address":"Litros Yolu G?dallar San. Sit. No. 7/31 Bayrampasa",
    "sg:city":"Kartal",
    "sg:classifiers":[
        {
            "category":"Manufacturing",
            "subcategory":"Tools & Machinery",
            "type":"Manufacturing & Wholesale Goods"
        }
    ],
    "sg:phone":"+90 212 482 4103",
    "sg:postcode":"34876",
    "sg:province":"Istanbul",
    "sg:tags":[
        "machine",
        "industry"
    ],
    "wof:name":"Tosyali Makina San. Tic. Ltd. Sti.",
    "wof:placetype":"venue"
},
  "geometry": {"coordinates":[29.2291717529,40.9073181152],"type":"Point"}
}