{
  "type": "Feature",
  "properties": {
    "addr:full":"Dolapdere Cd. No:147 Sisli Bah\u00e7elievler Istanbul 34180",
    "addr:housenumber":"no",
    "addr:postcode":"34180",
    "addr:street":"Dolapdere Cd.;Sisli",
    "iso:country":"TR",
    "sg:address":"Dolapdere Cd. No:147 Sisli",
    "sg:city":"Bah\u00e7elievler",
    "sg:orig_category":"General Industrial Products",
    "sg:phone":"+90 212 241 7692",
    "sg:postcode":"34180",
    "sg:province":"Istanbul",
    "wof:name":"Kaplanlar Sogutma San. Tic. Ltd. Sti.",
    "wof:placetype":"venue"
},
  "geometry": {"coordinates":[28.9838733673,41.0459136963],"type":"Point"}
}