{
  "type": "Feature",
  "properties": {
    "addr:full":"Sahil Mah.kumsal Cad. Bahar Sok. No:9 Ciftlikkoy Yalova 46360",
    "addr:housenumber":"no 9",
    "addr:postcode":"46360",
    "addr:street":"Mah.Kumsal Cad. Bahar Sok.;Ciftlikkoy Yalova",
    "iso:country":"TR",
    "sg:address":"Sahil Mah.kumsal Cad. Bahar Sok. No:9",
    "sg:city":"Ciftlikkoy",
    "sg:classifiers":[
        {
            "category":"Farming",
            "subcategory":"Farm",
            "type":"Manufacturing & Wholesale Goods"
        }
    ],
    "sg:phone":"+90 226 352 9825",
    "sg:postcode":"46360",
    "sg:province":"Yalova",
    "sg:tags":[
        "agricultural",
        "product"
    ],
    "wof:name":"Aye Dis Tic.ltd.sti.",
    "wof:placetype":"venue"
},
  "geometry": {"coordinates":[29.3100585938,40.6636924744],"type":"Point"}
}