{
  "type": "Feature",
  "properties": {
    "iso:country":"TR",
    "sg:address":"?obanyildizi Sk. No:8/7 ?ankaya",
    "sg:city":"Maltepe",
    "sg:classifiers":[
        {
            "category":"Banks & Credit Unions",
            "subcategory":"Investment Brokerage",
            "type":"Services"
        }
    ],
    "sg:phone":"+90 312 467 6571",
    "sg:postcode":"34843",
    "sg:province":"Ankara",
    "sg:tags":[
        "-",
        "export",
        "import"
    ],
    "wof:name":"Sinyal Dis Tic. Ltd. Sti.",
    "wof:placetype":"venue"
},
  "geometry": {"coordinates":[32.8604812622,39.9429283142],"type":"Point"}
}