{
  "type": "Feature",
  "properties": {
    "iso:country":"TR",
    "sg:address":"Haci Sahin",
    "sg:city":"Ke??en",
    "sg:classifiers":[
        {
            "category":"Government",
            "subcategory":"Office",
            "type":"Public Place"
        }
    ],
    "sg:phone":"+90 312 328 6800",
    "sg:province":"Ankara",
    "sg:tags":[
        "municipality"
    ],
    "wof:name":"Pursaklar Belediye Baskani",
    "wof:placetype":"venue"
},
  "geometry": {"coordinates":[32.8765678406,39.9285087585],"type":"Point"}
}