{
  "type": "Feature",
  "properties": {
    "addr:full":"Ankara Cd. Berksun Apt. No:41 D:13 Bati Mh. Pendik Kad\u0131k\u00f6y Istanbul 34722",
    "addr:housenumber":"d 13;mh.",
    "addr:postcode":"34722",
    "iso:country":"TR",
    "sg:address":"Ankara Cd. Berksun Apt. No:41 D:13 Bati Mh. Pendik",
    "sg:city":"Kad\u0131k\u00f6y",
    "sg:classifiers":[
        {
            "category":"Organizations",
            "subcategory":"Membership Organization",
            "type":"Services"
        }
    ],
    "sg:phone":"+90 216 375 4086",
    "sg:postcode":"34722",
    "sg:province":"Istanbul",
    "wof:name":"Kadin Sanat Kultur Dernegi",
    "wof:placetype":"venue"
},
  "geometry": {"coordinates":[28.9861831665,41.0408554077],"type":"Point"}
}