{
  "type": "Feature",
  "properties": {
    "addr:full":"Ticarethane Sk. No:41/3-4 Cagaloglu Levent - Besiktas Istanbul",
    "addr:housenumber":"41 / 3-4",
    "addr:street":"Ticarethane Sk. No",
    "iso:country":"TR",
    "sg:address":"Ticarethane Sk. No:41/3-4 Cagaloglu",
    "sg:city":"Levent - Besiktas",
    "sg:classifiers":[
        {
            "category":"Shopping",
            "subcategory":"Stationery & Office Supplies",
            "type":"Retail Goods"
        }
    ],
    "sg:phone":"+90 212 513 6769",
    "sg:province":"Istanbul",
    "wof:name":"Kitsan Kitap Kirtasiye Ve Dagitim",
    "wof:placetype":"venue"
},
  "geometry": {"coordinates":[28.975925,41.012379],"type":"Point"}
}