{
  "type": "Feature",
  "properties": {
    "iso:country":"TR",
    "sg:address":"Denizciler Yolu Ozgur Sok. No:14",
    "sg:city":"K.yali",
    "sg:classifiers":[
        {
            "category":"Shopping",
            "subcategory":"Baby Store",
            "type":"Retail Goods"
        }
    ],
    "sg:phone":"+90 216 388 6033",
    "sg:province":"Istanbul",
    "sg:tags":[
        "wear"
    ],
    "wof:name":"Baysa Bebe",
    "wof:placetype":"venue"
},
  "geometry": {"coordinates":[29.132589,41.114395],"type":"Point"}
}