{
  "type": "Feature",
  "properties": {
    "addr:full":"Ataturk Bulvari No.234 G?c? Kocaeli",
    "addr:housenumber":"no.234 g ? c ?",
    "addr:street":"Ataturk Bulvari",
    "iso:country":"TR",
    "sg:address":"Ataturk Bulvari No.234",
    "sg:city":"G?c?",
    "sg:classifiers":[
        {
            "category":"Food & Beverages",
            "subcategory":"Dairy",
            "type":"Retail Goods"
        }
    ],
    "sg:phone":"+90 262414796364",
    "sg:province":"Kocaeli",
    "sg:tags":[
        "pruducts",
        "milk"
    ],
    "wof:name":"Ay-pa Ltd.sti.",
    "wof:placetype":"venue"
},
  "geometry": {"coordinates":[29.8327407837,40.7148361206],"type":"Point"}
}