{
  "type": "Feature",
  "properties": {
    "addr:full":"Y.tabakhaneler Topel Sk. No.17 Tuzla Bursa 01900",
    "addr:postcode":"01900",
    "addr:street":"Topel Sk. No.17;Bursa",
    "iso:country":"TR",
    "sg:address":"Y.tabakhaneler Topel Sk. No.17",
    "sg:city":"Tuzla",
    "sg:classifiers":[
        {
            "category":"Social Services",
            "subcategory":"Job Training",
            "type":"Services"
        }
    ],
    "sg:phone":"+90 224 236 3800",
    "sg:postcode":"01900",
    "sg:province":"Bursa",
    "sg:tags":[
        "tannery"
    ],
    "wof:name":"?zy?kselen Deri A.s.",
    "wof:placetype":"venue"
},
  "geometry": {"coordinates":[29.0586109161,40.1844291687],"type":"Point"}
}