{
  "type": "Feature",
  "properties": {
    "iso:country":"TR",
    "sg:address":"Bayramtepe Mah.kibris Cad. No:18 K.cekmece",
    "sg:city":"Merkez",
    "sg:classifiers":[
        {
            "category":"Retail",
            "subcategory":"Storage",
            "type":"Services"
        }
    ],
    "sg:phone":"+90 212 637 1985",
    "sg:postcode":"20100",
    "sg:province":"Istanbul",
    "sg:tags":[
        "shelving",
        "system"
    ],
    "wof:name":"Dekosan",
    "wof:placetype":"venue"
},
  "geometry": {"coordinates":[28.975925,41.012379],"type":"Point"}
}