{
  "type": "Feature",
  "properties": {
    "iso:country":"TR",
    "sg:address":"Tahtakale Cd. Emniyet Han No:309 Emin?? Istanbul",
    "sg:city":"Okmeydani/sisli",
    "sg:classifiers":[
        {
            "category":"Shopping",
            "subcategory":"Stationery & Office Supplies",
            "type":"Retail Goods"
        }
    ],
    "sg:phone":"+90 212 512 1715",
    "sg:province":"Istanbul",
    "wof:name":"Mesut Kirtasiye",
    "wof:placetype":"venue"
},
  "geometry": {"coordinates":[28.975925,41.012379],"type":"Point"}
}