{
  "type": "Feature",
  "properties": {
    "iso:country":"TR",
    "sg:address":"Ggardenya 3-12 Blok D:2",
    "sg:city":"Atasehir",
    "sg:classifiers":[
        {
            "category":"Home & Garden",
            "subcategory":"Building Materials",
            "type":"Retail Goods"
        }
    ],
    "sg:phone":"+90 216 455 2826",
    "sg:postcode":"34758",
    "sg:province":"Istanbul",
    "sg:tags":[
        "stone",
        "natural",
        "marble"
    ],
    "wof:name":"Leonardo Granit Sanayii Ltd.sti.",
    "wof:placetype":"venue"
},
  "geometry": {"coordinates":[28.9105815887,41.049079895],"type":"Point"}
}