{
  "type": "Feature",
  "properties": {
    "addr:full":"Altay Cesme Mah.istiklal Cad. Birsen Sok.ozyasam Sit.b Blok No:1 Maltepe Istanbul 01000",
    "addr:housenumber":"blok no 1",
    "addr:postcode":"01000",
    "addr:street":"Mah.Istiklal Cad. Birsen Sok.Ozyasam Sit.B;Istanbul",
    "iso:country":"TR",
    "sg:address":"Altay Cesme Mah.istiklal Cad. Birsen Sok.ozyasam Sit.b Blok No:1",
    "sg:city":"Maltepe",
    "sg:classifiers":[
        {
            "category":"Manufacturing",
            "subcategory":"Chemicals & Compounds",
            "type":"Manufacturing & Wholesale Goods"
        }
    ],
    "sg:phone":"+90 216 441 8204",
    "sg:postcode":"01000",
    "sg:province":"Istanbul",
    "sg:tags":[
        "agricultural"
    ],
    "sg:website":"tarkoilaclama.com.tr",
    "wof:name":"Tarko Dis Tic.temizlik Gida Insaat.ltd.sti.",
    "wof:placetype":"venue"
},
  "geometry": {"coordinates":[28.9759254456,41.0123786926],"type":"Point"}
}