{
  "type": "Feature",
  "properties": {
    "addr:full":"Kore Sehit. Cd. No:36/1 Zincirlikuyu \u00dcmraniye Istanbul",
    "addr:housenumber":"no 36 / 1",
    "addr:street":"Sehit. Cd.;Zincirlikuyu",
    "iso:country":"TR",
    "sg:address":"Kore Sehit. Cd. No:36/1 Zincirlikuyu",
    "sg:city":"\u00dcmraniye",
    "sg:classifiers":[
        {
            "category":"Farming",
            "subcategory":"Fish & Marine Products",
            "type":"Manufacturing & Wholesale Goods"
        }
    ],
    "sg:phone":"+90 212 288 3275",
    "sg:province":"Istanbul",
    "sg:tags":[
        "automotive"
    ],
    "wof:name":"Viha-gti Dis Tic. Pazarlama Ltd. Sti.",
    "wof:placetype":"venue"
},
  "geometry": {"coordinates":[28.9759254456,41.0123786926],"type":"Point"}
}