{
  "type": "Feature",
  "properties": {
    "addr:full":"Sanayi Site. A Blok No:35 Acipayam Ikitelli/K\u00fc\u00e7\u00fck\u00e7ekmece Denizli 34670",
    "addr:housenumber":"blok no 35",
    "addr:postcode":"34670",
    "addr:street":"Site.",
    "iso:country":"TR",
    "sg:address":"Sanayi Site. A Blok No:35 Acipayam",
    "sg:city":"Ikitelli/K\u00fc\u00e7\u00fck\u00e7ekmece",
    "sg:classifiers":[
        {
            "category":"Retail",
            "subcategory":"Auto Repair",
            "type":"Services"
        }
    ],
    "sg:phone":"+90 258 518 2101",
    "sg:postcode":"34670",
    "sg:province":"Denizli",
    "sg:tags":[
        "maintenance"
    ],
    "wof:name":"Emin Tic.",
    "wof:placetype":"venue"
},
  "geometry": {"coordinates":[29.0788803101,37.7851867676],"type":"Point"}
}