{
  "type": "Feature",
  "properties": {
    "iso:country":"TR",
    "sg:address":"Yama?sk. No:4",
    "sg:city":"4.levent",
    "sg:classifiers":[
        {
            "category":"Manufacturing",
            "subcategory":"Glass & Minerals",
            "type":"Manufacturing & Wholesale Goods"
        }
    ],
    "sg:phone":"+90 212 264 9860",
    "sg:province":"Istanbul",
    "sg:tags":[
        "glass-mirror"
    ],
    "wof:name":"Erissan Cam Ve Ayna San. Tic. A.s.",
    "wof:placetype":"venue"
},
  "geometry": {"coordinates":[29.3034763336,40.833316803],"type":"Point"}
}