{
  "type": "Feature",
  "properties": {
    "iso:country":"TR",
    "sg:address":"Bilecik",
    "sg:city":"Ikitelli/K\u00fc\u00e7\u00fck\u00e7ekmece",
    "sg:classifiers":[
        {
            "category":"Health Services",
            "subcategory":"Hospital",
            "type":"Services"
        }
    ],
    "sg:phone":"+90 228 212 1036",
    "sg:postcode":"34660",
    "sg:province":"Bilecik",
    "sg:tags":[
        "state"
    ],
    "wof:name":"Devlet Hastanesi",
    "wof:placetype":"venue"
},
  "geometry": {"coordinates":[30.125834,40.106667],"type":"Point"}
}