{
  "type": "Feature",
  "properties": {
    "addr:full":"Kumbasi Mah.1 Nolu Sok. No:11 Torbali Ordu 35860",
    "addr:housenumber":"no 11",
    "addr:postcode":"35860",
    "addr:street":"Nolu Sok.;Torbali Ordu",
    "iso:country":"TR",
    "sg:address":"Kumbasi Mah.1 Nolu Sok. No:11",
    "sg:city":"Torbali",
    "sg:classifiers":[
        {
            "category":"Food & Beverages",
            "subcategory":"Groceries & Convenience Stores",
            "type":"Retail Goods"
        }
    ],
    "sg:phone":"+90 452 223 3461",
    "sg:postcode":"35860",
    "sg:province":"Ordu",
    "sg:tags":[
        "ready"
    ],
    "wof:name":"Goksa Gida San.ve Tic.ltd.sti.",
    "wof:placetype":"venue"
},
  "geometry": {"coordinates":[37.8740005493,40.9880981445],"type":"Point"}
}