{
  "type": "Feature",
  "properties": {
    "addr:full":"Demirciler Sit. 9. Cd. No:30 Zeytinburnu Y?egir Istanbul 01180",
    "addr:housenumber":"9 cd. no 30",
    "addr:postcode":"01180",
    "addr:street":"Sit.;Zeytinburnu Y ?",
    "iso:country":"TR",
    "sg:address":"Demirciler Sit. 9. Cd. No:30 Zeytinburnu",
    "sg:city":"Y?egir",
    "sg:classifiers":[
        {
            "category":"Manufacturing",
            "subcategory":"Metals",
            "type":"Manufacturing & Wholesale Goods"
        }
    ],
    "sg:phone":"+90 212 546 9610",
    "sg:postcode":"01180",
    "sg:province":"Istanbul",
    "sg:tags":[
        "industry"
    ],
    "wof:name":"Defne Metal San. Tic. Ltd. Sti.",
    "wof:placetype":"venue"
},
  "geometry": {"coordinates":[28.9759254456,41.0123786926],"type":"Point"}
}