{
  "type": "Feature",
  "properties": {
    "addr:full":"Dr. Esat Isik Cad. Dr. L?tfi Bey Apt. No:20 D?kkan 3. Kad\u0131k\u00f6y Istanbul 34990",
    "addr:housenumber":"?;d;3",
    "addr:postcode":"34990",
    "addr:street":"Dr.;Isik Cad. Dr. L;Kkan",
    "iso:country":"TR",
    "sg:address":"Dr. Esat Isik Cad. Dr. L?tfi Bey Apt. No:20 D?kkan 3.",
    "sg:city":"Kad\u0131k\u00f6y",
    "sg:classifiers":[
        {
            "category":"Travel",
            "subcategory":"Travel Agent",
            "type":"Entertainment"
        }
    ],
    "sg:phone":"+90 346813353",
    "sg:postcode":"34990",
    "sg:province":"Istanbul",
    "sg:tags":[
        "agency",
        "tourism"
    ],
    "wof:name":"Hurricane Tur Turizm",
    "wof:placetype":"venue"
},
  "geometry": {"coordinates":[28.9861831665,41.0408554077],"type":"Point"}
}