{
  "type": "Feature",
  "properties": {
    "addr:full":"Abide-i Hurriyet Cad. No:165/7 Sisli Istanbul 65710",
    "addr:housenumber":"165 / 7",
    "addr:postcode":"65710",
    "addr:street":"Hurriyet Cad. No",
    "iso:country":"TR",
    "sg:address":"Abide-i Hurriyet Cad. No:165/7",
    "sg:city":"Sisli",
    "sg:classifiers":[
        {
            "category":"Transit Center",
            "subcategory":"Freight",
            "type":"Transportation"
        }
    ],
    "sg:phone":"+90 212 219 9419",
    "sg:postcode":"65710",
    "sg:province":"Istanbul",
    "wof:name":"Tm Container Lines",
    "wof:placetype":"venue"
},
  "geometry": {"coordinates":[28.9843883514,41.0535774231],"type":"Point"}
}