{
  "type": "Feature",
  "properties": {
    "addr:full":"Farabi Sk. 40/3 Cankaya Merkez Ankara 32100",
    "addr:housenumber":"3",
    "addr:postcode":"32100",
    "addr:street":"Farabi Sk. 40 /",
    "iso:country":"TR",
    "sg:address":"Farabi Sk. 40/3 Cankaya",
    "sg:city":"Merkez",
    "sg:classifiers":[
        {
            "category":"Wholesale",
            "subcategory":"Medical Equipment & Supplies",
            "type":"Manufacturing & Wholesale Goods"
        }
    ],
    "sg:phone":"+90 312 428 6845",
    "sg:postcode":"32100",
    "sg:province":"Ankara",
    "wof:name":"Ekimsan Ltd. Sti.",
    "wof:placetype":"venue"
},
  "geometry": {"coordinates":[32.8604812622,39.9429283142],"type":"Point"}
}