{
  "type": "Feature",
  "properties": {
    "iso:country":"TR",
    "sg:address":"Rustuye Sok. 46/a 81030 Kalamis",
    "sg:city":"Merkez",
    "sg:classifiers":[
        {
            "category":"Wholesale",
            "subcategory":"Medical Equipment & Supplies",
            "type":"Manufacturing & Wholesale Goods"
        }
    ],
    "sg:phone":"+90 216 418 3337",
    "sg:postcode":"26000",
    "sg:province":"Istanbul",
    "sg:tags":[
        "material"
    ],
    "wof:name":"Sbs Dis Ticaret A.s.",
    "wof:placetype":"venue"
},
  "geometry": {"coordinates":[29.0393447876,40.9825897217],"type":"Point"}
}