{
  "type": "Feature",
  "properties": {
    "iso:country":"TR",
    "sg:address":"Yeni Yalova Yolu Belediye Bah? Tesisleri Arkasi Akg? Sk.no:37 (?zdilek Yani)",
    "sg:city":"Osmangazi",
    "sg:classifiers":[
        {
            "category":"Farming",
            "subcategory":"Fish & Marine Products",
            "type":"Manufacturing & Wholesale Goods"
        }
    ],
    "sg:phone":"+90 224 211 3175",
    "sg:postcode":"16070",
    "sg:province":"Bursa",
    "sg:tags":[
        "automotive"
    ],
    "wof:name":"Mutlu Karoseri Otom.ve Mak.san.ve Tic.ltd.sti",
    "wof:placetype":"venue"
},
  "geometry": {"coordinates":[29.0256233215,40.2018089294],"type":"Point"}
}