{
  "type": "Feature",
  "properties": {
    "addr:full":"Ali Osman Bayrak Ivrindi Denizli 10770",
    "addr:postcode":"10770",
    "iso:country":"TR",
    "sg:address":"Ali Osman Bayrak",
    "sg:city":"Ivrindi",
    "sg:classifiers":[
        {
            "category":"Government",
            "subcategory":"Office",
            "type":"Public Place"
        }
    ],
    "sg:phone":"+90 258 279 2139",
    "sg:postcode":"10770",
    "sg:province":"Denizli",
    "sg:tags":[
        "municipality"
    ],
    "wof:name":"Korucuuk Belediye Baskani",
    "wof:placetype":"venue"
},
  "geometry": {"coordinates":[29.0864906311,37.773525238],"type":"Point"}
}