{
  "type": "Feature",
  "properties": {
    "addr:full":"H?riyet Mh. Okul Sk. No:22/2 Sisli G?tepe Istanbul",
    "addr:housenumber":"22 / 2;?",
    "addr:street":"Riyet Mh. Okul Sk. No;Sisli G",
    "iso:country":"TR",
    "sg:address":"H?riyet Mh. Okul Sk. No:22/2 Sisli",
    "sg:city":"G?tepe",
    "sg:classifiers":[
        {
            "category":"Wholesale",
            "subcategory":"Home Furnishings",
            "type":"Manufacturing & Wholesale Goods"
        }
    ],
    "sg:phone":"+90 212 224 9658",
    "sg:province":"Istanbul",
    "sg:tags":[
        "furniture"
    ],
    "wof:name":"Tasarim Koltuk",
    "wof:placetype":"venue"
},
  "geometry": {"coordinates":[28.9891490936,41.0614891052],"type":"Point"}
}