{
  "type": "Feature",
  "properties": {
    "iso:country":"TR",
    "sg:address":"Kurbagalidere C. Sarig?el Ish. No.6/8",
    "sg:city":"Kad\u0131k\u00f6y",
    "sg:classifiers":[
        {
            "category":"Farming",
            "subcategory":"Farm",
            "type":"Manufacturing & Wholesale Goods"
        }
    ],
    "sg:phone":"+90 216 336 4366",
    "sg:postcode":"34990",
    "sg:province":"Istanbul",
    "sg:tags":[
        "agricultural",
        "product"
    ],
    "wof:name":"Bio Tarim ?rnl. San.ltd.sti.",
    "wof:placetype":"venue"
},
  "geometry": {"coordinates":[28.9759254456,41.0123786926],"type":"Point"}
}