{
  "type": "Feature",
  "properties": {
    "addr:full":"Des Sanayi Sitesi 112 Sk. D:02 Blok No: 02 Dudullu Merkez Istanbul 20100",
    "addr:housenumber":"112;02 blok no 02",
    "addr:postcode":"20100",
    "addr:street":"Des Sanayi Sitesi;Sk. D",
    "iso:country":"TR",
    "sg:address":"Des Sanayi Sitesi 112 Sk. D:02 Blok No: 02 Dudullu",
    "sg:city":"Merkez",
    "sg:classifiers":[
        {
            "category":"Home & Garden",
            "subcategory":"Kitchen Supply",
            "type":"Retail Goods"
        }
    ],
    "sg:phone":"+90 216 314 4275",
    "sg:postcode":"20100",
    "sg:province":"Istanbul",
    "sg:tags":[
        "steel",
        "utensil"
    ],
    "wof:name":"Guven Celik San. Ve Tic. Ltd. Sti.",
    "wof:placetype":"venue"
},
  "geometry": {"coordinates":[28.975925,41.012379],"type":"Point"}
}