{
  "type": "Feature",
  "properties": {
    "addr:full":"Ulus Mah 2115 Sok. No:7 K1 D:3-4 \u00dcmraniye Antalya 81231",
    "addr:housenumber":"no 7 k1 d 3-4",
    "addr:postcode":"2115;81231",
    "addr:street":"Mah;Sok.",
    "iso:country":"TR",
    "sg:address":"Ulus Mah 2115 Sok. No:7 K1 D:3-4",
    "sg:city":"\u00dcmraniye",
    "sg:classifiers":[
        {
            "category":"Manufacturing",
            "subcategory":"Building Materials",
            "type":"Manufacturing & Wholesale Goods"
        }
    ],
    "sg:phone":"+90 242 344 0887",
    "sg:postcode":"81231",
    "sg:province":"Antalya",
    "sg:tags":[
        "lifts-elevators"
    ],
    "wof:name":"Cesa Asansorleri Elektrik San Tic Ltd.",
    "wof:placetype":"venue"
},
  "geometry": {"coordinates":[30.688659668,36.910949707],"type":"Point"}
}