{
  "type": "Feature",
  "properties": {
    "addr:full":"Ilce Tarim Mudurlugu Susurluk Balikesir 10600",
    "addr:postcode":"10600",
    "addr:street":"Ilce;Balikesir",
    "iso:country":"TR",
    "sg:address":"Ilce Tarim Mudurlugu",
    "sg:city":"Susurluk",
    "sg:classifiers":[
        {
            "category":"Farming",
            "subcategory":"Farm & Veterinary Services",
            "type":"Manufacturing & Wholesale Goods"
        }
    ],
    "sg:phone":"+90 266865191686",
    "sg:postcode":"10600",
    "sg:province":"Balikesir",
    "sg:tags":[
        "veterinarian"
    ],
    "wof:name":"Mustafa Toklu",
    "wof:placetype":"venue"
},
  "geometry": {"coordinates":[27.965669632,40.3411865234],"type":"Point"}
}