{
  "type": "Feature",
  "properties": {
    "addr:full":"Bozkurt Cad.no:52 Kahramanlar Izmir 25700",
    "addr:housenumber":"52",
    "addr:postcode":"25700",
    "addr:street":"Kahramanlar Izmir",
    "iso:country":"TR",
    "sg:address":"Bozkurt Cad.no:52",
    "sg:city":"Kahramanlar",
    "sg:classifiers":[
        {
            "category":"Home & Garden",
            "subcategory":"Household Appliances",
            "type":"Retail Goods"
        }
    ],
    "sg:phone":"+90 232 445 2652",
    "sg:postcode":"25700",
    "sg:province":"Izmir",
    "sg:tags":[
        "conditioner",
        "air"
    ],
    "wof:name":"Ozkay Elk.elkn.klima Ltd.sti.",
    "wof:placetype":"venue"
},
  "geometry": {"coordinates":[27.1473617554,38.4247283936],"type":"Point"}
}