{
  "type": "Feature",
  "properties": {
    "addr:full":"Sanayi Sitesi Ciftlik Yolu No:10 Iskilkip Etiler ?orum 07010",
    "addr:housenumber":"no 10;?",
    "addr:postcode":"07010",
    "addr:street":"Sanayi Sitesi Ciftlik Yolu;Iskilkip Etiler",
    "iso:country":"TR",
    "sg:address":"Sanayi Sitesi Ciftlik Yolu No:10 Iskilkip",
    "sg:city":"Etiler",
    "sg:classifiers":[
        {
            "category":"Manufacturing",
            "subcategory":"Wood Products",
            "type":"Manufacturing & Wholesale Goods"
        }
    ],
    "sg:phone":"+90 364 531 2069",
    "sg:postcode":"07010",
    "sg:province":"?orum",
    "sg:tags":[
        "forest"
    ],
    "wof:name":"Agzikara Orman Urunleri Tic.ltd.sti.",
    "wof:placetype":"venue"
},
  "geometry": {"coordinates":[30.7143802643,36.8939399719],"type":"Point"}
}