{
  "type": "Feature",
  "properties": {
    "addr:full":"1.anafartalar Mh. 3 Sok. No: 6/5 Nisantasi Manisa 25370",
    "addr:housenumber":"no 6 / 5",
    "addr:postcode":"25370",
    "addr:street":"Mh. 3 Sok.;Nisantasi Manisa",
    "iso:country":"TR",
    "sg:address":"1.anafartalar Mh. 3 Sok. No: 6/5",
    "sg:city":"Nisantasi",
    "sg:classifiers":[
        {
            "category":"Banks & Credit Unions",
            "subcategory":"Investment Brokerage",
            "type":"Services"
        }
    ],
    "sg:phone":"+90 236 238 9658",
    "sg:postcode":"25370",
    "sg:province":"Manisa",
    "sg:tags":[
        "-",
        "export",
        "import"
    ],
    "wof:name":"Elit Dis Tic.ltd.",
    "wof:placetype":"venue"
},
  "geometry": {"coordinates":[27.4269599915,38.6141242981],"type":"Point"}
}