{
  "type": "Feature",
  "properties": {
    "iso:country":"TR",
    "sg:address":"Istanbul",
    "sg:city":"Bodrum",
    "sg:classifiers":[
        {
            "category":"Home & Garden",
            "subcategory":"Building Materials",
            "type":"Retail Goods"
        }
    ],
    "sg:phone":"+90 216 346 9231",
    "sg:postcode":"48400",
    "sg:province":"Istanbul",
    "sg:tags":[
        "stone",
        "natural",
        "marble"
    ],
    "wof:name":"Derinkok Marble Company",
    "wof:placetype":"venue"
},
  "geometry": {"coordinates":[29.1482200623,40.9827156067],"type":"Point"}
}