{
  "type": "Feature",
  "properties": {
    "iso:country":"TR",
    "sg:address":"B??hendek Cad. No.89 Sishane",
    "sg:city":"Bodrum",
    "sg:classifiers":[
        {
            "category":"Shopping",
            "subcategory":"Gifts & Souvenirs",
            "type":"Retail Goods"
        }
    ],
    "sg:phone":"+90 212 251 9132",
    "sg:postcode":"48400",
    "sg:province":"Istanbul",
    "wof:name":"Kumtel Telekom A.s.",
    "wof:placetype":"venue"
},
  "geometry": {"coordinates":[28.9671516418,41.0297813416],"type":"Point"}
}