{
  "type": "Feature",
  "properties": {
    "addr:full":"Orta Mah. Yeni Camii Karsisi No: 8 Gerede Bolu 14900",
    "addr:postcode":"14900",
    "addr:street":"No 8 Gerede Bolu",
    "iso:country":"TR",
    "sg:address":"Orta Mah. Yeni Camii Karsisi No: 8",
    "sg:city":"Gerede",
    "sg:classifiers":[
        {
            "category":"Travel",
            "subcategory":"Travel Agent",
            "type":"Entertainment"
        }
    ],
    "sg:phone":"+90 3743116574311",
    "sg:postcode":"14900",
    "sg:province":"Bolu",
    "sg:tags":[
        "agency",
        "tourism"
    ],
    "wof:name":"Uzman Turizm",
    "wof:placetype":"venue"
},
  "geometry": {"coordinates":[31.5988750458,40.7306365967],"type":"Point"}
}