{
  "type": "Feature",
  "properties": {
    "iso:country":"TR",
    "sg:address":"Rihtim Cad.",
    "sg:city":"Kadikoy",
    "sg:orig_category":"Hotels: Motels",
    "sg:phone":"+90 21234989418",
    "sg:postcode":"01370",
    "sg:province":"Istanbul",
    "wof:name":"Rihtim Hotel",
    "wof:placetype":"venue"
},
  "geometry": {"coordinates":[29.1290931702,40.9200286865],"type":"Point"}
}