{
  "type": "Feature",
  "properties": {
    "iso:country":"TR",
    "sg:address":"Istiklal Cd. No:348/15 Beyoglu",
    "sg:city":"Sisli",
    "sg:classifiers":[
        {
            "category":"Professional",
            "subcategory":"Detective & Security Services",
            "type":"Services"
        }
    ],
    "sg:phone":"+90 212 249 5070",
    "sg:postcode":"80270",
    "sg:province":"Istanbul",
    "sg:tags":[
        "material"
    ],
    "wof:name":"T?v Stutgart Teknik G?venlik Ltd. Sti.",
    "wof:placetype":"venue"
},
  "geometry": {"coordinates":[28.983305,41.035969],"type":"Point"}
}