{
  "type": "Feature",
  "properties": {
    "iso:country":"TR",
    "sg:address":"1453 Sk. No:14 Cagdas Apt. K.3 D.7",
    "sg:city":"Alsancak",
    "sg:classifiers":[
        {
            "category":"Freight",
            "type":"Transportation"
        }
    ],
    "sg:phone":"+90 232 424 4204",
    "sg:postcode":"01365",
    "sg:province":"Izmir",
    "sg:tags":[
        "agent",
        "shipping",
        "broker"
    ],
    "wof:name":"Simirna Denizcilik Nak. Trzm. Ve San. Tic. Ltd. Sti.",
    "wof:placetype":"venue"
},
  "geometry": {"coordinates":[27.082228,38.499607],"type":"Point"}
}