{
  "type": "Feature",
  "properties": {
    "iso:country":"TR",
    "sg:address":"41. Sk. No:12",
    "sg:city":"Ostim",
    "sg:classifiers":[
        {
            "category":"Manufacturing",
            "subcategory":"Building Materials",
            "type":"Manufacturing & Wholesale Goods"
        }
    ],
    "sg:phone":"+90 312 354 6516",
    "sg:postcode":"06374",
    "sg:province":"Ankara",
    "sg:tags":[
        "lifts-elevators"
    ],
    "wof:name":"Merih Asans?r San. Tic. Paz. Ltd. Sti.",
    "wof:placetype":"venue"
},
  "geometry": {"coordinates":[32.8966827393,39.9410324097],"type":"Point"}
}