{
  "type": "Feature",
  "properties": {
    "addr:full":"Davutpasa Cad.no: 34 Topkapi Okmeydani Istanbul 43050",
    "addr:housenumber":"34",
    "addr:postcode":"43050",
    "iso:country":"TR",
    "sg:address":"Davutpasa Cad.no: 34 Topkapi",
    "sg:city":"Okmeydani",
    "sg:classifiers":[
        {
            "category":"Home & Garden",
            "subcategory":"Hardware",
            "type":"Retail Goods"
        }
    ],
    "sg:phone":"+90 212 482 1600",
    "sg:postcode":"43050",
    "sg:province":"Istanbul",
    "sg:tags":[
        "generator",
        "power"
    ],
    "wof:name":"Cukurova Ithalat",
    "wof:placetype":"venue"
},
  "geometry": {"coordinates":[28.9270591736,41.0156517029],"type":"Point"}
}