{
  "type": "Feature",
  "properties": {
    "addr:full":"847. Sk. No:28/106 Konak Kartal Izmir 46000",
    "addr:housenumber":"28 / 106",
    "addr:postcode":"46000",
    "addr:street":"847 Sk. No;Konak Kartal",
    "iso:country":"TR",
    "sg:address":"847. Sk. No:28/106 Konak",
    "sg:city":"Kartal",
    "sg:classifiers":[
        {
            "category":"Wholesale",
            "subcategory":"Medical Equipment & Supplies",
            "type":"Manufacturing & Wholesale Goods"
        }
    ],
    "sg:phone":"+90 232 441 8471",
    "sg:postcode":"46000",
    "sg:province":"Izmir",
    "sg:tags":[
        "material"
    ],
    "wof:name":"Kalyon Medikal Ltd. Sti.",
    "wof:placetype":"venue"
},
  "geometry": {"coordinates":[27.1304893494,38.4168815613],"type":"Point"}
}