{
  "type": "Feature",
  "properties": {
    "addr:full":"1038 Sk. No.55 Yesildere \u00c7orlu Izmir",
    "addr:housenumber":"1038",
    "addr:street":"Sk. No.55 Yesildere",
    "iso:country":"TR",
    "sg:address":"1038 Sk. No.55 Yesildere",
    "sg:city":"\u00c7orlu",
    "sg:classifiers":[
        {
            "category":"Shopping",
            "subcategory":"Luggage & Leather Goods",
            "type":"Retail Goods"
        }
    ],
    "sg:phone":"+90 232 449 4676",
    "sg:province":"Izmir",
    "sg:tags":[
        "leather-fur",
        "wear"
    ],
    "wof:name":"Tirpan Deri Ltd.sti.",
    "wof:placetype":"venue"
},
  "geometry": {"coordinates":[27.1526126862,38.4090957642],"type":"Point"}
}