{
  "type": "Feature",
  "properties": {
    "addr:full":"Ayazaga Tic. Merk. B Blok Kat 15 Maslak Istanbul 34398",
    "addr:housenumber":"blok kat 15",
    "addr:postcode":"34398",
    "iso:country":"TR",
    "sg:address":"Ayazaga Tic. Merk. B Blok Kat 15",
    "sg:city":"Maslak",
    "sg:classifiers":[
        {
            "category":"Marine",
            "type":"Transportation"
        }
    ],
    "sg:phone":"+90 212 285 1212",
    "sg:postcode":"34398",
    "sg:province":"Istanbul",
    "sg:tags":[
        "shipowner"
    ],
    "wof:name":"Endo Denizcilika.s.",
    "wof:placetype":"venue"
},
  "geometry": {"coordinates":[29.019806,41.122284],"type":"Point"}
}