{
  "type": "Feature",
  "properties": {
    "addr:full":"Icacan Sok.no: 7/6 G.o.pasa Ankara",
    "addr:housenumber":"7 / 6",
    "addr:street":"Sok.No;G.O.Pasa",
    "iso:country":"TR",
    "sg:address":"Icacan Sok.no: 7/6",
    "sg:city":"G.o.pasa",
    "sg:classifiers":[
        {
            "category":"Parking",
            "subcategory":"Garage",
            "type":"Transportation"
        }
    ],
    "sg:phone":"+90 312 437 4362",
    "sg:province":"Ankara",
    "sg:tags":[
        "zipper"
    ],
    "wof:name":"Acatay Ltd.sti.",
    "wof:placetype":"venue"
},
  "geometry": {"coordinates":[32.8681602478,39.8960456848],"type":"Point"}
}