{
  "type": "Feature",
  "properties": {
    "addr:full":"B?? San. Cd. S?g? Sk. No:5 Iskitler Maltepe Ankara 01000",
    "addr:housenumber":"? ?;?",
    "addr:postcode":"01000",
    "addr:street":"B;San. Cd. S ? G;Sk. No 5 Iskitler Maltepe Ankara",
    "iso:country":"TR",
    "sg:address":"B?? San. Cd. S?g? Sk. No:5 Iskitler",
    "sg:city":"Maltepe",
    "sg:classifiers":[
        {
            "category":"Wholesale",
            "subcategory":"Books, Periodicals, & Newspapers",
            "type":"Manufacturing & Wholesale Goods"
        }
    ],
    "sg:phone":"+90 312 341 6186",
    "sg:postcode":"01000",
    "sg:province":"Ankara",
    "sg:tags":[
        "house",
        "publishing"
    ],
    "wof:name":"Karaman Teneke San. Tic. Ltd. Sti.",
    "wof:placetype":"venue"
},
  "geometry": {"coordinates":[32.8560333252,39.9438743591],"type":"Point"}
}