{
  "type": "Feature",
  "properties": {
    "iso:country":"TR",
    "sg:address":"100. Yil Mah. 435 Sk. No: 7/b Balgat",
    "sg:city":"Mecidiyek\u00f6y",
    "sg:classifiers":[
        {
            "category":"Shopping",
            "subcategory":"Party Supplies",
            "type":"Retail Goods"
        }
    ],
    "sg:phone":"+90 312 284 3366",
    "sg:province":"Ankara",
    "sg:tags":[
        "sound",
        "light",
        "system"
    ],
    "wof:name":"Demir Elektronik Ic & Dis Ticaret",
    "wof:placetype":"venue"
},
  "geometry": {"coordinates":[32.7858123779,39.9541511536],"type":"Point"}
}