{
  "type": "Feature",
  "properties": {
    "addr:full":"Kisikli Cd. No:90 Altunizade Osmangazi Istanbul 46050",
    "addr:housenumber":"no 90",
    "addr:postcode":"46050",
    "addr:street":"Kisikli Cd.",
    "iso:country":"TR",
    "sg:address":"Kisikli Cd. No:90 Altunizade",
    "sg:city":"Osmangazi",
    "sg:classifiers":[
        {
            "category":"Manufacturing",
            "subcategory":"Rubber & Plastics",
            "type":"Manufacturing & Wholesale Goods"
        }
    ],
    "sg:phone":"+90 216 339 3571",
    "sg:postcode":"46050",
    "sg:province":"Istanbul",
    "sg:tags":[
        "industry"
    ],
    "wof:name":"Pilsa A.s.",
    "wof:placetype":"venue"
},
  "geometry": {"coordinates":[29.0498027802,41.0229682922],"type":"Point"}
}