{
  "type": "Feature",
  "properties": {
    "iso:country":"TR",
    "sg:address":"Cumhuriyet Bulvari No:300/604",
    "sg:city":"Ulus",
    "sg:classifiers":[
        {
            "category":"Banks & Credit Unions",
            "subcategory":"Investment Brokerage",
            "type":"Services"
        }
    ],
    "sg:phone":"+90 232 463 3132",
    "sg:postcode":"34800",
    "sg:province":"Izmir",
    "sg:tags":[
        "-",
        "export",
        "import"
    ],
    "wof:name":"Intra I? Dis Tic. Ltd. Sti.",
    "wof:placetype":"venue"
},
  "geometry": {"coordinates":[27.1423015594,38.4251480103],"type":"Point"}
}