{
  "type": "Feature",
  "properties": {
    "iso:country":"TR",
    "sg:address":"Perpa Tic.merkezi A.blok Kat:9 No:1208 Okmeydani",
    "sg:city":"Iskenderun",
    "sg:classifiers":[
        {
            "category":"Building & Trades",
            "subcategory":"Electrical",
            "type":"Services"
        }
    ],
    "sg:phone":"+90 212 221 7741",
    "sg:postcode":"31200",
    "sg:province":"Istanbul",
    "sg:tags":[
        "equipment",
        "electric"
    ],
    "wof:name":"Elmas Elektrik Tic.",
    "wof:placetype":"venue"
},
  "geometry": {"coordinates":[28.9861831665,41.0408554077],"type":"Point"}
}