{
  "type": "Feature",
  "properties": {
    "iso:country":"TR",
    "sg:address":"Ulubas Cad. Dagistanli Sok. No:16 4.levent",
    "sg:city":"Ikitelli/K\u00fc\u00e7\u00fck\u00e7ekmece",
    "sg:classifiers":[
        {
            "category":"Manufacturing",
            "subcategory":"Tools & Machinery",
            "type":"Manufacturing & Wholesale Goods"
        }
    ],
    "sg:phone":"+90 212 279 8348",
    "sg:postcode":"34660",
    "sg:province":"Istanbul",
    "sg:tags":[
        "machine",
        "industry"
    ],
    "wof:name":"Sefa Metal Imalat Sanayi",
    "wof:placetype":"venue"
},
  "geometry": {"coordinates":[29.0040111542,41.0971031189],"type":"Point"}
}