{
  "type": "Feature",
  "properties": {
    "iso:country":"TR",
    "sg:address":"Girne Mah. Ataturk Cad. Elif Sok. No:7",
    "sg:city":"Beyoglu",
    "sg:classifiers":[
        {
            "category":"Wholesale",
            "subcategory":"Machinery & Supplies",
            "type":"Manufacturing & Wholesale Goods"
        }
    ],
    "sg:phone":"+90 216 442 0502",
    "sg:postcode":"46810",
    "sg:province":"Istanbul",
    "sg:tags":[
        "heavy",
        "construction",
        "macinery"
    ],
    "wof:name":"Ada Makina Kiralama Nak Ve Dis Tic.ltd.sti.",
    "wof:placetype":"venue"
},
  "geometry": {"coordinates":[28.9861831665,41.0408554077],"type":"Point"}
}