{
  "type": "Feature",
  "properties": {
    "addr:full":"Hilmi Cd. No:22 K.esat Findikzade-fatih Istanbul",
    "addr:housenumber":"no 22",
    "addr:street":"Hilmi Cd.",
    "iso:country":"TR",
    "sg:address":"Hilmi Cd. No:22 K.esat",
    "sg:city":"Findikzade-fatih",
    "sg:classifiers":[
        {
            "category":"Building & Trades",
            "subcategory":"Construction",
            "type":"Services"
        }
    ],
    "sg:phone":"+90 312 417 8685",
    "sg:province":"Istanbul",
    "sg:tags":[
        "foundation"
    ],
    "wof:name":"Turkiye Kalkinma Vakfi T.",
    "wof:placetype":"venue"
},
  "geometry": {"coordinates":[32.500617981,37.8714065552],"type":"Point"}
}