{
  "type": "Feature",
  "properties": {
    "addr:full":"Abidei Hurriyet Cad. No:111 Dilek Apt. D:2 Sisli 07100 Istanbul",
    "addr:housenumber":"111;2",
    "addr:postcode":"07100",
    "addr:street":"Hurriyet Cad. No;D",
    "iso:country":"TR",
    "sg:address":"Abidei Hurriyet Cad. No:111 Dilek Apt. D:2 Sisli",
    "sg:city":"07100",
    "sg:orig_category":"Scavening Services",
    "sg:phone":"+90 212 246 2268",
    "sg:province":"Istanbul",
    "wof:name":"Tem-pak Temizlik Ltd.sti.",
    "wof:placetype":"venue"
},
  "geometry": {"coordinates":[28.987904,41.058693],"type":"Point"}
}