{
  "type": "Feature",
  "properties": {
    "addr:full":"Yeni San. Sit. Blok No:22 Aksehir Bagcilar Konya 33115",
    "addr:postcode":"33115",
    "iso:country":"TR",
    "sg:address":"Yeni San. Sit. Blok No:22 Aksehir",
    "sg:city":"Bagcilar",
    "sg:classifiers":[
        {
            "category":"Wholesale",
            "subcategory":"Home Furnishings",
            "type":"Manufacturing & Wholesale Goods"
        }
    ],
    "sg:phone":"+90 332 813 9961",
    "sg:postcode":"33115",
    "sg:province":"Konya",
    "sg:tags":[
        "furniture"
    ],
    "wof:name":"Oya Mobilya",
    "wof:placetype":"venue"
},
  "geometry": {"coordinates":[33.0667152405,39.2111282349],"type":"Point"}
}