{
  "type": "Feature",
  "properties": {
    "addr:full":"Ahmet G?? Nazilli Aydin 65600",
    "addr:housenumber":"? ?",
    "addr:postcode":"65600",
    "addr:street":"Ahmet G;Aydin",
    "iso:country":"TR",
    "sg:address":"Ahmet G??",
    "sg:city":"Nazilli",
    "sg:classifiers":[
        {
            "category":"Government",
            "subcategory":"Office",
            "type":"Public Place"
        }
    ],
    "sg:phone":"+90 256 347 6002",
    "sg:postcode":"65600",
    "sg:province":"Aydin",
    "sg:tags":[
        "municipality"
    ],
    "wof:name":"Isabeyli Belediye Baskani",
    "wof:placetype":"venue"
},
  "geometry": {"coordinates":[27.2790355682,37.7410469055],"type":"Point"}
}