{
  "type": "Feature",
  "properties": {
    "addr:full":"Silifke Cd.eski Mezgitli Yolu Kavsagi Davultepe Koyu Turuncova I?el 07880",
    "addr:housenumber":"kavsagi;koyu;?",
    "addr:postcode":"07880",
    "addr:street":"Mezgitli Yolu;I;El",
    "iso:country":"TR",
    "sg:address":"Silifke Cd.eski Mezgitli Yolu Kavsagi Davultepe Koyu",
    "sg:city":"Turuncova",
    "sg:classifiers":[
        {
            "category":"Food & Beverages",
            "subcategory":"Fruits & Vegetables",
            "type":"Retail Goods"
        }
    ],
    "sg:phone":"+90 324 231 6797",
    "sg:postcode":"07880",
    "sg:province":"I?el",
    "sg:tags":[
        "fresh"
    ],
    "wof:name":"Samad Ltd.sti",
    "wof:placetype":"venue"
},
  "geometry": {"coordinates":[33.9208984375,36.3728981018],"type":"Point"}
}