{
  "type": "Feature",
  "properties": {
    "addr:full":"Tahtakale T. Sk. Isik Han K:2 Emin?? Istanbul Emin\u00f6n\u00fc/Ca\u011falo\u011flu Istanbul",
    "addr:housenumber":"2;? ?",
    "addr:street":"T. Sk.",
    "iso:country":"TR",
    "sg:address":"Tahtakale T. Sk. Isik Han K:2 Emin?? Istanbul",
    "sg:city":"Emin\u00f6n\u00fc/Ca\u011falo\u011flu",
    "sg:classifiers":[
        {
            "category":"Shopping",
            "subcategory":"Stationery & Office Supplies",
            "type":"Retail Goods"
        }
    ],
    "sg:phone":"+90 212 511 9598",
    "sg:province":"Istanbul",
    "wof:name":"?zdemir Kirtasiye",
    "wof:placetype":"venue"
},
  "geometry": {"coordinates":[28.975925,41.012379],"type":"Point"}
}