{
  "type": "Feature",
  "properties": {
    "iso:country":"TR",
    "sg:address":"Samanyolu Sk. No.29/8 Sisli",
    "sg:city":"\u00c7orlu",
    "sg:classifiers":[
        {
            "category":"Shopping",
            "subcategory":"Luggage & Leather Goods",
            "type":"Retail Goods"
        }
    ],
    "sg:phone":"+90 212 232 2229",
    "sg:province":"Istanbul",
    "sg:tags":[
        "leather-fur",
        "wear"
    ],
    "wof:name":"Ra-ka Ith.ihr. Ltd.sti.",
    "wof:placetype":"venue"
},
  "geometry": {"coordinates":[28.9877815247,41.0550422668],"type":"Point"}
}