{
  "type": "Feature",
  "properties": {
    "iso:country":"TR",
    "sg:address":"Ankara Asfalti Soganli Sapagi Karsisi Kartal",
    "sg:city":"Sel?klu",
    "sg:classifiers":[
        {
            "category":"Wholesale",
            "subcategory":"Auto Parts",
            "type":"Manufacturing & Wholesale Goods"
        }
    ],
    "sg:phone":"+90 216 488 6721",
    "sg:province":"Istanbul",
    "sg:tags":[
        "spare"
    ],
    "wof:name":"Honda Anadolu Motosiklet Uretim Ve Pazarlama A.s.",
    "wof:placetype":"venue"
},
  "geometry": {"coordinates":[29.2189102173,40.9053115845],"type":"Point"}
}