{
  "type": "Feature",
  "properties": {
    "iso:country":"TR",
    "sg:address":"160.sok. No:8 Karacaoglan Mah.",
    "sg:city":"Isikkent",
    "sg:classifiers":[
        {
            "category":"Wholesale",
            "subcategory":"Machinery & Supplies",
            "type":"Manufacturing & Wholesale Goods"
        }
    ],
    "sg:phone":"+90 232 436 4949",
    "sg:postcode":"32100",
    "sg:province":"Izmir",
    "sg:tags":[
        "agricultural"
    ],
    "wof:name":"Arpaz Tarim Ve Sulama Ekipmanlari Ltd.sti.",
    "wof:placetype":"venue"
},
  "geometry": {"coordinates":[27.2001399994,38.4306106567],"type":"Point"}
}