{
  "type": "Feature",
  "properties": {
    "iso:country":"TR",
    "sg:address":"Buyukdere Cad. Akincibiyik Sok.no:6",
    "sg:city":"M.koy",
    "sg:classifiers":[
        {
            "category":"Food & Beverages",
            "subcategory":"Groceries & Convenience Stores",
            "type":"Retail Goods"
        }
    ],
    "sg:phone":"+90 212 274 8536",
    "sg:province":"Istanbul",
    "sg:tags":[
        "ready"
    ],
    "wof:name":"C.p.standart Gida San.ve Tic.a.s.",
    "wof:placetype":"venue"
},
  "geometry": {"coordinates":[28.9759254456,41.0123786926],"type":"Point"}
}