{
  "type": "Feature",
  "properties": {
    "iso:country":"TR",
    "sg:address":"Hanimeli Sk. No:15/10 Sihhiye",
    "sg:city":"B.?ekmece",
    "sg:classifiers":[
        {
            "category":"Farming",
            "subcategory":"Fish & Marine Products",
            "type":"Manufacturing & Wholesale Goods"
        }
    ],
    "sg:phone":"+90 312 230 3435",
    "sg:province":"Ankara",
    "sg:tags":[
        "automotive"
    ],
    "wof:name":"G?nalp Ltd. Sti.",
    "wof:placetype":"venue"
},
  "geometry": {"coordinates":[32.8530845642,39.9264030457],"type":"Point"}
}