{
  "type": "Feature",
  "properties": {
    "iso:country":"TR",
    "sg:address":"Osman Kavuncu Cad. 11. Km. Ambar",
    "sg:city":"K???k?ekmece",
    "sg:classifiers":[
        {
            "category":"Home & Garden",
            "subcategory":"Household Appliances",
            "type":"Retail Goods"
        }
    ],
    "sg:phone":"+90 352311344631",
    "sg:province":"Kayseri",
    "sg:tags":[
        "kitchenware"
    ],
    "wof:name":"Artel Madeni Esya San. Tic.",
    "wof:placetype":"venue"
},
  "geometry": {"coordinates":[35.3675422668,38.7507095337],"type":"Point"}
}