{
  "type": "Feature",
  "properties": {
    "iso:country":"TR",
    "sg:address":"2.matbaacilar Sit.3 Ne 22",
    "sg:city":"Topkapi",
    "sg:classifiers":[
        {
            "category":"Manufacturing",
            "subcategory":"Textiles",
            "type":"Manufacturing & Wholesale Goods"
        }
    ],
    "sg:phone":"+90 212 316 4754",
    "sg:postcode":"24620",
    "sg:province":"Istanbul",
    "sg:tags":[
        "weaving",
        "narrow",
        "-",
        "label"
    ],
    "wof:name":"Buka -plast Damla Etiket",
    "wof:placetype":"venue"
},
  "geometry": {"coordinates":[29.3868732452,40.8826560974],"type":"Point"}
}