{
  "type": "Feature",
  "properties": {
    "iso:country":"TR",
    "sg:address":"Ziya Gokalp Cad. No:32/a",
    "sg:city":"Kizilay",
    "sg:classifiers":[
        {
            "category":"Building & Trades",
            "subcategory":"Electrical",
            "type":"Services"
        }
    ],
    "sg:phone":"+90 312 433 6551",
    "sg:postcode":"23050",
    "sg:province":"Ankara",
    "sg:tags":[
        "equipment",
        "lighting"
    ],
    "wof:name":"Gulcan Avize Aydinlatma Dek San Tic Ltd.",
    "wof:placetype":"venue"
},
  "geometry": {"coordinates":[32.8593482971,39.9217262268],"type":"Point"}
}