{
  "type": "Feature",
  "properties": {
    "addr:full":"Merkez: Behzat Cad. No:156 Aksaray Tokat 34280",
    "addr:housenumber":"156",
    "addr:postcode":"34280",
    "addr:street":"Behzat Cad. No",
    "iso:country":"TR",
    "sg:address":"Merkez: Behzat Cad. No:156",
    "sg:city":"Aksaray",
    "sg:classifiers":[
        {
            "category":"Food & Beverages",
            "subcategory":"Specialty",
            "type":"Retail Goods"
        }
    ],
    "sg:phone":"+90 356 212 0011",
    "sg:postcode":"34280",
    "sg:province":"Tokat",
    "sg:tags":[
        "honey"
    ],
    "wof:name":"Mufi Gida ?retim San. Ve Tic. A.s.",
    "wof:placetype":"venue"
},
  "geometry": {"coordinates":[36.5556526184,40.330116272],"type":"Point"}
}