{
  "type": "Feature",
  "properties": {
    "iso:country":"TR",
    "sg:address":"Ankara Yolu ?zeri Bayirbasi Sok.no:67",
    "sg:city":"Pelitli Beldesi",
    "sg:classifiers":[
        {
            "category":"Food & Beverages",
            "subcategory":"Dairy",
            "type":"Retail Goods"
        }
    ],
    "sg:phone":"+90 332 237 1274",
    "sg:province":"Konya",
    "sg:tags":[
        "pruducts",
        "milk"
    ],
    "wof:name":"Doga S?t",
    "wof:placetype":"venue"
},
  "geometry": {"coordinates":[32.4990272522,37.8715362549],"type":"Point"}
}