{
  "type": "Feature",
  "properties": {
    "iso:country":"TR",
    "sg:address":"Dr. Tevfik Saglam Cd. No:86/c Etlik",
    "sg:city":"Maltepe",
    "sg:classifiers":[
        {
            "category":"Home & Garden",
            "subcategory":"Building Materials",
            "type":"Retail Goods"
        }
    ],
    "sg:phone":"+90 312 322 5466",
    "sg:postcode":"01000",
    "sg:province":"Ankara",
    "sg:tags":[
        "window",
        "door",
        "plastic"
    ],
    "wof:name":"Ufe San. Tic. Ltd. Sti.",
    "wof:placetype":"venue"
},
  "geometry": {"coordinates":[32.8411941528,39.9751930237],"type":"Point"}
}