{
  "type": "Feature",
  "properties": {
    "iso:country":"TR",
    "sg:address":"Halkali Cd. No:170 Sefak?",
    "sg:city":"Ikitelli/K\u00fc\u00e7\u00fck\u00e7ekmece",
    "sg:classifiers":[
        {
            "category":"Building & Trades",
            "subcategory":"Construction",
            "type":"Services"
        }
    ],
    "sg:phone":"+90 212 624 0670",
    "sg:postcode":"34670",
    "sg:province":"Istanbul",
    "sg:tags":[
        "industry",
        "mold"
    ],
    "wof:name":"Kalekalip Mak. Kalip San. A.s.",
    "wof:placetype":"venue"
},
  "geometry": {"coordinates":[28.7924251556,40.9708900452],"type":"Point"}
}