{
  "type": "Feature",
  "properties": {
    "iso:country":"TR",
    "sg:address":"Imes San.sitesi A Blok 101. Sok.no:13 Y.dudullu",
    "sg:city":"\u00dcmraniye",
    "sg:classifiers":[
        {
            "category":"Manufacturing",
            "subcategory":"Metals",
            "type":"Manufacturing & Wholesale Goods"
        }
    ],
    "sg:phone":"+90 216 499 5990",
    "sg:province":"Istanbul",
    "sg:tags":[
        "iron-steel",
        "peoducts"
    ],
    "wof:name":"Thyssen Asal Celik Ticaret A.s.",
    "wof:placetype":"venue"
},
  "geometry": {"coordinates":[28.9759254456,41.0123786926],"type":"Point"}
}