{
  "type": "Feature",
  "properties": {
    "addr:full":"Im? 6. Blok No:6302 Unkapani Merkez Istanbul 77200",
    "addr:housenumber":"6 blok no 6302",
    "addr:postcode":"77200",
    "addr:street":"Im ?;Unkapani",
    "iso:country":"TR",
    "sg:address":"Im? 6. Blok No:6302 Unkapani",
    "sg:city":"Merkez",
    "sg:classifiers":[
        {
            "category":"Shopping",
            "subcategory":"Music",
            "type":"Retail Goods"
        }
    ],
    "sg:phone":"+90 212 519 1065",
    "sg:postcode":"77200",
    "sg:province":"Istanbul",
    "sg:tags":[
        "record",
        "casette"
    ],
    "wof:name":"Kent Elektronik San. Tic. A.s.",
    "wof:placetype":"venue"
},
  "geometry": {"coordinates":[28.9759254456,41.0123786926],"type":"Point"}
}