{
  "type": "Feature",
  "properties": {
    "addr:full":"Mithatpasa Cd. No:61/a Kizilay Ankara 23050",
    "addr:housenumber":"no 61 / a",
    "addr:postcode":"23050",
    "addr:street":"Mithatpasa Cd.;Kizilay Ankara",
    "iso:country":"TR",
    "sg:address":"Mithatpasa Cd. No:61/a",
    "sg:city":"Kizilay",
    "sg:classifiers":[
        {
            "category":"Building & Trades",
            "subcategory":"Electrical",
            "type":"Services"
        }
    ],
    "sg:phone":"+90 312 431 8300",
    "sg:postcode":"23050",
    "sg:province":"Ankara",
    "sg:tags":[
        "equipment",
        "lighting"
    ],
    "wof:name":"Senol Avize Aydinlatma San.",
    "wof:placetype":"venue"
},
  "geometry": {"coordinates":[32.8591308594,39.9197921753],"type":"Point"}
}