{
  "type": "Feature",
  "properties": {
    "addr:full":"Ataturk Mah.tepe Sok. Bahcekapi/eminonu Aydin 34100",
    "addr:housenumber":"bahcekapi / eminonu",
    "addr:postcode":"34100",
    "addr:street":"Mah.Tepe Sok.;Aydin",
    "iso:country":"TR",
    "sg:address":"Ataturk Mah.tepe Sok.",
    "sg:city":"Bahcekapi/eminonu",
    "sg:classifiers":[
        {
            "category":"Banks & Credit Unions",
            "subcategory":"Investment Brokerage",
            "type":"Services"
        }
    ],
    "sg:phone":"+90 256 513 2234",
    "sg:postcode":"34100",
    "sg:province":"Aydin",
    "sg:tags":[
        "-",
        "export",
        "import"
    ],
    "wof:name":"Akcaman Ltd.",
    "wof:placetype":"venue"
},
  "geometry": {"coordinates":[27.8324394226,37.8409690857],"type":"Point"}
}