{
  "type": "Feature",
  "properties": {
    "addr:full":"Guzelbahce Sok. Tugrul Apt. 33-35/2 Nisantasi Merter Istanbul 34010",
    "addr:housenumber":"33-35 / 2",
    "addr:postcode":"34010",
    "addr:street":"Guzelbahce Sok. Tugrul Apt.",
    "iso:country":"TR",
    "sg:address":"Guzelbahce Sok. Tugrul Apt. 33-35/2 Nisantasi",
    "sg:city":"Merter",
    "sg:orig_category":"Orthopedical Materials",
    "sg:phone":"+90 212 230 9122",
    "sg:postcode":"34010",
    "sg:province":"Istanbul",
    "wof:name":"Cerrahpasa Ortopedik Malz. San.tic. Ltd.sti.",
    "wof:placetype":"venue"
},
  "geometry": {"coordinates":[28.91355896,41.0233802795],"type":"Point"}
}