{
  "type": "Feature",
  "properties": {
    "iso:country":"TR",
    "sg:address":"Selimzade Mah.beyazit Cad.no:16/c",
    "sg:city":"Yildirim",
    "sg:classifiers":[
        {
            "category":"Home & Garden",
            "subcategory":"Garden Supply",
            "type":"Retail Goods"
        }
    ],
    "sg:phone":"+90 224 327 5117",
    "sg:postcode":"16350",
    "sg:province":"Bursa",
    "sg:tags":[
        "plant"
    ],
    "wof:name":"Euro Aquarium Art",
    "wof:placetype":"venue"
},
  "geometry": {"coordinates":[29.0803012848,40.1858139038],"type":"Point"}
}