{
  "type": "Feature",
  "properties": {
    "addr:full":"Fatih Sultan Cad. No.162 Okmeydani Bayrampasa Istanbul 36100",
    "addr:housenumber":"no.162",
    "addr:postcode":"36100",
    "addr:street":"Sultan Cad.",
    "iso:country":"TR",
    "sg:address":"Fatih Sultan Cad. No.162 Okmeydani",
    "sg:city":"Bayrampasa",
    "sg:classifiers":[
        {
            "category":"Manufacturing",
            "subcategory":"Rubber & Plastics",
            "type":"Manufacturing & Wholesale Goods"
        }
    ],
    "sg:phone":"+90 212 256 8122",
    "sg:postcode":"36100",
    "sg:province":"Istanbul",
    "sg:tags":[
        "industry"
    ],
    "wof:name":"Ufo Reklam Tampon Ve Serigrafi Baski",
    "wof:placetype":"venue"
},
  "geometry": {"coordinates":[28.9583969116,41.046421051],"type":"Point"}
}