{
  "type": "Feature",
  "properties": {
    "addr:full":"Litros Yolu 2 Matbaacilar Sit. E Blok 2 Ne 11 Topkapi Sisli Istanbul 34200",
    "addr:housenumber":"2;2;11",
    "addr:postcode":"34200",
    "addr:street":"Litros Yolu;Ne",
    "iso:country":"TR",
    "sg:address":"Litros Yolu 2 Matbaacilar Sit. E Blok 2 Ne 11 Topkapi",
    "sg:city":"Sisli",
    "sg:classifiers":[
        {
            "category":"Shopping",
            "subcategory":"Stationery & Office Supplies",
            "type":"Retail Goods"
        }
    ],
    "sg:phone":"+90 212 612 7175",
    "sg:postcode":"34200",
    "sg:province":"Istanbul",
    "sg:tags":[
        "paper"
    ],
    "wof:name":"Ko? Kagit?ilik Kagit Matbaa Malz.",
    "wof:placetype":"venue"
},
  "geometry": {"coordinates":[28.860408783,41.0367050171],"type":"Point"}
}