{
  "type": "Feature",
  "properties": {
    "iso:country":"TR",
    "sg:address":"Marangozlar Sit. Alptekin Sk. O Blok No:56 Ey?",
    "sg:city":"Ikitelli/K\u00fc\u00e7\u00fck\u00e7ekmece",
    "sg:classifiers":[
        {
            "category":"Home & Garden",
            "subcategory":"Hardware",
            "type":"Retail Goods"
        }
    ],
    "sg:phone":"+90 212 544 4776",
    "sg:postcode":"34660",
    "sg:province":"Istanbul",
    "sg:tags":[
        "lathe"
    ],
    "wof:name":"Erg?n Torna",
    "wof:placetype":"venue"
},
  "geometry": {"coordinates":[29.0496292114,41.0075798035],"type":"Point"}
}