{
  "type": "Feature",
  "properties": {
    "iso:country":"TR",
    "sg:address":"Cumh. Meyd. Celik Ish. No:3/3",
    "sg:city":"Kartal",
    "sg:classifiers":[
        {
            "category":"Wholesale",
            "subcategory":"Medical Equipment & Supplies",
            "type":"Manufacturing & Wholesale Goods"
        }
    ],
    "sg:phone":"+90 286 217 5937",
    "sg:postcode":"46000",
    "sg:province":"?anakkale",
    "sg:tags":[
        "material"
    ],
    "wof:name":"Kale Tip Tic.",
    "wof:placetype":"venue"
},
  "geometry": {"coordinates":[36.8413314819,37.6805305481],"type":"Point"}
}