{
  "type": "Feature",
  "properties": {
    "iso:country":"TR",
    "sg:address":"G?r? Bulvari No:71/54 Alemdar Pasaji Maltepe",
    "sg:city":"Emin?? 34440",
    "sg:orig_category":"Printinh House",
    "sg:phone":"+90 312 229 8161",
    "sg:province":"Ankara",
    "wof:name":"Matser Basim San. Ltd. Sti.",
    "wof:placetype":"venue"
},
  "geometry": {"coordinates":[32.8449440002,39.9250602722],"type":"Point"}
}