{
  "type": "Feature",
  "properties": {
    "iso:country":"TR",
    "sg:address":"Kennedy Cd. No:43/44 Kumkapi",
    "sg:city":"?akalburnu",
    "sg:classifiers":[
        {
            "category":"Shopping",
            "subcategory":"Bicycles & Sporting Goods",
            "type":"Retail Goods"
        }
    ],
    "sg:phone":"+90 212 517 7074",
    "sg:province":"Istanbul",
    "sg:tags":[
        "equipment",
        "marine",
        "hunting"
    ],
    "wof:name":"Akbal Balik?ilik",
    "wof:placetype":"venue"
},
  "geometry": {"coordinates":[28.9676399231,41.0036087036],"type":"Point"}
}