{
  "type": "Feature",
  "properties": {
    "iso:country":"TR",
    "sg:address":"Valikonagi Cad.madalyon Sok.no:46/4",
    "sg:city":"Nisantasi",
    "sg:classifiers":[
        {
            "category":"Shopping",
            "subcategory":"Clothing, Apparel, & Fashions",
            "type":"Retail Goods"
        }
    ],
    "sg:phone":"+90 212 343 0102",
    "sg:postcode":"25370",
    "sg:province":"Istanbul",
    "sg:tags":[
        "woman",
        "wear"
    ],
    "wof:name":"Se?n Tekstil",
    "wof:placetype":"venue"
},
  "geometry": {"coordinates":[28.9759254456,41.0123786926],"type":"Point"}
}