{
  "type": "Feature",
  "properties": {
    "addr:full":"8 Sk. No:25/4-d Bornova Izmir 35040",
    "addr:housenumber":"8;25 / 4-d",
    "addr:postcode":"35040",
    "addr:street":"Sk. No",
    "iso:country":"TR",
    "sg:address":"8 Sk. No:25/4-d",
    "sg:city":"Bornova",
    "sg:orig_category":"Muhtarliklar",
    "sg:phone":"+90 232 374 4452",
    "sg:postcode":"35040",
    "sg:province":"Izmir",
    "wof:name":"Erzene Mahallesi Muhtar: Ayse M?gan Paky?ek",
    "wof:placetype":"venue"
},
  "geometry": {"coordinates":[27.2217597961,38.4675140381],"type":"Point"}
}