{
  "type": "Feature",
  "properties": {
    "iso:country":"TR",
    "sg:address":"Atat?rk Cad. Pizza Harem Karsisi No: 17/a",
    "sg:city":"Pamukkale",
    "sg:classifiers":[
        {
            "category":"Travel",
            "subcategory":"Travel Agent",
            "type":"Entertainment"
        }
    ],
    "sg:phone":"+90 258 272 2743",
    "sg:postcode":"20280",
    "sg:province":"Denizli",
    "sg:tags":[
        "agency",
        "tourism"
    ],
    "wof:name":"Magic Valley Cappadocia Tur (denizli Sb.)",
    "wof:placetype":"venue"
},
  "geometry": {"coordinates":[29.0788803101,37.7851867676],"type":"Point"}
}