{
  "type": "Feature",
  "properties": {
    "iso:country":"TR",
    "sg:address":"O.s.b. Gri Cd. No:8",
    "sg:city":"Osmangazi",
    "sg:orig_category":"Prefabric Construction",
    "sg:phone":"+90 224 243 1182",
    "sg:postcode":"16110",
    "sg:province":"Bursa",
    "wof:name":"Sinta A.s.",
    "wof:placetype":"venue"
},
  "geometry": {"coordinates":[28.9609699249,40.2368850708],"type":"Point"}
}