{
  "type": "Feature",
  "properties": {
    "addr:full":"Cebeci Cad. 568/3. Sok. No: 22 Kucukkoy Merter Istanbul",
    "addr:housenumber":"568 / 3;no 22",
    "addr:street":"Cebeci Cad.;Sok.",
    "iso:country":"TR",
    "sg:address":"Cebeci Cad. 568/3. Sok. No: 22 Kucukkoy",
    "sg:city":"Merter",
    "sg:classifiers":[
        {
            "category":"Shopping",
            "subcategory":"Luggage & Leather Goods",
            "type":"Retail Goods"
        }
    ],
    "sg:phone":"+90 212 535 6678",
    "sg:province":"Istanbul",
    "sg:tags":[
        "supplementaries"
    ],
    "wof:name":"Ser Bant Uya Sanayi Tic.ltd.sti.",
    "wof:placetype":"venue"
},
  "geometry": {"coordinates":[28.8894042969,41.0884742737],"type":"Point"}
}