{
  "type": "Feature",
  "properties": {
    "iso:country":"TR",
    "sg:address":"Mahmut Sevket Pasa Mah. Piyale Pasa Bulv. No:8",
    "sg:city":"Okmeydani",
    "sg:classifiers":[
        {
            "category":"Shopping",
            "subcategory":"Florist",
            "type":"Retail Goods"
        }
    ],
    "sg:phone":"+90 212 237 1700",
    "sg:postcode":"43050",
    "sg:province":"Istanbul",
    "sg:tags":[
        "flower"
    ],
    "wof:name":"Emir Dis Ticaret Ltd. Sti.",
    "wof:placetype":"venue"
},
  "geometry": {"coordinates":[28.9759254456,41.0123786926],"type":"Point"}
}