{
  "type": "Feature",
  "properties": {
    "iso:country":"TR",
    "sg:address":"Cumhuriyet Bul 68",
    "sg:city":"Izmir",
    "sg:classifiers":[
        {
            "category":"Banks & Credit Unions",
            "subcategory":"Bank",
            "type":"Services"
        }
    ],
    "sg:phone":"+90 232 483 3359",
    "sg:province":"35250",
    "wof:name":"Bank Kapital Tas",
    "wof:placetype":"venue"
},
  "geometry": {"coordinates":[27.131718,38.423645],"type":"Point"}
}