{
  "type": "Feature",
  "properties": {
    "iso:country":"TR",
    "sg:address":"1578 Sk.no:4 Mersinli",
    "sg:city":"24000",
    "sg:classifiers":[
        {
            "category":"Manufacturing",
            "subcategory":"Wood Products",
            "type":"Manufacturing & Wholesale Goods"
        }
    ],
    "sg:phone":"+90 232 486 0135",
    "sg:province":"Izmir",
    "sg:tags":[
        "forest"
    ],
    "wof:name":"Doruklar Orman ?r?nleri Insaat Sanayi Ve Tic.ltd.sti.",
    "wof:placetype":"venue"
},
  "geometry": {"coordinates":[27.1765861511,38.4392738342],"type":"Point"}
}