{
  "type": "Feature",
  "properties": {
    "addr:full":"Cumhuriyet Cad 16 Istanbul 80200",
    "addr:housenumber":"16",
    "addr:postcode":"80200",
    "addr:street":"Cumhuriyet Cad",
    "iso:country":"TR",
    "sg:address":"Cumhuriyet Cad 16",
    "sg:city":"Istanbul",
    "sg:classifiers":[
        {
            "category":"Banks & Credit Unions",
            "subcategory":"Bank",
            "type":"Services"
        }
    ],
    "sg:phone":"+90 212 225 8779",
    "sg:province":"80200",
    "wof:name":"Yurt Ticaret, Ve Kredi Bankasi As",
    "wof:placetype":"venue"
},
  "geometry": {"coordinates":[36.154064,36.201237],"type":"Point"}
}