{
  "type": "Feature",
  "properties": {
    "addr:full":"Resatbey Mh. 5 Ocak Cd. Saniye Hanim Apt.zemin Kat. Seyhan Adana 01000",
    "addr:housenumber":"5",
    "addr:postcode":"01000",
    "addr:street":"Mh.;Ocak Cd. Saniye;Apt.Zemin Kat.",
    "iso:country":"TR",
    "sg:address":"Resatbey Mh. 5 Ocak Cd. Saniye Hanim Apt.zemin Kat.",
    "sg:city":"Seyhan",
    "sg:classifiers":[
        {
            "category":"Home & Garden",
            "subcategory":"Household Appliances",
            "type":"Retail Goods"
        }
    ],
    "sg:phone":"+90 322 459 0358",
    "sg:postcode":"01000",
    "sg:province":"Adana",
    "sg:tags":[
        "conditioner",
        "air"
    ],
    "wof:name":"Ada Klima San.",
    "wof:placetype":"venue"
},
  "geometry": {"coordinates":[35.3137359619,37.0007171631],"type":"Point"}
}