{
  "type": "Feature",
  "properties": {
    "addr:full":"Ikitelli Organize San. B?gesi Ipkas San. Sit. 4. Blok No:24 K???kmece Istanbul 34670",
    "addr:housenumber":"4 blok no 24 k ?",
    "addr:postcode":"34670",
    "addr:street":"Organize",
    "iso:country":"TR",
    "sg:address":"Ikitelli Organize San. B?gesi Ipkas San. Sit. 4. Blok No:24",
    "sg:city":"K???kmece",
    "sg:orig_category":"Ikitelli Ipkas Ind.site",
    "sg:phone":"+90 21254948080",
    "sg:postcode":"34670",
    "sg:province":"Istanbul",
    "wof:name":"?zkarakus Elektrk Malzemeleri Iml. Ve San.",
    "wof:placetype":"venue"
},
  "geometry": {"coordinates":[28.9861831665,41.0408554077],"type":"Point"}
}