{
  "type": "Feature",
  "properties": {
    "addr:full":"Ankara Izmir Ankara",
    "iso:country":"TR",
    "sg:address":"Ankara",
    "sg:city":"Izmir",
    "sg:classifiers":[
        {
            "category":"Banks & Credit Unions",
            "subcategory":"Bank",
            "type":"Services"
        }
    ],
    "sg:province":"Ankara",
    "wof:name":"Is Net",
    "wof:placetype":"venue"
},
  "geometry": {"coordinates":[32.856033,39.943874],"type":"Point"}
}