{
  "type": "Feature",
  "properties": {
    "addr:full":"Istanbul Cd.hamam Sok.no:10 Bakirk? Iskenderun Istanbul 31200",
    "addr:housenumber":"10;?",
    "addr:postcode":"31200",
    "addr:street":"Sok.No",
    "iso:country":"TR",
    "sg:address":"Istanbul Cd.hamam Sok.no:10 Bakirk?",
    "sg:city":"Iskenderun",
    "sg:classifiers":[
        {
            "category":"Education",
            "subcategory":"Special Training",
            "type":"Public Place"
        }
    ],
    "sg:phone":"+90 212 543 5454",
    "sg:postcode":"31200",
    "sg:province":"Istanbul",
    "sg:tags":[
        "course"
    ],
    "wof:name":"Kavram Dershanesi",
    "wof:placetype":"venue"
},
  "geometry": {"coordinates":[28.9861831665,41.0408554077],"type":"Point"}
}