{
  "type": "Feature",
  "properties": {
    "iso:country":"TR",
    "sg:address":"Kulusaga Koyu Battalgazi Ilcesi",
    "sg:city":"Baliseyh",
    "sg:classifiers":[
        {
            "category":"Farming",
            "subcategory":"Farm",
            "type":"Manufacturing & Wholesale Goods"
        }
    ],
    "sg:phone":"+90 422 848 1183",
    "sg:postcode":"71520",
    "sg:province":"Malatya",
    "sg:tags":[
        "agricultural",
        "product"
    ],
    "wof:name":"Avci Tarim Urunleri Pazarlama A.s.",
    "wof:placetype":"venue"
},
  "geometry": {"coordinates":[38.3143005371,38.3474998474],"type":"Point"}
}