{
  "type": "Feature",
  "properties": {
    "addr:full":"7 Eyl? Mah. Es-ko Ishani B Blok K:1 D:2 Yesildirek Aydin 63200",
    "addr:housenumber":"7;?;blok k 1 d 2",
    "addr:postcode":"63200",
    "addr:street":"Eyl;Es-Ko;Yesildirek Aydin",
    "iso:country":"TR",
    "sg:address":"7 Eyl? Mah. Es-ko Ishani B Blok K:1 D:2",
    "sg:city":"Yesildirek",
    "sg:classifiers":[
        {
            "category":"Shopping",
            "subcategory":"Clothing, Apparel, & Fashions",
            "type":"Retail Goods"
        }
    ],
    "sg:phone":"+90 256 585 4675",
    "sg:postcode":"63200",
    "sg:province":"Aydin",
    "sg:tags":[
        "ready",
        "wear"
    ],
    "wof:name":"Empa Teks. Konf. San. Tic. Ltd. Sti.",
    "wof:placetype":"venue"
},
  "geometry": {"coordinates":[28.4863967896,37.8117027283],"type":"Point"}
}