{
  "type": "Feature",
  "properties": {
    "addr:full":"Ikitelli Sanayi B?gesi ?zal Cad. No:145 Istanbul Eminonu Istanbul",
    "addr:housenumber":"?;145",
    "addr:postcode":"?",
    "addr:street":"Ikitelli Sanayi B;Zal Cad. No",
    "iso:country":"TR",
    "sg:address":"Ikitelli Sanayi B?gesi ?zal Cad. No:145 Istanbul",
    "sg:city":"Eminonu",
    "sg:classifiers":[
        {
            "category":"Shopping",
            "subcategory":"Clothing, Apparel, & Fashions",
            "type":"Retail Goods"
        }
    ],
    "sg:phone":"+90 212 549 2070",
    "sg:province":"Istanbul",
    "sg:tags":[
        "ready",
        "wear"
    ],
    "wof:name":"Oskar Tekstil A.s",
    "wof:placetype":"venue"
},
  "geometry": {"coordinates":[28.9759254456,41.0123786926],"type":"Point"}
}