{
  "type": "Feature",
  "properties": {
    "iso:country":"TR",
    "sg:address":"Saniye Ermutlu Sk. Tekno Is Merkezi No:10 Kozyatagi",
    "sg:city":"Ikitelli",
    "sg:classifiers":[
        {
            "category":"Professional",
            "subcategory":"Detective & Security Services",
            "type":"Services"
        }
    ],
    "sg:phone":"+90 216 463 6553",
    "sg:postcode":"34295",
    "sg:province":"Istanbul",
    "sg:tags":[
        "material"
    ],
    "wof:name":"Teknotur Mimarlik Muhendislik Musavirlik Ticaretltd. Sti.",
    "wof:placetype":"venue"
},
  "geometry": {"coordinates":[28.802141,41.00679],"type":"Point"}
}