{
  "type": "Feature",
  "properties": {
    "addr:full":"Merkez San. Sit. 546. Sok. No:25 Karsiyaka Seyhan Ankara 01000",
    "addr:housenumber":"no 25",
    "addr:postcode":"01000",
    "addr:street":"Merkez;Sit. 546 Sok.;Karsiyaka Seyhan",
    "iso:country":"TR",
    "sg:address":"Merkez San. Sit. 546. Sok. No:25 Karsiyaka",
    "sg:city":"Seyhan",
    "sg:orig_category":"Scavening Services",
    "sg:phone":"+90 312 395 1033",
    "sg:postcode":"01000",
    "sg:province":"Ankara",
    "wof:name":"Hali Yikama Ve Camasir Yikama",
    "wof:placetype":"venue"
},
  "geometry": {"coordinates":[32.856033,39.943874],"type":"Point"}
}