{
  "type": "Feature",
  "properties": {
    "addr:full":"Necatibey Cad. No:58/22 Kizilay Ankara 23050",
    "addr:housenumber":"58 / 22",
    "addr:postcode":"23050",
    "addr:street":"Necatibey Cad. No",
    "iso:country":"TR",
    "sg:address":"Necatibey Cad. No:58/22",
    "sg:city":"Kizilay",
    "sg:classifiers":[
        {
            "category":"Manufacturing",
            "subcategory":"Building Materials",
            "type":"Manufacturing & Wholesale Goods"
        }
    ],
    "sg:phone":"+90 312 418 0909",
    "sg:postcode":"23050",
    "sg:province":"Ankara",
    "sg:tags":[
        "lifts-elevators"
    ],
    "wof:name":"Demas Asansor San. Ve Tic. Ltd.sti.",
    "wof:placetype":"venue"
},
  "geometry": {"coordinates":[32.850151062,39.9240722656],"type":"Point"}
}