{
  "type": "Feature",
  "properties": {
    "iso:country":"TR",
    "sg:address":"Tavsanli Koyu Tasocaklari Mevkii",
    "sg:city":"Gebze",
    "sg:classifiers":[
        {
            "category":"Professional",
            "type":"Services"
        }
    ],
    "sg:phone":"+90 262 724 9321",
    "sg:postcode":"41400",
    "sg:province":"Kocaeli",
    "sg:tags":[
        "catering"
    ],
    "wof:name":"Havuzbasi Et Mangal",
    "wof:placetype":"venue"
},
  "geometry": {"coordinates":[29.9345855713,40.7669563293],"type":"Point"}
}