{
  "type": "Feature",
  "properties": {
    "addr:full":"H?riyet Mh. Egitim Sk. No:7 K?ithane Siteler Istanbul 06160",
    "addr:housenumber":"k ?",
    "addr:postcode":"06160",
    "addr:street":"Riyet Mh. Egitim Sk. No 7;Ithane",
    "iso:country":"TR",
    "sg:address":"H?riyet Mh. Egitim Sk. No:7 K?ithane",
    "sg:city":"Siteler",
    "sg:orig_category":"Aluminium Carpentary",
    "sg:phone":"+90 212 224 0117",
    "sg:postcode":"06160",
    "sg:province":"Istanbul",
    "wof:name":"Meda Alum. Ith. Ihr. San.a.s.",
    "wof:placetype":"venue"
},
  "geometry": {"coordinates":[28.9759254456,41.0123786926],"type":"Point"}
}