{
  "type": "Feature",
  "properties": {
    "addr:full":"Org. San. B?gesi G?su Denizli",
    "addr:housenumber":"?",
    "addr:street":"Org.;Gesi G",
    "iso:country":"TR",
    "sg:address":"Org. San. B?gesi",
    "sg:city":"G?su",
    "sg:classifiers":[
        {
            "category":"Shopping",
            "subcategory":"Clothing, Apparel, & Fashions",
            "type":"Retail Goods"
        }
    ],
    "sg:phone":"+90 258 269 1020",
    "sg:province":"Denizli",
    "sg:tags":[
        "-",
        "towel",
        "bathrobe"
    ],
    "wof:name":"Nese Tekstil A.s.",
    "wof:placetype":"venue"
},
  "geometry": {"coordinates":[29.3432292938,37.6734886169],"type":"Point"}
}