{
  "type": "Feature",
  "properties": {
    "addr:full":"Davutpasa Cd. Ser? Kale Sk. No:5 Topkapi Ikitelli Istanbul 34670",
    "addr:housenumber":"?",
    "addr:postcode":"34670",
    "addr:street":"Davutpasa Cd. Ser;Kale Sk. No 5 Topkapi",
    "iso:country":"TR",
    "sg:address":"Davutpasa Cd. Ser? Kale Sk. No:5 Topkapi",
    "sg:city":"Ikitelli",
    "sg:classifiers":[
        {
            "category":"Shopping",
            "subcategory":"Stationery & Office Supplies",
            "type":"Retail Goods"
        }
    ],
    "sg:phone":"+90 212 613 7035",
    "sg:postcode":"34670",
    "sg:province":"Istanbul",
    "sg:tags":[
        "paper"
    ],
    "wof:name":"Olcay Kagit?ilik San. Tic. A.s.",
    "wof:placetype":"venue"
},
  "geometry": {"coordinates":[28.9759254456,41.0123786926],"type":"Point"}
}