{
  "type": "Feature",
  "properties": {
    "addr:full":"Aydintepe Mah. 100.yil Sok. Evren Cad. No:13/z Tuzla Fax:(216) 4943031-32 Fax: 494 3033 Gum?suyu Istanbul",
    "addr:housenumber":"13 / z;-32;494;?",
    "addr:postcode":"3033",
    "addr:street":"Aydintepe Mah. 100.Yil Sok. Evren Cad. No;Fax (216) 4943031;Fax",
    "iso:country":"TR",
    "sg:address":"Aydintepe Mah. 100.yil Sok. Evren Cad. No:13/z Tuzla Fax:(216) 4943031-32 Fax: 494 3033",
    "sg:city":"Gum?suyu",
    "sg:classifiers":[
        {
            "category":"Manufacturing",
            "subcategory":"Watercraft",
            "type":"Manufacturing & Wholesale Goods"
        }
    ],
    "sg:phone":"+90 216493434849",
    "sg:province":"Istanbul",
    "sg:tags":[
        "builder",
        "yacht",
        "trough"
    ],
    "wof:name":"Marina Elektromekanik Gemi Ve Yat Donatimi Ltd.sti.",
    "wof:placetype":"venue"
},
  "geometry": {"coordinates":[28.9759254456,41.0123786926],"type":"Point"}
}