{
  "type": "Feature",
  "properties": {
    "iso:country":"TR",
    "sg:address":"Tomruk Sk. No:29 Tahtakale",
    "sg:city":"Okmeydani/sisli",
    "sg:classifiers":[
        {
            "category":"Shopping",
            "subcategory":"Stationery & Office Supplies",
            "type":"Retail Goods"
        }
    ],
    "sg:phone":"+90 212 520 1999",
    "sg:province":"Istanbul",
    "wof:name":"Nedim Ertal Kirtasiye B?ro Mak.",
    "wof:placetype":"venue"
},
  "geometry": {"coordinates":[28.969246,41.01593],"type":"Point"}
}