{
  "type": "Feature",
  "properties": {
    "addr:full":"Yapi Kredit Plaza, Buyukdere Caddesi, Levent, 80620 Istanbul Istanbul Istanbul",
    "addr:postcode":"80620",
    "addr:street":"Buyukdere Caddesi",
    "iso:country":"TR",
    "sg:address":"Yapi Kredit Plaza, Buyukdere Caddesi, Levent, 80620 Istanbul",
    "sg:city":"Istanbul",
    "sg:classifiers":[
        {
            "category":"Banks & Credit Unions",
            "subcategory":"Bank",
            "type":"Services"
        }
    ],
    "sg:phone":"+90 212 280 1111",
    "sg:province":"Istanbul",
    "sg:website":"http://www.ykb.com/english_ver/index3.html",
    "wof:name":"Yapi Kredi Finansal Kiralama Ao",
    "wof:placetype":"venue"
},
  "geometry": {"coordinates":[28.975925,41.012379],"type":"Point"}
}