{
  "type": "Feature",
  "properties": {
    "addr:full":"Atat?k Blv. No:91/56-58 Kizilay G?tepe Ankara",
    "addr:housenumber":"91 / 56-58;?",
    "addr:street":"K Blv. No;Kizilay G",
    "iso:country":"TR",
    "sg:address":"Atat?k Blv. No:91/56-58 Kizilay",
    "sg:city":"G?tepe",
    "sg:classifiers":[
        {
            "category":"Wholesale",
            "subcategory":"Medical Equipment & Supplies",
            "type":"Manufacturing & Wholesale Goods"
        }
    ],
    "sg:phone":"+90 312 433 3392",
    "sg:province":"Ankara",
    "sg:tags":[
        "material"
    ],
    "wof:name":"Ata Medikal Ltd. Sti.",
    "wof:placetype":"venue"
},
  "geometry": {"coordinates":[32.8510704041,39.9231300354],"type":"Point"}
}