{
  "type": "Feature",
  "properties": {
    "iso:country":"TR",
    "sg:address":"A. Mend. Bulv. 2 Sk. No:10/a",
    "sg:city":"Doganlar",
    "sg:classifiers":[
        {
            "category":"Shopping",
            "subcategory":"Clothing, Apparel, & Fashions",
            "type":"Retail Goods"
        }
    ],
    "sg:phone":"+90 256 214 4021",
    "sg:postcode":"44600",
    "sg:province":"Aydin",
    "sg:tags":[
        "ready",
        "wear"
    ],
    "wof:name":"Is-tek Teks. San. Tic. Ltd. Sti.",
    "wof:placetype":"venue"
},
  "geometry": {"coordinates":[28.4863967896,37.8117027283],"type":"Point"}
}