{
  "type": "Feature",
  "properties": {
    "iso:country":"TR",
    "sg:address":"Orman Sokak 10",
    "sg:city":"Florya",
    "sg:classifiers":[
        {
            "category":"Freight",
            "type":"Transportation"
        }
    ],
    "sg:phone":"+90 212 663 1829",
    "sg:postcode":"34153",
    "sg:province":"Istanbul",
    "sg:tags":[
        "cargo",
        "air"
    ],
    "wof:name":"Bon Air",
    "wof:placetype":"venue"
},
  "geometry": {"coordinates":[28.794801712,40.9752502441],"type":"Point"}
}