{
  "type": "Feature",
  "properties": {
    "addr:full":"Ankara Asfalti Uzeri Bolge Trafik Karsisi Gebze Sakarya 41400",
    "addr:postcode":"41400",
    "iso:country":"TR",
    "sg:address":"Ankara Asfalti Uzeri Bolge Trafik Karsisi",
    "sg:city":"Gebze",
    "sg:classifiers":[
        {
            "category":"Wholesale",
            "subcategory":"Auto Parts",
            "type":"Manufacturing & Wholesale Goods"
        }
    ],
    "sg:phone":"+90 264 275 1192",
    "sg:postcode":"41400",
    "sg:province":"Sakarya",
    "sg:tags":[
        "spare"
    ],
    "wof:name":"Oto Omercikoglu Otoyol Iveco Arac Satis & Servis Ve Yedek Parca Ana Bayii",
    "wof:placetype":"venue"
},
  "geometry": {"coordinates":[30.3791446686,40.7734336853],"type":"Point"}
}