{
  "type": "Feature",
  "properties": {
    "addr:full":"1456.sok.no:16/205 Barohan Ishani Kat:2 Karak\u00f6y Izmir 35800",
    "addr:housenumber":"16 / 205;kat 2",
    "addr:postcode":"35800",
    "addr:street":"Barohan Ishani;Karakoey Izmir",
    "iso:country":"TR",
    "sg:address":"1456.sok.no:16/205 Barohan Ishani Kat:2",
    "sg:city":"Karak\u00f6y",
    "sg:classifiers":[
        {
            "category":"Airport",
            "subcategory":"International",
            "type":"Transportation"
        }
    ],
    "sg:phone":"+90 232 463 6734",
    "sg:postcode":"35800",
    "sg:province":"Izmir",
    "wof:name":"Makro Uluslararasi Tasimacilik San.tic.ltd.sti.",
    "wof:placetype":"venue"
},
  "geometry": {"coordinates":[27.1423015594,38.4251480103],"type":"Point"}
}