{
  "type": "Feature",
  "properties": {
    "addr:full":"G?enlik Mah. 271 Sok. No:18/1 Krak? Antalya",
    "addr:housenumber":"271;no 18 / 1;?",
    "addr:street":"Enlik Mah.;Sok.;Krak",
    "iso:country":"TR",
    "sg:address":"G?enlik Mah. 271 Sok. No:18/1",
    "sg:city":"Krak?",
    "sg:classifiers":[
        {
            "category":"Marine",
            "type":"Transportation"
        }
    ],
    "sg:phone":"+90 242 334 5866",
    "sg:province":"Antalya",
    "sg:tags":[
        "equipment",
        "maritime"
    ],
    "wof:name":"Akdeniz Marina",
    "wof:placetype":"venue"
},
  "geometry": {"coordinates":[30.7092056274,36.8790512085],"type":"Point"}
}