{
  "type": "Feature",
  "properties": {
    "iso:country":"TR",
    "sg:address":"Ismet Pasa Cad 31/b",
    "sg:city":"Gaziantep",
    "sg:classifiers":[
        {
            "category":"Banks & Credit Unions",
            "subcategory":"Bank",
            "type":"Services"
        }
    ],
    "sg:phone":"+90 276 224 3802",
    "sg:postcode":"63570",
    "sg:province":"Usak",
    "wof:name":"Ege Giyim Sanayicileri, Bankasi As",
    "wof:placetype":"venue"
},
  "geometry": {"coordinates":[29.405594,38.675453],"type":"Point"}
}