{
  "type": "Feature",
  "properties": {
    "iso:country":"TR",
    "sg:address":"Organize San.b?gesi Misis",
    "sg:city":"Adalar",
    "sg:classifiers":[
        {
            "category":"Shopping",
            "subcategory":"Stationery & Office Supplies",
            "type":"Retail Goods"
        }
    ],
    "sg:phone":"+90 322 394 3564",
    "sg:postcode":"81340",
    "sg:province":"Adana",
    "sg:tags":[
        "paper"
    ],
    "wof:name":"Akasan Adanakagit San.ve Tic.ltd.sti.",
    "wof:placetype":"venue"
},
  "geometry": {"coordinates":[35.3137359619,37.0007171631],"type":"Point"}
}