{
  "type": "Feature",
  "properties": {
    "addr:full":"Levent Cd. No:35 1.levent Istanbul",
    "addr:housenumber":"no;1.levent",
    "addr:street":"Levent Cd.",
    "iso:country":"TR",
    "sg:address":"Levent Cd. No:35",
    "sg:city":"1.levent",
    "sg:classifiers":[
        {
            "category":"Airport",
            "subcategory":"International",
            "type":"Transportation"
        }
    ],
    "sg:phone":"+90 212 245 6517",
    "sg:province":"Istanbul",
    "wof:name":"Marti Uluslararasi Tasima. A.s.",
    "wof:placetype":"venue"
},
  "geometry": {"coordinates":[29.3651943207,40.8310394287],"type":"Point"}
}