{
  "type": "Feature",
  "properties": {
    "iso:country":"TR",
    "sg:address":"Bagdat Cad. No:126/6 Feneryolu",
    "sg:city":"Yenisehir",
    "sg:classifiers":[
        {
            "category":"Building & Trades",
            "subcategory":"Plumbing",
            "type":"Services"
        }
    ],
    "sg:phone":"+90 216 347 7684",
    "sg:postcode":"31750",
    "sg:province":"Istanbul",
    "wof:name":"Belde Yapi San. Ve Insaat Tic. A.s.",
    "wof:placetype":"venue"
},
  "geometry": {"coordinates":[29.044960022,40.9792175293],"type":"Point"}
}