{
  "type": "Feature",
  "properties": {
    "iso:country":"TR",
    "sg:address":"Mimar Kemalettin Cad. No:49",
    "sg:city":"Cankaya",
    "sg:classifiers":[
        {
            "category":"Shopping",
            "subcategory":"Clothing, Apparel, & Fashions",
            "type":"Retail Goods"
        }
    ],
    "sg:phone":"+90 232 445 3095",
    "sg:postcode":"07080",
    "sg:province":"Izmir",
    "sg:tags":[
        "woman",
        "wear"
    ],
    "wof:name":"Margizet Collection",
    "wof:placetype":"venue"
},
  "geometry": {"coordinates":[27.1339988708,38.4231185913],"type":"Point"}
}