{
  "type": "Feature",
  "properties": {
    "iso:country":"TR",
    "sg:address":"Denizli Yolu 3.km. Usak Cay Uzeri No:26",
    "sg:city":"Antakya",
    "sg:classifiers":[
        {
            "category":"Home & Garden",
            "subcategory":"Kitchen Supply",
            "type":"Retail Goods"
        }
    ],
    "sg:phone":"+90 276 231 0165",
    "sg:postcode":"31000",
    "sg:province":"Usak",
    "sg:tags":[
        "wardrobe"
    ],
    "wof:name":"Usak Coskun Insaat Ltd.sti.",
    "wof:placetype":"venue"
},
  "geometry": {"coordinates":[29.4055995941,38.6716003418],"type":"Point"}
}