{
  "type": "Feature",
  "properties": {
    "addr:full":"Karacakaya Cd. Dalboyu Sk. No:8/a Siteler Mersin Ankara 52750",
    "addr:postcode":"52750",
    "addr:street":"Karacakaya Cd. Dalboyu Sk. No 8 / A Siteler",
    "iso:country":"TR",
    "sg:address":"Karacakaya Cd. Dalboyu Sk. No:8/a Siteler",
    "sg:city":"Mersin",
    "sg:classifiers":[
        {
            "category":"Manufacturing",
            "subcategory":"Glass & Minerals",
            "type":"Manufacturing & Wholesale Goods"
        }
    ],
    "sg:phone":"+90 312 350 3175",
    "sg:postcode":"52750",
    "sg:province":"Ankara",
    "sg:tags":[
        "glassware"
    ],
    "wof:name":"Yildiz Kristal Dekor Cam Ayna San. Ltd. Sti.",
    "wof:placetype":"venue"
},
  "geometry": {"coordinates":[32.8952026367,39.9603385925],"type":"Point"}
}