{
  "type": "Feature",
  "properties": {
    "iso:country":"TR",
    "sg:address":"Gen?lik Mah. Tevfik Isik Cad. Meltem Sitesi 3 Blok K: 3 D: 6",
    "sg:city":"Koycegiz",
    "sg:classifiers":[
        {
            "category":"Travel",
            "subcategory":"Travel Agent",
            "type":"Entertainment"
        }
    ],
    "sg:phone":"+90 2423121781729",
    "sg:postcode":"25830",
    "sg:province":"Antalya",
    "sg:tags":[
        "agency",
        "tourism"
    ],
    "wof:name":"Trans Nature Turizm",
    "wof:placetype":"venue"
},
  "geometry": {"coordinates":[30.7092056274,36.8790512085],"type":"Point"}
}