{
  "type": "Feature",
  "properties": {
    "iso:country":"TR",
    "sg:address":"Bursa Yolu 5.km. Inegol",
    "sg:city":"41100",
    "sg:classifiers":[
        {
            "category":"Home & Garden",
            "subcategory":"Furniture",
            "type":"Retail Goods"
        }
    ],
    "sg:phone":"+90 224 714 8870",
    "sg:province":"Bursa",
    "sg:tags":[
        "armchair",
        "sofa"
    ],
    "wof:name":"Uz Kardesler Mobilya San.a.s",
    "wof:placetype":"venue"
},
  "geometry": {"coordinates":[29.4928894043,40.0896492004],"type":"Point"}
}