{
  "type": "Feature",
  "properties": {
    "addr:full":"Saray Mah. Zimbitlik Mevkii Ark Apart Otel Alti Alanya Antalya 07400",
    "addr:postcode":"07400",
    "addr:street":"Mah. Zimbitlik Mevkii Ark",
    "iso:country":"TR",
    "sg:address":"Saray Mah. Zimbitlik Mevkii Ark Apart Otel Alti",
    "sg:city":"Alanya",
    "sg:classifiers":[
        {
            "category":"Travel",
            "subcategory":"Travel Agent",
            "type":"Entertainment"
        }
    ],
    "sg:phone":"+90 24252237005223",
    "sg:postcode":"07400",
    "sg:province":"Antalya",
    "sg:tags":[
        "agency",
        "tourism"
    ],
    "wof:name":"Birlesim Turizm Tic. A.a. All Members Tour",
    "wof:placetype":"venue"
},
  "geometry": {"coordinates":[30.7092056274,36.8790512085],"type":"Point"}
}