{
  "type": "Feature",
  "properties": {
    "addr:full":"Yakacik Cd. 93 81410 Kartal Istanbul 46000",
    "addr:housenumber":"93",
    "addr:postcode":"81410;46000",
    "addr:street":"Yakacik Cd.",
    "iso:country":"TR",
    "sg:address":"Yakacik Cd. 93 81410",
    "sg:city":"Kartal",
    "sg:classifiers":[
        {
            "category":"Manufacturing",
            "subcategory":"Textiles",
            "type":"Manufacturing & Wholesale Goods"
        }
    ],
    "sg:phone":"+90 216 306 5700",
    "sg:postcode":"46000",
    "sg:province":"Istanbul",
    "sg:tags":[
        "cloth",
        "worker"
    ],
    "wof:name":"Mim Tekstil ?r?nleri Ltd. Sti.",
    "wof:placetype":"venue"
},
  "geometry": {"coordinates":[29.2521057129,40.9071159363],"type":"Point"}
}