{
  "type": "Feature",
  "properties": {
    "iso:country":"TR",
    "sg:address":"Ulucami Mahallesi",
    "sg:city":"Anamur",
    "sg:classifiers":[
        {
            "category":"Banks & Credit Unions",
            "subcategory":"Bank",
            "type":"Services"
        }
    ],
    "sg:phone":"+90 236 768 1061",
    "sg:postcode":"33630",
    "sg:province":"Ahmetli",
    "wof:name":"T?kiye Is Bankasi As",
    "wof:placetype":"venue"
},
  "geometry": {"coordinates":[27.9384,38.5219],"type":"Point"}
}