{
  "type": "Feature",
  "properties": {
    "addr:full":"Babadag Babadag Denizli 20480",
    "addr:postcode":"20480",
    "iso:country":"TR",
    "sg:address":"Babadag",
    "sg:city":"Babadag",
    "sg:classifiers":[
        {
            "category":"Shopping",
            "subcategory":"Computers & Home Electronics",
            "type":"Retail Goods"
        }
    ],
    "sg:phone":"+90 258 481 2026",
    "sg:postcode":"20480",
    "sg:province":"Denizli",
    "sg:tags":[
        "chamber",
        "commerce"
    ],
    "wof:name":"Babadag Ticaret Odasi",
    "wof:placetype":"venue"
},
  "geometry": {"coordinates":[28.8666992188,37.7999992371],"type":"Point"}
}