{
  "type": "Feature",
  "properties": {
    "addr:full":"Kurtulus Mah. Karaisali Cad. No:78 19 Mayis Apt. K:z/2 Balmumcu Adana 34349",
    "addr:housenumber":"19",
    "addr:postcode":"34349",
    "addr:street":"Mah. Karaisali Cad. No 78;Balmumcu",
    "iso:country":"TR",
    "sg:address":"Kurtulus Mah. Karaisali Cad. No:78 19 Mayis Apt. K:z/2",
    "sg:city":"Balmumcu",
    "sg:classifiers":[
        {
            "category":"Professional",
            "subcategory":"Engineering",
            "type":"Services"
        }
    ],
    "sg:phone":"+90 322 456 1163",
    "sg:postcode":"34349",
    "sg:province":"Adana",
    "sg:tags":[
        "architect"
    ],
    "wof:name":"Eta Mimarlik Dekorasyon Ltd.sti.",
    "wof:placetype":"venue"
},
  "geometry": {"coordinates":[35.3250198364,36.9854202271],"type":"Point"}
}