{
  "type": "Feature",
  "properties": {
    "addr:full":"Kagithane 4.levent Istanbul",
    "iso:country":"TR",
    "sg:address":"Kagithane",
    "sg:city":"4.levent",
    "sg:classifiers":[
        {
            "category":"Professional",
            "subcategory":"Printing & Photocopies",
            "type":"Services"
        }
    ],
    "sg:phone":"+90 212 295 7563",
    "sg:province":"Istanbul",
    "sg:tags":[
        "digital"
    ],
    "wof:name":"Avrupa Baski Merkezi",
    "wof:placetype":"venue"
},
  "geometry": {"coordinates":[28.9720802307,41.0798988342],"type":"Point"}
}