{
  "type": "Feature",
  "properties": {
    "addr:full":"Ertugrulgazi Cad. ?gri Sok. No:15 Ineg? Bursa 16400",
    "addr:housenumber":"?;no 15;?",
    "addr:postcode":"16400",
    "addr:street":"Ertugrulgazi Cad.;Gri Sok.;Ineg",
    "iso:country":"TR",
    "sg:address":"Ertugrulgazi Cad. ?gri Sok. No:15",
    "sg:city":"Ineg?",
    "sg:classifiers":[
        {
            "category":"Home & Garden",
            "subcategory":"Furniture",
            "type":"Retail Goods"
        }
    ],
    "sg:phone":"+90 536 989 0040",
    "sg:postcode":"16400",
    "sg:province":"Bursa",
    "sg:tags":[
        "armchair",
        "sofa"
    ],
    "wof:name":"H.o.t",
    "wof:placetype":"venue"
},
  "geometry": {"coordinates":[29.0586109161,40.1844291687],"type":"Point"}
}