{
  "type": "Feature",
  "properties": {
    "iso:country":"TR",
    "sg:address":"Dr.mustafa Enver Bey Cad. No:29 D:1 Alsancak",
    "sg:city":"Meram",
    "sg:classifiers":[
        {
            "category":"Professional",
            "subcategory":"Business Services",
            "type":"Services"
        }
    ],
    "sg:phone":"+90 232 464 9851",
    "sg:postcode":"42100",
    "sg:province":"Izmir",
    "wof:name":"Beta Organizasyon",
    "wof:placetype":"venue"
},
  "geometry": {"coordinates":[27.1379165649,38.4331665039],"type":"Point"}
}