{
  "type": "Feature",
  "properties": {
    "addr:full":"Perpa Tic.merkz.a Blok Kat.9 No:1283 Okmeydani Istanbul 34270",
    "addr:housenumber":"no 1283",
    "addr:postcode":"34270",
    "addr:street":"Okmeydani Istanbul",
    "iso:country":"TR",
    "sg:address":"Perpa Tic.merkz.a Blok Kat.9 No:1283",
    "sg:city":"Okmeydani",
    "sg:classifiers":[
        {
            "category":"Manufacturing",
            "subcategory":"Building Materials",
            "type":"Manufacturing & Wholesale Goods"
        }
    ],
    "sg:phone":"+90 212 220 2607",
    "sg:postcode":"34270",
    "sg:province":"Istanbul",
    "sg:tags":[
        "promotional"
    ],
    "wof:name":"Umut Matbaacilik Ve Reklam Hizmetleri",
    "wof:placetype":"venue"
},
  "geometry": {"coordinates":[28.8582191467,41.1257171631],"type":"Point"}
}