{
  "type": "Feature",
  "properties": {
    "addr:full":"Abide-i Hurriyet Cd. Hasat Sok. Omay Han No:4/4 Sisli Emin?? 34440 Istanbul",
    "addr:housenumber":"4;emin ? ?",
    "addr:postcode":"34440",
    "addr:street":"Hurriyet Cd. Hasat Sok. Omay Han No 4 /",
    "iso:country":"TR",
    "sg:address":"Abide-i Hurriyet Cd. Hasat Sok. Omay Han No:4/4 Sisli",
    "sg:city":"Emin?? 34440",
    "sg:orig_category":"Printinh House",
    "sg:phone":"+90 212 224 9222",
    "sg:province":"Istanbul",
    "wof:name":"Motorbike Dergisi",
    "wof:placetype":"venue"
},
  "geometry": {"coordinates":[28.987903595,41.0586929321],"type":"Point"}
}