{
  "type": "Feature",
  "properties": {
    "addr:full":"1249 Sk. No: 12 Beyazit Izmir 34420",
    "addr:housenumber":"12",
    "addr:postcode":"34420",
    "addr:street":"1249 Sk. No",
    "iso:country":"TR",
    "sg:address":"1249 Sk. No: 12",
    "sg:city":"Beyazit",
    "sg:classifiers":[
        {
            "category":"Shopping",
            "subcategory":"Luggage & Leather Goods",
            "type":"Retail Goods"
        }
    ],
    "sg:phone":"+90 232 459 5154",
    "sg:postcode":"34420",
    "sg:province":"Izmir",
    "sg:tags":[
        "leather-fur",
        "wear"
    ],
    "wof:name":"Krom Deri San. Ve Tic. Ltd. Sti.",
    "wof:placetype":"venue"
},
  "geometry": {"coordinates":[27.1646156311,38.4265327454],"type":"Point"}
}