{
  "type": "Feature",
  "properties": {
    "addr:full":"Hukumet Cad. 83/b Yerkoy \u00dcmraniye Yozgat 03650",
    "addr:housenumber":"83 / b",
    "addr:postcode":"03650",
    "addr:street":"Hukumet Cad.;Yerkoy U\u0308Mraniye",
    "iso:country":"TR",
    "sg:address":"Hukumet Cad. 83/b Yerkoy",
    "sg:city":"\u00dcmraniye",
    "sg:classifiers":[
        {
            "category":"Wholesale",
            "subcategory":"Plants",
            "type":"Manufacturing & Wholesale Goods"
        }
    ],
    "sg:phone":"+90 354 516 3729",
    "sg:postcode":"03650",
    "sg:province":"Yozgat",
    "sg:tags":[
        "natural",
        "spice"
    ],
    "wof:name":"Akdeniz Ticaret",
    "wof:placetype":"venue"
},
  "geometry": {"coordinates":[34.8055,39.821201],"type":"Point"}
}