{
  "type": "Feature",
  "properties": {
    "iso:country":"TR",
    "sg:address":"Nizip Yolu ?z. G?l??mev.",
    "sg:city":"Merter",
    "sg:classifiers":[
        {
            "category":"Shopping",
            "subcategory":"Crafts & Fabrics",
            "type":"Retail Goods"
        }
    ],
    "sg:phone":"+90 342 235 1000",
    "sg:province":"Gaziantep",
    "sg:tags":[
        "yarn"
    ],
    "wof:name":"Asko Pazar. Ith. Ihr. A.s.",
    "wof:placetype":"venue"
},
  "geometry": {"coordinates":[37.389919281,37.0719261169],"type":"Point"}
}