{
  "type": "Feature",
  "properties": {
    "addr:full":"Atalar Cd. Ayta?ar Pasaji K:1 No:42 Edremit Balikesir 04500",
    "addr:housenumber":"?;1 no 42",
    "addr:postcode":"04500",
    "addr:street":"Atalar Cd. Ayta",
    "iso:country":"TR",
    "sg:address":"Atalar Cd. Ayta?ar Pasaji K:1 No:42",
    "sg:city":"Edremit",
    "sg:classifiers":[
        {
            "category":"Food & Beverages",
            "subcategory":"Groceries & Convenience Stores",
            "type":"Retail Goods"
        }
    ],
    "sg:phone":"+90 266 241 5263",
    "sg:postcode":"04500",
    "sg:province":"Balikesir",
    "sg:tags":[
        "product"
    ],
    "wof:name":"?ayirhisar Soguk Hava Tesisleri A.s.",
    "wof:placetype":"venue"
},
  "geometry": {"coordinates":[27.8833007812,39.6520996094],"type":"Point"}
}