{
  "type": "Feature",
  "properties": {
    "iso:country":"TR",
    "sg:address":"Klodfarer Cd. Servet Han No:4/a Sultanahmet",
    "sg:city":"Ikitelli/K\u00fc\u00e7\u00fck\u00e7ekmece",
    "sg:classifiers":[
        {
            "category":"Shopping",
            "subcategory":"Stationery & Office Supplies",
            "type":"Retail Goods"
        }
    ],
    "sg:phone":"+90 212 518 2205",
    "sg:postcode":"34660",
    "sg:province":"Istanbul",
    "wof:name":"Reform Kagit Kirtasiye Malz.",
    "wof:placetype":"venue"
},
  "geometry": {"coordinates":[29.049629,41.00758],"type":"Point"}
}