{
  "type": "Feature",
  "properties": {
    "iso:country":"TR",
    "sg:address":"Bayindir 1 Sk. Fazil Bey Ish. No:15 D:20 Kizilay",
    "sg:city":"\u00dcsk\u00fcdar",
    "sg:classifiers":[
        {
            "category":"Building & Trades",
            "subcategory":"Construction",
            "type":"Services"
        }
    ],
    "sg:phone":"+90 312 435 1940",
    "sg:province":"Ankara",
    "sg:tags":[
        "foundation"
    ],
    "wof:name":"Egitimci. Birl. Vakfi",
    "wof:placetype":"venue"
},
  "geometry": {"coordinates":[32.8511962891,39.9229354858],"type":"Point"}
}