{
  "type": "Feature",
  "properties": {
    "iso:country":"TR",
    "sg:address":"1643.sok. No:133 Bayrakli Karsiyaka",
    "sg:city":"\u00dcmraniye",
    "sg:classifiers":[
        {
            "category":"Shopping",
            "type":"Retail Goods"
        }
    ],
    "sg:phone":"+90 232 346 3535",
    "sg:postcode":"81240",
    "sg:province":"Izmir",
    "sg:tags":[
        "material",
        "cleaning"
    ],
    "wof:name":"Kapmar Gida Kimya San.tic.ltd.sti.",
    "wof:placetype":"venue"
},
  "geometry": {"coordinates":[27.1423015594,38.4251480103],"type":"Point"}
}