{
  "type": "Feature",
  "properties": {
    "iso:country":"TR",
    "sg:address":"In??caddesi No:314/c Hatay Konak",
    "sg:city":"G?esli",
    "sg:classifiers":[
        {
            "category":"Shopping",
            "subcategory":"Clothing, Apparel, & Fashions",
            "type":"Retail Goods"
        }
    ],
    "sg:phone":"+90 232 231 9478",
    "sg:province":"Izmir",
    "sg:tags":[
        "watch",
        "lighter"
    ],
    "wof:name":"Durusel Saat",
    "wof:placetype":"venue"
},
  "geometry": {"coordinates":[27.1592006683,38.4269981384],"type":"Point"}
}