{
  "type": "Feature",
  "properties": {
    "iso:country":"TR",
    "sg:address":"Imes Sanayi Sitesi E-501 Sk. No.15 Y.dudullu",
    "sg:city":"\u00dcmraniye",
    "sg:orig_category":"Babycare Products",
    "sg:phone":"+90 216 364 3232",
    "sg:province":"Istanbul",
    "wof:name":"Tim Kozmetik, Sabun, Otel Malz. San.tic. Ltd.sti.",
    "wof:placetype":"venue"
},
  "geometry": {"coordinates":[28.975925,41.012379],"type":"Point"}
}