{
  "type": "Feature",
  "properties": {
    "iso:country":"TR",
    "sg:address":"Ahmet Duran",
    "sg:city":"Beypazari",
    "sg:classifiers":[
        {
            "category":"Government",
            "subcategory":"Office",
            "type":"Public Place"
        }
    ],
    "sg:phone":"+90 358 293 7544",
    "sg:postcode":"06730",
    "sg:province":"Amasya",
    "sg:tags":[
        "municipality"
    ],
    "wof:name":"Uygur Belediye Baskani",
    "wof:placetype":"venue"
},
  "geometry": {"coordinates":[35.8320007324,40.6543998718],"type":"Point"}
}