{
  "type": "Feature",
  "properties": {
    "iso:country":"TR",
    "sg:address":"S?er Mh.",
    "sg:city":"Zeytinburnu",
    "sg:classifiers":[
        {
            "category":"Manufacturing",
            "subcategory":"Metals",
            "type":"Manufacturing & Wholesale Goods"
        }
    ],
    "sg:phone":"+90 258 268 2113",
    "sg:postcode":"34780",
    "sg:province":"Denizli",
    "sg:tags":[
        "iron-steel",
        "peoducts"
    ],
    "wof:name":"Boztepe ?elik Ltd. Sti.",
    "wof:placetype":"venue"
},
  "geometry": {"coordinates":[29.1076107025,37.7767524719],"type":"Point"}
}