{
  "type": "Feature",
  "properties": {
    "addr:full":"Atisalani Cad. Gumustunc Is Hani No:8 Kat: 4 No:33 Esenler Istanbul 01350",
    "addr:housenumber":"kat 4 no 33",
    "addr:postcode":"01350",
    "addr:street":"Atisalani Cad. Gumustunc Is;No 8",
    "iso:country":"TR",
    "sg:address":"Atisalani Cad. Gumustunc Is Hani No:8 Kat: 4 No:33",
    "sg:city":"Esenler",
    "sg:classifiers":[
        {
            "category":"Insurance",
            "subcategory":"Hazard Insurance",
            "type":"Services"
        }
    ],
    "sg:phone":"+90 212 569 5880",
    "sg:postcode":"01350",
    "sg:province":"Istanbul",
    "wof:name":"Zirve Sigorta Trafik Musavirligi",
    "wof:placetype":"venue"
},
  "geometry": {"coordinates":[28.9861831665,41.0408554077],"type":"Point"}
}