{
  "type": "Feature",
  "properties": {
    "addr:full":"Zeytinlik Mah. ?mer Naci Sok. G?ldal Apt. No:2 / Kat:2 / Daire:2 Bak\u0131rk\u00f6y Istanbul",
    "addr:housenumber":"mah. ?;?;2;2",
    "addr:street":"Mer Naci Sok. G;Daire",
    "iso:country":"TR",
    "sg:address":"Zeytinlik Mah. ?mer Naci Sok. G?ldal Apt. No:2 / Kat:2 / Daire:2",
    "sg:city":"Bak\u0131rk\u00f6y",
    "sg:classifiers":[
        {
            "category":"Organizations",
            "subcategory":"Non-profit Organization",
            "type":"Services"
        }
    ],
    "sg:phone":"+90 212 571 3206",
    "sg:province":"Istanbul",
    "sg:tags":[
        "alarm",
        "system"
    ],
    "wof:name":"Ulusoy G?venlik Sistemleri San.tic.ltd.sti",
    "wof:placetype":"venue"
},
  "geometry": {"coordinates":[28.9759254456,41.0123786926],"type":"Point"}
}