{
  "type": "Feature",
  "properties": {
    "addr:full":"Dilovasi Mevkii Gebze Kocaeli 41400",
    "addr:postcode":"41400",
    "addr:street":"Dilovasi Mevkii",
    "iso:country":"TR",
    "sg:address":"Dilovasi Mevkii",
    "sg:city":"Gebze",
    "sg:classifiers":[
        {
            "category":"Utilities",
            "subcategory":"Natural Gas",
            "type":"Services"
        }
    ],
    "sg:phone":"+90 262 754 6390",
    "sg:postcode":"41400",
    "sg:province":"Kocaeli",
    "sg:tags":[
        "tank-heating-natural"
    ],
    "wof:name":"Izocam Tic. San. A.s.",
    "wof:placetype":"venue"
},
  "geometry": {"coordinates":[29.9345855713,40.7669563293],"type":"Point"}
}