{
  "type": "Feature",
  "properties": {
    "addr:full":"Ortacami Mah. Cinarli Cesme Sok. No:8 D:2 Kad\u0131k\u00f6y Tekirdag 59300",
    "addr:housenumber":"no 8 d 2",
    "addr:postcode":"59300",
    "addr:street":"Ortacami Mah. Cinarli Cesme Sok.;Tekirdag",
    "iso:country":"TR",
    "sg:address":"Ortacami Mah. Cinarli Cesme Sok. No:8 D:2",
    "sg:city":"Kad\u0131k\u00f6y",
    "sg:classifiers":[
        {
            "category":"Professional",
            "subcategory":"Computer Services",
            "type":"Services"
        }
    ],
    "sg:phone":"+90 282 262 7644",
    "sg:postcode":"59300",
    "sg:province":"Tekirdag",
    "sg:tags":[
        "application",
        "software"
    ],
    "wof:name":"Demo Bilgisayar Yazilim San.tic. Ltd.sti.",
    "wof:placetype":"venue"
},
  "geometry": {"coordinates":[27.518995285,40.9782791138],"type":"Point"}
}