{
  "type": "Feature",
  "properties": {
    "iso:country":"TR",
    "sg:address":"Inonu Cad.no:198/cc",
    "sg:city":"Sahinbey",
    "sg:classifiers":[
        {
            "category":"Manufacturing",
            "subcategory":"Building Materials",
            "type":"Manufacturing & Wholesale Goods"
        }
    ],
    "sg:phone":"+90 342 232 6173",
    "sg:postcode":"27100",
    "sg:province":"Gaziantep",
    "sg:tags":[
        "lifts-elevators"
    ],
    "wof:name":"Azim Makina",
    "wof:placetype":"venue"
},
  "geometry": {"coordinates":[37.3840560913,37.0913619995],"type":"Point"}
}