{
  "type": "Feature",
  "properties": {
    "iso:country":"TR",
    "sg:address":"Ihsaniye Mah. Fsm Bulvari Umit -2 Apt. No: 10 D:2",
    "sg:city":"Nilufer",
    "sg:classifiers":[
        {
            "category":"Professional",
            "subcategory":"Engineering",
            "type":"Services"
        }
    ],
    "sg:phone":"+90 224 249 6020",
    "sg:postcode":"16370",
    "sg:province":"Bursa",
    "sg:tags":[
        "architect"
    ],
    "wof:name":"5m Muhendislik Ltd.sti.",
    "wof:placetype":"venue"
},
  "geometry": {"coordinates":[29.0586109161,40.1844291687],"type":"Point"}
}