{
  "type": "Feature",
  "properties": {
    "iso:country":"TR",
    "sg:address":"Tabakhane 2253 Sk.no.70",
    "sg:city":"Beyazit",
    "sg:classifiers":[
        {
            "category":"Manufacturing",
            "subcategory":"Leather Goods",
            "type":"Manufacturing & Wholesale Goods"
        }
    ],
    "sg:phone":"+90 258 268 0133",
    "sg:postcode":"65400",
    "sg:province":"Denizli",
    "wof:name":"Sarksan Deri-k?sele Ltd.sti.",
    "wof:placetype":"venue"
},
  "geometry": {"coordinates":[29.0864906311,37.773525238],"type":"Point"}
}