{
  "type": "Feature",
  "properties": {
    "addr:full":"Vatan Cad. Fuar Siteleri D Blok 39/g Emin?? 34420 Konya",
    "addr:housenumber":"siteleri d blok 39 / g;? ?",
    "addr:postcode":"34420",
    "addr:street":"Vatan Cad. Fuar;Emin",
    "iso:country":"TR",
    "sg:address":"Vatan Cad. Fuar Siteleri D Blok 39/g",
    "sg:city":"Emin?? 34420",
    "sg:classifiers":[
        {
            "category":"Shopping",
            "subcategory":"Computers & Home Electronics",
            "type":"Retail Goods"
        }
    ],
    "sg:phone":"+90 332 350 2774",
    "sg:province":"Konya",
    "sg:tags":[
        "product",
        "electric-electronic"
    ],
    "wof:name":"Boca Makina A.s.",
    "wof:placetype":"venue"
},
  "geometry": {"coordinates":[32.8623580933,38.0141410828],"type":"Point"}
}