{
  "type": "Feature",
  "properties": {
    "iso:country":"TR",
    "sg:address":"Z?r?evler Handeg? Sok. No:55 Maltepe",
    "sg:city":"Fatih",
    "sg:classifiers":[
        {
            "category":"Wholesale",
            "subcategory":"Medical Equipment & Supplies",
            "type":"Manufacturing & Wholesale Goods"
        }
    ],
    "sg:phone":"+90 216 305 2495",
    "sg:postcode":"01740",
    "sg:province":"Istanbul",
    "sg:tags":[
        "material"
    ],
    "wof:name":"Medineks Ltd.",
    "wof:placetype":"venue"
},
  "geometry": {"coordinates":[28.9759254456,41.0123786926],"type":"Point"}
}