{
  "type": "Feature",
  "properties": {
    "addr:full":"Baglari? Cad. No:12 Avcilar Istanbul 01350",
    "addr:housenumber":"no 12",
    "addr:postcode":"01350",
    "addr:street":"Cad.;Istanbul",
    "iso:country":"TR",
    "sg:address":"Baglari? Cad. No:12",
    "sg:city":"Avcilar",
    "sg:orig_category":"Food Machinies",
    "sg:phone":"+90 212 591 0379",
    "sg:postcode":"01350",
    "sg:province":"Istanbul",
    "wof:name":"Kumkaya Makina Sanayi Ve Ticaret Ltd.sti.",
    "wof:placetype":"venue"
},
  "geometry": {"coordinates":[28.5186347961,41.0300712585],"type":"Point"}
}