{
  "type": "Feature",
  "properties": {
    "addr:full":"Organize San.bolg. Mavi Cad.2.sok. No: 216159 Nilufer 2nd Floor, Bury House Bursa LONDON",
    "addr:housenumber":"cad.2.sok no;2nd floor bury",
    "addr:postcode":"216159",
    "addr:street":"San.Bolg.;Bursa",
    "iso:country":"TR",
    "sg:address":"Organize San.bolg. Mavi Cad.2.sok. No: 216159 Nilufer",
    "sg:city":"2nd Floor, Bury House",
    "sg:classifiers":[
        {
            "category":"Government",
            "subcategory":"Post Office",
            "type":"Public Place"
        }
    ],
    "sg:phone":"+90 224 243 1500",
    "sg:postcode":"LONDON",
    "sg:province":"Bursa",
    "sg:tags":[
        "chamber",
        "industry"
    ],
    "wof:name":"Bursa Chamber Of Commerce And Industry",
    "wof:placetype":"venue"
},
  "geometry": {"coordinates":[29.0398807526,40.1076583862],"type":"Point"}
}