{
  "type": "Feature",
  "properties": {
    "addr:full":"Fevzipasa Mh. 939. Sk. No:12 Kutlukent Adana 06300",
    "addr:housenumber":"939;12",
    "addr:postcode":"06300",
    "addr:street":"Fevzipasa Mh.;Sk. No;Adana",
    "iso:country":"TR",
    "sg:address":"Fevzipasa Mh. 939. Sk. No:12",
    "sg:city":"Kutlukent",
    "sg:classifiers":[
        {
            "category":"Professional",
            "subcategory":"Business Services",
            "type":"Services"
        }
    ],
    "sg:phone":"+90 322 435 5735",
    "sg:postcode":"06300",
    "sg:province":"Adana",
    "sg:tags":[
        "industry",
        "casting"
    ],
    "wof:name":"S?rat Motor G?mlek. D?k?m San.",
    "wof:placetype":"venue"
},
  "geometry": {"coordinates":[35.3250198364,36.9854202271],"type":"Point"}
}