{
  "type": "Feature",
  "properties": {
    "addr:full":"Akin Sok.dostlar Apt. No: 14 D: 2 Suadiye Istanbul 34740",
    "addr:housenumber":"d 2",
    "addr:postcode":"34740",
    "iso:country":"TR",
    "sg:address":"Akin Sok.dostlar Apt. No: 14 D: 2",
    "sg:city":"Suadiye",
    "sg:classifiers":[
        {
            "category":"Professional",
            "subcategory":"Engineering",
            "type":"Services"
        }
    ],
    "sg:phone":"+90 2163637101729",
    "sg:postcode":"34740",
    "sg:province":"Istanbul",
    "sg:tags":[
        "architect"
    ],
    "wof:name":"E.e. Proje Insaat.san.tic.ltd.sti.",
    "wof:placetype":"venue"
},
  "geometry": {"coordinates":[28.9861831665,41.0408554077],"type":"Point"}
}