{
  "type": "Feature",
  "properties": {
    "iso:country":"TR",
    "sg:address":"Konya Sok. No:3/51 -52 Ulus",
    "sg:city":"Okmeydani/sisli",
    "sg:classifiers":[
        {
            "category":"Shopping",
            "subcategory":"Computers & Home Electronics",
            "type":"Retail Goods"
        }
    ],
    "sg:phone":"+90 312 309 3657",
    "sg:postcode":"80270",
    "sg:province":"Ankara",
    "sg:tags":[
        "product",
        "electric-electronic"
    ],
    "wof:name":"Dermanli Elektronik Ltd. Sti.",
    "wof:placetype":"venue"
},
  "geometry": {"coordinates":[32.8604812622,39.9429283142],"type":"Point"}
}