{
  "type": "Feature",
  "properties": {
    "addr:full":"100.yil Mah.yeni Sanayi Sitesi Is Merkezi B Blok No:2-3 M.kemal Pasa Tekirdag",
    "addr:street":"Mah.Yeni Sanayi Sitesi;M.Kemal",
    "iso:country":"TR",
    "sg:address":"100.yil Mah.yeni Sanayi Sitesi Is Merkezi B Blok No:2-3",
    "sg:city":"M.kemal Pasa",
    "sg:classifiers":[
        {
            "category":"Farming",
            "subcategory":"Farm & Veterinary Services",
            "type":"Manufacturing & Wholesale Goods"
        }
    ],
    "sg:phone":"+90 282 261 7738",
    "sg:province":"Tekirdag",
    "sg:tags":[
        "veterinarian"
    ],
    "wof:name":"Zeybekoglu Veterinerlik Hizmetleri Ilac San.ltd.sti.",
    "wof:placetype":"venue"
},
  "geometry": {"coordinates":[27.5144004822,40.9791984558],"type":"Point"}
}