{
  "type": "Feature",
  "properties": {
    "iso:country":"TR",
    "sg:address":"Parseller Mevkii San. Cd. G-44.sk. No:20 Pendik",
    "sg:city":"\u00dcmraniye",
    "sg:classifiers":[
        {
            "category":"Shopping",
            "subcategory":"Computers & Home Electronics",
            "type":"Retail Goods"
        }
    ],
    "sg:phone":"+90 216 378 4400",
    "sg:province":"Istanbul",
    "sg:tags":[
        "connector",
        "cable"
    ],
    "wof:name":"Kavi Kablo Ve Emaye Bobin Teli San. A.s.",
    "wof:placetype":"venue"
},
  "geometry": {"coordinates":[29.3492794037,40.9514503479],"type":"Point"}
}