{
  "type": "Feature",
  "properties": {
    "addr:full":"Oto Sanayi Sitesi Celik Sokak No:39 80260 4.levent Istanbul Cagaloglu Istanbul 34440",
    "addr:housenumber":"no 39",
    "addr:postcode":"80260;34440",
    "addr:street":"Celik Sokak",
    "iso:country":"TR",
    "sg:address":"Oto Sanayi Sitesi Celik Sokak No:39 80260 4.levent Istanbul",
    "sg:city":"Cagaloglu",
    "sg:classifiers":[
        {
            "category":"Shopping",
            "type":"Retail Goods"
        }
    ],
    "sg:phone":"+90 212 264 0777",
    "sg:postcode":"34440",
    "sg:province":"Istanbul",
    "sg:tags":[
        "finished",
        "-",
        "metallic"
    ],
    "wof:name":"Oygarsan Tappet Ve Supap Gaydlari San Tic Ltd Sti",
    "wof:placetype":"venue"
},
  "geometry": {"coordinates":[29.0409469604,41.0940933228],"type":"Point"}
}