{
  "type": "Feature",
  "properties": {
    "iso:country":"TR",
    "sg:address":"Yildirim Mah. Zafer Cad. No:111",
    "sg:city":"Bayrampasa",
    "sg:classifiers":[
        {
            "category":"Wholesale",
            "subcategory":"Machinery & Supplies",
            "type":"Manufacturing & Wholesale Goods"
        }
    ],
    "sg:phone":"+90 212 537 4527",
    "sg:postcode":"36100",
    "sg:province":"Istanbul",
    "sg:tags":[
        "agricultural"
    ],
    "wof:name":"Caliskan Pancar Motor Tic.",
    "wof:placetype":"venue"
},
  "geometry": {"coordinates":[28.893081665,41.0695648193],"type":"Point"}
}