{
  "type": "Feature",
  "properties": {
    "addr:full":"10015 Sokak No:7 A.o.s.b. Cisligi 35620 Dudullu Izmir",
    "addr:postcode":"35620",
    "addr:street":"10015 Sokak No 7 A.O.S.B. Cisligi",
    "iso:country":"TR",
    "sg:address":"10015 Sokak No:7 A.o.s.b. Cisligi 35620",
    "sg:city":"Dudullu",
    "sg:classifiers":[
        {
            "category":"Manufacturing",
            "subcategory":"Tools & Machinery",
            "type":"Manufacturing & Wholesale Goods"
        }
    ],
    "sg:phone":"+90 232 376 8030",
    "sg:province":"Izmir",
    "sg:tags":[
        "machine",
        "industry"
    ],
    "wof:name":"Havatek Makina Sanayi Ve Ticaret A.s.",
    "wof:placetype":"venue"
},
  "geometry": {"coordinates":[27.0418834686,38.4866600037],"type":"Point"}
}