{
  "type": "Feature",
  "properties": {
    "addr:full":"Bahariye Cad. Adliye Passaji No: 72-3 Kadikoy ?emberlitas Istanbul 34440",
    "addr:housenumber":"72-3;?",
    "addr:postcode":"34440",
    "addr:street":"Bahariye Cad. Adliye Passaji No;Kadikoy",
    "iso:country":"TR",
    "sg:address":"Bahariye Cad. Adliye Passaji No: 72-3 Kadikoy",
    "sg:city":"?emberlitas",
    "sg:classifiers":[
        {
            "category":"Shopping",
            "subcategory":"Jewelry",
            "type":"Retail Goods"
        }
    ],
    "sg:phone":"+90 216 449 2292",
    "sg:postcode":"34440",
    "sg:province":"Istanbul",
    "sg:tags":[
        "-",
        "golg-silver"
    ],
    "wof:name":"Som G?m?s",
    "wof:placetype":"venue"
},
  "geometry": {"coordinates":[28.9666919708,41.0404586792],"type":"Point"}
}