{
  "type": "Feature",
  "properties": {
    "iso:country":"TR",
    "sg:address":"?amlitepe Sk. No:109/a",
    "sg:city":"Siteler",
    "sg:classifiers":[
        {
            "category":"Home & Garden",
            "subcategory":"Hardware",
            "type":"Retail Goods"
        }
    ],
    "sg:phone":"+90 312 351 2029",
    "sg:postcode":"07070",
    "sg:province":"Ankara",
    "sg:tags":[
        "store"
    ],
    "wof:name":"Ugurlu Tic. San. Ltd. Sti.",
    "wof:placetype":"venue"
},
  "geometry": {"coordinates":[32.8604812622,39.9429283142],"type":"Point"}
}