{
  "type": "Feature",
  "properties": {
    "addr:full":"Ataturk Blv. Kosem Apt. N 9/6 Sisli K?tahya 34620",
    "addr:housenumber":"9 / 6",
    "addr:postcode":"34620",
    "addr:street":"Ataturk Blv. Kosem Apt. N;K ? Tahya",
    "iso:country":"TR",
    "sg:address":"Ataturk Blv. Kosem Apt. N 9/6",
    "sg:city":"Sisli",
    "sg:classifiers":[
        {
            "category":"Mining & Drilling",
            "type":"Manufacturing & Wholesale Goods"
        }
    ],
    "sg:phone":"+90 274 216 3364",
    "sg:postcode":"34620",
    "sg:province":"K?tahya",
    "sg:tags":[
        "industry",
        "mine"
    ],
    "wof:name":"Fidan Madencilik Ltd.sti.",
    "wof:placetype":"venue"
},
  "geometry": {"coordinates":[28.9674797058,41.0096588135],"type":"Point"}
}