{
  "type": "Feature",
  "properties": {
    "addr:full":"1762.sok.no:13 Karabaglar Kad\u0131k\u00f6y Izmir 35700",
    "addr:housenumber":"13",
    "addr:postcode":"35700",
    "addr:street":"Karabaglar Kadikoey",
    "iso:country":"TR",
    "sg:address":"1762.sok.no:13 Karabaglar",
    "sg:city":"Kad\u0131k\u00f6y",
    "sg:classifiers":[
        {
            "category":"Organizations",
            "subcategory":"Membership Organization",
            "type":"Services"
        }
    ],
    "sg:phone":"+90 232 369 3366",
    "sg:postcode":"35700",
    "sg:province":"Izmir",
    "wof:name":"Verem Savas Grup Baskanligi",
    "wof:placetype":"venue"
},
  "geometry": {"coordinates":[27.1423015594,38.4251480103],"type":"Point"}
}