{
  "type": "Feature",
  "properties": {
    "addr:full":"Fatih Cd. No:90/1 Y.bosna Istanbul",
    "addr:housenumber":"no 90 / 1",
    "addr:street":"Fatih Cd.",
    "iso:country":"TR",
    "sg:address":"Fatih Cd. No:90/1",
    "sg:city":"Y.bosna",
    "sg:classifiers":[
        {
            "category":"Utilities",
            "subcategory":"Natural Gas",
            "type":"Services"
        }
    ],
    "sg:phone":"+90 212 551 3352",
    "sg:province":"Istanbul",
    "sg:tags":[
        "tank-heating-natural"
    ],
    "wof:name":"Seda M?hendis. Insaat San. Tic. Ltd. Sti.",
    "wof:placetype":"venue"
},
  "geometry": {"coordinates":[28.9861831665,41.0408554077],"type":"Point"}
}