{
  "type": "Feature",
  "properties": {
    "addr:full":"Osmanaga Kardut Sk. No:17 Kad\u0131k\u00f6y Istanbul 34990",
    "addr:housenumber":"17",
    "addr:postcode":"34990",
    "addr:street":"Kardut Sk. No;Istanbul",
    "iso:country":"TR",
    "sg:address":"Osmanaga Kardut Sk. No:17",
    "sg:city":"Kad\u0131k\u00f6y",
    "sg:classifiers":[
        {
            "category":"Airport",
            "subcategory":"International",
            "type":"Transportation"
        }
    ],
    "sg:phone":"+90 216 414 1265",
    "sg:postcode":"34990",
    "sg:province":"Istanbul",
    "wof:name":"Aytug Uluslararasi Tasima. Turizm. I? Dis Tic.",
    "wof:placetype":"venue"
},
  "geometry": {"coordinates":[28.9861831665,41.0408554077],"type":"Point"}
}