{
  "type": "Feature",
  "properties": {
    "addr:full":"Ahmediye Cad. Hacisalih Sok. No:1 Kat:1 Fatih Istanbul 01740",
    "addr:housenumber":"no 1 kat 1",
    "addr:postcode":"01740",
    "addr:street":"Ahmediye Cad. Hacisalih Sok.",
    "iso:country":"TR",
    "sg:address":"Ahmediye Cad. Hacisalih Sok. No:1 Kat:1",
    "sg:city":"Fatih",
    "sg:classifiers":[
        {
            "category":"Manufacturing",
            "subcategory":"Building Materials",
            "type":"Manufacturing & Wholesale Goods"
        }
    ],
    "sg:phone":"+90 212 534 6290",
    "sg:postcode":"01740",
    "sg:province":"Istanbul",
    "sg:tags":[
        "floor-wall",
        "covering"
    ],
    "wof:name":"Genc Aktif Ins.",
    "wof:placetype":"venue"
},
  "geometry": {"coordinates":[28.9759254456,41.0123786926],"type":"Point"}
}