{
  "type": "Feature",
  "properties": {
    "addr:full":"G?su Evleri Yasemin Sok. A 62 A Kavacik Sisli Istanbul 65710",
    "addr:housenumber":"62 a",
    "addr:postcode":"65710",
    "addr:street":"Yasemin Sok. A",
    "iso:country":"TR",
    "sg:address":"G?su Evleri Yasemin Sok. A 62 A Kavacik",
    "sg:city":"Sisli",
    "sg:classifiers":[
        {
            "category":"Professional",
            "subcategory":"Business Services",
            "type":"Services"
        }
    ],
    "sg:phone":"+90 216 465 0293",
    "sg:postcode":"65710",
    "sg:province":"Istanbul",
    "wof:name":"Party Service Tanitim Organizasyon",
    "wof:placetype":"venue"
},
  "geometry": {"coordinates":[29.0538101196,41.1305809021],"type":"Point"}
}