{
  "type": "Feature",
  "properties": {
    "addr:full":"Ebuziya Cad. Bilgi Sok.no:1/a3 Bakirkoy 07100 Istanbul",
    "addr:housenumber":"bilgi;1 / a3 bakirkoy",
    "addr:postcode":"07100",
    "addr:street":"Ebuziya Cad.",
    "iso:country":"TR",
    "sg:address":"Ebuziya Cad. Bilgi Sok.no:1/a3 Bakirkoy",
    "sg:city":"07100",
    "sg:classifiers":[
        {
            "category":"Shopping",
            "subcategory":"Optical Goods",
            "type":"Retail Goods"
        }
    ],
    "sg:phone":"+90 212 570 8013",
    "sg:province":"Istanbul",
    "sg:tags":[
        "material"
    ],
    "wof:name":"Lens Dunyasi",
    "wof:placetype":"venue"
},
  "geometry": {"coordinates":[28.8349132538,40.9808235168],"type":"Point"}
}