{
  "type": "Feature",
  "properties": {
    "iso:country":"TR",
    "sg:address":"Ataturk Cad. No:202 Bandirma",
    "sg:city":"Ikitelli/K\u00fc\u00e7\u00fck\u00e7ekmece",
    "sg:classifiers":[
        {
            "category":"Home & Garden",
            "subcategory":"Hardware",
            "type":"Retail Goods"
        }
    ],
    "sg:phone":"+90 266 712 3510",
    "sg:postcode":"34670",
    "sg:province":"Balikesir",
    "sg:tags":[
        "compressor",
        "pump"
    ],
    "wof:name":"El-su Ticaret",
    "wof:placetype":"venue"
},
  "geometry": {"coordinates":[27.9763145447,40.3482475281],"type":"Point"}
}