{
  "type": "Feature",
  "properties": {
    "iso:country":"TR",
    "sg:address":"Abubekir Yakan",
    "sg:city":"Sincik",
    "sg:classifiers":[
        {
            "category":"Government",
            "subcategory":"Office",
            "type":"Public Place"
        }
    ],
    "sg:phone":"+90 416 427 2001",
    "sg:postcode":"02900",
    "sg:province":"Adiyaman",
    "sg:tags":[
        "municipality"
    ],
    "wof:name":"Inlice Belediye Baskani",
    "wof:placetype":"venue"
},
  "geometry": {"coordinates":[38.2784004211,37.7607002258],"type":"Point"}
}