{
  "type": "Feature",
  "properties": {
    "addr:full":"Vatan Mh. Esenler Cd. Ar Sk. No:15/1 Bayrampasa Iskenderun Istanbul 31200",
    "addr:housenumber":"15 / 1",
    "addr:postcode":"31200",
    "addr:street":"Esenler Cd.;Sk. No;Bayrampasa",
    "iso:country":"TR",
    "sg:address":"Vatan Mh. Esenler Cd. Ar Sk. No:15/1 Bayrampasa",
    "sg:city":"Iskenderun",
    "sg:classifiers":[
        {
            "category":"Manufacturing",
            "subcategory":"Tools & Machinery",
            "type":"Manufacturing & Wholesale Goods"
        }
    ],
    "sg:phone":"+90 212 577 8907",
    "sg:postcode":"31200",
    "sg:province":"Istanbul",
    "sg:tags":[
        "machine",
        "industry"
    ],
    "wof:name":"Baha Makina San.",
    "wof:placetype":"venue"
},
  "geometry": {"coordinates":[28.9058475494,41.030040741],"type":"Point"}
}