{
  "type": "Feature",
  "properties": {
    "iso:country":"TR",
    "sg:address":"Organize San. B?ge. 8.cd.",
    "sg:city":"\u00c7ankaya",
    "sg:classifiers":[
        {
            "category":"Home & Garden",
            "subcategory":"Building Materials",
            "type":"Retail Goods"
        }
    ],
    "sg:phone":"+90 222 236 0484",
    "sg:postcode":"06660",
    "sg:province":"Eskisehir",
    "sg:tags":[
        "window",
        "door",
        "plastic"
    ],
    "wof:name":"Reckendrees Plastik Pencere San. Ltd. Sti.",
    "wof:placetype":"venue"
},
  "geometry": {"coordinates":[30.5175457001,39.7700805664],"type":"Point"}
}