{
  "type": "Feature",
  "properties": {
    "iso:country":"TR",
    "sg:address":"Kibris Cd.no: 54",
    "sg:city":"Fethiye",
    "sg:classifiers":[
        {
            "category":"Manufacturing",
            "subcategory":"Food",
            "type":"Manufacturing & Wholesale Goods"
        }
    ],
    "sg:phone":"+90 274 224 3801",
    "sg:postcode":"48300",
    "sg:province":"K?tahya",
    "sg:tags":[
        "wholesaler"
    ],
    "wof:name":"Balaban Gida Ltd.sti.",
    "wof:placetype":"venue"
},
  "geometry": {"coordinates":[29.1296596527,36.6969795227],"type":"Point"}
}