{
  "type": "Feature",
  "properties": {
    "addr:full":"Tavuk?yolu Cad. No :238 Kat:1 Y.dudullu ?raniye Istanbul",
    "addr:housenumber":"?;238 kat 1 y.dudullu ?",
    "addr:street":"Yolu Cad. No",
    "iso:country":"TR",
    "sg:address":"Tavuk?yolu Cad. No :238 Kat:1 Y.dudullu",
    "sg:city":"?raniye",
    "sg:classifiers":[
        {
            "category":"Wholesale",
            "subcategory":"Vending Machines",
            "type":"Manufacturing & Wholesale Goods"
        }
    ],
    "sg:phone":"+90 216 526 0333",
    "sg:province":"Istanbul",
    "sg:tags":[
        "rod",
        "welding"
    ],
    "wof:name":"S? Kaynak San. Tic. Ltd. Sti",
    "wof:placetype":"venue"
},
  "geometry": {"coordinates":[28.9759254456,41.0123786926],"type":"Point"}
}