{
  "type": "Feature",
  "properties": {
    "iso:country":"TR",
    "sg:address":"Ciragan Cad. No:46",
    "sg:city":"Besiktas",
    "sg:classifiers":[
        {
            "category":"Building & Trades",
            "subcategory":"Electrical",
            "type":"Services"
        }
    ],
    "sg:phone":"+90 216 311 4700",
    "sg:postcode":"75200",
    "sg:province":"Istanbul",
    "sg:tags":[
        "equipment",
        "lighting"
    ],
    "wof:name":"Cedetas Elektromekanik A.s.",
    "wof:placetype":"venue"
},
  "geometry": {"coordinates":[29.0178165436,41.0452880859],"type":"Point"}
}