{
  "type": "Feature",
  "properties": {
    "iso:country":"TR",
    "sg:address":"Kozyatagi In??cd. Aydin Sk. No:5/1 Kozyatagi",
    "sg:city":"\u00dcmraniye",
    "sg:classifiers":[
        {
            "category":"Freight",
            "type":"Transportation"
        }
    ],
    "sg:phone":"+90 21263856279",
    "sg:postcode":"81260",
    "sg:province":"Istanbul",
    "sg:tags":[
        "packing",
        "industry"
    ],
    "wof:name":"Inpac Ambalaj Mak. Elekt. San. Ltd. Sti.",
    "wof:placetype":"venue"
},
  "geometry": {"coordinates":[29.0982494354,40.9642906189],"type":"Point"}
}