{
  "type": "Feature",
  "properties": {
    "addr:full":"Camiserif Mah.15.sok.no:12 Azizoglu Is Merkz. Mersin I?el 33050",
    "addr:housenumber":"12",
    "addr:postcode":"? el 33050",
    "addr:street":"Azizoglu Is Merkz.",
    "iso:country":"TR",
    "sg:address":"Camiserif Mah.15.sok.no:12 Azizoglu Is Merkz.",
    "sg:city":"Mersin",
    "sg:orig_category":"Dryfood-dried Nuts",
    "sg:phone":"+90 324 238 8182",
    "sg:postcode":"33050",
    "sg:province":"I?el",
    "wof:name":"Akg?nler Bakliyatgida San.tic.ltd.sti",
    "wof:placetype":"venue"
},
  "geometry": {"coordinates":[34.6333007812,36.7999992371],"type":"Point"}
}