{
  "type": "Feature",
  "properties": {
    "iso:country":"TR",
    "sg:address":"Kayisdagi Cad. No:205/5 G?tepe",
    "sg:city":"Fatih",
    "sg:classifiers":[
        {
            "category":"Wholesale",
            "subcategory":"Medical Equipment & Supplies",
            "type":"Manufacturing & Wholesale Goods"
        }
    ],
    "sg:phone":"+90 216 368 2810",
    "sg:postcode":"01740",
    "sg:province":"Istanbul",
    "sg:tags":[
        "material"
    ],
    "wof:name":"Meda Medikal Alet San. Tic. A.s.",
    "wof:placetype":"venue"
},
  "geometry": {"coordinates":[29.1212482452,40.9707527161],"type":"Point"}
}