{
  "type": "Feature",
  "properties": {
    "addr:full":"G?bag Mh. Esentepe Cd. No:30/11 Mecidiyek? 0038 Istanbul",
    "addr:housenumber":"no 30 / 11;?",
    "addr:postcode":"0038",
    "addr:street":"Mh. Esentepe Cd.;Mecidiyek",
    "iso:country":"TR",
    "sg:address":"G?bag Mh. Esentepe Cd. No:30/11 Mecidiyek?",
    "sg:city":"0038",
    "sg:classifiers":[
        {
            "category":"Home & Garden",
            "subcategory":"Household Appliances",
            "type":"Retail Goods"
        }
    ],
    "sg:phone":"+90 212 211 8181",
    "sg:province":"Istanbul",
    "sg:tags":[
        "utensil",
        "electrical"
    ],
    "wof:name":"Ceren Tic. A.s.",
    "wof:placetype":"venue"
},
  "geometry": {"coordinates":[28.9861793518,41.040851593],"type":"Point"}
}