{
  "type": "Feature",
  "properties": {
    "addr:full":"Talappasa Bulv. 72/3 Alsancak Kavaklidere Izmir 35040",
    "addr:housenumber":"72 / 3",
    "addr:postcode":"35040",
    "addr:street":"Talappasa Bulv.",
    "iso:country":"TR",
    "sg:address":"Talappasa Bulv. 72/3 Alsancak",
    "sg:city":"Kavaklidere",
    "sg:classifiers":[
        {
            "category":"Organizations",
            "subcategory":"Professional Association",
            "type":"Services"
        }
    ],
    "sg:phone":"+90 232 463 8621",
    "sg:postcode":"35040",
    "sg:province":"Izmir",
    "sg:tags":[
        "fair"
    ],
    "wof:name":"Efor Ege Fuarcilik Organizasyon",
    "wof:placetype":"venue"
},
  "geometry": {"coordinates":[27.1438140869,38.4352264404],"type":"Point"}
}