{
  "type": "Feature",
  "properties": {
    "iso:country":"TR",
    "sg:address":"Mesrutiyet Cad. 118 Tepebasi",
    "sg:city":"Istanbul",
    "sg:classifiers":[
        {
            "category":"Shopping",
            "subcategory":"Computers & Home Electronics",
            "type":"Retail Goods"
        }
    ],
    "sg:phone":"+90 212 252 2900",
    "sg:province":"80050",
    "sg:tags":[
        "chamber",
        "commerce"
    ],
    "sg:website":"www.iso.org.tr",
    "wof:name":"Istanbul Chamber Of Industry",
    "wof:placetype":"venue"
},
  "geometry": {"coordinates":[32.8614654541,39.986366272],"type":"Point"}
}