{
  "type": "Feature",
  "properties": {
    "addr:full":"Kagithane Cad. No:45 Caglayan Istanbul 07600",
    "addr:housenumber":"45",
    "addr:postcode":"07600",
    "addr:street":"Kagithane Cad. No",
    "iso:country":"TR",
    "sg:address":"Kagithane Cad. No:45",
    "sg:city":"Caglayan",
    "sg:classifiers":[
        {
            "category":"Wholesale",
            "subcategory":"Machinery & Supplies",
            "type":"Manufacturing & Wholesale Goods"
        }
    ],
    "sg:phone":"+90 212 210 1921",
    "sg:postcode":"07600",
    "sg:province":"Istanbul",
    "sg:tags":[
        "agricultural"
    ],
    "wof:name":"Sadal Tarim Mak. Dis Tic. A.s.",
    "wof:placetype":"venue"
},
  "geometry": {"coordinates":[28.9759998322,41.0751495361],"type":"Point"}
}