{
  "type": "Feature",
  "properties": {
    "iso:country":"TR",
    "sg:address":"Bedir Mah. Kuzey Sok.ozdavas Sitesi Alti No:12/e Selcuklu",
    "sg:city":"Kazasker",
    "sg:classifiers":[
        {
            "category":"Manufacturing",
            "subcategory":"Chemicals & Compounds",
            "type":"Manufacturing & Wholesale Goods"
        }
    ],
    "sg:phone":"+90 332 245 1608",
    "sg:province":"Konya",
    "sg:tags":[
        "pharmaceutical"
    ],
    "wof:name":"Univet Vet.tar.hayvancilik San. Tic.ltd.sti.",
    "wof:placetype":"venue"
},
  "geometry": {"coordinates":[32.4922866821,37.8815193176],"type":"Point"}
}