{
  "type": "Feature",
  "properties": {
    "iso:country":"TR",
    "sg:address":"Istiklal Mah.anafartalar Cad.no:17/b",
    "sg:city":"\u00dcmraniye",
    "sg:classifiers":[
        {
            "category":"Professional",
            "subcategory":"Detective & Security Services",
            "type":"Services"
        }
    ],
    "sg:phone":"+90 216 412 6230",
    "sg:province":"Istanbul",
    "sg:tags":[
        "material"
    ],
    "wof:name":"Power Control Systems Engineering Co.ltd",
    "wof:placetype":"venue"
},
  "geometry": {"coordinates":[29.100519,41.015129],"type":"Point"}
}