{
  "type": "Feature",
  "properties": {
    "iso:country":"TR",
    "sg:address":"Ambar Mah. Erdek Cad. No:72-74 Ambar",
    "sg:city":"Kutlukent",
    "sg:classifiers":[
        {
            "category":"Professional",
            "subcategory":"Business Services",
            "type":"Services"
        }
    ],
    "sg:phone":"+90 352326316132",
    "sg:postcode":"06300",
    "sg:province":"Kayseri",
    "sg:tags":[
        "industry",
        "casting"
    ],
    "wof:name":"Tek Dokum",
    "wof:placetype":"venue"
},
  "geometry": {"coordinates":[36.4393234253,38.2791290283],"type":"Point"}
}