{
  "type": "Feature",
  "properties": {
    "iso:country":"TR",
    "sg:address":"Kizilay Is Merkezi K.4 No:1",
    "sg:city":"Iskenderun",
    "sg:classifiers":[
        {
            "category":"Shopping",
            "subcategory":"Computers & Home Electronics",
            "type":"Retail Goods"
        }
    ],
    "sg:phone":"+90 442 234 4914",
    "sg:postcode":"31200",
    "sg:province":"Erzurum",
    "sg:tags":[
        "product",
        "electric-electronic"
    ],
    "wof:name":"Cemre Iletisim Insaat Ve Pazarlama Ltd. Sti.",
    "wof:placetype":"venue"
},
  "geometry": {"coordinates":[41.2808113098,39.8986663818],"type":"Point"}
}