{
  "type": "Feature",
  "properties": {
    "iso:country":"TR",
    "sg:address":"H?. Cd. Sarayk?",
    "sg:city":"Osmanbey",
    "sg:classifiers":[
        {
            "category":"Shopping",
            "subcategory":"Stationery & Office Supplies",
            "type":"Retail Goods"
        }
    ],
    "sg:phone":"+90 258 415 1195",
    "sg:postcode":"63000",
    "sg:province":"Denizli",
    "wof:name":"Egerci Kitap Kirtasiye",
    "wof:placetype":"venue"
},
  "geometry": {"coordinates":[29.086491,37.773525],"type":"Point"}
}