{
  "type": "Feature",
  "properties": {
    "iso:country":"TR",
    "sg:address":"Fevzipasa Mh. 939/54 Sk. No.36",
    "sg:city":"Seyhan",
    "sg:classifiers":[
        {
            "category":"Food & Beverages",
            "subcategory":"Meat & Fish",
            "type":"Retail Goods"
        }
    ],
    "sg:phone":"+90 322 428 1756",
    "sg:postcode":"01000",
    "sg:province":"Adana",
    "sg:tags":[
        "seafood"
    ],
    "wof:name":"Kilicaslan Su ?rn. A.s.",
    "wof:placetype":"venue"
},
  "geometry": {"coordinates":[35.2153358459,36.9985237122],"type":"Point"}
}