{
  "type": "Feature",
  "properties": {
    "addr:full":"Sezenler Sk. No:6 D:2 Sihhiye Ortak? Ankara 80840",
    "addr:housenumber":"2",
    "addr:postcode":"80840",
    "addr:street":"Sezenler Sk. No 6 D;Ortak;Ankara",
    "iso:country":"TR",
    "sg:address":"Sezenler Sk. No:6 D:2 Sihhiye",
    "sg:city":"Ortak?",
    "sg:classifiers":[
        {
            "category":"Organizations",
            "subcategory":"Professional Association",
            "type":"Services"
        }
    ],
    "sg:phone":"+90 312 229 5570",
    "sg:postcode":"80840",
    "sg:province":"Ankara",
    "wof:name":"Ttb Ankara Tabip Odasi",
    "wof:placetype":"venue"
},
  "geometry": {"coordinates":[32.8521308899,39.9256401062],"type":"Point"}
}