{
  "type": "Feature",
  "properties": {
    "iso:country":"TR",
    "sg:address":"Soganli Mah. Alper Sok. No:36 Bahcelievler",
    "sg:city":"Beyazit",
    "sg:classifiers":[
        {
            "category":"Shopping",
            "subcategory":"Clothing, Apparel, & Fashions",
            "type":"Retail Goods"
        }
    ],
    "sg:phone":"+90 212 507 6649",
    "sg:postcode":"34130",
    "sg:province":"Istanbul",
    "sg:tags":[
        "bag-belt-accessories"
    ],
    "wof:name":"Dema Deri Sanayi",
    "wof:placetype":"venue"
},
  "geometry": {"coordinates":[28.860487,41.012753],"type":"Point"}
}