{
  "type": "Feature",
  "properties": {
    "iso:country":"TR",
    "sg:address":"Yenipinar Sokak 2",
    "sg:city":"Ordu",
    "sg:classifiers":[
        {
            "category":"Banks & Credit Unions",
            "subcategory":"Bank",
            "type":"Services"
        }
    ],
    "sg:phone":"+90 452 214 7090",
    "sg:postcode":"52200",
    "sg:province":"52100",
    "wof:name":"T?kiye Halk, Bankasi As",
    "wof:placetype":"venue"
},
  "geometry": {"coordinates":[27.874058,39.651085],"type":"Point"}
}