{
  "type": "Feature",
  "properties": {
    "addr:full":"Ptt Araligi Yener Ishani No:84 Adapazari Melikgazi Sakarya 38000",
    "addr:housenumber":"84",
    "addr:postcode":"38000",
    "addr:street":"Ishani No;Melikgazi",
    "iso:country":"TR",
    "sg:address":"Ptt Araligi Yener Ishani No:84 Adapazari",
    "sg:city":"Melikgazi",
    "sg:classifiers":[
        {
            "category":"Banks & Credit Unions",
            "subcategory":"Investment Brokerage",
            "type":"Services"
        }
    ],
    "sg:phone":"+90 264 271 3300",
    "sg:postcode":"38000",
    "sg:province":"Sakarya",
    "sg:tags":[
        "-",
        "export",
        "import"
    ],
    "wof:name":"Farley International Trade",
    "wof:placetype":"venue"
},
  "geometry": {"coordinates":[30.3791446686,40.7734336853],"type":"Point"}
}