{
  "type": "Feature",
  "properties": {
    "addr:full":"Des San. Sit. 115.sok. C-20 Blok No:6 Y.dudullu Ikitelli/K\u00fc\u00e7\u00fck\u00e7ekmece Istanbul 34670",
    "addr:housenumber":"115.sok c-20 blok no 6",
    "addr:postcode":"34670",
    "addr:street":"Des San. Sit.",
    "iso:country":"TR",
    "sg:address":"Des San. Sit. 115.sok. C-20 Blok No:6 Y.dudullu",
    "sg:city":"Ikitelli/K\u00fc\u00e7\u00fck\u00e7ekmece",
    "sg:classifiers":[
        {
            "category":"Manufacturing",
            "subcategory":"Tools & Machinery",
            "type":"Manufacturing & Wholesale Goods"
        }
    ],
    "sg:phone":"+90 216 420 2045",
    "sg:postcode":"34670",
    "sg:province":"Istanbul",
    "sg:tags":[
        "machine",
        "industry"
    ],
    "wof:name":"Olusum Makina San. Ve Tic. Ltd.sti.",
    "wof:placetype":"venue"
},
  "geometry": {"coordinates":[28.9759254456,41.0123786926],"type":"Point"}
}