{
  "type": "Feature",
  "properties": {
    "addr:full":"Sakarya Cd. 1/22 10020 Sinop",
    "addr:housenumber":"1 / 22",
    "addr:postcode":"10020",
    "addr:street":"Cd.",
    "iso:country":"TR",
    "sg:address":"Sakarya Cd. 1/22",
    "sg:city":"10020",
    "sg:classifiers":[
        {
            "category":"Banks & Credit Unions",
            "subcategory":"Investment Brokerage",
            "type":"Services"
        }
    ],
    "sg:phone":"+90 368 261 4376",
    "sg:province":"Sinop",
    "sg:tags":[
        "-",
        "export",
        "import"
    ],
    "wof:name":"Rota Turizm Ve Dis Ticaret A.s.",
    "wof:placetype":"venue"
},
  "geometry": {"coordinates":[35.1506462097,42.0235900879],"type":"Point"}
}