{
  "type": "Feature",
  "properties": {
    "addr:full":"Telli Kavak Sok. 26/1 D: 64 Erenkoy Beylikduzu Istanbul 34520",
    "addr:housenumber":"26 / 1 d 64",
    "addr:postcode":"34520",
    "addr:street":"Kavak Sok.",
    "iso:country":"TR",
    "sg:address":"Telli Kavak Sok. 26/1 D: 64 Erenkoy",
    "sg:city":"Beylikduzu",
    "sg:orig_category":"General Industrial Products",
    "sg:phone":"+90 216 368 9443",
    "sg:postcode":"34520",
    "sg:province":"Istanbul",
    "wof:name":"Ozbabacan A.s.",
    "wof:placetype":"venue"
},
  "geometry": {"coordinates":[29.077394,40.972073],"type":"Point"}
}