{
  "type": "Feature",
  "properties": {
    "addr:full":"Camikebir Mah. Basma Sk. No:20/1-2 Sehir I? K???k?ekmece Kayseri",
    "addr:housenumber":"20 / 1-2",
    "addr:street":"Camikebir Mah. Basma Sk. No;I",
    "iso:country":"TR",
    "sg:address":"Camikebir Mah. Basma Sk. No:20/1-2 Sehir I?",
    "sg:city":"K???k?ekmece",
    "sg:classifiers":[
        {
            "category":"Home & Garden",
            "subcategory":"Household Appliances",
            "type":"Retail Goods"
        }
    ],
    "sg:phone":"+90 352 231 2859",
    "sg:province":"Kayseri",
    "sg:tags":[
        "kitchenware"
    ],
    "wof:name":"Artas Aluminyum San. Ltd. Sti.",
    "wof:placetype":"venue"
},
  "geometry": {"coordinates":[35.4891357422,38.7225761414],"type":"Point"}
}