{
  "type": "Feature",
  "properties": {
    "addr:full":"Etlik Garajlari No:72 Etlik Ikitelli Ankara 34670",
    "addr:postcode":"34670",
    "addr:street":"No 72 Etlik Ikitelli",
    "iso:country":"TR",
    "sg:address":"Etlik Garajlari No:72 Etlik",
    "sg:city":"Ikitelli",
    "sg:classifiers":[
        {
            "category":"Wholesale",
            "subcategory":"Auto Parts",
            "type":"Manufacturing & Wholesale Goods"
        }
    ],
    "sg:phone":"+90 312 341 0075",
    "sg:postcode":"34670",
    "sg:province":"Ankara",
    "sg:tags":[
        "spare"
    ],
    "wof:name":"Aksa Motorlu Araclar Ltd.sti.",
    "wof:placetype":"venue"
},
  "geometry": {"coordinates":[32.8604812622,39.9429283142],"type":"Point"}
}