{
  "type": "Feature",
  "properties": {
    "iso:country":"TR",
    "sg:address":"Iskele Cd.no55",
    "sg:city":"Alsancak",
    "sg:classifiers":[
        {
            "category":"Freight",
            "type":"Transportation"
        }
    ],
    "sg:phone":"+90 462 322 5432",
    "sg:postcode":"01365",
    "sg:province":"Trabzon",
    "sg:tags":[
        "agent",
        "shipping",
        "broker"
    ],
    "wof:name":"Karden Gemicilik A.s.",
    "wof:placetype":"venue"
},
  "geometry": {"coordinates":[39.719101,41.0061],"type":"Point"}
}