{
  "type": "Feature",
  "properties": {
    "addr:full":"19 Mayis Mah. Baris Cad. 25.sok. No:5/10 Incirli Bayrampasa Ankara 36100",
    "addr:housenumber":"19;25.sok no 5 / 10",
    "addr:postcode":"36100",
    "addr:street":"Mayis Mah. Baris Cad.",
    "iso:country":"TR",
    "sg:address":"19 Mayis Mah. Baris Cad. 25.sok. No:5/10 Incirli",
    "sg:city":"Bayrampasa",
    "sg:classifiers":[
        {
            "category":"Freight",
            "type":"Transportation"
        }
    ],
    "sg:phone":"+90 312 358 9277",
    "sg:postcode":"36100",
    "sg:province":"Ankara",
    "sg:tags":[
        "packing",
        "industry"
    ],
    "wof:name":"Turin Endustriyel Urunler Mum. Paz.",
    "wof:placetype":"venue"
},
  "geometry": {"coordinates":[32.8490943909,39.9841804504],"type":"Point"}
}