{
  "type": "Feature",
  "properties": {
    "iso:country":"TR",
    "sg:address":"Esenler Yolu Mobil Bitis. No:64/4 Bayrampasa",
    "sg:city":"Hask?y-beyoglu",
    "sg:classifiers":[
        {
            "category":"Shopping",
            "subcategory":"Stationery & Office Supplies",
            "type":"Retail Goods"
        }
    ],
    "sg:phone":"+90 212 698 3083",
    "sg:postcode":"34440",
    "sg:province":"Istanbul",
    "sg:tags":[
        "furniture"
    ],
    "wof:name":"Haksel Buro Mob.",
    "wof:placetype":"venue"
},
  "geometry": {"coordinates":[28.9666919708,41.0404586792],"type":"Point"}
}