{
  "type": "Feature",
  "properties": {
    "addr:full":"Yanyol No:54/b Alt Kaynarca Topkapi Istanbul 34020",
    "addr:postcode":"34020",
    "addr:street":"Alt",
    "iso:country":"TR",
    "sg:address":"Yanyol No:54/b Alt Kaynarca",
    "sg:city":"Topkapi",
    "sg:classifiers":[
        {
            "category":"Freight",
            "type":"Transportation"
        }
    ],
    "sg:phone":"+90 216 375 6834",
    "sg:postcode":"34020",
    "sg:province":"Istanbul",
    "sg:tags":[
        "packing",
        "industry"
    ],
    "wof:name":"?zen Ambalaj",
    "wof:placetype":"venue"
},
  "geometry": {"coordinates":[28.9026374817,40.9924430847],"type":"Point"}
}