{
  "type": "Feature",
  "properties": {
    "addr:full":"Gazcilar Cad.no:38/a Bayrampasa Bursa 36100",
    "addr:housenumber":"38 / a",
    "addr:postcode":"36100",
    "addr:street":"Bursa",
    "iso:country":"TR",
    "sg:address":"Gazcilar Cad.no:38/a",
    "sg:city":"Bayrampasa",
    "sg:orig_category":"Tricot",
    "sg:phone":"+90 224 254 4732",
    "sg:postcode":"36100",
    "sg:province":"Bursa",
    "wof:name":"?zkaymak Uludag Triko San.a.s",
    "wof:placetype":"venue"
},
  "geometry": {"coordinates":[29.0586109161,40.1844291687],"type":"Point"}
}