{
  "type": "Feature",
  "properties": {
    "addr:full":"Cendere Yolu No.16 Ayazaga ?atalca Istanbul 34870",
    "addr:housenumber":"no.16 ayazaga ?",
    "addr:postcode":"34870",
    "addr:street":"Cendere Yolu",
    "iso:country":"TR",
    "sg:address":"Cendere Yolu No.16 Ayazaga",
    "sg:city":"?atalca",
    "sg:classifiers":[
        {
            "category":"Manufacturing",
            "subcategory":"Leather Goods",
            "type":"Manufacturing & Wholesale Goods"
        }
    ],
    "sg:phone":"+90 212 285 2200",
    "sg:postcode":"34870",
    "sg:province":"Istanbul",
    "sg:tags":[
        "chemical"
    ],
    "wof:name":"Organik Kimya A.s.",
    "wof:placetype":"venue"
},
  "geometry": {"coordinates":[28.9608078003,41.1262893677],"type":"Point"}
}