{
  "type": "Feature",
  "properties": {
    "iso:country":"TR",
    "sg:address":"Oz Kafes Balikcilik Dolgu Sahasi Sehir Balik Hali",
    "sg:city":"Rami",
    "sg:classifiers":[
        {
            "category":"Food & Beverages",
            "subcategory":"Meat & Fish",
            "type":"Retail Goods"
        }
    ],
    "sg:phone":"+90 464 223 3045",
    "sg:postcode":"34055",
    "sg:province":"Rize",
    "sg:tags":[
        "seafood"
    ],
    "wof:name":"Oz Kafes Balikcilik Ltd.sti.",
    "wof:placetype":"venue"
},
  "geometry": {"coordinates":[40.5214004517,41.0223999023],"type":"Point"}
}