{
  "type": "Feature",
  "properties": {
    "iso:country":"TR",
    "sg:address":"Semsettin G. Cd. 250/1 Erenk?",
    "sg:city":"Ikitelli/K\u00fc\u00e7\u00fck\u00e7ekmece",
    "sg:orig_category":"Aluminium Carpentary",
    "sg:phone":"+90 216 386 4290",
    "sg:postcode":"34670",
    "sg:province":"Istanbul",
    "wof:name":"Yildirim Cam Ltd. Sti.",
    "wof:placetype":"venue"
},
  "geometry": {"coordinates":[29.0970497131,40.9578742981],"type":"Point"}
}