{
  "type": "Feature",
  "properties": {
    "iso:country":"TR",
    "sg:address":"Fevzipasa Cad. No:56",
    "sg:city":"Fatih",
    "sg:classifiers":[
        {
            "category":"Shopping",
            "subcategory":"Clothing, Apparel, & Fashions",
            "type":"Retail Goods"
        }
    ],
    "sg:phone":"+90 212523115552",
    "sg:postcode":"01740",
    "sg:province":"Istanbul",
    "sg:tags":[
        "woman",
        "wear"
    ],
    "wof:name":"Fuar Teks.",
    "wof:placetype":"venue"
},
  "geometry": {"coordinates":[28.5409946442,41.0288238525],"type":"Point"}
}