{
  "type": "Feature",
  "properties": {
    "iso:country":"TR",
    "sg:address":"1. San Sit Fatih Cad. No:87-",
    "sg:city":"Camdibi",
    "sg:classifiers":[
        {
            "category":"Manufacturing",
            "subcategory":"Glass & Minerals",
            "type":"Manufacturing & Wholesale Goods"
        }
    ],
    "sg:phone":"+90 232 486 3322",
    "sg:postcode":"24300",
    "sg:province":"Izmir",
    "sg:tags":[
        "glass-mirror"
    ],
    "wof:name":"Aytas Ayna San Ve Tic",
    "wof:placetype":"venue"
},
  "geometry": {"coordinates":[27.1296863556,38.4186973572],"type":"Point"}
}