{
  "type": "Feature",
  "properties": {
    "iso:country":"TR",
    "sg:address":"Izmir Cd. No:7/2 Kizilay",
    "sg:city":"Sariyer",
    "sg:classifiers":[
        {
            "category":"Mining & Drilling",
            "type":"Manufacturing & Wholesale Goods"
        }
    ],
    "sg:phone":"+90 312 230 5627",
    "sg:postcode":"33740",
    "sg:province":"Ankara",
    "sg:tags":[
        "industry",
        "mine"
    ],
    "wof:name":"?zdogan Madencilik A.s.",
    "wof:placetype":"venue"
},
  "geometry": {"coordinates":[32.8520812988,39.9247055054],"type":"Point"}
}