{
  "type": "Feature",
  "properties": {
    "iso:country":"TR",
    "sg:address":"100.yil Sanayi Sitesi No: 6 Maslak",
    "sg:city":"Bal?ova",
    "sg:classifiers":[
        {
            "category":"Shopping",
            "subcategory":"Computers & Home Electronics",
            "type":"Retail Goods"
        }
    ],
    "sg:phone":"+90 212 285 9104",
    "sg:postcode":"35330",
    "sg:province":"Istanbul",
    "sg:tags":[
        "product",
        "electric-electronic"
    ],
    "wof:name":"Tesla Elektrik & Pano San.tic.a.s.",
    "wof:placetype":"venue"
},
  "geometry": {"coordinates":[29.2031288147,40.8991088867],"type":"Point"}
}