{
  "type": "Feature",
  "properties": {
    "iso:country":"TR",
    "sg:address":"M.sami Cad. Altun Sok. No:26",
    "sg:city":"Merter",
    "sg:classifiers":[
        {
            "category":"Ice Cream",
            "type":"Food & Drink"
        }
    ],
    "sg:phone":"+90 332 342 2945",
    "sg:province":"Konya",
    "sg:tags":[
        "sugar"
    ],
    "wof:name":"Lawrubber",
    "wof:placetype":"venue"
},
  "geometry": {"coordinates":[32.499027,37.871536],"type":"Point"}
}