{
  "type": "Feature",
  "properties": {
    "addr:full":"M. Kemal Pasa Cd. No:50 Bah?lievler Bah\u00e7elievler Istanbul 34590",
    "addr:housenumber":"no 50;?",
    "addr:postcode":"34590",
    "addr:street":"M. Kemal Pasa Cd.;Bah",
    "iso:country":"TR",
    "sg:address":"M. Kemal Pasa Cd. No:50 Bah?lievler",
    "sg:city":"Bah\u00e7elievler",
    "sg:classifiers":[
        {
            "category":"Home & Garden",
            "subcategory":"Household Appliances",
            "type":"Retail Goods"
        }
    ],
    "sg:phone":"+90 212 505 0418",
    "sg:postcode":"34590",
    "sg:province":"Istanbul",
    "sg:tags":[
        "utensil",
        "electrical"
    ],
    "wof:name":"Miralay Day. T?k. Mal.",
    "wof:placetype":"venue"
},
  "geometry": {"coordinates":[28.9861831665,41.0408554077],"type":"Point"}
}