{
  "type": "Feature",
  "properties": {
    "addr:full":"Yildirim Mah. Ceberhan Sok. No:8 500 Evler Zeytinburnu Istanbul 34020",
    "addr:housenumber":"no",
    "addr:postcode":"500 evler;34020",
    "addr:street":"Yildirim Mah. Ceberhan Sok.;8",
    "iso:country":"TR",
    "sg:address":"Yildirim Mah. Ceberhan Sok. No:8 500 Evler",
    "sg:city":"Zeytinburnu",
    "sg:classifiers":[
        {
            "category":"Manufacturing",
            "subcategory":"Leather Goods",
            "type":"Manufacturing & Wholesale Goods"
        }
    ],
    "sg:phone":"+90 212 616 3762",
    "sg:postcode":"34020",
    "sg:province":"Istanbul",
    "wof:name":"Bade Deri San.tic.ltd.sti.",
    "wof:placetype":"venue"
},
  "geometry": {"coordinates":[28.8973484039,41.0688934326],"type":"Point"}
}