{
  "type": "Feature",
  "properties": {
    "addr:full":"Antalya Ikitelli/K\u00fc\u00e7\u00fck\u00e7ekmece Antalya 34660",
    "addr:postcode":"34660",
    "iso:country":"TR",
    "sg:address":"Antalya",
    "sg:city":"Ikitelli/K\u00fc\u00e7\u00fck\u00e7ekmece",
    "sg:classifiers":[
        {
            "category":"Health Services",
            "subcategory":"Hospital",
            "type":"Services"
        }
    ],
    "sg:phone":"+90 242 227 4343",
    "sg:postcode":"34660",
    "sg:province":"Antalya",
    "sg:tags":[
        "state"
    ],
    "wof:name":"Akdeniz ?niversitesi Tip Fak?tesi",
    "wof:placetype":"venue"
},
  "geometry": {"coordinates":[30.933332,37.181667],"type":"Point"}
}