{
  "type": "Feature",
  "properties": {
    "addr:full":"Osmancik Cd. No:51 Gebze ?orum 41400",
    "addr:housenumber":"no 51;?",
    "addr:postcode":"41400",
    "addr:street":"Osmancik Cd.",
    "iso:country":"TR",
    "sg:address":"Osmancik Cd. No:51",
    "sg:city":"Gebze",
    "sg:orig_category":"Aluminium Carpentary",
    "sg:phone":"+90 364 213 3651",
    "sg:postcode":"41400",
    "sg:province":"?orum",
    "wof:name":"Erbaslar Ins. Malz. Tic.",
    "wof:placetype":"venue"
},
  "geometry": {"coordinates":[34.9521141052,40.5535354614],"type":"Point"}
}