{
  "type": "Feature",
  "properties": {
    "iso:country":"TR",
    "sg:address":"N.kemal. Cad. No:4 Kisikk?",
    "sg:city":"Menderes",
    "sg:classifiers":[
        {
            "category":"Home & Garden",
            "subcategory":"Kitchen Supply",
            "type":"Retail Goods"
        }
    ],
    "sg:phone":"+90 232 257 5959",
    "sg:postcode":"35410",
    "sg:province":"Izmir",
    "sg:tags":[
        "wardrobe"
    ],
    "wof:name":"Akg? Mobilya",
    "wof:placetype":"venue"
},
  "geometry": {"coordinates":[27.1264743805,38.3336257935],"type":"Point"}
}