{
  "type": "Feature",
  "properties": {
    "addr:full":"Kasap Sok. No. 12 Kat. 2 Esentepe Istanbul 34394",
    "addr:housenumber":"no. 12;2",
    "addr:postcode":"34394",
    "addr:street":"Kasap Sok.;Kat.",
    "iso:country":"TR",
    "sg:address":"Kasap Sok. No. 12 Kat. 2 Esentepe",
    "sg:city":"Istanbul",
    "sg:classifiers":[
        {
            "category":"Professional",
            "subcategory":"Computer Services",
            "type":"Services"
        }
    ],
    "sg:postcode":"34394",
    "sg:tags":[
        "mobile",
        "vas",
        "community",
        "social-networking",
        "connected-devices",
        "android",
        "tablets",
        "smartphones"
    ],
    "sg:website":"http://www.buongiorno.com",
    "wof:name":"Buongiorno",
    "wof:placetype":"venue"
},
  "geometry": {"coordinates":[28.94057,41.029886],"type":"Point"}
}