{
  "type": "Feature",
  "properties": {
    "iso:country":"TR",
    "sg:address":"Halkali C. No.208 Sefak?",
    "sg:city":"\u00c7orlu",
    "sg:classifiers":[
        {
            "category":"Shopping",
            "subcategory":"Luggage & Leather Goods",
            "type":"Retail Goods"
        }
    ],
    "sg:phone":"+90 212 698 9800",
    "sg:province":"Istanbul",
    "sg:tags":[
        "leather-fur",
        "wear"
    ],
    "wof:name":"Desa Deri San. A.s.",
    "wof:placetype":"venue"
},
  "geometry": {"coordinates":[28.8132076263,41.0094261169],"type":"Point"}
}