{
  "type": "Feature",
  "properties": {
    "addr:full":"Yeni Hal Kompleksi Cok.amacli Bl.a.26 Derince I?el 31000",
    "addr:postcode":"31000",
    "addr:street":"El",
    "iso:country":"TR",
    "sg:address":"Yeni Hal Kompleksi Cok.amacli Bl.a.26",
    "sg:city":"Derince",
    "sg:classifiers":[
        {
            "category":"Home & Garden",
            "subcategory":"Garden Supply",
            "type":"Retail Goods"
        }
    ],
    "sg:phone":"+90 324 235 1098",
    "sg:postcode":"31000",
    "sg:province":"I?el",
    "sg:tags":[
        "fertilize",
        "soil"
    ],
    "wof:name":"Kurtulus Tarimsal Muhendislik Ltd.sti.",
    "wof:placetype":"venue"
},
  "geometry": {"coordinates":[36.247428894,36.4267196655],"type":"Point"}
}