{
  "type": "Feature",
  "properties": {
    "iso:country":"TR",
    "sg:address":"C.kebir Mah. Ulu Sok. Kaytim Is Merkezi No:2/901",
    "sg:city":"Alsancak",
    "sg:classifiers":[
        {
            "category":"Wholesale",
            "subcategory":"Petroleum",
            "type":"Manufacturing & Wholesale Goods"
        }
    ],
    "sg:phone":"+90 352 221 1818",
    "sg:postcode":"01365",
    "sg:province":"Kayseri",
    "wof:name":"?z Aydinlar Elk.lpg. Enr.sist. San. Ltd.sti.",
    "wof:placetype":"venue"
},
  "geometry": {"coordinates":[35.4891357422,38.7225761414],"type":"Point"}
}