{
  "type": "Feature",
  "properties": {
    "addr:full":"Y.emre Sk. No:1 4.levent Bayrampasa Istanbul 36100",
    "addr:housenumber":"4.levent",
    "addr:postcode":"36100",
    "addr:street":"Y.Emre Sk. No 1;Istanbul",
    "iso:country":"TR",
    "sg:address":"Y.emre Sk. No:1 4.levent",
    "sg:city":"Bayrampasa",
    "sg:classifiers":[
        {
            "category":"Communications",
            "subcategory":"Film & Video Production",
            "type":"Services"
        }
    ],
    "sg:phone":"+90 212 280 8167",
    "sg:postcode":"36100",
    "sg:province":"Istanbul",
    "sg:tags":[
        "-"
    ],
    "wof:name":"Protel Dis Tic. Ltd. Sti.",
    "wof:placetype":"venue"
},
  "geometry": {"coordinates":[28.9980163574,41.082157135],"type":"Point"}
}