{
  "type": "Feature",
  "properties": {
    "addr:full":"Kavakli Caddesi , S?mez Sokak, No : 18 Halkali Istanbul 23410",
    "addr:housenumber":"no 18",
    "addr:postcode":"23410",
    "addr:street":"Kavakli Caddesi S ? Mez Sokak;Istanbul",
    "iso:country":"TR",
    "sg:address":"Kavakli Caddesi , S?mez Sokak, No : 18",
    "sg:city":"Halkali",
    "sg:classifiers":[
        {
            "category":"Food & Beverages",
            "subcategory":"Candy",
            "type":"Retail Goods"
        }
    ],
    "sg:phone":"+90 2126975686729",
    "sg:postcode":"23410",
    "sg:province":"Istanbul",
    "sg:tags":[
        "biscuit-chocolate-candy"
    ],
    "wof:name":"Tatsam Tatlicilik Sanayi Tic.ltd.sti .",
    "wof:placetype":"venue"
},
  "geometry": {"coordinates":[28.975925,41.012379],"type":"Point"}
}