{
  "type": "Feature",
  "properties": {
    "iso:country":"TR",
    "sg:address":"Araban Yolu 4.km.",
    "sg:city":"Beylerbeyi",
    "sg:classifiers":[
        {
            "category":"Wholesale",
            "subcategory":"Farm Supplies",
            "type":"Manufacturing & Wholesale Goods"
        }
    ],
    "sg:phone":"+90 34242812354",
    "sg:postcode":"20300",
    "sg:province":"Gaziantep",
    "sg:tags":[
        "feed",
        "industry"
    ],
    "wof:name":"Keskin Yem San. A.s.",
    "wof:placetype":"venue"
},
  "geometry": {"coordinates":[37.3761024475,37.0629463196],"type":"Point"}
}