{
  "type": "Feature",
  "properties": {
    "addr:full":"Hurma Okul Cad. 271. Sok. No:21 07070 Antalya",
    "addr:housenumber":"271;no 21",
    "addr:postcode":"07070",
    "addr:street":"Okul Cad.;Sok.",
    "iso:country":"TR",
    "sg:address":"Hurma Okul Cad. 271. Sok. No:21",
    "sg:city":"07070",
    "sg:classifiers":[
        {
            "category":"Manufacturing",
            "subcategory":"Watercraft",
            "type":"Manufacturing & Wholesale Goods"
        }
    ],
    "sg:phone":"+90 242 259 2486",
    "sg:province":"Antalya",
    "sg:tags":[
        "builder",
        "yacht",
        "trough"
    ],
    "wof:name":"Alasiya Yat Insa Ve Onarim",
    "wof:placetype":"venue"
},
  "geometry": {"coordinates":[30.7031345367,36.8875045776],"type":"Point"}
}