{
  "type": "Feature",
  "properties": {
    "addr:full":"540 Sk 6/210 Agamustafa Bey Ishani Bornova Izmir 35040",
    "addr:housenumber":"6 / 210",
    "addr:postcode":"35040",
    "addr:street":"540 Sk;Agamustafa;Ishani",
    "iso:country":"TR",
    "sg:address":"540 Sk 6/210 Agamustafa Bey Ishani",
    "sg:city":"Bornova",
    "sg:classifiers":[
        {
            "category":"Professional",
            "subcategory":"Engineering",
            "type":"Services"
        }
    ],
    "sg:phone":"+90 232 388 9082",
    "sg:postcode":"35040",
    "sg:province":"Izmir",
    "sg:tags":[
        "architect"
    ],
    "wof:name":"Egem Muhendislik Ins. San. Tur. Ltd. Sti.",
    "wof:placetype":"venue"
},
  "geometry": {"coordinates":[27.1423015594,38.4251480103],"type":"Point"}
}