{
  "type": "Feature",
  "properties": {
    "iso:country":"TR",
    "sg:address":"Sair Mehmet Emin Sok. No:19/21 D:6",
    "sg:city":"Findikzade",
    "sg:classifiers":[
        {
            "category":"Shopping",
            "subcategory":"Clothing, Apparel, & Fashions",
            "type":"Retail Goods"
        }
    ],
    "sg:phone":"+90 212 530 4578",
    "sg:province":"Istanbul",
    "sg:tags":[
        "underwear"
    ],
    "wof:name":"Sekeroglu San.tic. Ltd.sti.",
    "wof:placetype":"venue"
},
  "geometry": {"coordinates":[28.937761,41.010685],"type":"Point"}
}