{
  "type": "Feature",
  "properties": {
    "addr:full":"Ergin Sk. No:39/3 Tandogan 10020 Ankara",
    "addr:housenumber":"39 / 3",
    "addr:postcode":"10020",
    "addr:street":"Ergin Sk. No;Tandogan",
    "iso:country":"TR",
    "sg:address":"Ergin Sk. No:39/3 Tandogan",
    "sg:city":"10020",
    "sg:classifiers":[
        {
            "category":"Banks & Credit Unions",
            "subcategory":"Investment Brokerage",
            "type":"Services"
        }
    ],
    "sg:phone":"+90 312 212 3375",
    "sg:province":"Ankara",
    "sg:tags":[
        "-",
        "export",
        "import"
    ],
    "wof:name":"Saroz Dis Tic. Ltd. Sti.",
    "wof:placetype":"venue"
},
  "geometry": {"coordinates":[32.5730400085,39.9639396667],"type":"Point"}
}