{
  "type": "Feature",
  "properties": {
    "addr:full":"Tunus Cad. 9/17 K.dere Mecidiyek\u00f6y Ankara",
    "addr:housenumber":"9 / 17",
    "addr:street":"Tunus Cad.",
    "iso:country":"TR",
    "sg:address":"Tunus Cad. 9/17 K.dere",
    "sg:city":"Mecidiyek\u00f6y",
    "sg:classifiers":[
        {
            "category":"Wholesale",
            "subcategory":"Medical Equipment & Supplies",
            "type":"Manufacturing & Wholesale Goods"
        }
    ],
    "sg:phone":"+90 312 417 0748",
    "sg:province":"Ankara",
    "wof:name":"Narman Medikal San. Ltd.",
    "wof:placetype":"venue"
},
  "geometry": {"coordinates":[32.8604812622,39.9429283142],"type":"Point"}
}