{
  "type": "Feature",
  "properties": {
    "iso:country":"TR",
    "sg:address":"Beyoglu Cd. No:53",
    "sg:city":"Esenyurt",
    "sg:classifiers":[
        {
            "category":"Shopping",
            "subcategory":"Florist",
            "type":"Retail Goods"
        }
    ],
    "sg:phone":"+90 212 690 1614",
    "sg:postcode":"07800",
    "sg:province":"Istanbul",
    "sg:tags":[
        "flower"
    ],
    "wof:name":"Ceylan ?i?ek Evi",
    "wof:placetype":"venue"
},
  "geometry": {"coordinates":[28.7053813934,41.0042724609],"type":"Point"}
}