{
  "type": "Feature",
  "properties": {
    "addr:full":"Hilton Center Kat.1 No:b.3.c ?demis Izmir",
    "addr:housenumber":"?",
    "addr:street":"No:B.;Demis",
    "iso:country":"TR",
    "sg:address":"Hilton Center Kat.1 No:b.3.c",
    "sg:city":"?demis",
    "sg:classifiers":[
        {
            "category":"Food & Beverages",
            "subcategory":"Groceries & Convenience Stores",
            "type":"Retail Goods"
        }
    ],
    "sg:phone":"+90 232 489 1342",
    "sg:province":"Izmir",
    "sg:tags":[
        "ready"
    ],
    "wof:name":"Hilpa International Industrial Trade And Foods Exp.& Imp.mark Inc.",
    "wof:placetype":"venue"
},
  "geometry": {"coordinates":[27.1296863556,38.4186973572],"type":"Point"}
}