{
  "type": "Feature",
  "properties": {
    "addr:full":"Kisla Cd. No:13 Demirkapi Ikitelli/K\u00fc\u00e7\u00fck\u00e7ekmece Istanbul 34670",
    "addr:housenumber":"no 13",
    "addr:postcode":"34670",
    "addr:street":"Kisla Cd.",
    "iso:country":"TR",
    "sg:address":"Kisla Cd. No:13 Demirkapi",
    "sg:city":"Ikitelli/K\u00fc\u00e7\u00fck\u00e7ekmece",
    "sg:classifiers":[
        {
            "category":"Manufacturing",
            "subcategory":"Metals",
            "type":"Manufacturing & Wholesale Goods"
        }
    ],
    "sg:phone":"+90 212 576 4202",
    "sg:postcode":"34670",
    "sg:province":"Istanbul",
    "sg:tags":[
        "iron-steel",
        "peoducts"
    ],
    "wof:name":"Decet Demir ?elik Tic. Ltd. Sti.",
    "wof:placetype":"venue"
},
  "geometry": {"coordinates":[28.8519821167,41.0567932129],"type":"Point"}
}