{
  "type": "Feature",
  "properties": {
    "iso:country":"TR",
    "sg:address":"Sogutlucesme Cad. Bulvar Carsisi No:70 Kat:5 D:138 Kadikoy",
    "sg:city":"Kagithane",
    "sg:classifiers":[
        {
            "category":"Shopping",
            "subcategory":"Party Supplies",
            "type":"Retail Goods"
        }
    ],
    "sg:phone":"+90 216 414 6681",
    "sg:postcode":"34403",
    "sg:province":"Istanbul",
    "sg:tags":[
        "sound",
        "light",
        "system"
    ],
    "wof:name":"Studio A Hi-fi Ses Ve Goruntu Sistemleri",
    "wof:placetype":"venue"
},
  "geometry": {"coordinates":[28.9819736481,41.0769729614],"type":"Point"}
}