{
  "type": "Feature",
  "properties": {
    "addr:full":"Camdibi Milas Camdibi 48200",
    "addr:postcode":"48200",
    "addr:street":"Camdibi",
    "iso:country":"TR",
    "sg:address":"Camdibi",
    "sg:city":"Milas",
    "sg:classifiers":[
        {
            "category":"Banks & Credit Unions",
            "subcategory":"Bank",
            "type":"Services"
        }
    ],
    "sg:phone":"+90 232 435 0029",
    "sg:postcode":"48200",
    "sg:province":"Camdibi",
    "wof:name":"T?kiye T??c?er, Bankasi Yasarbank As",
    "wof:placetype":"venue"
},
  "geometry": {"coordinates":[28.272747,36.864174],"type":"Point"}
}