{
  "type": "Feature",
  "properties": {
    "iso:country":"TR",
    "sg:address":"Bagdat Cad 471",
    "sg:city":"Istanbul",
    "sg:classifiers":[
        {
            "category":"Banks & Credit Unions",
            "subcategory":"Bank",
            "type":"Services"
        }
    ],
    "sg:phone":"+90 216 411 5455",
    "sg:province":"Suadiye",
    "wof:name":"Interbank As",
    "wof:placetype":"venue"
},
  "geometry": {"coordinates":[29.082542,40.959354],"type":"Point"}
}