{
  "type": "Feature",
  "properties": {
    "iso:country":"TR",
    "sg:address":"Tugay Yolu No:12 Kartal",
    "sg:city":"Ikitelli/K\u00fc\u00e7\u00fck\u00e7ekmece",
    "sg:classifiers":[
        {
            "category":"Manufacturing",
            "subcategory":"Tools & Machinery",
            "type":"Manufacturing & Wholesale Goods"
        }
    ],
    "sg:phone":"+90 216 399 1578",
    "sg:postcode":"34670",
    "sg:province":"Istanbul",
    "sg:tags":[
        "machine",
        "industry"
    ],
    "wof:name":"Sidmak Dikis Makina San. A.s.",
    "wof:placetype":"venue"
},
  "geometry": {"coordinates":[29.1584148407,40.9172477722],"type":"Point"}
}