{
  "type": "Feature",
  "properties": {
    "addr:full":"Narlikapi Cesme Sk. No:37 Yedikule Istanbul 34107",
    "addr:housenumber":"37",
    "addr:postcode":"34107",
    "addr:street":"Cesme Sk. No",
    "iso:country":"TR",
    "sg:address":"Narlikapi Cesme Sk. No:37",
    "sg:city":"Yedikule",
    "sg:classifiers":[
        {
            "category":"Home & Garden",
            "subcategory":"Building Materials",
            "type":"Retail Goods"
        }
    ],
    "sg:phone":"+90 212 858 5532",
    "sg:postcode":"34107",
    "sg:province":"Istanbul",
    "sg:tags":[
        "window",
        "door"
    ],
    "wof:name":"Uresin Mob. A.s.",
    "wof:placetype":"venue"
},
  "geometry": {"coordinates":[28.9861831665,41.0408554077],"type":"Point"}
}