{
  "type": "Feature",
  "properties": {
    "iso:country":"TR",
    "sg:address":"Kalpaklioglu Mah.yenisu Sk. D?ya Ism.b Blok No 20",
    "sg:city":"Melikgazi",
    "sg:classifiers":[
        {
            "category":"Professional",
            "subcategory":"Engineering",
            "type":"Services"
        }
    ],
    "sg:phone":"+90 352 231 5944",
    "sg:postcode":"38030",
    "sg:province":"Kayseri",
    "sg:tags":[
        "architect"
    ],
    "wof:name":"Mahiroglu Mim.ins.san.tic.ltd.sti.",
    "wof:placetype":"venue"
},
  "geometry": {"coordinates":[36.4393234253,38.2791290283],"type":"Point"}
}