{
  "type": "Feature",
  "properties": {
    "iso:country":"TR",
    "sg:address":"Hocahan Cad. Melek Is Hani No:111/304",
    "sg:city":"Yesildirek",
    "sg:classifiers":[
        {
            "category":"Shopping",
            "subcategory":"Clothing, Apparel, & Fashions",
            "type":"Retail Goods"
        }
    ],
    "sg:phone":"+90 212 520 1945",
    "sg:postcode":"63200",
    "sg:province":"Istanbul",
    "sg:tags":[
        "men",
        "wear"
    ],
    "wof:name":"Erbay Tekstil Insaat Tic.ltd.sti.",
    "wof:placetype":"venue"
},
  "geometry": {"coordinates":[28.9759254456,41.0123786926],"type":"Point"}
}