{
  "type": "Feature",
  "properties": {
    "addr:full":"Tersane Cad.nafe Sk.erdoganlar Is Mrk.no:1 K.2 Karakoy Nisantasi Istanbul 25370",
    "addr:housenumber":"1",
    "addr:postcode":"25370",
    "addr:street":"K.2 Karakoy",
    "iso:country":"TR",
    "sg:address":"Tersane Cad.nafe Sk.erdoganlar Is Mrk.no:1 K.2 Karakoy",
    "sg:city":"Nisantasi",
    "sg:classifiers":[
        {
            "category":"Banks & Credit Unions",
            "subcategory":"Investment Brokerage",
            "type":"Services"
        }
    ],
    "sg:phone":"+90 212 253 5678",
    "sg:postcode":"25370",
    "sg:province":"Istanbul",
    "sg:tags":[
        "-",
        "export",
        "import"
    ],
    "wof:name":"Enma Endustriyel Hirdavat Malzemeleri Ltd.sti.",
    "wof:placetype":"venue"
},
  "geometry": {"coordinates":[28.9861831665,41.0408554077],"type":"Point"}
}