{
  "type": "Feature",
  "properties": {
    "addr:full":"Cebeci Cad. No:175/2, 34080 K??k? - Gaziosmanpasa Istanbul Melikgazi Istanbul 38030",
    "addr:housenumber":"175 / 2;? ? k ?",
    "addr:postcode":"34080;38030",
    "addr:street":"Cebeci Cad. No",
    "iso:country":"TR",
    "sg:address":"Cebeci Cad. No:175/2, 34080 K??k? - Gaziosmanpasa Istanbul",
    "sg:city":"Melikgazi",
    "sg:classifiers":[
        {
            "category":"Shopping",
            "subcategory":"Computers & Home Electronics",
            "type":"Retail Goods"
        }
    ],
    "sg:phone":"+90 212 618 3853",
    "sg:postcode":"38030",
    "sg:province":"Istanbul",
    "sg:tags":[
        "electronic",
        "electrical",
        "equipment"
    ],
    "sg:website":"http://www.aytaclighting.com.tr",
    "wof:name":"Ayta? Aydinlatma Sanayi Ve Ticaret Ltd.sti.",
    "wof:placetype":"venue"
},
  "geometry": {"coordinates":[28.9861831665,41.0408554077],"type":"Point"}
}