{
  "type": "Feature",
  "properties": {
    "iso:country":"TR",
    "sg:address":"Anahtar Sk. No:5 Cihangir",
    "sg:city":"Seyhan",
    "sg:classifiers":[
        {
            "category":"Wholesale",
            "subcategory":"Medical Equipment & Supplies",
            "type":"Manufacturing & Wholesale Goods"
        }
    ],
    "sg:phone":"+90 212 244 6345",
    "sg:postcode":"01140",
    "sg:province":"Istanbul",
    "sg:tags":[
        "material"
    ],
    "wof:name":"Remeks Tibbi Mlz. San.",
    "wof:placetype":"venue"
},
  "geometry": {"coordinates":[28.983253479,41.0303993225],"type":"Point"}
}