{
  "type": "Feature",
  "properties": {
    "addr:full":"Necipbey Cd.25 Erenk? Samsun",
    "addr:street":"Erenk",
    "iso:country":"TR",
    "sg:address":"Necipbey Cd.25",
    "sg:city":"Erenk?",
    "sg:classifiers":[
        {
            "category":"Organizations",
            "subcategory":"Professional Association",
            "type":"Services"
        }
    ],
    "sg:phone":"+90 362 431 2809",
    "sg:province":"Samsun",
    "wof:name":"G??l? Elektrik",
    "wof:placetype":"venue"
},
  "geometry": {"coordinates":[36.3378410339,41.2897186279],"type":"Point"}
}