{
  "type": "Feature",
  "properties": {
    "iso:country":"TR",
    "sg:address":"86 Sk. No. 23 .",
    "sg:city":"Pinarbasi",
    "sg:classifiers":[
        {
            "category":"Food & Beverages",
            "subcategory":"Meat & Fish",
            "type":"Retail Goods"
        }
    ],
    "sg:phone":"+90 232 479 1659",
    "sg:postcode":"07630",
    "sg:province":"Izmir",
    "sg:tags":[
        "seafood"
    ],
    "wof:name":"Ege Balik Ihr. San. A.s.",
    "wof:placetype":"venue"
},
  "geometry": {"coordinates":[27.1730155945,38.3845024109],"type":"Point"}
}