{
  "type": "Feature",
  "properties": {
    "iso:country":"TR",
    "sg:address":"Eski ?ankiri Yolu 1. Km Balikhisar K?y?",
    "sg:city":"Akyurt",
    "sg:classifiers":[
        {
            "category":"Retail",
            "subcategory":"Storage",
            "type":"Services"
        }
    ],
    "sg:phone":"+90 3128416490729",
    "sg:postcode":"06750",
    "sg:province":"Ankara",
    "sg:tags":[
        "packing",
        "material"
    ],
    "wof:name":"Erginay Kereste Ve Ambalaj San. Ve Tic. Ltd. Sti.",
    "wof:placetype":"venue"
},
  "geometry": {"coordinates":[32.8560333252,39.9438743591],"type":"Point"}
}