{
  "type": "Feature",
  "properties": {
    "addr:full":"Mahmutbey Merkez Mah. Istoc Z Blok No:107 Bagc?lar Konak Istanbul 07110",
    "addr:housenumber":"blok no 107;?",
    "addr:postcode":"07110",
    "addr:street":"Merkez Mah. Istoc;Bagc",
    "iso:country":"TR",
    "sg:address":"Mahmutbey Merkez Mah. Istoc Z Blok No:107 Bagc?lar",
    "sg:city":"Konak",
    "sg:classifiers":[
        {
            "category":"Manufacturing",
            "subcategory":"Rubber & Plastics",
            "type":"Manufacturing & Wholesale Goods"
        }
    ],
    "sg:phone":"+90 212 659 2796",
    "sg:postcode":"07110",
    "sg:province":"Istanbul",
    "sg:tags":[
        "industry"
    ],
    "wof:name":"Celik Plastik Urunleri Imalat Paz. San.tic.ltd.sti.",
    "wof:placetype":"venue"
},
  "geometry": {"coordinates":[28.9759254456,41.0123786926],"type":"Point"}
}