{
  "type": "Feature",
  "properties": {
    "iso:country":"TR",
    "sg:address":"Vatan Mah. Ar Sok. Guldallar 11.san.sitesi No:58",
    "sg:city":"B.pasa",
    "sg:classifiers":[
        {
            "category":"Manufacturing",
            "subcategory":"Textiles",
            "type":"Manufacturing & Wholesale Goods"
        }
    ],
    "sg:phone":"+90 212 577 5166",
    "sg:province":"Istanbul",
    "sg:tags":[
        "machinery"
    ],
    "wof:name":"Cengiz Tekstil Makina Yedek Parca Ith.tic.ltd.sti.",
    "wof:placetype":"venue"
},
  "geometry": {"coordinates":[28.9861831665,41.0408554077],"type":"Point"}
}