{
  "type": "Feature",
  "properties": {
    "addr:full":"In??cad 60 Malatya 44100 44000",
    "addr:housenumber":"60",
    "addr:postcode":"44100 44000",
    "addr:street":"In ? ? Cad",
    "iso:country":"TR",
    "sg:address":"In??cad 60",
    "sg:city":"Malatya",
    "sg:classifiers":[
        {
            "category":"Banks & Credit Unions",
            "subcategory":"Bank",
            "type":"Services"
        }
    ],
    "sg:phone":"+90 422 325 0325",
    "sg:postcode":"44000",
    "sg:province":"44100",
    "wof:name":"Toprakbank As",
    "wof:placetype":"venue"
},
  "geometry": {"coordinates":[37.32103,37.054317],"type":"Point"}
}