{
  "type": "Feature",
  "properties": {
    "addr:full":"Ikitelli Organize Sanayi B?gesi Sefak? Sanayi Sitesi 7.blok No:5-7 Ikitelli7k???k?ekmece Istanbul 34670",
    "addr:housenumber":"?;sefak ?;7.blok no 5-7 ikitelli7k ? ? ? k ?",
    "addr:postcode":"34670",
    "addr:street":"Organize Sanayi B;Sanayi Sitesi",
    "iso:country":"TR",
    "sg:address":"Ikitelli Organize Sanayi B?gesi Sefak? Sanayi Sitesi 7.blok No:5-7",
    "sg:city":"Ikitelli7k???k?ekmece",
    "sg:classifiers":[
        {
            "category":"Manufacturing",
            "subcategory":"Chemicals & Compounds",
            "type":"Manufacturing & Wholesale Goods"
        }
    ],
    "sg:phone":"+90 212 671 4588",
    "sg:postcode":"34670",
    "sg:province":"Istanbul",
    "sg:tags":[
        "galvanize"
    ],
    "wof:name":"Poyraz Kimya",
    "wof:placetype":"venue"
},
  "geometry": {"coordinates":[28.9759254456,41.0123786926],"type":"Point"}
}