{
  "type": "Feature",
  "properties": {
    "addr:full":"Oto Sanayi Sitesi Demirbas Sok. No:17 4.levent Istanbul",
    "addr:housenumber":"no;4.levent",
    "addr:street":"Demirbas Sok.",
    "iso:country":"TR",
    "sg:address":"Oto Sanayi Sitesi Demirbas Sok. No:17",
    "sg:city":"4.levent",
    "sg:classifiers":[
        {
            "category":"Manufacturing",
            "subcategory":"Textiles",
            "type":"Manufacturing & Wholesale Goods"
        }
    ],
    "sg:phone":"+90 212 264 7522",
    "sg:province":"Istanbul",
    "sg:tags":[
        "product"
    ],
    "wof:name":"Desan Tekstil San. Ve Tic. Ltd.sti.",
    "wof:placetype":"venue"
},
  "geometry": {"coordinates":[29.0054225922,41.0927276611],"type":"Point"}
}