{
  "type": "Feature",
  "properties": {
    "addr:full":"Bashane Sk. No:8 Kasimpasa \u00dcmraniye Istanbul",
    "addr:street":"Bashane Sk. No 8 Kasimpasa",
    "iso:country":"TR",
    "sg:address":"Bashane Sk. No:8 Kasimpasa",
    "sg:city":"\u00dcmraniye",
    "sg:classifiers":[
        {
            "category":"Manufacturing",
            "subcategory":"Rubber & Plastics",
            "type":"Manufacturing & Wholesale Goods"
        }
    ],
    "sg:phone":"+90 212 250 3086",
    "sg:province":"Istanbul",
    "sg:tags":[
        "industry"
    ],
    "wof:name":"H?r Plastik San.",
    "wof:placetype":"venue"
},
  "geometry": {"coordinates":[28.9704647064,41.0333786011],"type":"Point"}
}