{
  "type": "Feature",
  "properties": {
    "addr:full":"Sair Nedim Cad. Haci Halit Bey Sok. 1/1 Besiktas 07230 Istanbul",
    "addr:housenumber":"1 / 1",
    "addr:postcode":"07230",
    "addr:street":"Nedim Cad. Haci Halit Bey Sok.;Besiktas",
    "iso:country":"TR",
    "sg:address":"Sair Nedim Cad. Haci Halit Bey Sok. 1/1 Besiktas",
    "sg:city":"07230",
    "sg:classifiers":[
        {
            "category":"Sports & Exercise",
            "subcategory":"Tennis Court",
            "type":"Entertainment"
        }
    ],
    "sg:phone":"+90 212 227 7080",
    "sg:province":"Istanbul",
    "sg:tags":[
        "equipment",
        "material"
    ],
    "wof:name":"Adrenalin Tirmanis Ve Doga Sporlari",
    "wof:placetype":"venue"
},
  "geometry": {"coordinates":[29.000515,41.043404],"type":"Point"}
}