{
  "type": "Feature",
  "properties": {
    "addr:full":"Ahmet Helvaci Gelibolu Afyon 63000",
    "addr:postcode":"63000",
    "addr:street":"Afyon",
    "iso:country":"TR",
    "sg:address":"Ahmet Helvaci",
    "sg:city":"Gelibolu",
    "sg:classifiers":[
        {
            "category":"Government",
            "subcategory":"Office",
            "type":"Public Place"
        }
    ],
    "sg:phone":"+90 272 612 5218",
    "sg:postcode":"63000",
    "sg:province":"Afyon",
    "sg:tags":[
        "municipality"
    ],
    "wof:name":"Bolvadin Belediye Baskani",
    "wof:placetype":"venue"
},
  "geometry": {"coordinates":[29.3098602295,40.9565353394],"type":"Point"}
}