{
  "type": "Feature",
  "properties": {
    "addr:full":"Fatih Cad.beyaz Saray Apt.no:29/2 77200 Yalova",
    "addr:housenumber":"29 / 2",
    "addr:postcode":"77200",
    "addr:street":"Apt.No",
    "iso:country":"TR",
    "sg:address":"Fatih Cad.beyaz Saray Apt.no:29/2",
    "sg:city":"77200",
    "sg:classifiers":[
        {
            "category":"Utilities",
            "subcategory":"Electric",
            "type":"Services"
        }
    ],
    "sg:phone":"+90 226 812 1777",
    "sg:province":"Yalova",
    "sg:tags":[
        "energy",
        "solar"
    ],
    "wof:name":"Bilgen G?nes Enerjisi",
    "wof:placetype":"venue"
},
  "geometry": {"coordinates":[29.2712,40.655998],"type":"Point"}
}