{
  "type": "Feature",
  "properties": {
    "iso:country":"TR",
    "sg:address":"Ordu Bul. No:12",
    "sg:city":"Sahraicedit",
    "sg:classifiers":[
        {
            "category":"Home & Garden",
            "subcategory":"Building Materials",
            "type":"Retail Goods"
        }
    ],
    "sg:phone":"+90 272 213 3300",
    "sg:province":"Afyon",
    "sg:tags":[
        "stone",
        "natural",
        "marble"
    ],
    "wof:name":"Ozeks Mermer A..s.",
    "wof:placetype":"venue"
},
  "geometry": {"coordinates":[30.5457286835,38.7607421875],"type":"Point"}
}