{
  "type": "Feature",
  "properties": {
    "addr:full":"Kubilay Sk. No:41/1 Tandogan Kizilay Ankara 23050",
    "addr:housenumber":"41 / 1",
    "addr:postcode":"23050",
    "addr:street":"Kubilay Sk. No",
    "iso:country":"TR",
    "sg:address":"Kubilay Sk. No:41/1 Tandogan",
    "sg:city":"Kizilay",
    "sg:classifiers":[
        {
            "category":"Manufacturing",
            "subcategory":"Chemicals & Compounds",
            "type":"Manufacturing & Wholesale Goods"
        }
    ],
    "sg:phone":"+90 312 231 8992",
    "sg:postcode":"23050",
    "sg:province":"Ankara",
    "sg:tags":[
        "medicine"
    ],
    "wof:name":"Modern Kimya Ltd. Sti.",
    "wof:placetype":"venue"
},
  "geometry": {"coordinates":[32.8420448303,39.9315452576],"type":"Point"}
}