{
  "type": "Feature",
  "properties": {
    "iso:country":"TR",
    "sg:address":"Davut Pasa Cd. No:10/3 Topkapi",
    "sg:city":"Gayrettepe/besiktas",
    "sg:classifiers":[
        {
            "category":"Farming",
            "subcategory":"Fish & Marine Products",
            "type":"Manufacturing & Wholesale Goods"
        }
    ],
    "sg:phone":"+90 212 612 6837",
    "sg:postcode":"80280",
    "sg:province":"Istanbul",
    "sg:tags":[
        "automotive"
    ],
    "wof:name":"Basak Otomotiv San. Tic. Ltd. Sti.",
    "wof:placetype":"venue"
},
  "geometry": {"coordinates":[28.9259796143,41.0198974609],"type":"Point"}
}