{
  "type": "Feature",
  "properties": {
    "addr:full":"Zuhtupasa Mah. Rustiye Sok. No:11 Kat:2 Kiziltoprak Maltepe Istanbul 01000",
    "addr:housenumber":"no 11 kat 2",
    "addr:postcode":"01000",
    "addr:street":"Zuhtupasa Mah. Rustiye Sok.;Kiziltoprak Maltepe Istanbul",
    "iso:country":"TR",
    "sg:address":"Zuhtupasa Mah. Rustiye Sok. No:11 Kat:2 Kiziltoprak",
    "sg:city":"Maltepe",
    "sg:classifiers":[
        {
            "category":"Wholesale",
            "subcategory":"Books, Periodicals, & Newspapers",
            "type":"Manufacturing & Wholesale Goods"
        }
    ],
    "sg:phone":"+90 216 418 8740",
    "sg:postcode":"01000",
    "sg:province":"Istanbul",
    "sg:tags":[
        "house",
        "publishing"
    ],
    "wof:name":"Onur Hologram",
    "wof:placetype":"venue"
},
  "geometry": {"coordinates":[28.9759254456,41.0123786926],"type":"Point"}
}