{
  "type": "Feature",
  "properties": {
    "addr:full":"3. Cd. No:103/b Bah?lievler K???kyali Ankara",
    "addr:housenumber":"3;no;/ b;?;k ?",
    "addr:street":"Cd.;Bah",
    "iso:country":"TR",
    "sg:address":"3. Cd. No:103/b Bah?lievler",
    "sg:city":"K???kyali",
    "sg:classifiers":[
        {
            "category":"Home & Garden",
            "subcategory":"Building Materials",
            "type":"Retail Goods"
        }
    ],
    "sg:phone":"+90 312 221 3885",
    "sg:province":"Ankara",
    "sg:tags":[
        "window",
        "door",
        "plastic"
    ],
    "wof:name":"Mega Us Ltd. Sti.",
    "wof:placetype":"venue"
},
  "geometry": {"coordinates":[32.8735351562,39.8817062378],"type":"Point"}
}