{
  "type": "Feature",
  "properties": {
    "addr:full":"Semaver Sk. Satir Han No:11/2 Mercan Istanbul 12600",
    "addr:housenumber":"11 / 2",
    "addr:postcode":"12600",
    "addr:street":"Semaver Sk.;Han No",
    "iso:country":"TR",
    "sg:address":"Semaver Sk. Satir Han No:11/2",
    "sg:city":"Mercan",
    "sg:orig_category":"Textile Suplementaries",
    "sg:phone":"+90 212 522 7737",
    "sg:postcode":"12600",
    "sg:province":"Istanbul",
    "wof:name":"Onur Teks. San. Tic.",
    "wof:placetype":"venue"
},
  "geometry": {"coordinates":[28.9861831665,41.0408554077],"type":"Point"}
}