{
  "type": "Feature",
  "properties": {
    "addr:full":"Mesihpasa Cad. Aksa Is Merkesi Kat.6 No:1002 Aksaray Kizilay Istanbul 06430",
    "addr:housenumber":"kat.6 no 1002",
    "addr:postcode":"06430",
    "addr:street":"Mesihpasa Cad. Aksa Is Merkesi",
    "iso:country":"TR",
    "sg:address":"Mesihpasa Cad. Aksa Is Merkesi Kat.6 No:1002 Aksaray",
    "sg:city":"Kizilay",
    "sg:classifiers":[
        {
            "category":"Government",
            "subcategory":"Office",
            "type":"Public Place"
        }
    ],
    "sg:phone":"+90 212 516 8788",
    "sg:postcode":"06430",
    "sg:province":"Istanbul",
    "sg:tags":[
        "patent",
        "mark"
    ],
    "wof:name":"Avrupa Patent Burosu",
    "wof:placetype":"venue"
},
  "geometry": {"coordinates":[28.9861831665,41.0408554077],"type":"Point"}
}