{
  "type": "Feature",
  "properties": {
    "addr:full":"Uzuncayir S. Deniz Apt. No: 11/3 Ust Goztepe Istanbul 01220",
    "addr:housenumber":"3",
    "addr:postcode":"01220",
    "addr:street":"Ust Goztepe",
    "iso:country":"TR",
    "sg:address":"Uzuncayir S. Deniz Apt. No: 11/3 Ust",
    "sg:city":"Goztepe",
    "sg:classifiers":[
        {
            "category":"Home & Garden",
            "subcategory":"Building Materials",
            "type":"Retail Goods"
        }
    ],
    "sg:phone":"+90 216 368 2470",
    "sg:postcode":"01220",
    "sg:province":"Istanbul",
    "sg:tags":[
        "insulation"
    ],
    "wof:name":"Boytim Boya Izo. San. Ltd.sti.",
    "wof:placetype":"venue"
},
  "geometry": {"coordinates":[28.9861831665,41.0408554077],"type":"Point"}
}