{
  "type": "Feature",
  "properties": {
    "iso:country":"TR",
    "sg:address":"Manisa",
    "sg:city":"Ikitelli/K\u00fc\u00e7\u00fck\u00e7ekmece",
    "sg:classifiers":[
        {
            "category":"Health Services",
            "subcategory":"Hospital",
            "type":"Services"
        }
    ],
    "sg:phone":"+90 236 231 4596",
    "sg:postcode":"34660",
    "sg:province":"Manisa",
    "sg:tags":[
        "state"
    ],
    "wof:name":"Devlet Hastanesi",
    "wof:placetype":"venue"
},
  "geometry": {"coordinates":[28.122778,38.749443],"type":"Point"}
}