{
  "type": "Feature",
  "properties": {
    "addr:full":"Organize San.bol.3.cad. Mersin Malatya 52750",
    "addr:housenumber":"san.bol.3.cad",
    "addr:postcode":"52750",
    "addr:street":"Organize",
    "iso:country":"TR",
    "sg:address":"Organize San.bol.3.cad.",
    "sg:city":"Mersin",
    "sg:classifiers":[
        {
            "category":"Professional",
            "subcategory":"Business Services",
            "type":"Services"
        }
    ],
    "sg:phone":"+90 422 237 5102",
    "sg:postcode":"52750",
    "sg:province":"Malatya",
    "sg:tags":[
        "food",
        "product",
        "exporter",
        "aricultural"
    ],
    "wof:name":"Kayisi Birlik Genel Mud.",
    "wof:placetype":"venue"
},
  "geometry": {"coordinates":[38.3143005371,38.3474998474],"type":"Point"}
}