{
  "type": "Feature",
  "properties": {
    "iso:country":"TR",
    "sg:address":"Yildirim Mah. Uludag Sok. No:48 Bayrampasa",
    "sg:city":"Isikkent",
    "sg:classifiers":[
        {
            "category":"Shopping",
            "subcategory":"Shoes",
            "type":"Retail Goods"
        }
    ],
    "sg:phone":"+90 212 617 4116",
    "sg:postcode":"35070",
    "sg:province":"Istanbul",
    "wof:name":"Kardesler Ayk. Ltd.sti.",
    "wof:placetype":"venue"
},
  "geometry": {"coordinates":[28.888481,41.067879],"type":"Point"}
}