{
  "type": "Feature",
  "properties": {
    "addr:full":"Manolya Sk. Siteler Istanbul 07070",
    "addr:postcode":"07070",
    "addr:street":"Manolya Sk.",
    "iso:country":"TR",
    "sg:address":"Manolya Sk.",
    "sg:city":"Siteler",
    "sg:classifiers":[
        {
            "category":"Manufacturing",
            "subcategory":"Glass & Minerals",
            "type":"Manufacturing & Wholesale Goods"
        }
    ],
    "sg:phone":"+90 212 241 2317",
    "sg:postcode":"07070",
    "sg:province":"Istanbul",
    "sg:tags":[
        "glass-mirror"
    ],
    "wof:name":"G?rtas Cam San. Ltd. Sti.",
    "wof:placetype":"venue"
},
  "geometry": {"coordinates":[28.2835521698,41.0648460388],"type":"Point"}
}