{
  "type": "Feature",
  "properties": {
    "addr:full":"Buttim Is Merkezi A4 No:1023 Seyhan Bursa 01000",
    "addr:housenumber":"a4 no 1023",
    "addr:postcode":"01000",
    "iso:country":"TR",
    "sg:address":"Buttim Is Merkezi A4 No:1023",
    "sg:city":"Seyhan",
    "sg:classifiers":[
        {
            "category":"Airport",
            "subcategory":"International",
            "type":"Transportation"
        }
    ],
    "sg:phone":"+90 224 211 2702",
    "sg:postcode":"01000",
    "sg:province":"Bursa",
    "wof:name":"Bursa Transport Service",
    "wof:placetype":"venue"
},
  "geometry": {"coordinates":[29.0586109161,40.1844291687],"type":"Point"}
}