{
  "type": "Feature",
  "properties": {
    "addr:full":"Ismet Inonu Blv.nail Goksu Ish.k:2 No:23 Turuncova I?el 07880",
    "addr:housenumber":"2 no 23;?",
    "addr:postcode":"07880",
    "addr:street":"Ish.K;I;El",
    "iso:country":"TR",
    "sg:address":"Ismet Inonu Blv.nail Goksu Ish.k:2 No:23",
    "sg:city":"Turuncova",
    "sg:classifiers":[
        {
            "category":"Food & Beverages",
            "subcategory":"Fruits & Vegetables",
            "type":"Retail Goods"
        }
    ],
    "sg:phone":"+90 324 238 0488",
    "sg:postcode":"07880",
    "sg:province":"I?el",
    "sg:tags":[
        "fresh"
    ],
    "wof:name":"Saturn Ic Ve Dis Tic Ltd. Sti.",
    "wof:placetype":"venue"
},
  "geometry": {"coordinates":[30.1224193573,36.3515396118],"type":"Point"}
}