{
  "type": "Feature",
  "properties": {
    "addr:full":"F Sultan Mehmet Bulv No:84/a Ihsaniye Bursa 07110",
    "addr:housenumber":"no 84 / a",
    "addr:postcode":"07110",
    "addr:street":"Mehmet Bulv;Bursa",
    "iso:country":"TR",
    "sg:address":"F Sultan Mehmet Bulv No:84/a",
    "sg:city":"Ihsaniye",
    "sg:classifiers":[
        {
            "category":"Building & Trades",
            "subcategory":"Landscaping Services",
            "type":"Services"
        }
    ],
    "sg:phone":"+90 224 249 6465",
    "sg:postcode":"07110",
    "sg:province":"Bursa",
    "sg:tags":[
        "landscape"
    ],
    "wof:name":"Garden Dizayn",
    "wof:placetype":"venue"
},
  "geometry": {"coordinates":[28.9783477783,40.2208976746],"type":"Point"}
}