{
  "type": "Feature",
  "properties": {
    "addr:full":"Alanaldi Cad. Bahcelerici Sok. No:25 Icerenkoy Istanbul 34752",
    "addr:housenumber":"no 25",
    "addr:postcode":"34752",
    "addr:street":"Alanaldi Cad. Bahcelerici Sok.;Istanbul",
    "iso:country":"TR",
    "sg:address":"Alanaldi Cad. Bahcelerici Sok. No:25",
    "sg:city":"Icerenkoy",
    "sg:classifiers":[
        {
            "category":"Home & Garden",
            "subcategory":"Home Furnishings",
            "type":"Retail Goods"
        }
    ],
    "sg:phone":"+90 216 362 0911",
    "sg:postcode":"34752",
    "sg:province":"Istanbul",
    "sg:tags":[
        "textile"
    ],
    "wof:name":"Nevsan Nevresim Sanayi",
    "wof:placetype":"venue"
},
  "geometry": {"coordinates":[28.9861831665,41.0408554077],"type":"Point"}
}