{
  "type": "Feature",
  "properties": {
    "iso:country":"TR",
    "sg:address":"Ortaklar Cd. No:2 K:3 D:3 Necatibey",
    "sg:city":"Eskigaraj",
    "sg:classifiers":[
        {
            "category":"Manufacturing",
            "subcategory":"Rubber & Plastics",
            "type":"Manufacturing & Wholesale Goods"
        }
    ],
    "sg:phone":"+90 212 275 7124",
    "sg:province":"Istanbul",
    "sg:tags":[
        "industry"
    ],
    "wof:name":"Saran Plastik Ambalaj San. Tic. A.s.",
    "wof:placetype":"venue"
},
  "geometry": {"coordinates":[29.010389328,41.022895813],"type":"Point"}
}