{
  "type": "Feature",
  "properties": {
    "iso:country":"TR",
    "sg:address":"Selanik Cd. No:19 D:1 Yenisehir",
    "sg:city":"Ortak?",
    "sg:classifiers":[
        {
            "category":"Organizations",
            "subcategory":"Professional Association",
            "type":"Services"
        }
    ],
    "sg:phone":"+90 312 417 4285",
    "sg:postcode":"80840",
    "sg:province":"Ankara",
    "wof:name":"Tmmob Ins. Muhendis. Odasi",
    "wof:placetype":"venue"
},
  "geometry": {"coordinates":[29.3005332947,40.9160232544],"type":"Point"}
}