{
  "type": "Feature",
  "properties": {
    "iso:country":"TR",
    "sg:address":"Gazi Cad. No:77/c",
    "sg:city":"Mersin",
    "sg:classifiers":[
        {
            "category":"Professional",
            "subcategory":"Computer Services",
            "type":"Services"
        }
    ],
    "sg:phone":"+90 364 225 4147",
    "sg:postcode":"52750",
    "sg:province":"?orum",
    "sg:tags":[
        "application",
        "software"
    ],
    "wof:name":"Fatih Bilgisayar",
    "wof:placetype":"venue"
},
  "geometry": {"coordinates":[37.7128486633,41.0530204773],"type":"Point"}
}