{
  "type": "Feature",
  "properties": {
    "addr:full":"Ramikisla Cd. Uluyol Iskent San. Sit. D Blok Bayrampasa Yukari Dudullu Istanbul 34776",
    "addr:housenumber":"blok bayrampasa",
    "addr:postcode":"34776",
    "addr:street":"Ramikisla Cd. Uluyol Iskent San. Sit. D",
    "iso:country":"TR",
    "sg:address":"Ramikisla Cd. Uluyol Iskent San. Sit. D Blok Bayrampasa",
    "sg:city":"Yukari Dudullu",
    "sg:classifiers":[
        {
            "category":"Manufacturing",
            "subcategory":"Rubber & Plastics",
            "type":"Manufacturing & Wholesale Goods"
        }
    ],
    "sg:phone":"+90 212 578 3924",
    "sg:postcode":"34776",
    "sg:province":"Istanbul",
    "sg:tags":[
        "industry"
    ],
    "wof:name":"2 M Ikiem Plastik Kalip San. Ltd. Sti.",
    "wof:placetype":"venue"
},
  "geometry": {"coordinates":[29.175403595,41.0060424805],"type":"Point"}
}