{
  "type": "Feature",
  "properties": {
    "iso:country":"TR",
    "sg:address":"Dr. Mustafabey",
    "sg:city":"Izmir",
    "sg:classifiers":[
        {
            "category":"Banks & Credit Unions",
            "subcategory":"Bank",
            "type":"Services"
        }
    ],
    "sg:phone":"+90 232 463 8094",
    "sg:province":"35220",
    "wof:name":"Tekstilbank",
    "wof:placetype":"venue"
},
  "geometry": {"coordinates":[27.143221,38.431789],"type":"Point"}
}