{
  "type": "Feature",
  "properties": {
    "addr:full":"Yavuz Sok. No:1/1 Kadikoy Istanbul 01370",
    "addr:housenumber":"no 1 / 1",
    "addr:postcode":"01370",
    "addr:street":"Yavuz Sok.",
    "iso:country":"TR",
    "sg:address":"Yavuz Sok. No:1/1",
    "sg:city":"Kadikoy",
    "sg:orig_category":"Food Machinies",
    "sg:phone":"+90 216 345 0189",
    "sg:postcode":"01370",
    "sg:province":"Istanbul",
    "wof:name":"Acar Makine Kimya Elektrik San. Ltd.sti.",
    "wof:placetype":"venue"
},
  "geometry": {"coordinates":[29.1432247162,40.9188041687],"type":"Point"}
}