{
  "type": "Feature",
  "properties": {
    "addr:full":"Demirciler Sitesi 9.yol No: 23 Zeytinburnu Ikitelli/K\u00fc\u00e7\u00fck\u00e7ekmece Istanbul 34670",
    "addr:housenumber":"no 23;ikitelli / kuec\u0327uekc\u0327ekmece",
    "addr:postcode":"34670",
    "addr:street":"Demirciler;Zeytinburnu;Istanbul",
    "iso:country":"TR",
    "sg:address":"Demirciler Sitesi 9.yol No: 23 Zeytinburnu",
    "sg:city":"Ikitelli/K\u00fc\u00e7\u00fck\u00e7ekmece",
    "sg:classifiers":[
        {
            "category":"Building & Trades",
            "subcategory":"Plumbing",
            "type":"Services"
        }
    ],
    "sg:phone":"+90 2126659537679",
    "sg:postcode":"34670",
    "sg:province":"Istanbul",
    "sg:tags":[
        "pipe",
        "industry"
    ],
    "wof:name":"Garanti Boru Fitings Paslanmaz San.ve Dis Tic.ltd.sti.",
    "wof:placetype":"venue"
},
  "geometry": {"coordinates":[28.9759254456,41.0123786926],"type":"Point"}
}