{
  "type": "Feature",
  "properties": {
    "addr:full":"Yukari Dudullu Bayraktar Bulvari No:59 \u00dcmraniye Istanbul",
    "addr:housenumber":"no 59",
    "addr:street":"Bayraktar Bulvari",
    "iso:country":"TR",
    "sg:address":"Yukari Dudullu Bayraktar Bulvari No:59",
    "sg:city":"\u00dcmraniye",
    "sg:classifiers":[
        {
            "category":"Manufacturing",
            "subcategory":"Building Materials",
            "type":"Manufacturing & Wholesale Goods"
        }
    ],
    "sg:phone":"+90 216 364 7634",
    "sg:province":"Istanbul",
    "sg:tags":[
        "lifts-elevators"
    ],
    "wof:name":"Dizayn Asans?r Sistemleri",
    "wof:placetype":"venue"
},
  "geometry": {"coordinates":[28.9759254456,41.0123786926],"type":"Point"}
}