{
  "type": "Feature",
  "properties": {
    "addr:full":"Cumhuriyet Cad.no:13 Laleli Denizli 34470",
    "addr:housenumber":"13",
    "addr:postcode":"34470",
    "addr:street":"Cad.No",
    "iso:country":"TR",
    "sg:address":"Cumhuriyet Cad.no:13",
    "sg:city":"Laleli",
    "sg:orig_category":"Hotels: Motels",
    "sg:phone":"+90 258 261 1179",
    "sg:postcode":"34470",
    "sg:province":"Denizli",
    "wof:name":"Gong Hotel",
    "wof:placetype":"venue"
},
  "geometry": {"coordinates":[29.0873508453,37.7860183716],"type":"Point"}
}