{
  "type": "Feature",
  "properties": {
    "addr:full":"Arabacilar Sok No: 27/2 Kad\u0131k\u00f6y Yalova 77050",
    "addr:housenumber":"no 27 / 2",
    "addr:postcode":"77050",
    "addr:street":"Arabacilar Sok;Kadikoey Yalova",
    "iso:country":"TR",
    "sg:address":"Arabacilar Sok No: 27/2",
    "sg:city":"Kad\u0131k\u00f6y",
    "sg:classifiers":[
        {
            "category":"Travel",
            "subcategory":"Travel Agent",
            "type":"Entertainment"
        }
    ],
    "sg:phone":"+90 226 813 9365",
    "sg:postcode":"77050",
    "sg:province":"Yalova",
    "sg:tags":[
        "agency",
        "tourism"
    ],
    "wof:name":"G?denogullari Turizm",
    "wof:placetype":"venue"
},
  "geometry": {"coordinates":[29.2999153137,40.6587982178],"type":"Point"}
}