{
  "type": "Feature",
  "properties": {
    "addr:full":"Idealtepe Mah.ozgur Sok. No: 16 Maltepe Selcuklu Istanbul 42020",
    "addr:housenumber":"no 16",
    "addr:postcode":"42020",
    "addr:street":"Mah.Ozgur Sok.;Maltepe Selcuklu",
    "iso:country":"TR",
    "sg:address":"Idealtepe Mah.ozgur Sok. No: 16 Maltepe",
    "sg:city":"Selcuklu",
    "sg:classifiers":[
        {
            "category":"Home & Garden",
            "subcategory":"Hardware",
            "type":"Retail Goods"
        }
    ],
    "sg:phone":"+90 216 518 1150",
    "sg:postcode":"42020",
    "sg:province":"Istanbul",
    "sg:tags":[
        "compressor",
        "pump"
    ],
    "wof:name":"Metrans Ltd.sti.",
    "wof:placetype":"venue"
},
  "geometry": {"coordinates":[29.1255321503,40.9434127808],"type":"Point"}
}