{
  "type": "Feature",
  "properties": {
    "iso:country":"TR",
    "sg:address":"Mustafa Irit?k",
    "sg:city":"Finike",
    "sg:classifiers":[
        {
            "category":"Government",
            "subcategory":"Office",
            "type":"Public Place"
        }
    ],
    "sg:phone":"+90 266 432 1035",
    "sg:postcode":"07740",
    "sg:province":"Balikesir",
    "sg:tags":[
        "municipality"
    ],
    "wof:name":"Havran Belediye Baskani",
    "wof:placetype":"venue"
},
  "geometry": {"coordinates":[27.8833007812,39.6520996094],"type":"Point"}
}