{
  "type": "Feature",
  "properties": {
    "iso:country":"TR",
    "sg:address":"Cumhuriyet Caddesi 39/i",
    "sg:city":"Taksim",
    "sg:classifiers":[
        {
            "category":"Freight",
            "type":"Transportation"
        }
    ],
    "sg:phone":"+90 212237420102",
    "sg:postcode":"24040",
    "sg:province":"Istanbul",
    "sg:tags":[
        "cargo",
        "air"
    ],
    "wof:name":"Azerbaijan Airlines",
    "wof:placetype":"venue"
},
  "geometry": {"coordinates":[29.0271968842,41.0280303955],"type":"Point"}
}