{
  "type": "Feature",
  "properties": {
    "iso:country":"TR",
    "sg:address":"Ata Cad No.17/d Bal?va Bal?va",
    "sg:city":"G?esli",
    "sg:classifiers":[
        {
            "category":"Shopping",
            "subcategory":"Clothing, Apparel, & Fashions",
            "type":"Retail Goods"
        }
    ],
    "sg:phone":"+90 2322598432329",
    "sg:province":"Izmir",
    "sg:tags":[
        "watch",
        "lighter"
    ],
    "wof:name":"Moda Saat Center",
    "wof:placetype":"venue"
},
  "geometry": {"coordinates":[27.1296863556,38.4186973572],"type":"Point"}
}