{
  "type": "Feature",
  "properties": {
    "addr:full":"Osmaniye M Ipek Sok. No:1/d- Gemlik Bursa 16600",
    "addr:housenumber":"no 1 / d",
    "addr:postcode":"16600",
    "addr:street":"Ipek Sok.;Bursa",
    "iso:country":"TR",
    "sg:address":"Osmaniye M Ipek Sok. No:1/d-",
    "sg:city":"Gemlik",
    "sg:classifiers":[
        {
            "category":"Government",
            "subcategory":"Fire Station",
            "type":"Public Place"
        }
    ],
    "sg:phone":"+90 224 514 3116",
    "sg:postcode":"16600",
    "sg:province":"Bursa",
    "sg:tags":[
        "decoration"
    ],
    "wof:name":"Yavuzlar Alci Dekorasyon",
    "wof:placetype":"venue"
},
  "geometry": {"coordinates":[29.0586109161,40.1844291687],"type":"Point"}
}