{
  "type": "Feature",
  "properties": {
    "addr:full":"Haydar Yilmaz Ayas Ankara 01680",
    "addr:postcode":"01680",
    "iso:country":"TR",
    "sg:address":"Haydar Yilmaz",
    "sg:city":"Ayas",
    "sg:classifiers":[
        {
            "category":"Government",
            "subcategory":"Office",
            "type":"Public Place"
        }
    ],
    "sg:phone":"+90 312 434 1546",
    "sg:postcode":"01680",
    "sg:province":"Ankara",
    "sg:tags":[
        "municipality"
    ],
    "wof:name":"?ankaya Belediye Baskani",
    "wof:placetype":"venue"
},
  "geometry": {"coordinates":[28.9546337128,41.0124168396],"type":"Point"}
}