{
  "type": "Feature",
  "properties": {
    "addr:full":"Ikitelli Organize San.dolapdere San.sitesi 15 Ada No: 2 Selcuklu Istanbul 42300",
    "addr:housenumber":"15",
    "addr:postcode":"42300",
    "addr:street":"San.Sitesi;No 2 Selcuklu",
    "iso:country":"TR",
    "sg:address":"Ikitelli Organize San.dolapdere San.sitesi 15 Ada No: 2",
    "sg:city":"Selcuklu",
    "sg:classifiers":[
        {
            "category":"Wholesale",
            "subcategory":"Auto Parts",
            "type":"Manufacturing & Wholesale Goods"
        }
    ],
    "sg:phone":"+90 212671025455",
    "sg:postcode":"42300",
    "sg:province":"Istanbul",
    "sg:tags":[
        "spare"
    ],
    "wof:name":"Star Dizel Makina San.ltd.sti.",
    "wof:placetype":"venue"
},
  "geometry": {"coordinates":[28.9861831665,41.0408554077],"type":"Point"}
}