{
  "type": "Feature",
  "properties": {
    "addr:full":"Istasyon Cad. Cihangir Ism. No:14 K:2/10 Gaziosmanpasa Elazig 06700",
    "addr:housenumber":"ism. no 14 k 2 / 10",
    "addr:postcode":"06700",
    "addr:street":"Istasyon Cad.;Elazig",
    "iso:country":"TR",
    "sg:address":"Istasyon Cad. Cihangir Ism. No:14 K:2/10",
    "sg:city":"Gaziosmanpasa",
    "sg:classifiers":[
        {
            "category":"Wholesale",
            "subcategory":"Medical Equipment & Supplies",
            "type":"Manufacturing & Wholesale Goods"
        }
    ],
    "sg:phone":"+90 424 236 8300",
    "sg:postcode":"06700",
    "sg:province":"Elazig",
    "wof:name":"Ozcihangir Ic Dis Tic. Ltd. Sti.",
    "wof:placetype":"venue"
},
  "geometry": {"coordinates":[39.2357254028,38.6678085327],"type":"Point"}
}