{
  "type": "Feature",
  "properties": {
    "iso:country":"TR",
    "sg:address":"Silahtar Cad. No:35 Halicioglu",
    "sg:city":"?akmakli",
    "sg:classifiers":[
        {
            "category":"Retail",
            "subcategory":"Storage",
            "type":"Services"
        }
    ],
    "sg:phone":"+90 212 320 8595",
    "sg:province":"Istanbul",
    "sg:tags":[
        "shelving",
        "system"
    ],
    "wof:name":"Rafsan Raf Sistemleri Ltd.sti.",
    "wof:placetype":"venue"
},
  "geometry": {"coordinates":[28.951157,41.063084],"type":"Point"}
}