{
  "type": "Feature",
  "properties": {
    "addr:full":"Ahmet ?zdemir B??orhan Bursa",
    "addr:housenumber":"?;b ? ?",
    "addr:street":"Ahmet",
    "iso:country":"TR",
    "sg:address":"Ahmet ?zdemir",
    "sg:city":"B??orhan",
    "sg:classifiers":[
        {
            "category":"Government",
            "subcategory":"Office",
            "type":"Public Place"
        }
    ],
    "sg:phone":"+90 224 852 5062",
    "sg:province":"Bursa",
    "sg:tags":[
        "municipality"
    ],
    "wof:name":"Kinik Belediye Baskani",
    "wof:placetype":"venue"
},
  "geometry": {"coordinates":[29.1887512207,40.2138900757],"type":"Point"}
}