{
  "type": "Feature",
  "properties": {
    "addr:full":"Saglik Sk. No:17/3 Sihhiye Okmeydani Ankara 43050",
    "addr:housenumber":"17 / 3",
    "addr:postcode":"43050",
    "addr:street":"Saglik Sk. No",
    "iso:country":"TR",
    "sg:address":"Saglik Sk. No:17/3 Sihhiye",
    "sg:city":"Okmeydani",
    "sg:classifiers":[
        {
            "category":"Shopping",
            "subcategory":"Stationery & Office Supplies",
            "type":"Retail Goods"
        }
    ],
    "sg:phone":"+90 312 433 3034",
    "sg:postcode":"43050",
    "sg:province":"Ankara",
    "wof:name":"Silka Kirtasiye Malzeme. San. Ltd. Sti.",
    "wof:placetype":"venue"
},
  "geometry": {"coordinates":[32.885136,39.920403],"type":"Point"}
}