{
  "type": "Feature",
  "properties": {
    "addr:full":"Ceyhan Yolu ?zeri Keresteciler Sitesi 191 Sk No:26 Y?egir Sapanca Adana 54600",
    "addr:housenumber":"?",
    "addr:postcode":"54600",
    "addr:street":"Ceyhan Yolu;191;Adana",
    "iso:country":"TR",
    "sg:address":"Ceyhan Yolu ?zeri Keresteciler Sitesi 191 Sk No:26 Y?egir",
    "sg:city":"Sapanca",
    "sg:classifiers":[
        {
            "category":"Manufacturing",
            "subcategory":"Wood Products",
            "type":"Manufacturing & Wholesale Goods"
        }
    ],
    "sg:phone":"+90 322 346 0466",
    "sg:postcode":"54600",
    "sg:province":"Adana",
    "sg:tags":[
        "forest"
    ],
    "wof:name":"?ukurova Kereste Ticarethanesi",
    "wof:placetype":"venue"
},
  "geometry": {"coordinates":[35.3137359619,37.0007171631],"type":"Point"}
}