{
  "type": "Feature",
  "properties": {
    "iso:country":"TR",
    "sg:address":"1. Murat Cad. 131",
    "sg:city":"?ekirge",
    "sg:orig_category":"Hotels: Motels",
    "sg:phone":"+90 22423452504",
    "sg:postcode":"16050",
    "sg:province":"Bursa",
    "wof:name":"Huzur Termal Hotel",
    "wof:placetype":"venue"
},
  "geometry": {"coordinates":[29.0237197876,40.2018318176],"type":"Point"}
}