{
  "type": "Feature",
  "properties": {
    "iso:country":"TR",
    "sg:address":"Atikali Pasa Camii Medrese Sokak No:23/b 34440 Cemberlitas Istanbul",
    "sg:city":"Besiktas",
    "sg:classifiers":[
        {
            "category":"Shopping",
            "subcategory":"Jewelry",
            "type":"Retail Goods"
        }
    ],
    "sg:phone":"+90 212 512 2394",
    "sg:postcode":"75200",
    "sg:province":"Istanbul",
    "sg:tags":[
        "jewellery"
    ],
    "wof:name":"Polat Kuyumculuk Ve Mucevherat San Tic Ltd Sti",
    "wof:placetype":"venue"
},
  "geometry": {"coordinates":[28.9759254456,41.0123786926],"type":"Point"}
}