{
  "type": "Feature",
  "properties": {
    "iso:country":"TR",
    "sg:address":"494.sok. No:2 Sirinyer",
    "sg:city":"Cankaya",
    "sg:classifiers":[
        {
            "category":"Health Services",
            "subcategory":"Clinic",
            "type":"Services"
        }
    ],
    "sg:phone":"+90 232 438 5959",
    "sg:postcode":"07080",
    "sg:province":"Izmir",
    "wof:name":"Ozel Nezahet Tip Merkezi",
    "wof:placetype":"venue"
},
  "geometry": {"coordinates":[27.1423015594,38.4251480103],"type":"Point"}
}