{
  "type": "Feature",
  "properties": {
    "addr:full":"Ulu ?arsi No:28 Kat.1 Nazilli Denizli 65600",
    "addr:housenumber":"kat.1",
    "addr:postcode":"65600",
    "addr:street":"No 28",
    "iso:country":"TR",
    "sg:address":"Ulu ?arsi No:28 Kat.1",
    "sg:city":"Nazilli",
    "sg:classifiers":[
        {
            "category":"Shopping",
            "subcategory":"Clothing, Apparel, & Fashions",
            "type":"Retail Goods"
        }
    ],
    "sg:phone":"+90 258 265 0941",
    "sg:postcode":"65600",
    "sg:province":"Denizli",
    "sg:tags":[
        "ready",
        "wear"
    ],
    "wof:name":"Sen Ticaret Import-export",
    "wof:placetype":"venue"
},
  "geometry": {"coordinates":[29.0864906311,37.773525238],"type":"Point"}
}