{
  "type": "Feature",
  "properties": {
    "addr:full":"Mehmet?k Cd. No:63 Mecidiyek? Mersin Istanbul 52750",
    "addr:housenumber":"no 63;?",
    "addr:postcode":"52750",
    "addr:street":"K Cd.;Mecidiyek",
    "iso:country":"TR",
    "sg:address":"Mehmet?k Cd. No:63 Mecidiyek?",
    "sg:city":"Mersin",
    "sg:classifiers":[
        {
            "category":"Professional",
            "subcategory":"Art Services",
            "type":"Services"
        }
    ],
    "sg:phone":"+90 212 272 6789",
    "sg:postcode":"52750",
    "sg:province":"Istanbul",
    "sg:tags":[
        "marketing"
    ],
    "wof:name":"Girisim Pazarlama A.s.",
    "wof:placetype":"venue"
},
  "geometry": {"coordinates":[28.9861831665,41.0408554077],"type":"Point"}
}