{
  "type": "Feature",
  "properties": {
    "iso:country":"TR",
    "sg:address":"Orta Mah.menekse Sok. No:16/1 Kartal",
    "sg:city":"Sihhiye",
    "sg:classifiers":[
        {
            "category":"Professional",
            "subcategory":"Testing Lab",
            "type":"Services"
        }
    ],
    "sg:phone":"+90 216 452 4822",
    "sg:postcode":"06410",
    "sg:province":"Istanbul",
    "sg:tags":[
        "laboratory",
        "material"
    ],
    "wof:name":"Seromed Biyolojik ?r?nler San.l",
    "wof:placetype":"venue"
},
  "geometry": {"coordinates":[29.2456226349,40.891078949],"type":"Point"}
}