{
  "type": "Feature",
  "properties": {
    "iso:country":"TR",
    "sg:address":"Ali Pasa Mh. Sebilerenler Cd. Kahramangil Apt. Zemin Kat",
    "sg:city":"07100",
    "sg:classifiers":[
        {
            "category":"Home & Garden",
            "subcategory":"Carpets & Floor Coverings",
            "type":"Retail Goods"
        }
    ],
    "sg:phone":"+90 274 216 2412",
    "sg:province":"K?tahya",
    "sg:tags":[
        "wall",
        "ceramics-porcelain",
        "tile",
        "-"
    ],
    "wof:name":"Altin Cini A.s.",
    "wof:placetype":"venue"
},
  "geometry": {"coordinates":[35.4317016602,38.9577407837],"type":"Point"}
}