{
  "type": "Feature",
  "properties": {
    "addr:full":"Bab-i Aksaray Mah. K?pr? Cad. K?sem Ishani K:2 No:201 Karatay Konya 42000",
    "addr:housenumber":"k ?;2 no 201",
    "addr:postcode":"42000",
    "addr:street":"Mah. K ?;? Cad.",
    "iso:country":"TR",
    "sg:address":"Bab-i Aksaray Mah. K?pr? Cad. K?sem Ishani K:2 No:201",
    "sg:city":"Karatay",
    "sg:classifiers":[
        {
            "category":"Travel",
            "subcategory":"Travel Agent",
            "type":"Entertainment"
        }
    ],
    "sg:phone":"+90 332 353 4253",
    "sg:postcode":"42000",
    "sg:province":"Konya",
    "sg:tags":[
        "agency",
        "tourism"
    ],
    "wof:name":"Vakit Turizm",
    "wof:placetype":"venue"
},
  "geometry": {"coordinates":[33.0667152405,39.2111282349],"type":"Point"}
}