{
  "type": "Feature",
  "properties": {
    "iso:country":"TR",
    "sg:address":"Fabrika: Ankara Cad. Erkilic Sok. No:12",
    "sg:city":"Kartal",
    "sg:classifiers":[
        {
            "category":"Shopping",
            "subcategory":"Clothing, Apparel, & Fashions",
            "type":"Retail Goods"
        }
    ],
    "sg:phone":"+90 216 374 1689",
    "sg:postcode":"46000",
    "sg:province":"Istanbul",
    "sg:tags":[
        "woman",
        "wear"
    ],
    "wof:name":"Vivid Moda Giyim San.tic.ltd.",
    "wof:placetype":"venue"
},
  "geometry": {"coordinates":[28.9759254456,41.0123786926],"type":"Point"}
}