{
  "type": "Feature",
  "properties": {
    "addr:full":"Mithatpasa Cad. Sara? Ishak Mah. Fermanli Sok. No: 7-9 D: 601 Beyazit Istanbul 65400",
    "addr:housenumber":"no 7-9 d 601",
    "addr:postcode":"65400",
    "addr:street":"Mithatpasa Cad. Sara ? Ishak;Fermanli Sok.;Beyazit Istanbul",
    "iso:country":"TR",
    "sg:address":"Mithatpasa Cad. Sara? Ishak Mah. Fermanli Sok. No: 7-9 D: 601",
    "sg:city":"Beyazit",
    "sg:classifiers":[
        {
            "category":"Travel",
            "subcategory":"Travel Agent",
            "type":"Entertainment"
        }
    ],
    "sg:phone":"+90 51700215173618",
    "sg:postcode":"65400",
    "sg:province":"Istanbul",
    "sg:tags":[
        "agency",
        "tourism"
    ],
    "wof:name":"Remzi Turizm",
    "wof:placetype":"venue"
},
  "geometry": {"coordinates":[28.9861831665,41.0408554077],"type":"Point"}
}