{
  "type": "Feature",
  "properties": {
    "addr:full":"Fuzumi Cad. Cihat Apt.no:36/a Kocasinan 55020 Kayseri",
    "addr:housenumber":"36 / a",
    "addr:postcode":"55020",
    "addr:street":"Fuzumi Cad. Cihat Apt.No;Kocasinan",
    "iso:country":"TR",
    "sg:address":"Fuzumi Cad. Cihat Apt.no:36/a Kocasinan",
    "sg:city":"55020",
    "sg:classifiers":[
        {
            "category":"Shopping",
            "type":"Retail Goods"
        }
    ],
    "sg:phone":"+90 352 223 0267",
    "sg:province":"Kayseri",
    "sg:tags":[
        "material",
        "cleaning"
    ],
    "wof:name":"Un-pa Endustriyel Temizlik Urun.ve Ekipmanlari",
    "wof:placetype":"venue"
},
  "geometry": {"coordinates":[35.4889183044,38.7189102173],"type":"Point"}
}