{
  "type": "Feature",
  "properties": {
    "addr:full":"Uskup Cad. No:2/e Kavaklidere Ankara 35040",
    "addr:postcode":"35040",
    "addr:street":"Uskup Cad. No 2 / E Kavaklidere",
    "iso:country":"TR",
    "sg:address":"Uskup Cad. No:2/e",
    "sg:city":"Kavaklidere",
    "sg:classifiers":[
        {
            "category":"Professional",
            "subcategory":"Engineering",
            "type":"Services"
        }
    ],
    "sg:phone":"+90 312426931227",
    "sg:postcode":"35040",
    "sg:province":"Ankara",
    "sg:tags":[
        "architect"
    ],
    "wof:name":"Zmd Muhendislik Insaat.taahut",
    "wof:placetype":"venue"
},
  "geometry": {"coordinates":[32.8604812622,39.9429283142],"type":"Point"}
}