{
  "type": "Feature",
  "properties": {
    "iso:country":"TR",
    "sg:address":"Gazi Mah.1320.sok. No:14",
    "sg:city":"Mersin",
    "sg:classifiers":[
        {
            "category":"Utilities",
            "subcategory":"Electric",
            "type":"Services"
        }
    ],
    "sg:phone":"+90 324 329 0305",
    "sg:postcode":"52750",
    "sg:province":"I?el",
    "sg:tags":[
        "energy",
        "solar"
    ],
    "wof:name":"Kuzey Enerji Sanayi Ve Tic.ltd.sti.",
    "wof:placetype":"venue"
},
  "geometry": {"coordinates":[39.245754,38.672215],"type":"Point"}
}