{
  "type": "Feature",
  "properties": {
    "addr:full":"M.f.cakmak Cad. 2.sok. No:1 Kat:4/28 Sirinevler Uskudar Istanbul 34704",
    "addr:housenumber":"2.sok no 1 kat 4 / 28",
    "addr:postcode":"34704",
    "addr:street":"M.F.Cakmak Cad.;Sirinevler Uskudar",
    "iso:country":"TR",
    "sg:address":"M.f.cakmak Cad. 2.sok. No:1 Kat:4/28 Sirinevler",
    "sg:city":"Uskudar",
    "sg:classifiers":[
        {
            "category":"Banks & Credit Unions",
            "subcategory":"Investment Brokerage",
            "type":"Services"
        }
    ],
    "sg:phone":"+90 212 639 2515",
    "sg:postcode":"34704",
    "sg:province":"Istanbul",
    "sg:tags":[
        "-",
        "export",
        "import"
    ],
    "wof:name":"Gulsen Gum. Nak. Trz. Eml. Teks. San. Ve Tic. Ltd.sti.",
    "wof:placetype":"venue"
},
  "geometry": {"coordinates":[28.9861831665,41.0408554077],"type":"Point"}
}