{
  "type": "Feature",
  "properties": {
    "iso:country":"TR",
    "sg:address":"Hayrettin Cavus Mah.sansar Sok. Kevser Is Hani No:14",
    "sg:city":"Goztepe",
    "sg:classifiers":[
        {
            "category":"Professional",
            "subcategory":"Employment Agencies",
            "type":"Services"
        }
    ],
    "sg:phone":"+90 216 333 3513",
    "sg:postcode":"01220",
    "sg:province":"Istanbul",
    "sg:tags":[
        "personnel"
    ],
    "wof:name":"Dadasim Turizm",
    "wof:placetype":"venue"
},
  "geometry": {"coordinates":[28.9759254456,41.0123786926],"type":"Point"}
}