{
  "type": "Feature",
  "properties": {
    "iso:country":"TR",
    "sg:address":"10001 Sok. No:27 A.o.s.b. Cigli",
    "sg:city":"Uskudar",
    "sg:classifiers":[
        {
            "category":"Banks & Credit Unions",
            "subcategory":"Investment Brokerage",
            "type":"Services"
        }
    ],
    "sg:phone":"+90 232 376 7530",
    "sg:postcode":"34704",
    "sg:province":"Izmir",
    "sg:tags":[
        "-",
        "export",
        "import"
    ],
    "wof:name":"Gul Turizm A.s.",
    "wof:placetype":"venue"
},
  "geometry": {"coordinates":[27.1423015594,38.4251480103],"type":"Point"}
}