{
  "type": "Feature",
  "properties": {
    "addr:full":"Fevzi Pasa Cd. No:55 Merter Izmir",
    "addr:housenumber":"no 55",
    "addr:street":"Fevzi Pasa Cd.",
    "iso:country":"TR",
    "sg:address":"Fevzi Pasa Cd. No:55",
    "sg:city":"Merter",
    "sg:classifiers":[
        {
            "category":"Shopping",
            "subcategory":"Clothing, Apparel, & Fashions",
            "type":"Retail Goods"
        }
    ],
    "sg:phone":"+90 232 483 6644",
    "sg:province":"Izmir",
    "sg:tags":[
        "house"
    ],
    "wof:name":"Sirmam Moda Evi",
    "wof:placetype":"venue"
},
  "geometry": {"coordinates":[27.1354885101,38.4224739075],"type":"Point"}
}