{
  "type": "Feature",
  "properties": {
    "addr:full":"Teknik Oto San.sit.5.blk.no:126 Topkapi Istanbul 34515",
    "addr:housenumber":"126",
    "addr:postcode":"34515",
    "addr:street":"Topkapi Istanbul",
    "iso:country":"TR",
    "sg:address":"Teknik Oto San.sit.5.blk.no:126",
    "sg:city":"Topkapi",
    "sg:classifiers":[
        {
            "category":"Wholesale",
            "subcategory":"Machinery & Supplies",
            "type":"Manufacturing & Wholesale Goods"
        }
    ],
    "sg:phone":"+90 212 481 8500",
    "sg:postcode":"34515",
    "sg:province":"Istanbul",
    "sg:tags":[
        "bearing",
        "ball"
    ],
    "wof:name":"Akbilya",
    "wof:placetype":"venue"
},
  "geometry": {"coordinates":[28.975925,41.012379],"type":"Point"}
}