{
  "type": "Feature",
  "properties": {
    "addr:full":"?i?eklibahar Sok No.5/1 Mecidiyek?y/sisli Istanbul 34394",
    "addr:housenumber":"?;?;no.5 / 1 mecidiyek ? y",
    "addr:postcode":"34394",
    "addr:street":"I;Eklibahar Sok",
    "iso:country":"TR",
    "sg:address":"?i?eklibahar Sok No.5/1",
    "sg:city":"Mecidiyek?y/sisli",
    "sg:classifiers":[
        {
            "category":"Communications",
            "subcategory":"Film & Video Production",
            "type":"Services"
        }
    ],
    "sg:phone":"+90 212 211 4626",
    "sg:postcode":"34394",
    "sg:province":"Istanbul",
    "sg:tags":[
        "packing",
        "material"
    ],
    "wof:name":"Arti Plastik Ambalaj San Ltd.sti",
    "wof:placetype":"venue"
},
  "geometry": {"coordinates":[29.0846271515,40.9987373352],"type":"Point"}
}