{
  "type": "Feature",
  "properties": {
    "iso:country":"TR",
    "sg:address":"B??dere Cd. No:103 K:9 Gayrettepe",
    "sg:city":"Mersin",
    "sg:classifiers":[
        {
            "category":"Mining & Drilling",
            "type":"Manufacturing & Wholesale Goods"
        }
    ],
    "sg:phone":"+90 212 275 1963",
    "sg:postcode":"52750",
    "sg:province":"Istanbul",
    "sg:tags":[
        "industry",
        "mine"
    ],
    "wof:name":"Birlik Madencilik Tur San. Tic. A.s.",
    "wof:placetype":"venue"
},
  "geometry": {"coordinates":[28.987569809,41.0759658813],"type":"Point"}
}