{
  "type": "Feature",
  "properties": {
    "iso:country":"TR",
    "sg:address":"Dogu San. Sit. No:22-24 Y.bosna",
    "sg:city":"Mersin",
    "sg:classifiers":[
        {
            "category":"Manufacturing",
            "subcategory":"Rubber & Plastics",
            "type":"Manufacturing & Wholesale Goods"
        }
    ],
    "sg:phone":"+90 212 552 0746",
    "sg:postcode":"52750",
    "sg:province":"Istanbul",
    "sg:tags":[
        "industry"
    ],
    "wof:name":"Kulpsan Plastik San. Tic. A.s.",
    "wof:placetype":"venue"
},
  "geometry": {"coordinates":[28.975925,41.012379],"type":"Point"}
}