{
  "type": "Feature",
  "properties": {
    "addr:full":"Eski Golcuk Yolu 5.km Izmit Gaziosmanpasa Kocaeli 34240",
    "addr:housenumber":"5.km",
    "addr:postcode":"34240",
    "addr:street":"Eski Golcuk Yolu;Gaziosmanpasa",
    "iso:country":"TR",
    "sg:address":"Eski Golcuk Yolu 5.km Izmit",
    "sg:city":"Gaziosmanpasa",
    "sg:classifiers":[
        {
            "category":"Manufacturing",
            "subcategory":"Metals",
            "type":"Manufacturing & Wholesale Goods"
        }
    ],
    "sg:phone":"+90 262 335 0116",
    "sg:postcode":"34240",
    "sg:province":"Kocaeli",
    "sg:tags":[
        "iron-steel",
        "peoducts"
    ],
    "wof:name":"Yilmazlar Celik Konstruksiyon Ve Makina Iml.montaj San. Tic.a.s.",
    "wof:placetype":"venue"
},
  "geometry": {"coordinates":[29.881521225,40.8532714844],"type":"Point"}
}