{
  "type": "Feature",
  "properties": {
    "iso:country":"TR",
    "sg:address":"Calislar Cad. No: 47/3 Bahcelievler",
    "sg:city":"Beyazit",
    "sg:classifiers":[
        {
            "category":"Manufacturing",
            "subcategory":"Leather Goods",
            "type":"Manufacturing & Wholesale Goods"
        }
    ],
    "sg:phone":"+90 212 677 9550",
    "sg:postcode":"65400",
    "sg:province":"Istanbul",
    "wof:name":"Nugget International Ltd.",
    "wof:placetype":"venue"
},
  "geometry": {"coordinates":[28.8712348938,41.0047454834],"type":"Point"}
}