{
  "type": "Feature",
  "properties": {
    "addr:full":"?oban?sme Kimiz Sok. No:15 Yenibosna Istanbul 43270",
    "addr:housenumber":"?;?;no 15",
    "addr:postcode":"43270",
    "addr:street":"Oban;Kimiz Sok.;Istanbul",
    "iso:country":"TR",
    "sg:address":"?oban?sme Kimiz Sok. No:15",
    "sg:city":"Yenibosna",
    "sg:classifiers":[
        {
            "category":"Wholesale",
            "subcategory":"Machinery & Supplies",
            "type":"Manufacturing & Wholesale Goods"
        }
    ],
    "sg:phone":"+90 212 503 8050",
    "sg:postcode":"43270",
    "sg:province":"Istanbul",
    "sg:tags":[
        "agricultural"
    ],
    "wof:name":"Altinova San.mam.tic.paz.ltd.sti.",
    "wof:placetype":"venue"
},
  "geometry": {"coordinates":[28.9759254456,41.0123786926],"type":"Point"}
}