{
  "type": "Feature",
  "properties": {
    "addr:full":"Bagdat Cd. No:311 Cevizli Yenibosna Istanbul 43270",
    "addr:housenumber":"no",
    "addr:postcode":"43270",
    "addr:street":"Bagdat Cd.;Cevizli",
    "iso:country":"TR",
    "sg:address":"Bagdat Cd. No:311 Cevizli",
    "sg:city":"Yenibosna",
    "sg:classifiers":[
        {
            "category":"Manufacturing",
            "subcategory":"Rubber & Plastics",
            "type":"Manufacturing & Wholesale Goods"
        }
    ],
    "sg:phone":"+90 216 352 8815",
    "sg:postcode":"43270",
    "sg:province":"Istanbul",
    "sg:tags":[
        "industry"
    ],
    "wof:name":"Bima Plastik San. Tic. A.s.",
    "wof:placetype":"venue"
},
  "geometry": {"coordinates":[29.1478233337,40.9155654907],"type":"Point"}
}