{
  "type": "Feature",
  "properties": {
    "iso:country":"TR",
    "sg:address":"Ankara Cad.kazim Dirik Mah. Ihsaniye Plaza No:75 Kat: 2 D:203",
    "sg:city":"\u00dcmraniye",
    "sg:classifiers":[
        {
            "category":"Professional",
            "subcategory":"Detective & Security Services",
            "type":"Services"
        }
    ],
    "sg:phone":"+90 232 461 7731",
    "sg:province":"Izmir",
    "sg:tags":[
        "material"
    ],
    "wof:name":"Prestij Uuvenlik",
    "wof:placetype":"venue"
},
  "geometry": {"coordinates":[27.129686,38.418697],"type":"Point"}
}