{
  "type": "Feature",
  "properties": {
    "addr:full":"108. Sk. No:13 Aykusan Isikkent Izmir 32100",
    "addr:housenumber":"13",
    "addr:postcode":"32100",
    "addr:street":"108 Sk. No",
    "iso:country":"TR",
    "sg:address":"108. Sk. No:13 Aykusan",
    "sg:city":"Isikkent",
    "sg:classifiers":[
        {
            "category":"Shopping",
            "subcategory":"Clothing, Apparel, & Fashions",
            "type":"Retail Goods"
        }
    ],
    "sg:phone":"+90 232 436 3582",
    "sg:postcode":"32100",
    "sg:province":"Izmir",
    "sg:tags":[
        "house"
    ],
    "wof:name":"Modelist Haluk Tiryaki",
    "wof:placetype":"venue"
},
  "geometry": {"coordinates":[27.1296863556,38.4186973572],"type":"Point"}
}