{
  "type": "Feature",
  "properties": {
    "iso:country":"TR",
    "sg:address":"Pazar Sok.no:3/4 Cide",
    "sg:city":"Kesan",
    "sg:classifiers":[
        {
            "category":"Shopping",
            "subcategory":"Bicycles & Sporting Goods",
            "type":"Retail Goods"
        }
    ],
    "sg:phone":"+90 366 866 2371",
    "sg:postcode":"22800",
    "sg:province":"Kastamonu",
    "sg:tags":[
        "equipment",
        "marine",
        "hunting"
    ],
    "wof:name":"Oral Av Malzemeleri",
    "wof:placetype":"venue"
},
  "geometry": {"coordinates":[33.8337211609,40.9265403748],"type":"Point"}
}