{
  "type": "Feature",
  "properties": {
    "iso:country":"TR",
    "sg:address":"Haci Ilbey Sok. Parlak Ishani 32/34 Dolapdere",
    "sg:city":"Yenidogan",
    "sg:orig_category":"Furniture Supplamentary",
    "sg:phone":"+90 212 255 1960",
    "sg:postcode":"81270",
    "sg:province":"Istanbul",
    "wof:name":"Cuneyt Aydinlatan Mobilya & Dekorasyon",
    "wof:placetype":"venue"
},
  "geometry": {"coordinates":[28.9759254456,41.0123786926],"type":"Point"}
}