{
  "type": "Feature",
  "properties": {
    "addr:full":"Aydievler Mah, In??cad - G?? Sokak - Gsd Bldg No 14, K??yali, 81570 Istanbul Elmadag Istanbul 65900",
    "addr:housenumber":"?;gsd bldg no 14 k ? ?",
    "addr:postcode":"81570;65900",
    "addr:street":"Aydievler Mah In ? ? Cad G;? Sokak",
    "iso:country":"TR",
    "sg:address":"Aydievler Mah, In??cad - G?? Sokak - Gsd Bldg No 14, K??yali, 81570 Istanbul",
    "sg:city":"Elmadag",
    "sg:classifiers":[
        {
            "category":"Banks & Credit Unions",
            "subcategory":"Bank",
            "type":"Services"
        }
    ],
    "sg:phone":"+90 216489975030",
    "sg:postcode":"65900",
    "sg:province":"Istanbul",
    "sg:website":"http://www.gsdbank.com.tr",
    "wof:name":"Gsd Yatirim Bankasi As",
    "wof:placetype":"venue"
},
  "geometry": {"coordinates":[28.975925,41.012379],"type":"Point"}
}