{
  "type": "Feature",
  "properties": {
    "addr:full":"Marangozlar San.sit.5.cad.no:70-76 Beypazari Ankara 06730",
    "addr:housenumber":"70-76",
    "addr:postcode":"06730",
    "addr:street":"Beypazari Ankara",
    "iso:country":"TR",
    "sg:address":"Marangozlar San.sit.5.cad.no:70-76",
    "sg:city":"Beypazari",
    "sg:classifiers":[
        {
            "category":"Professional",
            "subcategory":"Business Services",
            "type":"Services"
        }
    ],
    "sg:phone":"+90 31276255000",
    "sg:postcode":"06730",
    "sg:province":"Ankara",
    "sg:tags":[
        "food",
        "product",
        "exporter",
        "aricultural"
    ],
    "wof:name":"Bgs Beypazari Gida San.tic.ltd.sti",
    "wof:placetype":"venue"
},
  "geometry": {"coordinates":[32.8560333252,39.9438743591],"type":"Point"}
}