{
  "type": "Feature",
  "properties": {
    "iso:country":"TR",
    "sg:address":"Mersin Yolu ?zeri 19.km.cukubirlik Civari",
    "sg:city":"?raniye",
    "sg:classifiers":[
        {
            "category":"Utilities",
            "subcategory":"Recycling",
            "type":"Services"
        }
    ],
    "sg:phone":"+90 322 441 0321",
    "sg:postcode":"81260",
    "sg:province":"Adana",
    "sg:tags":[
        "measuring",
        "weighing"
    ],
    "wof:name":"Medeni Bask? San Ve Tic.ltd.sti",
    "wof:placetype":"venue"
},
  "geometry": {"coordinates":[35.3250198364,36.9854202271],"type":"Point"}
}