{
  "type": "Feature",
  "properties": {
    "addr:full":"Bomanti Firin Sk. No:3 Sisli Caglayan Istanbul 07600",
    "addr:postcode":"07600",
    "addr:street":"Firin Sk. No 3 Sisli",
    "iso:country":"TR",
    "sg:address":"Bomanti Firin Sk. No:3 Sisli",
    "sg:city":"Caglayan",
    "sg:classifiers":[
        {
            "category":"Manufacturing",
            "subcategory":"Glass & Minerals",
            "type":"Manufacturing & Wholesale Goods"
        }
    ],
    "sg:phone":"+90 212 246 3830",
    "sg:postcode":"07600",
    "sg:province":"Istanbul",
    "sg:tags":[
        "glassware"
    ],
    "wof:name":"Otomotiv Mam?l. ?r?n. Pazar. Danisma Ltd. Sti.",
    "wof:placetype":"venue"
},
  "geometry": {"coordinates":[28.9813499451,41.0785064697],"type":"Point"}
}