{
  "type": "Feature",
  "properties": {
    "iso:country":"TR",
    "sg:address":"Pak Is Merkezi Prof. Dr.b?ent Tarcan Sok. 5/1 Gayrettepe",
    "sg:city":"Alsancak",
    "sg:classifiers":[
        {
            "category":"Shopping",
            "subcategory":"Pharmacy",
            "type":"Retail Goods"
        }
    ],
    "sg:phone":"+90 212 274 8150",
    "sg:postcode":"35220",
    "sg:province":"Istanbul",
    "sg:tags":[
        "store",
        "drug"
    ],
    "wof:name":"Mustafa Nevzat Ilac San.",
    "wof:placetype":"venue"
},
  "geometry": {"coordinates":[28.9861831665,41.0408554077],"type":"Point"}
}