{
  "type": "Feature",
  "properties": {
    "iso:country":"TR",
    "sg:address":"Cemal Gursel Cad 200/a",
    "sg:city":"Izmir",
    "sg:classifiers":[
        {
            "category":"Banks & Credit Unions",
            "subcategory":"Bank",
            "type":"Services"
        }
    ],
    "sg:phone":"+90 232 368 7784",
    "sg:province":"35600",
    "wof:name":"T?k Dis Ticaret, Bankasi As",
    "wof:placetype":"venue"
},
  "geometry": {"coordinates":[27.119787,38.455357],"type":"Point"}
}