{
  "type": "Feature",
  "properties": {
    "iso:country":"TR",
    "sg:address":"Fevzi Cakmak Cad. No:5 Sefakoy",
    "sg:city":"Isikkent",
    "sg:classifiers":[
        {
            "category":"Shopping",
            "subcategory":"Shoes",
            "type":"Retail Goods"
        }
    ],
    "sg:phone":"+90 212 598 9648",
    "sg:postcode":"32100",
    "sg:province":"Istanbul",
    "wof:name":"Yelkenli Plastik A:s",
    "wof:placetype":"venue"
},
  "geometry": {"coordinates":[28.823336,41.032169],"type":"Point"}
}