{
  "type": "Feature",
  "properties": {
    "addr:full":"Yildiz Posta Cd. Emekli Subay Evleri Gayrettepe \u00c7ankaya Istanbul",
    "addr:street":"Posta Cd. Emekli Subay Evleri",
    "iso:country":"TR",
    "sg:address":"Yildiz Posta Cd. Emekli Subay Evleri Gayrettepe",
    "sg:city":"\u00c7ankaya",
    "sg:classifiers":[
        {
            "category":"Utilities",
            "subcategory":"Electric",
            "type":"Services"
        }
    ],
    "sg:phone":"+90 212 275 7232",
    "sg:province":"Istanbul",
    "sg:tags":[
        "accumulator",
        "-",
        "batery"
    ],
    "wof:name":"Vatan Pazarlama A.s.",
    "wof:placetype":"venue"
},
  "geometry": {"coordinates":[29.006334,41.062099],"type":"Point"}
}