{
  "type": "Feature",
  "properties": {
    "iso:country":"TR",
    "sg:address":"Ankara Karayolu Uzeri Yenice Mah. 128.sok. No:19",
    "sg:city":"Baspinar",
    "sg:classifiers":[
        {
            "category":"Food & Beverages",
            "subcategory":"Candy",
            "type":"Retail Goods"
        }
    ],
    "sg:phone":"+90 272 215 9829",
    "sg:postcode":"07800",
    "sg:province":"Afyon",
    "sg:tags":[
        "biscuit-chocolate-candy"
    ],
    "wof:name":"Deniz Sekerleme San. Ve Tic. Ltd. Sti.",
    "wof:placetype":"venue"
},
  "geometry": {"coordinates":[30.5418,38.755798],"type":"Point"}
}