{
  "type": "Feature",
  "properties": {
    "addr:full":"851. Sk. No:6 Zemin 2 Kurhan Konak Sel?klu Izmir 42060",
    "addr:housenumber":"851;2",
    "addr:postcode":"? klu;42060",
    "addr:street":"Sk. No 6 Zemin",
    "iso:country":"TR",
    "sg:address":"851. Sk. No:6 Zemin 2 Kurhan Konak",
    "sg:city":"Sel?klu",
    "sg:classifiers":[
        {
            "category":"Wholesale",
            "subcategory":"Medical Equipment & Supplies",
            "type":"Manufacturing & Wholesale Goods"
        }
    ],
    "sg:phone":"+90 232 483 8241",
    "sg:postcode":"42060",
    "sg:province":"Izmir",
    "wof:name":"Yigit Tib. Mlz. Ltd. Sti.",
    "wof:placetype":"venue"
},
  "geometry": {"coordinates":[27.1423015594,38.4251480103],"type":"Point"}
}