{
  "type": "Feature",
  "properties": {
    "iso:country":"TR",
    "sg:address":"Beyoglu Kasabasi",
    "sg:city":"Turkoglu",
    "sg:classifiers":[
        {
            "category":"Building & Trades",
            "subcategory":"Landscaping Services",
            "type":"Services"
        }
    ],
    "sg:phone":"+90 344 678 8466",
    "sg:postcode":"46000",
    "sg:province":"Kahramanmaras",
    "sg:tags":[
        "landscape"
    ],
    "wof:name":"Turba Ticaret",
    "wof:placetype":"venue"
},
  "geometry": {"coordinates":[36.9282989502,37.5894012451],"type":"Point"}
}