{
  "type": "Feature",
  "properties": {
    "addr:full":"Palmiye Mah. 1216.sok. Orhanbey Apt.no:4/11 Mersin 0003 I?el",
    "addr:housenumber":"1216.sok;4 / 11;0003 i ?",
    "addr:street":"Palmiye Mah.;Apt.No;Mersin;El",
    "iso:country":"TR",
    "sg:address":"Palmiye Mah. 1216.sok. Orhanbey Apt.no:4/11 Mersin",
    "sg:city":"0003",
    "sg:classifiers":[
        {
            "category":"Banks & Credit Unions",
            "subcategory":"Investment Brokerage",
            "type":"Services"
        }
    ],
    "sg:phone":"+90 324 329 0412",
    "sg:province":"I?el",
    "sg:tags":[
        "-",
        "export",
        "import"
    ],
    "wof:name":"Orka",
    "wof:placetype":"venue"
},
  "geometry": {"coordinates":[29.0630893707,40.1828918457],"type":"Point"}
}