{
  "type": "Feature",
  "properties": {
    "addr:full":"Kazanli Kavsagi Karaca Ilyas Mersin I?el 52750",
    "addr:postcode":"52750",
    "addr:street":"El",
    "iso:country":"TR",
    "sg:address":"Kazanli Kavsagi Karaca Ilyas",
    "sg:city":"Mersin",
    "sg:classifiers":[
        {
            "category":"Manufacturing",
            "subcategory":"Food",
            "type":"Manufacturing & Wholesale Goods"
        }
    ],
    "sg:phone":"+90 324 221 5013",
    "sg:postcode":"52750",
    "sg:province":"I?el",
    "sg:tags":[
        "product",
        "floury",
        "macaroni"
    ],
    "wof:name":"Mersin Un Sanayi Ve Tic.ltd.sti.",
    "wof:placetype":"venue"
},
  "geometry": {"coordinates":[39.1266708374,40.1894416809],"type":"Point"}
}