{
  "type": "Feature",
  "properties": {
    "iso:country":"TR",
    "sg:address":"Hosdere Cad. No:24/5",
    "sg:city":"Y.ayranci",
    "sg:classifiers":[
        {
            "category":"Utilities",
            "subcategory":"Electric",
            "type":"Services"
        }
    ],
    "sg:phone":"+90 31246867903",
    "sg:province":"Ankara",
    "sg:tags":[
        "energy",
        "solar"
    ],
    "wof:name":"Agd",
    "wof:placetype":"venue"
},
  "geometry": {"coordinates":[32.849815,39.903835],"type":"Point"}
}