{
  "type": "Feature",
  "properties": {
    "addr:full":"Savas C. No. 14 Merter Beyazit Istanbul 65400",
    "addr:housenumber":"no. 14",
    "addr:postcode":"65400",
    "iso:country":"TR",
    "sg:address":"Savas C. No. 14 Merter",
    "sg:city":"Beyazit",
    "sg:classifiers":[
        {
            "category":"Shopping",
            "subcategory":"Luggage & Leather Goods",
            "type":"Retail Goods"
        }
    ],
    "sg:phone":"+90 212 557 0621",
    "sg:postcode":"65400",
    "sg:province":"Istanbul",
    "sg:tags":[
        "leather-fur",
        "wear"
    ],
    "wof:name":"Sepici Deri San. Ltd.sti.",
    "wof:placetype":"venue"
},
  "geometry": {"coordinates":[28.874546051,41.0175247192],"type":"Point"}
}