{
  "type": "Feature",
  "properties": {
    "iso:country":"TR",
    "sg:address":"Acibadem Cd. No:115/8 Kadik?",
    "sg:city":"Iskenderun",
    "sg:classifiers":[
        {
            "category":"Mining & Drilling",
            "type":"Manufacturing & Wholesale Goods"
        }
    ],
    "sg:phone":"+90 216 326 1710",
    "sg:postcode":"31200",
    "sg:province":"Istanbul",
    "sg:tags":[
        "industry",
        "mine"
    ],
    "wof:name":"Etiler Madencilik San. Tic. A.s.",
    "wof:placetype":"venue"
},
  "geometry": {"coordinates":[29.0345897675,40.9952774048],"type":"Point"}
}