{
  "type": "Feature",
  "properties": {
    "iso:country":"TR",
    "sg:address":"Tarlabasi Blok Yogur? Faik Sk. No:13 Taksim",
    "sg:city":"?aglayan",
    "sg:classifiers":[
        {
            "category":"Shopping",
            "subcategory":"Stationery & Office Supplies",
            "type":"Retail Goods"
        }
    ],
    "sg:phone":"+90 212 256 4741",
    "sg:province":"Istanbul",
    "wof:name":"G?kt?rk Kirtasiye",
    "wof:placetype":"venue"
},
  "geometry": {"coordinates":[28.975925,41.012379],"type":"Point"}
}