{
  "type": "Feature",
  "properties": {
    "addr:full":"Babalik Mah. Keyhusrev Sok. Ozlen Ishani No:9/6 Iscehisar Konya 03750",
    "addr:housenumber":"6",
    "addr:postcode":"03750",
    "addr:street":"Babalik Mah. Keyhusrev Sok. Ozlen Ishani No 9 /",
    "iso:country":"TR",
    "sg:address":"Babalik Mah. Keyhusrev Sok. Ozlen Ishani No:9/6",
    "sg:city":"Iscehisar",
    "sg:classifiers":[
        {
            "category":"Home & Garden",
            "subcategory":"Building Materials",
            "type":"Retail Goods"
        }
    ],
    "sg:phone":"+90 332322232562",
    "sg:postcode":"03750",
    "sg:province":"Konya",
    "sg:tags":[
        "stone",
        "natural",
        "marble"
    ],
    "wof:name":"Remar Ltd.",
    "wof:placetype":"venue"
},
  "geometry": {"coordinates":[33.0667152405,39.2111282349],"type":"Point"}
}