{
  "type": "Feature",
  "properties": {
    "addr:full":"G?en?ismerk. B Blok K:2 Mersin I?el 52750",
    "addr:housenumber":"blok k 2",
    "addr:postcode":"? el 52750",
    "iso:country":"TR",
    "sg:address":"G?en?ismerk. B Blok K:2",
    "sg:city":"Mersin",
    "sg:classifiers":[
        {
            "category":"Transit Center",
            "subcategory":"Freight",
            "type":"Transportation"
        }
    ],
    "sg:phone":"+90 324 237 5996",
    "sg:postcode":"52750",
    "sg:province":"I?el",
    "wof:name":"Kontras Denizcilik Ltd. Sti.",
    "wof:placetype":"venue"
},
  "geometry": {"coordinates":[35.4317016602,38.9577407837],"type":"Point"}
}