{
  "type": "Feature",
  "properties": {
    "iso:country":"TR",
    "sg:address":"275/8 Sok.no: 17/a",
    "sg:city":"Bornova",
    "sg:classifiers":[
        {
            "category":"Building & Trades",
            "subcategory":"Landscaping Services",
            "type":"Services"
        }
    ],
    "sg:phone":"+90 232 345 0671",
    "sg:postcode":"35040",
    "sg:province":"Izmir",
    "sg:tags":[
        "landscape"
    ],
    "wof:name":"Pro-tek Cevre Sagligi Ve Sistemleri San.tic.ltd.sti.",
    "wof:placetype":"venue"
},
  "geometry": {"coordinates":[27.2210140228,38.4664802551],"type":"Point"}
}