{
  "type": "Feature",
  "properties": {
    "addr:full":"Lamartin Cd. No:11 K:3 Taksim Y?egir Istanbul 01280",
    "addr:housenumber":"no 11 k 3",
    "addr:postcode":"01280",
    "addr:street":"Lamartin Cd.;Y",
    "iso:country":"TR",
    "sg:address":"Lamartin Cd. No:11 K:3 Taksim",
    "sg:city":"Y?egir",
    "sg:classifiers":[
        {
            "category":"Wholesale",
            "subcategory":"Machinery & Supplies",
            "type":"Manufacturing & Wholesale Goods"
        }
    ],
    "sg:phone":"+90 212 238 0126",
    "sg:postcode":"01280",
    "sg:province":"Istanbul",
    "sg:tags":[
        "bearing",
        "ball"
    ],
    "wof:name":"Nsk. Rhp Rulmanlari",
    "wof:placetype":"venue"
},
  "geometry": {"coordinates":[28.985165,41.039009],"type":"Point"}
}