{
  "type": "Feature",
  "properties": {
    "addr:full":"Teoman Pasa Mah. 2226 Sok. No:5 Harbiye Antalya 31080",
    "addr:housenumber":"no 5",
    "addr:postcode":"2226;31080",
    "addr:street":"Teoman Pasa Mah.;Sok.",
    "iso:country":"TR",
    "sg:address":"Teoman Pasa Mah. 2226 Sok. No:5",
    "sg:city":"Harbiye",
    "sg:classifiers":[
        {
            "category":"Professional",
            "subcategory":"Employment Agencies",
            "type":"Services"
        }
    ],
    "sg:phone":"+90 242 339 4470",
    "sg:postcode":"31080",
    "sg:province":"Antalya",
    "sg:tags":[
        "personnel"
    ],
    "wof:name":"Yayla Tur Tasimacilik Ltd.sti.",
    "wof:placetype":"venue"
},
  "geometry": {"coordinates":[30.6899452209,36.9017868042],"type":"Point"}
}