{
  "type": "Feature",
  "properties": {
    "addr:full":"Haskoy Cad. No:2/2 A Haskoy Istanbul 75200",
    "addr:housenumber":"2 a",
    "addr:postcode":"75200",
    "addr:street":"Haskoy Cad. No 2 /",
    "iso:country":"TR",
    "sg:address":"Haskoy Cad. No:2/2 A",
    "sg:city":"Haskoy",
    "sg:classifiers":[
        {
            "category":"Food & Beverages",
            "subcategory":"Candy",
            "type":"Retail Goods"
        }
    ],
    "sg:phone":"+90 212254755556",
    "sg:postcode":"75200",
    "sg:province":"Istanbul",
    "sg:tags":[
        "biscuit-chocolate-candy"
    ],
    "wof:name":"Efes Cikolata Sekerleme Tic.san.a.s.",
    "wof:placetype":"venue"
},
  "geometry": {"coordinates":[28.932758,41.065979],"type":"Point"}
}