{
  "type": "Feature",
  "properties": {
    "iso:country":"TR",
    "sg:address":"A.o.s.b 10007 Sok. No:13 ?igili",
    "sg:city":"Nilufer",
    "sg:classifiers":[
        {
            "category":"Wholesale",
            "subcategory":"Auto Parts",
            "type":"Manufacturing & Wholesale Goods"
        }
    ],
    "sg:phone":"+90 232 328 0255",
    "sg:postcode":"16370",
    "sg:province":"Izmir",
    "sg:tags":[
        "spare"
    ],
    "wof:name":"Sismak Otomotiv Sanayi Ve Ticaret Ltd.",
    "wof:placetype":"venue"
},
  "geometry": {"coordinates":[27.1423015594,38.4251480103],"type":"Point"}
}