{
  "type": "Feature",
  "properties": {
    "addr:full":"Halasgargazi Cad.no:105 Harbiye-sisli Besiktas Istanbul 80200",
    "addr:housenumber":"105",
    "addr:postcode":"80200",
    "addr:street":"Harbiye-Sisli Besiktas",
    "iso:country":"TR",
    "sg:address":"Halasgargazi Cad.no:105 Harbiye-sisli",
    "sg:city":"Besiktas",
    "sg:classifiers":[
        {
            "category":"Communications",
            "subcategory":"Film & Video Production",
            "type":"Services"
        }
    ],
    "sg:phone":"+90 212 296 1525",
    "sg:postcode":"80200",
    "sg:province":"Istanbul",
    "sg:tags":[
        "-"
    ],
    "wof:name":"Digi Print",
    "wof:placetype":"venue"
},
  "geometry": {"coordinates":[28.9870586395,41.0553321838],"type":"Point"}
}