{
  "type": "Feature",
  "properties": {
    "addr:full":"Sivas Karayolu 13 Km. Serdivan Yozgat 54100",
    "addr:housenumber":"13 km.",
    "addr:postcode":"54100",
    "addr:street":"Karayolu;Serdivan Yozgat",
    "iso:country":"TR",
    "sg:address":"Sivas Karayolu 13 Km.",
    "sg:city":"Serdivan",
    "sg:classifiers":[
        {
            "category":"Wholesale",
            "subcategory":"Home Furnishings",
            "type":"Manufacturing & Wholesale Goods"
        }
    ],
    "sg:phone":"+90 354 223 6327",
    "sg:postcode":"54100",
    "sg:province":"Yozgat",
    "sg:tags":[
        "furniture"
    ],
    "wof:name":"Yimpas Mobilya Ti.ve San.a.s.",
    "wof:placetype":"venue"
},
  "geometry": {"coordinates":[34.8360786438,39.8292770386],"type":"Point"}
}