{
  "type": "Feature",
  "properties": {
    "iso:country":"TR",
    "sg:address":"Y.mumcu Dogu Ishani No:9/5",
    "sg:city":"Merkez",
    "sg:classifiers":[
        {
            "category":"Wholesale",
            "subcategory":"Medical Equipment & Supplies",
            "type":"Manufacturing & Wholesale Goods"
        }
    ],
    "sg:phone":"+90 442 235 7110",
    "sg:postcode":"03300",
    "sg:province":"Erzurum",
    "wof:name":"Cem-cen Tibbi Malzeme",
    "wof:placetype":"venue"
},
  "geometry": {"coordinates":[41.2808113098,39.8986663818],"type":"Point"}
}