{
  "type": "Feature",
  "properties": {
    "addr:full":"Bey Koop.2. B?ge Migros Arkasi Koru Sok. Ortahisar Sitesi F Blok Kat.6 Daire.13 Beylikd??/ B?y?k?ekm Beyoglu Istanbul 46810",
    "addr:housenumber":"koop.2 b ?;blok kat.6 daire.13 beylikd ? ? / b ? y ? k ?",
    "addr:postcode":"46810",
    "addr:street":"Koru;Ortahisar Sitesi F;Ekm Beyoglu",
    "iso:country":"TR",
    "sg:address":"Bey Koop.2. B?ge Migros Arkasi Koru Sok. Ortahisar Sitesi F Blok Kat.6 Daire.13 Beylikd??/ B?y?k?ekm",
    "sg:city":"Beyoglu",
    "sg:classifiers":[
        {
            "category":"Building & Trades",
            "subcategory":"Construction",
            "type":"Services"
        }
    ],
    "sg:phone":"+90 212 852 4451",
    "sg:postcode":"46810",
    "sg:province":"Istanbul",
    "sg:tags":[
        "foundation"
    ],
    "wof:name":"Reyhan K?lt?r Vakfi",
    "wof:placetype":"venue"
},
  "geometry": {"coordinates":[28.9759254456,41.0123786926],"type":"Point"}
}