{
  "type": "Feature",
  "properties": {
    "iso:country":"TR",
    "sg:address":"Kemeralti Cad 46",
    "sg:city":"Istanbul",
    "sg:classifiers":[
        {
            "category":"Banks & Credit Unions",
            "subcategory":"Bank",
            "type":"Services"
        }
    ],
    "sg:phone":"+90 12515694",
    "sg:province":"80030",
    "wof:name":"Faysal Islamic Bank Of Bahrain, Dmi Trust Representative Office",
    "wof:placetype":"venue"
},
  "geometry": {"coordinates":[28.976631,41.024578],"type":"Point"}
}