{
  "type": "Feature",
  "properties": {
    "addr:full":"Tarlabasi Cd. No:110/2 Beyoglu Istanbul 46810",
    "addr:housenumber":"no;/ 2",
    "addr:postcode":"46810",
    "addr:street":"Tarlabasi Cd.",
    "iso:country":"TR",
    "sg:address":"Tarlabasi Cd. No:110/2",
    "sg:city":"Beyoglu",
    "sg:classifiers":[
        {
            "category":"Home & Garden",
            "subcategory":"Household Appliances",
            "type":"Retail Goods"
        }
    ],
    "sg:phone":"+90 212 250 1500",
    "sg:postcode":"46810",
    "sg:province":"Istanbul",
    "sg:tags":[
        "conditioner",
        "air"
    ],
    "wof:name":"Delta Sog. Cih. San.",
    "wof:placetype":"venue"
},
  "geometry": {"coordinates":[29.0533714294,41.0530700684],"type":"Point"}
}