{
  "type": "Feature",
  "properties": {
    "iso:country":"TR",
    "sg:address":"Osman Aydin",
    "sg:city":"Ortak?",
    "sg:classifiers":[
        {
            "category":"Government",
            "subcategory":"Office",
            "type":"Public Place"
        }
    ],
    "sg:phone":"+90 256 711 6028",
    "sg:province":"Aydin",
    "sg:tags":[
        "municipality"
    ],
    "wof:name":"?ine Belediye Baskani",
    "wof:placetype":"venue"
},
  "geometry": {"coordinates":[27.8271389008,37.8280143738],"type":"Point"}
}