{
  "type": "Feature",
  "properties": {
    "iso:country":"TR",
    "sg:address":"Levent Caddesi No. 4, 1 Levent, Istanbul",
    "sg:city":"Istanbul",
    "sg:classifiers":[
        {
            "category":"Banks & Credit Unions",
            "subcategory":"Bank",
            "type":"Services"
        }
    ],
    "sg:phone":"+90 212 280 2172",
    "sg:province":"Istanbul",
    "wof:name":"Aktif Finans Factoring",
    "wof:placetype":"venue"
},
  "geometry": {"coordinates":[29.014431,41.077801],"type":"Point"}
}