{
  "type": "Feature",
  "properties": {
    "addr:full":"Kumrular Sk. No:26/2 Yenisehir Beylikduzu Ankara 34520",
    "addr:housenumber":"26 / 2",
    "addr:postcode":"34520",
    "addr:street":"Kumrular Sk. No",
    "iso:country":"TR",
    "sg:address":"Kumrular Sk. No:26/2 Yenisehir",
    "sg:city":"Beylikduzu",
    "sg:orig_category":"General Industrial Products",
    "sg:phone":"+90 312 230 8296",
    "sg:postcode":"34520",
    "sg:province":"Ankara",
    "wof:name":"N?ve San. Malz. Imal. Tic. A.s.",
    "wof:placetype":"venue"
},
  "geometry": {"coordinates":[32.8560333252,39.9438743591],"type":"Point"}
}