{
  "type": "Feature",
  "properties": {
    "addr:full":"Kemer Cesme M Guven Sok. No: 6/a Carsamba Pazari Bursa",
    "addr:housenumber":"no 6 / a",
    "addr:street":"Guven Sok.;Carsamba",
    "iso:country":"TR",
    "sg:address":"Kemer Cesme M Guven Sok. No: 6/a",
    "sg:city":"Carsamba Pazari",
    "sg:classifiers":[
        {
            "category":"Government",
            "subcategory":"Fire Station",
            "type":"Public Place"
        }
    ],
    "sg:phone":"+90 224 250 3987",
    "sg:province":"Bursa",
    "sg:tags":[
        "decoration"
    ],
    "wof:name":"Dekor Kalip",
    "wof:placetype":"venue"
},
  "geometry": {"coordinates":[29.0398807526,40.1076583862],"type":"Point"}
}