{
  "type": "Feature",
  "properties": {
    "iso:country":"TR",
    "sg:address":"Dr. Esat Isik Cad. No. 39 / A Bahariye",
    "sg:city":"Mersin",
    "sg:classifiers":[
        {
            "category":"Personal",
            "subcategory":"Sauna",
            "type":"Services"
        }
    ],
    "sg:phone":"+90 216 346 9938",
    "sg:postcode":"52750",
    "sg:province":"Istanbul",
    "sg:tags":[
        "pool"
    ],
    "wof:name":"Birim Yapi End. Tic. A.s.",
    "wof:placetype":"venue"
},
  "geometry": {"coordinates":[28.975925,41.012379],"type":"Point"}
}