{
  "type": "Feature",
  "properties": {
    "addr:full":"Tarim Mh. Aspendos Bulv. No.3 Pinarbasi Antalya 07630",
    "addr:housenumber":"tarim;no.3 pinarbasi",
    "addr:postcode":"07630",
    "addr:street":"Mh. Aspendos Bulv.",
    "iso:country":"TR",
    "sg:address":"Tarim Mh. Aspendos Bulv. No.3",
    "sg:city":"Pinarbasi",
    "sg:classifiers":[
        {
            "category":"Utilities",
            "subcategory":"Water",
            "type":"Services"
        }
    ],
    "sg:phone":"+90 242 321 7200",
    "sg:postcode":"07630",
    "sg:province":"Antalya",
    "sg:tags":[
        "vegetable",
        "margarine",
        "oil"
    ],
    "wof:name":"Yagpas Yag San. A.s.",
    "wof:placetype":"venue"
},
  "geometry": {"coordinates":[30.7435626984,36.8897323608],"type":"Point"}
}