{
  "type": "Feature",
  "properties": {
    "addr:full":"Ugur Mumcu Cad. No.29 Hadimk? Istanbul",
    "addr:housenumber":"?",
    "addr:street":"Mumcu Cad. No.29 Hadimk",
    "iso:country":"TR",
    "sg:address":"Ugur Mumcu Cad. No.29",
    "sg:city":"Hadimk?",
    "sg:classifiers":[
        {
            "category":"Government",
            "subcategory":"Fire Station",
            "type":"Public Place"
        }
    ],
    "sg:phone":"+90 212771304344",
    "sg:province":"Istanbul",
    "sg:tags":[
        "decoration"
    ],
    "wof:name":"Demo Dekorasyon Mobilya Uretim A.s.",
    "wof:placetype":"venue"
},
  "geometry": {"coordinates":[29.1678657532,40.9384002686],"type":"Point"}
}