{
  "type": "Feature",
  "properties": {
    "iso:country":"TR",
    "sg:address":"Istanbul Cd. 109",
    "sg:city":"Fethiye",
    "sg:orig_category":"Hotels: Motels",
    "sg:phone":"+90 332 351 2958",
    "sg:postcode":"44000",
    "sg:province":"Konya",
    "wof:name":"K?sk Otel",
    "wof:placetype":"venue"
},
  "geometry": {"coordinates":[33.0667152405,39.2111282349],"type":"Point"}
}