{
  "type": "Feature",
  "properties": {
    "iso:country":"TR",
    "sg:address":"Des San Sit 114 Sokak 13 Blok No:7 81260 Dudullu Istanbul",
    "sg:city":"Sariyer",
    "sg:orig_category":"Miscellaneous Products",
    "sg:phone":"+90 216 499 3345",
    "sg:postcode":"33740",
    "sg:province":"Istanbul",
    "wof:name":"Mumak Makina San Ve Tic As",
    "wof:placetype":"venue"
},
  "geometry": {"coordinates":[28.9759254456,41.0123786926],"type":"Point"}
}