{
  "type": "Feature",
  "properties": {
    "iso:country":"TR",
    "sg:address":"Sarikaya Pasaji Cumhuriyet Cad. No:1",
    "sg:city":"Okmeydani",
    "sg:classifiers":[
        {
            "category":"Shopping",
            "subcategory":"Computers & Home Electronics",
            "type":"Retail Goods"
        }
    ],
    "sg:phone":"+90 342 813 4263",
    "sg:postcode":"34385",
    "sg:province":"Kilis",
    "sg:tags":[
        "product",
        "electric-electronic"
    ],
    "wof:name":"Erdogan Ithalat Ihracat",
    "wof:placetype":"venue"
},
  "geometry": {"coordinates":[37.1009635925,36.7219009399],"type":"Point"}
}