{
  "type": "Feature",
  "properties": {
    "iso:country":"TR",
    "sg:address":"Ertem Sk. Nil Apt. K:4 No:9 Gayrettepe",
    "sg:city":"Karak\u00f6y",
    "sg:classifiers":[
        {
            "category":"Manufacturing",
            "subcategory":"Textiles",
            "type":"Manufacturing & Wholesale Goods"
        }
    ],
    "sg:phone":"+90 212 247 4843",
    "sg:postcode":"34110",
    "sg:province":"Istanbul",
    "sg:tags":[
        "fiberglass",
        "polyester"
    ],
    "wof:name":"Ayranci Tic. Ltd. Sti.",
    "wof:placetype":"venue"
},
  "geometry": {"coordinates":[28.9759254456,41.0123786926],"type":"Point"}
}