{
  "type": "Feature",
  "properties": {
    "addr:full":"Ziya G?kalp Caddesi Nurettin Bey Ishani No:6/401 K:4 Kizilay Ankara 23050",
    "addr:housenumber":"?;401 k 4",
    "addr:postcode":"23050",
    "addr:street":"Ziya G;Kalp Caddesi;Ishani No 6 /;Kizilay Ankara",
    "iso:country":"TR",
    "sg:address":"Ziya G?kalp Caddesi Nurettin Bey Ishani No:6/401 K:4",
    "sg:city":"Kizilay",
    "sg:classifiers":[
        {
            "category":"Travel",
            "subcategory":"Travel Agent",
            "type":"Entertainment"
        }
    ],
    "sg:phone":"+90 3124301351729",
    "sg:postcode":"23050",
    "sg:province":"Ankara",
    "sg:tags":[
        "agency",
        "tourism"
    ],
    "wof:name":"Makbul Turizm",
    "wof:placetype":"venue"
},
  "geometry": {"coordinates":[32.8604812622,39.9429283142],"type":"Point"}
}