{
  "type": "Feature",
  "properties": {
    "iso:country":"TR",
    "sg:address":"Demirkapi Cd. No:38 Bayrampasa",
    "sg:city":"Iskenderun",
    "sg:classifiers":[
        {
            "category":"Education",
            "subcategory":"Special Training",
            "type":"Public Place"
        }
    ],
    "sg:phone":"+90 212 612 1370",
    "sg:postcode":"31200",
    "sg:province":"Istanbul",
    "sg:tags":[
        "course"
    ],
    "wof:name":"Maya Dershanesi",
    "wof:placetype":"venue"
},
  "geometry": {"coordinates":[28.9861831665,41.0408554077],"type":"Point"}
}