{
  "type": "Feature",
  "properties": {
    "addr:full":"1203/8 Sok. No:8/a Yenisehir Beyoglu Izmir 80020",
    "addr:housenumber":"1203 / 8;no 8 / a",
    "addr:postcode":"80020",
    "addr:street":"Sok.;Yenisehir Beyoglu",
    "iso:country":"TR",
    "sg:address":"1203/8 Sok. No:8/a Yenisehir",
    "sg:city":"Beyoglu",
    "sg:classifiers":[
        {
            "category":"Building & Trades",
            "subcategory":"Electrical",
            "type":"Services"
        }
    ],
    "sg:phone":"+90 232 469 7180",
    "sg:postcode":"80020",
    "sg:province":"Izmir",
    "sg:tags":[
        "equipment",
        "electric"
    ],
    "wof:name":"Indeks Elektrik Elektronik San.tic. A.s.",
    "wof:placetype":"venue"
},
  "geometry": {"coordinates":[27.1423015594,38.4251480103],"type":"Point"}
}