{
  "type": "Feature",
  "properties": {
    "iso:country":"TR",
    "sg:address":"Cumhuriyet Cd. 21. Sk. No:5/10",
    "sg:city":"Bahcekapi/eminonu",
    "sg:classifiers":[
        {
            "category":"Banks & Credit Unions",
            "subcategory":"Investment Brokerage",
            "type":"Services"
        }
    ],
    "sg:phone":"+90 242 241 8733",
    "sg:postcode":"34100",
    "sg:province":"Antalya",
    "sg:tags":[
        "-",
        "export",
        "import"
    ],
    "wof:name":"Akdeniz Dis Tic. Ltd. Sti.",
    "wof:placetype":"venue"
},
  "geometry": {"coordinates":[30.7092056274,36.8790512085],"type":"Point"}
}