{
  "type": "Feature",
  "properties": {
    "iso:country":"TR",
    "sg:address":"Bankalar Cd. No:40",
    "sg:city":"Karak\u00f6y",
    "sg:classifiers":[
        {
            "category":"Home & Garden",
            "subcategory":"Household Appliances",
            "type":"Retail Goods"
        }
    ],
    "sg:phone":"+90 212 254 0434",
    "sg:province":"Istanbul",
    "sg:tags":[
        "conditioner",
        "air"
    ],
    "wof:name":"Saba Yapi Isi Malz. A.s.",
    "wof:placetype":"venue"
},
  "geometry": {"coordinates":[28.9737052917,41.023891449],"type":"Point"}
}