{
  "type": "Feature",
  "properties": {
    "addr:full":"Denizli Yolu Uzeri Pinar Sut Kars. Ikitelli/K\u00fc\u00e7\u00fck\u00e7ekmece Aydin 34670",
    "addr:housenumber":"uzeri",
    "addr:postcode":"34670",
    "addr:street":"Denizli Yolu;Sut;Aydin",
    "iso:country":"TR",
    "sg:address":"Denizli Yolu Uzeri Pinar Sut Kars.",
    "sg:city":"Ikitelli/K\u00fc\u00e7\u00fck\u00e7ekmece",
    "sg:classifiers":[
        {
            "category":"Retail",
            "subcategory":"Auto Repair",
            "type":"Services"
        }
    ],
    "sg:phone":"+90 256 225 3436",
    "sg:postcode":"34670",
    "sg:province":"Aydin",
    "sg:tags":[
        "maintenance"
    ],
    "wof:name":"Ozusta Karoser",
    "wof:placetype":"venue"
},
  "geometry": {"coordinates":[27.8324394226,37.8409690857],"type":"Point"}
}