{
  "type": "Feature",
  "properties": {
    "iso:country":"TR",
    "sg:address":"129/7 Sok. No:14 Bornova",
    "sg:city":"Merkez",
    "sg:classifiers":[
        {
            "category":"Wholesale",
            "subcategory":"Vending Machines",
            "type":"Manufacturing & Wholesale Goods"
        }
    ],
    "sg:phone":"+90 232 375 5642",
    "sg:postcode":"58070",
    "sg:province":"Izmir",
    "sg:tags":[
        "rod",
        "welding"
    ],
    "wof:name":"Remak Makina Endustri Ve Pazarlama Ltd.sti.",
    "wof:placetype":"venue"
},
  "geometry": {"coordinates":[27.2494106293,38.4622344971],"type":"Point"}
}