{
  "type": "Feature",
  "properties": {
    "addr:full":"Selamet Mah. Dogan Sok. No:17 Gulbahce Talebe Yurdu Karsisi Dudullu Bursa",
    "addr:housenumber":"no 17",
    "addr:street":"Selamet Mah. Dogan Sok.",
    "iso:country":"TR",
    "sg:address":"Selamet Mah. Dogan Sok. No:17 Gulbahce Talebe Yurdu Karsisi",
    "sg:city":"Dudullu",
    "sg:classifiers":[
        {
            "category":"Shopping",
            "subcategory":"Clothing, Apparel, & Fashions",
            "type":"Retail Goods"
        }
    ],
    "sg:phone":"+90 224 250 3161",
    "sg:province":"Bursa",
    "sg:tags":[
        "-",
        "towel",
        "bathrobe"
    ],
    "wof:name":"Toksteks Havlu",
    "wof:placetype":"venue"
},
  "geometry": {"coordinates":[29.0398807526,40.1076583862],"type":"Point"}
}