{
  "type": "Feature",
  "properties": {
    "addr:full":"Fener Mh. Lara Cd. 1959 Sk. 29 Ay Apt. No: 35/7 Lara 38010 Antalya",
    "addr:housenumber":"7",
    "addr:postcode":"38010",
    "addr:street":"Cd. 1959 Sk. 29;No 35 /",
    "iso:country":"TR",
    "sg:address":"Fener Mh. Lara Cd. 1959 Sk. 29 Ay Apt. No: 35/7 Lara",
    "sg:city":"38010",
    "sg:classifiers":[
        {
            "category":"Professional",
            "subcategory":"Computer Services",
            "type":"Services"
        }
    ],
    "sg:phone":"+90 242 323 0120",
    "sg:province":"Antalya",
    "sg:tags":[
        "application",
        "software"
    ],
    "wof:name":"C.a.p.i. Bilgisayar Program Ltd. Sti.",
    "wof:placetype":"venue"
},
  "geometry": {"coordinates":[30.7091999054,36.8790512085],"type":"Point"}
}