{
  "type": "Feature",
  "properties": {
    "iso:country":"TR",
    "sg:address":"Belediye Arsalari Civari Yesil Tome Mevkii",
    "sg:city":"Gole",
    "sg:classifiers":[
        {
            "category":"Farming",
            "subcategory":"Livestock Farm",
            "type":"Manufacturing & Wholesale Goods"
        }
    ],
    "sg:phone":"+90 382 213 1419",
    "sg:postcode":"75700",
    "sg:province":"Aksaray",
    "sg:tags":[
        "fattening-breeding"
    ],
    "wof:name":"Gungor Besicilik",
    "wof:placetype":"venue"
},
  "geometry": {"coordinates":[34.0284004211,38.3745994568],"type":"Point"}
}