{
  "type": "Feature",
  "properties": {
    "addr:full":"Ugurmumcu Cad. No:79/2 G.o.p. Ankara",
    "addr:housenumber":"79 / 2",
    "addr:street":"Ugurmumcu Cad. No;G.O.P.",
    "iso:country":"TR",
    "sg:address":"Ugurmumcu Cad. No:79/2",
    "sg:city":"G.o.p.",
    "sg:classifiers":[
        {
            "category":"Professional",
            "type":"Services"
        }
    ],
    "sg:phone":"+90 312 447 5780",
    "sg:province":"Ankara",
    "sg:tags":[
        "catering"
    ],
    "wof:name":"S.t. Catering & Organisation",
    "wof:placetype":"venue"
},
  "geometry": {"coordinates":[32.8604812622,39.9429283142],"type":"Point"}
}