{
  "type": "Feature",
  "properties": {
    "iso:country":"TR",
    "sg:address":"Pertevpasa Sk Malatya Ishani Carsikapi No:8/19-20 34450 Eminonu Istanbul",
    "sg:city":"Emin\u00f6n\u00fc/Ca\u011falo\u011flu",
    "sg:classifiers":[
        {
            "category":"Personal",
            "subcategory":"Shoe Repair & Shine",
            "type":"Services"
        }
    ],
    "sg:phone":"+90 212 516 3545",
    "sg:postcode":"34245",
    "sg:province":"Istanbul",
    "sg:tags":[
        "leather"
    ],
    "wof:name":"Turital Turlu Iskarpin Taban",
    "wof:placetype":"venue"
},
  "geometry": {"coordinates":[28.9128303528,41.0602035522],"type":"Point"}
}