{
  "type": "Feature",
  "properties": {
    "addr:full":"Akg?ercin Sk. No.1 K??yali \u00c7orlu Istanbul",
    "addr:housenumber":"k ? ?",
    "addr:street":"Ercin Sk. No.1",
    "iso:country":"TR",
    "sg:address":"Akg?ercin Sk. No.1 K??yali",
    "sg:city":"\u00c7orlu",
    "sg:classifiers":[
        {
            "category":"Shopping",
            "subcategory":"Luggage & Leather Goods",
            "type":"Retail Goods"
        }
    ],
    "sg:phone":"+90 212 501 4696",
    "sg:province":"Istanbul",
    "sg:tags":[
        "leather-fur",
        "wear"
    ],
    "wof:name":"Akderi Ith.ihr.ltd.sti.",
    "wof:placetype":"venue"
},
  "geometry": {"coordinates":[29.1307792664,40.9203033447],"type":"Point"}
}