{
  "type": "Feature",
  "properties": {
    "addr:full":"Sultan Mektebi Sok. Sultan Han No:23/67 Yesildirek Istanbul 63200",
    "addr:housenumber":"23 / 67",
    "addr:postcode":"63200",
    "addr:street":"Sultan Mektebi Sok. Sultan Han No;Istanbul",
    "iso:country":"TR",
    "sg:address":"Sultan Mektebi Sok. Sultan Han No:23/67",
    "sg:city":"Yesildirek",
    "sg:classifiers":[
        {
            "category":"Manufacturing",
            "subcategory":"Textiles",
            "type":"Manufacturing & Wholesale Goods"
        }
    ],
    "sg:phone":"+90 212 511 9754",
    "sg:postcode":"63200",
    "sg:province":"Istanbul",
    "sg:tags":[
        "weaving",
        "narrow",
        "-",
        "label"
    ],
    "wof:name":"Cilgin Etiket Ve Fiyonk Sanayi",
    "wof:placetype":"venue"
},
  "geometry": {"coordinates":[28.9861831665,41.0408554077],"type":"Point"}
}