{
  "type": "Feature",
  "properties": {
    "iso:country":"TR",
    "sg:address":"Firin Sk. No:5-c Tesvikiye",
    "sg:city":"Ikitelli/K\u00fc\u00e7\u00fck\u00e7ekmece",
    "sg:orig_category":"Aluminium Carpentary",
    "sg:phone":"+90 212 233 4060",
    "sg:postcode":"34670",
    "sg:province":"Istanbul",
    "wof:name":"Yeni Degisim Ltd. Sti.",
    "wof:placetype":"venue"
},
  "geometry": {"coordinates":[28.9962062836,41.0489959717],"type":"Point"}
}