{
  "type": "Feature",
  "properties": {
    "iso:country":"TR",
    "sg:address":"Anafartalar Cad. No.45",
    "sg:city":"Ulus",
    "sg:classifiers":[
        {
            "category":"Banks & Credit Unions",
            "subcategory":"Financial Services",
            "type":"Services"
        }
    ],
    "sg:phone":"+90 312 311 6665",
    "sg:postcode":"01940",
    "sg:province":"Ankara",
    "sg:tags":[
        "finance"
    ],
    "wof:name":"Merkez Yatirim Menkul Kiymetler",
    "wof:placetype":"venue"
},
  "geometry": {"coordinates":[32.8591766357,39.9382324219],"type":"Point"}
}