{
  "type": "Feature",
  "properties": {
    "addr:full":"Cumhuriyet Mah. Kartal Cd. No:31 Yakacik-kartal Osmanbey Istanbul 63000",
    "addr:housenumber":"no 31",
    "addr:postcode":"63000",
    "addr:street":"Cumhuriyet Mah. Kartal Cd.",
    "iso:country":"TR",
    "sg:address":"Cumhuriyet Mah. Kartal Cd. No:31 Yakacik-kartal",
    "sg:city":"Osmanbey",
    "sg:classifiers":[
        {
            "category":"Home & Garden",
            "subcategory":"Home Furnishings",
            "type":"Retail Goods"
        }
    ],
    "sg:phone":"+90 216 309 5410",
    "sg:postcode":"63000",
    "sg:province":"Istanbul",
    "sg:tags":[
        "quilt",
        "bed"
    ],
    "wof:name":"Yatas Istanbul Paz. A.s.",
    "wof:placetype":"venue"
},
  "geometry": {"coordinates":[29.21826,40.91354],"type":"Point"}
}