{
  "type": "Feature",
  "properties": {
    "iso:country":"TR",
    "sg:address":"Ornek Sanayi Sitesi 6.cad. No: 13",
    "sg:city":"Karak\u00f6y",
    "sg:classifiers":[
        {
            "category":"Manufacturing",
            "subcategory":"Textiles",
            "type":"Manufacturing & Wholesale Goods"
        }
    ],
    "sg:phone":"+90 342 235 1144",
    "sg:postcode":"34110",
    "sg:province":"Gaziantep",
    "sg:tags":[
        "fiberglass",
        "polyester"
    ],
    "wof:name":"Fibersan Fiberglas Sanayi Ve Tic.a.s.",
    "wof:placetype":"venue"
},
  "geometry": {"coordinates":[37.3761024475,37.0629463196],"type":"Point"}
}