{
  "type": "Feature",
  "properties": {
    "addr:full":"Cumhuriyet Bulvari No:191/2 0003 Izmir",
    "addr:housenumber":"no;/ 2",
    "addr:postcode":"0003",
    "addr:street":"Cumhuriyet Bulvari",
    "iso:country":"TR",
    "sg:address":"Cumhuriyet Bulvari No:191/2",
    "sg:city":"0003",
    "sg:classifiers":[
        {
            "category":"Banks & Credit Unions",
            "subcategory":"Investment Brokerage",
            "type":"Services"
        }
    ],
    "sg:phone":"+90 232 421 1425",
    "sg:province":"Izmir",
    "sg:tags":[
        "-",
        "export",
        "import"
    ],
    "wof:name":"Orpeks Dis Tic. Ltd. Sti.",
    "wof:placetype":"venue"
},
  "geometry": {"coordinates":[27.1423015594,38.4251480103],"type":"Point"}
}