{
  "type": "Feature",
  "properties": {
    "addr:full":"Mudanya Cd. No:10 Kizilay Bursa 06640",
    "addr:housenumber":"no 10",
    "addr:postcode":"06640",
    "addr:street":"Mudanya Cd.;Bursa",
    "iso:country":"TR",
    "sg:address":"Mudanya Cd. No:10",
    "sg:city":"Kizilay",
    "sg:classifiers":[
        {
            "category":"Building & Trades",
            "subcategory":"Plumbing",
            "type":"Services"
        }
    ],
    "sg:phone":"+90 224 235 1196",
    "sg:postcode":"06640",
    "sg:province":"Bursa",
    "wof:name":"Geylani Sihhi Tesis. Malz. Tic. A.s.",
    "wof:placetype":"venue"
},
  "geometry": {"coordinates":[29.0430011749,40.1990394592],"type":"Point"}
}