{
  "type": "Feature",
  "properties": {
    "addr:full":"Rihtim Cad. No:2 Kadikoy Mecidiyek\u00f6y Istanbul 34387",
    "addr:postcode":"34387",
    "addr:street":"Rihtim Cad. No 2 Kadikoy",
    "iso:country":"TR",
    "sg:address":"Rihtim Cad. No:2 Kadikoy",
    "sg:city":"Mecidiyek\u00f6y",
    "sg:classifiers":[
        {
            "category":"Professional",
            "subcategory":"Detective & Security Services",
            "type":"Services"
        }
    ],
    "sg:phone":"+90 216 348 2424",
    "sg:postcode":"34387",
    "sg:province":"Istanbul",
    "sg:tags":[
        "material"
    ],
    "wof:name":"Kotter Guvenlik A.s.",
    "wof:placetype":"venue"
},
  "geometry": {"coordinates":[29.127367,40.922428],"type":"Point"}
}