{
  "type": "Feature",
  "properties": {
    "iso:country":"TR",
    "sg:address":"Okcumusa Cad. Kismet Han No:94 K:4-5 Karak?",
    "sg:city":"1.sanayi Sitesi",
    "sg:classifiers":[
        {
            "category":"Wholesale",
            "subcategory":"Vending Machines",
            "type":"Manufacturing & Wholesale Goods"
        }
    ],
    "sg:phone":"+90 212 235 9900",
    "sg:postcode":"35110",
    "sg:province":"Istanbul",
    "sg:tags":[
        "rod",
        "welding"
    ],
    "wof:name":"Erbak Elektrolitik Bakir Sanayi Tic.a.s.",
    "wof:placetype":"venue"
},
  "geometry": {"coordinates":[28.9759254456,41.0123786926],"type":"Point"}
}