{
  "type": "Feature",
  "properties": {
    "iso:country":"TR",
    "sg:address":"Hoca A. Yesevi Cd. Yesiltepe Mh. 75/1 Sk. No:1 Zeytinburnu",
    "sg:city":"Kartal",
    "sg:classifiers":[
        {
            "category":"Freight",
            "type":"Transportation"
        }
    ],
    "sg:phone":"+90 212 665 0065",
    "sg:postcode":"34876",
    "sg:province":"Istanbul",
    "sg:tags":[
        "packing",
        "industry"
    ],
    "wof:name":"Deniz Kagit?ilik Ve Ambalaj",
    "wof:placetype":"venue"
},
  "geometry": {"coordinates":[28.9021072388,40.9942169189],"type":"Point"}
}