{
  "type": "Feature",
  "properties": {
    "addr:full":"Kantarcilar Cad. No:20 Eminonu Sel?klu Istanbul 42100",
    "addr:housenumber":"20;?",
    "addr:postcode":"42100",
    "addr:street":"Kantarcilar Cad. No;Eminonu Sel",
    "iso:country":"TR",
    "sg:address":"Kantarcilar Cad. No:20 Eminonu",
    "sg:city":"Sel?klu",
    "sg:classifiers":[
        {
            "category":"Utilities",
            "subcategory":"Recycling",
            "type":"Services"
        }
    ],
    "sg:phone":"+90 212 528 3659",
    "sg:postcode":"42100",
    "sg:province":"Istanbul",
    "sg:tags":[
        "measuring",
        "weighing"
    ],
    "wof:name":"Demir?z Tarti Aletler Ltd.sti.",
    "wof:placetype":"venue"
},
  "geometry": {"coordinates":[28.9861831665,41.0408554077],"type":"Point"}
}