{
  "type": "Feature",
  "properties": {
    "addr:full":"Alkop San Sit C 3 Blok No: 5-6 B.?ekmece Hadimk? Istanbul 34500",
    "addr:housenumber":"blok no 5-6 b. ?;?",
    "addr:postcode":"34500",
    "addr:street":"Alkop;3;Ekmece Hadimk",
    "iso:country":"TR",
    "sg:address":"Alkop San Sit C 3 Blok No: 5-6 B.?ekmece",
    "sg:city":"Hadimk?",
    "sg:orig_category":"Plastic Toy",
    "sg:phone":"+90 212 858 1190",
    "sg:postcode":"34500",
    "sg:province":"Istanbul",
    "wof:name":"Akay Plastik Amb San Ltd Sti",
    "wof:placetype":"venue"
},
  "geometry": {"coordinates":[28.9759254456,41.0123786926],"type":"Point"}
}