{
  "type": "Feature",
  "properties": {
    "addr:full":"R?garli Sk. Eser Han No:14/9 Ulus Tuzla Ankara 81700",
    "addr:housenumber":"14 / 9",
    "addr:postcode":"81700",
    "addr:street":"Garli Sk.;Han No;Ulus",
    "iso:country":"TR",
    "sg:address":"R?garli Sk. Eser Han No:14/9 Ulus",
    "sg:city":"Tuzla",
    "sg:classifiers":[
        {
            "category":"Building & Trades",
            "subcategory":"Plumbing",
            "type":"Services"
        }
    ],
    "sg:phone":"+90 312 311 7005",
    "sg:postcode":"81700",
    "sg:province":"Ankara",
    "wof:name":"Demir Tesisat Taahh?t Tic. Ltd. Sti.",
    "wof:placetype":"venue"
},
  "geometry": {"coordinates":[32.8560333252,39.9438743591],"type":"Point"}
}