{
  "type": "Feature",
  "properties": {
    "addr:full":"Dar?afaka Cd. Safa Apt. No:67 D:4 Fatih B.?ekmece Istanbul 34",
    "addr:housenumber":"67 d 4;?",
    "addr:street":"Afaka Cd. Safa Apt. No;Fatih B.",
    "iso:country":"TR",
    "sg:address":"Dar?afaka Cd. Safa Apt. No:67 D:4 Fatih",
    "sg:city":"B.?ekmece",
    "sg:classifiers":[
        {
            "category":"Organizations",
            "subcategory":"Community Association",
            "type":"Services"
        }
    ],
    "sg:phone":"+90 212 533 4946",
    "sg:postcode":"34",
    "sg:province":"Istanbul",
    "sg:tags":[
        "civil",
        "initiative"
    ],
    "wof:name":"Aileyi Korumada Medya Dest.",
    "wof:placetype":"venue"
},
  "geometry": {"coordinates":[28.9861831665,41.0408554077],"type":"Point"}
}