{
  "type": "Feature",
  "properties": {
    "addr:full":"42ao Gardenya 2 Plaza Kat: 2 Atasehir Istanbul 34758",
    "addr:housenumber":"2;2",
    "addr:postcode":"34758",
    "addr:street":"Gardenya;Plaza Kat",
    "iso:country":"TR",
    "sg:address":"42ao Gardenya 2 Plaza Kat: 2",
    "sg:city":"Atasehir",
    "sg:classifiers":[
        {
            "category":"Food & Beverages",
            "subcategory":"Groceries & Convenience Stores",
            "type":"Retail Goods"
        }
    ],
    "sg:phone":"+90 216 388 8224",
    "sg:postcode":"34758",
    "sg:province":"Istanbul",
    "sg:tags":[
        "ready"
    ],
    "wof:name":"Atg Makina Ve M?hendislik San. Ve Tic. Ltd. Sti.",
    "wof:placetype":"venue"
},
  "geometry": {"coordinates":[28.9759254456,41.0123786926],"type":"Point"}
}