{
  "type": "Feature",
  "properties": {
    "addr:full":"Tahtakale Cad.aktar Han.no:13 Eminonu Merkez Istanbul 80000",
    "addr:housenumber":"13",
    "addr:postcode":"80000",
    "addr:street":"Han.No",
    "iso:country":"TR",
    "sg:address":"Tahtakale Cad.aktar Han.no:13 Eminonu",
    "sg:city":"Merkez",
    "sg:classifiers":[
        {
            "category":"Manufacturing",
            "subcategory":"Building Materials",
            "type":"Manufacturing & Wholesale Goods"
        }
    ],
    "sg:phone":"+90 212 511 6677",
    "sg:postcode":"80000",
    "sg:province":"Istanbul",
    "sg:tags":[
        "promotional"
    ],
    "wof:name":"Sahin Pipo",
    "wof:placetype":"venue"
},
  "geometry": {"coordinates":[28.9759254456,41.0123786926],"type":"Point"}
}