{
  "type": "Feature",
  "properties": {
    "addr:full":"B.dere Cd. Oya Sk. No:109 Gayrettepe Istanbul 34349",
    "addr:housenumber":"109",
    "addr:postcode":"34349",
    "addr:street":"B.Dere Cd.;Sk. No",
    "iso:country":"TR",
    "sg:address":"B.dere Cd. Oya Sk. No:109",
    "sg:city":"Gayrettepe",
    "sg:classifiers":[
        {
            "category":"Airport",
            "subcategory":"International",
            "type":"Transportation"
        }
    ],
    "sg:phone":"+90 212 273 1540",
    "sg:postcode":"34349",
    "sg:province":"Istanbul",
    "wof:name":"Besa Trans Nakliyat Tic.",
    "wof:placetype":"venue"
},
  "geometry": {"coordinates":[29.1659507751,41.0045700073],"type":"Point"}
}