{
  "type": "Feature",
  "properties": {
    "iso:country":"TR",
    "sg:address":"Ikitelli Organize Sanayi B?gesi Metal-is Sanayi Sitesi 15.blok No:14-16-18",
    "sg:city":"Ikitelli/K\u00fc\u00e7\u00fck\u00e7ekmece",
    "sg:orig_category":"Ikitelli Metal-is Ind.site",
    "sg:phone":"+90 212671139596",
    "sg:postcode":"34660",
    "sg:province":"Istanbul",
    "sg:website":"kinaykalip.com",
    "wof:name":"Kinay Kalip Sanayi Ve ?ember Toka Imalati",
    "wof:placetype":"venue"
},
  "geometry": {"coordinates":[28.9086933136,41.0490837097],"type":"Point"}
}