{
  "type": "Feature",
  "properties": {
    "iso:country":"TR",
    "sg:address":"Esenboga Yolu Sirin Apt. No:27/c",
    "sg:city":"Pursaklar",
    "sg:classifiers":[
        {
            "category":"Home & Garden",
            "subcategory":"Building Materials",
            "type":"Retail Goods"
        }
    ],
    "sg:phone":"+90 312 328 2283",
    "sg:postcode":"06145",
    "sg:province":"Ankara",
    "sg:tags":[
        "window",
        "door"
    ],
    "wof:name":"Imamogullari Pvc Aluminyum Ins.nakl.petrl.urn.hayv.gida San.tic.ltd.sti.",
    "wof:placetype":"venue"
},
  "geometry": {"coordinates":[32.8604812622,39.9429283142],"type":"Point"}
}