{
  "type": "Feature",
  "properties": {
    "iso:country":"TR",
    "sg:address":"Turgut Ozal Bulvari No:96 /",
    "sg:city":"Iskitler",
    "sg:classifiers":[
        {
            "category":"Home & Garden",
            "subcategory":"Building Materials",
            "type":"Retail Goods"
        }
    ],
    "sg:phone":"+90 312 384 3097",
    "sg:postcode":"06070",
    "sg:province":"Ankara",
    "sg:tags":[
        "plaster",
        "cement-concrete"
    ],
    "wof:name":"Ali Riza Onat Ins. Taah. Tic. San. Ltd. Sti.",
    "wof:placetype":"venue"
},
  "geometry": {"coordinates":[32.8464851379,39.9564590454],"type":"Point"}
}