{
  "type": "Feature",
  "properties": {
    "iso:country":"TR",
    "sg:address":"Merkez Mh. 5/1 Sk. No: 14",
    "sg:city":"Bagcilar",
    "sg:classifiers":[
        {
            "category":"Shopping",
            "subcategory":"Baby Store",
            "type":"Retail Goods"
        }
    ],
    "sg:phone":"+90 2126106910111",
    "sg:postcode":"33115",
    "sg:province":"Istanbul",
    "sg:tags":[
        "wear"
    ],
    "wof:name":"?zsah Konfeksiyon Ltd. Sti.",
    "wof:placetype":"venue"
},
  "geometry": {"coordinates":[28.843315,40.994591],"type":"Point"}
}