{
  "type": "Feature",
  "properties": {
    "addr:full":"Istiklal Cad. Zambak Sk. No: 21/4 Beyoglu Istanbul 46810",
    "addr:housenumber":"21 / 4",
    "addr:postcode":"46810",
    "addr:street":"Istiklal Cad. Zambak Sk. No",
    "iso:country":"TR",
    "sg:address":"Istiklal Cad. Zambak Sk. No: 21/4",
    "sg:city":"Beyoglu",
    "sg:classifiers":[
        {
            "category":"Building & Trades",
            "subcategory":"Landscaping Services",
            "type":"Services"
        }
    ],
    "sg:phone":"+90 212 292 3986",
    "sg:postcode":"46810",
    "sg:province":"Istanbul",
    "sg:tags":[
        "landscape"
    ],
    "wof:name":"Abelya Turizm Ticaret Ve Sanayi Ltd. Sti.",
    "wof:placetype":"venue"
},
  "geometry": {"coordinates":[28.8335361481,41.0013885498],"type":"Point"}
}