{
  "type": "Feature",
  "properties": {
    "iso:country":"TR",
    "sg:address":"Yeni Yalova Yolu 13.km. (karadeniz Avize Yolu) P.k.13",
    "sg:city":"Ovaakca",
    "sg:classifiers":[
        {
            "category":"Professional",
            "type":"Services"
        }
    ],
    "sg:phone":"+90 224 267 1313",
    "sg:postcode":"16335",
    "sg:province":"Bursa",
    "sg:tags":[
        "catering"
    ],
    "wof:name":"Hacibey Kebapcisi",
    "wof:placetype":"venue"
},
  "geometry": {"coordinates":[29.0586109161,40.1844291687],"type":"Point"}
}