{
  "type": "Feature",
  "properties": {
    "addr:full":"Haci Mansur Sk. Ismail Ceylan Apt. No:76/7 Osmanbey Istanbul 63000",
    "addr:postcode":"63000",
    "addr:street":"Sk. Ismail",
    "iso:country":"TR",
    "sg:address":"Haci Mansur Sk. Ismail Ceylan Apt. No:76/7",
    "sg:city":"Osmanbey",
    "sg:classifiers":[
        {
            "category":"Shopping",
            "subcategory":"Clothing, Apparel, & Fashions",
            "type":"Retail Goods"
        }
    ],
    "sg:phone":"+90 212240525522",
    "sg:postcode":"63000",
    "sg:province":"Istanbul",
    "sg:tags":[
        "men",
        "wear"
    ],
    "wof:name":"Ilbay Teks. San. Tic.",
    "wof:placetype":"venue"
},
  "geometry": {"coordinates":[28.9759254456,41.0123786926],"type":"Point"}
}