{
  "type": "Feature",
  "properties": {
    "iso:country":"TR",
    "sg:address":"Kizilelma Cd. No:50",
    "sg:city":"Findikzade",
    "sg:classifiers":[
        {
            "category":"Shopping",
            "subcategory":"Florist",
            "type":"Retail Goods"
        }
    ],
    "sg:phone":"+90 212 588 0116",
    "sg:province":"Istanbul",
    "sg:tags":[
        "flower"
    ],
    "wof:name":"Og?n ?i?ek?ilik",
    "wof:placetype":"venue"
},
  "geometry": {"coordinates":[28.9372997284,41.008644104],"type":"Point"}
}