{
  "type": "Feature",
  "properties": {
    "addr:full":"Ardic Sk.no:24 Merter Istanbul",
    "addr:housenumber":"24",
    "addr:street":"Merter",
    "iso:country":"TR",
    "sg:address":"Ardic Sk.no:24",
    "sg:city":"Merter",
    "sg:classifiers":[
        {
            "category":"Shopping",
            "subcategory":"Crafts & Fabrics",
            "type":"Retail Goods"
        }
    ],
    "sg:phone":"+90 212 637 0514",
    "sg:province":"Istanbul",
    "sg:tags":[
        "knitting"
    ],
    "wof:name":"Cetinkaya Mensucat A.s",
    "wof:placetype":"venue"
},
  "geometry": {"coordinates":[28.5473651886,41.0350112915],"type":"Point"}
}