{
  "type": "Feature",
  "properties": {
    "iso:country":"TR",
    "sg:address":"Cemil B. Cd. No:2 Sisli",
    "sg:city":"\u00dcmraniye",
    "sg:classifiers":[
        {
            "category":"Wholesale",
            "subcategory":"Home Furnishings",
            "type":"Manufacturing & Wholesale Goods"
        }
    ],
    "sg:phone":"+90 212 224 2443",
    "sg:province":"Istanbul",
    "sg:tags":[
        "furniture"
    ],
    "wof:name":"Funda Mobilya",
    "wof:placetype":"venue"
},
  "geometry": {"coordinates":[28.9891490936,41.0614891052],"type":"Point"}
}