{
  "type": "Feature",
  "properties": {
    "addr:full":"Ataturk Cad. No: 378/1 Soyhan Kat: 4 Alsancak Izmir 01365",
    "addr:housenumber":"378 / 1;4",
    "addr:postcode":"01365",
    "addr:street":"Ataturk Cad. No;Soyhan Kat",
    "iso:country":"TR",
    "sg:address":"Ataturk Cad. No: 378/1 Soyhan Kat: 4",
    "sg:city":"Alsancak",
    "sg:classifiers":[
        {
            "category":"Farming",
            "subcategory":"Poultry Farm",
            "type":"Manufacturing & Wholesale Goods"
        }
    ],
    "sg:phone":"+90 232 421 6627",
    "sg:postcode":"01365",
    "sg:province":"Izmir",
    "sg:tags":[
        "poultry-turkey-ostrich"
    ],
    "wof:name":"Sec Tavukculuk San. Tic. A.s.",
    "wof:placetype":"venue"
},
  "geometry": {"coordinates":[27.1296863556,38.4186973572],"type":"Point"}
}