{
  "type": "Feature",
  "properties": {
    "iso:country":"TR",
    "sg:address":"Ismet Pasa Mah. Haciveli Camii Cad. Kizica Oba Sok. No:57",
    "sg:city":"Konak",
    "sg:classifiers":[
        {
            "category":"Shopping",
            "subcategory":"Baby Store",
            "type":"Retail Goods"
        }
    ],
    "sg:phone":"+90 342 220 5261",
    "sg:postcode":"35130",
    "sg:province":"Gaziantep",
    "sg:tags":[
        "wear"
    ],
    "wof:name":"Gulbebe Orme Tekstil San.tic. Ltd.sti.",
    "wof:placetype":"venue"
},
  "geometry": {"coordinates":[37.376102,37.062946],"type":"Point"}
}