{
  "type": "Feature",
  "properties": {
    "iso:country":"TR",
    "sg:address":"Savas Mah. 44 Sok Dal Ishani Zemin Kat No: 2",
    "sg:city":"Iskenderun",
    "sg:classifiers":[
        {
            "category":"Travel",
            "subcategory":"Travel Agent",
            "type":"Entertainment"
        }
    ],
    "sg:phone":"+90 326 613 3622",
    "sg:postcode":"31200",
    "sg:province":"Hatay",
    "sg:tags":[
        "agency",
        "tourism"
    ],
    "wof:name":"T?re Turizm",
    "wof:placetype":"venue"
},
  "geometry": {"coordinates":[36.2422409058,36.5966186523],"type":"Point"}
}