{
  "type": "Feature",
  "properties": {
    "iso:country":"TR",
    "sg:address":"Hurriyet Cad. No:161 Izmit",
    "sg:city":"\u00c7ankaya",
    "sg:classifiers":[
        {
            "category":"Professional",
            "subcategory":"Computer Services",
            "type":"Services"
        }
    ],
    "sg:phone":"+90 262 323 4034",
    "sg:province":"Kocaeli",
    "sg:tags":[
        "application",
        "software"
    ],
    "wof:name":"Elber Ltd.",
    "wof:placetype":"venue"
},
  "geometry": {"coordinates":[29.9345798492,40.7669487],"type":"Point"}
}