{
  "type": "Feature",
  "properties": {
    "addr:full":"Izzetpasa Mh. Yeniyol Sk. No:44 Sisli Edremit Istanbul 04500",
    "addr:housenumber":"44",
    "addr:postcode":"04500",
    "addr:street":"Izzetpasa Mh. Yeniyol Sk. No",
    "iso:country":"TR",
    "sg:address":"Izzetpasa Mh. Yeniyol Sk. No:44 Sisli",
    "sg:city":"Edremit",
    "sg:classifiers":[
        {
            "category":"Home & Garden",
            "subcategory":"Household Appliances",
            "type":"Retail Goods"
        }
    ],
    "sg:phone":"+90 212 224 5046",
    "sg:postcode":"04500",
    "sg:province":"Istanbul",
    "sg:tags":[
        "utensil",
        "electrical"
    ],
    "wof:name":"D?ndar Tic. Mobilya Day. T?k. Mal. San.",
    "wof:placetype":"venue"
},
  "geometry": {"coordinates":[28.9861831665,41.0408554077],"type":"Point"}
}