{
  "type": "Feature",
  "properties": {
    "addr:full":"Rasimpasa Mah. Elmalicesme Sok. Hurriyet Apt. No: 23/3 Kadikoy Besiktas Istanbul 75200",
    "addr:housenumber":"23 / 3",
    "addr:postcode":"75200",
    "addr:street":"Rasimpasa Mah. Elmalicesme Sok. Hurriyet Apt. No;Kadikoy Besiktas",
    "iso:country":"TR",
    "sg:address":"Rasimpasa Mah. Elmalicesme Sok. Hurriyet Apt. No: 23/3 Kadikoy",
    "sg:city":"Besiktas",
    "sg:classifiers":[
        {
            "category":"Professional",
            "subcategory":"Business Services",
            "type":"Services"
        }
    ],
    "sg:phone":"+90 216 348 7807",
    "sg:postcode":"75200",
    "sg:province":"Istanbul",
    "wof:name":"Efe Organizasyon",
    "wof:placetype":"venue"
},
  "geometry": {"coordinates":[28.9759254456,41.0123786926],"type":"Point"}
}