{
  "type": "Feature",
  "properties": {
    "addr:full":"Gozdagi Cad.uzum Sok. No:5 Dolayaba Pendik Mersin Istanbul 52750",
    "addr:housenumber":"no 5",
    "addr:postcode":"52750",
    "addr:street":"Cad.Uzum Sok.;Dolayaba",
    "iso:country":"TR",
    "sg:address":"Gozdagi Cad.uzum Sok. No:5 Dolayaba Pendik",
    "sg:city":"Mersin",
    "sg:classifiers":[
        {
            "category":"Wholesale",
            "subcategory":"Auto Parts",
            "type":"Manufacturing & Wholesale Goods"
        }
    ],
    "sg:phone":"+90 216 379 4950",
    "sg:postcode":"52750",
    "sg:province":"Istanbul",
    "sg:tags":[
        "spare"
    ],
    "wof:name":"Makersan Otomotiv Co.ltd.",
    "wof:placetype":"venue"
},
  "geometry": {"coordinates":[28.9861831665,41.0408554077],"type":"Point"}
}