{
  "type": "Feature",
  "properties": {
    "addr:full":"Esat Cd. No:45 K??esat Kutlukent Ankara 06300",
    "addr:housenumber":"k ? ?",
    "addr:postcode":"06300",
    "iso:country":"TR",
    "sg:address":"Esat Cd. No:45 K??esat",
    "sg:city":"Kutlukent",
    "sg:classifiers":[
        {
            "category":"Professional",
            "subcategory":"Business Services",
            "type":"Services"
        }
    ],
    "sg:phone":"+90 312 419 5345",
    "sg:postcode":"06300",
    "sg:province":"Ankara",
    "sg:tags":[
        "industry",
        "casting"
    ],
    "wof:name":"Sivas Demir ?elik Islet. A.s.",
    "wof:placetype":"venue"
},
  "geometry": {"coordinates":[32.8604812622,39.9429283142],"type":"Point"}
}