{
  "type": "Feature",
  "properties": {
    "iso:country":"TR",
    "sg:address":"Ismetpasa Mah. No:76",
    "sg:city":"Niksar",
    "sg:classifiers":[
        {
            "category":"Farming",
            "subcategory":"Farm",
            "type":"Manufacturing & Wholesale Goods"
        }
    ],
    "sg:phone":"+90 356 527 1378",
    "sg:postcode":"60600",
    "sg:province":"Tokat",
    "sg:tags":[
        "agricultural",
        "product"
    ],
    "wof:name":"Senmarket",
    "wof:placetype":"venue"
},
  "geometry": {"coordinates":[36.545539856,40.3167381287],"type":"Point"}
}