{
  "type": "Feature",
  "properties": {
    "iso:country":"TR",
    "sg:address":"Perdemsa?plaza Kozyatagi Bayer Cd. G?bahar Sk. No:17",
    "sg:city":"Erenk?",
    "sg:classifiers":[
        {
            "category":"Utilities",
            "subcategory":"Electric",
            "type":"Services"
        }
    ],
    "sg:phone":"+90 216 380 7294",
    "sg:province":"Istanbul",
    "sg:tags":[
        "energy",
        "solar"
    ],
    "wof:name":"Karahan Isi Ve Enerji Sistem San. Tic. A.s.",
    "wof:placetype":"venue"
},
  "geometry": {"coordinates":[28.975925,41.012379],"type":"Point"}
}