{
  "type": "Feature",
  "properties": {
    "iso:country":"TR",
    "sg:address":"Artvin",
    "sg:city":"Ikitelli/K\u00fc\u00e7\u00fck\u00e7ekmece",
    "sg:classifiers":[
        {
            "category":"Health Services",
            "subcategory":"Hospital",
            "type":"Services"
        }
    ],
    "sg:phone":"+90 466 212 1531",
    "sg:postcode":"34660",
    "sg:province":"Artvin",
    "sg:tags":[
        "state"
    ],
    "wof:name":"Devlet Hastanesi",
    "wof:placetype":"venue"
},
  "geometry": {"coordinates":[41.824265,41.188183],"type":"Point"}
}