{
  "type": "Feature",
  "properties": {
    "iso:country":"TR",
    "sg:address":"Barbaros Cad. Zafer Sk. No.64/2",
    "sg:city":"K.?ekmece",
    "sg:classifiers":[
        {
            "category":"Shopping",
            "subcategory":"Clothing, Apparel, & Fashions",
            "type":"Retail Goods"
        }
    ],
    "sg:phone":"+90 212 579 5629",
    "sg:province":"Istanbul",
    "sg:tags":[
        "ready",
        "wear"
    ],
    "wof:name":"Sporteks Giyim As.",
    "wof:placetype":"venue"
},
  "geometry": {"coordinates":[28.9416332245,41.0762405396],"type":"Point"}
}