{
  "type": "Feature",
  "properties": {
    "iso:country":"TR",
    "sg:address":"Sehit Pamir Cad. 17",
    "sg:city":"Denizli",
    "sg:classifiers":[
        {
            "category":"Banks & Credit Unions",
            "subcategory":"Bank",
            "type":"Services"
        }
    ],
    "sg:phone":"+90 326 613 3995",
    "sg:postcode":"01130",
    "sg:province":"Iskenderun",
    "wof:name":"Egebank As",
    "wof:placetype":"venue"
},
  "geometry": {"coordinates":[36.170338,36.587067],"type":"Point"}
}