{
  "type": "Feature",
  "properties": {
    "addr:full":"S. Fuzuli Cd. Kidan Ish. No:20 D:2 Besiktas Eskisehir 75200",
    "addr:housenumber":"20 d 2",
    "addr:postcode":"75200",
    "addr:street":"S. Fuzuli Cd. Kidan Ish. No;Besiktas Eskisehir",
    "iso:country":"TR",
    "sg:address":"S. Fuzuli Cd. Kidan Ish. No:20 D:2",
    "sg:city":"Besiktas",
    "sg:classifiers":[
        {
            "category":"Organizations",
            "subcategory":"Membership Organization",
            "type":"Services"
        }
    ],
    "sg:phone":"+90 222 230 9696",
    "sg:postcode":"75200",
    "sg:province":"Eskisehir",
    "wof:name":"Beyin Damar Hast. Dernegi",
    "wof:placetype":"venue"
},
  "geometry": {"coordinates":[30.5154705048,39.7782936096],"type":"Point"}
}