{
  "type": "Feature",
  "properties": {
    "addr:full":"Bas?vus Sk. No:9/606 Emintas Ish. Kad\u0131k\u00f6y Istanbul 34990",
    "addr:housenumber":"?;606",
    "addr:postcode":"34990",
    "addr:street":"Bas;Sk. No 9 /;Ish. Kadikoey",
    "iso:country":"TR",
    "sg:address":"Bas?vus Sk. No:9/606 Emintas Ish.",
    "sg:city":"Kad\u0131k\u00f6y",
    "sg:classifiers":[
        {
            "category":"Government",
            "subcategory":"Fire Station",
            "type":"Public Place"
        }
    ],
    "sg:phone":"+90 216 337 2606",
    "sg:postcode":"34990",
    "sg:province":"Istanbul",
    "sg:tags":[
        "decoration"
    ],
    "wof:name":"Dost Dekorasyon",
    "wof:placetype":"venue"
},
  "geometry": {"coordinates":[28.9861831665,41.0408554077],"type":"Point"}
}