{
  "type": "Feature",
  "properties": {
    "iso:country":"TR",
    "sg:address":"Yildirim Sok. No:16",
    "sg:city":"Kad\u0131k\u00f6y",
    "sg:orig_category":"Muhtarliklar",
    "sg:phone":"+90 216 336 2484",
    "sg:postcode":"34990",
    "sg:province":"Istanbul",
    "wof:name":"Fikirtepe Mahallesi Muhtari:erdogan Erg?",
    "wof:placetype":"venue"
},
  "geometry": {"coordinates":[28.5308933258,41.0129966736],"type":"Point"}
}