{
  "type": "Feature",
  "properties": {
    "iso:country":"TR",
    "sg:address":"Egemenlik Cad. Cuma Mah. No:7",
    "sg:city":"Germencik",
    "sg:classifiers":[
        {
            "category":"Farming",
            "subcategory":"Farm",
            "type":"Manufacturing & Wholesale Goods"
        }
    ],
    "sg:phone":"+90 256225862721",
    "sg:postcode":"09700",
    "sg:province":"Aydin",
    "sg:tags":[
        "agricultural",
        "product"
    ],
    "wof:name":"Ali Kutlu Bosnali",
    "wof:placetype":"venue"
},
  "geometry": {"coordinates":[27.8460540771,37.8512001038],"type":"Point"}
}