{
  "type": "Feature",
  "properties": {
    "addr:full":"Tuna Cd. Atac Sk. No:21 D:1 Cankaya Beyoglu Ankara 46810",
    "addr:housenumber":"21 d 1",
    "addr:postcode":"46810",
    "addr:street":"Sk. No;Cankaya Beyoglu",
    "iso:country":"TR",
    "sg:address":"Tuna Cd. Atac Sk. No:21 D:1 Cankaya",
    "sg:city":"Beyoglu",
    "sg:classifiers":[
        {
            "category":"Building & Trades",
            "subcategory":"Construction",
            "type":"Services"
        }
    ],
    "sg:phone":"+90 312 431 2950",
    "sg:postcode":"46810",
    "sg:province":"Ankara",
    "sg:tags":[
        "foundation"
    ],
    "wof:name":"Turk Kanser Arast. Savas Vakfi",
    "wof:placetype":"venue"
},
  "geometry": {"coordinates":[29.283039093,40.8853187561],"type":"Point"}
}