{
  "type": "Feature",
  "properties": {
    "addr:full":"Cevat Dundar Cad. No:102-104 06370 Ostim Ankara Yakapinar-misis Ankara",
    "addr:housenumber":"102-104",
    "addr:postcode":"06370",
    "addr:street":"Dundar Cad. No",
    "iso:country":"TR",
    "sg:address":"Cevat Dundar Cad. No:102-104 06370 Ostim Ankara",
    "sg:city":"Yakapinar-misis",
    "sg:classifiers":[
        {
            "category":"Farming",
            "subcategory":"Livestock Farm",
            "type":"Manufacturing & Wholesale Goods"
        }
    ],
    "sg:phone":"+90 312 385 0270",
    "sg:province":"Ankara",
    "sg:tags":[
        "agriculture"
    ],
    "wof:name":"Tunga Makina Elektrik San Tic Ltd Sti",
    "wof:placetype":"venue"
},
  "geometry": {"coordinates":[32.7424888611,39.980594635],"type":"Point"}
}