{
  "type": "Feature",
  "properties": {
    "iso:country":"TR",
    "sg:address":"Rihtim Cd.veli Alemdar Han K7 No716",
    "sg:city":"Karak\u00f6y",
    "sg:classifiers":[
        {
            "category":"Freight",
            "type":"Transportation"
        }
    ],
    "sg:phone":"+90 212 251 5507",
    "sg:province":"Istanbul",
    "sg:tags":[
        "agent",
        "shipping",
        "broker"
    ],
    "wof:name":"Yakin Dogu Deniz Act.a.s.",
    "wof:placetype":"venue"
},
  "geometry": {"coordinates":[28.975925,41.012379],"type":"Point"}
}