{
  "type": "Feature",
  "properties": {
    "iso:country":"TR",
    "sg:address":"Y.dudullu Yol Sk. No:8 ?mraniye",
    "sg:city":"Iskenderun",
    "sg:classifiers":[
        {
            "category":"Manufacturing",
            "subcategory":"Rubber & Plastics",
            "type":"Manufacturing & Wholesale Goods"
        }
    ],
    "sg:phone":"+90 216 420 5380",
    "sg:postcode":"31200",
    "sg:province":"Istanbul",
    "sg:tags":[
        "industry"
    ],
    "wof:name":"Enkay Plastik Metal San. Tic. Ltd. Sti.",
    "wof:placetype":"venue"
},
  "geometry": {"coordinates":[29.1989383698,41.0028610229],"type":"Point"}
}