{
  "type": "Feature",
  "properties": {
    "addr:full":"B.yeri Sel?k Cd. No:12 Bak\u0131rk\u00f6y Denizli",
    "addr:housenumber":"?;no 12",
    "addr:street":"B.Yeri;K Cd.;Bakirkoey Denizli",
    "iso:country":"TR",
    "sg:address":"B.yeri Sel?k Cd. No:12",
    "sg:city":"Bak\u0131rk\u00f6y",
    "sg:classifiers":[
        {
            "category":"Shopping",
            "subcategory":"Stationery & Office Supplies",
            "type":"Retail Goods"
        }
    ],
    "sg:phone":"+90 258 265 1371",
    "sg:province":"Denizli",
    "sg:tags":[
        "paper"
    ],
    "wof:name":"Koza Kagit?ilik",
    "wof:placetype":"venue"
},
  "geometry": {"coordinates":[29.0864906311,37.773525238],"type":"Point"}
}