{
  "type": "Feature",
  "properties": {
    "iso:country":"TR",
    "sg:address":"G?r? Bulvari No:108/13 Maltepe",
    "sg:city":"Cagaloglu",
    "sg:orig_category":"Printinh House",
    "sg:phone":"+90 212 229 4291",
    "sg:postcode":"34410",
    "sg:province":"Istanbul",
    "wof:name":"?ner Yayin Basim San. Tic. Ltd. Sti.",
    "wof:placetype":"venue"
},
  "geometry": {"coordinates":[28.9077205658,40.9980621338],"type":"Point"}
}