{
  "type": "Feature",
  "properties": {
    "iso:country":"TR",
    "sg:address":"Kirlangi?sk. No:26/3 G.osmanpasa",
    "sg:city":"\u00dcmraniye",
    "sg:classifiers":[
        {
            "category":"Manufacturing",
            "subcategory":"Metals",
            "type":"Manufacturing & Wholesale Goods"
        }
    ],
    "sg:phone":"+90 312 427 8997",
    "sg:province":"Ankara",
    "sg:tags":[
        "iron-steel",
        "peoducts"
    ],
    "wof:name":"Birlesik ?elik Tic. Ltd. Sti.",
    "wof:placetype":"venue"
},
  "geometry": {"coordinates":[28.9095478058,41.0631713867],"type":"Point"}
}