{
  "type": "Feature",
  "properties": {
    "addr:full":"Sanayi Cad. No.31 Bornova Izmir 35040",
    "addr:postcode":"35040",
    "addr:street":"Sanayi Cad. No.31",
    "iso:country":"TR",
    "sg:address":"Sanayi Cad. No.31",
    "sg:city":"Bornova",
    "sg:classifiers":[
        {
            "category":"Home & Garden",
            "subcategory":"Building Materials",
            "type":"Retail Goods"
        }
    ],
    "sg:phone":"+90 232 435 0661",
    "sg:postcode":"35040",
    "sg:province":"Izmir",
    "sg:tags":[
        "stone",
        "natural",
        "marble"
    ],
    "wof:name":"Famerit San. Ve Tic. Ltd.sti.",
    "wof:placetype":"venue"
},
  "geometry": {"coordinates":[27.2030029297,38.4532623291],"type":"Point"}
}