{
  "type": "Feature",
  "properties": {
    "addr:full":"Bankalar Cd. Yanikkapi Sk. Aslan D. Han No:210 Karak? Nazilli Istanbul 65600",
    "addr:postcode":"210;?;65600",
    "addr:street":"Bankalar Cd. Yanikkapi Sk. Aslan D. Han No",
    "iso:country":"TR",
    "sg:address":"Bankalar Cd. Yanikkapi Sk. Aslan D. Han No:210 Karak?",
    "sg:city":"Nazilli",
    "sg:classifiers":[
        {
            "category":"Shopping",
            "subcategory":"Computers & Home Electronics",
            "type":"Retail Goods"
        }
    ],
    "sg:phone":"+90 212 237 3575",
    "sg:postcode":"65600",
    "sg:province":"Istanbul",
    "sg:tags":[
        "product",
        "electric-electronic"
    ],
    "wof:name":"?ankaya Kablo San.",
    "wof:placetype":"venue"
},
  "geometry": {"coordinates":[28.9861831665,41.0408554077],"type":"Point"}
}