{
  "type": "Feature",
  "properties": {
    "addr:full":"Bayramyeri No:2/b Levent - Besiktas Denizli",
    "addr:housenumber":"bayramyeri;b",
    "addr:street":"No 2 /",
    "iso:country":"TR",
    "sg:address":"Bayramyeri No:2/b",
    "sg:city":"Levent - Besiktas",
    "sg:classifiers":[
        {
            "category":"Shopping",
            "subcategory":"Stationery & Office Supplies",
            "type":"Retail Goods"
        }
    ],
    "sg:phone":"+90 258 261 1509",
    "sg:province":"Denizli",
    "wof:name":"Kitap?ioglu Kirtasiye",
    "wof:placetype":"venue"
},
  "geometry": {"coordinates":[29.086491,37.773525],"type":"Point"}
}