{
  "type": "Feature",
  "properties": {
    "iso:country":"TR",
    "sg:address":"Yzb. Milli Kuvvetler Cd. No:18",
    "sg:city":"Susurluk",
    "sg:classifiers":[
        {
            "category":"Utilities",
            "subcategory":"Water",
            "type":"Services"
        }
    ],
    "sg:phone":"+90 266 865 1138",
    "sg:postcode":"10600",
    "sg:province":"Balikesir",
    "sg:tags":[
        "vegetable",
        "margarine",
        "oil"
    ],
    "wof:name":"Tunali Yag San. Tic. A.s.",
    "wof:placetype":"venue"
},
  "geometry": {"coordinates":[27.8833007812,39.6520996094],"type":"Point"}
}