{
  "type": "Feature",
  "properties": {
    "iso:country":"TR",
    "sg:address":"Organize San. B?. 7. Cad. No:25 Organize San. B?.",
    "sg:city":"Kad\u0131k\u00f6y",
    "sg:classifiers":[
        {
            "category":"Manufacturing",
            "subcategory":"Metals",
            "type":"Manufacturing & Wholesale Goods"
        }
    ],
    "sg:phone":"+90 352321190032",
    "sg:province":"Kayseri",
    "sg:tags":[
        "industry"
    ],
    "wof:name":"Evger Ev Gerec. San. Tic. A.s.",
    "wof:placetype":"venue"
},
  "geometry": {"coordinates":[35.4891357422,38.7225761414],"type":"Point"}
}