{
  "type": "Feature",
  "properties": {
    "iso:country":"TR",
    "sg:address":"Nenehatun Cd.no.109 G.o.p.",
    "sg:city":"Boyobat",
    "sg:classifiers":[
        {
            "category":"Government",
            "subcategory":"Embassy",
            "type":"Public Place"
        }
    ],
    "sg:phone":"+90 312 446 8247",
    "sg:province":"Ankara",
    "sg:tags":[
        "foreign"
    ],
    "wof:name":"Belcika Kiralligi B?y?kel?iligi",
    "wof:placetype":"venue"
},
  "geometry": {"coordinates":[32.8677101135,39.8995246887],"type":"Point"}
}