{
  "type": "Feature",
  "properties": {
    "iso:country":"TR",
    "sg:address":"Maresal ?akmak Cd. 3. Sk. Aydinlar Ishani Sirinevler",
    "sg:city":"Sisli",
    "sg:orig_category":"Scavening Services",
    "sg:phone":"+90 212 552 0444",
    "sg:postcode":"80270",
    "sg:province":"Istanbul",
    "wof:name":"Afm Ithalat Ihracat Ltd. Sti.",
    "wof:placetype":"venue"
},
  "geometry": {"coordinates":[28.975925,41.012379],"type":"Point"}
}