{
  "type": "Feature",
  "properties": {
    "addr:full":"Haci Halil Mah Belediye Gebze 41400 41400",
    "addr:postcode":"41400 41400",
    "addr:street":"Halil Mah Belediye",
    "iso:country":"TR",
    "sg:address":"Haci Halil Mah Belediye",
    "sg:city":"Gebze",
    "sg:classifiers":[
        {
            "category":"Banks & Credit Unions",
            "subcategory":"Bank",
            "type":"Services"
        }
    ],
    "sg:phone":"+90 262 642 3074",
    "sg:postcode":"41400",
    "sg:province":"41400",
    "wof:name":"T?kiye T??c?er, Bankasi Yasarbank As",
    "wof:placetype":"venue"
},
  "geometry": {"coordinates":[36.927338,37.583725],"type":"Point"}
}