{
  "type": "Feature",
  "properties": {
    "iso:country":"TR",
    "sg:address":"Kayisdagi Cd. No:4 I?renk?",
    "sg:city":"Sisli",
    "sg:classifiers":[
        {
            "category":"Home & Garden",
            "subcategory":"Home Furnishings",
            "type":"Retail Goods"
        }
    ],
    "sg:phone":"+90 216 380 9989",
    "sg:postcode":"65710",
    "sg:province":"Istanbul",
    "sg:tags":[
        "curtaining",
        "-",
        "upholstering"
    ],
    "wof:name":"?zmen Mefrusat K?rk??oglu Tekstil San. Tic. A.s.",
    "wof:placetype":"venue"
},
  "geometry": {"coordinates":[28.975925,41.012379],"type":"Point"}
}