{
  "type": "Feature",
  "properties": {
    "iso:country":"TR",
    "sg:address":"Galipdede Cd. No:73/75 T?el, Beyoglu",
    "sg:city":"14240",
    "sg:classifiers":[
        {
            "category":"Wholesale",
            "subcategory":"Home Furnishings",
            "type":"Manufacturing & Wholesale Goods"
        }
    ],
    "sg:phone":"+90 212 251 4480",
    "sg:province":"Istanbul",
    "sg:tags":[
        "furniture"
    ],
    "wof:name":"Basaran Kaplama Ltd. Sti.",
    "wof:placetype":"venue"
},
  "geometry": {"coordinates":[28.9745006561,41.0350418091],"type":"Point"}
}