{
  "type": "Feature",
  "properties": {
    "addr:full":"?evreyolu Cd. No:2 Bayrampasa Merter Istanbul",
    "addr:housenumber":"?;no 2",
    "addr:street":"Evreyolu Cd.",
    "iso:country":"TR",
    "sg:address":"?evreyolu Cd. No:2 Bayrampasa",
    "sg:city":"Merter",
    "sg:classifiers":[
        {
            "category":"Wholesale",
            "subcategory":"Machinery & Supplies",
            "type":"Manufacturing & Wholesale Goods"
        }
    ],
    "sg:phone":"+90 212 567 2710",
    "sg:province":"Istanbul",
    "sg:tags":[
        "heavy",
        "construction",
        "macinery"
    ],
    "wof:name":"?ukurova Ziraat End. Tic. A.s.",
    "wof:placetype":"venue"
},
  "geometry": {"coordinates":[28.912109375,41.0438117981],"type":"Point"}
}