{
  "type": "Feature",
  "properties": {
    "addr:full":"?alis Plaji Bulv. No:112 Hotel Fiesta Alti Fethiye Mugla 44000",
    "addr:housenumber":"?;no",
    "addr:postcode":"44000",
    "addr:street":"Alis Plaji Bulv.",
    "iso:country":"TR",
    "sg:address":"?alis Plaji Bulv. No:112 Hotel Fiesta Alti",
    "sg:city":"Fethiye",
    "sg:classifiers":[
        {
            "category":"Travel",
            "subcategory":"Travel Agent",
            "type":"Entertainment"
        }
    ],
    "sg:phone":"+90 252 613 2871",
    "sg:postcode":"44000",
    "sg:province":"Mugla",
    "sg:tags":[
        "agency",
        "tourism"
    ],
    "wof:name":"Kiss Luck Turizm",
    "wof:placetype":"venue"
},
  "geometry": {"coordinates":[28.3628406525,37.215675354],"type":"Point"}
}