{
  "type": "Feature",
  "properties": {
    "addr:full":"Tahir Sk Zafer Apt. No:9 Altiparmak Ortak? Bursa 80840",
    "addr:postcode":"80840",
    "addr:street":"Tahir;Bursa",
    "iso:country":"TR",
    "sg:address":"Tahir Sk Zafer Apt. No:9 Altiparmak",
    "sg:city":"Ortak?",
    "sg:classifiers":[
        {
            "category":"Organizations",
            "subcategory":"Professional Association",
            "type":"Services"
        }
    ],
    "sg:phone":"+90 224 220 9993",
    "sg:postcode":"80840",
    "sg:province":"Bursa",
    "wof:name":"Tmmob Kimya M?hendis Odasi",
    "wof:placetype":"venue"
},
  "geometry": {"coordinates":[29.0525588989,40.1912384033],"type":"Point"}
}