{
  "type": "Feature",
  "properties": {
    "iso:country":"TR",
    "sg:address":"Tarlabasi Bulvari No: 86 80080 Taksim Istanbul",
    "sg:city":"Konak",
    "sg:classifiers":[
        {
            "category":"Real Estate",
            "subcategory":"Surveying",
            "type":"Services"
        }
    ],
    "sg:phone":"+90 212 237 0306",
    "sg:postcode":"07110",
    "sg:province":"Istanbul",
    "sg:tags":[
        "equipment",
        "material",
        "good",
        "-",
        "handling"
    ],
    "wof:name":"Karakus Ltd Sti",
    "wof:placetype":"venue"
},
  "geometry": {"coordinates":[28.9837837219,41.0367660522],"type":"Point"}
}