{
  "type": "Feature",
  "properties": {
    "addr:full":"Yenidogan Mah. 42/4 Sok. No:2 Zeytinburnu \u00c7orlu Istanbul",
    "addr:housenumber":"42 / 4;no 2",
    "addr:street":"Yenidogan Mah.;Sok.;Zeytinburnu",
    "iso:country":"TR",
    "sg:address":"Yenidogan Mah. 42/4 Sok. No:2 Zeytinburnu",
    "sg:city":"\u00c7orlu",
    "sg:classifiers":[
        {
            "category":"Shopping",
            "subcategory":"Luggage & Leather Goods",
            "type":"Retail Goods"
        }
    ],
    "sg:phone":"+90 212 664 4955",
    "sg:province":"Istanbul",
    "sg:tags":[
        "leather-fur",
        "wear"
    ],
    "wof:name":"Duran Deri Tekstil San.ltd.",
    "wof:placetype":"venue"
},
  "geometry": {"coordinates":[28.9045524597,40.989906311],"type":"Point"}
}