{
  "type": "Feature",
  "properties": {
    "iso:country":"TR",
    "sg:address":"Cincin K?? Kocarli",
    "sg:city":"Bayrampasa",
    "sg:classifiers":[
        {
            "category":"Food & Beverages",
            "subcategory":"Dairy",
            "type":"Retail Goods"
        }
    ],
    "sg:phone":"+90 256 722 7045",
    "sg:postcode":"36100",
    "sg:province":"Aydin",
    "sg:tags":[
        "pruducts",
        "milk"
    ],
    "wof:name":"Sahinci Sut Urun. San. Tic.",
    "wof:placetype":"venue"
},
  "geometry": {"coordinates":[28.4863967896,37.8117027283],"type":"Point"}
}