{
  "type": "Feature",
  "properties": {
    "iso:country":"TR",
    "sg:address":"Yenidogan Mh. Tasit Sk. No:2",
    "sg:city":"Mersin",
    "sg:classifiers":[
        {
            "category":"Mining & Drilling",
            "type":"Manufacturing & Wholesale Goods"
        }
    ],
    "sg:phone":"+90 222 335 3406",
    "sg:postcode":"52750",
    "sg:province":"Eskisehir",
    "sg:tags":[
        "industry",
        "mine"
    ],
    "wof:name":"Mert Madencilik",
    "wof:placetype":"venue"
},
  "geometry": {"coordinates":[30.5503692627,39.7636070251],"type":"Point"}
}