{
  "type": "Feature",
  "properties": {
    "addr:full":"Belediye Is Merkezi No:82 Basinevleri ?anakkale 06010",
    "addr:housenumber":"no 82;?",
    "addr:postcode":"06010",
    "addr:street":"Basinevleri;Anakkale",
    "iso:country":"TR",
    "sg:address":"Belediye Is Merkezi No:82",
    "sg:city":"Basinevleri",
    "sg:classifiers":[
        {
            "category":"Wholesale",
            "subcategory":"Books, Periodicals, & Newspapers",
            "type":"Manufacturing & Wholesale Goods"
        }
    ],
    "sg:phone":"+90 286 212 6645",
    "sg:postcode":"06010",
    "sg:province":"?anakkale",
    "sg:tags":[
        "house",
        "publishing"
    ],
    "wof:name":"Burasi Canakkale Gazetesi",
    "wof:placetype":"venue"
},
  "geometry": {"coordinates":[32.8532714844,39.929309845],"type":"Point"}
}