{
  "type": "Feature",
  "properties": {
    "iso:country":"TR",
    "sg:address":"Havanci Sk. Havanci Han No:319-320 Mercan",
    "sg:city":"\u00dcmraniye",
    "sg:classifiers":[
        {
            "category":"Home & Garden",
            "subcategory":"Kitchen Supply",
            "type":"Retail Goods"
        }
    ],
    "sg:phone":"+90 212 875 1182",
    "sg:postcode":"81240",
    "sg:province":"Istanbul",
    "sg:tags":[
        "steel",
        "utensil"
    ],
    "wof:name":"H?rsah H?rsultan ?elik Esya San. Tic. Ltd. Sti.",
    "wof:placetype":"venue"
},
  "geometry": {"coordinates":[28.975925,41.012379],"type":"Point"}
}