{
  "type": "Feature",
  "properties": {
    "addr:full":"Ankara Asfalti 30.km. Kuyucak Koyu Yolu ?eri Kemalpasa Izmir 01340",
    "addr:housenumber":"?",
    "addr:postcode":"01340",
    "addr:street":"Koyu Yolu;Kemalpasa",
    "iso:country":"TR",
    "sg:address":"Ankara Asfalti 30.km. Kuyucak Koyu Yolu ?eri",
    "sg:city":"Kemalpasa",
    "sg:classifiers":[
        {
            "category":"Manufacturing",
            "subcategory":"Building Materials",
            "type":"Manufacturing & Wholesale Goods"
        }
    ],
    "sg:phone":"+90 232 877 1313",
    "sg:postcode":"01340",
    "sg:province":"Izmir",
    "sg:tags":[
        "floor-wall",
        "covering"
    ],
    "wof:name":"Topaz Prekast Yapi Elemanlari San. Ve Tic. A.s.",
    "wof:placetype":"venue"
},
  "geometry": {"coordinates":[27.1296863556,38.4186973572],"type":"Point"}
}