{
  "type": "Feature",
  "properties": {
    "addr:full":"Barbaros Bulvari Hossohbet Sok. No:1/14 Balmumcu Kizilay Istanbul 06430",
    "addr:housenumber":"no 1 / 14",
    "addr:postcode":"06430",
    "addr:street":"Barbaros Bulvari Hossohbet Sok.",
    "iso:country":"TR",
    "sg:address":"Barbaros Bulvari Hossohbet Sok. No:1/14 Balmumcu",
    "sg:city":"Kizilay",
    "sg:classifiers":[
        {
            "category":"Government",
            "subcategory":"Office",
            "type":"Public Place"
        }
    ],
    "sg:phone":"+90 212 216 7976",
    "sg:postcode":"06430",
    "sg:province":"Istanbul",
    "sg:tags":[
        "patent",
        "mark"
    ],
    "wof:name":"Aydin Patent Marka Tanitim Ve Danismanlik Ltd.sti",
    "wof:placetype":"venue"
},
  "geometry": {"coordinates":[28.9861831665,41.0408554077],"type":"Point"}
}