{
  "type": "Feature",
  "properties": {
    "addr:full":"Gmk Bulvari No:149/c Tandogan Incek No:57 Mecidiyek\u00f6y Ankara 80260",
    "addr:housenumber":"no;/ c",
    "addr:postcode":"80260",
    "addr:street":"Gmk Bulvari;No 57 Mecidiyekoey",
    "iso:country":"TR",
    "sg:address":"Gmk Bulvari No:149/c Tandogan Incek No:57",
    "sg:city":"Mecidiyek\u00f6y",
    "sg:classifiers":[
        {
            "category":"Professional",
            "subcategory":"Detective & Security Services",
            "type":"Services"
        }
    ],
    "sg:phone":"+90 312 229 1557",
    "sg:postcode":"80260",
    "sg:province":"Ankara",
    "sg:tags":[
        "material"
    ],
    "wof:name":"Sfs Ulusoy Ltd.sti.",
    "wof:placetype":"venue"
},
  "geometry": {"coordinates":[32.856033,39.943874],"type":"Point"}
}