{
  "type": "Feature",
  "properties": {
    "addr:full":"1313 Sok. No:15 Cankaya Izmir 07080",
    "addr:housenumber":"no 15",
    "addr:postcode":"07080",
    "addr:street":"1313 Sok.;Cankaya Izmir",
    "iso:country":"TR",
    "sg:address":"1313 Sok. No:15",
    "sg:city":"Cankaya",
    "sg:classifiers":[
        {
            "category":"Shopping",
            "subcategory":"Clothing, Apparel, & Fashions",
            "type":"Retail Goods"
        }
    ],
    "sg:phone":"+90 232 484 8253",
    "sg:postcode":"07080",
    "sg:province":"Izmir",
    "sg:tags":[
        "ready",
        "wear"
    ],
    "wof:name":"Safak Gomlek Penye Tic.ltd.sti.",
    "wof:placetype":"venue"
},
  "geometry": {"coordinates":[27.1362094879,38.4215316772],"type":"Point"}
}