{
  "type": "Feature",
  "properties": {
    "addr:full":"Alibeyk?y Alibeyk?y Istanbul",
    "iso:country":"TR",
    "sg:address":"Alibeyk?y",
    "sg:city":"Alibeyk?y",
    "sg:classifiers":[
        {
            "category":"Home & Garden",
            "subcategory":"Building Materials",
            "type":"Retail Goods"
        }
    ],
    "sg:phone":"+90 532 296 8177",
    "sg:province":"Istanbul",
    "sg:tags":[
        "stone",
        "natural",
        "marble"
    ],
    "wof:name":"?zsay Mermer A.s.",
    "wof:placetype":"venue"
},
  "geometry": {"coordinates":[28.9861793518,41.040851593],"type":"Point"}
}