{
  "type": "Feature",
  "properties": {
    "iso:country":"TR",
    "sg:address":"Bagdat Cad.no:61/8",
    "sg:city":"Kiziltporak",
    "sg:classifiers":[
        {
            "category":"Mining & Drilling",
            "type":"Manufacturing & Wholesale Goods"
        }
    ],
    "sg:phone":"+90 216 414 1771",
    "sg:province":"Istanbul",
    "sg:tags":[
        "underwater",
        "working"
    ],
    "wof:name":"Infar Insaat Denizcilik San,tic.a.s.",
    "wof:placetype":"venue"
},
  "geometry": {"coordinates":[29.09775,40.952053],"type":"Point"}
}