{
  "type": "Feature",
  "properties": {
    "iso:country":"TR",
    "sg:address":"Fatih Cd. Kayik? Sk. No: 7",
    "sg:city":"Merter",
    "sg:classifiers":[
        {
            "category":"Shopping",
            "subcategory":"Clothing, Apparel, & Fashions",
            "type":"Retail Goods"
        }
    ],
    "sg:phone":"+90 212 556 2862",
    "sg:province":"Istanbul",
    "sg:tags":[
        "underwear"
    ],
    "wof:name":"Hanimefendi ?orap San. Tic. A.s.",
    "wof:placetype":"venue"
},
  "geometry": {"coordinates":[28.875105,41.021217],"type":"Point"}
}