{
  "type": "Feature",
  "properties": {
    "addr:full":"Ferhatpasa Mah. M.fevzi ?akmak Cad. G-35 Sk. No:26 Kayisdagi Samandira Istanbul 80360",
    "addr:housenumber":"?;g-35 sk. no 26",
    "addr:postcode":"80360",
    "addr:street":"Ferhatpasa Mah. M.Fevzi;Akmak Cad.",
    "iso:country":"TR",
    "sg:address":"Ferhatpasa Mah. M.fevzi ?akmak Cad. G-35 Sk. No:26 Kayisdagi",
    "sg:city":"Samandira",
    "sg:classifiers":[
        {
            "category":"Social Services",
            "subcategory":"Retirement Home",
            "type":"Services"
        }
    ],
    "sg:phone":"+90 216 471 8080",
    "sg:postcode":"80360",
    "sg:province":"Istanbul",
    "sg:tags":[
        "door"
    ],
    "wof:name":"Hakan Reklam San. Tic. Ltd. Sti.",
    "wof:placetype":"venue"
},
  "geometry": {"coordinates":[28.9759254456,41.0123786926],"type":"Point"}
}