{
  "type": "Feature",
  "properties": {
    "addr:full":"28 Nisan Cd. No:37 Sisli Istanbul 65710",
    "addr:housenumber":"no 37",
    "addr:postcode":"65710",
    "addr:street":"28 Nisan Cd.;Istanbul",
    "iso:country":"TR",
    "sg:address":"28 Nisan Cd. No:37",
    "sg:city":"Sisli",
    "sg:classifiers":[
        {
            "category":"Shopping",
            "subcategory":"Florist",
            "type":"Retail Goods"
        }
    ],
    "sg:phone":"+90 212 222 1697",
    "sg:postcode":"65710",
    "sg:province":"Istanbul",
    "sg:tags":[
        "flower"
    ],
    "wof:name":"Reni ?i?ek?ilik",
    "wof:placetype":"venue"
},
  "geometry": {"coordinates":[28.9736385345,41.0693092346],"type":"Point"}
}