{
  "type": "Feature",
  "properties": {
    "iso:country":"TR",
    "sg:address":"?zcan Mah. N0.19-55",
    "sg:city":"Bakircilar",
    "sg:orig_category":"Textile Suplementaries",
    "sg:phone":"+90 258 264 7286",
    "sg:postcode":"49000",
    "sg:province":"Denizli",
    "wof:name":"Detsan Etiket Ltd.sti.",
    "wof:placetype":"venue"
},
  "geometry": {"coordinates":[29.0788803101,37.7851867676],"type":"Point"}
}