{
  "type": "Feature",
  "properties": {
    "addr:full":"Eski Oto Sanayi Sitesi Barbaros Cad. No.12 4.levent B. ?ekmece Istanbul 34400",
    "addr:housenumber":"4.levent b. ?",
    "addr:postcode":"34400",
    "addr:street":"Eski Oto Sanayi Sitesi Barbaros Cad. No.12",
    "iso:country":"TR",
    "sg:address":"Eski Oto Sanayi Sitesi Barbaros Cad. No.12 4.levent",
    "sg:city":"B. ?ekmece",
    "sg:classifiers":[
        {
            "category":"Manufacturing",
            "subcategory":"Metals",
            "type":"Manufacturing & Wholesale Goods"
        }
    ],
    "sg:phone":"+90 212 270 9243",
    "sg:postcode":"34400",
    "sg:province":"Istanbul",
    "sg:tags":[
        "industry"
    ],
    "wof:name":"Kromplast San. Tic.ltd.sti.",
    "wof:placetype":"venue"
},
  "geometry": {"coordinates":[29.0070343018,41.0842628479],"type":"Point"}
}