{
  "type": "Feature",
  "properties": {
    "addr:full":"G?es Cd. No:73 Bayrampasa Merkez Istanbul 77200",
    "addr:housenumber":"?;cd. no 73",
    "addr:postcode":"77200",
    "addr:street":"Bayrampasa",
    "iso:country":"TR",
    "sg:address":"G?es Cd. No:73 Bayrampasa",
    "sg:city":"Merkez",
    "sg:classifiers":[
        {
            "category":"Freight",
            "type":"Transportation"
        }
    ],
    "sg:phone":"+90 212 613 3385",
    "sg:postcode":"77200",
    "sg:province":"Istanbul",
    "sg:tags":[
        "packing",
        "industry"
    ],
    "wof:name":"Ada Plastik Ambalaj San. Tic. Ltd. Sti.",
    "wof:placetype":"venue"
},
  "geometry": {"coordinates":[28.9759254456,41.0123786926],"type":"Point"}
}