{
  "type": "Feature",
  "properties": {
    "iso:country":"TR",
    "sg:address":"Comlekci Mah.zanapa Yolu Uzeri No:244",
    "sg:city":"Eregli",
    "sg:classifiers":[
        {
            "category":"Food & Beverages",
            "subcategory":"Dairy",
            "type":"Retail Goods"
        }
    ],
    "sg:phone":"+90 332 713 6480",
    "sg:postcode":"42310",
    "sg:province":"Konya",
    "sg:tags":[
        "pruducts",
        "milk"
    ],
    "wof:name":"Kafaoglu Sut Ve Gida Mamulleri San.tic.ltd.sti.",
    "wof:placetype":"venue"
},
  "geometry": {"coordinates":[32.4990272522,37.8715362549],"type":"Point"}
}