{
  "type": "Feature",
  "properties": {
    "iso:country":"TR",
    "sg:address":"Musalla Baglari Gulyurdu Sk. No.10",
    "sg:city":"Cankaya",
    "sg:classifiers":[
        {
            "category":"Ice Cream",
            "type":"Food & Drink"
        }
    ],
    "sg:phone":"+90 332 233 7971",
    "sg:postcode":"07080",
    "sg:province":"Konya",
    "sg:tags":[
        "sugar"
    ],
    "wof:name":"Kevser Sekerleme Gida San.ltd.sti.",
    "wof:placetype":"venue"
},
  "geometry": {"coordinates":[32.50415,37.896709],"type":"Point"}
}