{
  "type": "Feature",
  "properties": {
    "addr:full":"Koza Sok. No:155/2 G.o.p. Ankara",
    "addr:housenumber":"no;/ 2",
    "addr:street":"Koza Sok.;G.O.P.",
    "iso:country":"TR",
    "sg:address":"Koza Sok. No:155/2",
    "sg:city":"G.o.p.",
    "sg:classifiers":[
        {
            "category":"Manufacturing",
            "subcategory":"Building Materials",
            "type":"Manufacturing & Wholesale Goods"
        }
    ],
    "sg:phone":"+90 3124475606729",
    "sg:province":"Ankara",
    "sg:tags":[
        "floor-wall",
        "covering"
    ],
    "wof:name":"Tusa Danismanlik Ve Dis Tic.ltd.sti.",
    "wof:placetype":"venue"
},
  "geometry": {"coordinates":[32.876625061,39.8992195129],"type":"Point"}
}