{
  "type": "Feature",
  "properties": {
    "iso:country":"TR",
    "sg:address":"Fuatpasa Cad. Ragip Bey Is Hani No: 60/14",
    "sg:city":"Mercan",
    "sg:classifiers":[
        {
            "category":"Manufacturing",
            "subcategory":"Textiles",
            "type":"Manufacturing & Wholesale Goods"
        }
    ],
    "sg:phone":"+90 212 508 9266",
    "sg:postcode":"12600",
    "sg:province":"Istanbul",
    "sg:tags":[
        "product"
    ],
    "wof:name":"Saribas Tekstil",
    "wof:placetype":"venue"
},
  "geometry": {"coordinates":[28.9759254456,41.0123786926],"type":"Point"}
}