{
  "type": "Feature",
  "properties": {
    "iso:country":"TR",
    "sg:address":"Organize Sanayi B?lgesi 15.cadde No:19",
    "sg:city":"Melikgazi",
    "sg:orig_category":"Mdf-fiberboard-coating",
    "sg:phone":"+90 352 321 1414",
    "sg:postcode":"38030",
    "sg:province":"Kayseri",
    "wof:name":"Baktiroglu Or.?r.as",
    "wof:placetype":"venue"
},
  "geometry": {"coordinates":[35.4364013672,38.7450408936],"type":"Point"}
}