{
  "type": "Feature",
  "properties": {
    "addr:full":"Selamsiz Cad. Kapalicarsi No:30 D:275-299 Uskudar Istanbul 34672",
    "addr:housenumber":"kapalicarsi",
    "addr:postcode":"275-299;34672",
    "addr:street":"Selamsiz Cad.;No 30 D",
    "iso:country":"TR",
    "sg:address":"Selamsiz Cad. Kapalicarsi No:30 D:275-299",
    "sg:city":"Uskudar",
    "sg:classifiers":[
        {
            "category":"Food & Beverages",
            "subcategory":"Specialty",
            "type":"Retail Goods"
        }
    ],
    "sg:phone":"+90 216 343 8127",
    "sg:postcode":"34672",
    "sg:province":"Istanbul",
    "sg:tags":[
        "materials-spices",
        "additive"
    ],
    "wof:name":"Dogal Urunler Merkezi San. Ve Tic.",
    "wof:placetype":"venue"
},
  "geometry": {"coordinates":[29.0154418945,41.0218315125],"type":"Point"}
}