{
  "type": "Feature",
  "properties": {
    "addr:full":"Mecidiye Mah.mehmet Afkan Sk.no.7 Kosuyolu Istanbul 47860",
    "addr:postcode":"47860",
    "iso:country":"TR",
    "sg:address":"Mecidiye Mah.mehmet Afkan Sk.no.7",
    "sg:city":"Kosuyolu",
    "sg:classifiers":[
        {
            "category":"Marine",
            "type":"Transportation"
        }
    ],
    "sg:phone":"+90 216 326 2095",
    "sg:postcode":"47860",
    "sg:province":"Istanbul",
    "sg:tags":[
        "shipowner"
    ],
    "wof:name":"Furtrans Denizcilik A.s.",
    "wof:placetype":"venue"
},
  "geometry": {"coordinates":[28.975925,41.012379],"type":"Point"}
}