{
  "type": "Feature",
  "properties": {
    "iso:country":"TR",
    "sg:address":"Gedikpasa Cad. No:88/1 Beyazit",
    "sg:city":"Hacilar",
    "sg:classifiers":[
        {
            "category":"Shopping",
            "subcategory":"Clothing, Apparel, & Fashions",
            "type":"Retail Goods"
        }
    ],
    "sg:phone":"+90 212 516 9426",
    "sg:postcode":"38000",
    "sg:province":"Istanbul",
    "sg:tags":[
        "bag-belt-accessories"
    ],
    "wof:name":"Aslantas Ltd.sti.",
    "wof:placetype":"venue"
},
  "geometry": {"coordinates":[28.966928,41.006443],"type":"Point"}
}