{
  "type": "Feature",
  "properties": {
    "addr:full":"Davutpasa Cad. Latsfatas Basoglu San. Sit. No:16-17-18 Davutpasa- Topkapi 64100 Istanbul",
    "addr:postcode":"16-17-18;64100",
    "addr:street":"Davutpasa Cad. Latsfatas Basoglu San. Sit. No",
    "iso:country":"TR",
    "sg:address":"Davutpasa Cad. Latsfatas Basoglu San. Sit. No:16-17-18 Davutpasa- Topkapi",
    "sg:city":"64100",
    "sg:classifiers":[
        {
            "category":"Manufacturing",
            "subcategory":"Leather Goods",
            "type":"Manufacturing & Wholesale Goods"
        }
    ],
    "sg:phone":"+90 212 482 4161",
    "sg:province":"Istanbul",
    "sg:tags":[
        "machine"
    ],
    "wof:name":"Boyut Makina San.ltd.sti.",
    "wof:placetype":"venue"
},
  "geometry": {"coordinates":[28.9759254456,41.0123786926],"type":"Point"}
}