{
  "type": "Feature",
  "properties": {
    "iso:country":"TR",
    "sg:address":"Aydintepe Mah.yavuz Cad.no:8/1",
    "sg:city":"Tuzla",
    "sg:classifiers":[
        {
            "category":"Manufacturing",
            "subcategory":"Textiles",
            "type":"Manufacturing & Wholesale Goods"
        }
    ],
    "sg:phone":"+90 216 494 0800",
    "sg:postcode":"01900",
    "sg:province":"Istanbul",
    "sg:tags":[
        "cloth",
        "worker"
    ],
    "wof:name":"Besiroglu Is Giyim",
    "wof:placetype":"venue"
},
  "geometry": {"coordinates":[29.2995872498,40.850528717],"type":"Point"}
}