{
  "type": "Feature",
  "properties": {
    "iso:country":"TR",
    "sg:address":"12. Cd. No:59",
    "sg:city":"D.evler",
    "sg:classifiers":[
        {
            "category":"Professional",
            "subcategory":"Engineering",
            "type":"Services"
        }
    ],
    "sg:phone":"+90 312 334 5423",
    "sg:province":"Ankara",
    "sg:tags":[
        "architect"
    ],
    "wof:name":"Acarlar I? Mimar. End?stri. Ltd. Sti.",
    "wof:placetype":"venue"
},
  "geometry": {"coordinates":[32.8604812622,39.9429283142],"type":"Point"}
}