{
  "type": "Feature",
  "properties": {
    "iso:country":"TR",
    "sg:address":"Fahrettin Altay Cad. 414.sok. No:9",
    "sg:city":"Gebze",
    "sg:orig_category":"Aluminium Carpentary",
    "sg:phone":"+90 242 247 4107",
    "sg:postcode":"41400",
    "sg:province":"Antalya",
    "wof:name":"Doruk Metal Ve Ins. Tic.ltd.sti.",
    "wof:placetype":"venue"
},
  "geometry": {"coordinates":[30.7031345367,36.8875045776],"type":"Point"}
}