{
  "type": "Feature",
  "properties": {
    "addr:full":"Halitaga Cad. Misaki Milli Sok.no:121 K:1 Kadikoy Istanbul 01370",
    "addr:housenumber":"121 k 1",
    "addr:postcode":"01370",
    "addr:street":"Halitaga Cad.;Milli Sok.No",
    "iso:country":"TR",
    "sg:address":"Halitaga Cad. Misaki Milli Sok.no:121 K:1",
    "sg:city":"Kadikoy",
    "sg:classifiers":[
        {
            "category":"Home & Garden",
            "subcategory":"Building Materials",
            "type":"Retail Goods"
        }
    ],
    "sg:phone":"+90 216 337 4819",
    "sg:postcode":"01370",
    "sg:province":"Istanbul",
    "sg:tags":[
        "insulation"
    ],
    "wof:name":"Izofer Tahhut Insaat Turizm San.tic.ltd.",
    "wof:placetype":"venue"
},
  "geometry": {"coordinates":[28.9861831665,41.0408554077],"type":"Point"}
}