{
  "type": "Feature",
  "properties": {
    "iso:country":"TR",
    "sg:address":"Imam Ramiz Sok. Demirli Sitesi A-1 Blok Kozyatagi",
    "sg:city":"Kartal",
    "sg:classifiers":[
        {
            "category":"Manufacturing",
            "subcategory":"Metals",
            "type":"Manufacturing & Wholesale Goods"
        }
    ],
    "sg:phone":"+90 2163021838729",
    "sg:postcode":"34880",
    "sg:province":"Istanbul",
    "sg:tags":[
        "iron-steel",
        "peoducts"
    ],
    "wof:name":"Palmiye Enerji Ve Baca Muh.mekanik Taahhut Ltd.sti.",
    "wof:placetype":"venue"
},
  "geometry": {"coordinates":[29.1972026825,40.9157752991],"type":"Point"}
}