{
  "type": "Feature",
  "properties": {
    "addr:full":"Perpa Tic. Merkezi B.blok Kat:6 No:609 Okmeydani G?esli Istanbul 34540",
    "addr:housenumber":"kat 6 no 609;?",
    "addr:postcode":"34540",
    "addr:street":"B.Blok;Okmeydani G",
    "iso:country":"TR",
    "sg:address":"Perpa Tic. Merkezi B.blok Kat:6 No:609 Okmeydani",
    "sg:city":"G?esli",
    "sg:classifiers":[
        {
            "category":"Wholesale",
            "subcategory":"Auto Parts",
            "type":"Manufacturing & Wholesale Goods"
        }
    ],
    "sg:phone":"+90 212 222 3040",
    "sg:postcode":"34540",
    "sg:province":"Istanbul",
    "sg:tags":[
        "spare"
    ],
    "wof:name":"Asas-ka Ltd.sti.",
    "wof:placetype":"venue"
},
  "geometry": {"coordinates":[28.9861831665,41.0408554077],"type":"Point"}
}