{
  "type": "Feature",
  "properties": {
    "iso:country":"TR",
    "sg:address":"3.cad.no:61",
    "sg:city":"Ikitelli/K\u00fc\u00e7\u00fck\u00e7ekmece",
    "sg:classifiers":[
        {
            "category":"Health Services",
            "subcategory":"Dentist",
            "type":"Services"
        }
    ],
    "sg:phone":"+90 232 257 6691",
    "sg:postcode":"34670",
    "sg:province":"Izmir",
    "sg:tags":[
        "dental",
        "material"
    ],
    "wof:name":"Umutsan Discilik",
    "wof:placetype":"venue"
},
  "geometry": {"coordinates":[27.0872993469,38.4958992004],"type":"Point"}
}