{
  "type": "Feature",
  "properties": {
    "iso:country":"TR",
    "sg:address":"Merkez :bostanci Yolu No:51/1 Birlik Is Merkezi Y.dudullu. Sube: Isto? 43 Ada No:9 Bagcilar",
    "sg:city":"\u00dcmraniye",
    "sg:classifiers":[
        {
            "category":"Professional",
            "subcategory":"Detective & Security Services",
            "type":"Services"
        }
    ],
    "sg:phone":"+90 21652794314428",
    "sg:province":"Istanbul",
    "sg:tags":[
        "material"
    ],
    "wof:name":"?zg?r G?venlik Otomasyon Ve Kontrol Sistemleri San",
    "wof:placetype":"venue"
},
  "geometry": {"coordinates":[28.840275,41.044971],"type":"Point"}
}