{
  "type": "Feature",
  "properties": {
    "addr:full":"Eseboga Hava Meydani Yolu 14 Km. Pursaklar Ankara 06145",
    "addr:housenumber":"14 km.",
    "addr:postcode":"06145",
    "addr:street":"Meydani Yolu",
    "iso:country":"TR",
    "sg:address":"Eseboga Hava Meydani Yolu 14 Km.",
    "sg:city":"Pursaklar",
    "sg:classifiers":[
        {
            "category":"Utilities",
            "subcategory":"Natural Gas",
            "type":"Services"
        }
    ],
    "sg:phone":"+90 312 328 8547",
    "sg:postcode":"06145",
    "sg:province":"Ankara",
    "sg:tags":[
        "tank-heating-natural"
    ],
    "wof:name":"Selnikel Isitma Klima Cihaz. San. A.s.",
    "wof:placetype":"venue"
},
  "geometry": {"coordinates":[32.8604812622,39.9429283142],"type":"Point"}
}