{
  "type": "Feature",
  "properties": {
    "addr:full":"Org.sanayi Bolgesi 7.cad. No: 20 Meklik Gazi Kayseri",
    "addr:housenumber":"no 20",
    "addr:street":"Meklik Gazi",
    "iso:country":"TR",
    "sg:address":"Org.sanayi Bolgesi 7.cad. No: 20",
    "sg:city":"Meklik Gazi",
    "sg:classifiers":[
        {
            "category":"Home & Garden",
            "subcategory":"Furniture",
            "type":"Retail Goods"
        }
    ],
    "sg:phone":"+90 352 336 7610",
    "sg:province":"Kayseri",
    "sg:tags":[
        "armchair",
        "sofa"
    ],
    "wof:name":"Levinda",
    "wof:placetype":"venue"
},
  "geometry": {"coordinates":[35.4364013672,38.7450408936],"type":"Point"}
}