{
  "type": "Feature",
  "properties": {
    "iso:country":"TR",
    "sg:address":"Firuzkoy Blv. No:194 Avcilar",
    "sg:city":"Kocasinan",
    "sg:classifiers":[
        {
            "category":"Manufacturing",
            "subcategory":"Metals",
            "type":"Manufacturing & Wholesale Goods"
        }
    ],
    "sg:phone":"+90 212 690 4007",
    "sg:postcode":"38010",
    "sg:province":"Istanbul",
    "sg:tags":[
        "aluminium",
        "industry"
    ],
    "wof:name":"Astas Aluminyum San. Tic. A.s.",
    "wof:placetype":"venue"
},
  "geometry": {"coordinates":[28.7024326324,41.0088577271],"type":"Point"}
}