{
  "type": "Feature",
  "properties": {
    "iso:country":"TR",
    "sg:address":"Antalya Yolu Uzeri 2.km.",
    "sg:city":"Sandikli",
    "sg:classifiers":[
        {
            "category":"Manufacturing",
            "subcategory":"Glass & Minerals",
            "type":"Manufacturing & Wholesale Goods"
        }
    ],
    "sg:phone":"+90 272 515 4656",
    "sg:postcode":"25900",
    "sg:province":"Afyon",
    "sg:tags":[
        "glass-mirror"
    ],
    "wof:name":"Cam-aks Cam Profil Nakliyat San.tic.ltd.sti.",
    "wof:placetype":"venue"
},
  "geometry": {"coordinates":[30.5417995453,38.7557983398],"type":"Point"}
}