{
  "type": "Feature",
  "properties": {
    "iso:country":"TR",
    "sg:address":"Beskardesler Sok. No:8",
    "sg:city":"Zeytinburnu",
    "sg:classifiers":[
        {
            "category":"Manufacturing",
            "subcategory":"Textiles",
            "type":"Manufacturing & Wholesale Goods"
        }
    ],
    "sg:phone":"+90 212 582 3392",
    "sg:postcode":"41000",
    "sg:province":"Istanbul",
    "sg:tags":[
        "product"
    ],
    "wof:name":"Kiriscioglu Mensucat Fabrikasi",
    "wof:placetype":"venue"
},
  "geometry": {"coordinates":[28.8420772552,41.0037612915],"type":"Point"}
}