{
  "type": "Feature",
  "properties": {
    "iso:country":"TR",
    "sg:address":"Rafet ?nc?",
    "sg:city":"Ortak?",
    "sg:classifiers":[
        {
            "category":"Government",
            "subcategory":"Office",
            "type":"Public Place"
        }
    ],
    "sg:phone":"+90 364 496 6018",
    "sg:province":"?orum",
    "sg:tags":[
        "municipality"
    ],
    "wof:name":"Asdagul Belediye Baskani",
    "wof:placetype":"venue"
},
  "geometry": {"coordinates":[-78.1781387329,34.9936599731],"type":"Point"}
}