{
  "type": "Feature",
  "properties": {
    "addr:full":"Gimat Toptancilar Sitesi 19.blok No: 580 4.levent Ankara",
    "addr:housenumber":"no",
    "addr:postcode":"4.levent",
    "iso:country":"TR",
    "sg:address":"Gimat Toptancilar Sitesi 19.blok No: 580",
    "sg:city":"4.levent",
    "sg:classifiers":[
        {
            "category":"Food & Beverages",
            "subcategory":"Specialty",
            "type":"Retail Goods"
        }
    ],
    "sg:phone":"+90 312 397 6691",
    "sg:province":"Ankara",
    "sg:tags":[
        "honey"
    ],
    "wof:name":"Tokgoz Food Industry And Trade Co.",
    "wof:placetype":"venue"
},
  "geometry": {"coordinates":[32.8604812622,39.9429283142],"type":"Point"}
}