{
  "type": "Feature",
  "properties": {
    "addr:full":"629. Sk. No:79 Sirinyer Mecidiyekoy Izmir 34387",
    "addr:housenumber":"79",
    "addr:postcode":"34387",
    "addr:street":"629 Sk. No",
    "iso:country":"TR",
    "sg:address":"629. Sk. No:79 Sirinyer",
    "sg:city":"Mecidiyekoy",
    "sg:classifiers":[
        {
            "category":"Manufacturing",
            "subcategory":"Glass & Minerals",
            "type":"Manufacturing & Wholesale Goods"
        }
    ],
    "sg:phone":"+90 232 253 5090",
    "sg:postcode":"34387",
    "sg:province":"Izmir",
    "sg:tags":[
        "glassware"
    ],
    "wof:name":"?amkur Ltd. Sti.",
    "wof:placetype":"venue"
},
  "geometry": {"coordinates":[27.1296863556,38.4186973572],"type":"Point"}
}