{
  "type": "Feature",
  "properties": {
    "addr:full":"Orhaniye M Mesudiye Cad. No: 35 Kasimpasa Bursa 25300",
    "addr:housenumber":"35",
    "addr:postcode":"25300",
    "addr:street":"Mesudiye Cad. No;Bursa",
    "iso:country":"TR",
    "sg:address":"Orhaniye M Mesudiye Cad. No: 35",
    "sg:city":"Kasimpasa",
    "sg:classifiers":[
        {
            "category":"Government",
            "subcategory":"Fire Station",
            "type":"Public Place"
        }
    ],
    "sg:phone":"+90 224 715 8553",
    "sg:postcode":"25300",
    "sg:province":"Bursa",
    "sg:tags":[
        "decoration"
    ],
    "wof:name":"Bedirhan Boya Ve Temizlik Urunerleri Tic",
    "wof:placetype":"venue"
},
  "geometry": {"coordinates":[29.0586109161,40.1844291687],"type":"Point"}
}