{
  "type": "Feature",
  "properties": {
    "iso:country":"TR",
    "sg:address":"Florya 5 Yol Kavsagi Reyhan Cad.sahinler Sok. No:13 Kat:1",
    "sg:city":"Sefakoy",
    "sg:classifiers":[
        {
            "category":"Shopping",
            "subcategory":"Clothing, Apparel, & Fashions",
            "type":"Retail Goods"
        }
    ],
    "sg:phone":"+90 212 425 8484",
    "sg:postcode":"42000",
    "sg:province":"Istanbul",
    "sg:tags":[
        "-",
        "towel",
        "bathrobe"
    ],
    "wof:name":"G & G & A Home Art",
    "wof:placetype":"venue"
},
  "geometry": {"coordinates":[28.9861831665,41.0408554077],"type":"Point"}
}