{
  "type": "Feature",
  "properties": {
    "iso:country":"TR",
    "sg:address":"Burakreis C. No.24/a ?amdibi",
    "sg:city":"Adapazari",
    "sg:classifiers":[
        {
            "category":"Manufacturing",
            "subcategory":"Leather Goods",
            "type":"Manufacturing & Wholesale Goods"
        }
    ],
    "sg:phone":"+90 232 461 1745",
    "sg:postcode":"54100",
    "sg:province":"Izmir",
    "sg:tags":[
        "machine"
    ],
    "wof:name":"Dermaksan Deri Mak.san.ltd.sti.",
    "wof:placetype":"venue"
},
  "geometry": {"coordinates":[27.1296863556,38.4186973572],"type":"Point"}
}