{
  "type": "Feature",
  "properties": {
    "addr:full":"Valikonagi Cd. No:33 D:6 Sisli Ey\u00fcp Istanbul 34050",
    "addr:housenumber":"no 33 d 6",
    "addr:postcode":"34050",
    "addr:street":"Valikonagi Cd.",
    "iso:country":"TR",
    "sg:address":"Valikonagi Cd. No:33 D:6 Sisli",
    "sg:city":"Ey\u00fcp",
    "sg:classifiers":[
        {
            "category":"Organizations",
            "subcategory":"Membership Organization",
            "type":"Services"
        }
    ],
    "sg:phone":"+90 212 225 0760",
    "sg:postcode":"34050",
    "sg:province":"Istanbul",
    "wof:name":"Istanbul Avukatlar Dernegi",
    "wof:placetype":"venue"
},
  "geometry": {"coordinates":[28.9861831665,41.0408554077],"type":"Point"}
}