{
  "type": "Feature",
  "properties": {
    "iso:country":"TR",
    "sg:address":"M.akif Ersoy Cad. Kinay Bldg. P.o.box:12",
    "sg:city":"Bandirma",
    "sg:classifiers":[
        {
            "category":"Freight",
            "type":"Transportation"
        }
    ],
    "sg:phone":"+90 266 718 3020",
    "sg:postcode":"10200",
    "sg:province":"Balikesir",
    "sg:tags":[
        "agent",
        "shipping",
        "broker"
    ],
    "wof:name":"A.riza Kinay Vapur Acenteligi Ve Tic. A.s.",
    "wof:placetype":"venue"
},
  "geometry": {"coordinates":[27.883301,39.6521],"type":"Point"}
}