{
  "type": "Feature",
  "properties": {
    "iso:country":"TR",
    "sg:address":"Piyalepasa Mh. G?eltepe Sk. No:16/a Kasimpasa",
    "sg:city":"Ineg?l",
    "sg:classifiers":[
        {
            "category":"Wholesale",
            "subcategory":"Home Furnishings",
            "type":"Manufacturing & Wholesale Goods"
        }
    ],
    "sg:phone":"+90 212 235 1241",
    "sg:province":"Istanbul",
    "sg:tags":[
        "furniture"
    ],
    "wof:name":"?eliksan Mobilya",
    "wof:placetype":"venue"
},
  "geometry": {"coordinates":[28.9661808014,41.0345916748],"type":"Point"}
}