{
  "type": "Feature",
  "properties": {
    "addr:full":"Esenyurt Evren Oto San.16.blok No:10 Esenyurt Ikitelli/K\u00fc\u00e7\u00fck\u00e7ekmece Istanbul 34670",
    "addr:housenumber":"no 10",
    "addr:postcode":"34670",
    "iso:country":"TR",
    "sg:address":"Esenyurt Evren Oto San.16.blok No:10 Esenyurt",
    "sg:city":"Ikitelli/K\u00fc\u00e7\u00fck\u00e7ekmece",
    "sg:classifiers":[
        {
            "category":"Manufacturing",
            "subcategory":"Tools & Machinery",
            "type":"Manufacturing & Wholesale Goods"
        }
    ],
    "sg:phone":"+90 212 672 5294",
    "sg:postcode":"34670",
    "sg:province":"Istanbul",
    "sg:tags":[
        "machine",
        "industry"
    ],
    "wof:name":"Promak Mechanical Seals",
    "wof:placetype":"venue"
},
  "geometry": {"coordinates":[28.9759254456,41.0123786926],"type":"Point"}
}