{
  "type": "Feature",
  "properties": {
    "iso:country":"TR",
    "sg:address":"Hurriyet Carsisi Kat:3 No:364-365",
    "sg:city":"Mahmutpasa",
    "sg:classifiers":[
        {
            "category":"Shopping",
            "subcategory":"Clothing, Apparel, & Fashions",
            "type":"Retail Goods"
        }
    ],
    "sg:phone":"+90 212 511 6809",
    "sg:postcode":"60100",
    "sg:province":"Istanbul",
    "sg:tags":[
        "woman",
        "wear"
    ],
    "wof:name":"Ags Artanlar Textil Ltd.sti.",
    "wof:placetype":"venue"
},
  "geometry": {"coordinates":[28.9759254456,41.0123786926],"type":"Point"}
}