{
  "type": "Feature",
  "properties": {
    "addr:full":"Gursel Mah. Nurtac Cad. No:74 Kagithane Istanbul 34406",
    "addr:housenumber":"74",
    "addr:postcode":"34406",
    "addr:street":"Gursel Mah. Nurtac Cad. No;Istanbul",
    "iso:country":"TR",
    "sg:address":"Gursel Mah. Nurtac Cad. No:74",
    "sg:city":"Kagithane",
    "sg:classifiers":[
        {
            "category":"Shopping",
            "subcategory":"Party Supplies",
            "type":"Retail Goods"
        }
    ],
    "sg:phone":"+90 212 321 0409",
    "sg:postcode":"34406",
    "sg:province":"Istanbul",
    "sg:tags":[
        "sound",
        "light",
        "system"
    ],
    "wof:name":"Csg Tanitim Organizasyon Ltd.sti.",
    "wof:placetype":"venue"
},
  "geometry": {"coordinates":[28.971113205,41.0742645264],"type":"Point"}
}