{
  "type": "Feature",
  "properties": {
    "addr:full":"Nuripasa Mah. 14.sok. 25 Yolcu Is Hani Kat.4/86 Zeytinburnu \u00c7orlu Istanbul",
    "addr:housenumber":"25;86",
    "addr:street":"Nuripasa Mah. 14.Sok;Zeytinburnu",
    "iso:country":"TR",
    "sg:address":"Nuripasa Mah. 14.sok. 25 Yolcu Is Hani Kat.4/86 Zeytinburnu",
    "sg:city":"\u00c7orlu",
    "sg:classifiers":[
        {
            "category":"Social Services",
            "subcategory":"Job Training",
            "type":"Services"
        }
    ],
    "sg:phone":"+90 212 679 0122",
    "sg:province":"Istanbul",
    "sg:tags":[
        "tannery"
    ],
    "wof:name":"Hil-teks Deri San. Ve Tic. Ltd. Sti.",
    "wof:placetype":"venue"
},
  "geometry": {"coordinates":[28.9021892548,40.9946517944],"type":"Point"}
}