{
  "type": "Feature",
  "properties": {
    "iso:country":"TR",
    "sg:address":"Gonen Belediyesi",
    "sg:city":"Gonen",
    "sg:classifiers":[
        {
            "category":"Farming",
            "subcategory":"Farm & Veterinary Services",
            "type":"Manufacturing & Wholesale Goods"
        }
    ],
    "sg:phone":"+90 266768184576",
    "sg:postcode":"32090",
    "sg:province":"Balikesir",
    "sg:tags":[
        "clinic"
    ],
    "wof:name":"Ahmet Duzer",
    "wof:placetype":"venue"
},
  "geometry": {"coordinates":[27.8833007812,39.6520996094],"type":"Point"}
}