{
  "type": "Feature",
  "properties": {
    "iso:country":"TR",
    "sg:address":"Strazburg Cd. No:30/b Sihhiye",
    "sg:city":"Maltepe",
    "sg:classifiers":[
        {
            "category":"Wholesale",
            "subcategory":"Books, Periodicals, & Newspapers",
            "type":"Manufacturing & Wholesale Goods"
        }
    ],
    "sg:phone":"+90 312 229 6397",
    "sg:postcode":"01000",
    "sg:province":"Ankara",
    "sg:tags":[
        "house",
        "publishing"
    ],
    "wof:name":"Sistem Ofset Basim Yayinci. San. Tic. Ltd. Sti.",
    "wof:placetype":"venue"
},
  "geometry": {"coordinates":[32.8544502258,39.9289398193],"type":"Point"}
}