{
  "type": "Feature",
  "properties": {
    "iso:country":"TR",
    "sg:address":"Kazimkarabekir Cad. No:41 Alibeykoy-fatih",
    "sg:city":"Caglayan",
    "sg:classifiers":[
        {
            "category":"Manufacturing",
            "subcategory":"Glass & Minerals",
            "type":"Manufacturing & Wholesale Goods"
        }
    ],
    "sg:phone":"+90 212691012528",
    "sg:postcode":"07600",
    "sg:province":"Istanbul",
    "sg:tags":[
        "glassware"
    ],
    "wof:name":"Kale Cam Ve Seramik San. Ve Tic. A.s.",
    "wof:placetype":"venue"
},
  "geometry": {"coordinates":[28.9469738007,41.0676765442],"type":"Point"}
}