{
  "type": "Feature",
  "properties": {
    "addr:full":"Calikusu Sok. No: 16 1.levent Istanbul 34330",
    "addr:housenumber":"no;1.levent",
    "addr:postcode":"34330",
    "addr:street":"Calikusu Sok.;Istanbul",
    "iso:country":"TR",
    "sg:address":"Calikusu Sok. No: 16 1.levent",
    "sg:city":"Istanbul",
    "sg:classifiers":[
        {
            "category":"Travel",
            "subcategory":"Travel Agent",
            "type":"Entertainment"
        }
    ],
    "sg:phone":"+90 902 122 8340",
    "sg:province":"34330",
    "sg:website":"www.ulusoytravel.com",
    "wof:name":"Ulusoy Tourism Travel Co.",
    "wof:placetype":"venue"
},
  "geometry": {"coordinates":[29.0142345428,41.0827636719],"type":"Point"}
}