{
  "type": "Feature",
  "properties": {
    "iso:country":"TR",
    "sg:address":"Resit Galip Cad.filistin Sok. 19/1",
    "sg:city":"G.o.p.",
    "sg:classifiers":[
        {
            "category":"Building & Trades",
            "subcategory":"Landscaping Services",
            "type":"Services"
        }
    ],
    "sg:phone":"+90 312 446 0912",
    "sg:province":"Ankara",
    "sg:tags":[
        "landscape"
    ],
    "wof:name":"Ozler Peysaj",
    "wof:placetype":"venue"
},
  "geometry": {"coordinates":[32.8690376282,39.8840484619],"type":"Point"}
}