{
  "type": "Feature",
  "properties": {
    "addr:full":"Musalla Baglari Bayhanli Sk. No:80 Ostim Konya 06120",
    "addr:housenumber":"80",
    "addr:postcode":"06120",
    "addr:street":"Bayhanli Sk. No",
    "iso:country":"TR",
    "sg:address":"Musalla Baglari Bayhanli Sk. No:80",
    "sg:city":"Ostim",
    "sg:classifiers":[
        {
            "category":"Wholesale",
            "subcategory":"Medical Equipment & Supplies",
            "type":"Manufacturing & Wholesale Goods"
        }
    ],
    "sg:phone":"+90 332 233 6331",
    "sg:postcode":"06120",
    "sg:province":"Konya",
    "wof:name":"Renal Ltd. Sti.",
    "wof:placetype":"venue"
},
  "geometry": {"coordinates":[33.0667152405,39.2111282349],"type":"Point"}
}