{
  "type": "Feature",
  "properties": {
    "addr:full":"Karaoglanoglu Cd. No:19 Sirinevler Yenisehir/konak Istanbul 35110",
    "addr:housenumber":"no 19",
    "addr:postcode":"35110",
    "addr:street":"Karaoglanoglu Cd.",
    "iso:country":"TR",
    "sg:address":"Karaoglanoglu Cd. No:19 Sirinevler",
    "sg:city":"Yenisehir/konak",
    "sg:classifiers":[
        {
            "category":"Wholesale",
            "subcategory":"Durable Goods & Equipment",
            "type":"Manufacturing & Wholesale Goods"
        }
    ],
    "sg:phone":"+90 212 556 9866",
    "sg:postcode":"35110",
    "sg:province":"Istanbul",
    "sg:tags":[
        "consumer"
    ],
    "wof:name":"Poyraz Day. T?k. Mal. San.",
    "wof:placetype":"venue"
},
  "geometry": {"coordinates":[28.9861831665,41.0408554077],"type":"Point"}
}