{
  "type": "Feature",
  "properties": {
    "iso:country":"TR",
    "sg:address":"Intizam Mh. Yatik Sk. Tekmenler Apt. No:s1",
    "sg:city":"Seyhan",
    "sg:classifiers":[
        {
            "category":"Manufacturing",
            "subcategory":"Chemicals & Compounds",
            "type":"Manufacturing & Wholesale Goods"
        }
    ],
    "sg:phone":"+90 224 222 6234",
    "sg:postcode":"01120",
    "sg:province":"Bursa",
    "sg:tags":[
        "pharmaceutical"
    ],
    "wof:name":"Ilsan Ila? San. Tic. A.s.",
    "wof:placetype":"venue"
},
  "geometry": {"coordinates":[29.0580043793,40.1947555542],"type":"Point"}
}