{
  "type": "Feature",
  "properties": {
    "addr:full":"Serafettin Cad. Akifpasa Sok. Hayat Is Hani No 22/306 Konya",
    "addr:housenumber":"306",
    "addr:street":"Serafettin Cad. Akifpasa Sok.",
    "iso:country":"TR",
    "sg:address":"Serafettin Cad. Akifpasa Sok. Hayat Is Hani No",
    "sg:city":"22/306",
    "sg:classifiers":[
        {
            "category":"Wholesale",
            "subcategory":"Medical Equipment & Supplies",
            "type":"Manufacturing & Wholesale Goods"
        }
    ],
    "sg:phone":"+90 332 352 8455",
    "sg:province":"Konya",
    "wof:name":"Global Medikal",
    "wof:placetype":"venue"
},
  "geometry": {"coordinates":[32.8623580933,38.0141410828],"type":"Point"}
}