{
  "type": "Feature",
  "properties": {
    "addr:full":"Abdi Ipekci Cad. Ozel Idare Is Merkezi No:227-228-201-202-203 Bayrampasa Alsancak Istanbul 01365",
    "addr:postcode":"01365",
    "addr:street":"Ipekci Cad. Ozel Idare;No",
    "iso:country":"TR",
    "sg:address":"Abdi Ipekci Cad. Ozel Idare Is Merkezi No:227-228-201-202-203 Bayrampasa",
    "sg:city":"Alsancak",
    "sg:classifiers":[
        {
            "category":"Manufacturing",
            "subcategory":"Chemicals & Compounds",
            "type":"Manufacturing & Wholesale Goods"
        }
    ],
    "sg:phone":"+90 212 674 4646",
    "sg:postcode":"01365",
    "sg:province":"Istanbul",
    "sg:tags":[
        "pharmaceutical"
    ],
    "wof:name":"Aroma & Polifarma Ilac.san.tic.a.s.",
    "wof:placetype":"venue"
},
  "geometry": {"coordinates":[28.9759254456,41.0123786926],"type":"Point"}
}