{
  "type": "Feature",
  "properties": {
    "addr:full":"H?riyet Cad. No: 437 Nazilli Aydin 65600",
    "addr:postcode":"437;65600",
    "addr:street":"Riyet Cad. No",
    "iso:country":"TR",
    "sg:address":"H?riyet Cad. No: 437",
    "sg:city":"Nazilli",
    "sg:classifiers":[
        {
            "category":"Manufacturing",
            "subcategory":"Food",
            "type":"Manufacturing & Wholesale Goods"
        }
    ],
    "sg:phone":"+90 256 313 5157",
    "sg:postcode":"65600",
    "sg:province":"Aydin",
    "sg:tags":[
        "wholesaler"
    ],
    "wof:name":"?etiner San. Tic. Ltd. Sti.",
    "wof:placetype":"venue"
},
  "geometry": {"coordinates":[32.6890640259,40.1948318481],"type":"Point"}
}