{
  "type": "Feature",
  "properties": {
    "addr:full":"Eski Golcuk Yolu 5.km. Kabatas Kocaeli 34427",
    "addr:housenumber":"5.km kabatas",
    "addr:postcode":"34427",
    "addr:street":"Eski Golcuk Yolu",
    "iso:country":"TR",
    "sg:address":"Eski Golcuk Yolu 5.km.",
    "sg:city":"Kabatas",
    "sg:classifiers":[
        {
            "category":"Manufacturing",
            "subcategory":"Tools & Machinery",
            "type":"Manufacturing & Wholesale Goods"
        }
    ],
    "sg:phone":"+90 262 335 3979",
    "sg:postcode":"34427",
    "sg:province":"Kocaeli",
    "sg:tags":[
        "machine",
        "industry"
    ],
    "wof:name":"Birmak Makina Imalati",
    "wof:placetype":"venue"
},
  "geometry": {"coordinates":[29.881521225,40.8532714844],"type":"Point"}
}