{
  "type": "Feature",
  "properties": {
    "iso:country":"TR",
    "sg:address":"Enver Demir",
    "sg:city":"Eskil",
    "sg:classifiers":[
        {
            "category":"Government",
            "subcategory":"Office",
            "type":"Public Place"
        }
    ],
    "sg:phone":"+90 312 244 3232",
    "sg:postcode":"68800",
    "sg:province":"Ankara",
    "sg:tags":[
        "municipality"
    ],
    "wof:name":"Etimesgut Belediye Baskani",
    "wof:placetype":"venue"
},
  "geometry": {"coordinates":[29.2442340851,40.9022102356],"type":"Point"}
}