{
  "type": "Feature",
  "properties": {
    "iso:country":"TR",
    "sg:address":"In??caddesi, 31/7 - Taksim",
    "sg:city":"Kizilay",
    "sg:classifiers":[
        {
            "category":"Shopping",
            "subcategory":"Stationery & Office Supplies",
            "type":"Retail Goods"
        }
    ],
    "sg:phone":"+90 212 249 8602",
    "sg:postcode":"06650",
    "sg:province":"Istanbul",
    "sg:website":"onkagency.com",
    "wof:name":"Onk Ajans Ltd",
    "wof:placetype":"venue"
},
  "geometry": {"coordinates":[28.976557,41.032806],"type":"Point"}
}