{
  "type": "Feature",
  "properties": {
    "addr:full":"Istiklal Mah.sair Nedim Sok. No.36 Dukkan 1 \u00dcmraniye Istanbul 03650",
    "addr:housenumber":"no.36;1",
    "addr:postcode":"03650",
    "addr:street":"Nedim Sok.;Dukkan",
    "iso:country":"TR",
    "sg:address":"Istiklal Mah.sair Nedim Sok. No.36 Dukkan 1",
    "sg:city":"\u00dcmraniye",
    "sg:classifiers":[
        {
            "category":"Professional",
            "type":"Services"
        }
    ],
    "sg:phone":"+90 216329734383",
    "sg:postcode":"03650",
    "sg:province":"Istanbul",
    "sg:tags":[
        "catering"
    ],
    "wof:name":"Zemzem Hazir Yemek Ve Gida San.tic.ltd.sti.",
    "wof:placetype":"venue"
},
  "geometry": {"coordinates":[28.9861831665,41.0408554077],"type":"Point"}
}