{
  "type": "Feature",
  "properties": {
    "addr:full":"Sanayi ?arsisi G?d? Sok. No:18 \u00dcmraniye Konya 81260",
    "addr:housenumber":"?;? d ?;no 18",
    "addr:postcode":"81260",
    "addr:street":"Sanayi;Arsisi G;Sok.",
    "iso:country":"TR",
    "sg:address":"Sanayi ?arsisi G?d? Sok. No:18",
    "sg:city":"\u00dcmraniye",
    "sg:classifiers":[
        {
            "category":"Manufacturing",
            "subcategory":"Tools & Machinery",
            "type":"Manufacturing & Wholesale Goods"
        }
    ],
    "sg:phone":"+90 332 233 2174",
    "sg:postcode":"81260",
    "sg:province":"Konya",
    "sg:tags":[
        "machine",
        "industry"
    ],
    "wof:name":"Akdogan Konvey?r Bant Sanayi",
    "wof:placetype":"venue"
},
  "geometry": {"coordinates":[32.4990272522,37.8715362549],"type":"Point"}
}