{
  "type": "Feature",
  "properties": {
    "addr:full":"Demirciler Sitesi, 10.cad. No.52-54 Zeytinburnu Istanbul 41000",
    "addr:housenumber":"no.52-54",
    "addr:postcode":"41000",
    "addr:street":"Demirciler;10.Cad",
    "iso:country":"TR",
    "sg:address":"Demirciler Sitesi, 10.cad. No.52-54",
    "sg:city":"Zeytinburnu",
    "sg:classifiers":[
        {
            "category":"Manufacturing",
            "subcategory":"Building Materials",
            "type":"Manufacturing & Wholesale Goods"
        }
    ],
    "sg:phone":"+90 212 558 1996",
    "sg:postcode":"41000",
    "sg:province":"Istanbul",
    "sg:tags":[
        "floor-wall",
        "covering"
    ],
    "wof:name":"Ulas Metal San. Dis Tic.ltd.sti.",
    "wof:placetype":"venue"
},
  "geometry": {"coordinates":[28.8070316315,41.0673942566],"type":"Point"}
}