{
  "type": "Feature",
  "properties": {
    "addr:full":"Davutpasa Kisla Cd. Firin Yolu Sk. No:1 Topkapi Kartal Istanbul 34873",
    "addr:postcode":"34873",
    "addr:street":"Kisla Cd. Firin Yolu Sk. No 1 Topkapi",
    "iso:country":"TR",
    "sg:address":"Davutpasa Kisla Cd. Firin Yolu Sk. No:1 Topkapi",
    "sg:city":"Kartal",
    "sg:classifiers":[
        {
            "category":"Manufacturing",
            "subcategory":"Tools & Machinery",
            "type":"Manufacturing & Wholesale Goods"
        }
    ],
    "sg:phone":"+90 212 544 0270",
    "sg:postcode":"34873",
    "sg:province":"Istanbul",
    "sg:tags":[
        "machine",
        "industry"
    ],
    "wof:name":"Camis Makina Kalip San. A.s.",
    "wof:placetype":"venue"
},
  "geometry": {"coordinates":[28.9066238403,41.0281181335],"type":"Point"}
}