{
  "type": "Feature",
  "properties": {
    "addr:full":"Eregli Yolu Biriketciler San.uzungol Sok. No:9 Melikgazi Konya 38030",
    "addr:housenumber":"biriketciler;no",
    "addr:postcode":"38030",
    "addr:street":"Eregli Yolu;San.Uzungol Sok.;Melikgazi",
    "iso:country":"TR",
    "sg:address":"Eregli Yolu Biriketciler San.uzungol Sok. No:9",
    "sg:city":"Melikgazi",
    "sg:classifiers":[
        {
            "category":"Utilities",
            "subcategory":"Electric",
            "type":"Services"
        }
    ],
    "sg:phone":"+90 332 355 5765",
    "sg:postcode":"38030",
    "sg:province":"Konya",
    "sg:tags":[
        "energy",
        "solar"
    ],
    "wof:name":"Derya G?nes Kollektorleri A.s.",
    "wof:placetype":"venue"
},
  "geometry": {"coordinates":[32.499027,37.871536],"type":"Point"}
}