{
  "type": "Feature",
  "properties": {
    "iso:country":"TR",
    "sg:address":"Bagdat Cad.no:179/170 Kartal-maltepe",
    "sg:city":"Sisli",
    "sg:classifiers":[
        {
            "category":"Freight",
            "type":"Transportation"
        }
    ],
    "sg:phone":"+90 216 399 7830",
    "sg:postcode":"80260",
    "sg:province":"Istanbul",
    "sg:tags":[
        "packing",
        "industry"
    ],
    "wof:name":"Yagiz Ambalaj Klise Grafik",
    "wof:placetype":"venue"
},
  "geometry": {"coordinates":[29.1478233337,40.9155654907],"type":"Point"}
}