{
  "type": "Feature",
  "properties": {
    "iso:country":"TR",
    "sg:address":"Yasar Inan",
    "sg:city":"Elmadag",
    "sg:classifiers":[
        {
            "category":"Government",
            "subcategory":"Office",
            "type":"Public Place"
        }
    ],
    "sg:phone":"+90 286 512 1044",
    "sg:postcode":"65900",
    "sg:province":"?anakkale",
    "sg:tags":[
        "municipality"
    ],
    "wof:name":"Lapseki Belediye Baskani",
    "wof:placetype":"venue"
},
  "geometry": {"coordinates":[43.6218986511,38.1232299805],"type":"Point"}
}