{
  "type": "Feature",
  "properties": {
    "addr:full":"Kazanci Yokusu Ak Apt. 20/5 Taksim Istanbul 24040",
    "addr:postcode":"24040",
    "iso:country":"TR",
    "sg:address":"Kazanci Yokusu Ak Apt. 20/5",
    "sg:city":"Taksim",
    "sg:classifiers":[
        {
            "category":"Airport",
            "subcategory":"International",
            "type":"Transportation"
        }
    ],
    "sg:phone":"+90 212 292 2398",
    "sg:postcode":"24040",
    "sg:province":"Istanbul",
    "wof:name":"Ifs Uluslararasi Tasimacilik Gumrukleme Ic Ve Dis Tic.",
    "wof:placetype":"venue"
},
  "geometry": {"coordinates":[28.9861831665,41.0408554077],"type":"Point"}
}