{
  "type": "Feature",
  "properties": {
    "addr:full":"Bursa ?nye Bursa 52300",
    "addr:postcode":"52300",
    "iso:country":"TR",
    "sg:address":"Bursa",
    "sg:city":"?nye",
    "sg:classifiers":[
        {
            "category":"Farming",
            "subcategory":"Fish & Marine Products",
            "type":"Manufacturing & Wholesale Goods"
        }
    ],
    "sg:phone":"+90 224 441 3196",
    "sg:postcode":"52300",
    "sg:province":"Bursa",
    "sg:tags":[
        "automotive"
    ],
    "wof:name":"Fss Fren Sistem. San. Ltd. Sti.",
    "wof:placetype":"venue"
},
  "geometry": {"coordinates":[29.0050125122,40.2335891724],"type":"Point"}
}