{
  "type": "Feature",
  "properties": {
    "iso:country":"TR",
    "sg:address":"Kiravasi Mevkii 78-2 Kemalpasa",
    "sg:city":"G.o.pasa",
    "sg:classifiers":[
        {
            "category":"Wholesale",
            "subcategory":"Plants",
            "type":"Manufacturing & Wholesale Goods"
        }
    ],
    "sg:phone":"+90 232 877 0241",
    "sg:province":"Izmir",
    "sg:tags":[
        "natural",
        "spice"
    ],
    "wof:name":"Mcormick Baharatlari",
    "wof:placetype":"venue"
},
  "geometry": {"coordinates":[27.261965,38.435955],"type":"Point"}
}