{
  "type": "Feature",
  "properties": {
    "iso:country":"TR",
    "sg:address":"Il Kontrol Laboratuvari",
    "sg:city":"Gonen",
    "sg:classifiers":[
        {
            "category":"Farming",
            "subcategory":"Farm & Veterinary Services",
            "type":"Manufacturing & Wholesale Goods"
        }
    ],
    "sg:phone":"+90 2222301328226",
    "sg:postcode":"32090",
    "sg:province":"Eskisehir",
    "sg:tags":[
        "veterinarian"
    ],
    "wof:name":"Ahmet Gokhan Senol",
    "wof:placetype":"venue"
},
  "geometry": {"coordinates":[30.5175457001,39.7700805664],"type":"Point"}
}