{
  "type": "Feature",
  "properties": {
    "addr:full":"M?derris Salih R?st? Sokak No:17 Emre Apt. D:1 2. Ulus Besiktas Istanbul 80200",
    "addr:housenumber":"no 17;1 2",
    "addr:postcode":"80200",
    "addr:street":"Derris;St ? Sokak;Emre Apt. D;Ulus",
    "iso:country":"TR",
    "sg:address":"M?derris Salih R?st? Sokak No:17 Emre Apt. D:1 2. Ulus",
    "sg:city":"Besiktas",
    "sg:classifiers":[
        {
            "category":"Communications",
            "subcategory":"Film & Video Production",
            "type":"Services"
        }
    ],
    "sg:phone":"+90 212 324 0521",
    "sg:postcode":"80200",
    "sg:province":"Istanbul",
    "sg:tags":[
        "-"
    ],
    "wof:name":"Contact Production",
    "wof:placetype":"venue"
},
  "geometry": {"coordinates":[28.9759254456,41.0123786926],"type":"Point"}
}