{
  "type": "Feature",
  "properties": {
    "addr:full":"Alemdag Yolu Tasdelen Sapagi Karsisi Sultanciftligi ?mraniye Rami Istanbul 34140",
    "addr:housenumber":"tasdelen",
    "addr:postcode":"34140",
    "addr:street":"Alemdag Yolu",
    "iso:country":"TR",
    "sg:address":"Alemdag Yolu Tasdelen Sapagi Karsisi Sultanciftligi ?mraniye",
    "sg:city":"Rami",
    "sg:classifiers":[
        {
            "category":"Manufacturing",
            "subcategory":"Rubber & Plastics",
            "type":"Manufacturing & Wholesale Goods"
        }
    ],
    "sg:phone":"+90 216 312 1344",
    "sg:postcode":"34140",
    "sg:province":"Istanbul",
    "sg:tags":[
        "industry"
    ],
    "wof:name":"?ge-pipsan Plastik San. Tic. A.s.",
    "wof:placetype":"venue"
},
  "geometry": {"coordinates":[28.8713321686,40.9776382446],"type":"Point"}
}