{
  "type": "Feature",
  "properties": {
    "addr:full":"Y.san. Sitesi C-7 Blok No:10-11-12 Nazilli Beylikd?? 34900 Aydin",
    "addr:housenumber":"blok",
    "addr:postcode":"10-11-12;beylikd ? ? 34900",
    "addr:street":"C-7;No",
    "iso:country":"TR",
    "sg:address":"Y.san. Sitesi C-7 Blok No:10-11-12 Nazilli",
    "sg:city":"Beylikd?? 34900",
    "sg:classifiers":[
        {
            "category":"Wholesale",
            "subcategory":"Auto Parts",
            "type":"Manufacturing & Wholesale Goods"
        }
    ],
    "sg:phone":"+90 256 316 2312",
    "sg:province":"Aydin",
    "sg:tags":[
        "spare"
    ],
    "wof:name":"Ozova Ticaret",
    "wof:placetype":"venue"
},
  "geometry": {"coordinates":[28.3244304657,37.9104614258],"type":"Point"}
}