{
  "type": "Feature",
  "properties": {
    "addr:full":"Haci Omersabanci Cad. 14/b Yeni Baraj Mah. 07100 Adana",
    "addr:housenumber":"14 / b;mah.",
    "addr:postcode":"07100",
    "addr:street":"Omersabanci Cad.;Yeni Baraj",
    "iso:country":"TR",
    "sg:address":"Haci Omersabanci Cad. 14/b Yeni Baraj Mah.",
    "sg:city":"07100",
    "sg:classifiers":[
        {
            "category":"Shopping",
            "subcategory":"Optical Goods",
            "type":"Retail Goods"
        }
    ],
    "sg:phone":"+90 322 228 4082",
    "sg:province":"Adana",
    "sg:tags":[
        "material"
    ],
    "wof:name":"Ce&ay Ozel Saglik Medikal Ltd.sti.",
    "wof:placetype":"venue"
},
  "geometry": {"coordinates":[35.3201179504,37.0221939087],"type":"Point"}
}