{
  "type": "Feature",
  "properties": {
    "iso:country":"TR",
    "sg:address":"Y?yil Mh. Massit Sit. 2. Cd. No:170 Bagcilar",
    "sg:city":"Bak\u0131rk\u00f6y",
    "sg:classifiers":[
        {
            "category":"Shopping",
            "subcategory":"Stationery & Office Supplies",
            "type":"Retail Goods"
        }
    ],
    "sg:phone":"+90 212 629 0007",
    "sg:province":"Istanbul",
    "sg:tags":[
        "paper"
    ],
    "wof:name":"Interfax Kagit?ilik",
    "wof:placetype":"venue"
},
  "geometry": {"coordinates":[28.8402748108,41.0449714661],"type":"Point"}
}