{
  "type": "Feature",
  "properties": {
    "iso:country":"TR",
    "sg:address":"M.k.e.karsisi Seymen Bahcecik",
    "sg:city":"Ikitelli",
    "sg:classifiers":[
        {
            "category":"Wholesale",
            "subcategory":"Auto Parts",
            "type":"Manufacturing & Wholesale Goods"
        }
    ],
    "sg:phone":"+90 262 343 2236",
    "sg:postcode":"34306",
    "sg:province":"Kocaeli",
    "sg:tags":[
        "spare"
    ],
    "wof:name":"Bimsan Birlik Makina M?h.tic.san.ltd.sti.",
    "wof:placetype":"venue"
},
  "geometry": {"coordinates":[29.9345855713,40.7669563293],"type":"Point"}
}