{
  "type": "Feature",
  "properties": {
    "addr:full":"Babiali Caddesi No:21 - Emin?? Istanbul 64020 Istanbul",
    "addr:housenumber":"no 21;? ?",
    "addr:postcode":"64020",
    "addr:street":"Babiali Caddesi;Emin;Istanbul",
    "iso:country":"TR",
    "sg:address":"Babiali Caddesi No:21 - Emin?? Istanbul",
    "sg:city":"64020",
    "sg:classifiers":[
        {
            "category":"Government",
            "subcategory":"Post Office",
            "type":"Public Place"
        }
    ],
    "sg:phone":"+90 212 511 5184",
    "sg:province":"Istanbul",
    "sg:tags":[
        "notary"
    ],
    "wof:name":"Istanbul 18 Noterligi",
    "wof:placetype":"venue"
},
  "geometry": {"coordinates":[28.9861793518,41.040851593],"type":"Point"}
}