{
  "type": "Feature",
  "properties": {
    "iso:country":"TR",
    "sg:address":"Istoc 22.ada No:28-30 Mahmutbey",
    "sg:city":"Merter",
    "sg:classifiers":[
        {
            "category":"Shopping",
            "subcategory":"Shoes",
            "type":"Retail Goods"
        }
    ],
    "sg:phone":"+90 212659396566",
    "sg:province":"Istanbul",
    "wof:name":"Elit Ic Ve Dis Ticaret Ltd.",
    "wof:placetype":"venue"
},
  "geometry": {"coordinates":[28.820398,41.057652],"type":"Point"}
}