{
  "type": "Feature",
  "properties": {
    "addr:full":"Tasocagi Cd.no:2 Mahmutbey-bagcilar Osmangazi Istanbul 16030",
    "addr:housenumber":"2",
    "addr:postcode":"16030",
    "addr:street":"Cd.No",
    "iso:country":"TR",
    "sg:address":"Tasocagi Cd.no:2 Mahmutbey-bagcilar",
    "sg:city":"Osmangazi",
    "sg:classifiers":[
        {
            "category":"Home & Garden",
            "subcategory":"Kitchen Supply",
            "type":"Retail Goods"
        }
    ],
    "sg:phone":"+90 21244630864",
    "sg:postcode":"16030",
    "sg:province":"Istanbul",
    "sg:tags":[
        "wardrobe"
    ],
    "wof:name":"Nil Yapi Market San. Ve Dis Tic.ltd.sti.",
    "wof:placetype":"venue"
},
  "geometry": {"coordinates":[28.8123207092,41.0490951538],"type":"Point"}
}