{
  "type": "Feature",
  "properties": {
    "iso:country":"TR",
    "sg:address":"Etiler Mah. Kizilirmak Cad.no: 5/b",
    "sg:city":"Sisli",
    "sg:classifiers":[
        {
            "category":"Professional",
            "subcategory":"Detective & Security Services",
            "type":"Services"
        }
    ],
    "sg:phone":"+90 242 321 3041",
    "sg:postcode":"65710",
    "sg:province":"Antalya",
    "sg:tags":[
        "material"
    ],
    "wof:name":"Security Company S.a.",
    "wof:placetype":"venue"
},
  "geometry": {"coordinates":[30.71479,36.898281],"type":"Point"}
}