{
  "type": "Feature",
  "properties": {
    "iso:country":"TR",
    "sg:address":"Balikesir Yolu ?zeri 2. Km",
    "sg:city":"Havran",
    "sg:classifiers":[
        {
            "category":"Food & Beverages",
            "subcategory":"Groceries & Convenience Stores",
            "type":"Retail Goods"
        }
    ],
    "sg:phone":"+90 266 432 3310",
    "sg:postcode":"10560",
    "sg:province":"Balikesir",
    "sg:tags":[
        "product"
    ],
    "wof:name":"E.z.e Zeytincilik Gida San. Tic. A.s.",
    "wof:placetype":"venue"
},
  "geometry": {"coordinates":[27.8833007812,39.6520996094],"type":"Point"}
}