{
  "type": "Feature",
  "properties": {
    "iso:country":"TR",
    "sg:address":"Bostanci Sanayi Sitesi Degirmenyolu Cad. Ilker Sok. 2nci Is Merkezi No:6/20 I?renk? Mah.",
    "sg:city":"Kad\u0131k\u00f6y",
    "sg:classifiers":[
        {
            "category":"Manufacturing",
            "subcategory":"Metals",
            "type":"Manufacturing & Wholesale Goods"
        }
    ],
    "sg:phone":"+90 216 575 2559",
    "sg:postcode":"34752",
    "sg:province":"Istanbul",
    "sg:tags":[
        "processing"
    ],
    "wof:name":"T?reci Makina Ticaret",
    "wof:placetype":"venue"
},
  "geometry": {"coordinates":[29.1114387512,40.9703979492],"type":"Point"}
}