{
  "type": "Feature",
  "properties": {
    "addr:full":"Keresteciler Sitesi Fatih Cad.akasya Sok.can Ishani No:14/2 Merter Istanbul",
    "addr:housenumber":"14 / 2",
    "addr:street":"Ishani No",
    "iso:country":"TR",
    "sg:address":"Keresteciler Sitesi Fatih Cad.akasya Sok.can Ishani No:14/2",
    "sg:city":"Merter",
    "sg:classifiers":[
        {
            "category":"Manufacturing",
            "subcategory":"Textiles",
            "type":"Manufacturing & Wholesale Goods"
        }
    ],
    "sg:phone":"+90 21263749203",
    "sg:province":"Istanbul",
    "sg:tags":[
        "machinery"
    ],
    "wof:name":"Tekstil Market",
    "wof:placetype":"venue"
},
  "geometry": {"coordinates":[28.9861831665,41.0408554077],"type":"Point"}
}