{
  "type": "Feature",
  "properties": {
    "addr:full":"Meydan Yeni Yol Cad. No:104 K?k Tokat",
    "addr:housenumber":"104 k ?",
    "addr:street":"Yeni Yol Cad. No;K Tokat",
    "iso:country":"TR",
    "sg:address":"Meydan Yeni Yol Cad. No:104",
    "sg:city":"K?k",
    "sg:classifiers":[
        {
            "category":"Manufacturing",
            "subcategory":"Food",
            "type":"Manufacturing & Wholesale Goods"
        }
    ],
    "sg:phone":"+90 356 214 8509",
    "sg:province":"Tokat",
    "sg:tags":[
        "wholesaler"
    ],
    "wof:name":"Sekerler Ticaret",
    "wof:placetype":"venue"
},
  "geometry": {"coordinates":[36.5559005737,40.3063011169],"type":"Point"}
}