{
  "type": "Feature",
  "properties": {
    "addr:full":"Huzurevleri Mahallesi 149 Sokak K.senbayrak Sitesi E Blok Zemin Kat Seyhan Adana 01000",
    "addr:housenumber":"k.senbayrak;blok zemin kat",
    "addr:postcode":"01000",
    "addr:street":"Huzurevleri Mahallesi 149 Sokak;E",
    "iso:country":"TR",
    "sg:address":"Huzurevleri Mahallesi 149 Sokak K.senbayrak Sitesi E Blok Zemin Kat",
    "sg:city":"Seyhan",
    "sg:classifiers":[
        {
            "category":"Home & Garden",
            "subcategory":"Building Materials",
            "type":"Retail Goods"
        }
    ],
    "sg:phone":"+90 322 248 6101",
    "sg:postcode":"01000",
    "sg:province":"Adana",
    "sg:tags":[
        "window",
        "door",
        "plastic"
    ],
    "wof:name":"Doraks Plastik Kau?k Metal San Ve Tic Ltd.sti.",
    "wof:placetype":"venue"
},
  "geometry": {"coordinates":[35.3137359619,37.0007171631],"type":"Point"}
}