{
  "type": "Feature",
  "properties": {
    "addr:full":"1145/4 Sok. No:10 Nazilli Izmir 65600",
    "addr:housenumber":"1145 / 4;no 10",
    "addr:postcode":"65600",
    "addr:street":"Sok.;Nazilli Izmir",
    "iso:country":"TR",
    "sg:address":"1145/4 Sok. No:10",
    "sg:city":"Nazilli",
    "sg:classifiers":[
        {
            "category":"Farming",
            "subcategory":"Farm",
            "type":"Manufacturing & Wholesale Goods"
        }
    ],
    "sg:phone":"+90 232 458 9006",
    "sg:postcode":"65600",
    "sg:province":"Izmir",
    "sg:tags":[
        "agricultural",
        "product"
    ],
    "wof:name":"Tarimsan Tarim Urunleri A.s.",
    "wof:placetype":"venue"
},
  "geometry": {"coordinates":[27.1820831299,38.3829727173],"type":"Point"}
}