{
  "type": "Feature",
  "properties": {
    "addr:full":"Marasal Cakmak Mah. Azak Sok. No:35/37 Gungoren Istanbul 33630",
    "addr:housenumber":"no 35 / 37",
    "addr:postcode":"33630",
    "addr:street":"Cakmak Mah. Azak Sok.;Istanbul",
    "iso:country":"TR",
    "sg:address":"Marasal Cakmak Mah. Azak Sok. No:35/37",
    "sg:city":"Gungoren",
    "sg:classifiers":[
        {
            "category":"Manufacturing",
            "subcategory":"Textiles",
            "type":"Manufacturing & Wholesale Goods"
        }
    ],
    "sg:phone":"+90 212 504 3838",
    "sg:postcode":"33630",
    "sg:province":"Istanbul",
    "sg:tags":[
        "cloth",
        "worker"
    ],
    "wof:name":"G?rsu Giyim San. Ve Tic. Ltd.sti.",
    "wof:placetype":"venue"
},
  "geometry": {"coordinates":[28.9759254456,41.0123786926],"type":"Point"}
}