{
  "type": "Feature",
  "properties": {
    "addr:full":"Tersane Cad. F??at Sk. No.12 Karak\u00f6y Istanbul",
    "addr:housenumber":"? ?",
    "addr:street":"Tersane Cad. F;At Sk. No.12 Karakoey",
    "iso:country":"TR",
    "sg:address":"Tersane Cad. F??at Sk. No.12",
    "sg:city":"Karak\u00f6y",
    "sg:classifiers":[
        {
            "category":"Home & Garden",
            "subcategory":"Hardware",
            "type":"Retail Goods"
        }
    ],
    "sg:phone":"+90 212 256 5428",
    "sg:province":"Istanbul",
    "sg:tags":[
        "store"
    ],
    "wof:name":"Kardesler Makina Hirdavat San. Ve Tic.ltd.sti.",
    "wof:placetype":"venue"
},
  "geometry": {"coordinates":[28.9861831665,41.0408554077],"type":"Point"}
}