{
  "type": "Feature",
  "properties": {
    "addr:full":"1335. Sk. No:15/201 Yenimahalle Izmir 15030",
    "addr:housenumber":"15 / 201",
    "addr:postcode":"15030",
    "addr:street":"1335 Sk. No",
    "iso:country":"TR",
    "sg:address":"1335. Sk. No:15/201",
    "sg:city":"Yenimahalle",
    "sg:classifiers":[
        {
            "category":"Shopping",
            "subcategory":"Clothing, Apparel, & Fashions",
            "type":"Retail Goods"
        }
    ],
    "sg:phone":"+90 232 425 8724",
    "sg:postcode":"15030",
    "sg:province":"Izmir",
    "sg:tags":[
        "house"
    ],
    "wof:name":"Nur Modaevi",
    "wof:placetype":"venue"
},
  "geometry": {"coordinates":[27.1369838715,38.4234466553],"type":"Point"}
}