{
  "type": "Feature",
  "properties": {
    "iso:country":"TR",
    "sg:address":"San. Site. 5. Blok Edremit",
    "sg:city":"35250",
    "sg:classifiers":[
        {
            "category":"Freight",
            "type":"Transportation"
        }
    ],
    "sg:phone":"+90 266 373 1052",
    "sg:province":"Balikesir",
    "sg:tags":[
        "packing",
        "industry"
    ],
    "wof:name":"G?ven Teneke Kutu Fabrika.",
    "wof:placetype":"venue"
},
  "geometry": {"coordinates":[27.0182991028,39.5941009521],"type":"Point"}
}