{
  "type": "Feature",
  "properties": {
    "iso:country":"TR",
    "sg:address":"Forbes Cad. No:96/a Sirinyer",
    "sg:city":"Mersin",
    "sg:classifiers":[
        {
            "category":"Professional",
            "subcategory":"Computer Services",
            "type":"Services"
        }
    ],
    "sg:phone":"+90 232 438 3978",
    "sg:postcode":"52750",
    "sg:province":"Izmir",
    "sg:tags":[
        "application",
        "software"
    ],
    "wof:name":"Medya Bilgisayar Ltd.sti.",
    "wof:placetype":"venue"
},
  "geometry": {"coordinates":[27.1423015594,38.4251480103],"type":"Point"}
}