{
  "type": "Feature",
  "properties": {
    "addr:full":"Kemer Mh. 936 Sk. No:4 Atisalani 4.levent Istanbul 80650",
    "addr:housenumber":"4.levent",
    "addr:postcode":"80650",
    "addr:street":"Mh. 936 Sk. No 4 Atisalani",
    "iso:country":"TR",
    "sg:address":"Kemer Mh. 936 Sk. No:4 Atisalani",
    "sg:city":"4.levent",
    "sg:orig_category":"Furniture Supplamentary",
    "sg:phone":"+90 212 562 5340",
    "sg:postcode":"80650",
    "sg:province":"Istanbul",
    "wof:name":"G?lseven Mobilya",
    "wof:placetype":"venue"
},
  "geometry": {"coordinates":[28.8794517517,41.0524482727],"type":"Point"}
}