{
  "type": "Feature",
  "properties": {
    "addr:full":"Vatan Cd. No:110/4 ?aglayan Istanbul",
    "addr:housenumber":"4 ?",
    "iso:country":"TR",
    "sg:address":"Vatan Cd. No:110/4",
    "sg:city":"?aglayan",
    "sg:classifiers":[
        {
            "category":"Manufacturing",
            "subcategory":"Glass & Minerals",
            "type":"Manufacturing & Wholesale Goods"
        }
    ],
    "sg:phone":"+90 212 247 5501",
    "sg:province":"Istanbul",
    "sg:tags":[
        "glass-mirror"
    ],
    "wof:name":"Aktas Cam San. Tic. A.s.",
    "wof:placetype":"venue"
},
  "geometry": {"coordinates":[28.8835372925,41.0352401733],"type":"Point"}
}