{
  "type": "Feature",
  "properties": {
    "iso:country":"TR",
    "sg:address":"Nalbantoglu Bademli Sk. No: 11",
    "sg:city":"Merter",
    "sg:classifiers":[
        {
            "category":"Sports & Exercise",
            "subcategory":"Ski Slope",
            "type":"Entertainment"
        }
    ],
    "sg:phone":"+90 224 224 3979",
    "sg:province":"Bursa",
    "sg:tags":[
        "wear"
    ],
    "wof:name":"Evkoc Tekstil Sanayi Ve Ticaret Ltd. Sti.",
    "wof:placetype":"venue"
},
  "geometry": {"coordinates":[29.063133,40.182796],"type":"Point"}
}