{
  "type": "Feature",
  "properties": {
    "iso:country":"TR",
    "sg:address":"B??dere Cad.?zsezen Is Merkezi No:122 C-blokkat:7 Esentepe",
    "sg:city":"\u00c7ankaya",
    "sg:classifiers":[
        {
            "category":"Shopping",
            "subcategory":"Pharmacy",
            "type":"Retail Goods"
        }
    ],
    "sg:phone":"+90 212 212 1227",
    "sg:province":"Istanbul",
    "sg:tags":[
        "store",
        "drug"
    ],
    "wof:name":"Abdi Ibrahim Ila? San. Ve Tic. A.s.",
    "wof:placetype":"venue"
},
  "geometry": {"coordinates":[28.9861793518,41.040851593],"type":"Point"}
}