{
  "type": "Feature",
  "properties": {
    "addr:full":"Ataevler Mah.nilufer Hatun Cad.muhasebeciler Sit Tabya Sok.a Blk No:1 2 Zeytinburnu Bursa 41000",
    "addr:housenumber":"blk;2",
    "addr:postcode":"41000",
    "addr:street":"Zeytinburnu Bursa",
    "iso:country":"TR",
    "sg:address":"Ataevler Mah.nilufer Hatun Cad.muhasebeciler Sit Tabya Sok.a Blk No:1 2",
    "sg:city":"Zeytinburnu",
    "sg:classifiers":[
        {
            "category":"Manufacturing",
            "subcategory":"Building Materials",
            "type":"Manufacturing & Wholesale Goods"
        }
    ],
    "sg:phone":"+90 224 443 2081",
    "sg:postcode":"41000",
    "sg:province":"Bursa",
    "sg:tags":[
        "lifts-elevators"
    ],
    "wof:name":"Kayiran Asansor",
    "wof:placetype":"venue"
},
  "geometry": {"coordinates":[29.0580043793,40.1947555542],"type":"Point"}
}