{
  "type": "Feature",
  "properties": {
    "addr:full":"I.inonu Blv.c.serif Mh. A.hayat Sigorta Ish. K:4 No:405 Turuncova I?el 07880",
    "addr:housenumber":"4;?",
    "addr:postcode":"07880",
    "addr:street":"Mh. A.Hayat Sigorta Ish. K;No 405 Turuncova I;El",
    "iso:country":"TR",
    "sg:address":"I.inonu Blv.c.serif Mh. A.hayat Sigorta Ish. K:4 No:405",
    "sg:city":"Turuncova",
    "sg:classifiers":[
        {
            "category":"Food & Beverages",
            "subcategory":"Fruits & Vegetables",
            "type":"Retail Goods"
        }
    ],
    "sg:phone":"+90 324 233 1762",
    "sg:postcode":"07880",
    "sg:province":"I?el",
    "sg:tags":[
        "fresh"
    ],
    "wof:name":"Peras Ith. Ihr.ltd.sti.",
    "wof:placetype":"venue"
},
  "geometry": {"coordinates":[30.1224193573,36.3515396118],"type":"Point"}
}