{
  "type": "Feature",
  "properties": {
    "addr:full":"Nal Sok. No:13 Kadikoy Sisli Istanbul 34571",
    "addr:housenumber":"no 13",
    "addr:postcode":"34571",
    "addr:street":"Nal Sok.;Kadikoy Sisli",
    "iso:country":"TR",
    "sg:address":"Nal Sok. No:13 Kadikoy",
    "sg:city":"Sisli",
    "sg:classifiers":[
        {
            "category":"Banks & Credit Unions",
            "subcategory":"Investment Brokerage",
            "type":"Services"
        }
    ],
    "sg:phone":"+90 216 347 4223",
    "sg:postcode":"34571",
    "sg:province":"Istanbul",
    "sg:tags":[
        "course",
        "language"
    ],
    "wof:name":"Newline Yeni Yontem",
    "wof:placetype":"venue"
},
  "geometry": {"coordinates":[29.0280685425,40.9909858704],"type":"Point"}
}