{
  "type": "Feature",
  "properties": {
    "addr:full":"Ege Tic. Ismerk. 1203/4. Sk. No:1/b Yenisehir Izmir 31750",
    "addr:housenumber":"1203 / 4;b",
    "addr:postcode":"31750",
    "addr:street":"Sk. No 1 /",
    "iso:country":"TR",
    "sg:address":"Ege Tic. Ismerk. 1203/4. Sk. No:1/b",
    "sg:city":"Yenisehir",
    "sg:classifiers":[
        {
            "category":"Utilities",
            "subcategory":"Natural Gas",
            "type":"Services"
        }
    ],
    "sg:phone":"+90 232 449 3439",
    "sg:postcode":"31750",
    "sg:province":"Izmir",
    "sg:tags":[
        "tank-heating-natural"
    ],
    "wof:name":"Termodinamik Makina San. Tic. A.s.",
    "wof:placetype":"venue"
},
  "geometry": {"coordinates":[27.1423015594,38.4251480103],"type":"Point"}
}