{
  "type": "Feature",
  "properties": {
    "addr:full":"Savas Mh. Ulucami Cd. Sayginlar Ish. No: 10/18 Iskenderun Hatay 31200",
    "addr:housenumber":"10 / 18",
    "addr:postcode":"31200",
    "addr:street":"Cd.;Ish. No",
    "iso:country":"TR",
    "sg:address":"Savas Mh. Ulucami Cd. Sayginlar Ish. No: 10/18",
    "sg:city":"Iskenderun",
    "sg:classifiers":[
        {
            "category":"Home & Garden",
            "subcategory":"Building Materials",
            "type":"Retail Goods"
        }
    ],
    "sg:phone":"+90 326 613 3534",
    "sg:postcode":"31200",
    "sg:province":"Hatay",
    "sg:tags":[
        "stone",
        "natural",
        "marble"
    ],
    "wof:name":"Deko-mer Merm. San. Ltd.sti.",
    "wof:placetype":"venue"
},
  "geometry": {"coordinates":[36.2422409058,36.5966186523],"type":"Point"}
}