{
  "type": "Feature",
  "properties": {
    "iso:country":"TR",
    "sg:address":"Y?etarla Cd. No:35 Zuhuratbaba",
    "sg:city":"Bak\u0131rk\u00f6y",
    "sg:classifiers":[
        {
            "category":"Shopping",
            "subcategory":"Florist",
            "type":"Retail Goods"
        }
    ],
    "sg:phone":"+90 212 583 3623",
    "sg:province":"Istanbul",
    "sg:tags":[
        "flower"
    ],
    "wof:name":"G?ksu Ulusl. ?i?ek?ilik",
    "wof:placetype":"venue"
},
  "geometry": {"coordinates":[28.8623104095,40.9885292053],"type":"Point"}
}