{
  "type": "Feature",
  "properties": {
    "iso:country":"TR",
    "sg:address":"San. Mh. Malazgirt Cd. No:1 G?g?en",
    "sg:city":"Tasdelen-umraniye",
    "sg:classifiers":[
        {
            "category":"Wholesale",
            "subcategory":"Furniture",
            "type":"Manufacturing & Wholesale Goods"
        }
    ],
    "sg:phone":"+90 212 554 2232",
    "sg:province":"Istanbul",
    "sg:tags":[
        "school"
    ],
    "wof:name":"Toros Metal San.",
    "wof:placetype":"venue"
},
  "geometry": {"coordinates":[28.975925,41.012379],"type":"Point"}
}