{
  "type": "Feature",
  "properties": {
    "addr:full":"Ankara Asf. ?z. Kartal \u00dcmraniye Istanbul",
    "iso:country":"TR",
    "sg:address":"Ankara Asf. ?z. Kartal",
    "sg:city":"\u00dcmraniye",
    "sg:classifiers":[
        {
            "category":"Manufacturing",
            "subcategory":"Tools & Machinery",
            "type":"Manufacturing & Wholesale Goods"
        }
    ],
    "sg:phone":"+90 216 306 4180",
    "sg:province":"Istanbul",
    "sg:tags":[
        "machine",
        "industry"
    ],
    "wof:name":"?elik Montaj Tic. San. Ltd. Sti.",
    "wof:placetype":"venue"
},
  "geometry": {"coordinates":[29.3477649689,40.9010238647],"type":"Point"}
}