{
  "type": "Feature",
  "properties": {
    "addr:full":"K. Karabekir Cd. No:56 G?g?en Kocasinan Istanbul 38100",
    "addr:housenumber":"no 56 g ? g ?",
    "addr:postcode":"38100",
    "addr:street":"K. Karabekir Cd.;En Kocasinan",
    "iso:country":"TR",
    "sg:address":"K. Karabekir Cd. No:56 G?g?en",
    "sg:city":"Kocasinan",
    "sg:classifiers":[
        {
            "category":"Retail",
            "subcategory":"Auto Repair",
            "type":"Services"
        }
    ],
    "sg:phone":"+90 212 539 5248",
    "sg:postcode":"38100",
    "sg:province":"Istanbul",
    "sg:tags":[
        "maintenance"
    ],
    "wof:name":"Kocabiyik Oto Kaporta Boya Tic. Ltd. Sti.",
    "wof:placetype":"venue"
},
  "geometry": {"coordinates":[28.9861831665,41.0408554077],"type":"Point"}
}