{
  "type": "Feature",
  "properties": {
    "iso:country":"TR",
    "sg:address":"Meydan Mah Istikal",
    "sg:city":"Antakya",
    "sg:classifiers":[
        {
            "category":"Banks & Credit Unions",
            "subcategory":"Bank",
            "type":"Services"
        }
    ],
    "sg:phone":"+90 326 214 2091",
    "sg:postcode":"31000",
    "sg:province":"31070",
    "wof:name":"T?kiye Is Bankasi As",
    "wof:placetype":"venue"
},
  "geometry": {"coordinates":[36.163254,36.205288],"type":"Point"}
}