{
  "type": "Feature",
  "properties": {
    "iso:country":"TR",
    "sg:address":"82.sok.h.ali Sekerci Psj. No:1/2",
    "sg:city":"Kumluca",
    "sg:classifiers":[
        {
            "category":"Manufacturing",
            "subcategory":"Building Materials",
            "type":"Manufacturing & Wholesale Goods"
        }
    ],
    "sg:phone":"+90 242 242 9284",
    "sg:postcode":"07350",
    "sg:province":"Antalya",
    "sg:tags":[
        "lifts-elevators"
    ],
    "wof:name":"Aysa Asansor",
    "wof:placetype":"venue"
},
  "geometry": {"coordinates":[30.7031345367,36.8875045776],"type":"Point"}
}