{
  "type": "Feature",
  "properties": {
    "iso:country":"TR",
    "sg:address":"S?r?kemerli",
    "sg:city":"G?basi",
    "sg:classifiers":[
        {
            "category":"Government",
            "subcategory":"Office",
            "type":"Public Place"
        }
    ],
    "sg:phone":"+90 28631610143",
    "sg:province":"?anakkale",
    "sg:tags":[
        "municipality"
    ],
    "wof:name":"Biga Belediye Baskani",
    "wof:placetype":"venue"
},
  "geometry": {"coordinates":[35.4317016602,38.9577407837],"type":"Point"}
}