{
  "type": "Feature",
  "properties": {
    "iso:country":"TR",
    "sg:address":"Mahmut Sevket Pasa Mah. Kuru ?ay Cad. No:16",
    "sg:city":"Okmeydani",
    "sg:classifiers":[
        {
            "category":"Food & Beverages",
            "subcategory":"Groceries & Convenience Stores",
            "type":"Retail Goods"
        }
    ],
    "sg:phone":"+90 212 253 2430",
    "sg:postcode":"43050",
    "sg:province":"Istanbul",
    "sg:tags":[
        "drink-",
        "soft"
    ],
    "wof:name":"Cengiz Ticaret",
    "wof:placetype":"venue"
},
  "geometry": {"coordinates":[28.975925,41.012379],"type":"Point"}
}