{
  "type": "Feature",
  "properties": {
    "addr:full":"Sanayi Carsisi 1.blok No:8 \u00dcmraniye Afyon 81260",
    "addr:housenumber":"no",
    "addr:postcode":"81260",
    "iso:country":"TR",
    "sg:address":"Sanayi Carsisi 1.blok No:8",
    "sg:city":"\u00dcmraniye",
    "sg:classifiers":[
        {
            "category":"Manufacturing",
            "subcategory":"Tools & Machinery",
            "type":"Manufacturing & Wholesale Goods"
        }
    ],
    "sg:phone":"+90 272 212 3303",
    "sg:postcode":"81260",
    "sg:province":"Afyon",
    "sg:tags":[
        "machine",
        "industry"
    ],
    "wof:name":"Onur Makina",
    "wof:placetype":"venue"
},
  "geometry": {"coordinates":[30.5417995453,38.7557983398],"type":"Point"}
}