{
  "type": "Feature",
  "properties": {
    "iso:country":"TR",
    "sg:address":"Hastane Cad. No:34 Kocasinan",
    "sg:city":"Kartal",
    "sg:classifiers":[
        {
            "category":"Professional",
            "subcategory":"Computer Services",
            "type":"Services"
        }
    ],
    "sg:phone":"+90 352 222 6635",
    "sg:postcode":"81420",
    "sg:province":"Kayseri",
    "sg:tags":[
        "application",
        "software"
    ],
    "wof:name":"Uzay Egitim Merkezi",
    "wof:placetype":"venue"
},
  "geometry": {"coordinates":[35.4364013672,38.7450408936],"type":"Point"}
}