{
  "type": "Feature",
  "properties": {
    "iso:country":"TR",
    "sg:address":"Saglik Sk. No:59/19 Sihhiye",
    "sg:city":"Merkez",
    "sg:classifiers":[
        {
            "category":"Wholesale",
            "subcategory":"Medical Equipment & Supplies",
            "type":"Manufacturing & Wholesale Goods"
        }
    ],
    "sg:phone":"+90 312 430 1153",
    "sg:postcode":"26000",
    "sg:province":"Ankara",
    "sg:tags":[
        "material"
    ],
    "wof:name":"Sante-med Medikal",
    "wof:placetype":"venue"
},
  "geometry": {"coordinates":[32.8570137024,39.9266967773],"type":"Point"}
}