{
  "type": "Feature",
  "properties": {
    "addr:full":"Hasanpasa Andelip Esat Sok. No:38/9 Kadikoy Merkez Istanbul 05000",
    "addr:housenumber":"no 38 / 9",
    "addr:postcode":"05000",
    "addr:street":"Esat Sok.;Kadikoy",
    "iso:country":"TR",
    "sg:address":"Hasanpasa Andelip Esat Sok. No:38/9 Kadikoy",
    "sg:city":"Merkez",
    "sg:classifiers":[
        {
            "category":"Professional",
            "subcategory":"Detective & Security Services",
            "type":"Services"
        }
    ],
    "sg:phone":"+90 216 338 3566",
    "sg:postcode":"05000",
    "sg:province":"Istanbul",
    "sg:tags":[
        "material"
    ],
    "wof:name":"Nokta Elektronik Sistemleri",
    "wof:placetype":"venue"
},
  "geometry": {"coordinates":[29.039316,40.994133],"type":"Point"}
}