{
  "type": "Feature",
  "properties": {
    "addr:full":"Mezarlik Yolu Uzeri No:7 Torbali Inegol Izmir 16400",
    "addr:housenumber":"uzeri",
    "addr:postcode":"16400",
    "addr:street":"Mezarlik Yolu;No 7 Torbali Inegol",
    "iso:country":"TR",
    "sg:address":"Mezarlik Yolu Uzeri No:7 Torbali",
    "sg:city":"Inegol",
    "sg:classifiers":[
        {
            "category":"Home & Garden",
            "subcategory":"Furniture",
            "type":"Retail Goods"
        }
    ],
    "sg:phone":"+90 232 853 2270",
    "sg:postcode":"16400",
    "sg:province":"Izmir",
    "sg:tags":[
        "armchair",
        "sofa"
    ],
    "wof:name":"Alkan Ev Giyim",
    "wof:placetype":"venue"
},
  "geometry": {"coordinates":[27.1423015594,38.4251480103],"type":"Point"}
}