{
  "type": "Feature",
  "properties": {
    "addr:full":"Modesa San.sit. Alptekin Sok. No: 77 Demirkapi Osmanbey Istanbul 63000",
    "addr:housenumber":"no 77",
    "addr:postcode":"63000",
    "addr:street":"Alptekin Sok.",
    "iso:country":"TR",
    "sg:address":"Modesa San.sit. Alptekin Sok. No: 77 Demirkapi",
    "sg:city":"Osmanbey",
    "sg:classifiers":[
        {
            "category":"Retail",
            "subcategory":"Car Wash",
            "type":"Services"
        }
    ],
    "sg:phone":"+90 212 565 0134",
    "sg:postcode":"63000",
    "sg:province":"Istanbul",
    "sg:tags":[
        "sponge"
    ],
    "wof:name":"Tuva S?nger Toptan Satisi",
    "wof:placetype":"venue"
},
  "geometry": {"coordinates":[28.975925,41.012379],"type":"Point"}
}