{
  "type": "Feature",
  "properties": {
    "addr:full":"Murtaza Cad.no:77 Kazasker Kilis",
    "addr:housenumber":"77",
    "addr:street":"Kazasker Kilis",
    "iso:country":"TR",
    "sg:address":"Murtaza Cad.no:77",
    "sg:city":"Kazasker",
    "sg:classifiers":[
        {
            "category":"Shopping",
            "subcategory":"Photographic Equipment",
            "type":"Retail Goods"
        }
    ],
    "sg:phone":"+90 348 813 4393",
    "sg:province":"Kilis",
    "sg:tags":[
        "photo"
    ],
    "wof:name":"Foto Engin",
    "wof:placetype":"venue"
},
  "geometry": {"coordinates":[37.1122894287,36.7180328369],"type":"Point"}
}