{
  "type": "Feature",
  "properties": {
    "addr:full":"Sirintepe, San. Mh. G??hane Cd. No:123 4.levent Kad\u0131k\u00f6y Istanbul 34990",
    "addr:housenumber":"? ?;cd. no 123",
    "addr:postcode":"4.levent;34990",
    "addr:street":"Mh. G",
    "iso:country":"TR",
    "sg:address":"Sirintepe, San. Mh. G??hane Cd. No:123 4.levent",
    "sg:city":"Kad\u0131k\u00f6y",
    "sg:classifiers":[
        {
            "category":"Home & Garden",
            "subcategory":"Kitchen Supply",
            "type":"Retail Goods"
        }
    ],
    "sg:phone":"+90 212 269 5193",
    "sg:postcode":"34990",
    "sg:province":"Istanbul",
    "sg:tags":[
        "wardrobe"
    ],
    "wof:name":"Karaca Mobilya Ltd. Sti.",
    "wof:placetype":"venue"
},
  "geometry": {"coordinates":[28.9759254456,41.0123786926],"type":"Point"}
}