{
  "type": "Feature",
  "properties": {
    "iso:country":"TR",
    "sg:address":"Bankalar Cd. No:19",
    "sg:city":"Karak\u00f6y",
    "sg:classifiers":[
        {
            "category":"Transit Center",
            "subcategory":"Freight",
            "type":"Transportation"
        }
    ],
    "sg:phone":"+90 212 251 5256",
    "sg:province":"Istanbul",
    "wof:name":"Ko?tug Denizcilik Tic. A.s.",
    "wof:placetype":"venue"
},
  "geometry": {"coordinates":[28.9737052917,41.023891449],"type":"Point"}
}