{
  "type": "Feature",
  "properties": {
    "addr:full":"Selanik Cd. No:36/15 Kizilay Cankaya Ankara 35200",
    "addr:housenumber":"no 36 / 15",
    "addr:postcode":"35200",
    "addr:street":"Selanik Cd.",
    "iso:country":"TR",
    "sg:address":"Selanik Cd. No:36/15 Kizilay",
    "sg:city":"Cankaya",
    "sg:classifiers":[
        {
            "category":"Banks & Credit Unions",
            "subcategory":"Investment Brokerage",
            "type":"Services"
        }
    ],
    "sg:phone":"+90 312 425 0978",
    "sg:postcode":"35200",
    "sg:province":"Ankara",
    "sg:tags":[
        "-",
        "export",
        "import"
    ],
    "wof:name":"Imre M?messil. M?savir. Tic. A.s.",
    "wof:placetype":"venue"
},
  "geometry": {"coordinates":[32.8604812622,39.9429283142],"type":"Point"}
}