{
  "type": "Feature",
  "properties": {
    "addr:full":"Karanfil Sok. No: 36/12 Kizilay Ankara 23050",
    "addr:housenumber":"no 36 / 12",
    "addr:postcode":"23050",
    "addr:street":"Karanfil Sok.;Kizilay Ankara",
    "iso:country":"TR",
    "sg:address":"Karanfil Sok. No: 36/12",
    "sg:city":"Kizilay",
    "sg:classifiers":[
        {
            "category":"Travel",
            "subcategory":"Travel Agent",
            "type":"Entertainment"
        }
    ],
    "sg:phone":"+90 3124253048418",
    "sg:postcode":"23050",
    "sg:province":"Ankara",
    "sg:tags":[
        "agency",
        "tourism"
    ],
    "wof:name":"Meram Opera Turizm",
    "wof:placetype":"venue"
},
  "geometry": {"coordinates":[32.8604812622,39.9429283142],"type":"Point"}
}