{
  "type": "Feature",
  "properties": {
    "addr:full":"Evrenoszade Sk. No:21 Seyhan Istanbul 01120",
    "addr:housenumber":"21",
    "addr:postcode":"01120",
    "addr:street":"Evrenoszade Sk. No",
    "iso:country":"TR",
    "sg:address":"Evrenoszade Sk. No:21",
    "sg:city":"Seyhan",
    "sg:classifiers":[
        {
            "category":"Manufacturing",
            "subcategory":"Chemicals & Compounds",
            "type":"Manufacturing & Wholesale Goods"
        }
    ],
    "sg:phone":"+90 212 247 0040",
    "sg:postcode":"01120",
    "sg:province":"Istanbul",
    "sg:tags":[
        "pharmaceutical"
    ],
    "wof:name":"Biotek Ilac San.",
    "wof:placetype":"venue"
},
  "geometry": {"coordinates":[28.9800338745,41.0552558899],"type":"Point"}
}