{
  "type": "Feature",
  "properties": {
    "iso:country":"TR",
    "sg:address":"K?? San. Sit. 25 Blok No: 38",
    "sg:city":"Bayrampasa",
    "sg:classifiers":[
        {
            "category":"Home & Garden",
            "subcategory":"Kitchen Supply",
            "type":"Retail Goods"
        }
    ],
    "sg:phone":"+90 224 441 1054",
    "sg:postcode":"36100",
    "sg:province":"Bursa",
    "sg:tags":[
        "steel",
        "utensil"
    ],
    "wof:name":"L?ks Mutfaksan San. Tic. Ltd. Sti.",
    "wof:placetype":"venue"
},
  "geometry": {"coordinates":[29.058004,40.194756],"type":"Point"}
}