{
  "type": "Feature",
  "properties": {
    "iso:country":"TR",
    "sg:address":"41/a Sok No: 30 06370 Ostim Ankara",
    "sg:city":"Merkez",
    "sg:classifiers":[
        {
            "category":"Manufacturing",
            "subcategory":"Wood Products",
            "type":"Manufacturing & Wholesale Goods"
        }
    ],
    "sg:phone":"+90 312 385 4340",
    "sg:postcode":"25000",
    "sg:province":"Ankara",
    "sg:tags":[
        "furniture"
    ],
    "wof:name":"Aydinlatma Elemanlari San Tic Ltd Sti",
    "wof:placetype":"venue"
},
  "geometry": {"coordinates":[32.7447471619,39.9757156372],"type":"Point"}
}