{
  "type": "Feature",
  "properties": {
    "iso:country":"TR",
    "sg:address":"Kasap Sk. No:15/3 Esentepe",
    "sg:city":"Kad\u0131k\u00f6y",
    "sg:classifiers":[
        {
            "category":"Building & Trades",
            "subcategory":"Plumbing",
            "type":"Services"
        }
    ],
    "sg:phone":"+90 212 272 4882",
    "sg:postcode":"34714",
    "sg:province":"Istanbul",
    "wof:name":"Tempas Tesisat Malzeme. Pazarlama A.s.",
    "wof:placetype":"venue"
},
  "geometry": {"coordinates":[29.0118808746,41.0676078796],"type":"Point"}
}