{
  "type": "Feature",
  "properties": {
    "iso:country":"TR",
    "sg:address":"Modoko San. Sit. 11. Sk. No:90",
    "sg:city":"Y.dudullu",
    "sg:classifiers":[
        {
            "category":"Government",
            "subcategory":"Fire Station",
            "type":"Public Place"
        }
    ],
    "sg:phone":"+90 216 364 2195",
    "sg:province":"Istanbul",
    "sg:tags":[
        "decoration"
    ],
    "wof:name":"Cihan Mobilya Dekorasyon",
    "wof:placetype":"venue"
},
  "geometry": {"coordinates":[29.157289505,41.0069847107],"type":"Point"}
}