{
  "type": "Feature",
  "properties": {
    "iso:country":"TR",
    "sg:address":"Mithatpasa Cad.no:58/9 Kizilay",
    "sg:city":"G?tepe",
    "sg:classifiers":[
        {
            "category":"Wholesale",
            "subcategory":"Medical Equipment & Supplies",
            "type":"Manufacturing & Wholesale Goods"
        }
    ],
    "sg:phone":"+90 312 424 1868",
    "sg:province":"Ankara",
    "sg:tags":[
        "material"
    ],
    "wof:name":"Alo Global Saglik Hizmetleri",
    "wof:placetype":"venue"
},
  "geometry": {"coordinates":[32.8510704041,39.9231300354],"type":"Point"}
}