{
  "type": "Feature",
  "properties": {
    "iso:country":"TR",
    "sg:address":"Itri Sk. No:8",
    "sg:city":"Balmumcu",
    "sg:classifiers":[
        {
            "category":"Freight",
            "type":"Transportation"
        }
    ],
    "sg:phone":"+90 212 272 6120",
    "sg:postcode":"34349",
    "sg:province":"Istanbul",
    "sg:tags":[
        "cargo",
        "air"
    ],
    "wof:name":"Atlantik Denizcilik",
    "wof:placetype":"venue"
},
  "geometry": {"coordinates":[29.017665863,41.0564346313],"type":"Point"}
}