{
  "type": "Feature",
  "properties": {
    "addr:full":"Yenidogan Mah. Zubeyde Hanim Cad. No.104 Zeytinburnu Beyazit Istanbul 34490",
    "addr:housenumber":"no.104 zeytinburnu",
    "addr:postcode":"34490",
    "addr:street":"Yenidogan Mah. Zubeyde Hanim Cad.;Istanbul",
    "iso:country":"TR",
    "sg:address":"Yenidogan Mah. Zubeyde Hanim Cad. No.104 Zeytinburnu",
    "sg:city":"Beyazit",
    "sg:classifiers":[
        {
            "category":"Shopping",
            "subcategory":"Luggage & Leather Goods",
            "type":"Retail Goods"
        }
    ],
    "sg:phone":"+90 212 664 4609",
    "sg:postcode":"34490",
    "sg:province":"Istanbul",
    "sg:tags":[
        "leather-fur",
        "wear"
    ],
    "wof:name":"A1 Deri Ve Tekstil San. Ve Tic. A.s.",
    "wof:placetype":"venue"
},
  "geometry": {"coordinates":[28.9075012207,40.988067627],"type":"Point"}
}