{
  "type": "Feature",
  "properties": {
    "addr:full":"Merkez Mah. 51 Sk. No: 2 Sasali- Cigli Konak Izmir 07110",
    "addr:housenumber":"51",
    "addr:postcode":"07110",
    "addr:street":"Merkez Mah.;Sk. No 2 Sasali",
    "iso:country":"TR",
    "sg:address":"Merkez Mah. 51 Sk. No: 2 Sasali- Cigli",
    "sg:city":"Konak",
    "sg:classifiers":[
        {
            "category":"Wholesale",
            "subcategory":"Durable Goods & Equipment",
            "type":"Manufacturing & Wholesale Goods"
        }
    ],
    "sg:phone":"+90 232 327 3311",
    "sg:postcode":"07110",
    "sg:province":"Izmir",
    "sg:tags":[
        "consumer"
    ],
    "wof:name":"Remak Elektrikli Araclar End. Ve Dis. Tic. A.s.",
    "wof:placetype":"venue"
},
  "geometry": {"coordinates":[27.1423015594,38.4251480103],"type":"Point"}
}