{
  "type": "Feature",
  "properties": {
    "addr:full":"Bahtiyar Han No.30 Yesildirek Istanbul 63200",
    "addr:postcode":"63200",
    "addr:street":"Yesildirek",
    "iso:country":"TR",
    "sg:address":"Bahtiyar Han No.30",
    "sg:city":"Yesildirek",
    "sg:classifiers":[
        {
            "category":"Shopping",
            "subcategory":"Baby Store",
            "type":"Retail Goods"
        }
    ],
    "sg:phone":"+90 212 511 8991",
    "sg:postcode":"63200",
    "sg:province":"Istanbul",
    "sg:tags":[
        "wear"
    ],
    "wof:name":"G?ven ?ocuk Giyim",
    "wof:placetype":"venue"
},
  "geometry": {"coordinates":[32.491287,37.901039],"type":"Point"}
}