{
  "type": "Feature",
  "properties": {
    "iso:country":"TR",
    "sg:address":"Mersin Yolu",
    "sg:city":"Bayrampasa",
    "sg:classifiers":[
        {
            "category":"Utilities",
            "subcategory":"Water",
            "type":"Services"
        }
    ],
    "sg:phone":"+90 322 435 0763",
    "sg:postcode":"36100",
    "sg:province":"Adana",
    "sg:tags":[
        "vegetable",
        "margarine",
        "oil"
    ],
    "wof:name":"Marsa Margarin San. A.s.",
    "wof:placetype":"venue"
},
  "geometry": {"coordinates":[34.9743499756,36.9785842896],"type":"Point"}
}