{
  "type": "Feature",
  "properties": {
    "addr:full":"Katip Mustafa ?elebi Mah. Siraselviler Cad. 48/8 Beyoglu Istanbul 46810",
    "addr:housenumber":"?;48 / 8",
    "addr:postcode":"46810",
    "addr:street":"Katip Mustafa;Elebi Mah. Siraselviler Cad.",
    "iso:country":"TR",
    "sg:address":"Katip Mustafa ?elebi Mah. Siraselviler Cad. 48/8",
    "sg:city":"Beyoglu",
    "sg:classifiers":[
        {
            "category":"Travel",
            "subcategory":"Travel Agent",
            "type":"Entertainment"
        }
    ],
    "sg:phone":"+90 2928808",
    "sg:postcode":"46810",
    "sg:province":"Istanbul",
    "sg:tags":[
        "agency",
        "tourism"
    ],
    "wof:name":"Asav Turizm",
    "wof:placetype":"venue"
},
  "geometry": {"coordinates":[28.9861831665,41.0408554077],"type":"Point"}
}