{
  "type": "Feature",
  "properties": {
    "addr:full":"Tahran Cad. No.30/9 Gaziosmanpasa Kizilay Istanbul 23050",
    "addr:housenumber":"no.30 / 9",
    "addr:postcode":"23050",
    "addr:street":"Tahran Cad.",
    "iso:country":"TR",
    "sg:address":"Tahran Cad. No.30/9 Gaziosmanpasa",
    "sg:city":"Kizilay",
    "sg:classifiers":[
        {
            "category":"Banks & Credit Unions",
            "subcategory":"Financial Services",
            "type":"Services"
        }
    ],
    "sg:phone":"+90 212 468 8750",
    "sg:postcode":"23050",
    "sg:province":"Istanbul",
    "sg:tags":[
        "finance"
    ],
    "wof:name":"Soymen Menkul Degerler",
    "wof:placetype":"venue"
},
  "geometry": {"coordinates":[32.8660430908,39.9043235779],"type":"Point"}
}