{
  "type": "Feature",
  "properties": {
    "addr:full":"Lise Cad.853 S No:4/b Karakoy Denizli 07700",
    "addr:housenumber":"cad.853 s no 4 / b",
    "addr:postcode":"07700",
    "addr:street":"Lise",
    "iso:country":"TR",
    "sg:address":"Lise Cad.853 S No:4/b",
    "sg:city":"Karakoy",
    "sg:classifiers":[
        {
            "category":"Building & Trades",
            "subcategory":"Electrical",
            "type":"Services"
        }
    ],
    "sg:phone":"+90 258 264 3242",
    "sg:postcode":"07700",
    "sg:province":"Denizli",
    "sg:tags":[
        "equipment",
        "lighting"
    ],
    "wof:name":"Gedikoglu Aydinlatma",
    "wof:placetype":"venue"
},
  "geometry": {"coordinates":[29.0867843628,37.7722892761],"type":"Point"}
}