{
  "type": "Feature",
  "properties": {
    "addr:full":"Kazim Orbay Cd. No:92 Sisli Bostanci Istanbul 25900",
    "addr:housenumber":"no 92",
    "addr:postcode":"25900",
    "addr:street":"Cd.",
    "iso:country":"TR",
    "sg:address":"Kazim Orbay Cd. No:92 Sisli",
    "sg:city":"Bostanci",
    "sg:classifiers":[
        {
            "category":"Home & Garden",
            "subcategory":"Hardware",
            "type":"Retail Goods"
        }
    ],
    "sg:phone":"+90 212 246 0980",
    "sg:postcode":"25900",
    "sg:province":"Istanbul",
    "sg:tags":[
        "generator",
        "power"
    ],
    "wof:name":"Pan? Elektronik San. Tic. A.s.",
    "wof:placetype":"venue"
},
  "geometry": {"coordinates":[28.9833946228,41.0604133606],"type":"Point"}
}