{
  "type": "Feature",
  "properties": {
    "addr:full":"Ihlamur Yolu No:34/a Nisantasi Sisli Istanbul 80200",
    "addr:housenumber":"no 34 / a",
    "addr:postcode":"80200",
    "addr:street":"Ihlamur Yolu",
    "iso:country":"TR",
    "sg:address":"Ihlamur Yolu No:34/a Nisantasi",
    "sg:city":"Sisli",
    "sg:classifiers":[
        {
            "category":"Shopping",
            "subcategory":"Florist",
            "type":"Retail Goods"
        }
    ],
    "sg:phone":"+90 212 240 4791",
    "sg:postcode":"80200",
    "sg:province":"Istanbul",
    "sg:tags":[
        "flower"
    ],
    "wof:name":"Incimiz ?i?ekligi San.tic.ltd.sti",
    "wof:placetype":"venue"
},
  "geometry": {"coordinates":[28.9857254028,41.0730552673],"type":"Point"}
}