{
  "type": "Feature",
  "properties": {
    "addr:full":"Hosdere Yolu Evren Oto San. Sit. 28/1 Esenyurt-avcilar Osmangazi Istanbul 46050",
    "addr:housenumber":"28 / 1",
    "addr:postcode":"46050",
    "addr:street":"Hosdere Yolu;Esenyurt-Avcilar Osmangazi",
    "iso:country":"TR",
    "sg:address":"Hosdere Yolu Evren Oto San. Sit. 28/1 Esenyurt-avcilar",
    "sg:city":"Osmangazi",
    "sg:classifiers":[
        {
            "category":"Manufacturing",
            "subcategory":"Rubber & Plastics",
            "type":"Manufacturing & Wholesale Goods"
        }
    ],
    "sg:phone":"+90 212 623 0355",
    "sg:postcode":"46050",
    "sg:province":"Istanbul",
    "sg:tags":[
        "industry"
    ],
    "wof:name":"Orta?lar San. Ve Tic. Koll. Sti.",
    "wof:placetype":"venue"
},
  "geometry": {"coordinates":[28.9759254456,41.0123786926],"type":"Point"}
}