{
  "type": "Feature",
  "properties": {
    "addr:full":"Ikitelli Cad. Imsan Kucuk Sanayi Sitesi A Blok No: 4 Ikitelli Istanbul 34306",
    "addr:housenumber":"blok no 4",
    "addr:postcode":"34306",
    "addr:street":"Ikitelli Cad. Imsan Kucuk Sanayi Sitesi A",
    "iso:country":"TR",
    "sg:address":"Ikitelli Cad. Imsan Kucuk Sanayi Sitesi A Blok No: 4",
    "sg:city":"Ikitelli",
    "sg:classifiers":[
        {
            "category":"Sports & Exercise",
            "subcategory":"Ski Slope",
            "type":"Entertainment"
        }
    ],
    "sg:phone":"+90 212 697 9494",
    "sg:postcode":"34306",
    "sg:province":"Istanbul",
    "sg:tags":[
        "wear"
    ],
    "wof:name":"Ispoteks Konfeksiyon San.tic.a.s.",
    "wof:placetype":"venue"
},
  "geometry": {"coordinates":[28.798496,41.088402],"type":"Point"}
}