{
  "type": "Feature",
  "properties": {
    "iso:country":"TR",
    "sg:address":"Gazeteciler Sit. Yazarlar Sk. No:29 E.tepe",
    "sg:city":"Bal?va",
    "sg:orig_category":"Enegy Contractors",
    "sg:phone":"+90 212 267 4892",
    "sg:province":"Istanbul",
    "wof:name":"H.e.i. Enerji A.s.",
    "wof:placetype":"venue"
},
  "geometry": {"coordinates":[28.9861793518,41.040851593],"type":"Point"}
}