{
  "type": "Feature",
  "properties": {
    "iso:country":"TR",
    "sg:address":"Bankalar Cad 11",
    "sg:city":"K?ahya",
    "sg:classifiers":[
        {
            "category":"Banks & Credit Unions",
            "subcategory":"Bank",
            "type":"Services"
        }
    ],
    "sg:phone":"+90 274 614 1104",
    "sg:province":"43400",
    "wof:name":"Esbank Eskisehir, Bankasi Tas",
    "wof:placetype":"venue"
},
  "geometry": {"coordinates":[29.162348,40.906921],"type":"Point"}
}