{
  "type": "Feature",
  "properties": {
    "iso:country":"TR",
    "sg:address":"Fatih Sultan Mehmet Cad. No: 49",
    "sg:city":"Altinyayla",
    "sg:classifiers":[
        {
            "category":"Shopping",
            "subcategory":"Clothing, Apparel, & Fashions",
            "type":"Retail Goods"
        }
    ],
    "sg:phone":"+90 224 328 3155",
    "sg:postcode":"58470",
    "sg:province":"Bursa",
    "sg:tags":[
        "-",
        "towel",
        "bathrobe"
    ],
    "wof:name":"Eftalya Tilekst",
    "wof:placetype":"venue"
},
  "geometry": {"coordinates":[28.9778461456,40.2207489014],"type":"Point"}
}