{
  "type": "Feature",
  "properties": {
    "addr:full":"Mithatpasa Cad. No:70/5 Yenisehir 16010 Ankara",
    "addr:housenumber":"70 / 5",
    "addr:postcode":"16010",
    "addr:street":"Mithatpasa Cad. No;Yenisehir",
    "iso:country":"TR",
    "sg:address":"Mithatpasa Cad. No:70/5 Yenisehir",
    "sg:city":"16010",
    "sg:classifiers":[
        {
            "category":"Health Services",
            "subcategory":"Clinic",
            "type":"Services"
        }
    ],
    "sg:phone":"+90 312 417 2898",
    "sg:province":"Ankara",
    "wof:name":"Biltas Saglik Hizm.ve Tic.a.s.",
    "wof:placetype":"venue"
},
  "geometry": {"coordinates":[32.8666992188,39.9166984558],"type":"Point"}
}