{
  "type": "Feature",
  "properties": {
    "iso:country":"TR",
    "sg:address":"Cengelkoy Bosna Bulv. (eski Nato Yolu) No:35/4",
    "sg:city":"Uskudar",
    "sg:classifiers":[
        {
            "category":"Farming",
            "subcategory":"Farm & Veterinary Services",
            "type":"Manufacturing & Wholesale Goods"
        }
    ],
    "sg:phone":"+90 216 521 3243",
    "sg:postcode":"34672",
    "sg:province":"Istanbul",
    "sg:tags":[
        "veterinarian"
    ],
    "wof:name":"A.kisikli Veteriner Klinigi",
    "wof:placetype":"venue"
},
  "geometry": {"coordinates":[29.0789756775,41.0443725586],"type":"Point"}
}