{
  "type": "Feature",
  "properties": {
    "addr:full":"Ramazan Pasa Mah. Hukumet Sok. No:3 Kizilay Aydin 23050",
    "addr:housenumber":"no 3",
    "addr:postcode":"23050",
    "addr:street":"Ramazan Pasa Mah. Hukumet Sok.;Kizilay Aydin",
    "iso:country":"TR",
    "sg:address":"Ramazan Pasa Mah. Hukumet Sok. No:3",
    "sg:city":"Kizilay",
    "sg:classifiers":[
        {
            "category":"Banks & Credit Unions",
            "subcategory":"Financial Services",
            "type":"Services"
        }
    ],
    "sg:phone":"+90 256 213 3604",
    "sg:postcode":"23050",
    "sg:province":"Aydin",
    "sg:tags":[
        "consultant"
    ],
    "wof:name":"Aydin-serbest Muhasebeci Mali Musavirler",
    "wof:placetype":"venue"
},
  "geometry": {"coordinates":[28.4863967896,37.8117027283],"type":"Point"}
}