{
  "type": "Feature",
  "properties": {
    "addr:full":"Inonu Bul.anadolu Hayat Sig.ish.k:2 No:213 Adapazari I?el 54200",
    "addr:housenumber":"2;?",
    "addr:postcode":"54200",
    "addr:street":"Sig.Ish.K;No 213 Adapazari I;El",
    "iso:country":"TR",
    "sg:address":"Inonu Bul.anadolu Hayat Sig.ish.k:2 No:213",
    "sg:city":"Adapazari",
    "sg:classifiers":[
        {
            "category":"Food & Beverages",
            "subcategory":"Fruits & Vegetables",
            "type":"Retail Goods"
        }
    ],
    "sg:phone":"+90 324 233 1231",
    "sg:postcode":"54200",
    "sg:province":"I?el",
    "sg:tags":[
        "fresh"
    ],
    "wof:name":"Yasin Gida Tic.ltd.",
    "wof:placetype":"venue"
},
  "geometry": {"coordinates":[30.4102096558,40.7897415161],"type":"Point"}
}