{
  "type": "Feature",
  "properties": {
    "addr:full":"Necatibey Cd. Hoca Tahsin Sk. No:27/a Karak\u00f6y Istanbul",
    "addr:housenumber":"27 / a",
    "addr:street":"Tahsin Sk. No",
    "iso:country":"TR",
    "sg:address":"Necatibey Cd. Hoca Tahsin Sk. No:27/a",
    "sg:city":"Karak\u00f6y",
    "sg:classifiers":[
        {
            "category":"Home & Garden",
            "subcategory":"Household Appliances",
            "type":"Retail Goods"
        }
    ],
    "sg:phone":"+90 212 249 1249",
    "sg:province":"Istanbul",
    "sg:tags":[
        "conditioner",
        "air"
    ],
    "wof:name":"Saya Isi San.",
    "wof:placetype":"venue"
},
  "geometry": {"coordinates":[28.9785308838,41.0247383118],"type":"Point"}
}