{
  "type": "Feature",
  "properties": {
    "addr:full":"Dizboyu Sk. No:19/1 Siteler B\u00fcy\u00fck\u00e7ekmece Ankara 34905",
    "addr:housenumber":"19 / 1",
    "addr:postcode":"34905",
    "addr:street":"Dizboyu Sk. No",
    "iso:country":"TR",
    "sg:address":"Dizboyu Sk. No:19/1 Siteler",
    "sg:city":"B\u00fcy\u00fck\u00e7ekmece",
    "sg:classifiers":[
        {
            "category":"Home & Garden",
            "subcategory":"Building Materials",
            "type":"Retail Goods"
        }
    ],
    "sg:phone":"+90 312 348 7851",
    "sg:postcode":"34905",
    "sg:province":"Ankara",
    "sg:tags":[
        "window",
        "door",
        "plastic"
    ],
    "wof:name":"Pentes Plastik Dograma San. Tic. Ltd. Sti.",
    "wof:placetype":"venue"
},
  "geometry": {"coordinates":[32.8911323547,39.9594535828],"type":"Point"}
}