{
  "type": "Feature",
  "properties": {
    "addr:full":"Bahce Sok. Kas Antalya 07580",
    "addr:postcode":"07580",
    "addr:street":"Bahce Sok.",
    "iso:country":"TR",
    "sg:address":"Bahce Sok.",
    "sg:city":"Kas",
    "sg:classifiers":[
        {
            "category":"Travel",
            "subcategory":"Travel Agent",
            "type":"Entertainment"
        }
    ],
    "sg:phone":"+90 2428361981699",
    "sg:postcode":"07580",
    "sg:province":"Antalya",
    "sg:tags":[
        "agency",
        "tourism"
    ],
    "wof:name":"Phellos Seyhat Acentasi",
    "wof:placetype":"venue"
},
  "geometry": {"coordinates":[29.6891994476,36.2063293457],"type":"Point"}
}