{
  "type": "Feature",
  "properties": {
    "iso:country":"TR",
    "sg:address":"Sakarya",
    "sg:city":"Karabaglar",
    "sg:classifiers":[
        {
            "category":"Government",
            "subcategory":"Office",
            "type":"Public Place"
        }
    ],
    "sg:phone":"+90 264 418 1466",
    "sg:postcode":"44210",
    "sg:province":"Sakarya",
    "sg:tags":[
        "army"
    ],
    "wof:name":"Akyazi (karap?r?ek) Askerlik Subesi",
    "wof:placetype":"venue"
},
  "geometry": {"coordinates":[30.4152469635,40.7566566467],"type":"Point"}
}