{
  "type": "Feature",
  "properties": {
    "addr:full":"E. Edirne Asf. G.o.pasa Istanbul",
    "addr:street":"E.",
    "iso:country":"TR",
    "sg:address":"E. Edirne Asf.",
    "sg:city":"G.o.pasa",
    "sg:classifiers":[
        {
            "category":"Manufacturing",
            "subcategory":"Textiles",
            "type":"Manufacturing & Wholesale Goods"
        }
    ],
    "sg:phone":"+90 212 595 1226",
    "sg:province":"Istanbul",
    "sg:tags":[
        "linen",
        "yarn"
    ],
    "wof:name":"Marmara Iplik Boya. Teks. San. Tic. A.s.",
    "wof:placetype":"venue"
},
  "geometry": {"coordinates":[28.8440303802,41.1214752197],"type":"Point"}
}