{
  "type": "Feature",
  "properties": {
    "iso:country":"TR",
    "sg:address":"Samanyolu Cd. No:7/9 B?? Sanayi",
    "sg:city":"Maslak",
    "sg:classifiers":[
        {
            "category":"Farming",
            "subcategory":"Fish & Marine Products",
            "type":"Manufacturing & Wholesale Goods"
        }
    ],
    "sg:phone":"+90 312 341 9525",
    "sg:postcode":"34398",
    "sg:province":"Ankara",
    "sg:tags":[
        "automotive"
    ],
    "wof:name":"?elik Oto Koll. Sti.",
    "wof:placetype":"venue"
},
  "geometry": {"coordinates":[32.8285293579,39.9310379028],"type":"Point"}
}