{
  "type": "Feature",
  "properties": {
    "addr:full":"G??ler Zeytinburnu Denizli 41000",
    "addr:housenumber":"? ?",
    "addr:postcode":"41000",
    "iso:country":"TR",
    "sg:address":"G??ler",
    "sg:city":"Zeytinburnu",
    "sg:classifiers":[
        {
            "category":"Shopping",
            "subcategory":"Crafts & Fabrics",
            "type":"Retail Goods"
        }
    ],
    "sg:phone":"+90 258 371 5090",
    "sg:postcode":"41000",
    "sg:province":"Denizli",
    "sg:tags":[
        "embroidery"
    ],
    "wof:name":"Nakosan Nakis Konfeksiyon Tekstil A.s.",
    "wof:placetype":"venue"
},
  "geometry": {"coordinates":[29.0788803101,37.7851867676],"type":"Point"}
}