{
  "type": "Feature",
  "properties": {
    "addr:full":"Dumlupinar Cad. Sakarya Sok. No:8 Bayrampasa Istanbul 36100",
    "addr:housenumber":"no 8",
    "addr:postcode":"36100",
    "addr:street":"Dumlupinar Cad. Sakarya Sok.",
    "iso:country":"TR",
    "sg:address":"Dumlupinar Cad. Sakarya Sok. No:8",
    "sg:city":"Bayrampasa",
    "sg:classifiers":[
        {
            "category":"Professional",
            "type":"Services"
        }
    ],
    "sg:phone":"+90 212 501 6625",
    "sg:postcode":"36100",
    "sg:province":"Istanbul",
    "sg:tags":[
        "catering"
    ],
    "wof:name":"G?laydin",
    "wof:placetype":"venue"
},
  "geometry": {"coordinates":[28.9861831665,41.0408554077],"type":"Point"}
}