{
  "type": "Feature",
  "properties": {
    "addr:full":"Istiklal Caddesi No:206 K:2-3-4 Beyoglu Istanbul 46810",
    "addr:housenumber":"no 206 k 2-3-4",
    "addr:postcode":"46810",
    "addr:street":"Istiklal Caddesi",
    "iso:country":"TR",
    "sg:address":"Istiklal Caddesi No:206 K:2-3-4",
    "sg:city":"Beyoglu",
    "sg:classifiers":[
        {
            "category":"Travel",
            "subcategory":"Travel Agent",
            "type":"Entertainment"
        }
    ],
    "sg:phone":"+90 2510566",
    "sg:postcode":"46810",
    "sg:province":"Istanbul",
    "sg:tags":[
        "agency",
        "tourism"
    ],
    "wof:name":"Istanbul Fotograf Evi Turizm",
    "wof:placetype":"venue"
},
  "geometry": {"coordinates":[28.9861831665,41.0408554077],"type":"Point"}
}