{
  "type": "Feature",
  "properties": {
    "iso:country":"TR",
    "sg:address":"Ankara Asfalti ?zeri Salihli 45300",
    "sg:city":"Diskapi",
    "sg:classifiers":[
        {
            "category":"Home & Garden",
            "subcategory":"Carpets & Floor Coverings",
            "type":"Retail Goods"
        }
    ],
    "sg:phone":"+90 236 714 4540",
    "sg:postcode":"06030",
    "sg:province":"Manisa",
    "sg:tags":[
        "tile",
        "brick",
        "earthenware"
    ],
    "wof:name":"Batisan Bati Toprak Sanayi Ve Ticaret A.s",
    "wof:placetype":"venue"
},
  "geometry": {"coordinates":[27.4269599915,38.6141242981],"type":"Point"}
}