{
  "type": "Feature",
  "properties": {
    "iso:country":"TR",
    "sg:address":"100. Yil Sit. No:11 Yakacik Yolu Kartal",
    "sg:city":"Bostanci",
    "sg:classifiers":[
        {
            "category":"Home & Garden",
            "subcategory":"Hardware",
            "type":"Retail Goods"
        }
    ],
    "sg:phone":"+90 216 374 1009",
    "sg:postcode":"25900",
    "sg:province":"Istanbul",
    "sg:tags":[
        "generator",
        "power"
    ],
    "wof:name":"Termo Ind?ksiyon",
    "wof:placetype":"venue"
},
  "geometry": {"coordinates":[28.9759254456,41.0123786926],"type":"Point"}
}