{
  "type": "Feature",
  "properties": {
    "addr:full":"Ziya Gokalp Cad. 36/18 Kizilay Ikitelli/K\u00fc\u00e7\u00fck\u00e7ekmece Ankara 34660",
    "addr:housenumber":"36 / 18",
    "addr:postcode":"34660",
    "addr:street":"Ziya Gokalp Cad.",
    "iso:country":"TR",
    "sg:address":"Ziya Gokalp Cad. 36/18 Kizilay",
    "sg:city":"Ikitelli/K\u00fc\u00e7\u00fck\u00e7ekmece",
    "sg:classifiers":[
        {
            "category":"Manufacturing",
            "subcategory":"Tools & Machinery",
            "type":"Manufacturing & Wholesale Goods"
        }
    ],
    "sg:phone":"+90 312 430 4315",
    "sg:postcode":"34660",
    "sg:province":"Ankara",
    "sg:tags":[
        "machine",
        "industry"
    ],
    "wof:name":"Mis Makina Imalat Sanayi Ltd.sti.",
    "wof:placetype":"venue"
},
  "geometry": {"coordinates":[32.8580169678,39.9213104248],"type":"Point"}
}