{
  "type": "Feature",
  "properties": {
    "iso:country":"TR",
    "sg:address":"Yayalar Mah. Ankara Cad. No: 26 Pendik",
    "sg:city":"K.?ekmece",
    "sg:classifiers":[
        {
            "category":"Manufacturing",
            "subcategory":"Building Materials",
            "type":"Manufacturing & Wholesale Goods"
        }
    ],
    "sg:phone":"+90 216 307 5707",
    "sg:postcode":"34670",
    "sg:province":"Istanbul",
    "sg:tags":[
        "promotional"
    ],
    "wof:name":"Desing Studio",
    "wof:placetype":"venue"
},
  "geometry": {"coordinates":[29.2468090057,40.8938903809],"type":"Point"}
}