{
  "type": "Feature",
  "properties": {
    "addr:full":"Cumhuriyet Mh. ?etin Sk. Yakacik Kartal Osmangazi Istanbul 46050",
    "addr:housenumber":"?",
    "addr:postcode":"46050",
    "addr:street":"Cumhuriyet Mh.;Etin Sk. Yakacik Kartal",
    "iso:country":"TR",
    "sg:address":"Cumhuriyet Mh. ?etin Sk. Yakacik Kartal",
    "sg:city":"Osmangazi",
    "sg:classifiers":[
        {
            "category":"Manufacturing",
            "subcategory":"Rubber & Plastics",
            "type":"Manufacturing & Wholesale Goods"
        }
    ],
    "sg:phone":"+90 216 377 4105",
    "sg:postcode":"46050",
    "sg:province":"Istanbul",
    "sg:tags":[
        "industry"
    ],
    "wof:name":"Pimak Plastik Mak. San. Tic. Ltd. Sti.",
    "wof:placetype":"venue"
},
  "geometry": {"coordinates":[29.2185573578,40.9096374512],"type":"Point"}
}