{
  "type": "Feature",
  "properties": {
    "iso:country":"TR",
    "sg:address":"Necatibey Cad. Hanimeli Sk. No:34/20 Sihhiye",
    "sg:city":"K.cekmece",
    "sg:classifiers":[
        {
            "category":"Professional",
            "subcategory":"Testing Lab",
            "type":"Services"
        }
    ],
    "sg:phone":"+90 312 229 7755",
    "sg:province":"Ankara",
    "sg:tags":[
        "laboratory",
        "material"
    ],
    "wof:name":"Dogan Medikal",
    "wof:placetype":"venue"
},
  "geometry": {"coordinates":[32.8505592346,39.9250259399],"type":"Point"}
}