{
  "type": "Feature",
  "properties": {
    "iso:country":"TR",
    "sg:address":"Karatas Yolu 10.km.",
    "sg:city":"Susehri",
    "sg:classifiers":[
        {
            "category":"Wholesale",
            "subcategory":"Farm Supplies",
            "type":"Manufacturing & Wholesale Goods"
        }
    ],
    "sg:phone":"+90 322 334 0117",
    "sg:postcode":"58600",
    "sg:province":"Adana",
    "sg:tags":[
        "feed",
        "industry"
    ],
    "wof:name":"Tavas Yem San.ve Tic.as.",
    "wof:placetype":"venue"
},
  "geometry": {"coordinates":[35.3137359619,37.0007171631],"type":"Point"}
}