{
  "type": "Feature",
  "properties": {
    "addr:full":"Resat Cakir Cad. No:54 Kad\u0131k\u00f6y Denizli 34714",
    "addr:housenumber":"54",
    "addr:postcode":"34714",
    "addr:street":"Cakir Cad. No",
    "iso:country":"TR",
    "sg:address":"Resat Cakir Cad. No:54",
    "sg:city":"Kad\u0131k\u00f6y",
    "sg:classifiers":[
        {
            "category":"Building & Trades",
            "subcategory":"Plumbing",
            "type":"Services"
        }
    ],
    "sg:phone":"+90 258 371 0829",
    "sg:postcode":"34714",
    "sg:province":"Denizli",
    "wof:name":"Sinyol Koll. Sti.",
    "wof:placetype":"venue"
},
  "geometry": {"coordinates":[29.0864906311,37.773525238],"type":"Point"}
}