{
  "type": "Feature",
  "properties": {
    "addr:full":"Esentepe Mah. Toros Cad. Orusbey Sok.no.5/b Kartal K.?ekmece Istanbul 34670",
    "addr:housenumber":"sok.no.5 / b;?",
    "addr:postcode":"34670",
    "addr:street":"Esentepe Mah. Toros Cad. Orusbey;Kartal K.",
    "iso:country":"TR",
    "sg:address":"Esentepe Mah. Toros Cad. Orusbey Sok.no.5/b Kartal",
    "sg:city":"K.?ekmece",
    "sg:classifiers":[
        {
            "category":"Manufacturing",
            "subcategory":"Building Materials",
            "type":"Manufacturing & Wholesale Goods"
        }
    ],
    "sg:phone":"+90 216 473 8290",
    "sg:postcode":"34670",
    "sg:province":"Istanbul",
    "sg:tags":[
        "promotional"
    ],
    "wof:name":"Doga Sanat Ve Sanat Urunleri",
    "wof:placetype":"venue"
},
  "geometry": {"coordinates":[28.9759254456,41.0123786926],"type":"Point"}
}