{
  "type": "Feature",
  "properties": {
    "addr:full":"Gaziler Cad.bati Ismrk.no:367 Yenisehir Osmanbey Izmir 63000",
    "addr:housenumber":"367",
    "addr:postcode":"63000",
    "addr:street":"Yenisehir Osmanbey",
    "iso:country":"TR",
    "sg:address":"Gaziler Cad.bati Ismrk.no:367 Yenisehir",
    "sg:city":"Osmanbey",
    "sg:classifiers":[
        {
            "category":"Shopping",
            "subcategory":"Crafts & Fabrics",
            "type":"Retail Goods"
        }
    ],
    "sg:phone":"+90 232 457 4000",
    "sg:postcode":"63000",
    "sg:province":"Izmir",
    "sg:tags":[
        "textile",
        "-leather",
        "exporter"
    ],
    "wof:name":"Kalkan Konfeksiyon Ltd.",
    "wof:placetype":"venue"
},
  "geometry": {"coordinates":[27.1423015594,38.4251480103],"type":"Point"}
}