{
  "type": "Feature",
  "properties": {
    "iso:country":"TR",
    "sg:address":"P.k. 98",
    "sg:city":"Sincan",
    "sg:classifiers":[
        {
            "category":"Food & Beverages",
            "subcategory":"Candy",
            "type":"Retail Goods"
        }
    ],
    "sg:phone":"+90 272 214 1933",
    "sg:postcode":"31900",
    "sg:province":"Afyon",
    "sg:tags":[
        "biscuit-chocolate-candy"
    ],
    "wof:name":"Al-ko Sekerleme Gida San. Ve Tic. A.s.",
    "wof:placetype":"venue"
},
  "geometry": {"coordinates":[30.536234,39.274254],"type":"Point"}
}