{
  "type": "Feature",
  "properties": {
    "addr:full":"Org. San. Blg. Fahri Karaca Cad. No.45 20200 G??ler Denizli",
    "addr:housenumber":"g ? ?",
    "addr:postcode":"20200",
    "addr:street":"Org.;Karaca Cad. No.45",
    "iso:country":"TR",
    "sg:address":"Org. San. Blg. Fahri Karaca Cad. No.45 20200",
    "sg:city":"G??ler",
    "sg:classifiers":[
        {
            "category":"Shopping",
            "subcategory":"Clothing, Apparel, & Fashions",
            "type":"Retail Goods"
        }
    ],
    "sg:phone":"+90 258 269 1886",
    "sg:province":"Denizli",
    "sg:tags":[
        "ready",
        "wear"
    ],
    "wof:name":"Abalioglu Yem-soya Tekstil San. A.s.",
    "wof:placetype":"venue"
},
  "geometry": {"coordinates":[29.0864906311,37.773525238],"type":"Point"}
}