{
  "type": "Feature",
  "properties": {
    "iso:country":"TR",
    "sg:address":"Demirciler 199. Sk. No:14",
    "sg:city":"\u00dcmraniye",
    "sg:classifiers":[
        {
            "category":"Building & Trades",
            "subcategory":"Construction",
            "type":"Services"
        }
    ],
    "sg:phone":"+90 232 433 4378",
    "sg:province":"Izmir",
    "sg:tags":[
        "industry",
        "mold"
    ],
    "wof:name":"Yilmaz Imalat Kalip San. A.s.",
    "wof:placetype":"venue"
},
  "geometry": {"coordinates":[29.1021766663,37.775100708],"type":"Point"}
}