{
  "type": "Feature",
  "properties": {
    "addr:full":"Asim Gunduz Cd. Banka Sk. Erdem Apt. No: 3 Mersin K?tahya 52750",
    "addr:postcode":"52750",
    "addr:street":"Sk.;Tahya",
    "iso:country":"TR",
    "sg:address":"Asim Gunduz Cd. Banka Sk. Erdem Apt. No: 3",
    "sg:city":"Mersin",
    "sg:classifiers":[
        {
            "category":"Mining & Drilling",
            "type":"Manufacturing & Wholesale Goods"
        }
    ],
    "sg:phone":"+90 274 216 7924",
    "sg:postcode":"52750",
    "sg:province":"K?tahya",
    "sg:tags":[
        "industry",
        "mine"
    ],
    "wof:name":"Kerem Madencilik Ltd.sti.",
    "wof:placetype":"venue"
},
  "geometry": {"coordinates":[37.7128486633,41.0530204773],"type":"Point"}
}