{
  "type": "Feature",
  "properties": {
    "addr:full":"Y?sel Cad. No.8/32 Kizilay Emin\u00f6n\u00fc/Ca\u011falo\u011flu Ankara",
    "addr:housenumber":"no.8 / 32",
    "addr:street":"Sel Cad.",
    "iso:country":"TR",
    "sg:address":"Y?sel Cad. No.8/32 Kizilay",
    "sg:city":"Emin\u00f6n\u00fc/Ca\u011falo\u011flu",
    "sg:classifiers":[
        {
            "category":"Shopping",
            "subcategory":"Stationery & Office Supplies",
            "type":"Retail Goods"
        }
    ],
    "sg:phone":"+90 312 418 8259",
    "sg:province":"Ankara",
    "wof:name":"Turhan Kitabevi",
    "wof:placetype":"venue"
},
  "geometry": {"coordinates":[32.843983,39.953411],"type":"Point"}
}