{
  "type": "Feature",
  "properties": {
    "addr:full":"Bagdat Cd. No:368 Ostim Pinarbasi Ankara 07630",
    "addr:housenumber":"no;ostim",
    "addr:postcode":"07630",
    "addr:street":"Bagdat Cd.",
    "iso:country":"TR",
    "sg:address":"Bagdat Cd. No:368 Ostim",
    "sg:city":"Pinarbasi",
    "sg:classifiers":[
        {
            "category":"Farming",
            "subcategory":"Fish & Marine Products",
            "type":"Manufacturing & Wholesale Goods"
        }
    ],
    "sg:phone":"+90 312 385 0019",
    "sg:postcode":"07630",
    "sg:province":"Ankara",
    "sg:tags":[
        "automotive"
    ],
    "wof:name":"Kuru?ayirli Otomotiv San. Tic. Ltd. Sti.",
    "wof:placetype":"venue"
},
  "geometry": {"coordinates":[32.7540740967,39.9640884399],"type":"Point"}
}