{
  "type": "Feature",
  "properties": {
    "addr:full":"Kulaksiz Mah. Nalinci Yokusu No:29-a Kasimpasa Alsancak Istanbul 35220",
    "addr:housenumber":"29-a",
    "addr:postcode":"35220",
    "addr:street":"Kulaksiz Mah. Nalinci Yokusu No",
    "iso:country":"TR",
    "sg:address":"Kulaksiz Mah. Nalinci Yokusu No:29-a Kasimpasa",
    "sg:city":"Alsancak",
    "sg:classifiers":[
        {
            "category":"Home & Garden",
            "subcategory":"Kitchen Supply",
            "type":"Retail Goods"
        }
    ],
    "sg:phone":"+90 212 297 4432",
    "sg:postcode":"35220",
    "sg:province":"Istanbul",
    "sg:tags":[
        "wardrobe"
    ],
    "wof:name":"Endustriyel Mutfak Servisleri",
    "wof:placetype":"venue"
},
  "geometry": {"coordinates":[28.9654216766,41.0363464355],"type":"Point"}
}