{
  "type": "Feature",
  "properties": {
    "iso:country":"TR",
    "sg:address":"?zel Idare Ishani B-1/5-10",
    "sg:city":"Fatih",
    "sg:classifiers":[
        {
            "category":"Professional",
            "subcategory":"Computer Services",
            "type":"Services"
        }
    ],
    "sg:phone":"+90 258 261 2865",
    "sg:postcode":"34080",
    "sg:province":"Denizli",
    "sg:tags":[
        "application",
        "software"
    ],
    "wof:name":"?gpa Bilgisayar",
    "wof:placetype":"venue"
},
  "geometry": {"coordinates":[29.0788803101,37.7851867676],"type":"Point"}
}