{
  "type": "Feature",
  "properties": {
    "addr:full":"Bagdat Cd. No:190 Kadik? Sisli Istanbul 34620",
    "addr:housenumber":"no",
    "addr:postcode":"34620",
    "addr:street":"Bagdat Cd.;Kadik",
    "iso:country":"TR",
    "sg:address":"Bagdat Cd. No:190 Kadik?",
    "sg:city":"Sisli",
    "sg:classifiers":[
        {
            "category":"Mining & Drilling",
            "type":"Manufacturing & Wholesale Goods"
        }
    ],
    "sg:phone":"+90 216 386 4610",
    "sg:postcode":"34620",
    "sg:province":"Istanbul",
    "sg:tags":[
        "industry",
        "mine"
    ],
    "wof:name":"Filiz Madencilik A.s.",
    "wof:placetype":"venue"
},
  "geometry": {"coordinates":[29.0808982849,40.9601516724],"type":"Point"}
}