{
  "type": "Feature",
  "properties": {
    "iso:country":"TR",
    "sg:address":"Egitim Mah. 1.acikgoz Sok.no.11/2 Hasanpasa",
    "sg:city":"4.levent",
    "sg:orig_category":"Printinh House",
    "sg:phone":"+90 216 330 4250",
    "sg:province":"Istanbul",
    "wof:name":"As Matbaa Ve Reklam Hizmetleri",
    "wof:placetype":"venue"
},
  "geometry": {"coordinates":[29.2499713898,40.9672317505],"type":"Point"}
}