{
  "type": "Feature",
  "properties": {
    "iso:country":"TR",
    "sg:address":"Cevreyolu Cad.orta Mah.no:51",
    "sg:city":"B.pasa",
    "sg:classifiers":[
        {
            "category":"Food & Beverages",
            "subcategory":"Candy",
            "type":"Retail Goods"
        }
    ],
    "sg:phone":"+90 212 567 4583",
    "sg:province":"Istanbul",
    "sg:tags":[
        "biscuit-chocolate-candy"
    ],
    "wof:name":"Cicisan Gida Sanayi A.s",
    "wof:placetype":"venue"
},
  "geometry": {"coordinates":[28.917452,41.034939],"type":"Point"}
}