{
  "type": "Feature",
  "properties": {
    "iso:country":"TR",
    "sg:address":"Yavuzselim Cad. No.33/8 Fatih",
    "sg:city":"Kizilay",
    "sg:classifiers":[
        {
            "category":"Building & Trades",
            "subcategory":"Plumbing",
            "type":"Services"
        }
    ],
    "sg:phone":"+90 212 523 7055",
    "sg:postcode":"06640",
    "sg:province":"Istanbul",
    "wof:name":"Enes Su Aritma Sistemleri",
    "wof:placetype":"venue"
},
  "geometry": {"coordinates":[28.7490940094,41.184879303],"type":"Point"}
}