{
  "type": "Feature",
  "properties": {
    "addr:full":"Cancilar No:21/1 Okmeydani Bursa 43050",
    "addr:postcode":"43050",
    "iso:country":"TR",
    "sg:address":"Cancilar No:21/1",
    "sg:city":"Okmeydani",
    "sg:classifiers":[
        {
            "category":"Building & Trades",
            "subcategory":"Electrical",
            "type":"Services"
        }
    ],
    "sg:phone":"+90 224 222 2289",
    "sg:postcode":"43050",
    "sg:province":"Bursa",
    "sg:tags":[
        "equipment",
        "lighting"
    ],
    "wof:name":"Sule Avize",
    "wof:placetype":"venue"
},
  "geometry": {"coordinates":[29.0666465759,40.1849250793],"type":"Point"}
}