{
  "type": "Feature",
  "properties": {
    "addr:full":"Cemil B. Cd. Yurt Sk. 4 Caglayan Kad\u0131k\u00f6y Istanbul 81010",
    "addr:postcode":"81010",
    "addr:street":"B. Cd.;Sk. 4 Caglayan Kadikoey",
    "iso:country":"TR",
    "sg:address":"Cemil B. Cd. Yurt Sk. 4 Caglayan",
    "sg:city":"Kad\u0131k\u00f6y",
    "sg:orig_category":"Aluminium Carpentary",
    "sg:phone":"+90 212 224 2742",
    "sg:postcode":"81010",
    "sg:province":"Istanbul",
    "wof:name":"Saray Dokum Alum. Dog. A.s.",
    "wof:placetype":"venue"
},
  "geometry": {"coordinates":[28.9821586609,41.0710830688],"type":"Point"}
}