{
  "type": "Feature",
  "properties": {
    "iso:country":"TR",
    "sg:address":"Sakir Pasa Mah. Emekciler Cad. 1089 Sk. No:12/a",
    "sg:city":"Mercan",
    "sg:classifiers":[
        {
            "category":"Sports & Exercise",
            "subcategory":"Ski Slope",
            "type":"Entertainment"
        }
    ],
    "sg:phone":"+90 322 435 3661",
    "sg:postcode":"12600",
    "sg:province":"Adana",
    "sg:tags":[
        "wear"
    ],
    "wof:name":"Leo Jeans Sena Tekstil",
    "wof:placetype":"venue"
},
  "geometry": {"coordinates":[35.313736,37.000717],"type":"Point"}
}