{
  "type": "Feature",
  "properties": {
    "iso:country":"TR",
    "sg:address":"Tabakhaneler Mevkii G?en",
    "sg:city":"Beyazit",
    "sg:classifiers":[
        {
            "category":"Manufacturing",
            "subcategory":"Leather Goods",
            "type":"Manufacturing & Wholesale Goods"
        }
    ],
    "sg:phone":"+90 266 772 6397",
    "sg:postcode":"34490",
    "sg:province":"Balikesir",
    "wof:name":"G?nd?z Deri San.",
    "wof:placetype":"venue"
},
  "geometry": {"coordinates":[27.8833007812,39.6520996094],"type":"Point"}
}