{
  "type": "Feature",
  "properties": {
    "addr:full":"Misir Carsisi No:75 Eminonu ?emberlitas Istanbul 34440",
    "addr:housenumber":"?",
    "addr:postcode":"34440",
    "addr:street":"No 75 Eminonu",
    "iso:country":"TR",
    "sg:address":"Misir Carsisi No:75 Eminonu",
    "sg:city":"?emberlitas",
    "sg:classifiers":[
        {
            "category":"Shopping",
            "subcategory":"Jewelry",
            "type":"Retail Goods"
        }
    ],
    "sg:phone":"+90 212 528 6760",
    "sg:postcode":"34440",
    "sg:province":"Istanbul",
    "sg:tags":[
        "-",
        "golg-silver"
    ],
    "wof:name":"Seyda Kuyumculuk",
    "wof:placetype":"venue"
},
  "geometry": {"coordinates":[28.9705562592,41.0163879395],"type":"Point"}
}