{
  "type": "Feature",
  "properties": {
    "addr:full":"Saraylar Mh. 458. Sk. Sefak?/ K???kmece Denizli",
    "addr:housenumber":"458;? / k ?",
    "addr:street":"Mh.;Sk. Sefak",
    "iso:country":"TR",
    "sg:address":"Saraylar Mh. 458. Sk.",
    "sg:city":"Sefak?/ K???kmece",
    "sg:classifiers":[
        {
            "category":"Wholesale",
            "subcategory":"Petroleum",
            "type":"Manufacturing & Wholesale Goods"
        }
    ],
    "sg:phone":"+90 258 262 1718",
    "sg:province":"Denizli",
    "wof:name":"G?zl?kaya Petrol",
    "wof:placetype":"venue"
},
  "geometry": {"coordinates":[29.087928772,37.786945343],"type":"Point"}
}