{
  "type": "Feature",
  "properties": {
    "addr:full":"Organize Sanayi B?.eskoop San. Sitesi C.3 Blok No:109 Ikitelli K.?kmece Istanbul",
    "addr:housenumber":"?;blok no 109;?",
    "addr:street":"Organize Sanayi B;San. Sitesi C.3;Ikitelli K.",
    "iso:country":"TR",
    "sg:address":"Organize Sanayi B?.eskoop San. Sitesi C.3 Blok No:109",
    "sg:city":"Ikitelli K.?kmece",
    "sg:classifiers":[
        {
            "category":"Manufacturing",
            "subcategory":"Building Materials",
            "type":"Manufacturing & Wholesale Goods"
        }
    ],
    "sg:phone":"+90 212 671 3091",
    "sg:province":"Istanbul",
    "sg:tags":[
        "lifts-elevators"
    ],
    "wof:name":"?zyigit Vin?ve Y? Asans?leri San.",
    "wof:placetype":"venue"
},
  "geometry": {"coordinates":[28.9759254456,41.0123786926],"type":"Point"}
}