{
  "type": "Feature",
  "properties": {
    "iso:country":"TR",
    "sg:address":"4.levent Oto Sanayi Sitesi Celik Sok.celik Sok.no:44 -",
    "sg:city":"4.levent",
    "sg:classifiers":[
        {
            "category":"Home & Garden",
            "subcategory":"Home Furnishings",
            "type":"Retail Goods"
        }
    ],
    "sg:phone":"+90 212 279 1028",
    "sg:province":"Istanbul",
    "sg:tags":[
        "-curtains",
        "upholstery"
    ],
    "wof:name":"Aksel Jaluzi Ve Perde San.",
    "wof:placetype":"venue"
},
  "geometry": {"coordinates":[29.019112,41.112995],"type":"Point"}
}