{
  "type": "Feature",
  "properties": {
    "addr:full":"4.cad.no:12/a Yildizevler Mah. Cankaya Karatay Ankara 42000",
    "addr:housenumber":"12 / a",
    "addr:postcode":"42000",
    "addr:street":"Yildizevler Mah. Cankaya",
    "iso:country":"TR",
    "sg:address":"4.cad.no:12/a Yildizevler Mah. Cankaya",
    "sg:city":"Karatay",
    "sg:classifiers":[
        {
            "category":"Home & Garden",
            "subcategory":"Hardware",
            "type":"Retail Goods"
        }
    ],
    "sg:phone":"+90 312 441 7395",
    "sg:postcode":"42000",
    "sg:province":"Ankara",
    "sg:tags":[
        "compressor",
        "pump"
    ],
    "wof:name":"Tektes",
    "wof:placetype":"venue"
},
  "geometry": {"coordinates":[32.8607215881,39.8764305115],"type":"Point"}
}