{
  "type": "Feature",
  "properties": {
    "addr:full":"Mithat Pasa Cad. No: 277 /a Konak Izmir 07110",
    "addr:housenumber":"277 / a",
    "addr:postcode":"07110",
    "addr:street":"Pasa Cad. No;Konak Izmir",
    "iso:country":"TR",
    "sg:address":"Mithat Pasa Cad. No: 277 /a",
    "sg:city":"Konak",
    "sg:classifiers":[
        {
            "category":"Home & Garden",
            "subcategory":"Household Appliances",
            "type":"Retail Goods"
        }
    ],
    "sg:phone":"+90 232 425 0330",
    "sg:postcode":"07110",
    "sg:province":"Izmir",
    "sg:tags":[
        "conditioner",
        "air"
    ],
    "wof:name":"Alfa Klima Mak.muhendislik Ltd.sti.",
    "wof:placetype":"venue"
},
  "geometry": {"coordinates":[27.8800258636,39.6436042786],"type":"Point"}
}