{
  "type": "Feature",
  "properties": {
    "iso:country":"TR",
    "sg:address":"2131 Sok 31/2 Adalet Mahallesi - Bayrakli",
    "sg:city":"Iskenderun",
    "sg:classifiers":[
        {
            "category":"Mining & Drilling",
            "type":"Manufacturing & Wholesale Goods"
        }
    ],
    "sg:phone":"+90 232 460 1339",
    "sg:postcode":"31200",
    "sg:province":"Izmir",
    "sg:tags":[
        "industry",
        "mine"
    ],
    "wof:name":"Enli Madencilik Sanayi Ve Ticaret A.s.",
    "wof:placetype":"venue"
},
  "geometry": {"coordinates":[27.178150177,38.4538993835],"type":"Point"}
}