{
  "type": "Feature",
  "properties": {
    "addr:full":"Oruculer Sok.no:14 Mercan Istanbul 12600",
    "addr:housenumber":"14",
    "addr:postcode":"12600",
    "addr:street":"Mercan Istanbul",
    "iso:country":"TR",
    "sg:address":"Oruculer Sok.no:14",
    "sg:city":"Mercan",
    "sg:classifiers":[
        {
            "category":"Parking",
            "subcategory":"Garage",
            "type":"Transportation"
        }
    ],
    "sg:phone":"+90 212 522 3377",
    "sg:postcode":"12600",
    "sg:province":"Istanbul",
    "sg:tags":[
        "zipper"
    ],
    "wof:name":"Ugur Fermuar",
    "wof:placetype":"venue"
},
  "geometry": {"coordinates":[28.967464447,41.0128631592],"type":"Point"}
}