{
  "type": "Feature",
  "properties": {
    "addr:full":"Pasalimani Cadesi No:3 - ?sk?ar 16010 Istanbul",
    "addr:postcode":"?;16010",
    "addr:street":"No;?",
    "iso:country":"TR",
    "sg:address":"Pasalimani Cadesi No:3 - ?sk?ar",
    "sg:city":"16010",
    "sg:classifiers":[
        {
            "category":"Health Services",
            "subcategory":"Clinic",
            "type":"Services"
        }
    ],
    "sg:phone":"+90 216 341 7090",
    "sg:province":"Istanbul",
    "wof:name":"Mihrimah Sultan Tip Merkezi",
    "wof:placetype":"venue"
},
  "geometry": {"coordinates":[28.9861793518,41.040851593],"type":"Point"}
}