{
  "type": "Feature",
  "properties": {
    "addr:full":"Antalya Kargo Kuzguncuk Antalya 42310",
    "addr:postcode":"42310",
    "iso:country":"TR",
    "sg:address":"Antalya Kargo",
    "sg:city":"Kuzguncuk",
    "sg:classifiers":[
        {
            "category":"Freight",
            "type":"Transportation"
        }
    ],
    "sg:phone":"+90 242330322033",
    "sg:postcode":"42310",
    "sg:province":"Antalya",
    "sg:tags":[
        "cargo",
        "air"
    ],
    "wof:name":"Turkish Airlines (thy)",
    "wof:placetype":"venue"
},
  "geometry": {"coordinates":[30.7031345367,36.8875045776],"type":"Point"}
}