{
  "type": "Feature",
  "properties": {
    "iso:country":"TR",
    "sg:address":"Mevlevi Cad. No:4/40",
    "sg:city":"\u00c7ankaya",
    "sg:classifiers":[
        {
            "category":"Wholesale",
            "subcategory":"Medical Equipment & Supplies",
            "type":"Manufacturing & Wholesale Goods"
        }
    ],
    "sg:phone":"+90 352 231 7747",
    "sg:postcode":"06420",
    "sg:province":"Kayseri",
    "sg:tags":[
        "material"
    ],
    "wof:name":"Misirli Medikal",
    "wof:placetype":"venue"
},
  "geometry": {"coordinates":[35.4901237488,38.719833374],"type":"Point"}
}