{
  "type": "Feature",
  "properties": {
    "iso:country":"TR",
    "sg:address":"E.buyukdere Cad.no:19 4",
    "sg:city":"Levet",
    "sg:classifiers":[
        {
            "category":"Bars & Pubs",
            "subcategory":"Nightclub",
            "type":"Food & Drink"
        }
    ],
    "sg:phone":"+90 212 264 0567",
    "sg:province":"Istanbul",
    "sg:tags":[
        "cake",
        "sweet"
    ],
    "wof:name":"Ari Gida San.a.s.",
    "wof:placetype":"venue"
},
  "geometry": {"coordinates":[29.013901,41.077305],"type":"Point"}
}