{
  "type": "Feature",
  "properties": {
    "addr:full":"Muh. Naci Bey Cad. Basegmez Apt. No:1/3 A.?ve?ler Kayseri 06460",
    "addr:housenumber":"3 a. ?;?",
    "addr:postcode":"06460",
    "addr:street":"Muh.;Bey Cad. Basegmez Apt. No 1 /;Ve",
    "iso:country":"TR",
    "sg:address":"Muh. Naci Bey Cad. Basegmez Apt. No:1/3",
    "sg:city":"A.?ve?ler",
    "sg:classifiers":[
        {
            "category":"Wholesale",
            "subcategory":"Machinery & Supplies",
            "type":"Manufacturing & Wholesale Goods"
        }
    ],
    "sg:phone":"+90 352 222 2220",
    "sg:postcode":"06460",
    "sg:province":"Kayseri",
    "sg:tags":[
        "laboratory",
        "equipment"
    ],
    "wof:name":"Cetinkaya Medikal",
    "wof:placetype":"venue"
},
  "geometry": {"coordinates":[35.4891357422,38.7225761414],"type":"Point"}
}