{
  "type": "Feature",
  "properties": {
    "addr:full":"Koska Cad.8 Laleli Istanbul 24300",
    "addr:postcode":"24300",
    "iso:country":"TR",
    "sg:address":"Koska Cad.8",
    "sg:city":"Laleli",
    "sg:orig_category":"Hotels: Motels",
    "sg:phone":"+90 212518828010",
    "sg:postcode":"24300",
    "sg:province":"Istanbul",
    "wof:name":"Prestige Hotel",
    "wof:placetype":"venue"
},
  "geometry": {"coordinates":[28.957906723,41.0076599121],"type":"Point"}
}