{
  "type": "Feature",
  "properties": {
    "iso:country":"TR",
    "sg:address":"402.sok. No:35 3.sanayi Sitesi Bornova",
    "sg:city":"Pendik",
    "sg:classifiers":[
        {
            "category":"Shopping",
            "subcategory":"Bicycles & Sporting Goods",
            "type":"Retail Goods"
        }
    ],
    "sg:phone":"+90 232 486 2910",
    "sg:postcode":"81480",
    "sg:province":"Izmir",
    "sg:tags":[
        "motorcycle"
    ],
    "wof:name":"Nurel Ltd.sti.",
    "wof:placetype":"venue"
},
  "geometry": {"coordinates":[27.181913,38.444359],"type":"Point"}
}