{
  "type": "Feature",
  "properties": {
    "addr:full":"Ostim Sanayi Sitesi 56 Sk. No: 151-153 Ostim Ankara 06374",
    "addr:housenumber":"56",
    "addr:postcode":"151-153;06374",
    "addr:street":"Ostim Sanayi Sitesi;Sk. No",
    "iso:country":"TR",
    "sg:address":"Ostim Sanayi Sitesi 56 Sk. No: 151-153",
    "sg:city":"Ostim",
    "sg:classifiers":[
        {
            "category":"Manufacturing",
            "subcategory":"Building Materials",
            "type":"Manufacturing & Wholesale Goods"
        }
    ],
    "sg:phone":"+90 3123540185354",
    "sg:postcode":"06374",
    "sg:province":"Ankara",
    "sg:tags":[
        "lifts-elevators"
    ],
    "wof:name":"Akal Makina Isi San. Tic. Ltd. Sti.",
    "wof:placetype":"venue"
},
  "geometry": {"coordinates":[32.7136268616,39.9477500916],"type":"Point"}
}