{
  "type": "Feature",
  "properties": {
    "iso:country":"TR",
    "sg:address":"Feritpasa Mah. Gokhan Sk. Reyhan Sitesi No.14/a Selcuklu",
    "sg:city":"Mersin",
    "sg:classifiers":[
        {
            "category":"Professional",
            "subcategory":"Computer Services",
            "type":"Services"
        }
    ],
    "sg:phone":"+90 332 238 7700",
    "sg:postcode":"52750",
    "sg:province":"Konya",
    "sg:tags":[
        "application",
        "software"
    ],
    "wof:name":"Oztek Tuketim Maddeleri San. Ve Tic.ltd.sti.",
    "wof:placetype":"venue"
},
  "geometry": {"coordinates":[33.0667152405,39.2111282349],"type":"Point"}
}