{
  "type": "Feature",
  "properties": {
    "addr:full":"Cami Vasat Mah. Inonu Cad. 1 Sok. No:27/a Kartal Balikesir 46000",
    "addr:housenumber":"1;no 27 / a",
    "addr:postcode":"46000",
    "addr:street":"Vasat Mah. Inonu Cad.;Sok.;Kartal Balikesir",
    "iso:country":"TR",
    "sg:address":"Cami Vasat Mah. Inonu Cad. 1 Sok. No:27/a",
    "sg:city":"Kartal",
    "sg:classifiers":[
        {
            "category":"Manufacturing",
            "subcategory":"Building Materials",
            "type":"Manufacturing & Wholesale Goods"
        }
    ],
    "sg:phone":"+90 266 374 9220",
    "sg:postcode":"46000",
    "sg:province":"Balikesir",
    "sg:tags":[
        "lifts-elevators"
    ],
    "wof:name":"Adigey Asansor",
    "wof:placetype":"venue"
},
  "geometry": {"coordinates":[27.8833007812,39.6520996094],"type":"Point"}
}