{
  "type": "Feature",
  "properties": {
    "addr:full":"Eski Meram Yolu Karacigan Camii Sk. No: 32 Ceyhan Konya 01920",
    "addr:housenumber":"32",
    "addr:postcode":"01920",
    "addr:street":"Eski Meram Yolu Karacigan Camii Sk. No",
    "iso:country":"TR",
    "sg:address":"Eski Meram Yolu Karacigan Camii Sk. No: 32",
    "sg:city":"Ceyhan",
    "sg:classifiers":[
        {
            "category":"Wholesale",
            "subcategory":"Machinery & Supplies",
            "type":"Manufacturing & Wholesale Goods"
        }
    ],
    "sg:phone":"+90 332 322 6937",
    "sg:postcode":"01920",
    "sg:province":"Konya",
    "sg:tags":[
        "agricultural"
    ],
    "wof:name":"Celiksac Zir. Mak. San. Koll. Sti.",
    "wof:placetype":"venue"
},
  "geometry": {"coordinates":[32.4990272522,37.8715362549],"type":"Point"}
}