{
  "type": "Feature",
  "properties": {
    "iso:country":"TR",
    "sg:address":"Bogazkesen Cd. No:123",
    "sg:city":"Tophane",
    "sg:classifiers":[
        {
            "category":"Transit Center",
            "subcategory":"Freight",
            "type":"Transportation"
        }
    ],
    "sg:phone":"+90 212 251 8220",
    "sg:postcode":"07400",
    "sg:province":"Istanbul",
    "wof:name":"Mistral Denizcilik A.s.",
    "wof:placetype":"venue"
},
  "geometry": {"coordinates":[28.9796981812,41.0288581848],"type":"Point"}
}