{
  "type": "Feature",
  "properties": {
    "iso:country":"TR",
    "sg:address":"Isiklar Cad.1318 Sok.no:3",
    "sg:city":"Nisantasi",
    "sg:orig_category":"Beaty Parlors",
    "sg:phone":"+90 242 243 8682",
    "sg:postcode":"25370",
    "sg:province":"Antalya",
    "wof:name":"Form Club Guzellik Salonu",
    "wof:placetype":"venue"
},
  "geometry": {"coordinates":[32.864861,39.951187],"type":"Point"}
}