{
  "type": "Feature",
  "properties": {
    "iso:country":"TR",
    "sg:address":"4.cad. No:61 Yildiz-cankaya",
    "sg:city":"Kadikoy",
    "sg:orig_category":"Art Galeries",
    "sg:phone":"+90 312 441 2211",
    "sg:postcode":"01370",
    "sg:province":"Ankara",
    "wof:name":"Spotlight Dans Ve Sahne Sanatlari Merkezi",
    "wof:placetype":"venue"
},
  "geometry": {"coordinates":[32.8604812622,39.9429283142],"type":"Point"}
}