{
  "type": "Feature",
  "properties": {
    "addr:full":"K?k?ler ?arsisi No:22 Kapali?rsi Beyazit Istanbul 34420",
    "addr:housenumber":"22",
    "addr:postcode":"?;34420",
    "addr:street":"Arsisi No;Rsi",
    "iso:country":"TR",
    "sg:address":"K?k?ler ?arsisi No:22 Kapali?rsi",
    "sg:city":"Beyazit",
    "sg:classifiers":[
        {
            "category":"Shopping",
            "subcategory":"Luggage & Leather Goods",
            "type":"Retail Goods"
        }
    ],
    "sg:phone":"+90 5275553",
    "sg:postcode":"34420",
    "sg:province":"Istanbul",
    "sg:tags":[
        "leather-fur",
        "wear"
    ],
    "wof:name":"Ko? Deri",
    "wof:placetype":"venue"
},
  "geometry": {"coordinates":[28.9725131989,41.0255050659],"type":"Point"}
}