{
  "type": "Feature",
  "properties": {
    "addr:full":"?alim Sk. No:19 Siteler Ankara 07070",
    "addr:housenumber":"?;19",
    "addr:postcode":"07070",
    "addr:street":"Alim Sk. No",
    "iso:country":"TR",
    "sg:address":"?alim Sk. No:19",
    "sg:city":"Siteler",
    "sg:classifiers":[
        {
            "category":"Manufacturing",
            "subcategory":"Glass & Minerals",
            "type":"Manufacturing & Wholesale Goods"
        }
    ],
    "sg:phone":"+90 312 348 9162",
    "sg:postcode":"07070",
    "sg:province":"Ankara",
    "sg:tags":[
        "glass-mirror"
    ],
    "wof:name":"Karatas Cam Tic. Ltd. Sti.",
    "wof:placetype":"venue"
},
  "geometry": {"coordinates":[33.0200386047,40.2344245911],"type":"Point"}
}