{
  "type": "Feature",
  "properties": {
    "addr:full":"Gazcilar Cd. Bozkaya Ismerk. No:3 Buca Bursa 35390",
    "addr:postcode":"35390",
    "addr:street":"Gazcilar Cd. Bozkaya Ismerk. No 3 Buca",
    "iso:country":"TR",
    "sg:address":"Gazcilar Cd. Bozkaya Ismerk. No:3",
    "sg:city":"Buca",
    "sg:classifiers":[
        {
            "category":"Professional",
            "subcategory":"Art Services",
            "type":"Services"
        }
    ],
    "sg:phone":"+90 224 254 8117",
    "sg:postcode":"35390",
    "sg:province":"Bursa",
    "sg:tags":[
        "marketing"
    ],
    "wof:name":"Vetas T?ketim Malzeme. End?stri Pazarlama A.s.",
    "wof:placetype":"venue"
},
  "geometry": {"coordinates":[29.0586109161,40.1844291687],"type":"Point"}
}