{
  "type": "Feature",
  "properties": {
    "addr:full":"Kemal? Mah. Milli Egemenlik Cad. No:83/d 27020 Usak",
    "addr:housenumber":"?;83 / d",
    "addr:postcode":"27020",
    "addr:street":"Kemal;Milli Egemenlik Cad. No",
    "iso:country":"TR",
    "sg:address":"Kemal? Mah. Milli Egemenlik Cad. No:83/d",
    "sg:city":"27020",
    "sg:classifiers":[
        {
            "category":"Wholesale",
            "subcategory":"Medical Equipment & Supplies",
            "type":"Manufacturing & Wholesale Goods"
        }
    ],
    "sg:phone":"+90 276 215 4000",
    "sg:province":"Usak",
    "wof:name":"Bugra-med Tibbi Cihazlar Ve Saglik Hizmetleri Ltd.sti.",
    "wof:placetype":"venue"
},
  "geometry": {"coordinates":[29.4063796997,38.5521507263],"type":"Point"}
}