{
  "type": "Feature",
  "properties": {
    "iso:country":"TR",
    "sg:address":"Yakacik Samandira Yolu Callik Mah. Samandira-",
    "sg:city":"Kartal",
    "sg:classifiers":[
        {
            "category":"Structure",
            "subcategory":"Warehouse",
            "type":"Public Place"
        }
    ],
    "sg:phone":"+90 216 311 4590",
    "sg:postcode":"46000",
    "sg:province":"Istanbul",
    "wof:name":"Turker Lojistik",
    "wof:placetype":"venue"
},
  "geometry": {"coordinates":[29.2258892059,40.9841117859],"type":"Point"}
}