{
  "type": "Feature",
  "properties": {
    "addr:full":"Kuseyri Cd. Kavaklilar Sk. Antakya Yenimahalle Hatay 15030",
    "addr:postcode":"15030",
    "addr:street":"Kuseyri Cd. Kavaklilar Sk.",
    "iso:country":"TR",
    "sg:address":"Kuseyri Cd. Kavaklilar Sk. Antakya",
    "sg:city":"Yenimahalle",
    "sg:classifiers":[
        {
            "category":"Banks & Credit Unions",
            "subcategory":"Investment Brokerage",
            "type":"Services"
        }
    ],
    "sg:phone":"+90 326 212 7830",
    "sg:postcode":"15030",
    "sg:province":"Hatay",
    "sg:tags":[
        "-",
        "export",
        "import"
    ],
    "wof:name":"Mena Dis Tic. Ltd. Sti.",
    "wof:placetype":"venue"
},
  "geometry": {"coordinates":[36.2382698059,36.4112091064],"type":"Point"}
}