{
  "type": "Feature",
  "properties": {
    "iso:country":"TR",
    "sg:address":"4321.sok.no:10 Karabaglar",
    "sg:city":"\u00dcmraniye",
    "sg:classifiers":[
        {
            "category":"Shopping",
            "subcategory":"Stationery & Office Supplies",
            "type":"Retail Goods"
        }
    ],
    "sg:phone":"+90 232 253 6215",
    "sg:postcode":"81230",
    "sg:province":"Izmir",
    "sg:tags":[
        "furniture"
    ],
    "wof:name":"Tansu Mobilya Metal Ve Or.ur.san.ve Tic.ltd.sti.",
    "wof:placetype":"venue"
},
  "geometry": {"coordinates":[27.1376056671,38.3662376404],"type":"Point"}
}