{
  "type": "Feature",
  "properties": {
    "iso:country":"TR",
    "sg:address":"Harmantepe Mh. Imren Sk. No: 56 G?tepe",
    "sg:city":"Y.dudullu/?mraniye",
    "sg:classifiers":[
        {
            "category":"Manufacturing",
            "subcategory":"Tools & Machinery",
            "type":"Manufacturing & Wholesale Goods"
        }
    ],
    "sg:phone":"+90 212 269 4037",
    "sg:postcode":"34776",
    "sg:province":"Istanbul",
    "sg:tags":[
        "machine",
        "industry"
    ],
    "wof:name":"?agdas Makina San.",
    "wof:placetype":"venue"
},
  "geometry": {"coordinates":[28.9887313843,41.0476341248],"type":"Point"}
}