{
  "type": "Feature",
  "properties": {
    "iso:country":"TR",
    "sg:address":"Sehit Muhtar Cd. No:70/8 Taksim",
    "sg:city":"Sefak?/ K???kmece",
    "sg:classifiers":[
        {
            "category":"Wholesale",
            "subcategory":"Petroleum",
            "type":"Manufacturing & Wholesale Goods"
        }
    ],
    "sg:phone":"+90 212 256 8490",
    "sg:province":"Istanbul",
    "wof:name":"Hazar Petrol ?rn. End. Tic. A.s.",
    "wof:placetype":"venue"
},
  "geometry": {"coordinates":[28.9846725464,41.0384254456],"type":"Point"}
}