{
  "type": "Feature",
  "properties": {
    "addr:full":"Fevzipasa Caddesi No:130/1 - Fatih Merkez Istanbul",
    "addr:housenumber":"no;/ 1",
    "addr:street":"Fevzipasa Caddesi;Fatih",
    "iso:country":"TR",
    "sg:address":"Fevzipasa Caddesi No:130/1 - Fatih",
    "sg:city":"Merkez",
    "sg:classifiers":[
        {
            "category":"Health Services",
            "subcategory":"Medical Lab",
            "type":"Services"
        }
    ],
    "sg:phone":"+90 212 523 5773",
    "sg:province":"Istanbul",
    "wof:name":"Atikali Laboratuvari",
    "wof:placetype":"venue"
},
  "geometry": {"coordinates":[28.9501304626,41.0054702759],"type":"Point"}
}