{
  "type": "Feature",
  "properties": {
    "addr:full":"Yildirim Beyazit Cad.no:274 Yenibosna/ \u00dcmraniye Istanbul",
    "addr:housenumber":"274",
    "addr:street":"Yenibosna /",
    "iso:country":"TR",
    "sg:address":"Yildirim Beyazit Cad.no:274 Yenibosna/",
    "sg:city":"\u00dcmraniye",
    "sg:classifiers":[
        {
            "category":"Utilities",
            "subcategory":"Fuel Oil & Lpg",
            "type":"Services"
        }
    ],
    "sg:phone":"+90 4516414",
    "sg:province":"Istanbul",
    "sg:tags":[
        "gas",
        "system"
    ],
    "wof:name":"Olipist Otogaz Donusum Sistemleri",
    "wof:placetype":"venue"
},
  "geometry": {"coordinates":[28.824136734,41.0147399902],"type":"Point"}
}