{
  "type": "Feature",
  "properties": {
    "iso:country":"TR",
    "sg:address":"Balmumcu Gazi Umur Pasa Sok. No:20 Besiktas",
    "sg:city":"Besiktas",
    "sg:classifiers":[
        {
            "category":"Home & Garden",
            "subcategory":"Building Materials",
            "type":"Retail Goods"
        }
    ],
    "sg:phone":"+90 212 287 6926",
    "sg:postcode":"75200",
    "sg:province":"Ankara",
    "sg:tags":[
        "window",
        "door"
    ],
    "wof:name":"Taysan Met. San.tic. Ltd.sti.",
    "wof:placetype":"venue"
},
  "geometry": {"coordinates":[32.8604812622,39.9429283142],"type":"Point"}
}