{
  "type": "Feature",
  "properties": {
    "addr:full":"Asmaalti Kizial Sk. No:29 Emin?? Istanbul Yenibosna Istanbul 43270",
    "addr:housenumber":"29;? ?",
    "addr:postcode":"43270",
    "addr:street":"Kizial Sk. No;Yenibosna",
    "iso:country":"TR",
    "sg:address":"Asmaalti Kizial Sk. No:29 Emin?? Istanbul",
    "sg:city":"Yenibosna",
    "sg:classifiers":[
        {
            "category":"Manufacturing",
            "subcategory":"Rubber & Plastics",
            "type":"Manufacturing & Wholesale Goods"
        }
    ],
    "sg:phone":"+90 212 597 2016",
    "sg:postcode":"43270",
    "sg:province":"Istanbul",
    "sg:tags":[
        "industry"
    ],
    "wof:name":"Bilsan Kau?uk Plastik San. A.s.",
    "wof:placetype":"venue"
},
  "geometry": {"coordinates":[28.9759254456,41.0123786926],"type":"Point"}
}