{
  "type": "Feature",
  "properties": {
    "iso:country":"TR",
    "sg:address":"Toptancilar Carsisi 4.blok No:53",
    "sg:city":"Selcuklu",
    "sg:classifiers":[
        {
            "category":"Food & Beverages",
            "subcategory":"Candy",
            "type":"Retail Goods"
        }
    ],
    "sg:phone":"+90 332 233 3331",
    "sg:postcode":"32650",
    "sg:province":"Konya",
    "sg:tags":[
        "biscuit-chocolate-candy"
    ],
    "wof:name":"Cogenler Gida San.",
    "wof:placetype":"venue"
},
  "geometry": {"coordinates":[32.499027,37.871536],"type":"Point"}
}