{
  "type": "Feature",
  "properties": {
    "addr:full":"Yenik? Mah. Turgutreis Cad. No:100 Bodrum Mugla 48400",
    "addr:housenumber":"?;100",
    "addr:postcode":"48400",
    "addr:street":"Mah. Turgutreis Cad. No",
    "iso:country":"TR",
    "sg:address":"Yenik? Mah. Turgutreis Cad. No:100",
    "sg:city":"Bodrum",
    "sg:classifiers":[
        {
            "category":"Recreation",
            "subcategory":"Boat Charter",
            "type":"Entertainment"
        }
    ],
    "sg:phone":"+90 25231658643",
    "sg:postcode":"48400",
    "sg:province":"Mugla",
    "sg:tags":[
        "yachting"
    ],
    "wof:name":"Dolphin Yachting (branch Office)",
    "wof:placetype":"venue"
},
  "geometry": {"coordinates":[28.3658008575,37.2196006775],"type":"Point"}
}