{
  "type": "Feature",
  "properties": {
    "iso:country":"TR",
    "sg:address":"K?r?asi Cd. No:16",
    "sg:city":"Besiktas",
    "sg:classifiers":[
        {
            "category":"Shopping",
            "subcategory":"Stationery & Office Supplies",
            "type":"Retail Goods"
        }
    ],
    "sg:phone":"+90 222 234 1633",
    "sg:postcode":"34347",
    "sg:province":"Eskisehir",
    "wof:name":"Cihan Kirtasiye San. Tic. Koll. Sti.",
    "wof:placetype":"venue"
},
  "geometry": {"coordinates":[30.517546,39.770081],"type":"Point"}
}