{
  "type": "Feature",
  "properties": {
    "addr:full":"Kale K??ank. Asf. Yol ?z. Tuzla Denizli 01900",
    "addr:housenumber":"? z.",
    "addr:postcode":"01900",
    "addr:street":"Kale K ? ? Ank. Asf. Yol",
    "iso:country":"TR",
    "sg:address":"Kale K??ank. Asf. Yol ?z.",
    "sg:city":"Tuzla",
    "sg:classifiers":[
        {
            "category":"Wholesale",
            "subcategory":"Petroleum",
            "type":"Manufacturing & Wholesale Goods"
        }
    ],
    "sg:phone":"+90 258 267 1114",
    "sg:postcode":"01900",
    "sg:province":"Denizli",
    "wof:name":"Akalin Petrol",
    "wof:placetype":"venue"
},
  "geometry": {"coordinates":[29.0864906311,37.773525238],"type":"Point"}
}