{
  "type": "Feature",
  "properties": {
    "iso:country":"TR",
    "sg:address":"Atat?k Organize Sanayi B?gesi 10006 Sok.no:51 B.?igli",
    "sg:city":"Sahinbey",
    "sg:classifiers":[
        {
            "category":"Shopping",
            "subcategory":"Crafts & Fabrics",
            "type":"Retail Goods"
        }
    ],
    "sg:phone":"+90 232 376 7138",
    "sg:postcode":"27700",
    "sg:province":"Izmir",
    "sg:tags":[
        "textile",
        "-leather",
        "exporter"
    ],
    "wof:name":"Milsan Pazarlama A.s",
    "wof:placetype":"venue"
},
  "geometry": {"coordinates":[27.1423015594,38.4251480103],"type":"Point"}
}