{
  "type": "Feature",
  "properties": {
    "iso:country":"TR",
    "sg:address":"Sinama Cad. No:59 Yesiltepe Yolu Belediye Kamyon Garaji",
    "sg:city":"Mecidiyekoy",
    "sg:classifiers":[
        {
            "category":"Airport",
            "subcategory":"International",
            "type":"Transportation"
        }
    ],
    "sg:phone":"+90 422 324 9570",
    "sg:postcode":"80310",
    "sg:province":"Malatya",
    "wof:name":"Ersan Nakliyat",
    "wof:placetype":"venue"
},
  "geometry": {"coordinates":[38.3195266724,38.3488922119],"type":"Point"}
}