{
  "type": "Feature",
  "properties": {
    "addr:full":"G.mustafa Kemal Bul.no:10 Kizilay Cankaya Ankara 07080",
    "addr:housenumber":"10",
    "addr:postcode":"07080",
    "addr:street":"Kizilay Cankaya",
    "iso:country":"TR",
    "sg:address":"G.mustafa Kemal Bul.no:10 Kizilay",
    "sg:city":"Cankaya",
    "sg:classifiers":[
        {
            "category":"Government",
            "subcategory":"Embassy",
            "type":"Public Place"
        }
    ],
    "sg:phone":"+90 312 418 6257",
    "sg:postcode":"07080",
    "sg:province":"Ankara",
    "sg:tags":[
        "foreign"
    ],
    "wof:name":"Macaristan Cumh.b?y?kel?iligi",
    "wof:placetype":"venue"
},
  "geometry": {"coordinates":[32.8515586853,39.9218139648],"type":"Point"}
}