{
  "type": "Feature",
  "properties": {
    "addr:full":"100.yil Bulvari 56. Sok. No:70 Ostim Ankara 06374",
    "addr:housenumber":"56;no 70",
    "addr:postcode":"06374",
    "addr:street":"100.Yil Bulvari;Sok.",
    "iso:country":"TR",
    "sg:address":"100.yil Bulvari 56. Sok. No:70",
    "sg:city":"Ostim",
    "sg:orig_category":"Ostim Ankara",
    "sg:phone":"+90 312 354 0524",
    "sg:postcode":"06374",
    "sg:province":"Ankara",
    "wof:name":"Akarsu Motor Red?kt?r Mak. San. I? Ve Dis Paz. Tic",
    "wof:placetype":"venue"
},
  "geometry": {"coordinates":[32.7458724976,39.9789962769],"type":"Point"}
}