{
  "type": "Feature",
  "properties": {
    "iso:country":"TR",
    "sg:address":"Osmanaga Mah. Kalem Sok. No:7 Kat:4 D:4 Kadikoy",
    "sg:city":"Yukari Dudullu",
    "sg:classifiers":[
        {
            "category":"Shopping",
            "subcategory":"Computers & Home Electronics",
            "type":"Retail Goods"
        }
    ],
    "sg:phone":"+90 216 418 9994",
    "sg:postcode":"34776",
    "sg:province":"Istanbul",
    "sg:tags":[
        "product",
        "electric-electronic"
    ],
    "wof:name":"Emsen Elektrik Muhendislik Taahhut",
    "wof:placetype":"venue"
},
  "geometry": {"coordinates":[28.9861831665,41.0408554077],"type":"Point"}
}