{
  "type": "Feature",
  "properties": {
    "iso:country":"TR",
    "sg:address":"Turhan Cemal Beriker Bul.ziya Algan Is Merkesi Kat 2 No 12",
    "sg:city":"Seyhan",
    "sg:orig_category":"Scavening Services",
    "sg:phone":"+90 322 352 7584",
    "sg:postcode":"01000",
    "sg:province":"Adana",
    "wof:name":"G?lfa Temizlik Taahh?t Ltd.sti",
    "wof:placetype":"venue"
},
  "geometry": {"coordinates":[35.313736,37.000717],"type":"Point"}
}