{
  "type": "Feature",
  "properties": {
    "addr:full":"Organize Sanayi Bolg.7.cad.no:39 Osmanbey Kayseri 63000",
    "addr:housenumber":"39",
    "addr:postcode":"63000",
    "addr:street":"Organize Sanayi Bolg.7.Cad.No",
    "iso:country":"TR",
    "sg:address":"Organize Sanayi Bolg.7.cad.no:39",
    "sg:city":"Osmanbey",
    "sg:classifiers":[
        {
            "category":"Home & Garden",
            "subcategory":"Home Furnishings",
            "type":"Retail Goods"
        }
    ],
    "sg:phone":"+90 352 321 1792",
    "sg:postcode":"63000",
    "sg:province":"Kayseri",
    "sg:tags":[
        "quilt",
        "bed"
    ],
    "wof:name":"Nevyat A.s.",
    "wof:placetype":"venue"
},
  "geometry": {"coordinates":[35.489136,38.722576],"type":"Point"}
}