{
  "type": "Feature",
  "properties": {
    "iso:country":"TR",
    "sg:address":"100. Yil Omorfo Mh. No:171/6 Balgat",
    "sg:city":"Basinevleri",
    "sg:classifiers":[
        {
            "category":"Wholesale",
            "subcategory":"Books, Periodicals, & Newspapers",
            "type":"Manufacturing & Wholesale Goods"
        }
    ],
    "sg:phone":"+90 312 287 8366",
    "sg:postcode":"06010",
    "sg:province":"Ankara",
    "sg:tags":[
        "house",
        "publishing"
    ],
    "wof:name":"Berkin Yayinci. Koll. Sti.",
    "wof:placetype":"venue"
},
  "geometry": {"coordinates":[32.8331260681,39.9742012024],"type":"Point"}
}