{
  "type": "Feature",
  "properties": {
    "addr:full":"Dolanti Sk. No:10 Siteler Ankara 07070",
    "addr:housenumber":"10",
    "addr:postcode":"07070",
    "addr:street":"Dolanti Sk. No",
    "iso:country":"TR",
    "sg:address":"Dolanti Sk. No:10",
    "sg:city":"Siteler",
    "sg:classifiers":[
        {
            "category":"Home & Garden",
            "subcategory":"Home Furnishings",
            "type":"Retail Goods"
        }
    ],
    "sg:phone":"+90 312 349 1845",
    "sg:postcode":"07070",
    "sg:province":"Ankara",
    "sg:tags":[
        "-curtains",
        "upholstery"
    ],
    "wof:name":"?z G?leser Mensucat Ltd. Sti.",
    "wof:placetype":"venue"
},
  "geometry": {"coordinates":[32.9023475647,39.9601554871],"type":"Point"}
}