{
  "type": "Feature",
  "properties": {
    "iso:country":"TR",
    "sg:address":"Fatih Mah. Eski San.futbol Sahasi Yani No: 10/a",
    "sg:city":"Bayrampasa",
    "sg:classifiers":[
        {
            "category":"Food & Beverages",
            "subcategory":"Meat & Fish",
            "type":"Retail Goods"
        }
    ],
    "sg:phone":"+90 332 251 7780",
    "sg:postcode":"34",
    "sg:province":"Konya",
    "sg:tags":[
        "product"
    ],
    "wof:name":"Selet Et Ve Sut Urunleri San.tic.a.s.",
    "wof:placetype":"venue"
},
  "geometry": {"coordinates":[33.0667152405,39.2111282349],"type":"Point"}
}