{
  "type": "Feature",
  "properties": {
    "iso:country":"TR",
    "sg:address":"Tem Yolu Kavacik Kavsagi Ford Plaza Ruzgarlibahce",
    "sg:city":"B.?ekmece",
    "sg:classifiers":[
        {
            "category":"Farming",
            "subcategory":"Fish & Marine Products",
            "type":"Manufacturing & Wholesale Goods"
        }
    ],
    "sg:phone":"+90 216 413 7200",
    "sg:province":"Istanbul",
    "sg:tags":[
        "automotive"
    ],
    "wof:name":"Gurbaslar Otomotiv San.tic.a.s.",
    "wof:placetype":"venue"
},
  "geometry": {"coordinates":[29.101808548,41.091758728],"type":"Point"}
}