{
  "type": "Feature",
  "properties": {
    "iso:country":"TR",
    "sg:address":"Kirsehir Cad. No:21",
    "sg:city":"Bala",
    "sg:classifiers":[
        {
            "category":"Farming",
            "subcategory":"Farm & Veterinary Services",
            "type":"Manufacturing & Wholesale Goods"
        }
    ],
    "sg:phone":"+90 312 876 1512",
    "sg:postcode":"15800",
    "sg:province":"Ankara",
    "sg:tags":[
        "veterinarian"
    ],
    "wof:name":"Omer Keskin",
    "wof:placetype":"venue"
},
  "geometry": {"coordinates":[34.1664237976,39.1499519348],"type":"Point"}
}