{
  "type": "Feature",
  "properties": {
    "addr:full":"Fahrettin Altay Cad Melih Sargin Apt No:26 Sehitkamil Antalya 27000",
    "addr:housenumber":"26",
    "addr:postcode":"27000",
    "addr:street":"Fahrettin Altay Cad Melih Sargin Apt No",
    "iso:country":"TR",
    "sg:address":"Fahrettin Altay Cad Melih Sargin Apt No:26",
    "sg:city":"Sehitkamil",
    "sg:classifiers":[
        {
            "category":"Manufacturing",
            "subcategory":"Glass & Minerals",
            "type":"Manufacturing & Wholesale Goods"
        }
    ],
    "sg:phone":"+90 242 322 2701",
    "sg:postcode":"27000",
    "sg:province":"Antalya",
    "sg:tags":[
        "glass-mirror"
    ],
    "wof:name":"Gur-al Cam Ticaret",
    "wof:placetype":"venue"
},
  "geometry": {"coordinates":[30.7031345367,36.8875045776],"type":"Point"}
}