{
  "type": "Feature",
  "properties": {
    "iso:country":"TR",
    "sg:address":"Fatih Mh. Pehlivanlar Sk. No:107",
    "sg:city":"Eregli",
    "sg:classifiers":[
        {
            "category":"Food & Beverages",
            "subcategory":"Dairy",
            "type":"Retail Goods"
        }
    ],
    "sg:phone":"+90 222",
    "sg:postcode":"42310",
    "sg:province":"Eskisehir",
    "sg:tags":[
        "pruducts",
        "milk"
    ],
    "wof:name":"La?in Maden Suyu Tic. San. Ltd. Sti.",
    "wof:placetype":"venue"
},
  "geometry": {"coordinates":[30.5224189758,39.7914924622],"type":"Point"}
}