{
  "type": "Feature",
  "properties": {
    "addr:full":"Kayisdagi Mah. Yazici Sk. No: 7/1 Kayisdagi Istanbul 34755",
    "addr:housenumber":"1",
    "addr:postcode":"34755",
    "addr:street":"Kayisdagi Mah. Yazici Sk. No 7 /",
    "iso:country":"TR",
    "sg:address":"Kayisdagi Mah. Yazici Sk. No: 7/1",
    "sg:city":"Kayisdagi",
    "sg:classifiers":[
        {
            "category":"Home & Garden",
            "subcategory":"Building Materials",
            "type":"Retail Goods"
        }
    ],
    "sg:phone":"+90 216 410 5409",
    "sg:postcode":"34755",
    "sg:province":"Istanbul",
    "sg:tags":[
        "window",
        "door"
    ],
    "wof:name":"Wegoma Makina San. Ve Tic. Ltd. Sti.",
    "wof:placetype":"venue"
},
  "geometry": {"coordinates":[28.9861831665,41.0408554077],"type":"Point"}
}