{
  "type": "Feature",
  "properties": {
    "addr:full":"Sinan Mah.1258 Sok.eyi? Apt.no:10/c Zeytinburnu Antalya 41000",
    "addr:housenumber":"mah.1258 sok.eyi ?;10 / c",
    "addr:postcode":"41000",
    "addr:street":"Sinan;Apt.No;Zeytinburnu",
    "iso:country":"TR",
    "sg:address":"Sinan Mah.1258 Sok.eyi? Apt.no:10/c",
    "sg:city":"Zeytinburnu",
    "sg:classifiers":[
        {
            "category":"Shopping",
            "subcategory":"Luggage & Leather Goods",
            "type":"Retail Goods"
        }
    ],
    "sg:phone":"+90 242 312 1673",
    "sg:postcode":"41000",
    "sg:province":"Antalya",
    "sg:tags":[
        "leather-fur",
        "wear"
    ],
    "wof:name":"Simge Deri",
    "wof:placetype":"venue"
},
  "geometry": {"coordinates":[30.7031345367,36.8875045776],"type":"Point"}
}