{
  "type": "Feature",
  "properties": {
    "addr:full":"Alemdag Cad. No:284 Umraniye Hask?y-beyoglu Istanbul 34440",
    "addr:housenumber":"284",
    "addr:postcode":"34440",
    "addr:street":"Alemdag Cad. No",
    "iso:country":"TR",
    "sg:address":"Alemdag Cad. No:284 Umraniye",
    "sg:city":"Hask?y-beyoglu",
    "sg:classifiers":[
        {
            "category":"Shopping",
            "subcategory":"Stationery & Office Supplies",
            "type":"Retail Goods"
        }
    ],
    "sg:phone":"+90 212 328 2915",
    "sg:postcode":"34440",
    "sg:province":"Istanbul",
    "sg:tags":[
        "furniture"
    ],
    "wof:name":"Hamurcuoglu Celik Esya Ve Buro Mob.san.tic.",
    "wof:placetype":"venue"
},
  "geometry": {"coordinates":[29.1050319672,41.0246353149],"type":"Point"}
}