{
  "type": "Feature",
  "properties": {
    "iso:country":"TR",
    "sg:address":"Plaza C Blok K 14, B??dere Cad Yapi Kredi Plaza, Levent, 80620 Istanbul",
    "sg:city":"Levent",
    "sg:classifiers":[
        {
            "category":"Banks & Credit Unions",
            "subcategory":"Bank",
            "type":"Services"
        }
    ],
    "sg:phone":"+90 212 279 7070",
    "sg:postcode":"01310",
    "sg:province":"Istanbul",
    "wof:name":"Credit Agricole Indosuez T?k Bank As",
    "wof:placetype":"venue"
},
  "geometry": {"coordinates":[28.975925,41.012379],"type":"Point"}
}