{
  "type": "Feature",
  "properties": {
    "addr:full":"Nuruosmaniye Cd. Yesilay Ish. No:17/1 K:3 Alemdar Mecidiyek\u00f6y Istanbul 34387",
    "addr:housenumber":"17 / 1 k 3",
    "addr:postcode":"34387",
    "addr:street":"Nuruosmaniye Cd. Yesilay Ish. No",
    "iso:country":"TR",
    "sg:address":"Nuruosmaniye Cd. Yesilay Ish. No:17/1 K:3 Alemdar",
    "sg:city":"Mecidiyek\u00f6y",
    "sg:classifiers":[
        {
            "category":"Organizations",
            "subcategory":"Membership Organization",
            "type":"Services"
        }
    ],
    "sg:phone":"+90 212 527 1683",
    "sg:postcode":"34387",
    "sg:province":"Istanbul",
    "wof:name":"Turkiye Yesilay Cem.",
    "wof:placetype":"venue"
},
  "geometry": {"coordinates":[28.9861831665,41.0408554077],"type":"Point"}
}