{
  "type": "Feature",
  "properties": {
    "addr:full":"Gazcilar Cad.bayar Sok. No:25/13 -a Merdivenkoy Bursa 34732",
    "addr:housenumber":"no 25 / 13 a",
    "addr:postcode":"34732",
    "addr:street":"Cad.Bayar Sok.;Bursa",
    "iso:country":"TR",
    "sg:address":"Gazcilar Cad.bayar Sok. No:25/13 -a",
    "sg:city":"Merdivenkoy",
    "sg:classifiers":[
        {
            "category":"Home & Garden",
            "subcategory":"Household Appliances",
            "type":"Retail Goods"
        }
    ],
    "sg:phone":"+90 224 273 4550",
    "sg:postcode":"34732",
    "sg:province":"Bursa",
    "sg:tags":[
        "conditioner",
        "air"
    ],
    "wof:name":"Donati Yalitim Isitma Havalandirma Taah.san. Tic.ltd.sti.",
    "wof:placetype":"venue"
},
  "geometry": {"coordinates":[29.0639476776,40.1940803528],"type":"Point"}
}