{
  "type": "Feature",
  "properties": {
    "addr:full":"Halkali Cad. Evren Mah. Seven Sok. No:2 Bagcilar Okmeydani Istanbul 43050",
    "addr:housenumber":"mah.;no 2",
    "addr:postcode":"43050",
    "addr:street":"Halkali Cad. Evren;Seven Sok.",
    "iso:country":"TR",
    "sg:address":"Halkali Cad. Evren Mah. Seven Sok. No:2 Bagcilar",
    "sg:city":"Okmeydani",
    "sg:classifiers":[
        {
            "category":"Shopping",
            "subcategory":"Stationery & Office Supplies",
            "type":"Retail Goods"
        }
    ],
    "sg:phone":"+90 212 630 3004",
    "sg:postcode":"43050",
    "sg:province":"Istanbul",
    "wof:name":"Speck Store Kubra Bilg Ve Buro Malz. San.tic. Ltd.sti.",
    "wof:placetype":"venue"
},
  "geometry": {"coordinates":[28.815723,41.032856],"type":"Point"}
}