{
  "type": "Feature",
  "properties": {
    "addr:full":"Gebze \u00dcsk\u00fcdar Kocaeli",
    "iso:country":"TR",
    "sg:address":"Gebze",
    "sg:city":"\u00dcsk\u00fcdar",
    "sg:classifiers":[
        {
            "category":"Transit Center",
            "subcategory":"Freight",
            "type":"Transportation"
        }
    ],
    "sg:phone":"+90 262 641 8294",
    "sg:province":"Kocaeli",
    "wof:name":"Berk Denizcilik Tic. Ltd. Sti.",
    "wof:placetype":"venue"
},
  "geometry": {"coordinates":[29.4381008148,40.800201416],"type":"Point"}
}