{
  "type": "Feature",
  "properties": {
    "iso:country":"TR",
    "sg:address":"Cevizlibag Yilanli Ayazma Yolu No. 18/73 Yildiz San.i Sitesi 34020 Topkapi Istanbul",
    "sg:city":"Erenk?",
    "sg:classifiers":[
        {
            "category":"Wholesale",
            "subcategory":"Machinery & Supplies",
            "type":"Manufacturing & Wholesale Goods"
        }
    ],
    "sg:phone":"+90 212 482 0983",
    "sg:province":"Istanbul",
    "sg:tags":[
        "equipment",
        "-",
        "instrument",
        "measurement"
    ],
    "wof:name":"Devotrans Elektrik Makineleri San. Tic Ltd Sti",
    "wof:placetype":"venue"
},
  "geometry": {"coordinates":[28.9364204407,41.0178985596],"type":"Point"}
}