{
  "type": "Feature",
  "properties": {
    "iso:country":"TR",
    "sg:address":"Turgut Ozal Cad. No:120 Ikitelli Organize San. Bolg. 34650 K.cekmece Istanbul",
    "sg:city":"Ikitelli/K\u00fc\u00e7\u00fck\u00e7ekmece",
    "sg:classifiers":[
        {
            "category":"Shopping",
            "subcategory":"Crafts & Fabrics",
            "type":"Retail Goods"
        }
    ],
    "sg:phone":"+90 212 549 2002",
    "sg:postcode":"34670",
    "sg:province":"Istanbul",
    "wof:name":"Akkon Iplik San. Ve Tic. As.",
    "wof:placetype":"venue"
},
  "geometry": {"coordinates":[28.9759254456,41.0123786926],"type":"Point"}
}