{
  "type": "Feature",
  "properties": {
    "addr:full":"100. Evler Bagdat Cd. Sefer Sk. No:6 K.maltepe Istanbul",
    "addr:housenumber":"100",
    "addr:street":"Evler Bagdat Cd. Sefer Sk. No 6 K.Maltepe",
    "iso:country":"TR",
    "sg:address":"100. Evler Bagdat Cd. Sefer Sk. No:6",
    "sg:city":"K.maltepe",
    "sg:classifiers":[
        {
            "category":"Home & Garden",
            "subcategory":"Building Materials",
            "type":"Retail Goods"
        }
    ],
    "sg:phone":"+90 216 371 0848",
    "sg:province":"Istanbul",
    "sg:tags":[
        "window",
        "door"
    ],
    "wof:name":"Rasyonel Celik Kapi",
    "wof:placetype":"venue"
},
  "geometry": {"coordinates":[28.9861831665,41.0408554077],"type":"Point"}
}