{
  "type": "Feature",
  "properties": {
    "addr:full":"Org San Bol Ss Metal Ist.5 Yol Ikitelli 34650 K.cekmece Istanbul Sariyer Istanbul 33740",
    "addr:postcode":"34650;33740",
    "iso:country":"TR",
    "sg:address":"Org San Bol Ss Metal Ist.5 Yol Ikitelli 34650 K.cekmece Istanbul",
    "sg:city":"Sariyer",
    "sg:orig_category":"Miscellaneous Products",
    "sg:phone":"+90 212 549 5782",
    "sg:postcode":"33740",
    "sg:province":"Istanbul",
    "wof:name":"Varlik Makina San Ic Ve Dis Tic",
    "wof:placetype":"venue"
},
  "geometry": {"coordinates":[28.9759254456,41.0123786926],"type":"Point"}
}