{
  "type": "Feature",
  "properties": {
    "addr:full":"Mersin Tarsus Org. San.bol. Idari Binasi Huzurkent -tarsus Sirinyer I?el 35140",
    "addr:postcode":"35140",
    "addr:street":"El",
    "iso:country":"TR",
    "sg:address":"Mersin Tarsus Org. San.bol. Idari Binasi Huzurkent -tarsus",
    "sg:city":"Sirinyer",
    "sg:classifiers":[
        {
            "category":"Organizations",
            "subcategory":"Membership Organization",
            "type":"Services"
        }
    ],
    "sg:phone":"+90 324 676 4252",
    "sg:postcode":"35140",
    "sg:province":"I?el",
    "wof:name":"Morskud Mersin-tarsus Org.san.bol.kulanicillar Dernegi",
    "wof:placetype":"venue"
},
  "geometry": {"coordinates":[34.8869895935,36.9086418152],"type":"Point"}
}