{
  "type": "Feature",
  "properties": {
    "addr:full":"Istasyon Cad. No:3 Erenkoy Istanbul 07060",
    "addr:postcode":"07060",
    "addr:street":"Istasyon Cad. No 3 Erenkoy",
    "iso:country":"TR",
    "sg:address":"Istasyon Cad. No:3",
    "sg:city":"Erenkoy",
    "sg:classifiers":[
        {
            "category":"Food & Beverages",
            "subcategory":"Groceries & Convenience Stores",
            "type":"Retail Goods"
        }
    ],
    "sg:phone":"+90 216 445 0532",
    "sg:postcode":"07060",
    "sg:province":"Istanbul",
    "sg:tags":[
        "product"
    ],
    "wof:name":"Elifoglu Gida San. Ve Tic. Ltd.sti.",
    "wof:placetype":"venue"
},
  "geometry": {"coordinates":[29.3033657074,40.8160438538],"type":"Point"}
}