{
  "type": "Feature",
  "properties": {
    "iso:country":"TR",
    "sg:address":"Kemerkaya Mah. Sultan Sok. No: 10/2",
    "sg:city":"Taksim",
    "sg:classifiers":[
        {
            "category":"Travel",
            "subcategory":"Travel Agent",
            "type":"Entertainment"
        }
    ],
    "sg:phone":"+90 4623262667683",
    "sg:postcode":"24040",
    "sg:province":"Trabzon",
    "sg:tags":[
        "agency",
        "tourism"
    ],
    "wof:name":"Kiyi Tur Turizm",
    "wof:placetype":"venue"
},
  "geometry": {"coordinates":[39.7165603638,41.0012931824],"type":"Point"}
}