{
  "type": "Feature",
  "properties": {
    "iso:country":"TR",
    "sg:address":"Fatih Mah. Camlik Cad. 184.sok. No:45",
    "sg:city":"Sarnic",
    "sg:classifiers":[
        {
            "category":"Shopping",
            "subcategory":"Baby Store",
            "type":"Retail Goods"
        }
    ],
    "sg:phone":"+90 232 281 2200",
    "sg:postcode":"35414",
    "sg:province":"Izmir",
    "sg:tags":[
        "wear"
    ],
    "wof:name":"Leana Tekstil San. Ve Tic. Ltd.sti.",
    "wof:placetype":"venue"
},
  "geometry": {"coordinates":[27.170511,38.309872],"type":"Point"}
}