{
  "type": "Feature",
  "properties": {
    "addr:full":"Cumhuriyet Mah Mehmetcik Sok. No:16 Bahcelievler Istanbul 01980",
    "addr:housenumber":"no 16",
    "addr:postcode":"01980",
    "addr:street":"Mehmetcik Sok.",
    "iso:country":"TR",
    "sg:address":"Cumhuriyet Mah Mehmetcik Sok. No:16",
    "sg:city":"Bahcelievler",
    "sg:classifiers":[
        {
            "category":"Manufacturing",
            "subcategory":"Building Materials",
            "type":"Manufacturing & Wholesale Goods"
        }
    ],
    "sg:phone":"+90 212 555 7778",
    "sg:postcode":"01980",
    "sg:province":"Istanbul",
    "sg:tags":[
        "lifts-elevators"
    ],
    "wof:name":"Gizem Ozmus Asans? San",
    "wof:placetype":"venue"
},
  "geometry": {"coordinates":[28.854385376,41.0147781372],"type":"Point"}
}