{
  "type": "Feature",
  "properties": {
    "addr:full":"Ulu Cad. Tan Sok. Kamburoglu Is Hani No:6/9 Osmangazi Ikitelli/K\u00fc\u00e7\u00fck\u00e7ekmece Bursa 34670",
    "addr:housenumber":"9",
    "addr:postcode":"34670",
    "addr:street":"Ulu Cad. Tan Sok. Kamburoglu Is;No 6 /",
    "iso:country":"TR",
    "sg:address":"Ulu Cad. Tan Sok. Kamburoglu Is Hani No:6/9 Osmangazi",
    "sg:city":"Ikitelli/K\u00fc\u00e7\u00fck\u00e7ekmece",
    "sg:classifiers":[
        {
            "category":"Manufacturing",
            "subcategory":"Rubber & Plastics",
            "type":"Manufacturing & Wholesale Goods"
        }
    ],
    "sg:phone":"+90 224256089091",
    "sg:postcode":"34670",
    "sg:province":"Bursa",
    "sg:tags":[
        "industry"
    ],
    "wof:name":"Eskapet Pet Urunleri",
    "wof:placetype":"venue"
},
  "geometry": {"coordinates":[29.0580043793,40.1947555542],"type":"Point"}
}