{
  "type": "Feature",
  "properties": {
    "addr:full":"Ipkas Plastikciler Sanayi Sitesi Ikitelli Org.san.b?.9/a Blok No:32-34 2.ulus Istanbul",
    "addr:housenumber":"9 / a blok no 32-34",
    "addr:postcode":"2.ulus",
    "addr:street":"Plastikciler Sanayi Sitesi Ikitelli Org.San.B ?",
    "iso:country":"TR",
    "sg:address":"Ipkas Plastikciler Sanayi Sitesi Ikitelli Org.san.b?.9/a Blok No:32-34",
    "sg:city":"2.ulus",
    "sg:classifiers":[
        {
            "category":"Manufacturing",
            "subcategory":"Rubber & Plastics",
            "type":"Manufacturing & Wholesale Goods"
        }
    ],
    "sg:phone":"+90 2125497825329",
    "sg:province":"Istanbul",
    "sg:tags":[
        "industry"
    ],
    "wof:name":"Barlo Plastik A.s.",
    "wof:placetype":"venue"
},
  "geometry": {"coordinates":[28.9759254456,41.0123786926],"type":"Point"}
}