{
  "type": "Feature",
  "properties": {
    "addr:full":"Polad Cad. No:180/a Yesilyurt Izmir 01955",
    "addr:housenumber":"180 / a",
    "addr:postcode":"01955",
    "addr:street":"Polad Cad. No;Yesilyurt Izmir",
    "iso:country":"TR",
    "sg:address":"Polad Cad. No:180/a",
    "sg:city":"Yesilyurt",
    "sg:classifiers":[
        {
            "category":"Shopping",
            "subcategory":"Baby Store",
            "type":"Retail Goods"
        }
    ],
    "sg:phone":"+90 232 232 0138",
    "sg:postcode":"01955",
    "sg:province":"Izmir",
    "sg:tags":[
        "wear"
    ],
    "wof:name":"Kirmizi Minib?s Tekstil",
    "wof:placetype":"venue"
},
  "geometry": {"coordinates":[27.101437,38.394947],"type":"Point"}
}