{
  "type": "Feature",
  "properties": {
    "addr:full":"Mustafa Kemal Amasya 05100 09760",
    "addr:postcode":"05100 09760",
    "iso:country":"TR",
    "sg:address":"Mustafa Kemal",
    "sg:city":"Amasya",
    "sg:classifiers":[
        {
            "category":"Banks & Credit Unions",
            "subcategory":"Bank",
            "type":"Services"
        }
    ],
    "sg:phone":"+90 358 218 3138",
    "sg:postcode":"09760",
    "sg:province":"05100",
    "wof:name":"Etibank Bao",
    "wof:placetype":"venue"
},
  "geometry": {"coordinates":[37.981647,40.976357],"type":"Point"}
}