{
  "type": "Feature",
  "properties": {
    "iso:country":"TR",
    "sg:address":"N.kemal Mah. Oral Sok.no:14 Osmangazi",
    "sg:city":"Hadimk?",
    "sg:classifiers":[
        {
            "category":"Home & Garden",
            "subcategory":"Kitchen Supply",
            "type":"Retail Goods"
        }
    ],
    "sg:phone":"+90 224 255 3976",
    "sg:postcode":"34555",
    "sg:province":"Bursa",
    "sg:tags":[
        "wardrobe"
    ],
    "wof:name":"Derya Mobilya Dekorasyon",
    "wof:placetype":"venue"
},
  "geometry": {"coordinates":[29.075920105,40.1943855286],"type":"Point"}
}