{
  "type": "Feature",
  "properties": {
    "addr:full":"Mis Sok.no: 13 /22 Sisli Istanbul 34360",
    "addr:housenumber":"13 / 22",
    "addr:postcode":"34360",
    "addr:street":"Istanbul",
    "iso:country":"TR",
    "sg:address":"Mis Sok.no: 13 /22",
    "sg:city":"Sisli",
    "sg:classifiers":[
        {
            "category":"Professional",
            "subcategory":"Business Services",
            "type":"Services"
        }
    ],
    "sg:phone":"+90 212 244 7628",
    "sg:postcode":"34360",
    "sg:province":"Istanbul",
    "wof:name":"Ajans Proline",
    "wof:placetype":"venue"
},
  "geometry": {"coordinates":[28.9818496704,41.0355110168],"type":"Point"}
}