{
  "type": "Feature",
  "properties": {
    "iso:country":"TR",
    "sg:address":"2. Cd. No:26 Anittepe",
    "sg:city":"\u00dcmraniye",
    "sg:classifiers":[
        {
            "category":"Home & Garden",
            "subcategory":"Building Materials",
            "type":"Retail Goods"
        }
    ],
    "sg:phone":"+90 312 229 2837",
    "sg:postcode":"34475",
    "sg:province":"Ankara",
    "sg:tags":[
        "window",
        "door",
        "plastic"
    ],
    "wof:name":"Afapen A.s.",
    "wof:placetype":"venue"
},
  "geometry": {"coordinates":[32.8619384766,39.9520149231],"type":"Point"}
}