{
  "type": "Feature",
  "properties": {
    "addr:full":"Tersane Cd. Hirdavat?lar ?ars. No:69 Karak? Karak?y Istanbul -",
    "addr:housenumber":"?;no 69",
    "addr:postcode":"? ars.;?;?",
    "addr:street":"Tersane Cd. Hirdavat",
    "iso:country":"TR",
    "sg:address":"Tersane Cd. Hirdavat?lar ?ars. No:69 Karak?",
    "sg:city":"Karak?y",
    "sg:classifiers":[
        {
            "category":"Wholesale",
            "subcategory":"Machinery & Supplies",
            "type":"Manufacturing & Wholesale Goods"
        }
    ],
    "sg:phone":"+90 212 243 4782",
    "sg:postcode":"-",
    "sg:province":"Istanbul",
    "sg:tags":[
        "bearing",
        "ball"
    ],
    "wof:name":"Rultan Rulman San. Tic. A.s.",
    "wof:placetype":"venue"
},
  "geometry": {"coordinates":[28.975925,41.012379],"type":"Point"}
}