{
  "type": "Feature",
  "properties": {
    "addr:full":"Demirkapi Cd. Ke?ci Ismerk. No:112 Rami 26110 Istanbul",
    "addr:housenumber":"ismerk.",
    "addr:postcode":"26110",
    "addr:street":"Demirkapi;Ke ? Ci;No 112 Rami",
    "iso:country":"TR",
    "sg:address":"Demirkapi Cd. Ke?ci Ismerk. No:112 Rami",
    "sg:city":"26110",
    "sg:classifiers":[
        {
            "category":"Building & Trades",
            "subcategory":"Construction",
            "type":"Services"
        }
    ],
    "sg:phone":"+90 212 567 1752",
    "sg:province":"Istanbul",
    "sg:tags":[
        "industry",
        "mold"
    ],
    "wof:name":"Oguz Kalip Plast Yedek Par?asan. Tic. Ltd. Sti.",
    "wof:placetype":"venue"
},
  "geometry": {"coordinates":[28.9759254456,41.0123786926],"type":"Point"}
}