{
  "type": "Feature",
  "properties": {
    "iso:country":"TR",
    "sg:address":"Beyaz Karanfil Sok. 45, 3.levent",
    "sg:city":"Boyobat",
    "sg:classifiers":[
        {
            "category":"Government",
            "subcategory":"Embassy",
            "type":"Public Place"
        }
    ],
    "sg:phone":"+90 212 281 3306",
    "sg:province":"Istanbul",
    "sg:tags":[
        "foreign"
    ],
    "wof:name":"Bosna Hersek",
    "wof:placetype":"venue"
},
  "geometry": {"coordinates":[29.0139293671,41.0836791992],"type":"Point"}
}