{
  "type": "Feature",
  "properties": {
    "iso:country":"TR",
    "sg:address":"Isto? (istanbul Toptancilar ?arsisi) 30.ada No:32",
    "sg:city":"Mahmutbey",
    "sg:classifiers":[
        {
            "category":"Home & Garden",
            "subcategory":"Kitchen Supply",
            "type":"Retail Goods"
        }
    ],
    "sg:phone":"+90 212 659 7900",
    "sg:postcode":"34217",
    "sg:province":"Istanbul",
    "sg:tags":[
        "wardrobe"
    ],
    "sg:website":"camaks.com",
    "wof:name":"Camaks Cam Ve Seramik Y?zey Leke Tutmaz Kaplama",
    "wof:placetype":"venue"
},
  "geometry": {"coordinates":[28.9759254456,41.0123786926],"type":"Point"}
}