{
  "type": "Feature",
  "properties": {
    "iso:country":"TR",
    "sg:address":"Kaskaval Sok. Celik Ishani No: 8/5 Dolapdere",
    "sg:city":"Kad\u0131k\u00f6y",
    "sg:classifiers":[
        {
            "category":"Shopping",
            "subcategory":"Gifts & Souvenirs",
            "type":"Retail Goods"
        }
    ],
    "sg:phone":"+90 212 361 1974",
    "sg:postcode":"34990",
    "sg:province":"Istanbul",
    "wof:name":"Ozgule Hediyelik",
    "wof:placetype":"venue"
},
  "geometry": {"coordinates":[28.9759254456,41.0123786926],"type":"Point"}
}