{
  "type": "Feature",
  "properties": {
    "addr:full":"Kore Sehitleri Cad. No.34/7-2 Zincirlikuyu Ikitelli Istanbul 34306",
    "addr:housenumber":"no.34 / 7-2",
    "addr:postcode":"34306",
    "addr:street":"Sehitleri Cad.;Zincirlikuyu Ikitelli",
    "iso:country":"TR",
    "sg:address":"Kore Sehitleri Cad. No.34/7-2 Zincirlikuyu",
    "sg:city":"Ikitelli",
    "sg:classifiers":[
        {
            "category":"Professional",
            "type":"Services"
        }
    ],
    "sg:phone":"+90 212273083031",
    "sg:postcode":"34306",
    "sg:province":"Istanbul",
    "sg:tags":[
        "industrial",
        "automation"
    ],
    "wof:name":"Weidmuller Elektronik San. Tic.ltd.sti.",
    "wof:placetype":"venue"
},
  "geometry": {"coordinates":[28.9861831665,41.0408554077],"type":"Point"}
}