{
  "type": "Feature",
  "properties": {
    "iso:country":"TR",
    "sg:address":"Mesihpasa Cad. 13,",
    "sg:city":"Laleli",
    "sg:orig_category":"Hotels: Motels",
    "sg:phone":"+90 212 518 5656",
    "sg:postcode":"34480",
    "sg:province":"Istanbul",
    "wof:name":"Em?n Hotel",
    "wof:placetype":"venue"
},
  "geometry": {"coordinates":[28.9542636871,41.0082130432],"type":"Point"}
}