{
  "type": "Feature",
  "properties": {
    "iso:country":"TR",
    "sg:address":"Bankalar Cad.e.tarikahya Is Merkz.no:3/1",
    "sg:city":"Mecidiyek\u00f6y",
    "sg:classifiers":[
        {
            "category":"Professional",
            "subcategory":"Computer Services",
            "type":"Services"
        }
    ],
    "sg:phone":"+90 346 224 6299",
    "sg:postcode":"80300",
    "sg:province":"Sivas",
    "sg:tags":[
        "application",
        "software"
    ],
    "wof:name":"Objektif Bilgisayar Ltd.sti",
    "wof:placetype":"venue"
},
  "geometry": {"coordinates":[37.0182571411,39.750087738],"type":"Point"}
}