{
  "type": "Feature",
  "properties": {
    "iso:country":"TR",
    "sg:address":"Aosb/ Yakapinar",
    "sg:city":"Bal?va",
    "sg:orig_category":"Enegy Contractors",
    "sg:phone":"+90 322 394 4030",
    "sg:province":"Adana",
    "wof:name":"Galvaniz Panel",
    "wof:placetype":"venue"
},
  "geometry": {"coordinates":[35.6428794861,36.9550094604],"type":"Point"}
}