{
  "type": "Feature",
  "properties": {
    "iso:country":"TR",
    "sg:address":"Cetin Emec Bulvari 77.sok. No:16/3a Ovecler",
    "sg:city":"Kutlukent",
    "sg:classifiers":[
        {
            "category":"Utilities",
            "subcategory":"Recycling",
            "type":"Services"
        }
    ],
    "sg:phone":"+90 312 479 9945",
    "sg:postcode":"55330",
    "sg:province":"Ankara",
    "sg:tags":[
        "measuring",
        "weighing"
    ],
    "wof:name":"Eylul Ltd.sti.",
    "wof:placetype":"venue"
},
  "geometry": {"coordinates":[32.8604812622,39.9429283142],"type":"Point"}
}