{
  "type": "Feature",
  "properties": {
    "iso:country":"TR",
    "sg:address":"Bornova Cad. No: 14/16",
    "sg:city":"Isikkent",
    "sg:classifiers":[
        {
            "category":"Wholesale",
            "subcategory":"Machinery & Supplies",
            "type":"Manufacturing & Wholesale Goods"
        }
    ],
    "sg:phone":"+90 2324720772729",
    "sg:postcode":"32100",
    "sg:province":"Izmir",
    "sg:tags":[
        "agricultural"
    ],
    "wof:name":"Palaplast Sulama Sistemleri A.s.",
    "wof:placetype":"venue"
},
  "geometry": {"coordinates":[27.1756687164,38.4614982605],"type":"Point"}
}