{
  "type": "Feature",
  "properties": {
    "addr:full":"Org.san.b?l.bagcilar-g?ng?ren San.sit ?arsi Grubu No:176 Ikitelli Istanbul 34306",
    "addr:postcode":"34306",
    "addr:street":"No;Ikitelli",
    "iso:country":"TR",
    "sg:address":"Org.san.b?l.bagcilar-g?ng?ren San.sit ?arsi Grubu No:176",
    "sg:city":"Ikitelli",
    "sg:orig_category":"Ikitelli Bagcilar-gungoren Ind.site",
    "sg:phone":"+90 5490692",
    "sg:postcode":"34306",
    "sg:province":"Istanbul",
    "wof:name":"Star Erkek Kuaf?r?",
    "wof:placetype":"venue"
},
  "geometry": {"coordinates":[28.9861831665,41.0408554077],"type":"Point"}
}