{
  "type": "Feature",
  "properties": {
    "iso:country":"TR",
    "sg:address":"Baglar Mh. S. Uzun Hasan Sk. No: 6",
    "sg:city":"G?esli",
    "sg:classifiers":[
        {
            "category":"Sports & Exercise",
            "subcategory":"Ski Slope",
            "type":"Entertainment"
        }
    ],
    "sg:phone":"+90 212 630 1355",
    "sg:province":"Istanbul",
    "sg:tags":[
        "wear"
    ],
    "wof:name":"Aycem Ithalat-ihracat Ve Pazarlama Ltd. Sti.",
    "wof:placetype":"venue"
},
  "geometry": {"coordinates":[28.827217,41.021152],"type":"Point"}
}