{
  "type": "Feature",
  "properties": {
    "addr:full":"Hadimkoy Yolu 1.bol. 4.cd. No: 23 Buyukcekmece Cayirova Istanbul 58900",
    "addr:housenumber":"1.bol 4.cd no 23",
    "addr:postcode":"58900",
    "addr:street":"Hadimkoy Yolu",
    "iso:country":"TR",
    "sg:address":"Hadimkoy Yolu 1.bol. 4.cd. No: 23 Buyukcekmece",
    "sg:city":"Cayirova",
    "sg:classifiers":[
        {
            "category":"Building & Trades",
            "subcategory":"Plumbing",
            "type":"Services"
        }
    ],
    "sg:phone":"+90 212 886 5741",
    "sg:postcode":"58900",
    "sg:province":"Istanbul",
    "sg:tags":[
        "pipe",
        "industry"
    ],
    "wof:name":"Dizayn Plas. Boru San. A.s.",
    "wof:placetype":"venue"
},
  "geometry": {"coordinates":[28.9759254456,41.0123786926],"type":"Point"}
}