{
  "type": "Feature",
  "properties": {
    "addr:full":"Petrol Cd. S?b? Sk. K?fez Iskenderun Kocaeli 31200",
    "addr:housenumber":"?",
    "addr:postcode":"31200",
    "addr:street":"S;B ? Sk. K",
    "iso:country":"TR",
    "sg:address":"Petrol Cd. S?b? Sk. K?fez",
    "sg:city":"Iskenderun",
    "sg:classifiers":[
        {
            "category":"Wholesale",
            "subcategory":"Petroleum",
            "type":"Manufacturing & Wholesale Goods"
        }
    ],
    "sg:phone":"+90 262 527 5093",
    "sg:postcode":"31200",
    "sg:province":"Kocaeli",
    "wof:name":"Ergaz Likitgaz San. Tic. A.s.",
    "wof:placetype":"venue"
},
  "geometry": {"coordinates":[29.881521225,40.8532714844],"type":"Point"}
}