{
  "type": "Feature",
  "properties": {
    "addr:full":"B??dere Cd. No:54/4 Mecidiyek? Mersin Istanbul 52750",
    "addr:housenumber":"? ?;no 54 / 4 mecidiyek ?",
    "addr:postcode":"52750",
    "addr:street":"B;Dere Cd.",
    "iso:country":"TR",
    "sg:address":"B??dere Cd. No:54/4 Mecidiyek?",
    "sg:city":"Mersin",
    "sg:classifiers":[
        {
            "category":"Professional",
            "subcategory":"Art Services",
            "type":"Services"
        }
    ],
    "sg:phone":"+90 212 274 6894",
    "sg:postcode":"52750",
    "sg:province":"Istanbul",
    "sg:tags":[
        "marketing"
    ],
    "wof:name":"Biltam M?messil. Dis Tic. San. A.s.",
    "wof:placetype":"venue"
},
  "geometry": {"coordinates":[28.9861831665,41.0408554077],"type":"Point"}
}