{
  "type": "Feature",
  "properties": {
    "addr:full":"Demirciler Sitesi 6.cad. No:83 D:91 Zeytinburnu Ikitelli/K\u00fc\u00e7\u00fck\u00e7ekmece Istanbul 34670",
    "addr:housenumber":"no 83 d 91",
    "addr:postcode":"34670",
    "addr:street":"Demirciler",
    "iso:country":"TR",
    "sg:address":"Demirciler Sitesi 6.cad. No:83 D:91 Zeytinburnu",
    "sg:city":"Ikitelli/K\u00fc\u00e7\u00fck\u00e7ekmece",
    "sg:classifiers":[
        {
            "category":"Manufacturing",
            "subcategory":"Metals",
            "type":"Manufacturing & Wholesale Goods"
        }
    ],
    "sg:phone":"+90 212679852930",
    "sg:postcode":"34670",
    "sg:province":"Istanbul",
    "sg:tags":[
        "iron-steel",
        "peoducts"
    ],
    "wof:name":"?alisir Metal Ve Mak. San. Ve Tic. Ltd.sti.",
    "wof:placetype":"venue"
},
  "geometry": {"coordinates":[28.9759254456,41.0123786926],"type":"Point"}
}