{
  "type": "Feature",
  "properties": {
    "iso:country":"TR",
    "sg:address":"Inonu Mh.917 Sk.gur Sitesi Bblok No:28",
    "sg:city":"07100",
    "sg:classifiers":[
        {
            "category":"Food & Beverages",
            "subcategory":"Fruits & Vegetables",
            "type":"Retail Goods"
        }
    ],
    "sg:phone":"+90 324 336 1018",
    "sg:province":"I?el",
    "sg:tags":[
        "fresh"
    ],
    "wof:name":"Aydas Tic.ltd.sti.",
    "wof:placetype":"venue"
},
  "geometry": {"coordinates":[37.270401001,38.7229003906],"type":"Point"}
}