{
  "type": "Feature",
  "properties": {
    "addr:full":"Ayazma Yolu Turin Is Merkezi No. 21 / 22 Kagithane Mersin Istanbul 52750",
    "addr:housenumber":"no. 21 / 22",
    "addr:postcode":"52750",
    "addr:street":"Ayazma Yolu;Kagithane",
    "iso:country":"TR",
    "sg:address":"Ayazma Yolu Turin Is Merkezi No. 21 / 22 Kagithane",
    "sg:city":"Mersin",
    "sg:classifiers":[
        {
            "category":"Personal",
            "subcategory":"Sauna",
            "type":"Services"
        }
    ],
    "sg:phone":"+90 212 294 5867",
    "sg:postcode":"52750",
    "sg:province":"Istanbul",
    "sg:tags":[
        "pool"
    ],
    "wof:name":"Libra End. ?r?nler San. Tic. A.s.",
    "wof:placetype":"venue"
},
  "geometry": {"coordinates":[28.975925,41.012379],"type":"Point"}
}