{
  "type": "Feature",
  "properties": {
    "iso:country":"TR",
    "sg:address":"Karpuzlu Sk. No:8/1 Siteler",
    "sg:city":"Altindag",
    "sg:classifiers":[
        {
            "category":"Home & Garden",
            "subcategory":"Kitchen Supply",
            "type":"Retail Goods"
        }
    ],
    "sg:phone":"+90 312 348 7810",
    "sg:postcode":"06230",
    "sg:province":"Ankara",
    "sg:tags":[
        "steel",
        "utensil"
    ],
    "wof:name":"Karinca Day. T?k. Mad. Tic. San. Ltd. Sti.",
    "wof:placetype":"venue"
},
  "geometry": {"coordinates":[29.100874,40.182892],"type":"Point"}
}