{
  "type": "Feature",
  "properties": {
    "addr:full":"Muammerbey Mh. Bah?cioglu Ishani K:3 No:305 Sehiri? Mersin Kayseri 52750",
    "addr:housenumber":"?;3 no 305;?",
    "addr:postcode":"52750",
    "addr:street":"Muammerbey Mh. Bah;Sehiri",
    "iso:country":"TR",
    "sg:address":"Muammerbey Mh. Bah?cioglu Ishani K:3 No:305 Sehiri?",
    "sg:city":"Mersin",
    "sg:classifiers":[
        {
            "category":"Freight",
            "type":"Transportation"
        }
    ],
    "sg:phone":"+90 352 231 7252",
    "sg:postcode":"52750",
    "sg:province":"Kayseri",
    "sg:tags":[
        "packing",
        "industry"
    ],
    "wof:name":"Plaska Ambalaj San. Tic. A.s.",
    "wof:placetype":"venue"
},
  "geometry": {"coordinates":[35.4891357422,38.7225761414],"type":"Point"}
}