{
  "type": "Feature",
  "properties": {
    "addr:full":"Yeni Hal Yolu Akturkler No:7/33 Suhut I?el 03800",
    "addr:housenumber":"akturkler;33;?",
    "addr:postcode":"03800",
    "addr:street":"Hal Yolu;No 7 /;I;El",
    "iso:country":"TR",
    "sg:address":"Yeni Hal Yolu Akturkler No:7/33",
    "sg:city":"Suhut",
    "sg:classifiers":[
        {
            "category":"Food & Beverages",
            "subcategory":"Fruits & Vegetables",
            "type":"Retail Goods"
        }
    ],
    "sg:phone":"+90 32423231231",
    "sg:postcode":"03800",
    "sg:province":"I?el",
    "sg:tags":[
        "fresh"
    ],
    "wof:name":"Kom-impeks Ith.ihr.tic.ltd.",
    "wof:placetype":"venue"
},
  "geometry": {"coordinates":[30.606300354,38.4294509888],"type":"Point"}
}