{
  "type": "Feature",
  "properties": {
    "iso:country":"TR",
    "sg:address":"Nuri Ziya Sok. 43/2",
    "sg:city":"Sisli",
    "sg:classifiers":[
        {
            "category":"Manufacturing",
            "subcategory":"Textiles",
            "type":"Manufacturing & Wholesale Goods"
        }
    ],
    "sg:phone":"+90 212 233 1112",
    "sg:postcode":"65710",
    "sg:province":"Istanbul",
    "sg:tags":[
        "product"
    ],
    "wof:name":"Berke Dis Ticaret Ltd.",
    "wof:placetype":"venue"
},
  "geometry": {"coordinates":[29.067691803,40.9773445129],"type":"Point"}
}