{
  "type": "Feature",
  "properties": {
    "addr:full":"Busan Org.sanayi 6.sok. No.5-7 Ikitelli/K\u00fc\u00e7\u00fck\u00e7ekmece Konya 34670",
    "addr:housenumber":"no.5-7 ikitelli",
    "addr:postcode":"34670",
    "addr:street":"6.Sok",
    "iso:country":"TR",
    "sg:address":"Busan Org.sanayi 6.sok. No.5-7",
    "sg:city":"Ikitelli/K\u00fc\u00e7\u00fck\u00e7ekmece",
    "sg:classifiers":[
        {
            "category":"Home & Garden",
            "subcategory":"Kitchen Supply",
            "type":"Retail Goods"
        }
    ],
    "sg:phone":"+90 332 322 2287",
    "sg:postcode":"34670",
    "sg:province":"Konya",
    "sg:tags":[
        "wardrobe"
    ],
    "wof:name":"Ersoz & Conta Mutfak Makina Ve Ekipmanlari Sanayi Tic.a.s.",
    "wof:placetype":"venue"
},
  "geometry": {"coordinates":[32.4990272522,37.8715362549],"type":"Point"}
}