{
  "type": "Feature",
  "properties": {
    "iso:country":"TR",
    "sg:address":"Umut Sok 12, 81120 Istanbul",
    "sg:city":"Istanbul",
    "sg:classifiers":[
        {
            "category":"Banks & Credit Unions",
            "subcategory":"Bank",
            "type":"Services"
        }
    ],
    "sg:province":"Istanbul",
    "wof:name":"?zilhan Sinai Yatirim As",
    "wof:placetype":"venue"
},
  "geometry": {"coordinates":[28.836718,41.054543],"type":"Point"}
}