{
  "type": "Feature",
  "properties": {
    "iso:country":"TR",
    "sg:address":"4086.sok. No:33 K:3 Karabaglar",
    "sg:city":"Beyazit",
    "sg:classifiers":[
        {
            "category":"Shopping",
            "subcategory":"Clothing, Apparel, & Fashions",
            "type":"Retail Goods"
        }
    ],
    "sg:phone":"+90 232 237 5055",
    "sg:postcode":"34130",
    "sg:province":"Izmir",
    "sg:tags":[
        "bag-belt-accessories"
    ],
    "wof:name":"Cinar Dis Tic.ltd.sti.",
    "wof:placetype":"venue"
},
  "geometry": {"coordinates":[27.123526,38.375877],"type":"Point"}
}