{
  "type": "Feature",
  "properties": {
    "addr:full":"?r??er, Seker Ahmet Pasa Sk. ?arsili Han No:123-124 Beyazit Istanbul 65400",
    "addr:postcode":"123-124;65400",
    "addr:street":"Ahmet Pasa Sk. ? Arsili Han No",
    "iso:country":"TR",
    "sg:address":"?r??er, Seker Ahmet Pasa Sk. ?arsili Han No:123-124",
    "sg:city":"Beyazit",
    "sg:classifiers":[
        {
            "category":"Shopping",
            "subcategory":"Clothing, Apparel, & Fashions",
            "type":"Retail Goods"
        }
    ],
    "sg:phone":"+90 212511648152",
    "sg:postcode":"65400",
    "sg:province":"Istanbul",
    "sg:tags":[
        "woman",
        "wear"
    ],
    "wof:name":"Fidan Teks. San. Tic. Ltd. Sti.",
    "wof:placetype":"venue"
},
  "geometry": {"coordinates":[28.9759254456,41.0123786926],"type":"Point"}
}