{
  "type": "Feature",
  "properties": {
    "addr:full":"Neyzen Tevfik Sk. No:25 Demirtepe Melikgazi Ankara 38000",
    "addr:housenumber":"25",
    "addr:postcode":"38000",
    "addr:street":"Neyzen Tevfik Sk. No;Melikgazi",
    "iso:country":"TR",
    "sg:address":"Neyzen Tevfik Sk. No:25 Demirtepe",
    "sg:city":"Melikgazi",
    "sg:classifiers":[
        {
            "category":"Banks & Credit Unions",
            "subcategory":"Investment Brokerage",
            "type":"Services"
        }
    ],
    "sg:phone":"+90 312 230 8166",
    "sg:postcode":"38000",
    "sg:province":"Ankara",
    "sg:tags":[
        "-",
        "export",
        "import"
    ],
    "wof:name":"Ful Medikal M?h. Cihaz. Tic. Ith. Ihr. M?messil. Ltd. Sti.",
    "wof:placetype":"venue"
},
  "geometry": {"coordinates":[32.8604812622,39.9429283142],"type":"Point"}
}