{
  "type": "Feature",
  "properties": {
    "addr:full":"Selahattin Pinar Cad.inan Apt.no:3/17 Mecidiyek? \u00c7ankaya Istanbul 06450",
    "addr:housenumber":"3 / 17;?",
    "addr:postcode":"06450",
    "addr:street":"Selahattin;Apt.No;Mecidiyek",
    "iso:country":"TR",
    "sg:address":"Selahattin Pinar Cad.inan Apt.no:3/17 Mecidiyek?",
    "sg:city":"\u00c7ankaya",
    "sg:classifiers":[
        {
            "category":"Professional",
            "subcategory":"Computer Services",
            "type":"Services"
        }
    ],
    "sg:phone":"+90 212 216 0510",
    "sg:postcode":"06450",
    "sg:province":"Istanbul",
    "sg:tags":[
        "application",
        "software"
    ],
    "wof:name":"Sahin Bilgisayar Kurslari",
    "wof:placetype":"venue"
},
  "geometry": {"coordinates":[28.9861831665,41.0408554077],"type":"Point"}
}