{
  "type": "Feature",
  "properties": {
    "addr:full":"Basin Sok. No:18 Kesan Balikesir 22800",
    "addr:housenumber":"no 18",
    "addr:postcode":"22800",
    "addr:street":"Basin Sok.;Balikesir",
    "iso:country":"TR",
    "sg:address":"Basin Sok. No:18",
    "sg:city":"Kesan",
    "sg:classifiers":[
        {
            "category":"Shopping",
            "subcategory":"Bicycles & Sporting Goods",
            "type":"Retail Goods"
        }
    ],
    "sg:phone":"+90 2456300",
    "sg:postcode":"22800",
    "sg:province":"Balikesir",
    "sg:tags":[
        "equipment",
        "marine",
        "hunting"
    ],
    "wof:name":"Rasgele Av Ticaret",
    "wof:placetype":"venue"
},
  "geometry": {"coordinates":[27.8853626251,39.6448822021],"type":"Point"}
}