{
  "type": "Feature",
  "properties": {
    "iso:country":"TR",
    "sg:address":"Hobyar Mh. Asirefendi Cd. Piyasa Han No:11/13 Sultanhamam",
    "sg:city":"Sisli",
    "sg:classifiers":[
        {
            "category":"Home & Garden",
            "subcategory":"Home Furnishings",
            "type":"Retail Goods"
        }
    ],
    "sg:phone":"+90 212 512 4620",
    "sg:postcode":"65710",
    "sg:province":"Istanbul",
    "sg:tags":[
        "curtaining",
        "-",
        "upholstering"
    ],
    "wof:name":"T?lmen T?l Mensucat San. Tic. A.s.",
    "wof:placetype":"venue"
},
  "geometry": {"coordinates":[28.975925,41.012379],"type":"Point"}
}