{
  "type": "Feature",
  "properties": {
    "addr:full":"Maden Arama Ve Isletme Arifiye Mh. Inhisar Sk. No:1 K:2/31 Iskenderun Eskisehir 31200",
    "addr:housenumber":"2 / 31",
    "addr:postcode":"31200",
    "addr:street":"Maden;Ve Isletme;Mh. Inhisar Sk. No 1 K;Eskisehir",
    "iso:country":"TR",
    "sg:address":"Maden Arama Ve Isletme Arifiye Mh. Inhisar Sk. No:1 K:2/31",
    "sg:city":"Iskenderun",
    "sg:classifiers":[
        {
            "category":"Mining & Drilling",
            "type":"Manufacturing & Wholesale Goods"
        }
    ],
    "sg:phone":"+90 222",
    "sg:postcode":"31200",
    "sg:province":"Eskisehir",
    "sg:tags":[
        "industry",
        "mine"
    ],
    "wof:name":"Eskisehir Granit San. Tic. A.s.",
    "wof:placetype":"venue"
},
  "geometry": {"coordinates":[30.5175457001,39.7700805664],"type":"Point"}
}