{
  "type": "Feature",
  "properties": {
    "iso:country":"TR",
    "sg:address":"Demirtas Org. San. B?g.",
    "sg:city":"Mecidiyek\u00f6y",
    "sg:classifiers":[
        {
            "category":"Shopping",
            "subcategory":"Crafts & Fabrics",
            "type":"Retail Goods"
        }
    ],
    "sg:phone":"+90 224 261 0000",
    "sg:province":"Bursa",
    "sg:tags":[
        "nylon",
        "yarn"
    ],
    "wof:name":"Sateks Iplik Teks. San. Tic. Ltd. Sti.",
    "wof:placetype":"venue"
},
  "geometry": {"coordinates":[29.0398807526,40.1076583862],"type":"Point"}
}