{
  "type": "Feature",
  "properties": {
    "addr:full":"H??et Konagi Zemin Kat No:3 Erdek Sivas 19000",
    "addr:housenumber":"kat no 3",
    "addr:postcode":"19000",
    "addr:street":"Erdek Sivas",
    "iso:country":"TR",
    "sg:address":"H??et Konagi Zemin Kat No:3",
    "sg:city":"Erdek",
    "sg:classifiers":[
        {
            "category":"Landmark",
            "subcategory":"Tourist Information",
            "type":"Public Place"
        }
    ],
    "sg:phone":"+90 346 221 3135",
    "sg:postcode":"19000",
    "sg:province":"Sivas",
    "sg:tags":[
        "tourism"
    ],
    "wof:name":"Turizm Danisma Burosu",
    "wof:placetype":"venue"
},
  "geometry": {"coordinates":[37.0182571411,39.750087738],"type":"Point"}
}