{
  "type": "Feature",
  "properties": {
    "addr:full":"Tahtakale Cd. C?ert Sk. Pirhan No:206 Emin?? Istanbul Emin\u00f6n\u00fc/Ca\u011falo\u011flu Istanbul",
    "addr:housenumber":"?;206;? ?",
    "addr:street":"Tahtakale Cd. C;Ert Sk. Pirhan No",
    "iso:country":"TR",
    "sg:address":"Tahtakale Cd. C?ert Sk. Pirhan No:206 Emin?? Istanbul",
    "sg:city":"Emin\u00f6n\u00fc/Ca\u011falo\u011flu",
    "sg:classifiers":[
        {
            "category":"Shopping",
            "subcategory":"Stationery & Office Supplies",
            "type":"Retail Goods"
        }
    ],
    "sg:phone":"+90 212 513 1113",
    "sg:province":"Istanbul",
    "wof:name":"T?rkmen Kirtasiye Tic. San. Ltd. Sti.",
    "wof:placetype":"venue"
},
  "geometry": {"coordinates":[28.975925,41.012379],"type":"Point"}
}