{
  "type": "Feature",
  "properties": {
    "addr:full":"Kizilay Cd. Caneri Apt. K:3 Mecidiyek\u00f6y Balikesir",
    "addr:housenumber":"3",
    "addr:street":"Kizilay Cd. Caneri Apt. K;Balikesir",
    "iso:country":"TR",
    "sg:address":"Kizilay Cd. Caneri Apt. K:3",
    "sg:city":"Mecidiyek\u00f6y",
    "sg:classifiers":[
        {
            "category":"Manufacturing",
            "subcategory":"Wood Products",
            "type":"Manufacturing & Wholesale Goods"
        }
    ],
    "sg:phone":"+90 266249340203",
    "sg:province":"Balikesir",
    "sg:tags":[
        "forest"
    ],
    "wof:name":"Dagtas Orman Urunleri Tic. Ltd. Sti.",
    "wof:placetype":"venue"
},
  "geometry": {"coordinates":[27.8833007812,39.6520996094],"type":"Point"}
}