{
  "type": "Feature",
  "properties": {
    "addr:full":"Kurtulus Mah. 304 Sok. Kismet Apt. Kahramanlar Adana 25700",
    "addr:housenumber":"kismet",
    "addr:postcode":"25700",
    "addr:street":"Mah. 304 Sok.;Kahramanlar",
    "iso:country":"TR",
    "sg:address":"Kurtulus Mah. 304 Sok. Kismet Apt.",
    "sg:city":"Kahramanlar",
    "sg:classifiers":[
        {
            "category":"Home & Garden",
            "subcategory":"Household Appliances",
            "type":"Retail Goods"
        }
    ],
    "sg:phone":"+90 322 453 0948",
    "sg:postcode":"25700",
    "sg:province":"Adana",
    "sg:tags":[
        "conditioner",
        "air"
    ],
    "wof:name":"Ozsayin Sanayi Ve Ticaret Taahut Ithalat Ve Ihracat Ltd.sti.",
    "wof:placetype":"venue"
},
  "geometry": {"coordinates":[35.3137359619,37.0007171631],"type":"Point"}
}