{
  "type": "Feature",
  "properties": {
    "iso:country":"TR",
    "sg:address":"Tahtakale Cad. No:20-22 Preuvayans Han Kat:3 No:333 34460 Eminonu",
    "sg:city":"Kadikoy",
    "sg:classifiers":[
        {
            "category":"Wholesale",
            "subcategory":"Plants",
            "type":"Manufacturing & Wholesale Goods"
        }
    ],
    "sg:phone":"+90 212 511 2996",
    "sg:postcode":"01370",
    "sg:province":"Istanbul",
    "sg:tags":[
        "natural",
        "spice"
    ],
    "wof:name":"Izmir Kimevi Mad.ith.ihr.san.tic. A.s.",
    "wof:placetype":"venue"
},
  "geometry": {"coordinates":[28.975925,41.012379],"type":"Point"}
}