{
  "type": "Feature",
  "properties": {
    "iso:country":"TR",
    "sg:address":"504 Sk. No:30",
    "sg:city":"Pinarbasi",
    "sg:orig_category":"Muhtarliklar",
    "sg:phone":"+90 232 388 5751",
    "sg:postcode":"07630",
    "sg:province":"Izmir",
    "wof:name":"Yunus Emre Mahallesi Muhtar: Selahattin ?zdemir",
    "wof:placetype":"venue"
},
  "geometry": {"coordinates":[27.1867866516,38.431350708],"type":"Point"}
}