{
  "type": "Feature",
  "properties": {
    "addr:full":"Akbasoglu Is Merkz. 119 Nuhkuyusu Cad. Uskudar Istanbul 34672",
    "addr:housenumber":"119",
    "addr:postcode":"34672",
    "addr:street":"Nuhkuyusu Cad.",
    "iso:country":"TR",
    "sg:address":"Akbasoglu Is Merkz. 119 Nuhkuyusu Cad.",
    "sg:city":"Uskudar",
    "sg:classifiers":[
        {
            "category":"Marine",
            "type":"Transportation"
        }
    ],
    "sg:phone":"+90 216 492 7200",
    "sg:postcode":"34672",
    "sg:province":"Istanbul",
    "sg:tags":[
        "shipowner"
    ],
    "wof:name":"Trans Ka Tanker Isletmeciligi Tic.ltd.sti.",
    "wof:placetype":"venue"
},
  "geometry": {"coordinates":[29.015442,41.021832],"type":"Point"}
}