{
  "type": "Feature",
  "properties": {
    "iso:country":"TR",
    "sg:address":"G?bet Hotel Flora D?kanlari No:1",
    "sg:city":"Bodrum",
    "sg:classifiers":[
        {
            "category":"Recreation",
            "subcategory":"Boat Charter",
            "type":"Entertainment"
        }
    ],
    "sg:phone":"+90 252 316 0172",
    "sg:postcode":"48400",
    "sg:province":"Mugla",
    "sg:tags":[
        "yachting"
    ],
    "wof:name":"Fantazi Tourism",
    "wof:placetype":"venue"
},
  "geometry": {"coordinates":[28.3658008575,37.2196006775],"type":"Point"}
}