{
  "type": "Feature",
  "properties": {
    "iso:country":"TR",
    "sg:address":"Savas Cd. No:4/6 Merter",
    "sg:city":"Kizilay",
    "sg:classifiers":[
        {
            "category":"Shopping",
            "subcategory":"Stationery & Office Supplies",
            "type":"Retail Goods"
        }
    ],
    "sg:phone":"+90 212 637 4415",
    "sg:postcode":"06650",
    "sg:province":"Istanbul",
    "wof:name":"Opel Kirtasiye",
    "wof:placetype":"venue"
},
  "geometry": {"coordinates":[28.894339,40.984306],"type":"Point"}
}