{
  "type": "Feature",
  "properties": {
    "addr:full":"Dogu San. Sit. 10 Blok No:6 Yenibosna Bagcilar Istanbul 33115",
    "addr:housenumber":"10 blok no 6",
    "addr:postcode":"33115",
    "iso:country":"TR",
    "sg:address":"Dogu San. Sit. 10 Blok No:6 Yenibosna",
    "sg:city":"Bagcilar",
    "sg:classifiers":[
        {
            "category":"Wholesale",
            "subcategory":"Home Furnishings",
            "type":"Manufacturing & Wholesale Goods"
        }
    ],
    "sg:phone":"+90 212 552 3664",
    "sg:postcode":"33115",
    "sg:province":"Istanbul",
    "sg:tags":[
        "furniture"
    ],
    "wof:name":"Pamuk?uoglu Ltd. Sti.",
    "wof:placetype":"venue"
},
  "geometry": {"coordinates":[29.2125148773,40.9275741577],"type":"Point"}
}