{
  "type": "Feature",
  "properties": {
    "addr:full":"Ziya G?alp Mh. 44 / 2 No:15 / A Zeytinburnu Kad\u0131k\u00f6y Istanbul 81010",
    "addr:housenumber":"?;44 / 2 no 15 / a",
    "addr:postcode":"81010",
    "addr:street":"Ziya G;Mh.;Zeytinburnu Kadikoey",
    "iso:country":"TR",
    "sg:address":"Ziya G?alp Mh. 44 / 2 No:15 / A Zeytinburnu",
    "sg:city":"Kad\u0131k\u00f6y",
    "sg:orig_category":"Aluminium Carpentary",
    "sg:phone":"+90 212 546 4789",
    "sg:postcode":"81010",
    "sg:province":"Istanbul",
    "wof:name":"Onur Aliminyum Dog.pvc A.s.",
    "wof:placetype":"venue"
},
  "geometry": {"coordinates":[28.9759254456,41.0123786926],"type":"Point"}
}