{
  "type": "Feature",
  "properties": {
    "addr:full":"Halasgargazi Cad.no:274/38-39 Osmanbey Istanbul 63000",
    "addr:housenumber":"274 / 38-39",
    "addr:postcode":"63000",
    "iso:country":"TR",
    "sg:address":"Halasgargazi Cad.no:274/38-39",
    "sg:city":"Osmanbey",
    "sg:classifiers":[
        {
            "category":"Shopping",
            "subcategory":"Clothing, Apparel, & Fashions",
            "type":"Retail Goods"
        }
    ],
    "sg:phone":"+90 212 247 6128",
    "sg:postcode":"63000",
    "sg:province":"Istanbul",
    "sg:tags":[
        "woman",
        "wear"
    ],
    "wof:name":"Dilli Tekstil San.tic.ltd.sti.",
    "wof:placetype":"venue"
},
  "geometry": {"coordinates":[28.9876327515,41.0505371094],"type":"Point"}
}