{
  "type": "Feature",
  "properties": {
    "addr:full":"Ambaryolu ?ikisi Alsancak Denizli 01365",
    "addr:postcode":"01365",
    "iso:country":"TR",
    "sg:address":"Ambaryolu ?ikisi",
    "sg:city":"Alsancak",
    "sg:orig_category":"Hotels: Motels",
    "sg:phone":"+90 2582152851215",
    "sg:postcode":"01365",
    "sg:province":"Denizli",
    "wof:name":"Karaca Otel",
    "wof:placetype":"venue"
},
  "geometry": {"coordinates":[29.0788803101,37.7851867676],"type":"Point"}
}