{
  "type": "Feature",
  "properties": {
    "addr:full":"Bursa Cd. No:106 Iskenderun Eskisehir 31200",
    "addr:postcode":"31200",
    "iso:country":"TR",
    "sg:address":"Bursa Cd. No:106",
    "sg:city":"Iskenderun",
    "sg:classifiers":[
        {
            "category":"Mining & Drilling",
            "type":"Manufacturing & Wholesale Goods"
        }
    ],
    "sg:phone":"+90 222 231 1248",
    "sg:postcode":"31200",
    "sg:province":"Eskisehir",
    "sg:tags":[
        "industry",
        "mine"
    ],
    "wof:name":"?iftkurt End?stri Tic. Ltd. Sti.",
    "wof:placetype":"venue"
},
  "geometry": {"coordinates":[30.4788150787,39.7928657532],"type":"Point"}
}