{
  "type": "Feature",
  "properties": {
    "addr:full":"Ikitelli Organize Sanayi B?gesi G?g?en Bagcilar Sanayi Sitesi 10.blok No:8-10-12-14 Ikitelli/K\u00fc\u00e7\u00fck\u00e7ekmece Istanbul 34670",
    "addr:housenumber":"?;? g ?;10.blok no",
    "addr:postcode":"34670",
    "addr:street":"Organize Sanayi B;G;En Bagcilar Sanayi Sitesi",
    "iso:country":"TR",
    "sg:address":"Ikitelli Organize Sanayi B?gesi G?g?en Bagcilar Sanayi Sitesi 10.blok No:8-10-12-14",
    "sg:city":"Ikitelli/K\u00fc\u00e7\u00fck\u00e7ekmece",
    "sg:classifiers":[
        {
            "category":"Building & Trades",
            "subcategory":"Construction",
            "type":"Services"
        }
    ],
    "sg:phone":"+90 212549035152",
    "sg:postcode":"34670",
    "sg:province":"Istanbul",
    "sg:tags":[
        "industry",
        "mold"
    ],
    "wof:name":"?zg?rko? Kalip Imalat San.ve Tic.ltd.sti",
    "wof:placetype":"venue"
},
  "geometry": {"coordinates":[28.9759254456,41.0123786926],"type":"Point"}
}