{
  "type": "Feature",
  "properties": {
    "iso:country":"TR",
    "sg:address":"Izmir Cd. No.141",
    "sg:city":"Pinarbasi",
    "sg:classifiers":[
        {
            "category":"Farming",
            "subcategory":"Farm",
            "type":"Manufacturing & Wholesale Goods"
        }
    ],
    "sg:phone":"+90 232 388 1022",
    "sg:postcode":"07630",
    "sg:province":"Izmir",
    "sg:tags":[
        "agricultural",
        "product"
    ],
    "wof:name":"Gurel Tarim Urn. Ihr. A.s.",
    "wof:placetype":"venue"
},
  "geometry": {"coordinates":[26.3458862305,38.3154563904],"type":"Point"}
}