{
  "type": "Feature",
  "properties": {
    "iso:country":"TR",
    "sg:address":"Recep Ko?k",
    "sg:city":"Ibradi",
    "sg:classifiers":[
        {
            "category":"Government",
            "subcategory":"Office",
            "type":"Public Place"
        }
    ],
    "sg:phone":"+90 376 615 1006",
    "sg:province":"?ankiri",
    "sg:tags":[
        "municipality"
    ],
    "wof:name":"Orta Belediye Baskani",
    "wof:placetype":"venue"
},
  "geometry": {"coordinates":[35.4317016602,38.9577407837],"type":"Point"}
}