{
  "type": "Feature",
  "properties": {
    "iso:country":"TR",
    "sg:address":"Sevketiye Mah. 212 Sk. No:23",
    "sg:city":"Cine",
    "sg:classifiers":[
        {
            "category":"Farming",
            "subcategory":"Farm",
            "type":"Manufacturing & Wholesale Goods"
        }
    ],
    "sg:phone":"+90 256711678071",
    "sg:postcode":"01370",
    "sg:province":"Aydin",
    "sg:tags":[
        "agricultural",
        "product"
    ],
    "wof:name":"Dogal Tar. Ur. San. Tic. Ltd. Sti.",
    "wof:placetype":"venue"
},
  "geometry": {"coordinates":[27.8492450714,37.8458518982],"type":"Point"}
}