{
  "type": "Feature",
  "properties": {
    "iso:country":"TR",
    "sg:address":"Istiklal Cd. 931 Sk. No:6/1",
    "sg:city":"Kartal",
    "sg:classifiers":[
        {
            "category":"Shopping",
            "subcategory":"Florist",
            "type":"Retail Goods"
        }
    ],
    "sg:phone":"+90 258 261 8634",
    "sg:postcode":"46000",
    "sg:province":"Denizli",
    "sg:tags":[
        "flower"
    ],
    "wof:name":"Mine ?i?ekcilik",
    "wof:placetype":"venue"
},
  "geometry": {"coordinates":[29.0923500061,37.7709884644],"type":"Point"}
}