{
  "type": "Feature",
  "properties": {
    "addr:full":"Ismetiye Cad. Sahende Sok. Aydin Han No: 23/14 Mercan Yukari Dudullu Istanbul 34776",
    "addr:housenumber":"23 / 14 mercan yukari",
    "addr:postcode":"34776",
    "addr:street":"Ismetiye Cad. Sahende Sok. Aydin Han No;Istanbul",
    "iso:country":"TR",
    "sg:address":"Ismetiye Cad. Sahende Sok. Aydin Han No: 23/14 Mercan",
    "sg:city":"Yukari Dudullu",
    "sg:classifiers":[
        {
            "category":"Manufacturing",
            "subcategory":"Rubber & Plastics",
            "type":"Manufacturing & Wholesale Goods"
        }
    ],
    "sg:phone":"+90 212 526 5093",
    "sg:postcode":"34776",
    "sg:province":"Istanbul",
    "sg:tags":[
        "industry"
    ],
    "wof:name":"Akgun Plastik San.tic.ltd.sti.",
    "wof:placetype":"venue"
},
  "geometry": {"coordinates":[29.175403595,41.0060424805],"type":"Point"}
}