{
  "type": "Feature",
  "properties": {
    "addr:full":"Takvimhane Caddesi No:19 - Emin?? Istanbul Macunk?y Istanbul",
    "addr:housenumber":"no 19;? ?",
    "addr:street":"Takvimhane Caddesi;Emin",
    "iso:country":"TR",
    "sg:address":"Takvimhane Caddesi No:19 - Emin?? Istanbul",
    "sg:city":"Macunk?y",
    "sg:classifiers":[
        {
            "category":"Banks & Credit Unions",
            "subcategory":"Investment Brokerage",
            "type":"Services"
        }
    ],
    "sg:phone":"+90 212 514 1704",
    "sg:province":"Istanbul",
    "sg:tags":[
        "aid",
        "material",
        "first"
    ],
    "wof:name":"Esnaf Hastanesi",
    "wof:placetype":"venue"
},
  "geometry": {"coordinates":[28.9759254456,41.0123786926],"type":"Point"}
}