{
  "type": "Feature",
  "properties": {
    "addr:full":"Karatas Yolu 10 Km. Gelibolu Adana 63000",
    "addr:housenumber":"10",
    "addr:postcode":"63000",
    "addr:street":"Karatas Yolu",
    "iso:country":"TR",
    "sg:address":"Karatas Yolu 10 Km.",
    "sg:city":"Gelibolu",
    "sg:classifiers":[
        {
            "category":"Farming",
            "subcategory":"Farm",
            "type":"Manufacturing & Wholesale Goods"
        }
    ],
    "sg:phone":"+90 322 321 5247",
    "sg:postcode":"63000",
    "sg:province":"Adana",
    "sg:tags":[
        "agricultural",
        "product"
    ],
    "wof:name":"Adana Un San. A.s",
    "wof:placetype":"venue"
},
  "geometry": {"coordinates":[35.3137359619,37.0007171631],"type":"Point"}
}