{
  "type": "Feature",
  "properties": {
    "iso:country":"TR",
    "sg:address":"545.sok.kocaoglu Is Hani No:4/401",
    "sg:city":"Bornova",
    "sg:classifiers":[
        {
            "category":"Farming",
            "subcategory":"Farm",
            "type":"Manufacturing & Wholesale Goods"
        }
    ],
    "sg:phone":"+90 232 374 4344",
    "sg:postcode":"35040",
    "sg:province":"Izmir",
    "sg:tags":[
        "agricultural",
        "product"
    ],
    "wof:name":"Agronat Tarim Urunleri Ltd.sti.",
    "wof:placetype":"venue"
},
  "geometry": {"coordinates":[27.2117557526,38.4634437561],"type":"Point"}
}