{
  "type": "Feature",
  "properties": {
    "iso:country":"TR",
    "sg:address":"Karsiyaka Mah.23 Eylul Cad. No:3",
    "sg:city":"Iskenderun",
    "sg:classifiers":[
        {
            "category":"Mining & Drilling",
            "type":"Manufacturing & Wholesale Goods"
        }
    ],
    "sg:phone":"+90 286 416 1135",
    "sg:postcode":"31200",
    "sg:province":"?anakkale",
    "sg:tags":[
        "industry",
        "mine"
    ],
    "wof:name":"Troas Minerals Madencilik Tic. Ve San.a.s.",
    "wof:placetype":"venue"
},
  "geometry": {"coordinates":[27.0315895081,38.5317192078],"type":"Point"}
}