{
  "type": "Feature",
  "properties": {
    "addr:full":"Org. San. 2. B?g. S?er Mh. Keresteciler Sit. 2466 Sk. Bayrampasa Denizli 36100",
    "addr:housenumber":"2 b ?;2466",
    "addr:postcode":"?;36100",
    "addr:street":"Org. San.;G. S;Er Mh. Keresteciler Sit.;Sk. Bayrampasa",
    "iso:country":"TR",
    "sg:address":"Org. San. 2. B?g. S?er Mh. Keresteciler Sit. 2466 Sk.",
    "sg:city":"Bayrampasa",
    "sg:classifiers":[
        {
            "category":"Home & Garden",
            "subcategory":"Kitchen Supply",
            "type":"Retail Goods"
        }
    ],
    "sg:phone":"+90 258 268 3137",
    "sg:postcode":"36100",
    "sg:province":"Denizli",
    "sg:tags":[
        "steel",
        "utensil"
    ],
    "wof:name":"Mega Elek. Ev Gere?. San. Tic. A.s.",
    "wof:placetype":"venue"
},
  "geometry": {"coordinates":[29.086491,37.773525],"type":"Point"}
}