{
  "type": "Feature",
  "properties": {
    "iso:country":"TR",
    "sg:address":"1580.sok. No:24/d Mersinli",
    "sg:city":"Mersin",
    "sg:classifiers":[
        {
            "category":"Manufacturing",
            "subcategory":"Rubber & Plastics",
            "type":"Manufacturing & Wholesale Goods"
        }
    ],
    "sg:phone":"+90 232 462 6016",
    "sg:postcode":"52750",
    "sg:province":"Izmir",
    "sg:tags":[
        "industry"
    ],
    "wof:name":"Koyuncu Plastik San. Ve Tic. Ltd.sti.",
    "wof:placetype":"venue"
},
  "geometry": {"coordinates":[27.1787204742,38.4409255981],"type":"Point"}
}