{
  "type": "Feature",
  "properties": {
    "addr:full":"Dogan Cd. No:7/c Merkez Denizli 10100",
    "addr:housenumber":"no 7 / c",
    "addr:postcode":"10100",
    "addr:street":"Dogan Cd.;Merkez",
    "iso:country":"TR",
    "sg:address":"Dogan Cd. No:7/c",
    "sg:city":"Merkez",
    "sg:classifiers":[
        {
            "category":"Shopping",
            "subcategory":"Florist",
            "type":"Retail Goods"
        }
    ],
    "sg:phone":"+90 258 262 4132",
    "sg:postcode":"10100",
    "sg:province":"Denizli",
    "sg:tags":[
        "flower"
    ],
    "wof:name":"Acar ?i?ek?ilik",
    "wof:placetype":"venue"
},
  "geometry": {"coordinates":[29.0925712585,37.7841911316],"type":"Point"}
}