{
  "type": "Feature",
  "properties": {
    "iso:country":"TR",
    "sg:address":"Belediye Balik Hali No:25",
    "sg:city":"Pendik",
    "sg:classifiers":[
        {
            "category":"Food & Beverages",
            "subcategory":"Meat & Fish",
            "type":"Retail Goods"
        }
    ],
    "sg:phone":"+90 362 445 1578",
    "sg:postcode":"34916",
    "sg:province":"Samsun",
    "sg:tags":[
        "seafood"
    ],
    "wof:name":"Kaptan Balikcilik Tic.ltd.sti.",
    "wof:placetype":"venue"
},
  "geometry": {"coordinates":[36.3327903748,41.3028373718],"type":"Point"}
}