{
  "type": "Feature",
  "properties": {
    "addr:full":"1203/ 2.sok. No: 3 Gida Carisi - Yenisehir Izmir 31750",
    "addr:housenumber":"1203 / 2.sok no 3",
    "addr:postcode":"31750",
    "addr:street":"Gida Carisi Yenisehir",
    "iso:country":"TR",
    "sg:address":"1203/ 2.sok. No: 3 Gida Carisi -",
    "sg:city":"Yenisehir",
    "sg:classifiers":[
        {
            "category":"Shopping",
            "subcategory":"Clothing, Apparel, & Fashions",
            "type":"Retail Goods"
        }
    ],
    "sg:phone":"+90 232 433 8619",
    "sg:postcode":"31750",
    "sg:province":"Izmir",
    "sg:tags":[
        "men",
        "wear"
    ],
    "wof:name":"Cagser Tekstil San.tic.ltd.sti.",
    "wof:placetype":"venue"
},
  "geometry": {"coordinates":[27.1296863556,38.4186973572],"type":"Point"}
}