{
  "type": "Feature",
  "properties": {
    "addr:full":"Cumhuriyet Mh. Tennur Sok. No:28/b Istinye Kayseri 34460",
    "addr:housenumber":"no 28 / b",
    "addr:postcode":"34460",
    "addr:street":"Cumhuriyet Mh. Tennur Sok.",
    "iso:country":"TR",
    "sg:address":"Cumhuriyet Mh. Tennur Sok. No:28/b",
    "sg:city":"Istinye",
    "sg:orig_category":"Carpet-kilim-blanket",
    "sg:phone":"+90 352 222 1455",
    "sg:postcode":"34460",
    "sg:province":"Kayseri",
    "wof:name":"Yoruk Kilim Imalati",
    "wof:placetype":"venue"
},
  "geometry": {"coordinates":[36.4393234253,38.2791290283],"type":"Point"}
}