{
  "type": "Feature",
  "properties": {
    "addr:full":"Bahriye Cd. No:191/a Kasimpasa \u00dcmraniye Istanbul 81260",
    "addr:housenumber":"no;/ a",
    "addr:postcode":"81260",
    "addr:street":"Bahriye Cd.;Kasimpasa",
    "iso:country":"TR",
    "sg:address":"Bahriye Cd. No:191/a Kasimpasa",
    "sg:city":"\u00dcmraniye",
    "sg:orig_category":"General Industrial Products",
    "sg:phone":"+90 212 237 8302",
    "sg:postcode":"81260",
    "sg:province":"Istanbul",
    "wof:name":"Mega Mutfak Esya. San. Buzdolaplari",
    "wof:placetype":"venue"
},
  "geometry": {"coordinates":[28.9672546387,41.0534515381],"type":"Point"}
}