{
  "type": "Feature",
  "properties": {
    "addr:full":"Yenidogan Mah. 50/1 Sk. No.1/b Zeytinburnu \u00c7orlu Istanbul",
    "addr:housenumber":"50 / 1;/ b",
    "addr:street":"Yenidogan Mah.;Sk. No.1;Zeytinburnu",
    "iso:country":"TR",
    "sg:address":"Yenidogan Mah. 50/1 Sk. No.1/b Zeytinburnu",
    "sg:city":"\u00c7orlu",
    "sg:classifiers":[
        {
            "category":"Shopping",
            "subcategory":"Luggage & Leather Goods",
            "type":"Retail Goods"
        }
    ],
    "sg:phone":"+90 212 679 1839",
    "sg:province":"Istanbul",
    "sg:tags":[
        "leather-fur",
        "wear"
    ],
    "wof:name":"Pinar Deri Textil Ve Makina San.ltd.sti.",
    "wof:placetype":"venue"
},
  "geometry": {"coordinates":[28.9047679901,40.9882469177],"type":"Point"}
}