{
  "type": "Feature",
  "properties": {
    "iso:country":"TR",
    "sg:address":"Istoc 27.ada No?:48-50",
    "sg:city":"Mahmutbey",
    "sg:classifiers":[
        {
            "category":"Food & Beverages",
            "subcategory":"Fruits & Vegetables",
            "type":"Retail Goods"
        }
    ],
    "sg:phone":"+90 212 659 2565",
    "sg:postcode":"46600",
    "sg:province":"Istanbul",
    "sg:tags":[
        "product",
        "organic"
    ],
    "wof:name":"Ekolojik Market Gida San.ve Tic.ltd.sti",
    "wof:placetype":"venue"
},
  "geometry": {"coordinates":[28.9759254456,41.0123786926],"type":"Point"}
}