{
  "type": "Feature",
  "properties": {
    "addr:full":"Degirmen K? Silivri Istanbul 34570",
    "addr:postcode":"34570",
    "iso:country":"TR",
    "sg:address":"Degirmen K?",
    "sg:city":"Silivri",
    "sg:classifiers":[
        {
            "category":"Shopping",
            "subcategory":"Crafts & Fabrics",
            "type":"Retail Goods"
        }
    ],
    "sg:phone":"+90 212 735 2741",
    "sg:postcode":"34570",
    "sg:province":"Istanbul",
    "sg:tags":[
        "knitting"
    ],
    "wof:name":"Tekfil Iplik Ve Orme San.ltd.sti.",
    "wof:placetype":"venue"
},
  "geometry": {"coordinates":[28.9320983887,41.0362091064],"type":"Point"}
}