{
  "type": "Feature",
  "properties": {
    "addr:full":"Esenler Cd. Elmas Sk. No:4 Bayrampasa Istanbul 36100",
    "addr:postcode":"36100",
    "addr:street":"Esenler Cd.;Sk. No 4 Bayrampasa",
    "iso:country":"TR",
    "sg:address":"Esenler Cd. Elmas Sk. No:4",
    "sg:city":"Bayrampasa",
    "sg:classifiers":[
        {
            "category":"Shopping",
            "subcategory":"Crafts & Fabrics",
            "type":"Retail Goods"
        }
    ],
    "sg:phone":"+90 212 567 8560",
    "sg:postcode":"36100",
    "sg:province":"Istanbul",
    "sg:tags":[
        "yarn"
    ],
    "wof:name":"?zak Mensucat Iplik San.",
    "wof:placetype":"venue"
},
  "geometry": {"coordinates":[29.2612094879,40.8896217346],"type":"Point"}
}