{
  "type": "Feature",
  "properties": {
    "addr:full":"G?tepe Egza Sk. Safter Han No:6 K:1 Levent Nazilli Istanbul 65600",
    "addr:housenumber":"1",
    "addr:postcode":"65600",
    "addr:street":"Egza Sk.;K",
    "iso:country":"TR",
    "sg:address":"G?tepe Egza Sk. Safter Han No:6 K:1 Levent",
    "sg:city":"Nazilli",
    "sg:classifiers":[
        {
            "category":"Home & Garden",
            "subcategory":"Household Appliances",
            "type":"Retail Goods"
        }
    ],
    "sg:phone":"+90 212 281 7307",
    "sg:postcode":"65600",
    "sg:province":"Istanbul",
    "sg:tags":[
        "utensil",
        "electrical"
    ],
    "wof:name":"Alier Imal. A.s.",
    "wof:placetype":"venue"
},
  "geometry": {"coordinates":[28.9861831665,41.0408554077],"type":"Point"}
}