{
  "type": "Feature",
  "properties": {
    "iso:country":"TR",
    "sg:address":"601/1 .sok. No: 30 D Blok Camdibi Is Merkezi Camdibi",
    "sg:city":"Bayrampasa",
    "sg:classifiers":[
        {
            "category":"Structure",
            "subcategory":"Office Building",
            "type":"Public Place"
        }
    ],
    "sg:phone":"+90 232 433 4956",
    "sg:postcode":"36100",
    "sg:province":"Izmir",
    "sg:tags":[
        "satellite",
        "system"
    ],
    "wof:name":"Takgor Elektronik Sanayi",
    "wof:placetype":"venue"
},
  "geometry": {"coordinates":[27.129686,38.418697],"type":"Point"}
}