{
  "type": "Feature",
  "properties": {
    "addr:full":"1643. Sok. No:7 Bayrakli Izmir 35580",
    "addr:housenumber":"no 7",
    "addr:postcode":"1643;35580",
    "addr:street":"Sok.;Bayrakli Izmir",
    "iso:country":"TR",
    "sg:address":"1643. Sok. No:7",
    "sg:city":"Bayrakli",
    "sg:classifiers":[
        {
            "category":"Home & Garden",
            "subcategory":"Building Materials",
            "type":"Retail Goods"
        }
    ],
    "sg:phone":"+90 232 421 2793",
    "sg:postcode":"35580",
    "sg:province":"Izmir",
    "sg:tags":[
        "window",
        "door"
    ],
    "wof:name":"Aydin Aluminyum",
    "wof:placetype":"venue"
},
  "geometry": {"coordinates":[27.1423015594,38.4251480103],"type":"Point"}
}