{
  "type": "Feature",
  "properties": {
    "iso:country":"TR",
    "sg:address":"Oz Ankara Gida Toptancilar Sitesi No:246",
    "sg:city":"Ostim",
    "sg:classifiers":[
        {
            "category":"Food & Beverages",
            "subcategory":"Groceries & Convenience Stores",
            "type":"Retail Goods"
        }
    ],
    "sg:phone":"+90 312 397 5966",
    "sg:postcode":"06374",
    "sg:province":"Ankara",
    "sg:tags":[
        "ready"
    ],
    "wof:name":"Dortnal Pazarlama Tic.ltd.sti.",
    "wof:placetype":"venue"
},
  "geometry": {"coordinates":[32.8560333252,39.9438743591],"type":"Point"}
}