{
  "type": "Feature",
  "properties": {
    "addr:full":"Konya Karabaglar Konya 44210",
    "addr:postcode":"44210",
    "iso:country":"TR",
    "sg:address":"Konya",
    "sg:city":"Karabaglar",
    "sg:classifiers":[
        {
            "category":"Government",
            "subcategory":"Office",
            "type":"Public Place"
        }
    ],
    "sg:phone":"+90 332 834 0293",
    "sg:postcode":"44210",
    "sg:province":"Konya",
    "sg:tags":[
        "army"
    ],
    "wof:name":"Kadinhani Askerlik Subesi",
    "wof:placetype":"venue"
},
  "geometry": {"coordinates":[32.5348510742,38.0135040283],"type":"Point"}
}