{
  "type": "Feature",
  "properties": {
    "iso:country":"TR",
    "sg:address":"Meydanbasi Cd. Il Halk K??hanesi",
    "sg:city":"Beyoglu",
    "sg:classifiers":[
        {
            "category":"Landmark",
            "subcategory":"Tourist Information",
            "type":"Public Place"
        }
    ],
    "sg:postcode":"46810",
    "sg:province":"Mardin",
    "sg:tags":[
        "tourism"
    ],
    "wof:name":"Turizm Danisma Burosu",
    "wof:placetype":"venue"
},
  "geometry": {"coordinates":[40.7201957703,37.3247451782],"type":"Point"}
}