{
  "type": "Feature",
  "properties": {
    "iso:country":"TR",
    "sg:address":"Ata San. 2. Cad. No: 4",
    "sg:city":"Iskitler",
    "sg:classifiers":[
        {
            "category":"Manufacturing",
            "subcategory":"Textiles",
            "type":"Manufacturing & Wholesale Goods"
        }
    ],
    "sg:phone":"+90 312 341 2762",
    "sg:postcode":"06070",
    "sg:province":"Ankara",
    "sg:tags":[
        "cloth",
        "worker"
    ],
    "wof:name":"Erg Metal Tic. Ltd.sti.",
    "wof:placetype":"venue"
},
  "geometry": {"coordinates":[32.8596839905,39.9402656555],"type":"Point"}
}