{
  "type": "Feature",
  "properties": {
    "iso:country":"TR",
    "sg:address":"56. Sk. No:17 Ostim",
    "sg:city":"Gebze",
    "sg:classifiers":[
        {
            "category":"Manufacturing",
            "subcategory":"Metals",
            "type":"Manufacturing & Wholesale Goods"
        }
    ],
    "sg:phone":"+90 312 354 1416",
    "sg:postcode":"41400",
    "sg:province":"Ankara",
    "sg:tags":[
        "aluminium",
        "industry"
    ],
    "wof:name":"Alta Metal San. Tic. Ltd. Sti.",
    "wof:placetype":"venue"
},
  "geometry": {"coordinates":[32.7425308228,39.9778327942],"type":"Point"}
}