{
  "type": "Feature",
  "properties": {
    "addr:full":"Necipbey Cd. No:90 Bostanci Samsun 25900",
    "addr:housenumber":"no 90",
    "addr:postcode":"25900",
    "addr:street":"Necipbey Cd.;Bostanci Samsun",
    "iso:country":"TR",
    "sg:address":"Necipbey Cd. No:90",
    "sg:city":"Bostanci",
    "sg:classifiers":[
        {
            "category":"Home & Garden",
            "subcategory":"Household Appliances",
            "type":"Retail Goods"
        }
    ],
    "sg:phone":"+90 362 431 1180",
    "sg:postcode":"25900",
    "sg:province":"Samsun",
    "sg:tags":[
        "conditioner",
        "air"
    ],
    "wof:name":"Biltes M?h. Tesisat. Klima San.",
    "wof:placetype":"venue"
},
  "geometry": {"coordinates":[36.3378410339,41.2897186279],"type":"Point"}
}