{
  "type": "Feature",
  "properties": {
    "addr:full":"Hosdere Caddesi Cankaya 06540 07080",
    "addr:postcode":"06540 07080",
    "addr:street":"Hosdere Caddesi Cankaya",
    "iso:country":"TR",
    "sg:address":"Hosdere Caddesi",
    "sg:city":"Cankaya",
    "sg:classifiers":[
        {
            "category":"Banks & Credit Unions",
            "subcategory":"Bank",
            "type":"Services"
        }
    ],
    "sg:phone":"+90 312 441 8427",
    "sg:postcode":"07080",
    "sg:province":"06540",
    "wof:name":"S?erbank As",
    "wof:placetype":"venue"
},
  "geometry": {"coordinates":[32.84848,39.896893],"type":"Point"}
}