{
  "type": "Feature",
  "properties": {
    "addr:full":"Avukat Cad. Lala Sahin Sk. No.25 Bomonti Unkapani Istanbul 55020",
    "addr:housenumber":"bomonti",
    "addr:postcode":"55020",
    "addr:street":"Avukat;Sk. No.25;Istanbul",
    "iso:country":"TR",
    "sg:address":"Avukat Cad. Lala Sahin Sk. No.25 Bomonti",
    "sg:city":"Unkapani",
    "sg:classifiers":[
        {
            "category":"Shopping",
            "subcategory":"Crafts & Fabrics",
            "type":"Retail Goods"
        }
    ],
    "sg:phone":"+90 212 225 9325",
    "sg:postcode":"55020",
    "sg:province":"Istanbul",
    "sg:tags":[
        "textile",
        "-leather",
        "exporter"
    ],
    "wof:name":"Art Textile",
    "wof:placetype":"venue"
},
  "geometry": {"coordinates":[28.9861831665,41.0408554077],"type":"Point"}
}