{
  "type": "Feature",
  "properties": {
    "addr:full":"Ikitelli Organize Sanayi B?gesi Demirciler San.sit.c-5 Blok No:255 Ikitelli/K\u00fc\u00e7\u00fck\u00e7ekmece Istanbul 34670",
    "addr:housenumber":"?;blok no 255",
    "addr:postcode":"san.sit.c-5;34670",
    "addr:street":"Organize Sanayi B",
    "iso:country":"TR",
    "sg:address":"Ikitelli Organize Sanayi B?gesi Demirciler San.sit.c-5 Blok No:255",
    "sg:city":"Ikitelli/K\u00fc\u00e7\u00fck\u00e7ekmece",
    "sg:classifiers":[
        {
            "category":"Wholesale",
            "subcategory":"Machinery & Supplies",
            "type":"Manufacturing & Wholesale Goods"
        }
    ],
    "sg:phone":"+90 212671129495",
    "sg:postcode":"34670",
    "sg:province":"Istanbul",
    "sg:tags":[
        "heavy",
        "construction",
        "macinery"
    ],
    "sg:website":"atilganmakine.com",
    "wof:name":"Atilgan Makine Hidrolik Yedek-forklift San.ltd.st",
    "wof:placetype":"venue"
},
  "geometry": {"coordinates":[28.9861831665,41.0408554077],"type":"Point"}
}