{
  "type": "Feature",
  "properties": {
    "addr:full":"Nayman Mh. 2.sk. No.1 Halkali Istanbul 23410",
    "addr:housenumber":"no.1",
    "addr:postcode":"23410",
    "addr:street":"Mh. 2.Sk;Istanbul",
    "iso:country":"TR",
    "sg:address":"Nayman Mh. 2.sk. No.1",
    "sg:city":"Halkali",
    "sg:classifiers":[
        {
            "category":"Shopping",
            "subcategory":"Clothing, Apparel, & Fashions",
            "type":"Retail Goods"
        }
    ],
    "sg:phone":"+90 212 548 4070",
    "sg:postcode":"23410",
    "sg:province":"Istanbul",
    "sg:tags":[
        "ready",
        "wear"
    ],
    "wof:name":"Kebo Giyim Sanayi A.s.",
    "wof:placetype":"venue"
},
  "geometry": {"coordinates":[28.9759254456,41.0123786926],"type":"Point"}
}