{
  "type": "Feature",
  "properties": {
    "iso:country":"TR",
    "sg:address":"Karatarla Mah. Tokatlioglu Sok. Eralp Ishani Kat:1 No:7",
    "sg:city":"Beyazit",
    "sg:classifiers":[
        {
            "category":"Shopping",
            "subcategory":"Crafts & Fabrics",
            "type":"Retail Goods"
        }
    ],
    "sg:phone":"+90 342221174041",
    "sg:postcode":"65400",
    "sg:province":"Gaziantep",
    "sg:tags":[
        "yarn"
    ],
    "wof:name":"Sertas Iplik Tekstil San. Ve Tic. A.s.",
    "wof:placetype":"venue"
},
  "geometry": {"coordinates":[37.3761024475,37.0629463196],"type":"Point"}
}