{
  "type": "Feature",
  "properties": {
    "addr:full":"G?es Cd. No:83 Bayrampasa 2.ulus Istanbul",
    "addr:housenumber":"?;cd. no 83;2.ulus",
    "addr:street":"Bayrampasa",
    "iso:country":"TR",
    "sg:address":"G?es Cd. No:83 Bayrampasa",
    "sg:city":"2.ulus",
    "sg:classifiers":[
        {
            "category":"Manufacturing",
            "subcategory":"Rubber & Plastics",
            "type":"Manufacturing & Wholesale Goods"
        }
    ],
    "sg:phone":"+90 212 613 1983",
    "sg:province":"Istanbul",
    "sg:tags":[
        "industry"
    ],
    "wof:name":"Baler Plastik Kalip San. Tic. Ltd. Sti.",
    "wof:placetype":"venue"
},
  "geometry": {"coordinates":[28.9011554718,41.0516204834],"type":"Point"}
}