{
  "type": "Feature",
  "properties": {
    "addr:full":"Hasanpasa Mandira Cad.konak Is Merkezi.no:2 B.blok D:22 Kad\u0131k\u00f6y Istanbul 34990",
    "addr:housenumber":"2;22",
    "addr:postcode":"34990",
    "addr:street":"B.Blok D;Istanbul",
    "iso:country":"TR",
    "sg:address":"Hasanpasa Mandira Cad.konak Is Merkezi.no:2 B.blok D:22",
    "sg:city":"Kad\u0131k\u00f6y",
    "sg:classifiers":[
        {
            "category":"Airport",
            "subcategory":"International",
            "type":"Transportation"
        }
    ],
    "sg:phone":"+90 216 428 3630",
    "sg:postcode":"34990",
    "sg:province":"Istanbul",
    "wof:name":"Partas Dis Ticaret Nak.ve G?mr?kleme Hiz.",
    "wof:placetype":"venue"
},
  "geometry": {"coordinates":[29.0938472748,41.0371398926],"type":"Point"}
}