{
  "type": "Feature",
  "properties": {
    "addr:full":"K?? San. Sitesi 1308. Sk. No:22 Bandirma Ikitelli/K\u00fc\u00e7\u00fck\u00e7ekmece Balikesir 34670",
    "addr:housenumber":"? ?;22",
    "addr:postcode":"34670",
    "addr:street":"San. Sitesi 1308 Sk. No;Balikesir",
    "iso:country":"TR",
    "sg:address":"K?? San. Sitesi 1308. Sk. No:22 Bandirma",
    "sg:city":"Ikitelli/K\u00fc\u00e7\u00fck\u00e7ekmece",
    "sg:classifiers":[
        {
            "category":"Manufacturing",
            "subcategory":"Tools & Machinery",
            "type":"Manufacturing & Wholesale Goods"
        }
    ],
    "sg:phone":"+90 266 718 1994",
    "sg:postcode":"34670",
    "sg:province":"Balikesir",
    "sg:tags":[
        "machine",
        "industry"
    ],
    "wof:name":"Odaman Degirmen Makina",
    "wof:placetype":"venue"
},
  "geometry": {"coordinates":[27.8833007812,39.6520996094],"type":"Point"}
}