{
  "type": "Feature",
  "properties": {
    "iso:country":"TR",
    "sg:address":"Meclis Mah.atat?k Cad Teraziler Mevkii No:51/3 Sarigazi",
    "sg:city":"Sarigazi/?mraniye",
    "sg:classifiers":[
        {
            "category":"Shopping",
            "subcategory":"Crafts & Fabrics",
            "type":"Retail Goods"
        }
    ],
    "sg:phone":"+90 216 621 8121",
    "sg:postcode":"34785",
    "sg:province":"Istanbul",
    "sg:tags":[
        "yarn"
    ],
    "wof:name":"Polytek Ltd.sti",
    "wof:placetype":"venue"
},
  "geometry": {"coordinates":[29.214799881,41.0071983337],"type":"Point"}
}