{
  "type": "Feature",
  "properties": {
    "addr:full":"Millet Cad. Aydin Apt. 131/10 Capa \u00c7ankaya Istanbul 06690",
    "addr:housenumber":"131 / 10",
    "addr:postcode":"06690",
    "addr:street":"Millet Cad. Aydin Apt.",
    "iso:country":"TR",
    "sg:address":"Millet Cad. Aydin Apt. 131/10 Capa",
    "sg:city":"\u00c7ankaya",
    "sg:classifiers":[
        {
            "category":"Wholesale",
            "subcategory":"Medical Equipment & Supplies",
            "type":"Manufacturing & Wholesale Goods"
        }
    ],
    "sg:phone":"+90 212 530 9718",
    "sg:postcode":"06690",
    "sg:province":"Istanbul",
    "wof:name":"Mega Med Tibbi Mlz. Ith. Ihr. Ltd.",
    "wof:placetype":"venue"
},
  "geometry": {"coordinates":[28.9861831665,41.0408554077],"type":"Point"}
}