{
  "type": "Feature",
  "properties": {
    "addr:full":"Fatih Mh. Akif Ersoy Cd. Fidan Apt. Alti G.o.p. K?tahya",
    "addr:housenumber":"k ?",
    "addr:street":"Akif Ersoy Cd. Fidan Apt. Alti G.O.P.;Tahya",
    "iso:country":"TR",
    "sg:address":"Fatih Mh. Akif Ersoy Cd. Fidan Apt. Alti",
    "sg:city":"G.o.p.",
    "sg:classifiers":[
        {
            "category":"Manufacturing",
            "subcategory":"Food",
            "type":"Manufacturing & Wholesale Goods"
        }
    ],
    "sg:phone":"+90 274 223 4804",
    "sg:province":"K?tahya",
    "sg:tags":[
        "wholesaler"
    ],
    "wof:name":"Sevgi Gida Ltd.sti.",
    "wof:placetype":"venue"
},
  "geometry": {"coordinates":[35.4317016602,38.9577407837],"type":"Point"}
}