{
  "type": "Feature",
  "properties": {
    "addr:full":"Koprubasi Cad. Yalbi Sok. Arif Bey Apt No:13/5 Kiziltoprak Eskisehir 07300",
    "addr:housenumber":"arif;apt;5",
    "addr:postcode":"07300",
    "addr:street":"Koprubasi Cad. Yalbi Sok.;No 13 /;Eskisehir",
    "iso:country":"TR",
    "sg:address":"Koprubasi Cad. Yalbi Sok. Arif Bey Apt No:13/5",
    "sg:city":"Kiziltoprak",
    "sg:classifiers":[
        {
            "category":"Manufacturing",
            "subcategory":"Building Materials",
            "type":"Manufacturing & Wholesale Goods"
        }
    ],
    "sg:phone":"+90 222 221 4679",
    "sg:postcode":"07300",
    "sg:province":"Eskisehir",
    "sg:tags":[
        "lifts-elevators"
    ],
    "wof:name":"Elas Asansorleri San Ve Tic Ltd.",
    "wof:placetype":"venue"
},
  "geometry": {"coordinates":[30.5175457001,39.7700805664],"type":"Point"}
}