{
  "type": "Feature",
  "properties": {
    "addr:full":"Marasal Cakmak Cad 41 Iskenderun 31200 31200",
    "addr:housenumber":"41",
    "addr:postcode":"31200 31200",
    "addr:street":"Cakmak Cad",
    "iso:country":"TR",
    "sg:address":"Marasal Cakmak Cad 41",
    "sg:city":"Iskenderun",
    "sg:classifiers":[
        {
            "category":"Banks & Credit Unions",
            "subcategory":"Bank",
            "type":"Services"
        }
    ],
    "sg:phone":"+90 326 613 0281",
    "sg:postcode":"31200",
    "sg:province":"31200",
    "wof:name":"Demirbank Tas",
    "wof:placetype":"venue"
},
  "geometry": {"coordinates":[40.49184,38.880863],"type":"Point"}
}