{
  "type": "Feature",
  "properties": {
    "iso:country":"TR",
    "sg:address":"Hazim Ulusahin Is Merkezi B-blok No:p/070",
    "sg:city":"Kartal",
    "sg:classifiers":[
        {
            "category":"Professional",
            "subcategory":"Computer Services",
            "type":"Services"
        }
    ],
    "sg:phone":"+90 332 233 9648",
    "sg:postcode":"81420",
    "sg:province":"Konya",
    "sg:tags":[
        "application",
        "software"
    ],
    "wof:name":"Verde Bilgisayar",
    "wof:placetype":"venue"
},
  "geometry": {"coordinates":[33.0667152405,39.2111282349],"type":"Point"}
}