{
  "type": "Feature",
  "properties": {
    "iso:country":"TR",
    "sg:address":"Zafer Cad. No:27",
    "sg:city":"Bornova",
    "sg:orig_category":"Muhtarliklar",
    "sg:phone":"+90 232 339 5945",
    "sg:postcode":"35040",
    "sg:province":"Izmir",
    "wof:name":"Kazimdirik Mahallesi Muhtar: Dilek Idug ?elik",
    "wof:placetype":"venue"
},
  "geometry": {"coordinates":[27.2114925385,38.4614334106],"type":"Point"}
}