{
  "type": "Feature",
  "properties": {
    "iso:country":"TR",
    "sg:address":"Ozelem San. Sit. 6. Sk. No:68",
    "sg:city":"Gayrettepe/besiktas",
    "sg:classifiers":[
        {
            "category":"Retail",
            "subcategory":"Auto Repair",
            "type":"Services"
        }
    ],
    "sg:phone":"+90 256 225 5791",
    "sg:postcode":"80280",
    "sg:province":"Aydin",
    "sg:tags":[
        "maintenance"
    ],
    "wof:name":"Aydin Oto Elekt.",
    "wof:placetype":"venue"
},
  "geometry": {"coordinates":[27.8324394226,37.8409690857],"type":"Point"}
}