{
  "type": "Feature",
  "properties": {
    "iso:country":"TR",
    "sg:address":"277/1 Sk. No:1/1",
    "sg:city":"Bornova",
    "sg:orig_category":"Muhtarliklar",
    "sg:phone":"+90 232 339 3339",
    "sg:postcode":"35040",
    "sg:province":"Izmir",
    "wof:name":"Manavkuyu Mahallesi Muhtar: L?fi Kirkpinar",
    "wof:placetype":"venue"
},
  "geometry": {"coordinates":[27.2203388214,38.46667099],"type":"Point"}
}