{
  "type": "Feature",
  "properties": {
    "iso:country":"TR",
    "sg:address":"B??dere Cd. No.59 Mecidiyek?",
    "sg:city":"Kepez",
    "sg:classifiers":[
        {
            "category":"Shopping",
            "subcategory":"Stationery & Office Supplies",
            "type":"Retail Goods"
        }
    ],
    "sg:phone":"+90 212 274 9782",
    "sg:postcode":"1710",
    "sg:province":"Istanbul",
    "sg:tags":[
        "furniture"
    ],
    "wof:name":"Uyar Celik Buro",
    "wof:placetype":"venue"
},
  "geometry": {"coordinates":[28.99177742,41.0796928406],"type":"Point"}
}