{
  "type": "Feature",
  "properties": {
    "addr:full":"Milli Egemenlik Cad. Baki Bey Apt. No:10/5 Mersin Antalya 52750",
    "addr:housenumber":"5",
    "addr:postcode":"52750",
    "addr:street":"Egemenlik Cad.",
    "iso:country":"TR",
    "sg:address":"Milli Egemenlik Cad. Baki Bey Apt. No:10/5",
    "sg:city":"Mersin",
    "sg:classifiers":[
        {
            "category":"Professional",
            "subcategory":"Computer Services",
            "type":"Services"
        }
    ],
    "sg:phone":"+90 242247679324",
    "sg:postcode":"52750",
    "sg:province":"Antalya",
    "sg:tags":[
        "application",
        "software"
    ],
    "wof:name":"Fon Bilgisayar Buro Malz. San. Ve Tic. Ltd. Sti.",
    "wof:placetype":"venue"
},
  "geometry": {"coordinates":[30.7092056274,36.8790512085],"type":"Point"}
}