{
  "type": "Feature",
  "properties": {
    "iso:country":"TR",
    "sg:address":"Tevfik Fikret Cad. Ninni Sok. 30/1 Sokullu",
    "sg:city":"Emin?? 34440",
    "sg:orig_category":"Printinh House",
    "sg:phone":"+90 312 481 3534",
    "sg:province":"Ankara",
    "wof:name":"Medinews Ihale Dergisi",
    "wof:placetype":"venue"
},
  "geometry": {"coordinates":[32.8361091614,39.8871040344],"type":"Point"}
}