{
  "type": "Feature",
  "properties": {
    "addr:full":"Alacahamam Cad. Cansu Han No: 14 Sultanhamam Istanbul",
    "addr:housenumber":"14",
    "addr:street":"Alacahamam Cad. Cansu Han No",
    "iso:country":"TR",
    "sg:address":"Alacahamam Cad. Cansu Han No: 14",
    "sg:city":"Sultanhamam",
    "sg:classifiers":[
        {
            "category":"Home & Garden",
            "subcategory":"Home Furnishings",
            "type":"Retail Goods"
        }
    ],
    "sg:phone":"+90 212 520 7431",
    "sg:province":"Istanbul",
    "sg:tags":[
        "-curtains",
        "upholstery"
    ],
    "wof:name":"Nurteks Tekstil Nakis Sanayi Ve Ticaret Ltd. Sti.",
    "wof:placetype":"venue"
},
  "geometry": {"coordinates":[28.9759254456,41.0123786926],"type":"Point"}
}