{
  "type": "Feature",
  "properties": {
    "iso:country":"TR",
    "sg:address":"Gersan Sanayi Sitesi 657 . Sok. No. 13 Sasmaz",
    "sg:city":"Sultan?ftligi-gosmanpasa",
    "sg:classifiers":[
        {
            "category":"Wholesale",
            "subcategory":"Furniture",
            "type":"Manufacturing & Wholesale Goods"
        }
    ],
    "sg:phone":"+90 312 255 4177",
    "sg:province":"Ankara",
    "sg:tags":[
        "school"
    ],
    "wof:name":"Elit Okul Gerecleri Iml.san.tic.ltd.sti.",
    "wof:placetype":"venue"
},
  "geometry": {"coordinates":[32.856033,39.943874],"type":"Point"}
}