{
  "type": "Feature",
  "properties": {
    "addr:full":"Halkali C. No.208 Sefak? Yenibosna Istanbul 34520",
    "addr:postcode":"34520",
    "addr:street":"C.;Sefak;Yenibosna",
    "iso:country":"TR",
    "sg:address":"Halkali C. No.208 Sefak?",
    "sg:city":"Yenibosna",
    "sg:classifiers":[
        {
            "category":"Shopping",
            "subcategory":"Clothing, Apparel, & Fashions",
            "type":"Retail Goods"
        }
    ],
    "sg:phone":"+90 212 698 9800",
    "sg:postcode":"34520",
    "sg:province":"Istanbul",
    "sg:tags":[
        "bag-belt-accessories"
    ],
    "wof:name":"Desa Deri San. A.s.",
    "wof:placetype":"venue"
},
  "geometry": {"coordinates":[28.975925,41.012379],"type":"Point"}
}