{
  "type": "Feature",
  "properties": {
    "iso:country":"TR",
    "sg:address":"Yesiloba Mevkii No. 808",
    "sg:city":"Nizip",
    "sg:classifiers":[
        {
            "category":"Utilities",
            "subcategory":"Water",
            "type":"Services"
        }
    ],
    "sg:phone":"+90 322 428 0017",
    "sg:postcode":"27700",
    "sg:province":"Adana",
    "sg:tags":[
        "vegetable",
        "margarine",
        "oil"
    ],
    "wof:name":"Aslan Yag San. Ltd.sti.",
    "wof:placetype":"venue"
},
  "geometry": {"coordinates":[35.3137359619,37.0007171631],"type":"Point"}
}