{
  "type": "Feature",
  "properties": {
    "addr:full":"Hastane Cd. No: 40 Aklan Apt. 3/6 Besiktas I?el 75200",
    "addr:housenumber":"no 40;apt. 3 / 6;?",
    "addr:postcode":"75200",
    "addr:street":"Hastane Cd.;Besiktas I;El",
    "iso:country":"TR",
    "sg:address":"Hastane Cd. No: 40 Aklan Apt. 3/6",
    "sg:city":"Besiktas",
    "sg:classifiers":[
        {
            "category":"Shopping",
            "subcategory":"Florist",
            "type":"Retail Goods"
        }
    ],
    "sg:phone":"+90 324 231 4022",
    "sg:postcode":"75200",
    "sg:province":"I?el",
    "sg:tags":[
        "flower"
    ],
    "wof:name":"Aklan Sigorta Ltd. Sti.",
    "wof:placetype":"venue"
},
  "geometry": {"coordinates":[43.0151405334,41.1403884888],"type":"Point"}
}