{
  "type": "Feature",
  "properties": {
    "addr:full":"Murat Inan Dinar Bitlis 03400",
    "addr:postcode":"03400",
    "addr:street":"Dinar",
    "iso:country":"TR",
    "sg:address":"Murat Inan",
    "sg:city":"Dinar",
    "sg:classifiers":[
        {
            "category":"Government",
            "subcategory":"Office",
            "type":"Public Place"
        }
    ],
    "sg:phone":"+90 434 241 2001",
    "sg:postcode":"03400",
    "sg:province":"Bitlis",
    "sg:tags":[
        "municipality"
    ],
    "wof:name":"Yolalan Belediye Baskani",
    "wof:placetype":"venue"
},
  "geometry": {"coordinates":[32.8594665527,39.9355583191],"type":"Point"}
}