{
  "type": "Feature",
  "properties": {
    "iso:country":"TR",
    "sg:address":"Calica Mah.belediy D?kan No:5-6 K.culha",
    "sg:city":"Fethiye",
    "sg:classifiers":[
        {
            "category":"Home & Garden",
            "subcategory":"Garden Supply",
            "type":"Retail Goods"
        }
    ],
    "sg:phone":"+90 6464868",
    "sg:postcode":"44000",
    "sg:province":"Mugla",
    "sg:tags":[
        "fertilize",
        "soil"
    ],
    "wof:name":"Murat Tarim Ve Kimya Ltd.sti.",
    "wof:placetype":"venue"
},
  "geometry": {"coordinates":[28.3658008575,37.2196006775],"type":"Point"}
}