{
  "type": "Feature",
  "properties": {
    "addr:full":"Temiz Cad. No:30 Merter Bursa 34010",
    "addr:housenumber":"30",
    "addr:postcode":"34010",
    "addr:street":"Temiz Cad. No;Bursa",
    "iso:country":"TR",
    "sg:address":"Temiz Cad. No:30",
    "sg:city":"Merter",
    "sg:orig_category":"Orthopedical Materials",
    "sg:phone":"+90 224 225 4515",
    "sg:postcode":"34010",
    "sg:province":"Bursa",
    "wof:name":"Bengisu Medikal",
    "wof:placetype":"venue"
},
  "geometry": {"coordinates":[29.0920085907,40.1837921143],"type":"Point"}
}