{
  "type": "Feature",
  "properties": {
    "addr:full":"Mersin Cd. No:168 Bp Istasyonu Gursu I?el 07070",
    "addr:housenumber":"no;bp;?",
    "addr:postcode":"07070",
    "addr:street":"Mersin Cd.;Istasyonu Gursu I;El",
    "iso:country":"TR",
    "sg:address":"Mersin Cd. No:168 Bp Istasyonu",
    "sg:city":"Gursu",
    "sg:classifiers":[
        {
            "category":"Farming",
            "subcategory":"Farm",
            "type":"Manufacturing & Wholesale Goods"
        }
    ],
    "sg:phone":"+90 324 231 7286",
    "sg:postcode":"07070",
    "sg:province":"I?el",
    "sg:tags":[
        "agricultural",
        "product"
    ],
    "wof:name":"Alhar Ltd.sti.",
    "wof:placetype":"venue"
},
  "geometry": {"coordinates":[34.6325416565,36.7999000549],"type":"Point"}
}