{
  "type": "Feature",
  "properties": {
    "addr:full":"Eski Hal Civari No: 67 Urgup Seyhan Nevsehir 01000",
    "addr:housenumber":"67;seyhan",
    "addr:postcode":"01000",
    "addr:street":"Eski Hal Civari No",
    "iso:country":"TR",
    "sg:address":"Eski Hal Civari No: 67 Urgup",
    "sg:city":"Seyhan",
    "sg:classifiers":[
        {
            "category":"Shopping",
            "subcategory":"Pharmacy",
            "type":"Retail Goods"
        }
    ],
    "sg:phone":"+90 384 341 2378",
    "sg:postcode":"01000",
    "sg:province":"Nevsehir",
    "sg:tags":[
        "store",
        "drug"
    ],
    "wof:name":"Aydan Eczanesi",
    "wof:placetype":"venue"
},
  "geometry": {"coordinates":[34.7110939026,38.6325645447],"type":"Point"}
}