{
  "type": "Feature",
  "properties": {
    "addr:full":"Tevfikbey Mah.istiklal Cad.no:33 B.blk.k.1-2 Sefakoy Kad\u0131k\u00f6y Istanbul 34734",
    "addr:housenumber":"33",
    "addr:postcode":"34734",
    "addr:street":"Cad.No",
    "iso:country":"TR",
    "sg:address":"Tevfikbey Mah.istiklal Cad.no:33 B.blk.k.1-2 Sefakoy",
    "sg:city":"Kad\u0131k\u00f6y",
    "sg:classifiers":[
        {
            "category":"Shopping",
            "subcategory":"Crafts & Fabrics",
            "type":"Retail Goods"
        }
    ],
    "sg:phone":"+90 212 624 2944",
    "sg:postcode":"34734",
    "sg:province":"Istanbul",
    "sg:tags":[
        "textile",
        "-leather",
        "exporter"
    ],
    "wof:name":"Caretta Leather Deri Konf.san.tic.ltd.sti.",
    "wof:placetype":"venue"
},
  "geometry": {"coordinates":[28.9861831665,41.0408554077],"type":"Point"}
}