{
  "type": "Feature",
  "properties": {
    "addr:full":"Keles Iskenderun Bursa 31200",
    "addr:postcode":"31200",
    "iso:country":"TR",
    "sg:address":"Keles",
    "sg:city":"Iskenderun",
    "sg:classifiers":[
        {
            "category":"Mining & Drilling",
            "type":"Manufacturing & Wholesale Goods"
        }
    ],
    "sg:phone":"+90 224 861 2362",
    "sg:postcode":"31200",
    "sg:province":"Bursa",
    "sg:tags":[
        "industry",
        "mine"
    ],
    "wof:name":"Marmara Linyit K?m?r Isletmesi",
    "wof:placetype":"venue"
},
  "geometry": {"coordinates":[29.2260494232,39.911895752],"type":"Point"}
}