{
  "type": "Feature",
  "properties": {
    "addr:full":"Gedikpasa Hamam Cad. No:18 Neviye Sokak Beyazit 34450 Eminonu Istanbul K???k?ekmece Istanbul 34620",
    "addr:housenumber":"18;beyazit",
    "addr:postcode":"34450;?;34620",
    "addr:street":"Hamam Cad. No;Neviye Sokak",
    "iso:country":"TR",
    "sg:address":"Gedikpasa Hamam Cad. No:18 Neviye Sokak Beyazit 34450 Eminonu Istanbul",
    "sg:city":"K???k?ekmece",
    "sg:classifiers":[
        {
            "category":"Manufacturing",
            "subcategory":"Textiles",
            "type":"Manufacturing & Wholesale Goods"
        }
    ],
    "sg:phone":"+90 212 517 4931",
    "sg:postcode":"34620",
    "sg:province":"Istanbul",
    "sg:tags":[
        "leather",
        "raw",
        "material",
        "-"
    ],
    "wof:name":"Kadir Okce Ve Kundura Yan San",
    "wof:placetype":"venue"
},
  "geometry": {"coordinates":[28.9759254456,41.0123786926],"type":"Point"}
}