{
  "type": "Feature",
  "properties": {
    "iso:country":"TR",
    "sg:address":"Hekimsuyu C. No.33 K??k?",
    "sg:city":"Isikkent",
    "sg:classifiers":[
        {
            "category":"Shopping",
            "subcategory":"Shoes",
            "type":"Retail Goods"
        }
    ],
    "sg:phone":"+90 212 558 1108",
    "sg:postcode":"35070",
    "sg:province":"Istanbul",
    "wof:name":"J?tsan J?t Espadril San. A.s.",
    "wof:placetype":"venue"
},
  "geometry": {"coordinates":[28.905655,41.075817],"type":"Point"}
}