{
  "type": "Feature",
  "properties": {
    "iso:country":"TR",
    "sg:address":"Muh. Naci Bey. Cad. Basegmez Apt No:1/3",
    "sg:city":"Merkez",
    "sg:classifiers":[
        {
            "category":"Wholesale",
            "subcategory":"Medical Equipment & Supplies",
            "type":"Manufacturing & Wholesale Goods"
        }
    ],
    "sg:phone":"+90 352 222 2220",
    "sg:postcode":"03300",
    "sg:province":"Kayseri",
    "wof:name":"Cetinkaya Medikal",
    "wof:placetype":"venue"
},
  "geometry": {"coordinates":[35.4364013672,38.7450408936],"type":"Point"}
}