{
  "type": "Feature",
  "properties": {
    "addr:full":"Rihtim Cad. Resit Efendi Sk. No:1/6 Kadik? Merter Istanbul 34010",
    "addr:housenumber":"6;?",
    "addr:postcode":"34010",
    "addr:street":"Rihtim Cad. Resit Efendi Sk. No 1 /",
    "iso:country":"TR",
    "sg:address":"Rihtim Cad. Resit Efendi Sk. No:1/6 Kadik?",
    "sg:city":"Merter",
    "sg:orig_category":"Orthopedical Materials",
    "sg:phone":"+90 216 346 0212",
    "sg:postcode":"34010",
    "sg:province":"Istanbul",
    "wof:name":"Adnan Medikal",
    "wof:placetype":"venue"
},
  "geometry": {"coordinates":[28.91355896,41.0233802795],"type":"Point"}
}