{
  "type": "Feature",
  "properties": {
    "addr:full":"Hasim Iscan Mah. Fevzi ?akmak Cad. ?ilek?i Apt. A Blok 2/3 Yenikapi Antalya 23000",
    "addr:housenumber":"?;?;?;2 / 3",
    "addr:postcode":"23000",
    "addr:street":"Iscan Mah. Fevzi;Akmak Cad.;I Apt. A Blok;Yenikapi",
    "iso:country":"TR",
    "sg:address":"Hasim Iscan Mah. Fevzi ?akmak Cad. ?ilek?i Apt. A Blok 2/3",
    "sg:city":"Yenikapi",
    "sg:classifiers":[
        {
            "category":"Travel",
            "subcategory":"Travel Agent",
            "type":"Entertainment"
        }
    ],
    "sg:phone":"+90 242248484624",
    "sg:postcode":"23000",
    "sg:province":"Antalya",
    "sg:tags":[
        "agency",
        "tourism"
    ],
    "wof:name":"Nts/nur Travel",
    "wof:placetype":"venue"
},
  "geometry": {"coordinates":[30.7092056274,36.8790512085],"type":"Point"}
}