{
  "type": "Feature",
  "properties": {
    "addr:full":"B??dere Cad. No:107/7 G.tepe Osmangazi Istanbul 16330",
    "addr:housenumber":"? ?;107 / 7",
    "addr:postcode":"16330",
    "addr:street":"B;Dere Cad. No;G.Tepe Osmangazi",
    "iso:country":"TR",
    "sg:address":"B??dere Cad. No:107/7 G.tepe",
    "sg:city":"Osmangazi",
    "sg:classifiers":[
        {
            "category":"Wholesale",
            "subcategory":"Medical Equipment & Supplies",
            "type":"Manufacturing & Wholesale Goods"
        }
    ],
    "sg:phone":"+90 212 267 5908",
    "sg:postcode":"16330",
    "sg:province":"Istanbul",
    "wof:name":"Uni-ten Uls. Tic.",
    "wof:placetype":"venue"
},
  "geometry": {"coordinates":[28.9861831665,41.0408554077],"type":"Point"}
}