{
  "type": "Feature",
  "properties": {
    "addr:full":"Organize San. Bolgesi 10.cad. Kad\u0131k\u00f6y Eskisehir",
    "addr:street":"Organize",
    "iso:country":"TR",
    "sg:address":"Organize San. Bolgesi 10.cad.",
    "sg:city":"Kad\u0131k\u00f6y",
    "sg:classifiers":[
        {
            "category":"Utilities",
            "subcategory":"Natural Gas",
            "type":"Services"
        }
    ],
    "sg:phone":"+90 22223605734428",
    "sg:province":"Eskisehir",
    "sg:tags":[
        "tank-heating-natural"
    ],
    "wof:name":"Rem-ak Endustriyel Yatirimlar San. Ve Tic. A.s.",
    "wof:placetype":"venue"
},
  "geometry": {"coordinates":[31.0192203522,39.6195106506],"type":"Point"}
}