{
  "type": "Feature",
  "properties": {
    "iso:country":"TR",
    "sg:address":"G??pala Zabit Sk. No: 1",
    "sg:city":"Avcilar",
    "sg:classifiers":[
        {
            "category":"Mining & Drilling",
            "type":"Manufacturing & Wholesale Goods"
        }
    ],
    "sg:phone":"+90 212 591 8686",
    "sg:postcode":"01350",
    "sg:province":"Istanbul",
    "sg:tags":[
        "industry",
        "mine"
    ],
    "wof:name":"Canel Madencilik Ticaret Ve Sanayi A.s.",
    "wof:placetype":"venue"
},
  "geometry": {"coordinates":[28.9759254456,41.0123786926],"type":"Point"}
}