{
  "type": "Feature",
  "properties": {
    "addr:full":"Mustafa Akif Ekeman ?arsi Mah. Iskele Meydani P.k. 282 Bodrum Mugla 48400",
    "addr:housenumber":"?",
    "addr:postcode":"48400",
    "addr:street":"Mustafa Akif Ekeman;Iskele Meydani P.K. 282",
    "iso:country":"TR",
    "sg:address":"Mustafa Akif Ekeman ?arsi Mah. Iskele Meydani P.k. 282",
    "sg:city":"Bodrum",
    "sg:classifiers":[
        {
            "category":"Recreation",
            "subcategory":"Boat Charter",
            "type":"Entertainment"
        }
    ],
    "sg:phone":"+90 252 316 4686",
    "sg:postcode":"48400",
    "sg:province":"Mugla",
    "sg:tags":[
        "yachting"
    ],
    "wof:name":"Sunday Yat. Isl.",
    "wof:placetype":"venue"
},
  "geometry": {"coordinates":[28.3658008575,37.2196006775],"type":"Point"}
}