{
  "type": "Feature",
  "properties": {
    "iso:country":"TR",
    "sg:address":"Dumlupinar Mh. 255 Sk. No: 26",
    "sg:city":"Iskenderun",
    "sg:classifiers":[
        {
            "category":"Manufacturing",
            "subcategory":"Tools & Machinery",
            "type":"Manufacturing & Wholesale Goods"
        }
    ],
    "sg:phone":"+90 326 615 7520",
    "sg:postcode":"31200",
    "sg:province":"Hatay",
    "sg:tags":[
        "machine",
        "industry"
    ],
    "wof:name":"Ragbet Mak. Ltd. Sti.",
    "wof:placetype":"venue"
},
  "geometry": {"coordinates":[36.1578292847,36.2030792236],"type":"Point"}
}