{
  "type": "Feature",
  "properties": {
    "addr:full":"Onur Sok. No:27/4 Maltepe Kad\u0131k\u00f6y Ankara 34714",
    "addr:housenumber":"no 27 / 4",
    "addr:postcode":"34714",
    "addr:street":"Onur Sok.;Maltepe Kadikoey",
    "iso:country":"TR",
    "sg:address":"Onur Sok. No:27/4 Maltepe",
    "sg:city":"Kad\u0131k\u00f6y",
    "sg:classifiers":[
        {
            "category":"Building & Trades",
            "subcategory":"Plumbing",
            "type":"Services"
        }
    ],
    "sg:phone":"+90 312 231 5197",
    "sg:postcode":"34714",
    "sg:province":"Ankara",
    "wof:name":"Teskon Insaat Tesisat Tic.taahhut Ltd.sti.",
    "wof:placetype":"venue"
},
  "geometry": {"coordinates":[32.8463783264,39.925983429],"type":"Point"}
}