{
  "type": "Feature",
  "properties": {
    "addr:full":"P.k. 98, 35212 Izm. Avcilar Izmir 01350",
    "addr:postcode":"35212;01350",
    "addr:street":"P.K. 98",
    "iso:country":"TR",
    "sg:address":"P.k. 98, 35212 Izm.",
    "sg:city":"Avcilar",
    "sg:classifiers":[
        {
            "category":"Food & Beverages",
            "subcategory":"Meat & Fish",
            "type":"Retail Goods"
        }
    ],
    "sg:phone":"+90 232 421 7644",
    "sg:postcode":"01350",
    "sg:province":"Izmir",
    "sg:tags":[
        "seafood"
    ],
    "wof:name":"Sistemar Akva A.s.",
    "wof:placetype":"venue"
},
  "geometry": {"coordinates":[27.1275043488,38.3968811035],"type":"Point"}
}