{
  "type": "Feature",
  "properties": {
    "iso:country":"TR",
    "sg:address":"Ivedik Org.san.bolg.hasemek San. Sit.22.cad.no:86 667.sok.",
    "sg:city":"Ostim",
    "sg:classifiers":[
        {
            "category":"Home & Garden",
            "subcategory":"Building Materials",
            "type":"Retail Goods"
        }
    ],
    "sg:phone":"+90 312 395 6325",
    "sg:postcode":"06374",
    "sg:province":"Ankara",
    "sg:tags":[
        "insulation"
    ],
    "wof:name":"Atlantik Insaat",
    "wof:placetype":"venue"
},
  "geometry": {"coordinates":[32.8604812622,39.9429283142],"type":"Point"}
}