{
  "type": "Feature",
  "properties": {
    "addr:full":"Ikitelli Organize Sanayi B?gesi Galvano Teknik Sanayi Sitesi A Blok No:77 Ikitelli/K\u00fc\u00e7\u00fck\u00e7ekmece Istanbul 34660",
    "addr:housenumber":"?;blok no 77",
    "addr:postcode":"34660",
    "addr:street":"Organize Sanayi B",
    "iso:country":"TR",
    "sg:address":"Ikitelli Organize Sanayi B?gesi Galvano Teknik Sanayi Sitesi A Blok No:77",
    "sg:city":"Ikitelli/K\u00fc\u00e7\u00fck\u00e7ekmece",
    "sg:classifiers":[
        {
            "category":"Wholesale",
            "subcategory":"Metals & Minerals",
            "type":"Manufacturing & Wholesale Goods"
        }
    ],
    "sg:phone":"+90 212 549 4430",
    "sg:postcode":"34660",
    "sg:province":"Istanbul",
    "sg:tags":[
        "coating"
    ],
    "wof:name":"Ay?i?ek Eloksal",
    "wof:placetype":"venue"
},
  "geometry": {"coordinates":[29.0496292114,41.0075798035],"type":"Point"}
}