{
  "type": "Feature",
  "properties": {
    "addr:full":"Adnan Menderes Bulvari Hilicilar K?k?sok. No.11 Fatih Beyoglu Istanbul 46810",
    "addr:housenumber":"hilicilar k ? k ?;no.11",
    "addr:postcode":"46810",
    "addr:street":"Adnan Menderes Bulvari;Sok.",
    "iso:country":"TR",
    "sg:address":"Adnan Menderes Bulvari Hilicilar K?k?sok. No.11 Fatih",
    "sg:city":"Beyoglu",
    "sg:classifiers":[
        {
            "category":"Building & Trades",
            "subcategory":"Construction",
            "type":"Services"
        }
    ],
    "sg:phone":"+90 212 631 1522",
    "sg:postcode":"46810",
    "sg:province":"Istanbul",
    "sg:tags":[
        "foundation"
    ],
    "wof:name":"Saglik Vakfi",
    "wof:placetype":"venue"
},
  "geometry": {"coordinates":[28.9759254456,41.0123786926],"type":"Point"}
}