{
  "type": "Feature",
  "properties": {
    "addr:full":"Yenidogan Mah.numunebag Cad.no:106/b Bayrampasa Istanbul 36100",
    "addr:housenumber":"106 / b",
    "addr:postcode":"36100",
    "iso:country":"TR",
    "sg:address":"Yenidogan Mah.numunebag Cad.no:106/b",
    "sg:city":"Bayrampasa",
    "sg:classifiers":[
        {
            "category":"Structure",
            "subcategory":"Office Building",
            "type":"Public Place"
        }
    ],
    "sg:phone":"+90 212 674 9454",
    "sg:postcode":"36100",
    "sg:province":"Istanbul",
    "sg:tags":[
        "satellite",
        "system"
    ],
    "wof:name":"Master Elektronik",
    "wof:placetype":"venue"
},
  "geometry": {"coordinates":[28.975925,41.012379],"type":"Point"}
}