{
  "type": "Feature",
  "properties": {
    "addr:full":"Kazanci Yokusu No:42 Taksim Bosatnci Istanbul",
    "addr:street":"No",
    "iso:country":"TR",
    "sg:address":"Kazanci Yokusu No:42 Taksim",
    "sg:city":"Bosatnci",
    "sg:classifiers":[
        {
            "category":"Retail",
            "subcategory":"Laundry & Dry Cleaning",
            "type":"Services"
        }
    ],
    "sg:phone":"+90 212 249 7333",
    "sg:province":"Istanbul",
    "wof:name":"Barbaros Kuru Temiz.",
    "wof:placetype":"venue"
},
  "geometry": {"coordinates":[28.9864387512,41.0343742371],"type":"Point"}
}