{
  "type": "Feature",
  "properties": {
    "addr:full":"Selmanaga Mah. Seyh Yokusu Sok. Birlik Apt.no:10 D:1 Uskudar Istanbul 34672",
    "addr:housenumber":"birlik;10;1",
    "addr:postcode":"34672",
    "addr:street":"Selmanaga Mah. Seyh Yokusu Sok.;D",
    "iso:country":"TR",
    "sg:address":"Selmanaga Mah. Seyh Yokusu Sok. Birlik Apt.no:10 D:1",
    "sg:city":"Uskudar",
    "sg:classifiers":[
        {
            "category":"Professional",
            "subcategory":"Engineering",
            "type":"Services"
        }
    ],
    "sg:phone":"+90 216 334 8926",
    "sg:postcode":"34672",
    "sg:province":"Istanbul",
    "sg:tags":[
        "architect"
    ],
    "wof:name":"Bilkart Elektronik Tesisat Muh.hizm.san.tic.ltd.sti.",
    "wof:placetype":"venue"
},
  "geometry": {"coordinates":[28.9861831665,41.0408554077],"type":"Point"}
}