{
  "type": "Feature",
  "properties": {
    "addr:full":"Yogurt Paz.ozyurt Ish.k:1 No:1/2 Beyoglu I?el 80030",
    "addr:housenumber":"1;2;?",
    "addr:postcode":"80030",
    "addr:street":"Ish.K;No 1 /;Beyoglu I;El",
    "iso:country":"TR",
    "sg:address":"Yogurt Paz.ozyurt Ish.k:1 No:1/2",
    "sg:city":"Beyoglu",
    "sg:classifiers":[
        {
            "category":"Food & Beverages",
            "subcategory":"Fruits & Vegetables",
            "type":"Retail Goods"
        }
    ],
    "sg:phone":"+90 324 232 2715",
    "sg:postcode":"80030",
    "sg:province":"I?el",
    "sg:tags":[
        "fresh"
    ],
    "wof:name":"Anka Tic.ltd.",
    "wof:placetype":"venue"
},
  "geometry": {"coordinates":[28.9674797058,41.0096588135],"type":"Point"}
}