{
  "type": "Feature",
  "properties": {
    "addr:full":"Ataturk Bulvari No: 105/403 Kizilay Sisli Ankara 34380",
    "addr:housenumber":"no;/ 403",
    "addr:postcode":"34380",
    "addr:street":"Ataturk Bulvari;Kizilay Sisli",
    "iso:country":"TR",
    "sg:address":"Ataturk Bulvari No: 105/403 Kizilay",
    "sg:city":"Sisli",
    "sg:orig_category":"Translation Servies",
    "sg:phone":"+90 312 418 8728",
    "sg:postcode":"34380",
    "sg:province":"Ankara",
    "wof:name":"Arda Tercume Bilgisayar Ltd.sti.",
    "wof:placetype":"venue"
},
  "geometry": {"coordinates":[32.8604812622,39.9429283142],"type":"Point"}
}