{
  "type": "Feature",
  "properties": {
    "iso:country":"TR",
    "sg:address":"Aksemsettin Cad.no:1",
    "sg:city":"Kad\u0131k\u00f6y",
    "sg:classifiers":[
        {
            "category":"Shopping",
            "subcategory":"Crafts & Fabrics",
            "type":"Retail Goods"
        }
    ],
    "sg:phone":"+90 216 461 0132",
    "sg:postcode":"34990",
    "sg:province":"Istanbul",
    "sg:tags":[
        "knitting"
    ],
    "wof:name":"Nobel Group",
    "wof:placetype":"venue"
},
  "geometry": {"coordinates":[29.2380027771,40.9736938477],"type":"Point"}
}