{
  "type": "Feature",
  "properties": {
    "iso:country":"TR",
    "sg:address":"Gaziantep",
    "sg:city":"Karabaglar",
    "sg:classifiers":[
        {
            "category":"Government",
            "subcategory":"Office",
            "type":"Public Place"
        }
    ],
    "sg:phone":"+90 342 571 3050",
    "sg:postcode":"44210",
    "sg:province":"Gaziantep",
    "sg:tags":[
        "army"
    ],
    "wof:name":"Oguzeli Askerlik Subesi",
    "wof:placetype":"venue"
},
  "geometry": {"coordinates":[37.4416732788,36.9459457397],"type":"Point"}
}