{
  "type": "Feature",
  "properties": {
    "addr:full":"K.karabekir Mah. Mandira Cad. Elmalikent B2 Blok D:1 Umraniye Gaziosmanpasa Istanbul 06700",
    "addr:housenumber":"elmalikent b2;1",
    "addr:postcode":"06700",
    "addr:street":"K.Karabekir Mah. Mandira Cad.;Blok D",
    "iso:country":"TR",
    "sg:address":"K.karabekir Mah. Mandira Cad. Elmalikent B2 Blok D:1 Umraniye",
    "sg:city":"Gaziosmanpasa",
    "sg:classifiers":[
        {
            "category":"Wholesale",
            "subcategory":"Medical Equipment & Supplies",
            "type":"Manufacturing & Wholesale Goods"
        }
    ],
    "sg:phone":"+90 216 329 0691",
    "sg:postcode":"06700",
    "sg:province":"Istanbul",
    "wof:name":"Pakartek Ltd.sti.",
    "wof:placetype":"venue"
},
  "geometry": {"coordinates":[28.9861831665,41.0408554077],"type":"Point"}
}