{
  "type": "Feature",
  "properties": {
    "iso:country":"TR",
    "sg:address":"302. Sk. No:31 2. San. Site.",
    "sg:city":"Top?lar",
    "sg:classifiers":[
        {
            "category":"Manufacturing",
            "subcategory":"Metals",
            "type":"Manufacturing & Wholesale Goods"
        }
    ],
    "sg:phone":"+90 232 435 7512",
    "sg:postcode":"34056",
    "sg:province":"Izmir",
    "sg:tags":[
        "iron-steel",
        "peoducts"
    ],
    "wof:name":"Asil Demir Tic. Ltd. Sti.",
    "wof:placetype":"venue"
},
  "geometry": {"coordinates":[27.1296863556,38.4186973572],"type":"Point"}
}