{
  "type": "Feature",
  "properties": {
    "addr:full":"Ostim San. Sit. 40. Sk. 25 Ostim B\u00fcy\u00fck\u00e7ekmece Ankara 34900",
    "addr:housenumber":"40",
    "addr:postcode":"34900",
    "addr:street":"Sk. 25 Ostim Bueyuekc\u0327Ekmece",
    "iso:country":"TR",
    "sg:address":"Ostim San. Sit. 40. Sk. 25 Ostim",
    "sg:city":"B\u00fcy\u00fck\u00e7ekmece",
    "sg:orig_category":"Aluminium Carpentary",
    "sg:phone":"+90 312 354 3999",
    "sg:postcode":"34900",
    "sg:province":"Ankara",
    "wof:name":"Ankara Aluminyum San. A.s.",
    "wof:placetype":"venue"
},
  "geometry": {"coordinates":[32.8560333252,39.9438743591],"type":"Point"}
}