{
  "type": "Feature",
  "properties": {
    "addr:full":"Millet Cad. Karag? Ism. A Blok No:183. F.zade Nazilli Istanbul 65600",
    "addr:housenumber":"?;blok no 183",
    "addr:postcode":"65600",
    "addr:street":"Millet Cad. Karag;A;F.Zade Nazilli",
    "iso:country":"TR",
    "sg:address":"Millet Cad. Karag? Ism. A Blok No:183. F.zade",
    "sg:city":"Nazilli",
    "sg:classifiers":[
        {
            "category":"Wholesale",
            "subcategory":"Medical Equipment & Supplies",
            "type":"Manufacturing & Wholesale Goods"
        }
    ],
    "sg:phone":"+90 212 631 9848",
    "sg:postcode":"65600",
    "sg:province":"Istanbul",
    "wof:name":"Olmez Tip Tibbi Mlz.",
    "wof:placetype":"venue"
},
  "geometry": {"coordinates":[28.9861831665,41.0408554077],"type":"Point"}
}