{
  "type": "Feature",
  "properties": {
    "addr:full":"Oguzhan Cad 5/b Etiler Denizli 07010",
    "addr:housenumber":"5 / b",
    "addr:postcode":"07010",
    "addr:street":"Oguzhan Cad;Etiler",
    "iso:country":"TR",
    "sg:address":"Oguzhan Cad 5/b",
    "sg:city":"Etiler",
    "sg:classifiers":[
        {
            "category":"Banks & Credit Unions",
            "subcategory":"Bank",
            "type":"Services"
        }
    ],
    "sg:phone":"+90 258 241 2300",
    "sg:postcode":"07010",
    "sg:province":"Denizli",
    "wof:name":"Kentbank As",
    "wof:placetype":"venue"
},
  "geometry": {"coordinates":[29.113979,37.734531],"type":"Point"}
}