{
  "type": "Feature",
  "properties": {
    "addr:full":"Yesil Mah. 247- Sk. No:9 Nazili Mersin Aydin 52750",
    "addr:housenumber":"247",
    "addr:postcode":"52750",
    "addr:street":"Yesil Mah.;Sk. No 9 Nazili",
    "iso:country":"TR",
    "sg:address":"Yesil Mah. 247- Sk. No:9 Nazili",
    "sg:city":"Mersin",
    "sg:classifiers":[
        {
            "category":"Professional",
            "subcategory":"Business Services",
            "type":"Services"
        }
    ],
    "sg:phone":"+90 256 214 2666",
    "sg:postcode":"52750",
    "sg:province":"Aydin",
    "sg:tags":[
        "food",
        "product",
        "exporter",
        "aricultural"
    ],
    "wof:name":"Basak Italat Ve Ihracat",
    "wof:placetype":"venue"
},
  "geometry": {"coordinates":[28.4863967896,37.8117027283],"type":"Point"}
}