{
  "type": "Feature",
  "properties": {
    "iso:country":"TR",
    "sg:address":"Canip Erbey",
    "sg:city":"Nil?er",
    "sg:classifiers":[
        {
            "category":"Government",
            "subcategory":"Office",
            "type":"Public Place"
        }
    ],
    "sg:phone":"+90 224 493 2006",
    "sg:province":"Bursa",
    "sg:tags":[
        "municipality"
    ],
    "wof:name":"Kayapa Belediye Baskani",
    "wof:placetype":"venue"
},
  "geometry": {"coordinates":[29.0580043793,40.1947555542],"type":"Point"}
}