{
  "type": "Feature",
  "properties": {
    "iso:country":"TR",
    "sg:address":"Feneryolu Bagdat Cad., No.128/1 Kadikoy",
    "sg:city":"Ostim",
    "sg:classifiers":[
        {
            "category":"Banks & Credit Unions",
            "subcategory":"Financial Services",
            "type":"Services"
        }
    ],
    "sg:phone":"+90 216 348 1654",
    "sg:postcode":"06370",
    "sg:province":"Istanbul",
    "sg:tags":[
        "finance"
    ],
    "wof:name":"Menka Yatirim Menkul Kiymetler",
    "wof:placetype":"venue"
},
  "geometry": {"coordinates":[29.068983078,40.9665565491],"type":"Point"}
}