{
  "type": "Feature",
  "properties": {
    "iso:country":"TR",
    "sg:address":"Vatan Mh. Cumhuriyet Cd. No: 5 Bayrampasa",
    "sg:city":"\u00dcmraniye",
    "sg:classifiers":[
        {
            "category":"Farming",
            "subcategory":"Fish & Marine Products",
            "type":"Manufacturing & Wholesale Goods"
        }
    ],
    "sg:phone":"+90 212 501 8501",
    "sg:province":"Istanbul",
    "sg:tags":[
        "automotive"
    ],
    "wof:name":"Erciyes Madeni Yaglar San. Ve Tic. Ltd.",
    "wof:placetype":"venue"
},
  "geometry": {"coordinates":[28.9050865173,41.0299224854],"type":"Point"}
}