{
  "type": "Feature",
  "properties": {
    "addr:full":"Organize Sanayi Bolg. Karak?y-beyoglu Manisa",
    "addr:housenumber":"?",
    "addr:street":"Organize Sanayi Bolg.;Y-Beyoglu Manisa",
    "iso:country":"TR",
    "sg:address":"Organize Sanayi Bolg.",
    "sg:city":"Karak?y-beyoglu",
    "sg:classifiers":[
        {
            "category":"Manufacturing",
            "subcategory":"Metals",
            "type":"Manufacturing & Wholesale Goods"
        }
    ],
    "sg:phone":"+90 236 233 1290",
    "sg:province":"Manisa",
    "sg:tags":[
        "iron-steel",
        "peoducts"
    ],
    "wof:name":"Manisa Dokum Sanayi",
    "wof:placetype":"venue"
},
  "geometry": {"coordinates":[27.4297008514,38.6222000122],"type":"Point"}
}