{
  "type": "Feature",
  "properties": {
    "addr:full":"Ankara Devlet Yolu 15. Km. Iscehisar Afyon 03750",
    "addr:housenumber":"15 km.",
    "addr:postcode":"03750",
    "addr:street":"Devlet Yolu;Iscehisar Afyon",
    "iso:country":"TR",
    "sg:address":"Ankara Devlet Yolu 15. Km.",
    "sg:city":"Iscehisar",
    "sg:classifiers":[
        {
            "category":"Home & Garden",
            "subcategory":"Building Materials",
            "type":"Retail Goods"
        }
    ],
    "sg:phone":"+90 272 213 2249",
    "sg:postcode":"03750",
    "sg:province":"Afyon",
    "sg:tags":[
        "stone",
        "natural",
        "marble"
    ],
    "wof:name":"Genmersan Mermer San. A.s.",
    "wof:placetype":"venue"
},
  "geometry": {"coordinates":[30.5382652283,38.7579841614],"type":"Point"}
}