{
  "type": "Feature",
  "properties": {
    "iso:country":"TR",
    "sg:address":"Belediye Pasaji No:10 Dursunbey",
    "sg:city":"Sapanca",
    "sg:classifiers":[
        {
            "category":"Manufacturing",
            "subcategory":"Wood Products",
            "type":"Manufacturing & Wholesale Goods"
        }
    ],
    "sg:phone":"+90 266 662 1350",
    "sg:postcode":"54600",
    "sg:province":"Balikesir",
    "sg:tags":[
        "forest"
    ],
    "wof:name":"Y?r?kler Orman ?r?n. San. Koll. Sti.",
    "wof:placetype":"venue"
},
  "geometry": {"coordinates":[27.8833007812,39.6520996094],"type":"Point"}
}