{
  "type": "Feature",
  "properties": {
    "addr:full":"Izmir Asf. ?z. 7. Km. \u00c7ankaya Denizli",
    "addr:housenumber":"7 km.",
    "addr:street":"Z.;C\u0327Ankaya Denizli",
    "iso:country":"TR",
    "sg:address":"Izmir Asf. ?z. 7. Km.",
    "sg:city":"\u00c7ankaya",
    "sg:classifiers":[
        {
            "category":"Shopping",
            "subcategory":"Crafts & Fabrics",
            "type":"Retail Goods"
        }
    ],
    "sg:phone":"+90 258 371 2060",
    "sg:province":"Denizli",
    "sg:tags":[
        "yarn"
    ],
    "wof:name":"Eke Teks. San. Tic. A.s.",
    "wof:placetype":"venue"
},
  "geometry": {"coordinates":[29.0864906311,37.773525238],"type":"Point"}
}