{
  "type": "Feature",
  "properties": {
    "addr:full":"Merkez: Bostanci Yolu No51/1 Birlik Ismerkezi Y.dudullu/ist. \u00dcmraniye Istanbul",
    "addr:housenumber":"no51 / 1",
    "addr:street":"Bostanci Yolu;Birlik Ismerkezi",
    "iso:country":"TR",
    "sg:address":"Merkez: Bostanci Yolu No51/1 Birlik Ismerkezi Y.dudullu/ist.",
    "sg:city":"\u00dcmraniye",
    "sg:classifiers":[
        {
            "category":"Organizations",
            "subcategory":"Non-profit Organization",
            "type":"Services"
        }
    ],
    "sg:phone":"+90 21652794314428",
    "sg:province":"Istanbul",
    "sg:tags":[
        "alarm",
        "system"
    ],
    "wof:name":"?zg?r G?nelik Otomasyon Ve Kontrol Sistemleri",
    "wof:placetype":"venue"
},
  "geometry": {"coordinates":[28.8206958771,40.9819564819],"type":"Point"}
}