{
  "type": "Feature",
  "properties": {
    "addr:full":"Turgut Ozal Bulv. No: 188 Iskenderun Batman 31200",
    "addr:housenumber":"no",
    "addr:postcode":"31200",
    "addr:street":"Turgut Ozal Bulv.",
    "iso:country":"TR",
    "sg:address":"Turgut Ozal Bulv. No: 188",
    "sg:city":"Iskenderun",
    "sg:classifiers":[
        {
            "category":"Wholesale",
            "subcategory":"Petroleum",
            "type":"Manufacturing & Wholesale Goods"
        }
    ],
    "sg:phone":"+90 488 213 1030",
    "sg:postcode":"31200",
    "sg:province":"Batman",
    "wof:name":"Boran Petrol",
    "wof:placetype":"venue"
},
  "geometry": {"coordinates":[41.1307029724,37.897567749],"type":"Point"}
}