{
  "type": "Feature",
  "properties": {
    "iso:country":"TR",
    "sg:address":"Muhtar Kamil Sk. No.5/3 Taksim",
    "sg:city":"Sisli",
    "sg:classifiers":[
        {
            "category":"Professional",
            "subcategory":"Detective & Security Services",
            "type":"Services"
        }
    ],
    "sg:phone":"+90 212 245 2702",
    "sg:postcode":"80220",
    "sg:province":"Istanbul",
    "sg:tags":[
        "material"
    ],
    "wof:name":"A.l.s. Guvenlik Sistemleri San. Tic.ltd.sti.",
    "wof:placetype":"venue"
},
  "geometry": {"coordinates":[28.986195,41.035854],"type":"Point"}
}