{
  "type": "Feature",
  "properties": {
    "iso:country":"TR",
    "sg:address":"Halkapinar Kaymakamligi",
    "sg:city":"\u00c7ankaya",
    "sg:classifiers":[
        {
            "category":"Professional",
            "subcategory":"Computer Services",
            "type":"Services"
        }
    ],
    "sg:phone":"+90 332 771 2313",
    "sg:postcode":"06450",
    "sg:province":"Konya",
    "sg:tags":[
        "application",
        "software"
    ],
    "wof:name":"Rem Yazilim",
    "wof:placetype":"venue"
},
  "geometry": {"coordinates":[33.0667152405,39.2111282349],"type":"Point"}
}