{
  "type": "Feature",
  "properties": {
    "addr:full":"Izzet Dede Mustafa Kemal Pasa Bursa 57500",
    "addr:postcode":"57500",
    "addr:street":"Izzet;Mustafa Kemal Pasa",
    "iso:country":"TR",
    "sg:address":"Izzet Dede",
    "sg:city":"Mustafa Kemal Pasa",
    "sg:classifiers":[
        {
            "category":"Government",
            "subcategory":"Office",
            "type":"Public Place"
        }
    ],
    "sg:phone":"+90 224 642 7248",
    "sg:postcode":"57500",
    "sg:province":"Bursa",
    "sg:tags":[
        "municipality"
    ],
    "wof:name":"?eltik? Belediye Baskani",
    "wof:placetype":"venue"
},
  "geometry": {"coordinates":[30.0355377197,39.9131240845],"type":"Point"}
}