{
  "type": "Feature",
  "properties": {
    "iso:country":"TR",
    "sg:address":"169.sok.no:8/z 03 Menas Sitesi",
    "sg:city":"Isikkent",
    "sg:classifiers":[
        {
            "category":"Professional",
            "type":"Services"
        }
    ],
    "sg:phone":"+90 232 472 2186",
    "sg:postcode":"32100",
    "sg:province":"Izmir",
    "sg:tags":[
        "catering"
    ],
    "wof:name":"Pina Tabldot Yemek San.ltd.sti.",
    "wof:placetype":"venue"
},
  "geometry": {"coordinates":[27.1423015594,38.4251480103],"type":"Point"}
}