{
  "type": "Feature",
  "properties": {
    "addr:full":"Cemil Topuzlu Cad. Korupalas Apt. No:105/5 Caddebostan- Kadikoy Istanbul 01370",
    "addr:housenumber":"105 / 5",
    "addr:postcode":"01370",
    "addr:street":"Topuzlu Cad. Korupalas Apt. No;Caddebostan Kadikoy",
    "iso:country":"TR",
    "sg:address":"Cemil Topuzlu Cad. Korupalas Apt. No:105/5 Caddebostan-",
    "sg:city":"Kadikoy",
    "sg:classifiers":[
        {
            "category":"Home & Garden",
            "subcategory":"Household Appliances",
            "type":"Retail Goods"
        }
    ],
    "sg:phone":"+90 216 363 2410",
    "sg:postcode":"01370",
    "sg:province":"Istanbul",
    "sg:tags":[
        "conditioner",
        "air"
    ],
    "wof:name":"Elit Muhendislik Ltd.sti.",
    "wof:placetype":"venue"
},
  "geometry": {"coordinates":[28.9759254456,41.0123786926],"type":"Point"}
}