{
  "type": "Feature",
  "properties": {
    "addr:full":"Kodaman Sk. No:128/6 Osmanbey Istanbul 63000",
    "addr:housenumber":"128 / 6",
    "addr:postcode":"63000",
    "addr:street":"Kodaman Sk. No",
    "iso:country":"TR",
    "sg:address":"Kodaman Sk. No:128/6",
    "sg:city":"Osmanbey",
    "sg:classifiers":[
        {
            "category":"Shopping",
            "subcategory":"Clothing, Apparel, & Fashions",
            "type":"Retail Goods"
        }
    ],
    "sg:phone":"+90 212 234 1172",
    "sg:postcode":"63000",
    "sg:province":"Istanbul",
    "sg:tags":[
        "woman",
        "wear"
    ],
    "wof:name":"Kilerci Giyim San. Tic. Ltd. Sti.",
    "wof:placetype":"venue"
},
  "geometry": {"coordinates":[28.9889469147,41.0556373596],"type":"Point"}
}