{
  "type": "Feature",
  "properties": {
    "iso:country":"TR",
    "sg:address":"Gazeteciler Sitesi Matbuat Sok. No:3 Esentepe 80670",
    "sg:city":"Sihhiye",
    "sg:classifiers":[
        {
            "category":"Shopping",
            "subcategory":"Pharmacy",
            "type":"Retail Goods"
        }
    ],
    "sg:phone":"+90 212 213 3280",
    "sg:postcode":"06410",
    "sg:province":"Istanbul",
    "sg:tags":[
        "store",
        "drug"
    ],
    "wof:name":"Boehringer Ingelheim Ila? Tic. A.s.",
    "wof:placetype":"venue"
},
  "geometry": {"coordinates":[28.9861831665,41.0408554077],"type":"Point"}
}