{
  "type": "Feature",
  "properties": {
    "iso:country":"TR",
    "sg:address":"Gemdak San. Sit. No:11 Tuzla",
    "sg:city":"1.sanayi Sitesi",
    "sg:classifiers":[
        {
            "category":"Wholesale",
            "subcategory":"Vending Machines",
            "type":"Manufacturing & Wholesale Goods"
        }
    ],
    "sg:phone":"+90 216 392 6071",
    "sg:postcode":"35110",
    "sg:province":"Istanbul",
    "sg:tags":[
        "rod",
        "welding"
    ],
    "wof:name":"Gesan Kaynak Mak. Ekipman. San.",
    "wof:placetype":"venue"
},
  "geometry": {"coordinates":[28.9759254456,41.0123786926],"type":"Point"}
}