{
  "type": "Feature",
  "properties": {
    "iso:country":"TR",
    "sg:address":"Yenimahalle Yanikses Sok. No: 15",
    "sg:city":"Bakirkoy",
    "sg:classifiers":[
        {
            "category":"Home & Garden",
            "subcategory":"Household Appliances",
            "type":"Retail Goods"
        }
    ],
    "sg:phone":"+90 212 570 7688",
    "sg:postcode":"35790",
    "sg:province":"Istanbul",
    "sg:tags":[
        "conditioner",
        "air"
    ],
    "wof:name":"Tempo Isitma Ve Klima San Ve Tic Ltd",
    "wof:placetype":"venue"
},
  "geometry": {"coordinates":[32.8585166931,39.9472160339],"type":"Point"}
}