{
  "type": "Feature",
  "properties": {
    "iso:country":"TR",
    "sg:address":"Ayakkabicilar San. Sitesi 115 Sok. No:23 Isikkent-bornova",
    "sg:city":"Isikkent",
    "sg:classifiers":[
        {
            "category":"Shopping",
            "subcategory":"Shoes",
            "type":"Retail Goods"
        }
    ],
    "sg:phone":"+90 232 436 0578",
    "sg:postcode":"35070",
    "sg:province":"Izmir",
    "wof:name":"Kenar Deri Urunleri Dis Tic.san. Ltd.sti.",
    "wof:placetype":"venue"
},
  "geometry": {"coordinates":[27.225721,38.432278],"type":"Point"}
}