{
  "type": "Feature",
  "properties": {
    "addr:full":"Ikitelli Org.san.b?lg. Turgut ?zal Cd. No:102 /14-15 Ikitelli Istanbul 34306",
    "addr:housenumber":"?;no;/ 14-15",
    "addr:postcode":"34306",
    "addr:street":"Turgut;Zal Cd.;Ikitelli Istanbul",
    "iso:country":"TR",
    "sg:address":"Ikitelli Org.san.b?lg. Turgut ?zal Cd. No:102 /14-15",
    "sg:city":"Ikitelli",
    "sg:classifiers":[
        {
            "category":"Shopping",
            "subcategory":"Stationery & Office Supplies",
            "type":"Retail Goods"
        }
    ],
    "sg:phone":"+90 212 671 1530",
    "sg:postcode":"34306",
    "sg:province":"Istanbul",
    "wof:name":"Nedpa Kagit San Ve Dis Tic. A.s.",
    "wof:placetype":"venue"
},
  "geometry": {"coordinates":[28.798496,41.088402],"type":"Point"}
}