{
  "type": "Feature",
  "properties": {
    "addr:full":"Ortabaglar Mah. Adalet Sok. No:14/1 Yildirim Bursa 03300",
    "addr:housenumber":"no 14 / 1",
    "addr:postcode":"03300",
    "addr:street":"Ortabaglar Mah. Adalet Sok.;Bursa",
    "iso:country":"TR",
    "sg:address":"Ortabaglar Mah. Adalet Sok. No:14/1",
    "sg:city":"Yildirim",
    "sg:classifiers":[
        {
            "category":"Travel",
            "subcategory":"Travel Agent",
            "type":"Entertainment"
        }
    ],
    "sg:phone":"+90 224 366 0685",
    "sg:postcode":"03300",
    "sg:province":"Bursa",
    "sg:tags":[
        "agency",
        "tourism"
    ],
    "wof:name":"Selimiye Turizm (bursa Sb.)",
    "wof:placetype":"venue"
},
  "geometry": {"coordinates":[29.0586109161,40.1844291687],"type":"Point"}
}