{
  "type": "Feature",
  "properties": {
    "addr:full":"D.s.i. Alti Kirkpinar Cad. No:20 K.bakkalk? Bursa",
    "addr:housenumber":"20;?",
    "addr:street":"Kirkpinar Cad. No;Bursa",
    "iso:country":"TR",
    "sg:address":"D.s.i. Alti Kirkpinar Cad. No:20",
    "sg:city":"K.bakkalk?",
    "sg:classifiers":[
        {
            "category":"Shopping",
            "subcategory":"Clothing, Apparel, & Fashions",
            "type":"Retail Goods"
        }
    ],
    "sg:phone":"+90 224 360 6972",
    "sg:province":"Bursa",
    "sg:tags":[
        "ready",
        "wear"
    ],
    "wof:name":"Bukmen Tekstil San.tic. Ltd.sti.",
    "wof:placetype":"venue"
},
  "geometry": {"coordinates":[29.5096263885,40.7007904053],"type":"Point"}
}