{
  "type": "Feature",
  "properties": {
    "iso:country":"TR",
    "sg:address":"Gunesli Merkez Mah. Deve Kaldirim Cad. No:3",
    "sg:city":"Bagcilar",
    "sg:classifiers":[
        {
            "category":"Manufacturing",
            "subcategory":"Tools & Machinery",
            "type":"Manufacturing & Wholesale Goods"
        }
    ],
    "sg:phone":"+90 212 550 2994",
    "sg:postcode":"34540",
    "sg:province":"Istanbul",
    "sg:tags":[
        "machine",
        "industry"
    ],
    "wof:name":"K?seler Teknik Kalip Ve Makina Sanayi Ve Ticaret Ltd.sti.",
    "wof:placetype":"venue"
},
  "geometry": {"coordinates":[28.9759254456,41.0123786926],"type":"Point"}
}