{
  "type": "Feature",
  "properties": {
    "iso:country":"TR",
    "sg:address":"Bulten Sok.no:4/ 4 Kavaklidere",
    "sg:city":"Ke??en",
    "sg:classifiers":[
        {
            "category":"Organizations",
            "subcategory":"Membership Organization",
            "type":"Services"
        }
    ],
    "sg:phone":"+90 312 426 0254",
    "sg:province":"Ankara",
    "wof:name":"Ozel Radyo Ve Televizyon Yayincilari Dernegi",
    "wof:placetype":"venue"
},
  "geometry": {"coordinates":[32.8576202393,39.9128990173],"type":"Point"}
}