{
  "type": "Feature",
  "properties": {
    "iso:country":"TR",
    "sg:address":"Sair Arsi Cad.no:19/21 M.koy.goztepe",
    "sg:city":"Okmeydani",
    "sg:classifiers":[
        {
            "category":"Professional",
            "subcategory":"Detective & Security Services",
            "type":"Services"
        }
    ],
    "sg:phone":"+90 216 302 8702",
    "sg:postcode":"34900",
    "sg:province":"Istanbul",
    "sg:tags":[
        "material"
    ],
    "wof:name":"Kiratli Celik Kasa San.ve Tic. Ltd. Sti.",
    "wof:placetype":"venue"
},
  "geometry": {"coordinates":[28.975925,41.012379],"type":"Point"}
}