{
  "type": "Feature",
  "properties": {
    "addr:full":"Z?k? Emirhanoglu Suluova Diyarbakir 05500",
    "addr:postcode":"05500",
    "addr:street":"Diyarbakir",
    "iso:country":"TR",
    "sg:address":"Z?k? Emirhanoglu",
    "sg:city":"Suluova",
    "sg:classifiers":[
        {
            "category":"Government",
            "subcategory":"Office",
            "type":"Public Place"
        }
    ],
    "sg:phone":"+90 412 611 5021",
    "sg:postcode":"05500",
    "sg:province":"Diyarbakir",
    "sg:tags":[
        "municipality"
    ],
    "wof:name":"Ergani Belediye Baskani",
    "wof:placetype":"venue"
},
  "geometry": {"coordinates":[40.2253341675,37.9158096313],"type":"Point"}
}