{
  "type": "Feature",
  "properties": {
    "iso:country":"TR",
    "sg:address":"Dervisoglu Sopk.",
    "sg:city":"Sirkeci",
    "sg:classifiers":[
        {
            "category":"Banks & Credit Unions",
            "subcategory":"Bank",
            "type":"Services"
        }
    ],
    "sg:phone":"+90 212 512 1059",
    "sg:postcode":"34112",
    "sg:province":"34420",
    "wof:name":"Derbank As",
    "wof:placetype":"venue"
},
  "geometry": {"coordinates":[28.975203,41.015438],"type":"Point"}
}