{
  "type": "Feature",
  "properties": {
    "addr:full":"Istiklal Cad. Suriye Pasaji 348/1 Beyoglu Istanbul 46810",
    "addr:housenumber":"348 / 1",
    "addr:postcode":"46810",
    "addr:street":"Istiklal Cad.;Pasaji",
    "iso:country":"TR",
    "sg:address":"Istiklal Cad. Suriye Pasaji 348/1",
    "sg:city":"Beyoglu",
    "sg:classifiers":[
        {
            "category":"Shopping",
            "subcategory":"Crafts & Fabrics",
            "type":"Retail Goods"
        }
    ],
    "sg:phone":"+90 212 249 1231",
    "sg:postcode":"46810",
    "sg:province":"Istanbul",
    "sg:tags":[
        "weaving"
    ],
    "wof:name":"Sera Kumas",
    "wof:placetype":"venue"
},
  "geometry": {"coordinates":[28.9759254456,41.0123786926],"type":"Point"}
}