{
  "type": "Feature",
  "properties": {
    "addr:full":"Ankara Asfalti 6.km Silivri Ankara 34570",
    "addr:postcode":"34570",
    "iso:country":"TR",
    "sg:address":"Ankara Asfalti 6.km",
    "sg:city":"Silivri",
    "sg:classifiers":[
        {
            "category":"Wholesale",
            "subcategory":"Farm Supplies",
            "type":"Manufacturing & Wholesale Goods"
        }
    ],
    "sg:phone":"+90 312 837 0622",
    "sg:postcode":"34570",
    "sg:province":"Ankara",
    "sg:tags":[
        "feed",
        "industry"
    ],
    "wof:name":"Ankara Ofis Yem Gida Ve Mak.san.a.s.",
    "wof:placetype":"venue"
},
  "geometry": {"coordinates":[32.8560333252,39.9438743591],"type":"Point"}
}