{
  "type": "Feature",
  "properties": {
    "addr:full":"K?? Sanayi Sitesi A Blok No 5 Darica Gebze Kocaeli 41870",
    "addr:housenumber":"? ?;blok no 5",
    "addr:postcode":"41870",
    "addr:street":"Sanayi Sitesi A;Darica",
    "iso:country":"TR",
    "sg:address":"K?? Sanayi Sitesi A Blok No 5 Darica",
    "sg:city":"Gebze",
    "sg:classifiers":[
        {
            "category":"Shopping",
            "subcategory":"Computers & Home Electronics",
            "type":"Retail Goods"
        }
    ],
    "sg:phone":"+90 262 653 2570",
    "sg:postcode":"41870",
    "sg:province":"Kocaeli",
    "sg:tags":[
        "product",
        "electric-electronic"
    ],
    "wof:name":"Panko Pano Ve Kondansator Tesisleri San.tic.a.s.",
    "wof:placetype":"venue"
},
  "geometry": {"coordinates":[29.9345855713,40.7669563293],"type":"Point"}
}