{
  "type": "Feature",
  "properties": {
    "addr:full":"Turgut Ozal Cad. Cevre Sanayi Sitesi 11.blok No.51 Ikitelli Ikitelli7k???k?ekmece Istanbul 34670",
    "addr:housenumber":"11.blok no.51;ikitelli7k ? ? ? k ?",
    "addr:postcode":"34670",
    "addr:street":"Turgut Ozal Cad. Cevre Sanayi Sitesi;Ikitelli",
    "iso:country":"TR",
    "sg:address":"Turgut Ozal Cad. Cevre Sanayi Sitesi 11.blok No.51 Ikitelli",
    "sg:city":"Ikitelli7k???k?ekmece",
    "sg:classifiers":[
        {
            "category":"Building & Trades",
            "subcategory":"Plumbing",
            "type":"Services"
        }
    ],
    "sg:phone":"+90 212 485 5498",
    "sg:postcode":"34670",
    "sg:province":"Istanbul",
    "sg:tags":[
        "gasket"
    ],
    "wof:name":"Yuksel Conta",
    "wof:placetype":"venue"
},
  "geometry": {"coordinates":[28.9759254456,41.0123786926],"type":"Point"}
}