{
  "type": "Feature",
  "properties": {
    "iso:country":"TR",
    "sg:address":"10026 Sk. No:12 B. ?igli",
    "sg:city":"\u00dcmraniye",
    "sg:classifiers":[
        {
            "category":"Home & Garden",
            "subcategory":"Hardware",
            "type":"Retail Goods"
        }
    ],
    "sg:phone":"+90 232 433 0256",
    "sg:postcode":"81360",
    "sg:province":"Izmir",
    "sg:tags":[
        "generator",
        "power"
    ],
    "wof:name":"G?nd?z Trafo Elektrik Makine. Tic. San. Koll. Sti.",
    "wof:placetype":"venue"
},
  "geometry": {"coordinates":[27.1296863556,38.4186973572],"type":"Point"}
}