{
  "type": "Feature",
  "properties": {
    "addr:full":"Atat?k Cd. No: 37/b Polatli Ankara 06900",
    "addr:housenumber":"no 37 / b",
    "addr:postcode":"06900",
    "addr:street":"K Cd.;Polatli Ankara",
    "iso:country":"TR",
    "sg:address":"Atat?k Cd. No: 37/b",
    "sg:city":"Polatli",
    "sg:classifiers":[
        {
            "category":"Farming",
            "subcategory":"Farm",
            "type":"Manufacturing & Wholesale Goods"
        }
    ],
    "sg:phone":"+90 312 237 6314",
    "sg:postcode":"06900",
    "sg:province":"Ankara",
    "sg:tags":[
        "agricultural",
        "product"
    ],
    "wof:name":"Elbir A.s.",
    "wof:placetype":"venue"
},
  "geometry": {"coordinates":[32.8560333252,39.9438743591],"type":"Point"}
}