{
  "type": "Feature",
  "properties": {
    "iso:country":"TR",
    "sg:address":"Namik Kemal Mah.c.topel Cad.cem Sok.no:1 Umraniye",
    "sg:city":"?atalca",
    "sg:classifiers":[
        {
            "category":"Shopping",
            "subcategory":"Stationery & Office Supplies",
            "type":"Retail Goods"
        }
    ],
    "sg:phone":"+90 216 328 1812",
    "sg:province":"Istanbul",
    "wof:name":"Mert Insaat Nakliyat Kirtasiye Gida",
    "wof:placetype":"venue"
},
  "geometry": {"coordinates":[29.106501,41.0303],"type":"Point"}
}