{
  "type": "Feature",
  "properties": {
    "iso:country":"TR",
    "sg:address":"Mehmet Kaynak",
    "sg:city":"Kuyucak",
    "sg:classifiers":[
        {
            "category":"Government",
            "subcategory":"Office",
            "type":"Public Place"
        }
    ],
    "sg:phone":"+90 256 373 5003",
    "sg:postcode":"07655",
    "sg:province":"Aydin",
    "sg:tags":[
        "municipality"
    ],
    "wof:name":"Basaran Belediye Baskani",
    "wof:placetype":"venue"
},
  "geometry": {"coordinates":[27.2573165894,37.8561935425],"type":"Point"}
}