{
  "type": "Feature",
  "properties": {
    "iso:country":"TR",
    "sg:address":"1807 Sok. No : 17/c",
    "sg:city":"Karsiyaka",
    "sg:classifiers":[
        {
            "category":"Organizations",
            "subcategory":"Non-profit Organization",
            "type":"Services"
        }
    ],
    "sg:phone":"+90 232 362 6263",
    "sg:postcode":"35530",
    "sg:province":"Izmir",
    "sg:tags":[
        "alarm",
        "system"
    ],
    "wof:name":"Din?er Elektronik",
    "wof:placetype":"venue"
},
  "geometry": {"coordinates":[27.0971698761,38.4570999146],"type":"Point"}
}