{
  "type": "Feature",
  "properties": {
    "addr:full":"Murat Mh. Tuna Cd. Kolaman Sk. No:14/1 Bayrampasa Ikitelli/K\u00fc\u00e7\u00fck\u00e7ekmece Istanbul 34670",
    "addr:housenumber":"14 / 1",
    "addr:postcode":"34670",
    "addr:street":"Sk. No",
    "iso:country":"TR",
    "sg:address":"Murat Mh. Tuna Cd. Kolaman Sk. No:14/1 Bayrampasa",
    "sg:city":"Ikitelli/K\u00fc\u00e7\u00fck\u00e7ekmece",
    "sg:classifiers":[
        {
            "category":"Manufacturing",
            "subcategory":"Tools & Machinery",
            "type":"Manufacturing & Wholesale Goods"
        }
    ],
    "sg:phone":"+90 212 576 7827",
    "sg:postcode":"34670",
    "sg:province":"Istanbul",
    "sg:tags":[
        "machine",
        "industry"
    ],
    "wof:name":"Enka Klas?r Makina San. Tic. Ltd. Sti.",
    "wof:placetype":"venue"
},
  "geometry": {"coordinates":[28.9759254456,41.0123786926],"type":"Point"}
}