{
  "type": "Feature",
  "properties": {
    "iso:country":"TR",
    "sg:address":"Koprubasi Cad. No:72",
    "sg:city":"Baspinar",
    "sg:classifiers":[
        {
            "category":"Food & Beverages",
            "subcategory":"Candy",
            "type":"Retail Goods"
        }
    ],
    "sg:phone":"+90 222 231 1188",
    "sg:postcode":"07800",
    "sg:province":"Eskisehir",
    "sg:tags":[
        "biscuit-chocolate-candy"
    ],
    "wof:name":"Ermey Meyve Urunleri Gida San. Ve Tic. A.s.",
    "wof:placetype":"venue"
},
  "geometry": {"coordinates":[30.519379,39.774986],"type":"Point"}
}