{
  "type": "Feature",
  "properties": {
    "iso:country":"TR",
    "sg:address":"30 Agustos Cd. No:36/a",
    "sg:city":"Nisantasi",
    "sg:classifiers":[
        {
            "category":"Banks & Credit Unions",
            "subcategory":"Investment Brokerage",
            "type":"Services"
        }
    ],
    "sg:phone":"+90 242 242 8861",
    "sg:postcode":"25370",
    "sg:province":"Antalya",
    "sg:tags":[
        "-",
        "export",
        "import"
    ],
    "wof:name":"Empa Ithalat A.s.",
    "wof:placetype":"venue"
},
  "geometry": {"coordinates":[30.7092056274,36.8790512085],"type":"Point"}
}