{
  "type": "Feature",
  "properties": {
    "addr:full":"Zonguldak Ikitelli/K\u00fc\u00e7\u00fck\u00e7ekmece Zonguldak 34660",
    "addr:postcode":"34660",
    "iso:country":"TR",
    "sg:address":"Zonguldak",
    "sg:city":"Ikitelli/K\u00fc\u00e7\u00fck\u00e7ekmece",
    "sg:classifiers":[
        {
            "category":"Health Services",
            "subcategory":"Hospital",
            "type":"Services"
        }
    ],
    "sg:phone":"+90 372 252 1900",
    "sg:postcode":"34660",
    "sg:province":"Zonguldak",
    "sg:tags":[
        "state"
    ],
    "wof:name":"Ssk Hastanesi",
    "wof:placetype":"venue"
},
  "geometry": {"coordinates":[31.73361,41.320557],"type":"Point"}
}