{
  "type": "Feature",
  "properties": {
    "addr:full":"Ali Samiyen Sok.gun 2 Apt. No:6 D:3 Gayrettepe Istanbul 34349",
    "addr:housenumber":"2;3",
    "addr:postcode":"34349",
    "addr:street":"Sok.Gun;No 6 D",
    "iso:country":"TR",
    "sg:address":"Ali Samiyen Sok.gun 2 Apt. No:6 D:3",
    "sg:city":"Gayrettepe",
    "sg:classifiers":[
        {
            "category":"Government",
            "subcategory":"Post Office",
            "type":"Public Place"
        }
    ],
    "sg:phone":"+90 212347805152",
    "sg:postcode":"34349",
    "sg:province":"Istanbul",
    "sg:tags":[
        "distribution"
    ],
    "wof:name":"Maksimum Iletisim Dagitim Org. Paz.rek.ltd.sti.",
    "wof:placetype":"venue"
},
  "geometry": {"coordinates":[29.0118026733,41.0541763306],"type":"Point"}
}