{
  "type": "Feature",
  "properties": {
    "addr:full":"Cevher Nesibe Mah. Mecidiye Sok.no:10/4 Melikgazi Kayseri 38000",
    "addr:housenumber":"10 / 4",
    "addr:postcode":"38000",
    "addr:street":"Nesibe Mah. Mecidiye Sok.No;Melikgazi",
    "iso:country":"TR",
    "sg:address":"Cevher Nesibe Mah. Mecidiye Sok.no:10/4",
    "sg:city":"Melikgazi",
    "sg:classifiers":[
        {
            "category":"Banks & Credit Unions",
            "subcategory":"Investment Brokerage",
            "type":"Services"
        }
    ],
    "sg:phone":"+90 352 221 3551",
    "sg:postcode":"38000",
    "sg:province":"Kayseri",
    "sg:tags":[
        "-",
        "export",
        "import"
    ],
    "wof:name":"Fmg Foreign Trade",
    "wof:placetype":"venue"
},
  "geometry": {"coordinates":[36.4393234253,38.2791290283],"type":"Point"}
}