{
  "type": "Feature",
  "properties": {
    "addr:full":"Yenidogan Mah.d-100 Karayolu ?zeri Tezcan Apt.no:100/g 41020 Kocaeli",
    "addr:housenumber":"100 / g",
    "addr:postcode":"41020",
    "addr:street":"Karayolu",
    "iso:country":"TR",
    "sg:address":"Yenidogan Mah.d-100 Karayolu ?zeri Tezcan Apt.no:100/g",
    "sg:city":"41020",
    "sg:classifiers":[
        {
            "category":"Manufacturing",
            "subcategory":"Tools & Machinery",
            "type":"Manufacturing & Wholesale Goods"
        }
    ],
    "sg:phone":"+90 262 323 6710",
    "sg:province":"Kocaeli",
    "sg:tags":[
        "machine",
        "industry"
    ],
    "wof:name":"Mrc Akaryakit Ekipmanlari Satis Ve Servis",
    "wof:placetype":"venue"
},
  "geometry": {"coordinates":[29.881521225,40.8532714844],"type":"Point"}
}