{
  "type": "Feature",
  "properties": {
    "addr:full":"1145/8 Sokak No:30/a Yenisehir Dudullu Izmir",
    "addr:housenumber":"1145 /;no 30 / a",
    "addr:street":"8 Sokak;Yenisehir Dudullu",
    "iso:country":"TR",
    "sg:address":"1145/8 Sokak No:30/a Yenisehir",
    "sg:city":"Dudullu",
    "sg:classifiers":[
        {
            "category":"Manufacturing",
            "subcategory":"Tools & Machinery",
            "type":"Manufacturing & Wholesale Goods"
        }
    ],
    "sg:phone":"+90 232 449 0441",
    "sg:province":"Izmir",
    "sg:tags":[
        "machine",
        "industry"
    ],
    "wof:name":"Hedef Makina Taahh?t Ve D?k?m Sanayi Ticaret Limited Sirketi",
    "wof:placetype":"venue"
},
  "geometry": {"coordinates":[27.1689720154,38.4255065918],"type":"Point"}
}