{
  "type": "Feature",
  "properties": {
    "addr:full":"Gmk. Blv. No.166 Tandogan Ankara 44050",
    "addr:postcode":"44050",
    "addr:street":"Blv. No.166 Tandogan",
    "iso:country":"TR",
    "sg:address":"Gmk. Blv. No.166",
    "sg:city":"Tandogan",
    "sg:classifiers":[
        {
            "category":"Manufacturing",
            "subcategory":"Food",
            "type":"Manufacturing & Wholesale Goods"
        }
    ],
    "sg:phone":"+90 312 231 2832",
    "sg:postcode":"44050",
    "sg:province":"Ankara",
    "sg:tags":[
        "wholesaler"
    ],
    "wof:name":"Tandogan Soguk Hava Depo. Gida Ltd. Sti.",
    "wof:placetype":"venue"
},
  "geometry": {"coordinates":[32.681060791,40.2051124573],"type":"Point"}
}