{
  "type": "Feature",
  "properties": {
    "iso:country":"TR",
    "sg:address":"Yunus Emre Sk. No:1/4 4.levent",
    "sg:city":"Bak\u0131rk\u00f6y",
    "sg:orig_category":"Printinh House",
    "sg:phone":"+90 212 281 0390",
    "sg:postcode":"34140",
    "sg:province":"Istanbul",
    "wof:name":"Trend Yayinci. A.s.",
    "wof:placetype":"venue"
},
  "geometry": {"coordinates":[28.9980163574,41.082157135],"type":"Point"}
}