{
  "type": "Feature",
  "properties": {
    "addr:full":"1743. Sk. No:27 Aksoy Mh. Ortak? Adana 80840",
    "addr:housenumber":"27;?",
    "addr:postcode":"aksoy;80840",
    "addr:street":"1743 Sk. No;Mh. Ortak",
    "iso:country":"TR",
    "sg:address":"1743. Sk. No:27 Aksoy Mh.",
    "sg:city":"Ortak?",
    "sg:classifiers":[
        {
            "category":"Organizations",
            "subcategory":"Professional Association",
            "type":"Services"
        }
    ],
    "sg:phone":"+90 322 381 4141",
    "sg:postcode":"80840",
    "sg:province":"Adana",
    "wof:name":"Tmmob Orman M?hendisleri Odasi",
    "wof:placetype":"venue"
},
  "geometry": {"coordinates":[35.3137359619,37.0007171631],"type":"Point"}
}