{
  "type": "Feature",
  "properties": {
    "addr:full":"Birlik San. Sit. 2. Cd. No:41 B.?ekmece Topkapi Istanbul 24620",
    "addr:housenumber":"2;no 41 b. ?",
    "addr:postcode":"24620",
    "addr:street":"Cd.;Ekmece",
    "iso:country":"TR",
    "sg:address":"Birlik San. Sit. 2. Cd. No:41 B.?ekmece",
    "sg:city":"Topkapi",
    "sg:classifiers":[
        {
            "category":"Manufacturing",
            "subcategory":"Rubber & Plastics",
            "type":"Manufacturing & Wholesale Goods"
        }
    ],
    "sg:phone":"+90 212 875 1232",
    "sg:postcode":"24620",
    "sg:province":"Istanbul",
    "sg:tags":[
        "industry"
    ],
    "wof:name":"?zk?se Plastik Kalip Tic. Ltd. Sti.",
    "wof:placetype":"venue"
},
  "geometry": {"coordinates":[28.9759254456,41.0123786926],"type":"Point"}
}