{
  "type": "Feature",
  "properties": {
    "iso:country":"TR",
    "sg:address":"Hasircilar Cad. No:11 Kizilhan Sokak 34460 Eminonu Istanbul",
    "sg:city":"Merkez",
    "sg:classifiers":[
        {
            "category":"Manufacturing",
            "subcategory":"Rubber & Plastics",
            "type":"Manufacturing & Wholesale Goods"
        }
    ],
    "sg:phone":"+90 212 522 3240",
    "sg:postcode":"77200",
    "sg:province":"Istanbul",
    "sg:tags":[
        "packaging",
        "material",
        "-"
    ],
    "wof:name":"Bereket Plastik San Tic As",
    "wof:placetype":"venue"
},
  "geometry": {"coordinates":[28.9691638947,41.0174636841],"type":"Point"}
}