{
  "type": "Feature",
  "properties": {
    "iso:country":"TR",
    "sg:address":"?ankiri Yolu 24 Km Akyurt",
    "sg:city":"07100",
    "sg:classifiers":[
        {
            "category":"Manufacturing",
            "subcategory":"Wood Products",
            "type":"Manufacturing & Wholesale Goods"
        }
    ],
    "sg:phone":"+90 312 844 1395",
    "sg:province":"Ankara",
    "sg:tags":[
        "forest"
    ],
    "wof:name":"Kahramanlar Orman ?r?n. San. Tic. A.s.",
    "wof:placetype":"venue"
},
  "geometry": {"coordinates":[33.0861167908,40.1352233887],"type":"Point"}
}