{
  "type": "Feature",
  "properties": {
    "iso:country":"TR",
    "sg:address":"Neyzen Tevfik Cad. No:48/b",
    "sg:city":"Bodrum",
    "sg:classifiers":[
        {
            "category":"Recreation",
            "subcategory":"Boat Charter",
            "type":"Entertainment"
        }
    ],
    "sg:phone":"+90 25231604433",
    "sg:postcode":"48400",
    "sg:province":"Mugla",
    "sg:tags":[
        "yachting"
    ],
    "wof:name":"Pruva Yachting",
    "wof:placetype":"venue"
},
  "geometry": {"coordinates":[27.4263858795,37.0363769531],"type":"Point"}
}