{
  "type": "Feature",
  "properties": {
    "iso:country":"TR",
    "sg:address":"Merkez Mah. Istanbul Cad. No: 44/ A",
    "sg:city":"Bagcilar",
    "sg:classifiers":[
        {
            "category":"Building & Trades",
            "subcategory":"Landscaping Services",
            "type":"Services"
        }
    ],
    "sg:phone":"+90 212 569 4527",
    "sg:postcode":"33115",
    "sg:province":"Istanbul",
    "sg:tags":[
        "landscape"
    ],
    "wof:name":"Otoyol Insaat Nak. Taah. Tic. Ltd. Sti.",
    "wof:placetype":"venue"
},
  "geometry": {"coordinates":[28.5484008789,41.025970459],"type":"Point"}
}