{
  "type": "Feature",
  "properties": {
    "iso:country":"TR",
    "sg:address":"Uzun?rsi No:53 Mercan",
    "sg:city":"Kesan",
    "sg:classifiers":[
        {
            "category":"Shopping",
            "subcategory":"Bicycles & Sporting Goods",
            "type":"Retail Goods"
        }
    ],
    "sg:phone":"+90 212 526 9690",
    "sg:postcode":"22800",
    "sg:province":"Istanbul",
    "sg:tags":[
        "equipment",
        "marine",
        "hunting"
    ],
    "wof:name":"I?ten Av Silah. San. Ins. Taah. Tic. Ltd. Sti.",
    "wof:placetype":"venue"
},
  "geometry": {"coordinates":[28.9861831665,41.0408554077],"type":"Point"}
}