{
  "type": "Feature",
  "properties": {
    "addr:full":"Hazim Ulusahin Is Merkz. B-blok Kat:3 No:315 Ikitelli/K\u00fc\u00e7\u00fck\u00e7ekmece Konya 34660",
    "addr:housenumber":"kat 3 no 315",
    "addr:postcode":"34660",
    "iso:country":"TR",
    "sg:address":"Hazim Ulusahin Is Merkz. B-blok Kat:3 No:315",
    "sg:city":"Ikitelli/K\u00fc\u00e7\u00fck\u00e7ekmece",
    "sg:classifiers":[
        {
            "category":"Wholesale",
            "subcategory":"Auto Parts",
            "type":"Manufacturing & Wholesale Goods"
        }
    ],
    "sg:phone":"+90 332 238 1435",
    "sg:postcode":"34660",
    "sg:province":"Konya",
    "sg:tags":[
        "spare"
    ],
    "wof:name":"Ksp Ipekyolu Automotive Spare Parts Manufacturers Co.",
    "wof:placetype":"venue"
},
  "geometry": {"coordinates":[33.0667152405,39.2111282349],"type":"Point"}
}