{
  "type": "Feature",
  "properties": {
    "addr:full":"O.nuri Serdenge?ti Cad. G?kdag Apt. No:131/3-4 A Blok Barinaklar Antalya",
    "addr:housenumber":"?;3-4 a blok barinaklar",
    "addr:street":"Ti Cad. G",
    "iso:country":"TR",
    "sg:address":"O.nuri Serdenge?ti Cad. G?kdag Apt. No:131/3-4 A Blok",
    "sg:city":"Barinaklar",
    "sg:classifiers":[
        {
            "category":"Travel",
            "subcategory":"Travel Agent",
            "type":"Entertainment"
        }
    ],
    "sg:phone":"+90 2423238151729",
    "sg:province":"Antalya",
    "sg:tags":[
        "agency",
        "tourism"
    ],
    "wof:name":"Altona Turizm",
    "wof:placetype":"venue"
},
  "geometry": {"coordinates":[30.7091999054,36.8790512085],"type":"Point"}
}