{
  "type": "Feature",
  "properties": {
    "addr:full":"Aanadolu Mah. 13.sok .no: 36 /a Yenibosna Adana 43270",
    "addr:housenumber":"13.sok no 36 / a",
    "addr:postcode":"43270",
    "addr:street":"Aanadolu Mah.;Yenibosna Adana",
    "iso:country":"TR",
    "sg:address":"Aanadolu Mah. 13.sok .no: 36 /a",
    "sg:city":"Yenibosna",
    "sg:classifiers":[
        {
            "category":"Manufacturing",
            "subcategory":"Rubber & Plastics",
            "type":"Manufacturing & Wholesale Goods"
        }
    ],
    "sg:phone":"+90 322 321 5798",
    "sg:postcode":"43270",
    "sg:province":"Adana",
    "sg:tags":[
        "industry"
    ],
    "wof:name":"Bsm Plasti Ltd.sti.",
    "wof:placetype":"venue"
},
  "geometry": {"coordinates":[35.3708839417,36.9744987488],"type":"Point"}
}