{
  "type": "Feature",
  "properties": {
    "iso:country":"TR",
    "sg:address":"Sanayi Mah.sultan Selim Cad. No:161/a",
    "sg:city":"Levent",
    "sg:classifiers":[
        {
            "category":"Manufacturing",
            "subcategory":"Glass & Minerals",
            "type":"Manufacturing & Wholesale Goods"
        }
    ],
    "sg:phone":"+90 212 270 8745",
    "sg:postcode":"01310",
    "sg:province":"Istanbul",
    "sg:tags":[
        "glass-mirror"
    ],
    "wof:name":"Akdeniz Cam Filmleri",
    "wof:placetype":"venue"
},
  "geometry": {"coordinates":[28.993368,41.093098],"type":"Point"}
}