{
  "type": "Feature",
  "properties": {
    "addr:full":"Esat Cad.33/b K.esat Ankara 06660",
    "addr:postcode":"06660",
    "iso:country":"TR",
    "sg:address":"Esat Cad.33/b",
    "sg:city":"K.esat",
    "sg:classifiers":[
        {
            "category":"Government",
            "subcategory":"Fire Station",
            "type":"Public Place"
        }
    ],
    "sg:phone":"+90 312 417 9600",
    "sg:postcode":"06660",
    "sg:province":"Ankara",
    "sg:tags":[
        "decoration"
    ],
    "wof:name":"Polizer Insaat Ltd.sti.",
    "wof:placetype":"venue"
},
  "geometry": {"coordinates":[32.8604812622,39.9429283142],"type":"Point"}
}