{
  "type": "Feature",
  "properties": {
    "iso:country":"TR",
    "sg:address":"Martili Mevkii Aydin 2.sok.",
    "sg:city":"G?eloba",
    "sg:classifiers":[
        {
            "category":"Shopping",
            "subcategory":"Florist",
            "type":"Retail Goods"
        }
    ],
    "sg:phone":"+90 242 321 4623",
    "sg:province":"Antalya",
    "sg:tags":[
        "flower"
    ],
    "wof:name":"Alfa Tarim ?r?nleri Ltd.sti.",
    "wof:placetype":"venue"
},
  "geometry": {"coordinates":[30.7031345367,36.8875045776],"type":"Point"}
}