{
  "type": "Feature",
  "properties": {
    "iso:country":"TR",
    "sg:address":"Eskiosmanli Sok. No:29-2",
    "sg:city":"Mecidiyek\u00f6y",
    "sg:classifiers":[
        {
            "category":"Structure",
            "subcategory":"Office Building",
            "type":"Public Place"
        }
    ],
    "sg:phone":"+90 212 356 6595",
    "sg:postcode":"34387",
    "sg:province":"Istanbul",
    "sg:tags":[
        "satellite",
        "system"
    ],
    "wof:name":"Fidan Elektronik Bilgisayar San.dis.tic.ltd.sti.",
    "wof:placetype":"venue"
},
  "geometry": {"coordinates":[28.995707,41.069057],"type":"Point"}
}