{
  "type": "Feature",
  "properties": {
    "iso:country":"TR",
    "sg:address":"Kisla Cad. Emintas Erciyez Sanayi Sitesi No:56 34160 Ist",
    "sg:city":"Rami",
    "sg:classifiers":[
        {
            "category":"Home & Garden",
            "subcategory":"Home Furnishings",
            "type":"Retail Goods"
        }
    ],
    "sg:phone":"+90 212 501 3804",
    "sg:postcode":"34055",
    "sg:province":"Istanbul",
    "sg:tags":[
        "textile"
    ],
    "wof:name":"Elza Star Tekstil Sanayi Ve Ticaret Ltd.",
    "wof:placetype":"venue"
},
  "geometry": {"coordinates":[28.9861831665,41.0408554077],"type":"Point"}
}