{
  "type": "Feature",
  "properties": {
    "addr:full":"Kocamansur Sk. No:87/89 Sisli Istanbul 65710",
    "addr:housenumber":"87 / 89",
    "addr:postcode":"65710",
    "addr:street":"Kocamansur Sk. No;Istanbul",
    "iso:country":"TR",
    "sg:address":"Kocamansur Sk. No:87/89",
    "sg:city":"Sisli",
    "sg:classifiers":[
        {
            "category":"Transit Center",
            "subcategory":"Freight",
            "type":"Transportation"
        }
    ],
    "sg:phone":"+90 212 232 4120",
    "sg:postcode":"65710",
    "sg:province":"Istanbul",
    "wof:name":"Argos Denizcilik Dis Tic. A.s.",
    "wof:placetype":"venue"
},
  "geometry": {"coordinates":[28.9869747162,41.0631217957],"type":"Point"}
}