{
  "type": "Feature",
  "properties": {
    "iso:country":"TR",
    "sg:address":"Kemeralti Cad. No.87 Tophane",
    "sg:city":"Ikitelli/K\u00fc\u00e7\u00fck\u00e7ekmece",
    "sg:classifiers":[
        {
            "category":"Real Estate",
            "subcategory":"Surveying",
            "type":"Services"
        }
    ],
    "sg:phone":"+90 212 245 4299",
    "sg:postcode":"34670",
    "sg:province":"Istanbul",
    "sg:tags":[
        "adhesive",
        "glue"
    ],
    "wof:name":"Asm End?stri ?r?nleri Ltd.sti.",
    "wof:placetype":"venue"
},
  "geometry": {"coordinates":[28.9818763733,41.025844574],"type":"Point"}
}