{
  "type": "Feature",
  "properties": {
    "addr:full":"Zahire Pazari No:33 Gumusler Denizli 20085",
    "addr:postcode":"20085",
    "addr:street":"Gumusler",
    "iso:country":"TR",
    "sg:address":"Zahire Pazari No:33",
    "sg:city":"Gumusler",
    "sg:classifiers":[
        {
            "category":"Farming",
            "subcategory":"Farm",
            "type":"Manufacturing & Wholesale Goods"
        }
    ],
    "sg:phone":"+90 258 371 6342",
    "sg:postcode":"20085",
    "sg:province":"Denizli",
    "sg:tags":[
        "agricultural",
        "product"
    ],
    "wof:name":"Karakose Tarim Urunleri",
    "wof:placetype":"venue"
},
  "geometry": {"coordinates":[29.0583553314,37.8060188293],"type":"Point"}
}