{
  "type": "Feature",
  "properties": {
    "iso:country":"TR",
    "sg:address":"Yeni Cami Karsisi No:4",
    "sg:city":"Gerede",
    "sg:classifiers":[
        {
            "category":"Travel",
            "subcategory":"Travel Agent",
            "type":"Entertainment"
        }
    ],
    "sg:phone":"+90 374 311 5852",
    "sg:postcode":"14900",
    "sg:province":"Bolu",
    "sg:tags":[
        "agency",
        "tourism"
    ],
    "wof:name":"Kutsalgazi Turizm (gerede Sb.)",
    "wof:placetype":"venue"
},
  "geometry": {"coordinates":[31.5988750458,40.7306365967],"type":"Point"}
}