{
  "type": "Feature",
  "properties": {
    "addr:full":"Cirpici Yedikule Yolu Turkmen Is Merkezi No:13/8 Cevizlibag- Topkapi Istanbul 24620",
    "addr:housenumber":"no 13 / 8",
    "addr:postcode":"24620",
    "addr:street":"Yedikule Yolu;Cevizlibag",
    "iso:country":"TR",
    "sg:address":"Cirpici Yedikule Yolu Turkmen Is Merkezi No:13/8 Cevizlibag-",
    "sg:city":"Topkapi",
    "sg:classifiers":[
        {
            "category":"Shopping",
            "subcategory":"Clothing, Apparel, & Fashions",
            "type":"Retail Goods"
        }
    ],
    "sg:phone":"+90 212 482 1945",
    "sg:postcode":"24620",
    "sg:province":"Istanbul",
    "sg:tags":[
        "manikin"
    ],
    "wof:name":"Simge Manken",
    "wof:placetype":"venue"
},
  "geometry": {"coordinates":[28.9861831665,41.0408554077],"type":"Point"}
}