{
  "type": "Feature",
  "properties": {
    "iso:country":"TR",
    "sg:address":"Kurtulus Cad.no:81/c Bornova 35040",
    "sg:city":"Sirinevler",
    "sg:classifiers":[
        {
            "category":"Manufacturing",
            "subcategory":"Building Materials",
            "type":"Manufacturing & Wholesale Goods"
        }
    ],
    "sg:phone":"+90 232 339 3887",
    "sg:postcode":"15040",
    "sg:province":"Izmir",
    "sg:tags":[
        "lifts-elevators"
    ],
    "wof:name":"Oz Ucler Asansorleri San.ve Tic.ltd.sti",
    "wof:placetype":"venue"
},
  "geometry": {"coordinates":[27.2059497833,38.461025238],"type":"Point"}
}