{
  "type": "Feature",
  "properties": {
    "iso:country":"TR",
    "sg:address":"Icadiye Mah.hasaci Raif Sk.no:24",
    "sg:city":"\u00dcsk\u00fcdar",
    "sg:classifiers":[
        {
            "category":"Shopping",
            "subcategory":"Baby Store",
            "type":"Retail Goods"
        }
    ],
    "sg:phone":"+90 216 461 5786",
    "sg:postcode":"34672",
    "sg:province":"Istanbul",
    "sg:tags":[
        "wear"
    ],
    "wof:name":"Cemka Tekstil Ltd.",
    "wof:placetype":"venue"
},
  "geometry": {"coordinates":[29.036102,41.026825],"type":"Point"}
}