{
  "type": "Feature",
  "properties": {
    "addr:full":"Buyukdere Cad. Ejder Apt. No.63/10 Mecidiyekoy Sisli Istanbul 80650",
    "addr:housenumber":"10",
    "addr:postcode":"80650",
    "addr:street":"Buyukdere Cad. Ejder Apt. No.63 /",
    "iso:country":"TR",
    "sg:address":"Buyukdere Cad. Ejder Apt. No.63/10 Mecidiyekoy",
    "sg:city":"Sisli",
    "sg:classifiers":[
        {
            "category":"Government",
            "subcategory":"Office",
            "type":"Public Place"
        }
    ],
    "sg:phone":"+90 212 356 6232",
    "sg:postcode":"80650",
    "sg:province":"Istanbul",
    "sg:tags":[
        "patent",
        "mark"
    ],
    "wof:name":"Marmara Patent Office",
    "wof:placetype":"venue"
},
  "geometry": {"coordinates":[28.9861831665,41.0408554077],"type":"Point"}
}