{
  "type": "Feature",
  "properties": {
    "iso:country":"TR",
    "sg:address":"Cumhuriyet Bulvari No:95/601",
    "sg:city":"Alsancak",
    "sg:classifiers":[
        {
            "category":"Building & Trades",
            "subcategory":"Landscaping Services",
            "type":"Services"
        }
    ],
    "sg:phone":"+90 232 257 5759",
    "sg:postcode":"01365",
    "sg:province":"Izmir",
    "sg:tags":[
        "landscape"
    ],
    "wof:name":"Oncu Ltd.sti.",
    "wof:placetype":"venue"
},
  "geometry": {"coordinates":[27.1349411011,38.4293060303],"type":"Point"}
}