{
  "type": "Feature",
  "properties": {
    "iso:country":"TR",
    "sg:address":".zuhuratbaba Cd. No:8/c Bakirk?",
    "sg:city":"Kad\u0131k\u00f6y",
    "sg:classifiers":[
        {
            "category":"Home & Garden",
            "subcategory":"Kitchen Supply",
            "type":"Retail Goods"
        }
    ],
    "sg:phone":"+90 212 572 9757",
    "sg:postcode":"34990",
    "sg:province":"Istanbul",
    "sg:tags":[
        "wardrobe"
    ],
    "wof:name":"Istabul Mutfak Banyo Ltd",
    "wof:placetype":"venue"
},
  "geometry": {"coordinates":[28.9039058685,41.0038414001],"type":"Point"}
}