{
  "type": "Feature",
  "properties": {
    "addr:full":"Kartaltepe Mh. Filiz Sk. No:25 Bak\u0131rk\u00f6y Istanbul",
    "addr:housenumber":"25",
    "addr:street":"Sk. No",
    "iso:country":"TR",
    "sg:address":"Kartaltepe Mh. Filiz Sk. No:25",
    "sg:city":"Bak\u0131rk\u00f6y",
    "sg:classifiers":[
        {
            "category":"Home & Garden",
            "subcategory":"Household Appliances",
            "type":"Retail Goods"
        }
    ],
    "sg:phone":"+90 212 543 0642",
    "sg:province":"Istanbul",
    "sg:tags":[
        "conditioner",
        "air"
    ],
    "wof:name":"?elik Isi Ltd.",
    "wof:placetype":"venue"
},
  "geometry": {"coordinates":[28.8765296936,40.9826316833],"type":"Point"}
}