{
  "type": "Feature",
  "properties": {
    "addr:full":"I. In??cd. No:61/a G?tepe Eskisehir",
    "addr:housenumber":"no 61 / a g ?",
    "addr:street":"I. In ? ? Cd.",
    "iso:country":"TR",
    "sg:address":"I. In??cd. No:61/a",
    "sg:city":"G?tepe",
    "sg:classifiers":[
        {
            "category":"Wholesale",
            "subcategory":"Home Furnishings",
            "type":"Manufacturing & Wholesale Goods"
        }
    ],
    "sg:phone":"+90 222 231 4867",
    "sg:province":"Eskisehir",
    "sg:tags":[
        "furniture"
    ],
    "wof:name":"Ta? Moble",
    "wof:placetype":"venue"
},
  "geometry": {"coordinates":[30.5154705048,39.7782936096],"type":"Point"}
}