{
  "type": "Feature",
  "properties": {
    "addr:full":"Kuyuyazisi Cd. Kivrimli Sk. No:25 D:27 Ke??en Ankara",
    "addr:housenumber":"25 d 27",
    "addr:street":"Kuyuyazisi Cd. Kivrimli Sk. No;Ke ? ? En Ankara",
    "iso:country":"TR",
    "sg:address":"Kuyuyazisi Cd. Kivrimli Sk. No:25 D:27",
    "sg:city":"Ke??en",
    "sg:classifiers":[
        {
            "category":"Organizations",
            "subcategory":"Membership Organization",
            "type":"Services"
        }
    ],
    "sg:phone":"+90 312 321 0252",
    "sg:province":"Ankara",
    "wof:name":"Ogretilebilir Cocuk. Kor. Dernegi",
    "wof:placetype":"venue"
},
  "geometry": {"coordinates":[32.8604812622,39.9429283142],"type":"Point"}
}