{
  "type": "Feature",
  "properties": {
    "iso:country":"TR",
    "sg:address":"Sanayi Mah. Sultanselim Cad. Boz.sok. No:10/b",
    "sg:city":"4.levent",
    "sg:classifiers":[
        {
            "category":"Food & Beverages",
            "subcategory":"Groceries & Convenience Stores",
            "type":"Retail Goods"
        }
    ],
    "sg:phone":"+90 212 284 5093",
    "sg:province":"Istanbul",
    "sg:tags":[
        "drink-",
        "soft"
    ],
    "wof:name":"Febas I? Ve Dis Ticaret",
    "wof:placetype":"venue"
},
  "geometry": {"coordinates":[28.975925,41.012379],"type":"Point"}
}