{
  "type": "Feature",
  "properties": {
    "addr:full":"Yesilce Mah. D?enli Sk. No:15 4. Levent Istanbul",
    "addr:housenumber":"?;4",
    "addr:street":"Yesilce Mah. D;Sk. No 15",
    "iso:country":"TR",
    "sg:address":"Yesilce Mah. D?enli Sk. No:15",
    "sg:city":"4. Levent",
    "sg:classifiers":[
        {
            "category":"Sports & Exercise",
            "subcategory":"Ski Slope",
            "type":"Entertainment"
        }
    ],
    "sg:phone":"+90 212 269 6867",
    "sg:province":"Istanbul",
    "sg:tags":[
        "wear"
    ],
    "wof:name":"Siprinter Teks. San. Tic.",
    "wof:placetype":"venue"
},
  "geometry": {"coordinates":[28.975925,41.012379],"type":"Point"}
}