{
  "type": "Feature",
  "properties": {
    "addr:full":"Talatpasa M.keskingil C.no:37 Kagithane Istanbul 80270",
    "addr:housenumber":"37",
    "addr:postcode":"80270",
    "addr:street":"C.No;Istanbul",
    "iso:country":"TR",
    "sg:address":"Talatpasa M.keskingil C.no:37",
    "sg:city":"Kagithane",
    "sg:classifiers":[
        {
            "category":"Home & Garden",
            "subcategory":"Building Materials",
            "type":"Retail Goods"
        }
    ],
    "sg:phone":"+90 2203949",
    "sg:postcode":"80270",
    "sg:province":"Istanbul",
    "sg:tags":[
        "window",
        "door",
        "plastic"
    ],
    "wof:name":"Alpas Yapi Malzemeleri Ltd.sti.",
    "wof:placetype":"venue"
},
  "geometry": {"coordinates":[28.9615898132,41.060344696],"type":"Point"}
}