{
  "type": "Feature",
  "properties": {
    "iso:country":"TR",
    "sg:address":"Bagdat Cd. No:128/5",
    "sg:city":"Maltepe",
    "sg:classifiers":[
        {
            "category":"Shopping",
            "subcategory":"Florist",
            "type":"Retail Goods"
        }
    ],
    "sg:phone":"+90 216 352 2553",
    "sg:postcode":"01000",
    "sg:province":"Istanbul",
    "sg:tags":[
        "flower"
    ],
    "wof:name":"A. Sedef Ulusl. ?i?ek?ilik",
    "wof:placetype":"venue"
},
  "geometry": {"coordinates":[29.0978336334,40.9519577026],"type":"Point"}
}