{
  "type": "Feature",
  "properties": {
    "addr:full":"Hurriyet Cd. Vakif Ish. N 2/212 Iskenderun K?tahya 31200",
    "addr:housenumber":"2 / 212;k ?",
    "addr:postcode":"31200",
    "addr:street":"Hurriyet Cd. Vakif Ish. N;Tahya",
    "iso:country":"TR",
    "sg:address":"Hurriyet Cd. Vakif Ish. N 2/212",
    "sg:city":"Iskenderun",
    "sg:classifiers":[
        {
            "category":"Mining & Drilling",
            "type":"Manufacturing & Wholesale Goods"
        }
    ],
    "sg:phone":"+90 274 216 4142",
    "sg:postcode":"31200",
    "sg:province":"K?tahya",
    "sg:tags":[
        "industry",
        "mine"
    ],
    "wof:name":"Tas.hal. Cevher Madencilik A.s.",
    "wof:placetype":"venue"
},
  "geometry": {"coordinates":[36.2422409058,36.5966186523],"type":"Point"}
}