{
  "type": "Feature",
  "properties": {
    "addr:full":"In??cad.1.sok.no:10-11 Karam?sel Kocaeli 41500",
    "addr:housenumber":"cad.1.sok.no",
    "addr:postcode":"10-11;?;41500",
    "addr:street":"In ? ?",
    "iso:country":"TR",
    "sg:address":"In??cad.1.sok.no:10-11",
    "sg:city":"Karam?sel",
    "sg:classifiers":[
        {
            "category":"Manufacturing",
            "subcategory":"Wood Products",
            "type":"Manufacturing & Wholesale Goods"
        }
    ],
    "sg:phone":"+90 262 454 4055",
    "sg:postcode":"41500",
    "sg:province":"Kocaeli",
    "sg:tags":[
        "forest"
    ],
    "wof:name":"Konus Yapi San.ve Tic.ltd.sti",
    "wof:placetype":"venue"
},
  "geometry": {"coordinates":[29.8761863708,40.7653274536],"type":"Point"}
}