{
  "type": "Feature",
  "properties": {
    "addr:full":"Gen?ik Spor Il M??. Tesis. Ke??en Samsun",
    "addr:street":"Gen ?;M ? ?;Ke ? ? En Samsun",
    "iso:country":"TR",
    "sg:address":"Gen?ik Spor Il M??. Tesis.",
    "sg:city":"Ke??en",
    "sg:classifiers":[
        {
            "category":"Organizations",
            "subcategory":"Membership Organization",
            "type":"Services"
        }
    ],
    "sg:phone":"+90 362 238 1897",
    "sg:province":"Samsun",
    "wof:name":"Samsun Genclik Merk. Genc Spor Klubu",
    "wof:placetype":"venue"
},
  "geometry": {"coordinates":[36.3381195068,41.2815704346],"type":"Point"}
}