{
  "type": "Feature",
  "properties": {
    "iso:country":"TR",
    "sg:address":"Koru Mevkii",
    "sg:city":"Dat?",
    "sg:orig_category":"Hotels: Motels",
    "sg:phone":"+90 252 712 2001",
    "sg:province":"Mugla",
    "wof:name":"Olimpos Hotel",
    "wof:placetype":"venue"
},
  "geometry": {"coordinates":[28.3568096161,37.2202987671],"type":"Point"}
}