{
  "type": "Feature",
  "properties": {
    "addr:full":"Korkadi S. Turizm Sitesi Blok D Etiler Bagcilar Istanbul 33115",
    "addr:postcode":"33115",
    "iso:country":"TR",
    "sg:address":"Korkadi S. Turizm Sitesi Blok D Etiler",
    "sg:city":"Bagcilar",
    "sg:classifiers":[
        {
            "category":"Home & Garden",
            "subcategory":"Building Materials",
            "type":"Retail Goods"
        }
    ],
    "sg:phone":"+90 212 265 9023",
    "sg:postcode":"33115",
    "sg:province":"Istanbul",
    "sg:tags":[
        "window",
        "door",
        "plastic"
    ],
    "wof:name":"Aysu Dis Tic. San. A.s.",
    "wof:placetype":"venue"
},
  "geometry": {"coordinates":[28.9759254456,41.0123786926],"type":"Point"}
}