{
  "type": "Feature",
  "properties": {
    "iso:country":"TR",
    "sg:address":"Tasocagi Cad. No:80/5 Caglayan",
    "sg:city":"Fatih",
    "sg:orig_category":"Scavening Services",
    "sg:phone":"+90 212 224 6544",
    "sg:postcode":"01740",
    "sg:province":"Istanbul",
    "wof:name":"Elite Sosyal Hizmetler Ltd.sti.",
    "wof:placetype":"venue"
},
  "geometry": {"coordinates":[28.981201,41.07217],"type":"Point"}
}