{
  "type": "Feature",
  "properties": {
    "addr:full":"Divan-i Ali Sk.no.12 Beyazit \u00c7orlu Istanbul",
    "addr:street":"Divan-I",
    "iso:country":"TR",
    "sg:address":"Divan-i Ali Sk.no.12 Beyazit",
    "sg:city":"\u00c7orlu",
    "sg:classifiers":[
        {
            "category":"Shopping",
            "subcategory":"Luggage & Leather Goods",
            "type":"Retail Goods"
        }
    ],
    "sg:phone":"+90 212 516 3260",
    "sg:province":"Istanbul",
    "sg:tags":[
        "leather-fur",
        "wear"
    ],
    "wof:name":"?zege Dericilik A.s.",
    "wof:placetype":"venue"
},
  "geometry": {"coordinates":[28.9777488708,41.0078239441],"type":"Point"}
}