{
  "type": "Feature",
  "properties": {
    "iso:country":"TR",
    "sg:address":"Davutpasa Cad. Dagli Is Merkezi No:5/21",
    "sg:city":"Topkapi",
    "sg:classifiers":[
        {
            "category":"Communications",
            "subcategory":"Newspaper",
            "type":"Services"
        }
    ],
    "sg:phone":"+90 212 481 8899",
    "sg:postcode":"24620",
    "sg:province":"Istanbul",
    "sg:tags":[
        "magazine"
    ],
    "wof:name":"Bizim Sekt?r Ayakkabi Ve Deri Dergisi",
    "wof:placetype":"venue"
},
  "geometry": {"coordinates":[28.9861831665,41.0408554077],"type":"Point"}
}