{
  "type": "Feature",
  "properties": {
    "iso:country":"TR",
    "sg:address":"Simav",
    "sg:city":"Karam?sel",
    "sg:classifiers":[
        {
            "category":"Manufacturing",
            "subcategory":"Wood Products",
            "type":"Manufacturing & Wholesale Goods"
        }
    ],
    "sg:phone":"+90 274 513 2465",
    "sg:postcode":"41500",
    "sg:province":"K?tahya",
    "sg:tags":[
        "forest"
    ],
    "wof:name":"Koyuncuoglu Aga? San. Tic. A.s.",
    "wof:placetype":"venue"
},
  "geometry": {"coordinates":[28.9787006378,39.0895996094],"type":"Point"}
}