{
  "type": "Feature",
  "properties": {
    "iso:country":"TR",
    "sg:address":"1 Nolu Saglik Ocagi Cad. 11/c",
    "sg:city":"?aglayan",
    "sg:classifiers":[
        {
            "category":"Shopping",
            "subcategory":"Stationery & Office Supplies",
            "type":"Retail Goods"
        }
    ],
    "sg:phone":"+90 416 213 7277",
    "sg:province":"Adiyaman",
    "wof:name":"Gen?lik Kitap Kirtasiye",
    "wof:placetype":"venue"
},
  "geometry": {"coordinates":[38.2784,37.7607],"type":"Point"}
}