{
  "type": "Feature",
  "properties": {
    "iso:country":"TR",
    "sg:address":"Kisla Cd. No:245 Bayrampasa",
    "sg:city":"Eskigaraj",
    "sg:classifiers":[
        {
            "category":"Manufacturing",
            "subcategory":"Rubber & Plastics",
            "type":"Manufacturing & Wholesale Goods"
        }
    ],
    "sg:phone":"+90 212 563 2613",
    "sg:province":"Istanbul",
    "sg:tags":[
        "industry"
    ],
    "wof:name":"Sahin Metal Ve Plastik San.",
    "wof:placetype":"venue"
},
  "geometry": {"coordinates":[28.9097423553,41.0475349426],"type":"Point"}
}