{
  "type": "Feature",
  "properties": {
    "iso:country":"TR",
    "sg:address":"Nailbey Mah. Yesildere Sok. Hakim Sevket Bey Apt.no:21 Kat:7/14",
    "sg:city":"Fomara",
    "sg:classifiers":[
        {
            "category":"Wholesale",
            "subcategory":"Medical Equipment & Supplies",
            "type":"Manufacturing & Wholesale Goods"
        }
    ],
    "sg:phone":"+90 424 236 8300",
    "sg:province":"Elazig",
    "sg:tags":[
        "material"
    ],
    "wof:name":"Ozcihangir Ic Ve Dis Tic.ltd.sti.",
    "wof:placetype":"venue"
},
  "geometry": {"coordinates":[39.2229003906,38.6754989624],"type":"Point"}
}