{
  "type": "Feature",
  "properties": {
    "addr:full":"Abidin Daver Sk. No:12/a-b \u00c7ankaya Ankara 06105",
    "addr:housenumber":"12 / a-b",
    "addr:postcode":"06105",
    "addr:street":"Daver Sk. No",
    "iso:country":"TR",
    "sg:address":"Abidin Daver Sk. No:12/a-b",
    "sg:city":"\u00c7ankaya",
    "sg:classifiers":[
        {
            "category":"Professional",
            "subcategory":"Engineering",
            "type":"Services"
        }
    ],
    "sg:phone":"+90 312 438 8565",
    "sg:postcode":"06105",
    "sg:province":"Ankara",
    "sg:tags":[
        "architect"
    ],
    "wof:name":"Mesa Mesken A.s.",
    "wof:placetype":"venue"
},
  "geometry": {"coordinates":[32.8604812622,39.9429283142],"type":"Point"}
}