{
  "type": "Feature",
  "properties": {
    "addr:full":"Talimhane Cd. No:45/c Rami Istanbul 34055",
    "addr:housenumber":"no 45 / c",
    "addr:postcode":"34055",
    "addr:street":"Talimhane Cd.",
    "iso:country":"TR",
    "sg:address":"Talimhane Cd. No:45/c",
    "sg:city":"Rami",
    "sg:classifiers":[
        {
            "category":"Shopping",
            "subcategory":"Florist",
            "type":"Retail Goods"
        }
    ],
    "sg:phone":"+90 212 545 0886",
    "sg:postcode":"34055",
    "sg:province":"Istanbul",
    "sg:tags":[
        "flower"
    ],
    "wof:name":"Star ?i?ek?ilik",
    "wof:placetype":"venue"
},
  "geometry": {"coordinates":[28.9172706604,41.0463752747],"type":"Point"}
}