{
  "type": "Feature",
  "properties": {
    "iso:country":"TR",
    "sg:address":"Karacakaya Cd. No:88 Siteler",
    "sg:city":"Gebze",
    "sg:classifiers":[
        {
            "category":"Home & Garden",
            "subcategory":"Home Furnishings",
            "type":"Retail Goods"
        }
    ],
    "sg:phone":"+90 312 350 9009",
    "sg:postcode":"41400",
    "sg:province":"Ankara",
    "sg:tags":[
        "curtaining",
        "-",
        "upholstering"
    ],
    "wof:name":"Anadolu Mensucat Tic. Koll. Sti.",
    "wof:placetype":"venue"
},
  "geometry": {"coordinates":[32.898899,39.958359],"type":"Point"}
}