{
  "type": "Feature",
  "properties": {
    "addr:full":"Gaziosmanpasa Mh. Soma Cd. No:22 Diskapi Balikesir 06030",
    "addr:postcode":"06030",
    "addr:street":"Gaziosmanpasa Mh.",
    "iso:country":"TR",
    "sg:address":"Gaziosmanpasa Mh. Soma Cd. No:22",
    "sg:city":"Diskapi",
    "sg:classifiers":[
        {
            "category":"Home & Garden",
            "subcategory":"Carpets & Floor Coverings",
            "type":"Retail Goods"
        }
    ],
    "sg:phone":"+90 266 221 2370",
    "sg:postcode":"06030",
    "sg:province":"Balikesir",
    "sg:tags":[
        "tile",
        "brick",
        "earthenware"
    ],
    "wof:name":"Balikesir ?imento San. Tic. A.s.",
    "wof:placetype":"venue"
},
  "geometry": {"coordinates":[27.8853626251,39.6448822021],"type":"Point"}
}