{
  "type": "Feature",
  "properties": {
    "iso:country":"TR",
    "sg:address":"Fevzi Cakmak Mah. Ucar Sok. No:13 Sefakoy",
    "sg:city":"24000",
    "sg:classifiers":[
        {
            "category":"Manufacturing",
            "subcategory":"Wood Products",
            "type":"Manufacturing & Wholesale Goods"
        }
    ],
    "sg:phone":"+90 212 579 2023",
    "sg:province":"Istanbul",
    "sg:tags":[
        "forest"
    ],
    "wof:name":"Dedeagacli Ticaret",
    "wof:placetype":"venue"
},
  "geometry": {"coordinates":[28.9759254456,41.0123786926],"type":"Point"}
}