{
  "type": "Feature",
  "properties": {
    "addr:full":"Inye Cad.no:38/3 Inye- Yenikoy Istanbul 01720",
    "addr:housenumber":"38 / 3",
    "addr:postcode":"01720",
    "iso:country":"TR",
    "sg:address":"Inye Cad.no:38/3 Inye-",
    "sg:city":"Yenikoy",
    "sg:classifiers":[
        {
            "category":"Home & Garden",
            "subcategory":"Garden Supply",
            "type":"Retail Goods"
        }
    ],
    "sg:phone":"+90 212 323 1959",
    "sg:postcode":"01720",
    "sg:province":"Istanbul",
    "sg:tags":[
        "fertilize",
        "soil"
    ],
    "wof:name":"Venus Uluslararasi Ticaret",
    "wof:placetype":"venue"
},
  "geometry": {"coordinates":[28.9759254456,41.0123786926],"type":"Point"}
}