{
  "type": "Feature",
  "properties": {
    "addr:full":"Erguvan Sok. 5/2 Kalamis Istanbul",
    "addr:housenumber":"5 / 2",
    "addr:street":"Erguvan Sok.",
    "iso:country":"TR",
    "sg:address":"Erguvan Sok. 5/2",
    "sg:city":"Kalamis",
    "sg:classifiers":[
        {
            "category":"Transit Center",
            "subcategory":"Freight",
            "type":"Transportation"
        }
    ],
    "sg:phone":"+90 216 345 3360",
    "sg:province":"Istanbul",
    "wof:name":"Venus Denizcilik Ic Ve Dis Tic. Ltd. Sti.",
    "wof:placetype":"venue"
},
  "geometry": {"coordinates":[28.8740596771,41.0114746094],"type":"Point"}
}