{
  "type": "Feature",
  "properties": {
    "iso:country":"TR",
    "sg:address":"Cemal Gursel Cad. No:16/d Ustkaynarca-pendik",
    "sg:city":"\u00c7ankaya",
    "sg:classifiers":[
        {
            "category":"Utilities",
            "subcategory":"Electric",
            "type":"Services"
        }
    ],
    "sg:phone":"+90 216 397 0652",
    "sg:province":"Istanbul",
    "sg:tags":[
        "accumulator",
        "-",
        "batery"
    ],
    "wof:name":"Spot Ticaret",
    "wof:placetype":"venue"
},
  "geometry": {"coordinates":[29.256001,40.8787],"type":"Point"}
}