{
  "type": "Feature",
  "properties": {
    "addr:full":"Kadik? Mh.turan G?es Cd.no:179 Izmit Bekirpasa Kocaeli 41100",
    "addr:housenumber":"?;179",
    "addr:postcode":"41100",
    "addr:street":"Mh.Turan G;Izmit Bekirpasa",
    "iso:country":"TR",
    "sg:address":"Kadik? Mh.turan G?es Cd.no:179",
    "sg:city":"Izmit Bekirpasa",
    "sg:classifiers":[
        {
            "category":"Shopping",
            "subcategory":"Computers & Home Electronics",
            "type":"Retail Goods"
        }
    ],
    "sg:phone":"+90 262 323 5673",
    "sg:postcode":"41100",
    "sg:province":"Kocaeli",
    "sg:tags":[
        "product",
        "electric-electronic"
    ],
    "wof:name":"Filiz Elektronik",
    "wof:placetype":"venue"
},
  "geometry": {"coordinates":[29.9345855713,40.7669563293],"type":"Point"}
}