{
  "type": "Feature",
  "properties": {
    "addr:full":"Mahmut Esat Bozkurt Cad. No.75/9 Incesu Maltepe Ankara 34843",
    "addr:housenumber":"no.75 / 9",
    "addr:postcode":"34843",
    "addr:street":"Mahmut;Cad.;Incesu Maltepe Ankara",
    "iso:country":"TR",
    "sg:address":"Mahmut Esat Bozkurt Cad. No.75/9 Incesu",
    "sg:city":"Maltepe",
    "sg:classifiers":[
        {
            "category":"Banks & Credit Unions",
            "subcategory":"Investment Brokerage",
            "type":"Services"
        }
    ],
    "sg:phone":"+90 312 431 5402",
    "sg:postcode":"34843",
    "sg:province":"Ankara",
    "sg:tags":[
        "-",
        "export",
        "import"
    ],
    "wof:name":"Smd Elektronik Sanayi Ve Dis Tic.ltd.sti.",
    "wof:placetype":"venue"
},
  "geometry": {"coordinates":[32.8604812622,39.9429283142],"type":"Point"}
}