{
  "type": "Feature",
  "properties": {
    "addr:full":"Fatih Cad. No:25/104 Camdibi Alsancak Izmir 01365",
    "addr:housenumber":"25 / 104",
    "addr:postcode":"01365",
    "addr:street":"Fatih Cad. No;Camdibi Alsancak",
    "iso:country":"TR",
    "sg:address":"Fatih Cad. No:25/104 Camdibi",
    "sg:city":"Alsancak",
    "sg:classifiers":[
        {
            "category":"Manufacturing",
            "subcategory":"Chemicals & Compounds",
            "type":"Manufacturing & Wholesale Goods"
        }
    ],
    "sg:phone":"+90 232 435 2174",
    "sg:postcode":"01365",
    "sg:province":"Izmir",
    "sg:tags":[
        "medicine"
    ],
    "wof:name":"3 H Kimya San. Ltd. Sti.",
    "wof:placetype":"venue"
},
  "geometry": {"coordinates":[27.1296863556,38.4186973572],"type":"Point"}
}