{
  "type": "Feature",
  "properties": {
    "addr:full":"Haramidere San.sitesi F Blok No: 326 Avcilar Erenk? Istanbul",
    "addr:housenumber":"blok no 326;?",
    "addr:street":"Avcilar Erenk",
    "iso:country":"TR",
    "sg:address":"Haramidere San.sitesi F Blok No: 326 Avcilar",
    "sg:city":"Erenk?",
    "sg:classifiers":[
        {
            "category":"Home & Garden",
            "subcategory":"Kitchen Supply",
            "type":"Retail Goods"
        }
    ],
    "sg:phone":"+90 2124222220729",
    "sg:province":"Istanbul",
    "sg:tags":[
        "wardrobe"
    ],
    "wof:name":"Star Mutfak Mob.aks.san.tic.ltd.sti.",
    "wof:placetype":"venue"
},
  "geometry": {"coordinates":[28.7231006622,40.9812011719],"type":"Point"}
}