{
  "type": "Feature",
  "properties": {
    "iso:country":"TR",
    "sg:address":"Yilanli Ayazma Cd. No:2 Cevizlibag",
    "sg:city":"K.?ekmece",
    "sg:classifiers":[
        {
            "category":"Building & Trades",
            "subcategory":"Plumbing",
            "type":"Services"
        }
    ],
    "sg:phone":"+90 212 577 6637",
    "sg:postcode":"34670",
    "sg:province":"Istanbul",
    "sg:tags":[
        "gasket"
    ],
    "wof:name":"Standart Conta",
    "wof:placetype":"venue"
},
  "geometry": {"coordinates":[28.9072113037,41.0155906677],"type":"Point"}
}