{
  "type": "Feature",
  "properties": {
    "iso:country":"TR",
    "sg:address":"Yeni Sie Pazari C/blok No:12",
    "sg:city":"Mersin",
    "sg:classifiers":[
        {
            "category":"Professional",
            "subcategory":"Business Services",
            "type":"Services"
        }
    ],
    "sg:phone":"+90 422 322 0516",
    "sg:postcode":"52750",
    "sg:province":"Malatya",
    "sg:tags":[
        "food",
        "product",
        "exporter",
        "aricultural"
    ],
    "wof:name":"Altunisik Gida San Ve Ihr.ltd.sti",
    "wof:placetype":"venue"
},
  "geometry": {"coordinates":[38.3143005371,38.3474998474],"type":"Point"}
}