{
  "type": "Feature",
  "properties": {
    "iso:country":"TR",
    "sg:address":"A?kg?oglu Sk. No.21",
    "sg:city":"Bornova",
    "sg:classifiers":[
        {
            "category":"Manufacturing",
            "subcategory":"Food",
            "type":"Manufacturing & Wholesale Goods"
        }
    ],
    "sg:phone":"+90 272 215 3696",
    "sg:postcode":"35100",
    "sg:province":"Afyon",
    "sg:tags":[
        "product",
        "floury",
        "macaroni"
    ],
    "wof:name":"Coskun Un Ve Gida San. A.s.",
    "wof:placetype":"venue"
},
  "geometry": {"coordinates":[30.5382652283,38.7579841614],"type":"Point"}
}