{
  "type": "Feature",
  "properties": {
    "iso:country":"TR",
    "sg:address":"Tarik Bura Cad. Bel.dukkanlari No:176",
    "sg:city":"Aksehir",
    "sg:classifiers":[
        {
            "category":"Ice Cream",
            "type":"Food & Drink"
        }
    ],
    "sg:phone":"+90 332 813 1391",
    "sg:postcode":"42550",
    "sg:province":"Konya",
    "sg:tags":[
        "sugar"
    ],
    "wof:name":"Arzum Ltd.sti.",
    "wof:placetype":"venue"
},
  "geometry": {"coordinates":[32.499027,37.871536],"type":"Point"}
}