{
  "type": "Feature",
  "properties": {
    "iso:country":"TR",
    "sg:address":"Hamidiye Mah. Girne Cad.no:58",
    "sg:city":"Kagithane",
    "sg:classifiers":[
        {
            "category":"Food & Beverages",
            "subcategory":"Groceries & Convenience Stores",
            "type":"Retail Goods"
        }
    ],
    "sg:phone":"+90 212 321 0186",
    "sg:postcode":"34406",
    "sg:province":"Istanbul",
    "sg:tags":[
        "ready"
    ],
    "wof:name":"Sah Gida Ve Kimya Mad.san.tic.ltd.sti.",
    "wof:placetype":"venue"
},
  "geometry": {"coordinates":[28.9761371613,41.0930023193],"type":"Point"}
}