{
  "type": "Feature",
  "properties": {
    "iso:country":"TR",
    "sg:address":"Ismet Pasa Mah. Haci Veli Cami Cad. Ballihan No:1",
    "sg:city":"Osmanbey",
    "sg:classifiers":[
        {
            "category":"Shopping",
            "subcategory":"Clothing, Apparel, & Fashions",
            "type":"Retail Goods"
        }
    ],
    "sg:phone":"+90 342 232 1063",
    "sg:postcode":"63000",
    "sg:province":"Gaziantep",
    "sg:tags":[
        "men",
        "wear"
    ],
    "wof:name":"By Buttik Gomlek",
    "wof:placetype":"venue"
},
  "geometry": {"coordinates":[37.3761024475,37.0629463196],"type":"Point"}
}