{
  "type": "Feature",
  "properties": {
    "addr:full":"Ostim Sanayi Sitesi 13. Sok. No:20 Ostim Ankara 06374",
    "addr:housenumber":"13;no 20",
    "addr:postcode":"06374",
    "addr:street":"Ostim Sanayi Sitesi;Sok.;Ostim Ankara",
    "iso:country":"TR",
    "sg:address":"Ostim Sanayi Sitesi 13. Sok. No:20",
    "sg:city":"Ostim",
    "sg:orig_category":"Ostim Ankara",
    "sg:phone":"+90 312 354 3704",
    "sg:postcode":"06374",
    "sg:province":"Ankara",
    "wof:name":"Taskaya Makina San. Ve Tic. Ltd. Sti.",
    "wof:placetype":"venue"
},
  "geometry": {"coordinates":[32.7652435303,39.9583816528],"type":"Point"}
}