{
  "type": "Feature",
  "properties": {
    "addr:full":"Hasanpasa Hamiyet Sok. ?zgur Han No:10/3 Kadikoy Sultanbeyli Istanbul",
    "addr:housenumber":"?;3",
    "addr:street":"Hamiyet Sok.;Kadikoy",
    "iso:country":"TR",
    "sg:address":"Hasanpasa Hamiyet Sok. ?zgur Han No:10/3 Kadikoy",
    "sg:city":"Sultanbeyli",
    "sg:classifiers":[
        {
            "category":"Home & Garden",
            "subcategory":"Carpets & Floor Coverings",
            "type":"Retail Goods"
        }
    ],
    "sg:phone":"+90 216 325 1669",
    "sg:province":"Istanbul",
    "sg:tags":[
        "wall",
        "ceramics-porcelain",
        "tile",
        "-"
    ],
    "wof:name":"Barbutin Seramik Dekorasyon San.ve Tic. Ltd.sti.",
    "wof:placetype":"venue"
},
  "geometry": {"coordinates":[29.0294399261,40.9855613708],"type":"Point"}
}