{
  "type": "Feature",
  "properties": {
    "addr:full":"Mahmutbey Yolu Kir?klar Ismerk. No:3/50 Sirinevler Ey\u00fcp Istanbul 34050",
    "addr:housenumber":"kir ?;50",
    "addr:postcode":"34050",
    "addr:street":"Mahmutbey Yolu;No 3 /",
    "iso:country":"TR",
    "sg:address":"Mahmutbey Yolu Kir?klar Ismerk. No:3/50 Sirinevler",
    "sg:city":"Ey\u00fcp",
    "sg:classifiers":[
        {
            "category":"Freight",
            "type":"Transportation"
        }
    ],
    "sg:phone":"+90 212 654 6333",
    "sg:postcode":"34050",
    "sg:province":"Istanbul",
    "sg:tags":[
        "packing",
        "industry"
    ],
    "wof:name":"?zg?n Ambalaj San.",
    "wof:placetype":"venue"
},
  "geometry": {"coordinates":[28.9339408875,41.0509300232],"type":"Point"}
}