{
  "type": "Feature",
  "properties": {
    "addr:full":"Organize Sanayi B?gesi 4.cad.1/a Merkez Afyon 03200",
    "addr:housenumber":"?;a",
    "addr:postcode":"03200",
    "addr:street":"Organize Sanayi B;Merkez Afyon",
    "iso:country":"TR",
    "sg:address":"Organize Sanayi B?gesi 4.cad.1/a",
    "sg:city":"Merkez",
    "sg:classifiers":[
        {
            "category":"Home & Garden",
            "subcategory":"Building Materials",
            "type":"Retail Goods"
        }
    ],
    "sg:phone":"+90 272 221 1244",
    "sg:postcode":"03200",
    "sg:province":"Afyon",
    "sg:tags":[
        "stone",
        "natural",
        "marble"
    ],
    "sg:website":"ugurmarble.com",
    "wof:name":"Ugur Insaat Mermer Ve Maden San.tic.ltd.sti",
    "wof:placetype":"venue"
},
  "geometry": {"coordinates":[30.5382652283,38.7579841614],"type":"Point"}
}