{
  "type": "Feature",
  "properties": {
    "addr:full":"Eskisehir Yolu No:294 Lodumlu Ankara 6800",
    "addr:housenumber":"no",
    "addr:postcode":"6800",
    "addr:street":"Eskisehir Yolu;Lodumlu Ankara",
    "iso:country":"TR",
    "sg:address":"Eskisehir Yolu No:294",
    "sg:city":"Lodumlu",
    "sg:classifiers":[
        {
            "category":"Wholesale",
            "subcategory":"Machinery & Supplies",
            "type":"Manufacturing & Wholesale Goods"
        }
    ],
    "sg:phone":"+90 312 289 8900",
    "sg:postcode":"6800",
    "sg:province":"Ankara",
    "sg:tags":[
        "bearing",
        "ball"
    ],
    "wof:name":"Ortadogu Rulman San. Tic. A.s.",
    "wof:placetype":"venue"
},
  "geometry": {"coordinates":[32.662373,39.883926],"type":"Point"}
}