{
  "type": "Feature",
  "properties": {
    "addr:full":"Tormak San. Sitesi G-blok No:14 Ikitelli Istanbul 34306",
    "addr:housenumber":"14",
    "addr:postcode":"34306",
    "addr:street":"G-Blok No;Istanbul",
    "iso:country":"TR",
    "sg:address":"Tormak San. Sitesi G-blok No:14",
    "sg:city":"Ikitelli",
    "sg:classifiers":[
        {
            "category":"Wholesale",
            "subcategory":"Machinery & Supplies",
            "type":"Manufacturing & Wholesale Goods"
        }
    ],
    "sg:phone":"+90 212851822728",
    "sg:postcode":"34306",
    "sg:province":"Istanbul",
    "sg:tags":[
        "agricultural"
    ],
    "wof:name":"Yildiz Dovme Civata Ltd.sti.",
    "wof:placetype":"venue"
},
  "geometry": {"coordinates":[28.7984962463,41.0884017944],"type":"Point"}
}