{
  "type": "Feature",
  "properties": {
    "iso:country":"TR",
    "sg:address":"Bagdat Cd. No:133",
    "sg:city":"Kad\u0131k\u00f6y",
    "sg:classifiers":[
        {
            "category":"Building & Trades",
            "subcategory":"Electrical",
            "type":"Services"
        }
    ],
    "sg:phone":"+90 216 337 7035",
    "sg:postcode":"34990",
    "sg:province":"Istanbul",
    "sg:tags":[
        "equipment",
        "lighting"
    ],
    "wof:name":"Odin Aydinlatma Tic. San. A.s.",
    "wof:placetype":"venue"
},
  "geometry": {"coordinates":[29.0458011627,40.978603363],"type":"Point"}
}