{
  "type": "Feature",
  "properties": {
    "addr:full":"Rumeli Cad. Suleyman Nazif Sk. No: 70/4 Osmanbey Bakirkoy Istanbul 35790",
    "addr:housenumber":"70 / 4",
    "addr:postcode":"35790",
    "addr:street":"Rumeli Cad. Suleyman Nazif Sk. No",
    "iso:country":"TR",
    "sg:address":"Rumeli Cad. Suleyman Nazif Sk. No: 70/4 Osmanbey",
    "sg:city":"Bakirkoy",
    "sg:orig_category":"Translation Servies",
    "sg:phone":"+90 212 230 0002",
    "sg:postcode":"35790",
    "sg:province":"Istanbul",
    "wof:name":"Turkiye Cevirmenler Dernegi",
    "wof:placetype":"venue"
},
  "geometry": {"coordinates":[28.9861831665,41.0408554077],"type":"Point"}
}