{
  "type": "Feature",
  "properties": {
    "addr:full":"Barbaros Bulvari, Uzay Apt. No.51 K.5 D.13 Besiktas Istanbul 75200",
    "addr:housenumber":"d.13",
    "addr:postcode":"75200",
    "addr:street":"Barbaros Bulvari Uzay Apt. No.51 K.5",
    "iso:country":"TR",
    "sg:address":"Barbaros Bulvari, Uzay Apt. No.51 K.5 D.13",
    "sg:city":"Besiktas",
    "sg:classifiers":[
        {
            "category":"Freight",
            "type":"Transportation"
        }
    ],
    "sg:phone":"+90 212 258 7162",
    "sg:postcode":"75200",
    "sg:province":"Istanbul",
    "sg:tags":[
        "agent",
        "shipping",
        "broker"
    ],
    "wof:name":"Uzunoglu Gozetme Ltd.sti.",
    "wof:placetype":"venue"
},
  "geometry": {"coordinates":[28.838055,41.028065],"type":"Point"}
}