{
  "type": "Feature",
  "properties": {
    "addr:full":"Atat?k Mh. Fahri K. Cd. No:4/1 B.?ekmece Nazilli Istanbul 65600",
    "addr:housenumber":"no 4 / 1 b. ?",
    "addr:postcode":"65600",
    "addr:street":"K Mh. Fahri K. Cd.;Ekmece Nazilli",
    "iso:country":"TR",
    "sg:address":"Atat?k Mh. Fahri K. Cd. No:4/1 B.?ekmece",
    "sg:city":"Nazilli",
    "sg:classifiers":[
        {
            "category":"Wholesale",
            "subcategory":"Durable Goods & Equipment",
            "type":"Manufacturing & Wholesale Goods"
        }
    ],
    "sg:phone":"+90 212 883 4407",
    "sg:postcode":"65600",
    "sg:province":"Istanbul",
    "sg:tags":[
        "consumer"
    ],
    "wof:name":"Empa Ev Gere?. San. Tic.",
    "wof:placetype":"venue"
},
  "geometry": {"coordinates":[28.9861831665,41.0408554077],"type":"Point"}
}