{
  "type": "Feature",
  "properties": {
    "iso:country":"TR",
    "sg:address":"Karadeniz Mahallesi General Aldogan Caddesi No:2 - Gaziosmanpasa",
    "sg:city":"Macunk?y",
    "sg:classifiers":[
        {
            "category":"Banks & Credit Unions",
            "subcategory":"Investment Brokerage",
            "type":"Services"
        }
    ],
    "sg:phone":"+90 212 649 0380",
    "sg:province":"Istanbul",
    "sg:tags":[
        "aid",
        "material",
        "first"
    ],
    "wof:name":"Arma - Med ?zel Saglik Hizmetleri",
    "wof:placetype":"venue"
},
  "geometry": {"coordinates":[28.8881092072,41.0794868469],"type":"Point"}
}