{
  "type": "Feature",
  "properties": {
    "addr:full":"Bagdat Cad. K?k Sk. Bagdat Apt. 333/3 Saskinbakkal \u00c7ankaya Istanbul 06610",
    "addr:housenumber":"k ?;333 / 3",
    "addr:postcode":"06610",
    "addr:street":"Bagdat Cad.;K Sk. Bagdat Apt.",
    "iso:country":"TR",
    "sg:address":"Bagdat Cad. K?k Sk. Bagdat Apt. 333/3 Saskinbakkal",
    "sg:city":"\u00c7ankaya",
    "sg:classifiers":[
        {
            "category":"Communications",
            "subcategory":"Radio Station",
            "type":"Services"
        }
    ],
    "sg:phone":"+90 216 385 0830",
    "sg:postcode":"06610",
    "sg:province":"Istanbul",
    "sg:tags":[
        "hair",
        "transplantation"
    ],
    "wof:name":"Euro Clinic Sac Ekim Merkezi",
    "wof:placetype":"venue"
},
  "geometry": {"coordinates":[28.9861831665,41.0408554077],"type":"Point"}
}