{
  "type": "Feature",
  "properties": {
    "iso:country":"TR",
    "sg:address":"Karatas Yolu ?zeri 10.km. Havutlu Mevki",
    "sg:city":"Merter",
    "sg:classifiers":[
        {
            "category":"Food & Beverages",
            "subcategory":"Groceries & Convenience Stores",
            "type":"Retail Goods"
        }
    ],
    "sg:phone":"+90 322 336 3206",
    "sg:province":"Adana",
    "sg:tags":[
        "drink-",
        "soft"
    ],
    "wof:name":"Fruko Tamek Meyva Sulari San.as.",
    "wof:placetype":"venue"
},
  "geometry": {"coordinates":[35.313736,37.000717],"type":"Point"}
}