{
  "type": "Feature",
  "properties": {
    "addr:full":"Perpa Tic. Mrk. Kat: 11 No: 1627 Isikkent Istanbul 32100",
    "addr:housenumber":"11 no 1627",
    "addr:postcode":"32100",
    "addr:street":"Kat;Isikkent Istanbul",
    "iso:country":"TR",
    "sg:address":"Perpa Tic. Mrk. Kat: 11 No: 1627",
    "sg:city":"Isikkent",
    "sg:classifiers":[
        {
            "category":"Home & Garden",
            "subcategory":"Hardware",
            "type":"Retail Goods"
        }
    ],
    "sg:phone":"+90 21222162144",
    "sg:postcode":"32100",
    "sg:province":"Istanbul",
    "sg:tags":[
        "store"
    ],
    "wof:name":"Mitar Hirdavatcilik Ith. Ve Ihr. A.s.",
    "wof:placetype":"venue"
},
  "geometry": {"coordinates":[28.9861831665,41.0408554077],"type":"Point"}
}