{
  "type": "Feature",
  "properties": {
    "addr:full":"Bilkent Bulvari Beytepe Emin?? 34440 Ankara",
    "addr:housenumber":"? ?",
    "addr:postcode":"34440",
    "addr:street":"Bilkent Bulvari",
    "iso:country":"TR",
    "sg:address":"Bilkent Bulvari Beytepe",
    "sg:city":"Emin?? 34440",
    "sg:orig_category":"Printinh House",
    "sg:phone":"+90 312 266 4150",
    "sg:province":"Ankara",
    "wof:name":"Meteksan Matbaacilik Ve Teknik San. Tic. Ltd. Sti.",
    "wof:placetype":"venue"
},
  "geometry": {"coordinates":[32.7665367126,39.8940010071],"type":"Point"}
}