{
  "type": "Feature",
  "properties": {
    "addr:full":"Mumhane Cad. Suhalfazli 2 Han. No:101/3 Karakoy Istanbul 07700",
    "addr:housenumber":"2;101 / 3",
    "addr:postcode":"07700",
    "addr:street":"Mumhane Cad. Suhalfazli;Han. No",
    "iso:country":"TR",
    "sg:address":"Mumhane Cad. Suhalfazli 2 Han. No:101/3",
    "sg:city":"Karakoy",
    "sg:classifiers":[
        {
            "category":"Farming",
            "subcategory":"Farm",
            "type":"Manufacturing & Wholesale Goods"
        }
    ],
    "sg:phone":"+90 212 245 3566",
    "sg:postcode":"07700",
    "sg:province":"Istanbul",
    "sg:tags":[
        "agricultural",
        "product"
    ],
    "wof:name":"Da-ye Konfeksiyon Ve Ev Ihtiyaclari San. Ve Dis Tic.",
    "wof:placetype":"venue"
},
  "geometry": {"coordinates":[28.9759254456,41.0123786926],"type":"Point"}
}