{
  "type": "Feature",
  "properties": {
    "addr:full":"Ilyasbey Cd. No:56 Yedikule Istanbul 34107",
    "addr:housenumber":"no 56",
    "addr:postcode":"34107",
    "addr:street":"Ilyasbey Cd.",
    "iso:country":"TR",
    "sg:address":"Ilyasbey Cd. No:56",
    "sg:city":"Yedikule",
    "sg:classifiers":[
        {
            "category":"Home & Garden",
            "subcategory":"Household Appliances",
            "type":"Retail Goods"
        }
    ],
    "sg:phone":"+90 212 588 7843",
    "sg:postcode":"34107",
    "sg:province":"Istanbul",
    "sg:tags":[
        "conditioner",
        "air"
    ],
    "wof:name":"Ensa Isi. Sog. Ltd.",
    "wof:placetype":"venue"
},
  "geometry": {"coordinates":[28.9276046753,40.9964790344],"type":"Point"}
}