{
  "type": "Feature",
  "properties": {
    "addr:full":"1649 Sok.no:15 Bayrakli Aksaray Izmir 31030",
    "addr:housenumber":"1649;15",
    "addr:postcode":"31030",
    "addr:street":"Sok.No",
    "iso:country":"TR",
    "sg:address":"1649 Sok.no:15 Bayrakli",
    "sg:city":"Aksaray",
    "sg:classifiers":[
        {
            "category":"Shopping",
            "subcategory":"Pharmacy",
            "type":"Retail Goods"
        }
    ],
    "sg:phone":"+90 232 365 6187",
    "sg:postcode":"31030",
    "sg:province":"Izmir",
    "sg:tags":[
        "store",
        "drug"
    ],
    "wof:name":"?agdas Eczacilar Laboratuvari San. Ve Tic. A.s.",
    "wof:placetype":"venue"
},
  "geometry": {"coordinates":[27.1423015594,38.4251480103],"type":"Point"}
}