{
  "type": "Feature",
  "properties": {
    "addr:full":"Ankara Cad.no:63 Altiparmak Cad.no:58 K/4 Kadikoy Bursa 01370",
    "addr:housenumber":"63;58 k / 4",
    "addr:postcode":"01370",
    "addr:street":"Altiparmak Cad.No;Kadikoy Bursa",
    "iso:country":"TR",
    "sg:address":"Ankara Cad.no:63 Altiparmak Cad.no:58 K/4",
    "sg:city":"Kadikoy",
    "sg:classifiers":[
        {
            "category":"Home & Garden",
            "subcategory":"Building Materials",
            "type":"Retail Goods"
        }
    ],
    "sg:phone":"+90 224 222 2101",
    "sg:postcode":"01370",
    "sg:province":"Bursa",
    "sg:tags":[
        "stone",
        "natural",
        "marble"
    ],
    "wof:name":"Vks Or.trd.cons.co",
    "wof:placetype":"venue"
},
  "geometry": {"coordinates":[29.0586109161,40.1844291687],"type":"Point"}
}