{
  "type": "Feature",
  "properties": {
    "iso:country":"TR",
    "sg:address":"Ataturk Cad. Akdeniz Apt. No:68/1 D:8 Sahrayicedit-kadikoy",
    "sg:city":"Kartal",
    "sg:classifiers":[
        {
            "category":"Building & Trades",
            "subcategory":"Electrical",
            "type":"Services"
        }
    ],
    "sg:phone":"+90 216 360 4682",
    "sg:postcode":"46000",
    "sg:province":"Istanbul",
    "sg:tags":[
        "equipment",
        "electric"
    ],
    "wof:name":"Ark Endustriyel Sistemleri Ltd.sti.",
    "wof:placetype":"venue"
},
  "geometry": {"coordinates":[28.9861831665,41.0408554077],"type":"Point"}
}