{
  "type": "Feature",
  "properties": {
    "addr:full":"Bugday Pazari Necipbey Cad. No:10 Nazilli Samsun 65600",
    "addr:housenumber":"10",
    "addr:postcode":"65600",
    "addr:street":"Necipbey Cad. No",
    "iso:country":"TR",
    "sg:address":"Bugday Pazari Necipbey Cad. No:10",
    "sg:city":"Nazilli",
    "sg:classifiers":[
        {
            "category":"Manufacturing",
            "subcategory":"Food",
            "type":"Manufacturing & Wholesale Goods"
        }
    ],
    "sg:postcode":"65600",
    "sg:province":"Samsun",
    "sg:tags":[
        "wholesaler"
    ],
    "wof:name":"Birkol Gida Maddeleri Ve Sanayi A.s.",
    "wof:placetype":"venue"
},
  "geometry": {"coordinates":[36.3378410339,41.2897186279],"type":"Point"}
}