{
  "type": "Feature",
  "properties": {
    "addr:full":"Astim Organize San B?gesi 5.cad.no:1 Pk 172 Aydin Aydin 01513",
    "addr:housenumber":"?;1",
    "addr:postcode":"01513",
    "addr:street":"Organize San B;Pk 172",
    "iso:country":"TR",
    "sg:address":"Astim Organize San B?gesi 5.cad.no:1 Pk 172",
    "sg:city":"Aydin",
    "sg:classifiers":[
        {
            "category":"Manufacturing",
            "subcategory":"Textiles",
            "type":"Manufacturing & Wholesale Goods"
        }
    ],
    "sg:phone":"+90 256 231 0464",
    "sg:postcode":"01513",
    "sg:province":"Aydin",
    "sg:tags":[
        "machinery"
    ],
    "wof:name":"Balkan Tekstil Makinalari San. Ve Tic. Ltd. Sti.",
    "wof:placetype":"venue"
},
  "geometry": {"coordinates":[27.8324394226,37.8409690857],"type":"Point"}
}