{
  "type": "Feature",
  "properties": {
    "addr:full":"Mithatpasa Cd. No:62 D:15-18 Ortak? Ankara 80840",
    "addr:housenumber":"no 62 d",
    "addr:postcode":"15-18;?;80840",
    "addr:street":"Mithatpasa Cd.",
    "iso:country":"TR",
    "sg:address":"Mithatpasa Cd. No:62 D:15-18",
    "sg:city":"Ortak?",
    "sg:classifiers":[
        {
            "category":"Organizations",
            "subcategory":"Professional Association",
            "type":"Services"
        }
    ],
    "sg:phone":"+90 312 417 2672",
    "sg:postcode":"80840",
    "sg:province":"Ankara",
    "wof:name":"Turk Tabipleri Birligi Merk.",
    "wof:placetype":"venue"
},
  "geometry": {"coordinates":[32.8565330505,39.9245910645],"type":"Point"}
}