{
  "type": "Feature",
  "properties": {
    "addr:full":"?ifkurtlar Plaza Maslak Ist. Maslak Istanbul 34398",
    "addr:housenumber":"?",
    "addr:postcode":"34398",
    "addr:street":"Ifkurtlar Plaza",
    "iso:country":"TR",
    "sg:address":"?ifkurtlar Plaza Maslak Ist.",
    "sg:city":"Maslak",
    "sg:classifiers":[
        {
            "category":"Farming",
            "subcategory":"Fish & Marine Products",
            "type":"Manufacturing & Wholesale Goods"
        }
    ],
    "sg:phone":"+90 212 276 1867",
    "sg:postcode":"34398",
    "sg:province":"Istanbul",
    "sg:tags":[
        "automotive"
    ],
    "wof:name":"?eltur Otomotiv San. Tic. Ltd. Sti.",
    "wof:placetype":"venue"
},
  "geometry": {"coordinates":[29.0198059082,41.1222839355],"type":"Point"}
}