{
  "type": "Feature",
  "properties": {
    "addr:full":"G.o.s.b.ihsandede Cad. 800.sok. Gebze Kad\u0131k\u00f6y Kocaeli 34714",
    "addr:housenumber":"800.sok",
    "addr:postcode":"34714",
    "addr:street":"G.O.S.B.Ihsandede Cad.;Kadikoey",
    "iso:country":"TR",
    "sg:address":"G.o.s.b.ihsandede Cad. 800.sok. Gebze",
    "sg:city":"Kad\u0131k\u00f6y",
    "sg:classifiers":[
        {
            "category":"Building & Trades",
            "subcategory":"Plumbing",
            "type":"Services"
        }
    ],
    "sg:phone":"+90 262 751 1254",
    "sg:postcode":"34714",
    "sg:province":"Kocaeli",
    "wof:name":"Sismat Steel Machin.manufac.treatment & Assembly Ind.inc",
    "wof:placetype":"venue"
},
  "geometry": {"coordinates":[29.4293422699,40.8393745422],"type":"Point"}
}