{
  "type": "Feature",
  "properties": {
    "addr:full":"Inonu Cad. No:8 Dr. Tarik Zafer Tunay Sok. K:2/5 80080 Beyoglu Istanbul Osmanbey Istanbul 63000",
    "addr:housenumber":"k 2 / 5",
    "addr:postcode":"80080;63000",
    "addr:street":"Inonu Cad. No 8;Tunay Sok.",
    "iso:country":"TR",
    "sg:address":"Inonu Cad. No:8 Dr. Tarik Zafer Tunay Sok. K:2/5 80080 Beyoglu Istanbul",
    "sg:city":"Osmanbey",
    "sg:classifiers":[
        {
            "category":"Real Estate",
            "subcategory":"Architect",
            "type":"Services"
        }
    ],
    "sg:phone":"+90 212 251 1368",
    "sg:postcode":"63000",
    "sg:province":"Istanbul",
    "sg:tags":[
        "textile",
        "clothing"
    ],
    "wof:name":"Canan Tekstil San. Ve Dis Tic. Ltd. Sti.",
    "wof:placetype":"venue"
},
  "geometry": {"coordinates":[28.9861831665,41.0408554077],"type":"Point"}
}