{
  "type": "Feature",
  "properties": {
    "iso:country":"TR",
    "sg:address":"Karakoy Mumhane Cad. 35",
    "sg:city":"\u00dcmraniye",
    "sg:classifiers":[
        {
            "category":"Home & Garden",
            "subcategory":"Building Materials",
            "type":"Retail Goods"
        }
    ],
    "sg:phone":"+90 212 244 1009",
    "sg:province":"Istanbul",
    "sg:tags":[
        "stone",
        "natural",
        "marble"
    ],
    "wof:name":"Elkay A.s.",
    "wof:placetype":"venue"
},
  "geometry": {"coordinates":[29.0296726227,40.9949073792],"type":"Point"}
}