{
  "type": "Feature",
  "properties": {
    "iso:country":"TR",
    "sg:address":"Vasif Cinar Bulv. No:19/c",
    "sg:city":"Alsancak",
    "sg:classifiers":[
        {
            "category":"Home & Garden",
            "subcategory":"Household Appliances",
            "type":"Retail Goods"
        }
    ],
    "sg:phone":"+90 232 464 2464",
    "sg:postcode":"01365",
    "sg:province":"Izmir",
    "sg:tags":[
        "conditioner",
        "air"
    ],
    "wof:name":"Tem Termo Makina Ve Turizm San.tic. Ltd.sti.",
    "wof:placetype":"venue"
},
  "geometry": {"coordinates":[27.1410770416,38.4300765991],"type":"Point"}
}