{
  "type": "Feature",
  "properties": {
    "iso:country":"TR",
    "sg:address":"Cay Mah.sahil Cad. No: 16 Ocal Apt.d:1",
    "sg:city":"Iskenderun",
    "sg:classifiers":[
        {
            "category":"Freight",
            "type":"Transportation"
        }
    ],
    "sg:phone":"+90 326 613 3293",
    "sg:postcode":"31200",
    "sg:province":"Hatay",
    "sg:tags":[
        "agent",
        "shipping",
        "broker"
    ],
    "wof:name":"Onur Shipping & Trading Agency Co.ltd.",
    "wof:placetype":"venue"
},
  "geometry": {"coordinates":[36.349812,36.401848],"type":"Point"}
}