{
  "type": "Feature",
  "properties": {
    "iso:country":"TR",
    "sg:address":"354.sok. No:6 2.sanayi Sitesi Bornova",
    "sg:city":"Besevler",
    "sg:classifiers":[
        {
            "category":"Manufacturing",
            "subcategory":"Chemicals & Compounds",
            "type":"Manufacturing & Wholesale Goods"
        }
    ],
    "sg:phone":"+90 232 461 1160",
    "sg:postcode":"04100",
    "sg:province":"Izmir",
    "sg:tags":[
        "industry"
    ],
    "wof:name":"Unisan Kimyevi Maddeler Ins.tur.san.tic.ltd.sti.",
    "wof:placetype":"venue"
},
  "geometry": {"coordinates":[27.1394844055,38.3448867798],"type":"Point"}
}