{
  "type": "Feature",
  "properties": {
    "addr:full":"K.karabekir C.no.13 G?eslik? Emin?? 34450 Istanbul",
    "addr:housenumber":"?;?;? ?",
    "addr:postcode":"34450",
    "addr:street":"C.No.13 G",
    "iso:country":"TR",
    "sg:address":"K.karabekir C.no.13 G?eslik?",
    "sg:city":"Emin?? 34450",
    "sg:classifiers":[
        {
            "category":"Shopping",
            "subcategory":"Clothing, Apparel, & Fashions",
            "type":"Retail Goods"
        }
    ],
    "sg:phone":"+90 212 550 2896",
    "sg:province":"Istanbul",
    "sg:tags":[
        "bag-belt-accessories"
    ],
    "wof:name":"Yusuf ?anta San. Ltd.sti.",
    "wof:placetype":"venue"
},
  "geometry": {"coordinates":[28.789261,41.022137],"type":"Point"}
}