{
  "type": "Feature",
  "properties": {
    "addr:full":"Belediye Rant Tesisleri Kat:2 No:38 Emirdag Sefak? Afyon 34620",
    "addr:housenumber":"kat 2 no 38",
    "addr:postcode":"34620",
    "iso:country":"TR",
    "sg:address":"Belediye Rant Tesisleri Kat:2 No:38 Emirdag",
    "sg:city":"Sefak?",
    "sg:classifiers":[
        {
            "category":"Banks & Credit Unions",
            "subcategory":"Investment Brokerage",
            "type":"Services"
        }
    ],
    "sg:phone":"+90 272 442 7884",
    "sg:postcode":"34620",
    "sg:province":"Afyon",
    "sg:tags":[
        "-",
        "export",
        "import"
    ],
    "wof:name":"Tapmaz Ithalat-ihracat",
    "wof:placetype":"venue"
},
  "geometry": {"coordinates":[30.5382652283,38.7579841614],"type":"Point"}
}