{
  "type": "Feature",
  "properties": {
    "addr:full":"Persembe Pazari Cad. Ticaret Han No:26/5 Karakoy Kad\u0131k\u00f6y Istanbul 34714",
    "addr:housenumber":"5",
    "addr:postcode":"34714",
    "addr:street":"Pazari",
    "iso:country":"TR",
    "sg:address":"Persembe Pazari Cad. Ticaret Han No:26/5 Karakoy",
    "sg:city":"Kad\u0131k\u00f6y",
    "sg:classifiers":[
        {
            "category":"Building & Trades",
            "subcategory":"Plumbing",
            "type":"Services"
        }
    ],
    "sg:phone":"+90 212 235 5190",
    "sg:postcode":"34714",
    "sg:province":"Istanbul",
    "wof:name":"Set Endustri Malzemeleri Tic.ltd.sti.",
    "wof:placetype":"venue"
},
  "geometry": {"coordinates":[29.0285358429,40.9890937805],"type":"Point"}
}