{
  "type": "Feature",
  "properties": {
    "addr:full":"Senlik? Orman Sok.no:10 Florya Istanbul 34153",
    "addr:housenumber":"10",
    "addr:postcode":"34153",
    "addr:street":"Florya Istanbul",
    "iso:country":"TR",
    "sg:address":"Senlik? Orman Sok.no:10",
    "sg:city":"Florya",
    "sg:classifiers":[
        {
            "category":"Freight",
            "type":"Transportation"
        }
    ],
    "sg:phone":"+90 212 574 0147",
    "sg:postcode":"34153",
    "sg:province":"Istanbul",
    "sg:tags":[
        "cargo",
        "air"
    ],
    "wof:name":"Bon Air Havacilik",
    "wof:placetype":"venue"
},
  "geometry": {"coordinates":[29.2552528381,41.0353469849],"type":"Point"}
}