{
  "type": "Feature",
  "properties": {
    "addr:full":"Kumyaka K??16960 Mudanya Bursa 16940",
    "addr:postcode":"16960;16940",
    "iso:country":"TR",
    "sg:address":"Kumyaka K??16960",
    "sg:city":"Mudanya",
    "sg:classifiers":[
        {
            "category":"Food & Beverages",
            "subcategory":"Groceries & Convenience Stores",
            "type":"Retail Goods"
        }
    ],
    "sg:phone":"+90 2245652017565",
    "sg:postcode":"16940",
    "sg:province":"Bursa",
    "sg:tags":[
        "olive",
        "oil"
    ],
    "wof:name":"?z Ertas Zeytincilik Ticaret San.ltd.sti.",
    "wof:placetype":"venue"
},
  "geometry": {"coordinates":[28.8633651733,40.3823852539],"type":"Point"}
}