{
  "type": "Feature",
  "properties": {
    "addr:full":"H?eyinaga Mah. Nane Sk. No:18/2 Beyoglu Osmangazi Istanbul 16330",
    "addr:housenumber":"18 / 2",
    "addr:postcode":"16330",
    "addr:street":"Eyinaga Mah. Nane Sk. No;Beyoglu Osmangazi",
    "iso:country":"TR",
    "sg:address":"H?eyinaga Mah. Nane Sk. No:18/2 Beyoglu",
    "sg:city":"Osmangazi",
    "sg:classifiers":[
        {
            "category":"Wholesale",
            "subcategory":"Medical Equipment & Supplies",
            "type":"Manufacturing & Wholesale Goods"
        }
    ],
    "sg:phone":"+90 212 252 6557",
    "sg:postcode":"16330",
    "sg:province":"Istanbul",
    "wof:name":"Vitalyim Dis Lab. Ltd. Sti.",
    "wof:placetype":"venue"
},
  "geometry": {"coordinates":[28.9861831665,41.0408554077],"type":"Point"}
}