{
  "type": "Feature",
  "properties": {
    "iso:country":"TR",
    "sg:address":"Gultepe Mah. Kardes Sok. No:12",
    "sg:city":"Hadimk?",
    "sg:classifiers":[
        {
            "category":"Home & Garden",
            "subcategory":"Kitchen Supply",
            "type":"Retail Goods"
        }
    ],
    "sg:phone":"+90 222 229 0814",
    "sg:postcode":"34555",
    "sg:province":"Eskisehir",
    "sg:tags":[
        "wardrobe"
    ],
    "wof:name":"Demre Mutfak Mobilya Dekorasyon",
    "wof:placetype":"venue"
},
  "geometry": {"coordinates":[30.5175457001,39.7700805664],"type":"Point"}
}