{
  "type": "Feature",
  "properties": {
    "iso:country":"TR",
    "sg:address":"Mezbaha Yolu No.24",
    "sg:city":"Sefak?",
    "sg:classifiers":[
        {
            "category":"Shopping",
            "subcategory":"Clothing, Apparel, & Fashions",
            "type":"Retail Goods"
        }
    ],
    "sg:phone":"+90 212 598 9880",
    "sg:province":"Istanbul",
    "sg:tags":[
        "ready",
        "wear"
    ],
    "wof:name":"Mayopen Tekstil A.s.",
    "wof:placetype":"venue"
},
  "geometry": {"coordinates":[28.8965091705,41.0402870178],"type":"Point"}
}