{
  "type": "Feature",
  "properties": {
    "addr:full":"Yesilbahce Mah. 1461. Sok. Kirmizigul Apt. No:17/5 Sisli Antalya 65710",
    "addr:housenumber":"17 / 5",
    "addr:postcode":"1461;65710",
    "addr:street":"Yesilbahce Mah.;Sok. Kirmizigul Apt. No;Sisli",
    "iso:country":"TR",
    "sg:address":"Yesilbahce Mah. 1461. Sok. Kirmizigul Apt. No:17/5",
    "sg:city":"Sisli",
    "sg:classifiers":[
        {
            "category":"Professional",
            "subcategory":"Business Services",
            "type":"Services"
        }
    ],
    "sg:phone":"+90 242 312 6326",
    "sg:postcode":"65710",
    "sg:province":"Antalya",
    "wof:name":"So Halkla Iliskiler -merchanasing Marketing -ltd.sti.",
    "wof:placetype":"venue"
},
  "geometry": {"coordinates":[30.7031345367,36.8875045776],"type":"Point"}
}