{
  "type": "Feature",
  "properties": {
    "iso:country":"TR",
    "sg:address":"12.sok. No:19 Ostim",
    "sg:city":"\u00dcmraniye",
    "sg:classifiers":[
        {
            "category":"Manufacturing",
            "subcategory":"Metals",
            "type":"Manufacturing & Wholesale Goods"
        }
    ],
    "sg:phone":"+90 312 354 0858",
    "sg:postcode":"34775",
    "sg:province":"Ankara",
    "sg:tags":[
        "industry"
    ],
    "wof:name":"Baris Galvaniz",
    "wof:placetype":"venue"
},
  "geometry": {"coordinates":[32.7440605164,39.9656639099],"type":"Point"}
}