{
  "type": "Feature",
  "properties": {
    "addr:full":"S?eyman Sirri Sk. No:0/5 Sihhiye \u00dcmraniye Ankara 81260",
    "addr:housenumber":"?;5",
    "addr:postcode":"81260",
    "addr:street":"S;Sirri Sk. No 0 /",
    "iso:country":"TR",
    "sg:address":"S?eyman Sirri Sk. No:0/5 Sihhiye",
    "sg:city":"\u00dcmraniye",
    "sg:orig_category":"General Industrial Products",
    "sg:phone":"+90 312 435 4142",
    "sg:postcode":"81260",
    "sg:province":"Ankara",
    "wof:name":"Mertas Su Aritma Filtrasyon San. Tic. Ltd. Sti.",
    "wof:placetype":"venue"
},
  "geometry": {"coordinates":[32.8560333252,39.9438743591],"type":"Point"}
}