{
  "type": "Feature",
  "properties": {
    "iso:country":"TR",
    "sg:address":"Ikitelli Organize Sanayi B?.demirciler Sanayi Sitesi B-3 Blok No:76",
    "sg:city":"Ikitelli/K\u00fc\u00e7\u00fck\u00e7ekmece",
    "sg:classifiers":[
        {
            "category":"Train Station",
            "subcategory":"Rail",
            "type":"Transportation"
        }
    ],
    "sg:phone":"+90 212549603637",
    "sg:postcode":"34670",
    "sg:province":"Istanbul",
    "sg:tags":[
        "sheet",
        "iron"
    ],
    "sg:website":"kartalbombe.com.tr",
    "wof:name":"G?ven Bombe Makina Sanayi Ve Tic.ltd.sti",
    "wof:placetype":"venue"
},
  "geometry": {"coordinates":[28.975925,41.012379],"type":"Point"}
}