{
  "type": "Feature",
  "properties": {
    "addr:full":"Bornova Bornova Izmir 35040",
    "addr:postcode":"35040",
    "iso:country":"TR",
    "sg:address":"Bornova",
    "sg:city":"Bornova",
    "sg:orig_category":"Muhtarliklar",
    "sg:phone":"+90 232 375 0066",
    "sg:postcode":"35040",
    "sg:province":"Izmir",
    "wof:name":"Evka-3 Mahallesi Muhtar: F.g?ay Isin",
    "wof:placetype":"venue"
},
  "geometry": {"coordinates":[27.2196006775,38.4662017822],"type":"Point"}
}