{
  "type": "Feature",
  "properties": {
    "iso:country":"TR",
    "sg:address":"Ahmet T?ek?",
    "sg:city":"Adilcevaz",
    "sg:classifiers":[
        {
            "category":"Government",
            "subcategory":"Office",
            "type":"Public Place"
        }
    ],
    "sg:phone":"+90 266 312 1021",
    "sg:postcode":"13500",
    "sg:province":"Balikesir",
    "sg:tags":[
        "municipality"
    ],
    "wof:name":"Ayvalik Belediye Baskani",
    "wof:placetype":"venue"
},
  "geometry": {"coordinates":[27.5164794922,40.9796104431],"type":"Point"}
}