{
  "type": "Feature",
  "properties": {
    "addr:full":"Uzuncayir Yolu Cad.ali Dayi Is Merkezi No:13 D:12 Hasanpasa- Kadikoy Istanbul 01370",
    "addr:housenumber":"cad.ali;no 13 d 12",
    "addr:postcode":"01370",
    "addr:street":"Uzuncayir Yolu;Hasanpasa Kadikoy",
    "iso:country":"TR",
    "sg:address":"Uzuncayir Yolu Cad.ali Dayi Is Merkezi No:13 D:12 Hasanpasa-",
    "sg:city":"Kadikoy",
    "sg:classifiers":[
        {
            "category":"Home & Garden",
            "subcategory":"Household Appliances",
            "type":"Retail Goods"
        }
    ],
    "sg:phone":"+90 216 428 0606",
    "sg:postcode":"01370",
    "sg:province":"Istanbul",
    "sg:tags":[
        "conditioner",
        "air"
    ],
    "wof:name":"Meg Mekanik Elektrik Insaat Taahut Ve Tic.ltd.sti.",
    "wof:placetype":"venue"
},
  "geometry": {"coordinates":[28.9759254456,41.0123786926],"type":"Point"}
}