{
  "type": "Feature",
  "properties": {
    "iso:country":"TR",
    "sg:address":"Tutuncu Mehmet Efendi Cad. No:90",
    "sg:city":"Goztepe",
    "sg:orig_category":"Carpet-kilim-blanket",
    "sg:phone":"+90 216 356 9321",
    "sg:postcode":"01220",
    "sg:province":"Istanbul",
    "wof:name":"Mavi Halicilik Pazarl. Ltd. Sti.",
    "wof:placetype":"venue"
},
  "geometry": {"coordinates":[29.0660362244,40.978477478],"type":"Point"}
}