{
  "type": "Feature",
  "properties": {
    "iso:country":"TR",
    "sg:address":"Haramidere Sanayi Sitesi B Bl. No:206 Avcilar",
    "sg:city":"Ikitelli/K\u00fc\u00e7\u00fck\u00e7ekmece",
    "sg:orig_category":"Aluminium Carpentary",
    "sg:phone":"+90 212 590 2642",
    "sg:postcode":"34670",
    "sg:province":"Istanbul",
    "wof:name":"Zaman Pancur Aliminyum Dog.a.s.",
    "wof:placetype":"venue"
},
  "geometry": {"coordinates":[28.6845092773,41.00258255],"type":"Point"}
}