{
  "type": "Feature",
  "properties": {
    "iso:country":"TR",
    "sg:address":"Cemal G. Cd. No:44/a Cebeci",
    "sg:city":"Maslak",
    "sg:classifiers":[
        {
            "category":"Farming",
            "subcategory":"Fish & Marine Products",
            "type":"Manufacturing & Wholesale Goods"
        }
    ],
    "sg:phone":"+90 312 435 2525",
    "sg:postcode":"34398",
    "sg:province":"Ankara",
    "sg:tags":[
        "automotive"
    ],
    "wof:name":"?zkardesler Otomotiv A.s.",
    "wof:placetype":"venue"
},
  "geometry": {"coordinates":[32.8698120117,39.9286613464],"type":"Point"}
}