{
  "type": "Feature",
  "properties": {
    "addr:full":"In??cad. Eke A Blok D:6 81090 Kozyatasi Kizilay Istanbul 06640",
    "addr:housenumber":"blok d 6",
    "addr:postcode":"81090;06640",
    "addr:street":"In ? ? Cad.;A",
    "iso:country":"TR",
    "sg:address":"In??cad. Eke A Blok D:6 81090 Kozyatasi",
    "sg:city":"Kizilay",
    "sg:classifiers":[
        {
            "category":"Building & Trades",
            "subcategory":"Plumbing",
            "type":"Services"
        }
    ],
    "sg:phone":"+90 216 456 1128",
    "sg:postcode":"06640",
    "sg:province":"Istanbul",
    "wof:name":"Eltes Insaat Tesisat Sanayi Ve Ticaret A.s.",
    "wof:placetype":"venue"
},
  "geometry": {"coordinates":[28.9759254456,41.0123786926],"type":"Point"}
}