{
  "type": "Feature",
  "properties": {
    "addr:full":"Eski Londra Asfalti No:13 Sirinevler Bak\u0131rk\u00f6y Istanbul",
    "addr:housenumber":"13",
    "addr:street":"Eski Londra Asfalti No",
    "iso:country":"TR",
    "sg:address":"Eski Londra Asfalti No:13 Sirinevler",
    "sg:city":"Bak\u0131rk\u00f6y",
    "sg:classifiers":[
        {
            "category":"Utilities",
            "subcategory":"Natural Gas",
            "type":"Services"
        }
    ],
    "sg:phone":"+90 212 551 3999",
    "sg:province":"Istanbul",
    "sg:tags":[
        "tank-heating-natural"
    ],
    "wof:name":"A.f. Insaat Gida Isi San. Tic. A.s.",
    "wof:placetype":"venue"
},
  "geometry": {"coordinates":[28.8464202881,41.0033416748],"type":"Point"}
}