{
  "type": "Feature",
  "properties": {
    "addr:full":"Semsettin G?altay Cad. Beyazg? Sok.no:19 Suadiye Eminonu Istanbul",
    "addr:housenumber":"?;beyazg ?;19",
    "addr:street":"Semsettin G;Cad.;Sok.No",
    "iso:country":"TR",
    "sg:address":"Semsettin G?altay Cad. Beyazg? Sok.no:19 Suadiye",
    "sg:city":"Eminonu",
    "sg:classifiers":[
        {
            "category":"Shopping",
            "subcategory":"Hobbies, Toys, & Games",
            "type":"Retail Goods"
        }
    ],
    "sg:phone":"+90 216 384 0506",
    "sg:province":"Istanbul",
    "sg:tags":[
        "equipment",
        "toy"
    ],
    "wof:name":"Dogam Pazarlama Finans Ltd.sti",
    "wof:placetype":"venue"
},
  "geometry": {"coordinates":[28.9861793518,41.040851593],"type":"Point"}
}