{
  "type": "Feature",
  "properties": {
    "addr:full":"?akmak Cad. No: 28/d Alsancak Hatay 01365",
    "addr:housenumber":"?;28 / d",
    "addr:postcode":"01365",
    "addr:street":"Akmak Cad. No",
    "iso:country":"TR",
    "sg:address":"?akmak Cad. No: 28/d",
    "sg:city":"Alsancak",
    "sg:classifiers":[
        {
            "category":"Travel",
            "subcategory":"Travel Agent",
            "type":"Entertainment"
        }
    ],
    "sg:phone":"+90 326 613 0361",
    "sg:postcode":"01365",
    "sg:province":"Hatay",
    "sg:tags":[
        "agency",
        "tourism"
    ],
    "wof:name":"Catoni Turizm (iskenderun Subesi)",
    "wof:placetype":"venue"
},
  "geometry": {"coordinates":[36.2382698059,36.4112091064],"type":"Point"}
}