{
  "type": "Feature",
  "properties": {
    "addr:full":"Yesiltepe Mh. 39 Nolu Sk. No: 65 Osmangazi Sakarya 16220",
    "addr:housenumber":"39;sk. no 65",
    "addr:postcode":"16220",
    "addr:street":"Yesiltepe Mh.",
    "iso:country":"TR",
    "sg:address":"Yesiltepe Mh. 39 Nolu Sk. No: 65",
    "sg:city":"Osmangazi",
    "sg:classifiers":[
        {
            "category":"Wholesale",
            "subcategory":"Auto Parts",
            "type":"Manufacturing & Wholesale Goods"
        }
    ],
    "sg:phone":"+90 264 276 6345",
    "sg:postcode":"16220",
    "sg:province":"Sakarya",
    "sg:tags":[
        "spare"
    ],
    "wof:name":"G?nes ?zel Renault Servisi",
    "wof:placetype":"venue"
},
  "geometry": {"coordinates":[30.3791446686,40.7734336853],"type":"Point"}
}