{
  "type": "Feature",
  "properties": {
    "iso:country":"TR",
    "sg:address":"?inarli Sk. Oto San. Sit. No:11 Seyrantepe",
    "sg:city":"Bagcilar",
    "sg:classifiers":[
        {
            "category":"Shopping",
            "subcategory":"Stationery & Office Supplies",
            "type":"Retail Goods"
        }
    ],
    "sg:phone":"+90 212 264 2588",
    "sg:postcode":"33115",
    "sg:province":"Istanbul",
    "sg:tags":[
        "paper"
    ],
    "wof:name":"Tarsa Kagit Ve Kimya San. A.s.",
    "wof:placetype":"venue"
},
  "geometry": {"coordinates":[28.9759254456,41.0123786926],"type":"Point"}
}