{
  "type": "Feature",
  "properties": {
    "iso:country":"TR",
    "sg:address":"Persembe Pazari Nafe Sk. Nafe Han K:2 No:17/8",
    "sg:city":"Karak\u00f6y",
    "sg:classifiers":[
        {
            "category":"Utilities",
            "subcategory":"Natural Gas",
            "type":"Services"
        }
    ],
    "sg:phone":"+90 212 255 5610",
    "sg:province":"Istanbul",
    "sg:tags":[
        "tank-heating-natural"
    ],
    "wof:name":"Akvan Vana San. Tic. Ltd. Sti.",
    "wof:placetype":"venue"
},
  "geometry": {"coordinates":[28.9861831665,41.0408554077],"type":"Point"}
}