{
  "type": "Feature",
  "properties": {
    "iso:country":"TR",
    "sg:address":"Molla Bayiri Sk.no16/3",
    "sg:city":"Findikli",
    "sg:classifiers":[
        {
            "category":"Landmark",
            "subcategory":"Square",
            "type":"Public Place"
        }
    ],
    "sg:phone":"+90 2122938521339",
    "sg:postcode":"01470",
    "sg:province":"Istanbul",
    "sg:tags":[
        "surveyor"
    ],
    "wof:name":"Med Marine Denizcilik Ltd.sti.",
    "wof:placetype":"venue"
},
  "geometry": {"coordinates":[28.975925,41.012379],"type":"Point"}
}