{
  "type": "Feature",
  "properties": {
    "addr:full":"Ismetpasa Cd.no. 48 Ikitelli Antalya 34306",
    "addr:housenumber":"48",
    "addr:postcode":"34306",
    "addr:street":"Ikitelli",
    "iso:country":"TR",
    "sg:address":"Ismetpasa Cd.no. 48",
    "sg:city":"Ikitelli",
    "sg:classifiers":[
        {
            "category":"Farming",
            "subcategory":"Poultry Farm",
            "type":"Manufacturing & Wholesale Goods"
        }
    ],
    "sg:phone":"+90 242 241 9057",
    "sg:postcode":"34306",
    "sg:province":"Antalya",
    "sg:tags":[
        "poultry-turkey-ostrich"
    ],
    "wof:name":"An-tav Antalya Tavuk Yumurta A.s.",
    "wof:placetype":"venue"
},
  "geometry": {"coordinates":[30.7059688568,36.8899688721],"type":"Point"}
}