{
  "type": "Feature",
  "properties": {
    "iso:country":"TR",
    "sg:address":"Reyhan Cad. No:13 K.1 Besyol-",
    "sg:city":"Sefakoy",
    "sg:classifiers":[
        {
            "category":"Shopping",
            "subcategory":"Clothing, Apparel, & Fashions",
            "type":"Retail Goods"
        }
    ],
    "sg:phone":"+90 212 624 0041",
    "sg:postcode":"42000",
    "sg:province":"Istanbul",
    "sg:tags":[
        "ready",
        "wear"
    ],
    "wof:name":"Ozerteks Tekstil San. Ve Tic. Ltd. Sti.",
    "wof:placetype":"venue"
},
  "geometry": {"coordinates":[28.8276500702,41.0093002319],"type":"Point"}
}