{
  "type": "Feature",
  "properties": {
    "iso:country":"TR",
    "sg:address":"Yildiz Cad. No: 45/1",
    "sg:city":"Besiktas",
    "sg:classifiers":[
        {
            "category":"Home & Garden",
            "subcategory":"Household Appliances",
            "type":"Retail Goods"
        }
    ],
    "sg:phone":"+90 212 260 7803",
    "sg:postcode":"75200",
    "sg:province":"Istanbul",
    "sg:tags":[
        "conditioner",
        "air"
    ],
    "wof:name":"Isites Yapi Ve Endustri Tesisleri San Ve Tic. Ltd. Sti.",
    "wof:placetype":"venue"
},
  "geometry": {"coordinates":[29.0060081482,41.0481567383],"type":"Point"}
}