{
  "type": "Feature",
  "properties": {
    "addr:full":"Kurtulus Cd. No:46/2 Kurtulus Istanbul 01470",
    "addr:housenumber":"no 46 / 2",
    "addr:postcode":"01470",
    "iso:country":"TR",
    "sg:address":"Kurtulus Cd. No:46/2",
    "sg:city":"Kurtulus",
    "sg:classifiers":[
        {
            "category":"Farming",
            "subcategory":"Farm & Veterinary Services",
            "type":"Manufacturing & Wholesale Goods"
        }
    ],
    "sg:phone":"+90 212 225 9857",
    "sg:postcode":"01470",
    "sg:province":"Istanbul",
    "sg:tags":[
        "veterinarian"
    ],
    "wof:name":"Kurtulus Veteriner Hiz.ltd.sti.",
    "wof:placetype":"venue"
},
  "geometry": {"coordinates":[28.8395271301,41.0378456116],"type":"Point"}
}