{
  "type": "Feature",
  "properties": {
    "addr:full":"Istiklal Mah. Dilek Sok. No:14 Nazilli Eskisehir 65600",
    "addr:housenumber":"no 14",
    "addr:postcode":"65600",
    "addr:street":"Istiklal Mah. Dilek Sok.;Eskisehir",
    "iso:country":"TR",
    "sg:address":"Istiklal Mah. Dilek Sok. No:14",
    "sg:city":"Nazilli",
    "sg:classifiers":[
        {
            "category":"Home & Garden",
            "subcategory":"Household Appliances",
            "type":"Retail Goods"
        }
    ],
    "sg:phone":"+90 22223212212323",
    "sg:postcode":"65600",
    "sg:province":"Eskisehir",
    "sg:tags":[
        "utensil",
        "electrical"
    ],
    "wof:name":"Reta Elektromekanik San. Ve Tic. A.s.",
    "wof:placetype":"venue"
},
  "geometry": {"coordinates":[30.5154705048,39.7782936096],"type":"Point"}
}