{
  "type": "Feature",
  "properties": {
    "addr:full":"Ulucami Cd. K?ahya M?esi B?ek. Sirinyer K?tahya 35140",
    "addr:postcode":"35140",
    "addr:street":"Tahya",
    "iso:country":"TR",
    "sg:address":"Ulucami Cd. K?ahya M?esi B?ek.",
    "sg:city":"Sirinyer",
    "sg:classifiers":[
        {
            "category":"Organizations",
            "subcategory":"Membership Organization",
            "type":"Services"
        }
    ],
    "sg:phone":"+90 274 223 6990",
    "sg:postcode":"35140",
    "sg:province":"K?tahya",
    "wof:name":"Kutahya Muze. Kor. Yasat. Dernegi",
    "wof:placetype":"venue"
},
  "geometry": {"coordinates":[27.145980835,38.4284286499],"type":"Point"}
}