{
  "type": "Feature",
  "properties": {
    "addr:full":"Cemal Ulusoy Cad. No:13 Sefak? Caglayan Istanbul 07600",
    "addr:housenumber":"13;?",
    "addr:postcode":"07600",
    "addr:street":"Ulusoy Cad. No",
    "iso:country":"TR",
    "sg:address":"Cemal Ulusoy Cad. No:13 Sefak?",
    "sg:city":"Caglayan",
    "sg:classifiers":[
        {
            "category":"Home & Garden",
            "subcategory":"Home Furnishings",
            "type":"Retail Goods"
        }
    ],
    "sg:phone":"+90 212 426 4691",
    "sg:postcode":"07600",
    "sg:province":"Istanbul",
    "sg:tags":[
        "curtaining",
        "-",
        "upholstering"
    ],
    "wof:name":"Bissa Tekstil Ve Turizm San.tic.ltd.sti",
    "wof:placetype":"venue"
},
  "geometry": {"coordinates":[28.812235,41.010742],"type":"Point"}
}