{
  "type": "Feature",
  "properties": {
    "addr:full":"Maltepe Cad.nebati Is Merkezi No:52/37 Bayrampasa Y.dudullu Istanbul",
    "addr:housenumber":"no 52 / 37",
    "addr:street":"Maltepe",
    "iso:country":"TR",
    "sg:address":"Maltepe Cad.nebati Is Merkezi No:52/37 Bayrampasa",
    "sg:city":"Y.dudullu",
    "sg:orig_category":"General Industrial Products",
    "sg:phone":"+90 212 501 4920",
    "sg:province":"Istanbul",
    "wof:name":"Teknoser Ltd. Sti.",
    "wof:placetype":"venue"
},
  "geometry": {"coordinates":[28.9011554718,41.0516204834],"type":"Point"}
}