{
  "type": "Feature",
  "properties": {
    "iso:country":"TR",
    "sg:address":"Balikesir Asfalti 5. Km Pk:50 Bandirma",
    "sg:city":"Bornova",
    "sg:classifiers":[
        {
            "category":"Manufacturing",
            "subcategory":"Tools & Machinery",
            "type":"Manufacturing & Wholesale Goods"
        }
    ],
    "sg:phone":"+90 266 733 8550",
    "sg:postcode":"35040",
    "sg:province":"Balikesir",
    "sg:tags":[
        "machine",
        "industry"
    ],
    "wof:name":"Yemtar Pnomatik Kantar San. Tic. Ltd. Sti.",
    "wof:placetype":"venue"
},
  "geometry": {"coordinates":[27.8833007812,39.6520996094],"type":"Point"}
}