{
  "type": "Feature",
  "properties": {
    "addr:full":"Fatih Sultan Mehmet San.sit.b3 Blok No: 41-42 Umraniye Pendik Istanbul 34916",
    "addr:housenumber":"san.sit.b3 blok no 41-42",
    "addr:postcode":"34916",
    "addr:street":"Fatih Sultan Mehmet",
    "iso:country":"TR",
    "sg:address":"Fatih Sultan Mehmet San.sit.b3 Blok No: 41-42 Umraniye",
    "sg:city":"Pendik",
    "sg:classifiers":[
        {
            "category":"Manufacturing",
            "subcategory":"Tools & Machinery",
            "type":"Manufacturing & Wholesale Goods"
        }
    ],
    "sg:phone":"+90 216 316 6171",
    "sg:postcode":"34916",
    "sg:province":"Istanbul",
    "sg:tags":[
        "machine",
        "industry"
    ],
    "wof:name":"Kamon Monopomp",
    "wof:placetype":"venue"
},
  "geometry": {"coordinates":[28.9759254456,41.0123786926],"type":"Point"}
}