{
  "type": "Feature",
  "properties": {
    "iso:country":"TR",
    "sg:address":"?mraniye",
    "sg:city":"\u00dcmraniye",
    "sg:classifiers":[
        {
            "category":"Communications",
            "type":"Services"
        }
    ],
    "sg:phone":"+90 216 000 0000",
    "sg:postcode":"81240",
    "sg:province":"Istanbul",
    "sg:tags":[
        "web",
        "design"
    ],
    "wof:name":"Maviportakal",
    "wof:placetype":"venue"
},
  "geometry": {"coordinates":[29.1437149048,41.016418457],"type":"Point"}
}