{
  "type": "Feature",
  "properties": {
    "addr:full":"Ornek San. Sitesi No:4/8 Baspinar Gaziantep 07800",
    "addr:postcode":"07800",
    "addr:street":"Ornek",
    "iso:country":"TR",
    "sg:address":"Ornek San. Sitesi No:4/8",
    "sg:city":"Baspinar",
    "sg:classifiers":[
        {
            "category":"Shopping",
            "subcategory":"Crafts & Fabrics",
            "type":"Retail Goods"
        }
    ],
    "sg:phone":"+90 342 235 6426",
    "sg:postcode":"07800",
    "sg:province":"Gaziantep",
    "sg:tags":[
        "yarn"
    ],
    "wof:name":"Fanteks Fantazi Iplik",
    "wof:placetype":"venue"
},
  "geometry": {"coordinates":[37.3761024475,37.0629463196],"type":"Point"}
}