{
  "type": "Feature",
  "properties": {
    "addr:full":"Genclik Mh. 30 Agust. Cd. No.35 Cine Antalya 01370",
    "addr:housenumber":"30",
    "addr:postcode":"01370",
    "addr:street":"Genclik Mh.;Agust. Cd. No.35",
    "iso:country":"TR",
    "sg:address":"Genclik Mh. 30 Agust. Cd. No.35",
    "sg:city":"Cine",
    "sg:classifiers":[
        {
            "category":"Food & Beverages",
            "subcategory":"Meat & Fish",
            "type":"Retail Goods"
        }
    ],
    "sg:phone":"+90 242 241 9579",
    "sg:postcode":"01370",
    "sg:province":"Antalya",
    "sg:tags":[
        "product"
    ],
    "wof:name":"S?nmez Et Ve Gida Mad. Ltd.sti.",
    "wof:placetype":"venue"
},
  "geometry": {"coordinates":[30.7092056274,36.8790512085],"type":"Point"}
}