{
  "type": "Feature",
  "properties": {
    "iso:country":"TR",
    "sg:address":"B.haydar Efendi Sk. No.12-14/c Beyazit",
    "sg:city":"\u00c7orlu",
    "sg:classifiers":[
        {
            "category":"Shopping",
            "subcategory":"Luggage & Leather Goods",
            "type":"Retail Goods"
        }
    ],
    "sg:phone":"+90 212 518 2217",
    "sg:province":"Istanbul",
    "sg:tags":[
        "leather-fur",
        "wear"
    ],
    "wof:name":"Elibol Deri Konf. Ltd.sti.",
    "wof:placetype":"venue"
},
  "geometry": {"coordinates":[28.9649524689,41.0075263977],"type":"Point"}
}