{
  "type": "Feature",
  "properties": {
    "iso:country":"TR",
    "sg:address":"Tuna Cad. 30/a Yenisehir",
    "sg:city":"Merkez",
    "sg:classifiers":[
        {
            "category":"Wholesale",
            "subcategory":"Medical Equipment & Supplies",
            "type":"Manufacturing & Wholesale Goods"
        }
    ],
    "sg:phone":"+90 312 435 5301",
    "sg:postcode":"26000",
    "sg:province":"Ankara",
    "sg:tags":[
        "material"
    ],
    "wof:name":"Sasan Ltd.sti.",
    "wof:placetype":"venue"
},
  "geometry": {"coordinates":[29.2784557343,40.9379081726],"type":"Point"}
}