{
  "type": "Feature",
  "properties": {
    "addr:full":"1607.sok. No:21/a Doganlar Ikitelli/K\u00fc\u00e7\u00fck\u00e7ekmece Izmir 34670",
    "addr:housenumber":"no 21 / a",
    "addr:postcode":"34670",
    "iso:country":"TR",
    "sg:address":"1607.sok. No:21/a Doganlar",
    "sg:city":"Ikitelli/K\u00fc\u00e7\u00fck\u00e7ekmece",
    "sg:classifiers":[
        {
            "category":"Manufacturing",
            "subcategory":"Metals",
            "type":"Manufacturing & Wholesale Goods"
        }
    ],
    "sg:phone":"+90 232 478 3470",
    "sg:postcode":"34670",
    "sg:province":"Izmir",
    "sg:tags":[
        "iron-steel",
        "peoducts"
    ],
    "wof:name":"Karhan Metal",
    "wof:placetype":"venue"
},
  "geometry": {"coordinates":[27.2555713654,38.4450874329],"type":"Point"}
}