{
  "type": "Feature",
  "properties": {
    "iso:country":"TR",
    "sg:address":"Meclisi Meblusan Yokusu Abisa Ismek. No.48 K.2",
    "sg:city":"Findikli",
    "sg:classifiers":[
        {
            "category":"Marine",
            "type":"Transportation"
        }
    ],
    "sg:phone":"+90 212 293 2400",
    "sg:postcode":"01470",
    "sg:province":"Istanbul",
    "sg:tags":[
        "shipowner"
    ],
    "wof:name":"Bati Nakl. A.s. .",
    "wof:placetype":"venue"
},
  "geometry": {"coordinates":[28.975925,41.012379],"type":"Point"}
}