{
  "type": "Feature",
  "properties": {
    "addr:full":"Kazim Karabekir Cad. Ornek Han No:27/39 Iskitler Iskenderun Ankara 31200",
    "addr:housenumber":"27 / 39",
    "addr:postcode":"31200",
    "addr:street":"Karabekir Cad. Ornek Han No;Iskitler",
    "iso:country":"TR",
    "sg:address":"Kazim Karabekir Cad. Ornek Han No:27/39 Iskitler",
    "sg:city":"Iskenderun",
    "sg:classifiers":[
        {
            "category":"Building & Trades",
            "subcategory":"Plumbing",
            "type":"Services"
        }
    ],
    "sg:phone":"+90 312 342 0470",
    "sg:postcode":"31200",
    "sg:province":"Ankara",
    "sg:tags":[
        "filter",
        "industry"
    ],
    "wof:name":"Dozer San.tic. Ltd.sti.",
    "wof:placetype":"venue"
},
  "geometry": {"coordinates":[32.8560333252,39.9438743591],"type":"Point"}
}