{
  "type": "Feature",
  "properties": {
    "iso:country":"TR",
    "sg:address":"Zahire Borsa Sk. Rasimpasa Ishani K.2 Eminonu",
    "sg:city":"Kagithane",
    "sg:classifiers":[
        {
            "category":"Shopping",
            "subcategory":"Stationery & Office Supplies",
            "type":"Retail Goods"
        }
    ],
    "sg:phone":"+90 212 512 6851",
    "sg:postcode":"80690",
    "sg:province":"Istanbul",
    "wof:name":"Esmo Buro Araclari Ve Tersim Malz. Tic. A.s.",
    "wof:placetype":"venue"
},
  "geometry": {"coordinates":[28.975925,41.012379],"type":"Point"}
}