{
  "type": "Feature",
  "properties": {
    "addr:full":"Sisli Merkez - Sisli Ikitelli Istanbul 34306",
    "addr:postcode":"34306",
    "iso:country":"TR",
    "sg:address":"Sisli Merkez - Sisli",
    "sg:city":"Ikitelli",
    "sg:classifiers":[
        {
            "category":"Banks & Credit Unions",
            "subcategory":"Investment Brokerage",
            "type":"Services"
        }
    ],
    "sg:phone":"+90 212 231 2209",
    "sg:postcode":"34306",
    "sg:province":"Istanbul",
    "sg:tags":[
        "aid",
        "material",
        "first"
    ],
    "wof:name":"Sisli Etfal Hastanesi",
    "wof:placetype":"venue"
},
  "geometry": {"coordinates":[28.9873638153,41.0617904663],"type":"Point"}
}