{
  "type": "Feature",
  "properties": {
    "addr:full":"Menemen Asfalti 2.km. Menemen Izmir 35660",
    "addr:housenumber":"menemen",
    "addr:postcode":"35660",
    "addr:street":"Izmir",
    "iso:country":"TR",
    "sg:address":"Menemen Asfalti 2.km.",
    "sg:city":"Menemen",
    "sg:classifiers":[
        {
            "category":"Shopping",
            "subcategory":"Clothing, Apparel, & Fashions",
            "type":"Retail Goods"
        }
    ],
    "sg:phone":"+90 232 831 6336",
    "sg:postcode":"35660",
    "sg:province":"Izmir",
    "sg:tags":[
        "ready",
        "wear"
    ],
    "wof:name":"Karyateks Tekstil Sanayi Ve Ticaret",
    "wof:placetype":"venue"
},
  "geometry": {"coordinates":[27.1296863556,38.4186973572],"type":"Point"}
}