{
  "type": "Feature",
  "properties": {
    "addr:full":"Koklupinar Mah.koymen Cad.no:2 Osmangazi Bursa 46050",
    "addr:housenumber":"2",
    "addr:postcode":"46050",
    "addr:street":"Cad.No;Bursa",
    "iso:country":"TR",
    "sg:address":"Koklupinar Mah.koymen Cad.no:2",
    "sg:city":"Osmangazi",
    "sg:classifiers":[
        {
            "category":"Shopping",
            "subcategory":"Clothing, Apparel, & Fashions",
            "type":"Retail Goods"
        }
    ],
    "sg:phone":"+90 224 250 8462",
    "sg:postcode":"46050",
    "sg:province":"Bursa",
    "sg:tags":[
        "ready",
        "wear"
    ],
    "wof:name":"M.sait Makina San.",
    "wof:placetype":"venue"
},
  "geometry": {"coordinates":[29.0580043793,40.1947555542],"type":"Point"}
}