{
  "type": "Feature",
  "properties": {
    "iso:country":"TR",
    "sg:address":"P.o.box 313",
    "sg:city":"Merkez",
    "sg:classifiers":[
        {
            "category":"Shopping",
            "subcategory":"Florist",
            "type":"Retail Goods"
        }
    ],
    "sg:phone":"+90 352 231 9355",
    "sg:postcode":"10100",
    "sg:province":"Kayseri",
    "sg:tags":[
        "flower"
    ],
    "wof:name":"Acelya Flowers International Flower Delivery Services Inc.",
    "wof:placetype":"venue"
},
  "geometry": {"coordinates":[35.8325004578,38.625],"type":"Point"}
}