{
  "type": "Feature",
  "properties": {
    "iso:country":"TR",
    "sg:address":"Vatan Mh. Cumhuriyet Cd. Ferah Ishani No:9 Bayrampasa",
    "sg:city":"\u00dcmraniye",
    "sg:classifiers":[
        {
            "category":"Manufacturing",
            "subcategory":"Rubber & Plastics",
            "type":"Manufacturing & Wholesale Goods"
        }
    ],
    "sg:phone":"+90 1215440453",
    "sg:province":"Istanbul",
    "sg:tags":[
        "industry"
    ],
    "wof:name":"Kalay Plastik San.",
    "wof:placetype":"venue"
},
  "geometry": {"coordinates":[28.9011554718,41.0516204834],"type":"Point"}
}