{
  "type": "Feature",
  "properties": {
    "addr:full":"Sakizg??sk. No:31 Bahariye Kadik? Kusadasi Istanbul 09400",
    "addr:housenumber":"31",
    "addr:postcode":"09400",
    "addr:street":"Sk. No",
    "iso:country":"TR",
    "sg:address":"Sakizg??sk. No:31 Bahariye Kadik?",
    "sg:city":"Kusadasi",
    "sg:orig_category":"Art Galeries",
    "sg:phone":"+90 216 337 9637",
    "sg:postcode":"09400",
    "sg:province":"Istanbul",
    "wof:name":"Hakan Sinemasi",
    "wof:placetype":"venue"
},
  "geometry": {"coordinates":[28.9861831665,41.0408554077],"type":"Point"}
}