{
  "type": "Feature",
  "properties": {
    "iso:country":"TR",
    "sg:address":"Eski Kepsut Cad. 3.km.",
    "sg:city":"Karatay",
    "sg:classifiers":[
        {
            "category":"Wholesale",
            "subcategory":"Farm Supplies",
            "type":"Manufacturing & Wholesale Goods"
        }
    ],
    "sg:phone":"+90 266 243 2494",
    "sg:postcode":"42000",
    "sg:province":"Balikesir",
    "sg:tags":[
        "feed",
        "industry"
    ],
    "wof:name":"Bilcanli Yem Sanayi",
    "wof:placetype":"venue"
},
  "geometry": {"coordinates":[27.8833007812,39.6520996094],"type":"Point"}
}