{
  "type": "Feature",
  "properties": {
    "iso:country":"TR",
    "sg:address":"Kodaman Sk. No:56/3",
    "sg:city":"Osmanbey",
    "sg:classifiers":[
        {
            "category":"Shopping",
            "subcategory":"Clothing, Apparel, & Fashions",
            "type":"Retail Goods"
        }
    ],
    "sg:phone":"+90 212 233 7808",
    "sg:postcode":"63000",
    "sg:province":"Istanbul",
    "sg:tags":[
        "woman",
        "wear"
    ],
    "wof:name":"Pirlanta Dah. Tic. Ltd. Sti. .",
    "wof:placetype":"venue"
},
  "geometry": {"coordinates":[28.9888916016,41.0558242798],"type":"Point"}
}