{
  "type": "Feature",
  "properties": {
    "iso:country":"TR",
    "sg:address":"Kukurtlu Mah. Basaran Sok. Ornek Apt.no:15/a Osmangazi",
    "sg:city":"Kad\u0131k\u00f6y",
    "sg:classifiers":[
        {
            "category":"Professional",
            "subcategory":"Detective & Security Services",
            "type":"Services"
        }
    ],
    "sg:phone":"+90 224 236 9322",
    "sg:province":"Bursa",
    "sg:tags":[
        "material"
    ],
    "wof:name":"Yansi Iletisim Ve Guvenlik Sistemleri Ltd. Sti.",
    "wof:placetype":"venue"
},
  "geometry": {"coordinates":[29.000948,40.218124],"type":"Point"}
}