{
  "type": "Feature",
  "properties": {
    "addr:full":"Sarihamzali K??girisi No:43 Mahmutbey Adana 46600",
    "addr:postcode":"46600",
    "addr:street":"No 43",
    "iso:country":"TR",
    "sg:address":"Sarihamzali K??girisi No:43",
    "sg:city":"Mahmutbey",
    "sg:classifiers":[
        {
            "category":"Food & Beverages",
            "subcategory":"Candy",
            "type":"Retail Goods"
        }
    ],
    "sg:phone":"+90 322 441 0353",
    "sg:postcode":"46600",
    "sg:province":"Adana",
    "sg:tags":[
        "biscuit-chocolate-candy"
    ],
    "wof:name":"Kayaoglu Gida San.ve Tic.ltd.sti.",
    "wof:placetype":"venue"
},
  "geometry": {"coordinates":[35.313736,37.000717],"type":"Point"}
}