{
  "type": "Feature",
  "properties": {
    "addr:full":"H?riyet Mh. H?riyet Cd. G?es ?ik. No:36 Sirinevler Beylikd?? 34905 Istanbul",
    "addr:housenumber":"?;?;?;no 36",
    "addr:postcode":"34905",
    "addr:street":"Riyet Mh. H;Riyet Cd. G;Ik.",
    "iso:country":"TR",
    "sg:address":"H?riyet Mh. H?riyet Cd. G?es ?ik. No:36 Sirinevler",
    "sg:city":"Beylikd?? 34905",
    "sg:classifiers":[
        {
            "category":"Manufacturing",
            "subcategory":"Tools & Machinery",
            "type":"Manufacturing & Wholesale Goods"
        }
    ],
    "sg:phone":"+90 212 503 2309",
    "sg:province":"Istanbul",
    "sg:tags":[
        "machine",
        "industry"
    ],
    "wof:name":"Dogus ?t? Makina San.",
    "wof:placetype":"venue"
},
  "geometry": {"coordinates":[28.8469848633,40.999080658],"type":"Point"}
}