{
  "type": "Feature",
  "properties": {
    "addr:full":"Inonu Bulvari No.14 Istanbul Kusadasi",
    "addr:housenumber":"no.14",
    "addr:street":"Inonu Bulvari",
    "iso:country":"TR",
    "sg:address":"Inonu Bulvari No.14",
    "sg:city":"Istanbul",
    "sg:classifiers":[
        {
            "category":"Travel",
            "subcategory":"Travel Agent",
            "type":"Entertainment"
        }
    ],
    "sg:province":"Kusadasi",
    "wof:name":"Anker Turizm San Vc Tic, Ltd.",
    "wof:placetype":"venue"
},
  "geometry": {"coordinates":[27.2473583221,37.8581733704],"type":"Point"}
}