{
  "type": "Feature",
  "properties": {
    "addr:full":"D?zce Bayrampasa D?zce 36100",
    "addr:postcode":"36100",
    "addr:street":"Zce",
    "iso:country":"TR",
    "sg:address":"D?zce",
    "sg:city":"Bayrampasa",
    "sg:classifiers":[
        {
            "category":"Education",
            "subcategory":"University",
            "type":"Public Place"
        }
    ],
    "sg:phone":"+90 380524138081",
    "sg:postcode":"36100",
    "sg:province":"D?zce",
    "sg:tags":[
        "national",
        "chief"
    ],
    "wof:name":"D?ce Milli Egitim M?d?rl?g?",
    "wof:placetype":"venue"
},
  "geometry": {"coordinates":[43.0778312683,40.5926704407],"type":"Point"}
}