{
  "type": "Feature",
  "properties": {
    "iso:country":"TR",
    "sg:address":"S?er Mh. Adnan K. Cd. No:58 Zeytinburnu",
    "sg:city":"Melikgazi",
    "sg:classifiers":[
        {
            "category":"Wholesale",
            "subcategory":"Durable Goods & Equipment",
            "type":"Manufacturing & Wholesale Goods"
        }
    ],
    "sg:phone":"+90 212 547 8609",
    "sg:postcode":"38030",
    "sg:province":"Istanbul",
    "sg:tags":[
        "consumer"
    ],
    "wof:name":"Y?ksel Halici. Tic.",
    "wof:placetype":"venue"
},
  "geometry": {"coordinates":[28.9861831665,41.0408554077],"type":"Point"}
}