{
  "type": "Feature",
  "properties": {
    "iso:country":"TR",
    "sg:address":"Farabi Sk. No:13/b",
    "sg:city":"Kavaklidere",
    "sg:classifiers":[
        {
            "category":"Shopping",
            "subcategory":"Florist",
            "type":"Retail Goods"
        }
    ],
    "sg:phone":"+90 312 467 2807",
    "sg:postcode":"35040",
    "sg:province":"Ankara",
    "sg:tags":[
        "flower"
    ],
    "wof:name":"Eser ?i?ekcilik Tic. Pazarlama A.s.",
    "wof:placetype":"venue"
},
  "geometry": {"coordinates":[32.5817298889,39.9880256653],"type":"Point"}
}