{
  "type": "Feature",
  "properties": {
    "addr:full":"Konay Yolu No: 193 06520 Balgat Ankara Melikgazi Ankara 38030",
    "addr:housenumber":"no",
    "addr:postcode":"06520;38030",
    "addr:street":"Konay Yolu",
    "iso:country":"TR",
    "sg:address":"Konay Yolu No: 193 06520 Balgat Ankara",
    "sg:city":"Melikgazi",
    "sg:classifiers":[
        {
            "category":"Food & Beverages",
            "subcategory":"Bakery",
            "type":"Retail Goods"
        }
    ],
    "sg:phone":"+90 312 287 3530",
    "sg:postcode":"38030",
    "sg:province":"Ankara",
    "sg:tags":[
        "grain",
        "cereal"
    ],
    "wof:name":"Ankara Un San As",
    "wof:placetype":"venue"
},
  "geometry": {"coordinates":[32.8604812622,39.9429283142],"type":"Point"}
}