{
  "type": "Feature",
  "properties": {
    "iso:country":"TR",
    "sg:address":"1202 / 1 Sk. No. 69 / 608 Yenisehir",
    "sg:city":"Mersin",
    "sg:classifiers":[
        {
            "category":"Personal",
            "subcategory":"Sauna",
            "type":"Services"
        }
    ],
    "sg:phone":"+90 232 459 5353",
    "sg:postcode":"52750",
    "sg:province":"Izmir",
    "sg:tags":[
        "pool"
    ],
    "wof:name":"Beme Havuzculuk Insaat Turizm San. Tic. Ltd. Sti.",
    "wof:placetype":"venue"
},
  "geometry": {"coordinates":[27.170172,38.425434],"type":"Point"}
}