{
  "type": "Feature",
  "properties": {
    "iso:country":"TR",
    "sg:address":"Acibadem Cad. 11/a",
    "sg:city":"Kadikoy",
    "sg:classifiers":[
        {
            "category":"Home & Garden",
            "subcategory":"Household Appliances",
            "type":"Retail Goods"
        }
    ],
    "sg:phone":"+90 216418094647",
    "sg:postcode":"01370",
    "sg:province":"Istanbul",
    "sg:tags":[
        "conditioner",
        "air"
    ],
    "wof:name":"Mert Muhendislik Insaat San Ve Tic A.s.",
    "wof:placetype":"venue"
},
  "geometry": {"coordinates":[29.0345573425,40.9952850342],"type":"Point"}
}