{
  "type": "Feature",
  "properties": {
    "addr:full":"Fener Mahallesi Sinanoglu Caddesi Oktay Apt. Harbiye Antalya 31080",
    "addr:postcode":"31080",
    "addr:street":"Fener Mahallesi Sinanoglu Caddesi Oktay Apt. Harbiye",
    "iso:country":"TR",
    "sg:address":"Fener Mahallesi Sinanoglu Caddesi Oktay Apt.",
    "sg:city":"Harbiye",
    "sg:classifiers":[
        {
            "category":"Banks & Credit Unions",
            "subcategory":"Investment Brokerage",
            "type":"Services"
        }
    ],
    "sg:phone":"+90 242323404748",
    "sg:postcode":"31080",
    "sg:province":"Antalya",
    "sg:tags":[
        "line",
        "air"
    ],
    "wof:name":"Sunexpress",
    "wof:placetype":"venue"
},
  "geometry": {"coordinates":[30.7031345367,36.8875045776],"type":"Point"}
}