{
  "type": "Feature",
  "properties": {
    "addr:full":"Eskisehir Dalaman Eskisehir 48770",
    "addr:postcode":"48770",
    "addr:street":"Eskisehir",
    "iso:country":"TR",
    "sg:address":"Eskisehir",
    "sg:city":"Dalaman",
    "sg:classifiers":[
        {
            "category":"Banks & Credit Unions",
            "subcategory":"Investment Brokerage",
            "type":"Services"
        }
    ],
    "sg:phone":"+90 222 221 6263",
    "sg:postcode":"48770",
    "sg:province":"Eskisehir",
    "sg:tags":[
        "line",
        "air"
    ],
    "wof:name":"Turkish Airlines (thy)",
    "wof:placetype":"venue"
},
  "geometry": {"coordinates":[31.036945343,39.6586112976],"type":"Point"}
}