{
  "type": "Feature",
  "properties": {
    "addr:full":"Degirmenhan Sok. Balkanli Ishani B Blok K.4 D.58 Harbiye Sakarya 31080",
    "addr:housenumber":"blok k.4 d.58",
    "addr:postcode":"31080",
    "addr:street":"Degirmenhan Sok. Balkanli",
    "iso:country":"TR",
    "sg:address":"Degirmenhan Sok. Balkanli Ishani B Blok K.4 D.58",
    "sg:city":"Harbiye",
    "sg:classifiers":[
        {
            "category":"Airport",
            "subcategory":"International",
            "type":"Transportation"
        }
    ],
    "sg:phone":"+90 264 278 7781",
    "sg:postcode":"31080",
    "sg:province":"Sakarya",
    "wof:name":"Islar Tic. Petrol Urunleri Paz.ltd.sti.",
    "wof:placetype":"venue"
},
  "geometry": {"coordinates":[30.3791446686,40.7734336853],"type":"Point"}
}