{
  "type": "Feature",
  "properties": {
    "addr:full":"Teyfik Fikret Sok. No:24/a Cennet Mah. K.cekmece Istanbul",
    "addr:housenumber":"no 24 / a",
    "addr:street":"Fikret Sok.;Cennet Mah. K.Cekmece",
    "iso:country":"TR",
    "sg:address":"Teyfik Fikret Sok. No:24/a Cennet Mah.",
    "sg:city":"K.cekmece",
    "sg:classifiers":[
        {
            "category":"Shopping",
            "subcategory":"Clothing, Apparel, & Fashions",
            "type":"Retail Goods"
        }
    ],
    "sg:phone":"+90 212 541 9725",
    "sg:province":"Istanbul",
    "sg:tags":[
        "ready",
        "wear"
    ],
    "wof:name":"Niss Mayo Ve Konfeksiyon",
    "wof:placetype":"venue"
},
  "geometry": {"coordinates":[28.7782707214,40.9916152954],"type":"Point"}
}