{
  "type": "Feature",
  "properties": {
    "iso:country":"TR",
    "sg:address":"Sanayi Carsisi Gunduz Sok. No.22/b",
    "sg:city":"Beylikd?? 34900",
    "sg:classifiers":[
        {
            "category":"Wholesale",
            "subcategory":"Auto Parts",
            "type":"Manufacturing & Wholesale Goods"
        }
    ],
    "sg:phone":"+90 332 233 1955",
    "sg:province":"Konya",
    "sg:tags":[
        "spare"
    ],
    "wof:name":"Ozencler Otomotiv Tic.ve San.a.s.",
    "wof:placetype":"venue"
},
  "geometry": {"coordinates":[32.8623580933,38.0141410828],"type":"Point"}
}