{
  "type": "Feature",
  "properties": {
    "addr:full":"?niversite Bulvari 224/b 27020 Gaziantep",
    "addr:housenumber":"?;224 / b",
    "addr:postcode":"27020",
    "addr:street":"Niversite Bulvari",
    "iso:country":"TR",
    "sg:address":"?niversite Bulvari 224/b",
    "sg:city":"27020",
    "sg:classifiers":[
        {
            "category":"Wholesale",
            "subcategory":"Medical Equipment & Supplies",
            "type":"Manufacturing & Wholesale Goods"
        }
    ],
    "sg:phone":"+90 342 360 5700",
    "sg:province":"Gaziantep",
    "wof:name":"Biodal Ic Ve Dis Tic.a.s",
    "wof:placetype":"venue"
},
  "geometry": {"coordinates":[37.3781585693,37.0629348755],"type":"Point"}
}