{
  "type": "Feature",
  "properties": {
    "iso:country":"TR",
    "sg:address":"Asmali ?esme Sok. 2",
    "sg:city":"Sultanahmet",
    "sg:orig_category":"Hotels: Motels",
    "sg:phone":"+90 212516295651",
    "sg:postcode":"34400",
    "sg:province":"Istanbul",
    "wof:name":"Turkoman Hotel",
    "wof:placetype":"venue"
},
  "geometry": {"coordinates":[28.9742717743,41.0058898926],"type":"Point"}
}