{
  "type": "Feature",
  "properties": {
    "iso:country":"TR",
    "sg:address":"Yeni Sanayi Sitesi 42.sok. No:13",
    "sg:city":"Kagithane",
    "sg:orig_category":"Aluminium Carpentary",
    "sg:phone":"+90 266 246 4420",
    "sg:postcode":"34406",
    "sg:province":"Balikesir",
    "wof:name":"Bati Metal",
    "wof:placetype":"venue"
},
  "geometry": {"coordinates":[26.4259967804,40.1464996338],"type":"Point"}
}