{
  "type": "Feature",
  "properties": {
    "addr:full":"Kuleli Sk.no:12 G.o.p. Etiler Ankara 07010",
    "addr:housenumber":"12",
    "addr:postcode":"07010",
    "addr:street":"G.O.P.",
    "iso:country":"TR",
    "sg:address":"Kuleli Sk.no:12 G.o.p.",
    "sg:city":"Etiler",
    "sg:classifiers":[
        {
            "category":"Government",
            "subcategory":"Embassy",
            "type":"Public Place"
        }
    ],
    "sg:phone":"+90 312 437 7812",
    "sg:postcode":"07010",
    "sg:province":"Ankara",
    "sg:tags":[
        "foreign"
    ],
    "wof:name":"Tunus B?y?kel?iligi",
    "wof:placetype":"venue"
},
  "geometry": {"coordinates":[32.8726654053,39.8975448608],"type":"Point"}
}