{
  "type": "Feature",
  "properties": {
    "addr:full":"Bahriye Cd. No:121/a Kasimpasa \u00dcmraniye Istanbul",
    "addr:housenumber":"no;/ a",
    "addr:street":"Bahriye Cd.;Kasimpasa",
    "iso:country":"TR",
    "sg:address":"Bahriye Cd. No:121/a Kasimpasa",
    "sg:city":"\u00dcmraniye",
    "sg:orig_category":"General Industrial Products",
    "sg:phone":"+90 212 254 9396",
    "sg:province":"Istanbul",
    "wof:name":"Halsan Mutfak Gere?. Koll. Sti.",
    "wof:placetype":"venue"
},
  "geometry": {"coordinates":[28.96616745,41.0369644165],"type":"Point"}
}