{
  "type": "Feature",
  "properties": {
    "addr:full":"Kavakpinar Mah. Mahmut Bayram Cad. No:13 Pendik 07100 Istanbul",
    "addr:housenumber":"13",
    "addr:postcode":"07100",
    "addr:street":"Kavakpinar Mah. Mahmut Bayram Cad. No",
    "iso:country":"TR",
    "sg:address":"Kavakpinar Mah. Mahmut Bayram Cad. No:13 Pendik",
    "sg:city":"07100",
    "sg:classifiers":[
        {
            "category":"Home & Garden",
            "subcategory":"Carpets & Floor Coverings",
            "type":"Retail Goods"
        }
    ],
    "sg:phone":"+90 216 378 2016",
    "sg:province":"Istanbul",
    "sg:tags":[
        "wall",
        "ceramics-porcelain",
        "tile",
        "-"
    ],
    "wof:name":"Anadolu Porselen San.tic.a.s.",
    "wof:placetype":"venue"
},
  "geometry": {"coordinates":[29.3492794037,40.9514503479],"type":"Point"}
}