{
  "type": "Feature",
  "properties": {
    "addr:full":"Semsipasa Sok.43/1 Uskudar Istanbul 34672",
    "addr:housenumber":"1",
    "addr:postcode":"34672",
    "addr:street":"Uskudar Istanbul",
    "iso:country":"TR",
    "sg:address":"Semsipasa Sok.43/1",
    "sg:city":"Uskudar",
    "sg:classifiers":[
        {
            "category":"Professional",
            "subcategory":"Engineering",
            "type":"Services"
        }
    ],
    "sg:phone":"+90 216 342 0838",
    "sg:postcode":"34672",
    "sg:province":"Istanbul",
    "sg:tags":[
        "architect"
    ],
    "wof:name":"Agk Mimarlik",
    "wof:placetype":"venue"
},
  "geometry": {"coordinates":[28.9861831665,41.0408554077],"type":"Point"}
}