{
  "type": "Feature",
  "properties": {
    "iso:country":"TR",
    "sg:address":"Ak?kale Sk. No:33",
    "sg:city":"Siteler",
    "sg:classifiers":[
        {
            "category":"Manufacturing",
            "subcategory":"Glass & Minerals",
            "type":"Manufacturing & Wholesale Goods"
        }
    ],
    "sg:phone":"+90 312 348 2590",
    "sg:postcode":"07070",
    "sg:province":"Ankara",
    "sg:tags":[
        "glass-mirror"
    ],
    "wof:name":"Vetro Cam San. Tic. A.s.",
    "wof:placetype":"venue"
},
  "geometry": {"coordinates":[33.78074646,41.3800773621],"type":"Point"}
}