{
  "type": "Feature",
  "properties": {
    "addr:full":"Seyran Mah. 19 Mayis Cad. 14 Sok. Apt. No:1/a-4 Yesiltepe Malatya 01000",
    "addr:housenumber":"19;14;apt.;a-4",
    "addr:postcode":"01000",
    "addr:street":"Mah.;Mayis Cad.;Sok.;No 1 /",
    "iso:country":"TR",
    "sg:address":"Seyran Mah. 19 Mayis Cad. 14 Sok. Apt. No:1/a-4",
    "sg:city":"Yesiltepe",
    "sg:orig_category":"Dryfood-dried Nuts",
    "sg:phone":"+90 422 336 0777",
    "sg:postcode":"01000",
    "sg:province":"Malatya",
    "wof:name":"Ersoylar Ticaret",
    "wof:placetype":"venue"
},
  "geometry": {"coordinates":[38.3195266724,38.3488922119],"type":"Point"}
}