{
  "type": "Feature",
  "properties": {
    "iso:country":"TR",
    "sg:address":"Kars Veteriner Fak. Kars Fak.",
    "sg:city":"Nazilli",
    "sg:classifiers":[
        {
            "category":"Farming",
            "subcategory":"Farm & Veterinary Services",
            "type":"Manufacturing & Wholesale Goods"
        }
    ],
    "sg:phone":"+90 474 212 4386",
    "sg:postcode":"65600",
    "sg:province":"Kars",
    "sg:tags":[
        "veterinarian"
    ],
    "wof:name":"Kafkas Un. Veteriner Fakultesi",
    "wof:placetype":"venue"
},
  "geometry": {"coordinates":[43.0957984924,40.6094017029],"type":"Point"}
}