{
  "type": "Feature",
  "properties": {
    "addr:full":"?iftehavuzlar Cd. No:13 Bayrampasa \u00c7orlu Istanbul",
    "addr:housenumber":"?;no 13",
    "addr:street":"Iftehavuzlar Cd.",
    "iso:country":"TR",
    "sg:address":"?iftehavuzlar Cd. No:13 Bayrampasa",
    "sg:city":"\u00c7orlu",
    "sg:classifiers":[
        {
            "category":"Retail",
            "subcategory":"Auto Repair",
            "type":"Services"
        }
    ],
    "sg:phone":"+90 212 577 9855",
    "sg:province":"Istanbul",
    "sg:tags":[
        "maintenance"
    ],
    "wof:name":"S?per Firinli Boyama San. Tic. Ltd. Sti.",
    "wof:placetype":"venue"
},
  "geometry": {"coordinates":[28.912109375,41.0438117981],"type":"Point"}
}