{
  "type": "Feature",
  "properties": {
    "addr:full":"Org.san. B?. Altinyayla Denizli 58470",
    "addr:postcode":"58470",
    "iso:country":"TR",
    "sg:address":"Org.san. B?.",
    "sg:city":"Altinyayla",
    "sg:classifiers":[
        {
            "category":"Shopping",
            "subcategory":"Clothing, Apparel, & Fashions",
            "type":"Retail Goods"
        }
    ],
    "sg:phone":"+90 258 269 1344",
    "sg:postcode":"58470",
    "sg:province":"Denizli",
    "sg:tags":[
        "-",
        "towel",
        "bathrobe"
    ],
    "wof:name":"Dok-san Dokuma San.a.s.",
    "wof:placetype":"venue"
},
  "geometry": {"coordinates":[29.0788803101,37.7851867676],"type":"Point"}
}