{
  "type": "Feature",
  "properties": {
    "iso:country":"TR",
    "sg:address":"Cetin Emec Bulvari 4.cad. 66.sok. No:8/4 Ovecler",
    "sg:city":"Harbiye",
    "sg:classifiers":[
        {
            "category":"Shopping",
            "subcategory":"Party Supplies",
            "type":"Retail Goods"
        }
    ],
    "sg:phone":"+90 31247828504799",
    "sg:postcode":"31080",
    "sg:province":"Ankara",
    "sg:tags":[
        "sound",
        "light",
        "system"
    ],
    "wof:name":"Gul Elektro Mum. Pr. Ve Taah. Ltd.sti.",
    "wof:placetype":"venue"
},
  "geometry": {"coordinates":[32.8194999695,39.9253234863],"type":"Point"}
}