{
  "type": "Feature",
  "properties": {
    "iso:country":"TR",
    "sg:address":"Bagdat Cd. No:120/80",
    "sg:city":"Maltepe",
    "sg:classifiers":[
        {
            "category":"Mining & Drilling",
            "type":"Manufacturing & Wholesale Goods"
        }
    ],
    "sg:phone":"+90 216 399 5271",
    "sg:postcode":"01000",
    "sg:province":"Istanbul",
    "sg:tags":[
        "excavation",
        "demolition"
    ],
    "wof:name":"Tosun-er Hafriyat Ltd. Sti.",
    "wof:placetype":"venue"
},
  "geometry": {"coordinates":[29.2939548492,40.9115180969],"type":"Point"}
}