{
  "type": "Feature",
  "properties": {
    "addr:full":"Aktas Cad.no:6 Kavakli B.cekmece Istanbul",
    "addr:housenumber":"6",
    "addr:street":"Cad.No",
    "iso:country":"TR",
    "sg:address":"Aktas Cad.no:6 Kavakli",
    "sg:city":"B.cekmece",
    "sg:classifiers":[
        {
            "category":"Manufacturing",
            "subcategory":"Building Materials",
            "type":"Manufacturing & Wholesale Goods"
        }
    ],
    "sg:phone":"+90 212 875 1870",
    "sg:province":"Istanbul",
    "sg:tags":[
        "lifts-elevators"
    ],
    "wof:name":"Akar Asansor",
    "wof:placetype":"venue"
},
  "geometry": {"coordinates":[28.2631855011,41.0774536133],"type":"Point"}
}