{
  "type": "Feature",
  "properties": {
    "addr:full":"Meclisi Mebusan Yokusu Selime Hatun Camii Sok. Sukran Apt. No:11/2 Findikli Istanbul 01470",
    "addr:postcode":"01470",
    "addr:street":"Sok.",
    "iso:country":"TR",
    "sg:address":"Meclisi Mebusan Yokusu Selime Hatun Camii Sok. Sukran Apt. No:11/2",
    "sg:city":"Findikli",
    "sg:classifiers":[
        {
            "category":"Government",
            "subcategory":"Fire Station",
            "type":"Public Place"
        }
    ],
    "sg:phone":"+90 212 244 6434",
    "sg:postcode":"01470",
    "sg:province":"Istanbul",
    "sg:tags":[
        "decoration"
    ],
    "wof:name":"Standart Mimarlik Ltd.sti.",
    "wof:placetype":"venue"
},
  "geometry": {"coordinates":[28.9861831665,41.0408554077],"type":"Point"}
}