{
  "type": "Feature",
  "properties": {
    "iso:country":"TR",
    "sg:address":"Konya",
    "sg:city":"Bayrami?",
    "sg:classifiers":[
        {
            "category":"Food & Beverages",
            "subcategory":"Candy",
            "type":"Retail Goods"
        }
    ],
    "sg:phone":"+90 332 355 2268",
    "sg:postcode":"17700",
    "sg:province":"Konya",
    "sg:tags":[
        "biscuit-chocolate-candy"
    ],
    "wof:name":"Tatlidil Gida Sanayi Ve Ticaret A.s.",
    "wof:placetype":"venue"
},
  "geometry": {"coordinates":[32.5769,37.983585],"type":"Point"}
}