{
  "type": "Feature",
  "properties": {
    "iso:country":"TR",
    "sg:address":"4.levent Oto San. Sitesi Ulubas Cad. No:3 4.levent",
    "sg:city":"Topkapi",
    "sg:classifiers":[
        {
            "category":"Wholesale",
            "subcategory":"Machinery & Supplies",
            "type":"Manufacturing & Wholesale Goods"
        }
    ],
    "sg:phone":"+90 2122803073729",
    "sg:postcode":"34515",
    "sg:province":"Istanbul",
    "sg:tags":[
        "bearing",
        "ball"
    ],
    "wof:name":"Barkin Rulman Hicabi Bayindir",
    "wof:placetype":"venue"
},
  "geometry": {"coordinates":[28.975925,41.012379],"type":"Point"}
}