{
  "type": "Feature",
  "properties": {
    "addr:full":"Cengiz Topel Cd. Yali Apt. Ablok No:4/7 Mersin I?el 52750",
    "addr:housenumber":"7",
    "addr:postcode":"? el 52750",
    "addr:street":"Cengiz Topel Cd. Yali Apt. Ablok No 4 /",
    "iso:country":"TR",
    "sg:address":"Cengiz Topel Cd. Yali Apt. Ablok No:4/7",
    "sg:city":"Mersin",
    "sg:classifiers":[
        {
            "category":"Professional",
            "subcategory":"Business Services",
            "type":"Services"
        }
    ],
    "sg:phone":"+90 324 232 6604",
    "sg:postcode":"52750",
    "sg:province":"I?el",
    "sg:tags":[
        "food",
        "product",
        "exporter",
        "aricultural"
    ],
    "wof:name":"Tudas Tarim A.s.",
    "wof:placetype":"venue"
},
  "geometry": {"coordinates":[37.7128486633,41.0530204773],"type":"Point"}
}