{
  "type": "Feature",
  "properties": {
    "addr:full":"Kongre Cad. Nazik ?arsi No: E/2 \u00c7ankaya Erzurum",
    "addr:housenumber":"?;2",
    "addr:street":"Kongre Cad. Nazik;No E /",
    "iso:country":"TR",
    "sg:address":"Kongre Cad. Nazik ?arsi No: E/2",
    "sg:city":"\u00c7ankaya",
    "sg:classifiers":[
        {
            "category":"Travel",
            "subcategory":"Travel Agent",
            "type":"Entertainment"
        }
    ],
    "sg:phone":"+90 442233310923",
    "sg:province":"Erzurum",
    "sg:tags":[
        "agency",
        "tourism"
    ],
    "wof:name":"Es-dost Turizm",
    "wof:placetype":"venue"
},
  "geometry": {"coordinates":[41.2808113098,39.8986663818],"type":"Point"}
}