{
  "type": "Feature",
  "properties": {
    "iso:country":"TR",
    "sg:address":"Nazmi G?d?",
    "sg:city":"Akca?en",
    "sg:classifiers":[
        {
            "category":"Government",
            "subcategory":"Office",
            "type":"Public Place"
        }
    ],
    "sg:phone":"+90 258 276 5083",
    "sg:province":"Denizli",
    "sg:tags":[
        "municipality"
    ],
    "wof:name":"Cankurtaran Belediye Baskani",
    "wof:placetype":"venue"
},
  "geometry": {"coordinates":[35.5135536194,38.7180671692],"type":"Point"}
}