{
  "type": "Feature",
  "properties": {
    "addr:full":"Karatay Sanayi 42300 Konya Topkapi Konya 34020",
    "addr:postcode":"42300;34020",
    "addr:street":"Sanayi",
    "iso:country":"TR",
    "sg:address":"Karatay Sanayi 42300 Konya",
    "sg:city":"Topkapi",
    "sg:classifiers":[
        {
            "category":"Wholesale",
            "subcategory":"Auto Parts",
            "type":"Manufacturing & Wholesale Goods"
        }
    ],
    "sg:phone":"+90 212 233 7714",
    "sg:postcode":"34020",
    "sg:province":"Konya",
    "sg:tags":[
        "spare"
    ],
    "wof:name":"Duysak Otomotiv",
    "wof:placetype":"venue"
},
  "geometry": {"coordinates":[33.0667152405,39.2111282349],"type":"Point"}
}