{
  "type": "Feature",
  "properties": {
    "iso:country":"TR",
    "sg:address":"K. Karabekir Cd. No:5 Kizilcahamam",
    "sg:city":"Merkez",
    "sg:classifiers":[
        {
            "category":"Shopping",
            "subcategory":"Music",
            "type":"Retail Goods"
        }
    ],
    "sg:phone":"+90 312 736 1770",
    "sg:postcode":"77200",
    "sg:province":"Ankara",
    "sg:tags":[
        "record",
        "casette"
    ],
    "wof:name":"Alpdogan Plak?ilik",
    "wof:placetype":"venue"
},
  "geometry": {"coordinates":[32.6452102661,40.4699401855],"type":"Point"}
}