{
  "type": "Feature",
  "properties": {
    "iso:country":"TR",
    "sg:address":"Kisla Cd.",
    "sg:city":"Fikirtepe",
    "sg:classifiers":[
        {
            "category":"Food & Beverages",
            "subcategory":"Dairy",
            "type":"Retail Goods"
        }
    ],
    "sg:phone":"+90 322 321 0757",
    "sg:postcode":"34720",
    "sg:province":"Adana",
    "sg:tags":[
        "pruducts",
        "milk"
    ],
    "wof:name":"Adana S?t Mam. Isl.",
    "wof:placetype":"venue"
},
  "geometry": {"coordinates":[35.3429145813,37.0017471313],"type":"Point"}
}