{
  "type": "Feature",
  "properties": {
    "addr:full":"Merdivenkoy Mah.imam Ramiz Sok. Ozcan Apt.no: 75/3 Kadikoy 4640 Istanbul",
    "addr:housenumber":"75 / 3",
    "addr:postcode":"4640",
    "addr:street":"Ramiz Sok. Ozcan Apt.No;Kadikoy",
    "iso:country":"TR",
    "sg:address":"Merdivenkoy Mah.imam Ramiz Sok. Ozcan Apt.no: 75/3 Kadikoy",
    "sg:city":"4640",
    "sg:classifiers":[
        {
            "category":"Shopping",
            "subcategory":"Gifts & Souvenirs",
            "type":"Retail Goods"
        }
    ],
    "sg:phone":"+90 216 302 5195",
    "sg:province":"Istanbul",
    "wof:name":"Ege San.tic.",
    "wof:placetype":"venue"
},
  "geometry": {"coordinates":[29.0755596161,40.9884567261],"type":"Point"}
}