{
  "type": "Feature",
  "properties": {
    "iso:country":"TR",
    "sg:address":"Tahsin ?nal Mah.30 Mtlik Yol ?zeri Atat?k Bulvari",
    "sg:city":"70000",
    "sg:classifiers":[
        {
            "category":"Structure",
            "subcategory":"Office Building",
            "type":"Public Place"
        }
    ],
    "sg:phone":"+90 338 214 3586",
    "sg:province":"Karaman",
    "sg:tags":[
        "satellite",
        "system"
    ],
    "wof:name":"Ata Elektronik",
    "wof:placetype":"venue"
},
  "geometry": {"coordinates":[33.221901,37.1814],"type":"Point"}
}