{
  "type": "Feature",
  "properties": {
    "addr:full":"Ataturk Cad. No:2 Biga Levent - Besiktas ?anakkale",
    "addr:housenumber":"?",
    "addr:street":"Ataturk Cad. No 2 Biga;Besiktas",
    "iso:country":"TR",
    "sg:address":"Ataturk Cad. No:2 Biga",
    "sg:city":"Levent - Besiktas",
    "sg:classifiers":[
        {
            "category":"Shopping",
            "subcategory":"Stationery & Office Supplies",
            "type":"Retail Goods"
        }
    ],
    "sg:phone":"+90 286 316 4845",
    "sg:province":"?anakkale",
    "wof:name":"Kilkis Yayin Pazarlama Tic.ltd.sti.",
    "wof:placetype":"venue"
},
  "geometry": {"coordinates":[29.166471,40.913818],"type":"Point"}
}