{
  "type": "Feature",
  "properties": {
    "addr:full":"Ramikisla Cd. G?dogar Ismerk. No:84/283 Top?lar Etiler Istanbul 07010",
    "addr:housenumber":"?;283",
    "addr:postcode":"?;07010",
    "addr:street":"Ramikisla Cd. G;No 84 /",
    "iso:country":"TR",
    "sg:address":"Ramikisla Cd. G?dogar Ismerk. No:84/283 Top?lar",
    "sg:city":"Etiler",
    "sg:classifiers":[
        {
            "category":"Manufacturing",
            "subcategory":"Wood Products",
            "type":"Manufacturing & Wholesale Goods"
        }
    ],
    "sg:phone":"+90 212 565 7150",
    "sg:postcode":"07010",
    "sg:province":"Istanbul",
    "sg:tags":[
        "forest"
    ],
    "wof:name":"Agaker Orman ?r?nleri",
    "wof:placetype":"venue"
},
  "geometry": {"coordinates":[28.9759254456,41.0123786926],"type":"Point"}
}