{
  "type": "Feature",
  "properties": {
    "iso:country":"TR",
    "sg:address":"B??dere Cd. No:57/4 Maslak",
    "sg:city":"Topkapi",
    "sg:orig_category":"Printinh House",
    "sg:phone":"+90 212 276 2767",
    "sg:postcode":"24620",
    "sg:province":"Istanbul",
    "wof:name":"Ana Yayincilik San. ?r?n. Pazarlama Tic. A.s.",
    "wof:placetype":"venue"
},
  "geometry": {"coordinates":[29.0366592407,41.1291542053],"type":"Point"}
}