{
  "type": "Feature",
  "properties": {
    "addr:full":"Yeni ?amlica Mah. Yedpa Ticaret Merkezi D Caddesi No:90 \u00dcmraniye Istanbul 81260",
    "addr:housenumber":"ticaret merkezi;no 90",
    "addr:postcode":"81260",
    "addr:street":"Amlica Mah. Yedpa;D Caddesi",
    "iso:country":"TR",
    "sg:address":"Yeni ?amlica Mah. Yedpa Ticaret Merkezi D Caddesi No:90",
    "sg:city":"\u00dcmraniye",
    "sg:orig_category":"Yedpa Org.ind.site",
    "sg:phone":"+90 216 471 0590",
    "sg:postcode":"81260",
    "sg:province":"Istanbul",
    "wof:name":"Yakaoglu San. Tic. - Ya&ka Buji Kablo Sistemleri",
    "wof:placetype":"venue"
},
  "geometry": {"coordinates":[28.9759254456,41.0123786926],"type":"Point"}
}