{
  "type": "Feature",
  "properties": {
    "addr:full":"Ankara Asf. No:98 Kartal Kartal Istanbul 81450",
    "addr:postcode":"81450",
    "addr:street":"Kartal",
    "iso:country":"TR",
    "sg:address":"Ankara Asf. No:98 Kartal",
    "sg:city":"Kartal",
    "sg:classifiers":[
        {
            "category":"Wholesale",
            "subcategory":"Durable Goods & Equipment",
            "type":"Manufacturing & Wholesale Goods"
        }
    ],
    "sg:phone":"+90 216 353 4720",
    "sg:postcode":"81450",
    "sg:province":"Istanbul",
    "sg:tags":[
        "consumer"
    ],
    "wof:name":"Yeni Sefak Ev Cih. San.",
    "wof:placetype":"venue"
},
  "geometry": {"coordinates":[28.9861831665,41.0408554077],"type":"Point"}
}