{
  "type": "Feature",
  "properties": {
    "addr:full":"Veliefendi Mah. 75/1 Sok. 34 34760 Zeytinburnu Istanbul Ikitelli/K\u00fc\u00e7\u00fck\u00e7ekmece Istanbul 34670",
    "addr:housenumber":"75 / 1;34",
    "addr:postcode":"34760;34670",
    "addr:street":"Veliefendi Mah.;Sok.",
    "iso:country":"TR",
    "sg:address":"Veliefendi Mah. 75/1 Sok. 34 34760 Zeytinburnu Istanbul",
    "sg:city":"Ikitelli/K\u00fc\u00e7\u00fck\u00e7ekmece",
    "sg:classifiers":[
        {
            "category":"Shopping",
            "subcategory":"Crafts & Fabrics",
            "type":"Retail Goods"
        }
    ],
    "sg:phone":"+90 212 679 1751",
    "sg:postcode":"34670",
    "sg:province":"Istanbul",
    "sg:tags":[
        "linen"
    ],
    "wof:name":"Senol Tekstil San",
    "wof:placetype":"venue"
},
  "geometry": {"coordinates":[28.8956832886,40.9956932068],"type":"Point"}
}