{
  "type": "Feature",
  "properties": {
    "addr:full":"Sezenler Sk. No:2/2 Sihhiye Ankara 06410",
    "addr:housenumber":"2",
    "addr:postcode":"06410",
    "addr:street":"Sezenler Sk. No 2 /",
    "iso:country":"TR",
    "sg:address":"Sezenler Sk. No:2/2",
    "sg:city":"Sihhiye",
    "sg:classifiers":[
        {
            "category":"Utilities",
            "subcategory":"Natural Gas",
            "type":"Services"
        }
    ],
    "sg:phone":"+90 312 230 1017",
    "sg:postcode":"06410",
    "sg:province":"Ankara",
    "sg:tags":[
        "tank-heating-natural"
    ],
    "wof:name":"Alfagas Elektronik Ltd. Sti.",
    "wof:placetype":"venue"
},
  "geometry": {"coordinates":[32.8604812622,39.9429283142],"type":"Point"}
}