{
  "type": "Feature",
  "properties": {
    "addr:full":"Dalboyu Sk. No:33/3 Siteler 07100 Ankara",
    "addr:housenumber":"33 / 3",
    "addr:postcode":"07100",
    "addr:street":"Dalboyu Sk. No;Siteler",
    "iso:country":"TR",
    "sg:address":"Dalboyu Sk. No:33/3 Siteler",
    "sg:city":"07100",
    "sg:classifiers":[
        {
            "category":"Manufacturing",
            "subcategory":"Wood Products",
            "type":"Manufacturing & Wholesale Goods"
        }
    ],
    "sg:phone":"+90 312 353 0281",
    "sg:province":"Ankara",
    "sg:tags":[
        "forest"
    ],
    "wof:name":"Kaysan Kastamonu Aga? San. Tic. A.s.",
    "wof:placetype":"venue"
},
  "geometry": {"coordinates":[32.8945007324,39.9587516785],"type":"Point"}
}