{
  "type": "Feature",
  "properties": {
    "iso:country":"TR",
    "sg:address":"Valikonagi Cad.akkavak Sok.no:6/3 Nisantasi",
    "sg:city":"Fatih",
    "sg:classifiers":[
        {
            "category":"Health Services",
            "subcategory":"Medical Lab",
            "type":"Services"
        }
    ],
    "sg:phone":"+90 212 246 6819",
    "sg:postcode":"01740",
    "sg:province":"Istanbul",
    "wof:name":"Genomet Saglik Hizmetleri A.s",
    "wof:placetype":"venue"
},
  "geometry": {"coordinates":[28.9861831665,41.0408554077],"type":"Point"}
}