{
  "type": "Feature",
  "properties": {
    "addr:full":"Istiklal Cd.ozbek Apt. K:4 Serik I?el 07500",
    "addr:housenumber":"4;?",
    "addr:postcode":"07500",
    "addr:street":"Serik I;El",
    "iso:country":"TR",
    "sg:address":"Istiklal Cd.ozbek Apt. K:4",
    "sg:city":"Serik",
    "sg:classifiers":[
        {
            "category":"Food & Beverages",
            "subcategory":"Fruits & Vegetables",
            "type":"Retail Goods"
        }
    ],
    "sg:phone":"+90 324 231 6635",
    "sg:postcode":"07500",
    "sg:province":"I?el",
    "sg:tags":[
        "fresh"
    ],
    "wof:name":"Akpa",
    "wof:placetype":"venue"
},
  "geometry": {"coordinates":[29.2567100525,40.9646568298],"type":"Point"}
}