{
  "type": "Feature",
  "properties": {
    "addr:full":"Fatikli Mah. Baliseyh Altin?? Hatay 71520",
    "addr:housenumber":"? ?",
    "addr:postcode":"71520",
    "addr:street":"Fatikli Mah. Baliseyh Altin",
    "iso:country":"TR",
    "sg:address":"Fatikli Mah.",
    "sg:city":"Baliseyh",
    "sg:classifiers":[
        {
            "category":"Farming",
            "subcategory":"Farm",
            "type":"Manufacturing & Wholesale Goods"
        }
    ],
    "sg:phone":"+90 326 311 3303",
    "sg:postcode":"71520",
    "sg:province":"Altin?? Hatay",
    "sg:tags":[
        "agricultural",
        "product"
    ],
    "wof:name":"Avarlar Ltd.sti.",
    "wof:placetype":"venue"
},
  "geometry": {"coordinates":[36.349811554,36.4018478394],"type":"Point"}
}