{
  "type": "Feature",
  "properties": {
    "addr:full":"Kazim Karabekir Cad. Kavakli Apt. No:19/1 D:21 Erenkoy Istanbul 07060",
    "addr:housenumber":"19 / 1 d 21",
    "addr:postcode":"07060",
    "addr:street":"Karabekir Cad. Kavakli Apt. No;Istanbul",
    "iso:country":"TR",
    "sg:address":"Kazim Karabekir Cad. Kavakli Apt. No:19/1 D:21",
    "sg:city":"Erenkoy",
    "sg:classifiers":[
        {
            "category":"Building & Trades",
            "subcategory":"Electrical",
            "type":"Services"
        }
    ],
    "sg:phone":"+90 216 369 3151",
    "sg:postcode":"07060",
    "sg:province":"Istanbul",
    "sg:tags":[
        "equipment",
        "lighting"
    ],
    "wof:name":"Zg Tasarim",
    "wof:placetype":"venue"
},
  "geometry": {"coordinates":[29.1140804291,40.9719276428],"type":"Point"}
}