{
  "type": "Feature",
  "properties": {
    "addr:full":"Gebze Sariyer Kocaeli 33740",
    "addr:postcode":"33740",
    "addr:street":"Kocaeli",
    "iso:country":"TR",
    "sg:address":"Gebze",
    "sg:city":"Sariyer",
    "sg:classifiers":[
        {
            "category":"Mining & Drilling",
            "type":"Manufacturing & Wholesale Goods"
        }
    ],
    "sg:phone":"+90 262 641 6258",
    "sg:postcode":"33740",
    "sg:province":"Kocaeli",
    "sg:tags":[
        "industry",
        "mine"
    ],
    "wof:name":"?zlem Madencilik Mermer San. Tic. A.s.",
    "wof:placetype":"venue"
},
  "geometry": {"coordinates":[29.4400043488,40.8058662415],"type":"Point"}
}