{
  "type": "Feature",
  "properties": {
    "addr:full":"M. Naci Cd. Melek Is Han. K:2 No:41 Besiktas Bah?elievler Istanbul 06490",
    "addr:housenumber":"2 no 41;?",
    "addr:postcode":"06490",
    "addr:street":"M. Naci Cd. Melek;Besiktas Bah",
    "iso:country":"TR",
    "sg:address":"M. Naci Cd. Melek Is Han. K:2 No:41 Besiktas",
    "sg:city":"Bah?elievler",
    "sg:classifiers":[
        {
            "category":"Organizations",
            "subcategory":"Membership Organization",
            "type":"Services"
        }
    ],
    "sg:phone":"+90 212 258 9227",
    "sg:postcode":"06490",
    "sg:province":"Istanbul",
    "wof:name":"Darussafakalilar Dernegi",
    "wof:placetype":"venue"
},
  "geometry": {"coordinates":[28.9861831665,41.0408554077],"type":"Point"}
}