{
  "type": "Feature",
  "properties": {
    "addr:full":"Organize San.bol.9.cad. No:24 G?ng?ren Kayseri 34600",
    "addr:housenumber":"san.bol.9.cad no 24 g ?;?",
    "addr:postcode":"34600",
    "addr:street":"Organize;Ng",
    "iso:country":"TR",
    "sg:address":"Organize San.bol.9.cad. No:24",
    "sg:city":"G?ng?ren",
    "sg:classifiers":[
        {
            "category":"Manufacturing",
            "subcategory":"Rubber & Plastics",
            "type":"Manufacturing & Wholesale Goods"
        }
    ],
    "sg:phone":"+90 352 321 1510",
    "sg:postcode":"34600",
    "sg:province":"Kayseri",
    "sg:tags":[
        "industry"
    ],
    "wof:name":"Renk Plastik",
    "wof:placetype":"venue"
},
  "geometry": {"coordinates":[35.4891357422,38.7225761414],"type":"Point"}
}