{
  "type": "Feature",
  "properties": {
    "iso:country":"TR",
    "sg:address":"5709 Sk. No:9 Karabaglar",
    "sg:city":"Merkez",
    "sg:classifiers":[
        {
            "category":"Home & Garden",
            "subcategory":"Kitchen Supply",
            "type":"Retail Goods"
        }
    ],
    "sg:phone":"+90 232 237 9740",
    "sg:postcode":"20100",
    "sg:province":"Izmir",
    "sg:tags":[
        "steel",
        "utensil"
    ],
    "wof:name":"G?rkomp Kompros?r. Ve Basin?li Kaplar San. Tic. A.s.",
    "wof:placetype":"venue"
},
  "geometry": {"coordinates":[27.132231,38.390255],"type":"Point"}
}