{
  "type": "Feature",
  "properties": {
    "iso:country":"TR",
    "sg:address":"Nispetiye Cd. Birlik Sk. Levent",
    "sg:city":"Findikzade-fatih",
    "sg:classifiers":[
        {
            "category":"Building & Trades",
            "subcategory":"Construction",
            "type":"Services"
        }
    ],
    "sg:phone":"+90 212 278 8341",
    "sg:province":"Istanbul",
    "sg:tags":[
        "foundation"
    ],
    "wof:name":"Turkiye Kanser. Savas Vakfi",
    "wof:placetype":"venue"
},
  "geometry": {"coordinates":[29.021692276,41.0634727478],"type":"Point"}
}