{
  "type": "Feature",
  "properties": {
    "addr:full":"Kisikli Cad. No:110 Altunizade 81190 Uskudar Istanbul Adalar Istanbul 81340",
    "addr:housenumber":"110",
    "addr:postcode":"81190;81340",
    "addr:street":"Kisikli Cad. No",
    "iso:country":"TR",
    "sg:address":"Kisikli Cad. No:110 Altunizade 81190 Uskudar Istanbul",
    "sg:city":"Adalar",
    "sg:classifiers":[
        {
            "category":"Manufacturing",
            "subcategory":"Paper Products",
            "type":"Manufacturing & Wholesale Goods"
        }
    ],
    "sg:phone":"+90 216 325 7273",
    "sg:postcode":"81340",
    "sg:province":"Istanbul",
    "sg:tags":[
        "cardboard"
    ],
    "wof:name":"Papirus Kagit San Ve Tic As",
    "wof:placetype":"venue"
},
  "geometry": {"coordinates":[29.0509853363,41.0230178833],"type":"Point"}
}