{
  "type": "Feature",
  "properties": {
    "addr:full":"Karatay San. D??c?er Sit. G?enilir Sk. No:12 Seyhan Konya 01010",
    "addr:housenumber":"?;12",
    "addr:postcode":"01010",
    "addr:street":"Sit. G;Enilir Sk. No",
    "iso:country":"TR",
    "sg:address":"Karatay San. D??c?er Sit. G?enilir Sk. No:12",
    "sg:city":"Seyhan",
    "sg:classifiers":[
        {
            "category":"Wholesale",
            "subcategory":"Machinery & Supplies",
            "type":"Manufacturing & Wholesale Goods"
        }
    ],
    "sg:phone":"+90 332 248 9540",
    "sg:postcode":"01010",
    "sg:province":"Konya",
    "sg:tags":[
        "heavy",
        "construction",
        "macinery"
    ],
    "wof:name":"Canbilen D?k?m San.",
    "wof:placetype":"venue"
},
  "geometry": {"coordinates":[33.0667152405,39.2111282349],"type":"Point"}
}