{
  "type": "Feature",
  "properties": {
    "iso:country":"TR",
    "sg:address":"Mimar Vedat Cad 26-28",
    "sg:city":"Bahcekapi",
    "sg:classifiers":[
        {
            "category":"Banks & Credit Unions",
            "subcategory":"Bank",
            "type":"Services"
        }
    ],
    "sg:phone":"+90 212 519 1845",
    "sg:postcode":"23000",
    "sg:province":"34420",
    "wof:name":"S?erbank As",
    "wof:placetype":"venue"
},
  "geometry": {"coordinates":[28.974396,41.014874],"type":"Point"}
}