{
  "type": "Feature",
  "properties": {
    "iso:country":"TR",
    "sg:address":"Istasyon Cad. No: 67",
    "sg:city":"?rg?p",
    "sg:classifiers":[
        {
            "category":"Travel",
            "subcategory":"Travel Agent",
            "type":"Entertainment"
        }
    ],
    "sg:phone":"+90 388213211723",
    "sg:province":"Nigde",
    "sg:tags":[
        "agency",
        "tourism"
    ],
    "wof:name":"Sobek Turizm",
    "wof:placetype":"venue"
},
  "geometry": {"coordinates":[34.68384552,37.9660568237],"type":"Point"}
}