{
  "type": "Feature",
  "properties": {
    "iso:country":"TR",
    "sg:address":"Barbaros Hayrettin Pasa Mah. 1058 Sok.no:38 K???kk?y G.o.pasa",
    "sg:city":"Hadimk?",
    "sg:classifiers":[
        {
            "category":"Banks & Credit Unions",
            "subcategory":"Investment Brokerage",
            "type":"Services"
        }
    ],
    "sg:phone":"+90 212 618 7080",
    "sg:province":"Istanbul",
    "sg:tags":[
        "-",
        "export",
        "import"
    ],
    "wof:name":"Korhan Paz Ve Dis Tic.a.s",
    "wof:placetype":"venue"
},
  "geometry": {"coordinates":[28.9861793518,41.040851593],"type":"Point"}
}