{
  "type": "Feature",
  "properties": {
    "iso:country":"TR",
    "sg:address":"Yeni Mah.yeni Cadde No:59",
    "sg:city":"Ko?rli",
    "sg:classifiers":[
        {
            "category":"Wholesale",
            "subcategory":"Machinery & Supplies",
            "type":"Manufacturing & Wholesale Goods"
        }
    ],
    "sg:phone":"+90 256 761 4035",
    "sg:province":"Aydin",
    "sg:tags":[
        "agricultural"
    ],
    "wof:name":"Kaplan Ziraat Aletleri Nejat Kaplan",
    "wof:placetype":"venue"
},
  "geometry": {"coordinates":[40.5156288147,38.888759613],"type":"Point"}
}