{
  "type": "Feature",
  "properties": {
    "addr:full":"Moda Cad. Damaci Pasaji No:73/8 Kadikoy Maltepe Istanbul 01000",
    "addr:housenumber":"73 / 8",
    "addr:postcode":"01000",
    "addr:street":"Moda Cad. Damaci Pasaji No;Kadikoy Maltepe Istanbul",
    "iso:country":"TR",
    "sg:address":"Moda Cad. Damaci Pasaji No:73/8 Kadikoy",
    "sg:city":"Maltepe",
    "sg:classifiers":[
        {
            "category":"Manufacturing",
            "subcategory":"Chemicals & Compounds",
            "type":"Manufacturing & Wholesale Goods"
        }
    ],
    "sg:phone":"+90 216 336 2378",
    "sg:postcode":"01000",
    "sg:province":"Istanbul",
    "sg:tags":[
        "industry"
    ],
    "wof:name":"Onay Kimya San.ic Ve Dis Tic.ltd.sti.",
    "wof:placetype":"venue"
},
  "geometry": {"coordinates":[28.9861831665,41.0408554077],"type":"Point"}
}