{
  "type": "Feature",
  "properties": {
    "addr:full":"Eski Uskudar Yolu G-38 .sok. No: 1/3 / Icerenkoy Istanbul 34752",
    "addr:housenumber":"g-38 sok. no 1 / 3 / icerenkoy",
    "addr:postcode":"34752",
    "addr:street":"Eski Uskudar Yolu;Istanbul",
    "iso:country":"TR",
    "sg:address":"Eski Uskudar Yolu G-38 .sok. No: 1/3 /",
    "sg:city":"Icerenkoy",
    "sg:classifiers":[
        {
            "category":"Building & Trades",
            "subcategory":"Locksmith",
            "type":"Services"
        }
    ],
    "sg:phone":"+90 216 574 8674",
    "sg:postcode":"34752",
    "sg:province":"Istanbul",
    "sg:tags":[
        "lock",
        "key"
    ],
    "wof:name":"Anahtarci Cozum Ltd.sti.",
    "wof:placetype":"venue"
},
  "geometry": {"coordinates":[29.1776027679,40.9837188721],"type":"Point"}
}