{
  "type": "Feature",
  "properties": {
    "addr:full":"?iftehavuzlar Cd. No:7 Bayrampasa Ikitelli/K\u00fc\u00e7\u00fck\u00e7ekmece Istanbul 34670",
    "addr:housenumber":"?;no 7",
    "addr:postcode":"34670",
    "addr:street":"Iftehavuzlar Cd.",
    "iso:country":"TR",
    "sg:address":"?iftehavuzlar Cd. No:7 Bayrampasa",
    "sg:city":"Ikitelli/K\u00fc\u00e7\u00fck\u00e7ekmece",
    "sg:classifiers":[
        {
            "category":"Manufacturing",
            "subcategory":"Rubber & Plastics",
            "type":"Manufacturing & Wholesale Goods"
        }
    ],
    "sg:phone":"+90 212 576 1352",
    "sg:postcode":"34670",
    "sg:province":"Istanbul",
    "sg:tags":[
        "industry"
    ],
    "wof:name":"Fatih Plastik Teks. San. Tic. Ltd. Sti.",
    "wof:placetype":"venue"
},
  "geometry": {"coordinates":[28.9039669037,41.0271606445],"type":"Point"}
}