{
  "type": "Feature",
  "properties": {
    "addr:full":"Inonu Cad. Sumko Sit. Sumer Sok. Beta Binasi Kozyatagi Kagithane Istanbul 34406",
    "addr:housenumber":"sumko",
    "addr:postcode":"34406",
    "addr:street":"Inonu Cad.;Sumer Sok. Beta Binasi Kozyatagi Kagithane",
    "iso:country":"TR",
    "sg:address":"Inonu Cad. Sumko Sit. Sumer Sok. Beta Binasi Kozyatagi",
    "sg:city":"Kagithane",
    "sg:classifiers":[
        {
            "category":"Home & Garden",
            "subcategory":"Hardware",
            "type":"Retail Goods"
        }
    ],
    "sg:phone":"+90 216 372 7330",
    "sg:postcode":"34406",
    "sg:province":"Istanbul",
    "sg:tags":[
        "generator",
        "power"
    ],
    "wof:name":"Bimeks Ithalat Ihracat Ltd.sti.",
    "wof:placetype":"venue"
},
  "geometry": {"coordinates":[28.9681472778,41.0811843872],"type":"Point"}
}