{
  "type": "Feature",
  "properties": {
    "addr:full":"Fevzipasa Cad. No:23/4 Fatih \u00dcsk\u00fcdar Istanbul 34672",
    "addr:housenumber":"23 / 4",
    "addr:postcode":"34672",
    "addr:street":"Fevzipasa Cad. No;Fatih U\u0308Skuedar",
    "iso:country":"TR",
    "sg:address":"Fevzipasa Cad. No:23/4 Fatih",
    "sg:city":"\u00dcsk\u00fcdar",
    "sg:classifiers":[
        {
            "category":"Building & Trades",
            "subcategory":"Construction",
            "type":"Services"
        }
    ],
    "sg:phone":"+90 212 635 3849",
    "sg:postcode":"34672",
    "sg:province":"Istanbul",
    "sg:tags":[
        "foundation"
    ],
    "wof:name":"Davet Egitim K?lt?r Ve Kardeslik Vakfi",
    "wof:placetype":"venue"
},
  "geometry": {"coordinates":[28.0629882812,41.0558013916],"type":"Point"}
}