{
  "type": "Feature",
  "properties": {
    "iso:country":"TR",
    "sg:address":"Camiatik Mah. Fatih Sok. Arin Pasaji No:12/13 Corlu",
    "sg:city":"10 Sirinevler",
    "sg:orig_category":"Translation Servies",
    "sg:phone":"+90 282 652 9043",
    "sg:province":"Tekirdag",
    "wof:name":"Makro Muhendislik",
    "wof:placetype":"venue"
},
  "geometry": {"coordinates":[27.8041000366,41.159198761],"type":"Point"}
}