{
  "type": "Feature",
  "properties": {
    "addr:full":"Organize Sanayi B?gesi Corlu Usak 01770",
    "addr:housenumber":"?",
    "addr:postcode":"01770",
    "addr:street":"Organize Sanayi B;Usak",
    "iso:country":"TR",
    "sg:address":"Organize Sanayi B?gesi",
    "sg:city":"Corlu",
    "sg:classifiers":[
        {
            "category":"Farming",
            "subcategory":"Farm",
            "type":"Manufacturing & Wholesale Goods"
        }
    ],
    "sg:phone":"+90 276 266 7708",
    "sg:postcode":"01770",
    "sg:province":"Usak",
    "sg:tags":[
        "agricultural",
        "product"
    ],
    "wof:name":"Sezerler Tarim ?r?nleri",
    "wof:placetype":"venue"
},
  "geometry": {"coordinates":[29.4055995941,38.6716003418],"type":"Point"}
}