{
  "type": "Feature",
  "properties": {
    "addr:full":"Millet Cad. Belediye Durmaz Is Merkezi K:5 No:512 Kayseri Kad\u0131k\u00f6y Kayseri 34722",
    "addr:postcode":"512;34722",
    "addr:street":"Millet Cad. Belediye Durmaz;K 5 No",
    "iso:country":"TR",
    "sg:address":"Millet Cad. Belediye Durmaz Is Merkezi K:5 No:512 Kayseri",
    "sg:city":"Kad\u0131k\u00f6y",
    "sg:classifiers":[
        {
            "category":"Organizations",
            "subcategory":"Membership Organization",
            "type":"Services"
        }
    ],
    "sg:phone":"+90 352 222 0053",
    "sg:postcode":"34722",
    "sg:province":"Kayseri",
    "wof:name":"Kayseri Genc Sanayici Ve Is Adamlari Dernegi",
    "wof:placetype":"venue"
},
  "geometry": {"coordinates":[36.4393234253,38.2791290283],"type":"Point"}
}