{
  "type": "Feature",
  "properties": {
    "iso:country":"TR",
    "sg:address":"G?en?sk. No.11 Bomonti Is Merkz. Bomonti Sisli",
    "sg:city":"\u00c7orlu",
    "sg:classifiers":[
        {
            "category":"Shopping",
            "subcategory":"Luggage & Leather Goods",
            "type":"Retail Goods"
        }
    ],
    "sg:phone":"+90 212 225 0420",
    "sg:province":"Istanbul",
    "sg:tags":[
        "leather-fur",
        "wear"
    ],
    "wof:name":"Y?kseller Deri Konfeksiyon San. Ve Tic. A.s.",
    "wof:placetype":"venue"
},
  "geometry": {"coordinates":[28.987903595,41.0586929321],"type":"Point"}
}