{
  "type": "Feature",
  "properties": {
    "iso:country":"TR",
    "sg:address":"E-5 Karayolu ?st?tuzla",
    "sg:city":"Yenisehir",
    "sg:classifiers":[
        {
            "category":"Building & Trades",
            "subcategory":"Plumbing",
            "type":"Services"
        }
    ],
    "sg:phone":"+90 216 395 0030",
    "sg:postcode":"31750",
    "sg:province":"Istanbul",
    "wof:name":"Eczacibasi Banyo K?vet San. Tic. A.s.",
    "wof:placetype":"venue"
},
  "geometry": {"coordinates":[32.4792823792,37.8843307495],"type":"Point"}
}