{
  "type": "Feature",
  "properties": {
    "addr:full":"Yapi Kredi Plaza C.blok Kat:8 P.k Ishani Kat:6 D:26 4.levent Besiktas Istanbul 34350",
    "addr:housenumber":"kat 8;kat 6 d 26 4.levent",
    "addr:postcode":"34350",
    "addr:street":"C.Blok;P.K Ishani",
    "iso:country":"TR",
    "sg:address":"Yapi Kredi Plaza C.blok Kat:8 P.k Ishani Kat:6 D:26 4.levent",
    "sg:city":"Besiktas",
    "sg:classifiers":[
        {
            "category":"Banks & Credit Unions",
            "subcategory":"Investment Brokerage",
            "type":"Services"
        }
    ],
    "sg:phone":"+90 212 270 6180",
    "sg:postcode":"34350",
    "sg:province":"Istanbul",
    "sg:tags":[
        "-",
        "export",
        "import"
    ],
    "wof:name":"Troyka Insaat Ve Tic.a.s.",
    "wof:placetype":"venue"
},
  "geometry": {"coordinates":[28.9861831665,41.0408554077],"type":"Point"}
}