{
  "type": "Feature",
  "properties": {
    "iso:country":"TR",
    "sg:address":"Menderes Mh. 22. Sk. No:15/b Esenler",
    "sg:city":"Topkapi",
    "sg:classifiers":[
        {
            "category":"Freight",
            "type":"Transportation"
        }
    ],
    "sg:phone":"+90 212 568 7260",
    "sg:postcode":"34020",
    "sg:province":"Istanbul",
    "sg:tags":[
        "packing",
        "industry"
    ],
    "wof:name":"?uvalsan ?uval Imal. San. Tic. Ltd. Sti.",
    "wof:placetype":"venue"
},
  "geometry": {"coordinates":[28.8945293427,41.0321731567],"type":"Point"}
}