{
  "type": "Feature",
  "properties": {
    "iso:country":"TR",
    "sg:address":"M.pasa Cad. No:264/a",
    "sg:city":"Narlidere",
    "sg:classifiers":[
        {
            "category":"Home & Garden",
            "subcategory":"Household Appliances",
            "type":"Retail Goods"
        }
    ],
    "sg:phone":"+90 232 239 0325",
    "sg:postcode":"33600",
    "sg:province":"Izmir",
    "sg:tags":[
        "conditioner",
        "air"
    ],
    "wof:name":"Ema Isitma Sogutma Klima San.ve Tic.ltd.sti.",
    "wof:placetype":"venue"
},
  "geometry": {"coordinates":[27.1584873199,38.3880996704],"type":"Point"}
}