{
  "type": "Feature",
  "properties": {
    "addr:full":"Perpa Tic.merkezi Kat:9 No:1522 Okmeydani \u00dcmraniye Istanbul",
    "addr:housenumber":"kat 9 no 1522",
    "addr:street":"Okmeydani",
    "iso:country":"TR",
    "sg:address":"Perpa Tic.merkezi Kat:9 No:1522 Okmeydani",
    "sg:city":"\u00dcmraniye",
    "sg:classifiers":[
        {
            "category":"Shopping",
            "subcategory":"Stationery & Office Supplies",
            "type":"Retail Goods"
        }
    ],
    "sg:phone":"+90 212 222 3303",
    "sg:province":"Istanbul",
    "wof:name":"Merve Kagitcilik Ve Kirtasiye Ltd.sti.",
    "wof:placetype":"venue"
},
  "geometry": {"coordinates":[28.975925,41.012379],"type":"Point"}
}