{
  "type": "Feature",
  "properties": {
    "addr:full":"Nuriseker Cad. No: 244 \u00c7orlu Usak",
    "addr:housenumber":"244",
    "addr:street":"Nuriseker Cad. No;Usak",
    "iso:country":"TR",
    "sg:address":"Nuriseker Cad. No: 244",
    "sg:city":"\u00c7orlu",
    "sg:classifiers":[
        {
            "category":"Shopping",
            "subcategory":"Luggage & Leather Goods",
            "type":"Retail Goods"
        }
    ],
    "sg:phone":"+90 276 231 3738",
    "sg:province":"Usak",
    "sg:tags":[
        "leather-fur",
        "wear"
    ],
    "wof:name":"Erkal Deri Tekstil San.tic.ltd.sti.",
    "wof:placetype":"venue"
},
  "geometry": {"coordinates":[29.4252529144,38.6794242859],"type":"Point"}
}