{
  "type": "Feature",
  "properties": {
    "addr:full":"Elif Apt. No:37/c Kanatli Ortak? Hatay 80840",
    "addr:postcode":"80840",
    "iso:country":"TR",
    "sg:address":"Elif Apt. No:37/c Kanatli",
    "sg:city":"Ortak?",
    "sg:classifiers":[
        {
            "category":"Organizations",
            "subcategory":"Professional Association",
            "type":"Services"
        }
    ],
    "sg:phone":"+90 326 214 3202",
    "sg:postcode":"80840",
    "sg:province":"Hatay",
    "wof:name":"Teb 28. .bolge Hatay Eczaci Odasi",
    "wof:placetype":"venue"
},
  "geometry": {"coordinates":[36.349811554,36.4018478394],"type":"Point"}
}