{
  "type": "Feature",
  "properties": {
    "iso:country":"TR",
    "sg:address":"?. ?esme San. Cd. No:44/1 Yenibosna",
    "sg:city":"Kad\u0131k\u00f6y",
    "sg:orig_category":"Printinh House",
    "sg:phone":"+90 212 503 4233",
    "sg:postcode":"34990",
    "sg:province":"Istanbul",
    "wof:name":"Gelisim Matbaacilik San. Tic. Ltd. Sti.",
    "wof:placetype":"venue"
},
  "geometry": {"coordinates":[28.9759254456,41.0123786926],"type":"Point"}
}