{
  "type": "Feature",
  "properties": {
    "addr:full":"Gida Toptancilar Sitesi N-blok No:16 Altindag Denizli 06160",
    "addr:housenumber":"16",
    "addr:postcode":"06160",
    "addr:street":"N-Blok No",
    "iso:country":"TR",
    "sg:address":"Gida Toptancilar Sitesi N-blok No:16",
    "sg:city":"Altindag",
    "sg:classifiers":[
        {
            "category":"Home & Garden",
            "subcategory":"Home Furnishings",
            "type":"Retail Goods"
        }
    ],
    "sg:phone":"+90 258 371 9228",
    "sg:postcode":"06160",
    "sg:province":"Denizli",
    "sg:tags":[
        "textile"
    ],
    "wof:name":"Aba Tekstil San.tic. Ltd.sti.",
    "wof:placetype":"venue"
},
  "geometry": {"coordinates":[29.0788803101,37.7851867676],"type":"Point"}
}