{
  "type": "Feature",
  "properties": {
    "iso:country":"TR",
    "sg:address":"Konur Sk. No:4 Kizilay",
    "sg:city":"Besiktas",
    "sg:classifiers":[
        {
            "category":"Shopping",
            "subcategory":"Stationery & Office Supplies",
            "type":"Retail Goods"
        }
    ],
    "sg:phone":"+90 312 418 8327",
    "sg:postcode":"34347",
    "sg:province":"Ankara",
    "wof:name":"Dost Kitap - Yayinevi",
    "wof:placetype":"venue"
},
  "geometry": {"coordinates":[32.856403,39.917927],"type":"Point"}
}