{
  "type": "Feature",
  "properties": {
    "addr:full":"Iskele Cad. G?ek Fethiye Mugla 44000",
    "addr:housenumber":"?",
    "addr:postcode":"44000",
    "addr:street":"Iskele Cad. G",
    "iso:country":"TR",
    "sg:address":"Iskele Cad. G?ek",
    "sg:city":"Fethiye",
    "sg:classifiers":[
        {
            "category":"Recreation",
            "subcategory":"Boat Charter",
            "type":"Entertainment"
        }
    ],
    "sg:phone":"+90 252 645 2317",
    "sg:postcode":"44000",
    "sg:province":"Mugla",
    "sg:tags":[
        "yachting"
    ],
    "wof:name":"Melis Tours",
    "wof:placetype":"venue"
},
  "geometry": {"coordinates":[28.3658008575,37.2196006775],"type":"Point"}
}