{
  "type": "Feature",
  "properties": {
    "addr:full":"Konya Devlet Karayolu 12. Km. Okmeydani Afyon 43050",
    "addr:housenumber":"12 km.",
    "addr:postcode":"43050",
    "addr:street":"Karayolu;Okmeydani Afyon",
    "iso:country":"TR",
    "sg:address":"Konya Devlet Karayolu 12. Km.",
    "sg:city":"Okmeydani",
    "sg:classifiers":[
        {
            "category":"Home & Garden",
            "subcategory":"Building Materials",
            "type":"Retail Goods"
        }
    ],
    "sg:phone":"+90 272 221 1156",
    "sg:postcode":"43050",
    "sg:province":"Afyon",
    "sg:tags":[
        "stone",
        "natural",
        "marble"
    ],
    "wof:name":"Oz Ugur Mermer A.s.",
    "wof:placetype":"venue"
},
  "geometry": {"coordinates":[30.5382652283,38.7579841614],"type":"Point"}
}