{
  "type": "Feature",
  "properties": {
    "iso:country":"TR",
    "sg:address":"Kucuk Balikli Mah. Fevzibey Cad.no:8",
    "sg:city":"Osmangazi",
    "sg:classifiers":[
        {
            "category":"Shopping",
            "subcategory":"Crafts & Fabrics",
            "type":"Retail Goods"
        }
    ],
    "sg:phone":"+90 224 215 9131",
    "sg:postcode":"46050",
    "sg:province":"Bursa",
    "sg:tags":[
        "knitting"
    ],
    "wof:name":"Katipler Tekstil Orme San.tic.a.s.",
    "wof:placetype":"venue"
},
  "geometry": {"coordinates":[29.0580043793,40.1947555542],"type":"Point"}
}