{
  "type": "Feature",
  "properties": {
    "addr:full":"Nalbantoglu Mah. Sekerhoca Cad. Bagdemli Sok. No:2/a Osmangazi Bursa 46050",
    "addr:housenumber":"no 2 / a",
    "addr:postcode":"46050",
    "addr:street":"Nalbantoglu Mah. Sekerhoca Cad. Bagdemli Sok.;Osmangazi Bursa",
    "iso:country":"TR",
    "sg:address":"Nalbantoglu Mah. Sekerhoca Cad. Bagdemli Sok. No:2/a",
    "sg:city":"Osmangazi",
    "sg:classifiers":[
        {
            "category":"Shopping",
            "subcategory":"Clothing, Apparel, & Fashions",
            "type":"Retail Goods"
        }
    ],
    "sg:phone":"+90 224 222 8051",
    "sg:postcode":"46050",
    "sg:province":"Bursa",
    "sg:tags":[
        "woman",
        "wear"
    ],
    "wof:name":"Menekse Tekstil",
    "wof:placetype":"venue"
},
  "geometry": {"coordinates":[29.058004,40.194756],"type":"Point"}
}