{
  "type": "Feature",
  "properties": {
    "iso:country":"TR",
    "sg:address":"Oguzhan Cd. Saglik Han No:13 D:16 Saraylar",
    "sg:city":"Erenk?",
    "sg:classifiers":[
        {
            "category":"Organizations",
            "subcategory":"Professional Association",
            "type":"Services"
        }
    ],
    "sg:phone":"+90 258 262 3419",
    "sg:province":"Denizli",
    "wof:name":"Denizli Lokantaci Esnaf Ve Sanatkar. Odasi",
    "wof:placetype":"venue"
},
  "geometry": {"coordinates":[29.0853366852,37.7837028503],"type":"Point"}
}