{
  "type": "Feature",
  "properties": {
    "iso:country":"TR",
    "sg:address":"Karakurt Koyu",
    "sg:city":"Suluca",
    "sg:classifiers":[
        {
            "category":"Shopping",
            "subcategory":"Crafts & Fabrics",
            "type":"Retail Goods"
        }
    ],
    "sg:phone":"+90 258 288 1101",
    "sg:postcode":"01350",
    "sg:province":"Denizli",
    "sg:tags":[
        "yarn"
    ],
    "wof:name":"Isil Tekstil Ltd.sti.",
    "wof:placetype":"venue"
},
  "geometry": {"coordinates":[32.4724235535,37.8867301941],"type":"Point"}
}