{
  "type": "Feature",
  "properties": {
    "addr:full":"Sedir Sokak No. 15 Armutlu Kemalpasa Izmir 35180",
    "addr:housenumber":"no. 15",
    "addr:postcode":"35180",
    "addr:street":"Sedir Sokak;Armutlu Kemalpasa",
    "iso:country":"TR",
    "sg:address":"Sedir Sokak No. 15 Armutlu",
    "sg:city":"Kemalpasa",
    "sg:classifiers":[
        {
            "category":"Food & Beverages",
            "subcategory":"Fruits & Vegetables",
            "type":"Retail Goods"
        }
    ],
    "sg:phone":"+90 232 886 7720",
    "sg:postcode":"35180",
    "sg:province":"Izmir",
    "sg:tags":[
        "product",
        "organic"
    ],
    "wof:name":"Blumeks Dis Ticaret Ltd. Sti.",
    "wof:placetype":"venue"
},
  "geometry": {"coordinates":[27.1000003815,38.3652763367],"type":"Point"}
}