{
  "type": "Feature",
  "properties": {
    "iso:country":"TR",
    "sg:address":"Lale Cad. No:34",
    "sg:city":"Gemlik",
    "sg:classifiers":[
        {
            "category":"Food & Beverages",
            "subcategory":"Groceries & Convenience Stores",
            "type":"Retail Goods"
        }
    ],
    "sg:phone":"+90 384 213 1925",
    "sg:postcode":"16600",
    "sg:province":"Nevsehir",
    "sg:tags":[
        "product"
    ],
    "wof:name":"Sura Gida Sanayi Ve Ticaret Ltd.sti.",
    "wof:placetype":"venue"
},
  "geometry": {"coordinates":[34.7150497437,38.6251106262],"type":"Point"}
}