{
  "type": "Feature",
  "properties": {
    "addr:full":"Merkez K?? San. Sitesi No:49/4 19/a 2.ulus Balikesir",
    "addr:housenumber":"19 / a 2.ulus",
    "addr:street":"Balikesir",
    "iso:country":"TR",
    "sg:address":"Merkez K?? San. Sitesi No:49/4 19/a",
    "sg:city":"2.ulus",
    "sg:classifiers":[
        {
            "category":"Manufacturing",
            "subcategory":"Rubber & Plastics",
            "type":"Manufacturing & Wholesale Goods"
        }
    ],
    "sg:phone":"+90 266 244 0057",
    "sg:province":"Balikesir",
    "sg:tags":[
        "industry"
    ],
    "wof:name":"Balpen Plastik Insaat Malzeme. Ltd. Sti.",
    "wof:placetype":"venue"
},
  "geometry": {"coordinates":[27.8833007812,39.6520996094],"type":"Point"}
}