{
  "type": "Feature",
  "properties": {
    "iso:country":"TR",
    "sg:address":"Kaptanpasa Sk.no:49 G.o.p.",
    "sg:city":"Cankaya",
    "sg:classifiers":[
        {
            "category":"Government",
            "subcategory":"Embassy",
            "type":"Public Place"
        }
    ],
    "sg:phone":"+90 312 446 1026",
    "sg:postcode":"07080",
    "sg:province":"Ankara",
    "sg:tags":[
        "foreign"
    ],
    "wof:name":"Moldova B?y?kel?iligi",
    "wof:placetype":"venue"
},
  "geometry": {"coordinates":[32.8741264343,39.8948402405],"type":"Point"}
}