{
  "type": "Feature",
  "properties": {
    "iso:country":"TR",
    "sg:address":"Banka. Ok?musa Cd. No:61 K:2 Karak?",
    "sg:city":"Ulus",
    "sg:classifiers":[
        {
            "category":"Shopping",
            "subcategory":"Computers & Home Electronics",
            "type":"Retail Goods"
        }
    ],
    "sg:phone":"+90 212 293 6500",
    "sg:postcode":"06050",
    "sg:province":"Istanbul",
    "sg:tags":[
        "product",
        "electric-electronic"
    ],
    "wof:name":"Silika Kablo San. Tic. Ltd.",
    "wof:placetype":"venue"
},
  "geometry": {"coordinates":[28.9861831665,41.0408554077],"type":"Point"}
}