{
  "type": "Feature",
  "properties": {
    "iso:country":"TR",
    "sg:address":"Keyap ?rsi No:131 Y.dudullu",
    "sg:city":"\u00dcmraniye",
    "sg:classifiers":[
        {
            "category":"Park",
            "subcategory":"Provincial",
            "type":"Public Place"
        }
    ],
    "sg:phone":"+90 216 420 9093",
    "sg:postcode":"34776",
    "sg:province":"Istanbul",
    "sg:tags":[
        "ind",
        "site",
        "keyap"
    ],
    "wof:name":"Azim Pastane Ihtiya? Mamulleri Paz. Ltd. Sti.",
    "wof:placetype":"venue"
},
  "geometry": {"coordinates":[29.175403595,41.0060424805],"type":"Point"}
}