{
  "type": "Feature",
  "properties": {
    "iso:country":"TR",
    "sg:address":"Nispetiye Cad.no:1/1",
    "sg:city":"Etiler",
    "sg:classifiers":[
        {
            "category":"Food & Beverages",
            "subcategory":"Candy",
            "type":"Retail Goods"
        }
    ],
    "sg:phone":"+90 212 257 2155",
    "sg:postcode":"07010",
    "sg:province":"Istanbul",
    "sg:tags":[
        "biscuit-chocolate-candy"
    ],
    "wof:name":"Neuhaus",
    "wof:placetype":"venue"
},
  "geometry": {"coordinates":[29.017464,41.074951],"type":"Point"}
}