{
  "type": "Feature",
  "properties": {
    "addr:full":"E-5 ?zeri, K??yali Yanyol, Irmak Sk. K??yali Is Mrk. D Blk. N.9 - N. 20 Maltepe Istanbul 01000",
    "addr:housenumber":"? ?;blk.",
    "addr:postcode":"01000",
    "addr:street":"Zeri;Yali Yanyol;Sk. K ? ? Yali;N. 20 Maltepe Istanbul",
    "iso:country":"TR",
    "sg:address":"E-5 ?zeri, K??yali Yanyol, Irmak Sk. K??yali Is Mrk. D Blk. N.9 - N. 20",
    "sg:city":"Maltepe",
    "sg:classifiers":[
        {
            "category":"Manufacturing",
            "subcategory":"Motor Vehicles & Parts",
            "type":"Manufacturing & Wholesale Goods"
        }
    ],
    "sg:phone":"+90 216 417 8760",
    "sg:postcode":"01000",
    "sg:province":"Istanbul",
    "sg:tags":[
        "machine",
        "spare"
    ],
    "sg:website":"deltaendustriyel.com",
    "wof:name":"Delta Endustriyel Urn Ve Dis Tic. Ltd.sti.",
    "wof:placetype":"venue"
},
  "geometry": {"coordinates":[28.9861831665,41.0408554077],"type":"Point"}
}