{
  "type": "Feature",
  "properties": {
    "iso:country":"TR",
    "sg:address":"Vatan Cad.dizer Sok. No:1/a-",
    "sg:city":"Caglayan",
    "sg:classifiers":[
        {
            "category":"Manufacturing",
            "subcategory":"Glass & Minerals",
            "type":"Manufacturing & Wholesale Goods"
        }
    ],
    "sg:phone":"+90 212 233 8373",
    "sg:postcode":"07600",
    "sg:province":"Istanbul",
    "sg:tags":[
        "glass-mirror"
    ],
    "wof:name":"Sevsan Cam Kapi San Ve Tic Ltd.",
    "wof:placetype":"venue"
},
  "geometry": {"coordinates":[28.9844207764,41.0793380737],"type":"Point"}
}