{
  "type": "Feature",
  "properties": {
    "addr:full":"Besevler San.sitesi 23 Blok Iskenderun Bursa 31200",
    "addr:housenumber":"23 blok iskenderun",
    "addr:postcode":"31200",
    "iso:country":"TR",
    "sg:address":"Besevler San.sitesi 23 Blok",
    "sg:city":"Iskenderun",
    "sg:classifiers":[
        {
            "category":"Building & Trades",
            "subcategory":"Plumbing",
            "type":"Services"
        }
    ],
    "sg:phone":"+90 224 441 1349",
    "sg:postcode":"31200",
    "sg:province":"Bursa",
    "sg:tags":[
        "filter",
        "industry"
    ],
    "wof:name":"Filcosan Filitre San.a.s",
    "wof:placetype":"venue"
},
  "geometry": {"coordinates":[29.0580043793,40.1947555542],"type":"Point"}
}