{
  "type": "Feature",
  "properties": {
    "iso:country":"TR",
    "sg:address":"Incesu Cad. No:96 Apt.kolej",
    "sg:city":"Maltepe",
    "sg:classifiers":[
        {
            "category":"Wholesale",
            "subcategory":"Books, Periodicals, & Newspapers",
            "type":"Manufacturing & Wholesale Goods"
        }
    ],
    "sg:phone":"+90 312 435 3790",
    "sg:postcode":"01000",
    "sg:province":"Ankara",
    "sg:tags":[
        "house",
        "publishing"
    ],
    "wof:name":"Kardelen Ofset Baski Ve Tanitim Hizm.ltd.sti.",
    "wof:placetype":"venue"
},
  "geometry": {"coordinates":[32.8985366821,39.9189834595],"type":"Point"}
}