{
  "type": "Feature",
  "properties": {
    "addr:full":"Girishane Mah.etibank Cad. No:9 Beyoglu Bursa 80320",
    "addr:postcode":"80320",
    "addr:street":"Mah.Etibank Cad. No 9 Beyoglu",
    "iso:country":"TR",
    "sg:address":"Girishane Mah.etibank Cad. No:9",
    "sg:city":"Beyoglu",
    "sg:classifiers":[
        {
            "category":"Building & Trades",
            "subcategory":"Electrical",
            "type":"Services"
        }
    ],
    "sg:phone":"+90 224 233 0505",
    "sg:postcode":"80320",
    "sg:province":"Bursa",
    "sg:tags":[
        "equipment",
        "lighting"
    ],
    "wof:name":"Yildiz Avize",
    "wof:placetype":"venue"
},
  "geometry": {"coordinates":[29.0523338318,40.2047157288],"type":"Point"}
}