{
  "type": "Feature",
  "properties": {
    "addr:full":"Fevzi Cakmak Mah. Karakayis Cad. Sadakat Sok. No:1 Karatay Mersin Konya 52750",
    "addr:housenumber":"no 1",
    "addr:postcode":"52750",
    "addr:street":"Cakmak Mah. Karakayis Cad. Sadakat Sok.;Karatay",
    "iso:country":"TR",
    "sg:address":"Fevzi Cakmak Mah. Karakayis Cad. Sadakat Sok. No:1 Karatay",
    "sg:city":"Mersin",
    "sg:classifiers":[
        {
            "category":"Professional",
            "subcategory":"Art Services",
            "type":"Services"
        }
    ],
    "sg:phone":"+90 332342088283",
    "sg:postcode":"52750",
    "sg:province":"Konya",
    "sg:tags":[
        "marketing"
    ],
    "wof:name":"G?lab Ithalat Ihracat Dagitim Pazarlama A.s.",
    "wof:placetype":"venue"
},
  "geometry": {"coordinates":[33.0667152405,39.2111282349],"type":"Point"}
}