{
  "type": "Feature",
  "properties": {
    "addr:full":"Kayisdagi Sok.metal Is Merk. No: 31/30 I?renk? Istanbul Bak\u0131rk\u00f6y Istanbul",
    "addr:housenumber":"30;?",
    "addr:postcode":"?",
    "addr:street":"I",
    "iso:country":"TR",
    "sg:address":"Kayisdagi Sok.metal Is Merk. No: 31/30 I?renk? Istanbul",
    "sg:city":"Bak\u0131rk\u00f6y",
    "sg:classifiers":[
        {
            "category":"Shopping",
            "type":"Retail Goods"
        }
    ],
    "sg:phone":"+90 216 573 0696",
    "sg:province":"Istanbul",
    "sg:tags":[
        "material",
        "cleaning"
    ],
    "wof:name":"Neftflot Kimya",
    "wof:placetype":"venue"
},
  "geometry": {"coordinates":[28.9861793518,41.040851593],"type":"Point"}
}