{
  "type": "Feature",
  "properties": {
    "addr:full":"Mecidiye Cad. No:7/50 K.3-4 Mecidiyek? Yesilk?y Istanbul 34830",
    "addr:housenumber":"50 k.3-4 mecidiyek ?;?",
    "addr:postcode":"34830",
    "addr:street":"Mecidiye Cad. No 7 /;Yesilk;Y Istanbul",
    "iso:country":"TR",
    "sg:address":"Mecidiye Cad. No:7/50 K.3-4 Mecidiyek?",
    "sg:city":"Yesilk?y",
    "sg:classifiers":[
        {
            "category":"Organizations",
            "subcategory":"Membership Organization",
            "type":"Services"
        }
    ],
    "sg:phone":"+90 212 213 6100",
    "sg:postcode":"34830",
    "sg:province":"Istanbul",
    "wof:name":"M?siad",
    "wof:placetype":"venue"
},
  "geometry": {"coordinates":[28.9861831665,41.0408554077],"type":"Point"}
}