{
  "type": "Feature",
  "properties": {
    "iso:country":"TR",
    "sg:address":"Kultur Mah. Nazim Sok.mutlu Pasaji No:3/b",
    "sg:city":"Duzce",
    "sg:classifiers":[
        {
            "category":"Farming",
            "subcategory":"Farm & Veterinary Services",
            "type":"Manufacturing & Wholesale Goods"
        }
    ],
    "sg:phone":"+90 374 523 5369",
    "sg:postcode":"01000",
    "sg:province":"Bolu",
    "sg:tags":[
        "veterinarian"
    ],
    "wof:name":"Dogan Horel",
    "wof:placetype":"venue"
},
  "geometry": {"coordinates":[31.6107006073,40.7332992554],"type":"Point"}
}