{
  "type": "Feature",
  "properties": {
    "addr:full":"Ramikisla Cd. Seferaga San. Sit. No:47 Top?lar Gemlik Istanbul 16600",
    "addr:housenumber":"no 47;?",
    "addr:postcode":"16600",
    "addr:street":"Ramikisla Cd. Seferaga San. Sit.;Top",
    "iso:country":"TR",
    "sg:address":"Ramikisla Cd. Seferaga San. Sit. No:47 Top?lar",
    "sg:city":"Gemlik",
    "sg:classifiers":[
        {
            "category":"Manufacturing",
            "subcategory":"Tools & Machinery",
            "type":"Manufacturing & Wholesale Goods"
        }
    ],
    "sg:phone":"+90 212 577 4968",
    "sg:postcode":"16600",
    "sg:province":"Istanbul",
    "sg:tags":[
        "machine",
        "industry"
    ],
    "wof:name":"Asel Makina Teks. Yedek Par?a San.",
    "wof:placetype":"venue"
},
  "geometry": {"coordinates":[28.9759254456,41.0123786926],"type":"Point"}
}