{
  "type": "Feature",
  "properties": {
    "addr:full":"Ikitelli Organize Sanayi B?gesi Metal Is Sanayi Sitesi 12 Blok No:11 Ikitelli/K\u00fc\u00e7\u00fck\u00e7ekmece Istanbul 34660",
    "addr:housenumber":"?;12 blok no 11",
    "addr:postcode":"34660",
    "addr:street":"Organize Sanayi B;Sitesi",
    "iso:country":"TR",
    "sg:address":"Ikitelli Organize Sanayi B?gesi Metal Is Sanayi Sitesi 12 Blok No:11",
    "sg:city":"Ikitelli/K\u00fc\u00e7\u00fck\u00e7ekmece",
    "sg:classifiers":[
        {
            "category":"Building & Trades",
            "subcategory":"Construction",
            "type":"Services"
        }
    ],
    "sg:phone":"+90 212 549 3082",
    "sg:postcode":"34660",
    "sg:province":"Istanbul",
    "sg:tags":[
        "industry",
        "mold"
    ],
    "wof:name":"?nder Kalip Ve Plastik San.tic.ltd.sti",
    "wof:placetype":"venue"
},
  "geometry": {"coordinates":[29.0496292114,41.0075798035],"type":"Point"}
}