{
  "type": "Feature",
  "properties": {
    "iso:country":"TR",
    "sg:address":"?zg? Mah. C?b?l?cad. No:40",
    "sg:city":"Bornova",
    "sg:classifiers":[
        {
            "category":"Wholesale",
            "subcategory":"Farm Supplies",
            "type":"Manufacturing & Wholesale Goods"
        }
    ],
    "sg:phone":"+90 248 234 1808",
    "sg:postcode":"35040",
    "sg:province":"Burdur",
    "sg:tags":[
        "feed",
        "industry"
    ],
    "wof:name":"B?gd?zl?ler Tarim Hayvancilik Yem Ltd.sti.",
    "wof:placetype":"venue"
},
  "geometry": {"coordinates":[30.2842998505,37.7192993164],"type":"Point"}
}