{
  "type": "Feature",
  "properties": {
    "addr:full":"Sivrihisar Cd. B?? Otel Pasaji No:40/118 Kad\u0131k\u00f6y Eskisehir 34718",
    "addr:housenumber":"? ?;40 / 118",
    "addr:postcode":"34718",
    "addr:street":"Sivrihisar Cd. B;Pasaji No;Kadikoey Eskisehir",
    "iso:country":"TR",
    "sg:address":"Sivrihisar Cd. B?? Otel Pasaji No:40/118",
    "sg:city":"Kad\u0131k\u00f6y",
    "sg:classifiers":[
        {
            "category":"Mining & Drilling",
            "type":"Manufacturing & Wholesale Goods"
        }
    ],
    "sg:phone":"+90 222 231 2788",
    "sg:postcode":"34718",
    "sg:province":"Eskisehir",
    "sg:tags":[
        "industry",
        "mine"
    ],
    "wof:name":"Kon?ak L?letasi San. Ve Tic. Koll. Sti.",
    "wof:placetype":"venue"
},
  "geometry": {"coordinates":[30.5175457001,39.7700805664],"type":"Point"}
}