{
  "type": "Feature",
  "properties": {
    "addr:full":"Imes San.sit.b Blok 204 Sok.no:16 Dudullu Istanbul",
    "addr:housenumber":"blok 204;16",
    "addr:street":"Sok.No",
    "iso:country":"TR",
    "sg:address":"Imes San.sit.b Blok 204 Sok.no:16",
    "sg:city":"Dudullu",
    "sg:classifiers":[
        {
            "category":"Shopping",
            "subcategory":"Computers & Home Electronics",
            "type":"Retail Goods"
        }
    ],
    "sg:phone":"+90 216 420 1860",
    "sg:province":"Istanbul",
    "sg:tags":[
        "product",
        "electric-electronic"
    ],
    "wof:name":"Emikon Elektonik San.ve Tic.ltd.sti.",
    "wof:placetype":"venue"
},
  "geometry": {"coordinates":[28.9861831665,41.0408554077],"type":"Point"}
}