{
  "type": "Feature",
  "properties": {
    "addr:full":"Kizilirmak Sk. No:45 Kizilay Iskenderun Ankara 31200",
    "addr:housenumber":"45",
    "addr:postcode":"31200",
    "addr:street":"Kizilirmak Sk. No",
    "iso:country":"TR",
    "sg:address":"Kizilirmak Sk. No:45 Kizilay",
    "sg:city":"Iskenderun",
    "sg:classifiers":[
        {
            "category":"Mining & Drilling",
            "type":"Manufacturing & Wholesale Goods"
        }
    ],
    "sg:phone":"+90 312 417 7641",
    "sg:postcode":"31200",
    "sg:province":"Ankara",
    "sg:tags":[
        "industry",
        "mine"
    ],
    "wof:name":"Yeni ?eltek K?m?r Madencilik Isletmesi A.s.",
    "wof:placetype":"venue"
},
  "geometry": {"coordinates":[32.8596153259,39.9175682068],"type":"Point"}
}