{
  "type": "Feature",
  "properties": {
    "addr:full":"Tepe?t?alemdag Cd. No:68 ?mraniye Mahmutbey Istanbul 84581",
    "addr:housenumber":"no 68 ?",
    "addr:postcode":"84581",
    "addr:street":"T;Alemdag Cd.;Mraniye Mahmutbey",
    "iso:country":"TR",
    "sg:address":"Tepe?t?alemdag Cd. No:68 ?mraniye",
    "sg:city":"Mahmutbey",
    "sg:classifiers":[
        {
            "category":"Wholesale",
            "subcategory":"Machinery & Supplies",
            "type":"Manufacturing & Wholesale Goods"
        }
    ],
    "sg:phone":"+90 216 364 1754",
    "sg:postcode":"84581",
    "sg:province":"Istanbul",
    "sg:tags":[
        "heavy",
        "construction",
        "macinery"
    ],
    "wof:name":"Vin? Mak. Hidrolik Vin? Mak. San. Ltd. Sti.",
    "wof:placetype":"venue"
},
  "geometry": {"coordinates":[28.9861831665,41.0408554077],"type":"Point"}
}