{
  "type": "Feature",
  "properties": {
    "iso:country":"TR",
    "sg:address":"Siteler Mah.fevzi Cakmak Cad. No: 34",
    "sg:city":"B.cekmece",
    "sg:classifiers":[
        {
            "category":"Retail",
            "subcategory":"Driving School",
            "type":"Services"
        }
    ],
    "sg:phone":"+90 384 214 3174",
    "sg:province":"Nevsehir",
    "sg:tags":[
        "cargo"
    ],
    "wof:name":"Birlesik Dagitim Nakliyat Anbari",
    "wof:placetype":"venue"
},
  "geometry": {"coordinates":[34.7110939026,38.6325645447],"type":"Point"}
}