{
  "type": "Feature",
  "properties": {
    "addr:full":"Strazburg Cad.no:27/19 Sihiye 1.levent Besiktas Ankara 80600",
    "addr:housenumber":"27 / 19",
    "addr:postcode":"80600",
    "addr:street":"Sihiye;Besiktas",
    "iso:country":"TR",
    "sg:address":"Strazburg Cad.no:27/19 Sihiye",
    "sg:city":"1.levent Besiktas",
    "sg:classifiers":[
        {
            "category":"Manufacturing",
            "subcategory":"Building Materials",
            "type":"Manufacturing & Wholesale Goods"
        }
    ],
    "sg:phone":"+90 312 230 2196",
    "sg:postcode":"80600",
    "sg:province":"Ankara",
    "sg:tags":[
        "promotional"
    ],
    "wof:name":"Serap Babacan",
    "wof:placetype":"venue"
},
  "geometry": {"coordinates":[32.8988227844,39.9432601929],"type":"Point"}
}