{
  "type": "Feature",
  "properties": {
    "iso:country":"TR",
    "sg:address":"Cumhuriyet Mah.devrim Sok.no:2",
    "sg:city":"Kusadasi",
    "sg:classifiers":[
        {
            "category":"Government",
            "subcategory":"Fire Station",
            "type":"Public Place"
        }
    ],
    "sg:phone":"+90 256 612 5138",
    "sg:postcode":"09400",
    "sg:province":"Aydin",
    "sg:tags":[
        "decoration"
    ],
    "wof:name":"Milano Kartonpiyer Alci Dizayn",
    "wof:placetype":"venue"
},
  "geometry": {"coordinates":[27.8324394226,37.8409690857],"type":"Point"}
}