{
  "type": "Feature",
  "properties": {
    "addr:full":"I.a.h.l Serbest Bolgesi Plaza No:608 Yesilkoy \u00dcmraniye Istanbul",
    "addr:street":"Yesilkoy",
    "iso:country":"TR",
    "sg:address":"I.a.h.l Serbest Bolgesi Plaza No:608 Yesilkoy",
    "sg:city":"\u00dcmraniye",
    "sg:classifiers":[
        {
            "category":"Home & Garden",
            "subcategory":"Hardware",
            "type":"Retail Goods"
        }
    ],
    "sg:phone":"+90 212 465 0561",
    "sg:province":"Istanbul",
    "sg:tags":[
        "generator",
        "power"
    ],
    "sg:website":"globalmotor.com.tr",
    "wof:name":"Global Motor Paz.dis Tic.ltd.",
    "wof:placetype":"venue"
},
  "geometry": {"coordinates":[28.8221492767,40.9777297974],"type":"Point"}
}