{
  "type": "Feature",
  "properties": {
    "iso:country":"TR",
    "sg:address":"I.m.? 4. Blok No:4303",
    "sg:city":"Unkapani",
    "sg:classifiers":[
        {
            "category":"Government",
            "subcategory":"Fire Station",
            "type":"Public Place"
        }
    ],
    "sg:phone":"+90 21252802040",
    "sg:postcode":"55020",
    "sg:province":"Istanbul",
    "sg:tags":[
        "decoration"
    ],
    "wof:name":"Ekin Halicilik Tic. Ve San. Ltd. Sti.",
    "wof:placetype":"venue"
},
  "geometry": {"coordinates":[28.9861831665,41.0408554077],"type":"Point"}
}