{
  "type": "Feature",
  "properties": {
    "addr:full":"Izmir Ankara Asfalti 25.km. Uncubasi Mevkii Kemalpasi Izmir",
    "addr:street":"Uncubasi Mevkii Kemalpasi",
    "iso:country":"TR",
    "sg:address":"Izmir Ankara Asfalti 25.km. Uncubasi Mevkii",
    "sg:city":"Kemalpasi",
    "sg:classifiers":[
        {
            "category":"Manufacturing",
            "subcategory":"Textiles",
            "type":"Manufacturing & Wholesale Goods"
        }
    ],
    "sg:phone":"+90 232 877 1181",
    "sg:province":"Izmir",
    "sg:tags":[
        "sizing",
        "dye"
    ],
    "wof:name":"Nur-ka Tekstil Sanayi Ve Ticaret A.s",
    "wof:placetype":"venue"
},
  "geometry": {"coordinates":[27.1422595978,38.4252090454],"type":"Point"}
}