{
  "type": "Feature",
  "properties": {
    "iso:country":"TR",
    "sg:address":"?oban?sme G?esli Sok. Durmazel Han. No:4/4",
    "sg:city":"Yenibosna",
    "sg:classifiers":[
        {
            "category":"Parking",
            "subcategory":"Garage",
            "type":"Transportation"
        }
    ],
    "sg:phone":"+90 212 551 3245",
    "sg:postcode":"43270",
    "sg:province":"Istanbul",
    "sg:tags":[
        "zipper"
    ],
    "wof:name":"Bosnateks Tekstil San. Ve Tic.ltd.sti.",
    "wof:placetype":"venue"
},
  "geometry": {"coordinates":[28.9759254456,41.0123786926],"type":"Point"}
}