{
  "type": "Feature",
  "properties": {
    "addr:full":"Baglar Mah.cesme Alti Sok. No:8 G?esli Iskenderun Istanbul 31200",
    "addr:housenumber":"no 8 g ?",
    "addr:postcode":"31200",
    "addr:street":"Alti Sok.;Esli",
    "iso:country":"TR",
    "sg:address":"Baglar Mah.cesme Alti Sok. No:8 G?esli",
    "sg:city":"Iskenderun",
    "sg:classifiers":[
        {
            "category":"Manufacturing",
            "subcategory":"Tools & Machinery",
            "type":"Manufacturing & Wholesale Goods"
        }
    ],
    "sg:phone":"+90 212 550 6339",
    "sg:postcode":"31200",
    "sg:province":"Istanbul",
    "sg:tags":[
        "machine",
        "industry"
    ],
    "wof:name":"Alev Inoks Makina San.tic.ltd.sti.",
    "wof:placetype":"venue"
},
  "geometry": {"coordinates":[28.9759254456,41.0123786926],"type":"Point"}
}