{
  "type": "Feature",
  "properties": {
    "addr:full":"Valikonagi Cd. Sakayik Sk. No:40 K:5 Tesvikiye Kadikoy Istanbul 01370",
    "addr:housenumber":"40 k 5",
    "addr:postcode":"01370",
    "addr:street":"Valikonagi Cd. Sakayik Sk. No;Tesvikiye Kadikoy",
    "iso:country":"TR",
    "sg:address":"Valikonagi Cd. Sakayik Sk. No:40 K:5 Tesvikiye",
    "sg:city":"Kadikoy",
    "sg:orig_category":"Art Galeries",
    "sg:phone":"+90 212 234 4044",
    "sg:postcode":"01370",
    "sg:province":"Istanbul",
    "wof:name":"Nuans Sanat Merk.",
    "wof:placetype":"venue"
},
  "geometry": {"coordinates":[28.9861831665,41.0408554077],"type":"Point"}
}