{
  "type": "Feature",
  "properties": {
    "addr:full":"Emirhan Cad. Yenigelin Sok. No:17 Dikilitas Besiktas Istanbul 75200",
    "addr:housenumber":"no 17",
    "addr:postcode":"75200",
    "addr:street":"Emirhan Cad. Yenigelin Sok.;Dikilitas Besiktas",
    "iso:country":"TR",
    "sg:address":"Emirhan Cad. Yenigelin Sok. No:17 Dikilitas",
    "sg:city":"Besiktas",
    "sg:classifiers":[
        {
            "category":"Community Center",
            "type":"Public Place"
        }
    ],
    "sg:phone":"+90 212 236 3060",
    "sg:postcode":"75200",
    "sg:province":"Istanbul",
    "sg:tags":[
        "education",
        "private"
    ],
    "wof:name":"Boem-besiktas ?zel Egitim Ve Rehabilitasyon Merk.",
    "wof:placetype":"venue"
},
  "geometry": {"coordinates":[29.006685257,41.0581359863],"type":"Point"}
}