{
  "type": "Feature",
  "properties": {
    "addr:full":"Cumhuriyet Meydani 1 Tavsanli 43300 43300",
    "addr:housenumber":"1",
    "addr:postcode":"43300 43300",
    "addr:street":"Meydani",
    "iso:country":"TR",
    "sg:address":"Cumhuriyet Meydani 1",
    "sg:city":"Tavsanli",
    "sg:classifiers":[
        {
            "category":"Banks & Credit Unions",
            "subcategory":"Bank",
            "type":"Services"
        }
    ],
    "sg:phone":"+90 274 614 0836",
    "sg:postcode":"43300",
    "sg:province":"43300",
    "wof:name":"Etibank Bao",
    "wof:placetype":"venue"
},
  "geometry": {"coordinates":[28.364073,37.215111],"type":"Point"}
}