{
  "type": "Feature",
  "properties": {
    "iso:country":"TR",
    "sg:address":"M?ercim Asim Cad 13/a",
    "sg:city":"D?d?co Levent",
    "sg:classifiers":[
        {
            "category":"Banks & Credit Unions",
            "subcategory":"Bank",
            "type":"Services"
        }
    ],
    "sg:phone":"+90 8524377",
    "sg:province":"Gaziantep",
    "wof:name":"T?kiye Garanti Bankasi",
    "wof:placetype":"venue"
},
  "geometry": {"coordinates":[37.376102,37.062946],"type":"Point"}
}