{
  "type": "Feature",
  "properties": {
    "iso:country":"TR",
    "sg:address":"Sakarya Cad. No: 1/28",
    "sg:city":"Kizilay",
    "sg:classifiers":[
        {
            "category":"Travel",
            "subcategory":"Travel Agent",
            "type":"Entertainment"
        }
    ],
    "sg:phone":"+90 3124356093435",
    "sg:postcode":"23050",
    "sg:province":"Ankara",
    "sg:tags":[
        "agency",
        "tourism"
    ],
    "wof:name":"Kervan Turizm",
    "wof:placetype":"venue"
},
  "geometry": {"coordinates":[33.1742515564,39.9841461182],"type":"Point"}
}