{
  "type": "Feature",
  "properties": {
    "addr:full":"Mithatpasa C. 1.sk. No. 37-39 Sirinevler Zeytinburnu Istanbul 41000",
    "addr:housenumber":"no. 37-39",
    "addr:postcode":"41000",
    "addr:street":"Sirinevler Zeytinburnu",
    "iso:country":"TR",
    "sg:address":"Mithatpasa C. 1.sk. No. 37-39 Sirinevler",
    "sg:city":"Zeytinburnu",
    "sg:classifiers":[
        {
            "category":"Shopping",
            "subcategory":"Luggage & Leather Goods",
            "type":"Retail Goods"
        }
    ],
    "sg:phone":"+90 212 551 4308",
    "sg:postcode":"41000",
    "sg:province":"Istanbul",
    "sg:tags":[
        "leather-fur",
        "wear"
    ],
    "wof:name":"Stil Deri Giy. Ltd. Sti.",
    "wof:placetype":"venue"
},
  "geometry": {"coordinates":[28.8500328064,40.993144989],"type":"Point"}
}