{
  "type": "Feature",
  "properties": {
    "addr:full":"Maresal F.cakmak Cad. 2.sok.no: 2/11 Sirinevler Istanbul 15040",
    "addr:housenumber":"2.sok.no 2 / 11",
    "addr:postcode":"15040",
    "addr:street":"F.Cakmak Cad.;Istanbul",
    "iso:country":"TR",
    "sg:address":"Maresal F.cakmak Cad. 2.sok.no: 2/11",
    "sg:city":"Sirinevler",
    "sg:classifiers":[
        {
            "category":"Farming",
            "subcategory":"Farm",
            "type":"Manufacturing & Wholesale Goods"
        }
    ],
    "sg:phone":"+90 212 551 4563",
    "sg:postcode":"15040",
    "sg:province":"Istanbul",
    "sg:tags":[
        "agricultural",
        "product"
    ],
    "wof:name":"Apricot Garden",
    "wof:placetype":"venue"
},
  "geometry": {"coordinates":[28.9318790436,41.0656166077],"type":"Point"}
}