{
  "type": "Feature",
  "properties": {
    "iso:country":"TR",
    "sg:address":"Ozankara Top. Sitesi 2.blok No:68 Macunkoy",
    "sg:city":"\u00dcmraniye",
    "sg:classifiers":[
        {
            "category":"Shopping",
            "type":"Retail Goods"
        }
    ],
    "sg:phone":"+90 312397453233",
    "sg:postcode":"81240",
    "sg:province":"Ankara",
    "sg:tags":[
        "material",
        "cleaning"
    ],
    "wof:name":"Keytem Temizlik Gida Ve Iht. Mad. Ltd.sti.",
    "wof:placetype":"venue"
},
  "geometry": {"coordinates":[32.8604812622,39.9429283142],"type":"Point"}
}