{
  "type": "Feature",
  "properties": {
    "iso:country":"TR",
    "sg:address":"Alemdag Cad 60/2",
    "sg:city":"\u00dcmraniye",
    "sg:classifiers":[
        {
            "category":"Banks & Credit Unions",
            "subcategory":"Bank",
            "type":"Services"
        }
    ],
    "sg:phone":"+90 216 316 3186",
    "sg:province":"81230",
    "wof:name":"Kocbank As",
    "wof:placetype":"venue"
},
  "geometry": {"coordinates":[29.089121,41.02499],"type":"Point"}
}