{
  "type": "Feature",
  "properties": {
    "iso:country":"TR",
    "sg:address":"Demirkapi Cd. G?su Sk. No:24 Bayrampasa",
    "sg:city":"Ikitelli/K\u00fc\u00e7\u00fck\u00e7ekmece",
    "sg:orig_category":"Furniture Supplamentary",
    "sg:phone":"+90 212 576 6590",
    "sg:postcode":"34660",
    "sg:province":"Istanbul",
    "wof:name":"Seme Dekor.",
    "wof:placetype":"venue"
},
  "geometry": {"coordinates":[28.927274704,41.0086631775],"type":"Point"}
}