{
  "type": "Feature",
  "properties": {
    "iso:country":"TR",
    "sg:address":"Zafer Mah.",
    "sg:city":"G??ler",
    "sg:classifiers":[
        {
            "category":"Shopping",
            "subcategory":"Clothing, Apparel, & Fashions",
            "type":"Retail Goods"
        }
    ],
    "sg:phone":"+90 258 371 5590",
    "sg:province":"Denizli",
    "sg:tags":[
        "-",
        "towel",
        "bathrobe"
    ],
    "wof:name":"Derek?yl? Tekstil Ltd.sti.",
    "wof:placetype":"venue"
},
  "geometry": {"coordinates":[29.0618400574,37.7908935547],"type":"Point"}
}