{
  "type": "Feature",
  "properties": {
    "iso:country":"TR",
    "sg:address":"M.sanayi Sitesi 1.cad.no:15/a",
    "sg:city":"B.cekmece",
    "sg:classifiers":[
        {
            "category":"Home & Garden",
            "subcategory":"Household Appliances",
            "type":"Retail Goods"
        }
    ],
    "sg:phone":"+90 212 875 7979",
    "sg:province":"Istanbul",
    "sg:tags":[
        "conditioner",
        "air"
    ],
    "wof:name":"Proses Mekanik Isi Endustrisi Taahhut Proje Ve Tic.ltd.",
    "wof:placetype":"venue"
},
  "geometry": {"coordinates":[29.0317134857,41.0945167542],"type":"Point"}
}