{
  "type": "Feature",
  "properties": {
    "addr:full":"Talatpasa Caddesi No:142 - Sisli 64020 Istanbul",
    "addr:housenumber":"no",
    "addr:postcode":"64020",
    "addr:street":"Talatpasa Caddesi;Sisli",
    "iso:country":"TR",
    "sg:address":"Talatpasa Caddesi No:142 - Sisli",
    "sg:city":"64020",
    "sg:classifiers":[
        {
            "category":"Government",
            "subcategory":"Post Office",
            "type":"Public Place"
        }
    ],
    "sg:phone":"+90 212 268 6548",
    "sg:province":"Istanbul",
    "sg:tags":[
        "notary"
    ],
    "wof:name":"Beyoglu 32 Noterligi",
    "wof:placetype":"venue"
},
  "geometry": {"coordinates":[28.9992389679,41.0789108276],"type":"Point"}
}