{
  "type": "Feature",
  "properties": {
    "iso:country":"TR",
    "sg:address":"Izmir Yolu ?zeri 8 Km.",
    "sg:city":"Iskenderun",
    "sg:classifiers":[
        {
            "category":"Mining & Drilling",
            "type":"Manufacturing & Wholesale Goods"
        }
    ],
    "sg:phone":"+90 266 221 1050",
    "sg:postcode":"31200",
    "sg:province":"Balikesir",
    "sg:tags":[
        "industry",
        "mine"
    ],
    "wof:name":"Sayak?i Madencilik Tic. Ltd. Sti.",
    "wof:placetype":"venue"
},
  "geometry": {"coordinates":[27.8833007812,39.6520996094],"type":"Point"}
}