{
  "type": "Feature",
  "properties": {
    "addr:full":"Afitap Sk. No:15 Pendik Samsun 34916",
    "addr:housenumber":"15",
    "addr:postcode":"34916",
    "addr:street":"Afitap Sk. No",
    "iso:country":"TR",
    "sg:address":"Afitap Sk. No:15",
    "sg:city":"Pendik",
    "sg:classifiers":[
        {
            "category":"Wholesale",
            "subcategory":"Home Furnishings",
            "type":"Manufacturing & Wholesale Goods"
        }
    ],
    "sg:phone":"+90 362 238 1313",
    "sg:postcode":"34916",
    "sg:province":"Samsun",
    "sg:tags":[
        "furniture"
    ],
    "wof:name":"Evma Mobilya",
    "wof:placetype":"venue"
},
  "geometry": {"coordinates":[36.3381233215,41.2815742493],"type":"Point"}
}