{
  "type": "Feature",
  "properties": {
    "addr:full":"Elmali Mah. Cumhuriyet Cad. Isik Apt. No:76/3 Kat:2 Sisli Antalya 65710",
    "addr:housenumber":"76 / 3 kat 2",
    "addr:postcode":"65710",
    "addr:street":"Elmali Mah. Cumhuriyet Cad. Isik Apt. No;Sisli",
    "iso:country":"TR",
    "sg:address":"Elmali Mah. Cumhuriyet Cad. Isik Apt. No:76/3 Kat:2",
    "sg:city":"Sisli",
    "sg:classifiers":[
        {
            "category":"Professional",
            "subcategory":"Business Services",
            "type":"Services"
        }
    ],
    "sg:phone":"+90 242 247 0146",
    "sg:postcode":"65710",
    "sg:province":"Antalya",
    "wof:name":"Podyum Ajans",
    "wof:placetype":"venue"
},
  "geometry": {"coordinates":[30.7031345367,36.8875045776],"type":"Point"}
}