{
  "type": "Feature",
  "properties": {
    "iso:country":"TR",
    "sg:address":"Sarig? Sok. No:18/a",
    "sg:city":"Kad\u0131k\u00f6y",
    "sg:orig_category":"Muhtarliklar",
    "sg:phone":"+90 216 350 1309",
    "sg:postcode":"34990",
    "sg:province":"Istanbul",
    "wof:name":"Caddebostan Mahallesi Muhtari:h?eyin Balik?",
    "wof:placetype":"venue"
},
  "geometry": {"coordinates":[28.8518600464,41.0114898682],"type":"Point"}
}