{
  "type": "Feature",
  "properties": {
    "addr:full":"3. San. Sit. 5. Sk. No:32 \u00c7orlu Aydin",
    "addr:housenumber":"3;5;32",
    "addr:street":"San. Sit.;Sk. No",
    "iso:country":"TR",
    "sg:address":"3. San. Sit. 5. Sk. No:32",
    "sg:city":"\u00c7orlu",
    "sg:classifiers":[
        {
            "category":"Retail",
            "subcategory":"Auto Repair",
            "type":"Services"
        }
    ],
    "sg:phone":"+90 256225397022",
    "sg:province":"Aydin",
    "sg:tags":[
        "maintenance"
    ],
    "wof:name":"Sua Aku Teks. San. Tic.",
    "wof:placetype":"venue"
},
  "geometry": {"coordinates":[27.8324394226,37.8409690857],"type":"Point"}
}