{
  "type": "Feature",
  "properties": {
    "addr:full":"19 Mayis Mah.ononu Cad.no:5/3 B.cekmece Zeytinburnu Istanbul 34020",
    "addr:housenumber":"19;5 / 3",
    "addr:postcode":"34020",
    "addr:street":"Mayis Mah.Ononu Cad.No;B.Cekmece Zeytinburnu",
    "iso:country":"TR",
    "sg:address":"19 Mayis Mah.ononu Cad.no:5/3 B.cekmece",
    "sg:city":"Zeytinburnu",
    "sg:classifiers":[
        {
            "category":"Manufacturing",
            "subcategory":"Leather Goods",
            "type":"Manufacturing & Wholesale Goods"
        }
    ],
    "sg:phone":"+90 212 882 1592",
    "sg:postcode":"34020",
    "sg:province":"Istanbul",
    "wof:name":"Aybotanik Export Import",
    "wof:placetype":"venue"
},
  "geometry": {"coordinates":[28.9026374817,40.9924430847],"type":"Point"}
}