{
  "type": "Feature",
  "properties": {
    "addr:full":"Uzun?rsi Cd. B?? Okurhan No:317/3 Tahtakale Rami Istanbul 34140",
    "addr:housenumber":"?;? ?;317 / 3",
    "addr:postcode":"34140",
    "addr:street":"Uzun;Rsi Cd. B;Okurhan No;Tahtakale Rami",
    "iso:country":"TR",
    "sg:address":"Uzun?rsi Cd. B?? Okurhan No:317/3 Tahtakale",
    "sg:city":"Rami",
    "sg:classifiers":[
        {
            "category":"Manufacturing",
            "subcategory":"Rubber & Plastics",
            "type":"Manufacturing & Wholesale Goods"
        }
    ],
    "sg:phone":"+90 212 513 7313",
    "sg:postcode":"34140",
    "sg:province":"Istanbul",
    "sg:tags":[
        "industry"
    ],
    "wof:name":"?zgen Plastik Kalip San. Ltd. Sti.",
    "wof:placetype":"venue"
},
  "geometry": {"coordinates":[28.8713321686,40.9776382446],"type":"Point"}
}