{
  "type": "Feature",
  "properties": {
    "addr:full":"Doktorlar Cad. Dispanser Yani Kocasinan Denizli 38010",
    "addr:postcode":"38010",
    "addr:street":"Doktorlar Cad. Dispanser Yani",
    "iso:country":"TR",
    "sg:address":"Doktorlar Cad. Dispanser Yani",
    "sg:city":"Kocasinan",
    "sg:classifiers":[
        {
            "category":"Wholesale",
            "subcategory":"Medical Equipment & Supplies",
            "type":"Manufacturing & Wholesale Goods"
        }
    ],
    "sg:phone":"+90 258 261 2443",
    "sg:postcode":"38010",
    "sg:province":"Denizli",
    "sg:tags":[
        "material"
    ],
    "wof:name":"Burak Ortopedi",
    "wof:placetype":"venue"
},
  "geometry": {"coordinates":[29.0788803101,37.7851867676],"type":"Point"}
}