{
  "type": "Feature",
  "properties": {
    "addr:full":"Karatas Yolu ?eri Balgat Adana 63510",
    "addr:housenumber":"?",
    "addr:postcode":"63510",
    "addr:street":"Karatas Yolu",
    "iso:country":"TR",
    "sg:address":"Karatas Yolu ?eri",
    "sg:city":"Balgat",
    "sg:classifiers":[
        {
            "category":"Farming",
            "subcategory":"Poultry Farm",
            "type":"Manufacturing & Wholesale Goods"
        }
    ],
    "sg:phone":"+90 322 321 0891",
    "sg:postcode":"63510",
    "sg:province":"Adana",
    "sg:tags":[
        "poultry-turkey-ostrich"
    ],
    "wof:name":"Tavas Tavukculuk A.s.",
    "wof:placetype":"venue"
},
  "geometry": {"coordinates":[35.3137359619,37.0007171631],"type":"Point"}
}