{
  "type": "Feature",
  "properties": {
    "iso:country":"TR",
    "sg:address":"Tuncbilek Karayolu 3.km.",
    "sg:city":"Tavsanli",
    "sg:classifiers":[
        {
            "category":"Manufacturing",
            "subcategory":"Food",
            "type":"Manufacturing & Wholesale Goods"
        }
    ],
    "sg:phone":"+90 274 614 1428",
    "sg:postcode":"43300",
    "sg:province":"K?tahya",
    "sg:tags":[
        "product",
        "floury",
        "macaroni"
    ],
    "wof:name":"Ozden Un San.tic. Ltd.sti.",
    "wof:placetype":"venue"
},
  "geometry": {"coordinates":[29.491569519,39.544380188],"type":"Point"}
}