{
  "type": "Feature",
  "properties": {
    "addr:full":"Ataturk Bul. Cad. 136/2 Aksaray Ikitelli/K\u00fc\u00e7\u00fck\u00e7ekmece Istanbul 34670",
    "addr:housenumber":"136 / 2",
    "addr:postcode":"34670",
    "addr:street":"Bul. Cad.",
    "iso:country":"TR",
    "sg:address":"Ataturk Bul. Cad. 136/2 Aksaray",
    "sg:city":"Ikitelli/K\u00fc\u00e7\u00fck\u00e7ekmece",
    "sg:classifiers":[
        {
            "category":"Manufacturing",
            "subcategory":"Metals",
            "type":"Manufacturing & Wholesale Goods"
        }
    ],
    "sg:phone":"+90 212 512 7724",
    "sg:postcode":"34670",
    "sg:province":"Istanbul",
    "sg:tags":[
        "iron-steel",
        "peoducts"
    ],
    "wof:name":"Holland Line",
    "wof:placetype":"venue"
},
  "geometry": {"coordinates":[28.8784427643,41.032535553],"type":"Point"}
}