{
  "type": "Feature",
  "properties": {
    "iso:country":"TR",
    "sg:address":"R?garli Sk. No:20/48",
    "sg:city":"B?y?k?ekmece",
    "sg:classifiers":[
        {
            "category":"Building & Trades",
            "subcategory":"Plumbing",
            "type":"Services"
        }
    ],
    "sg:phone":"+90 312 311 9534",
    "sg:postcode":"34900",
    "sg:province":"Ankara",
    "wof:name":"Ak Is Ltd. Sti.",
    "wof:placetype":"venue"
},
  "geometry": {"coordinates":[32.8560333252,39.9438743591],"type":"Point"}
}