{
  "type": "Feature",
  "properties": {
    "addr:full":"Molla Bayiri Sk.no.4 K.3 Kabatas Istanbul 24600",
    "addr:postcode":"24600",
    "iso:country":"TR",
    "sg:address":"Molla Bayiri Sk.no.4 K.3",
    "sg:city":"Kabatas",
    "sg:classifiers":[
        {
            "category":"Marine",
            "type":"Transportation"
        }
    ],
    "sg:phone":"+90 212 245 0500",
    "sg:postcode":"24600",
    "sg:province":"Istanbul",
    "sg:tags":[
        "shipowner"
    ],
    "wof:name":"Ayder Denizcilik A.s..",
    "wof:placetype":"venue"
},
  "geometry": {"coordinates":[28.990093,41.032986],"type":"Point"}
}