{
  "type": "Feature",
  "properties": {
    "addr:full":"1. Organize San. ?arman Sk. No: 11 ?mraniye Y.dudullu Konya",
    "addr:housenumber":"1;?;sk. no 11 ?",
    "addr:street":"Organize San.;Mraniye Y.Dudullu",
    "iso:country":"TR",
    "sg:address":"1. Organize San. ?arman Sk. No: 11",
    "sg:city":"?mraniye Y.dudullu",
    "sg:classifiers":[
        {
            "category":"Wholesale",
            "subcategory":"Machinery & Supplies",
            "type":"Manufacturing & Wholesale Goods"
        }
    ],
    "sg:phone":"+90 332 248 9191",
    "sg:province":"Konya",
    "sg:tags":[
        "press",
        "hydraulic"
    ],
    "wof:name":"Yilmaz Kardes Hidrolik Mak. San. Ve Damper San.",
    "wof:placetype":"venue"
},
  "geometry": {"coordinates":[33.0667152405,39.2111282349],"type":"Point"}
}