{
  "type": "Feature",
  "properties": {
    "addr:full":"Nuripasa Mah. 56.sok. No:53/1 Zeytinburnu Istanbul 41000",
    "addr:housenumber":"56.sok no 53 / 1",
    "addr:postcode":"41000",
    "addr:street":"Nuripasa Mah.",
    "iso:country":"TR",
    "sg:address":"Nuripasa Mah. 56.sok. No:53/1",
    "sg:city":"Zeytinburnu",
    "sg:classifiers":[
        {
            "category":"Shopping",
            "subcategory":"Clothing, Apparel, & Fashions",
            "type":"Retail Goods"
        }
    ],
    "sg:phone":"+90 212 664 6204",
    "sg:postcode":"41000",
    "sg:province":"Istanbul",
    "sg:tags":[
        "ready",
        "wear"
    ],
    "wof:name":"Bogazici Teksil",
    "wof:placetype":"venue"
},
  "geometry": {"coordinates":[28.9000377655,40.9904251099],"type":"Point"}
}