{
  "type": "Feature",
  "properties": {
    "addr:full":"San Sok. Satiroglu Is Hani Kat:5 Ulus Merter/g?g?en Ankara",
    "addr:housenumber":"kat 5;g ? g ?",
    "addr:street":"San Sok. Satiroglu Is;Ulus Merter /",
    "iso:country":"TR",
    "sg:address":"San Sok. Satiroglu Is Hani Kat:5 Ulus",
    "sg:city":"Merter/g?g?en",
    "sg:classifiers":[
        {
            "category":"Banks & Credit Unions",
            "subcategory":"Financial Services",
            "type":"Services"
        }
    ],
    "sg:phone":"+90 312 312 5526",
    "sg:province":"Ankara",
    "sg:tags":[
        "consultant"
    ],
    "wof:name":"Ozturk Muhasebe",
    "wof:placetype":"venue"
},
  "geometry": {"coordinates":[32.8560333252,39.9438743591],"type":"Point"}
}