{
  "type": "Feature",
  "properties": {
    "addr:full":"Kagithane Cd. Limon Sk. No: 5/1 Caglayan Kizilay Istanbul 23050",
    "addr:housenumber":"1",
    "addr:postcode":"23050",
    "addr:street":"Kagithane Cd. Limon Sk. No 5 /",
    "iso:country":"TR",
    "sg:address":"Kagithane Cd. Limon Sk. No: 5/1 Caglayan",
    "sg:city":"Kizilay",
    "sg:classifiers":[
        {
            "category":"Banks & Credit Unions",
            "subcategory":"Financial Services",
            "type":"Services"
        }
    ],
    "sg:phone":"+90 212 232 8577",
    "sg:postcode":"23050",
    "sg:province":"Istanbul",
    "sg:tags":[
        "consultant"
    ],
    "wof:name":"Analiz Muhasebe Danismanlik",
    "wof:placetype":"venue"
},
  "geometry": {"coordinates":[28.9777507782,41.0733337402],"type":"Point"}
}