{
  "type": "Feature",
  "properties": {
    "iso:country":"TR",
    "sg:address":"Recep Peker Cad. No:42/k Kiziltoprak/kadikoy",
    "sg:city":"Cagaloglu",
    "sg:classifiers":[
        {
            "category":"Home & Garden",
            "subcategory":"Kitchen Supply",
            "type":"Retail Goods"
        }
    ],
    "sg:phone":"+90 216 330 4066",
    "sg:postcode":"34440",
    "sg:province":"Istanbul",
    "sg:tags":[
        "fire",
        "extinguisher"
    ],
    "wof:name":"Abc Yangindan Koruma Ve Kurtarma Sis. San. Dis Tic.ltd.sti.",
    "wof:placetype":"venue"
},
  "geometry": {"coordinates":[29.045124054,40.9824943542],"type":"Point"}
}