{
  "type": "Feature",
  "properties": {
    "addr:full":"In??cd. 1. Sk. Hal Arkasi Z?eydehanim Ishani No:7 Edremit Balikesir 04500",
    "addr:housenumber":"1;z ?",
    "addr:postcode":"04500",
    "addr:street":"In ? ? Cd.;Sk. Hal Arkasi;Eydehanim Ishani No 7 Edremit Balikesir",
    "iso:country":"TR",
    "sg:address":"In??cd. 1. Sk. Hal Arkasi Z?eydehanim Ishani No:7",
    "sg:city":"Edremit",
    "sg:classifiers":[
        {
            "category":"Manufacturing",
            "subcategory":"Building Materials",
            "type":"Manufacturing & Wholesale Goods"
        }
    ],
    "sg:phone":"+90 266 241 8907",
    "sg:postcode":"04500",
    "sg:province":"Balikesir",
    "sg:tags":[
        "lifts-elevators"
    ],
    "wof:name":"Karesi Asans?r San.",
    "wof:placetype":"venue"
},
  "geometry": {"coordinates":[27.8833007812,39.6520996094],"type":"Point"}
}