{
  "type": "Feature",
  "properties": {
    "addr:full":"Libya Cd. 60/21 K. Esat B\u00fcy\u00fck\u00e7ekmece Ankara 34900",
    "addr:housenumber":"21 k.",
    "addr:postcode":"34900",
    "addr:street":"Cd. 60 /",
    "iso:country":"TR",
    "sg:address":"Libya Cd. 60/21 K. Esat",
    "sg:city":"B\u00fcy\u00fck\u00e7ekmece",
    "sg:orig_category":"Aluminium Carpentary",
    "sg:phone":"+90 312417510506",
    "sg:postcode":"34900",
    "sg:province":"Ankara",
    "wof:name":"Aspet Asfalt Yapi Malz. San. A.s.",
    "wof:placetype":"venue"
},
  "geometry": {"coordinates":[32.8650894165,39.949962616],"type":"Point"}
}