{
  "type": "Feature",
  "properties": {
    "addr:full":"Ulu Mah.cakmak Sok. No: 11/16 Maltepe Bursa 01000",
    "addr:housenumber":"no 11 / 16",
    "addr:postcode":"01000",
    "addr:street":"Mah.Cakmak Sok.;Bursa",
    "iso:country":"TR",
    "sg:address":"Ulu Mah.cakmak Sok. No: 11/16",
    "sg:city":"Maltepe",
    "sg:classifiers":[
        {
            "category":"Professional",
            "subcategory":"Employment Agencies",
            "type":"Services"
        }
    ],
    "sg:phone":"+90 224 273 2336",
    "sg:postcode":"01000",
    "sg:province":"Bursa",
    "sg:tags":[
        "machine"
    ],
    "wof:name":"Bursa Fotokopi Sist.ltd.sti.",
    "wof:placetype":"venue"
},
  "geometry": {"coordinates":[29.063211441,40.1949386597],"type":"Point"}
}