{
  "type": "Feature",
  "properties": {
    "addr:full":"Litros Hastane Yolu Baltas San. Sitesi No:10/1 Bayrampasa G?g?en Istanbul",
    "addr:housenumber":"no 10 / 1;? g ?",
    "addr:street":"Hastane Yolu Baltas San. Sitesi;Bayrampasa G",
    "iso:country":"TR",
    "sg:address":"Litros Hastane Yolu Baltas San. Sitesi No:10/1 Bayrampasa",
    "sg:city":"G?g?en",
    "sg:classifiers":[
        {
            "category":"Manufacturing",
            "subcategory":"Rubber & Plastics",
            "type":"Manufacturing & Wholesale Goods"
        }
    ],
    "sg:phone":"+90 2125762658501",
    "sg:province":"Istanbul",
    "sg:tags":[
        "industry"
    ],
    "wof:name":"Polimer Ambalaj Sanayi Ve Ticaret",
    "wof:placetype":"venue"
},
  "geometry": {"coordinates":[28.9011554718,41.0516204834],"type":"Point"}
}