{
  "type": "Feature",
  "properties": {
    "iso:country":"TR",
    "sg:address":"Kars",
    "sg:city":"Karabaglar",
    "sg:classifiers":[
        {
            "category":"Government",
            "subcategory":"Office",
            "type":"Public Place"
        }
    ],
    "sg:phone":"+90 474 212 6486",
    "sg:postcode":"44210",
    "sg:province":"Kars",
    "sg:tags":[
        "army"
    ],
    "wof:name":"Kars (digor, Akyaka, Susuz) Askerlik Subesi",
    "wof:placetype":"venue"
},
  "geometry": {"coordinates":[43.1012611389,40.6059799194],"type":"Point"}
}