{
  "type": "Feature",
  "properties": {
    "iso:country":"TR",
    "sg:address":"Cumh. Bulv. Necipoglu Ish. 60/304",
    "sg:city":"Alsancak",
    "sg:classifiers":[
        {
            "category":"Manufacturing",
            "subcategory":"Chemicals & Compounds",
            "type":"Manufacturing & Wholesale Goods"
        }
    ],
    "sg:phone":"+90 232 425 2523",
    "sg:postcode":"01365",
    "sg:province":"Izmir",
    "sg:tags":[
        "pharmaceutical"
    ],
    "wof:name":"Adeka Ilac San.",
    "wof:placetype":"venue"
},
  "geometry": {"coordinates":[27.1296863556,38.4186973572],"type":"Point"}
}