{
  "type": "Feature",
  "properties": {
    "addr:full":"Anafartalar Cd. Arap Hani No:264 D:14 G?elyurt Ortak? Izmir 80840",
    "addr:housenumber":"d 14 g ?;?",
    "addr:postcode":"80840",
    "addr:street":"Anafartalar Cd. Arap;Elyurt Ortak",
    "iso:country":"TR",
    "sg:address":"Anafartalar Cd. Arap Hani No:264 D:14 G?elyurt",
    "sg:city":"Ortak?",
    "sg:classifiers":[
        {
            "category":"Organizations",
            "subcategory":"Professional Association",
            "type":"Services"
        }
    ],
    "sg:phone":"+90 232 484 3863",
    "sg:postcode":"80840",
    "sg:province":"Izmir",
    "wof:name":"Tuhafiye, Manifatura Benz. Odasi",
    "wof:placetype":"venue"
},
  "geometry": {"coordinates":[27.1296863556,38.4186973572],"type":"Point"}
}