{
  "type": "Feature",
  "properties": {
    "addr:full":"Uzun?yir Cd. Yapi Hizmet. Ismerk. D 1 Blok No:31 D:19 Kad\u0131k\u00f6y Istanbul 34990",
    "addr:housenumber":"?;ismerk. d 1 blok no 31 d 19",
    "addr:postcode":"34990",
    "addr:street":"Uzun;Yir Cd. Yapi Hizmet.;Istanbul",
    "iso:country":"TR",
    "sg:address":"Uzun?yir Cd. Yapi Hizmet. Ismerk. D 1 Blok No:31 D:19",
    "sg:city":"Kad\u0131k\u00f6y",
    "sg:classifiers":[
        {
            "category":"Professional",
            "subcategory":"Engineering",
            "type":"Services"
        }
    ],
    "sg:phone":"+90 216 326 0486",
    "sg:postcode":"34990",
    "sg:province":"Istanbul",
    "sg:tags":[
        "architect"
    ],
    "wof:name":"Miro Mimarlik Insaat San. Tic. Ltd. Sti.",
    "wof:placetype":"venue"
},
  "geometry": {"coordinates":[28.9110984802,41.0489578247],"type":"Point"}
}