{
  "type": "Feature",
  "properties": {
    "iso:country":"TR",
    "sg:address":"Halkali Cad.no: 46 Besyol Mah. Sefakoy",
    "sg:city":"B\u00fcy\u00fck\u00e7ekmece",
    "sg:classifiers":[
        {
            "category":"Home & Garden",
            "subcategory":"Kitchen Supply",
            "type":"Retail Goods"
        }
    ],
    "sg:phone":"+90 212 592 0107",
    "sg:postcode":"34905",
    "sg:province":"Istanbul",
    "sg:tags":[
        "wardrobe"
    ],
    "wof:name":"Aryildiz Madeni Esya San.ve Tic.a.s.",
    "wof:placetype":"venue"
},
  "geometry": {"coordinates":[28.7974090576,40.9874725342],"type":"Point"}
}