{
  "type": "Feature",
  "properties": {
    "addr:full":"Halaskargazi Cad. Safak Sk. Aydin Han No:50 K:3 D:22/25 Osmanbey Istanbul 63000",
    "addr:housenumber":"50 k 3 d 22 / 25",
    "addr:postcode":"63000",
    "addr:street":"Halaskargazi Cad. Safak Sk. Aydin Han No;Istanbul",
    "iso:country":"TR",
    "sg:address":"Halaskargazi Cad. Safak Sk. Aydin Han No:50 K:3 D:22/25",
    "sg:city":"Osmanbey",
    "sg:classifiers":[
        {
            "category":"Shopping",
            "subcategory":"Clothing, Apparel, & Fashions",
            "type":"Retail Goods"
        }
    ],
    "sg:phone":"+90 212 230 8310",
    "sg:postcode":"63000",
    "sg:province":"Istanbul",
    "sg:tags":[
        "men",
        "wear"
    ],
    "wof:name":"Ulusoy Teks. Tic. Sti.",
    "wof:placetype":"venue"
},
  "geometry": {"coordinates":[28.9759254456,41.0123786926],"type":"Point"}
}