{
  "type": "Feature",
  "properties": {
    "iso:country":"TR",
    "sg:address":"Pendik Merkez - Pendik",
    "sg:city":"Ikitelli",
    "sg:classifiers":[
        {
            "category":"Banks & Credit Unions",
            "subcategory":"Investment Brokerage",
            "type":"Services"
        }
    ],
    "sg:phone":"+90 216 354 4593",
    "sg:postcode":"34306",
    "sg:province":"Istanbul",
    "sg:tags":[
        "aid",
        "material",
        "first"
    ],
    "wof:name":"Pendik Devlet Hastanesi",
    "wof:placetype":"venue"
},
  "geometry": {"coordinates":[29.2431602478,40.88804245],"type":"Point"}
}