{
  "type": "Feature",
  "properties": {
    "iso:country":"TR",
    "sg:address":"Isiklar C. Yol Sk. Avcilar",
    "sg:city":"?atalca",
    "sg:classifiers":[
        {
            "category":"Manufacturing",
            "subcategory":"Leather Goods",
            "type":"Manufacturing & Wholesale Goods"
        }
    ],
    "sg:phone":"+90 212 690 1900",
    "sg:postcode":"34870",
    "sg:province":"Istanbul",
    "sg:tags":[
        "chemical"
    ],
    "wof:name":"Oynurden Kimya San.a.s.",
    "wof:placetype":"venue"
},
  "geometry": {"coordinates":[29.1198043823,40.9406661987],"type":"Point"}
}