{
  "type": "Feature",
  "properties": {
    "addr:full":"Istiklal Cd Cebirhan Kocaeli",
    "addr:street":"Istiklal",
    "iso:country":"TR",
    "sg:address":"Istiklal Cd",
    "sg:city":"Cebirhan",
    "sg:classifiers":[
        {
            "category":"Manufacturing",
            "subcategory":"Food",
            "type":"Manufacturing & Wholesale Goods"
        }
    ],
    "sg:phone":"+90 262 322 2256",
    "sg:province":"Kocaeli",
    "sg:tags":[
        "wholesaler"
    ],
    "wof:name":"Martas Marmara Gida San. As.",
    "wof:placetype":"venue"
},
  "geometry": {"coordinates":[29.9040737152,40.7083435059],"type":"Point"}
}