{
  "type": "Feature",
  "properties": {
    "addr:full":"Hurriyet Mah. Dr. Camil Bengu Cad. No:3/a Balgat Istanbul 63510",
    "addr:postcode":"63510",
    "addr:street":"Hurriyet Mah. Dr. Camil Bengu Cad. No 3 / A Balgat",
    "iso:country":"TR",
    "sg:address":"Hurriyet Mah. Dr. Camil Bengu Cad. No:3/a",
    "sg:city":"Balgat",
    "sg:classifiers":[
        {
            "category":"Home & Garden",
            "subcategory":"Building Materials",
            "type":"Retail Goods"
        }
    ],
    "sg:phone":"+90 212 225 3187",
    "sg:postcode":"63510",
    "sg:province":"Istanbul",
    "sg:tags":[
        "window",
        "door"
    ],
    "wof:name":"Yetisler Aluminyum San. Ve Tic. Ltd.sti.",
    "wof:placetype":"venue"
},
  "geometry": {"coordinates":[28.9861831665,41.0408554077],"type":"Point"}
}