{
  "type": "Feature",
  "properties": {
    "iso:country":"TR",
    "sg:address":"Mumhane Cd.hoca Tahsin Sk.polat Ish.no21/16",
    "sg:city":"Karak\u00f6y",
    "sg:classifiers":[
        {
            "category":"Marine",
            "type":"Transportation"
        }
    ],
    "sg:phone":"+90 212 243 6331",
    "sg:province":"Istanbul",
    "sg:tags":[
        "stevedores-tally"
    ],
    "wof:name":"Gen? Denizcilik Ltd.sti.",
    "wof:placetype":"venue"
},
  "geometry": {"coordinates":[28.975925,41.012379],"type":"Point"}
}