{
  "type": "Feature",
  "properties": {
    "addr:full":"Ataturk Cad. No: 7/1 S.cedid Zeytinburnu Istanbul 34780",
    "addr:housenumber":"1",
    "addr:postcode":"34780",
    "addr:street":"Ataturk Cad. No 7 /",
    "iso:country":"TR",
    "sg:address":"Ataturk Cad. No: 7/1 S.cedid",
    "sg:city":"Zeytinburnu",
    "sg:classifiers":[
        {
            "category":"Manufacturing",
            "subcategory":"Metals",
            "type":"Manufacturing & Wholesale Goods"
        }
    ],
    "sg:phone":"+90 216 360 5337",
    "sg:postcode":"34780",
    "sg:province":"Istanbul",
    "sg:tags":[
        "iron-steel",
        "peoducts"
    ],
    "wof:name":"C.t.metal Ticaret",
    "wof:placetype":"venue"
},
  "geometry": {"coordinates":[29.9358177185,40.7662734985],"type":"Point"}
}