{
  "type": "Feature",
  "properties": {
    "addr:full":"Mis Sk. 6/9 Beyoglu Istanbul 46810",
    "addr:housenumber":"9",
    "addr:postcode":"46810",
    "addr:street":"Sk. 6 /",
    "iso:country":"TR",
    "sg:address":"Mis Sk. 6/9",
    "sg:city":"Beyoglu",
    "sg:classifiers":[
        {
            "category":"Travel",
            "subcategory":"Travel Agent",
            "type":"Entertainment"
        }
    ],
    "sg:phone":"+90 212251095758",
    "sg:postcode":"46810",
    "sg:province":"Istanbul",
    "sg:tags":[
        "agency",
        "tourism"
    ],
    "wof:name":"Alternatif Gezi Merkezi",
    "wof:placetype":"venue"
},
  "geometry": {"coordinates":[28.9861831665,41.0408554077],"type":"Point"}
}