{
  "type": "Feature",
  "properties": {
    "addr:full":"Hasanpasa Uzun?yir Cad. No:31 B Blok D:19 Kadik? Kizilay Istanbul 06410",
    "addr:housenumber":"?;31 b;19;?",
    "addr:postcode":"06410",
    "addr:street":"Uzun;Yir Cad. No;Blok D;Kizilay Istanbul",
    "iso:country":"TR",
    "sg:address":"Hasanpasa Uzun?yir Cad. No:31 B Blok D:19 Kadik?",
    "sg:city":"Kizilay",
    "sg:classifiers":[
        {
            "category":"Wholesale",
            "subcategory":"Medical Equipment & Supplies",
            "type":"Manufacturing & Wholesale Goods"
        }
    ],
    "sg:phone":"+90 216 326 9182",
    "sg:postcode":"06410",
    "sg:province":"Istanbul",
    "wof:name":"Emek Egitim Arc. Tic.",
    "wof:placetype":"venue"
},
  "geometry": {"coordinates":[28.9861831665,41.0408554077],"type":"Point"}
}