{
  "type": "Feature",
  "properties": {
    "addr:full":"1716 Sk.no:1/1 No:3/304 Karsiyaka \u00dcmraniye Izmir 81260",
    "addr:housenumber":"1716;1 / 1 no 3 / 304",
    "addr:postcode":"81260",
    "addr:street":"Sk.No;Karsiyaka",
    "iso:country":"TR",
    "sg:address":"1716 Sk.no:1/1 No:3/304 Karsiyaka",
    "sg:city":"\u00dcmraniye",
    "sg:classifiers":[
        {
            "category":"Manufacturing",
            "subcategory":"Tools & Machinery",
            "type":"Manufacturing & Wholesale Goods"
        }
    ],
    "sg:phone":"+90 232 331 5885",
    "sg:postcode":"81260",
    "sg:province":"Izmir",
    "sg:tags":[
        "machine",
        "industry"
    ],
    "wof:name":"Teknotrans Makina San.tic.ltd.sti.",
    "wof:placetype":"venue"
},
  "geometry": {"coordinates":[27.1127605438,38.4512748718],"type":"Point"}
}