{
  "type": "Feature",
  "properties": {
    "iso:country":"TR",
    "sg:address":"M. Kemalpasa Cd. No:52",
    "sg:city":"Bah\u00e7elievler",
    "sg:classifiers":[
        {
            "category":"Building & Trades",
            "subcategory":"Electrical",
            "type":"Services"
        }
    ],
    "sg:phone":"+90 212 505 0227",
    "sg:postcode":"34180",
    "sg:province":"Istanbul",
    "sg:tags":[
        "equipment",
        "lighting"
    ],
    "wof:name":"G?rtas Avize Cam Sarayi San. Tic. Ltd. Sti.",
    "wof:placetype":"venue"
},
  "geometry": {"coordinates":[29.269985199,40.8764533997],"type":"Point"}
}