{
  "type": "Feature",
  "properties": {
    "addr:full":"Galata Kulesi Kat:1 Kuledibi \u00dcsk\u00fcdar Istanbul 34672",
    "addr:housenumber":"kat 1",
    "addr:postcode":"34672",
    "iso:country":"TR",
    "sg:address":"Galata Kulesi Kat:1 Kuledibi",
    "sg:city":"\u00dcsk\u00fcdar",
    "sg:classifiers":[
        {
            "category":"Shopping",
            "subcategory":"Gifts & Souvenirs",
            "type":"Retail Goods"
        }
    ],
    "sg:phone":"+90 212 517 3530",
    "sg:postcode":"34672",
    "sg:province":"Istanbul",
    "wof:name":"Galata Hediyelik Esya Turizm Ltd.sti.",
    "wof:placetype":"venue"
},
  "geometry": {"coordinates":[29.0154418945,41.0218315125],"type":"Point"}
}