{
  "type": "Feature",
  "properties": {
    "iso:country":"TR",
    "sg:address":"Nuruosmaniye Cad. No:80",
    "sg:city":"Cagaloglu",
    "sg:orig_category":"Carpet-kilim-blanket",
    "sg:phone":"+90 212 267 4848",
    "sg:province":"Istanbul",
    "wof:name":"Aykut Halicilik San. Ve Tic. A.s.",
    "wof:placetype":"venue"
},
  "geometry": {"coordinates":[28.9727706909,41.0719985962],"type":"Point"}
}