{
  "type": "Feature",
  "properties": {
    "iso:country":"TR",
    "sg:address":"K. Karabekir Cd. Cetinkaya-arat Ish. No:93 D:73 Iskitler",
    "sg:city":"Besiktas",
    "sg:classifiers":[
        {
            "category":"Organizations",
            "subcategory":"Membership Organization",
            "type":"Services"
        }
    ],
    "sg:phone":"+90 312 341 1262",
    "sg:postcode":"80630",
    "sg:province":"Ankara",
    "wof:name":"Ankara Ins. Muteahhit. Dernegi",
    "wof:placetype":"venue"
},
  "geometry": {"coordinates":[32.8604812622,39.9429283142],"type":"Point"}
}