{
  "type": "Feature",
  "properties": {
    "addr:full":"Organize Sanayii Bolgesi 7. Cad. Kad\u0131k\u00f6y Eskisehir",
    "addr:housenumber":"7",
    "addr:street":"Bolgesi;Cad. Kadikoey Eskisehir",
    "iso:country":"TR",
    "sg:address":"Organize Sanayii Bolgesi 7. Cad.",
    "sg:city":"Kad\u0131k\u00f6y",
    "sg:classifiers":[
        {
            "category":"Shopping",
            "subcategory":"Computers & Home Electronics",
            "type":"Retail Goods"
        }
    ],
    "sg:phone":"+90 222 236 0274",
    "sg:province":"Eskisehir",
    "sg:tags":[
        "connector",
        "cable"
    ],
    "wof:name":"Baycan Elektrik A.s.",
    "wof:placetype":"venue"
},
  "geometry": {"coordinates":[31.0192203522,39.6195106506],"type":"Point"}
}