{
  "type": "Feature",
  "properties": {
    "addr:full":"Atat?k Cad. Ekmekciler Apt. Kat 5 No: 10 Seyhan Seyrantepe Konya 46700",
    "addr:housenumber":"5 no 10",
    "addr:postcode":"46700",
    "addr:street":"K Cad. Ekmekciler Apt. Kat;Seyhan",
    "iso:country":"TR",
    "sg:address":"Atat?k Cad. Ekmekciler Apt. Kat 5 No: 10 Seyhan",
    "sg:city":"Seyrantepe",
    "sg:orig_category":"Food Machinies",
    "sg:phone":"+90 332 459 5050",
    "sg:postcode":"46700",
    "sg:province":"Konya",
    "wof:name":"Ekmekciler Pamuk A.s.",
    "wof:placetype":"venue"
},
  "geometry": {"coordinates":[32.4990272522,37.8715362549],"type":"Point"}
}