{
  "type": "Feature",
  "properties": {
    "addr:full":"Tekel C. Yaliboyu Sk. Yildiz Apt. No: 8/4 Rahmanlar- Kartal Istanbul 46000",
    "addr:housenumber":"apt.;4",
    "addr:postcode":"46000",
    "addr:street":"Yaliboyu Sk. Yildiz;No 8 /",
    "iso:country":"TR",
    "sg:address":"Tekel C. Yaliboyu Sk. Yildiz Apt. No: 8/4 Rahmanlar-",
    "sg:city":"Kartal",
    "sg:classifiers":[
        {
            "category":"Manufacturing",
            "subcategory":"Building Materials",
            "type":"Manufacturing & Wholesale Goods"
        }
    ],
    "sg:phone":"+90 216 387 3918",
    "sg:postcode":"46000",
    "sg:province":"Istanbul",
    "sg:tags":[
        "floor-wall",
        "covering"
    ],
    "wof:name":"Yapi End. San A.s.",
    "wof:placetype":"venue"
},
  "geometry": {"coordinates":[29.1420707703,40.9079322815],"type":"Point"}
}