{
  "type": "Feature",
  "properties": {
    "addr:full":"Kartaltepe Mh. 50. Yil Cd. No:91 Bayrampasa Istanbul 36100",
    "addr:housenumber":"50 yil cd. no 91",
    "addr:postcode":"36100",
    "addr:street":"Mh.;Istanbul",
    "iso:country":"TR",
    "sg:address":"Kartaltepe Mh. 50. Yil Cd. No:91",
    "sg:city":"Bayrampasa",
    "sg:classifiers":[
        {
            "category":"Home & Garden",
            "subcategory":"Hardware",
            "type":"Retail Goods"
        }
    ],
    "sg:phone":"+90 212 616 9571",
    "sg:postcode":"36100",
    "sg:province":"Istanbul",
    "sg:tags":[
        "store"
    ],
    "wof:name":"Duy-mer Bronz San. Tic. Ltd. Sti.",
    "wof:placetype":"venue"
},
  "geometry": {"coordinates":[28.9861831665,41.0408554077],"type":"Point"}
}