{
  "type": "Feature",
  "properties": {
    "iso:country":"TR",
    "sg:address":"Fatih Mah. Oguz Cad. 19/a",
    "sg:city":"Kocasinan",
    "sg:classifiers":[
        {
            "category":"Shopping",
            "subcategory":"Clothing, Apparel, & Fashions",
            "type":"Retail Goods"
        }
    ],
    "sg:phone":"+90 352 231 7820",
    "sg:postcode":"38100",
    "sg:province":"Kayseri",
    "sg:tags":[
        "underwear"
    ],
    "wof:name":"Misten Konfeksiyon San.tic. Ltd.sti.",
    "wof:placetype":"venue"
},
  "geometry": {"coordinates":[35.485191,38.728992],"type":"Point"}
}