{
  "type": "Feature",
  "properties": {
    "iso:country":"TR",
    "sg:address":"Osman Kavuncu Sk. No.11",
    "sg:city":"Ceyhan",
    "sg:classifiers":[
        {
            "category":"Manufacturing",
            "subcategory":"Food",
            "type":"Manufacturing & Wholesale Goods"
        }
    ],
    "sg:phone":"+90 352 336 4384",
    "sg:postcode":"01920",
    "sg:province":"Kayseri",
    "sg:tags":[
        "product",
        "floury",
        "macaroni"
    ],
    "wof:name":"Sariyildiz Un Fab.",
    "wof:placetype":"venue"
},
  "geometry": {"coordinates":[35.4587402344,38.7257614136],"type":"Point"}
}