{
  "type": "Feature",
  "properties": {
    "addr:full":"Gazimuhtarpasa Bulvari Kalyon Is Merkezi Kat:4 No:25 Sehitkamil Ikitelli/K\u00fc\u00e7\u00fck\u00e7ekmece Gaziantep 34670",
    "addr:housenumber":"kat 4 no 25",
    "addr:postcode":"34670",
    "addr:street":"Gazimuhtarpasa Bulvari Kalyon",
    "iso:country":"TR",
    "sg:address":"Gazimuhtarpasa Bulvari Kalyon Is Merkezi Kat:4 No:25 Sehitkamil",
    "sg:city":"Ikitelli/K\u00fc\u00e7\u00fck\u00e7ekmece",
    "sg:classifiers":[
        {
            "category":"Manufacturing",
            "subcategory":"Chemicals & Compounds",
            "type":"Manufacturing & Wholesale Goods"
        }
    ],
    "sg:phone":"+90 342 215 0250",
    "sg:postcode":"34670",
    "sg:province":"Gaziantep",
    "sg:tags":[
        "industry"
    ],
    "wof:name":"Sns Boya Kimya San.tic.a.s.",
    "wof:placetype":"venue"
},
  "geometry": {"coordinates":[37.4416732788,36.9459457397],"type":"Point"}
}