{
  "type": "Feature",
  "properties": {
    "iso:country":"TR",
    "sg:address":"1470. Sk. No:5/507 Alsancak",
    "sg:city":"Sel?klu",
    "sg:classifiers":[
        {
            "category":"Wholesale",
            "subcategory":"Medical Equipment & Supplies",
            "type":"Manufacturing & Wholesale Goods"
        }
    ],
    "sg:phone":"+90 232 463 2802",
    "sg:postcode":"42060",
    "sg:province":"Izmir",
    "wof:name":"Yeni Alsancak San.",
    "wof:placetype":"venue"
},
  "geometry": {"coordinates":[27.1423015594,38.4251480103],"type":"Point"}
}