{
  "type": "Feature",
  "properties": {
    "addr:full":"Millet Cad. Aydin Apt. No:131/10 Capa Mersin Istanbul 52750",
    "addr:housenumber":"131 / 10",
    "addr:postcode":"52750",
    "addr:street":"Millet Cad. Aydin Apt. No",
    "iso:country":"TR",
    "sg:address":"Millet Cad. Aydin Apt. No:131/10 Capa",
    "sg:city":"Mersin",
    "sg:classifiers":[
        {
            "category":"Wholesale",
            "subcategory":"Medical Equipment & Supplies",
            "type":"Manufacturing & Wholesale Goods"
        }
    ],
    "sg:phone":"+90 212 587 3686",
    "sg:postcode":"52750",
    "sg:province":"Istanbul",
    "wof:name":"Endo-mek Dis Tic. Ltd. Sti.",
    "wof:placetype":"venue"
},
  "geometry": {"coordinates":[28.9861831665,41.0408554077],"type":"Point"}
}