{
  "type": "Feature",
  "properties": {
    "iso:country":"TR",
    "sg:address":"Seyrantepe Cihat Sk. No. 3 4.levent",
    "sg:city":"Atasehir",
    "sg:classifiers":[
        {
            "category":"Personal",
            "subcategory":"Sauna",
            "type":"Services"
        }
    ],
    "sg:phone":"+90 212 279 7867",
    "sg:postcode":"34758",
    "sg:province":"Istanbul",
    "sg:tags":[
        "pool"
    ],
    "wof:name":"Olimpik Y?zme Havuz End. Tes. Taah. San. Tic. Ltd. Sti.",
    "wof:placetype":"venue"
},
  "geometry": {"coordinates":[29.309153,40.859035],"type":"Point"}
}