{
  "type": "Feature",
  "properties": {
    "iso:country":"TR",
    "sg:address":"1.murat Cad. ?nl??el Psj. 45/b",
    "sg:city":"Maltepe",
    "sg:classifiers":[
        {
            "category":"Wholesale",
            "subcategory":"Plants",
            "type":"Manufacturing & Wholesale Goods"
        }
    ],
    "sg:phone":"+90 266 239 6748",
    "sg:postcode":"01000",
    "sg:province":"Bursa",
    "sg:tags":[
        "natural",
        "spice"
    ],
    "wof:name":"Ilayda Gida Turizm Tekstil Ltd.sti.",
    "wof:placetype":"venue"
},
  "geometry": {"coordinates":[29.058004,40.194756],"type":"Point"}
}