{
  "type": "Feature",
  "properties": {
    "addr:full":"?arsamba Pazari Ilkbahar Cd. I?i Sk. No:10/b Avcilar Bursa 01350",
    "addr:housenumber":"?;?;10 / b",
    "addr:postcode":"01350",
    "addr:street":"Arsamba;Ilkbahar Cd. I;I Sk. No;Bursa",
    "iso:country":"TR",
    "sg:address":"?arsamba Pazari Ilkbahar Cd. I?i Sk. No:10/b",
    "sg:city":"Avcilar",
    "sg:classifiers":[
        {
            "category":"Utilities",
            "subcategory":"Natural Gas",
            "type":"Services"
        }
    ],
    "sg:phone":"+90 224 254 0833",
    "sg:postcode":"01350",
    "sg:province":"Bursa",
    "sg:tags":[
        "tank-heating-natural"
    ],
    "wof:name":"Oltes Ltd. Sti.",
    "wof:placetype":"venue"
},
  "geometry": {"coordinates":[29.0586109161,40.1844291687],"type":"Point"}
}