{
  "type": "Feature",
  "properties": {
    "addr:full":"Trabzon Karabaglar Trabzon 44210",
    "addr:postcode":"44210",
    "addr:street":"Trabzon",
    "iso:country":"TR",
    "sg:address":"Trabzon",
    "sg:city":"Karabaglar",
    "sg:classifiers":[
        {
            "category":"Government",
            "subcategory":"Office",
            "type":"Public Place"
        }
    ],
    "sg:phone":"+90 462 771 5112",
    "sg:postcode":"44210",
    "sg:province":"Trabzon",
    "sg:tags":[
        "army"
    ],
    "wof:name":"Of (hayrat) Askerlik Subesi",
    "wof:placetype":"venue"
},
  "geometry": {"coordinates":[39.7165603638,41.0012931824],"type":"Point"}
}