{
  "type": "Feature",
  "properties": {
    "addr:full":"Istiklal Cd. No: 349 Beyoglu Y. Bosna Istanbul",
    "addr:housenumber":"no",
    "addr:street":"Istiklal Cd.;Beyoglu Y. Bosna",
    "iso:country":"TR",
    "sg:address":"Istiklal Cd. No: 349 Beyoglu",
    "sg:city":"Y. Bosna",
    "sg:orig_category":"General Industrial Products",
    "sg:phone":"+90 212 252 4900",
    "sg:province":"Istanbul",
    "wof:name":"Beko Tic. A.s.",
    "wof:placetype":"venue"
},
  "geometry": {"coordinates":[28.9785957336,41.0340538025],"type":"Point"}
}