{
  "type": "Feature",
  "properties": {
    "addr:full":"Denizli Asfalti Akarca Mevkii 1.kume No: 7 Alasehir Manisa 45600",
    "addr:postcode":"45600",
    "addr:street":"Akarca Mevkii 1.Kume No 7 Alasehir",
    "iso:country":"TR",
    "sg:address":"Denizli Asfalti Akarca Mevkii 1.kume No: 7",
    "sg:city":"Alasehir",
    "sg:classifiers":[
        {
            "category":"Food & Beverages",
            "subcategory":"Dairy",
            "type":"Retail Goods"
        }
    ],
    "sg:phone":"+90 236 653 1515",
    "sg:postcode":"45600",
    "sg:province":"Manisa",
    "sg:tags":[
        "pruducts",
        "milk"
    ],
    "wof:name":"Koylum Sut Urunleri San.tic.a.s.",
    "wof:placetype":"venue"
},
  "geometry": {"coordinates":[27.4297008514,38.6222000122],"type":"Point"}
}