{
  "type": "Feature",
  "properties": {
    "iso:country":"TR",
    "sg:address":"Ankara Cad. Caglayan Is Merkezi Kat: 6 No:40 Izmit",
    "sg:city":"Y. Bosna",
    "sg:orig_category":"General Industrial Products",
    "sg:phone":"+90 262 324 0933",
    "sg:province":"Kocaeli",
    "wof:name":"Atakim Kimya Makina Ve Petrol End.ltd.sti.",
    "wof:placetype":"venue"
},
  "geometry": {"coordinates":[29.9483566284,40.7759857178],"type":"Point"}
}