{
  "type": "Feature",
  "properties": {
    "iso:country":"TR",
    "sg:address":"Valikonagi Cad. Sirin Apt. No: 36/4",
    "sg:city":"Nisantasi",
    "sg:classifiers":[
        {
            "category":"Travel",
            "subcategory":"Travel Agent",
            "type":"Entertainment"
        }
    ],
    "sg:phone":"+90 22547912250300",
    "sg:postcode":"25370",
    "sg:province":"Istanbul",
    "sg:tags":[
        "agency",
        "tourism"
    ],
    "wof:name":"Delos Turizm",
    "wof:placetype":"venue"
},
  "geometry": {"coordinates":[28.9861831665,41.0408554077],"type":"Point"}
}