{
  "type": "Feature",
  "properties": {
    "addr:full":"Demirciler Sit. 7. Cd. No: 75 Z.burnu Istanbul",
    "addr:housenumber":"7 cd. no 75",
    "addr:street":"Sit.",
    "iso:country":"TR",
    "sg:address":"Demirciler Sit. 7. Cd. No: 75",
    "sg:city":"Z.burnu",
    "sg:classifiers":[
        {
            "category":"Manufacturing",
            "subcategory":"Textiles",
            "type":"Manufacturing & Wholesale Goods"
        }
    ],
    "sg:phone":"+90 212510558081",
    "sg:province":"Istanbul",
    "sg:tags":[
        "sizing",
        "dye"
    ],
    "wof:name":"Henatex Boya Ve Apre San. Tic. A.s.",
    "wof:placetype":"venue"
},
  "geometry": {"coordinates":[28.8978595734,41.0060081482],"type":"Point"}
}