{
  "type": "Feature",
  "properties": {
    "addr:full":"Mahmutbey Yolu No:72/1 Sirinevler Istanbul 15040",
    "addr:housenumber":"no 72 / 1",
    "addr:postcode":"15040",
    "addr:street":"Mahmutbey Yolu",
    "iso:country":"TR",
    "sg:address":"Mahmutbey Yolu No:72/1",
    "sg:city":"Sirinevler",
    "sg:classifiers":[
        {
            "category":"Home & Garden",
            "subcategory":"Household Appliances",
            "type":"Retail Goods"
        }
    ],
    "sg:phone":"+90 212 652 3325",
    "sg:postcode":"15040",
    "sg:province":"Istanbul",
    "sg:tags":[
        "conditioner",
        "air"
    ],
    "wof:name":"Yalin M?h. Dogalgaz Isi Sistem. San. Tic.",
    "wof:placetype":"venue"
},
  "geometry": {"coordinates":[28.8545074463,41.0693359375],"type":"Point"}
}