{
  "type": "Feature",
  "properties": {
    "addr:full":"San. Sit. Kars. Bornova Edirne 3500",
    "addr:postcode":"3500",
    "addr:street":"Edirne",
    "iso:country":"TR",
    "sg:address":"San. Sit. Kars.",
    "sg:city":"Bornova",
    "sg:classifiers":[
        {
            "category":"Wholesale",
            "subcategory":"Medical Equipment & Supplies",
            "type":"Manufacturing & Wholesale Goods"
        }
    ],
    "sg:phone":"+90 284 212 0027",
    "sg:postcode":"3500",
    "sg:province":"Edirne",
    "wof:name":"Labor Kimya Ofisi Ltd. Sti.",
    "wof:placetype":"venue"
},
  "geometry": {"coordinates":[26.554069519,41.6770401001],"type":"Point"}
}