{
  "type": "Feature",
  "properties": {
    "addr:full":"O.s.m. T?san San. Sit. 7. Blok No:18/20 Ikitelli/K\u00fc\u00e7\u00fck\u00e7ekmece Istanbul 34670",
    "addr:housenumber":"7 blok no 18 / 20",
    "addr:postcode":"34670",
    "addr:street":"San;Sit.",
    "iso:country":"TR",
    "sg:address":"O.s.m. T?san San. Sit. 7. Blok No:18/20",
    "sg:city":"Ikitelli/K\u00fc\u00e7\u00fck\u00e7ekmece",
    "sg:classifiers":[
        {
            "category":"Wholesale",
            "subcategory":"Auto Parts",
            "type":"Manufacturing & Wholesale Goods"
        }
    ],
    "sg:phone":"+90 212 485 0976",
    "sg:postcode":"34670",
    "sg:province":"Istanbul",
    "sg:tags":[
        "spare"
    ],
    "wof:name":"Teknotim Ltd. Sti.",
    "wof:placetype":"venue"
},
  "geometry": {"coordinates":[28.9861831665,41.0408554077],"type":"Point"}
}