{
  "type": "Feature",
  "properties": {
    "addr:full":"Perpa Ticaret Merkz.b Blok Kat:8 No:920 Okmeydani Istanbul 43050",
    "addr:housenumber":"blok kat 8 no 920",
    "addr:postcode":"43050",
    "addr:street":"Okmeydani Istanbul",
    "iso:country":"TR",
    "sg:address":"Perpa Ticaret Merkz.b Blok Kat:8 No:920",
    "sg:city":"Okmeydani",
    "sg:classifiers":[
        {
            "category":"Manufacturing",
            "subcategory":"Tools & Machinery",
            "type":"Manufacturing & Wholesale Goods"
        }
    ],
    "sg:phone":"+90 212222023132",
    "sg:postcode":"43050",
    "sg:province":"Istanbul",
    "sg:tags":[
        "hand"
    ],
    "wof:name":"Akteknik Makina San.tic.a.s.",
    "wof:placetype":"venue"
},
  "geometry": {"coordinates":[28.9861831665,41.0408554077],"type":"Point"}
}