{
  "type": "Feature",
  "properties": {
    "addr:full":"D?gmeci Mah. Suburcu Cad. Sehir Pasaji K: 1 No: 41 Fatih Gaziantep 01740",
    "addr:housenumber":"1 no 41",
    "addr:postcode":"01740",
    "addr:street":"Gmeci Mah. Suburcu Cad. Sehir Pasaji K",
    "iso:country":"TR",
    "sg:address":"D?gmeci Mah. Suburcu Cad. Sehir Pasaji K: 1 No: 41",
    "sg:city":"Fatih",
    "sg:classifiers":[
        {
            "category":"Travel",
            "subcategory":"Travel Agent",
            "type":"Entertainment"
        }
    ],
    "sg:phone":"+90 342231487071",
    "sg:postcode":"01740",
    "sg:province":"Gaziantep",
    "sg:tags":[
        "agency",
        "tourism"
    ],
    "wof:name":"Altinoluk Turizm",
    "wof:placetype":"venue"
},
  "geometry": {"coordinates":[37.4416732788,36.9459457397],"type":"Point"}
}