{
  "type": "Feature",
  "properties": {
    "addr:full":"Bozburun K??yolu G??ler Denizli",
    "addr:housenumber":"?;? ?",
    "addr:street":"? Yolu G",
    "iso:country":"TR",
    "sg:address":"Bozburun K??yolu",
    "sg:city":"G??ler",
    "sg:classifiers":[
        {
            "category":"Shopping",
            "subcategory":"Clothing, Apparel, & Fashions",
            "type":"Retail Goods"
        }
    ],
    "sg:phone":"+90 258 371 0162",
    "sg:province":"Denizli",
    "sg:tags":[
        "-",
        "towel",
        "bathrobe"
    ],
    "wof:name":"Fam Takstil Ltd.sti.",
    "wof:placetype":"venue"
},
  "geometry": {"coordinates":[29.3432292938,37.6734886169],"type":"Point"}
}