{
  "type": "Feature",
  "properties": {
    "iso:country":"TR",
    "sg:address":"Mustafa Muglali Cd.no:40",
    "sg:city":"Marmaris",
    "sg:classifiers":[
        {
            "category":"Freight",
            "type":"Transportation"
        }
    ],
    "sg:phone":"+90 252 412 1928",
    "sg:postcode":"48700",
    "sg:province":"Mugla",
    "sg:tags":[
        "agent",
        "shipping",
        "broker"
    ],
    "wof:name":"G & G Shipping",
    "wof:placetype":"venue"
},
  "geometry": {"coordinates":[28.366346,37.217827],"type":"Point"}
}