{
  "type": "Feature",
  "properties": {
    "addr:full":"Halkali Caddesi No: 231 Sefak? Istanbul 34630",
    "addr:housenumber":"no",
    "addr:postcode":"34630",
    "addr:street":"Halkali Caddesi;Sefak;Istanbul",
    "iso:country":"TR",
    "sg:address":"Halkali Caddesi No: 231",
    "sg:city":"Sefak?",
    "sg:classifiers":[
        {
            "category":"Home & Garden",
            "subcategory":"Kitchen Supply",
            "type":"Retail Goods"
        }
    ],
    "sg:phone":"+90 212 698 9180",
    "sg:postcode":"34630",
    "sg:province":"Istanbul",
    "sg:tags":[
        "tomato",
        "paste"
    ],
    "wof:name":"Hilal Gida San. Ve Tic. A.s.",
    "wof:placetype":"venue"
},
  "geometry": {"coordinates":[28.7918777466,41.0128631592],"type":"Point"}
}