{
  "type": "Feature",
  "properties": {
    "addr:full":"Ismet ?zarslan Pasinler Amasya 25300",
    "addr:housenumber":"?",
    "addr:postcode":"25300",
    "addr:street":"Ismet",
    "iso:country":"TR",
    "sg:address":"Ismet ?zarslan",
    "sg:city":"Pasinler",
    "sg:classifiers":[
        {
            "category":"Government",
            "subcategory":"Office",
            "type":"Public Place"
        }
    ],
    "sg:phone":"+90 358 218 8014",
    "sg:postcode":"25300",
    "sg:province":"Amasya",
    "sg:tags":[
        "municipality"
    ],
    "wof:name":"Amasya Ili Belediye Baskani",
    "wof:placetype":"venue"
},
  "geometry": {"coordinates":[29.2808799744,40.9824485779],"type":"Point"}
}