{
  "type": "Feature",
  "properties": {
    "addr:full":"Aksaray Cad.azimkar Sok.no:12 Laleli Istanbul 24300",
    "addr:housenumber":"12",
    "addr:postcode":"24300",
    "addr:street":"Sok.No;Istanbul",
    "iso:country":"TR",
    "sg:address":"Aksaray Cad.azimkar Sok.no:12",
    "sg:city":"Laleli",
    "sg:classifiers":[
        {
            "category":"Shopping",
            "subcategory":"Clothing, Apparel, & Fashions",
            "type":"Retail Goods"
        }
    ],
    "sg:phone":"+90 212 638 5413",
    "sg:postcode":"24300",
    "sg:province":"Istanbul",
    "sg:tags":[
        "men",
        "wear"
    ],
    "wof:name":"Klasmen",
    "wof:placetype":"venue"
},
  "geometry": {"coordinates":[28.9546756744,41.0077056885],"type":"Point"}
}