{
  "type": "Feature",
  "properties": {
    "addr:full":"Eskisehir Yolu Inonu Bulv.odtu Yerles Kesi Odtu Kad\u0131k\u00f6y Ankara 06920",
    "addr:housenumber":"inonu",
    "addr:postcode":"06920",
    "addr:street":"Eskisehir Yolu",
    "iso:country":"TR",
    "sg:address":"Eskisehir Yolu Inonu Bulv.odtu Yerles Kesi Odtu",
    "sg:city":"Kad\u0131k\u00f6y",
    "sg:orig_category":"Printinh House",
    "sg:phone":"+90 312 210 3870",
    "sg:postcode":"06920",
    "sg:province":"Ankara",
    "wof:name":"Odtu G.v.yayincilik Ve Iletisim A.s.",
    "wof:placetype":"venue"
},
  "geometry": {"coordinates":[32.8560333252,39.9438743591],"type":"Point"}
}