{
  "type": "Feature",
  "properties": {
    "addr:full":"Karatay San. Sit. Bah?lik Sk. No:3 Ikitelli/K\u00fc\u00e7\u00fck\u00e7ekmece Konya 34670",
    "addr:postcode":"34670",
    "addr:street":"Sk. No 3",
    "iso:country":"TR",
    "sg:address":"Karatay San. Sit. Bah?lik Sk. No:3",
    "sg:city":"Ikitelli/K\u00fc\u00e7\u00fck\u00e7ekmece",
    "sg:classifiers":[
        {
            "category":"Manufacturing",
            "subcategory":"Tools & Machinery",
            "type":"Manufacturing & Wholesale Goods"
        }
    ],
    "sg:phone":"+90 332 233 9763",
    "sg:postcode":"34670",
    "sg:province":"Konya",
    "sg:tags":[
        "machine",
        "industry"
    ],
    "wof:name":"Gaysan Surnap Gaydlari San. Tic. Ltd. Sti.",
    "wof:placetype":"venue"
},
  "geometry": {"coordinates":[32.4990272522,37.8715362549],"type":"Point"}
}