{
  "type": "Feature",
  "properties": {
    "iso:country":"TR",
    "sg:address":"Kurtismailpasa 2.sk.saadet Apt.no:33/a",
    "sg:city":"21100",
    "sg:classifiers":[
        {
            "category":"Professional",
            "subcategory":"Detective & Security Services",
            "type":"Services"
        }
    ],
    "sg:phone":"+90 412 228 2098",
    "sg:province":"Diyarbakir",
    "sg:tags":[
        "material"
    ],
    "wof:name":"Elkom",
    "wof:placetype":"venue"
},
  "geometry": {"coordinates":[40.225334,37.91581],"type":"Point"}
}