{
  "type": "Feature",
  "properties": {
    "addr:full":"Tufanpata Mah.ustun Sok. Atcioslu Apt.k:1 No:3 Kozan / Adana",
    "addr:housenumber":"1",
    "addr:street":"Mah.Ustun Sok. Atcioslu Apt.K;No 3",
    "iso:country":"TR",
    "sg:address":"Tufanpata Mah.ustun Sok. Atcioslu",
    "sg:city":"Apt.k:1 No:3",
    "sg:classifiers":[
        {
            "category":"Shopping",
            "subcategory":"Computers & Home Electronics",
            "type":"Retail Goods"
        }
    ],
    "sg:phone":"+90 322 515 8466",
    "sg:province":"Kozan / Adana",
    "sg:tags":[
        "chamber",
        "commerce"
    ],
    "wof:name":"Kozan Chamber Of Commerce",
    "wof:placetype":"venue"
},
  "geometry": {"coordinates":[35.8307609558,37.445148468],"type":"Point"}
}