{
  "type": "Feature",
  "properties": {
    "iso:country":"TR",
    "sg:address":"Inonu Mah.evren Cad.no:6/1 Icerenkoy",
    "sg:city":"Kartal",
    "sg:classifiers":[
        {
            "category":"Freight",
            "type":"Transportation"
        }
    ],
    "sg:phone":"+90 216 574 2738",
    "sg:postcode":"34876",
    "sg:province":"Istanbul",
    "sg:tags":[
        "packing",
        "industry"
    ],
    "wof:name":"Cok-oz Ambalaj San.tic.ltd.sti.",
    "wof:placetype":"venue"
},
  "geometry": {"coordinates":[29.131193161,40.9772491455],"type":"Point"}
}