{
  "type": "Feature",
  "properties": {
    "iso:country":"TR",
    "sg:address":"Visnelik Mah. Savas Cad. No: 116 A",
    "sg:city":"Mecidiyek\u00f6y",
    "sg:classifiers":[
        {
            "category":"Professional",
            "subcategory":"Detective & Security Services",
            "type":"Services"
        }
    ],
    "sg:phone":"+90 222 224 0732",
    "sg:province":"Eskisehir",
    "sg:tags":[
        "material"
    ],
    "wof:name":"Kut Electronic",
    "wof:placetype":"venue"
},
  "geometry": {"coordinates":[30.507975,39.754551],"type":"Point"}
}