{
  "type": "Feature",
  "properties": {
    "addr:full":"Galip Dede Cd. Tamer Han No:30 \u00c7ankaya Ankara 06105",
    "addr:housenumber":"han",
    "addr:postcode":"06105",
    "addr:street":"Galip Dede Cd. Tamer;No 30 C\u0327Ankaya",
    "iso:country":"TR",
    "sg:address":"Galip Dede Cd. Tamer Han No:30",
    "sg:city":"\u00c7ankaya",
    "sg:classifiers":[
        {
            "category":"Transit Center",
            "subcategory":"Freight",
            "type":"Transportation"
        }
    ],
    "sg:phone":"+90 312 445 1090",
    "sg:postcode":"06105",
    "sg:province":"Ankara",
    "wof:name":"Obsmar Denizcilik Tic. A.s.",
    "wof:placetype":"venue"
},
  "geometry": {"coordinates":[32.7654190063,40.0357513428],"type":"Point"}
}