{
  "type": "Feature",
  "properties": {
    "addr:full":"Esat \u00c7ankaya Ankara 06550",
    "addr:postcode":"06550",
    "iso:country":"TR",
    "sg:address":"Esat",
    "sg:city":"\u00c7ankaya",
    "sg:classifiers":[
        {
            "category":"Professional",
            "subcategory":"Detective & Security Services",
            "type":"Services"
        }
    ],
    "sg:phone":"+90 312 447 5495",
    "sg:postcode":"06550",
    "sg:province":"Ankara",
    "sg:tags":[
        "material"
    ],
    "wof:name":"Celebi Guvenlik",
    "wof:placetype":"venue"
},
  "geometry": {"coordinates":[32.857803,39.867405],"type":"Point"}
}