{
  "type": "Feature",
  "properties": {
    "addr:full":"Y. Beyazit Cd. G?c?glu Ismerk. No:50/8 Y.bosna Emin\u00f6n\u00fc/Ca\u011falo\u011flu Istanbul 34110",
    "addr:housenumber":"? c ?;50 / 8",
    "addr:postcode":"34110",
    "addr:street":"Cd. G;Glu Ismerk. No",
    "iso:country":"TR",
    "sg:address":"Y. Beyazit Cd. G?c?glu Ismerk. No:50/8 Y.bosna",
    "sg:city":"Emin\u00f6n\u00fc/Ca\u011falo\u011flu",
    "sg:classifiers":[
        {
            "category":"Shopping",
            "subcategory":"Stationery & Office Supplies",
            "type":"Retail Goods"
        }
    ],
    "sg:phone":"+90 212 551 2288",
    "sg:postcode":"34110",
    "sg:province":"Istanbul",
    "wof:name":"?zt?rk Kirtasiye San. Tic. Ltd. Sti.",
    "wof:placetype":"venue"
},
  "geometry": {"coordinates":[28.975925,41.012379],"type":"Point"}
}