{
  "type": "Feature",
  "properties": {
    "addr:full":"Atisalani Cad. No:37 Esenler B.?ekmece Istanbul",
    "addr:housenumber":"37;?",
    "addr:street":"Atisalani Cad. No",
    "iso:country":"TR",
    "sg:address":"Atisalani Cad. No:37 Esenler",
    "sg:city":"B.?ekmece",
    "sg:classifiers":[
        {
            "category":"Farming",
            "subcategory":"Fish & Marine Products",
            "type":"Manufacturing & Wholesale Goods"
        }
    ],
    "sg:phone":"+90 212611464495",
    "sg:province":"Istanbul",
    "sg:tags":[
        "automotive"
    ],
    "wof:name":"Gurses Otomotiv A.s.",
    "wof:placetype":"venue"
},
  "geometry": {"coordinates":[28.8807487488,41.0420074463],"type":"Point"}
}