{
  "type": "Feature",
  "properties": {
    "addr:full":"302. Sk. No:42 2. San. Sit. Bornova Y. Bosna Izmir",
    "addr:housenumber":"302;2;bornova",
    "addr:street":"Sk. No 42;San. Sit.;Y. Bosna",
    "iso:country":"TR",
    "sg:address":"302. Sk. No:42 2. San. Sit. Bornova",
    "sg:city":"Y. Bosna",
    "sg:orig_category":"General Industrial Products",
    "sg:phone":"+90 232 486 5022",
    "sg:province":"Izmir",
    "wof:name":"Baygan Sinai Ve Sosyal Tesis. Taah. A.s.",
    "wof:placetype":"venue"
},
  "geometry": {"coordinates":[27.2196006775,38.4662017822],"type":"Point"}
}