{
  "type": "Feature",
  "properties": {
    "iso:country":"TR",
    "sg:address":"2.san.sitesi 301 Sk.no:59 Bornova-",
    "sg:city":"Gazi Osman Pasa",
    "sg:classifiers":[
        {
            "category":"Manufacturing",
            "subcategory":"Tools & Machinery",
            "type":"Manufacturing & Wholesale Goods"
        }
    ],
    "sg:phone":"+90 232 486 4079",
    "sg:postcode":"35993",
    "sg:province":"Izmir",
    "sg:tags":[
        "machine",
        "industry"
    ],
    "wof:name":"?zes Makina Sanayi Ve Ticaret Ltd.sti.",
    "wof:placetype":"venue"
},
  "geometry": {"coordinates":[27.1296863556,38.4186973572],"type":"Point"}
}