{
  "type": "Feature",
  "properties": {
    "addr:full":"Ekin San. Sitesi No:62 Y.dudullu Umraniye Etiler Istanbul 07010",
    "addr:postcode":"07010",
    "iso:country":"TR",
    "sg:address":"Ekin San. Sitesi No:62 Y.dudullu Umraniye",
    "sg:city":"Etiler",
    "sg:classifiers":[
        {
            "category":"Manufacturing",
            "subcategory":"Wood Products",
            "type":"Manufacturing & Wholesale Goods"
        }
    ],
    "sg:phone":"+90 216 466 0548",
    "sg:postcode":"07010",
    "sg:province":"Istanbul",
    "sg:tags":[
        "forest"
    ],
    "wof:name":"Akkapsan Orman Urunleri",
    "wof:placetype":"venue"
},
  "geometry": {"coordinates":[28.9759254456,41.0123786926],"type":"Point"}
}