{
  "type": "Feature",
  "properties": {
    "addr:full":"Fabrika Cad. No:6 Soganlik?y \u00c7orlu Bursa",
    "addr:housenumber":"?",
    "addr:street":"Fabrika Cad. No 6 Soganlik;Y C\u0327Orlu",
    "iso:country":"TR",
    "sg:address":"Fabrika Cad. No:6 Soganlik?y",
    "sg:city":"\u00c7orlu",
    "sg:classifiers":[
        {
            "category":"Social Services",
            "subcategory":"Job Training",
            "type":"Services"
        }
    ],
    "sg:phone":"+90 224 234 1229",
    "sg:province":"Bursa",
    "sg:tags":[
        "tannery"
    ],
    "wof:name":"Bur-der A.s.",
    "wof:placetype":"venue"
},
  "geometry": {"coordinates":[29.0398807526,40.1076583862],"type":"Point"}
}