{
  "type": "Feature",
  "properties": {
    "iso:country":"TR",
    "sg:address":"Tunali Hilmi Cad. No:51/b Kucukesat",
    "sg:city":"Izmit",
    "sg:classifiers":[
        {
            "category":"Shopping",
            "subcategory":"Shoes",
            "type":"Retail Goods"
        }
    ],
    "sg:phone":"+90 312 425 5221",
    "sg:postcode":"41000",
    "sg:province":"Ankara",
    "wof:name":"Moda Kundura -canta",
    "wof:placetype":"venue"
},
  "geometry": {"coordinates":[32.861473,39.907902],"type":"Point"}
}