{
  "type": "Feature",
  "properties": {
    "iso:country":"TR",
    "sg:address":"Fatih Sk. No:21 Siteler",
    "sg:city":"Gebze",
    "sg:classifiers":[
        {
            "category":"Manufacturing",
            "subcategory":"Wood Products",
            "type":"Manufacturing & Wholesale Goods"
        }
    ],
    "sg:phone":"+90 312 348 2470",
    "sg:postcode":"41400",
    "sg:province":"Ankara",
    "sg:tags":[
        "forest"
    ],
    "wof:name":"G?vercinler Orman ?r?n. Insaat Tic. Ltd.",
    "wof:placetype":"venue"
},
  "geometry": {"coordinates":[29.1190490723,40.1803741455],"type":"Point"}
}