{
  "type": "Feature",
  "properties": {
    "iso:country":"TR",
    "sg:address":"Istanbul Cad. No:25 Yenicubuk Gemerek",
    "sg:city":"Emin?? 34450",
    "sg:classifiers":[
        {
            "category":"Shopping",
            "subcategory":"Clothing, Apparel, & Fashions",
            "type":"Retail Goods"
        }
    ],
    "sg:phone":"+90 346 654 7197",
    "sg:province":"Sivas",
    "sg:tags":[
        "bag-belt-accessories"
    ],
    "wof:name":"Tirse Dericilik",
    "wof:placetype":"venue"
},
  "geometry": {"coordinates":[36.096901,39.212299],"type":"Point"}
}