{
  "type": "Feature",
  "properties": {
    "addr:full":"Sehit Dursun Bakan Sk. No.3 K.1 Besiktas Osmangazi Istanbul 16010",
    "addr:housenumber":"k.1",
    "addr:postcode":"16010",
    "addr:street":"Bakan Sk. No.3",
    "iso:country":"TR",
    "sg:address":"Sehit Dursun Bakan Sk. No.3 K.1 Besiktas",
    "sg:city":"Osmangazi",
    "sg:classifiers":[
        {
            "category":"Professional",
            "subcategory":"Computer Services",
            "type":"Services"
        }
    ],
    "sg:phone":"+90 212 236 2323",
    "sg:postcode":"16010",
    "sg:province":"Istanbul",
    "sg:tags":[
        "application",
        "software"
    ],
    "wof:name":"Net Bilgisayar Yazilim & Donanim Ve Danismanlik Hizmetleri",
    "wof:placetype":"venue"
},
  "geometry": {"coordinates":[28.9861831665,41.0408554077],"type":"Point"}
}