{
  "type": "Feature",
  "properties": {
    "iso:country":"TR",
    "sg:address":"Gaziler Cad. No: 78/607",
    "sg:city":"Bak\u0131rk\u00f6y",
    "sg:classifiers":[
        {
            "category":"Professional",
            "subcategory":"Detective & Security Services",
            "type":"Services"
        }
    ],
    "sg:phone":"+90 232 469 3330",
    "sg:postcode":"34720",
    "sg:province":"Izmir",
    "sg:tags":[
        "material"
    ],
    "wof:name":"Berkay Elektronik",
    "wof:placetype":"venue"
},
  "geometry": {"coordinates":[27.144867,38.422256],"type":"Point"}
}