{
  "type": "Feature",
  "properties": {
    "iso:country":"TR",
    "sg:address":"Inonu Cad. Eski Sebze Hali A.blok No:7",
    "sg:city":"Karak\u00f6y",
    "sg:classifiers":[
        {
            "category":"Home & Garden",
            "subcategory":"Household Appliances",
            "type":"Retail Goods"
        }
    ],
    "sg:phone":"+90 224 220 2714",
    "sg:postcode":"16510",
    "sg:province":"Bursa",
    "sg:tags":[
        "conditioner",
        "air"
    ],
    "wof:name":"Uludag Klima San.tic. Ltd.sti.",
    "wof:placetype":"venue"
},
  "geometry": {"coordinates":[29.0580043793,40.1947555542],"type":"Point"}
}