{
  "type": "Feature",
  "properties": {
    "iso:country":"TR",
    "sg:address":"Maresal Fevzi Cakmak Cad.no:113 Alibeyk?-",
    "sg:city":"Ey\u00fcp",
    "sg:classifiers":[
        {
            "category":"Food & Beverages",
            "subcategory":"Dairy",
            "type":"Retail Goods"
        }
    ],
    "sg:phone":"+90 212 627 1000",
    "sg:postcode":"34050",
    "sg:province":"Istanbul",
    "sg:tags":[
        "pruducts",
        "milk"
    ],
    "wof:name":"Danonesa Tikvesli S?t ?r?nleri San",
    "wof:placetype":"venue"
},
  "geometry": {"coordinates":[28.9633369446,41.0813789368],"type":"Point"}
}