{
  "type": "Feature",
  "properties": {
    "iso:country":"TR",
    "sg:address":"Velimese Sanayi B?gesi",
    "sg:city":"Corlu",
    "sg:classifiers":[
        {
            "category":"Shopping",
            "subcategory":"Clothing, Apparel, & Fashions",
            "type":"Retail Goods"
        }
    ],
    "sg:phone":"+90 282 674 4235",
    "sg:postcode":"01770",
    "sg:province":"Tekirdag",
    "sg:tags":[
        "ready",
        "wear"
    ],
    "wof:name":"Beltas Ic Ve Dis Tic. A.s.",
    "wof:placetype":"venue"
},
  "geometry": {"coordinates":[27.5144004822,40.9791984558],"type":"Point"}
}