{
  "type": "Feature",
  "properties": {
    "addr:full":"Oto Par?cilar Sitesi Koray Sk. 30 Melikgazi Konya 38000",
    "addr:postcode":"38000",
    "addr:street":"Koray Sk. 30 Melikgazi",
    "iso:country":"TR",
    "sg:address":"Oto Par?cilar Sitesi Koray Sk. 30",
    "sg:city":"Melikgazi",
    "sg:classifiers":[
        {
            "category":"Banks & Credit Unions",
            "subcategory":"Investment Brokerage",
            "type":"Services"
        }
    ],
    "sg:phone":"+90 332236995051",
    "sg:postcode":"38000",
    "sg:province":"Konya",
    "sg:tags":[
        "-",
        "export",
        "import"
    ],
    "wof:name":"Expoes Dis Ticaret A.s.",
    "wof:placetype":"venue"
},
  "geometry": {"coordinates":[33.0667152405,39.2111282349],"type":"Point"}
}