{
  "type": "Feature",
  "properties": {
    "iso:country":"TR",
    "sg:address":"Kosuyolu Aksu Cad. No.3",
    "sg:city":"Bak\u0131rk\u00f6y",
    "sg:classifiers":[
        {
            "category":"Shopping",
            "subcategory":"Clothing, Apparel, & Fashions",
            "type":"Retail Goods"
        }
    ],
    "sg:phone":"+90 212 570 5925",
    "sg:province":"Istanbul",
    "sg:tags":[
        "ready",
        "wear"
    ],
    "wof:name":"Prima Konf A.s.",
    "wof:placetype":"venue"
},
  "geometry": {"coordinates":[28.8851184845,40.9916534424],"type":"Point"}
}