{
  "type": "Feature",
  "properties": {
    "iso:country":"TR",
    "sg:address":"Tahran Cd. No:3 Kavaklidere",
    "sg:city":"Maltepe",
    "sg:classifiers":[
        {
            "category":"Home & Garden",
            "subcategory":"Building Materials",
            "type":"Retail Goods"
        }
    ],
    "sg:phone":"+90 312 427 0492",
    "sg:postcode":"01000",
    "sg:province":"Ankara",
    "sg:tags":[
        "window",
        "door",
        "plastic"
    ],
    "wof:name":"Tusas Havacilik Uzay San. A.s.",
    "wof:placetype":"venue"
},
  "geometry": {"coordinates":[32.8646965027,39.9032897949],"type":"Point"}
}