{
  "type": "Feature",
  "properties": {
    "addr:full":"Inonu Bul. Uysal Apt.k:1/1 Mersin I?el 52750",
    "addr:housenumber":"1 / 1",
    "addr:postcode":"? el 52750",
    "addr:street":"Bul. Uysal Apt.K",
    "iso:country":"TR",
    "sg:address":"Inonu Bul. Uysal Apt.k:1/1",
    "sg:city":"Mersin",
    "sg:orig_category":"Dryfood-dried Nuts",
    "sg:phone":"+90 324",
    "sg:postcode":"52750",
    "sg:province":"I?el",
    "wof:name":"Sameks Ltd.sti.",
    "wof:placetype":"venue"
},
  "geometry": {"coordinates":[37.7128486633,41.0530204773],"type":"Point"}
}