{
  "type": "Feature",
  "properties": {
    "iso:country":"TR",
    "sg:address":"Inonu Bul. Uysal Apt.k:1/1",
    "sg:city":"Mersin",
    "sg:orig_category":"Dryfood-dried Nuts",
    "sg:phone":"+90 324",
    "sg:postcode":"52750",
    "sg:province":"I?el",
    "wof:name":"Sameks Ltd.sti.",
    "wof:placetype":"venue"
},
  "geometry": {"coordinates":[37.7128486633,41.0530204773],"type":"Point"}
}