{
  "type": "Feature",
  "properties": {
    "iso:country":"TR",
    "sg:address":"Eski Sanayi Gundogdu Sok. No:3",
    "sg:city":"Y?egir",
    "sg:classifiers":[
        {
            "category":"Wholesale",
            "subcategory":"Machinery & Supplies",
            "type":"Manufacturing & Wholesale Goods"
        }
    ],
    "sg:phone":"+90 332237277374",
    "sg:postcode":"01280",
    "sg:province":"Konya",
    "sg:tags":[
        "bearing",
        "ball"
    ],
    "wof:name":"Konya Rulman San.tic. Ltd.sti.",
    "wof:placetype":"venue"
},
  "geometry": {"coordinates":[32.493847,37.899544],"type":"Point"}
}