{
  "type": "Feature",
  "properties": {
    "iso:country":"TR",
    "sg:address":"Mermerciler Cd. No: 22",
    "sg:city":"Yenidogan",
    "sg:classifiers":[
        {
            "category":"Home & Garden",
            "subcategory":"Building Materials",
            "type":"Retail Goods"
        }
    ],
    "sg:phone":"+90 216 312 3652",
    "sg:postcode":"01260",
    "sg:province":"Istanbul",
    "sg:tags":[
        "stone",
        "natural",
        "marble"
    ],
    "wof:name":"Ortadogu Mermer San.ve Ins. A.s.",
    "wof:placetype":"venue"
},
  "geometry": {"coordinates":[29.2369174957,41.0168151855],"type":"Point"}
}