{
  "type": "Feature",
  "properties": {
    "iso:country":"TR",
    "sg:address":"G.pala Mah.rizabey Sok. No:19/1 Avcilar",
    "sg:city":"Merter",
    "sg:classifiers":[
        {
            "category":"Shopping",
            "subcategory":"Shoes",
            "type":"Retail Goods"
        }
    ],
    "sg:phone":"+90 212 694 8717",
    "sg:province":"Istanbul",
    "wof:name":"Sinderella Baby Shoes Collection",
    "wof:placetype":"venue"
},
  "geometry": {"coordinates":[28.723101,40.981201],"type":"Point"}
}