{
  "type": "Feature",
  "properties": {
    "iso:country":"TR",
    "sg:address":"Iskele Cad. N0:10/4",
    "sg:city":"Bak\u0131rk\u00f6y",
    "sg:classifiers":[
        {
            "category":"Professional",
            "subcategory":"Detective & Security Services",
            "type":"Services"
        }
    ],
    "sg:phone":"+90 212 660 6370",
    "sg:postcode":"34720",
    "sg:province":"Istanbul",
    "sg:tags":[
        "material"
    ],
    "wof:name":"Aytem G?venlik Ve Elektronik Sistemleri",
    "wof:placetype":"venue"
},
  "geometry": {"coordinates":[28.877758,40.977654],"type":"Point"}
}