{
  "type": "Feature",
  "properties": {
    "addr:full":"Degirmenyolu Cad. Birman Is Merkezi No:11 Kat:1 Icerenkoy Istanbul 34752",
    "addr:housenumber":"no 11 kat 1",
    "addr:postcode":"34752",
    "addr:street":"Degirmenyolu Cad. Birman",
    "iso:country":"TR",
    "sg:address":"Degirmenyolu Cad. Birman Is Merkezi No:11 Kat:1",
    "sg:city":"Icerenkoy",
    "sg:classifiers":[
        {
            "category":"Food & Beverages",
            "subcategory":"Specialty",
            "type":"Retail Goods"
        }
    ],
    "sg:phone":"+90 216 574 5096",
    "sg:postcode":"34752",
    "sg:province":"Istanbul",
    "sg:tags":[
        "materials-spices",
        "additive"
    ],
    "wof:name":"Arosel Gida Gida Katki Madd. Ve Makina San. Dis Tic. Ltd.sti.",
    "wof:placetype":"venue"
},
  "geometry": {"coordinates":[29.1114387512,40.9703979492],"type":"Point"}
}