{
  "type": "Feature",
  "properties": {
    "iso:country":"TR",
    "sg:address":"Hukumet Bulvari 1.sok. No:2",
    "sg:city":"Beyoglu",
    "sg:classifiers":[
        {
            "category":"Wholesale",
            "subcategory":"Books, Periodicals, & Newspapers",
            "type":"Manufacturing & Wholesale Goods"
        }
    ],
    "sg:phone":"+90 256 225 0784",
    "sg:postcode":"46810",
    "sg:province":"Aydin",
    "sg:tags":[
        "house",
        "publishing"
    ],
    "wof:name":"Aydin Yayinevi",
    "wof:placetype":"venue"
},
  "geometry": {"coordinates":[27.8520698547,37.8272247314],"type":"Point"}
}