{
  "type": "Feature",
  "properties": {
    "iso:country":"TR",
    "sg:address":"Balkaner Plaza, Eski Buyukdere Cad. No.31 K.7 Maslak",
    "sg:city":"Ostim",
    "sg:classifiers":[
        {
            "category":"Banks & Credit Unions",
            "subcategory":"Financial Services",
            "type":"Services"
        }
    ],
    "sg:phone":"+90 212 286 3152",
    "sg:postcode":"06370",
    "sg:province":"Istanbul",
    "sg:tags":[
        "finance"
    ],
    "wof:name":"Med Menkul Degerler A.s.",
    "wof:placetype":"venue"
},
  "geometry": {"coordinates":[28.9759254456,41.0123786926],"type":"Point"}
}