{
  "type": "Feature",
  "properties": {
    "addr:full":"Millet Cad. S. Mehmet Emin Sk. 15/2 F.zade \u00c7ankaya Istanbul",
    "addr:housenumber":"2",
    "addr:street":"Millet Cad. S.;Sk. 15 /",
    "iso:country":"TR",
    "sg:address":"Millet Cad. S. Mehmet Emin Sk. 15/2 F.zade",
    "sg:city":"\u00c7ankaya",
    "sg:classifiers":[
        {
            "category":"Wholesale",
            "subcategory":"Medical Equipment & Supplies",
            "type":"Manufacturing & Wholesale Goods"
        }
    ],
    "sg:phone":"+90 212 530 7375",
    "sg:province":"Istanbul",
    "wof:name":"Hekimsan Medikal",
    "wof:placetype":"venue"
},
  "geometry": {"coordinates":[28.9861793518,41.040851593],"type":"Point"}
}