{
  "type": "Feature",
  "properties": {
    "addr:full":"San. Cd. No:24 Pendik Sisli Istanbul 80260",
    "addr:housenumber":"no 24",
    "addr:postcode":"80260",
    "addr:street":"San. Cd.",
    "iso:country":"TR",
    "sg:address":"San. Cd. No:24 Pendik",
    "sg:city":"Sisli",
    "sg:classifiers":[
        {
            "category":"Freight",
            "type":"Transportation"
        }
    ],
    "sg:phone":"+90 216 378 3636",
    "sg:postcode":"80260",
    "sg:province":"Istanbul",
    "sg:tags":[
        "packing",
        "industry"
    ],
    "wof:name":"United Ambalaj San. Tic. Ltd. Sti.",
    "wof:placetype":"venue"
},
  "geometry": {"coordinates":[29.2745132446,40.9686775208],"type":"Point"}
}