{
  "type": "Feature",
  "properties": {
    "iso:country":"TR",
    "sg:address":"?irpan Mh Karaosman Sk No:22/a",
    "sg:city":"Osmangazi",
    "sg:classifiers":[
        {
            "category":"Social Services",
            "subcategory":"Retirement Home",
            "type":"Services"
        }
    ],
    "sg:phone":"+90 224 251 5080",
    "sg:postcode":"16050",
    "sg:province":"Bursa",
    "sg:tags":[
        "door"
    ],
    "wof:name":"Pmp Production",
    "wof:placetype":"venue"
},
  "geometry": {"coordinates":[29.0804786682,40.1926574707],"type":"Point"}
}