{
  "type": "Feature",
  "properties": {
    "iso:country":"TR",
    "sg:address":"Cekirge Mah.kavakdibi Sok.no:21-5",
    "sg:city":"Fatih",
    "sg:classifiers":[
        {
            "category":"Wholesale",
            "subcategory":"Medical Equipment & Supplies",
            "type":"Manufacturing & Wholesale Goods"
        }
    ],
    "sg:phone":"+90 224 234 0900",
    "sg:postcode":"01740",
    "sg:province":"Bursa",
    "sg:tags":[
        "material"
    ],
    "wof:name":"Medika Farma Ltd.sti.",
    "wof:placetype":"venue"
},
  "geometry": {"coordinates":[29.0248355865,40.2000007629],"type":"Point"}
}