{
  "type": "Feature",
  "properties": {
    "addr:full":"?amlica Cd. No:1/b Kuru?sme \u00dcsk\u00fcdar Istanbul 34672",
    "addr:housenumber":"?;no 1 / b;?",
    "addr:postcode":"34672",
    "addr:street":"Amlica Cd.;Kuru",
    "iso:country":"TR",
    "sg:address":"?amlica Cd. No:1/b Kuru?sme",
    "sg:city":"\u00dcsk\u00fcdar",
    "sg:classifiers":[
        {
            "category":"Shopping",
            "subcategory":"Florist",
            "type":"Retail Goods"
        }
    ],
    "sg:phone":"+90 216 334 6781",
    "sg:postcode":"34672",
    "sg:province":"Istanbul",
    "sg:tags":[
        "flower"
    ],
    "wof:name":"?agin ?i?ek Sar.",
    "wof:placetype":"venue"
},
  "geometry": {"coordinates":[29.0154418945,41.0218315125],"type":"Point"}
}