{
  "type": "Feature",
  "properties": {
    "iso:country":"TR",
    "sg:address":"Siraselviler Cad.no:189/1",
    "sg:city":"Sisli",
    "sg:classifiers":[
        {
            "category":"Home & Garden",
            "subcategory":"Household Appliances",
            "type":"Retail Goods"
        }
    ],
    "sg:phone":"+90 212 245 1389",
    "sg:postcode":"65710",
    "sg:province":"Istanbul",
    "sg:tags":[
        "conditioner",
        "air"
    ],
    "wof:name":"Ilke Muhendislik Mutaahitlik Makina Sanayi Ve Ticaret Ltd.sti.",
    "wof:placetype":"venue"
},
  "geometry": {"coordinates":[28.9830513,41.0319862366],"type":"Point"}
}