{
  "type": "Feature",
  "properties": {
    "addr:full":"Kalender Sk. No.1 Merter Istanbul",
    "addr:street":"Kalender Sk. No.1",
    "iso:country":"TR",
    "sg:address":"Kalender Sk. No.1",
    "sg:city":"Merter",
    "sg:classifiers":[
        {
            "category":"Shopping",
            "subcategory":"Crafts & Fabrics",
            "type":"Retail Goods"
        }
    ],
    "sg:phone":"+90 212 637 1315",
    "sg:province":"Istanbul",
    "sg:tags":[
        "knitting"
    ],
    "wof:name":"Karaata Tekstil ?rme Ltd.sti.",
    "wof:placetype":"venue"
},
  "geometry": {"coordinates":[28.5548038483,41.0122947693],"type":"Point"}
}