{
  "type": "Feature",
  "properties": {
    "iso:country":"TR",
    "sg:address":"Yeni Yalova Yolu Cad.5 Km Aybey Sok. No: 1 Panayir",
    "sg:city":"Osmangazi",
    "sg:orig_category":"Food Machinies",
    "sg:phone":"+90 224 257 0396",
    "sg:postcode":"16250",
    "sg:province":"Bursa",
    "wof:name":"Aybey Makina Sanayii",
    "wof:placetype":"venue"
},
  "geometry": {"coordinates":[29.0743560791,40.2151756287],"type":"Point"}
}