{
  "type": "Feature",
  "properties": {
    "addr:full":"Nato Yolu Kumru Sok. No:69 \u00dcmraniye Istanbul",
    "addr:housenumber":"no 69",
    "addr:street":"Nato Yolu Kumru Sok.",
    "iso:country":"TR",
    "sg:address":"Nato Yolu Kumru Sok. No:69",
    "sg:city":"\u00dcmraniye",
    "sg:classifiers":[
        {
            "category":"Home & Garden",
            "subcategory":"Hardware",
            "type":"Retail Goods"
        }
    ],
    "sg:phone":"+90 216 314 8324",
    "sg:province":"Istanbul",
    "sg:tags":[
        "store"
    ],
    "wof:name":"Durmaz Vida San. Ve Tic. Ltd.sti.",
    "wof:placetype":"venue"
},
  "geometry": {"coordinates":[28.9861831665,41.0408554077],"type":"Point"}
}