{
  "type": "Feature",
  "properties": {
    "addr:full":"San Mah. Y.sultan Selim Cad. Boz Sok. No:9 4.levent Beyoglu Istanbul 46810",
    "addr:housenumber":"no;4.levent",
    "addr:postcode":"46810",
    "addr:street":"San Mah. Y.Sultan Selim Cad. Boz Sok.;Beyoglu Istanbul",
    "iso:country":"TR",
    "sg:address":"San Mah. Y.sultan Selim Cad. Boz Sok. No:9 4.levent",
    "sg:city":"Beyoglu",
    "sg:classifiers":[
        {
            "category":"Wholesale",
            "subcategory":"Books, Periodicals, & Newspapers",
            "type":"Manufacturing & Wholesale Goods"
        }
    ],
    "sg:phone":"+90 212282990809",
    "sg:postcode":"46810",
    "sg:province":"Istanbul",
    "sg:tags":[
        "house",
        "publishing"
    ],
    "wof:name":"As Matbaacilik San.tic.ltd.",
    "wof:placetype":"venue"
},
  "geometry": {"coordinates":[28.9759254456,41.0123786926],"type":"Point"}
}