{
  "type": "Feature",
  "properties": {
    "addr:full":"Mesrutiyet Cd. Hatay Sk. No:23 D:8 Kocatepe Ke??en Ankara",
    "addr:housenumber":"23 d 8",
    "addr:street":"Mesrutiyet Cd.;Sk. No;Ke ? ? En Ankara",
    "iso:country":"TR",
    "sg:address":"Mesrutiyet Cd. Hatay Sk. No:23 D:8 Kocatepe",
    "sg:city":"Ke??en",
    "sg:classifiers":[
        {
            "category":"Organizations",
            "subcategory":"Membership Organization",
            "type":"Services"
        }
    ],
    "sg:phone":"+90 312 425 4189",
    "sg:province":"Ankara",
    "wof:name":"Saglik Gerec. Uret. Temsil. Dernegi",
    "wof:placetype":"venue"
},
  "geometry": {"coordinates":[32.8584594727,39.9201202393],"type":"Point"}
}