{
  "type": "Feature",
  "properties": {
    "addr:full":"Tersane Cd.arapkayyum Sk.no25 Karak\u00f6y Istanbul",
    "iso:country":"TR",
    "sg:address":"Tersane Cd.arapkayyum Sk.no25",
    "sg:city":"Karak\u00f6y",
    "sg:classifiers":[
        {
            "category":"Marine",
            "type":"Transportation"
        }
    ],
    "sg:phone":"+90 212 244 2737",
    "sg:province":"Istanbul",
    "sg:tags":[
        "shipowner"
    ],
    "wof:name":"Karavelioglu Denizcilik A.s. .",
    "wof:placetype":"venue"
},
  "geometry": {"coordinates":[28.975925,41.012379],"type":"Point"}
}