{
  "type": "Feature",
  "properties": {
    "iso:country":"TR",
    "sg:address":"Ankara Asvalti Tavsanlar Rampasi Dilovasi-gebze",
    "sg:city":"Kartal",
    "sg:orig_category":"General Industrial Products",
    "sg:phone":"+90 2627546149329",
    "sg:postcode":"46000",
    "sg:province":"Kocaeli",
    "wof:name":"Armaplast Polyester San.ve Tic. Ltd.sti.",
    "wof:placetype":"venue"
},
  "geometry": {"coordinates":[29.881521225,40.8532714844],"type":"Point"}
}