{
  "type": "Feature",
  "properties": {
    "addr:full":"Oz-san San. Sitesi 20.blok Yesilyurt Torbali Malatya 35860",
    "addr:postcode":"35860",
    "iso:country":"TR",
    "sg:address":"Oz-san San. Sitesi 20.blok Yesilyurt",
    "sg:city":"Torbali",
    "sg:orig_category":"Non-classified Establishments",
    "sg:phone":"+90 422 238 3695",
    "sg:postcode":"35860",
    "sg:province":"Malatya",
    "wof:name":"Laskap Oto Lastik Kaplama",
    "wof:placetype":"venue"
},
  "geometry": {"coordinates":[38.3195266724,38.3488922119],"type":"Point"}
}