{
  "type": "Feature",
  "properties": {
    "addr:full":"K?ithane Cd. No:125/a Caglayan ?aglayan Istanbul",
    "addr:housenumber":"no;/ a;?",
    "addr:street":"Ithane Cd.;Caglayan",
    "iso:country":"TR",
    "sg:address":"K?ithane Cd. No:125/a Caglayan",
    "sg:city":"?aglayan",
    "sg:classifiers":[
        {
            "category":"Shopping",
            "subcategory":"Stationery & Office Supplies",
            "type":"Retail Goods"
        }
    ],
    "sg:phone":"+90 212 233 0580",
    "sg:province":"Istanbul",
    "sg:tags":[
        "furniture"
    ],
    "wof:name":"Cagin Buro Mob.",
    "wof:placetype":"venue"
},
  "geometry": {"coordinates":[28.9824085236,41.0775985718],"type":"Point"}
}