{
  "type": "Feature",
  "properties": {
    "addr:full":"666.sok.no:43 Ivedik Org.san.ostim/ankara. Gaziosmanpasa Ankara 06700",
    "addr:housenumber":"43",
    "addr:postcode":"06700",
    "addr:street":"Ivedik Org.San.Ostim / Ankara. Gaziosmanpasa",
    "iso:country":"TR",
    "sg:address":"666.sok.no:43 Ivedik Org.san.ostim/ankara.",
    "sg:city":"Gaziosmanpasa",
    "sg:classifiers":[
        {
            "category":"Wholesale",
            "subcategory":"Medical Equipment & Supplies",
            "type":"Manufacturing & Wholesale Goods"
        }
    ],
    "sg:phone":"+90 312 395 5648",
    "sg:postcode":"06700",
    "sg:province":"Ankara",
    "wof:name":"Physio Inc.",
    "wof:placetype":"venue"
},
  "geometry": {"coordinates":[32.8604812622,39.9429283142],"type":"Point"}
}