{
  "type": "Feature",
  "properties": {
    "addr:full":"H?riyet Mh. H?riyet Cd. No:28 Sirinevler A.dudullu Istanbul",
    "addr:housenumber":"?;no 28",
    "addr:street":"Riyet Mh. H;Riyet Cd.",
    "iso:country":"TR",
    "sg:address":"H?riyet Mh. H?riyet Cd. No:28 Sirinevler",
    "sg:city":"A.dudullu",
    "sg:classifiers":[
        {
            "category":"Home & Garden",
            "subcategory":"Kitchen Supply",
            "type":"Retail Goods"
        }
    ],
    "sg:phone":"+90 212 552 4794",
    "sg:province":"Istanbul",
    "sg:tags":[
        "steel",
        "utensil"
    ],
    "wof:name":"Yesiltan Madeni Esya San. Tic. Ltd.",
    "wof:placetype":"venue"
},
  "geometry": {"coordinates":[28.846985,40.999081],"type":"Point"}
}