{
  "type": "Feature",
  "properties": {
    "iso:country":"TR",
    "sg:address":"Cakmak Mah. 23 Nisan Cad.no:3 ?mraniye",
    "sg:city":"Basinevleri",
    "sg:classifiers":[
        {
            "category":"Wholesale",
            "subcategory":"Books, Periodicals, & Newspapers",
            "type":"Manufacturing & Wholesale Goods"
        }
    ],
    "sg:phone":"+90 216 443 4266",
    "sg:postcode":"06010",
    "sg:province":"Istanbul",
    "sg:tags":[
        "house",
        "publishing"
    ],
    "wof:name":"Cantas Ltd.",
    "wof:placetype":"venue"
},
  "geometry": {"coordinates":[28.9759254456,41.0123786926],"type":"Point"}
}