{
  "type": "Feature",
  "properties": {
    "addr:full":"Aksu Cad.no:15 Kartaltepe-bakirk? Kizilay Istanbul 06640",
    "addr:housenumber":"15;?",
    "addr:postcode":"06640",
    "addr:street":"Kartaltepe-Bakirk",
    "iso:country":"TR",
    "sg:address":"Aksu Cad.no:15 Kartaltepe-bakirk?",
    "sg:city":"Kizilay",
    "sg:classifiers":[
        {
            "category":"Shopping",
            "subcategory":"Shoes",
            "type":"Retail Goods"
        }
    ],
    "sg:phone":"+90 212 571 9960",
    "sg:postcode":"06640",
    "sg:province":"Istanbul",
    "wof:name":"Dora Plastik Fab.a.s",
    "wof:placetype":"venue"
},
  "geometry": {"coordinates":[28.884516,40.983349],"type":"Point"}
}