{
  "type": "Feature",
  "properties": {
    "iso:country":"TR",
    "sg:address":"Cami Meydani No:5",
    "sg:city":"Manyas",
    "sg:classifiers":[
        {
            "category":"Food & Beverages",
            "subcategory":"Dairy",
            "type":"Retail Goods"
        }
    ],
    "sg:phone":"+90 266 818 1721",
    "sg:postcode":"10470",
    "sg:province":"Balikesir",
    "sg:tags":[
        "pruducts",
        "milk"
    ],
    "wof:name":"Unal Ciftligi S?t ?r?nleri",
    "wof:placetype":"venue"
},
  "geometry": {"coordinates":[27.8754005432,39.6615219116],"type":"Point"}
}