{
  "type": "Feature",
  "properties": {
    "iso:country":"TR",
    "sg:address":"Olgunlar Sk. No:2/5 Bakanliklar",
    "sg:city":"Findikzade",
    "sg:classifiers":[
        {
            "category":"Wholesale",
            "subcategory":"Medical Equipment & Supplies",
            "type":"Manufacturing & Wholesale Goods"
        }
    ],
    "sg:phone":"+90 312 417 6389",
    "sg:postcode":"34270",
    "sg:province":"Ankara",
    "wof:name":"Behzat Balin",
    "wof:placetype":"venue"
},
  "geometry": {"coordinates":[32.8604812622,39.9429283142],"type":"Point"}
}