{
  "type": "Feature",
  "properties": {
    "iso:country":"TR",
    "sg:address":"Miralay Sefikbey Sokak No:1/1 80090 Gumussuyu Istanbul",
    "sg:city":"Salihli",
    "sg:classifiers":[
        {
            "category":"Autos & Motor Vehicles",
            "subcategory":"Automobile Sales",
            "type":"Retail Goods"
        }
    ],
    "sg:phone":"+90 212 243 1712",
    "sg:postcode":"24600",
    "sg:province":"Istanbul",
    "sg:tags":[
        "equipment",
        "transport"
    ],
    "wof:name":"Madenci Gemi San Ltd Sti",
    "wof:placetype":"venue"
},
  "geometry": {"coordinates":[28.9891204834,41.0379676819],"type":"Point"}
}