{
  "type": "Feature",
  "properties": {
    "iso:country":"TR",
    "sg:address":"Divan Yolu Cad. No:16 Sultanahmet 34450 Eminonu Istanbul",
    "sg:city":"Ikitelli/K\u00fc\u00e7\u00fck\u00e7ekmece",
    "sg:classifiers":[
        {
            "category":"Shopping",
            "subcategory":"Crafts & Fabrics",
            "type":"Retail Goods"
        }
    ],
    "sg:phone":"+90 212 511 6529",
    "sg:postcode":"34670",
    "sg:province":"Istanbul",
    "sg:tags":[
        "linen"
    ],
    "wof:name":"Yurdan Hali Kuyumcu Tur. Ins",
    "wof:placetype":"venue"
},
  "geometry": {"coordinates":[28.9782657623,41.0080604553],"type":"Point"}
}