{
  "type": "Feature",
  "properties": {
    "iso:country":"TR",
    "sg:address":"Mahmutbey Pirireis Mah. K?r?cad. No:20 Kat:5",
    "sg:city":"Bagcilar",
    "sg:classifiers":[
        {
            "category":"Sports & Exercise",
            "subcategory":"Ski Slope",
            "type":"Entertainment"
        }
    ],
    "sg:phone":"+90 21244501767780",
    "sg:postcode":"33115",
    "sg:province":"Istanbul",
    "sg:tags":[
        "wear"
    ],
    "wof:name":"?ztop Konfeksiyon ?r?nleri San. Ve Tic. Ithalat Ihracat A.s.",
    "wof:placetype":"venue"
},
  "geometry": {"coordinates":[28.975925,41.012379],"type":"Point"}
}