{
  "type": "Feature",
  "properties": {
    "iso:country":"TR",
    "sg:address":"I.d.t.m A2 Blok No.395 K.13",
    "sg:city":"Cobancesme",
    "sg:classifiers":[
        {
            "category":"Freight",
            "type":"Transportation"
        }
    ],
    "sg:phone":"+90 212 465 6070",
    "sg:postcode":"34196",
    "sg:province":"Istanbul",
    "sg:tags":[
        "cargo",
        "air"
    ],
    "wof:name":"Ekol Hava Kargo Tasimacilik Ltd.sti.",
    "wof:placetype":"venue"
},
  "geometry": {"coordinates":[28.9089794159,41.0306739807],"type":"Point"}
}