{
  "type": "Feature",
  "properties": {
    "iso:country":"TR",
    "sg:address":"Cumh. Cd. Yesilyurt Apt. No:3",
    "sg:city":"Kartal",
    "sg:classifiers":[
        {
            "category":"Shopping",
            "subcategory":"Computers & Home Electronics",
            "type":"Retail Goods"
        }
    ],
    "sg:phone":"+90 216 353 5032",
    "sg:postcode":"46000",
    "sg:province":"Istanbul",
    "sg:tags":[
        "animal"
    ],
    "wof:name":"Metsel Akvaryum Ve Kus Galerisi",
    "wof:placetype":"venue"
},
  "geometry": {"coordinates":[28.9861831665,41.0408554077],"type":"Point"}
}