{
  "type": "Feature",
  "properties": {
    "iso:country":"TR",
    "sg:address":"Esentepe In??cd. No:159 Kartal",
    "sg:city":"Yukari Dudullu",
    "sg:classifiers":[
        {
            "category":"Manufacturing",
            "subcategory":"Rubber & Plastics",
            "type":"Manufacturing & Wholesale Goods"
        }
    ],
    "sg:phone":"+90 212 389 2209",
    "sg:postcode":"34776",
    "sg:province":"Istanbul",
    "sg:tags":[
        "industry"
    ],
    "wof:name":"Alpsan Al?minyum Plastik Profil San. Tic. A.s.",
    "wof:placetype":"venue"
},
  "geometry": {"coordinates":[29.2145366669,40.9441184998],"type":"Point"}
}