{
  "type": "Feature",
  "properties": {
    "iso:country":"TR",
    "sg:address":"Demirtas Org.san. Bolg. Gul Sok.no:11",
    "sg:city":"Sultanhamam",
    "sg:classifiers":[
        {
            "category":"Home & Garden",
            "subcategory":"Home Furnishings",
            "type":"Retail Goods"
        }
    ],
    "sg:phone":"+90 224261061416",
    "sg:province":"Bursa",
    "sg:tags":[
        "curtaining",
        "-",
        "upholstering"
    ],
    "wof:name":"Erkoc Tekstil San.tic.a.s.",
    "wof:placetype":"venue"
},
  "geometry": {"coordinates":[29.058004,40.194756],"type":"Point"}
}