{
  "type": "Feature",
  "properties": {
    "iso:country":"TR",
    "sg:address":"Abide-i H?riyet Cad 125",
    "sg:city":"Sisli",
    "sg:classifiers":[
        {
            "category":"Banks & Credit Unions",
            "subcategory":"Bank",
            "type":"Services"
        }
    ],
    "sg:phone":"+90 212 224 9494",
    "sg:postcode":"65710",
    "sg:province":"80220",
    "wof:name":"Derbank As",
    "wof:placetype":"venue"
},
  "geometry": {"coordinates":[28.973923,41.054859],"type":"Point"}
}