{
  "type": "Feature",
  "properties": {
    "iso:country":"TR",
    "sg:address":"L?eburgaz",
    "sg:city":"L?eburgaz",
    "sg:classifiers":[
        {
            "category":"Manufacturing",
            "subcategory":"Glass & Minerals",
            "type":"Manufacturing & Wholesale Goods"
        }
    ],
    "sg:phone":"+90 288 417 3126",
    "sg:province":"Kirklareli",
    "sg:tags":[
        "glassware"
    ],
    "wof:name":"Cam Pazarlama A.s.",
    "wof:placetype":"venue"
},
  "geometry": {"coordinates":[27.3535003662,41.4056015015],"type":"Point"}
}