{
  "type": "Feature",
  "properties": {
    "iso:country":"TR",
    "sg:address":"Dilek",
    "sg:city":"Savstepe",
    "sg:classifiers":[
        {
            "category":"Farming",
            "subcategory":"Farm & Veterinary Services",
            "type":"Manufacturing & Wholesale Goods"
        }
    ],
    "sg:phone":"+90 442 398 2180",
    "sg:province":"Malatya",
    "sg:tags":[
        "veterinarian"
    ],
    "wof:name":"Mehmet Donmez Dilik Ved. Kli.",
    "wof:placetype":"venue"
},
  "geometry": {"coordinates":[38.2489013672,38.4416999817],"type":"Point"}
}