{
  "type": "Feature",
  "properties": {
    "addr:full":"Olgunlar Sk. No:20/24 Bakanliklar Ankara",
    "addr:housenumber":"20 / 24",
    "addr:street":"Olgunlar Sk. No;Bakanliklar",
    "iso:country":"TR",
    "sg:address":"Olgunlar Sk. No:20/24",
    "sg:city":"Bakanliklar",
    "sg:classifiers":[
        {
            "category":"Utilities",
            "subcategory":"Electric",
            "type":"Services"
        }
    ],
    "sg:phone":"+90 312 417 4961",
    "sg:province":"Ankara",
    "sg:tags":[
        "energy",
        "solar"
    ],
    "wof:name":"Ete Enerji Tesisat End?stri San. Tic. Ltd.",
    "wof:placetype":"venue"
},
  "geometry": {"coordinates":[32.857182,39.915054],"type":"Point"}
}