{
  "type": "Feature",
  "properties": {
    "addr:full":"8.cad. 34/3 Emek Osmangazi Ankara 16220",
    "addr:housenumber":"34 / 3",
    "addr:postcode":"16220",
    "addr:street":"Emek",
    "iso:country":"TR",
    "sg:address":"8.cad. 34/3 Emek",
    "sg:city":"Osmangazi",
    "sg:classifiers":[
        {
            "category":"Wholesale",
            "subcategory":"Medical Equipment & Supplies",
            "type":"Manufacturing & Wholesale Goods"
        }
    ],
    "sg:phone":"+90 312 222 2210",
    "sg:postcode":"16220",
    "sg:province":"Ankara",
    "sg:tags":[
        "material"
    ],
    "wof:name":"Tolman Ic Ve Dis Tic.ltd.sti.",
    "wof:placetype":"venue"
},
  "geometry": {"coordinates":[32.7859268188,39.9745483398],"type":"Point"}
}