{
  "type": "Feature",
  "properties": {
    "addr:full":"Hacibey Mah. Cesmeli 2 Nolu Sok. No:5 Alasehir Manisa 45600",
    "addr:housenumber":"2;no 5",
    "addr:postcode":"45600",
    "addr:street":"Hacibey Mah. Cesmeli;Nolu Sok.;Alasehir Manisa",
    "iso:country":"TR",
    "sg:address":"Hacibey Mah. Cesmeli 2 Nolu Sok. No:5",
    "sg:city":"Alasehir",
    "sg:classifiers":[
        {
            "category":"Manufacturing",
            "subcategory":"Food",
            "type":"Manufacturing & Wholesale Goods"
        }
    ],
    "sg:phone":"+90 236 654 3248",
    "sg:postcode":"45600",
    "sg:province":"Manisa",
    "sg:tags":[
        "wholesaler"
    ],
    "wof:name":"Sartek Import-export",
    "wof:placetype":"venue"
},
  "geometry": {"coordinates":[27.4297008514,38.6222000122],"type":"Point"}
}