{
  "type": "Feature",
  "properties": {
    "addr:full":"1 San.sitesi 2829. Sok.no:45/a Izmit Izmir 41000",
    "addr:housenumber":"1;45 / a",
    "addr:postcode":"2829;41000",
    "addr:street":"San.Sitesi;Sok.No;Izmit Izmir",
    "iso:country":"TR",
    "sg:address":"1 San.sitesi 2829. Sok.no:45/a",
    "sg:city":"Izmit",
    "sg:classifiers":[
        {
            "category":"Building & Trades",
            "subcategory":"Plumbing",
            "type":"Services"
        }
    ],
    "sg:phone":"+90 232 457 3789",
    "sg:postcode":"41000",
    "sg:province":"Izmir",
    "sg:tags":[
        "filter",
        "industry"
    ],
    "wof:name":"Garanti Filitre San.ltd.",
    "wof:placetype":"venue"
},
  "geometry": {"coordinates":[27.1296863556,38.4186973572],"type":"Point"}
}