{
  "type": "Feature",
  "properties": {
    "iso:country":"TR",
    "sg:address":"129/7 Sokak No:18 Doganlar Mahallesi 35050",
    "sg:city":"Karsiyaka",
    "sg:classifiers":[
        {
            "category":"Utilities",
            "subcategory":"Electric",
            "type":"Services"
        }
    ],
    "sg:phone":"+90 232 388 9446",
    "sg:postcode":"01900",
    "sg:province":"Izmir",
    "sg:tags":[
        "energy",
        "solar"
    ],
    "wof:name":"Akin Enerji Insaat Makina Sanayi Ve Ticaret Limited",
    "wof:placetype":"venue"
},
  "geometry": {"coordinates":[27.250257,38.46204],"type":"Point"}
}