{
  "type": "Feature",
  "properties": {
    "addr:full":"Murbasan Sok. Koza Ismrk. A- Blok Balmumcu Niksar Istanbul 60600",
    "addr:housenumber":"koza;a blok balmumcu",
    "addr:postcode":"60600",
    "addr:street":"Murbasan Sok.",
    "iso:country":"TR",
    "sg:address":"Murbasan Sok. Koza Ismrk. A- Blok Balmumcu",
    "sg:city":"Niksar",
    "sg:classifiers":[
        {
            "category":"Insurance",
            "subcategory":"Hazard Insurance",
            "type":"Services"
        }
    ],
    "sg:phone":"+90 212 288 1245",
    "sg:postcode":"60600",
    "sg:province":"Istanbul",
    "wof:name":"Ticaret Sigorta A.s",
    "wof:placetype":"venue"
},
  "geometry": {"coordinates":[28.9861831665,41.0408554077],"type":"Point"}
}