{
  "type": "Feature",
  "properties": {
    "addr:full":"Kocatepe Mah.5.sokak No:16 Bayrampasa Istanbul 34145",
    "addr:housenumber":"no 16",
    "addr:postcode":"34145",
    "addr:street":"Istanbul",
    "iso:country":"TR",
    "sg:address":"Kocatepe Mah.5.sokak No:16",
    "sg:city":"Bayrampasa",
    "sg:classifiers":[
        {
            "category":"Train Station",
            "subcategory":"Light Rail",
            "type":"Transportation"
        }
    ],
    "sg:phone":"+90 212 640 1717",
    "sg:postcode":"34145",
    "sg:province":"Istanbul",
    "sg:tags":[
        "nail",
        "wire"
    ],
    "wof:name":"?obanoglu Kafes Tel ?rg?ve ?it Sistemelri",
    "wof:placetype":"venue"
},
  "geometry": {"coordinates":[28.8944892883,41.0527191162],"type":"Point"}
}