{
  "type": "Feature",
  "properties": {
    "iso:country":"TR",
    "sg:address":"Atmaca Sok. No:1/d-e Diskapi",
    "sg:city":"Karak\u00f6y",
    "sg:orig_category":"Non-classified Establishments",
    "sg:phone":"+90 31231131763112",
    "sg:postcode":"80030",
    "sg:province":"Ankara",
    "wof:name":"Alphan-arslan Yaman",
    "wof:placetype":"venue"
},
  "geometry": {"coordinates":[32.8604812622,39.9429283142],"type":"Point"}
}