{
  "type": "Feature",
  "properties": {
    "iso:country":"TR",
    "sg:address":"Atat?rk Caddesi Selamoglu ?arsisi No:1/115",
    "sg:city":"K???kyali",
    "sg:classifiers":[
        {
            "category":"Travel",
            "subcategory":"Travel Agent",
            "type":"Entertainment"
        }
    ],
    "sg:phone":"+90 417780708",
    "sg:province":"Istanbul",
    "sg:tags":[
        "agency",
        "tourism"
    ],
    "wof:name":"?eken Turizm",
    "wof:placetype":"venue"
},
  "geometry": {"coordinates":[28.9861831665,41.0408554077],"type":"Point"}
}