{
  "type": "Feature",
  "properties": {
    "addr:full":"Aksaray Cd. No:2/b Laleli Kazasker Istanbul",
    "iso:country":"TR",
    "sg:address":"Aksaray Cd. No:2/b Laleli",
    "sg:city":"Kazasker",
    "sg:classifiers":[
        {
            "category":"Shopping",
            "subcategory":"Photographic Equipment",
            "type":"Retail Goods"
        }
    ],
    "sg:phone":"+90 212 526 7806",
    "sg:province":"Istanbul",
    "sg:tags":[
        "photo"
    ],
    "wof:name":"Istanbul Color Foto Laboratuvar",
    "wof:placetype":"venue"
},
  "geometry": {"coordinates":[28.9563121796,41.0088500977],"type":"Point"}
}