{
  "type": "Feature",
  "properties": {
    "iso:country":"TR",
    "sg:address":"Ankara Cd. No:95 Sirkeci",
    "sg:city":"Ikitelli/K\u00fc\u00e7\u00fck\u00e7ekmece",
    "sg:orig_category":"Printinh House",
    "sg:phone":"+90 212 514 0612",
    "sg:postcode":"34670",
    "sg:province":"Istanbul",
    "wof:name":"Inkilap Katibevi Yayincilik San. Tic. A.s.",
    "wof:placetype":"venue"
},
  "geometry": {"coordinates":[28.9762134552,41.0155601501],"type":"Point"}
}