{
  "type": "Feature",
  "properties": {
    "addr:full":"Mustafa Bey Cad.no:1 Alsancak Izmir 01365",
    "addr:housenumber":"1",
    "addr:postcode":"01365",
    "addr:street":"Cad.No",
    "iso:country":"TR",
    "sg:address":"Mustafa Bey Cad.no:1",
    "sg:city":"Alsancak",
    "sg:orig_category":"Hotels: Motels",
    "sg:phone":"+90 232 441 0963",
    "sg:postcode":"01365",
    "sg:province":"Izmir",
    "wof:name":"Savranoglu Tur.tes.",
    "wof:placetype":"venue"
},
  "geometry": {"coordinates":[27.1423015594,38.4251480103],"type":"Point"}
}