{
  "type": "Feature",
  "properties": {
    "iso:country":"TR",
    "sg:address":"Horasan Sk. No:24 G.osmanpasa",
    "sg:city":"Merkez",
    "sg:classifiers":[
        {
            "category":"Banks & Credit Unions",
            "subcategory":"Investment Brokerage",
            "type":"Services"
        }
    ],
    "sg:phone":"+90 312 437 6098",
    "sg:postcode":"20100",
    "sg:province":"Ankara",
    "sg:tags":[
        "-",
        "export",
        "import"
    ],
    "wof:name":"Doruk Dis Tic. A.s.",
    "wof:placetype":"venue"
},
  "geometry": {"coordinates":[32.8604812622,39.9429283142],"type":"Point"}
}