{
  "type": "Feature",
  "properties": {
    "iso:country":"TR",
    "sg:address":"Cinnah Cad Enisbehic",
    "sg:city":"Ankara",
    "sg:classifiers":[
        {
            "category":"Banks & Credit Unions",
            "subcategory":"Bank",
            "type":"Services"
        }
    ],
    "sg:phone":"+90 312 440 9927",
    "sg:postcode":"63570",
    "sg:province":"06690",
    "wof:name":"T?kiye T??c?er, Bankasi Yasarbank As",
    "wof:placetype":"venue"
},
  "geometry": {"coordinates":[32.85553,39.894547],"type":"Point"}
}