{
  "type": "Feature",
  "properties": {
    "addr:full":"928.sok. No:17 Mezarlikbasi Beyazit Izmir 65400",
    "addr:housenumber":"no 17",
    "addr:postcode":"65400",
    "iso:country":"TR",
    "sg:address":"928.sok. No:17 Mezarlikbasi",
    "sg:city":"Beyazit",
    "sg:classifiers":[
        {
            "category":"Shopping",
            "subcategory":"Jewelry",
            "type":"Retail Goods"
        }
    ],
    "sg:phone":"+90 232 484 1805",
    "sg:postcode":"65400",
    "sg:province":"Izmir",
    "sg:tags":[
        "-",
        "golg-silver"
    ],
    "wof:name":"Karya Alyans Jevellery Co.",
    "wof:placetype":"venue"
},
  "geometry": {"coordinates":[27.1296863556,38.4186973572],"type":"Point"}
}