{
  "type": "Feature",
  "properties": {
    "addr:full":"Incilipinar Mah Osmanli Is Mrk Kat 1 No 59 Sehitkamil Gaziantep 27000",
    "addr:housenumber":"kat 1 no 59",
    "addr:postcode":"27000",
    "addr:street":"Incilipinar Mah Osmanli Is Mrk;Sehitkamil Gaziantep",
    "iso:country":"TR",
    "sg:address":"Incilipinar Mah Osmanli Is Mrk Kat 1 No 59",
    "sg:city":"Sehitkamil",
    "sg:orig_category":"Radio-tv Electronics",
    "sg:phone":"+90 342 215 3034",
    "sg:postcode":"27000",
    "sg:province":"Gaziantep",
    "wof:name":"Megaprodiksiyon",
    "wof:placetype":"venue"
},
  "geometry": {"coordinates":[37.3761024475,37.0629463196],"type":"Point"}
}