{
  "type": "Feature",
  "properties": {
    "addr:full":"Mithatpasa Cad. No:610/4 Kucukyali Izmir 35280",
    "addr:housenumber":"610 / 4",
    "addr:postcode":"35280",
    "addr:street":"Mithatpasa Cad. No;Kucukyali Izmir",
    "iso:country":"TR",
    "sg:address":"Mithatpasa Cad. No:610/4",
    "sg:city":"Kucukyali",
    "sg:classifiers":[
        {
            "category":"Wholesale",
            "subcategory":"Machinery & Supplies",
            "type":"Manufacturing & Wholesale Goods"
        }
    ],
    "sg:phone":"+90 232 231 9065",
    "sg:postcode":"35280",
    "sg:province":"Izmir",
    "sg:tags":[
        "agricultural"
    ],
    "wof:name":"Guvenli Tarim Ve Makina End. Ltd.sti.",
    "wof:placetype":"venue"
},
  "geometry": {"coordinates":[27.1058311462,38.4070243835],"type":"Point"}
}