{
  "type": "Feature",
  "properties": {
    "addr:full":"Demirhendek Cd. No:123 Siteler Etiler Ankara 07010",
    "addr:housenumber":"no;siteler etiler",
    "addr:postcode":"07010",
    "addr:street":"Demirhendek Cd.",
    "iso:country":"TR",
    "sg:address":"Demirhendek Cd. No:123 Siteler",
    "sg:city":"Etiler",
    "sg:classifiers":[
        {
            "category":"Manufacturing",
            "subcategory":"Wood Products",
            "type":"Manufacturing & Wholesale Goods"
        }
    ],
    "sg:phone":"+90 312 349 0908",
    "sg:postcode":"07010",
    "sg:province":"Ankara",
    "sg:tags":[
        "forest"
    ],
    "wof:name":"Acarlar Kereste Ticaret",
    "wof:placetype":"venue"
},
  "geometry": {"coordinates":[32.9006652832,39.9557991028],"type":"Point"}
}