{
  "type": "Feature",
  "properties": {
    "addr:full":"Bayar Cad. No:103/a Demirkaya Is Merkezi Kat:6 Kozyatagi Ikitelli/K\u00fc\u00e7\u00fck\u00e7ekmece Istanbul 34670",
    "addr:housenumber":"103 / a;kat 6",
    "addr:postcode":"34670",
    "addr:street":"Bayar Cad. No;Demirkaya",
    "iso:country":"TR",
    "sg:address":"Bayar Cad. No:103/a Demirkaya Is Merkezi Kat:6 Kozyatagi",
    "sg:city":"Ikitelli/K\u00fc\u00e7\u00fck\u00e7ekmece",
    "sg:classifiers":[
        {
            "category":"Manufacturing",
            "subcategory":"Chemicals & Compounds",
            "type":"Manufacturing & Wholesale Goods"
        }
    ],
    "sg:phone":"+90 216 361 9713",
    "sg:postcode":"34670",
    "sg:province":"Istanbul",
    "sg:tags":[
        "industry"
    ],
    "wof:name":"Ktm Kimyevi Maddeler A.s.",
    "wof:placetype":"venue"
},
  "geometry": {"coordinates":[28.9861831665,41.0408554077],"type":"Point"}
}