{
  "type": "Feature",
  "properties": {
    "iso:country":"TR",
    "sg:address":"Veli Efendi Mah. Prof. Turan Gunes Cad. No:188",
    "sg:city":"Zeytinburnu",
    "sg:classifiers":[
        {
            "category":"Manufacturing",
            "subcategory":"Textiles",
            "type":"Manufacturing & Wholesale Goods"
        }
    ],
    "sg:phone":"+90 212 665 5049",
    "sg:postcode":"41000",
    "sg:province":"Istanbul",
    "sg:tags":[
        "product"
    ],
    "wof:name":"Hazpa Tekstil Ihr. Ve Paz. A.s.",
    "wof:placetype":"venue"
},
  "geometry": {"coordinates":[28.9759254456,41.0123786926],"type":"Point"}
}