{
  "type": "Feature",
  "properties": {
    "addr:full":"Cemal Y. Tosyali Cd. No:58 Vefa G?g?en Istanbul",
    "addr:housenumber":"no 58;? g ?",
    "addr:street":"Cemal Y. Tosyali Cd.;Vefa G",
    "iso:country":"TR",
    "sg:address":"Cemal Y. Tosyali Cd. No:58 Vefa",
    "sg:city":"G?g?en",
    "sg:classifiers":[
        {
            "category":"Manufacturing",
            "subcategory":"Rubber & Plastics",
            "type":"Manufacturing & Wholesale Goods"
        }
    ],
    "sg:phone":"+90 212 511 5715",
    "sg:province":"Istanbul",
    "sg:tags":[
        "industry"
    ],
    "wof:name":"Polikur Plastik S?nger San. Ltd.",
    "wof:placetype":"venue"
},
  "geometry": {"coordinates":[28.9603042603,41.0173912048],"type":"Point"}
}