{
  "type": "Feature",
  "properties": {
    "addr:full":"Yeni Yol Ramazanoglu Sit. 2. Blok No:9/11 Bayrampasa Ikitelli/K\u00fc\u00e7\u00fck\u00e7ekmece Istanbul 34670",
    "addr:housenumber":"2 blok no 9 / 11",
    "addr:postcode":"34670",
    "addr:street":"Sit.",
    "iso:country":"TR",
    "sg:address":"Yeni Yol Ramazanoglu Sit. 2. Blok No:9/11 Bayrampasa",
    "sg:city":"Ikitelli/K\u00fc\u00e7\u00fck\u00e7ekmece",
    "sg:classifiers":[
        {
            "category":"Home & Garden",
            "subcategory":"Kitchen Supply",
            "type":"Retail Goods"
        }
    ],
    "sg:phone":"+90 212 578 6277",
    "sg:postcode":"34670",
    "sg:province":"Istanbul",
    "sg:tags":[
        "steel",
        "utensil"
    ],
    "wof:name":"Ahu Madeni Esya San.",
    "wof:placetype":"venue"
},
  "geometry": {"coordinates":[28.975925,41.012379],"type":"Point"}
}