{
  "type": "Feature",
  "properties": {
    "addr:full":"Dolapdere Cd. No:155 Pangalti Istanbul 34373",
    "addr:housenumber":"no",
    "addr:postcode":"34373",
    "addr:street":"Dolapdere Cd.",
    "iso:country":"TR",
    "sg:address":"Dolapdere Cd. No:155",
    "sg:city":"Pangalti",
    "sg:classifiers":[
        {
            "category":"Utilities",
            "subcategory":"Electric",
            "type":"Services"
        }
    ],
    "sg:phone":"+90 212 230 5861",
    "sg:postcode":"34373",
    "sg:province":"Istanbul",
    "sg:tags":[
        "energy",
        "solar"
    ],
    "wof:name":"Man Enerji Sistem Ltd.",
    "wof:placetype":"venue"
},
  "geometry": {"coordinates":[28.981224,41.042233],"type":"Point"}
}