{
  "type": "Feature",
  "properties": {
    "addr:full":"167.sok.no:6/b Kemalpasa Izmir 01340",
    "addr:housenumber":"6 / b",
    "addr:postcode":"01340",
    "addr:street":"Kemalpasa Izmir",
    "iso:country":"TR",
    "sg:address":"167.sok.no:6/b",
    "sg:city":"Kemalpasa",
    "sg:classifiers":[
        {
            "category":"Farming",
            "subcategory":"Farm & Veterinary Services",
            "type":"Manufacturing & Wholesale Goods"
        }
    ],
    "sg:phone":"+90 232 878 9172",
    "sg:postcode":"01340",
    "sg:province":"Izmir",
    "sg:tags":[
        "veterinarian"
    ],
    "wof:name":"Bativet Ltd.",
    "wof:placetype":"venue"
},
  "geometry": {"coordinates":[27.1966400146,38.4406509399],"type":"Point"}
}