{
  "type": "Feature",
  "properties": {
    "addr:full":"Ko?bey Sk. Gazi Ismerk. No:40/1 Aksaray Rami Istanbul 34140",
    "addr:housenumber":"?;1",
    "addr:postcode":"34140",
    "addr:street":"Ko;No 40 /",
    "iso:country":"TR",
    "sg:address":"Ko?bey Sk. Gazi Ismerk. No:40/1 Aksaray",
    "sg:city":"Rami",
    "sg:classifiers":[
        {
            "category":"Manufacturing",
            "subcategory":"Rubber & Plastics",
            "type":"Manufacturing & Wholesale Goods"
        }
    ],
    "sg:phone":"+90 212 529 5690",
    "sg:postcode":"34140",
    "sg:province":"Istanbul",
    "sg:tags":[
        "industry"
    ],
    "wof:name":"?zaydin Plastik Hirdavat San. Tic. Ltd. Sti.",
    "wof:placetype":"venue"
},
  "geometry": {"coordinates":[28.8713321686,40.9776382446],"type":"Point"}
}