{
  "type": "Feature",
  "properties": {
    "iso:country":"TR",
    "sg:address":"2.org.san.dursun Bak Bul.",
    "sg:city":"Baspinar",
    "sg:classifiers":[
        {
            "category":"Food & Beverages",
            "subcategory":"Candy",
            "type":"Retail Goods"
        }
    ],
    "sg:phone":"+90 342 337 2461",
    "sg:postcode":"07800",
    "sg:province":"Gaziantep",
    "sg:tags":[
        "biscuit-chocolate-candy"
    ],
    "wof:name":"Degirmenci Gida San.tic.ltd.sti.",
    "wof:placetype":"venue"
},
  "geometry": {"coordinates":[37.376102,37.062946],"type":"Point"}
}