{
  "type": "Feature",
  "properties": {
    "addr:full":"Salih Sakarya Ipsala Edirne 22400",
    "addr:postcode":"22400",
    "addr:street":"Edirne",
    "iso:country":"TR",
    "sg:address":"Salih Sakarya",
    "sg:city":"Ipsala",
    "sg:classifiers":[
        {
            "category":"Government",
            "subcategory":"Office",
            "type":"Public Place"
        }
    ],
    "sg:phone":"+90 284 686 9024",
    "sg:postcode":"22400",
    "sg:province":"Edirne",
    "sg:tags":[
        "municipality"
    ],
    "wof:name":"Haci Belediye Baskani",
    "wof:placetype":"venue"
},
  "geometry": {"coordinates":[28.9072189331,41.0540084839],"type":"Point"}
}