{
  "type": "Feature",
  "properties": {
    "addr:full":"Koop. Mah. Nihat Aykut Cd. No:36 Eminonu Siirt",
    "addr:housenumber":"no 36",
    "addr:street":"Koop. Mah. Nihat Aykut Cd.;Eminonu",
    "iso:country":"TR",
    "sg:address":"Koop. Mah. Nihat Aykut Cd. No:36",
    "sg:city":"Eminonu",
    "sg:orig_category":"Carpet-kilim-blanket",
    "sg:phone":"+90 484 223 6058",
    "sg:province":"Siirt",
    "wof:name":"Siirt Kilim Ve Battaniyeleri Online",
    "wof:placetype":"venue"
},
  "geometry": {"coordinates":[41.9430389404,37.9270439148],"type":"Point"}
}