{
  "type": "Feature",
  "properties": {
    "iso:country":"TR",
    "sg:address":"Hurriyet Mah. Hurriyet Cad. Sedef Sok.no:9",
    "sg:city":"Yenibosna",
    "sg:classifiers":[
        {
            "category":"Manufacturing",
            "subcategory":"Glass & Minerals",
            "type":"Manufacturing & Wholesale Goods"
        }
    ],
    "sg:phone":"+90 212 552 4913",
    "sg:postcode":"43270",
    "sg:province":"Istanbul",
    "sg:tags":[
        "glass-mirror"
    ],
    "wof:name":"Ak-san Bombe Cam Sanayi",
    "wof:placetype":"venue"
},
  "geometry": {"coordinates":[28.8354530334,41.0275192261],"type":"Point"}
}