{
  "type": "Feature",
  "properties": {
    "iso:country":"TR",
    "sg:address":"San. Mh. Sultan Selim Cd. No:56/5 4.levent",
    "sg:city":"\u00dcmraniye",
    "sg:classifiers":[
        {
            "category":"Manufacturing",
            "subcategory":"Rubber & Plastics",
            "type":"Manufacturing & Wholesale Goods"
        }
    ],
    "sg:phone":"+90 212 268 6936",
    "sg:province":"Istanbul",
    "sg:tags":[
        "industry"
    ],
    "wof:name":"Kipsas Kimya Plastik San. Tic. A.s.",
    "wof:placetype":"venue"
},
  "geometry": {"coordinates":[28.9813518524,41.0773696899],"type":"Point"}
}