{
  "type": "Feature",
  "properties": {
    "iso:country":"TR",
    "sg:address":"K.s.s.d. Blok 20 Nolu Cad. No:1-2",
    "sg:city":"1.sanayi",
    "sg:classifiers":[
        {
            "category":"Wholesale",
            "subcategory":"Auto Parts",
            "type":"Manufacturing & Wholesale Goods"
        }
    ],
    "sg:phone":"+90 342235284849",
    "sg:province":"Gaziantep",
    "sg:tags":[
        "spare"
    ],
    "wof:name":"Lasparsan Kaucuk San.tic.ltd.sti.",
    "wof:placetype":"venue"
},
  "geometry": {"coordinates":[37.4416732788,36.9459457397],"type":"Point"}
}