{
  "type": "Feature",
  "properties": {
    "iso:country":"TR",
    "sg:address":"M. Gandi Cd. No:104/7 G.osmanpasa",
    "sg:city":"K??cekmece",
    "sg:orig_category":"Scavening Services",
    "sg:phone":"+90 312 447 0514",
    "sg:postcode":"34670",
    "sg:province":"Ankara",
    "wof:name":"Melissa Tic. Turizm Ltd. Sti.",
    "wof:placetype":"venue"
},
  "geometry": {"coordinates":[32.856033,39.943874],"type":"Point"}
}