{
  "type": "Feature",
  "properties": {
    "iso:country":"TR",
    "sg:address":"Kale Mah. Ziya Gokalp Cad. No:3/10 Gazi Cad. No:176/b",
    "sg:city":"Sihhiye",
    "sg:classifiers":[
        {
            "category":"Shopping",
            "subcategory":"Clothing, Apparel, & Fashions",
            "type":"Retail Goods"
        }
    ],
    "sg:phone":"+90 362 435 2730",
    "sg:postcode":"06410",
    "sg:province":"Samsun",
    "sg:tags":[
        "woman",
        "wear"
    ],
    "wof:name":"Siva Konfeksiyon",
    "wof:placetype":"venue"
},
  "geometry": {"coordinates":[36.33152771,41.2921676636],"type":"Point"}
}