{
  "type": "Feature",
  "properties": {
    "iso:country":"TR",
    "sg:address":"Recep Peker Cad. ??apilar Ishani No:2/11",
    "sg:city":"Merkez",
    "sg:classifiers":[
        {
            "category":"Banks & Credit Unions",
            "subcategory":"Investment Brokerage",
            "type":"Services"
        }
    ],
    "sg:phone":"+90 242 244 8207",
    "sg:postcode":"07100",
    "sg:province":"Antalya",
    "sg:tags":[
        "line",
        "air"
    ],
    "wof:name":"Last Minute Flight Center",
    "wof:placetype":"venue"
},
  "geometry": {"coordinates":[30.7134380341,36.8814849854],"type":"Point"}
}