{
  "type": "Feature",
  "properties": {
    "iso:country":"TR",
    "sg:address":"Karapinar Koyu",
    "sg:city":"Pamukova",
    "sg:classifiers":[
        {
            "category":"Farming",
            "subcategory":"Farm",
            "type":"Manufacturing & Wholesale Goods"
        }
    ],
    "sg:phone":"+90 264 551 5150",
    "sg:postcode":"54900",
    "sg:province":"Sakarya",
    "sg:tags":[
        "agricultural",
        "product"
    ],
    "wof:name":"Karapinar Tarim",
    "wof:placetype":"venue"
},
  "geometry": {"coordinates":[30.3022174835,40.851348877],"type":"Point"}
}