{
  "type": "Feature",
  "properties": {
    "addr:full":"Org.san.b?g. Cerkezk? Tekirdag",
    "iso:country":"TR",
    "sg:address":"Org.san.b?g.",
    "sg:city":"Cerkezk?",
    "sg:classifiers":[
        {
            "category":"Manufacturing",
            "subcategory":"Textiles",
            "type":"Manufacturing & Wholesale Goods"
        }
    ],
    "sg:phone":"+90 282 716 4493",
    "sg:province":"Tekirdag",
    "sg:tags":[
        "sizing",
        "dye"
    ],
    "wof:name":"Flokser Tekstil A.s.",
    "wof:placetype":"venue"
},
  "geometry": {"coordinates":[27.4093494415,41.053478241],"type":"Point"}
}