{
  "type": "Feature",
  "properties": {
    "addr:full":"?eve Sk. No:16/1 ?ankaya Maltepe Ankara 34843",
    "addr:housenumber":"?;16 / 1 ?",
    "addr:postcode":"34843",
    "addr:street":"Eve Sk. No;Ankaya Maltepe Ankara",
    "iso:country":"TR",
    "sg:address":"?eve Sk. No:16/1 ?ankaya",
    "sg:city":"Maltepe",
    "sg:classifiers":[
        {
            "category":"Banks & Credit Unions",
            "subcategory":"Investment Brokerage",
            "type":"Services"
        }
    ],
    "sg:phone":"+90 312 467 2002",
    "sg:postcode":"34843",
    "sg:province":"Ankara",
    "sg:tags":[
        "-",
        "export",
        "import"
    ],
    "wof:name":"Sir William Halcrow And Partners Ltd. Sti.",
    "wof:placetype":"venue"
},
  "geometry": {"coordinates":[32.8604812622,39.9429283142],"type":"Point"}
}