{
  "type": "Feature",
  "properties": {
    "iso:country":"TR",
    "sg:address":"Akyol Sokak No:18/2 Haci Izzet Pasa Sokak Rota Apt.setustu 80040 Kabatas Istanbul",
    "sg:city":"Atasehir",
    "sg:classifiers":[
        {
            "category":"Travel",
            "subcategory":"Travel Agent",
            "type":"Entertainment"
        }
    ],
    "sg:phone":"+90 212 243 4220",
    "sg:postcode":"81120",
    "sg:province":"Istanbul",
    "sg:tags":[
        "business"
    ],
    "wof:name":"Afeks Uluslar Arasi Ticari Fuarlar As",
    "wof:placetype":"venue"
},
  "geometry": {"coordinates":[28.975925,41.012379],"type":"Point"}
}