{
  "type": "Feature",
  "properties": {
    "iso:country":"TR",
    "sg:address":"Yalova Yolu 3. Km Gemlik",
    "sg:city":"Iskenderun",
    "sg:classifiers":[
        {
            "category":"Mining & Drilling",
            "type":"Manufacturing & Wholesale Goods"
        }
    ],
    "sg:phone":"+90 224 514 0060",
    "sg:postcode":"31200",
    "sg:province":"Bursa",
    "sg:tags":[
        "industry",
        "mine"
    ],
    "wof:name":"Aydin Madencilik Insaat Asfalt Dis.tic. Ltd. Sti.",
    "wof:placetype":"venue"
},
  "geometry": {"coordinates":[29.0580043793,40.1947555542],"type":"Point"}
}