{
  "type": "Feature",
  "properties": {
    "addr:full":"Merkez Sanayi Bolgesi 5.cad. 18.sok. No:32/a \u00dcmraniye Kayseri 34776",
    "addr:housenumber":"5.cad 18.sok no 32 / a",
    "addr:postcode":"34776",
    "addr:street":"Merkez Sanayi Bolgesi",
    "iso:country":"TR",
    "sg:address":"Merkez Sanayi Bolgesi 5.cad. 18.sok. No:32/a",
    "sg:city":"\u00dcmraniye",
    "sg:classifiers":[
        {
            "category":"Building & Trades",
            "subcategory":"Plumbing",
            "type":"Services"
        }
    ],
    "sg:phone":"+90 352 330 3186",
    "sg:postcode":"34776",
    "sg:province":"Kayseri",
    "sg:tags":[
        "pipe",
        "industry"
    ],
    "wof:name":"Asya Boru Profil",
    "wof:placetype":"venue"
},
  "geometry": {"coordinates":[35.4891357422,38.7225761414],"type":"Point"}
}