{
  "type": "Feature",
  "properties": {
    "iso:country":"TR",
    "sg:address":"Sultan Cd. N?et Sk. No:35 Okmeydani",
    "sg:city":"Topkapi",
    "sg:classifiers":[
        {
            "category":"Home & Garden",
            "subcategory":"Kitchen Supply",
            "type":"Retail Goods"
        }
    ],
    "sg:phone":"+90 212 250 9256",
    "sg:postcode":"24620",
    "sg:province":"Istanbul",
    "sg:tags":[
        "steel",
        "utensil"
    ],
    "wof:name":"D?zen Metal Esya F.",
    "wof:placetype":"venue"
},
  "geometry": {"coordinates":[28.975925,41.012379],"type":"Point"}
}