{
  "type": "Feature",
  "properties": {
    "addr:full":"Yeni Mah. Nev-yap 5.blok No:21/c Osmangazi Nevsehir 16030",
    "addr:housenumber":"5.blok no 21 / c",
    "addr:postcode":"16030",
    "addr:street":"Yeni Mah. Nev-Yap;Osmangazi",
    "iso:country":"TR",
    "sg:address":"Yeni Mah. Nev-yap 5.blok No:21/c",
    "sg:city":"Osmangazi",
    "sg:classifiers":[
        {
            "category":"Home & Garden",
            "subcategory":"Kitchen Supply",
            "type":"Retail Goods"
        }
    ],
    "sg:phone":"+90 384 214 1414",
    "sg:postcode":"16030",
    "sg:province":"Nevsehir",
    "sg:tags":[
        "wardrobe"
    ],
    "wof:name":"Nevmobsan",
    "wof:placetype":"venue"
},
  "geometry": {"coordinates":[34.7140007019,38.6245994568],"type":"Point"}
}