{
  "type": "Feature",
  "properties": {
    "addr:full":"Ikitelli Organize San. B?gesi Metal Is San. Sit. 10. Blok No:14 Ikitelli Istanbul 34306",
    "addr:housenumber":"10 blok no 14",
    "addr:postcode":"34306",
    "addr:street":"Organize;Istanbul",
    "iso:country":"TR",
    "sg:address":"Ikitelli Organize San. B?gesi Metal Is San. Sit. 10. Blok No:14",
    "sg:city":"Ikitelli",
    "sg:orig_category":"Ikitelli Metal-is Ind.site",
    "sg:phone":"+90 21254964838",
    "sg:postcode":"34306",
    "sg:province":"Istanbul",
    "wof:name":"?st?n Kazan Plastik Ve Tel ?rme San. Tic.",
    "wof:placetype":"venue"
},
  "geometry": {"coordinates":[29.2123756409,40.927822113],"type":"Point"}
}