{
  "type": "Feature",
  "properties": {
    "iso:country":"TR",
    "sg:address":"Karpuzatan Mevki No.48",
    "sg:city":"Cine",
    "sg:classifiers":[
        {
            "category":"Food & Beverages",
            "subcategory":"Meat & Fish",
            "type":"Retail Goods"
        }
    ],
    "sg:phone":"+90 352 339 4142",
    "sg:postcode":"01370",
    "sg:province":"Kayseri",
    "sg:tags":[
        "product"
    ],
    "wof:name":"Tam-et Gida San. A.s.",
    "wof:placetype":"venue"
},
  "geometry": {"coordinates":[36.4393234253,38.2791290283],"type":"Point"}
}