{
  "type": "Feature",
  "properties": {
    "iso:country":"TR",
    "sg:address":"Cinnah Cad 102",
    "sg:city":"Ankara",
    "sg:classifiers":[
        {
            "category":"Banks & Credit Unions",
            "subcategory":"Bank",
            "type":"Services"
        }
    ],
    "sg:phone":"+90 312 440 9966",
    "sg:postcode":"63570",
    "sg:province":"06690",
    "wof:name":"Esbank Eskisehir, Bankasi Tas",
    "wof:placetype":"venue"
},
  "geometry": {"coordinates":[32.855148,39.886375],"type":"Point"}
}