{
  "type": "Feature",
  "properties": {
    "iso:country":"TR",
    "sg:address":"Buy?dere Cd.no3 Simsek Apt.d3",
    "sg:city":"Sisli",
    "sg:classifiers":[
        {
            "category":"Marine",
            "type":"Transportation"
        }
    ],
    "sg:phone":"+90 212 241 5892",
    "sg:postcode":"65710",
    "sg:province":"Istanbul",
    "sg:tags":[
        "stevedores-tally"
    ],
    "wof:name":"Kalyon Denizcilik A.s.",
    "wof:placetype":"venue"
},
  "geometry": {"coordinates":[28.975925,41.012379],"type":"Point"}
}