{
  "type": "Feature",
  "properties": {
    "iso:country":"TR",
    "sg:address":"Emekyemez Mh. Mektep Sk. No:39/1",
    "sg:city":"Sishane",
    "sg:classifiers":[
        {
            "category":"Home & Garden",
            "subcategory":"Household Appliances",
            "type":"Retail Goods"
        }
    ],
    "sg:phone":"+90 212 255 5090",
    "sg:province":"Istanbul",
    "sg:tags":[
        "conditioner",
        "air"
    ],
    "wof:name":"Nurol Isi Armat?r. San.",
    "wof:placetype":"venue"
},
  "geometry": {"coordinates":[28.9706764221,41.0120429993],"type":"Point"}
}