{
  "type": "Feature",
  "properties": {
    "iso:country":"TR",
    "sg:address":"Durak Mahallesi Fatih Cad. No:10",
    "sg:city":"Sisli",
    "sg:classifiers":[
        {
            "category":"Travel",
            "subcategory":"Travel Agent",
            "type":"Entertainment"
        }
    ],
    "sg:phone":"+90 276 227 3578",
    "sg:postcode":"65710",
    "sg:province":"Usak",
    "sg:tags":[
        "agency",
        "tourism"
    ],
    "wof:name":"Asigo Turizm",
    "wof:placetype":"venue"
},
  "geometry": {"coordinates":[29.4078292847,38.6682548523],"type":"Point"}
}