{
  "type": "Feature",
  "properties": {
    "addr:full":"Kurtulus Cad Paros Bldg164/1, Sisli Istanbul 34377",
    "addr:housenumber":"bldg164 / 1",
    "addr:postcode":"34377",
    "addr:street":"Kurtulus Cad Paros",
    "iso:country":"TR",
    "sg:address":"Kurtulus Cad Paros Bldg164/1, Sisli",
    "sg:city":"Istanbul",
    "sg:classifiers":[
        {
            "category":"Travel",
            "subcategory":"Travel Agent",
            "type":"Entertainment"
        }
    ],
    "sg:phone":"+90 902 122 9602",
    "sg:province":"34377",
    "sg:website":"www.parostravel.com",
    "wof:name":"Paros Travel Service & Services",
    "wof:placetype":"venue"
},
  "geometry": {"coordinates":[28.9891529083,41.0614967346],"type":"Point"}
}