{
  "type": "Feature",
  "properties": {
    "iso:country":"TR",
    "sg:address":"Istanbul",
    "sg:city":"Sincan",
    "sg:classifiers":[
        {
            "category":"Education",
            "subcategory":"Special Training",
            "type":"Public Place"
        }
    ],
    "sg:phone":"+90 212 633 2343",
    "sg:postcode":"06930",
    "sg:province":"Istanbul",
    "sg:tags":[
        "course"
    ],
    "wof:name":"Findikzade Dersanesi",
    "wof:placetype":"venue"
},
  "geometry": {"coordinates":[28.625787735,41.0093803406],"type":"Point"}
}