{
  "type": "Feature",
  "properties": {
    "addr:full":"Mimar Sinan Cad. Altun Sok.no:2/5 Sehli Ikitelli/K\u00fc\u00e7\u00fck\u00e7ekmece Istanbul 34670",
    "addr:housenumber":"2 / 5",
    "addr:postcode":"34670",
    "addr:street":"Mimar Sinan Cad.;Sok.No",
    "iso:country":"TR",
    "sg:address":"Mimar Sinan Cad. Altun Sok.no:2/5 Sehli",
    "sg:city":"Ikitelli/K\u00fc\u00e7\u00fck\u00e7ekmece",
    "sg:classifiers":[
        {
            "category":"Manufacturing",
            "subcategory":"Tools & Machinery",
            "type":"Manufacturing & Wholesale Goods"
        }
    ],
    "sg:phone":"+90 216 378 8619",
    "sg:postcode":"34670",
    "sg:province":"Istanbul",
    "sg:tags":[
        "machine",
        "industry"
    ],
    "wof:name":"Nurlu Makina Plastik San.dis.tic.ltd.sti.",
    "wof:placetype":"venue"
},
  "geometry": {"coordinates":[28.9759254456,41.0123786926],"type":"Point"}
}