{
  "type": "Feature",
  "properties": {
    "iso:country":"TR",
    "sg:address":"Kemalpasa Yolu 2.km.",
    "sg:city":"Torbali",
    "sg:orig_category":"Dryfood-dried Nuts",
    "sg:phone":"+90 232 866 2115",
    "sg:postcode":"35860",
    "sg:province":"Izmir",
    "wof:name":"Gemas Gida Mam. San. A.s.",
    "wof:placetype":"venue"
},
  "geometry": {"coordinates":[27.1423015594,38.4251480103],"type":"Point"}
}