{
  "type": "Feature",
  "properties": {
    "addr:full":"Evren Cad. Yigitler Sok. No:16 Y.dudullu Istanbul",
    "addr:housenumber":"no 16",
    "addr:street":"Evren Cad. Yigitler Sok.",
    "iso:country":"TR",
    "sg:address":"Evren Cad. Yigitler Sok. No:16",
    "sg:city":"Y.dudullu",
    "sg:classifiers":[
        {
            "category":"Shopping",
            "subcategory":"Clothing, Apparel, & Fashions",
            "type":"Retail Goods"
        }
    ],
    "sg:phone":"+90 216 420 6596",
    "sg:province":"Istanbul",
    "sg:tags":[
        "ready",
        "wear"
    ],
    "wof:name":"Grup Tekstil",
    "wof:placetype":"venue"
},
  "geometry": {"coordinates":[29.0422649384,41.137840271],"type":"Point"}
}