{
  "type": "Feature",
  "properties": {
    "addr:full":"Selahattin Pinar Cad. No:29 Kilic Pasaji Mecidiyekoy Tuzla Istanbul 81700",
    "addr:housenumber":"29",
    "addr:postcode":"81700",
    "addr:street":"Selahattin Pinar Cad. No",
    "iso:country":"TR",
    "sg:address":"Selahattin Pinar Cad. No:29 Kilic Pasaji Mecidiyekoy",
    "sg:city":"Tuzla",
    "sg:classifiers":[
        {
            "category":"Home & Garden",
            "subcategory":"Kitchen Supply",
            "type":"Retail Goods"
        }
    ],
    "sg:phone":"+90 212212282021",
    "sg:postcode":"81700",
    "sg:province":"Istanbul",
    "sg:tags":[
        "wardrobe"
    ],
    "wof:name":"Form Ic Ve Dis Ticaret Ltd.sti.",
    "wof:placetype":"venue"
},
  "geometry": {"coordinates":[28.9759254456,41.0123786926],"type":"Point"}
}