{
  "type": "Feature",
  "properties": {
    "iso:country":"TR",
    "sg:address":"40. Sk. No: 115 Ostim",
    "sg:city":"Osmangazi",
    "sg:classifiers":[
        {
            "category":"Manufacturing",
            "subcategory":"Rubber & Plastics",
            "type":"Manufacturing & Wholesale Goods"
        }
    ],
    "sg:phone":"+90 312 354 4235",
    "sg:postcode":"46050",
    "sg:province":"Ankara",
    "sg:tags":[
        "industry"
    ],
    "wof:name":"Ozfiber Insaat Taah?t San. Tic. Ltd. Sti.",
    "wof:placetype":"venue"
},
  "geometry": {"coordinates":[32.7479972839,39.9787788391],"type":"Point"}
}