{
  "type": "Feature",
  "properties": {
    "addr:full":"Ismetpasa Cad.no:62 Tuzla Usak 93334",
    "addr:housenumber":"62",
    "addr:postcode":"93334",
    "addr:street":"Usak",
    "iso:country":"TR",
    "sg:address":"Ismetpasa Cad.no:62",
    "sg:city":"Tuzla",
    "sg:classifiers":[
        {
            "category":"Shopping",
            "subcategory":"Luggage & Leather Goods",
            "type":"Retail Goods"
        }
    ],
    "sg:phone":"+90 276 223 3811",
    "sg:postcode":"93334",
    "sg:province":"Usak",
    "sg:tags":[
        "leather-fur",
        "wear"
    ],
    "wof:name":"Agaoglu Teks.san.tic.a.s.",
    "wof:placetype":"venue"
},
  "geometry": {"coordinates":[29.4055938721,38.675453186],"type":"Point"}
}