{
  "type": "Feature",
  "properties": {
    "addr:full":"Pasatarlasi Cad. No:21 Bodrum Mugla 48400",
    "addr:housenumber":"21",
    "addr:postcode":"48400",
    "addr:street":"Pasatarlasi Cad. No",
    "iso:country":"TR",
    "sg:address":"Pasatarlasi Cad. No:21",
    "sg:city":"Bodrum",
    "sg:classifiers":[
        {
            "category":"Recreation",
            "subcategory":"Boat Charter",
            "type":"Entertainment"
        }
    ],
    "sg:phone":"+90 25231615173",
    "sg:postcode":"48400",
    "sg:province":"Mugla",
    "sg:tags":[
        "yachting"
    ],
    "wof:name":"Aegean Yachting",
    "wof:placetype":"venue"
},
  "geometry": {"coordinates":[27.4407844543,37.0267791748],"type":"Point"}
}