{
  "type": "Feature",
  "properties": {
    "iso:country":"TR",
    "sg:address":"Kavakli K??deniz Aktas Cd. Tamer Center B.?ekmece",
    "sg:city":"Okmeydani",
    "sg:classifiers":[
        {
            "category":"Sports & Exercise",
            "subcategory":"Tennis Court",
            "type":"Entertainment"
        }
    ],
    "sg:phone":"+90 212 875 0850",
    "sg:postcode":"80270",
    "sg:province":"Istanbul",
    "sg:tags":[
        "equipment",
        "material"
    ],
    "wof:name":"Tnt Teks. San. Tic. A.s",
    "wof:placetype":"venue"
},
  "geometry": {"coordinates":[28.975925,41.012379],"type":"Point"}
}