{
  "type": "Feature",
  "properties": {
    "addr:full":"Rami Uluyol Cad. Osman Nuri Is Merk. No:11 Bayrampasa Istanbul 36100",
    "addr:housenumber":"11",
    "addr:postcode":"36100",
    "addr:street":"Uluyol Cad. Osman Nuri Is Merk. No;Istanbul",
    "iso:country":"TR",
    "sg:address":"Rami Uluyol Cad. Osman Nuri Is Merk. No:11",
    "sg:city":"Bayrampasa",
    "sg:orig_category":"Non-classified Establishments",
    "sg:phone":"+90 212 565 9575",
    "sg:postcode":"36100",
    "sg:province":"Istanbul",
    "wof:name":"Teknik Tekstil Urunleri Ith. Ihr. San.ve Tic.ltd.sti.",
    "wof:placetype":"venue"
},
  "geometry": {"coordinates":[28.9861831665,41.0408554077],"type":"Point"}
}