{
  "type": "Feature",
  "properties": {
    "iso:country":"TR",
    "sg:address":"Koca Vezir Mah. 2.sok. No:34 /b",
    "sg:city":"Seyhan",
    "sg:classifiers":[
        {
            "category":"Manufacturing",
            "subcategory":"Food",
            "type":"Manufacturing & Wholesale Goods"
        }
    ],
    "sg:phone":"+90 322 365 0695",
    "sg:postcode":"01000",
    "sg:province":"Adana",
    "sg:tags":[
        "wholesaler"
    ],
    "wof:name":"Altunok Gida Ve Tarim Tic.san.ltd.sti.",
    "wof:placetype":"venue"
},
  "geometry": {"coordinates":[35.3137359619,37.0007171631],"type":"Point"}
}