{
  "type": "Feature",
  "properties": {
    "addr:full":"Ceyhan Yolu Keresteciler Sitesi \u00dcmraniye Adana",
    "addr:street":"Ceyhan Yolu Keresteciler Sitesi",
    "iso:country":"TR",
    "sg:address":"Ceyhan Yolu Keresteciler Sitesi",
    "sg:city":"\u00dcmraniye",
    "sg:classifiers":[
        {
            "category":"Manufacturing",
            "subcategory":"Wood Products",
            "type":"Manufacturing & Wholesale Goods"
        }
    ],
    "sg:phone":"+90 322 346 1964",
    "sg:province":"Adana",
    "sg:tags":[
        "forest"
    ],
    "wof:name":"G?m? Kereste Ve Orman ?r?leri Degerlendirme San Ve Tic.as.",
    "wof:placetype":"venue"
},
  "geometry": {"coordinates":[35.3137359619,37.0007171631],"type":"Point"}
}