{
  "type": "Feature",
  "properties": {
    "iso:country":"TR",
    "sg:address":"1431 Sok.no:18/3 Kahramanlar",
    "sg:city":"Gaziosmanpasa",
    "sg:orig_category":"Scavening Services",
    "sg:phone":"+90 232 421 0011",
    "sg:postcode":"34100",
    "sg:province":"Izmir",
    "wof:name":"Naturel Temizlik Ltd.sti",
    "wof:placetype":"venue"
},
  "geometry": {"coordinates":[27.150606,38.431221],"type":"Point"}
}