{
  "type": "Feature",
  "properties": {
    "iso:country":"TR",
    "sg:address":"Sehit Muhtar Cad. No:35",
    "sg:city":"Taksim",
    "sg:classifiers":[
        {
            "category":"Travel",
            "subcategory":"Travel Agent",
            "type":"Entertainment"
        }
    ],
    "sg:phone":"+90 212 235 0233",
    "sg:postcode":"24040",
    "sg:province":"Istanbul",
    "sg:tags":[
        "agency",
        "tourism"
    ],
    "wof:name":"Ilos Travel",
    "wof:placetype":"venue"
},
  "geometry": {"coordinates":[28.9839420319,41.0394363403],"type":"Point"}
}