{
  "type": "Feature",
  "properties": {
    "iso:country":"TR",
    "sg:address":"Mend Bulv. G. Hisar Mah. 4. Sk. No:30/a",
    "sg:city":"\u00c7orlu",
    "sg:classifiers":[
        {
            "category":"Shopping",
            "subcategory":"Luggage & Leather Goods",
            "type":"Retail Goods"
        }
    ],
    "sg:phone":"+90 256 225 6267",
    "sg:province":"Aydin",
    "sg:tags":[
        "leather-fur",
        "wear"
    ],
    "wof:name":"Elegant Leather",
    "wof:placetype":"venue"
},
  "geometry": {"coordinates":[28.4863967896,37.8117027283],"type":"Point"}
}