{
  "type": "Feature",
  "properties": {
    "addr:full":"Organize San. Bolg. 16.cad. Ey\u00fcp Kayseri",
    "addr:housenumber":"16.cad",
    "addr:street":"Organize San. Bolg.",
    "iso:country":"TR",
    "sg:address":"Organize San. Bolg. 16.cad.",
    "sg:city":"Ey\u00fcp",
    "sg:classifiers":[
        {
            "category":"Wholesale",
            "subcategory":"Durable Goods & Equipment",
            "type":"Manufacturing & Wholesale Goods"
        }
    ],
    "sg:phone":"+90 352 321 1430",
    "sg:province":"Kayseri",
    "sg:tags":[
        "consumer"
    ],
    "wof:name":"Kaysu Mini Bar",
    "wof:placetype":"venue"
},
  "geometry": {"coordinates":[35.4364013672,38.7450408936],"type":"Point"}
}