{
  "type": "Feature",
  "properties": {
    "iso:country":"TR",
    "sg:address":"Ankara",
    "sg:city":"Karabaglar",
    "sg:classifiers":[
        {
            "category":"Government",
            "subcategory":"Office",
            "type":"Public Place"
        }
    ],
    "sg:phone":"+90 312 362 4934",
    "sg:postcode":"44210",
    "sg:province":"Ankara",
    "sg:tags":[
        "army"
    ],
    "wof:name":"Mamak (elmadag) Askerlik Subesi",
    "wof:placetype":"venue"
},
  "geometry": {"coordinates":[32.8061790466,39.7928504944],"type":"Point"}
}