{
  "type": "Feature",
  "properties": {
    "addr:full":"Asirefendi Cad.no:33 Sirkeci Istanbul 34112",
    "addr:housenumber":"33",
    "addr:postcode":"34112",
    "iso:country":"TR",
    "sg:address":"Asirefendi Cad.no:33",
    "sg:city":"Sirkeci",
    "sg:classifiers":[
        {
            "category":"Home & Garden",
            "subcategory":"Hardware",
            "type":"Retail Goods"
        }
    ],
    "sg:phone":"+90 212 522 4212",
    "sg:postcode":"34112",
    "sg:province":"Istanbul",
    "sg:tags":[
        "store"
    ],
    "wof:name":"Handy Lastik Eldiven San.tic.a.s.",
    "wof:placetype":"venue"
},
  "geometry": {"coordinates":[28.9729957581,41.0144042969],"type":"Point"}
}