{
  "type": "Feature",
  "properties": {
    "addr:full":"Degirmenyolu Sok Sasmaz Sit.b1-blok K:4 D:11 No:2 81080 Kozyatagi Istanbul Sariyer Istanbul 33740",
    "addr:housenumber":"4 d 11 no 2",
    "addr:postcode":"81080;33740",
    "addr:street":"Degirmenyolu Sok Sasmaz Sit.B1-Blok K",
    "iso:country":"TR",
    "sg:address":"Degirmenyolu Sok Sasmaz Sit.b1-blok K:4 D:11 No:2 81080 Kozyatagi Istanbul",
    "sg:city":"Sariyer",
    "sg:orig_category":"Miscellaneous Products",
    "sg:phone":"+90 216 463 2601",
    "sg:postcode":"33740",
    "sg:province":"Istanbul",
    "wof:name":"Ra-met Bakir Ve San Hammadde Dis Tic As",
    "wof:placetype":"venue"
},
  "geometry": {"coordinates":[28.9759254456,41.0123786926],"type":"Point"}
}