{
  "type": "Feature",
  "properties": {
    "addr:full":"Yeni Yalova Yolu 14. Km Ovaakca Bursa 16335",
    "addr:housenumber":"14 km",
    "addr:postcode":"16335",
    "addr:street":"Yalova Yolu;Ovaakca Bursa",
    "iso:country":"TR",
    "sg:address":"Yeni Yalova Yolu 14. Km",
    "sg:city":"Ovaakca",
    "sg:classifiers":[
        {
            "category":"Shopping",
            "subcategory":"Clothing, Apparel, & Fashions",
            "type":"Retail Goods"
        }
    ],
    "sg:phone":"+90 224 267 0098",
    "sg:postcode":"16335",
    "sg:province":"Bursa",
    "sg:tags":[
        "woman",
        "wear"
    ],
    "wof:name":"Oztekstil San.ltd. Sti.",
    "wof:placetype":"venue"
},
  "geometry": {"coordinates":[29.0580043793,40.1947555542],"type":"Point"}
}