{
  "type": "Feature",
  "properties": {
    "addr:full":"Yesilk? Cad. No: 226 \u00dcmraniye Denizli",
    "addr:postcode":"226",
    "addr:street":"Cad. No",
    "iso:country":"TR",
    "sg:address":"Yesilk? Cad. No: 226",
    "sg:city":"\u00dcmraniye",
    "sg:classifiers":[
        {
            "category":"Manufacturing",
            "subcategory":"Rubber & Plastics",
            "type":"Manufacturing & Wholesale Goods"
        }
    ],
    "sg:phone":"+90 258 373 1330",
    "sg:province":"Denizli",
    "sg:tags":[
        "industry"
    ],
    "wof:name":"Isisan Ltd.sti.",
    "wof:placetype":"venue"
},
  "geometry": {"coordinates":[29.0632152557,37.7833366394],"type":"Point"}
}