{
  "type": "Feature",
  "properties": {
    "addr:full":"Merkez Mah.fatih Cad. No:17 Arnavutkoy -gaziosmanpasa G?tepe Istanbul",
    "addr:housenumber":"17;?",
    "addr:street":"Mah.Fatih Cad. No;Gaziosmanpasa G",
    "iso:country":"TR",
    "sg:address":"Merkez Mah.fatih Cad. No:17 Arnavutkoy -gaziosmanpasa",
    "sg:city":"G?tepe",
    "sg:classifiers":[
        {
            "category":"Wholesale",
            "subcategory":"Home Furnishings",
            "type":"Manufacturing & Wholesale Goods"
        }
    ],
    "sg:phone":"+90 212 597 1066",
    "sg:province":"Istanbul",
    "sg:tags":[
        "furniture"
    ],
    "wof:name":"Tecirler Ahsap Kereste & Mobilya San.tic.a.s.",
    "wof:placetype":"venue"
},
  "geometry": {"coordinates":[28.7415790558,41.1860198975],"type":"Point"}
}