{
  "type": "Feature",
  "properties": {
    "addr:full":"Recep Tayyip Erdogan Sariyer Ankara 33740",
    "addr:postcode":"33740",
    "iso:country":"TR",
    "sg:address":"Recep Tayyip Erdogan",
    "sg:city":"Sariyer",
    "sg:classifiers":[
        {
            "category":"Organizations",
            "subcategory":"Religious Organization",
            "type":"Services"
        }
    ],
    "sg:phone":"+90 3124195897984",
    "sg:postcode":"33740",
    "sg:province":"Ankara",
    "sg:tags":[
        "minister"
    ],
    "wof:name":"Basbakan",
    "wof:placetype":"venue"
},
  "geometry": {"coordinates":[32.5705108643,39.9567604065],"type":"Point"}
}