{
  "type": "Feature",
  "properties": {
    "addr:full":"Cinnah Cad. Pilot Sok. No:5/1 Cankaya 4. Levent Ankara",
    "addr:housenumber":"no 5 / 1;4",
    "addr:street":"Cinnah Cad. Pilot Sok.;Cankaya",
    "iso:country":"TR",
    "sg:address":"Cinnah Cad. Pilot Sok. No:5/1 Cankaya",
    "sg:city":"4. Levent",
    "sg:orig_category":"Prefabric Construction",
    "sg:phone":"+90 3124416807729",
    "sg:province":"Ankara",
    "wof:name":"Alfa Insaat Sanayi Ve Ticaret A.s.",
    "wof:placetype":"venue"
},
  "geometry": {"coordinates":[32.8525772095,39.8884925842],"type":"Point"}
}