{
  "type": "Feature",
  "properties": {
    "addr:full":"Unalan Mah. Ayazma Cad. B2.blok Kucuk Camlica Uskudar Ikitelli/K\u00fc\u00e7\u00fck\u00e7ekmece Istanbul 34670",
    "addr:housenumber":"b2.blok;ikitelli / kuec\u0327uekc\u0327ekmece",
    "addr:postcode":"34670",
    "addr:street":"Unalan Mah. Ayazma Cad.;Kucuk Camlica Uskudar;Istanbul",
    "iso:country":"TR",
    "sg:address":"Unalan Mah. Ayazma Cad. B2.blok Kucuk Camlica Uskudar",
    "sg:city":"Ikitelli/K\u00fc\u00e7\u00fck\u00e7ekmece",
    "sg:classifiers":[
        {
            "category":"Professional",
            "subcategory":"Business Services",
            "type":"Services"
        }
    ],
    "sg:phone":"+90 216 454 1530",
    "sg:postcode":"34670",
    "sg:province":"Istanbul",
    "sg:tags":[
        "industry",
        "casting"
    ],
    "wof:name":"Turk Demir Dokum Fabrikalari A.s.",
    "wof:placetype":"venue"
},
  "geometry": {"coordinates":[28.9861831665,41.0408554077],"type":"Point"}
}