{
  "type": "Feature",
  "properties": {
    "iso:country":"TR",
    "sg:address":"Buttim D.3 No:915",
    "sg:city":"Eminonu",
    "sg:classifiers":[
        {
            "category":"Shopping",
            "subcategory":"Crafts & Fabrics",
            "type":"Retail Goods"
        }
    ],
    "sg:phone":"+90 224 211 5010",
    "sg:province":"Bursa",
    "sg:tags":[
        "weaving"
    ],
    "wof:name":"Bersa Tekstil",
    "wof:placetype":"venue"
},
  "geometry": {"coordinates":[29.0655345917,40.2357215881],"type":"Point"}
}