{
  "type": "Feature",
  "properties": {
    "iso:country":"TR",
    "sg:address":"Baglar Mah.fatih Cad.baris Sok.no:14",
    "sg:city":"G?esli",
    "sg:classifiers":[
        {
            "category":"Building & Trades",
            "subcategory":"Electrical",
            "type":"Services"
        }
    ],
    "sg:phone":"+90 212 657 8988",
    "sg:postcode":"34540",
    "sg:province":"Istanbul",
    "sg:tags":[
        "equipment",
        "lighting"
    ],
    "wof:name":"D-light Aydinlatma",
    "wof:placetype":"venue"
},
  "geometry": {"coordinates":[28.8219108582,41.0270004272],"type":"Point"}
}