{
  "type": "Feature",
  "properties": {
    "iso:country":"TR",
    "sg:address":"Marmara Cad. ?alislar Sok No:2/2",
    "sg:city":"G?ng?ren",
    "sg:classifiers":[
        {
            "category":"Shopping",
            "subcategory":"Clothing, Apparel, & Fashions",
            "type":"Retail Goods"
        }
    ],
    "sg:phone":"+92 1250 21349",
    "sg:province":"Istanbul",
    "sg:tags":[
        "jean"
    ],
    "wof:name":"Itaccenter",
    "wof:placetype":"venue"
},
  "geometry": {"coordinates":[28.8565750122,41.0131874084],"type":"Point"}
}