{
  "type": "Feature",
  "properties": {
    "addr:full":"Merter M.akif Mah. Simir Sok. No:6 Merter Istanbul",
    "addr:housenumber":"no 6",
    "addr:street":"M.Akif Mah. Simir Sok.",
    "iso:country":"TR",
    "sg:address":"Merter M.akif Mah. Simir Sok. No:6",
    "sg:city":"Merter",
    "sg:classifiers":[
        {
            "category":"Shopping",
            "subcategory":"Crafts & Fabrics",
            "type":"Retail Goods"
        }
    ],
    "sg:phone":"+90 212 557 5721",
    "sg:province":"Istanbul",
    "sg:tags":[
        "yarn"
    ],
    "wof:name":"Yurdakullar Tekstil San.ve Tic.ltd.sti.",
    "wof:placetype":"venue"
},
  "geometry": {"coordinates":[28.9759254456,41.0123786926],"type":"Point"}
}