{
  "type": "Feature",
  "properties": {
    "iso:country":"TR",
    "sg:address":"Halasgargazi Cad. Halas Apt. No: 277-3",
    "sg:city":"Osmanbey",
    "sg:classifiers":[
        {
            "category":"Bars & Pubs",
            "subcategory":"Nightclub",
            "type":"Food & Drink"
        }
    ],
    "sg:phone":"+90 212 232 4449",
    "sg:postcode":"63000",
    "sg:province":"Istanbul",
    "sg:tags":[
        "cake",
        "sweet"
    ],
    "wof:name":"Seckin Gida",
    "wof:placetype":"venue"
},
  "geometry": {"coordinates":[28.979822,41.036015],"type":"Point"}
}