{
  "type": "Feature",
  "properties": {
    "addr:full":"Tibbiye Cad. No: 18-20 Selimiye-uskudar Sisli Istanbul 80220",
    "addr:housenumber":"no 18-20",
    "addr:postcode":"80220",
    "addr:street":"Tibbiye Cad.;Selimiye-Uskudar Sisli",
    "iso:country":"TR",
    "sg:address":"Tibbiye Cad. No: 18-20 Selimiye-uskudar",
    "sg:city":"Sisli",
    "sg:classifiers":[
        {
            "category":"Social Services",
            "subcategory":"Retirement Home",
            "type":"Services"
        }
    ],
    "sg:phone":"+90 216 341 4545",
    "sg:postcode":"80220",
    "sg:province":"Istanbul",
    "sg:tags":[
        "door"
    ],
    "wof:name":"Tan Bilgisayar Reklam.hizm.a.s.",
    "wof:placetype":"venue"
},
  "geometry": {"coordinates":[29.0187530518,41.0122871399],"type":"Point"}
}