{
  "type": "Feature",
  "properties": {
    "addr:full":"Tahtakale Yavascasahin Sok. No:18 Eminonu Saray?n? Istanbul 63100",
    "addr:housenumber":"no 18;saray ?;?",
    "addr:postcode":"63100",
    "addr:street":"Yavascasahin Sok.;Eminonu;N",
    "iso:country":"TR",
    "sg:address":"Tahtakale Yavascasahin Sok. No:18 Eminonu",
    "sg:city":"Saray?n?",
    "sg:orig_category":"Bijouterie",
    "sg:phone":"+90 212 520 9024",
    "sg:postcode":"63100",
    "sg:province":"Istanbul",
    "wof:name":"Ugur Kardesler Bijuteri Ltd.sti.",
    "wof:placetype":"venue"
},
  "geometry": {"coordinates":[28.975925,41.012379],"type":"Point"}
}