{
  "type": "Feature",
  "properties": {
    "iso:country":"TR",
    "sg:address":"Vatan Mh. Ar Sk. G?dallar 11. San. Sit. No:50 Bayrampasa",
    "sg:city":"Incesu",
    "sg:classifiers":[
        {
            "category":"Home & Garden",
            "subcategory":"Hardware",
            "type":"Retail Goods"
        }
    ],
    "sg:phone":"+90 212 577 4503",
    "sg:postcode":"32765",
    "sg:province":"Istanbul",
    "sg:tags":[
        "lathe"
    ],
    "wof:name":"Titiz Torna",
    "wof:placetype":"venue"
},
  "geometry": {"coordinates":[28.9759254456,41.0123786926],"type":"Point"}
}