{
  "type": "Feature",
  "properties": {
    "iso:country":"TR",
    "sg:address":"Urfa Yolu 10.km.",
    "sg:city":"Kestel",
    "sg:classifiers":[
        {
            "category":"Home & Garden",
            "subcategory":"Home Furnishings",
            "type":"Retail Goods"
        }
    ],
    "sg:phone":"+90 412 255 0055",
    "sg:postcode":"09800",
    "sg:province":"Diyarbakir",
    "sg:tags":[
        "textile"
    ],
    "wof:name":"Akyil Tekstil Gurubu",
    "wof:placetype":"venue"
},
  "geometry": {"coordinates":[40.2107009888,37.9244651794],"type":"Point"}
}