{
  "type": "Feature",
  "properties": {
    "iso:country":"TR",
    "sg:address":"Abdullah C. Sk. No:26/1 ?ankaya",
    "sg:city":"Bandirma",
    "sg:classifiers":[
        {
            "category":"Banks & Credit Unions",
            "subcategory":"Investment Brokerage",
            "type":"Services"
        }
    ],
    "sg:phone":"+90 312 440 5572",
    "sg:postcode":"10200",
    "sg:province":"Ankara",
    "sg:tags":[
        "-",
        "export",
        "import"
    ],
    "wof:name":"Marconi Overseas Ltd. Sti.",
    "wof:placetype":"venue"
},
  "geometry": {"coordinates":[32.8604812622,39.9429283142],"type":"Point"}
}