{
  "type": "Feature",
  "properties": {
    "addr:full":"Bostan Sk. No:34 Moda \u00c7ankaya Istanbul",
    "addr:street":"Bostan Sk. No",
    "iso:country":"TR",
    "sg:address":"Bostan Sk. No:34 Moda",
    "sg:city":"\u00c7ankaya",
    "sg:classifiers":[
        {
            "category":"Retail",
            "subcategory":"Laundry & Dry Cleaning",
            "type":"Services"
        }
    ],
    "sg:phone":"+90 216 346 1451",
    "sg:province":"Istanbul",
    "wof:name":"Roventea Kuru Temiz. San.",
    "wof:placetype":"venue"
},
  "geometry": {"coordinates":[29.0226707458,40.9840812683],"type":"Point"}
}