{
  "type": "Feature",
  "properties": {
    "addr:full":"Yavuzeli Yolu Uzeri 3.km. 9. Cad. Sahinbey Gaziantep 27700",
    "addr:housenumber":"uzeri;9",
    "addr:postcode":"27700",
    "addr:street":"Yavuzeli Yolu;Cad. Sahinbey",
    "iso:country":"TR",
    "sg:address":"Yavuzeli Yolu Uzeri 3.km. 9. Cad.",
    "sg:city":"Sahinbey",
    "sg:classifiers":[
        {
            "category":"Shopping",
            "subcategory":"Crafts & Fabrics",
            "type":"Retail Goods"
        }
    ],
    "sg:phone":"+90 34232898784",
    "sg:postcode":"27700",
    "sg:province":"Gaziantep",
    "sg:tags":[
        "yarn"
    ],
    "wof:name":"Ansa Ambalaj San.ve Tic.a.s.",
    "wof:placetype":"venue"
},
  "geometry": {"coordinates":[37.3761024475,37.0629463196],"type":"Point"}
}