{
  "type": "Feature",
  "properties": {
    "addr:full":"Samanyolu Sk. Bilge Han 5/3-1 Osmanbey Istanbul 63000",
    "addr:housenumber":"5 / 3-1",
    "addr:postcode":"63000",
    "addr:street":"Samanyolu Sk.;Han",
    "iso:country":"TR",
    "sg:address":"Samanyolu Sk. Bilge Han 5/3-1",
    "sg:city":"Osmanbey",
    "sg:classifiers":[
        {
            "category":"Shopping",
            "subcategory":"Clothing, Apparel, & Fashions",
            "type":"Retail Goods"
        }
    ],
    "sg:phone":"+90 212 248 4493",
    "sg:postcode":"63000",
    "sg:province":"Istanbul",
    "sg:tags":[
        "woman",
        "wear"
    ],
    "wof:name":"Bilge Teks. San. Tic. Ltd. Sti.",
    "wof:placetype":"venue"
},
  "geometry": {"coordinates":[29.2828407288,40.8855628967],"type":"Point"}
}