{
  "type": "Feature",
  "properties": {
    "addr:full":"Konak Mahallesi Dereboyu Sokak No:49-51 Merkez Trabzon 61200",
    "addr:housenumber":"konak;no 49-51",
    "addr:postcode":"61200",
    "addr:street":"Mahallesi Dereboyu Sokak",
    "iso:country":"TR",
    "sg:address":"Konak Mahallesi Dereboyu Sokak No:49-51",
    "sg:city":"Merkez",
    "sg:classifiers":[
        {
            "category":"Home & Garden",
            "subcategory":"Kitchen Supply",
            "type":"Retail Goods"
        }
    ],
    "sg:phone":"+90 462 273 2560",
    "sg:postcode":"61200",
    "sg:province":"Trabzon",
    "sg:tags":[
        "wardrobe"
    ],
    "wof:name":"Bilmob Mobilya&dekorasyon",
    "wof:placetype":"venue"
},
  "geometry": {"coordinates":[39.7191009521,41.0060997009],"type":"Point"}
}