{
  "type": "Feature",
  "properties": {
    "addr:full":"Ivedik Org. San. Bolgesi Oz Anadolu Sit. 664.sok. No:75 Ostim Ankara 06374",
    "addr:housenumber":"no 75",
    "addr:postcode":"06374",
    "addr:street":"Org.;Bolgesi",
    "iso:country":"TR",
    "sg:address":"Ivedik Org. San. Bolgesi Oz Anadolu Sit. 664.sok. No:75",
    "sg:city":"Ostim",
    "sg:classifiers":[
        {
            "category":"Shopping",
            "subcategory":"Crafts & Fabrics",
            "type":"Retail Goods"
        }
    ],
    "sg:phone":"+90 312 395 4131",
    "sg:postcode":"06374",
    "sg:province":"Ankara",
    "sg:tags":[
        "knitting"
    ],
    "wof:name":"Muda Tekstil Ve Orme San.ltd.sti.",
    "wof:placetype":"venue"
},
  "geometry": {"coordinates":[32.8560333252,39.9438743591],"type":"Point"}
}