{
  "type": "Feature",
  "properties": {
    "addr:full":"?ankiri Karabaglar ?ankiri 44210",
    "addr:housenumber":"?;?",
    "addr:postcode":"44210",
    "addr:street":"Ankiri Karabaglar;Ankiri",
    "iso:country":"TR",
    "sg:address":"?ankiri",
    "sg:city":"Karabaglar",
    "sg:classifiers":[
        {
            "category":"Government",
            "subcategory":"Office",
            "type":"Public Place"
        }
    ],
    "sg:phone":"+90 376 416 1102",
    "sg:postcode":"44210",
    "sg:province":"?ankiri",
    "sg:tags":[
        "army"
    ],
    "wof:name":"Ilgaz Askerlik Subesi",
    "wof:placetype":"venue"
},
  "geometry": {"coordinates":[38.4896812439,38.455280304],"type":"Point"}
}