{
  "type": "Feature",
  "properties": {
    "iso:country":"TR",
    "sg:address":"Org. Sanayi B?g. 19. Cd. No:24",
    "sg:city":"Merkez",
    "sg:classifiers":[
        {
            "category":"Home & Garden",
            "subcategory":"Kitchen Supply",
            "type":"Retail Goods"
        }
    ],
    "sg:phone":"+90 352 321 1416",
    "sg:postcode":"20100",
    "sg:province":"Kayseri",
    "sg:tags":[
        "steel",
        "utensil"
    ],
    "wof:name":"Evin Celik Esya Tel Cekme San.tic.a.s.",
    "wof:placetype":"venue"
},
  "geometry": {"coordinates":[35.489136,38.722576],"type":"Point"}
}