{
  "type": "Feature",
  "properties": {
    "addr:full":"Tesvikiye Cad. Ikbal Is Mrk. No.103 K.6 Tesvikiye Asagi Ayranci Istanbul",
    "addr:housenumber":"no.103 k.6 tesvikiye",
    "addr:street":"Tesvikiye Cad. Ikbal;Mrk.;Asagi Ayranci",
    "iso:country":"TR",
    "sg:address":"Tesvikiye Cad. Ikbal Is Mrk. No.103 K.6 Tesvikiye",
    "sg:city":"Asagi Ayranci",
    "sg:classifiers":[
        {
            "category":"Banks & Credit Unions",
            "subcategory":"Financial Services",
            "type":"Services"
        }
    ],
    "sg:phone":"+90 212 236 4274",
    "sg:province":"Istanbul",
    "sg:tags":[
        "finance"
    ],
    "wof:name":"Delta Menkul Degerler A.s",
    "wof:placetype":"venue"
},
  "geometry": {"coordinates":[28.9969673157,41.0520401001],"type":"Point"}
}