{
  "type": "Feature",
  "properties": {
    "iso:country":"TR",
    "sg:address":"19 Mayis Mah.",
    "sg:city":"Kozyatagi",
    "sg:classifiers":[
        {
            "category":"Shopping",
            "subcategory":"Clothing, Apparel, & Fashions",
            "type":"Retail Goods"
        }
    ],
    "sg:phone":"+90 216",
    "sg:postcode":"34742",
    "sg:province":"Istanbul",
    "sg:tags":[
        "ready",
        "wear"
    ],
    "wof:name":"Me-ba International Trade Center",
    "wof:placetype":"venue"
},
  "geometry": {"coordinates":[29.0819149017,40.976348877],"type":"Point"}
}