{
  "type": "Feature",
  "properties": {
    "addr:full":"Keresteciler Sitesi Fatih Cad. Ardi?sk. No:5 Merter Istanbul",
    "addr:housenumber":"?",
    "addr:street":"Fatih Cad. Ardi;Sk. No 5 Merter",
    "iso:country":"TR",
    "sg:address":"Keresteciler Sitesi Fatih Cad. Ardi?sk. No:5",
    "sg:city":"Merter",
    "sg:classifiers":[
        {
            "category":"Manufacturing",
            "subcategory":"Textiles",
            "type":"Manufacturing & Wholesale Goods"
        }
    ],
    "sg:phone":"+90 212637466463",
    "sg:province":"Istanbul",
    "sg:tags":[
        "weaving",
        "narrow",
        "-",
        "label"
    ],
    "wof:name":"Rototeks Etiket Teks. Tic.",
    "wof:placetype":"venue"
},
  "geometry": {"coordinates":[28.9861831665,41.0408554077],"type":"Point"}
}