{
  "type": "Feature",
  "properties": {
    "iso:country":"TR",
    "sg:address":"Akay Cd. Bankaci Sk. No:20/11",
    "sg:city":"Bakanliklar",
    "sg:classifiers":[
        {
            "category":"Manufacturing",
            "subcategory":"Building Materials",
            "type":"Manufacturing & Wholesale Goods"
        }
    ],
    "sg:phone":"+90 312 418 4301",
    "sg:province":"Ankara",
    "sg:tags":[
        "lifts-elevators"
    ],
    "wof:name":"Aushan Ustaoglu Asans?r San. Tic. Ltd. Sti.",
    "wof:placetype":"venue"
},
  "geometry": {"coordinates":[32.8316802979,39.9247131348],"type":"Point"}
}