{
  "type": "Feature",
  "properties": {
    "iso:country":"TR",
    "sg:address":"Ali ?etinkaya Cad. No:57",
    "sg:city":"Gayrettepe",
    "sg:classifiers":[
        {
            "category":"Professional",
            "subcategory":"Engineering",
            "type":"Services"
        }
    ],
    "sg:phone":"+90 242 312 0650",
    "sg:postcode":"34349",
    "sg:province":"Antalya",
    "sg:tags":[
        "architect"
    ],
    "wof:name":"Arma Mimarlik Insaat Imalat San. Ve Tic.ltd.sti.",
    "wof:placetype":"venue"
},
  "geometry": {"coordinates":[30.7111740112,36.8889389038],"type":"Point"}
}