{
  "type": "Feature",
  "properties": {
    "addr:full":"Ptt Yani Kigili Vakif Ish. 22/306 Malatya",
    "addr:housenumber":"22 / 306",
    "addr:street":"Ish.",
    "iso:country":"TR",
    "sg:address":"Ptt Yani Kigili Vakif Ish.",
    "sg:city":"22/306",
    "sg:classifiers":[
        {
            "category":"Wholesale",
            "subcategory":"Medical Equipment & Supplies",
            "type":"Manufacturing & Wholesale Goods"
        }
    ],
    "sg:phone":"+90 422 323 0707",
    "sg:province":"Malatya",
    "wof:name":"Guneydogu Ortopedi",
    "wof:placetype":"venue"
},
  "geometry": {"coordinates":[38.1918411255,38.5174293518],"type":"Point"}
}