{
  "type": "Feature",
  "properties": {
    "addr:full":"Ulucami Mah. Cengiz Topel Cad. 69 K?cegiz Mugla",
    "addr:housenumber":"69 k ?",
    "addr:street":"Cengiz Topel Cad.;Cegiz Mugla",
    "iso:country":"TR",
    "sg:address":"Ulucami Mah. Cengiz Topel Cad. 69",
    "sg:city":"K?cegiz",
    "sg:orig_category":"Hotels: Motels",
    "sg:phone":"+90 252262377326",
    "sg:province":"Mugla",
    "wof:name":"Panorama Plaza Hotel",
    "wof:placetype":"venue"
},
  "geometry": {"coordinates":[28.3628406525,37.215675354],"type":"Point"}
}