{
  "type": "Feature",
  "properties": {
    "iso:country":"TR",
    "sg:address":"Sebze Hali No.12",
    "sg:city":"Merkez",
    "sg:classifiers":[
        {
            "category":"Manufacturing",
            "subcategory":"Food",
            "type":"Manufacturing & Wholesale Goods"
        }
    ],
    "sg:phone":"+90 272 215 2495",
    "sg:postcode":"53100",
    "sg:province":"Afyon",
    "sg:tags":[
        "wholesaler"
    ],
    "wof:name":"Alba Meyve Sebze Ltd. Sti.",
    "wof:placetype":"venue"
},
  "geometry": {"coordinates":[30.5417995453,38.7557983398],"type":"Point"}
}