{
  "type": "Feature",
  "properties": {
    "addr:full":"Sanayi ?arsisi No:6 09350 Yenipazar Aydin 09350",
    "addr:housenumber":"?;no 6",
    "addr:postcode":"09350;09350",
    "addr:street":"Sanayi",
    "iso:country":"TR",
    "sg:address":"Sanayi ?arsisi No:6 09350",
    "sg:city":"Yenipazar",
    "sg:classifiers":[
        {
            "category":"Wholesale",
            "subcategory":"Machinery & Supplies",
            "type":"Manufacturing & Wholesale Goods"
        }
    ],
    "sg:phone":"+90 256 361 3073",
    "sg:postcode":"09350",
    "sg:province":"Aydin",
    "sg:tags":[
        "agricultural"
    ],
    "wof:name":"G?ven Ziraat Aletleri Imalathanesi",
    "wof:placetype":"venue"
},
  "geometry": {"coordinates":[29.0182037354,41.0724983215],"type":"Point"}
}