{
  "type": "Feature",
  "properties": {
    "iso:country":"TR",
    "sg:address":"Aydin",
    "sg:city":"Yenimahalle",
    "sg:classifiers":[
        {
            "category":"Shopping",
            "subcategory":"Florist",
            "type":"Retail Goods"
        }
    ],
    "sg:phone":"+90 256 212 4990",
    "sg:postcode":"06200",
    "sg:province":"Aydin",
    "sg:tags":[
        "flower"
    ],
    "wof:name":"Aydin Canli Agac Ltd.sti.",
    "wof:placetype":"venue"
},
  "geometry": {"coordinates":[27.9372215271,37.7283325195],"type":"Point"}
}