{
  "type": "Feature",
  "properties": {
    "addr:full":"Peykhane Sk. No:1 ?emberlitas Istanbul",
    "addr:housenumber":"1 ?",
    "addr:street":"Peykhane Sk. No",
    "iso:country":"TR",
    "sg:address":"Peykhane Sk. No:1",
    "sg:city":"?emberlitas",
    "sg:classifiers":[
        {
            "category":"Shopping",
            "subcategory":"Florist",
            "type":"Retail Goods"
        }
    ],
    "sg:phone":"+90 212 516 3594",
    "sg:province":"Istanbul",
    "sg:tags":[
        "flower"
    ],
    "wof:name":"Nilay ?i?ek?ilik San. Tic. Ltd. Sti.",
    "wof:placetype":"venue"
},
  "geometry": {"coordinates":[28.9721565247,41.0071182251],"type":"Point"}
}