{
  "type": "Feature",
  "properties": {
    "iso:country":"TR",
    "sg:address":"Turan Gunes Bulvari 4.cad.no: 60/7 Yildiz",
    "sg:city":"Besiktas",
    "sg:classifiers":[
        {
            "category":"Communications",
            "subcategory":"Film & Video Production",
            "type":"Services"
        }
    ],
    "sg:phone":"+90 312 440 8525",
    "sg:postcode":"80200",
    "sg:province":"Ankara",
    "sg:tags":[
        "-"
    ],
    "wof:name":"Cyramaxx Films",
    "wof:placetype":"venue"
},
  "geometry": {"coordinates":[30.005645752,40.7737541199],"type":"Point"}
}