{
  "type": "Feature",
  "properties": {
    "iso:country":"TR",
    "sg:address":"Esentepe Mah.kocatepe Cad.g-11 Sok.no:1",
    "sg:city":"Kartal",
    "sg:classifiers":[
        {
            "category":"Manufacturing",
            "subcategory":"Glass & Minerals",
            "type":"Manufacturing & Wholesale Goods"
        }
    ],
    "sg:phone":"+90 216 353 7883",
    "sg:postcode":"46000",
    "sg:province":"Istanbul",
    "sg:tags":[
        "glass-mirror"
    ],
    "wof:name":"Yeni Kartal Cam",
    "wof:placetype":"venue"
},
  "geometry": {"coordinates":[29.1643123627,40.9424858093],"type":"Point"}
}