{
  "type": "Feature",
  "properties": {
    "iso:country":"TR",
    "sg:address":"Zafer Mah. 1040.sok. No:12",
    "sg:city":"Gumusler",
    "sg:classifiers":[
        {
            "category":"Shopping",
            "subcategory":"Crafts & Fabrics",
            "type":"Retail Goods"
        }
    ],
    "sg:phone":"+90 258 371 0204",
    "sg:postcode":"20085",
    "sg:province":"Denizli",
    "sg:tags":[
        "weaving"
    ],
    "wof:name":"Gunsar Tekstil",
    "wof:placetype":"venue"
},
  "geometry": {"coordinates":[29.0792789459,37.799331665],"type":"Point"}
}