{
  "type": "Feature",
  "properties": {
    "addr:full":"Muallim Naci Cad. K?pr? Basi Sok. No:2 Ortak?y Istanbul",
    "addr:housenumber":"?;?;no 2 ortak ? y",
    "addr:street":"Muallim Naci;Pr;Basi Sok.;Istanbul",
    "iso:country":"TR",
    "sg:address":"Muallim Naci Cad. K?pr? Basi Sok. No:2",
    "sg:city":"Ortak?y",
    "sg:classifiers":[
        {
            "category":"Travel",
            "subcategory":"Travel Agent",
            "type":"Entertainment"
        }
    ],
    "sg:phone":"+90 23642342366964",
    "sg:province":"Istanbul",
    "sg:tags":[
        "agency",
        "tourism"
    ],
    "wof:name":"Opus-92 Turizm",
    "wof:placetype":"venue"
},
  "geometry": {"coordinates":[28.9861831665,41.0408554077],"type":"Point"}
}