{
  "type": "Feature",
  "properties": {
    "iso:country":"TR",
    "sg:address":"Serceonu Mah. Bayfuat Cad. Muhendisler Kat:1 No:101",
    "sg:city":"Laleli",
    "sg:classifiers":[
        {
            "category":"Shopping",
            "subcategory":"Crafts & Fabrics",
            "type":"Retail Goods"
        }
    ],
    "sg:phone":"+90 352222458384",
    "sg:postcode":"24300",
    "sg:province":"Kayseri",
    "sg:tags":[
        "yarn"
    ],
    "wof:name":"Safir Dis Ticaret Ve Aracilik Hizm.ltd.sti.",
    "wof:placetype":"venue"
},
  "geometry": {"coordinates":[35.4891357422,38.7225761414],"type":"Point"}
}