{
  "type": "Feature",
  "properties": {
    "addr:full":"Ataturk Cad. Cebesoy Sk. 65/1 Sahrayicedit Maltepe Istanbul 01000",
    "addr:housenumber":"1",
    "addr:postcode":"01000",
    "addr:street":"Ataturk Cad. Cebesoy Sk. 65 /;Maltepe",
    "iso:country":"TR",
    "sg:address":"Ataturk Cad. Cebesoy Sk. 65/1 Sahrayicedit",
    "sg:city":"Maltepe",
    "sg:classifiers":[
        {
            "category":"Wholesale",
            "subcategory":"Books, Periodicals, & Newspapers",
            "type":"Manufacturing & Wholesale Goods"
        }
    ],
    "sg:postcode":"01000",
    "sg:province":"Istanbul",
    "sg:tags":[
        "house",
        "publishing"
    ],
    "wof:name":"Teknoset Ltd.",
    "wof:placetype":"venue"
},
  "geometry": {"coordinates":[29.0907649994,40.9824028015],"type":"Point"}
}