{
  "type": "Feature",
  "properties": {
    "addr:full":"Baksan San. Sitesi 5.blok No:5 Bagdic Eskisehir",
    "addr:housenumber":"no",
    "addr:street":"Baksan",
    "iso:country":"TR",
    "sg:address":"Baksan San. Sitesi 5.blok No:5",
    "sg:city":"Bagdic",
    "sg:classifiers":[
        {
            "category":"Wholesale",
            "subcategory":"Machinery & Supplies",
            "type":"Manufacturing & Wholesale Goods"
        }
    ],
    "sg:phone":"+90 222 320 9520",
    "sg:province":"Eskisehir",
    "sg:tags":[
        "agricultural"
    ],
    "wof:name":"Dundarlar Makine San. Ve Tic. Ltd.sti.",
    "wof:placetype":"venue"
},
  "geometry": {"coordinates":[30.5175457001,39.7700805664],"type":"Point"}
}