{
  "type": "Feature",
  "properties": {
    "iso:country":"TR",
    "sg:address":"Namik Kemal Cd. No:103 Aksaray",
    "sg:city":"Kocasinan",
    "sg:classifiers":[
        {
            "category":"Utilities",
            "subcategory":"Electric",
            "type":"Services"
        }
    ],
    "sg:phone":"+90 212 530 0106",
    "sg:postcode":"38110",
    "sg:province":"Istanbul",
    "sg:tags":[
        "accumulator",
        "-",
        "batery"
    ],
    "wof:name":"Alfa Ak? San. Ltd. Sti.",
    "wof:placetype":"venue"
},
  "geometry": {"coordinates":[28.950176,41.003723],"type":"Point"}
}