{
  "type": "Feature",
  "properties": {
    "addr:full":"Cumhuriyet Bulv. No.373/1 35220 Iskenderun Izmir 31200",
    "addr:housenumber":"no.373 / 1",
    "addr:postcode":"35220;31200",
    "addr:street":"Cumhuriyet Bulv.",
    "iso:country":"TR",
    "sg:address":"Cumhuriyet Bulv. No.373/1 35220",
    "sg:city":"Iskenderun",
    "sg:classifiers":[
        {
            "category":"Manufacturing",
            "subcategory":"Metals",
            "type":"Manufacturing & Wholesale Goods"
        }
    ],
    "sg:phone":"+90 232 422 6130",
    "sg:postcode":"31200",
    "sg:province":"Izmir",
    "sg:tags":[
        "industry"
    ],
    "wof:name":"Altintas M?hendislik Ve ?elik Konstr?ksiyon San. Ve Tic.a.s.",
    "wof:placetype":"venue"
},
  "geometry": {"coordinates":[27.1433906555,38.4411659241],"type":"Point"}
}