{
  "type": "Feature",
  "properties": {
    "iso:country":"TR",
    "sg:address":"28 Nisan Cd. No:52/1-3",
    "sg:city":"?aglayan",
    "sg:classifiers":[
        {
            "category":"Home & Garden",
            "subcategory":"Home Furnishings",
            "type":"Retail Goods"
        }
    ],
    "sg:phone":"+90 212 222 3249",
    "sg:province":"Istanbul",
    "sg:tags":[
        "-curtains",
        "upholstery"
    ],
    "wof:name":"Tupasteks Tekstil San. Tic. A.s.",
    "wof:placetype":"venue"
},
  "geometry": {"coordinates":[28.9744281769,41.0679206848],"type":"Point"}
}