{
  "type": "Feature",
  "properties": {
    "iso:country":"TR",
    "sg:address":"Turgut?zal Bulvari 52/5",
    "sg:city":"Iskitler",
    "sg:classifiers":[
        {
            "category":"Airport",
            "subcategory":"International",
            "type":"Transportation"
        }
    ],
    "sg:phone":"+90 312 384 1706",
    "sg:postcode":"06060",
    "sg:province":"Ankara",
    "wof:name":"Demirgil Transport",
    "wof:placetype":"venue"
},
  "geometry": {"coordinates":[32.8604812622,39.9429283142],"type":"Point"}
}