{
  "type": "Feature",
  "properties": {
    "addr:full":"Turgut Reis Cd. No:26/1 Tandogan Kad\u0131k\u00f6y Ankara 34726",
    "addr:housenumber":"no 26 / 1",
    "addr:postcode":"34726",
    "addr:street":"Turgut Reis",
    "iso:country":"TR",
    "sg:address":"Turgut Reis Cd. No:26/1 Tandogan",
    "sg:city":"Kad\u0131k\u00f6y",
    "sg:classifiers":[
        {
            "category":"Communications",
            "subcategory":"Film & Video Production",
            "type":"Services"
        }
    ],
    "sg:phone":"+90 312 229 9903",
    "sg:postcode":"34726",
    "sg:province":"Ankara",
    "sg:tags":[
        "-"
    ],
    "wof:name":"B?y?k Baskent St?dyosu Video Isletme. A.s.",
    "wof:placetype":"venue"
},
  "geometry": {"coordinates":[32.8480262756,39.9471282959],"type":"Point"}
}