{
  "type": "Feature",
  "properties": {
    "iso:country":"TR",
    "sg:address":"Estim San.sitesi 3.cad. No:104",
    "sg:city":"Kisikkoy",
    "sg:classifiers":[
        {
            "category":"Manufacturing",
            "subcategory":"Building Materials",
            "type":"Manufacturing & Wholesale Goods"
        }
    ],
    "sg:phone":"+90 232 257 5398",
    "sg:province":"Izmir",
    "sg:tags":[
        "lifts-elevators"
    ],
    "wof:name":"Astor Asansor Makina Motor Imalat San. Tic.ltd.sti.",
    "wof:placetype":"venue"
},
  "geometry": {"coordinates":[27.1296863556,38.4186973572],"type":"Point"}
}