{
  "type": "Feature",
  "properties": {
    "iso:country":"TR",
    "sg:address":"Akdeniz Cad. 1",
    "sg:city":"Izmir",
    "sg:classifiers":[
        {
            "category":"Banks & Credit Unions",
            "subcategory":"Bank",
            "type":"Services"
        }
    ],
    "sg:phone":"+90 232 489 2000",
    "sg:province":"35210",
    "wof:name":"Finansbank As",
    "wof:placetype":"venue"
},
  "geometry": {"coordinates":[27.132601,38.427837],"type":"Point"}
}