{
  "type": "Feature",
  "properties": {
    "iso:country":"TR",
    "sg:address":"Kayalik Mah.662 Sok.no:6",
    "sg:city":"Bayramic",
    "sg:classifiers":[
        {
            "category":"Food & Beverages",
            "subcategory":"Dairy",
            "type":"Retail Goods"
        }
    ],
    "sg:phone":"+90 258 261 9720",
    "sg:postcode":"10900",
    "sg:province":"Denizli",
    "sg:tags":[
        "pruducts",
        "milk"
    ],
    "wof:name":"Aktan S?t Mam.san.tic.",
    "wof:placetype":"venue"
},
  "geometry": {"coordinates":[29.0941886902,37.7774238586],"type":"Point"}
}