{
  "type": "Feature",
  "properties": {
    "addr:full":"Imes San.sitesi E Blok 501.sok. No:2 Dudullu-umraniye Tuzla Istanbul 81700",
    "addr:housenumber":"no",
    "addr:postcode":"81700",
    "addr:street":"Dudullu-Umraniye;Istanbul",
    "iso:country":"TR",
    "sg:address":"Imes San.sitesi E Blok 501.sok. No:2 Dudullu-umraniye",
    "sg:city":"Tuzla",
    "sg:classifiers":[
        {
            "category":"Home & Garden",
            "subcategory":"Kitchen Supply",
            "type":"Retail Goods"
        }
    ],
    "sg:phone":"+90 216 364 3088",
    "sg:postcode":"81700",
    "sg:province":"Istanbul",
    "sg:tags":[
        "wardrobe"
    ],
    "wof:name":"Gelisim Mak.mutfak -banyo Aks.",
    "wof:placetype":"venue"
},
  "geometry": {"coordinates":[28.9759254456,41.0123786926],"type":"Point"}
}