{
  "type": "Feature",
  "properties": {
    "addr:full":"Barbaros Bulvari 44/8 Balmumcu 42200 Istanbul",
    "addr:housenumber":"44 / 8",
    "addr:postcode":"42200",
    "addr:street":"Barbaros Bulvari;Balmumcu",
    "iso:country":"TR",
    "sg:address":"Barbaros Bulvari 44/8 Balmumcu",
    "sg:city":"42200",
    "sg:classifiers":[
        {
            "category":"Banks & Credit Unions",
            "subcategory":"Investment Brokerage",
            "type":"Services"
        }
    ],
    "sg:phone":"+90 212 266 8283",
    "sg:province":"Istanbul",
    "sg:tags":[
        "course",
        "language"
    ],
    "wof:name":"The Sandwich Method",
    "wof:placetype":"venue"
},
  "geometry": {"coordinates":[29.0116100311,41.0619277954],"type":"Point"}
}