{
  "type": "Feature",
  "properties": {
    "addr:full":"Izmir Ankara Asfalti Bayramkuyu Mevkii No:202 Kemalpasa G?g?en Izmir",
    "addr:housenumber":"202;? g ?",
    "addr:street":"Bayramkuyu Mevkii No;Kemalpasa G;En Izmir",
    "iso:country":"TR",
    "sg:address":"Izmir Ankara Asfalti Bayramkuyu Mevkii No:202 Kemalpasa",
    "sg:city":"G?g?en",
    "sg:classifiers":[
        {
            "category":"Manufacturing",
            "subcategory":"Rubber & Plastics",
            "type":"Manufacturing & Wholesale Goods"
        }
    ],
    "sg:phone":"+90 232 877 0580",
    "sg:province":"Izmir",
    "sg:tags":[
        "industry"
    ],
    "wof:name":"Pms Polietilen Mamulleri San. Tic. Ltd. Sti.",
    "wof:placetype":"venue"
},
  "geometry": {"coordinates":[27.261964798,38.4359550476],"type":"Point"}
}