{
  "type": "Feature",
  "properties": {
    "addr:full":"Perpa Ticaret Merkezi A Blok Kat:13 No: 2085 Okmeydani Topkapi Istanbul 34020",
    "addr:housenumber":"blok kat 13 no 2085",
    "addr:postcode":"34020",
    "addr:street":"A;Okmeydani",
    "iso:country":"TR",
    "sg:address":"Perpa Ticaret Merkezi A Blok Kat:13 No: 2085 Okmeydani",
    "sg:city":"Topkapi",
    "sg:classifiers":[
        {
            "category":"Shopping",
            "subcategory":"Stationery & Office Supplies",
            "type":"Retail Goods"
        }
    ],
    "sg:phone":"+90 212221582522",
    "sg:postcode":"34020",
    "sg:province":"Istanbul",
    "sg:tags":[
        "paper"
    ],
    "wof:name":"Atilim Ic Ve Dis Ticaret",
    "wof:placetype":"venue"
},
  "geometry": {"coordinates":[28.9026374817,40.9924430847],"type":"Point"}
}