{
  "type": "Feature",
  "properties": {
    "iso:country":"TR",
    "sg:address":"Menderes Mah. Nalcaci Cad. Emlakbankasi Alti No:74/f",
    "sg:city":"Mecidiyek\u00f6y",
    "sg:classifiers":[
        {
            "category":"Utilities",
            "subcategory":"Natural Gas",
            "type":"Services"
        }
    ],
    "sg:phone":"+90 332 238 8044",
    "sg:province":"Konya",
    "sg:tags":[
        "tank-heating-natural"
    ],
    "wof:name":"Alamat Iklimlendirme Muh.ins.ltd.sti.",
    "wof:placetype":"venue"
},
  "geometry": {"coordinates":[32.8623580933,38.0141410828],"type":"Point"}
}