{
  "type": "Feature",
  "properties": {
    "addr:full":"Okcumusa Cad. Tutsak Sk. No.23/405 Karak? ?igli Istanbul 35600",
    "addr:housenumber":"/ 405;? ?",
    "addr:postcode":"35600",
    "addr:street":"Okcumusa Cad. Tutsak Sk. No.23",
    "iso:country":"TR",
    "sg:address":"Okcumusa Cad. Tutsak Sk. No.23/405 Karak?",
    "sg:city":"?igli",
    "sg:classifiers":[
        {
            "category":"Shopping",
            "subcategory":"Computers & Home Electronics",
            "type":"Retail Goods"
        }
    ],
    "sg:phone":"+90 212 254 7140",
    "sg:postcode":"35600",
    "sg:province":"Istanbul",
    "sg:tags":[
        "product",
        "electric-electronic"
    ],
    "wof:name":"Den-san Ltd.sti.",
    "wof:placetype":"venue"
},
  "geometry": {"coordinates":[28.9861831665,41.0408554077],"type":"Point"}
}