{
  "type": "Feature",
  "properties": {
    "addr:full":"Akdeniz Cad. No:76/7 Fatih Beyoglu Istanbul 46810",
    "addr:housenumber":"76 / 7",
    "addr:postcode":"46810",
    "addr:street":"Akdeniz Cad. No;Fatih Beyoglu",
    "iso:country":"TR",
    "sg:address":"Akdeniz Cad. No:76/7 Fatih",
    "sg:city":"Beyoglu",
    "sg:classifiers":[
        {
            "category":"Banks & Credit Unions",
            "subcategory":"Investment Brokerage",
            "type":"Services"
        }
    ],
    "sg:phone":"+90 212525697091",
    "sg:postcode":"46810",
    "sg:province":"Istanbul",
    "sg:tags":[
        "course",
        "language"
    ],
    "wof:name":"Easyway International Student Center",
    "wof:placetype":"venue"
},
  "geometry": {"coordinates":[29.1548461914,41.0815429688],"type":"Point"}
}