{
  "type": "Feature",
  "properties": {
    "addr:full":"Kazanci Yokusu No:48 Cihangir Ikitelli Istanbul 34306",
    "addr:postcode":"34306",
    "addr:street":"No 48",
    "iso:country":"TR",
    "sg:address":"Kazanci Yokusu No:48 Cihangir",
    "sg:city":"Ikitelli",
    "sg:orig_category":"Beaty Parlors",
    "sg:phone":"+90 212 243 3551",
    "sg:postcode":"34306",
    "sg:province":"Istanbul",
    "wof:name":"Cengiz Kuaf?r Kaynak Salonu",
    "wof:placetype":"venue"
},
  "geometry": {"coordinates":[28.986069,41.032108],"type":"Point"}
}