{
  "type": "Feature",
  "properties": {
    "addr:full":"Gedikpasa C. No.100 Emin?? 34450 Istanbul",
    "addr:housenumber":"? ?",
    "addr:postcode":"34450",
    "addr:street":"C.",
    "iso:country":"TR",
    "sg:address":"Gedikpasa C. No.100",
    "sg:city":"Emin?? 34450",
    "sg:classifiers":[
        {
            "category":"Shopping",
            "subcategory":"Clothing, Apparel, & Fashions",
            "type":"Retail Goods"
        }
    ],
    "sg:phone":"+90 212 517 1876",
    "sg:province":"Istanbul",
    "sg:tags":[
        "bag-belt-accessories"
    ],
    "wof:name":"Ta?yildiz ?anta Ve Saraciye Ltd.sti.",
    "wof:placetype":"venue"
},
  "geometry": {"coordinates":[29.272097,40.971249],"type":"Point"}
}