{
  "type": "Feature",
  "properties": {
    "addr:full":"Ali Cetinkaya Bulvari No:53/5 Alsancak Izmir 01365",
    "addr:housenumber":"no 53 / 5",
    "addr:postcode":"01365",
    "addr:street":"Cetinkaya Bulvari",
    "iso:country":"TR",
    "sg:address":"Ali Cetinkaya Bulvari No:53/5",
    "sg:city":"Alsancak",
    "sg:classifiers":[
        {
            "category":"Transit Center",
            "subcategory":"Freight",
            "type":"Transportation"
        }
    ],
    "sg:phone":"+90 232 463 7553",
    "sg:postcode":"01365",
    "sg:province":"Izmir",
    "wof:name":"Acs Uluslararasi Tasimacilik Ve Tic.ltd.sti.",
    "wof:placetype":"venue"
},
  "geometry": {"coordinates":[27.1421928406,38.4345817566],"type":"Point"}
}