{
  "type": "Feature",
  "properties": {
    "addr:full":"Mete Cad. No:24/1 Ovalar Apt. 80090 Taksim Istanbul 24040",
    "addr:housenumber":"24 / 1",
    "addr:postcode":"80090;24040",
    "addr:street":"Mete Cad. No;Ovalar",
    "iso:country":"TR",
    "sg:address":"Mete Cad. No:24/1 Ovalar Apt. 80090",
    "sg:city":"Taksim",
    "sg:classifiers":[
        {
            "category":"Banks & Credit Unions",
            "subcategory":"Investment Brokerage",
            "type":"Services"
        }
    ],
    "sg:phone":"+90 212 334 2970",
    "sg:postcode":"24040",
    "sg:province":"Istanbul",
    "sg:tags":[
        "line",
        "air"
    ],
    "wof:name":"Virgin Atlantic",
    "wof:placetype":"venue"
},
  "geometry": {"coordinates":[28.9759254456,41.0123786926],"type":"Point"}
}