{
  "type": "Feature",
  "properties": {
    "addr:full":"Sefer Pasa M Derekendir Sok. No:37/b Bak\u0131rk\u00f6y Gaziantep",
    "addr:housenumber":"no 37 / b",
    "addr:street":"Pasa;Derekendir Sok.;Bakirkoey Gaziantep",
    "iso:country":"TR",
    "sg:address":"Sefer Pasa M Derekendir Sok. No:37/b",
    "sg:city":"Bak\u0131rk\u00f6y",
    "sg:classifiers":[
        {
            "category":"Manufacturing",
            "subcategory":"Glass & Minerals",
            "type":"Manufacturing & Wholesale Goods"
        }
    ],
    "sg:phone":"+90 342 221 1643",
    "sg:province":"Gaziantep",
    "sg:tags":[
        "glass-mirror"
    ],
    "wof:name":"Emre Cam",
    "wof:placetype":"venue"
},
  "geometry": {"coordinates":[37.3761024475,37.0629463196],"type":"Point"}
}