{
  "type": "Feature",
  "properties": {
    "iso:country":"TR",
    "sg:address":"Isto? Istanbul Toptancilar ?arsisi 9.ada No:31-33 34550 Mahmutbey",
    "sg:city":"?atalca",
    "sg:classifiers":[
        {
            "category":"Shopping",
            "subcategory":"Stationery & Office Supplies",
            "type":"Retail Goods"
        }
    ],
    "sg:phone":"+90 212 659 4040",
    "sg:province":"Istanbul",
    "wof:name":"Melsan B?ro Malzemeleri Sanayi Ve Ticaret A.s.",
    "wof:placetype":"venue"
},
  "geometry": {"coordinates":[28.820398,41.057652],"type":"Point"}
}