{
  "type": "Feature",
  "properties": {
    "iso:country":"TR",
    "sg:address":"Baksan San. Sitesi 34.blok No:3-4-5",
    "sg:city":"Bandirma",
    "sg:orig_category":"Food Machinies",
    "sg:phone":"+90 222 335 0505",
    "sg:postcode":"10200",
    "sg:province":"Eskisehir",
    "wof:name":"Onder Makina Sanayi",
    "wof:placetype":"venue"
},
  "geometry": {"coordinates":[30.5175457001,39.7700805664],"type":"Point"}
}