{
  "type": "Feature",
  "properties": {
    "iso:country":"TR",
    "sg:address":"Imkb Building, Istinye, 80860 Istanbul",
    "sg:city":"Istanbul",
    "sg:classifiers":[
        {
            "category":"Banks & Credit Unions",
            "subcategory":"Bank",
            "type":"Services"
        }
    ],
    "sg:phone":"+90 212 298 2160",
    "sg:province":"Istanbul",
    "sg:website":"http://www.feas.org",
    "wof:name":"Federation Of Euro-asian Stock Exchanges (feas)",
    "wof:placetype":"venue"
},
  "geometry": {"coordinates":[29.037479,41.110271],"type":"Point"}
}