{
  "type": "Feature",
  "properties": {
    "addr:full":"Yeni Yalova Yolu 2.km G??k? Bursa",
    "addr:housenumber":"2.km g ? ? k ?",
    "addr:street":"Yalova Yolu",
    "iso:country":"TR",
    "sg:address":"Yeni Yalova Yolu 2.km",
    "sg:city":"G??k?",
    "sg:classifiers":[
        {
            "category":"Shopping",
            "subcategory":"Crafts & Fabrics",
            "type":"Retail Goods"
        }
    ],
    "sg:phone":"+90 224 256 6000",
    "sg:province":"Bursa",
    "sg:tags":[
        "weaving"
    ],
    "wof:name":"Butona Tekstil A.s",
    "wof:placetype":"venue"
},
  "geometry": {"coordinates":[29.0580043793,40.1947555542],"type":"Point"}
}