{
  "type": "Feature",
  "properties": {
    "iso:country":"TR",
    "sg:address":"Y.posta Cd. Vefa Bayiri Sk. No:14/2 G.tepe",
    "sg:city":"Bak\u0131rk\u00f6y",
    "sg:classifiers":[
        {
            "category":"Professional",
            "subcategory":"Detective & Security Services",
            "type":"Services"
        }
    ],
    "sg:phone":"+90 212 288 3800",
    "sg:postcode":"34720",
    "sg:province":"Istanbul",
    "sg:tags":[
        "material"
    ],
    "wof:name":"Bardes Ltd. Sti.",
    "wof:placetype":"venue"
},
  "geometry": {"coordinates":[28.980183,41.080418],"type":"Point"}
}