{
  "type": "Feature",
  "properties": {
    "addr:full":"Atat?k Cd. Ugur Ish. K:1 No:132 D:75 Sehit Mustafa Mh. Tarsus Fatih I?el 01740",
    "addr:housenumber":"1;75",
    "addr:postcode":"01740",
    "addr:street":"K Cd.;Ish. K;No 132 D;Sehit Mustafa Mh.;El",
    "iso:country":"TR",
    "sg:address":"Atat?k Cd. Ugur Ish. K:1 No:132 D:75 Sehit Mustafa Mh. Tarsus",
    "sg:city":"Fatih",
    "sg:classifiers":[
        {
            "category":"Organizations",
            "subcategory":"Membership Organization",
            "type":"Services"
        }
    ],
    "sg:phone":"+90 324 613 2569",
    "sg:postcode":"01740",
    "sg:province":"I?el",
    "wof:name":"Tarsus Turk Sanat Musikisi Dernegi",
    "wof:placetype":"venue"
},
  "geometry": {"coordinates":[34.8869895935,36.9086418152],"type":"Point"}
}