{
  "type": "Feature",
  "properties": {
    "iso:country":"TR",
    "sg:address":"Bankalar Cad.no: 16",
    "sg:city":"Bergama",
    "sg:classifiers":[
        {
            "category":"Farming",
            "subcategory":"Farm",
            "type":"Manufacturing & Wholesale Goods"
        }
    ],
    "sg:phone":"+90 232 633 2804",
    "sg:postcode":"35700",
    "sg:province":"Izmir",
    "sg:tags":[
        "agricultural",
        "product"
    ],
    "wof:name":"Karahanlar Tar.urun.san.tic.a.s.",
    "wof:placetype":"venue"
},
  "geometry": {"coordinates":[29.1720409393,40.910823822],"type":"Point"}
}