{
  "type": "Feature",
  "properties": {
    "iso:country":"TR",
    "sg:address":"Cengiz Topel Cad. Sefalilar Ishani K: 2 No: 10 Y?ksekova",
    "sg:city":"Beykoz",
    "sg:classifiers":[
        {
            "category":"Travel",
            "subcategory":"Travel Agent",
            "type":"Entertainment"
        }
    ],
    "sg:phone":"+90 438 351 5252",
    "sg:postcode":"37870",
    "sg:province":"Hakkari",
    "sg:tags":[
        "agency",
        "tourism"
    ],
    "wof:name":"Onay Turizm",
    "wof:placetype":"venue"
},
  "geometry": {"coordinates":[44.0831298828,37.7704467773],"type":"Point"}
}