{
  "type": "Feature",
  "properties": {
    "iso:country":"TR",
    "sg:address":"Millet Cd. No:64/1 Fatih",
    "sg:city":"\u00dcmraniye",
    "sg:classifiers":[
        {
            "category":"Farming",
            "subcategory":"Fish & Marine Products",
            "type":"Manufacturing & Wholesale Goods"
        }
    ],
    "sg:phone":"+90 212 525 9185",
    "sg:province":"Istanbul",
    "sg:tags":[
        "automotive"
    ],
    "wof:name":"Uysallar Otomotiv San. Tic. A.s.",
    "wof:placetype":"venue"
},
  "geometry": {"coordinates":[28.0863113403,41.0754432678],"type":"Point"}
}