{
  "type": "Feature",
  "properties": {
    "iso:country":"TR",
    "sg:address":"Perpa Tic.merkezi 11.kat. A Blok 1436 Okmeydani/sisli",
    "sg:city":"\u00dcmraniye",
    "sg:classifiers":[
        {
            "category":"Utilities",
            "subcategory":"Fuel Oil & Lpg",
            "type":"Services"
        }
    ],
    "sg:phone":"+90 212 210 0540",
    "sg:province":"Istanbul",
    "sg:tags":[
        "gas",
        "system"
    ],
    "wof:name":"Nova Engineering Tunagas Ltd.",
    "wof:placetype":"venue"
},
  "geometry": {"coordinates":[28.987903595,41.0586929321],"type":"Point"}
}