{
  "type": "Feature",
  "properties": {
    "iso:country":"TR",
    "sg:address":"B??dere Cad.no 20 G?ilcineli Apt Kat:3 D:6",
    "sg:city":"Sisli",
    "sg:classifiers":[
        {
            "category":"Professional",
            "subcategory":"Detective & Security Services",
            "type":"Services"
        }
    ],
    "sg:phone":"+90 212 224 4711",
    "sg:postcode":"80220",
    "sg:province":"Istanbul",
    "sg:tags":[
        "material"
    ],
    "wof:name":"A.g.m M?endislik Elektronik G?enlik Sistemler",
    "wof:placetype":"venue"
},
  "geometry": {"coordinates":[28.975925,41.012379],"type":"Point"}
}