{
  "type": "Feature",
  "properties": {
    "iso:country":"TR",
    "sg:address":"Z. G?alp Cd. K?e Apt. No:22 D:30 Sihhiye",
    "sg:city":"\u00dcsk\u00fcdar",
    "sg:classifiers":[
        {
            "category":"Building & Trades",
            "subcategory":"Construction",
            "type":"Services"
        }
    ],
    "sg:phone":"+90 312 431 0095",
    "sg:province":"Ankara",
    "sg:tags":[
        "foundation"
    ],
    "wof:name":"Etibank Toplulugu Yardim Vakfi",
    "wof:placetype":"venue"
},
  "geometry": {"coordinates":[36.3320388794,41.2859153748],"type":"Point"}
}