{
  "type": "Feature",
  "properties": {
    "addr:full":"I.m.c 5.blok No:5558 Unkapani Istanbul 55020",
    "addr:housenumber":"5.blok no 5558",
    "addr:postcode":"55020",
    "addr:street":"Unkapani Istanbul",
    "iso:country":"TR",
    "sg:address":"I.m.c 5.blok No:5558",
    "sg:city":"Unkapani",
    "sg:classifiers":[
        {
            "category":"Manufacturing",
            "subcategory":"Textiles",
            "type":"Manufacturing & Wholesale Goods"
        }
    ],
    "sg:phone":"+90 212 520 9688",
    "sg:postcode":"55020",
    "sg:province":"Istanbul",
    "sg:tags":[
        "cloth",
        "worker"
    ],
    "wof:name":"Pgs Personel Giyim San.tic. Ltd.sti.",
    "wof:placetype":"venue"
},
  "geometry": {"coordinates":[28.7931404114,41.0928535461],"type":"Point"}
}