{
  "type": "Feature",
  "properties": {
    "addr:full":"Gulumbe Koyu Mersin Bilecik 52750",
    "addr:postcode":"52750",
    "iso:country":"TR",
    "sg:address":"Gulumbe Koyu",
    "sg:city":"Mersin",
    "sg:classifiers":[
        {
            "category":"Mining & Drilling",
            "type":"Manufacturing & Wholesale Goods"
        }
    ],
    "sg:phone":"+90 228 223 3102",
    "sg:postcode":"52750",
    "sg:province":"Bilecik",
    "sg:tags":[
        "industry",
        "mine"
    ],
    "wof:name":"Bimtas A.s.",
    "wof:placetype":"venue"
},
  "geometry": {"coordinates":[29.9804992676,40.1426010132],"type":"Point"}
}