{
  "type": "Feature",
  "properties": {
    "iso:country":"TR",
    "sg:address":"Ankara Cad. No:42",
    "sg:city":"Gaziosmanpasa",
    "sg:orig_category":"Scavening Services",
    "sg:phone":"+90 262 331 7599",
    "sg:postcode":"34100",
    "sg:province":"Kocaeli",
    "wof:name":"Nas Insaat Gida Sanayi Ve Ticaret Ltd. Sti.",
    "wof:placetype":"venue"
},
  "geometry": {"coordinates":[30.026228,40.753242],"type":"Point"}
}