{
  "type": "Feature",
  "properties": {
    "addr:full":"Inonu Mah. Ibrahimaga Cad. No:191 Gebze Kocaeli 41400",
    "addr:housenumber":"191",
    "addr:postcode":"41400",
    "addr:street":"Inonu Mah. Ibrahimaga Cad. No",
    "iso:country":"TR",
    "sg:address":"Inonu Mah. Ibrahimaga Cad. No:191",
    "sg:city":"Gebze",
    "sg:classifiers":[
        {
            "category":"Home & Garden",
            "subcategory":"Hardware",
            "type":"Retail Goods"
        }
    ],
    "sg:phone":"+90 262 643 6411",
    "sg:postcode":"41400",
    "sg:province":"Kocaeli",
    "sg:tags":[
        "store"
    ],
    "wof:name":"Ats Metal Mekanik Tesisat Taah.ltd.sti.",
    "wof:placetype":"venue"
},
  "geometry": {"coordinates":[29.9345855713,40.7669563293],"type":"Point"}
}