{
  "type": "Feature",
  "properties": {
    "iso:country":"TR",
    "sg:address":"Siyavus Pasa Sk.melek Is Hani No:56/57 S?leymaniye/istanbul Fabrika:ugur Mumcu Mh.2274 Sk.no:15/17 S",
    "sg:city":"Emin\u00f6n\u00fc/Ca\u011falo\u011flu",
    "sg:classifiers":[
        {
            "category":"Home & Garden",
            "subcategory":"Kitchen Supply",
            "type":"Retail Goods"
        }
    ],
    "sg:postcode":"34110",
    "sg:province":"Istanbul",
    "sg:tags":[
        "steel",
        "utensil"
    ],
    "wof:name":"Mimar Sinan Mutfak Esyalari Imalat San.i? Ve Dis T",
    "wof:placetype":"venue"
},
  "geometry": {"coordinates":[28.975925,41.012379],"type":"Point"}
}