{
  "type": "Feature",
  "properties": {
    "iso:country":"TR",
    "sg:address":"Selanik Cd. No:33/2 Kizilay",
    "sg:city":"Beyoglu",
    "sg:classifiers":[
        {
            "category":"Wholesale",
            "subcategory":"Books, Periodicals, & Newspapers",
            "type":"Manufacturing & Wholesale Goods"
        }
    ],
    "sg:phone":"+90 312 419 4926",
    "sg:postcode":"46810",
    "sg:province":"Ankara",
    "sg:tags":[
        "house",
        "publishing"
    ],
    "wof:name":"Arty Yayincilik Reklam. Turizm",
    "wof:placetype":"venue"
},
  "geometry": {"coordinates":[32.8566589355,39.9195251465],"type":"Point"}
}