{
  "type": "Feature",
  "properties": {
    "addr:full":"Maslakcesme Cad.no: 30 Sefakoy Ikitelli/K\u00fc\u00e7\u00fck\u00e7ekmece Istanbul 34670",
    "addr:housenumber":"30",
    "addr:postcode":"34670",
    "addr:street":"Sefakoy Ikitelli / Kuec\u0327Uekc\u0327Ekmece",
    "iso:country":"TR",
    "sg:address":"Maslakcesme Cad.no: 30 Sefakoy",
    "sg:city":"Ikitelli/K\u00fc\u00e7\u00fck\u00e7ekmece",
    "sg:classifiers":[
        {
            "category":"Home & Garden",
            "subcategory":"Building Materials",
            "type":"Retail Goods"
        }
    ],
    "sg:phone":"+90 212 425 9627",
    "sg:postcode":"34670",
    "sg:province":"Istanbul",
    "sg:tags":[
        "window",
        "door",
        "plastic"
    ],
    "wof:name":"Yelpen Pvc Kapi Ve Pencere Sistemleri",
    "wof:placetype":"venue"
},
  "geometry": {"coordinates":[28.7977390289,41.0147361755],"type":"Point"}
}