{
  "type": "Feature",
  "properties": {
    "iso:country":"TR",
    "sg:address":"Bebek L",
    "sg:city":"Cankaya",
    "sg:classifiers":[
        {
            "category":"Government",
            "subcategory":"Embassy",
            "type":"Public Place"
        }
    ],
    "sg:phone":"+90 212 263 3989",
    "sg:postcode":"07080",
    "sg:province":"Istanbul",
    "sg:tags":[
        "foreign"
    ],
    "wof:name":"Monaco",
    "wof:placetype":"venue"
},
  "geometry": {"coordinates":[29.0672397614,40.9666900635],"type":"Point"}
}