{
  "type": "Feature",
  "properties": {
    "iso:country":"TR",
    "sg:address":"Dalboyu Sk. No:31/b Siteler",
    "sg:city":"Maltepe",
    "sg:classifiers":[
        {
            "category":"Home & Garden",
            "subcategory":"Home Furnishings",
            "type":"Retail Goods"
        }
    ],
    "sg:phone":"+90 312 353 2884",
    "sg:postcode":"01000",
    "sg:province":"Ankara",
    "sg:tags":[
        "quilt",
        "bed"
    ],
    "wof:name":"Benan Tekstil",
    "wof:placetype":"venue"
},
  "geometry": {"coordinates":[32.895912,39.961815],"type":"Point"}
}