{
  "type": "Feature",
  "properties": {
    "iso:country":"TR",
    "sg:address":"Keresteciler Sit. Alaybey Sk. No:15 Merter",
    "sg:city":"Cagaloglu",
    "sg:classifiers":[
        {
            "category":"Freight",
            "type":"Transportation"
        }
    ],
    "sg:phone":"+90 212 556 3400",
    "sg:postcode":"34410",
    "sg:province":"Istanbul",
    "sg:tags":[
        "packing",
        "industry"
    ],
    "wof:name":"?zt?kel Basim Ve Ambalaj San. A.s.",
    "wof:placetype":"venue"
},
  "geometry": {"coordinates":[28.9957962036,41.0822792053],"type":"Point"}
}