{
  "type": "Feature",
  "properties": {
    "addr:full":"Dikilitas Cad. No:7 Merkez Sivas 55020",
    "addr:postcode":"55020",
    "addr:street":"Dikilitas Cad. No 7 Merkez",
    "iso:country":"TR",
    "sg:address":"Dikilitas Cad. No:7",
    "sg:city":"Merkez",
    "sg:classifiers":[
        {
            "category":"Manufacturing",
            "subcategory":"Wood Products",
            "type":"Manufacturing & Wholesale Goods"
        }
    ],
    "sg:phone":"+90 346 223 2358",
    "sg:postcode":"55020",
    "sg:province":"Sivas",
    "sg:tags":[
        "forest"
    ],
    "wof:name":"Sedef Orman Yan Urunleri",
    "wof:placetype":"venue"
},
  "geometry": {"coordinates":[37.0230178833,39.7510223389],"type":"Point"}
}