{
  "type": "Feature",
  "properties": {
    "iso:country":"TR",
    "sg:address":"Samanyolu Sk. Isik Apt. No:42/1",
    "sg:city":"Osmanbey",
    "sg:classifiers":[
        {
            "category":"Shopping",
            "subcategory":"Clothing, Apparel, & Fashions",
            "type":"Retail Goods"
        }
    ],
    "sg:phone":"+90 212 247 6565",
    "sg:postcode":"63000",
    "sg:province":"Istanbul",
    "sg:tags":[
        "men",
        "wear"
    ],
    "wof:name":"Egemen Giyim",
    "wof:placetype":"venue"
},
  "geometry": {"coordinates":[28.987657547,41.0566482544],"type":"Point"}
}