{
  "type": "Feature",
  "properties": {
    "addr:full":"Sanayi Mh.sancakli Cd.no:6 Merter G?g?en Istanbul",
    "addr:housenumber":"6;? g ?",
    "addr:street":"Cd.No;Merter G",
    "iso:country":"TR",
    "sg:address":"Sanayi Mh.sancakli Cd.no:6 Merter",
    "sg:city":"G?g?en",
    "sg:classifiers":[
        {
            "category":"Parking",
            "subcategory":"Garage",
            "type":"Transportation"
        }
    ],
    "sg:phone":"+90 212642135455",
    "sg:province":"Istanbul",
    "sg:tags":[
        "zipper"
    ],
    "wof:name":"Neto Fermuar San. Tic. Ltd. Sti.",
    "wof:placetype":"venue"
},
  "geometry": {"coordinates":[28.9759254456,41.0123786926],"type":"Point"}
}