{
  "type": "Feature",
  "properties": {
    "addr:full":"Des Sanayi Sitesi 106 Sk. B12 Blok No:13 Y.dudullu \u00dcmraniye Istanbul",
    "addr:housenumber":"106;blok no 13",
    "addr:postcode":"b12",
    "addr:street":"Des Sanayi Sitesi;Sk.;Y.Dudullu",
    "iso:country":"TR",
    "sg:address":"Des Sanayi Sitesi 106 Sk. B12 Blok No:13 Y.dudullu",
    "sg:city":"\u00dcmraniye",
    "sg:orig_category":"Des Istanbul",
    "sg:phone":"+90 216 499 5260",
    "sg:province":"Istanbul",
    "wof:name":"Ege Dis Ticaret Yedek Par?a Ithalat Ihracat Ltd.st",
    "wof:placetype":"venue"
},
  "geometry": {"coordinates":[28.9861793518,41.040851593],"type":"Point"}
}