{
  "type": "Feature",
  "properties": {
    "iso:country":"TR",
    "sg:address":"Ostim San. Sit. 3. Blok 3/a Sk. No:2-4-6",
    "sg:city":"Kagithane",
    "sg:classifiers":[
        {
            "category":"Home & Garden",
            "subcategory":"Hardware",
            "type":"Retail Goods"
        }
    ],
    "sg:phone":"+90 312 354 1106",
    "sg:postcode":"34406",
    "sg:province":"Ankara",
    "sg:tags":[
        "generator",
        "power"
    ],
    "wof:name":"Aremsan Elektrik Makine San. Tic. Ltd. Sti.",
    "wof:placetype":"venue"
},
  "geometry": {"coordinates":[32.8560333252,39.9438743591],"type":"Point"}
}