{
  "type": "Feature",
  "properties": {
    "addr:full":"Mescitli Sok. No:23/a Kad\u0131k\u00f6y Istanbul 34990",
    "addr:housenumber":"no 23 / a",
    "addr:postcode":"34990",
    "addr:street":"Mescitli Sok.",
    "iso:country":"TR",
    "sg:address":"Mescitli Sok. No:23/a",
    "sg:city":"Kad\u0131k\u00f6y",
    "sg:orig_category":"Muhtarliklar",
    "sg:phone":"+90 216 385 5100",
    "sg:postcode":"34990",
    "sg:province":"Istanbul",
    "wof:name":"Sahra-i Cedid Mahallesi Muhtari:sadan Batok",
    "wof:placetype":"venue"
},
  "geometry": {"coordinates":[29.0838813782,40.9804534912],"type":"Point"}
}