{
  "type": "Feature",
  "properties": {
    "addr:full":"Zubeyde Hanim Cad. No:208 Zeytinburnu \u00c7orlu Istanbul",
    "addr:housenumber":"208",
    "addr:street":"Hanim Cad. No;Zeytinburnu",
    "iso:country":"TR",
    "sg:address":"Zubeyde Hanim Cad. No:208 Zeytinburnu",
    "sg:city":"\u00c7orlu",
    "sg:classifiers":[
        {
            "category":"Shopping",
            "subcategory":"Luggage & Leather Goods",
            "type":"Retail Goods"
        }
    ],
    "sg:phone":"+90 212 547 1283",
    "sg:province":"Istanbul",
    "sg:tags":[
        "leather-fur",
        "wear"
    ],
    "wof:name":"Sayram Collection",
    "wof:placetype":"venue"
},
  "geometry": {"coordinates":[28.9025211334,40.9839324951],"type":"Point"}
}