{
  "type": "Feature",
  "properties": {
    "addr:full":"Birlik San. Sit. 3 Cd. No:101 B.?ekmece Top?lar Istanbul 34055",
    "addr:housenumber":"3;no 101 b. ?;?",
    "addr:postcode":"34055",
    "addr:street":"Cd.;Ekmece Top",
    "iso:country":"TR",
    "sg:address":"Birlik San. Sit. 3 Cd. No:101 B.?ekmece",
    "sg:city":"Top?lar",
    "sg:classifiers":[
        {
            "category":"Manufacturing",
            "subcategory":"Tools & Machinery",
            "type":"Manufacturing & Wholesale Goods"
        }
    ],
    "sg:phone":"+90 212 875 1286",
    "sg:postcode":"34055",
    "sg:province":"Istanbul",
    "sg:tags":[
        "machine",
        "industry"
    ],
    "wof:name":"Din?kal Elek. Makina San. Tic. Ltd. Sti.",
    "wof:placetype":"venue"
},
  "geometry": {"coordinates":[28.9230213165,41.0406188965],"type":"Point"}
}