{
  "type": "Feature",
  "properties": {
    "iso:country":"TR",
    "sg:address":"Demirtaspasa Mah. Selvili Sok.gilipbey Ap. No: 9",
    "sg:city":"Uskudar",
    "sg:classifiers":[
        {
            "category":"Banks & Credit Unions",
            "subcategory":"Investment Brokerage",
            "type":"Services"
        }
    ],
    "sg:phone":"+90 224 271 4673",
    "sg:postcode":"34704",
    "sg:province":"Bursa",
    "sg:tags":[
        "-",
        "export",
        "import"
    ],
    "wof:name":"Goknar Ic Ve Dis Tic. Ltd. Sti.",
    "wof:placetype":"venue"
},
  "geometry": {"coordinates":[29.0586109161,40.1844291687],"type":"Point"}
}