{
  "type": "Feature",
  "properties": {
    "addr:full":"Burgaz Mah.su?m Mevkii Milas Mugla 48200",
    "addr:postcode":"48200",
    "addr:street":"M Mevkii Milas",
    "iso:country":"TR",
    "sg:address":"Burgaz Mah.su?m Mevkii",
    "sg:city":"Milas",
    "sg:classifiers":[
        {
            "category":"Home & Garden",
            "subcategory":"Building Materials",
            "type":"Retail Goods"
        }
    ],
    "sg:phone":"+90 252 545 4361",
    "sg:postcode":"48200",
    "sg:province":"Mugla",
    "sg:tags":[
        "stone",
        "natural",
        "marble"
    ],
    "wof:name":"Didim Mermer Ticaret Ltd.sti",
    "wof:placetype":"venue"
},
  "geometry": {"coordinates":[28.3628406525,37.215675354],"type":"Point"}
}