{
  "type": "Feature",
  "properties": {
    "addr:full":"Ankara Cad.kastel Is Merk. B Blok Kat.2 No.83-84 Sirkeci Emin?n? Mersin Istanbul 52750",
    "addr:housenumber":"blok kat.2 no.83-84;?",
    "addr:postcode":"52750",
    "addr:street":"? N",
    "iso:country":"TR",
    "sg:address":"Ankara Cad.kastel Is Merk. B Blok Kat.2 No.83-84 Sirkeci Emin?n?",
    "sg:city":"Mersin",
    "sg:classifiers":[
        {
            "category":"Professional",
            "subcategory":"Business Services",
            "type":"Services"
        }
    ],
    "sg:phone":"+90 212 514 0850",
    "sg:postcode":"52750",
    "sg:province":"Istanbul",
    "sg:tags":[
        "food",
        "product",
        "exporter",
        "aricultural"
    ],
    "wof:name":"Findik San.ve Tic.a.s.",
    "wof:placetype":"venue"
},
  "geometry": {"coordinates":[28.9759254456,41.0123786926],"type":"Point"}
}