{
  "type": "Feature",
  "properties": {
    "addr:full":"Hukumet Cad. Firin Sok. No:1 Elfani Karab?k 78300",
    "addr:housenumber":"no 1",
    "addr:postcode":"78300",
    "addr:street":"Hukumet Cad. Firin Sok.;Karab",
    "iso:country":"TR",
    "sg:address":"Hukumet Cad. Firin Sok. No:1",
    "sg:city":"Elfani",
    "sg:classifiers":[
        {
            "category":"Food & Beverages",
            "subcategory":"Dairy",
            "type":"Retail Goods"
        }
    ],
    "sg:phone":"+90 372 461 2500",
    "sg:postcode":"78300",
    "sg:province":"Karab?k",
    "sg:tags":[
        "pruducts",
        "milk"
    ],
    "wof:name":"Etab Tarim Beslicilik Orman Urunleri San.tic.a.s.",
    "wof:placetype":"venue"
},
  "geometry": {"coordinates":[32.9789581299,41.4262199402],"type":"Point"}
}