{
  "type": "Feature",
  "properties": {
    "iso:country":"TR",
    "sg:address":"Merkez Mh. Nazli Sk. No:1 Kocasinan",
    "sg:city":"Gazi Osman Pasa",
    "sg:classifiers":[
        {
            "category":"Manufacturing",
            "subcategory":"Tools & Machinery",
            "type":"Manufacturing & Wholesale Goods"
        }
    ],
    "sg:phone":"+90 212 552 8306",
    "sg:postcode":"35993",
    "sg:province":"Istanbul",
    "sg:tags":[
        "machine",
        "industry"
    ],
    "wof:name":"?zdemir Makina Ltd. Sti.",
    "wof:placetype":"venue"
},
  "geometry": {"coordinates":[28.8799953461,41.0189971924],"type":"Point"}
}