{
  "type": "Feature",
  "properties": {
    "iso:country":"TR",
    "sg:address":"1586/11 Sk. No.2",
    "sg:city":"Salhane",
    "sg:orig_category":"Dryfood-dried Nuts",
    "sg:phone":"+90 232 435 3861",
    "sg:postcode":"65970",
    "sg:province":"Izmir",
    "wof:name":"Doyum Gida San. Ltd.sti.",
    "wof:placetype":"venue"
},
  "geometry": {"coordinates":[27.1423015594,38.4251480103],"type":"Point"}
}