{
  "type": "Feature",
  "properties": {
    "iso:country":"TR",
    "sg:address":"Aydin Mugla Karayolu 3.km.",
    "sg:city":"G?ng?ren",
    "sg:classifiers":[
        {
            "category":"Mining & Drilling",
            "type":"Manufacturing & Wholesale Goods"
        }
    ],
    "sg:phone":"+90 256 226 2324",
    "sg:postcode":"34165",
    "sg:province":"Aydin",
    "wof:name":"Jeotay Sondaj Ve Madencilik San. Ve Tic. A.s.",
    "wof:placetype":"venue"
},
  "geometry": {"coordinates":[27.8324394226,37.8409690857],"type":"Point"}
}