{
  "type": "Feature",
  "properties": {
    "iso:country":"TR",
    "sg:address":"Ferdi G??y Sk. No.7/b",
    "sg:city":"Cagaloglu",
    "sg:classifiers":[
        {
            "category":"Shopping",
            "subcategory":"Baby Store",
            "type":"Retail Goods"
        }
    ],
    "sg:phone":"+90 212 527 3548",
    "sg:province":"Istanbul",
    "sg:tags":[
        "wear"
    ],
    "wof:name":"Kivircik Bebe Triko Koll.sti.",
    "wof:placetype":"venue"
},
  "geometry": {"coordinates":[29.273825,40.990456],"type":"Point"}
}