{
  "type": "Feature",
  "properties": {
    "iso:country":"TR",
    "sg:address":"Bostanci",
    "sg:city":"Gaziantep",
    "sg:classifiers":[
        {
            "category":"Banks & Credit Unions",
            "subcategory":"Bank",
            "type":"Services"
        }
    ],
    "sg:phone":"+90 216 362 6589",
    "sg:postcode":"63570",
    "sg:province":"81118",
    "wof:name":"T?kiye Emlak, Bankasi As",
    "wof:placetype":"venue"
},
  "geometry": {"coordinates":[29.104858,40.964973],"type":"Point"}
}