{
  "type": "Feature",
  "properties": {
    "iso:country":"TR",
    "sg:address":"Kisla Cad.apek ?retmen Is Mrk. B Blok No:7-8",
    "sg:city":"34140",
    "sg:classifiers":[
        {
            "category":"Home & Garden",
            "subcategory":"Household Appliances",
            "type":"Retail Goods"
        }
    ],
    "sg:phone":"+90 212 613 2467",
    "sg:province":"Istanbul",
    "sg:tags":[
        "conditioner",
        "air"
    ],
    "wof:name":"06 Sogutma Klima Ith.ihr.san.tic.ltd.sti",
    "wof:placetype":"venue"
},
  "geometry": {"coordinates":[28.9759254456,41.0123786926],"type":"Point"}
}