{
  "type": "Feature",
  "properties": {
    "iso:country":"TR",
    "sg:address":"Gazi Sahin",
    "sg:city":"Alanya",
    "sg:classifiers":[
        {
            "category":"Government",
            "subcategory":"Office",
            "type":"Public Place"
        }
    ],
    "sg:phone":"+90 312 320 2901",
    "sg:postcode":"07400",
    "sg:province":"Ankara",
    "sg:tags":[
        "municipality"
    ],
    "wof:name":"Mamak Belediye Baskani",
    "wof:placetype":"venue"
},
  "geometry": {"coordinates":[32.7182121277,39.9646682739],"type":"Point"}
}