{
  "type": "Feature",
  "properties": {
    "addr:full":"Yeni Gazi Ali Cd. 44. Sk. No:18 Iskenderun Kayseri 31300",
    "addr:housenumber":"18",
    "addr:postcode":"31300",
    "addr:street":"Ali Cd. 44 Sk. No",
    "iso:country":"TR",
    "sg:address":"Yeni Gazi Ali Cd. 44. Sk. No:18",
    "sg:city":"Iskenderun",
    "sg:classifiers":[
        {
            "category":"Utilities",
            "subcategory":"Electric",
            "type":"Services"
        }
    ],
    "sg:phone":"+90 352 336 1658",
    "sg:postcode":"31300",
    "sg:province":"Kayseri",
    "sg:tags":[
        "accumulator",
        "-",
        "batery"
    ],
    "wof:name":"Kaysan Ak?m?lat?r San. Ltd. Sti.",
    "wof:placetype":"venue"
},
  "geometry": {"coordinates":[35.484669,38.740334],"type":"Point"}
}