{
  "type": "Feature",
  "properties": {
    "iso:country":"TR",
    "sg:address":"Bagdat Cad. No:82/1 Kiziltoprak Kadikoy",
    "sg:city":"B???kmece",
    "sg:classifiers":[
        {
            "category":"Banks & Credit Unions",
            "subcategory":"Investment Brokerage",
            "type":"Services"
        }
    ],
    "sg:phone":"+90 216 347 8334",
    "sg:province":"Istanbul",
    "sg:tags":[
        "-",
        "export",
        "import"
    ],
    "wof:name":"Paykom Bilgisayar A.s.",
    "wof:placetype":"venue"
},
  "geometry": {"coordinates":[29.0294399261,40.9855613708],"type":"Point"}
}