{
  "type": "Feature",
  "properties": {
    "addr:full":"G?lsan Sanayi Sitesi 35. Sokak No:34 55080 Samsun",
    "addr:housenumber":"35;no 34",
    "addr:postcode":"55080",
    "addr:street":"Lsan Sanayi Sitesi;Sokak",
    "iso:country":"TR",
    "sg:address":"G?lsan Sanayi Sitesi 35. Sokak No:34",
    "sg:city":"55080",
    "sg:classifiers":[
        {
            "category":"Manufacturing",
            "subcategory":"Lumber",
            "type":"Manufacturing & Wholesale Goods"
        }
    ],
    "sg:phone":"+90 362 238 8761",
    "sg:province":"Samsun",
    "sg:tags":[
        "timber"
    ],
    "wof:name":"19 Mayis Dograma",
    "wof:placetype":"venue"
},
  "geometry": {"coordinates":[36.3378410339,41.2897186279],"type":"Point"}
}