{
  "type": "Feature",
  "properties": {
    "addr:full":"Ko?an Cd. ?esme Sk. No:1/b Bagcilar Yukari Dudullu Istanbul 34776",
    "addr:housenumber":"? an;?;b",
    "addr:postcode":"34776",
    "addr:street":"Ko;Cd.;Sk. No 1 /;Yukari;Istanbul",
    "iso:country":"TR",
    "sg:address":"Ko?an Cd. ?esme Sk. No:1/b Bagcilar",
    "sg:city":"Yukari Dudullu",
    "sg:classifiers":[
        {
            "category":"Manufacturing",
            "subcategory":"Rubber & Plastics",
            "type":"Manufacturing & Wholesale Goods"
        }
    ],
    "sg:phone":"+90 212 515 6675",
    "sg:postcode":"34776",
    "sg:province":"Istanbul",
    "sg:tags":[
        "industry"
    ],
    "wof:name":"Altaylar Plastik San. Tic. Ltd. Sti.",
    "wof:placetype":"venue"
},
  "geometry": {"coordinates":[29.175403595,41.0060424805],"type":"Point"}
}