{
  "type": "Feature",
  "properties": {
    "iso:country":"TR",
    "sg:address":"G?l?ya Mah.kaya Sok.no:36/2",
    "sg:city":"Ke??en",
    "sg:classifiers":[
        {
            "category":"Shopping",
            "subcategory":"Clothing, Apparel, & Fashions",
            "type":"Retail Goods"
        }
    ],
    "sg:phone":"+90 312 361 3437",
    "sg:province":"Ankara",
    "sg:tags":[
        "ready",
        "wear"
    ],
    "wof:name":"Hece Tekstil",
    "wof:placetype":"venue"
},
  "geometry": {"coordinates":[32.8560333252,39.9438743591],"type":"Point"}
}