{
  "type": "Feature",
  "properties": {
    "addr:full":"Bayram Sid Cad. No.47/b Organize Sanayi Bolgesi Yenibosna Denizli 43270",
    "addr:housenumber":"no.47 / b",
    "addr:postcode":"43270",
    "addr:street":"Sid Cad.;Organize Sanayi Bolgesi Yenibosna",
    "iso:country":"TR",
    "sg:address":"Bayram Sid Cad. No.47/b Organize Sanayi Bolgesi",
    "sg:city":"Yenibosna",
    "sg:classifiers":[
        {
            "category":"Shopping",
            "subcategory":"Crafts & Fabrics",
            "type":"Retail Goods"
        }
    ],
    "sg:phone":"+90 258269154143",
    "sg:postcode":"43270",
    "sg:province":"Denizli",
    "sg:tags":[
        "knitting"
    ],
    "wof:name":"Erikoglu Tekstil A.s.",
    "wof:placetype":"venue"
},
  "geometry": {"coordinates":[29.0864906311,37.773525238],"type":"Point"}
}