{
  "type": "Feature",
  "properties": {
    "addr:full":"Posta Cd. Sehit Tegmen Kalmaz Sk. No:7/9 Ulus Kizilay Ankara 06650",
    "addr:housenumber":"9",
    "addr:postcode":"06650",
    "addr:street":"Posta Cd. Sehit Tegmen Kalmaz Sk. No 7 /",
    "iso:country":"TR",
    "sg:address":"Posta Cd. Sehit Tegmen Kalmaz Sk. No:7/9 Ulus",
    "sg:city":"Kizilay",
    "sg:classifiers":[
        {
            "category":"Shopping",
            "subcategory":"Stationery & Office Supplies",
            "type":"Retail Goods"
        }
    ],
    "sg:phone":"+90 312 309 0629",
    "sg:postcode":"06650",
    "sg:province":"Ankara",
    "wof:name":"Oguz Kirtasiye Ltd. Sti.",
    "wof:placetype":"venue"
},
  "geometry": {"coordinates":[32.849346,39.915485],"type":"Point"}
}