{
  "type": "Feature",
  "properties": {
    "addr:full":"K.sehitleri Cad. No:28 Kat:6/14 Alsancak Sisli Izmir 34384",
    "addr:housenumber":"28 kat 6 / 14",
    "addr:postcode":"34384",
    "addr:street":"K.Sehitleri Cad. No",
    "iso:country":"TR",
    "sg:address":"K.sehitleri Cad. No:28 Kat:6/14 Alsancak",
    "sg:city":"Sisli",
    "sg:orig_category":"Printinh House",
    "sg:phone":"+90 2324226239464",
    "sg:postcode":"34384",
    "sg:province":"Izmir",
    "wof:name":"Sanal Mevzuat Yay.bil.rek.hiz.ltd.sti",
    "wof:placetype":"venue"
},
  "geometry": {"coordinates":[27.1296863556,38.4186973572],"type":"Point"}
}