{
  "type": "Feature",
  "properties": {
    "addr:full":"Sair Nedim Cd. No:136 Besiktas Gebze Istanbul 41400",
    "addr:housenumber":"no",
    "addr:postcode":"41400",
    "addr:street":"Cd.;Besiktas",
    "iso:country":"TR",
    "sg:address":"Sair Nedim Cd. No:136 Besiktas",
    "sg:city":"Gebze",
    "sg:classifiers":[
        {
            "category":"Home & Garden",
            "subcategory":"Household Appliances",
            "type":"Retail Goods"
        }
    ],
    "sg:phone":"+90 212 260 7694",
    "sg:postcode":"41400",
    "sg:province":"Istanbul",
    "sg:tags":[
        "utensil",
        "electrical"
    ],
    "wof:name":"Tarhanlar Elek. Cih. San.",
    "wof:placetype":"venue"
},
  "geometry": {"coordinates":[28.9861831665,41.0408554077],"type":"Point"}
}