{
  "type": "Feature",
  "properties": {
    "addr:full":"E5 Karayolu No:43 B.?ekmece Istanbul 34",
    "addr:housenumber":"?",
    "addr:street":"No 43 B.",
    "iso:country":"TR",
    "sg:address":"E5 Karayolu No:43",
    "sg:city":"B.?ekmece",
    "sg:classifiers":[
        {
            "category":"Professional",
            "subcategory":"Engineering",
            "type":"Services"
        }
    ],
    "sg:phone":"+90 2128826715161",
    "sg:postcode":"34",
    "sg:province":"Istanbul",
    "sg:tags":[
        "civil"
    ],
    "wof:name":"??z?m Izolasyon Havuz Ltd Sti",
    "wof:placetype":"venue"
},
  "geometry": {"coordinates":[28.9861831665,41.0408554077],"type":"Point"}
}