{
  "type": "Feature",
  "properties": {
    "addr:full":"Telsiz Mah. Prof. Muammer Aksoy Cad. No: 24/a Zeytinburnu \u00c7orlu Istanbul",
    "addr:housenumber":"24 / a",
    "addr:street":"Telsiz Mah. Prof. Muammer Aksoy Cad. No;Zeytinburnu",
    "iso:country":"TR",
    "sg:address":"Telsiz Mah. Prof. Muammer Aksoy Cad. No: 24/a Zeytinburnu",
    "sg:city":"\u00c7orlu",
    "sg:classifiers":[
        {
            "category":"Shopping",
            "subcategory":"Luggage & Leather Goods",
            "type":"Retail Goods"
        }
    ],
    "sg:phone":"+90 212 664 2030",
    "sg:province":"Istanbul",
    "sg:tags":[
        "leather-fur",
        "wear"
    ],
    "wof:name":"Asflas Deri San. Tic. Ltd. Sti.",
    "wof:placetype":"venue"
},
  "geometry": {"coordinates":[28.9128303528,40.9949417114],"type":"Point"}
}