{
  "type": "Feature",
  "properties": {
    "iso:country":"TR",
    "sg:address":"Balikesir",
    "sg:city":"Karabaglar",
    "sg:classifiers":[
        {
            "category":"Government",
            "subcategory":"Office",
            "type":"Public Place"
        }
    ],
    "sg:phone":"+90 266 576 1147",
    "sg:postcode":"44210",
    "sg:province":"Balikesir",
    "sg:tags":[
        "army"
    ],
    "wof:name":"Kepsut Askerlik Subesi",
    "wof:placetype":"venue"
},
  "geometry": {"coordinates":[27.8853626251,39.6448822021],"type":"Point"}
}