{
  "type": "Feature",
  "properties": {
    "iso:country":"TR",
    "sg:address":"Atasehir Sitesi Manolya Sik. 2-1 No:5 K.bakkalk? / Ist.",
    "sg:city":"1.levent",
    "sg:classifiers":[
        {
            "category":"Wholesale",
            "subcategory":"Machinery & Supplies",
            "type":"Manufacturing & Wholesale Goods"
        }
    ],
    "sg:phone":"+90 216 455 2589",
    "sg:postcode":"34340",
    "sg:province":"Istanbul",
    "sg:tags":[
        "laboratory",
        "equipment"
    ],
    "wof:name":"Atomika Teknik Cihazlar Ltd.sti.",
    "wof:placetype":"venue"
},
  "geometry": {"coordinates":[29.0270805359,41.0670776367],"type":"Point"}
}