{
  "type": "Feature",
  "properties": {
    "iso:country":"TR",
    "sg:address":"M.pasa Bulv.1268 Sk. No.2 Basmane",
    "sg:city":"Isikkent",
    "sg:classifiers":[
        {
            "category":"Shopping",
            "subcategory":"Shoes",
            "type":"Retail Goods"
        }
    ],
    "sg:phone":"+90 232 484 5939",
    "sg:postcode":"32100",
    "sg:province":"Izmir",
    "wof:name":"Ugurcan Deri Islm. Ltd.sti.",
    "wof:placetype":"venue"
},
  "geometry": {"coordinates":[27.129686,38.418697],"type":"Point"}
}