{
  "type": "Feature",
  "properties": {
    "addr:full":"In??cd. No:174 Sefak? Bagcilar Istanbul 33115",
    "addr:housenumber":"no",
    "addr:postcode":"33115",
    "addr:street":"In ? ? Cd.;Sefak",
    "iso:country":"TR",
    "sg:address":"In??cd. No:174 Sefak?",
    "sg:city":"Bagcilar",
    "sg:classifiers":[
        {
            "category":"Shopping",
            "subcategory":"Stationery & Office Supplies",
            "type":"Retail Goods"
        }
    ],
    "sg:phone":"+90 212 698 0790",
    "sg:postcode":"33115",
    "sg:province":"Istanbul",
    "sg:tags":[
        "paper"
    ],
    "wof:name":"Taksa Defter San. Tic. A.s.",
    "wof:placetype":"venue"
},
  "geometry": {"coordinates":[28.790681839,41.0253562927],"type":"Point"}
}