{
  "type": "Feature",
  "properties": {
    "iso:country":"TR",
    "sg:address":"Yenikent Mah. Canan Sok. No:20",
    "sg:city":"Esenyurt",
    "sg:classifiers":[
        {
            "category":"Shopping",
            "subcategory":"Clothing, Apparel, & Fashions",
            "type":"Retail Goods"
        }
    ],
    "sg:phone":"+90 212 620 0765",
    "sg:postcode":"07800",
    "sg:province":"Istanbul",
    "sg:tags":[
        "ready",
        "wear"
    ],
    "wof:name":"Bhc Tekstil",
    "wof:placetype":"venue"
},
  "geometry": {"coordinates":[28.6838970184,41.0419883728],"type":"Point"}
}