{
  "type": "Feature",
  "properties": {
    "addr:full":"Kader Sok. No: 6/1 Gaziosmanpasa Ikitelli/K\u00fc\u00e7\u00fck\u00e7ekmece Ankara 34670",
    "addr:housenumber":"no 6 / 1",
    "addr:postcode":"34670",
    "addr:street":"Kader Sok.",
    "iso:country":"TR",
    "sg:address":"Kader Sok. No: 6/1 Gaziosmanpasa",
    "sg:city":"Ikitelli/K\u00fc\u00e7\u00fck\u00e7ekmece",
    "sg:classifiers":[
        {
            "category":"Organizations",
            "subcategory":"Professional Association",
            "type":"Services"
        }
    ],
    "sg:phone":"+90 312 468 6767",
    "sg:postcode":"34670",
    "sg:province":"Ankara",
    "sg:tags":[
        "fair"
    ],
    "wof:name":"Abc Fuar Organizasyon Merkezi A.s.",
    "wof:placetype":"venue"
},
  "geometry": {"coordinates":[32.8677330017,39.8961296082],"type":"Point"}
}