{
  "type": "Feature",
  "properties": {
    "iso:country":"TR",
    "sg:address":"Kilikya Hotel Kizkalesi",
    "sg:city":"Mersin",
    "sg:orig_category":"Hotels: Motels",
    "sg:phone":"+90 324 523 2116",
    "sg:postcode":"52750",
    "sg:province":"I?el",
    "wof:name":"Kilikya Hotel",
    "wof:placetype":"venue"
},
  "geometry": {"coordinates":[37.7128486633,41.0530204773],"type":"Point"}
}