{
  "type": "Feature",
  "properties": {
    "iso:country":"TR",
    "sg:address":"Ankara Asfalti Gebze Askerlik Subesi Yolu No:41 41410 Gebze Kocaeli",
    "sg:city":"Beyoglu",
    "sg:classifiers":[
        {
            "category":"Manufacturing",
            "subcategory":"Metals",
            "type":"Manufacturing & Wholesale Goods"
        }
    ],
    "sg:phone":"+90 262 642 8437",
    "sg:postcode":"34437",
    "sg:province":"Ankara",
    "sg:tags":[
        "metallurgy",
        "metalworking"
    ],
    "wof:name":"Poly Metal Metalurji Ve Dokum San Tic As",
    "wof:placetype":"venue"
},
  "geometry": {"coordinates":[32.8560333252,39.9438743591],"type":"Point"}
}