{
  "type": "Feature",
  "properties": {
    "addr:full":"Oto Sanayi Sitesi Fatih Cad. No: 6 4.levent Mersin Istanbul 52750",
    "addr:housenumber":"4.levent",
    "addr:postcode":"52750",
    "addr:street":"Fatih Cad. No 6",
    "iso:country":"TR",
    "sg:address":"Oto Sanayi Sitesi Fatih Cad. No: 6 4.levent",
    "sg:city":"Mersin",
    "sg:classifiers":[
        {
            "category":"Manufacturing",
            "subcategory":"Glass & Minerals",
            "type":"Manufacturing & Wholesale Goods"
        }
    ],
    "sg:phone":"+90 212 264 5902",
    "sg:postcode":"52750",
    "sg:province":"Istanbul",
    "sg:tags":[
        "glassware"
    ],
    "wof:name":"Guvenlik Aynalari Ve Camlari San.tic.",
    "wof:placetype":"venue"
},
  "geometry": {"coordinates":[29.0311145782,41.0946311951],"type":"Point"}
}