{
  "type": "Feature",
  "properties": {
    "addr:full":"Hasim Iscan Cd Ayti Plaza No:55/3 Bayrampasa Bursa 36100",
    "addr:housenumber":"cd;55 / 3",
    "addr:postcode":"36100",
    "addr:street":"Plaza No;Bursa",
    "iso:country":"TR",
    "sg:address":"Hasim Iscan Cd Ayti Plaza No:55/3",
    "sg:city":"Bayrampasa",
    "sg:classifiers":[
        {
            "category":"Manufacturing",
            "subcategory":"Building Materials",
            "type":"Manufacturing & Wholesale Goods"
        }
    ],
    "sg:phone":"+90 224 220 5206",
    "sg:postcode":"36100",
    "sg:province":"Bursa",
    "sg:tags":[
        "lifts-elevators"
    ],
    "wof:name":"Nizam Asansor",
    "wof:placetype":"venue"
},
  "geometry": {"coordinates":[29.0580043793,40.1947555542],"type":"Point"}
}