{
  "type": "Feature",
  "properties": {
    "addr:full":"Kirklareli Cad. No:38 ?sk? Merkez Kirklareli 53100",
    "addr:housenumber":"38 ?;?",
    "addr:postcode":"53100",
    "addr:street":"Kirklareli Cad. No;Merkez Kirklareli",
    "iso:country":"TR",
    "sg:address":"Kirklareli Cad. No:38 ?sk?",
    "sg:city":"Merkez",
    "sg:classifiers":[
        {
            "category":"Manufacturing",
            "subcategory":"Wood Products",
            "type":"Manufacturing & Wholesale Goods"
        }
    ],
    "sg:phone":"+90 288 273 1234",
    "sg:postcode":"53100",
    "sg:province":"Kirklareli",
    "sg:tags":[
        "forest"
    ],
    "wof:name":"Pido Aga? San. Tic.ltd.sti.",
    "wof:placetype":"venue"
},
  "geometry": {"coordinates":[27.2285003662,41.7378005981],"type":"Point"}
}