{
  "type": "Feature",
  "properties": {
    "iso:country":"TR",
    "sg:address":"Sair Nefi Sk. No:24",
    "sg:city":"Moda",
    "sg:classifiers":[
        {
            "category":"Shopping",
            "subcategory":"Computers & Home Electronics",
            "type":"Retail Goods"
        }
    ],
    "sg:phone":"+90 216 346 3167",
    "sg:postcode":"30800",
    "sg:province":"Istanbul",
    "sg:tags":[
        "animal"
    ],
    "wof:name":"Anadolu Akvaryum San. Tic. A.s.",
    "wof:placetype":"venue"
},
  "geometry": {"coordinates":[29.0263519287,40.9834098816],"type":"Point"}
}