{
  "type": "Feature",
  "properties": {
    "iso:country":"TR",
    "sg:address":"Keresteciler Sit Savas Cad 8/2",
    "sg:city":"Merter",
    "sg:classifiers":[
        {
            "category":"Shopping",
            "subcategory":"Crafts & Fabrics",
            "type":"Retail Goods"
        }
    ],
    "sg:phone":"+90 212 637 1739",
    "sg:postcode":"34169",
    "sg:province":"Istanbul",
    "sg:tags":[
        "knitting"
    ],
    "wof:name":"?if-sa Tekstil Gida San Tic Ltd Sti",
    "wof:placetype":"venue"
},
  "geometry": {"coordinates":[28.8924465179,41.0138511658],"type":"Point"}
}