{
  "type": "Feature",
  "properties": {
    "addr:full":"Halisarayi B Blok Merk Ortak? Isparta 80840",
    "addr:housenumber":"blok",
    "addr:postcode":"80840",
    "addr:street":"Ortak;Isparta",
    "iso:country":"TR",
    "sg:address":"Halisarayi B Blok Merk",
    "sg:city":"Ortak?",
    "sg:classifiers":[
        {
            "category":"Organizations",
            "subcategory":"Professional Association",
            "type":"Services"
        }
    ],
    "sg:phone":"+90 246 223 7363",
    "sg:postcode":"80840",
    "sg:province":"Isparta",
    "wof:name":"Tmmob Ins. Muhendis. Odasi",
    "wof:placetype":"venue"
},
  "geometry": {"coordinates":[30.5589008331,37.7635993958],"type":"Point"}
}