{
  "type": "Feature",
  "properties": {
    "iso:country":"TR",
    "sg:address":"Bankalar Cad 18",
    "sg:city":"Samsun",
    "sg:classifiers":[
        {
            "category":"Banks & Credit Unions",
            "subcategory":"Bank",
            "type":"Services"
        }
    ],
    "sg:phone":"+90 362 431 4671",
    "sg:postcode":"61420",
    "sg:province":"55030",
    "wof:name":"T?kiye Sinai, Kalkinma Bankasi As",
    "wof:placetype":"venue"
},
  "geometry": {"coordinates":[31.156771,40.843201],"type":"Point"}
}