{
  "type": "Feature",
  "properties": {
    "iso:country":"TR",
    "sg:address":"Rami Kisla Cd. Top?lar Ismerk. No:88/191 Top?lar",
    "sg:city":"B. ?ekmece",
    "sg:classifiers":[
        {
            "category":"Manufacturing",
            "subcategory":"Metals",
            "type":"Manufacturing & Wholesale Goods"
        }
    ],
    "sg:phone":"+90 212 612 6936",
    "sg:postcode":"34400",
    "sg:province":"Istanbul",
    "sg:tags":[
        "industry"
    ],
    "wof:name":"Lider Metal San. Tic. Ltd. Sti.",
    "wof:placetype":"venue"
},
  "geometry": {"coordinates":[28.9652347565,41.0676307678],"type":"Point"}
}