{
  "type": "Feature",
  "properties": {
    "iso:country":"TR",
    "sg:address":"F. Sultan Mehmet San. Sit. B3 Blok No:25 ?mraniye",
    "sg:city":"Iskenderun",
    "sg:classifiers":[
        {
            "category":"Manufacturing",
            "subcategory":"Rubber & Plastics",
            "type":"Manufacturing & Wholesale Goods"
        }
    ],
    "sg:phone":"+90 216 328 3874",
    "sg:postcode":"31200",
    "sg:province":"Istanbul",
    "sg:tags":[
        "industry"
    ],
    "wof:name":"Ersan Kimya Plastik Kozmetik San. Tic. Ltd. Sti.",
    "wof:placetype":"venue"
},
  "geometry": {"coordinates":[28.9759254456,41.0123786926],"type":"Point"}
}