{
  "type": "Feature",
  "properties": {
    "addr:full":"E-5 Karayolu Mavievler Mevkii Deniciler Yolu Sincap Sokak No:8 Idaltepe K???kyali Istanbul 81580",
    "addr:postcode":"81580",
    "addr:street":"Mavievler Mevkii Deniciler Yolu Sincap Sokak No 8;K ?",
    "iso:country":"TR",
    "sg:address":"E-5 Karayolu Mavievler Mevkii Deniciler Yolu Sincap Sokak No:8 Idaltepe",
    "sg:city":"K???kyali",
    "sg:classifiers":[
        {
            "category":"Building & Trades",
            "subcategory":"Plumbing",
            "type":"Services"
        }
    ],
    "sg:phone":"+90 2164891250489",
    "sg:postcode":"81580",
    "sg:province":"Istanbul",
    "sg:tags":[
        "pipe",
        "twist"
    ],
    "sg:website":"konayliservis.com",
    "wof:name":"Konmaksan Otomotiv Ve Makina Tic.ltd.sti",
    "wof:placetype":"venue"
},
  "geometry": {"coordinates":[28.9759254456,41.0123786926],"type":"Point"}
}