{
  "type": "Feature",
  "properties": {
    "addr:full":"A.menderes Bulvari 6.sok. No:12 Sultanhamam Aydin",
    "addr:housenumber":"6.sok no 12",
    "addr:street":"A.Menderes Bulvari;Sultanhamam Aydin",
    "iso:country":"TR",
    "sg:address":"A.menderes Bulvari 6.sok. No:12",
    "sg:city":"Sultanhamam",
    "sg:classifiers":[
        {
            "category":"Shopping",
            "subcategory":"Clothing, Apparel, & Fashions",
            "type":"Retail Goods"
        }
    ],
    "sg:phone":"+90 256 213 3696",
    "sg:province":"Aydin",
    "sg:tags":[
        "woman",
        "wear"
    ],
    "wof:name":"Flash Butik",
    "wof:placetype":"venue"
},
  "geometry": {"coordinates":[27.1669082642,38.2959365845],"type":"Point"}
}