{
  "type": "Feature",
  "properties": {
    "addr:full":"Tesvikiye Cd. No:95/13 Tesvikiye Ikitelli/K\u00fc\u00e7\u00fck\u00e7ekmece Istanbul 34670",
    "addr:housenumber":"no 95 / 13",
    "addr:postcode":"34670",
    "addr:street":"Tesvikiye Cd.",
    "iso:country":"TR",
    "sg:address":"Tesvikiye Cd. No:95/13 Tesvikiye",
    "sg:city":"Ikitelli/K\u00fc\u00e7\u00fck\u00e7ekmece",
    "sg:classifiers":[
        {
            "category":"Building & Trades",
            "subcategory":"Construction",
            "type":"Services"
        }
    ],
    "sg:phone":"+90 212 236 1119",
    "sg:postcode":"34670",
    "sg:province":"Istanbul",
    "sg:tags":[
        "industry",
        "mold"
    ],
    "wof:name":"Paschal Beton Kalip Tic. Ltd.sti.",
    "wof:placetype":"venue"
},
  "geometry": {"coordinates":[28.9932956696,41.0500030518],"type":"Point"}
}