{
  "type": "Feature",
  "properties": {
    "iso:country":"TR",
    "sg:address":"Cinnah Cd. No:57/1 ?ankaya",
    "sg:city":"Iskenderun",
    "sg:classifiers":[
        {
            "category":"Mining & Drilling",
            "type":"Manufacturing & Wholesale Goods"
        }
    ],
    "sg:phone":"+90 312 441 2560",
    "sg:postcode":"31200",
    "sg:province":"Ankara",
    "sg:tags":[
        "industry",
        "mine"
    ],
    "wof:name":"Mad San Madde. San. Tic. Ltd. Sti.",
    "wof:placetype":"venue"
},
  "geometry": {"coordinates":[32.8561172485,39.8920822144],"type":"Point"}
}