{
  "type": "Feature",
  "properties": {
    "addr:full":"Yeni ?arsi No:68 Tatvan Bitlis 13200",
    "addr:postcode":"13200",
    "addr:street":"No 68",
    "iso:country":"TR",
    "sg:address":"Yeni ?arsi No:68",
    "sg:city":"Tatvan",
    "sg:classifiers":[
        {
            "category":"Travel",
            "subcategory":"Travel Agent",
            "type":"Entertainment"
        }
    ],
    "sg:phone":"+90 434 827 9910",
    "sg:postcode":"13200",
    "sg:province":"Bitlis",
    "sg:tags":[
        "agency",
        "tourism"
    ],
    "wof:name":"?zta? Turizm (tatvan Sb)",
    "wof:placetype":"venue"
},
  "geometry": {"coordinates":[42.1081352234,38.399356842],"type":"Point"}
}