{
  "type": "Feature",
  "properties": {
    "addr:full":"Aslantepe Cad. Kircuval Mah.no:53 Mecidiyek\u00f6y Malatya",
    "addr:housenumber":"53",
    "addr:street":"Aslantepe Cad. Kircuval Mah.No",
    "iso:country":"TR",
    "sg:address":"Aslantepe Cad. Kircuval Mah.no:53",
    "sg:city":"Mecidiyek\u00f6y",
    "sg:classifiers":[
        {
            "category":"Utilities",
            "subcategory":"Natural Gas",
            "type":"Services"
        }
    ],
    "sg:phone":"+90 422 322 3445",
    "sg:province":"Malatya",
    "sg:tags":[
        "tank-heating-natural"
    ],
    "wof:name":"Altinova Tic.",
    "wof:placetype":"venue"
},
  "geometry": {"coordinates":[38.3195266724,38.3488922119],"type":"Point"}
}