{
  "type": "Feature",
  "properties": {
    "iso:country":"TR",
    "sg:address":"Mahmut Yildiz",
    "sg:city":"Ceyhan",
    "sg:classifiers":[
        {
            "category":"Government",
            "subcategory":"Office",
            "type":"Public Place"
        }
    ],
    "sg:phone":"+90 412 651 2091",
    "sg:postcode":"01920",
    "sg:province":"Diyarbakir",
    "sg:tags":[
        "municipality"
    ],
    "wof:name":"Hani Belediye Baskani",
    "wof:placetype":"venue"
},
  "geometry": {"coordinates":[40.2352294922,37.9198379517],"type":"Point"}
}