{
  "type": "Feature",
  "properties": {
    "iso:country":"TR",
    "sg:address":"Agir San. B?g. T.m.o. Arkasi 7",
    "sg:city":"Merkez",
    "sg:classifiers":[
        {
            "category":"Home & Garden",
            "subcategory":"Kitchen Supply",
            "type":"Retail Goods"
        }
    ],
    "sg:phone":"+90 352 336 4387",
    "sg:postcode":"20100",
    "sg:province":"Kayseri",
    "sg:tags":[
        "steel",
        "utensil"
    ],
    "wof:name":"Erendemir Madeni Esya San. Tic. A.s.",
    "wof:placetype":"venue"
},
  "geometry": {"coordinates":[35.489136,38.722576],"type":"Point"}
}