{
  "type": "Feature",
  "properties": {
    "iso:country":"TR",
    "sg:address":"Elma Bah?si Cebeci Cad. No:138",
    "sg:city":"K??k?",
    "sg:orig_category":"Printinh House",
    "sg:phone":"+90 212 617 2219",
    "sg:postcode":"34760",
    "sg:province":"Istanbul",
    "wof:name":"Al-mer Merdane Sanayi",
    "wof:placetype":"venue"
},
  "geometry": {"coordinates":[29.1056232452,41.0173683167],"type":"Point"}
}