{
  "type": "Feature",
  "properties": {
    "addr:full":"Anadolu Mh. Cigdem Sk. 5 Kad\u0131k\u00f6y Bursa 81010",
    "addr:housenumber":"5",
    "addr:postcode":"81010",
    "addr:street":"Cigdem Sk.;Bursa",
    "iso:country":"TR",
    "sg:address":"Anadolu Mh. Cigdem Sk. 5",
    "sg:city":"Kad\u0131k\u00f6y",
    "sg:orig_category":"Aluminium Carpentary",
    "sg:phone":"+90 224 362 9030",
    "sg:postcode":"81010",
    "sg:province":"Bursa",
    "wof:name":"Oz Erdem San. Tic.",
    "wof:placetype":"venue"
},
  "geometry": {"coordinates":[29.0905761719,40.1924781799],"type":"Point"}
}