{
  "type": "Feature",
  "properties": {
    "iso:country":"TR",
    "sg:address":"Platin Sok. No:20/32",
    "sg:city":"Cankaya",
    "sg:classifiers":[
        {
            "category":"Home & Garden",
            "subcategory":"Household Appliances",
            "type":"Retail Goods"
        }
    ],
    "sg:phone":"+90 312 442 7013",
    "sg:postcode":"07080",
    "sg:province":"Ankara",
    "sg:tags":[
        "conditioner",
        "air"
    ],
    "wof:name":"Emair Havacilik",
    "wof:placetype":"venue"
},
  "geometry": {"coordinates":[29.2130393982,40.8920860291],"type":"Point"}
}