{
  "type": "Feature",
  "properties": {
    "iso:country":"TR",
    "sg:address":"Y. Beyazit Mh. No:5/e Ulus",
    "sg:city":"Ikitelli",
    "sg:classifiers":[
        {
            "category":"Farming",
            "subcategory":"Fish & Marine Products",
            "type":"Manufacturing & Wholesale Goods"
        }
    ],
    "sg:phone":"+90 312 312 2338",
    "sg:postcode":"34306",
    "sg:province":"Ankara",
    "sg:tags":[
        "automotive"
    ],
    "wof:name":"Tuna Otomotiv Tic. Ltd. Sti.",
    "wof:placetype":"venue"
},
  "geometry": {"coordinates":[29.1155071259,40.1916618347],"type":"Point"}
}