{
  "type": "Feature",
  "properties": {
    "iso:country":"TR",
    "sg:address":"Sanayi Cad.no:53",
    "sg:city":"Of",
    "sg:classifiers":[
        {
            "category":"Home & Garden",
            "subcategory":"Building Materials",
            "type":"Retail Goods"
        }
    ],
    "sg:phone":"+90 462 771 5519",
    "sg:postcode":"61550",
    "sg:province":"Trabzon",
    "sg:tags":[
        "stone",
        "natural",
        "marble"
    ],
    "wof:name":"Renktas Mermer Sanayi",
    "wof:placetype":"venue"
},
  "geometry": {"coordinates":[39.7165603638,41.0012931824],"type":"Point"}
}