{
  "type": "Feature",
  "properties": {
    "addr:full":"Universite Mah. Baglarici Cad.no:29 Avcilar Istanbul 01350",
    "addr:housenumber":"29",
    "addr:postcode":"01350",
    "addr:street":"Mah. Baglarici Cad.No;Istanbul",
    "iso:country":"TR",
    "sg:address":"Universite Mah. Baglarici Cad.no:29",
    "sg:city":"Avcilar",
    "sg:classifiers":[
        {
            "category":"Food & Beverages",
            "subcategory":"Supermarket",
            "type":"Retail Goods"
        }
    ],
    "sg:phone":"+90 212 695 0000",
    "sg:postcode":"01350",
    "sg:province":"Istanbul",
    "sg:tags":[
        "frozen"
    ],
    "wof:name":"Kerevitas Gida San.a.s",
    "wof:placetype":"venue"
},
  "geometry": {"coordinates":[28.7191314697,40.9944534302],"type":"Point"}
}