{
  "type": "Feature",
  "properties": {
    "iso:country":"TR",
    "sg:address":"Istiklal Mah. Resadiye Cad. 3/b",
    "sg:city":"Sisli",
    "sg:classifiers":[
        {
            "category":"Food & Beverages",
            "subcategory":"Groceries & Convenience Stores",
            "type":"Retail Goods"
        }
    ],
    "sg:phone":"+90 222 234 2149",
    "sg:postcode":"65710",
    "sg:province":"Eskisehir",
    "sg:tags":[
        "ready"
    ],
    "wof:name":"Tosan Zeytincilik Gida A,s.",
    "wof:placetype":"venue"
},
  "geometry": {"coordinates":[30.516626358,39.7717323303],"type":"Point"}
}