{
  "type": "Feature",
  "properties": {
    "addr:full":"Ziya Gokalp Mah. Abdullah Pasa Cad. Orkide Sok. No:1 Ikitelli Istanbul 34306",
    "addr:housenumber":"no 1",
    "addr:postcode":"34306",
    "addr:street":"Ziya Gokalp Mah. Abdullah Pasa Cad. Orkide Sok.",
    "iso:country":"TR",
    "sg:address":"Ziya Gokalp Mah. Abdullah Pasa Cad. Orkide Sok. No:1",
    "sg:city":"Ikitelli",
    "sg:classifiers":[
        {
            "category":"Food & Beverages",
            "subcategory":"Groceries & Convenience Stores",
            "type":"Retail Goods"
        }
    ],
    "sg:phone":"+90 212 670 2616",
    "sg:postcode":"34306",
    "sg:province":"Istanbul",
    "sg:tags":[
        "product"
    ],
    "wof:name":"Aksu Vital A.s.",
    "wof:placetype":"venue"
},
  "geometry": {"coordinates":[28.7984962463,41.0884017944],"type":"Point"}
}