{
  "type": "Feature",
  "properties": {
    "iso:country":"TR",
    "sg:address":"Kurtulus Mah. Cimcim Cad. No:27/a",
    "sg:city":"Kad\u0131k\u00f6y",
    "sg:orig_category":"Scavening Services",
    "sg:phone":"+90 276 212 1473",
    "sg:province":"Usak",
    "wof:name":"?agda Temizlik",
    "wof:placetype":"venue"
},
  "geometry": {"coordinates":[29.402338,38.677666],"type":"Point"}
}