{
  "type": "Feature",
  "properties": {
    "addr:full":"Yenice Mah.d?zenli ?ikmaz Sk.no:1 Kagithane Istanbul 34406",
    "addr:housenumber":"1",
    "addr:postcode":"34406",
    "addr:street":"Sk.No",
    "iso:country":"TR",
    "sg:address":"Yenice Mah.d?zenli ?ikmaz Sk.no:1",
    "sg:city":"Kagithane",
    "sg:classifiers":[
        {
            "category":"Manufacturing",
            "subcategory":"Metals",
            "type":"Manufacturing & Wholesale Goods"
        }
    ],
    "sg:phone":"+90 212 282 8776",
    "sg:postcode":"34406",
    "sg:province":"Istanbul",
    "sg:tags":[
        "processing"
    ],
    "wof:name":"C.v.s Civata Vida Somun Sanayi",
    "wof:placetype":"venue"
},
  "geometry": {"coordinates":[28.9681472778,41.0811843872],"type":"Point"}
}