{
  "type": "Feature",
  "properties": {
    "iso:country":"TR",
    "sg:address":"F. Cakmak Cd. K?t? M??. No:2 Veysipasa Mh. Merkez",
    "sg:city":"Besiktas",
    "sg:classifiers":[
        {
            "category":"Organizations",
            "subcategory":"Membership Organization",
            "type":"Services"
        }
    ],
    "sg:phone":"+90 256 212 8506",
    "sg:postcode":"75200",
    "sg:province":"Aydin",
    "wof:name":"Aydin Il Kultur Mudur. Faaliyet. Yayma Gelis. Tan. Dernegi",
    "wof:placetype":"venue"
},
  "geometry": {"coordinates":[27.8324394226,37.8409690857],"type":"Point"}
}