{
  "type": "Feature",
  "properties": {
    "iso:country":"TR",
    "sg:address":"Fevzi Cakmak Cad 67",
    "sg:city":"Bursa",
    "sg:classifiers":[
        {
            "category":"Banks & Credit Unions",
            "subcategory":"Bank",
            "type":"Services"
        }
    ],
    "sg:phone":"+90 224 255 7080",
    "sg:province":"16050",
    "wof:name":"Iktisat Bankasi, T?k As",
    "wof:placetype":"venue"
},
  "geometry": {"coordinates":[41.834286,41.181858],"type":"Point"}
}