{
  "type": "Feature",
  "properties": {
    "addr:full":"Bagdat Cad. Feyzullah Mah. Kaptan Sok. No:1/2 Maltepe Istanbul 01000",
    "addr:housenumber":"no 1 / 2",
    "addr:postcode":"01000",
    "addr:street":"Bagdat Cad.;Mah. Kaptan Sok.;Istanbul",
    "iso:country":"TR",
    "sg:address":"Bagdat Cad. Feyzullah Mah. Kaptan Sok. No:1/2",
    "sg:city":"Maltepe",
    "sg:classifiers":[
        {
            "category":"Manufacturing",
            "subcategory":"Wood Products",
            "type":"Manufacturing & Wholesale Goods"
        }
    ],
    "sg:phone":"+90 216 457 2055",
    "sg:postcode":"01000",
    "sg:province":"Istanbul",
    "sg:tags":[
        "forest"
    ],
    "wof:name":"Talat Parke",
    "wof:placetype":"venue"
},
  "geometry": {"coordinates":[29.1287631989,40.9264564514],"type":"Point"}
}