{
  "type": "Feature",
  "properties": {
    "iso:country":"TR",
    "sg:address":"Guvenlik Cad. 60-b",
    "sg:city":"Mersin",
    "sg:classifiers":[
        {
            "category":"Manufacturing",
            "subcategory":"Glass & Minerals",
            "type":"Manufacturing & Wholesale Goods"
        }
    ],
    "sg:phone":"+90 312 467 5429",
    "sg:postcode":"52750",
    "sg:province":"Ankara",
    "sg:tags":[
        "glass-mirror"
    ],
    "wof:name":"Tugba Cam",
    "wof:placetype":"venue"
},
  "geometry": {"coordinates":[32.853553772,39.8982658386],"type":"Point"}
}