{
  "type": "Feature",
  "properties": {
    "iso:country":"TR",
    "sg:address":"Sakir Kesebir Cd. No:27 Balmumcu",
    "sg:city":"07100",
    "sg:classifiers":[
        {
            "category":"Professional",
            "subcategory":"Detective & Security Services",
            "type":"Services"
        }
    ],
    "sg:phone":"+90 212 288 1685",
    "sg:province":"Istanbul",
    "sg:tags":[
        "material"
    ],
    "wof:name":"As Guvenlik Sistemleri",
    "wof:placetype":"venue"
},
  "geometry": {"coordinates":[29.012461,41.062237],"type":"Point"}
}