{
  "type": "Feature",
  "properties": {
    "iso:country":"TR",
    "sg:address":"Akdeniz Cad.sari Nasuh Sok.no.63/1",
    "sg:city":"Fatih",
    "sg:classifiers":[
        {
            "category":"Shopping",
            "subcategory":"Clothing, Apparel, & Fashions",
            "type":"Retail Goods"
        }
    ],
    "sg:phone":"+90 212 635 6987",
    "sg:postcode":"01740",
    "sg:province":"Istanbul",
    "sg:tags":[
        "woman",
        "wear"
    ],
    "wof:name":"Basaran Tekstil",
    "wof:placetype":"venue"
},
  "geometry": {"coordinates":[28.9411373138,41.0194740295],"type":"Point"}
}