{
  "type": "Feature",
  "properties": {
    "iso:country":"TR",
    "sg:address":"Marmara Cad. 6/32",
    "sg:city":"Merkez",
    "sg:orig_category":"Musi Instruments",
    "sg:phone":"+90 226 813 4414",
    "sg:postcode":"77200",
    "sg:province":"Yalova",
    "wof:name":"?nem-kar Ltd.",
    "wof:placetype":"venue"
},
  "geometry": {"coordinates":[29.2558631897,40.6536521912],"type":"Point"}
}