{
  "type": "Feature",
  "properties": {
    "addr:full":"Aleaddin Bulvari Zafer Carsisi K:1 No: 120 Meram Konya 42000",
    "addr:housenumber":"zafer;120",
    "addr:postcode":"42000",
    "addr:street":"Aleaddin Bulvari;K 1 No",
    "iso:country":"TR",
    "sg:address":"Aleaddin Bulvari Zafer Carsisi K:1 No: 120",
    "sg:city":"Meram",
    "sg:classifiers":[
        {
            "category":"Home & Garden",
            "subcategory":"Building Materials",
            "type":"Retail Goods"
        }
    ],
    "sg:phone":"+90 332 353 8775",
    "sg:postcode":"42000",
    "sg:province":"Konya",
    "sg:tags":[
        "stone",
        "natural",
        "marble"
    ],
    "wof:name":"Hikmet Tuncay Ildan",
    "wof:placetype":"venue"
},
  "geometry": {"coordinates":[33.0667152405,39.2111282349],"type":"Point"}
}