{
  "type": "Feature",
  "properties": {
    "addr:full":"Bahcelievler Mah.pendik Kucuk San.sitesi Nasip Sok. No:1 Pendik Istanbul 34916",
    "addr:housenumber":"no 1",
    "addr:postcode":"34916",
    "addr:street":"Kucuk San.Sitesi Nasip Sok.",
    "iso:country":"TR",
    "sg:address":"Bahcelievler Mah.pendik Kucuk San.sitesi Nasip Sok. No:1",
    "sg:city":"Pendik",
    "sg:classifiers":[
        {
            "category":"Manufacturing",
            "subcategory":"Textiles",
            "type":"Manufacturing & Wholesale Goods"
        }
    ],
    "sg:phone":"+90 216 491 9187",
    "sg:postcode":"34916",
    "sg:province":"Istanbul",
    "sg:tags":[
        "weaving",
        "narrow",
        "-",
        "label"
    ],
    "wof:name":"Demsan Tekstil San. Ve Tic. Ltd.sti.",
    "wof:placetype":"venue"
},
  "geometry": {"coordinates":[28.9861831665,41.0408554077],"type":"Point"}
}