{
  "type": "Feature",
  "properties": {
    "iso:country":"TR",
    "sg:address":"Kemeralti Mah.60 Sk.7/3",
    "sg:city":"Marmaris",
    "sg:orig_category":"Printinh House",
    "sg:phone":"+90 2524132200413",
    "sg:postcode":"48700",
    "sg:province":"Mugla",
    "wof:name":"Yaprak Grafik",
    "wof:placetype":"venue"
},
  "geometry": {"coordinates":[28.2684211731,36.8538475037],"type":"Point"}
}