{
  "type": "Feature",
  "properties": {
    "addr:full":"Mahmutpasa Cad. No:225 Sultanhamam Istanbul",
    "addr:housenumber":"225",
    "addr:street":"Mahmutpasa Cad. No",
    "iso:country":"TR",
    "sg:address":"Mahmutpasa Cad. No:225",
    "sg:city":"Sultanhamam",
    "sg:classifiers":[
        {
            "category":"Shopping",
            "subcategory":"Clothing, Apparel, & Fashions",
            "type":"Retail Goods"
        }
    ],
    "sg:phone":"+90 212 513 0110",
    "sg:province":"Istanbul",
    "sg:tags":[
        "woman",
        "wear"
    ],
    "wof:name":"Minelli (esarplari) Pazarlama",
    "wof:placetype":"venue"
},
  "geometry": {"coordinates":[28.9700717926,41.0140190125],"type":"Point"}
}