{
  "type": "Feature",
  "properties": {
    "addr:full":"Koca Tahsin Sk. No:21 Karak\u00f6y Istanbul",
    "addr:housenumber":"21",
    "addr:street":"Sk. No",
    "iso:country":"TR",
    "sg:address":"Koca Tahsin Sk. No:21",
    "sg:city":"Karak\u00f6y",
    "sg:classifiers":[
        {
            "category":"Marine",
            "type":"Transportation"
        }
    ],
    "sg:phone":"+90 212 244 5902",
    "sg:province":"Istanbul",
    "sg:tags":[
        "equipment",
        "maritime"
    ],
    "wof:name":"Ege Gemi End?stri. A.s.",
    "wof:placetype":"venue"
},
  "geometry": {"coordinates":[28.9785480499,41.0249481201],"type":"Point"}
}