{
  "type": "Feature",
  "properties": {
    "addr:full":"1203/7 Sok. No:3/d Yenisehir Ege Tic.merkezi Bayrampasa Izmir 36100",
    "addr:housenumber":"1203 / 7;no 3 / d",
    "addr:postcode":"36100",
    "addr:street":"Sok.;Yenisehir",
    "iso:country":"TR",
    "sg:address":"1203/7 Sok. No:3/d Yenisehir Ege Tic.merkezi",
    "sg:city":"Bayrampasa",
    "sg:classifiers":[
        {
            "category":"Home & Garden",
            "subcategory":"Household Appliances",
            "type":"Retail Goods"
        }
    ],
    "sg:phone":"+90 232 458 1403",
    "sg:postcode":"36100",
    "sg:province":"Izmir",
    "sg:tags":[
        "conditioner",
        "air"
    ],
    "wof:name":"Imbat Makina San. Ve Tic. Ltd.sti.",
    "wof:placetype":"venue"
},
  "geometry": {"coordinates":[27.1296863556,38.4186973572],"type":"Point"}
}