{
  "type": "Feature",
  "properties": {
    "addr:full":"12 Cad. No:112 San Bir Bul 5 Bolge 34900 B.cekmece Istanbul Emin\u00f6n\u00fc/Ca\u011falo\u011flu Istanbul 34245",
    "addr:housenumber":"112;5",
    "addr:postcode":"34900;34245",
    "addr:street":"12 Cad. No;San Bir Bul",
    "iso:country":"TR",
    "sg:address":"12 Cad. No:112 San Bir Bul 5 Bolge 34900 B.cekmece Istanbul",
    "sg:city":"Emin\u00f6n\u00fc/Ca\u011falo\u011flu",
    "sg:classifiers":[
        {
            "category":"Personal",
            "subcategory":"Shoe Repair & Shine",
            "type":"Services"
        }
    ],
    "sg:phone":"+90 212 886 8380",
    "sg:postcode":"34245",
    "sg:province":"Istanbul",
    "sg:tags":[
        "leather"
    ],
    "wof:name":"Toktas Ayakkabi Kaliplari San",
    "wof:placetype":"venue"
},
  "geometry": {"coordinates":[28.9128303528,41.0602035522],"type":"Point"}
}