{
  "type": "Feature",
  "properties": {
    "iso:country":"TR",
    "sg:address":"Rihtim Cd. No:231",
    "sg:city":"Tophane",
    "sg:classifiers":[
        {
            "category":"Transit Center",
            "subcategory":"Freight",
            "type":"Transportation"
        }
    ],
    "sg:phone":"+90 212 244 8047",
    "sg:postcode":"07400",
    "sg:province":"Istanbul",
    "wof:name":"Catoni Deniz Isleri A.s.",
    "wof:placetype":"venue"
},
  "geometry": {"coordinates":[29.1273918152,40.9223670959],"type":"Point"}
}