{
  "type": "Feature",
  "properties": {
    "iso:country":"TR",
    "sg:address":"Inonu Cad. No:52/a Kozyatagi",
    "sg:city":"?skudar",
    "sg:classifiers":[
        {
            "category":"Shopping",
            "subcategory":"Gifts & Souvenirs",
            "type":"Retail Goods"
        }
    ],
    "sg:phone":"+90 216 360 4151",
    "sg:province":"Istanbul",
    "wof:name":"Once Ithalat- Pazarlama Ltd.",
    "wof:placetype":"venue"
},
  "geometry": {"coordinates":[29.0892314911,40.9792518616],"type":"Point"}
}