{
  "type": "Feature",
  "properties": {
    "addr:full":"?iftehavuzlar Cd. No:6 Bayrampasa Top?lar Istanbul 34056",
    "addr:housenumber":"?;no 6;?",
    "addr:postcode":"34056",
    "addr:street":"Iftehavuzlar Cd.;Bayrampasa Top",
    "iso:country":"TR",
    "sg:address":"?iftehavuzlar Cd. No:6 Bayrampasa",
    "sg:city":"Top?lar",
    "sg:classifiers":[
        {
            "category":"Manufacturing",
            "subcategory":"Metals",
            "type":"Manufacturing & Wholesale Goods"
        }
    ],
    "sg:phone":"+90 212 576 4219",
    "sg:postcode":"34056",
    "sg:province":"Istanbul",
    "sg:tags":[
        "iron-steel",
        "peoducts"
    ],
    "wof:name":"Aydin ?elik Tic. Ltd. Sti.",
    "wof:placetype":"venue"
},
  "geometry": {"coordinates":[28.906419754,41.0275306702],"type":"Point"}
}