{
  "type": "Feature",
  "properties": {
    "addr:full":"Mevlevihane Cad. Firin Sok. No: 4 34780 Merkezefendi-zeytinburnu Istanbul Ikitelli/K\u00fc\u00e7\u00fck\u00e7ekmece Istanbul 34670",
    "addr:housenumber":"no 4",
    "addr:postcode":"34780;34670",
    "addr:street":"Mevlevihane Cad. Firin Sok.",
    "iso:country":"TR",
    "sg:address":"Mevlevihane Cad. Firin Sok. No: 4 34780 Merkezefendi-zeytinburnu Istanbul",
    "sg:city":"Ikitelli/K\u00fc\u00e7\u00fck\u00e7ekmece",
    "sg:classifiers":[
        {
            "category":"Shopping",
            "subcategory":"Crafts & Fabrics",
            "type":"Retail Goods"
        }
    ],
    "sg:phone":"+90 212 510 3635",
    "sg:postcode":"34670",
    "sg:province":"Istanbul",
    "wof:name":"Baysan Boya Ve Tekstil San. Tic. A.s.",
    "wof:placetype":"venue"
},
  "geometry": {"coordinates":[28.9026584625,41.0249862671],"type":"Point"}
}