{
  "type": "Feature",
  "properties": {
    "iso:country":"TR",
    "sg:address":"Karacakaya Cd. No:71/f Siteler",
    "sg:city":"Merkez",
    "sg:classifiers":[
        {
            "category":"Manufacturing",
            "subcategory":"Wood Products",
            "type":"Manufacturing & Wholesale Goods"
        }
    ],
    "sg:phone":"+90 312 353 2061",
    "sg:postcode":"55020",
    "sg:province":"Ankara",
    "sg:tags":[
        "forest"
    ],
    "wof:name":"Senem Ticaret Parke Orman ?r?n.san.",
    "wof:placetype":"venue"
},
  "geometry": {"coordinates":[32.8954162598,39.9594688416],"type":"Point"}
}