{
  "type": "Feature",
  "properties": {
    "addr:full":"100.yil Bulvari 27 Mecidiyek\u00f6y Antalya",
    "addr:housenumber":"27",
    "addr:street":"100.Yil Bulvari",
    "iso:country":"TR",
    "sg:address":"100.yil Bulvari 27",
    "sg:city":"Mecidiyek\u00f6y",
    "sg:classifiers":[
        {
            "category":"Retail",
            "subcategory":"Driving School",
            "type":"Services"
        }
    ],
    "sg:phone":"+90 24224816472486",
    "sg:province":"Antalya",
    "sg:tags":[
        "cargo"
    ],
    "wof:name":"Intercargo",
    "wof:placetype":"venue"
},
  "geometry": {"coordinates":[30.6647071838,36.8854827881],"type":"Point"}
}