{
  "type": "Feature",
  "properties": {
    "iso:country":"TR",
    "sg:address":"Y.bosna Dogu San. Sit. Blok 11/10 Ist.",
    "sg:city":"80800",
    "sg:classifiers":[
        {
            "category":"Home & Garden",
            "subcategory":"Hardware",
            "type":"Retail Goods"
        }
    ],
    "sg:phone":"+90 212 552 1819",
    "sg:province":"Istanbul",
    "sg:tags":[
        "generator",
        "power"
    ],
    "wof:name":"Ko? Remo Elektronik Devre Eleman. San. Tic. A.s.",
    "wof:placetype":"venue"
},
  "geometry": {"coordinates":[28.8206958771,40.9819564819],"type":"Point"}
}