{
  "type": "Feature",
  "properties": {
    "iso:country":"TR",
    "sg:address":"Kavaklidere",
    "sg:city":"Ankara",
    "sg:classifiers":[
        {
            "category":"Banks & Credit Unions",
            "subcategory":"Bank",
            "type":"Services"
        }
    ],
    "sg:phone":"+90 312 467 1170",
    "sg:postcode":"63570",
    "sg:province":"06700",
    "wof:name":"Banca Commerciale, Italiana Spa",
    "wof:placetype":"venue"
},
  "geometry": {"coordinates":[32.864826,39.905682],"type":"Point"}
}