{
  "type": "Feature",
  "properties": {
    "iso:country":"TR",
    "sg:address":"Zeytinlik Mh. T?k? Sk. No:8/b",
    "sg:city":"Bak\u0131rk\u00f6y",
    "sg:classifiers":[
        {
            "category":"Shopping",
            "subcategory":"Florist",
            "type":"Retail Goods"
        }
    ],
    "sg:phone":"+90 212 571 3185",
    "sg:province":"Istanbul",
    "sg:tags":[
        "flower"
    ],
    "wof:name":"Sardunya ?i?ek Evi",
    "wof:placetype":"venue"
},
  "geometry": {"coordinates":[28.8979244232,40.9836273193],"type":"Point"}
}