{
  "type": "Feature",
  "properties": {
    "iso:country":"TR",
    "sg:address":"Barbaros Cad. No:18 Bahcelievler",
    "sg:city":"\u00dcsk\u00fcdar",
    "sg:classifiers":[
        {
            "category":"Professional",
            "subcategory":"Detective & Security Services",
            "type":"Services"
        }
    ],
    "sg:phone":"+90 212 442 1238",
    "sg:postcode":"34676",
    "sg:province":"Istanbul",
    "sg:tags":[
        "material"
    ],
    "wof:name":"Secgun Yangin Sondurme",
    "wof:placetype":"venue"
},
  "geometry": {"coordinates":[29.095232,41.05014],"type":"Point"}
}