{
  "type": "Feature",
  "properties": {
    "addr:full":"Recep Peker Cad.sefikbey Sok. No:23-2 Kiziltoprak Istanbul 07300",
    "addr:housenumber":"no",
    "addr:postcode":"07300",
    "addr:street":"Cad.Sefikbey Sok.",
    "iso:country":"TR",
    "sg:address":"Recep Peker Cad.sefikbey Sok. No:23-2",
    "sg:city":"Kiziltoprak",
    "sg:classifiers":[
        {
            "category":"Manufacturing",
            "subcategory":"Building Materials",
            "type":"Manufacturing & Wholesale Goods"
        }
    ],
    "sg:phone":"+90 216 337 3116",
    "sg:postcode":"07300",
    "sg:province":"Istanbul",
    "sg:tags":[
        "lifts-elevators"
    ],
    "wof:name":"Liftsan Asans? San",
    "wof:placetype":"venue"
},
  "geometry": {"coordinates":[28.9759254456,41.0123786926],"type":"Point"}
}