{
  "type": "Feature",
  "properties": {
    "addr:full":"Halkali Caddesi No:218 Sefak? 34295 Sahinbey Istanbul 27700",
    "addr:housenumber":"no",
    "addr:postcode":"34295;27700",
    "addr:street":"Halkali Caddesi;Sefak",
    "iso:country":"TR",
    "sg:address":"Halkali Caddesi No:218 Sefak? 34295",
    "sg:city":"Sahinbey",
    "sg:classifiers":[
        {
            "category":"Bars & Pubs",
            "subcategory":"Hookah Bar",
            "type":"Food & Drink"
        }
    ],
    "sg:phone":"+90 2126989830729",
    "sg:postcode":"27700",
    "sg:province":"Istanbul",
    "sg:tags":[
        "hard"
    ],
    "wof:name":"Doluca Sarap?lik Pazarlama Ve Ticaret A.s.",
    "wof:placetype":"venue"
},
  "geometry": {"coordinates":[28.9861831665,41.0408554077],"type":"Point"}
}