{
  "type": "Feature",
  "properties": {
    "iso:country":"TR",
    "sg:address":"Haci Mansur Sk. No:71",
    "sg:city":"Osmanbey",
    "sg:classifiers":[
        {
            "category":"Shopping",
            "subcategory":"Clothing, Apparel, & Fashions",
            "type":"Retail Goods"
        }
    ],
    "sg:phone":"+90 212 232 8219",
    "sg:postcode":"63000",
    "sg:province":"Istanbul",
    "sg:tags":[
        "woman",
        "wear"
    ],
    "wof:name":"Rerital Teks. San. Tic. Ltd. Sti. .",
    "wof:placetype":"venue"
},
  "geometry": {"coordinates":[28.9897766113,41.0541152954],"type":"Point"}
}