{
  "type": "Feature",
  "properties": {
    "addr:full":"Mektep Sk. No:11 Sishane Istanbul",
    "addr:housenumber":"11",
    "addr:street":"Mektep Sk. No",
    "iso:country":"TR",
    "sg:address":"Mektep Sk. No:11",
    "sg:city":"Sishane",
    "sg:classifiers":[
        {
            "category":"Manufacturing",
            "subcategory":"Glass & Minerals",
            "type":"Manufacturing & Wholesale Goods"
        }
    ],
    "sg:phone":"+90 212 253 8374",
    "sg:province":"Istanbul",
    "sg:tags":[
        "glass-mirror"
    ],
    "wof:name":"Isincam Ltd. Sti.",
    "wof:placetype":"venue"
},
  "geometry": {"coordinates":[28.7107048035,40.9991035461],"type":"Point"}
}