{
  "type": "Feature",
  "properties": {
    "iso:country":"TR",
    "sg:address":"Ilk Belediye Cad. No:43/1 Karakoy",
    "sg:city":"Erenk?",
    "sg:classifiers":[
        {
            "category":"Utilities",
            "subcategory":"Recycling",
            "type":"Services"
        }
    ],
    "sg:phone":"+90 212 251 8190",
    "sg:province":"Istanbul",
    "sg:tags":[
        "measuring",
        "weighing"
    ],
    "wof:name":"Amper Elek.ins.san.a.s.",
    "wof:placetype":"venue"
},
  "geometry": {"coordinates":[28.9748401642,41.0251808167],"type":"Point"}
}