{
  "type": "Feature",
  "properties": {
    "iso:country":"TR",
    "sg:address":"Hosdere Cd. No:149/a Y.ayranci",
    "sg:city":"Ikitelli",
    "sg:classifiers":[
        {
            "category":"Farming",
            "subcategory":"Fish & Marine Products",
            "type":"Manufacturing & Wholesale Goods"
        }
    ],
    "sg:phone":"+90 312 438 8727",
    "sg:postcode":"34306",
    "sg:province":"Ankara",
    "sg:tags":[
        "automotive"
    ],
    "wof:name":"Sun-sat Otomotiv Tic. Ltd. Sti.",
    "wof:placetype":"venue"
},
  "geometry": {"coordinates":[32.8467407227,39.8882598877],"type":"Point"}
}