{
  "type": "Feature",
  "properties": {
    "addr:full":"Yalvac Sok. Sp Is Hani Kat:3 No: 11 Taksim Istanbul 80080",
    "addr:housenumber":"kat 3 no 11",
    "addr:postcode":"80080",
    "addr:street":"Yalvac;Sp Is",
    "iso:country":"TR",
    "sg:address":"Yalvac Sok. Sp Is Hani Kat:3 No: 11",
    "sg:city":"Taksim",
    "sg:classifiers":[
        {
            "category":"Wholesale",
            "subcategory":"Auto Parts",
            "type":"Manufacturing & Wholesale Goods"
        }
    ],
    "sg:phone":"+90 216 575 5888",
    "sg:postcode":"80080",
    "sg:province":"Istanbul",
    "sg:tags":[
        "spare"
    ],
    "wof:name":"Seapart Dis Tic.ve Mum Ltd.sti.",
    "wof:placetype":"venue"
},
  "geometry": {"coordinates":[28.9861831665,41.0408554077],"type":"Point"}
}