{
  "type": "Feature",
  "properties": {
    "iso:country":"TR",
    "sg:address":"Imes San. Site. C 308. Sk. No:2 Y.dudullu",
    "sg:city":"\u00dcmraniye",
    "sg:classifiers":[
        {
            "category":"Utilities",
            "subcategory":"Natural Gas",
            "type":"Services"
        }
    ],
    "sg:phone":"+90 216 313 1100",
    "sg:province":"Istanbul",
    "sg:tags":[
        "tank-heating-natural"
    ],
    "wof:name":"S?g?t Plastik Kalip San. Tic. A.s.",
    "wof:placetype":"venue"
},
  "geometry": {"coordinates":[28.9861793518,41.040851593],"type":"Point"}
}