{
  "type": "Feature",
  "properties": {
    "iso:country":"TR",
    "sg:address":"Fazilpasa Cad.no:6",
    "sg:city":"Topkapi",
    "sg:classifiers":[
        {
            "category":"Manufacturing",
            "subcategory":"Textiles",
            "type":"Manufacturing & Wholesale Goods"
        }
    ],
    "sg:phone":"+90 212 544 7620",
    "sg:postcode":"24620",
    "sg:province":"Istanbul",
    "sg:tags":[
        "sizing",
        "dye"
    ],
    "wof:name":"Aco Tekstil A.s",
    "wof:placetype":"venue"
},
  "geometry": {"coordinates":[29.1408233643,40.9876289368],"type":"Point"}
}