{
  "type": "Feature",
  "properties": {
    "addr:full":"Bomonti Firin Sk. No:53 Sisli Okmeydani Istanbul 80270",
    "addr:housenumber":"53",
    "addr:postcode":"80270",
    "addr:street":"Sk. No",
    "iso:country":"TR",
    "sg:address":"Bomonti Firin Sk. No:53 Sisli",
    "sg:city":"Okmeydani",
    "sg:classifiers":[
        {
            "category":"Sports & Exercise",
            "subcategory":"Tennis Court",
            "type":"Entertainment"
        }
    ],
    "sg:phone":"+90 212 247 8550",
    "sg:postcode":"80270",
    "sg:province":"Istanbul",
    "sg:tags":[
        "equipment",
        "material"
    ],
    "wof:name":"Zevk Triko San. Tic. A.s.",
    "wof:placetype":"venue"
},
  "geometry": {"coordinates":[28.980698,41.080601],"type":"Point"}
}