{
  "type": "Feature",
  "properties": {
    "addr:full":"Antbirlik Mh. ?st? Sk. No.4 G?nen Antalya 10900",
    "addr:housenumber":"?;g ?",
    "addr:postcode":"10900",
    "addr:street":"Antbirlik Mh.;St ? Sk. No.4",
    "iso:country":"TR",
    "sg:address":"Antbirlik Mh. ?st? Sk. No.4",
    "sg:city":"G?nen",
    "sg:classifiers":[
        {
            "category":"Food & Beverages",
            "subcategory":"Fruits & Vegetables",
            "type":"Retail Goods"
        }
    ],
    "sg:phone":"+90 242 321 7650",
    "sg:postcode":"10900",
    "sg:province":"Antalya",
    "sg:tags":[
        "fresh"
    ],
    "wof:name":"G?ven Tarim Turizm Ith.ihr. Ltd.sti.",
    "wof:placetype":"venue"
},
  "geometry": {"coordinates":[30.7031345367,36.8875045776],"type":"Point"}
}