{
  "type": "Feature",
  "properties": {
    "iso:country":"TR",
    "sg:address":"923 Sk. No.11 Mezarlikbasi",
    "sg:city":"Tuzla",
    "sg:classifiers":[
        {
            "category":"Social Services",
            "subcategory":"Job Training",
            "type":"Services"
        }
    ],
    "sg:phone":"+90 232 484 4646",
    "sg:postcode":"01900",
    "sg:province":"Izmir",
    "sg:tags":[
        "tannery"
    ],
    "wof:name":"G?zelcan Deri Ltd.sti.",
    "wof:placetype":"venue"
},
  "geometry": {"coordinates":[27.1423015594,38.4251480103],"type":"Point"}
}