{
  "type": "Feature",
  "properties": {
    "iso:country":"TR",
    "sg:address":"Organize San. B?ge. Bab? Cd. No:4 Sincan",
    "sg:city":"Kizilay",
    "sg:classifiers":[
        {
            "category":"Building & Trades",
            "subcategory":"Plumbing",
            "type":"Services"
        }
    ],
    "sg:phone":"+90 312 267 0629",
    "sg:postcode":"06640",
    "sg:province":"Ankara",
    "wof:name":"Protek Ithalat Ihracat Ltd. Sti.",
    "wof:placetype":"venue"
},
  "geometry": {"coordinates":[32.8563957214,39.9164428711],"type":"Point"}
}