{
  "type": "Feature",
  "properties": {
    "addr:full":"Cumhuriyet Cad. 259/8 Harbiye Ikitelli/K\u00fc\u00e7\u00fck\u00e7ekmece Istanbul 34660",
    "addr:housenumber":"259 / 8",
    "addr:postcode":"34660",
    "addr:street":"Cumhuriyet Cad.;Harbiye Ikitelli / Kuec\u0327Uekc\u0327Ekmece",
    "iso:country":"TR",
    "sg:address":"Cumhuriyet Cad. 259/8 Harbiye",
    "sg:city":"Ikitelli/K\u00fc\u00e7\u00fck\u00e7ekmece",
    "sg:classifiers":[
        {
            "category":"Social Services",
            "subcategory":"Retirement Home",
            "type":"Services"
        }
    ],
    "sg:phone":"+90 212 296 4614",
    "sg:postcode":"34660",
    "sg:province":"Istanbul",
    "sg:tags":[
        "door"
    ],
    "wof:name":"Alma Media Group",
    "wof:placetype":"venue"
},
  "geometry": {"coordinates":[28.9865970612,41.0421485901],"type":"Point"}
}