{
  "type": "Feature",
  "properties": {
    "addr:full":"1841/1. Sk. 5/1 Karsiyaka Nisantasi Izmir 80200",
    "addr:housenumber":"1841 / 1;5 / 1",
    "addr:postcode":"80200",
    "addr:street":"Sk.",
    "iso:country":"TR",
    "sg:address":"1841/1. Sk. 5/1 Karsiyaka",
    "sg:city":"Nisantasi",
    "sg:classifiers":[
        {
            "category":"Shopping",
            "subcategory":"Gifts & Souvenirs",
            "type":"Retail Goods"
        }
    ],
    "sg:phone":"+90 232 367 4089",
    "sg:postcode":"80200",
    "sg:province":"Izmir",
    "wof:name":"Bilge Promosyon",
    "wof:placetype":"venue"
},
  "geometry": {"coordinates":[27.1164093018,38.4653434753],"type":"Point"}
}