{
  "type": "Feature",
  "properties": {
    "addr:full":"Yildiz Posta Cad. 23/16 Esentepe Istanbul 01930",
    "addr:housenumber":"23 / 16",
    "addr:postcode":"01930",
    "addr:street":"Posta Cad.;Istanbul",
    "iso:country":"TR",
    "sg:address":"Yildiz Posta Cad. 23/16",
    "sg:city":"Esentepe",
    "sg:classifiers":[
        {
            "category":"Travel",
            "subcategory":"Travel Agent",
            "type":"Entertainment"
        }
    ],
    "sg:phone":"+90 27444602662991",
    "sg:postcode":"01930",
    "sg:province":"Istanbul",
    "sg:tags":[
        "agency",
        "tourism"
    ],
    "wof:name":"Transbalkan Turizm",
    "wof:placetype":"venue"
},
  "geometry": {"coordinates":[28.9861831665,41.0408554077],"type":"Point"}
}