{
  "type": "Feature",
  "properties": {
    "addr:full":"Caddesi 66/1 Gebze Cankaya 41400",
    "addr:housenumber":"66 / 1",
    "addr:postcode":"41400",
    "addr:street":"Caddesi;Cankaya",
    "iso:country":"TR",
    "sg:address":"Caddesi 66/1",
    "sg:city":"Gebze",
    "sg:classifiers":[
        {
            "category":"Banks & Credit Unions",
            "subcategory":"Bank",
            "type":"Services"
        }
    ],
    "sg:phone":"+90 312 441 6145",
    "sg:postcode":"41400",
    "sg:province":"Cankaya",
    "wof:name":"Turkish Bank As",
    "wof:placetype":"venue"
},
  "geometry": {"coordinates":[32.837067,39.86697],"type":"Point"}
}