{
  "type": "Feature",
  "properties": {
    "addr:full":"1201/1 Sok. No:14/r Besik?oglu Is Merkezi Yenisehir Izmir 31750",
    "addr:housenumber":"1201 / 1;no 14 / r;?",
    "addr:postcode":"31750",
    "addr:street":"Sok.;Oglu;Yenisehir",
    "iso:country":"TR",
    "sg:address":"1201/1 Sok. No:14/r Besik?oglu Is Merkezi",
    "sg:city":"Yenisehir",
    "sg:classifiers":[
        {
            "category":"Bars & Pubs",
            "subcategory":"Nightclub",
            "type":"Food & Drink"
        }
    ],
    "sg:phone":"+90 232 458 4270",
    "sg:postcode":"31750",
    "sg:province":"Izmir",
    "sg:tags":[
        "oprerators",
        "pier",
        "jetty"
    ],
    "wof:name":"Martek End. Mlz. Ltd.sti.",
    "wof:placetype":"venue"
},
  "geometry": {"coordinates":[27.1296863556,38.4186973572],"type":"Point"}
}