{
  "type": "Feature",
  "properties": {
    "iso:country":"TR",
    "sg:address":"Atifet Sok. No:20/1 Moda-kadikoy",
    "sg:city":"Kazasker",
    "sg:classifiers":[
        {
            "category":"Shopping",
            "subcategory":"Photographic Equipment",
            "type":"Retail Goods"
        }
    ],
    "sg:phone":"+90 216 349 4486",
    "sg:province":"Istanbul",
    "sg:tags":[
        "photo"
    ],
    "wof:name":"Civa Yayincilik Ltd.",
    "wof:placetype":"venue"
},
  "geometry": {"coordinates":[29.0245838165,40.9815216064],"type":"Point"}
}