{
  "type": "Feature",
  "properties": {
    "addr:full":"Meri?cad. 69 Ada Mimoza 4-6 D.3 Atasehir Kad\u0131k\u00f6y Istanbul 34990",
    "addr:housenumber":"?;69;4-6 d.3",
    "addr:postcode":"34990",
    "addr:street":"Meri;Cad.;Mimoza",
    "iso:country":"TR",
    "sg:address":"Meri?cad. 69 Ada Mimoza 4-6 D.3 Atasehir",
    "sg:city":"Kad\u0131k\u00f6y",
    "sg:classifiers":[
        {
            "category":"Structure",
            "subcategory":"Office Building",
            "type":"Public Place"
        }
    ],
    "sg:phone":"+90 216 456 5256",
    "sg:postcode":"34990",
    "sg:province":"Istanbul",
    "sg:tags":[
        "scaffolding",
        "form"
    ],
    "wof:name":"Tms T?fek?ioglu M?h. Kalip Ve Iskele Sistemleri",
    "wof:placetype":"venue"
},
  "geometry": {"coordinates":[28.975925,41.012379],"type":"Point"}
}