{
  "type": "Feature",
  "properties": {
    "iso:country":"TR",
    "sg:address":"Fevzicakmak Cd Degirmen Sk No:3/a",
    "sg:city":"Bayrampasa",
    "sg:classifiers":[
        {
            "category":"Building & Trades",
            "subcategory":"Electrical",
            "type":"Services"
        }
    ],
    "sg:phone":"+90 224 225 2453",
    "sg:postcode":"36100",
    "sg:province":"Bursa",
    "sg:tags":[
        "equipment",
        "lighting"
    ],
    "wof:name":"Lite Aydinlatma",
    "wof:placetype":"venue"
},
  "geometry": {"coordinates":[28.8026065826,41.0152511597],"type":"Point"}
}