{
  "type": "Feature",
  "properties": {
    "iso:country":"TR",
    "sg:address":"Akmazcesme Sk. No:31 / 3 Besiktas",
    "sg:city":"Argincik",
    "sg:classifiers":[
        {
            "category":"Home & Garden",
            "subcategory":"Kitchen Supply",
            "type":"Retail Goods"
        }
    ],
    "sg:phone":"+90 212 258 4895",
    "sg:postcode":"63850",
    "sg:province":"Istanbul",
    "sg:tags":[
        "wardrobe"
    ],
    "wof:name":"Asli Yapi",
    "wof:placetype":"venue"
},
  "geometry": {"coordinates":[28.9759254456,41.0123786926],"type":"Point"}
}