{
  "type": "Feature",
  "properties": {
    "addr:full":"Cankaya Mh.istiklal Cd.149 Sk.no:2/36 Mersin I?el 52750",
    "addr:housenumber":"2 / 36",
    "addr:postcode":"? el 52750",
    "addr:street":"Sk.No",
    "iso:country":"TR",
    "sg:address":"Cankaya Mh.istiklal Cd.149 Sk.no:2/36",
    "sg:city":"Mersin",
    "sg:classifiers":[
        {
            "category":"Professional",
            "subcategory":"Business Services",
            "type":"Services"
        }
    ],
    "sg:phone":"+90 324 233 9863",
    "sg:postcode":"52750",
    "sg:province":"I?el",
    "sg:tags":[
        "food",
        "product",
        "exporter",
        "aricultural"
    ],
    "wof:name":"Isiklar Ltd Sti.",
    "wof:placetype":"venue"
},
  "geometry": {"coordinates":[37.7128486633,41.0530204773],"type":"Point"}
}