{
  "type": "Feature",
  "properties": {
    "iso:country":"TR",
    "sg:address":"B?? Toptancilar Cars. 18. Blok No:147 Y?egir",
    "sg:city":"B\u00fcy\u00fck\u00e7ekmece",
    "sg:orig_category":"Aluminium Carpentary",
    "sg:phone":"+90 322 346 0274",
    "sg:postcode":"34900",
    "sg:province":"Adana",
    "wof:name":"Aslamacilar Ltd. Sti.",
    "wof:placetype":"venue"
},
  "geometry": {"coordinates":[35.3137359619,37.0007171631],"type":"Point"}
}