{
  "type": "Feature",
  "properties": {
    "iso:country":"TR",
    "sg:address":"Cumhuriyet Cd. Nazili Pasaji No:16",
    "sg:city":"Kartal",
    "sg:classifiers":[
        {
            "category":"Manufacturing",
            "subcategory":"Food",
            "type":"Manufacturing & Wholesale Goods"
        }
    ],
    "sg:phone":"+90 274 223 9306",
    "sg:postcode":"46000",
    "sg:province":"K?tahya",
    "sg:tags":[
        "wholesaler"
    ],
    "wof:name":"Entes Group",
    "wof:placetype":"venue"
},
  "geometry": {"coordinates":[35.4317016602,38.9577407837],"type":"Point"}
}