{
  "type": "Feature",
  "properties": {
    "iso:country":"TR",
    "sg:address":"Elbasan Yolu 1.km Catalca",
    "sg:city":"Altindag",
    "sg:classifiers":[
        {
            "category":"Autos & Motor Vehicles",
            "subcategory":"Auto Supplies",
            "type":"Retail Goods"
        }
    ],
    "sg:phone":"+90 212 776 4120",
    "sg:postcode":"06070",
    "sg:province":"Istanbul",
    "sg:tags":[
        "accessory"
    ],
    "wof:name":"Dost Cam Oto Cam Sanayi Tic.ltd.sti.",
    "wof:placetype":"venue"
},
  "geometry": {"coordinates":[28.9861831665,41.0408554077],"type":"Point"}
}