{
  "type": "Feature",
  "properties": {
    "addr:full":"Perpa Tic. Mrk. Kat 13 No.2411, Okmeydani Maltepe Istanbul 34843",
    "addr:housenumber":"13 no.2411",
    "addr:postcode":"34843",
    "addr:street":"Kat;Okmeydani Maltepe Istanbul",
    "iso:country":"TR",
    "sg:address":"Perpa Tic. Mrk. Kat 13 No.2411, Okmeydani",
    "sg:city":"Maltepe",
    "sg:classifiers":[
        {
            "category":"Banks & Credit Unions",
            "subcategory":"Investment Brokerage",
            "type":"Services"
        }
    ],
    "sg:phone":"+90 212210681516",
    "sg:postcode":"34843",
    "sg:province":"Istanbul",
    "sg:tags":[
        "-",
        "export",
        "import"
    ],
    "wof:name":"Su Tekstil, Plastik, Turizm Ve Gida San. Dis Tic.ltd.sti.",
    "wof:placetype":"venue"
},
  "geometry": {"coordinates":[28.9861831665,41.0408554077],"type":"Point"}
}