{
  "type": "Feature",
  "properties": {
    "addr:full":"Ataturk Bulvari And Is Hani No:69/246 Kizilay Ankara 23050",
    "addr:housenumber":"246",
    "addr:postcode":"23050",
    "addr:street":"Ataturk Bulvari And;Kizilay Ankara",
    "iso:country":"TR",
    "sg:address":"Ataturk Bulvari And Is Hani No:69/246",
    "sg:city":"Kizilay",
    "sg:classifiers":[
        {
            "category":"Food & Beverages",
            "subcategory":"Groceries & Convenience Stores",
            "type":"Retail Goods"
        }
    ],
    "sg:phone":"+90 312 435 9836",
    "sg:postcode":"23050",
    "sg:province":"Ankara",
    "sg:tags":[
        "ready"
    ],
    "wof:name":"Tayf Bilgisayar Insaat Turz.san.ve Tic.ltd.sti.",
    "wof:placetype":"venue"
},
  "geometry": {"coordinates":[32.8560333252,39.9438743591],"type":"Point"}
}