{
  "type": "Feature",
  "properties": {
    "addr:full":"Kurtulus Mah Kibris Kahramanmaras 46040 46000",
    "addr:postcode":"46040 46000",
    "addr:street":"Mah",
    "iso:country":"TR",
    "sg:address":"Kurtulus Mah Kibris",
    "sg:city":"Kahramanmaras",
    "sg:classifiers":[
        {
            "category":"Banks & Credit Unions",
            "subcategory":"Bank",
            "type":"Services"
        }
    ],
    "sg:phone":"+90 344 255 3891",
    "sg:postcode":"46000",
    "sg:province":"46040",
    "wof:name":"S?erbank As",
    "wof:placetype":"venue"
},
  "geometry": {"coordinates":[27.842413,37.842815],"type":"Point"}
}