{
  "type": "Feature",
  "properties": {
    "iso:country":"TR",
    "sg:address":"Abdi Ipek? Cad. No:3 Yakacik-",
    "sg:city":"Kartal",
    "sg:classifiers":[
        {
            "category":"Home & Garden",
            "subcategory":"Household Appliances",
            "type":"Retail Goods"
        }
    ],
    "sg:phone":"+90 216 451 6204",
    "sg:postcode":"46000",
    "sg:province":"Istanbul",
    "sg:tags":[
        "conditioner",
        "air"
    ],
    "wof:name":"Aldag Sogutma Sanayii A.s.",
    "wof:placetype":"venue"
},
  "geometry": {"coordinates":[29.2479724884,40.8909797668],"type":"Point"}
}