{
  "type": "Feature",
  "properties": {
    "iso:country":"TR",
    "sg:address":"Bahariye No: 78/6",
    "sg:city":"Kadikoy",
    "sg:classifiers":[
        {
            "category":"Manufacturing",
            "subcategory":"Building Materials",
            "type":"Manufacturing & Wholesale Goods"
        }
    ],
    "sg:phone":"+90 216 336 6484",
    "sg:postcode":"01370",
    "sg:province":"Istanbul",
    "sg:tags":[
        "floor-wall",
        "covering"
    ],
    "wof:name":"Onarsan Ins. San. A.s.",
    "wof:placetype":"venue"
},
  "geometry": {"coordinates":[28.8388462067,41.0121078491],"type":"Point"}
}