{
  "type": "Feature",
  "properties": {
    "iso:country":"TR",
    "sg:address":"Baskale",
    "sg:city":"Istanbul",
    "sg:classifiers":[
        {
            "category":"Banks & Credit Unions",
            "subcategory":"Bank",
            "type":"Services"
        }
    ],
    "sg:phone":"+90 432 212 1476",
    "sg:province":"Van",
    "wof:name":"Tc Ziraat Bankasi",
    "wof:placetype":"venue"
},
  "geometry": {"coordinates":[44.0149,38.0476],"type":"Point"}
}