{
  "type": "Feature",
  "properties": {
    "iso:country":"TR",
    "sg:address":"Abdullah Cevdet Sk. No:20/1 ?ankaya",
    "sg:city":"Kartal",
    "sg:classifiers":[
        {
            "category":"Farming",
            "subcategory":"Fish & Marine Products",
            "type":"Manufacturing & Wholesale Goods"
        }
    ],
    "sg:phone":"+90 312 440 3595",
    "sg:postcode":"46000",
    "sg:province":"Ankara",
    "sg:tags":[
        "automotive"
    ],
    "wof:name":"Rayal Otomotiv San. Tic. A.s.",
    "wof:placetype":"venue"
},
  "geometry": {"coordinates":[32.8578948975,39.8858413696],"type":"Point"}
}