{
  "type": "Feature",
  "properties": {
    "iso:country":"TR",
    "sg:address":"Egitim Mah. Deveciler Sk. No:11/c",
    "sg:city":"Mersin",
    "sg:classifiers":[
        {
            "category":"Wholesale",
            "subcategory":"Medical Equipment & Supplies",
            "type":"Manufacturing & Wholesale Goods"
        }
    ],
    "sg:phone":"+90 224 360 9898",
    "sg:postcode":"52750",
    "sg:province":"Bursa",
    "wof:name":"Ar-tip Tic.",
    "wof:placetype":"venue"
},
  "geometry": {"coordinates":[29.0586109161,40.1844291687],"type":"Point"}
}