{
  "type": "Feature",
  "properties": {
    "addr:full":"Anafartalar Cad. 84/b Samanpazari 06641 06230",
    "addr:housenumber":"84 / b;06641",
    "addr:postcode":"06230",
    "addr:street":"Anafartalar Cad.;Samanpazari",
    "iso:country":"TR",
    "sg:address":"Anafartalar Cad. 84/b",
    "sg:city":"Samanpazari",
    "sg:classifiers":[
        {
            "category":"Banks & Credit Unions",
            "subcategory":"Bank",
            "type":"Services"
        }
    ],
    "sg:phone":"+90 312 324 0922",
    "sg:postcode":"06230",
    "sg:province":"06641",
    "wof:name":"Etibank Bao",
    "wof:placetype":"venue"
},
  "geometry": {"coordinates":[32.840611,39.92075],"type":"Point"}
}