{
  "type": "Feature",
  "properties": {
    "iso:country":"TR",
    "sg:address":"Saraylar Mah. Konakhan Is Merkezi No:2 Kat:3/303 Birlik Carsisi Kat:3 No:15/80",
    "sg:city":"Merkez",
    "sg:classifiers":[
        {
            "category":"Mining & Drilling",
            "type":"Manufacturing & Wholesale Goods"
        }
    ],
    "sg:phone":"+90 25824131902621",
    "sg:postcode":"07100",
    "sg:province":"Denizli",
    "sg:tags":[
        "industry",
        "mine"
    ],
    "wof:name":"Aks Madencilik Ve Mermercilik Ltd.sti.",
    "wof:placetype":"venue"
},
  "geometry": {"coordinates":[29.0864906311,37.773525238],"type":"Point"}
}