{
  "type": "Feature",
  "properties": {
    "iso:country":"TR",
    "sg:address":"Eskisehir",
    "sg:city":"Ikitelli/K\u00fc\u00e7\u00fck\u00e7ekmece",
    "sg:classifiers":[
        {
            "category":"Health Services",
            "subcategory":"Hospital",
            "type":"Services"
        }
    ],
    "sg:phone":"+90 222239297918",
    "sg:postcode":"34660",
    "sg:province":"Eskisehir",
    "sg:tags":[
        "state"
    ],
    "wof:name":"Osmangazi ?ni. Tip Fak?tesi",
    "wof:placetype":"venue"
},
  "geometry": {"coordinates":[31.036945,39.658611],"type":"Point"}
}