{
  "type": "Feature",
  "properties": {
    "iso:country":"TR",
    "sg:address":"Sair Esref Bul 23",
    "sg:city":"Izmir",
    "sg:classifiers":[
        {
            "category":"Banks & Credit Unions",
            "subcategory":"Bank",
            "type":"Services"
        }
    ],
    "sg:phone":"+90 232 441 4900",
    "sg:province":"35210",
    "wof:name":"T?k Dis Ticaret, Bankasi As",
    "wof:placetype":"venue"
},
  "geometry": {"coordinates":[27.139328,38.426022],"type":"Point"}
}