{
  "type": "Feature",
  "properties": {
    "addr:full":"Cukurcesme Cad. No:57 34130 G.o.p Istanbul Ikitelli/K\u00fc\u00e7\u00fck\u00e7ekmece Istanbul 34670",
    "addr:housenumber":"57",
    "addr:postcode":"34130;34670",
    "addr:street":"Cukurcesme Cad. No",
    "iso:country":"TR",
    "sg:address":"Cukurcesme Cad. No:57 34130 G.o.p Istanbul",
    "sg:city":"Ikitelli/K\u00fc\u00e7\u00fck\u00e7ekmece",
    "sg:classifiers":[
        {
            "category":"Shopping",
            "subcategory":"Crafts & Fabrics",
            "type":"Retail Goods"
        }
    ],
    "sg:phone":"+90 212 616 4251",
    "sg:postcode":"34670",
    "sg:province":"Istanbul",
    "wof:name":"Modern Mensucat San Tic As",
    "wof:placetype":"venue"
},
  "geometry": {"coordinates":[28.8702011108,41.0919151306],"type":"Point"}
}