{
  "type": "Feature",
  "properties": {
    "addr:full":"Yeni Mh. Osmancik Ke??en ?orum",
    "addr:street":"Ke ? ? En ?",
    "iso:country":"TR",
    "sg:address":"Yeni Mh. Osmancik",
    "sg:city":"Ke??en",
    "sg:classifiers":[
        {
            "category":"Organizations",
            "subcategory":"Membership Organization",
            "type":"Services"
        }
    ],
    "sg:phone":"+90 364 611 4102",
    "sg:province":"?orum",
    "wof:name":"Osmancik Halk Egitim Dernegi",
    "wof:placetype":"venue"
},
  "geometry": {"coordinates":[34.8117790222,40.9758682251],"type":"Point"}
}