{
  "type": "Feature",
  "properties": {
    "addr:full":"Org. San. B?g. Dosan San. Sit. O Blok Y.dudullu Bayrampasa Istanbul 36100",
    "addr:postcode":"36100",
    "addr:street":"Org.",
    "iso:country":"TR",
    "sg:address":"Org. San. B?g. Dosan San. Sit. O Blok Y.dudullu",
    "sg:city":"Bayrampasa",
    "sg:classifiers":[
        {
            "category":"Manufacturing",
            "subcategory":"Tools & Machinery",
            "type":"Manufacturing & Wholesale Goods"
        }
    ],
    "sg:phone":"+90 216 415 7615",
    "sg:postcode":"36100",
    "sg:province":"Istanbul",
    "sg:tags":[
        "machine",
        "industry"
    ],
    "wof:name":"Unicorn Makina San. Tic. Ltd. Sti.",
    "wof:placetype":"venue"
},
  "geometry": {"coordinates":[28.9759254456,41.0123786926],"type":"Point"}
}