{
  "type": "Feature",
  "properties": {
    "addr:full":"Ayvali Koyu ?rg? Nevsehir",
    "addr:housenumber":"koyu",
    "addr:street":"Rg",
    "iso:country":"TR",
    "sg:address":"Ayvali Koyu",
    "sg:city":"?rg?",
    "sg:classifiers":[
        {
            "category":"Utilities",
            "subcategory":"Water",
            "type":"Services"
        }
    ],
    "sg:phone":"+90 384 354 5815",
    "sg:province":"Nevsehir",
    "sg:tags":[
        "spring"
    ],
    "wof:name":"Gamirasu Hotel",
    "wof:placetype":"venue"
},
  "geometry": {"coordinates":[34.714001,38.624599],"type":"Point"}
}