{
  "type": "Feature",
  "properties": {
    "iso:country":"TR",
    "sg:address":"Acibadem C. No: 200/b Kadik?",
    "sg:city":"Ikitelli/K\u00fc\u00e7\u00fck\u00e7ekmece",
    "sg:classifiers":[
        {
            "category":"Home & Garden",
            "subcategory":"Building Materials",
            "type":"Retail Goods"
        }
    ],
    "sg:phone":"+90 216 325 7272",
    "sg:postcode":"34670",
    "sg:province":"Istanbul",
    "sg:tags":[
        "window",
        "door",
        "plastic"
    ],
    "wof:name":"Ecem Pen Ins. San. Tic. Ltd. Sti.",
    "wof:placetype":"venue"
},
  "geometry": {"coordinates":[29.045759201,41.0047683716],"type":"Point"}
}