{
  "type": "Feature",
  "properties": {
    "iso:country":"TR",
    "sg:address":"San. Sit. Ahsap Isl. 8. Blok No:5",
    "sg:city":"Mersin",
    "sg:classifiers":[
        {
            "category":"Wholesale",
            "subcategory":"Home Furnishings",
            "type":"Manufacturing & Wholesale Goods"
        }
    ],
    "sg:phone":"+90 242 345 7071",
    "sg:postcode":"52750",
    "sg:province":"Antalya",
    "sg:tags":[
        "furniture"
    ],
    "wof:name":"Yuva Mobilya",
    "wof:placetype":"venue"
},
  "geometry": {"coordinates":[30.7092056274,36.8790512085],"type":"Point"}
}