{
  "type": "Feature",
  "properties": {
    "addr:full":"Karaduvar Mah. 1727.sok. No:12 Mersin I?el 52750",
    "addr:housenumber":"1727.sok no 12",
    "addr:postcode":"? el 52750",
    "addr:street":"Karaduvar Mah.",
    "iso:country":"TR",
    "sg:address":"Karaduvar Mah. 1727.sok. No:12",
    "sg:city":"Mersin",
    "sg:classifiers":[
        {
            "category":"Manufacturing",
            "subcategory":"Food",
            "type":"Manufacturing & Wholesale Goods"
        }
    ],
    "sg:phone":"+90 3242219630729",
    "sg:postcode":"52750",
    "sg:province":"I?el",
    "sg:tags":[
        "wholesaler"
    ],
    "wof:name":"Targid Ltd. Sti.",
    "wof:placetype":"venue"
},
  "geometry": {"coordinates":[34.6949615479,36.8255958557],"type":"Point"}
}