{
  "type": "Feature",
  "properties": {
    "iso:country":"TR",
    "sg:address":"Agva Yeniyol Sok. No.2 Sile",
    "sg:city":"07100",
    "sg:classifiers":[
        {
            "category":"Manufacturing",
            "subcategory":"Wood Products",
            "type":"Manufacturing & Wholesale Goods"
        }
    ],
    "sg:phone":"+90 216 723 5255",
    "sg:province":"Istanbul",
    "sg:tags":[
        "forest"
    ],
    "wof:name":"Karbon Orman Urunler",
    "wof:placetype":"venue"
},
  "geometry": {"coordinates":[29.6133995056,41.1739006042],"type":"Point"}
}