{
  "type": "Feature",
  "properties": {
    "addr:full":"Sahidi Kuscu Sungurlu Bartin 19300",
    "addr:postcode":"19300",
    "addr:street":"Bartin",
    "iso:country":"TR",
    "sg:address":"Sahidi Kuscu",
    "sg:city":"Sungurlu",
    "sg:classifiers":[
        {
            "category":"Government",
            "subcategory":"Office",
            "type":"Public Place"
        }
    ],
    "sg:phone":"+90 378 234 1272",
    "sg:postcode":"19300",
    "sg:province":"Bartin",
    "sg:tags":[
        "municipality"
    ],
    "wof:name":"Arit Belediye Baskani",
    "wof:placetype":"venue"
},
  "geometry": {"coordinates":[32.3377990723,41.6363983154],"type":"Point"}
}