{
  "type": "Feature",
  "properties": {
    "iso:country":"TR",
    "sg:address":"Cumhuriyet Meydani No:28 Canakkale",
    "sg:city":"Merkez",
    "sg:orig_category":"Hotels: Motels",
    "sg:phone":"+90 286 213 2000",
    "sg:province":"?anakkale",
    "wof:name":"Hotel Artur",
    "wof:placetype":"venue"
},
  "geometry": {"coordinates":[26.79570961,39.964679718],"type":"Point"}
}