{
  "type": "Feature",
  "properties": {
    "addr:full":"Cumhuriyet Cd. Celik Apt.no:235/3 Harbiye Mecidiyek\u00f6y Istanbul 34387",
    "addr:housenumber":"235 / 3",
    "addr:postcode":"34387",
    "addr:street":"Cumhuriyet Cd. Celik Apt.No;Harbiye Mecidiyekoey",
    "iso:country":"TR",
    "sg:address":"Cumhuriyet Cd. Celik Apt.no:235/3 Harbiye",
    "sg:city":"Mecidiyek\u00f6y",
    "sg:classifiers":[
        {
            "category":"Organizations",
            "subcategory":"Membership Organization",
            "type":"Services"
        }
    ],
    "sg:phone":"+90 212 234 5245",
    "sg:postcode":"34387",
    "sg:province":"Istanbul",
    "wof:name":"Turkiye Turizm Yatirimcilari Dernegi",
    "wof:placetype":"venue"
},
  "geometry": {"coordinates":[28.9861831665,41.0408554077],"type":"Point"}
}