{
  "type": "Feature",
  "properties": {
    "iso:country":"TR",
    "sg:address":"Kuleli Sok. No:37/4 G.o.pasa-",
    "sg:city":"Cankaya",
    "sg:classifiers":[
        {
            "category":"Building & Trades",
            "subcategory":"Landscaping Services",
            "type":"Services"
        }
    ],
    "sg:phone":"+90 312 437 2573",
    "sg:postcode":"07080",
    "sg:province":"Ankara",
    "sg:tags":[
        "landscape"
    ],
    "wof:name":"Cevrem Tur Dan.pey.ith.ihr.san.tic.ltd.sti.",
    "wof:placetype":"venue"
},
  "geometry": {"coordinates":[32.8735351562,39.8968048096],"type":"Point"}
}