{
  "type": "Feature",
  "properties": {
    "iso:country":"TR",
    "sg:address":"Izmir Asfalti Belediye Cad.no:5 Gumusler",
    "sg:city":"Mersin",
    "sg:classifiers":[
        {
            "category":"Home & Garden",
            "subcategory":"Building Materials",
            "type":"Retail Goods"
        }
    ],
    "sg:phone":"+90 258 371 0656",
    "sg:postcode":"52750",
    "sg:province":"Denizli",
    "sg:tags":[
        "window",
        "door",
        "plastic"
    ],
    "wof:name":"Isik Pen",
    "wof:placetype":"venue"
},
  "geometry": {"coordinates":[29.0864906311,37.773525238],"type":"Point"}
}