{
  "type": "Feature",
  "properties": {
    "addr:full":"Ataturk Cad.no:3/38 Merter/cesme ?aglayan Istanbul",
    "addr:housenumber":"3 / 38",
    "iso:country":"TR",
    "sg:address":"Ataturk Cad.no:3/38 Merter/cesme",
    "sg:city":"?aglayan",
    "sg:classifiers":[
        {
            "category":"Shopping",
            "subcategory":"Stationery & Office Supplies",
            "type":"Retail Goods"
        }
    ],
    "sg:phone":"+90 212 637 3481",
    "sg:province":"Istanbul",
    "wof:name":"Ibrahim Ordu Kagir Ve Dahili Tic.",
    "wof:placetype":"venue"
},
  "geometry": {"coordinates":[28.868673,41.020142],"type":"Point"}
}