{
  "type": "Feature",
  "properties": {
    "iso:country":"TR",
    "sg:address":"Carsi Mah In?? Artvin",
    "sg:city":"Denizli",
    "sg:classifiers":[
        {
            "category":"Banks & Credit Unions",
            "subcategory":"Bank",
            "type":"Services"
        }
    ],
    "sg:phone":"+90 466 212 1298",
    "sg:postcode":"01130",
    "sg:province":"08000",
    "wof:name":"T?kiye Is Bankasi As",
    "wof:placetype":"venue"
},
  "geometry": {"coordinates":[41.819569,41.180637],"type":"Point"}
}