{
  "type": "Feature",
  "properties": {
    "addr:full":"Abide-i H?riyet Cd. No:69 Sisli Istanbul 65710",
    "addr:housenumber":"no 69",
    "addr:postcode":"65710",
    "addr:street":"Riyet Cd.;Istanbul",
    "iso:country":"TR",
    "sg:address":"Abide-i H?riyet Cd. No:69",
    "sg:city":"Sisli",
    "sg:classifiers":[
        {
            "category":"Shopping",
            "subcategory":"Florist",
            "type":"Retail Goods"
        }
    ],
    "sg:phone":"+90 212 232 0725",
    "sg:postcode":"65710",
    "sg:province":"Istanbul",
    "sg:tags":[
        "flower"
    ],
    "wof:name":"Orkide Florya ?i?ek?ilik Ith. Ihr.",
    "wof:placetype":"venue"
},
  "geometry": {"coordinates":[28.9759254456,41.0123786926],"type":"Point"}
}