{
  "type": "Feature",
  "properties": {
    "addr:full":"Bagdat Cd. No:449 D:3 Suadiye Kusadasi Istanbul 09400",
    "addr:housenumber":"no 449 d 3",
    "addr:postcode":"09400",
    "addr:street":"Bagdat Cd.;Suadiye",
    "iso:country":"TR",
    "sg:address":"Bagdat Cd. No:449 D:3 Suadiye",
    "sg:city":"Kusadasi",
    "sg:orig_category":"Art Galeries",
    "sg:phone":"+90 212 363 7594",
    "sg:postcode":"09400",
    "sg:province":"Istanbul",
    "wof:name":"Exclusive Sanat Merk.",
    "wof:placetype":"venue"
},
  "geometry": {"coordinates":[28.9861831665,41.0408554077],"type":"Point"}
}