{
  "type": "Feature",
  "properties": {
    "addr:full":"Perpa Tic. Merkz. B-blok Kat:8 No:956 Okmeydani Okmeydani Istanbul 43050",
    "addr:housenumber":"kat 8 no 956",
    "addr:postcode":"43050",
    "addr:street":"Okmeydani Okmeydani",
    "iso:country":"TR",
    "sg:address":"Perpa Tic. Merkz. B-blok Kat:8 No:956 Okmeydani",
    "sg:city":"Okmeydani",
    "sg:classifiers":[
        {
            "category":"Home & Garden",
            "subcategory":"Hardware",
            "type":"Retail Goods"
        }
    ],
    "sg:phone":"+90 212 221 5493",
    "sg:postcode":"43050",
    "sg:province":"Istanbul",
    "sg:tags":[
        "generator",
        "power"
    ],
    "wof:name":"Burtas Makina Sanayi Ticaret",
    "wof:placetype":"venue"
},
  "geometry": {"coordinates":[28.9759254456,41.0123786926],"type":"Point"}
}