{
  "type": "Feature",
  "properties": {
    "iso:country":"TR",
    "sg:address":"Zubeyde Hanim Cad. No.104 Zeytinburnu",
    "sg:city":"Beyazit",
    "sg:classifiers":[
        {
            "category":"Manufacturing",
            "subcategory":"Leather Goods",
            "type":"Manufacturing & Wholesale Goods"
        }
    ],
    "sg:phone":"+90 21254662315466",
    "sg:postcode":"65400",
    "sg:province":"Istanbul",
    "wof:name":"Seyman Dericilik San.tic.ltd.sti.",
    "wof:placetype":"venue"
},
  "geometry": {"coordinates":[28.9075012207,40.988067627],"type":"Point"}
}