{
  "type": "Feature",
  "properties": {
    "addr:full":"Gazi Bulv.no.59 ?ankaya Zeytinburnu Izmir 41000",
    "addr:housenumber":"bulv.no.59 ?",
    "addr:postcode":"41000",
    "addr:street":"Gazi;Ankaya Zeytinburnu",
    "iso:country":"TR",
    "sg:address":"Gazi Bulv.no.59 ?ankaya",
    "sg:city":"Zeytinburnu",
    "sg:classifiers":[
        {
            "category":"Shopping",
            "subcategory":"Luggage & Leather Goods",
            "type":"Retail Goods"
        }
    ],
    "sg:phone":"+90 232 484 4362",
    "sg:postcode":"41000",
    "sg:province":"Izmir",
    "sg:tags":[
        "leather-fur",
        "wear"
    ],
    "wof:name":"Simkal Deri Mam. Ltd.sti.",
    "wof:placetype":"venue"
},
  "geometry": {"coordinates":[27.1372013092,38.4242401123],"type":"Point"}
}