{
  "type": "Feature",
  "properties": {
    "iso:country":"TR",
    "sg:address":"Organize San. B?.",
    "sg:city":"Kabatas",
    "sg:classifiers":[
        {
            "category":"Manufacturing",
            "subcategory":"Tools & Machinery",
            "type":"Manufacturing & Wholesale Goods"
        }
    ],
    "sg:phone":"+90 352321131332",
    "sg:postcode":"34427",
    "sg:province":"Kayseri",
    "sg:tags":[
        "machine",
        "industry"
    ],
    "wof:name":"Bora Tanker Dorse Araroz Imal.",
    "wof:placetype":"venue"
},
  "geometry": {"coordinates":[35.4558753967,38.6452293396],"type":"Point"}
}