{
  "type": "Feature",
  "properties": {
    "iso:country":"TR",
    "sg:address":"58. Sk. No:21 Ostim",
    "sg:city":"Topkapi",
    "sg:classifiers":[
        {
            "category":"Manufacturing",
            "subcategory":"Rubber & Plastics",
            "type":"Manufacturing & Wholesale Goods"
        }
    ],
    "sg:phone":"+90 312 354 2171",
    "sg:postcode":"24620",
    "sg:province":"Ankara",
    "sg:tags":[
        "industry"
    ],
    "wof:name":"?zler Plastik San. Tic. Ltd. Sti.",
    "wof:placetype":"venue"
},
  "geometry": {"coordinates":[32.7414016724,39.9793052673],"type":"Point"}
}