{
  "type": "Feature",
  "properties": {
    "addr:full":"Cumhuriyet Bulvari No:302 Mersin Izmir 52750",
    "addr:housenumber":"no",
    "addr:postcode":"52750",
    "addr:street":"Cumhuriyet Bulvari",
    "iso:country":"TR",
    "sg:address":"Cumhuriyet Bulvari No:302",
    "sg:city":"Mersin",
    "sg:classifiers":[
        {
            "category":"Transit Center",
            "subcategory":"Freight",
            "type":"Transportation"
        }
    ],
    "sg:phone":"+90 232 463 0067",
    "sg:postcode":"52750",
    "sg:province":"Izmir",
    "wof:name":"Delta Denizcilik Tic. A.s.",
    "wof:placetype":"venue"
},
  "geometry": {"coordinates":[27.1439380646,38.4419326782],"type":"Point"}
}