{
  "type": "Feature",
  "properties": {
    "iso:country":"TR",
    "sg:address":"Malkara",
    "sg:city":"Pinarbasi",
    "sg:classifiers":[
        {
            "category":"Farming",
            "subcategory":"Farm",
            "type":"Manufacturing & Wholesale Goods"
        }
    ],
    "sg:phone":"+90 282 427 2743",
    "sg:postcode":"07630",
    "sg:province":"Tekirdag",
    "sg:tags":[
        "agricultural",
        "product"
    ],
    "wof:name":"Argill",
    "wof:placetype":"venue"
},
  "geometry": {"coordinates":[26.8930702209,40.8835830688],"type":"Point"}
}