{
  "type": "Feature",
  "properties": {
    "iso:country":"TR",
    "sg:address":"Aytar Cad. No:22/9 Levent",
    "sg:city":"Maltepe",
    "sg:orig_category":"Prefabric Construction",
    "sg:phone":"+90 212 283 4985",
    "sg:postcode":"01000",
    "sg:province":"Istanbul",
    "wof:name":"Cap Insaat Sanayi Ticaret A.s.",
    "wof:placetype":"venue"
},
  "geometry": {"coordinates":[29.0177345276,41.0744361877],"type":"Point"}
}