{
  "type": "Feature",
  "properties": {
    "addr:full":"Adliye Yani Okmeydani Aydin 43050",
    "addr:postcode":"43050",
    "addr:street":"Adliye;Aydin",
    "iso:country":"TR",
    "sg:address":"Adliye Yani",
    "sg:city":"Okmeydani",
    "sg:classifiers":[
        {
            "category":"Government",
            "subcategory":"Post Office",
            "type":"Public Place"
        }
    ],
    "sg:phone":"+90 256 214 0010",
    "sg:postcode":"43050",
    "sg:province":"Aydin",
    "sg:tags":[
        "distribution"
    ],
    "wof:name":"Dost Group",
    "wof:placetype":"venue"
},
  "geometry": {"coordinates":[28.4863967896,37.8117027283],"type":"Point"}
}