{
  "type": "Feature",
  "properties": {
    "addr:full":"Cakirhamam Temiz Cad.no:13/c Bornova Bursa 35040",
    "addr:housenumber":"13 / c",
    "addr:postcode":"35040",
    "addr:street":"Cad.No;Bornova Bursa",
    "iso:country":"TR",
    "sg:address":"Cakirhamam Temiz Cad.no:13/c",
    "sg:city":"Bornova",
    "sg:classifiers":[
        {
            "category":"Wholesale",
            "subcategory":"Machinery & Supplies",
            "type":"Manufacturing & Wholesale Goods"
        }
    ],
    "sg:phone":"+90 224 221 5599",
    "sg:postcode":"35040",
    "sg:province":"Bursa",
    "sg:tags":[
        "laboratory",
        "equipment"
    ],
    "wof:name":"Labor Teknik Ltd.sti.",
    "wof:placetype":"venue"
},
  "geometry": {"coordinates":[29.0580043793,40.1947555542],"type":"Point"}
}