{
  "type": "Feature",
  "properties": {
    "addr:full":"Dereboyu Mevkii Boyalik Cesme Izmir 15930",
    "addr:postcode":"15930",
    "addr:street":"Dereboyu Mevkii Boyalik Cesme",
    "iso:country":"TR",
    "sg:address":"Dereboyu Mevkii Boyalik",
    "sg:city":"Cesme",
    "sg:orig_category":"Hotels: Motels",
    "sg:phone":"+90 232 723 3756",
    "sg:postcode":"15930",
    "sg:province":"Izmir",
    "wof:name":"Turban Ilica",
    "wof:placetype":"venue"
},
  "geometry": {"coordinates":[27.1423015594,38.4251480103],"type":"Point"}
}