{
  "type": "Feature",
  "properties": {
    "addr:full":"Hast. Cd. 494. Sk. No:1/5 Etiler Denizli 07010",
    "addr:housenumber":"494;5",
    "addr:postcode":"07010",
    "addr:street":"Hast. Cd.;Sk. No 1 /",
    "iso:country":"TR",
    "sg:address":"Hast. Cd. 494. Sk. No:1/5",
    "sg:city":"Etiler",
    "sg:classifiers":[
        {
            "category":"Shopping",
            "subcategory":"Florist",
            "type":"Retail Goods"
        }
    ],
    "sg:phone":"+90 258 264 3677",
    "sg:postcode":"07010",
    "sg:province":"Denizli",
    "sg:tags":[
        "flower"
    ],
    "wof:name":"?zlem ?i?ekcilik",
    "wof:placetype":"venue"
},
  "geometry": {"coordinates":[29.0864906311,37.773525238],"type":"Point"}
}