{
  "type": "Feature",
  "properties": {
    "iso:country":"TR",
    "sg:address":"Velibaba Mh. Dolayoba Cd. No:95",
    "sg:city":"Pendik",
    "sg:classifiers":[
        {
            "category":"Manufacturing",
            "subcategory":"Textiles",
            "type":"Manufacturing & Wholesale Goods"
        }
    ],
    "sg:phone":"+90 216 307 4867",
    "sg:postcode":"34916",
    "sg:province":"Istanbul",
    "sg:tags":[
        "cloth",
        "worker"
    ],
    "wof:name":"Oben Is Elbise. Ltd. Sti.",
    "wof:placetype":"venue"
},
  "geometry": {"coordinates":[29.2562561035,40.9008712769],"type":"Point"}
}