{
  "type": "Feature",
  "properties": {
    "addr:full":"Kumbaraci Yok. Sk. Kumbaraci Han No:115 D:2 Beyoglu Ey\u00fcp Istanbul 34050",
    "addr:housenumber":"d 2",
    "addr:postcode":"34050",
    "addr:street":"Yok. Sk.;Beyoglu Eyuep",
    "iso:country":"TR",
    "sg:address":"Kumbaraci Yok. Sk. Kumbaraci Han No:115 D:2 Beyoglu",
    "sg:city":"Ey\u00fcp",
    "sg:classifiers":[
        {
            "category":"Organizations",
            "subcategory":"Membership Organization",
            "type":"Services"
        }
    ],
    "sg:phone":"+90 212 252 4461",
    "sg:postcode":"34050",
    "sg:province":"Istanbul",
    "wof:name":"Istanbul Fotograf Sinema Amatorleri Dernegi",
    "wof:placetype":"venue"
},
  "geometry": {"coordinates":[28.9861831665,41.0408554077],"type":"Point"}
}