{
  "type": "Feature",
  "properties": {
    "iso:country":"TR",
    "sg:address":"G.osmanpasa Bulv. Ko?s Ism. No:87 D:105 Cankaya",
    "sg:city":"Erenk?",
    "sg:classifiers":[
        {
            "category":"Organizations",
            "subcategory":"Professional Association",
            "type":"Services"
        }
    ],
    "sg:phone":"+90 232 483 2701",
    "sg:province":"Izmir",
    "wof:name":"Izmir Elbiseciler Ve Benz. Odasi",
    "wof:placetype":"venue"
},
  "geometry": {"coordinates":[27.1007118225,38.4045791626],"type":"Point"}
}