{
  "type": "Feature",
  "properties": {
    "addr:full":"Organize Sanayi B?gesi Ii. Kisim Osmanbey Denizli 63000",
    "addr:housenumber":"?",
    "addr:postcode":"63000",
    "addr:street":"Organize Sanayi B;Ii. Kisim Osmanbey",
    "iso:country":"TR",
    "sg:address":"Organize Sanayi B?gesi Ii. Kisim",
    "sg:city":"Osmanbey",
    "sg:classifiers":[
        {
            "category":"Sports & Exercise",
            "subcategory":"Ski Slope",
            "type":"Entertainment"
        }
    ],
    "sg:phone":"+90 258 269 1038",
    "sg:postcode":"63000",
    "sg:province":"Denizli",
    "sg:tags":[
        "wear"
    ],
    "wof:name":"Dok-san Denizli Dokuma A.s",
    "wof:placetype":"venue"
},
  "geometry": {"coordinates":[29.086491,37.773525],"type":"Point"}
}