{
  "type": "Feature",
  "properties": {
    "addr:full":"Ibrahim Akkus Nallihan Gen? Bing?l 06920",
    "addr:housenumber":"?",
    "addr:postcode":"06920",
    "addr:street":"Gen;L",
    "iso:country":"TR",
    "sg:address":"Ibrahim Akkus",
    "sg:city":"Nallihan",
    "sg:classifiers":[
        {
            "category":"Government",
            "subcategory":"Office",
            "type":"Public Place"
        }
    ],
    "sg:phone":"+90 426 422 1050",
    "sg:postcode":"06920",
    "sg:province":"Gen? Bing?l",
    "sg:tags":[
        "municipality"
    ],
    "wof:name":"?aytepe Belediye Baskani",
    "wof:placetype":"venue"
},
  "geometry": {"coordinates":[31.2825603485,40.1758918762],"type":"Point"}
}