{
  "type": "Feature",
  "properties": {
    "addr:full":"Yuksek Kaldirim Cad. No:56 Karakoy Kizilay Istanbul 23050",
    "addr:housenumber":"56",
    "addr:postcode":"23050",
    "addr:street":"Kaldirim Cad. No",
    "iso:country":"TR",
    "sg:address":"Yuksek Kaldirim Cad. No:56 Karakoy",
    "sg:city":"Kizilay",
    "sg:classifiers":[
        {
            "category":"Shopping",
            "subcategory":"Party Supplies",
            "type":"Retail Goods"
        }
    ],
    "sg:phone":"+90 212 293 5632",
    "sg:postcode":"23050",
    "sg:province":"Istanbul",
    "sg:tags":[
        "sound",
        "light",
        "system"
    ],
    "wof:name":"Atak Eletronik San.tic.ltd.sti.",
    "wof:placetype":"venue"
},
  "geometry": {"coordinates":[28.9759254456,41.0123786926],"type":"Point"}
}