{
  "type": "Feature",
  "properties": {
    "addr:full":"Millet Cad. Karag? Ism. No:41 F.zade 22/306 Istanbul",
    "addr:housenumber":"?;no 41;22 / 306",
    "addr:street":"Millet Cad. Karag;F.Zade",
    "iso:country":"TR",
    "sg:address":"Millet Cad. Karag? Ism. No:41 F.zade",
    "sg:city":"22/306",
    "sg:classifiers":[
        {
            "category":"Wholesale",
            "subcategory":"Medical Equipment & Supplies",
            "type":"Manufacturing & Wholesale Goods"
        }
    ],
    "sg:phone":"+90 212 524 2282",
    "sg:province":"Istanbul",
    "wof:name":"Gulyuva Sag. Urn.",
    "wof:placetype":"venue"
},
  "geometry": {"coordinates":[28.9861793518,41.040851593],"type":"Point"}
}