{
  "type": "Feature",
  "properties": {
    "addr:full":"Halk Cd.erdem Ish.no19 K3 D6 Usk?ar Istanbul",
    "addr:housenumber":"d6;?",
    "iso:country":"TR",
    "sg:address":"Halk Cd.erdem Ish.no19 K3 D6",
    "sg:city":"Usk?ar",
    "sg:classifiers":[
        {
            "category":"Freight",
            "type":"Transportation"
        }
    ],
    "sg:phone":"+90 216 391 7843",
    "sg:province":"Istanbul",
    "sg:tags":[
        "agent",
        "shipping",
        "broker"
    ],
    "wof:name":"Sunmarine Den.ltd.sti.",
    "wof:placetype":"venue"
},
  "geometry": {"coordinates":[28.975925,41.012379],"type":"Point"}
}