{
  "type": "Feature",
  "properties": {
    "iso:country":"TR",
    "sg:address":"Mustafa Sarig?",
    "sg:city":"?ubuk",
    "sg:classifiers":[
        {
            "category":"Government",
            "subcategory":"Office",
            "type":"Public Place"
        }
    ],
    "sg:province":"Istanbul",
    "sg:tags":[
        "municipality"
    ],
    "wof:name":"Sisli Belediye Baskani",
    "wof:placetype":"venue"
},
  "geometry": {"coordinates":[29.0487785339,41.1466178894],"type":"Point"}
}