{
  "type": "Feature",
  "properties": {
    "iso:country":"TR",
    "sg:address":"Kaynarca/",
    "sg:city":"Pendik",
    "sg:classifiers":[
        {
            "category":"Shopping",
            "subcategory":"Clothing, Apparel, & Fashions",
            "type":"Retail Goods"
        }
    ],
    "sg:phone":"+90 216 397 6247",
    "sg:postcode":"34916",
    "sg:province":"Istanbul",
    "sg:tags":[
        "ready",
        "wear"
    ],
    "wof:name":"Fatson",
    "wof:placetype":"venue"
},
  "geometry": {"coordinates":[29.2800884247,40.8692970276],"type":"Point"}
}