{
  "type": "Feature",
  "properties": {
    "iso:country":"TR",
    "sg:address":"Eski Londra Asfalti No: 139/5 Cesme Duragi",
    "sg:city":"Gungoren",
    "sg:classifiers":[
        {
            "category":"Parking",
            "subcategory":"Garage",
            "type":"Transportation"
        }
    ],
    "sg:phone":"+90 212 637 9161",
    "sg:postcode":"33630",
    "sg:province":"Istanbul",
    "sg:tags":[
        "zipper"
    ],
    "wof:name":"Ensar Fermuar Teks.san.tic.ltd.sti.",
    "wof:placetype":"venue"
},
  "geometry": {"coordinates":[26.5556755066,41.6762008667],"type":"Point"}
}