{
  "type": "Feature",
  "properties": {
    "iso:country":"TR",
    "sg:address":"Cumhuriyet Cad.yildiz Apt.kat:4 No:8-c",
    "sg:city":"Karatay",
    "sg:classifiers":[
        {
            "category":"Wholesale",
            "subcategory":"Medical Equipment & Supplies",
            "type":"Manufacturing & Wholesale Goods"
        }
    ],
    "sg:phone":"+90 242 247 9393",
    "sg:postcode":"42000",
    "sg:province":"Antalya",
    "wof:name":"Alp Medikal ?r?n-tibbi Cihaz",
    "wof:placetype":"venue"
},
  "geometry": {"coordinates":[30.7092056274,36.8790512085],"type":"Point"}
}