{
  "type": "Feature",
  "properties": {
    "addr:full":"Ok?musa Cd. Menekse Ismerk. No:54/61 Karak\u00f6y Istanbul",
    "addr:housenumber":"54 / 61",
    "addr:street":"Musa Cd. Menekse Ismerk. No",
    "iso:country":"TR",
    "sg:address":"Ok?musa Cd. Menekse Ismerk. No:54/61",
    "sg:city":"Karak\u00f6y",
    "sg:classifiers":[
        {
            "category":"Home & Garden",
            "subcategory":"Household Appliances",
            "type":"Retail Goods"
        }
    ],
    "sg:phone":"+90 212 253 8076",
    "sg:province":"Istanbul",
    "sg:tags":[
        "conditioner",
        "air"
    ],
    "wof:name":"Frekans Elekt. Isi San.",
    "wof:placetype":"venue"
},
  "geometry": {"coordinates":[28.9759254456,41.0123786926],"type":"Point"}
}