{
  "type": "Feature",
  "properties": {
    "addr:full":"1471. Sk. No:9 K:5 Izmir B\u00fcy\u00fck\u00e7ekmece Izmir 34905",
    "addr:housenumber":"1471;5",
    "addr:postcode":"34905",
    "addr:street":"Sk. No 9 K;Bueyuekc\u0327Ekmece",
    "iso:country":"TR",
    "sg:address":"1471. Sk. No:9 K:5 Izmir",
    "sg:city":"B\u00fcy\u00fck\u00e7ekmece",
    "sg:classifiers":[
        {
            "category":"Home & Garden",
            "subcategory":"Kitchen Supply",
            "type":"Retail Goods"
        }
    ],
    "sg:phone":"+90 232 422 5189",
    "sg:postcode":"34905",
    "sg:province":"Izmir",
    "sg:tags":[
        "wardrobe"
    ],
    "wof:name":"Bayindir Ins. Dekor. A.s.",
    "wof:placetype":"venue"
},
  "geometry": {"coordinates":[27.1454391479,38.4395141602],"type":"Point"}
}