{
  "type": "Feature",
  "properties": {
    "addr:full":"Siyavuspasa Cad.no:52 /12 Bahcelievler Istanbul 01980",
    "addr:housenumber":"52 / 12",
    "addr:postcode":"01980",
    "iso:country":"TR",
    "sg:address":"Siyavuspasa Cad.no:52 /12",
    "sg:city":"Bahcelievler",
    "sg:classifiers":[
        {
            "category":"Manufacturing",
            "subcategory":"Glass & Minerals",
            "type":"Manufacturing & Wholesale Goods"
        }
    ],
    "sg:postcode":"01980",
    "sg:province":"Istanbul",
    "sg:tags":[
        "glass-mirror"
    ],
    "wof:name":"Akgun Btb Cam Mozaik",
    "wof:placetype":"venue"
},
  "geometry": {"coordinates":[28.9030857086,40.991230011],"type":"Point"}
}