{
  "type": "Feature",
  "properties": {
    "addr:full":"Haramidere Sanayi Sitesi M Blok 2.yol No:110 Avcilar Istanbul 34840",
    "addr:housenumber":"2.yol no 110",
    "addr:postcode":"34840",
    "addr:street":"Haramidere Sanayi Sitesi M Blok;Avcilar Istanbul",
    "iso:country":"TR",
    "sg:address":"Haramidere Sanayi Sitesi M Blok 2.yol No:110",
    "sg:city":"Avcilar",
    "sg:classifiers":[
        {
            "category":"Building & Trades",
            "subcategory":"Construction",
            "type":"Services"
        }
    ],
    "sg:phone":"+90 212422795657",
    "sg:postcode":"34840",
    "sg:province":"Istanbul",
    "sg:tags":[
        "steel"
    ],
    "wof:name":"Enermak M?h. Makina Kons.ins.ve San.ltd.sti",
    "wof:placetype":"venue"
},
  "geometry": {"coordinates":[29.107077,40.951256],"type":"Point"}
}