{
  "type": "Feature",
  "properties": {
    "addr:full":"Polatlar Mah. Sedirler Cad. No: 142 Sirinevler Konya 34188",
    "addr:housenumber":"142",
    "addr:postcode":"34188",
    "addr:street":"Polatlar Mah. Sedirler Cad. No",
    "iso:country":"TR",
    "sg:address":"Polatlar Mah. Sedirler Cad. No: 142",
    "sg:city":"Sirinevler",
    "sg:classifiers":[
        {
            "category":"Banks & Credit Unions",
            "subcategory":"Investment Brokerage",
            "type":"Services"
        }
    ],
    "sg:phone":"+90 332 355 8612",
    "sg:postcode":"34188",
    "sg:province":"Konya",
    "sg:tags":[
        "-",
        "export",
        "import"
    ],
    "wof:name":"Hameks Ic Ve Dis Tic.a.s.",
    "wof:placetype":"venue"
},
  "geometry": {"coordinates":[33.0667152405,39.2111282349],"type":"Point"}
}