{
  "type": "Feature",
  "properties": {
    "iso:country":"TR",
    "sg:address":"1718.sok. No: 18 Mustabe Apt.k:2 D:4 Karsiyaka",
    "sg:city":"Sisli",
    "sg:classifiers":[
        {
            "category":"Government",
            "subcategory":"Office",
            "type":"Public Place"
        }
    ],
    "sg:phone":"+90 2323647988729",
    "sg:postcode":"80650",
    "sg:province":"Izmir",
    "sg:tags":[
        "patent",
        "mark"
    ],
    "wof:name":"Pamar Patent & Marka Sinai Mulkiyet Musavirligi",
    "wof:placetype":"venue"
},
  "geometry": {"coordinates":[27.1423015594,38.4251480103],"type":"Point"}
}