{
  "type": "Feature",
  "properties": {
    "iso:country":"TR",
    "sg:address":"Savas Cad.no:12/7",
    "sg:city":"Merter",
    "sg:classifiers":[
        {
            "category":"Shopping",
            "subcategory":"Crafts & Fabrics",
            "type":"Retail Goods"
        }
    ],
    "sg:phone":"+90 212 637 8235",
    "sg:province":"Istanbul",
    "sg:tags":[
        "yarn"
    ],
    "wof:name":"T.t. Tekstil",
    "wof:placetype":"venue"
},
  "geometry": {"coordinates":[28.886756897,41.0164871216],"type":"Point"}
}