{
  "type": "Feature",
  "properties": {
    "addr:full":"1420.sok. No.5 D:2 Kahramanlar Sisli Izmir 65710",
    "addr:housenumber":"d 2",
    "addr:postcode":"65710",
    "addr:street":"Kahramanlar Sisli",
    "iso:country":"TR",
    "sg:address":"1420.sok. No.5 D:2 Kahramanlar",
    "sg:city":"Sisli",
    "sg:classifiers":[
        {
            "category":"Professional",
            "subcategory":"Detective & Security Services",
            "type":"Services"
        }
    ],
    "sg:phone":"+90 232 425 4002",
    "sg:postcode":"65710",
    "sg:province":"Izmir",
    "sg:tags":[
        "material"
    ],
    "wof:name":"Denge Guvenlik Sist.elektronik San.tic.ltd.sti.",
    "wof:placetype":"venue"
},
  "geometry": {"coordinates":[27.151987,38.427483],"type":"Point"}
}