{
  "type": "Feature",
  "properties": {
    "addr:full":"Soganlik Cad. No:68 A Karlitepe Kartal Istanbul 46000",
    "addr:housenumber":"68 a",
    "addr:postcode":"46000",
    "addr:street":"Soganlik Cad. No;Karlitepe Kartal",
    "iso:country":"TR",
    "sg:address":"Soganlik Cad. No:68 A Karlitepe",
    "sg:city":"Kartal",
    "sg:classifiers":[
        {
            "category":"Manufacturing",
            "subcategory":"Glass & Minerals",
            "type":"Manufacturing & Wholesale Goods"
        }
    ],
    "sg:phone":"+90 216 353 6707",
    "sg:postcode":"46000",
    "sg:province":"Istanbul",
    "sg:tags":[
        "glass-mirror"
    ],
    "wof:name":"Baran Cam",
    "wof:placetype":"venue"
},
  "geometry": {"coordinates":[28.8793239594,40.9890136719],"type":"Point"}
}