{
  "type": "Feature",
  "properties": {
    "addr:full":"Tunus Cd. No:63/2 Kavaklidere Maltepe Ankara 01000",
    "addr:housenumber":"no 63 / 2",
    "addr:postcode":"01000",
    "addr:street":"Cd.;Kavaklidere Maltepe Ankara",
    "iso:country":"TR",
    "sg:address":"Tunus Cd. No:63/2 Kavaklidere",
    "sg:city":"Maltepe",
    "sg:classifiers":[
        {
            "category":"Professional",
            "subcategory":"Employment Agencies",
            "type":"Services"
        }
    ],
    "sg:phone":"+90 312 426 4932",
    "sg:postcode":"01000",
    "sg:province":"Ankara",
    "sg:tags":[
        "machine"
    ],
    "wof:name":"Bil-roks B?ro Sistem. San. Tic. A.s.",
    "wof:placetype":"venue"
},
  "geometry": {"coordinates":[32.8553466797,39.9127502441],"type":"Point"}
}