{
  "type": "Feature",
  "properties": {
    "addr:full":"Fevzi Pasa Cad. No.129/3 Fatih Istanbul 01740",
    "addr:housenumber":"no.129 / 3",
    "addr:postcode":"01740",
    "addr:street":"Fevzi Pasa Cad.",
    "iso:country":"TR",
    "sg:address":"Fevzi Pasa Cad. No.129/3",
    "sg:city":"Fatih",
    "sg:orig_category":"Dryfood-dried Nuts",
    "sg:phone":"+90 212 534 3323",
    "sg:postcode":"01740",
    "sg:province":"Istanbul",
    "wof:name":"Mete Dis Ticaret",
    "wof:placetype":"venue"
},
  "geometry": {"coordinates":[28.9861831665,41.0408554077],"type":"Point"}
}