{
  "type": "Feature",
  "properties": {
    "addr:full":"Tepebasi Mesrutiyet Cd. Y?el Han No:124 Beyoglu B. ?ekmece Istanbul 34400",
    "addr:housenumber":"124;b. ?",
    "addr:postcode":"beyoglu;34400",
    "addr:street":"Cd. Y ? El Han No",
    "iso:country":"TR",
    "sg:address":"Tepebasi Mesrutiyet Cd. Y?el Han No:124 Beyoglu",
    "sg:city":"B. ?ekmece",
    "sg:classifiers":[
        {
            "category":"Manufacturing",
            "subcategory":"Metals",
            "type":"Manufacturing & Wholesale Goods"
        }
    ],
    "sg:phone":"+90 212 243 6127",
    "sg:postcode":"34400",
    "sg:province":"Istanbul",
    "sg:tags":[
        "industry"
    ],
    "wof:name":"Marmara Metal Metalurji San. Tic. A.s.",
    "wof:placetype":"venue"
},
  "geometry": {"coordinates":[28.9652347565,41.0676307678],"type":"Point"}
}