{
  "type": "Feature",
  "properties": {
    "iso:country":"TR",
    "sg:address":"Adana Organize Sanayi B?gesi Yakapinar",
    "sg:city":"G?esli",
    "sg:classifiers":[
        {
            "category":"Wholesale",
            "subcategory":"Auto Parts",
            "type":"Manufacturing & Wholesale Goods"
        }
    ],
    "sg:phone":"+90 322 394 3912",
    "sg:postcode":"34540",
    "sg:province":"Adana",
    "sg:tags":[
        "spare"
    ],
    "wof:name":"As Makina Imal Montaj Sanayi Tic. Ith.ihr .a.s.",
    "wof:placetype":"venue"
},
  "geometry": {"coordinates":[35.3250198364,36.9854202271],"type":"Point"}
}