{
  "type": "Feature",
  "properties": {
    "addr:full":"Sakayik Sk. No:11 Tesvikiye Kadikoy Istanbul 01370",
    "addr:housenumber":"11",
    "addr:postcode":"01370",
    "addr:street":"Sakayik Sk. No;Kadikoy",
    "iso:country":"TR",
    "sg:address":"Sakayik Sk. No:11 Tesvikiye",
    "sg:city":"Kadikoy",
    "sg:orig_category":"Art Galeries",
    "sg:phone":"+90 212 231 5069",
    "sg:postcode":"01370",
    "sg:province":"Istanbul",
    "wof:name":"Resim Onarim Merk.",
    "wof:placetype":"venue"
},
  "geometry": {"coordinates":[28.9861831665,41.0408554077],"type":"Point"}
}