{
  "type": "Feature",
  "properties": {
    "iso:country":"TR",
    "sg:address":"Yesilce Mh. Durgun Sk. No:3 Oto Sanayi Levent",
    "sg:city":"\u00dcmraniye",
    "sg:classifiers":[
        {
            "category":"Farming",
            "subcategory":"Fish & Marine Products",
            "type":"Manufacturing & Wholesale Goods"
        }
    ],
    "sg:phone":"+90 212 268 4027",
    "sg:postcode":"81260",
    "sg:province":"Istanbul",
    "sg:tags":[
        "automotive"
    ],
    "wof:name":"Mega Otomotiv San. Tic. Ltd. Sti.",
    "wof:placetype":"venue"
},
  "geometry": {"coordinates":[29.0054225922,41.0927276611],"type":"Point"}
}