{
  "type": "Feature",
  "properties": {
    "iso:country":"TR",
    "sg:address":"1672. Sokak No:2/1",
    "sg:city":"Karsiyaka",
    "sg:classifiers":[
        {
            "category":"Utilities",
            "subcategory":"Electric",
            "type":"Services"
        }
    ],
    "sg:phone":"+90 232 372 1594",
    "sg:postcode":"01900",
    "sg:province":"Izmir",
    "sg:tags":[
        "energy",
        "solar"
    ],
    "wof:name":"Intersun Solar Energy",
    "wof:placetype":"venue"
},
  "geometry": {"coordinates":[27.219444,38.466789],"type":"Point"}
}