{
  "type": "Feature",
  "properties": {
    "iso:country":"TR",
    "sg:address":"B.evler Mah. Turgutreis Cad. 17/2",
    "sg:city":"\u00dcsk\u00fcdar",
    "sg:classifiers":[
        {
            "category":"Shopping",
            "subcategory":"Gifts & Souvenirs",
            "type":"Retail Goods"
        }
    ],
    "sg:phone":"+90 242 248 6830",
    "sg:province":"Antalya",
    "wof:name":"Hidroset Yapay Kaya Sistemleri",
    "wof:placetype":"venue"
},
  "geometry": {"coordinates":[29.3047962189,40.926902771],"type":"Point"}
}