{
  "type": "Feature",
  "properties": {
    "addr:full":"Ruzgarli Esdost Sok. No: 6 06030 Ulus Fethiye Ankara 44000",
    "addr:housenumber":"no 6",
    "addr:postcode":"06030;44000",
    "addr:street":"Esdost Sok.",
    "iso:country":"TR",
    "sg:address":"Ruzgarli Esdost Sok. No: 6 06030 Ulus",
    "sg:city":"Fethiye",
    "sg:orig_category":"Hotels: Motels",
    "sg:phone":"+90 312 311 4655",
    "sg:postcode":"44000",
    "sg:province":"Ankara",
    "wof:name":"Ogulturk Hotel",
    "wof:placetype":"venue"
},
  "geometry": {"coordinates":[32.8604812622,39.9429283142],"type":"Point"}
}