{
  "type": "Feature",
  "properties": {
    "addr:full":"Gen?sman Cd. No:2 ?eliketepe B\u00fcy\u00fck\u00e7ekmece Istanbul 34905",
    "addr:housenumber":"no 2 ?",
    "addr:postcode":"34905",
    "addr:street":"Gen ? Sman Cd.;Eliketepe Bueyuekc\u0327Ekmece",
    "iso:country":"TR",
    "sg:address":"Gen?sman Cd. No:2 ?eliketepe",
    "sg:city":"B\u00fcy\u00fck\u00e7ekmece",
    "sg:orig_category":"Aluminium Carpentary",
    "sg:phone":"+90 212 281 9474",
    "sg:postcode":"34905",
    "sg:province":"Istanbul",
    "wof:name":"Flas Al. Dog. Pvc",
    "wof:placetype":"venue"
},
  "geometry": {"coordinates":[29.000038147,41.0828437805],"type":"Point"}
}