{
  "type": "Feature",
  "properties": {
    "addr:full":"Hasimiscan Cad. Hasimiscan Ishani Kat:1 D:8 Alsancak Bursa 01365",
    "addr:housenumber":"kat 1 d 8",
    "addr:postcode":"01365",
    "addr:street":"Hasimiscan Cad. Hasimiscan Ishani",
    "iso:country":"TR",
    "sg:address":"Hasimiscan Cad. Hasimiscan Ishani Kat:1 D:8",
    "sg:city":"Alsancak",
    "sg:orig_category":"Orthopedical Materials",
    "sg:phone":"+90 224 224 0783",
    "sg:postcode":"01365",
    "sg:province":"Bursa",
    "wof:name":"Nursu Medikal",
    "wof:placetype":"venue"
},
  "geometry": {"coordinates":[29.0580043793,40.1947555542],"type":"Point"}
}