{
  "type": "Feature",
  "properties": {
    "iso:country":"TR",
    "sg:address":"H??et Cad. G?b? Ishani Kat:3 D:13 Aliaga",
    "sg:city":"Maltepe",
    "sg:classifiers":[
        {
            "category":"Wholesale",
            "subcategory":"Books, Periodicals, & Newspapers",
            "type":"Manufacturing & Wholesale Goods"
        }
    ],
    "sg:phone":"+90 232 617 2520",
    "sg:postcode":"01000",
    "sg:province":"Izmir",
    "sg:tags":[
        "house",
        "publishing"
    ],
    "wof:name":"Yeni Vizyon Gazetesi",
    "wof:placetype":"venue"
},
  "geometry": {"coordinates":[27.1296863556,38.4186973572],"type":"Point"}
}