{
  "type": "Feature",
  "properties": {
    "addr:full":"G?r? Cd. No:33 Ayvalik Balikesir 01680",
    "addr:housenumber":"no 33",
    "addr:postcode":"01680",
    "addr:street":"Cd.;Balikesir",
    "iso:country":"TR",
    "sg:address":"G?r? Cd. No:33",
    "sg:city":"Ayvalik",
    "sg:orig_category":"Food Machinies",
    "sg:phone":"+90 266 312 1947",
    "sg:postcode":"01680",
    "sg:province":"Balikesir",
    "wof:name":"H?seyin Derneli",
    "wof:placetype":"venue"
},
  "geometry": {"coordinates":[27.9334659576,39.6729278564],"type":"Point"}
}