{
  "type": "Feature",
  "properties": {
    "addr:full":"Londra Asf. Kuleli Dur. No:44 Sirinevler \u00dcmraniye Istanbul",
    "addr:street":"Sirinevler",
    "iso:country":"TR",
    "sg:address":"Londra Asf. Kuleli Dur. No:44 Sirinevler",
    "sg:city":"\u00dcmraniye",
    "sg:orig_category":"General Industrial Products",
    "sg:phone":"+90 212 551 2578",
    "sg:province":"Istanbul",
    "wof:name":"G?nes Mutfak Esya . Tic. San. Ltd. Sti.",
    "wof:placetype":"venue"
},
  "geometry": {"coordinates":[28.8469848633,40.999080658],"type":"Point"}
}