{
  "type": "Feature",
  "properties": {
    "addr:full":"Numunebagi Cad 32 Kayseri Bayrampasa 63600",
    "addr:housenumber":"32",
    "addr:postcode":"63600",
    "addr:street":"Numunebagi Cad",
    "iso:country":"TR",
    "sg:address":"Numunebagi Cad 32",
    "sg:city":"Kayseri",
    "sg:classifiers":[
        {
            "category":"Banks & Credit Unions",
            "subcategory":"Bank",
            "type":"Services"
        }
    ],
    "sg:phone":"+90 212 544 6761",
    "sg:postcode":"63600",
    "sg:province":"Bayrampasa",
    "wof:name":"Etibank Bao",
    "wof:placetype":"venue"
},
  "geometry": {"coordinates":[28.914286,41.0322],"type":"Point"}
}