{
  "type": "Feature",
  "properties": {
    "addr:full":"Kisla Cd. No:40 Demirkapi Kartal Istanbul 46000",
    "addr:housenumber":"no 40",
    "addr:postcode":"46000",
    "addr:street":"Kisla Cd.;Demirkapi Kartal",
    "iso:country":"TR",
    "sg:address":"Kisla Cd. No:40 Demirkapi",
    "sg:city":"Kartal",
    "sg:classifiers":[
        {
            "category":"Shopping",
            "subcategory":"Stationery & Office Supplies",
            "type":"Retail Goods"
        }
    ],
    "sg:phone":"+90 212 544 7484",
    "sg:postcode":"46000",
    "sg:province":"Istanbul",
    "sg:tags":[
        "furniture"
    ],
    "wof:name":"Atilim Buro Mob.",
    "wof:placetype":"venue"
},
  "geometry": {"coordinates":[28.8530864716,41.0647010803],"type":"Point"}
}