{
  "type": "Feature",
  "properties": {
    "iso:country":"TR",
    "sg:address":"G?sever Sk.no.20",
    "sg:city":"Merter",
    "sg:classifiers":[
        {
            "category":"Shopping",
            "subcategory":"Clothing, Apparel, & Fashions",
            "type":"Retail Goods"
        }
    ],
    "sg:phone":"+90 212 507 4086",
    "sg:province":"Istanbul",
    "sg:tags":[
        "ready",
        "wear"
    ],
    "wof:name":"Corart Tekstil Giyim A.s. (corda)",
    "wof:placetype":"venue"
},
  "geometry": {"coordinates":[29.2754707336,40.8879585266],"type":"Point"}
}