{
  "type": "Feature",
  "properties": {
    "addr:full":"Abdullah Cevdet Sk. No:29/6 ?ankaya Iskenderun Ankara 31200",
    "addr:housenumber":"29 / 6 ?",
    "addr:postcode":"31200",
    "addr:street":"Cevdet Sk. No;Ankaya",
    "iso:country":"TR",
    "sg:address":"Abdullah Cevdet Sk. No:29/6 ?ankaya",
    "sg:city":"Iskenderun",
    "sg:classifiers":[
        {
            "category":"Mining & Drilling",
            "type":"Manufacturing & Wholesale Goods"
        }
    ],
    "sg:phone":"+90 312 438 6882",
    "sg:postcode":"31200",
    "sg:province":"Ankara",
    "sg:tags":[
        "industry",
        "mine"
    ],
    "wof:name":"T?rkok Pres Kati Yakit San. Tic. Ltd. Sti.",
    "wof:placetype":"venue"
},
  "geometry": {"coordinates":[32.8573913574,39.8854522705],"type":"Point"}
}