{
  "type": "Feature",
  "properties": {
    "addr:full":"Bayindir Sok.68/11 Kocatepe Alsancak Ankara 01365",
    "addr:housenumber":"11",
    "addr:postcode":"01365",
    "iso:country":"TR",
    "sg:address":"Bayindir Sok.68/11 Kocatepe",
    "sg:city":"Alsancak",
    "sg:classifiers":[
        {
            "category":"Government",
            "subcategory":"Office",
            "type":"Public Place"
        }
    ],
    "sg:phone":"+90 312 425 2270",
    "sg:postcode":"01365",
    "sg:province":"Ankara",
    "sg:tags":[
        "patent",
        "mark"
    ],
    "wof:name":"Kutlu Musavirlik",
    "wof:placetype":"venue"
},
  "geometry": {"coordinates":[32.8604812622,39.9429283142],"type":"Point"}
}