{
  "type": "Feature",
  "properties": {
    "addr:full":"417.sok. No:18 Kat:2 Sirinyer Emin?? 34410 Izmir",
    "addr:housenumber":"no 18 kat 2;? ?",
    "addr:postcode":"34410",
    "addr:street":"Sirinyer Emin",
    "iso:country":"TR",
    "sg:address":"417.sok. No:18 Kat:2 Sirinyer",
    "sg:city":"Emin?? 34410",
    "sg:classifiers":[
        {
            "category":"Manufacturing",
            "subcategory":"Building Materials",
            "type":"Manufacturing & Wholesale Goods"
        }
    ],
    "sg:phone":"+90 232 853 1723",
    "sg:province":"Izmir",
    "sg:tags":[
        "promotional"
    ],
    "wof:name":"Adamer Marble & Granite",
    "wof:placetype":"venue"
},
  "geometry": {"coordinates":[27.1296863556,38.4186973572],"type":"Point"}
}