{
  "type": "Feature",
  "properties": {
    "iso:country":"TR",
    "sg:address":"Kargili Sk. No:11/13 Sirkeci",
    "sg:city":"Gayrettepe/besiktas",
    "sg:classifiers":[
        {
            "category":"Farming",
            "subcategory":"Fish & Marine Products",
            "type":"Manufacturing & Wholesale Goods"
        }
    ],
    "sg:phone":"+90 212 513 7881",
    "sg:postcode":"80280",
    "sg:province":"Istanbul",
    "sg:tags":[
        "automotive"
    ],
    "wof:name":"Bayraktaroglu Motorlu Ara?lar Tic. Ltd. Sti.",
    "wof:placetype":"venue"
},
  "geometry": {"coordinates":[28.9778251648,41.0136871338],"type":"Point"}
}