{
  "type": "Feature",
  "properties": {
    "iso:country":"TR",
    "sg:address":"Evren San.sit 16.blok No: 10",
    "sg:city":"Esenyurt",
    "sg:classifiers":[
        {
            "category":"Building & Trades",
            "subcategory":"Locksmith",
            "type":"Services"
        }
    ],
    "sg:phone":"+90 212 672 5294",
    "sg:postcode":"34800",
    "sg:province":"Istanbul",
    "sg:tags":[
        "repair",
        "ship"
    ],
    "wof:name":"Promak Mekanik Salmastralari",
    "wof:placetype":"venue"
},
  "geometry": {"coordinates":[29.114344,41.115475],"type":"Point"}
}