{
  "type": "Feature",
  "properties": {
    "iso:country":"TR",
    "sg:address":"In??blv. No:69",
    "sg:city":"Sihhiye",
    "sg:classifiers":[
        {
            "category":"Professional",
            "subcategory":"Testing Lab",
            "type":"Services"
        }
    ],
    "sg:phone":"+90 352 222 6853",
    "sg:postcode":"06410",
    "sg:province":"Kayseri",
    "sg:tags":[
        "laboratory",
        "material"
    ],
    "wof:name":"Rasel Tic.",
    "wof:placetype":"venue"
},
  "geometry": {"coordinates":[33.1183013916,39.9408226013],"type":"Point"}
}