{
  "type": "Feature",
  "properties": {
    "iso:country":"TR",
    "sg:address":"Ankara Cad. Fahrettin Kerim Gokay Vakif Ishani No:31 Kat: 2 D:20 Cagaloglu",
    "sg:city":"?atalca",
    "sg:classifiers":[
        {
            "category":"Shopping",
            "subcategory":"Stationery & Office Supplies",
            "type":"Retail Goods"
        }
    ],
    "sg:phone":"+90 212 520 5874",
    "sg:province":"Istanbul",
    "wof:name":"Marka Kagit Urunleri A.s.",
    "wof:placetype":"venue"
},
  "geometry": {"coordinates":[28.975925,41.012379],"type":"Point"}
}