{
  "type": "Feature",
  "properties": {
    "iso:country":"TR",
    "sg:address":"?mraniye G?e Sanayi Sitesi O Blok No:30",
    "sg:city":"\u00dcmraniye",
    "sg:classifiers":[
        {
            "category":"Retail",
            "subcategory":"Auto Repair",
            "type":"Services"
        }
    ],
    "sg:phone":"+90 216 335 3286",
    "sg:postcode":"81250",
    "sg:province":"Istanbul",
    "sg:tags":[
        "maintenance"
    ],
    "wof:name":"Se?kin Oto",
    "wof:placetype":"venue"
},
  "geometry": {"coordinates":[28.9861831665,41.0408554077],"type":"Point"}
}