{
  "type": "Feature",
  "properties": {
    "iso:country":"TR",
    "sg:address":"Abide-i H?riyet Cad.gecit Sok.no:12 Hacionbasilar Ishani",
    "sg:city":"Sisli",
    "sg:classifiers":[
        {
            "category":"Building & Trades",
            "subcategory":"Pest Control",
            "type":"Services"
        }
    ],
    "sg:phone":"+90 212 231 4282",
    "sg:postcode":"65710",
    "sg:province":"Istanbul",
    "sg:tags":[
        "quality"
    ],
    "wof:name":"Sentez Kalite Kontrol Laboratuarlari Ltd.",
    "wof:placetype":"venue"
},
  "geometry": {"coordinates":[28.9759254456,41.0123786926],"type":"Point"}
}