{
  "type": "Feature",
  "properties": {
    "addr:full":"Ziya G?alp Cd. No:9 Iskenderun 0003 Hatay",
    "addr:housenumber":"?;no 9",
    "addr:postcode":"0003",
    "addr:street":"Ziya G;Cd.",
    "iso:country":"TR",
    "sg:address":"Ziya G?alp Cd. No:9 Iskenderun",
    "sg:city":"0003",
    "sg:classifiers":[
        {
            "category":"Banks & Credit Unions",
            "subcategory":"Investment Brokerage",
            "type":"Services"
        }
    ],
    "sg:phone":"+90 326 612 9034",
    "sg:province":"Hatay",
    "sg:tags":[
        "-",
        "export",
        "import"
    ],
    "wof:name":"Olgun M?messillik Ltd. Sti.",
    "wof:placetype":"venue"
},
  "geometry": {"coordinates":[36.1766014099,36.585899353],"type":"Point"}
}