{
  "type": "Feature",
  "properties": {
    "addr:full":"2 Eyl? Cad. Yediler Sk. No:2/b Bak\u0131rk\u00f6y Eskisehir",
    "addr:housenumber":"2;b",
    "addr:street":"Eyl ? Cad. Yediler Sk. No 2 /",
    "iso:country":"TR",
    "sg:address":"2 Eyl? Cad. Yediler Sk. No:2/b",
    "sg:city":"Bak\u0131rk\u00f6y",
    "sg:orig_category":"Orthopedical Materials",
    "sg:phone":"+90 222 221 4044",
    "sg:province":"Eskisehir",
    "wof:name":"Tolga Tip Tic.",
    "wof:placetype":"venue"
},
  "geometry": {"coordinates":[30.5175457001,39.7700805664],"type":"Point"}
}