{
  "type": "Feature",
  "properties": {
    "addr:full":"Yusuf Cerit Emirdag Afyon 03600",
    "addr:postcode":"03600",
    "addr:street":"Afyon",
    "iso:country":"TR",
    "sg:address":"Yusuf Cerit",
    "sg:city":"Emirdag",
    "sg:classifiers":[
        {
            "category":"Government",
            "subcategory":"Office",
            "type":"Public Place"
        }
    ],
    "sg:phone":"+90 272 448 3001",
    "sg:postcode":"03600",
    "sg:province":"Afyon",
    "sg:tags":[
        "municipality"
    ],
    "wof:name":"Bademli Belediye Baskani",
    "wof:placetype":"venue"
},
  "geometry": {"coordinates":[30.5417995453,38.7557983398],"type":"Point"}
}