{
  "type": "Feature",
  "properties": {
    "addr:full":"Ulucanlar Cad. 88/22 Cebeci 58010 Ankara",
    "addr:housenumber":"88 / 22",
    "addr:postcode":"58010",
    "addr:street":"Ulucanlar Cad.;Cebeci",
    "iso:country":"TR",
    "sg:address":"Ulucanlar Cad. 88/22 Cebeci",
    "sg:city":"58010",
    "sg:classifiers":[
        {
            "category":"Wholesale",
            "subcategory":"Medical Equipment & Supplies",
            "type":"Manufacturing & Wholesale Goods"
        }
    ],
    "sg:phone":"+90 312 363 5052",
    "sg:province":"Ankara",
    "sg:tags":[
        "material"
    ],
    "wof:name":"4a Medical Industry",
    "wof:placetype":"venue"
},
  "geometry": {"coordinates":[32.8789405823,39.9321098328],"type":"Point"}
}