{
  "type": "Feature",
  "properties": {
    "addr:full":"Mumhane Cd. No:3 Karak\u00f6y Istanbul",
    "addr:housenumber":"no 3",
    "addr:street":"Mumhane Cd.",
    "iso:country":"TR",
    "sg:address":"Mumhane Cd. No:3",
    "sg:city":"Karak\u00f6y",
    "sg:classifiers":[
        {
            "category":"Transit Center",
            "subcategory":"Freight",
            "type":"Transportation"
        }
    ],
    "sg:phone":"+90 212 251 2560",
    "sg:province":"Istanbul",
    "wof:name":"Mim-tur Denizcilik Tic. Ltd. Sti.",
    "wof:placetype":"venue"
},
  "geometry": {"coordinates":[28.9412059784,41.0354766846],"type":"Point"}
}