{
  "type": "Feature",
  "properties": {
    "iso:country":"TR",
    "sg:address":"1884 Sk. No. 73",
    "sg:city":"Inciralti",
    "sg:classifiers":[
        {
            "category":"Farming",
            "subcategory":"Farm",
            "type":"Manufacturing & Wholesale Goods"
        }
    ],
    "sg:phone":"+90 542 431 9402",
    "sg:postcode":"35340",
    "sg:province":"Izmir",
    "sg:tags":[
        "agricultural",
        "product"
    ],
    "wof:name":"Karamanli Seracilik Ve Cicekcilik",
    "wof:placetype":"venue"
},
  "geometry": {"coordinates":[27.0737476349,38.3909645081],"type":"Point"}
}