{
  "type": "Feature",
  "properties": {
    "iso:country":"TR",
    "sg:address":"Bagcilar Cd. No:179 Bagcilar",
    "sg:city":"0038",
    "sg:classifiers":[
        {
            "category":"Home & Garden",
            "subcategory":"Household Appliances",
            "type":"Retail Goods"
        }
    ],
    "sg:phone":"+90 212 575 0373",
    "sg:province":"Istanbul",
    "sg:tags":[
        "utensil",
        "electrical"
    ],
    "wof:name":"Cansizoglu A.s.",
    "wof:placetype":"venue"
},
  "geometry": {"coordinates":[28.8513698578,41.0430297852],"type":"Point"}
}