{
  "type": "Feature",
  "properties": {
    "iso:country":"TR",
    "sg:address":"Pancar Kasabasi",
    "sg:city":"Torbali",
    "sg:classifiers":[
        {
            "category":"Shopping",
            "subcategory":"Crafts & Fabrics",
            "type":"Retail Goods"
        }
    ],
    "sg:phone":"+90 232 864 1100",
    "sg:postcode":"35860",
    "sg:province":"Izmir",
    "sg:tags":[
        "knitting"
    ],
    "wof:name":"P?tas Pamuk A.s",
    "wof:placetype":"venue"
},
  "geometry": {"coordinates":[27.1296863556,38.4186973572],"type":"Point"}
}