{
  "type": "Feature",
  "properties": {
    "addr:full":"Sair Nigar Sk. No.56 Sisli Istanbul 65710",
    "addr:postcode":"65710",
    "addr:street":"Sair Nigar",
    "iso:country":"TR",
    "sg:address":"Sair Nigar Sk. No.56",
    "sg:city":"Sisli",
    "sg:classifiers":[
        {
            "category":"Shopping",
            "subcategory":"Clothing, Apparel, & Fashions",
            "type":"Retail Goods"
        }
    ],
    "sg:phone":"+90 212 241 1837",
    "sg:postcode":"65710",
    "sg:province":"Istanbul",
    "sg:tags":[
        "ready",
        "wear"
    ],
    "wof:name":"Abc Giyim Ltd.sti.",
    "wof:placetype":"venue"
},
  "geometry": {"coordinates":[28.9893245697,41.0536842346],"type":"Point"}
}