{
  "type": "Feature",
  "properties": {
    "addr:full":"Davutpasa Emintas K. Din?r San. Sit. No:81 Topkapi Bak\u0131rk\u00f6y Istanbul",
    "iso:country":"TR",
    "sg:address":"Davutpasa Emintas K. Din?r San. Sit. No:81 Topkapi",
    "sg:city":"Bak\u0131rk\u00f6y",
    "sg:classifiers":[
        {
            "category":"Shopping",
            "subcategory":"Stationery & Office Supplies",
            "type":"Retail Goods"
        }
    ],
    "sg:phone":"+90 212 565 5283",
    "sg:province":"Istanbul",
    "sg:tags":[
        "paper"
    ],
    "wof:name":"Kili?kaya Kagit?ilik San. Tic. Ltd. Sti.",
    "wof:placetype":"venue"
},
  "geometry": {"coordinates":[28.9759254456,41.0123786926],"type":"Point"}
}