{
  "type": "Feature",
  "properties": {
    "addr:full":"Ak?m Sk. No:40 Levent Bayrampasa Istanbul 36100",
    "addr:housenumber":"40",
    "addr:postcode":"36100",
    "addr:street":"M Sk. No",
    "iso:country":"TR",
    "sg:address":"Ak?m Sk. No:40 Levent",
    "sg:city":"Bayrampasa",
    "sg:classifiers":[
        {
            "category":"Communications",
            "subcategory":"Film & Video Production",
            "type":"Services"
        }
    ],
    "sg:phone":"+90 212 264 0690",
    "sg:postcode":"36100",
    "sg:province":"Istanbul",
    "sg:tags":[
        "-"
    ],
    "wof:name":"Reklamlar Film Prod?ksiyon Tic. A.s.",
    "wof:placetype":"venue"
},
  "geometry": {"coordinates":[28.9975948334,41.0700378418],"type":"Point"}
}