{
  "type": "Feature",
  "properties": {
    "addr:full":"873.sok. No:32-34 Kestanepazari Izmir",
    "addr:housenumber":"no 32-34",
    "addr:street":"Kestanepazari",
    "iso:country":"TR",
    "sg:address":"873.sok. No:32-34",
    "sg:city":"Kestanepazari",
    "sg:classifiers":[
        {
            "category":"Home & Garden",
            "subcategory":"Home Furnishings",
            "type":"Retail Goods"
        }
    ],
    "sg:phone":"+90 232 489 0266",
    "sg:province":"Izmir",
    "sg:tags":[
        "textile"
    ],
    "wof:name":"Gokceler Tekstil",
    "wof:placetype":"venue"
},
  "geometry": {"coordinates":[27.1423015594,38.4251480103],"type":"Point"}
}