{
  "type": "Feature",
  "properties": {
    "addr:full":"Harbiye Halaskargazi Cad.dersane Sok. No:14 Sisli Istanbul 65710",
    "addr:housenumber":"no 14",
    "addr:postcode":"65710",
    "addr:street":"Harbiye;Cad.Dersane Sok.;Istanbul",
    "iso:country":"TR",
    "sg:address":"Harbiye Halaskargazi Cad.dersane Sok. No:14",
    "sg:city":"Sisli",
    "sg:classifiers":[
        {
            "category":"Shopping",
            "subcategory":"Clothing, Apparel, & Fashions",
            "type":"Retail Goods"
        }
    ],
    "sg:phone":"+90 212 232 5513",
    "sg:postcode":"65710",
    "sg:province":"Istanbul",
    "sg:tags":[
        "ready",
        "wear"
    ],
    "wof:name":"Balinler Pazarlama Ve Tic.a.s.",
    "wof:placetype":"venue"
},
  "geometry": {"coordinates":[28.9759254456,41.0123786926],"type":"Point"}
}