{
  "type": "Feature",
  "properties": {
    "iso:country":"TR",
    "sg:address":"Mahmut Sayin",
    "sg:city":"Ipsala",
    "sg:classifiers":[
        {
            "category":"Government",
            "subcategory":"Office",
            "type":"Public Place"
        }
    ],
    "sg:phone":"+90 284 626 3002",
    "sg:postcode":"22400",
    "sg:province":"Edirne",
    "sg:tags":[
        "municipality"
    ],
    "wof:name":"Kocahidir Belediye Baskani",
    "wof:placetype":"venue"
},
  "geometry": {"coordinates":[26.5672454834,41.6706771851],"type":"Point"}
}