{
  "type": "Feature",
  "properties": {
    "iso:country":"TR",
    "sg:address":"Org. San. B?g. G?t?k Cd. 4 Sincan",
    "sg:city":"Osmanbey",
    "sg:classifiers":[
        {
            "category":"Home & Garden",
            "subcategory":"Home Furnishings",
            "type":"Retail Goods"
        }
    ],
    "sg:phone":"+90 312 267 0641",
    "sg:postcode":"63000",
    "sg:province":"Ankara",
    "sg:tags":[
        "quilt",
        "bed"
    ],
    "wof:name":"Samanyolu San. Tic. A.s.",
    "wof:placetype":"venue"
},
  "geometry": {"coordinates":[32.856033,39.943874],"type":"Point"}
}