{
  "type": "Feature",
  "properties": {
    "iso:country":"TR",
    "sg:address":"Imes Sanayi Sitesi E Blk. 501 Sk. No: 29 Dudullu",
    "sg:city":"\u00dcmraniye",
    "sg:classifiers":[
        {
            "category":"Manufacturing",
            "subcategory":"Tools & Machinery",
            "type":"Manufacturing & Wholesale Goods"
        }
    ],
    "sg:phone":"+90 216 415 3158",
    "sg:postcode":"81260",
    "sg:province":"Istanbul",
    "sg:tags":[
        "machine",
        "industry"
    ],
    "wof:name":"Temposan Hidroelektronik Makina San. Ve Tic. Ltd.",
    "wof:placetype":"venue"
},
  "geometry": {"coordinates":[28.9759254456,41.0123786926],"type":"Point"}
}