{
  "type": "Feature",
  "properties": {
    "addr:full":"Izzettin ?alislar Caddesi No:57/1 - Bah?lievler 64020 Istanbul",
    "addr:housenumber":"no 57 / 1;?",
    "addr:postcode":"64020",
    "addr:street":"Alislar Caddesi;Bah;Lievler",
    "iso:country":"TR",
    "sg:address":"Izzettin ?alislar Caddesi No:57/1 - Bah?lievler",
    "sg:city":"64020",
    "sg:classifiers":[
        {
            "category":"Government",
            "subcategory":"Post Office",
            "type":"Public Place"
        }
    ],
    "sg:phone":"+90 212 553 4373",
    "sg:province":"Istanbul",
    "sg:tags":[
        "notary"
    ],
    "wof:name":"Bakirk?y 21 Noterligi",
    "wof:placetype":"venue"
},
  "geometry": {"coordinates":[28.9861793518,41.040851593],"type":"Point"}
}