{
  "type": "Feature",
  "properties": {
    "addr:full":"Kagithane C. Ugur Sk. No: 48 Caglayan Istanbul 07600",
    "addr:housenumber":"48",
    "addr:postcode":"07600",
    "addr:street":"Ugur Sk. No;Istanbul",
    "iso:country":"TR",
    "sg:address":"Kagithane C. Ugur Sk. No: 48",
    "sg:city":"Caglayan",
    "sg:classifiers":[
        {
            "category":"Manufacturing",
            "subcategory":"Glass & Minerals",
            "type":"Manufacturing & Wholesale Goods"
        }
    ],
    "sg:phone":"+90 212 222 4433",
    "sg:postcode":"07600",
    "sg:province":"Istanbul",
    "sg:tags":[
        "glassware"
    ],
    "wof:name":"Osel A.s.",
    "wof:placetype":"venue"
},
  "geometry": {"coordinates":[28.9766407013,41.0753173828],"type":"Point"}
}