{
  "type": "Feature",
  "properties": {
    "iso:country":"TR",
    "sg:address":"Fatih Cad.no:101 ?amdibi 35090",
    "sg:city":"Beyoglu",
    "sg:classifiers":[
        {
            "category":"Manufacturing",
            "subcategory":"Metals",
            "type":"Manufacturing & Wholesale Goods"
        }
    ],
    "sg:phone":"+90 232 449 0489",
    "sg:postcode":"34437",
    "sg:province":"Izmir",
    "sg:tags":[
        "industry"
    ],
    "wof:name":"?agmak Yapi End?stri Taahh?t Ve Ticaret Ltd.sti",
    "wof:placetype":"venue"
},
  "geometry": {"coordinates":[27.1296863556,38.4186973572],"type":"Point"}
}