{
  "type": "Feature",
  "properties": {
    "iso:country":"TR",
    "sg:address":"S?eyman Sirri Sk. No:16/6 Sihhiye",
    "sg:city":"Hasanpasa/kadik?",
    "sg:classifiers":[
        {
            "category":"Wholesale",
            "subcategory":"Medical Equipment & Supplies",
            "type":"Manufacturing & Wholesale Goods"
        }
    ],
    "sg:phone":"+90 312 434 3467",
    "sg:postcode":"34722",
    "sg:province":"Ankara",
    "sg:tags":[
        "material"
    ],
    "wof:name":"Siyomed Medikal Sag. Mlz. Ith. Ihr.",
    "wof:placetype":"venue"
},
  "geometry": {"coordinates":[32.8560333252,39.9438743591],"type":"Point"}
}