{
  "type": "Feature",
  "properties": {
    "addr:full":"Ey? Sultan Mah. Imam Hapip Lisesi Cad. No: 17 81470 Samandera Kartal Istanbul Konak Istanbul 07110",
    "addr:housenumber":"?;17",
    "addr:postcode":"81470;07110",
    "addr:street":"Ey;Sultan Mah. Imam Hapip Lisesi Cad. No",
    "iso:country":"TR",
    "sg:address":"Ey? Sultan Mah. Imam Hapip Lisesi Cad. No: 17 81470 Samandera Kartal Istanbul",
    "sg:city":"Konak",
    "sg:classifiers":[
        {
            "category":"Real Estate",
            "subcategory":"Surveying",
            "type":"Services"
        }
    ],
    "sg:phone":"+90 216 311 0428",
    "sg:postcode":"07110",
    "sg:province":"Istanbul",
    "sg:tags":[
        "equipment",
        "material",
        "good",
        "-",
        "handling"
    ],
    "wof:name":"Isas Asans?r San Ve Tic Ltd Sti",
    "wof:placetype":"venue"
},
  "geometry": {"coordinates":[28.9759254456,41.0123786926],"type":"Point"}
}