{
  "type": "Feature",
  "properties": {
    "addr:full":"2822.sok.no: 94/a 1.san.sitesi Camdibi Ostim Izmir 06374",
    "addr:housenumber":"94 / a 1.san.sitesi camdibi ostim",
    "addr:postcode":"06374",
    "iso:country":"TR",
    "sg:address":"2822.sok.no: 94/a 1.san.sitesi Camdibi",
    "sg:city":"Ostim",
    "sg:classifiers":[
        {
            "category":"Wholesale",
            "subcategory":"Machinery & Supplies",
            "type":"Manufacturing & Wholesale Goods"
        }
    ],
    "sg:phone":"+90 232 433 6795",
    "sg:postcode":"06374",
    "sg:province":"Izmir",
    "sg:tags":[
        "bearing",
        "ball"
    ],
    "wof:name":"Oto Seker",
    "wof:placetype":"venue"
},
  "geometry": {"coordinates":[27.129686,38.418697],"type":"Point"}
}