{
  "type": "Feature",
  "properties": {
    "addr:full":"A. Ipek? Cd. Y?sel Emintas San. Sit. Bayrampasa Rami Istanbul 34140",
    "addr:housenumber":"?",
    "addr:postcode":"34140",
    "addr:street":"A.;Cd. Y ? Sel Emintas San. Sit. Bayrampasa",
    "iso:country":"TR",
    "sg:address":"A. Ipek? Cd. Y?sel Emintas San. Sit. Bayrampasa",
    "sg:city":"Rami",
    "sg:classifiers":[
        {
            "category":"Manufacturing",
            "subcategory":"Rubber & Plastics",
            "type":"Manufacturing & Wholesale Goods"
        }
    ],
    "sg:phone":"+90 212 567 4339",
    "sg:postcode":"34140",
    "sg:province":"Istanbul",
    "sg:tags":[
        "industry"
    ],
    "wof:name":"?zkan Plastik Mak. San. Tic. Ltd. Sti.",
    "wof:placetype":"venue"
},
  "geometry": {"coordinates":[28.8713321686,40.9776382446],"type":"Point"}
}