{
  "type": "Feature",
  "properties": {
    "addr:full":"Ibrahim ?ztas Nazilli Aydin 65600",
    "addr:housenumber":"?",
    "addr:postcode":"65600",
    "addr:street":"Ibrahim;Aydin",
    "iso:country":"TR",
    "sg:address":"Ibrahim ?ztas",
    "sg:city":"Nazilli",
    "sg:classifiers":[
        {
            "category":"Government",
            "subcategory":"Office",
            "type":"Public Place"
        }
    ],
    "sg:phone":"+90 256 337 2002",
    "sg:postcode":"65600",
    "sg:province":"Aydin",
    "sg:tags":[
        "municipality"
    ],
    "wof:name":"Pirlibey Belediye Baskani",
    "wof:placetype":"venue"
},
  "geometry": {"coordinates":[28.4863967896,37.8117027283],"type":"Point"}
}