{
  "type": "Feature",
  "properties": {
    "addr:full":"Yavuzselim Mah.hancer Sok.no:4 Ortakoy Bursa 01640",
    "addr:housenumber":"4",
    "addr:postcode":"01640",
    "addr:street":"Sok.No;Bursa",
    "iso:country":"TR",
    "sg:address":"Yavuzselim Mah.hancer Sok.no:4",
    "sg:city":"Ortakoy",
    "sg:classifiers":[
        {
            "category":"Manufacturing",
            "subcategory":"Textiles",
            "type":"Manufacturing & Wholesale Goods"
        }
    ],
    "sg:phone":"+90 224 367 5964",
    "sg:postcode":"01640",
    "sg:province":"Bursa",
    "sg:tags":[
        "chemical"
    ],
    "wof:name":"Apretks Tekstil Kimya Ltd.sti.",
    "wof:placetype":"venue"
},
  "geometry": {"coordinates":[29.0586109161,40.1844291687],"type":"Point"}
}