{
  "type": "Feature",
  "properties": {
    "addr:full":"Beylikpasa Mah.cengiz Topel Cad. 0309. Sok. No:2 Gebze Iskitler Kocaeli 06070",
    "addr:housenumber":"no 2",
    "addr:postcode":"0309;06070",
    "addr:street":"Topel Cad.;Sok.;Iskitler",
    "iso:country":"TR",
    "sg:address":"Beylikpasa Mah.cengiz Topel Cad. 0309. Sok. No:2 Gebze",
    "sg:city":"Iskitler",
    "sg:classifiers":[
        {
            "category":"Utilities",
            "subcategory":"Fuel Oil & Lpg",
            "type":"Services"
        }
    ],
    "sg:phone":"+90 262 744 1964",
    "sg:postcode":"06070",
    "sg:province":"Kocaeli",
    "sg:tags":[
        "gas",
        "system"
    ],
    "wof:name":"Yilmaz Dayanikli Tuketim Mallari Petrol Urunleri Tic.ltd.sti.",
    "wof:placetype":"venue"
},
  "geometry": {"coordinates":[29.881521225,40.8532714844],"type":"Point"}
}