{
  "type": "Feature",
  "properties": {
    "addr:full":"Piyalepasa Bulv.m.sevket Pasa Mah.no:22 Okmeydani Ikitelli/K\u00fc\u00e7\u00fck\u00e7ekmece Istanbul 34670",
    "addr:housenumber":"22",
    "addr:postcode":"34670",
    "addr:street":"Bulv.M.Sevket;Mah.No",
    "iso:country":"TR",
    "sg:address":"Piyalepasa Bulv.m.sevket Pasa Mah.no:22 Okmeydani",
    "sg:city":"Ikitelli/K\u00fc\u00e7\u00fck\u00e7ekmece",
    "sg:orig_category":"Prefabric Construction",
    "sg:phone":"+90 212 237 2758",
    "sg:postcode":"34670",
    "sg:province":"Istanbul",
    "wof:name":"Prizma Moduler Yapi Elemanlari Ltd",
    "wof:placetype":"venue"
},
  "geometry": {"coordinates":[28.9772090912,41.0705490112],"type":"Point"}
}