{
  "type": "Feature",
  "properties": {
    "iso:country":"TR",
    "sg:address":"Atat?k Bul No 53",
    "sg:city":"Merkez",
    "sg:classifiers":[
        {
            "category":"Food & Beverages",
            "subcategory":"Bakery",
            "type":"Retail Goods"
        }
    ],
    "sg:phone":"+90 454 216 6037",
    "sg:postcode":"28100",
    "sg:province":"Giresun",
    "sg:tags":[
        "hazelnut-pistachio-walnut"
    ],
    "wof:name":"Un-at",
    "wof:placetype":"venue"
},
  "geometry": {"coordinates":[38.384601593,40.9175300598],"type":"Point"}
}