{
  "type": "Feature",
  "properties": {
    "iso:country":"TR",
    "sg:address":"11. Sk. No:32 Ostim",
    "sg:city":"Ikitelli/K\u00fc\u00e7\u00fck\u00e7ekmece",
    "sg:classifiers":[
        {
            "category":"Manufacturing",
            "subcategory":"Metals",
            "type":"Manufacturing & Wholesale Goods"
        }
    ],
    "sg:phone":"+90 312 354 0222",
    "sg:postcode":"34670",
    "sg:province":"Ankara",
    "sg:tags":[
        "aluminium",
        "industry"
    ],
    "wof:name":"Modo Modern Dograma San. Tic. A.s.",
    "wof:placetype":"venue"
},
  "geometry": {"coordinates":[32.7404747009,39.9730148315],"type":"Point"}
}