{
  "type": "Feature",
  "properties": {
    "iso:country":"TR",
    "sg:address":"Turgut ?zal Cad. Sefak? San.sit 5 Blok No:15/17/19",
    "sg:city":"K???kmece",
    "sg:classifiers":[
        {
            "category":"Airport",
            "subcategory":"International",
            "type":"Transportation"
        }
    ],
    "sg:phone":"+90 212 671 1634",
    "sg:province":"Istanbul",
    "wof:name":"Marcom Loj. Hizm.ve Ulus.nak.tic.ltd.sti",
    "wof:placetype":"venue"
},
  "geometry": {"coordinates":[28.9861831665,41.0408554077],"type":"Point"}
}