{
  "type": "Feature",
  "properties": {
    "addr:full":"Toros Sk. No:5/1 Sihhiye Kad\u0131k\u00f6y Ankara 06920",
    "addr:housenumber":"1",
    "addr:postcode":"06920",
    "addr:street":"Toros Sk. No 5 /",
    "iso:country":"TR",
    "sg:address":"Toros Sk. No:5/1 Sihhiye",
    "sg:city":"Kad\u0131k\u00f6y",
    "sg:classifiers":[
        {
            "category":"Professional",
            "subcategory":"Employment Agencies",
            "type":"Services"
        }
    ],
    "sg:phone":"+90 312 231 4603",
    "sg:postcode":"06920",
    "sg:province":"Ankara",
    "sg:tags":[
        "machine"
    ],
    "wof:name":"Se Mak B?ro Makina. San. Tic. Ltd. Sti.",
    "wof:placetype":"venue"
},
  "geometry": {"coordinates":[32.8517684937,39.9288864136],"type":"Point"}
}