{
  "type": "Feature",
  "properties": {
    "iso:country":"TR",
    "sg:address":"San. B?ge. Sarik?-",
    "sg:city":"G?en",
    "sg:classifiers":[
        {
            "category":"Food & Beverages",
            "subcategory":"Ethnic Foods",
            "type":"Retail Goods"
        }
    ],
    "sg:phone":"+90 266 718 3194",
    "sg:province":"Balikesir",
    "sg:tags":[
        "canned"
    ],
    "wof:name":"Bandirma Zahirecilik Tic. San. Ltd. Sti.",
    "wof:placetype":"venue"
},
  "geometry": {"coordinates":[27.8853607178,39.6448783875],"type":"Point"}
}