{
  "type": "Feature",
  "properties": {
    "iso:country":"TR",
    "sg:address":"Ikitelli Org.san.b?. Bagcilar-g?g?en San.sit. 9.bl. No.27",
    "sg:city":"Ikitelli",
    "sg:classifiers":[
        {
            "category":"Wholesale",
            "subcategory":"Vending Machines",
            "type":"Manufacturing & Wholesale Goods"
        }
    ],
    "sg:phone":"+90 21254961555",
    "sg:postcode":"34306",
    "sg:province":"Istanbul",
    "sg:tags":[
        "packing"
    ],
    "wof:name":"Tamsa Ambalajlama Makineleri",
    "wof:placetype":"venue"
},
  "geometry": {"coordinates":[28.7984962463,41.0884017944],"type":"Point"}
}