{
  "type": "Feature",
  "properties": {
    "addr:full":"Delikli?nar No:12 K?cegiz Denizli 48800",
    "addr:housenumber":"k ?",
    "addr:postcode":"48800",
    "addr:street":"Cegiz Denizli",
    "iso:country":"TR",
    "sg:address":"Delikli?nar No:12",
    "sg:city":"K?cegiz",
    "sg:classifiers":[
        {
            "category":"Shopping",
            "subcategory":"Florist",
            "type":"Retail Goods"
        }
    ],
    "sg:phone":"+90 258 264 6563",
    "sg:postcode":"48800",
    "sg:province":"Denizli",
    "sg:tags":[
        "flower"
    ],
    "wof:name":"Pamukkale ?i?ekcilik",
    "wof:placetype":"venue"
},
  "geometry": {"coordinates":[29.0864906311,37.773525238],"type":"Point"}
}