{
  "type": "Feature",
  "properties": {
    "addr:full":"Maslak Cd. Korler Rehabilitasyon Merk. No:69 Sariyer \u00dcsk\u00fcdar Istanbul 34672",
    "addr:housenumber":"69",
    "addr:postcode":"34672",
    "addr:street":"Maslak Cd. Korler Rehabilitasyon Merk. No",
    "iso:country":"TR",
    "sg:address":"Maslak Cd. Korler Rehabilitasyon Merk. No:69 Sariyer",
    "sg:city":"\u00dcsk\u00fcdar",
    "sg:classifiers":[
        {
            "category":"Building & Trades",
            "subcategory":"Construction",
            "type":"Services"
        }
    ],
    "sg:phone":"+90 212 277 6228",
    "sg:postcode":"34672",
    "sg:province":"Istanbul",
    "sg:tags":[
        "foundation"
    ],
    "wof:name":"Altinokta Korler Vakfi",
    "wof:placetype":"venue"
},
  "geometry": {"coordinates":[29.0154418945,41.0218315125],"type":"Point"}
}