{
  "type": "Feature",
  "properties": {
    "addr:full":"Feritpasa Mah. Rauf Denktas Cad. Cali Sitesi Alti 18/a Bahcelievler Konya 01980",
    "addr:housenumber":"18 / a",
    "addr:postcode":"01980",
    "addr:street":"Feritpasa Mah. Rauf Denktas Cad.;Alti;Bahcelievler",
    "iso:country":"TR",
    "sg:address":"Feritpasa Mah. Rauf Denktas Cad. Cali Sitesi Alti 18/a",
    "sg:city":"Bahcelievler",
    "sg:classifiers":[
        {
            "category":"Manufacturing",
            "subcategory":"Building Materials",
            "type":"Manufacturing & Wholesale Goods"
        }
    ],
    "sg:phone":"+90 332 238 7739",
    "sg:postcode":"01980",
    "sg:province":"Konya",
    "sg:tags":[
        "lifts-elevators"
    ],
    "wof:name":"Nida Asansor",
    "wof:placetype":"venue"
},
  "geometry": {"coordinates":[32.4990272522,37.8715362549],"type":"Point"}
}