{
  "type": "Feature",
  "properties": {
    "iso:country":"TR",
    "sg:address":"1196 Sk. No.6",
    "sg:city":"Yenisehir",
    "sg:classifiers":[
        {
            "category":"Shopping",
            "subcategory":"Clothing, Apparel, & Fashions",
            "type":"Retail Goods"
        }
    ],
    "sg:phone":"+90 232 433 8000",
    "sg:postcode":"31750",
    "sg:province":"Izmir",
    "sg:tags":[
        "ready",
        "wear"
    ],
    "wof:name":"Koza Tekstil A.s.",
    "wof:placetype":"venue"
},
  "geometry": {"coordinates":[27.1554889679,38.4223747253],"type":"Point"}
}