{
  "type": "Feature",
  "properties": {
    "addr:full":"Mor S?b? No:3 Yeni Mh. Bakirk? Mahmutbey Istanbul 46600",
    "addr:housenumber":"b ? no 3;?",
    "addr:postcode":"?;46600",
    "addr:street":"Mor S;Yeni Mh. Bakirk",
    "iso:country":"TR",
    "sg:address":"Mor S?b? No:3 Yeni Mh. Bakirk?",
    "sg:city":"Mahmutbey",
    "sg:classifiers":[
        {
            "category":"Shopping",
            "subcategory":"Stationery & Office Supplies",
            "type":"Retail Goods"
        }
    ],
    "sg:phone":"+90 212 583 3659",
    "sg:postcode":"46600",
    "sg:province":"Istanbul",
    "wof:name":"Beyaz Adam Kitap Ve Kirtasiye",
    "wof:placetype":"venue"
},
  "geometry": {"coordinates":[28.975925,41.012379],"type":"Point"}
}