{
  "type": "Feature",
  "properties": {
    "addr:full":"Bagdat Cd. No:225 D:6 Kadik? Fatih Istanbul 01740",
    "addr:housenumber":"no 225 d 6 kadik ?",
    "addr:postcode":"01740",
    "addr:street":"Bagdat Cd.",
    "iso:country":"TR",
    "sg:address":"Bagdat Cd. No:225 D:6 Kadik?",
    "sg:city":"Fatih",
    "sg:classifiers":[
        {
            "category":"Building & Trades",
            "subcategory":"Construction",
            "type":"Services"
        }
    ],
    "sg:phone":"+90 216 355 1173",
    "sg:postcode":"01740",
    "sg:province":"Istanbul",
    "sg:tags":[
        "foundation"
    ],
    "wof:name":"Pathfinder Vakfi Irtibat Buro.",
    "wof:placetype":"venue"
},
  "geometry": {"coordinates":[29.0550556183,40.9739837646],"type":"Point"}
}