{
  "type": "Feature",
  "properties": {
    "addr:full":"Haciomer Mah.yahya Kemal Cad. N0 14 Adana Adiyaman 63570",
    "addr:housenumber":"14",
    "addr:postcode":"63570",
    "addr:street":"Kemal Cad. N0;Adiyaman",
    "iso:country":"TR",
    "sg:address":"Haciomer Mah.yahya Kemal Cad. N0 14",
    "sg:city":"Adana",
    "sg:classifiers":[
        {
            "category":"Shopping",
            "subcategory":"Computers & Home Electronics",
            "type":"Retail Goods"
        }
    ],
    "sg:phone":"+90 416 216 4646",
    "sg:postcode":"63570",
    "sg:province":"Adiyaman",
    "sg:tags":[
        "chamber",
        "commerce"
    ],
    "wof:name":"Adiyaman Chamber Of Commerce And Industry",
    "wof:placetype":"venue"
},
  "geometry": {"coordinates":[38.2764396667,37.7605743408],"type":"Point"}
}