{
  "type": "Feature",
  "properties": {
    "iso:country":"TR",
    "sg:address":"Cevizli Tugay Yolu No:4 K. Maltepe",
    "sg:city":"Bayrampasa",
    "sg:classifiers":[
        {
            "category":"Structure",
            "subcategory":"Office Building",
            "type":"Public Place"
        }
    ],
    "sg:phone":"+90 216 399 4829",
    "sg:postcode":"36100",
    "sg:province":"Istanbul",
    "sg:tags":[
        "satellite",
        "system"
    ],
    "wof:name":"Tron Elektrik Sistemleri",
    "wof:placetype":"venue"
},
  "geometry": {"coordinates":[29.160032,40.917732],"type":"Point"}
}