{
  "type": "Feature",
  "properties": {
    "iso:country":"TR",
    "sg:address":"Cankiri Yolu 7 Km.",
    "sg:city":"Akyurt",
    "sg:classifiers":[
        {
            "category":"Government",
            "subcategory":"Fire Station",
            "type":"Public Place"
        }
    ],
    "sg:phone":"+90 312 844 1280",
    "sg:postcode":"24800",
    "sg:province":"Ankara",
    "sg:tags":[
        "decoration"
    ],
    "wof:name":"Mob",
    "wof:placetype":"venue"
},
  "geometry": {"coordinates":[32.8604812622,39.9429283142],"type":"Point"}
}