{
  "type": "Feature",
  "properties": {
    "iso:country":"TR",
    "sg:address":"Adsiz K??s??l? Mevkii Aksehir",
    "sg:city":"Maslak",
    "sg:classifiers":[
        {
            "category":"Banks & Credit Unions",
            "subcategory":"Investment Brokerage",
            "type":"Services"
        }
    ],
    "sg:phone":"+90 332 813 2035",
    "sg:postcode":"34396",
    "sg:province":"Konya",
    "sg:tags":[
        "-",
        "export",
        "import"
    ],
    "wof:name":"Raner Dis Tic. Ltd. Sti.",
    "wof:placetype":"venue"
},
  "geometry": {"coordinates":[33.0667152405,39.2111282349],"type":"Point"}
}