{
  "type": "Feature",
  "properties": {
    "iso:country":"TR",
    "sg:address":"Besyol Halkali Cd. No:55 / 8 Sefak?",
    "sg:city":"Siteler",
    "sg:orig_category":"Aluminium Carpentary",
    "sg:phone":"+90 212 579 4229",
    "sg:postcode":"06160",
    "sg:province":"Istanbul",
    "wof:name":"Metsan Al.dog. A.s.",
    "wof:placetype":"venue"
},
  "geometry": {"coordinates":[28.8175258636,41.0154151917],"type":"Point"}
}