{
  "type": "Feature",
  "properties": {
    "addr:full":"Sehitler Cad No:2 Sahinbey Gaziantep 27060",
    "addr:postcode":"27060",
    "addr:street":"Sehitler Cad No 2 Sahinbey",
    "iso:country":"TR",
    "sg:address":"Sehitler Cad No:2",
    "sg:city":"Sahinbey",
    "sg:classifiers":[
        {
            "category":"Manufacturing",
            "subcategory":"Food",
            "type":"Manufacturing & Wholesale Goods"
        }
    ],
    "sg:phone":"+90 342 231 4583",
    "sg:postcode":"27060",
    "sg:province":"Gaziantep",
    "sg:tags":[
        "wholesaler"
    ],
    "wof:name":"Oz Yemen Baharat",
    "wof:placetype":"venue"
},
  "geometry": {"coordinates":[37.3873291016,37.0610084534],"type":"Point"}
}