{
  "type": "Feature",
  "properties": {
    "iso:country":"TR",
    "sg:address":"Adnan Saygun Cd. No:34 D.2 Ulus",
    "sg:city":"\u00c7ankaya",
    "sg:classifiers":[
        {
            "category":"Retail",
            "subcategory":"Laundry & Dry Cleaning",
            "type":"Services"
        }
    ],
    "sg:phone":"+90 212 268 0316",
    "sg:province":"Istanbul",
    "wof:name":"Orso Bianco Lan-sel Paz. Ve Tic. Ltd. Sti.",
    "wof:placetype":"venue"
},
  "geometry": {"coordinates":[29.0269794464,41.0645217896],"type":"Point"}
}