{
  "type": "Feature",
  "properties": {
    "iso:country":"TR",
    "sg:address":"Turgutreis Cd. No. 69",
    "sg:city":"B?y?k?ekmece",
    "sg:classifiers":[
        {
            "category":"Food & Beverages",
            "subcategory":"Meat & Fish",
            "type":"Retail Goods"
        }
    ],
    "sg:phone":"+90 242 247 1547",
    "sg:province":"Antalya",
    "sg:tags":[
        "seafood"
    ],
    "wof:name":"G?ney Balik?ilik Ltd.sti.",
    "wof:placetype":"venue"
},
  "geometry": {"coordinates":[32.501209259,37.8994293213],"type":"Point"}
}