{
  "type": "Feature",
  "properties": {
    "iso:country":"TR",
    "sg:address":"Aytekin Sok.no:9",
    "sg:city":"4.levent",
    "sg:classifiers":[
        {
            "category":"Home & Garden",
            "subcategory":"Household Appliances",
            "type":"Retail Goods"
        }
    ],
    "sg:phone":"+90 212 270 0269",
    "sg:province":"Istanbul",
    "sg:tags":[
        "conditioner",
        "air"
    ],
    "wof:name":"Alsem Servis Ve Muhendislik Hizm.a.s.",
    "wof:placetype":"venue"
},
  "geometry": {"coordinates":[29.0027523041,41.0961990356],"type":"Point"}
}