{
  "type": "Feature",
  "properties": {
    "addr:full":"Kozyatagi,bayar Cd.g2 Beyaz Kanarya Sk.no3/3 Yuvam Apt. Erenk? Istanbul",
    "iso:country":"TR",
    "sg:address":"Kozyatagi,bayar Cd.g2 Beyaz Kanarya Sk.no3/3 Yuvam Apt.",
    "sg:city":"Erenk?",
    "sg:classifiers":[
        {
            "category":"Mining & Drilling",
            "type":"Manufacturing & Wholesale Goods"
        }
    ],
    "sg:phone":"+90 216362254938",
    "sg:province":"Istanbul",
    "sg:tags":[
        "underwater",
        "working"
    ],
    "wof:name":"Yosun Dalgic Koll.sti.",
    "wof:placetype":"venue"
},
  "geometry": {"coordinates":[28.975925,41.012379],"type":"Point"}
}