{
  "type": "Feature",
  "properties": {
    "iso:country":"TR",
    "sg:address":"Topcu Cad. 34,",
    "sg:city":"Taksim",
    "sg:orig_category":"Hotels: Motels",
    "sg:phone":"+90 212256080325",
    "sg:postcode":"80090",
    "sg:province":"Istanbul",
    "wof:name":"Eresin Taksim Hotel",
    "wof:placetype":"venue"
},
  "geometry": {"coordinates":[29.2293510437,40.9040641785],"type":"Point"}
}