{
  "type": "Feature",
  "properties": {
    "addr:full":"Ankara Cad. No: 197 Kat:5 D:9 Bornova Sultanbeyli Izmir 81458",
    "addr:housenumber":"197 kat 5 d 9",
    "addr:postcode":"81458",
    "addr:street":"Ankara Cad. No;Bornova",
    "iso:country":"TR",
    "sg:address":"Ankara Cad. No: 197 Kat:5 D:9 Bornova",
    "sg:city":"Sultanbeyli",
    "sg:classifiers":[
        {
            "category":"Manufacturing",
            "subcategory":"Tools & Machinery",
            "type":"Manufacturing & Wholesale Goods"
        }
    ],
    "sg:phone":"+90 232 342 6070",
    "sg:postcode":"81458",
    "sg:province":"Izmir",
    "sg:tags":[
        "machine",
        "industry"
    ],
    "wof:name":"Betay Makin A Imalat Ins. Bilgsayar Ve Sist.san.tic.ltd.sti.",
    "wof:placetype":"venue"
},
  "geometry": {"coordinates":[27.1296863556,38.4186973572],"type":"Point"}
}