{
  "type": "Feature",
  "properties": {
    "iso:country":"TR",
    "sg:address":"Kenan Evren Blv 109 Sok Senlik Apt Alti 4/c",
    "sg:city":"Gulbahce",
    "sg:classifiers":[
        {
            "category":"Manufacturing",
            "subcategory":"Building Materials",
            "type":"Manufacturing & Wholesale Goods"
        }
    ],
    "sg:phone":"+90 322 235 5185",
    "sg:postcode":"31070",
    "sg:province":"Adana",
    "sg:tags":[
        "lifts-elevators"
    ],
    "wof:name":"Yorunge Asansorleri Elek San Tic Ltd.",
    "wof:placetype":"venue"
},
  "geometry": {"coordinates":[35.3137359619,37.0007171631],"type":"Point"}
}