{
  "type": "Feature",
  "properties": {
    "addr:full":"Mumin Deresi Yolu Derya Sok No 11/6 Erenkoy Istanbul 07060",
    "addr:housenumber":"no 11 / 6",
    "addr:postcode":"07060",
    "addr:street":"Deresi Yolu Derya Sok",
    "iso:country":"TR",
    "sg:address":"Mumin Deresi Yolu Derya Sok No 11/6",
    "sg:city":"Erenkoy",
    "sg:classifiers":[
        {
            "category":"Professional",
            "subcategory":"Computer Services",
            "type":"Services"
        }
    ],
    "sg:phone":"+90 216 360 0653",
    "sg:postcode":"07060",
    "sg:province":"Istanbul",
    "sg:tags":[
        "application",
        "software"
    ],
    "wof:name":"Axis Yazilim & Bilisim",
    "wof:placetype":"venue"
},
  "geometry": {"coordinates":[28.9861831665,41.0408554077],"type":"Point"}
}