{
  "type": "Feature",
  "properties": {
    "iso:country":"TR",
    "sg:address":"Cumhuriyet Cad. No: 14",
    "sg:city":"Elmadag",
    "sg:classifiers":[
        {
            "category":"Travel",
            "subcategory":"Travel Agent",
            "type":"Entertainment"
        }
    ],
    "sg:phone":"+90 2529030",
    "sg:postcode":"65900",
    "sg:province":"Istanbul",
    "sg:tags":[
        "agency",
        "tourism"
    ],
    "wof:name":"Milta Turizm",
    "wof:placetype":"venue"
},
  "geometry": {"coordinates":[29.0746898651,41.0635566711],"type":"Point"}
}