{
  "type": "Feature",
  "properties": {
    "addr:full":"6678 Sokak No:2 35570 Karsiyaka Ikitelli/K\u00fc\u00e7\u00fck\u00e7ekmece Izmir 34670",
    "addr:postcode":"35570;34670",
    "addr:street":"6678 Sokak No 2",
    "iso:country":"TR",
    "sg:address":"6678 Sokak No:2 35570 Karsiyaka",
    "sg:city":"Ikitelli/K\u00fc\u00e7\u00fck\u00e7ekmece",
    "sg:classifiers":[
        {
            "category":"Manufacturing",
            "subcategory":"Metals",
            "type":"Manufacturing & Wholesale Goods"
        }
    ],
    "sg:phone":"+90 232 365 1193",
    "sg:postcode":"34670",
    "sg:province":"Izmir",
    "sg:tags":[
        "industry"
    ],
    "wof:name":"Ge Ka Insaat Gere?leri San.ve Tic. A.s.",
    "wof:placetype":"venue"
},
  "geometry": {"coordinates":[27.0949478149,38.4792633057],"type":"Point"}
}