{
  "type": "Feature",
  "properties": {
    "addr:full":"Yeni Sanayi Zafer Cad.no:2 Ineg?l Bursa 16400",
    "addr:housenumber":"2;?",
    "addr:postcode":"16400",
    "addr:street":"Yeni Sanayi Zafer Cad.No;L Bursa",
    "iso:country":"TR",
    "sg:address":"Yeni Sanayi Zafer Cad.no:2",
    "sg:city":"Ineg?l",
    "sg:classifiers":[
        {
            "category":"Home & Garden",
            "subcategory":"Furniture",
            "type":"Retail Goods"
        }
    ],
    "sg:phone":"+90 224 711 7364",
    "sg:postcode":"16400",
    "sg:province":"Bursa",
    "sg:tags":[
        "armchair",
        "sofa"
    ],
    "wof:name":"Mercan Koltuk&mobilya",
    "wof:placetype":"venue"
},
  "geometry": {"coordinates":[29.0586109161,40.1844291687],"type":"Point"}
}