{
  "type": "Feature",
  "properties": {
    "addr:full":"Susam Sk. No.26 Cihangir Istanbul 13500",
    "addr:postcode":"13500",
    "addr:street":"Sk. No.26",
    "iso:country":"TR",
    "sg:address":"Susam Sk. No.26",
    "sg:city":"Cihangir",
    "sg:classifiers":[
        {
            "category":"Home & Garden",
            "subcategory":"Garden Supply",
            "type":"Retail Goods"
        }
    ],
    "sg:phone":"+90 212 293 0885",
    "sg:postcode":"13500",
    "sg:province":"Istanbul",
    "sg:tags":[
        "fertilize",
        "soil"
    ],
    "wof:name":"Bag-fas Bandirma G?bre A.s.",
    "wof:placetype":"venue"
},
  "geometry": {"coordinates":[28.8306083679,41.0301399231],"type":"Point"}
}