{
  "type": "Feature",
  "properties": {
    "addr:full":"Agir San. B?ge. Kepsut Cd. No:75 Kizilay Balikesir 23050",
    "addr:housenumber":"no 75",
    "addr:postcode":"23050",
    "addr:street":"Cd.;Balikesir",
    "iso:country":"TR",
    "sg:address":"Agir San. B?ge. Kepsut Cd. No:75",
    "sg:city":"Kizilay",
    "sg:classifiers":[
        {
            "category":"Wholesale",
            "subcategory":"Machinery & Supplies",
            "type":"Manufacturing & Wholesale Goods"
        }
    ],
    "sg:phone":"+90 266 241 3695",
    "sg:postcode":"23050",
    "sg:province":"Balikesir",
    "sg:tags":[
        "agricultural"
    ],
    "wof:name":"Tarsan Tarim Makina San.",
    "wof:placetype":"venue"
},
  "geometry": {"coordinates":[27.8833007812,39.6520996094],"type":"Point"}
}