{
  "type": "Feature",
  "properties": {
    "addr:full":"Ali Cetinkaya Cad.no:127 /a-b Etlik Antalya 06010",
    "addr:housenumber":"127 / a-b",
    "addr:postcode":"06010",
    "iso:country":"TR",
    "sg:address":"Ali Cetinkaya Cad.no:127 /a-b",
    "sg:city":"Etlik",
    "sg:classifiers":[
        {
            "category":"Home & Garden",
            "subcategory":"Household Appliances",
            "type":"Retail Goods"
        }
    ],
    "sg:phone":"+90 242 322 9238",
    "sg:postcode":"06010",
    "sg:province":"Antalya",
    "sg:tags":[
        "conditioner",
        "air"
    ],
    "wof:name":"Form Endusri Urunleri Tic.a.s.",
    "wof:placetype":"venue"
},
  "geometry": {"coordinates":[30.7182064056,36.8887214661],"type":"Point"}
}