{
  "type": "Feature",
  "properties": {
    "addr:full":"28 Nisan Cad. No.8 G?sel Mah. Kagithane Istanbul 34406",
    "addr:housenumber":"g ?",
    "addr:postcode":"34406",
    "addr:street":"28 Nisan Cad. No.8",
    "iso:country":"TR",
    "sg:address":"28 Nisan Cad. No.8 G?sel Mah.",
    "sg:city":"Kagithane",
    "sg:classifiers":[
        {
            "category":"Shopping",
            "subcategory":"Clothing, Apparel, & Fashions",
            "type":"Retail Goods"
        }
    ],
    "sg:phone":"+90 212210119394",
    "sg:postcode":"34406",
    "sg:province":"Istanbul",
    "sg:tags":[
        "woman",
        "wear"
    ],
    "wof:name":"Promise Tekstil",
    "wof:placetype":"venue"
},
  "geometry": {"coordinates":[29.0669937134,40.9733924866],"type":"Point"}
}