{
  "type": "Feature",
  "properties": {
    "addr:full":"Nezihe Gurbuz Sok. No:3/1 Moda- Kadikoy Istanbul 01370",
    "addr:housenumber":"no 3 / 1",
    "addr:postcode":"01370",
    "addr:street":"Gurbuz Sok.",
    "iso:country":"TR",
    "sg:address":"Nezihe Gurbuz Sok. No:3/1 Moda-",
    "sg:city":"Kadikoy",
    "sg:classifiers":[
        {
            "category":"Freight",
            "type":"Transportation"
        }
    ],
    "sg:phone":"+90 216 418 5060",
    "sg:postcode":"01370",
    "sg:province":"Istanbul",
    "sg:tags":[
        "agent",
        "shipping",
        "broker"
    ],
    "wof:name":"Adda Deniz Acent.ltd.sti.",
    "wof:placetype":"venue"
},
  "geometry": {"coordinates":[29.018038,41.008312],"type":"Point"}
}