{
  "type": "Feature",
  "properties": {
    "iso:country":"TR",
    "sg:address":"Menderes Cd. Ata Apt. A Blok No: 28",
    "sg:city":"Kavaklidere",
    "sg:classifiers":[
        {
            "category":"Mining & Drilling",
            "type":"Manufacturing & Wholesale Goods"
        }
    ],
    "sg:phone":"+90 274 216 1319",
    "sg:postcode":"06660",
    "sg:province":"K?tahya",
    "sg:tags":[
        "industry",
        "mine"
    ],
    "wof:name":"Atabek Madencilik San. Ltd.sti.",
    "wof:placetype":"venue"
},
  "geometry": {"coordinates":[32.8532714844,39.929309845],"type":"Point"}
}