{
  "type": "Feature",
  "properties": {
    "addr:full":"Atat?k Cd. Irmak Apt. K:6 D:12 G?ztepe Eskisehir",
    "addr:housenumber":"6 d 12 g ?",
    "addr:street":"K Cd. Irmak Apt. K;Ztepe Eskisehir",
    "iso:country":"TR",
    "sg:address":"Atat?k Cd. Irmak Apt. K:6 D:12",
    "sg:city":"G?ztepe",
    "sg:classifiers":[
        {
            "category":"Banks & Credit Unions",
            "subcategory":"Investment Brokerage",
            "type":"Services"
        }
    ],
    "sg:phone":"+90 222 233 5232",
    "sg:province":"Eskisehir",
    "sg:tags":[
        "-",
        "export",
        "import"
    ],
    "wof:name":"Cabir Hayreddini Dis Tic. Ltd. Sti.",
    "wof:placetype":"venue"
},
  "geometry": {"coordinates":[30.5154705048,39.7782936096],"type":"Point"}
}