{
  "type": "Feature",
  "properties": {
    "addr:full":"Yavuz Sk. No:3/a ?aglayan Ikitelli/K\u00fc\u00e7\u00fck\u00e7ekmece Istanbul 34670",
    "addr:housenumber":"a ?",
    "addr:postcode":"34670",
    "addr:street":"Sk. No 3 /;Aglayan Ikitelli / Kuec\u0327Uekc\u0327Ekmece",
    "iso:country":"TR",
    "sg:address":"Yavuz Sk. No:3/a ?aglayan",
    "sg:city":"Ikitelli/K\u00fc\u00e7\u00fck\u00e7ekmece",
    "sg:classifiers":[
        {
            "category":"Manufacturing",
            "subcategory":"Tools & Machinery",
            "type":"Manufacturing & Wholesale Goods"
        }
    ],
    "sg:phone":"+90 212 233 4878",
    "sg:postcode":"34670",
    "sg:province":"Istanbul",
    "sg:tags":[
        "machine",
        "industry"
    ],
    "wof:name":"Epa Akin Makina San. Dis Tic. A.s.",
    "wof:placetype":"venue"
},
  "geometry": {"coordinates":[28.9759254456,41.0123786926],"type":"Point"}
}