{
  "type": "Feature",
  "properties": {
    "addr:full":"Dere Sk.no.20/6 Osmanbey Istanbul 63000",
    "addr:postcode":"63000",
    "iso:country":"TR",
    "sg:address":"Dere Sk.no.20/6",
    "sg:city":"Osmanbey",
    "sg:classifiers":[
        {
            "category":"Shopping",
            "subcategory":"Clothing, Apparel, & Fashions",
            "type":"Retail Goods"
        }
    ],
    "sg:phone":"+90 212 240 1842",
    "sg:postcode":"63000",
    "sg:province":"Istanbul",
    "sg:tags":[
        "ready",
        "wear"
    ],
    "wof:name":"Ome Giyim Ltd.sti.",
    "wof:placetype":"venue"
},
  "geometry": {"coordinates":[29.2841091156,40.8689346313],"type":"Point"}
}