{
  "type": "Feature",
  "properties": {
    "iso:country":"TR",
    "sg:address":"Cemal M?? Cad. No:72 Dereli",
    "sg:city":"Ikitelli",
    "sg:classifiers":[
        {
            "category":"Manufacturing",
            "subcategory":"Wood Products",
            "type":"Manufacturing & Wholesale Goods"
        }
    ],
    "sg:phone":"+90 454 381 3053",
    "sg:postcode":"34306",
    "sg:province":"Giresun",
    "sg:tags":[
        "forest"
    ],
    "wof:name":"T?r?d?oglu Tic. Koll. Sti.",
    "wof:placetype":"venue"
},
  "geometry": {"coordinates":[32.4717826843,37.8708839417],"type":"Point"}
}