{
  "type": "Feature",
  "properties": {
    "addr:full":"Harzemsah Sok. No:30-a Sisli Istanbul 65710",
    "addr:housenumber":"30-a",
    "addr:postcode":"65710",
    "addr:street":"Harzemsah Sok. No",
    "iso:country":"TR",
    "sg:address":"Harzemsah Sok. No:30-a",
    "sg:city":"Sisli",
    "sg:classifiers":[
        {
            "category":"Manufacturing",
            "subcategory":"Glass & Minerals",
            "type":"Manufacturing & Wholesale Goods"
        }
    ],
    "sg:phone":"+90 212 232 9985",
    "sg:postcode":"65710",
    "sg:province":"Istanbul",
    "sg:tags":[
        "glass-mirror"
    ],
    "wof:name":"Ortac Cam Ayna Tablo Cerceve",
    "wof:placetype":"venue"
},
  "geometry": {"coordinates":[28.9841842651,41.0591201782],"type":"Point"}
}