{
  "type": "Feature",
  "properties": {
    "iso:country":"TR",
    "sg:address":"Saglik Sk. No:10/1 Sihhiye",
    "sg:city":"Fomara",
    "sg:classifiers":[
        {
            "category":"Wholesale",
            "subcategory":"Medical Equipment & Supplies",
            "type":"Manufacturing & Wholesale Goods"
        }
    ],
    "sg:phone":"+90 312 433 1892",
    "sg:province":"Ankara",
    "sg:tags":[
        "material"
    ],
    "wof:name":"Onursal Medikal Ltd. Sti.",
    "wof:placetype":"venue"
},
  "geometry": {"coordinates":[32.8635978699,39.950843811],"type":"Point"}
}