{
  "type": "Feature",
  "properties": {
    "addr:full":"Zafer Mh.1008 Sk.no:61 Gumusler Denizli 20085",
    "addr:housenumber":"61",
    "addr:postcode":"20085",
    "addr:street":"Sk.No",
    "iso:country":"TR",
    "sg:address":"Zafer Mh.1008 Sk.no:61",
    "sg:city":"Gumusler",
    "sg:classifiers":[
        {
            "category":"Shopping",
            "subcategory":"Crafts & Fabrics",
            "type":"Retail Goods"
        }
    ],
    "sg:phone":"+90 258 371 1112",
    "sg:postcode":"20085",
    "sg:province":"Denizli",
    "sg:tags":[
        "weaving"
    ],
    "wof:name":"Kaynak Tekstil A.s",
    "wof:placetype":"venue"
},
  "geometry": {"coordinates":[29.0758953094,37.8041381836],"type":"Point"}
}