{
  "type": "Feature",
  "properties": {
    "iso:country":"TR",
    "sg:address":"Guvenlik Cad. No:54/5 A.ayranci",
    "sg:city":"Ikitelli/K\u00fc\u00e7\u00fck\u00e7ekmece",
    "sg:orig_category":"Furniture Supplamentary",
    "sg:phone":"+90 312 468 5187",
    "sg:postcode":"34670",
    "sg:province":"Ankara",
    "wof:name":"Only",
    "wof:placetype":"venue"
},
  "geometry": {"coordinates":[32.8526153564,39.907699585],"type":"Point"}
}