{
  "type": "Feature",
  "properties": {
    "addr:full":"Ankara Cad. Naci Gurginsoy Sok. No:82 41040 Cankaya Kocaeli 35200",
    "addr:housenumber":"no 82",
    "addr:postcode":"41040;35200",
    "addr:street":"Ankara Cad. Naci Gurginsoy Sok.",
    "iso:country":"TR",
    "sg:address":"Ankara Cad. Naci Gurginsoy Sok. No:82 41040",
    "sg:city":"Cankaya",
    "sg:classifiers":[
        {
            "category":"Banks & Credit Unions",
            "subcategory":"Investment Brokerage",
            "type":"Services"
        }
    ],
    "sg:phone":"+90 262 321 3213",
    "sg:postcode":"35200",
    "sg:province":"Kocaeli",
    "sg:tags":[
        "-",
        "export",
        "import"
    ],
    "wof:name":"Ikiler Ticaret Sanayi Mamulleri Uretim Ve Pazarlama A.s.",
    "wof:placetype":"venue"
},
  "geometry": {"coordinates":[29.9345855713,40.7669563293],"type":"Point"}
}