{
  "type": "Feature",
  "properties": {
    "iso:country":"TR",
    "sg:address":"Cevat D?dar Cad. No.19",
    "sg:city":"Ostim",
    "sg:classifiers":[
        {
            "category":"Banks & Credit Unions",
            "subcategory":"Financial Services",
            "type":"Services"
        }
    ],
    "sg:phone":"+90 312 385 4501",
    "sg:postcode":"06370",
    "sg:province":"Ankara",
    "sg:tags":[
        "finance"
    ],
    "wof:name":"Kredi Garanti Fonu Isletme Ve Arastirma A.s.",
    "wof:placetype":"venue"
},
  "geometry": {"coordinates":[32.7294197083,39.9771499634],"type":"Point"}
}