{
  "type": "Feature",
  "properties": {
    "iso:country":"TR",
    "sg:address":"Kazim Karabekir Mah. Ihlamur Sok. No:1",
    "sg:city":"Kad\u0131k\u00f6y",
    "sg:orig_category":"Muhtarliklar",
    "sg:phone":"+90 226 812 1776",
    "sg:postcode":"77050",
    "sg:province":"Yalova",
    "wof:name":"Kazim Karabekir Mahallesi Muhtar:mehmet Oru?",
    "wof:placetype":"venue"
},
  "geometry": {"coordinates":[29.2509860992,40.6522026062],"type":"Point"}
}