{
  "type": "Feature",
  "properties": {
    "iso:country":"TR",
    "sg:address":"Hurriyet Cd. No.13",
    "sg:city":"Kagithane",
    "sg:classifiers":[
        {
            "category":"Marine",
            "type":"Transportation"
        }
    ],
    "sg:phone":"+90 212 220 9845",
    "sg:postcode":"34406",
    "sg:province":"Istanbul",
    "sg:tags":[
        "shipowner"
    ],
    "wof:name":"Atlas Ul.denizcilik Ve Tic.a.s..",
    "wof:placetype":"venue"
},
  "geometry": {"coordinates":[28.985113,41.05484],"type":"Point"}
}