{
  "type": "Feature",
  "properties": {
    "iso:country":"TR",
    "sg:address":"Cakmak Mah.basak Sok.no:44",
    "sg:city":"Iskenderun",
    "sg:classifiers":[
        {
            "category":"Manufacturing",
            "subcategory":"Rubber & Plastics",
            "type":"Manufacturing & Wholesale Goods"
        }
    ],
    "sg:phone":"+90 342 323 7767",
    "sg:postcode":"31200",
    "sg:province":"Gaziantep",
    "sg:tags":[
        "industry"
    ],
    "wof:name":"Epas Eti Plastik San.ve Tic",
    "wof:placetype":"venue"
},
  "geometry": {"coordinates":[37.3900146484,37.0711135864],"type":"Point"}
}