{
  "type": "Feature",
  "properties": {
    "addr:full":"Ressam Hikmet Onat Sk. No:9 Kat:1 Istinye Istanbul 34460",
    "addr:housenumber":"1",
    "addr:postcode":"34460",
    "addr:street":"Sk. No 9 Kat",
    "iso:country":"TR",
    "sg:address":"Ressam Hikmet Onat Sk. No:9 Kat:1",
    "sg:city":"Istinye",
    "sg:classifiers":[
        {
            "category":"Organizations",
            "subcategory":"Non-profit Organization",
            "type":"Services"
        }
    ],
    "sg:phone":"+90 21222933600212",
    "sg:postcode":"34460",
    "sg:province":"Istanbul",
    "sg:tags":[
        "alarm",
        "system"
    ],
    "wof:name":"Matriks Bina Kontrol Sistemleri",
    "wof:placetype":"venue"
},
  "geometry": {"coordinates":[29.0452651978,41.1170196533],"type":"Point"}
}