{
  "type": "Feature",
  "properties": {
    "addr:full":"Konya Sk. 17/11 Ulus/ankara Ulus Ankara 01940",
    "addr:housenumber":"11",
    "addr:postcode":"01940",
    "addr:street":"Sk. 17 /",
    "iso:country":"TR",
    "sg:address":"Konya Sk. 17/11 Ulus/ankara",
    "sg:city":"Ulus",
    "sg:classifiers":[
        {
            "category":"Shopping",
            "subcategory":"Computers & Home Electronics",
            "type":"Retail Goods"
        }
    ],
    "sg:phone":"+90 312 311 2607",
    "sg:postcode":"01940",
    "sg:province":"Ankara",
    "sg:tags":[
        "product",
        "electric-electronic"
    ],
    "wof:name":"Acun Elektronik Ltd.sti.",
    "wof:placetype":"venue"
},
  "geometry": {"coordinates":[32.8604812622,39.9429283142],"type":"Point"}
}