{
  "type": "Feature",
  "properties": {
    "addr:full":"Duacinari Mah.yesilova Cad. No:10/b- Yildirim Bursa 03300",
    "addr:housenumber":"10 / b",
    "addr:postcode":"03300",
    "addr:street":"Mah.Yesilova Cad. No;Bursa",
    "iso:country":"TR",
    "sg:address":"Duacinari Mah.yesilova Cad. No:10/b-",
    "sg:city":"Yildirim",
    "sg:classifiers":[
        {
            "category":"Manufacturing",
            "subcategory":"Glass & Minerals",
            "type":"Manufacturing & Wholesale Goods"
        }
    ],
    "sg:phone":"+90 532 307 5109",
    "sg:postcode":"03300",
    "sg:province":"Bursa",
    "sg:tags":[
        "glass-mirror"
    ],
    "wof:name":"Yavuz Cam Ticaret",
    "wof:placetype":"venue"
},
  "geometry": {"coordinates":[29.0995178223,40.1921730042],"type":"Point"}
}