{
  "type": "Feature",
  "properties": {
    "addr:full":"In??cd. No:23/b Nizip Gaziantep 27700",
    "addr:housenumber":"no 23 / b",
    "addr:postcode":"27700",
    "addr:street":"In ? ? Cd.;Nizip Gaziantep",
    "iso:country":"TR",
    "sg:address":"In??cd. No:23/b",
    "sg:city":"Nizip",
    "sg:classifiers":[
        {
            "category":"Banks & Credit Unions",
            "subcategory":"Investment Brokerage",
            "type":"Services"
        }
    ],
    "sg:phone":"+90 342 231 8297",
    "sg:postcode":"27700",
    "sg:province":"Gaziantep",
    "sg:tags":[
        "-",
        "export",
        "import"
    ],
    "wof:name":"Bediroglu Ithalat Ihracat Pazarlama A.s.",
    "wof:placetype":"venue"
},
  "geometry": {"coordinates":[37.3781585693,37.0629348755],"type":"Point"}
}