{
  "type": "Feature",
  "properties": {
    "iso:country":"TR",
    "sg:address":"Musalla Mahallesi Hulusi ?ztin Caddesi No:2",
    "sg:city":"?esme",
    "sg:classifiers":[
        {
            "category":"Travel",
            "subcategory":"Travel Agent",
            "type":"Entertainment"
        }
    ],
    "sg:phone":"+90 2327127654729",
    "sg:province":"Izmir",
    "sg:tags":[
        "agency",
        "tourism"
    ],
    "wof:name":"Maskot Turizm",
    "wof:placetype":"venue"
},
  "geometry": {"coordinates":[27.1423015594,38.4251480103],"type":"Point"}
}