{
  "type": "Feature",
  "properties": {
    "iso:country":"TR",
    "sg:address":"Ziya G?alp Cad. 22/e Kizilay",
    "sg:city":"07100",
    "sg:classifiers":[
        {
            "category":"Shopping",
            "subcategory":"Optical Goods",
            "type":"Retail Goods"
        }
    ],
    "sg:phone":"+90 312 431 5853",
    "sg:province":"Ankara",
    "sg:tags":[
        "material"
    ],
    "wof:name":"Optik Lenti A.s.",
    "wof:placetype":"venue"
},
  "geometry": {"coordinates":[32.8511962891,39.9229354858],"type":"Point"}
}