{
  "type": "Feature",
  "properties": {
    "addr:full":"Yedieylul Mah. Manisa Yolu No:52 Turgutlu Mersin Manisa 52750",
    "addr:housenumber":"no 52",
    "addr:postcode":"52750",
    "addr:street":"Yedieylul Mah. Manisa Yolu",
    "iso:country":"TR",
    "sg:address":"Yedieylul Mah. Manisa Yolu No:52 Turgutlu",
    "sg:city":"Mersin",
    "sg:classifiers":[
        {
            "category":"Shopping",
            "subcategory":"Computers & Home Electronics",
            "type":"Retail Goods"
        }
    ],
    "sg:phone":"+90 236 312 4204",
    "sg:postcode":"52750",
    "sg:province":"Manisa",
    "sg:tags":[
        "product",
        "electric-electronic"
    ],
    "wof:name":"Cilel Elektronik",
    "wof:placetype":"venue"
},
  "geometry": {"coordinates":[27.4269599915,38.6141242981],"type":"Point"}
}