{
  "type": "Feature",
  "properties": {
    "iso:country":"TR",
    "sg:address":"Atiye Sk. Polar Apt. No:12/6 Tesvikiye",
    "sg:city":"Kirac-buyukcekmece",
    "sg:orig_category":"Printinh House",
    "sg:phone":"+90 212 231 9283",
    "sg:province":"Istanbul",
    "wof:name":"G?zlem Gazetecilik Basin Yayin A.s.",
    "wof:placetype":"venue"
},
  "geometry": {"coordinates":[28.9969673157,41.0520401001],"type":"Point"}
}