{
  "type": "Feature",
  "properties": {
    "addr:full":"Kiremithane Mh.170 Sk.kayseri Apt.alti Mersin I?el 52750",
    "addr:postcode":"52750",
    "addr:street":"El",
    "iso:country":"TR",
    "sg:address":"Kiremithane Mh.170 Sk.kayseri Apt.alti",
    "sg:city":"Mersin",
    "sg:classifiers":[
        {
            "category":"Professional",
            "subcategory":"Business Services",
            "type":"Services"
        }
    ],
    "sg:phone":"+90 324 232 0764",
    "sg:postcode":"52750",
    "sg:province":"I?el",
    "sg:tags":[
        "food",
        "product",
        "exporter",
        "aricultural"
    ],
    "wof:name":"Junya Tic.ltd.sti.",
    "wof:placetype":"venue"
},
  "geometry": {"coordinates":[37.7128486633,41.0530204773],"type":"Point"}
}